{
  "type": "Feature",
  "properties": {
    "iso:country":"CH",
    "sg:address":"Route Des Champs-neufs",
    "sg:city":"Sion",
    "sg:orig_category":"Sanit\u00e4r, Heizungs U L\u00fcftungsinstallation",
    "sg:phone":"+41 27 322 54 19",
    "sg:postcode":"1950",
    "sg:province":"Valais",
    "wof:name":"Zumoberhaus Siegfried.",
    "wof:placetype":"venue"
},
  "geometry": {"coordinates":[7.3588571548,46.2280921936],"type":"Point"}
}