{
  "type": "Feature",
  "properties": {
    "addr:full":"Gallusstrasse 1 Olten Solothurn 4600",
    "addr:housenumber":"1",
    "addr:postcode":"4600",
    "addr:street":"Gallusstrasse",
    "iso:country":"CH",
    "sg:address":"Gallusstrasse 1",
    "sg:city":"Olten",
    "sg:orig_category":"Betrieb von Taxis",
    "sg:phone":"+41 62 205 22 22",
    "sg:postcode":"4600",
    "sg:province":"Solothurn",
    "wof:name":"Taxi Bur A. Ag",
    "wof:placetype":"venue"
},
  "geometry": {"coordinates":[7.891439,47.351013],"type":"Point"}
}