{
  "type": "Feature",
  "properties": {
    "iso:country":"CH",
    "sg:address":"Bachmatt 9",
    "sg:city":"Fahrwangen",
    "sg:orig_category":"Abwasserreinigung",
    "sg:phone":"+41 56 667 16 06",
    "sg:postcode":"5615",
    "sg:province":"Aargau",
    "wof:name":"Abwasserreinigungsanlage Louis Strebel",
    "wof:placetype":"venue"
},
  "geometry": {"coordinates":[8.24211,47.293571],"type":"Point"}
}