{
  "type": "Feature",
  "properties": {
    "addr:full":"6822 Arogno Ticino 6822",
    "addr:postcode":"6822;6822",
    "iso:country":"CH",
    "sg:address":"6822",
    "sg:city":"Arogno",
    "sg:orig_category":"Autoreiseunternehmen Reiseb\u00fcros",
    "sg:postcode":"6822",
    "sg:province":"Ticino",
    "wof:name":"Alpstein-touristik",
    "wof:placetype":"venue"
},
  "geometry": {"coordinates":[9.195661,47.229259],"type":"Point"}
}