{
  "type": "Feature",
  "properties": {
    "iso:country":"CH",
    "sg:address":"Sixfeld",
    "sg:city":"Liedertswil",
    "sg:orig_category":"Wasserversorgung",
    "sg:phone":"+41 61 961 92 09",
    "sg:postcode":"4436",
    "sg:province":"Basel-Landschaft",
    "wof:name":"Wasserversorgung Liedertswil",
    "wof:placetype":"venue"
},
  "geometry": {"coordinates":[7.7489027977,47.3897705078],"type":"Point"}
}