{
  "type": "Feature",
  "properties": {
    "iso:country":"CH",
    "sg:address":"Neustadtgasse 1a 8400 Winterthur. Postfach",
    "sg:city":"Winterthur",
    "sg:orig_category":"Interessenvertretungen",
    "sg:postcode":"8400",
    "sg:province":"Z\u00fcrich",
    "wof:name":"Fondation Gaspoz Henri Et Marcelle",
    "wof:placetype":"venue"
},
  "geometry": {"coordinates":[8.7320327759,47.4983596802],"type":"Point"}
}