{
  "type": "Feature",
  "properties": {
    "iso:country":"CH",
    "sg:address":"Kirchenstrasse 44",
    "sg:city":"Oberiberg",
    "sg:orig_category":"Landesverteidigung, Sozialversicherung \u00d6ffentliche Verwaltung",
    "sg:phone":"+41 41 921 66 33",
    "sg:postcode":"8843",
    "sg:province":"Schwyz",
    "wof:name":"Zivilschutzstelle Oberkirch",
    "wof:placetype":"venue"
},
  "geometry": {"coordinates":[8.1154155731,47.1549568176],"type":"Point"}
}