{
  "type": "Feature",
  "properties": {
    "iso:country":"CH",
    "sg:address":"Niklaus Wengistrasse 37",
    "sg:city":"Grenchen",
    "sg:orig_category":"Unternehmensberatung",
    "sg:phone":"+41 31 829 25 63",
    "sg:postcode":"2540",
    "sg:province":"Solothurn",
    "wof:name":"M\u00f6rikofer Marketing & Engineering",
    "wof:placetype":"venue"
},
  "geometry": {"coordinates":[7.3590831757,46.9736785889],"type":"Point"}
}