{
  "type": "Feature",
  "properties": {
    "iso:country":"CH",
    "sg:address":"Metzgerh\u00fcsi 8",
    "sg:city":"Walkringen",
    "sg:orig_category":"Autogaragen",
    "sg:phone":"+41 52 238 25 26",
    "sg:postcode":"3512",
    "sg:province":"Bern",
    "wof:name":"Garage Seen S.islami",
    "wof:placetype":"venue"
},
  "geometry": {"coordinates":[8.760722,47.483559],"type":"Point"}
}