{
  "type": "Feature",
  "properties": {
    "iso:country":"CH",
    "sg:address":"G\u00f6nhardweg 48",
    "sg:city":"Aarau",
    "sg:orig_category":"Berufsberatungen",
    "sg:phone":"+41 62 835 21 30",
    "sg:postcode":"5000",
    "sg:province":"Aargau",
    "wof:name":"Kantonale Studienberatung",
    "wof:placetype":"venue"
},
  "geometry": {"coordinates":[8.053107,47.384109],"type":"Point"}
}