{
  "type": "Feature",
  "properties": {
    "iso:country":"CH",
    "sg:address":"Sennheimerstrasse 50",
    "sg:city":"Basel",
    "sg:orig_category":"Erbringung von sonstigen Dienstleistungen f\u00fcr Unternehmen Sonstige pers\u00f6nliche Dienstleistungen",
    "sg:phone":"+41 61 303 93 93",
    "sg:postcode":"4054",
    "sg:province":"Basel-Stadt",
    "wof:name":"Hotelcheck.li Beat Braun",
    "wof:placetype":"venue"
},
  "geometry": {"coordinates":[7.5703148842,47.5545310974],"type":"Point"}
}