{
  "type": "Feature",
  "properties": {
    "iso:country":"CH",
    "sg:address":"Aarbergstrasse 99",
    "sg:city":"Biel/bienne",
    "sg:classifiers":[
        {
            "category":"Restaurant",
            "type":"Food & Drink"
        }
    ],
    "sg:phone":"+41 32 322 49 73",
    "sg:postcode":"2502",
    "sg:province":"Bern",
    "wof:name":"Caf\u00e9 Bel-air",
    "wof:placetype":"venue"
},
  "geometry": {"coordinates":[7.240571022,47.1340904236],"type":"Point"}
}