{
  "type": "Feature",
  "properties": {
    "iso:country":"CH",
    "sg:address":"2915",
    "sg:city":"Bure",
    "sg:orig_category":"Verwertung von Milch",
    "sg:phone":"+41 32 466 92 40",
    "sg:postcode":"2915",
    "sg:province":"Jura",
    "wof:name":"Soci\u00e9t\u00e9 De Laiterie De Bure",
    "wof:placetype":"venue"
},
  "geometry": {"coordinates":[7.0065431595,47.4420890808],"type":"Point"}
}