{
  "type": "Feature",
  "properties": {
    "iso:country":"CH",
    "sg:address":"Bahnhofstrasse 73",
    "sg:city":"Ins",
    "sg:orig_category":"Blumen U Zierpflanzenbau Detailhandel mit Blumen U Pflanzen",
    "sg:phone":"+41 32 313 15 93",
    "sg:postcode":"3232",
    "sg:province":"Bern",
    "wof:name":"Chopard Peter.",
    "wof:placetype":"venue"
},
  "geometry": {"coordinates":[7.102477,47.003288],"type":"Point"}
}