{
  "type": "Feature",
  "properties": {
    "iso:country":"CH",
    "sg:address":"Rue De La Servette 67",
    "sg:city":"Gen\u00e8ve",
    "sg:orig_category":"Rechtsberatung Unternehmensberatung",
    "sg:phone":"+41 22 740 34 20",
    "sg:postcode":"1202",
    "sg:province":"Gen\u00e8ve",
    "wof:name":"Jean-fran\u00e7ois Duc Bureau Fiduciaire",
    "wof:placetype":"venue"
},
  "geometry": {"coordinates":[6.1330928802,46.2117843628],"type":"Point"}
}