{
  "type": "Feature",
  "properties": {
    "iso:country":"CH",
    "sg:address":"R\u00e4uchlisberg 49",
    "sg:city":"Amriswil",
    "sg:orig_category":"Grosshandel mit lebenden Tieren",
    "sg:phone":"+41 71 411 16 48",
    "sg:postcode":"8580",
    "sg:province":"Thurgau",
    "wof:name":"Kaderli Fritz",
    "wof:placetype":"venue"
},
  "geometry": {"coordinates":[9.2949180603,47.5339775085],"type":"Point"}
}