{
  "type": "Feature",
  "properties": {
    "iso:country":"CH",
    "sg:address":"1541",
    "sg:city":"S\u00e9vaz",
    "sg:orig_category":"Grosshandel mit lebenden Tieren",
    "sg:phone":"+41 26 663 11 97",
    "sg:postcode":"1541",
    "sg:province":"Fribourg",
    "wof:name":"Losey Fernand.",
    "wof:placetype":"venue"
},
  "geometry": {"coordinates":[6.8753180504,46.8386802673],"type":"Point"}
}