{
  "type": "Feature",
  "properties": {
    "iso:country":"CH",
    "sg:address":"S\u00e4ngergasse 9",
    "sg:city":"Basel",
    "sg:orig_category":"Reiseb\u00fcros U Reiseveranstalter",
    "sg:postcode":"4054",
    "sg:province":"Basel-Stadt",
    "wof:name":"Beach Travel Sa",
    "wof:placetype":"venue"
},
  "geometry": {"coordinates":[7.5718002319,47.5560188293],"type":"Point"}
}