{
  "type": "Feature",
  "properties": {
    "iso:country":"CH",
    "sg:address":"1196 Gland Case Postale 422",
    "sg:city":"Gland",
    "sg:orig_category":"Sportvereine Ballsport Tischtennis",
    "sg:phone":"+41 21 625 01 71",
    "sg:postcode":"1196",
    "sg:province":"Vaud",
    "wof:name":"Club De Tennis De Table Lausanne",
    "wof:placetype":"venue"
},
  "geometry": {"coordinates":[6.6876702309,46.559551239],"type":"Point"}
}