{
  "type": "Feature",
  "properties": {
    "iso:country":"CH",
    "sg:address":"Avenue De Rhodanie 23",
    "sg:city":"Lausanne",
    "sg:orig_category":"Detailhandel mit Bekleidung Detailhandel mit Zeitungen U Zeitschriften Kioske",
    "sg:phone":"+41 81 826 54 04",
    "sg:postcode":"1007",
    "sg:province":"Vaud",
    "wof:name":"Kahl-staub Monika, Boutique-kiosk Alvetern",
    "wof:placetype":"venue"
},
  "geometry": {"coordinates":[9.764172,46.428764],"type":"Point"}
}