{
  "type": "Feature",
  "properties": {
    "iso:country":"CH",
    "sg:address":"Uerkeweg 7",
    "sg:city":"Unterentfelden",
    "sg:classifiers":[
        {
            "category":"Structure",
            "subcategory":"Building",
            "type":"Public Place"
        }
    ],
    "sg:phone":"+41 33 676 22 31",
    "sg:postcode":"5035",
    "sg:province":"Aargau",
    "sg:tags":[
        "attic",
        "addition",
        "finishing",
        "roof",
        "trusses"
    ],
    "wof:name":"Zurbr\u00fcgg Holzbau Ag Reichenbach",
    "wof:placetype":"venue"
},
  "geometry": {"coordinates":[7.66956,46.615585],"type":"Point"}
}