{
  "type": "Feature",
  "properties": {
    "iso:country":"CH",
    "sg:address":"Rue De L'avenir 29",
    "sg:city":"Del\u00e9mont",
    "sg:orig_category":"Arztpraxen",
    "sg:phone":"+41 32 422 34 88",
    "sg:postcode":"2800",
    "sg:province":"Jura",
    "wof:name":"Dr M\u00e9d. Fran\u00e7ois Membrez M\u00e9decin Sp\u00e9cialiste Fmh",
    "wof:placetype":"venue"
},
  "geometry": {"coordinates":[7.35009,47.364998],"type":"Point"}
}