{
  "type": "Feature",
  "properties": {
    "iso:country":"CH",
    "sg:address":"Baumgartenstrasse 25",
    "sg:city":"Urdorf",
    "sg:orig_category":"Architektur U Ingenieurb\u00fcros",
    "sg:phone":"+41 17351220",
    "sg:postcode":"8902",
    "sg:province":"Z\u00fcrich",
    "wof:name":"Daniel Gutknecht, Dipl. Ingenieur Eth",
    "wof:placetype":"venue"
},
  "geometry": {"coordinates":[8.421417,47.378559],"type":"Point"}
}