{
  "type": "Feature",
  "properties": {
    "iso:country":"CH",
    "sg:address":"Maienstrasse 6",
    "sg:city":"Grenchen",
    "sg:classifiers":[
        {
            "category":"Banks & Credit Unions",
            "subcategory":"Investment Brokerage",
            "type":"Services"
        }
    ],
    "sg:phone":"+41 32 351 34 65",
    "sg:postcode":"2540",
    "sg:province":"Solothurn",
    "sg:tags":[
        "machine",
        "assembly",
        "automatic"
    ],
    "wof:name":"Promec Ag",
    "wof:placetype":"venue"
},
  "geometry": {"coordinates":[7.385473,47.143414],"type":"Point"}
}