{
  "type": "Feature",
  "properties": {
    "iso:country":"CH",
    "sg:address":"Hauptstr. 26",
    "sg:city":"Uesslingen",
    "sg:orig_category":"Instandhaltung U Reparatur von Automobilen",
    "sg:postcode":"8524",
    "sg:province":"Thurgau",
    "wof:name":"Grubemann Max",
    "wof:placetype":"venue"
},
  "geometry": {"coordinates":[8.8380708694,47.5987319946],"type":"Point"}
}