{
  "type": "Feature",
  "properties": {
    "iso:country":"CH",
    "sg:address":"Unterneuhaus 232",
    "sg:city":"Wilchingen",
    "sg:orig_category":"Herstellung von Betonerzeugnissen f\u00fcr den Bau",
    "sg:phone":"+41 27 322 11 62",
    "sg:postcode":"8217",
    "sg:province":"Schaffhausen",
    "wof:name":"La Pl\u00e2tri\u00e8re Sa",
    "wof:placetype":"venue"
},
  "geometry": {"coordinates":[7.4636449814,46.2584381104],"type":"Point"}
}