{
  "type": "Feature",
  "properties": {
    "iso:country":"CH",
    "sg:address":"Rue Juste-olivier 7",
    "sg:city":"Nyon",
    "sg:orig_category":"Organisationen des Gesundheitswesen",
    "sg:phone":"+41 22 362 17 62",
    "sg:postcode":"1260",
    "sg:province":"Vaud",
    "wof:name":"Centre M\u00e9dico-social Du Secteur De Nyon",
    "wof:placetype":"venue"
},
  "geometry": {"coordinates":[6.2369217873,46.3837356567],"type":"Point"}
}