{
  "type": "Feature",
  "properties": {
    "iso:country":"CH",
    "sg:address":"Muttenzerstrasse 14",
    "sg:city":"Birsfelden",
    "sg:orig_category":"Herstellung von Automobilen",
    "sg:phone":"+41 61 312 39 19",
    "sg:postcode":"4127",
    "sg:province":"Basel-Landschaft",
    "wof:name":"Lag-fahrzeuge Peter Wildermuth",
    "wof:placetype":"venue"
},
  "geometry": {"coordinates":[7.6240348816,47.5506515503],"type":"Point"}
}