{
  "type": "Feature",
  "properties": {
    "iso:country":"CH",
    "sg:address":"Sonnental 9",
    "sg:city":"Muolen",
    "sg:orig_category":"Instandhaltung U Reparatur von Automobilen",
    "sg:phone":"+41 71 411 36 44",
    "sg:postcode":"9313",
    "sg:province":"St. Gallen",
    "wof:name":"Bosshart Ag Autospritzwerk",
    "wof:placetype":"venue"
},
  "geometry": {"coordinates":[9.3179941177,47.521522522],"type":"Point"}
}