{
  "type": "Feature",
  "properties": {
    "iso:country":"CH",
    "sg:address":"Langhausstrasse 1",
    "sg:city":"Turgi",
    "sg:orig_category":"Detailhandel mit Getr\u00e4nken Grosshandel mit Getr\u00e4nken",
    "sg:phone":"+41 56 222 78 12",
    "sg:postcode":"5300",
    "sg:province":"Aargau",
    "wof:name":"Svetlana Funk Wiihus Schiibe",
    "wof:placetype":"venue"
},
  "geometry": {"coordinates":[8.2528486252,47.4938621521],"type":"Point"}
}