{
  "type": "Feature",
  "properties": {
    "iso:country":"CH",
    "sg:address":"Auenstrasse 19",
    "sg:city":"Kloten",
    "sg:orig_category":"Vereine Musik/Blasmusik",
    "sg:phone":"+41 32 653 13 01",
    "sg:postcode":"8302",
    "sg:province":"Z\u00fcrich",
    "wof:name":"Stadtmusik Konkordia Grenchen",
    "wof:placetype":"venue"
},
  "geometry": {"coordinates":[7.3996858597,47.1861190796],"type":"Point"}
}