{
  "type": "Feature",
  "properties": {
    "addr:full":"Sonnenrainstrasse 12 D\u00fcrnten Z\u00fcrich 8635",
    "addr:housenumber":"12",
    "addr:postcode":"8635",
    "addr:street":"Sonnenrainstrasse;Zuerich",
    "iso:country":"CH",
    "sg:address":"Sonnenrainstrasse 12",
    "sg:city":"D\u00fcrnten",
    "sg:orig_category":"Baugewerbe Herstellung von K\u00fcchenm\u00f6beln",
    "sg:phone":"+41 55 240 81 61",
    "sg:postcode":"8635",
    "sg:province":"Z\u00fcrich",
    "wof:name":"Fritz Giezendanner Montageunternehmen",
    "wof:placetype":"venue"
},
  "geometry": {"coordinates":[8.876517,47.276627],"type":"Point"}
}