{
  "type": "Feature",
  "properties": {
    "iso:country":"CH",
    "sg:address":"1644",
    "sg:city":"Avry-devant-pont",
    "sg:orig_category":"Detailhandel mit Sportartikeln Fachdetailhandel in Verkaufsr\u00e4umen",
    "sg:phone":"+41 26 915 12 42",
    "sg:postcode":"1644",
    "sg:province":"Fribourg",
    "wof:name":"Sports Et Loisirs, Sottas Brigitte",
    "wof:placetype":"venue"
},
  "geometry": {"coordinates":[7.0862498283,46.6852684021],"type":"Point"}
}