{
  "type": "Feature",
  "properties": {
    "iso:country":"CH",
    "sg:address":"Bahnhofstrasse 59",
    "sg:city":"D\u00fcbendorf",
    "sg:orig_category":"RESTAURANTS: TEA-ROOMS",
    "sg:postcode":"8600",
    "sg:province":"Z\u00fcrich",
    "wof:name":"Honegger-danieli Anita Frau",
    "wof:placetype":"venue"
},
  "geometry": {"coordinates":[8.6221017838,47.3998908997],"type":"Point"}
}