{
  "type": "Feature",
  "properties": {
    "iso:country":"CH",
    "sg:address":"St. Jakobs-strasse 191",
    "sg:city":"Basel",
    "sg:classifiers":[
        {
            "category":"Communications",
            "subcategory":"Radio Station",
            "type":"Services"
        }
    ],
    "sg:phone":"+41 61 319 35 35",
    "sg:postcode":"4052",
    "sg:province":"Basel-Stadt",
    "sg:tags":[
        "fernsehanstalten",
        "u"
    ],
    "wof:name":"Wf Werba Fair Ag",
    "wof:placetype":"venue"
},
  "geometry": {"coordinates":[7.6088252068,47.5440788269],"type":"Point"}
}