{
  "type": "Feature",
  "properties": {
    "iso:country":"CH",
    "sg:address":"Rte De La Taille",
    "sg:city":"Cernier",
    "sg:classifiers":[
        {
            "category":"Park",
            "type":"Public Place"
        }
    ],
    "sg:phone":"+41 32 853 35 46",
    "sg:postcode":"2053",
    "sg:province":"Neuch\u00e2tel",
    "sg:tags":[
        "work",
        "construction",
        "sport"
    ],
    "wof:name":"Multireal",
    "wof:placetype":"venue"
},
  "geometry": {"coordinates":[6.91048,47.06086],"type":"Point"}
}