{
  "type": "Feature",
  "properties": {
    "iso:country":"CH",
    "sg:address":"3615",
    "sg:city":"Heimenschwand",
    "sg:classifiers":[
        {
            "category":"Travel",
            "subcategory":"Hotels & Motels",
            "type":"Entertainment"
        }
    ],
    "sg:phone":"+41 33 453 14 21",
    "sg:postcode":"3615",
    "sg:province":"Bern",
    "sg:tags":[
        "hotels",
        "mit",
        "restaurant"
    ],
    "wof:name":"Hotel Rohrimoosbad",
    "wof:placetype":"venue"
},
  "geometry": {"coordinates":[7.6969399452,46.8286209106],"type":"Point"}
}