{
  "type": "Feature",
  "properties": {
    "iso:country":"CH",
    "sg:address":"Hauptstrasse",
    "sg:city":"Cazis",
    "sg:classifiers":[
        {
            "category":"Restaurant",
            "type":"Food & Drink"
        }
    ],
    "sg:phone":"+41 81 651 14 23",
    "sg:postcode":"7408",
    "sg:province":"Graubunden",
    "wof:name":"Restaurant Adler",
    "wof:placetype":"venue"
},
  "geometry": {"coordinates":[9.4273872375,46.7245292664],"type":"Point"}
}