{
  "type": "Feature",
  "properties": {
    "iso:country":"CH",
    "sg:address":"Chileweg 9",
    "sg:city":"Obfelden",
    "sg:orig_category":"Unclassifiable Establishments",
    "sg:postcode":"8912",
    "sg:province":"Z\u00fcrich",
    "wof:name":"Ursula Bichsel Gartenpflege",
    "wof:placetype":"venue"
},
  "geometry": {"coordinates":[8.4217576981,47.26304245],"type":"Point"}
}