{
  "type": "Feature",
  "properties": {
    "iso:country":"CH",
    "sg:address":"General Wille-strasse 288",
    "sg:city":"Feldmeilen",
    "sg:orig_category":"Interessenvertretungen",
    "sg:postcode":"8706",
    "sg:province":"Z\u00fcrich",
    "wof:name":"Verein Der Berner Sennenhunde Berner Sennenhunde, Rasseverwandte Hunde; Haltung, Ern\u00e4hrung",
    "wof:placetype":"venue"
},
  "geometry": {"coordinates":[9.3682832718,47.4178771973],"type":"Point"}
}