{
  "type": "Feature",
  "properties": {
    "iso:country":"CH",
    "sg:address":"Industriestrasse 49",
    "sg:city":"Zug",
    "sg:orig_category":"Forschung U Entwicklung im Bereich der Naturwissenschaften",
    "sg:postcode":"6300",
    "sg:province":"Zug",
    "wof:name":"Triskel Integrated Services Sa",
    "wof:placetype":"venue"
},
  "geometry": {"coordinates":[6.1400208473,46.2060317993],"type":"Point"}
}