{
  "type": "Feature",
  "properties": {
    "iso:country":"CH",
    "sg:address":"Route Bois",
    "sg:city":"Matran",
    "sg:orig_category":"Grosshandel mit Getr\u00e4nken Grosshandel mit Wein U Spirituosen",
    "sg:phone":"+41 26 401 30 15",
    "sg:postcode":"1753",
    "sg:province":"Fribourg",
    "wof:name":"Hb La Halle Aux Boissons Sa",
    "wof:placetype":"venue"
},
  "geometry": {"coordinates":[7.0878682137,46.7796707153],"type":"Point"}
}