{
  "type": "Feature",
  "properties": {
    "iso:country":"CH",
    "sg:address":"Fontaine Chemin De La",
    "sg:city":"Chandolin-savi\u00e8se",
    "sg:orig_category":"Grosshandel mit Nahrungsmitteln, Getr\u00e4nken U Tabakwaren ohne ausgepr\u00e4gten Schwerpunkt",
    "sg:postcode":"1965",
    "sg:province":"Valais",
    "wof:name":"Dubuis Raymond",
    "wof:placetype":"venue"
},
  "geometry": {"coordinates":[7.3385391235,46.2504730225],"type":"Point"}
}