{
  "type": "Feature",
  "properties": {
    "iso:country":"CH",
    "sg:address":"Geissgasse 21",
    "sg:city":"Rheinfelden",
    "sg:orig_category":"Detailhandel mit B\u00fcchern, Zeitungen, Schreib U Papeteriewaren",
    "sg:phone":"+41 61 831 73 36",
    "sg:postcode":"4310",
    "sg:province":"Aargau",
    "wof:name":"Buchhandlung Zum Leuchtturm",
    "wof:placetype":"venue"
},
  "geometry": {"coordinates":[7.794945,47.554394],"type":"Point"}
}