{
  "type": "Feature",
  "properties": {
    "iso:country":"CH",
    "sg:address":"Rebhaldenstrasse 2 8182 Hochfelden. Postfach",
    "sg:city":"Hochfelden",
    "sg:orig_category":"Softwareentwicklung U beratung",
    "sg:phone":"+41 18862006",
    "sg:postcode":"8182",
    "sg:province":"Z\u00fcrich",
    "wof:name":"Br\u00fcgger & Partner Dienstleistungen In Den Bereichen Informatik U. Organisation. Hard, Software; Handel",
    "wof:placetype":"venue"
},
  "geometry": {"coordinates":[8.5137453079,47.5230293274],"type":"Point"}
}