{
  "type": "Feature",
  "properties": {
    "iso:country":"CH",
    "sg:address":"Rue De Lausanne 42",
    "sg:city":"Fribourg",
    "sg:orig_category":"Herstellung von Schmuck, Gold U Silberschmiedwaren",
    "sg:postcode":"1700",
    "sg:province":"Fribourg",
    "wof:name":"Pavior, Guinand Pierre-alain",
    "wof:placetype":"venue"
},
  "geometry": {"coordinates":[6.8187971115,47.098575592],"type":"Point"}
}