{
  "type": "Feature",
  "properties": {
    "iso:country":"CH",
    "sg:address":"Riehentorstrasse 13",
    "sg:city":"Basel",
    "sg:orig_category":"Detailhandel mit elektrischen Haushalts-,Radio U Fernsehger\u00e4ten sowie Musikinstrumenten",
    "sg:phone":"+41 61 681 61 66",
    "sg:postcode":"4058",
    "sg:province":"Basel-Stadt",
    "wof:name":"Guitar Center Spicher Mischa",
    "wof:placetype":"venue"
},
  "geometry": {"coordinates":[7.5955038071,47.5592956543],"type":"Point"}
}