{
  "type": "Feature",
  "properties": {
    "iso:country":"CH",
    "sg:address":"Chamerstrasse 3",
    "sg:city":"Zug",
    "sg:orig_category":"Unclassifiable Establishments",
    "sg:postcode":"6300",
    "sg:province":"Zug",
    "wof:name":"Wii Industrial Investment Ag",
    "wof:placetype":"venue"
},
  "geometry": {"coordinates":[8.5120458603,47.171295166],"type":"Point"}
}