{
  "type": "Feature",
  "properties": {
    "iso:country":"CH",
    "sg:address":"Via San Gottardo 6598 Tenero Casella Postale",
    "sg:city":"Tenero",
    "sg:orig_category":"Instandhaltung U Reparatur von Automobilen Tankstellen",
    "sg:phone":"+41 91 745 13 02",
    "sg:postcode":"6598",
    "sg:province":"Ticino",
    "wof:name":"Garage Fochetti Sa",
    "wof:placetype":"venue"
},
  "geometry": {"coordinates":[8.8498601913,46.180896759],"type":"Point"}
}