{
  "type": "Feature",
  "properties": {
    "iso:country":"CH",
    "sg:address":"Yung Rue Emile- 1 1205 Gen\u00e8ve. Postfach",
    "sg:city":"Gen\u00e8ve",
    "sg:orig_category":"Wirtschaftspr\u00fcfung, Steuerberatung U Treuhand",
    "sg:phone":"+41 22 346 28 33",
    "sg:postcode":"1205",
    "sg:province":"Gen\u00e8ve",
    "wof:name":"Ms Consulting, Sicuro Maria",
    "wof:placetype":"venue"
},
  "geometry": {"coordinates":[6.1501579285,46.1957473755],"type":"Point"}
}