{
  "type": "Feature",
  "properties": {
    "iso:country":"CH",
    "sg:address":"G\u00e9rine Route De La 11",
    "sg:city":"Marly",
    "sg:orig_category":"Vermietung von Gebrauchsg\u00fctern",
    "sg:phone":"+41 26 413 20 21",
    "sg:postcode":"1723",
    "sg:province":"Fribourg",
    "wof:name":"Mascarade, Mme Andrea Tamborini",
    "wof:placetype":"venue"
},
  "geometry": {"coordinates":[7.1608052254,46.7766113281],"type":"Point"}
}