{
  "type": "Feature",
  "properties": {
    "iso:country":"CH",
    "sg:address":"Geroldsaustrasse 3b",
    "sg:city":"M\u00e4rstetten",
    "sg:orig_category":"Sportvereine Turnen",
    "sg:phone":"+41 71 657 18 64",
    "sg:postcode":"8560",
    "sg:province":"Thurgau",
    "wof:name":"M\u00e4nnerriege M\u00e4rstetten",
    "wof:placetype":"venue"
},
  "geometry": {"coordinates":[9.0614919662,47.5861358643],"type":"Point"}
}