{
  "type": "Feature",
  "properties": {
    "iso:country":"CH",
    "sg:address":"Bielstrasse 44",
    "sg:city":"Solothurn",
    "sg:orig_category":"Softwareentwicklung U beratung",
    "sg:phone":"+41 32 628 60 40",
    "sg:postcode":"4500",
    "sg:province":"Solothurn",
    "wof:name":"Implementa Software Ag Software; Handel, Einf\u00fchrung, Support. Informatidienstleistungen",
    "wof:placetype":"venue"
},
  "geometry": {"coordinates":[7.5296602249,47.2102279663],"type":"Point"}
}