{
  "type": "Feature",
  "properties": {
    "iso:country":"CH",
    "sg:address":"Spitzi 8716 Schmerikon. Postfach",
    "sg:city":"Schmerikon",
    "sg:orig_category":"Kauf U Verkauf von Immobilien auf eigene Rechnung",
    "sg:phone":"+423 232 02 31",
    "sg:postcode":"8716",
    "sg:province":"St. Gallen",
    "wof:name":"Seehof Schmerikon A.g.",
    "wof:placetype":"venue"
},
  "geometry": {"coordinates":[8.9311513901,47.2271003723],"type":"Point"}
}