{
  "type": "Feature",
  "properties": {
    "iso:country":"CH",
    "sg:address":"Bahnhofpl. 1",
    "sg:city":"M\u00fcnsingen",
    "sg:classifiers":[
        {
            "category":"Communications",
            "subcategory":"Newspaper",
            "type":"Services"
        }
    ],
    "sg:phone":"+41 31 720 51 11",
    "sg:postcode":"3110",
    "sg:province":"Bern",
    "sg:tags":[
        "printing",
        "publishing"
    ],
    "wof:name":"Fischer Ag F\u00dcr Data Und Print",
    "wof:placetype":"venue"
},
  "geometry": {"coordinates":[7.5597290993,46.8739585876],"type":"Point"}
}