{
  "type": "Feature",
  "properties": {
    "iso:country":"CH",
    "sg:address":"3946 Turtmann. Postfach 55",
    "sg:city":"Turtmann",
    "sg:orig_category":"Sportvereine Ballsport Fussball",
    "sg:postcode":"3946",
    "sg:province":"Valais",
    "wof:name":"Fc Turtmann",
    "wof:placetype":"venue"
},
  "geometry": {"coordinates":[7.7031202316,46.3017997742],"type":"Point"}
}