{
  "type": "Feature",
  "properties": {
    "iso:country":"CH",
    "sg:address":"3945",
    "sg:city":"Gampel",
    "sg:orig_category":"Campingpl\u00e4tze",
    "sg:phone":"+41 27 932 20 41",
    "sg:postcode":"3945",
    "sg:province":"Valais",
    "wof:name":"Camping Rhone Brunner Werner",
    "wof:placetype":"venue"
},
  "geometry": {"coordinates":[7.744009,46.316509],"type":"Point"}
}