{
  "type": "Feature",
  "properties": {
    "iso:country":"CH",
    "sg:address":"Via Stefano Franscini 27 6600 Locarno Casella Postale 328",
    "sg:city":"Locarno",
    "sg:orig_category":"Detailhandel mit Metallwaren, Anstrichmitteln, Glaswaren, Bau U Heimwerkerbedarf Glaserei",
    "sg:phone":"+41 79 633 45 45",
    "sg:postcode":"6600",
    "sg:province":"Ticino",
    "wof:name":"Vetreria Peduzzi Sa",
    "wof:placetype":"venue"
},
  "geometry": {"coordinates":[8.8003940582,46.1705741882],"type":"Point"}
}