{
  "type": "Feature",
  "properties": {
    "iso:country":"CH",
    "sg:address":"Gotthardstrasse 165",
    "sg:city":"Silenen",
    "sg:classifiers":[
        {
            "category":"Restaurant",
            "type":"Food & Drink"
        }
    ],
    "sg:phone":"+41 41 883 11 24",
    "sg:postcode":"6473",
    "sg:province":"Uri",
    "wof:name":"Restaurant Tell",
    "wof:placetype":"venue"
},
  "geometry": {"coordinates":[8.6703100204,46.7903137207],"type":"Point"}
}