{
  "type": "Feature",
  "properties": {
    "iso:country":"CH",
    "sg:address":"8913",
    "sg:city":"Ottenbach",
    "sg:orig_category":"Sportvereine Wassersport",
    "sg:phone":"+41 41 630 34 74",
    "sg:postcode":"8913",
    "sg:province":"Z\u00fcrich",
    "wof:name":"Wassersportclub",
    "wof:placetype":"venue"
},
  "geometry": {"coordinates":[8.3112096786,46.9831390381],"type":"Point"}
}