{
  "type": "Feature",
  "properties": {
    "iso:country":"CH",
    "sg:address":"Ryffstrasse 23 4056 Basel. Postfach",
    "sg:city":"Basel",
    "sg:orig_category":"Softwareentwicklung U beratung",
    "sg:postcode":"4051",
    "sg:province":"Basel-Stadt",
    "wof:name":"Vukmir",
    "wof:placetype":"venue"
},
  "geometry": {"coordinates":[7.5784568787,47.5683288574],"type":"Point"}
}