{
  "type": "Feature",
  "properties": {
    "iso:country":"CH",
    "sg:address":"Z\u00fcrcherstrasse 137",
    "sg:city":"Schlieren",
    "sg:orig_category":"Grosshandel mit B\u00fcromaschinen Grosshandel mit Datenverarbeitungsger\u00e4ten",
    "sg:phone":"+41 17152202",
    "sg:postcode":"8952",
    "sg:province":"Z\u00fcrich",
    "wof:name":"Flash Pc Verkaufsb\u00fcro, Graf",
    "wof:placetype":"venue"
},
  "geometry": {"coordinates":[8.5487670898,47.3227767944],"type":"Point"}
}