{
  "type": "Feature",
  "properties": {
    "iso:country":"CH",
    "sg:address":"Industriestrasse 7",
    "sg:city":"Huttwil",
    "sg:orig_category":"M\u00f6belschreinereien",
    "sg:phone":"+41 41 914 11 41",
    "sg:postcode":"4950",
    "sg:province":"Bern",
    "wof:name":"Ergonom Ag",
    "wof:placetype":"venue"
},
  "geometry": {"coordinates":[7.8622970581,47.1108665466],"type":"Point"}
}