{
  "type": "Feature",
  "properties": {
    "iso:country":"CH",
    "sg:address":"Spycherweg 3",
    "sg:city":"Riniken",
    "sg:orig_category":"Architekturb\u00fcros",
    "sg:phone":"+41 56 442 15 24",
    "sg:postcode":"5223",
    "sg:province":"Aargau",
    "wof:name":"Hans-rudolf Rebsamen Architekturb\u00fcro",
    "wof:placetype":"venue"
},
  "geometry": {"coordinates":[8.187241,47.493958],"type":"Point"}
}