{
  "type": "Feature",
  "properties": {
    "iso:country":"CH",
    "sg:address":"Weissbachbad 1002",
    "sg:city":"B\u00fchler",
    "sg:orig_category":"Elektroinstallation",
    "sg:phone":"+41 71 793 25 11",
    "sg:postcode":"9055",
    "sg:province":"Appenzell Ausserrhoden",
    "wof:name":"Hans Wicki Elektro Installationen",
    "wof:placetype":"venue"
},
  "geometry": {"coordinates":[9.4249200821,47.3730773926],"type":"Point"}
}