{
  "type": "Feature",
  "properties": {
    "iso:country":"CH",
    "sg:address":"Riedstrasse 7-9 6330 Cham. Postfach",
    "sg:city":"Cham",
    "sg:orig_category":"Grosshandel mit Parf\u00fcmerieartikeln U K\u00f6rperpflegemitteln",
    "sg:phone":"+41 41 740 08 82",
    "sg:postcode":"6330",
    "sg:province":"Zug",
    "wof:name":"Tanner Sa Kosmetik & Accessoire",
    "wof:placetype":"venue"
},
  "geometry": {"coordinates":[8.4766769409,47.1891326904],"type":"Point"}
}