{
  "type": "Feature",
  "properties": {
    "iso:country":"CH",
    "sg:address":"Zentrum Im Tobel",
    "sg:city":"Hadlikon",
    "sg:orig_category":"Detailhandel mit Haustieren U zoologischem Bedarf Fischerei U Fischzucht",
    "sg:phone":"+41 19383399",
    "sg:postcode":"8340",
    "sg:province":"Z\u00fcrich",
    "wof:name":"Aquasystems Suess & Meerwasseraquaristik",
    "wof:placetype":"venue"
},
  "geometry": {"coordinates":[8.8435297012,47.3023300171],"type":"Point"}
}