{
  "type": "Feature",
  "properties": {
    "iso:country":"CH",
    "sg:address":"Largo Libero Olgiati 75a 6512 Giubiasco. Postfach Caselle Postale 545",
    "sg:city":"Giubiasco",
    "sg:orig_category":"Versicherungen Generalagenturen",
    "sg:phone":"+41 91 857 55 73",
    "sg:postcode":"6512",
    "sg:province":"Ticino",
    "wof:name":"Rentenanstalt/swiss Life Agenzia Generale Di Giubiasco",
    "wof:placetype":"venue"
},
  "geometry": {"coordinates":[9.0097942352,46.1726875305],"type":"Point"}
}