{
  "type": "Feature",
  "properties": {
    "iso:country":"CH",
    "sg:address":"Rue Du Botzet 20",
    "sg:city":"Fribourg",
    "sg:orig_category":"Bauschreinerei Herstellung von M\u00f6beln verschiedener Art",
    "sg:phone":"+41 26 424 67 35",
    "sg:postcode":"1700",
    "sg:province":"Fribourg",
    "wof:name":"Louis & Denise Falcone Eb\u00e9nisterie D'art",
    "wof:placetype":"venue"
},
  "geometry": {"coordinates":[7.157005,46.797115],"type":"Point"}
}