{
  "type": "Feature",
  "properties": {
    "iso:country":"CH",
    "sg:address":"Route Du Centre 6",
    "sg:city":"Marly",
    "sg:orig_category":"Dienstleistungen von Beteiligungsgesellschaften",
    "sg:postcode":"1723",
    "sg:province":"Fribourg",
    "wof:name":"Benem Services, Tous Travaux Administratifs, B. Emmenegger",
    "wof:placetype":"venue"
},
  "geometry": {"coordinates":[7.1498742104,46.7828216553],"type":"Point"}
}