{
  "type": "Feature",
  "properties": {
    "iso:country":"CH",
    "sg:address":"Pulverm\u00fchlestrasse 12",
    "sg:city":"Chur",
    "sg:orig_category":"Sanit\u00e4r U Heizungsinstallation",
    "sg:phone":"+41 27 203 37 67",
    "sg:postcode":"7000",
    "sg:province":"Graubunden",
    "wof:name":"Oertli Service Ag",
    "wof:placetype":"venue"
},
  "geometry": {"coordinates":[7.3697719574,46.2272453308],"type":"Point"}
}