{
  "type": "Feature",
  "properties": {
    "iso:country":"CH",
    "sg:address":"Egolzwilerstrasse 14 6244 Nebikon. Postfach 157",
    "sg:city":"Nebikon",
    "sg:orig_category":"Grosshandel mit Erzen U Metallen",
    "sg:phone":"+41 62 748 33 33",
    "sg:postcode":"6244",
    "sg:province":"Luzern",
    "wof:name":"Rekag Ag",
    "wof:placetype":"venue"
},
  "geometry": {"coordinates":[7.978302002,47.1921081543],"type":"Point"}
}