{
  "type": "Feature",
  "properties": {
    "iso:country":"CH",
    "sg:address":"Kappelenring 44 C Hinterkappelen 3033 Wohlen B. Bern. Postfach",
    "sg:city":"Hinterkappelen",
    "sg:orig_category":"Architektur U Ingenieurb\u00fcros",
    "sg:postcode":"3032",
    "sg:province":"Bern",
    "wof:name":"Luxon Ag",
    "wof:placetype":"venue"
},
  "geometry": {"coordinates":[7.35617,46.971165],"type":"Point"}
}