{
  "type": "Feature",
  "properties": {
    "addr:full":"Bahnhofstrasse 2 Root Luzern 6037",
    "addr:housenumber":"2",
    "addr:postcode":"6037",
    "addr:street":"Bahnhofstrasse",
    "iso:country":"CH",
    "sg:address":"Bahnhofstrasse 2",
    "sg:city":"Root",
    "sg:orig_category":"Detailhandel mit B\u00fcchern, Zeitungen, Schreib U Papeteriewaren Schnelldruck U Kopierservice",
    "sg:phone":"+41 41 450 34 51",
    "sg:postcode":"6037",
    "sg:province":"Luzern",
    "wof:name":"Papeterie Mazenauer Ag",
    "wof:placetype":"venue"
},
  "geometry": {"coordinates":[8.39027,47.115078],"type":"Point"}
}