{
  "type": "Feature",
  "properties": {
    "iso:country":"CH",
    "sg:address":"1562",
    "sg:city":"Corcelles-payerne",
    "sg:orig_category":"Haltung von Schafen, Ziegen, Pferden U Eseln",
    "sg:postcode":"1562",
    "sg:province":"Vaud",
    "wof:name":"Syndicat D'\u00e9levage Du Cheval Payerne-avenches.",
    "wof:placetype":"venue"
},
  "geometry": {"coordinates":[6.9492001534,46.8255996704],"type":"Point"}
}