{
  "type": "Feature",
  "properties": {
    "iso:country":"CH",
    "sg:address":"Hinterdorfstrasse 28",
    "sg:city":"Landschlacht",
    "sg:orig_category":"Innenarchitekturb\u00fcros",
    "sg:phone":"+41 71 690 01 61",
    "sg:postcode":"8597",
    "sg:province":"Thurgau",
    "wof:name":"Christof & Brigitte Roell Innenarchitektur",
    "wof:placetype":"venue"
},
  "geometry": {"coordinates":[9.2400007248,47.6251144409],"type":"Point"}
}