{
  "type": "Feature",
  "properties": {
    "iso:country":"CH",
    "sg:address":"Grauholzstrasse 66",
    "sg:city":"Ittigen",
    "sg:orig_category":"Unternehmensberatung",
    "sg:postcode":"3063",
    "sg:province":"Bern",
    "wof:name":"W.b Wirtschaftsberatung Pero Brajinovic",
    "wof:placetype":"venue"
},
  "geometry": {"coordinates":[7.4798769951,46.9852561951],"type":"Point"}
}