{
  "type": "Feature",
  "properties": {
    "iso:country":"CH",
    "sg:address":"Egliswilerstrasse 35",
    "sg:city":"Seengen",
    "sg:orig_category":"Instandhaltung U Reparatur von Automobilen",
    "sg:phone":"+41 55 615 14 54",
    "sg:postcode":"5707",
    "sg:province":"Aargau",
    "wof:name":"Feldgarage, Zahner Erwin",
    "wof:placetype":"venue"
},
  "geometry": {"coordinates":[9.0545148849,47.1724510193],"type":"Point"}
}