{
  "type": "Feature",
  "properties": {
    "iso:country":"CH",
    "sg:address":"Querstrasse 8 8105 Regensdorf. Postfach",
    "sg:city":"Regensdorf",
    "sg:orig_category":"Grosshandel mit sonstigen Konsumg\u00fctern Handelsvermittlung von Textilien, Bekleidung, Schuhen U Leder",
    "sg:phone":"+41 18402930",
    "sg:postcode":"8105",
    "sg:province":"Z\u00fcrich",
    "wof:name":"Zimmermann Robert & Co",
    "wof:placetype":"venue"
},
  "geometry": {"coordinates":[8.461625,47.442631],"type":"Point"}
}