{
  "type": "Feature",
  "properties": {
    "addr:full":"9122 Mogelsberg St. Gallen 9122",
    "addr:housenumber":"9122;st.",
    "addr:postcode":"9122",
    "addr:street":"Mogelsberg",
    "iso:country":"CH",
    "sg:address":"9122",
    "sg:city":"Mogelsberg",
    "sg:classifiers":[
        {
            "category":"Education",
            "subcategory":"Library",
            "type":"Public Place"
        }
    ],
    "sg:postcode":"9122",
    "sg:province":"St. Gallen",
    "sg:tags":[
        "u",
        "bibliotheken",
        "archive"
    ],
    "wof:name":"Katholische Volksbibliothek",
    "wof:placetype":"venue"
},
  "geometry": {"coordinates":[9.517035,47.27721],"type":"Point"}
}