{
  "type": "Feature",
  "properties": {
    "iso:country":"CH",
    "sg:address":"Crusch 31",
    "sg:city":"Samedan",
    "sg:orig_category":"Kaminfeger",
    "sg:phone":"+41 81 852 31 18",
    "sg:postcode":"7503",
    "sg:province":"Graubunden",
    "wof:name":"Franz Andri Kaminfegermeister",
    "wof:placetype":"venue"
},
  "geometry": {"coordinates":[9.8752183914,46.5397148132],"type":"Point"}
}