{
  "type": "Feature",
  "properties": {
    "iso:country":"CH",
    "sg:address":"Avenue De La Gare 10 1000 Lausanne. Postfach",
    "sg:city":"Lausanne",
    "sg:orig_category":"Finanzierungsinstitutionen",
    "sg:postcode":"1003",
    "sg:province":"Vaud",
    "wof:name":"Advorgef Sa",
    "wof:placetype":"venue"
},
  "geometry": {"coordinates":[6.6359519958,46.5169792175],"type":"Point"}
}