{
  "type": "Feature",
  "properties": {
    "iso:country":"CH",
    "sg:address":"Avenue Des Ormonts 20 1860 Aigle Case Postale 301",
    "sg:city":"Aigle",
    "sg:orig_category":"Instandhaltung U Reparatur von Automobilen Vermietung von Automobilen",
    "sg:phone":"+41 24 466 14 11",
    "sg:postcode":"1860",
    "sg:province":"Vaud",
    "wof:name":"Roger Gailloud Garage-carrosserie",
    "wof:placetype":"venue"
},
  "geometry": {"coordinates":[6.9742817879,46.3174781799],"type":"Point"}
}