{
  "type": "Feature",
  "properties": {
    "iso:country":"CH",
    "sg:address":"Hauptstrasse 87",
    "sg:city":"Frick",
    "sg:classifiers":[
        {
            "category":"Restaurant",
            "type":"Food & Drink"
        }
    ],
    "sg:phone":"+41 62 871 71 75",
    "sg:postcode":"5070",
    "sg:province":"Aargau",
    "wof:name":"Restaurant Central",
    "wof:placetype":"venue"
},
  "geometry": {"coordinates":[8.0236988068,47.5060997009],"type":"Point"}
}