{
  "type": "Feature",
  "properties": {
    "iso:country":"CH",
    "sg:address":"Br\u00fchlstrasse 2",
    "sg:city":"Arbon",
    "sg:orig_category":"Interessenvertretungen",
    "sg:postcode":"9320",
    "sg:province":"Thurgau",
    "wof:name":"Wohlfahrtsfonds Der Firma Ingenieurb\u00fcro W\u00e4lli Ag, Arbon",
    "wof:placetype":"venue"
},
  "geometry": {"coordinates":[9.4315891266,47.5129699707],"type":"Point"}
}