{
  "type": "Feature",
  "properties": {
    "iso:country":"CH",
    "sg:address":"Breitenbachstrasse 45b",
    "sg:city":"B\u00fcsserach",
    "sg:orig_category":"Mechanische Werkst\u00e4tten",
    "sg:phone":"+41 61 781 24 24",
    "sg:postcode":"4227",
    "sg:province":"Solothurn",
    "wof:name":"Stefan Neyerlin Mechanische Werkstatt",
    "wof:placetype":"venue"
},
  "geometry": {"coordinates":[7.5415549278,47.3950462341],"type":"Point"}
}