{
  "type": "Feature",
  "properties": {
    "iso:country":"CH",
    "sg:address":"Cho D'punt 51",
    "sg:city":"Samedan",
    "sg:orig_category":"Einzelhandel mit Automobilteilen U Zubeh\u00f6r Herstellung von Bereifungen",
    "sg:phone":"+41 62 207 80 10",
    "sg:postcode":"7503",
    "sg:province":"Graubunden",
    "wof:name":"Viborg Ag Serviccenter",
    "wof:placetype":"venue"
},
  "geometry": {"coordinates":[7.8637719154,47.3422622681],"type":"Point"}
}