{
  "type": "Feature",
  "properties": {
    "iso:country":"CH",
    "sg:address":"Hauptstrasse 75",
    "sg:city":"Siblingen",
    "sg:classifiers":[
        {
            "category":"Restaurant",
            "type":"Food & Drink"
        }
    ],
    "sg:phone":"+41 61 711 12 82",
    "sg:postcode":"8225",
    "sg:province":"Schaffhausen",
    "wof:name":"Restaurant Im Zentrum",
    "wof:placetype":"venue"
},
  "geometry": {"coordinates":[7.5935587883,47.4929580688],"type":"Point"}
}