{
  "type": "Feature",
  "properties": {
    "iso:country":"CH",
    "sg:address":"Seetalstrasse 47",
    "sg:city":"Seon",
    "sg:classifiers":[
        {
            "category":"Banks & Credit Unions",
            "subcategory":"Bank",
            "type":"Services"
        }
    ],
    "sg:phone":"+41 4164551112",
    "sg:postcode":"5703",
    "sg:province":"Aargau",
    "wof:name":"Hypothekarbank Lenzburg",
    "wof:placetype":"venue"
},
  "geometry": {"coordinates":[8.159143,47.347187],"type":"Point"}
}