{
  "type": "Feature",
  "properties": {
    "iso:country":"CH",
    "sg:address":"Dorfstrasse 10",
    "sg:city":"L\u00fctzelfl\u00fch-goldb",
    "sg:orig_category":"Drogerien",
    "sg:phone":"+41 34 461 15 88",
    "sg:postcode":"3432",
    "sg:province":"Bern",
    "wof:name":"Hans W\u00fcthrich",
    "wof:placetype":"venue"
},
  "geometry": {"coordinates":[7.684899807,47.0065917969],"type":"Point"}
}