{
  "type": "Feature",
  "properties": {
    "iso:country":"CH",
    "sg:address":"T\u00fcftelstr. 50",
    "sg:city":"Koblenz",
    "sg:classifiers":[
        {
            "category":"Shopping",
            "subcategory":"Computers & Home Electronics",
            "type":"Retail Goods"
        }
    ],
    "sg:phone":"+41 32 925 61 11",
    "sg:postcode":"5322",
    "sg:province":"Aargau",
    "sg:tags":[
        "electronic",
        "electrical",
        "equipment"
    ],
    "wof:name":"Portescap",
    "wof:placetype":"venue"
},
  "geometry": {"coordinates":[6.8133649826,47.0942764282],"type":"Point"}
}