{
  "type": "Feature",
  "properties": {
    "addr:full":"Via Maggio 2 Lugano Ticino 6900",
    "addr:housenumber":"2",
    "addr:postcode":"6900",
    "addr:street":"Via Maggio",
    "iso:country":"CH",
    "sg:address":"Via Maggio 2",
    "sg:city":"Lugano",
    "sg:orig_category":"Arztpraxen",
    "sg:phone":"+41 91 971 65 55",
    "sg:postcode":"6900",
    "sg:province":"Ticino",
    "wof:name":"Dres Med. J. & A. B\u00e9rub\u00e9 Specialisti Fmh",
    "wof:placetype":"venue"
},
  "geometry": {"coordinates":[8.961249,46.007786],"type":"Point"}
}