{
  "type": "Feature",
  "properties": {
    "iso:country":"CH",
    "sg:address":"St-cergue Route De 308",
    "sg:city":"Nyon",
    "sg:orig_category":"Allgemeiner Hoch U Tiefbau",
    "sg:postcode":"1260",
    "sg:province":"Vaud",
    "wof:name":"P.b.m.e. Forchaux & Cie",
    "wof:placetype":"venue"
},
  "geometry": {"coordinates":[6.23908,46.382366],"type":"Point"}
}