{
  "type": "Feature",
  "properties": {
    "iso:country":"CH",
    "sg:address":"Wiese 5",
    "sg:city":"Mitl\u00f6di",
    "sg:orig_category":"Malerei",
    "sg:phone":"+41 79 290 04 08",
    "sg:postcode":"8756",
    "sg:province":"Glarus",
    "wof:name":"Dino Lovisetto Malergesch\u00e4ft",
    "wof:placetype":"venue"
},
  "geometry": {"coordinates":[9.0779190063,47.0090332031],"type":"Point"}
}