{
  "type": "Feature",
  "properties": {
    "iso:country":"CH",
    "sg:address":"Schiblerweg 2 5026 Densb\u00fcren. Postfach",
    "sg:city":"Densb\u00fcren",
    "sg:orig_category":"M\u00f6belschreinereien",
    "sg:phone":"+41 62 893 12 84",
    "sg:postcode":"5026",
    "sg:province":"Aargau",
    "wof:name":"Walter Thut Ag, M\u00f6belfabrik, M\u00f6riken",
    "wof:placetype":"venue"
},
  "geometry": {"coordinates":[8.1889638901,47.4144325256],"type":"Point"}
}