{
  "type": "Feature",
  "properties": {
    "iso:country":"CH",
    "sg:address":"Rue Marterey 5 1000 Lausanne. Postfach",
    "sg:city":"Gen\u00e8ve",
    "sg:orig_category":"Detektivb\u00fcros U \u00dcberwachung",
    "sg:postcode":"1201",
    "sg:province":"Gen\u00e8ve",
    "wof:name":"F.g. Security S\u00e0rl",
    "wof:placetype":"venue"
},
  "geometry": {"coordinates":[6.6379141808,46.5203781128],"type":"Point"}
}