{
  "type": "Feature",
  "properties": {
    "iso:country":"CH",
    "sg:address":"Valais Avenue Du 3",
    "sg:city":"Vouvry",
    "sg:orig_category":"Unclassifiable Establishments",
    "sg:postcode":"1896",
    "sg:province":"Valais",
    "wof:name":"Caf\u00e9-restaurant De L'union S.\u00e0 R.l.",
    "wof:placetype":"venue"
},
  "geometry": {"coordinates":[6.8908228874,46.3360748291],"type":"Point"}
}