{
  "type": "Feature",
  "properties": {
    "iso:country":"CH",
    "sg:address":"Josefstrasse 140 8005 Z\u00fcrich. Postfach",
    "sg:city":"Z\u00fcrich",
    "sg:orig_category":"Sonstiger Grosshandel",
    "sg:postcode":"8001",
    "sg:province":"Z\u00fcrich",
    "wof:name":"Lipczynski Cezary Waren Usw; Export, Import U. Handel",
    "wof:placetype":"venue"
},
  "geometry": {"coordinates":[8.5279493332,47.3843574524],"type":"Point"}
}