{
  "type": "Feature",
  "properties": {
    "iso:country":"CH",
    "sg:address":"Bahnhofstrasse 8",
    "sg:city":"M\u00fcntschemier",
    "sg:orig_category":"Vereine Gesang",
    "sg:postcode":"3225",
    "sg:province":"Bern",
    "wof:name":"M\u00e4nnerchor Affoltern",
    "wof:placetype":"venue"
},
  "geometry": {"coordinates":[8.4532852173,47.2772254944],"type":"Point"}
}