{
  "type": "Feature",
  "properties": {
    "iso:country":"CH",
    "sg:address":"Dufourstrasse 23",
    "sg:city":"Z\u00fcrich",
    "sg:orig_category":"Fotografische Ateliers Korrespondenz U Nachrichtenb\u00fcros",
    "sg:phone":"+41 31 351 14 33",
    "sg:postcode":"8008",
    "sg:province":"Z\u00fcrich",
    "wof:name":"Roland Aellig Atelier F. Fotografie U. Video",
    "wof:placetype":"venue"
},
  "geometry": {"coordinates":[7.4557747841,46.9415779114],"type":"Point"}
}