{
  "type": "Feature",
  "properties": {
    "iso:country":"CH",
    "sg:address":"Aachstrasse 4",
    "sg:city":"Erlen",
    "sg:orig_category":"Maurerarbeiten",
    "sg:phone":"+41 71 648 18 27",
    "sg:postcode":"8586",
    "sg:province":"Thurgau",
    "wof:name":"Bernardo Di Vincenzo Gmbh Kundenmaurer /hoch- & Tiefbau",
    "wof:placetype":"venue"
},
  "geometry": {"coordinates":[9.2286148071,47.5518341064],"type":"Point"}
}