{
  "type": "Feature",
  "properties": {
    "iso:country":"CH",
    "sg:address":"Im Dorf 56",
    "sg:city":"Schellenberg",
    "sg:orig_category":"Bibliotheken U Archive Wohnheime",
    "sg:phone":"+41 75 373 45 78",
    "sg:postcode":"9488",
    "wof:name":"Frauenkloster Vom",
    "wof:placetype":"venue"
},
  "geometry": {"coordinates":[9.547331,47.232578],"type":"Point"}
}