{
  "type": "Feature",
  "properties": {
    "iso:country":"CH",
    "sg:address":"Schwandmatt 317",
    "sg:city":"R\u00fceggisberg",
    "sg:orig_category":"Allgemeiner Hochbau Zimmerei, Dachdeckerei, Bauspenglerei U Abdichtung",
    "sg:phone":"+41 62 926 35 08",
    "sg:postcode":"3088",
    "sg:province":"Bern",
    "wof:name":"Strub Kurt Zimmerei + Bedachungen",
    "wof:placetype":"venue"
},
  "geometry": {"coordinates":[7.848037,47.272717],"type":"Point"}
}