{
  "type": "Feature",
  "properties": {
    "iso:country":"CH",
    "sg:address":"Schellenrainstrasse 24",
    "sg:city":"Sursee",
    "sg:orig_category":"Finanzierungsinstitutionen",
    "sg:phone":"+41 41 921 02 24",
    "sg:postcode":"6210",
    "sg:province":"Luzern",
    "wof:name":"Bowo Vertriebshandlung Bohner Wolfgang",
    "wof:placetype":"venue"
},
  "geometry": {"coordinates":[8.1029310226,47.1668701172],"type":"Point"}
}