{
  "type": "Feature",
  "properties": {
    "iso:country":"CH",
    "sg:address":"Mattenstrasse 1",
    "sg:city":"Lostorf",
    "sg:orig_category":"Unternehmensberatung",
    "sg:phone":"+41 62 298 28 19",
    "sg:postcode":"4654",
    "sg:province":"Solothurn",
    "wof:name":"Lutz Dr. Hans Rudolf",
    "wof:placetype":"venue"
},
  "geometry": {"coordinates":[7.9526629448,47.3808822632],"type":"Point"}
}