{
  "type": "Feature",
  "properties": {
    "iso:country":"CH",
    "sg:address":"Brauihof 2 4900 Langenthal. Postfach 836",
    "sg:city":"Langenthal",
    "sg:orig_category":"Grosshandel mit Maschinen U Ausr\u00fcstungen Sonstige mit der Informatik verbundene T\u00e4tigkeiten",
    "sg:phone":"+41 62 919 10 00",
    "sg:postcode":"4900",
    "sg:province":"Bern",
    "wof:name":"Personal Soft Ag",
    "wof:placetype":"venue"
},
  "geometry": {"coordinates":[7.7880578041,47.2128448486],"type":"Point"}
}