{
  "type": "Feature",
  "properties": {
    "iso:country":"CH",
    "sg:address":"Trittligasse 5",
    "sg:city":"Z\u00fcrich",
    "sg:orig_category":"Forschung U Entwicklung im Bereich der Naturwissenschaften",
    "sg:postcode":"8001",
    "sg:province":"Z\u00fcrich",
    "wof:name":"Organismus Und Technik, Arbeitskreis F\u00fcr Eine Organgesetzliche Lebensgestaltung Erarbeitung Humanbiolog. Erkenntnisse, Usw.",
    "wof:placetype":"venue"
},
  "geometry": {"coordinates":[8.5450954437,47.3693695068],"type":"Point"}
}