{
  "type": "Feature",
  "properties": {
    "iso:country":"CH",
    "sg:address":"Bahnhofstrasse 1",
    "sg:city":"Steinhausen",
    "sg:orig_category":"Physiotherapie",
    "sg:phone":"+41 41 429 95 44",
    "sg:postcode":"6312",
    "sg:province":"Zug",
    "wof:name":"Thomas & Domenica Nyffeler Physiotherapie",
    "wof:placetype":"venue"
},
  "geometry": {"coordinates":[8.4840221405,47.1964073181],"type":"Point"}
}