{
  "type": "Feature",
  "properties": {
    "iso:country":"CH",
    "sg:address":"1730",
    "sg:city":"Ecuvillens",
    "sg:orig_category":"Sportvereine Sch\u00fctzen",
    "sg:phone":"+41 21 869 82 55",
    "sg:postcode":"1730",
    "sg:province":"Fribourg",
    "wof:name":"St\u00e9 De Tir De La Senoge",
    "wof:placetype":"venue"
},
  "geometry": {"coordinates":[6.4675898552,46.555770874],"type":"Point"}
}