{
  "type": "Feature",
  "properties": {
    "iso:country":"CH",
    "sg:address":"Matthof 30 6014 Littau. Postfach",
    "sg:city":"Emmenbr\u00fccke",
    "sg:orig_category":"Detailhandel mit elektrischen Haushalts-,Radio U Fernsehger\u00e4ten sowie Musikinstrumenten",
    "sg:postcode":"6020",
    "sg:province":"Luzern",
    "wof:name":"Electra Riccio",
    "wof:placetype":"venue"
},
  "geometry": {"coordinates":[8.268576622,47.0516357422],"type":"Point"}
}