{
  "type": "Feature",
  "properties": {
    "iso:country":"CH",
    "sg:address":"M\u00fcnchensteinerstrasse 1",
    "sg:city":"Basel",
    "sg:orig_category":"Diskotheken, Dancings, Night Clubs",
    "sg:phone":"+41 61 313 60 72",
    "sg:postcode":"4052",
    "sg:province":"Basel-Stadt",
    "wof:name":"Discothek Tr\u00e4mli",
    "wof:placetype":"venue"
},
  "geometry": {"coordinates":[7.5983290672,47.5475387573],"type":"Point"}
}