{
  "type": "Feature",
  "properties": {
    "addr:full":"Haus Furkablick/tomelistrasse 7050 Arosa. Postfach 104 Arosa Graubunden 7050",
    "addr:housenumber":"104",
    "addr:postcode":"7050 arosa.;7050",
    "addr:street":"Tomelistrasse;Postfach;Graubunden",
    "iso:country":"CH",
    "sg:address":"Haus Furkablick/tomelistrasse 7050 Arosa. Postfach 104",
    "sg:city":"Arosa",
    "sg:orig_category":"Detailhandel mit Brennstoffen U Heizmaterial Detailhandel mit Getr\u00e4nken",
    "sg:phone":"+41 27 932 19 05",
    "sg:postcode":"7050",
    "sg:province":"Graubunden",
    "wof:name":"Max Schnydrig Ag",
    "wof:placetype":"venue"
},
  "geometry": {"coordinates":[7.752598,46.312737],"type":"Point"}
}