{
  "type": "Feature",
  "properties": {
    "iso:country":"CH",
    "sg:address":"Rue Du Milieu 17 2500 Biel/bienne. Postfach",
    "sg:city":"Biel/bienne",
    "sg:orig_category":"Softwareentwicklung U beratung",
    "sg:postcode":"2502",
    "sg:province":"Bern",
    "wof:name":"Les Marquis, Marcheggiani R.",
    "wof:placetype":"venue"
},
  "geometry": {"coordinates":[7.2495861053,47.1415672302],"type":"Point"}
}