{
  "type": "Feature",
  "properties": {
    "iso:country":"CH",
    "sg:address":"Chemin Du Verger 3",
    "sg:city":"Ballaigues",
    "sg:orig_category":"Unclassifiable Establishments",
    "sg:postcode":"1338",
    "sg:province":"Vaud",
    "wof:name":"Maillefer Instruments Holding S\u00e0rl",
    "wof:placetype":"venue"
},
  "geometry": {"coordinates":[6.4194102287,46.7284355164],"type":"Point"}
}