{
  "type": "Feature",
  "properties": {
    "iso:country":"CH",
    "sg:address":"Bahnhofstrasse 18",
    "sg:city":"Zermatt",
    "sg:orig_category":"RESTAURANTS: TEA-ROOMS",
    "sg:phone":"+41 27 967 58 55",
    "sg:postcode":"3920",
    "sg:province":"Valais",
    "wof:name":"Restaurant Swiss Chalet, Julen Emil",
    "wof:placetype":"venue"
},
  "geometry": {"coordinates":[7.7472782135,46.0228233337],"type":"Point"}
}