{
  "type": "Feature",
  "properties": {
    "addr:full":"B\u00f6deli Appenzell Appenzell Innerhoden 9050",
    "addr:postcode":"9050",
    "iso:country":"CH",
    "sg:address":"B\u00f6deli",
    "sg:city":"Appenzell",
    "sg:orig_category":"Abwasserreinigung",
    "sg:phone":"+41 71 787 33 07",
    "sg:postcode":"9050",
    "sg:province":"Appenzell Innerhoden",
    "wof:name":"Ara Appenzell Abwasserreinigungsanlage",
    "wof:placetype":"venue"
},
  "geometry": {"coordinates":[9.412077,47.336052],"type":"Point"}
}