{
  "type": "Feature",
  "properties": {
    "iso:country":"CH",
    "sg:address":"Gaswerkstrasse 66",
    "sg:city":"Langenthal",
    "sg:classifiers":[
        {
            "category":"Wholesale",
            "subcategory":"Plants",
            "type":"Manufacturing & Wholesale Goods"
        }
    ],
    "sg:phone":"+41 62 922 63 22",
    "sg:postcode":"4900",
    "sg:province":"Bern",
    "sg:tags":[
        "mobile",
        "plants",
        "asphalting"
    ],
    "wof:name":"Graber Baumschinen Ag",
    "wof:placetype":"venue"
},
  "geometry": {"coordinates":[7.790539,47.229439],"type":"Point"}
}