{
  "type": "Feature",
  "properties": {
    "iso:country":"CH",
    "sg:address":"Rue Du Scex 21 1950 Sion. Postfach",
    "sg:city":"Sion",
    "sg:orig_category":"Berufsbildende weiterf\u00fchrende Schulen",
    "sg:phone":"+41 71 274 51 71",
    "sg:postcode":"1950",
    "sg:province":"Valais",
    "wof:name":"Elektrofachschule St.gallen",
    "wof:placetype":"venue"
},
  "geometry": {"coordinates":[9.346289,47.413025],"type":"Point"}
}