{
  "type": "Feature",
  "properties": {
    "iso:country":"CH",
    "sg:address":"Morgentalstrasse 34 8355 Aadorf. Postfach",
    "sg:city":"Aadorf",
    "sg:orig_category":"Galvanische Betriebe",
    "sg:phone":"+41 52 365 34 93",
    "sg:postcode":"8355",
    "sg:province":"Thurgau",
    "wof:name":"Ren\u00e9 Sch\u00e4fer Metallveredlung Verzinkerei",
    "wof:placetype":"venue"
},
  "geometry": {"coordinates":[8.8960943222,47.4940986633],"type":"Point"}
}