{
  "type": "Feature",
  "properties": {
    "iso:country":"CH",
    "sg:address":"Gerliswilstrasse 70",
    "sg:city":"Emmenbr\u00fccke",
    "sg:orig_category":"Detailhandel mit Fleisch U Fleischwaren",
    "sg:phone":"+41 41 260 17 51",
    "sg:postcode":"6020",
    "sg:province":"Luzern",
    "wof:name":"Josef B\u00fchlmann Metzgerei",
    "wof:placetype":"venue"
},
  "geometry": {"coordinates":[8.275850296,47.0773696899],"type":"Point"}
}