{
  "type": "Feature",
  "properties": {
    "iso:country":"CH",
    "sg:address":"Masanserstrasse 182",
    "sg:city":"Chur",
    "sg:orig_category":"Instandhaltung U Reparatur von Automobilen",
    "sg:phone":"+41 79 222 22 23",
    "sg:postcode":"7000",
    "sg:province":"Graubunden",
    "wof:name":"Weisstorkel Garage Ag",
    "wof:placetype":"venue"
},
  "geometry": {"coordinates":[9.5352087021,46.8655738831],"type":"Point"}
}