{
  "type": "Feature",
  "properties": {
    "iso:country":"CH",
    "sg:address":"Hammerstrasse 89",
    "sg:city":"Basel",
    "sg:orig_category":"Datenverarbeitungsdienste",
    "sg:phone":"+41 61 691 70 10",
    "sg:postcode":"4057",
    "sg:province":"Basel-Stadt",
    "wof:name":"Hans Peter Tschopp Edv-beratung",
    "wof:placetype":"venue"
},
  "geometry": {"coordinates":[7.595267,47.564831],"type":"Point"}
}