{
  "type": "Feature",
  "properties": {
    "iso:country":"CH",
    "sg:address":"Dorfstrasse 32",
    "sg:city":"Lupfig",
    "sg:orig_category":"Detailhandel mit Fleisch U Fleischwaren Grosshandel mit lebenden Tieren",
    "sg:phone":"+41 79 302 93 01",
    "sg:postcode":"5242",
    "sg:province":"Aargau",
    "wof:name":"Kyburz-stebler Hansruedi",
    "wof:placetype":"venue"
},
  "geometry": {"coordinates":[8.2015342712,47.4413108826],"type":"Point"}
}