{
  "type": "Feature",
  "properties": {
    "iso:country":"CH",
    "sg:address":"R\u00fctiweg 7",
    "sg:city":"Pratteln",
    "sg:orig_category":"Tapezierer/Dekorateure",
    "sg:phone":"+41 21 923 67 62",
    "sg:postcode":"4133",
    "sg:province":"Basel-Landschaft",
    "wof:name":"Atg S\u00e0rl Paul Grisafi",
    "wof:placetype":"venue"
},
  "geometry": {"coordinates":[5.1808700562,45.8973388672],"type":"Point"}
}