{
  "type": "Feature",
  "properties": {
    "iso:country":"CH",
    "sg:address":"Brunngasse 1",
    "sg:city":"M\u00f6hlin",
    "sg:orig_category":"Allgemeiner Hoch U Tiefbau",
    "sg:phone":"+41 61 851 32 52",
    "sg:postcode":"4313",
    "sg:province":"Aargau",
    "wof:name":"Max Andermatt Baugesch\u00e4ft",
    "wof:placetype":"venue"
},
  "geometry": {"coordinates":[7.84526,47.557472],"type":"Point"}
}