{
  "type": "Feature",
  "properties": {
    "iso:country":"CH",
    "sg:address":"Esparcette Chemin De L' 2",
    "sg:city":"Crissier",
    "sg:classifiers":[
        {
            "category":"Travel",
            "subcategory":"Hotels & Motels",
            "type":"Entertainment"
        }
    ],
    "sg:postcode":"1023",
    "sg:province":"Vaud",
    "sg:tags":[
        "hotels",
        "mit",
        "restaurant"
    ],
    "wof:name":"Cristal Bad Ragaz Ag",
    "wof:placetype":"venue"
},
  "geometry": {"coordinates":[9.505109787,47.0095329285],"type":"Point"}
}