{
  "type": "Feature",
  "properties": {
    "iso:country":"CH",
    "sg:address":"Rte Choulex 111",
    "sg:city":"Choulex",
    "sg:classifiers":[
        {
            "category":"Banks & Credit Unions",
            "subcategory":"Bank",
            "type":"Services"
        }
    ],
    "sg:phone":"+41 22 750 18 76",
    "sg:postcode":"1244",
    "sg:province":"Gen\u00e8ve",
    "wof:name":"Banque Raiffeisen",
    "wof:placetype":"venue"
},
  "geometry": {"coordinates":[6.222339,46.2229],"type":"Point"}
}