{
  "type": "Feature",
  "properties": {
    "iso:country":"CH",
    "sg:address":"Baslerstrasse 32",
    "sg:city":"Olten",
    "sg:classifiers":[
        {
            "category":"Banks & Credit Unions",
            "subcategory":"Bank",
            "type":"Services"
        }
    ],
    "sg:phone":"+41 4162323737",
    "sg:postcode":"4600",
    "sg:province":"Solothurn",
    "wof:name":"Schweiz. Mobiliar",
    "wof:placetype":"venue"
},
  "geometry": {"coordinates":[7.902838,47.351215],"type":"Point"}
}