{
  "type": "Feature",
  "properties": {
    "iso:country":"CH",
    "sg:address":"Brandschenkestrasse 6",
    "sg:city":"Z\u00fcrich",
    "sg:orig_category":"Fachdetailhandel in Verkaufsr\u00e4umen",
    "sg:phone":"+41 79 445 78 90",
    "sg:postcode":"8002",
    "sg:province":"Z\u00fcrich",
    "wof:name":"Elrowi-vertretungen E. + R. Wiesmann",
    "wof:placetype":"venue"
},
  "geometry": {"coordinates":[8.7984800339,47.3245201111],"type":"Point"}
}