{
  "type": "Feature",
  "properties": {
    "iso:country":"CH",
    "sg:address":"7064",
    "sg:city":"Tschiertschen",
    "sg:classifiers":[
        {
            "category":"Education",
            "subcategory":"Library",
            "type":"Public Place"
        }
    ],
    "sg:postcode":"7064",
    "sg:province":"Graubunden",
    "sg:tags":[
        "u",
        "bibliotheken",
        "archive"
    ],
    "wof:name":"Volksbibliothek Tschiertschen-praden",
    "wof:placetype":"venue"
},
  "geometry": {"coordinates":[9.606309,46.819122],"type":"Point"}
}