{
  "type": "Feature",
  "properties": {
    "iso:country":"CH",
    "sg:address":"Route Mon-foyer 4",
    "sg:city":"Fribourg",
    "sg:orig_category":"Micromeasuring Devices, Measuring Tools",
    "sg:phone":"+41 26 407 11 11",
    "sg:postcode":"1700",
    "sg:province":"Fribourg",
    "wof:name":"Vibro Meter S.a.",
    "wof:placetype":"venue"
},
  "geometry": {"coordinates":[7.1392469406,46.8093605042],"type":"Point"}
}