{
  "type": "Feature",
  "properties": {
    "iso:country":"CH",
    "sg:address":"Avenue Du Grand-st-bernard 25",
    "sg:city":"Martigny",
    "sg:orig_category":"Herstellung von medizinischen U chirurgischen Ger\u00e4ten sowie orthop\u00e4dischen Vorrichtungen Zahntechnis",
    "sg:phone":"+41 27 722 79 59",
    "sg:postcode":"1920",
    "sg:province":"Valais",
    "wof:name":"Laboratoire Dentaire Livet Christian",
    "wof:placetype":"venue"
},
  "geometry": {"coordinates":[7.0707168579,46.0988960266],"type":"Point"}
}