{
  "type": "Feature",
  "properties": {
    "addr:full":"Zugerstrasse 3 Ebikon Luzern 6030",
    "addr:housenumber":"3",
    "addr:postcode":"6030",
    "addr:street":"Zugerstrasse",
    "iso:country":"CH",
    "sg:address":"Zugerstrasse 3",
    "sg:city":"Ebikon",
    "sg:orig_category":"Autogaragen",
    "sg:phone":"+41 79 209 22 82",
    "sg:postcode":"6030",
    "sg:province":"Luzern",
    "wof:name":"Hans Fleischli Garage",
    "wof:placetype":"venue"
},
  "geometry": {"coordinates":[8.345659,47.084694],"type":"Point"}
}