{
  "type": "Feature",
  "properties": {
    "iso:country":"CH",
    "sg:address":"Tannerstrasse 25",
    "sg:city":"Aarau",
    "sg:orig_category":"Unclassifiable Establishments",
    "sg:postcode":"5000",
    "sg:province":"Aargau",
    "wof:name":"Genossenschaft Hestia - Wohnprojekt Fraueninitiative",
    "wof:placetype":"venue"
},
  "geometry": {"coordinates":[8.0458946228,47.3840141296],"type":"Point"}
}