{
  "type": "Feature",
  "properties": {
    "iso:country":"CH",
    "sg:address":"3754",
    "sg:city":"Diemtigen",
    "sg:orig_category":"Elektrizit\u00e4tsversorgung",
    "sg:postcode":"3754",
    "sg:province":"Bern",
    "wof:name":"Elektrizit\u00e4tsgenossenschaft Zwischenfl\u00fch U. Umgebung Diemtigtal",
    "wof:placetype":"venue"
},
  "geometry": {"coordinates":[7.5575098991,46.6429710388],"type":"Point"}
}