{
  "type": "Feature",
  "properties": {
    "iso:country":"CH",
    "sg:address":"Landstrasse 23",
    "sg:city":"Rafz",
    "sg:orig_category":"Maler U Glasergewerbe",
    "sg:phone":"+41 56 225 22 40",
    "sg:postcode":"8197",
    "sg:province":"Z\u00fcrich",
    "wof:name":"Meier Henri, Malergesch\u00e4ft",
    "wof:placetype":"venue"
},
  "geometry": {"coordinates":[8.2447719574,47.4617195129],"type":"Point"}
}