{
  "type": "Feature",
  "properties": {
    "iso:country":"CH",
    "sg:address":"Schuppisweg 8",
    "sg:city":"Frauenfeld",
    "sg:orig_category":"Detailhandel mit Brot, Back U S\u00fcsswaren",
    "sg:phone":"+41 52 721 10 16",
    "sg:postcode":"8500",
    "sg:province":"Thurgau",
    "wof:name":"Max Tobler Confiserie",
    "wof:placetype":"venue"
},
  "geometry": {"coordinates":[8.902666,47.550461],"type":"Point"}
}