{
  "type": "Feature",
  "properties": {
    "iso:country":"CH",
    "sg:address":"Point-du-jour Chemin Du 14 1012 Lausanne. Postfach",
    "sg:city":"Lausanne",
    "sg:orig_category":"Sonstige mit der Informatik verbundene T\u00e4tigkeiten",
    "sg:postcode":"1003",
    "sg:province":"Vaud",
    "wof:name":"Cavin Blaise Services, Comm D Le Dom De L'informatique",
    "wof:placetype":"venue"
},
  "geometry": {"coordinates":[6.6587171555,46.5328063965],"type":"Point"}
}