{
  "type": "Feature",
  "properties": {
    "iso:country":"CH",
    "sg:address":"Schaffhauserstrasse 127",
    "sg:city":"Kloten",
    "sg:orig_category":"Physiotherapie",
    "sg:phone":"+41 18142828",
    "sg:postcode":"8302",
    "sg:province":"Z\u00fcrich",
    "wof:name":"Andreas Caviezel Physiotherapie",
    "wof:placetype":"venue"
},
  "geometry": {"coordinates":[8.580909729,47.4512252808],"type":"Point"}
}