{
  "type": "Feature",
  "properties": {
    "iso:country":"CH",
    "sg:address":"Bleichenbergstrasse 2",
    "sg:city":"Biberist",
    "sg:orig_category":"Zahntechnische Laboratorien",
    "sg:phone":"+41 32 672 24 42",
    "sg:postcode":"4562",
    "sg:province":"Solothurn",
    "wof:name":"Mario Tschanz Zahntechnisches Labor",
    "wof:placetype":"venue"
},
  "geometry": {"coordinates":[7.5643000603,47.1876602173],"type":"Point"}
}