{
  "type": "Feature",
  "properties": {
    "iso:country":"CH",
    "sg:address":"Hauptstrasse 24",
    "sg:city":"Sch\u00f6nenbaumgarten",
    "sg:orig_category":"Festh\u00fctten- and Zeltvermietung",
    "sg:phone":"+41 71 695 14 47",
    "sg:postcode":"8585",
    "sg:province":"Thurgau",
    "wof:name":"Walter Spengler Ihr Festpartner",
    "wof:placetype":"venue"
},
  "geometry": {"coordinates":[9.2315530777,47.6137733459],"type":"Point"}
}