{
  "type": "Feature",
  "properties": {
    "iso:country":"CH",
    "sg:address":"Birkenstrasse",
    "sg:city":"Rotkreuz",
    "sg:orig_category":"Herstellung von elektrischen Lampen U Leuchten",
    "sg:phone":"+41 41 767 24 24",
    "sg:postcode":"6343",
    "sg:province":"Zug",
    "wof:name":"O.g.e Ott General Engineering Ag",
    "wof:placetype":"venue"
},
  "geometry": {"coordinates":[8.435549736,47.1470756531],"type":"Point"}
}