{
  "type": "Feature",
  "properties": {
    "iso:country":"CH",
    "sg:address":"Simon-gfellerstrasse 2b 3400 Burgdorf. Postfach",
    "sg:city":"Burgdorf",
    "sg:orig_category":"Vermietung U Verpachtung von eigenen Immobilien",
    "sg:phone":"+41 34 422 15 71",
    "sg:postcode":"3400",
    "sg:province":"Bern",
    "wof:name":"B. Sommer Ag",
    "wof:placetype":"venue"
},
  "geometry": {"coordinates":[7.6238079071,47.0511856079],"type":"Point"}
}