{
  "type": "Feature",
  "properties": {
    "iso:country":"CH",
    "sg:address":"Hegibachstrasse 34",
    "sg:city":"Z\u00fcrich",
    "sg:orig_category":"Public-Relations-Agenturen Werbeagenturen",
    "sg:postcode":"8032",
    "sg:province":"Z\u00fcrich",
    "wof:name":"Rainbow Communications Gmbh",
    "wof:placetype":"venue"
},
  "geometry": {"coordinates":[8.562833786,47.3627204895],"type":"Point"}
}