{
  "type": "Feature",
  "properties": {
    "iso:country":"CH",
    "sg:address":"Chaletweg 12",
    "sg:city":"Dietlikon",
    "sg:orig_category":"Ger\u00fcstbau Vermietung von Baumaschinen U ger\u00e4ten",
    "sg:phone":"+41 18333043",
    "sg:postcode":"8305",
    "sg:province":"Z\u00fcrich",
    "wof:name":"Josef Deuerer Ger\u00fcstbau",
    "wof:placetype":"venue"
},
  "geometry": {"coordinates":[8.6206140518,47.4229278564],"type":"Point"}
}