{
  "type": "Feature",
  "properties": {
    "iso:country":"CH",
    "sg:address":"Spitalstrasse",
    "sg:city":"Brig",
    "sg:orig_category":"Reinigungsgewerbe",
    "sg:phone":"+41 27 923 15 89",
    "sg:postcode":"3900",
    "sg:province":"Valais",
    "wof:name":"Tankunterhalt Ag Brig-glis",
    "wof:placetype":"venue"
},
  "geometry": {"coordinates":[7.9838271141,46.3188171387],"type":"Point"}
}