{
  "type": "Feature",
  "properties": {
    "iso:country":"CH",
    "sg:address":"Grimselstrasse",
    "sg:city":"Innertkirchen",
    "sg:orig_category":"Allgemeiner Hoch U Tiefbau",
    "sg:phone":"+41 33 971 62 62",
    "sg:postcode":"3862",
    "sg:province":"Bern",
    "wof:name":"H.u. Ingold, Planungen Und Bauleitungen Gmbh",
    "wof:placetype":"venue"
},
  "geometry": {"coordinates":[8.232105,46.701439],"type":"Point"}
}