{
  "type": "Feature",
  "properties": {
    "iso:country":"CH",
    "sg:address":"R\u00fctistrasse 80 8134 Adliswil. Postfach 47",
    "sg:city":"Adliswil",
    "sg:orig_category":"Maler U Glasergewerbe",
    "sg:phone":"+41 17108871",
    "sg:postcode":"8134",
    "sg:province":"Z\u00fcrich",
    "wof:name":"Metzler & Hediger",
    "wof:placetype":"venue"
},
  "geometry": {"coordinates":[8.531539917,47.3069038391],"type":"Point"}
}