{
  "type": "Feature",
  "properties": {
    "iso:country":"CH",
    "sg:address":"Schaffhauserstrasse 73",
    "sg:city":"Seuzach",
    "sg:orig_category":"Einzelhandel mit Automobilteilen U Zubeh\u00f6r Herstellung von Teilen U Zubeh\u00f6r f\u00fcr Automobile",
    "sg:phone":"+41 52 335 14 47",
    "sg:postcode":"8472",
    "sg:province":"Z\u00fcrich",
    "wof:name":"Meteor-motors Ag Us-car Shop",
    "wof:placetype":"venue"
},
  "geometry": {"coordinates":[8.7155752182,47.5233535767],"type":"Point"}
}