{
  "type": "Feature",
  "properties": {
    "iso:country":"CH",
    "sg:address":"Wasserfurrenstrasse 7 8600 D\u00fcbendorf. Postfach 131",
    "sg:city":"D\u00fcbendorf",
    "sg:orig_category":"Hochschulen U h\u00f6here Ausbildung",
    "sg:phone":"+41 18018484",
    "sg:postcode":"8600",
    "sg:province":"Z\u00fcrich",
    "wof:name":"Stiftung Weiterbildungskurse D\u00dcbendorf",
    "wof:placetype":"venue"
},
  "geometry": {"coordinates":[8.6082057953,47.3940429688],"type":"Point"}
}