{
  "type": "Feature",
  "properties": {
    "iso:country":"CH",
    "sg:address":"6713 Malvaglia. Postfach",
    "sg:city":"Malvaglia",
    "sg:orig_category":"Sanit\u00e4r, Heizungs U L\u00fcftungsinstallation",
    "sg:phone":"+41 91 870 22 03",
    "sg:postcode":"6713",
    "sg:province":"Ticino",
    "wof:name":"Baggi Adriano Sagl Impianti Sanitari, Idraulici Ecc.; Fornitura, Esecuzione, Posa",
    "wof:placetype":"venue"
},
  "geometry": {"coordinates":[8.9809846878,46.4114151001],"type":"Point"}
}