{
  "type": "Feature",
  "properties": {
    "iso:country":"CH",
    "sg:address":"Eyr\u00fctti 25",
    "sg:city":"Schattdorf",
    "sg:orig_category":"Sportvereine Turnen Vereine Damen",
    "sg:postcode":"6467",
    "sg:province":"Uri",
    "wof:name":"Damenriege Stv Altdorf",
    "wof:placetype":"venue"
},
  "geometry": {"coordinates":[8.6458377838,46.8655395508],"type":"Point"}
}