{
  "type": "Feature",
  "properties": {
    "iso:country":"CH",
    "sg:address":"Grienweg 8 B 3600 Thun. Postfach",
    "sg:city":"Thun",
    "sg:orig_category":"Unternehmensberatung",
    "sg:postcode":"3601",
    "sg:province":"Bern",
    "wof:name":"Exemplic Gmbh",
    "wof:placetype":"venue"
},
  "geometry": {"coordinates":[7.6196780205,46.7506103516],"type":"Point"}
}