{
  "type": "Feature",
  "properties": {
    "iso:country":"CH",
    "sg:address":"Br\u00fcckenstrasse 5",
    "sg:city":"Bern",
    "sg:orig_category":"Datenverarbeitungsdienste",
    "sg:phone":"+41 31 311 66 31",
    "sg:postcode":"3005",
    "sg:province":"Bern",
    "wof:name":"Peter Lucas Informatik",
    "wof:placetype":"venue"
},
  "geometry": {"coordinates":[7.444338,46.944592],"type":"Point"}
}