{
  "type": "Feature",
  "properties": {
    "iso:country":"CH",
    "sg:address":"Chemin De Combes 1",
    "sg:city":"Pully",
    "sg:orig_category":"Konsulate",
    "sg:phone":"+41 21 728 91 22",
    "sg:postcode":"1009",
    "sg:province":"Vaud",
    "wof:name":"Consulat Du Luxembourg",
    "wof:placetype":"venue"
},
  "geometry": {"coordinates":[6.6507611275,46.5121002197],"type":"Point"}
}