{
  "type": "Feature",
  "properties": {
    "iso:country":"CH",
    "sg:address":"Kirchgasse 31",
    "sg:city":"Z\u00fcrich",
    "sg:orig_category":"Detailhandel mit Antiquit\u00e4ten Kunsthandel",
    "sg:phone":"+41 12612862",
    "sg:postcode":"8001",
    "sg:province":"Z\u00fcrich",
    "wof:name":"Galerie Fortuna, Sz\u00e9ch\u00e9nyi Margrit Galerie F\u00fcr Alte Kunst",
    "wof:placetype":"venue"
},
  "geometry": {"coordinates":[8.546146,47.370735],"type":"Point"}
}