{
  "type": "Feature",
  "properties": {
    "iso:country":"CH",
    "sg:address":"1437",
    "sg:city":"Susc\u00e9vaz",
    "sg:orig_category":"Vermietung U Verpachtung von eigenen Immobilien",
    "sg:postcode":"1437",
    "sg:province":"Vaud",
    "wof:name":"Kofin Ag",
    "wof:placetype":"venue"
},
  "geometry": {"coordinates":[8.6303491592,46.8894424438],"type":"Point"}
}