{
  "type": "Feature",
  "properties": {
    "iso:country":"CH",
    "sg:address":"Boulevard James-fazy 33",
    "sg:city":"Genf",
    "sg:orig_category":"Kinos",
    "sg:postcode":"1200",
    "sg:province":"Gen\u00e8ve",
    "wof:name":"Europlex Cinemas S\u00e0rl, Succursale De Gen\u00e8ve",
    "wof:placetype":"venue"
},
  "geometry": {"coordinates":[6.1421098709,46.209438324],"type":"Point"}
}