{
  "type": "Feature",
  "properties": {
    "iso:country":"CH",
    "sg:address":"Aarestrasse 20",
    "sg:city":"Turgi",
    "sg:orig_category":"Reiseb\u00fcros U Reiseveranstalter",
    "sg:phone":"+41 56 223 43 39",
    "sg:postcode":"5300",
    "sg:province":"Aargau",
    "wof:name":"Jolly Busreisen Gmbh",
    "wof:placetype":"venue"
},
  "geometry": {"coordinates":[8.2528953552,47.4935798645],"type":"Point"}
}