{
  "type": "Feature",
  "properties": {
    "iso:country":"CH",
    "sg:address":"Blumenweg 8 6003 Luzern. Postfach",
    "sg:city":"Luzern",
    "sg:orig_category":"Kauf U Verkauf von Immobilien auf eigene Rechnung Verwaltung von Immobilien",
    "sg:phone":"+41 41 210 99 77",
    "sg:postcode":"6002",
    "sg:province":"Luzern",
    "wof:name":"Eckert Immobilien Ag",
    "wof:placetype":"venue"
},
  "geometry": {"coordinates":[8.3060731888,47.0498008728],"type":"Point"}
}