{
  "type": "Feature",
  "properties": {
    "iso:country":"CH",
    "sg:address":"Waldstrasse 16",
    "sg:city":"Schlosswil",
    "sg:orig_category":"Elektroinstallation Herstellung von k\u00e4lte U lufttechnischen Erzeugnissen f\u00fcr gewerbliche Zwecke",
    "sg:phone":"+41 71 277 40 46",
    "sg:postcode":"3082",
    "sg:province":"Bern",
    "wof:name":"Deetz Klimatechnik Ag",
    "wof:placetype":"venue"
},
  "geometry": {"coordinates":[9.3315343857,47.4040527344],"type":"Point"}
}