{
  "type": "Feature",
  "properties": {
    "iso:country":"CH",
    "sg:address":"Avenue De La Rosiaz 14",
    "sg:city":"Pully",
    "sg:orig_category":"Grosshandel mit Nahrungsmitteln, Getr\u00e4nken U Tabakwaren ohne ausgepr\u00e4gten Schwerpunkt",
    "sg:phone":"+41 21 728 42 08",
    "sg:postcode":"1009",
    "sg:province":"Vaud",
    "wof:name":"Gueissaz M.",
    "wof:placetype":"venue"
},
  "geometry": {"coordinates":[6.6619048119,46.5214042664],"type":"Point"}
}