{
  "type": "Feature",
  "properties": {
    "iso:country":"CH",
    "sg:address":"Grand-rue 51",
    "sg:city":"Bulle",
    "sg:orig_category":"RESTAURANTS: TEA-ROOMS",
    "sg:postcode":"1630",
    "sg:province":"Fribourg",
    "wof:name":"Bepacaf Sa",
    "wof:placetype":"venue"
},
  "geometry": {"coordinates":[7.0578131676,46.6204490662],"type":"Point"}
}