{
  "type": "Feature",
  "properties": {
    "iso:country":"CH",
    "sg:address":"Morgartenstrasse 15",
    "sg:city":"Z\u00fcrich",
    "sg:orig_category":"Fussreflexzonenmassage P\u00e9dicure",
    "sg:phone":"+41 12421162",
    "sg:postcode":"8004",
    "sg:province":"Z\u00fcrich",
    "wof:name":"Helena Schmid",
    "wof:placetype":"venue"
},
  "geometry": {"coordinates":[8.5287952423,47.3712081909],"type":"Point"}
}