{
  "type": "Feature",
  "properties": {
    "iso:country":"CH",
    "sg:address":"Regina Via 65c",
    "sg:city":"Manno",
    "sg:orig_category":"Unclassifiable Establishments",
    "sg:postcode":"6928",
    "sg:province":"Ticino",
    "wof:name":"Carelle Sagl",
    "wof:placetype":"venue"
},
  "geometry": {"coordinates":[8.9187545776,46.0369949341],"type":"Point"}
}