{
  "type": "Feature",
  "properties": {
    "iso:country":"CH",
    "sg:address":"Avenue Adrien-jeandin 33",
    "sg:city":"Th\u00f4nex",
    "sg:orig_category":"Primarschulen Vorschulen, Kinderg\u00e4rten",
    "sg:phone":"+41 22 348 67 30",
    "sg:postcode":"1226",
    "sg:province":"Gen\u00e8ve",
    "wof:name":"Bilingue Montessori",
    "wof:placetype":"venue"
},
  "geometry": {"coordinates":[6.2009940147,46.18983078],"type":"Point"}
}