{
  "type": "Feature",
  "properties": {
    "iso:country":"CH",
    "sg:address":"Ponte Piazza 9",
    "sg:city":"Mendrisio",
    "sg:orig_category":"Wirtschaftspr\u00fcfung, Steuerberatung U Treuhand",
    "sg:phone":"+41 91 640 60 80",
    "sg:postcode":"6850",
    "sg:province":"Ticino",
    "wof:name":"Interfida Revisioni E Consulenze Sa",
    "wof:placetype":"venue"
},
  "geometry": {"coordinates":[8.9880838394,45.870098114],"type":"Point"}
}