{
  "type": "Feature",
  "properties": {
    "iso:country":"CH",
    "sg:address":"Contre Montet 12",
    "sg:city":"Pr\u00eales",
    "sg:orig_category":"Grosshandel mit Baumaterialien Verlegen von Fliesen U Platten",
    "sg:phone":"+41 32 315 28 93",
    "sg:postcode":"2515",
    "sg:province":"Bern",
    "wof:name":"B E M A C A S\u00e0rl Entreprise De Carrelage",
    "wof:placetype":"venue"
},
  "geometry": {"coordinates":[7.1328339577,47.1000289917],"type":"Point"}
}