{
  "type": "Feature",
  "properties": {
    "iso:country":"CH",
    "sg:address":"Hauptstrasse 20 4416 Bubendorf. Postfach",
    "sg:city":"Bubendorf",
    "sg:orig_category":"Herstellung von Werkzeugmaschinen Mechanische Werkst\u00e4tten",
    "sg:phone":"+41 61 931 23 21",
    "sg:postcode":"4416",
    "sg:province":"Basel-Landschaft",
    "wof:name":"Schweisstechnik Wolewinski Gmbh",
    "wof:placetype":"venue"
},
  "geometry": {"coordinates":[7.7378997803,47.4542160034],"type":"Point"}
}