{
  "type": "Feature",
  "properties": {
    "iso:country":"CH",
    "sg:address":"Lerchenfeldstrasse 20",
    "sg:city":"Meggen",
    "sg:orig_category":"Innendekorationsateliers",
    "sg:phone":"+41 41 377 01 77",
    "sg:postcode":"6045",
    "sg:province":"Luzern",
    "wof:name":"Pius L\u00f6ffel Innendekoration",
    "wof:placetype":"venue"
},
  "geometry": {"coordinates":[8.3625440598,47.0426216125],"type":"Point"}
}