{
  "type": "Feature",
  "properties": {
    "iso:country":"CH",
    "sg:address":"Hofgasse 1",
    "sg:city":"Arlesheim",
    "sg:orig_category":"RESTAURANTS: TEA-ROOMS",
    "sg:phone":"+41 61 701 90 98",
    "sg:postcode":"4144",
    "sg:province":"Basel-Landschaft",
    "wof:name":"Caf\u00e9 Domenig",
    "wof:placetype":"venue"
},
  "geometry": {"coordinates":[7.6213669777,47.4942169189],"type":"Point"}
}