{
  "type": "Feature",
  "properties": {
    "iso:country":"CH",
    "sg:address":"Via Vignalunga 7",
    "sg:city":"Mendrisio",
    "sg:orig_category":"Grosshandel mit Holz U Baustoffen",
    "sg:phone":"+41 91 646 24 10",
    "sg:postcode":"6850",
    "sg:province":"Ticino",
    "wof:name":"Zago & Co Sa",
    "wof:placetype":"venue"
},
  "geometry": {"coordinates":[8.9835777283,45.8778381348],"type":"Point"}
}