{
  "type": "Feature",
  "properties": {
    "iso:country":"CH",
    "sg:address":"Buckstrasse 17",
    "sg:city":"Endingen",
    "sg:orig_category":"Fachdetailhandel in Verkaufsr\u00e4umen",
    "sg:phone":"+41 56 242 16 44",
    "sg:postcode":"5304",
    "sg:province":"Aargau",
    "wof:name":"Atelier Gassmann Barbara",
    "wof:placetype":"venue"
},
  "geometry": {"coordinates":[8.2943029404,47.5362968445],"type":"Point"}
}