{
  "type": "Feature",
  "properties": {
    "iso:country":"CH",
    "sg:address":"Industriestrasse",
    "sg:city":"Sarnen",
    "sg:orig_category":"Erschliessung von Grundst\u00fccken",
    "sg:postcode":"6060",
    "sg:province":"Obwalden",
    "wof:name":"Wohnbau Ag Sarnen",
    "wof:placetype":"venue"
},
  "geometry": {"coordinates":[8.2517948151,46.9028129578],"type":"Point"}
}