{
  "type": "Feature",
  "properties": {
    "iso:country":"CH",
    "sg:address":"Chemin Des Semailles 47",
    "sg:city":"Grand-lancy",
    "sg:orig_category":"Malerei Stukkateurgewerbe, Gipserei U Verputzerei",
    "sg:phone":"+41 22 794 88 63",
    "sg:postcode":"1212",
    "sg:province":"Gen\u00e8ve",
    "wof:name":"Jean Meregnani Gypserie & Peinture",
    "wof:placetype":"venue"
},
  "geometry": {"coordinates":[6.1177401543,46.1745033264],"type":"Point"}
}