{
  "type": "Feature",
  "properties": {
    "iso:country":"CH",
    "sg:address":"Eichstrasse 45",
    "sg:city":"Cham",
    "sg:orig_category":"Non-Classified Establishments",
    "sg:postcode":"6330",
    "sg:province":"Zug",
    "wof:name":"Fahrschule Enes Sadikovic",
    "wof:placetype":"venue"
},
  "geometry": {"coordinates":[8.4724349976,47.1850662231],"type":"Point"}
}