{
  "type": "Feature",
  "properties": {
    "iso:country":"CH",
    "sg:address":"Posat",
    "sg:city":"Posat",
    "sg:orig_category":"Verwertung von Milch",
    "sg:postcode":"1726",
    "sg:province":"Fribourg",
    "wof:name":"Soci\u00e9t\u00e9 De Laiterie De Posat",
    "wof:placetype":"venue"
},
  "geometry": {"coordinates":[7.0652561188,46.7214279175],"type":"Point"}
}