{
  "type": "Feature",
  "properties": {
    "iso:country":"CH",
    "sg:address":"Spalenring 111 4055 Basel. Postfach",
    "sg:city":"Basel",
    "sg:orig_category":"Reiseb\u00fcros U Reiseveranstalter",
    "sg:phone":"+41 61 205 94 94",
    "sg:postcode":"4009",
    "sg:province":"Basel-Stadt",
    "wof:name":"Reiseb\u00fcro Glur Skandinavienspezialist, Generalagent F\u00fcr Hurtigruten",
    "wof:placetype":"venue"
},
  "geometry": {"coordinates":[7.5755739212,47.5564193726],"type":"Point"}
}