{
  "type": "Feature",
  "properties": {
    "iso:country":"CH",
    "sg:address":"Bungertweg 4",
    "sg:city":"Niederhasli",
    "sg:orig_category":"Herstellung von Metallkonstruktionen",
    "sg:phone":"+41 19322231",
    "sg:postcode":"8155",
    "sg:province":"Z\u00fcrich",
    "wof:name":"Weber Ernst Ag Produkte D. Metall, Eisen, Maschinenbaus Usw.; Herst., Montage, Handel",
    "wof:placetype":"venue"
},
  "geometry": {"coordinates":[8.7912931442,47.3194694519],"type":"Point"}
}