{
  "type": "Feature",
  "properties": {
    "iso:country":"CH",
    "sg:address":"Rue De L'etraz",
    "sg:city":"F\u00e9chy",
    "sg:orig_category":"Handels-H\u00e4user U Gesellschaften",
    "sg:postcode":"1173",
    "sg:province":"Vaud",
    "wof:name":"Jadon Ltd Londres, Succursale De F\u00e9chy",
    "wof:placetype":"venue"
},
  "geometry": {"coordinates":[6.378592968,46.4806556702],"type":"Point"}
}