{
  "type": "Feature",
  "properties": {
    "iso:country":"CH",
    "sg:address":"Florastrasse 13 8800 Thalwil. Postfach 1167",
    "sg:city":"Thalwil",
    "sg:orig_category":"Bau U Wohngenossenschaften",
    "sg:phone":"+41 17231330",
    "sg:postcode":"8800",
    "sg:province":"Z\u00fcrich",
    "wof:name":"Genossenschaft Wiesenstrasse C/o Spreag Beratungen",
    "wof:placetype":"venue"
},
  "geometry": {"coordinates":[8.561346,47.297394],"type":"Point"}
}