{
  "type": "Feature",
  "properties": {
    "iso:country":"CH",
    "sg:address":"Rue De Gruy\u00e8res 33",
    "sg:city":"Bulle",
    "sg:orig_category":"RESTAURANTS: TEA-ROOMS",
    "sg:postcode":"1630",
    "sg:province":"Fribourg",
    "wof:name":"Osteria Chez Angelo, A. Et R. Martellotta",
    "wof:placetype":"venue"
},
  "geometry": {"coordinates":[7.0574378967,46.6159210205],"type":"Point"}
}