{
  "type": "Feature",
  "properties": {
    "addr:full":"Sch\u00f6nauweg 10 Bern Bern 3007",
    "addr:housenumber":"10",
    "addr:postcode":"3007",
    "addr:street":"Schoenauweg;Bern",
    "iso:country":"CH",
    "sg:address":"Sch\u00f6nauweg 10",
    "sg:city":"Bern",
    "sg:orig_category":"Aktivit\u00e4ten der Generalunternehmen im Baugewerbe Architekturb\u00fcros",
    "sg:phone":"+41 31 371 04 57",
    "sg:postcode":"3007",
    "sg:province":"Bern",
    "wof:name":"Walter Liechti Architektur & Generaluntern.",
    "wof:placetype":"venue"
},
  "geometry": {"coordinates":[7.443629,46.933926],"type":"Point"}
}