{
  "type": "Feature",
  "properties": {
    "iso:country":"CH",
    "sg:address":"Dorfstrasse 87",
    "sg:city":"Geroldswil",
    "sg:orig_category":"Sportvereine",
    "sg:phone":"+41 19503243",
    "sg:postcode":"8954",
    "sg:province":"Z\u00fcrich",
    "wof:name":"Sc Glatt-& Limmattal",
    "wof:placetype":"venue"
},
  "geometry": {"coordinates":[8.7769393921,47.3728294373],"type":"Point"}
}