{
  "type": "Feature",
  "properties": {
    "iso:country":"CH",
    "sg:address":"Champ-pamont Chemin De 39",
    "sg:city":"Cheseaux-lausanne",
    "sg:orig_category":"Sonstige mit der Informatik verbundene T\u00e4tigkeiten",
    "sg:phone":"+41 21 731 38 43",
    "sg:postcode":"1033",
    "sg:province":"Vaud",
    "wof:name":"Save System, Novatti Luis",
    "wof:placetype":"venue"
},
  "geometry": {"coordinates":[6.6048598289,46.5855407715],"type":"Point"}
}