{
  "type": "Feature",
  "properties": {
    "addr:full":"Rainstrasse 35 Unter\u00e4geri Zug 6314",
    "addr:housenumber":"35",
    "addr:postcode":"6314",
    "addr:street":"Rainstrasse;Zug",
    "iso:country":"CH",
    "sg:address":"Rainstrasse 35",
    "sg:city":"Unter\u00e4geri",
    "sg:classifiers":[
        {
            "category":"Industrial Area",
            "type":"Public Place"
        }
    ],
    "sg:phone":"+41 43 317 71 11",
    "sg:postcode":"6314",
    "sg:province":"Zug",
    "sg:tags":[
        "large",
        "private"
    ],
    "wof:name":"Abb Ltd.",
    "wof:placetype":"venue"
},
  "geometry": {"coordinates":[8.541409,47.411251],"type":"Point"}
}