{
  "type": "Feature",
  "properties": {
    "iso:country":"CH",
    "sg:address":"Agustoni Via Degli 1",
    "sg:city":"Chiasso",
    "sg:orig_category":"Non-Classified Establishments",
    "sg:phone":"+41 91 682 43 71",
    "sg:postcode":"6830",
    "sg:province":"Ticino",
    "wof:name":"Tevrax Sa",
    "wof:placetype":"venue"
},
  "geometry": {"coordinates":[9.0347957611,45.8330116272],"type":"Point"}
}