{
  "type": "Feature",
  "properties": {
    "iso:country":"CH",
    "sg:address":"Chemin Des Crues 6",
    "sg:city":"Perly",
    "sg:orig_category":"R\u00fcckgewinnung U Vorbereitung f\u00fcr die Wiederverwertung Recycling von Schrott",
    "sg:phone":"+41 22 771 16 00",
    "sg:postcode":"1258",
    "sg:province":"Gen\u00e8ve",
    "wof:name":"Stoll & Cie Tarbouriech Jean-pierre Succ.",
    "wof:placetype":"venue"
},
  "geometry": {"coordinates":[6.0993151665,46.1625442505],"type":"Point"}
}