{
  "type": "Feature",
  "properties": {
    "iso:country":"CH",
    "sg:address":"Rorschacher Strasse 1",
    "sg:city":"St.gallen",
    "sg:orig_category":"Unclassifiable Establishments",
    "sg:postcode":"9000",
    "sg:province":"St. Gallen",
    "wof:name":"Engelbert Stieger E. Ag",
    "wof:placetype":"venue"
},
  "geometry": {"coordinates":[9.3785400391,47.4264144897],"type":"Point"}
}