{
  "type": "Feature",
  "properties": {
    "iso:country":"CH",
    "sg:address":"Lachenstrasse 14",
    "sg:city":"Allschwil",
    "sg:orig_category":"Grosshandel mit sonstigen Halbwaren Herstellung von Wellpapier U pappe sowie von Verpackungsmitteln ",
    "sg:phone":"+41 71 313 41 41",
    "sg:postcode":"4123",
    "sg:province":"Basel-Landschaft",
    "wof:name":"Hohl + Co Ag Papier, Karton, Kunststoff; Verarbeitung. Flexo-druckerei, Packmaterial-grosshandel",
    "wof:placetype":"venue"
},
  "geometry": {"coordinates":[9.3096923828,47.4154930115],"type":"Point"}
}