{
  "type": "Feature",
  "properties": {
    "iso:country":"CH",
    "sg:address":"6776",
    "sg:city":"Piotta",
    "sg:orig_category":"Herstellung von Metallerzeugnissen ohne Maschinenbau Maschinenbau",
    "sg:phone":"+41 91 873 66 11",
    "sg:postcode":"6776",
    "sg:province":"Ticino",
    "wof:name":"Tensol Rail Sa",
    "wof:placetype":"venue"
},
  "geometry": {"coordinates":[8.6774301529,46.5127983093],"type":"Point"}
}