{
  "type": "Feature",
  "properties": {
    "iso:country":"CH",
    "sg:address":"Maison De Ville",
    "sg:city":"Montagny-les-monts",
    "sg:orig_category":"Interessenvertretungen",
    "sg:postcode":"1774",
    "sg:province":"Fribourg",
    "wof:name":"Fondation G\u00e9n\u00e9ral Nicolas De Gady Pour La Sauvegarde De La Tour De Montagny",
    "wof:placetype":"venue"
},
  "geometry": {"coordinates":[6.9772849083,46.8183364868],"type":"Point"}
}