{
  "type": "Feature",
  "properties": {
    "iso:country":"CH",
    "sg:address":"Les Pontis",
    "sg:city":"Sierre",
    "sg:classifiers":[
        {
            "category":"Restaurant",
            "type":"Food & Drink"
        }
    ],
    "sg:phone":"+41 21 784 11 31",
    "sg:postcode":"3960",
    "sg:province":"Valais",
    "wof:name":"Caf\u00e9 Populaire",
    "wof:placetype":"venue"
},
  "geometry": {"coordinates":[6.6945109367,46.5544090271],"type":"Point"}
}