{
  "type": "Feature",
  "properties": {
    "iso:country":"CH",
    "sg:address":"Klosterhof 1",
    "sg:city":"Engelberg",
    "sg:orig_category":"Arztpraxen",
    "sg:phone":"+41 41 637 40 60",
    "sg:postcode":"6390",
    "sg:province":"Obwalden",
    "wof:name":"Dr.med.peter Beutler Arzt F.allgemeine Medizin Fmh",
    "wof:placetype":"venue"
},
  "geometry": {"coordinates":[8.408155,46.819771],"type":"Point"}
}