{
  "type": "Feature",
  "properties": {
    "iso:country":"CH",
    "sg:address":"Rainweg 12",
    "sg:city":"Bannwil",
    "sg:orig_category":"Handelsvermittlung U Grosshandel Sonstige Finanzierungsinstitutionen",
    "sg:phone":"+41 71 622 37 72",
    "sg:postcode":"4913",
    "sg:province":"Bern",
    "wof:name":"Ae Import-export Investment Ag",
    "wof:placetype":"venue"
},
  "geometry": {"coordinates":[9.1381845474,47.5666694641],"type":"Point"}
}