{
  "type": "Feature",
  "properties": {
    "iso:country":"CH",
    "sg:address":"Via Della Salina 3",
    "sg:city":"Muralto",
    "sg:orig_category":"Zahnarztpraxen",
    "sg:phone":"+41 91 743 54 33",
    "sg:postcode":"6600",
    "sg:province":"Ticino",
    "wof:name":"Dott.med.dent.robert D. Philps Dentista",
    "wof:placetype":"venue"
},
  "geometry": {"coordinates":[8.8013048172,46.1715354919],"type":"Point"}
}