{
  "type": "Feature",
  "properties": {
    "iso:country":"CH",
    "sg:address":"Oberwiesenstrasse 5 8057 Z\u00fcrich. Postfach",
    "sg:city":"Z\u00fcrich",
    "sg:orig_category":"Fussboden, Fliesen U Plattenlegerei, Tapeziererei",
    "sg:phone":"+41 13626688",
    "sg:postcode":"8057",
    "sg:province":"Z\u00fcrich",
    "wof:name":"A. Suter Ag",
    "wof:placetype":"venue"
},
  "geometry": {"coordinates":[8.5310344696,47.4079551697],"type":"Point"}
}