{
  "type": "Feature",
  "properties": {
    "iso:country":"CH",
    "sg:address":"Heusserstrasse 9 8634 Hombrechtikon. Postfach",
    "sg:city":"Hombrechtikon",
    "sg:orig_category":"Grosshandel mit Holz U Baustoffen",
    "sg:phone":"+41 55 244 56 76",
    "sg:postcode":"8634",
    "sg:province":"Z\u00fcrich",
    "wof:name":"Maga De Conti Mario Baumaterialien; Handel. Maurer- U. Plattenlegerarbeiten. Chemin\u00e9ebau.",
    "wof:placetype":"venue"
},
  "geometry": {"coordinates":[8.7740621567,47.2541656494],"type":"Point"}
}