{
  "type": "Feature",
  "properties": {
    "addr:full":"Stockerstrasse 35 Horgen Z\u00fcrich 8810",
    "addr:housenumber":"35",
    "addr:postcode":"8810",
    "addr:street":"Stockerstrasse",
    "iso:country":"CH",
    "sg:address":"Stockerstrasse 35",
    "sg:city":"Horgen",
    "sg:orig_category":"Arztpraxen",
    "sg:phone":"+41 17254848",
    "sg:postcode":"8810",
    "sg:province":"Z\u00fcrich",
    "wof:name":"Dr.med.werner Hausheer Arzt F.allgemeine Medizin Fmh",
    "wof:placetype":"venue"
},
  "geometry": {"coordinates":[8.591541,47.26086],"type":"Point"}
}