{
  "type": "Feature",
  "properties": {
    "iso:country":"CH",
    "sg:address":"Dixence Rue De La 46",
    "sg:city":"Sion",
    "sg:orig_category":"RESTAURANTS: TEA-ROOMS",
    "sg:phone":"+41 52 375 11 41",
    "sg:postcode":"1950",
    "sg:province":"Valais",
    "wof:name":"Paul Bernath Gastronomie Ag",
    "wof:placetype":"venue"
},
  "geometry": {"coordinates":[8.8238649368,47.5625343323],"type":"Point"}
}