{
  "type": "Feature",
  "properties": {
    "iso:country":"CH",
    "sg:address":"Salinenstrasse 3",
    "sg:city":"Birsfelden",
    "sg:orig_category":"Sanit\u00e4r U Heizungsinstallation Sanit\u00e4r, Heizungs U L\u00fcftungsinstallation",
    "sg:phone":"+41 61 378 85 00",
    "sg:postcode":"4127",
    "sg:province":"Basel-Landschaft",
    "wof:name":"Omlin + Partner",
    "wof:placetype":"venue"
},
  "geometry": {"coordinates":[7.6255130768,47.5477561951],"type":"Point"}
}