{
  "type": "Feature",
  "properties": {
    "iso:country":"CH",
    "sg:address":"Deutsche Strasse 35 7000 Chur. Postfach",
    "sg:city":"Chur",
    "sg:classifiers":[
        {
            "category":"Restaurant",
            "type":"Food & Drink"
        }
    ],
    "sg:phone":"+41 62 893 04 44",
    "sg:postcode":"7005",
    "wof:name":"Restaurant Oliveb\u00e4umli",
    "wof:placetype":"venue"
},
  "geometry": {"coordinates":[8.166973114,47.4291992188],"type":"Point"}
}