{
  "type": "Feature",
  "properties": {
    "iso:country":"CH",
    "sg:address":"H\u00e4rdlistrasse 6",
    "sg:city":"Spreitenbach",
    "sg:orig_category":"Handel mit Automobilen Handelsvermittlung U Grosshandel mit Automobilteilen U Zubeh\u00f6r",
    "sg:phone":"+41 21 801 90 38",
    "sg:postcode":"8957",
    "sg:province":"Aargau",
    "wof:name":"Chauvy Marcel",
    "wof:placetype":"venue"
},
  "geometry": {"coordinates":[6.4920930862,46.5077590942],"type":"Point"}
}