{
  "type": "Feature",
  "properties": {
    "iso:country":"CH",
    "sg:address":"Kanonengasse 19",
    "sg:city":"Liestal",
    "sg:orig_category":"Architekturb\u00fcros",
    "sg:phone":"+41 79 433 65 61",
    "sg:postcode":"4410",
    "sg:province":"Basel-Landschaft",
    "wof:name":"Beyer Ag, Altst\u00e4tten Innenarchitekturarbeiten Usw",
    "wof:placetype":"venue"
},
  "geometry": {"coordinates":[9.539881,47.378765],"type":"Point"}
}