{
  "type": "Feature",
  "properties": {
    "iso:country":"CH",
    "sg:address":"Chemin Des Grandes Vies 25",
    "sg:city":"Porrentruy",
    "sg:classifiers":[
        {
            "category":"Social Services",
            "subcategory":"Job Training",
            "type":"Services"
        }
    ],
    "sg:phone":"+41 32 968 59 55",
    "sg:postcode":"2900",
    "sg:province":"Jura",
    "sg:tags":[
        "metallurgy",
        "metal",
        "processing",
        "-",
        "metalworking",
        "machine",
        "engineering",
        "mechanical"
    ],
    "wof:name":"Surdez Mathey Sa",
    "wof:placetype":"venue"
},
  "geometry": {"coordinates":[6.8233628273,47.1072044373],"type":"Point"}
}