{
  "type": "Feature",
  "properties": {
    "iso:country":"CH",
    "sg:address":"Cr\u00eat De La Fin 28 2024 St-aubin-sauges. Postfach",
    "sg:city":"St-aubin-sauges",
    "sg:orig_category":"Detailhandel mit Metallwaren, Anstrichmitteln, Glaswaren, Bau U Heimwerkerbedarf",
    "sg:phone":"+41 32 835 15 19",
    "sg:postcode":"2024",
    "sg:province":"Neuch\u00e2tel",
    "wof:name":"Rumpf Armin",
    "wof:placetype":"venue"
},
  "geometry": {"coordinates":[6.7786259651,46.8996887207],"type":"Point"}
}