{
  "type": "Feature",
  "properties": {
    "iso:country":"CH",
    "sg:address":"Steinackerstrasse",
    "sg:city":"Leuzigen",
    "sg:orig_category":"Instandhaltung U Reparatur von Automobilen",
    "sg:postcode":"3297",
    "sg:province":"Bern",
    "wof:name":"Gshc Garage Station Humair Claude",
    "wof:placetype":"venue"
},
  "geometry": {"coordinates":[6.9275298119,47.0324363708],"type":"Point"}
}