{
  "type": "Feature",
  "properties": {
    "iso:country":"CH",
    "sg:address":"Avenir Rue De L' 11 1950 Sitten. Postfach",
    "sg:city":"Sitten",
    "sg:orig_category":"Sonstige pers\u00f6nliche Dienstleistungen",
    "sg:phone":"+41 27 322 31 11",
    "sg:postcode":"1950",
    "sg:province":"Valais",
    "wof:name":"Swisstraffic Ag",
    "wof:placetype":"venue"
},
  "geometry": {"coordinates":[1.6175060272,50.2207794189],"type":"Point"}
}