{
  "type": "Feature",
  "properties": {
    "iso:country":"CH",
    "sg:address":"Moosstrasse 2 3073 G\u00fcmligen. Postfach 29",
    "sg:city":"G\u00fcmligen",
    "sg:orig_category":"Internationale Organisationen mit Beh\u00f6rdecharakter",
    "sg:phone":"+41 22 749 01 11",
    "sg:postcode":"3073",
    "sg:province":"Bern",
    "wof:name":"International Organization For Standardization Iso",
    "wof:placetype":"venue"
},
  "geometry": {"coordinates":[6.1395249367,46.22108078],"type":"Point"}
}