{
  "type": "Feature",
  "properties": {
    "iso:country":"CH",
    "sg:address":"Verwaltungsgeb\u00e4ude Z 8423 Embrach-embraport. Postfach 15",
    "sg:city":"Embrach-embraport",
    "sg:orig_category":"Grosshandel mit sonstigen Nahrungsmitteln",
    "sg:phone":"+41 55 442 50 22",
    "sg:postcode":"8423",
    "sg:province":"Z\u00fcrich",
    "wof:name":"Porimex Trading Ag",
    "wof:placetype":"venue"
},
  "geometry": {"coordinates":[8.8529558182,47.1920051575],"type":"Point"}
}