{
  "type": "Feature",
  "properties": {
    "iso:country":"CH",
    "sg:address":"Blumenstrasse 7",
    "sg:city":"Berneck",
    "sg:orig_category":"Non-Classified Establishments",
    "sg:postcode":"9442",
    "sg:province":"St. Gallen",
    "wof:name":"Elektrogesch\u00e4ft W. Meier, Inh. Sergio Botondi",
    "wof:placetype":"venue"
},
  "geometry": {"coordinates":[8.5134067535,47.4717292786],"type":"Point"}
}