{
  "type": "Feature",
  "properties": {
    "iso:country":"CH",
    "sg:address":"F\u00e4llmisstrasse 2a 8832 Wilen B. Wollerau. Postfach",
    "sg:city":"Wollerau",
    "sg:orig_category":"S\u00e4ge, Hobel U Holzimpr\u00e4gnierwerke",
    "sg:postcode":"8832",
    "sg:province":"Schwyz",
    "wof:name":"Swissform (schweiz) Ag",
    "wof:placetype":"venue"
},
  "geometry": {"coordinates":[8.7341480255,47.1973953247],"type":"Point"}
}