{
  "type": "Feature",
  "properties": {
    "iso:country":"CH",
    "sg:address":"Bossi Via Emilio 12d",
    "sg:city":"Chiasso",
    "sg:orig_category":"Wirtschaftspr\u00fcfung, Steuerberatung U Treuhand",
    "sg:postcode":"6830",
    "sg:province":"Ticino",
    "wof:name":"Bozzone Dottor Emanuele, Studio Fiduciario E Commercialista",
    "wof:placetype":"venue"
},
  "geometry": {"coordinates":[9.0314903259,45.8346862793],"type":"Point"}
}