{
  "type": "Feature",
  "properties": {
    "iso:country":"CH",
    "sg:address":"Adolf L\u00fcchinger-strasse 117 8000 Z\u00fcrich. Postfach 8045 Z\u00fcrich",
    "sg:city":"Zust",
    "sg:orig_category":"RESTAURANTS: TEA-ROOMS",
    "sg:postcode":"45",
    "wof:name":"Hofmann's Grill-g\u00fcggeli",
    "wof:placetype":"venue"
},
  "geometry": {"coordinates":[8.5076637268,47.356338501],"type":"Point"}
}