{
  "type": "Feature",
  "properties": {
    "iso:country":"CH",
    "sg:address":"Dachslernstrasse 38",
    "sg:city":"Z\u00fcrich",
    "sg:orig_category":"Unclassifiable Establishments",
    "sg:phone":"+41 14323082",
    "sg:postcode":"8048",
    "sg:province":"Z\u00fcrich",
    "wof:name":"Protectia Ag",
    "wof:placetype":"venue"
},
  "geometry": {"coordinates":[8.4796686172,47.3891181946],"type":"Point"}
}