{
  "type": "Feature",
  "properties": {
    "iso:country":"CH",
    "sg:address":"Chemin Des Esserpis 1",
    "sg:city":"Estavayer-le-lac",
    "sg:classifiers":[
        {
            "category":"Building & Trades",
            "subcategory":"Construction",
            "type":"Services"
        }
    ],
    "sg:phone":"+41 26 663 93 93",
    "sg:postcode":"1470",
    "sg:province":"Fribourg",
    "sg:tags":[
        "front",
        "door"
    ],
    "wof:name":"Gutknecht S.a.",
    "wof:placetype":"venue"
},
  "geometry": {"coordinates":[6.8529381752,46.8456993103],"type":"Point"}
}