{
  "type": "Feature",
  "properties": {
    "iso:country":"CH",
    "sg:address":"Seestrasse 100",
    "sg:city":"Walenstadt",
    "sg:classifiers":[
        {
            "category":"Bars & Pubs",
            "type":"Food & Drink"
        }
    ],
    "sg:phone":"+41 55 442 53 50",
    "sg:postcode":"8880",
    "sg:province":"St. Gallen",
    "wof:name":"Seehus-bar",
    "wof:placetype":"venue"
},
  "geometry": {"coordinates":[8.855349,47.195087],"type":"Point"}
}