{
  "type": "Feature",
  "properties": {
    "iso:country":"CH",
    "sg:address":"Hummelbergstrasse 14",
    "sg:city":"Jona",
    "sg:orig_category":"Non-Classified Establishments",
    "sg:postcode":"8645",
    "sg:province":"St. Gallen",
    "wof:name":"Eugen Z\u00fcger Schreinerei",
    "wof:placetype":"venue"
},
  "geometry": {"coordinates":[8.8535404205,47.2311820984],"type":"Point"}
}