{
  "type": "Feature",
  "properties": {
    "iso:country":"CH",
    "sg:address":"Industriestrasse Haag (rheintal) 9466 Sennwald. Postfach",
    "sg:city":"Sennwald",
    "sg:orig_category":"Mineral\u00f6lverarbeitung",
    "sg:postcode":"9466",
    "sg:province":"St. Gallen",
    "wof:name":"Nutt Josef",
    "wof:placetype":"venue"
},
  "geometry": {"coordinates":[9.5036201477,47.2606582642],"type":"Point"}
}