{
  "type": "Feature",
  "properties": {
    "iso:country":"CH",
    "sg:address":"Vorimholz",
    "sg:city":"Grossaffoltern",
    "sg:orig_category":"Primarschulen",
    "sg:phone":"+41 32 389 18 68",
    "sg:postcode":"3257",
    "sg:province":"Bern",
    "wof:name":"Primarschule",
    "wof:placetype":"venue"
},
  "geometry": {"coordinates":[7.3673601151,47.0706100464],"type":"Point"}
}