{
  "type": "Feature",
  "properties": {
    "iso:country":"CH",
    "sg:address":"Rue De La Croix-d'or 1",
    "sg:city":"Hauterive",
    "sg:classifiers":[
        {
            "category":"Restaurant",
            "type":"Food & Drink"
        }
    ],
    "sg:phone":"+41 32 753 34 01",
    "sg:postcode":"2068",
    "sg:province":"Neuch\u00e2tel",
    "wof:name":"Caf\u00e9 De La Croix-d'or",
    "wof:placetype":"venue"
},
  "geometry": {"coordinates":[2.2755849361,43.6353874207],"type":"Point"}
}