{
  "type": "Feature",
  "properties": {
    "iso:country":"CH",
    "sg:address":"St. Gallerstrasse 18 8500 Frauenfeld. Postfach",
    "sg:city":"Frauenfeld",
    "sg:orig_category":"Kauf U Verkauf von Immobilien auf eigene Rechnung",
    "sg:postcode":"8500",
    "sg:province":"Thurgau",
    "wof:name":"Lady Liegenschaften Ag",
    "wof:placetype":"venue"
},
  "geometry": {"coordinates":[8.8984651566,47.5538444519],"type":"Point"}
}