{
  "type": "Feature",
  "properties": {
    "iso:country":"CH",
    "sg:address":"Landstrasse 19",
    "sg:city":"Glarus",
    "sg:orig_category":"Unclassifiable Establishments",
    "sg:postcode":"8750",
    "sg:province":"Glarus",
    "wof:name":"Corfina Holding Ag",
    "wof:placetype":"venue"
},
  "geometry": {"coordinates":[9.2861280441,46.8375511169],"type":"Point"}
}