{
  "type": "Feature",
  "properties": {
    "iso:country":"CH",
    "sg:address":"Kirchdorfstrasse 39",
    "sg:city":"Kriessern",
    "sg:classifiers":[
        {
            "category":"Restaurant",
            "type":"Food & Drink"
        }
    ],
    "sg:phone":"+41 71 761 12 22",
    "sg:postcode":"9451",
    "sg:province":"St. Gallen",
    "wof:name":"Restaurant Sch\u00e4fle",
    "wof:placetype":"venue"
},
  "geometry": {"coordinates":[9.5467367172,47.3187332153],"type":"Point"}
}