{
  "type": "Feature",
  "properties": {
    "addr:full":"Chemin De Paris 9 Bernex Gen\u00e8ve 1233",
    "addr:housenumber":"9",
    "addr:postcode":"1233",
    "addr:street":"Chemin De Paris",
    "iso:country":"CH",
    "sg:address":"Chemin De Paris 9",
    "sg:city":"Bernex",
    "sg:orig_category":"Arztpraxen",
    "sg:phone":"+41 22 777 07 00",
    "sg:postcode":"1233",
    "sg:province":"Gen\u00e8ve",
    "wof:name":"Dr M\u00e9d. Berdj Papazian M\u00e9decin Sp\u00e9cialiste Fmh",
    "wof:placetype":"venue"
},
  "geometry": {"coordinates":[6.069236,46.176517],"type":"Point"}
}