{
  "type": "Feature",
  "properties": {
    "addr:full":"Neustadt 69 Schaffhausen Schaffhausen 8200",
    "addr:housenumber":"69",
    "addr:postcode":"8200",
    "addr:street":"Neustadt",
    "iso:country":"CH",
    "sg:address":"Neustadt 69",
    "sg:city":"Schaffhausen",
    "sg:orig_category":"Detailhandel mit Antiquit\u00e4ten",
    "sg:phone":"+41 52 624 82 84",
    "sg:postcode":"8200",
    "sg:province":"Schaffhausen",
    "wof:name":"Bernhard Saenz Arana Antiquit\u00e4ten",
    "wof:placetype":"venue"
},
  "geometry": {"coordinates":[8.63213,47.695717],"type":"Point"}
}