{
  "type": "Feature",
  "properties": {
    "addr:full":"Schorenweg 15 Basel Basel-Stadt 4058",
    "addr:housenumber":"15",
    "addr:postcode":"4058",
    "addr:street":"Schorenweg",
    "iso:country":"CH",
    "sg:address":"Schorenweg 15",
    "sg:city":"Basel",
    "sg:orig_category":"Detailhandel mit Bekleidung Fachdetailhandel in Verkaufsr\u00e4umen",
    "sg:phone":"+41 81 933 21 21",
    "sg:postcode":"4058",
    "sg:province":"Basel-Stadt",
    "wof:name":"Cresta Sport Mode Ag",
    "wof:placetype":"venue"
},
  "geometry": {"coordinates":[9.12251,46.756142],"type":"Point"}
}