{
  "type": "Feature",
  "properties": {
    "iso:country":"CH",
    "sg:address":"Lyon Rue De 110 1203 Gen\u00e8ve. Postfach",
    "sg:city":"Gen\u00e8ve",
    "sg:orig_category":"Herstellung von Duft U K\u00f6rperpflegemitteln",
    "sg:phone":"+41 21 923 07 77",
    "sg:postcode":"1201",
    "sg:province":"Gen\u00e8ve",
    "wof:name":"Docteur Herzog Paul Et Karin Sa",
    "wof:placetype":"venue"
},
  "geometry": {"coordinates":[6.8593130112,46.4669837952],"type":"Point"}
}