{
  "type": "Feature",
  "properties": {
    "iso:country":"CH",
    "sg:address":"T\u00e4gerackerstrasse 17 8610 Uster. Postfach",
    "sg:city":"Uster",
    "sg:orig_category":"Architektur U Ingenieurb\u00fcros",
    "sg:postcode":"8610",
    "sg:province":"Z\u00fcrich",
    "wof:name":"Albrecht.aschwanden.gmbh Dienstleistungen Im Bauwesen U. In Der Vermarktung Wie Bebauungstudien, Vorabkl\u00e4rungen, Berechnungen",
    "wof:placetype":"venue"
},
  "geometry": {"coordinates":[8.718987,47.342236],"type":"Point"}
}