{
  "type": "Feature",
  "properties": {
    "iso:country":"CH",
    "sg:address":"Seestr. 189 B\u00e4ch",
    "sg:city":"Freienbach",
    "sg:orig_category":"RESTAURANTS: TEA-ROOMS",
    "sg:postcode":"8807",
    "sg:province":"Schwyz",
    "wof:name":"Bloch-triet Fredi",
    "wof:placetype":"venue"
},
  "geometry": {"coordinates":[8.7577753067,47.2063064575],"type":"Point"}
}