{
  "type": "Feature",
  "properties": {
    "iso:country":"CH",
    "sg:address":"Cinastrasse 4",
    "sg:city":"Salgesch",
    "sg:orig_category":"Selbst\u00e4ndige bildende K\u00fcnstler",
    "sg:phone":"+41 27 973 18 43",
    "sg:postcode":"3970",
    "sg:province":"Valais",
    "wof:name":"Gregor Jerjen Schnitzerei",
    "wof:placetype":"venue"
},
  "geometry": {"coordinates":[8.245880127,46.4678459167],"type":"Point"}
}