{
  "type": "Feature",
  "properties": {
    "iso:country":"CH",
    "sg:address":"Via Galbisio 91",
    "sg:city":"Bellinzona",
    "sg:orig_category":"RESTAURANTS: TEA-ROOMS",
    "sg:phone":"+41 91 825 00 97",
    "sg:postcode":"6503",
    "sg:province":"Ticino",
    "wof:name":"Grotto S. Anna Di Pereira Teixeira Vasco Ristorante",
    "wof:placetype":"venue"
},
  "geometry": {"coordinates":[9.0335836411,46.2149543762],"type":"Point"}
}