{
  "type": "Feature",
  "properties": {
    "iso:country":"CH",
    "sg:address":"B\u00e4chelsr\u00fcti",
    "sg:city":"Gr\u00fcningen",
    "sg:orig_category":"Grosshandel mit lebenden Tieren",
    "sg:phone":"+41 19352771",
    "sg:postcode":"8627",
    "sg:province":"Z\u00fcrich",
    "wof:name":"Titus Zangger Jun. Viehhandel",
    "wof:placetype":"venue"
},
  "geometry": {"coordinates":[8.7429132462,47.2869529724],"type":"Point"}
}