{
  "type": "Feature",
  "properties": {
    "iso:country":"CH",
    "sg:address":"Route Aloys-fauquez 36",
    "sg:city":"Lausanne",
    "sg:orig_category":"Detailhandel mit Brot, Back U S\u00fcsswaren",
    "sg:phone":"+41 79 332 33 40",
    "sg:postcode":"1018",
    "sg:province":"Vaud",
    "wof:name":"Boulangerie-p\u00e2tisserie-confiserie-tea-room Fontana Daniello",
    "wof:placetype":"venue"
},
  "geometry": {"coordinates":[6.633528,46.533154],"type":"Point"}
}