{
  "type": "Feature",
  "properties": {
    "iso:country":"CH",
    "sg:address":"Oberm\u00fclistrasse 79",
    "sg:city":"Fehraltorf",
    "sg:orig_category":"Detailhandel mit Metallwaren, Anstrichmitteln, Glaswaren, Bau U Heimwerkerbedarf Handelsvermittlung ",
    "sg:phone":"+41 19550666",
    "sg:postcode":"8320",
    "sg:province":"Z\u00fcrich",
    "wof:name":"Techno-transfer Sa",
    "wof:placetype":"venue"
},
  "geometry": {"coordinates":[8.7459440231,47.3891983032],"type":"Point"}
}