{
  "type": "Feature",
  "properties": {
    "iso:country":"CH",
    "sg:address":"Le Coll\u00e8ge",
    "sg:city":"St-cierges",
    "sg:orig_category":"Landesverteidigung, Sozialversicherung \u00d6ffentliche Verwaltung",
    "sg:phone":"+41 21 905 30 62",
    "sg:postcode":"1064",
    "wof:name":"Centre De Protection Civile",
    "wof:placetype":"venue"
},
  "geometry": {"coordinates":[6.7349619865,46.6901321411],"type":"Point"}
}