{
  "type": "Feature",
  "properties": {
    "iso:country":"CH",
    "sg:address":"Dorfstrasse 7",
    "sg:city":"Weisslingen",
    "sg:orig_category":"Pensionskassen",
    "sg:phone":"+41 52 396 32 32",
    "sg:postcode":"8484",
    "sg:province":"Z\u00fcrich",
    "wof:name":"Personalstiftung Der Smc-gruppe",
    "wof:placetype":"venue"
},
  "geometry": {"coordinates":[8.7651176453,47.4298324585],"type":"Point"}
}