{
  "type": "Feature",
  "properties": {
    "iso:country":"CH",
    "sg:address":"6514 Sementina. Postfach Caselle Postale 20",
    "sg:city":"Sementina",
    "sg:orig_category":"Vereine Lions",
    "sg:postcode":"6514",
    "sg:province":"Ticino",
    "wof:name":"Lions Club Bellinzona",
    "wof:placetype":"venue"
},
  "geometry": {"coordinates":[8.9902734756,46.1847915649],"type":"Point"}
}