{
  "type": "Feature",
  "properties": {
    "iso:country":"CH",
    "sg:address":"Wartstrasse 3",
    "sg:city":"Winterthur",
    "sg:orig_category":"Interessenvertretungen",
    "sg:postcode":"8400",
    "sg:province":"Z\u00fcrich",
    "wof:name":"Genossenschaft R\u00e4geboge, Biologische Produkte",
    "wof:placetype":"venue"
},
  "geometry": {"coordinates":[8.7224531174,47.5006408691],"type":"Point"}
}