{
  "type": "Feature",
  "properties": {
    "iso:country":"CH",
    "sg:address":"Midi Rue Du 6",
    "sg:city":"Pully",
    "sg:orig_category":"Detailhandel mit Schuhen U Lederwaren",
    "sg:postcode":"1009",
    "sg:province":"Vaud",
    "wof:name":"Promleather Ag",
    "wof:placetype":"venue"
},
  "geometry": {"coordinates":[8.3137350082,46.9894294739],"type":"Point"}
}