{
  "type": "Feature",
  "properties": {
    "iso:country":"CH",
    "sg:address":"2745",
    "sg:city":"Grandval",
    "sg:orig_category":"Gemeindeverwaltungen",
    "sg:phone":"+41 32 499 95 55",
    "sg:postcode":"2745",
    "sg:province":"Bern",
    "wof:name":"Administration Communale De Grandval",
    "wof:placetype":"venue"
},
  "geometry": {"coordinates":[7.4230508804,47.2830162048],"type":"Point"}
}