{
  "type": "Feature",
  "properties": {
    "iso:country":"CH",
    "sg:address":"Schmelzistrasse 53",
    "sg:city":"Erschwil",
    "sg:orig_category":"Architekturb\u00fcros",
    "sg:phone":"+41 61 791 00 43",
    "sg:postcode":"4228",
    "sg:province":"Solothurn",
    "wof:name":"Arch 78 Rolf Bl\u00f6sch Architekturb\u00fcro",
    "wof:placetype":"venue"
},
  "geometry": {"coordinates":[7.541233,47.372437],"type":"Point"}
}