{
  "type": "Feature",
  "properties": {
    "addr:full":"Rue De Gen\u00e8ve 123b 1226 Th\u00f4nex Case Postale 146 Th\u00f4nex Gen\u00e8ve 1226",
    "addr:housenumber":"123b;146",
    "addr:postcode":"1226;1226",
    "addr:street":"Rue De Gene\u0300Ve;Case Postale",
    "iso:country":"CH",
    "sg:address":"Rue De Gen\u00e8ve 123b 1226 Th\u00f4nex Case Postale 146",
    "sg:city":"Th\u00f4nex",
    "sg:orig_category":"Detailhandel mit Brillen U anderen Sehhilfen Fachdetailhandel in Verkaufsr\u00e4umen",
    "sg:phone":"+41 22 348 26 10",
    "sg:postcode":"1226",
    "sg:province":"Gen\u00e8ve",
    "wof:name":"Optique Th\u00f4nex G. Busulini.",
    "wof:placetype":"venue"
},
  "geometry": {"coordinates":[6.203658,46.192959],"type":"Point"}
}