{
  "type": "Feature",
  "properties": {
    "iso:country":"CH",
    "sg:address":"Bahnhofstr. 3 8487 Zell Zh. Postfach",
    "sg:city":"Kollbrunn",
    "sg:orig_category":"Non-Classified Establishments",
    "sg:postcode":"8483",
    "sg:province":"Z\u00fcrich",
    "wof:name":"Drogerie Bichsel",
    "wof:placetype":"venue"
},
  "geometry": {"coordinates":[8.8192653656,47.4410743713],"type":"Point"}
}