{
  "type": "Feature",
  "properties": {
    "iso:country":"CH",
    "sg:address":"Elvezia Corso 16",
    "sg:city":"Lugano",
    "sg:orig_category":"Finanzierungsinstitutionen",
    "sg:phone":"+41 91 910 76 00",
    "sg:postcode":"6900",
    "sg:province":"Ticino",
    "wof:name":"M.b.i. Sa Money Bonds Investments",
    "wof:placetype":"venue"
},
  "geometry": {"coordinates":[8.9558868408,46.007774353],"type":"Point"}
}