{
  "type": "Feature",
  "properties": {
    "iso:country":"CH",
    "sg:address":"Hammerstrasse 14",
    "sg:city":"Basel",
    "sg:orig_category":"Mit dem Versicherungsgewerbe verbundene T\u00e4tigkeiten",
    "sg:postcode":"4058",
    "sg:province":"Basel-Stadt",
    "wof:name":"Intertransfers Ag",
    "wof:placetype":"venue"
},
  "geometry": {"coordinates":[7.5982818604,47.560005188],"type":"Point"}
}