{
  "type": "Feature",
  "properties": {
    "iso:country":"CH",
    "sg:address":"Viollier Avenue 24 1260 Nyon. Postfach",
    "sg:city":"Lausanne",
    "sg:orig_category":"Sonstige mit Sport verbundene T\u00e4tigkeiten",
    "sg:postcode":"1003",
    "sg:province":"Vaud",
    "wof:name":"S.c. Sport Management International Sa Assistance Aux Joueurs Du Football Professionnel, Notamment Recherche, N\u00e9gociation Etc",
    "wof:placetype":"venue"
},
  "geometry": {"coordinates":[6.236989975,46.3843650818],"type":"Point"}
}