{
  "type": "Feature",
  "properties": {
    "iso:country":"CH",
    "sg:address":"Bernstrasse 51",
    "sg:city":"Bern",
    "sg:orig_category":"Herstellung von Medikamenten U sonstigen pharmazeutischen Erzeugnissen Herstellung von pharmazeutisc",
    "sg:phone":"+41 31 991 22 20",
    "sg:postcode":"3018",
    "sg:province":"Bern",
    "wof:name":"Pharmalabor Dr. Brandt Ag Pharmazeut. Produkte; Fabr., Verkauf",
    "wof:placetype":"venue"
},
  "geometry": {"coordinates":[7.396132946,46.9420623779],"type":"Point"}
}