{
  "type": "Feature",
  "properties": {
    "iso:country":"CH",
    "sg:address":"Gempenstrasse 69 4053 Basel. Postfach",
    "sg:city":"Basel",
    "sg:orig_category":"Herstellung von Radio U Fernsehger\u00e4ten sowie phono U videotechnischen Ger\u00e4ten",
    "sg:phone":"+41 61 361 64 66",
    "sg:postcode":"4051",
    "sg:province":"Basel-Stadt",
    "wof:name":"Arbelos Mijnssen Christoph Akustische U. Elektronische Ger\u00e4te; Entwickl., Herst., Im, Export Usw",
    "wof:placetype":"venue"
},
  "geometry": {"coordinates":[7.5858950615,47.5428848267],"type":"Point"}
}