{
  "type": "Feature",
  "properties": {
    "iso:country":"CH",
    "sg:address":"Widenb\u00fcelstrasse 7",
    "sg:city":"M\u00f6nchaltorf",
    "sg:orig_category":"Grosshandel mit elektrischen Haushaltsger\u00e4ten, Radio U Fernsehger\u00e4ten Herstellung von Betonerzeugnis",
    "sg:phone":"+41 19481600",
    "sg:postcode":"8617",
    "sg:province":"Z\u00fcrich",
    "wof:name":"Fischer Walter",
    "wof:placetype":"venue"
},
  "geometry": {"coordinates":[8.7241706848,47.3104476929],"type":"Point"}
}