{
  "type": "Feature",
  "properties": {
    "iso:country":"CH",
    "sg:address":"Schulweg 14 8503 Frauenfeld. Postfach",
    "sg:city":"Frauenfeld",
    "sg:orig_category":"Unclassifiable Establishments",
    "sg:postcode":"8500",
    "sg:province":"Thurgau",
    "wof:name":"Rofida-holding Ag Beteiligungen Usw",
    "wof:placetype":"venue"
},
  "geometry": {"coordinates":[8.9059581757,47.5595092773],"type":"Point"}
}