{
  "type": "Feature",
  "properties": {
    "iso:country":"CH",
    "sg:address":"Viale Balli 2",
    "sg:city":"Locarno",
    "sg:orig_category":"Kauf U Verkauf von Immobilien auf eigene Rechnung Sonstige Finanzierungsinstitutionen",
    "sg:postcode":"6600",
    "sg:province":"Ticino",
    "wof:name":"E.p. Europe Partecipations Sa Howald Lussemburgo Succ. Di Locarno",
    "wof:placetype":"venue"
},
  "geometry": {"coordinates":[8.7998170853,46.1711769104],"type":"Point"}
}