{
  "type": "Feature",
  "properties": {
    "iso:country":"CH",
    "sg:address":"1233",
    "sg:city":"Bernex",
    "sg:orig_category":"Vereine Gesang",
    "sg:phone":"+41 22 757 10 35",
    "sg:postcode":"1233",
    "sg:province":"Gen\u00e8ve",
    "wof:name":"Chorale Catholique",
    "wof:placetype":"venue"
},
  "geometry": {"coordinates":[6.0726900101,46.1749458313],"type":"Point"}
}