{
  "type": "Feature",
  "properties": {
    "iso:country":"CH",
    "sg:address":"Sumpfstrasse 26",
    "sg:city":"Steinhausen",
    "sg:orig_category":"Sonstiger Grosshandel",
    "sg:postcode":"6312",
    "sg:province":"Zug",
    "wof:name":"Kran + Trans Gmbh",
    "wof:placetype":"venue"
},
  "geometry": {"coordinates":[9.6325750351,47.4300308228],"type":"Point"}
}