{
  "type": "Feature",
  "properties": {
    "iso:country":"CH",
    "sg:address":"Steinhauserstrasse 6",
    "sg:city":"Cham",
    "sg:orig_category":"Sonstiger Grosshandel",
    "sg:phone":"+41 41 741 86 86",
    "sg:postcode":"6330",
    "sg:province":"Zug",
    "wof:name":"Assmann & Co.",
    "wof:placetype":"venue"
},
  "geometry": {"coordinates":[8.4677534103,47.2133598328],"type":"Point"}
}