{
  "type": "Feature",
  "properties": {
    "iso:country":"CH",
    "sg:address":"Salinenstrasse 9",
    "sg:city":"Basel",
    "sg:orig_category":"Verwaltung von Immobilien Wirtschaftspr\u00fcfung, Steuerberatung U Treuhand",
    "sg:phone":"+41 61 319 93 00",
    "sg:postcode":"4052",
    "sg:province":"Basel-Stadt",
    "wof:name":"Lampert Treuhand & Revision",
    "wof:placetype":"venue"
},
  "geometry": {"coordinates":[7.60962677,47.5470085144],"type":"Point"}
}