{
  "type": "Feature",
  "properties": {
    "iso:country":"CH",
    "sg:address":"Route D'a\u00efre 161",
    "sg:city":"A\u00efre",
    "sg:orig_category":"Herstellung von Schmuck, Gold U Silberschmiedwaren",
    "sg:postcode":"1219",
    "sg:province":"Gen\u00e8ve",
    "wof:name":"Rafael Torres",
    "wof:placetype":"venue"
},
  "geometry": {"coordinates":[6.1003398895,46.1972198486],"type":"Point"}
}