{
  "type": "Feature",
  "properties": {
    "iso:country":"CH",
    "sg:address":"Innere Margarethenstrasse 9 4051 Basel. Postfach",
    "sg:city":"Basel",
    "sg:orig_category":"Herstellung von sonstigen M\u00f6beln",
    "sg:postcode":"4051",
    "sg:province":"Basel-Stadt",
    "wof:name":"Mariz Berardinelli & Cie. Fabrikat. V. U. Handel Mit Bilderleisten",
    "wof:placetype":"venue"
},
  "geometry": {"coordinates":[7.5870141983,47.5502891541],"type":"Point"}
}