{
  "type": "Feature",
  "properties": {
    "iso:country":"CH",
    "sg:address":"Obstgarten 5",
    "sg:city":"Niederhelfenschwil",
    "sg:orig_category":"Wirtschaftspr\u00fcfung, Steuerberatung U Treuhand",
    "sg:phone":"+41 41 741 33 73",
    "sg:postcode":"9527",
    "sg:province":"St. Gallen",
    "wof:name":"Responsa Partners Ag",
    "wof:placetype":"venue"
},
  "geometry": {"coordinates":[9.1836977005,47.4735145569],"type":"Point"}
}