{
  "type": "Feature",
  "properties": {
    "iso:country":"CH",
    "sg:address":"Bahnhofstrasse 23",
    "sg:city":"Laufen",
    "sg:orig_category":"Grosshandel mit sonstigen Gebrauchs U Verbrauchsg\u00fctern",
    "sg:postcode":"4242",
    "sg:province":"Basel-Landschaft",
    "wof:name":"Roger R\u00e9rat, Waffen Und Munition, B\u00fcchsenmacherei",
    "wof:placetype":"venue"
},
  "geometry": {"coordinates":[7.5020561218,47.4191017151],"type":"Point"}
}