{
  "type": "Feature",
  "properties": {
    "addr:full":"Gewerbestrasse 2 Gerlafingen Solothurn 4563",
    "addr:housenumber":"2",
    "addr:postcode":"4563",
    "addr:street":"Gewerbestrasse",
    "iso:country":"CH",
    "sg:address":"Gewerbestrasse 2",
    "sg:city":"Gerlafingen",
    "sg:orig_category":"Detailhandel mit Blumen U Pflanzen Fachdetailhandel in Verkaufsr\u00e4umen",
    "sg:phone":"+41 32 675 12 40",
    "sg:postcode":"4563",
    "sg:province":"Solothurn",
    "wof:name":"Blumen-boutique Susi, Tjandra Susi",
    "wof:placetype":"venue"
},
  "geometry": {"coordinates":[7.572663,47.170547],"type":"Point"}
}