{
  "type": "Feature",
  "properties": {
    "addr:full":"Via Della Posta Bioggio Ticino 6934",
    "addr:postcode":"6934",
    "addr:street":"Via Della Posta",
    "iso:country":"CH",
    "sg:address":"Via Della Posta",
    "sg:city":"Bioggio",
    "sg:classifiers":[
        {
            "category":"Education",
            "subcategory":"Vocational School",
            "type":"Public Place"
        }
    ],
    "sg:phone":"+41 91 610 70 70",
    "sg:postcode":"6934",
    "sg:province":"Ticino",
    "sg:tags":[
        "assembly",
        "testing",
        "printed",
        "circuit",
        "pcb",
        "board"
    ],
    "wof:name":"Rob S.a.",
    "wof:placetype":"venue"
},
  "geometry": {"coordinates":[8.910595,46.014694],"type":"Point"}
}