{
  "type": "Feature",
  "properties": {
    "iso:country":"CH",
    "sg:address":"Oberhofstrasse 30",
    "sg:city":"Emmenbr\u00fccke",
    "sg:orig_category":"Detailhandel mit Textilien Herstellung von Teppichen",
    "sg:phone":"+41 52 657 15 75",
    "sg:postcode":"6020",
    "sg:province":"Luzern",
    "wof:name":"Doggwiler Karl Ag",
    "wof:placetype":"venue"
},
  "geometry": {"coordinates":[8.69851017,47.6676940918],"type":"Point"}
}