{
  "type": "Feature",
  "properties": {
    "addr:full":"Oberdorfstrasse 1 H\u00e4gglingen Aargau 5607",
    "addr:housenumber":"1",
    "addr:postcode":"5607",
    "addr:street":"Oberdorfstrasse",
    "iso:country":"CH",
    "sg:address":"Oberdorfstrasse 1",
    "sg:city":"H\u00e4gglingen",
    "sg:orig_category":"Darlehenskassen U Raiffeisenbanken",
    "sg:phone":"+41 56 616 90 90",
    "sg:postcode":"5607",
    "sg:province":"Aargau",
    "wof:name":"Raiffeisenbank",
    "wof:placetype":"venue"
},
  "geometry": {"coordinates":[8.254874,47.386974],"type":"Point"}
}