{
  "type": "Feature",
  "properties": {
    "iso:country":"CH",
    "sg:address":"Eggstrasse 17",
    "sg:city":"Wittenbach",
    "sg:orig_category":"Non-Classified Establishments",
    "sg:postcode":"9303",
    "wof:name":"Rolf Gross Unternehmensberatung",
    "wof:placetype":"venue"
},
  "geometry": {"coordinates":[9.3795070648,47.4642448425],"type":"Point"}
}