{
  "type": "Feature",
  "properties": {
    "iso:country":"CH",
    "sg:address":"Blumenrainweg 11",
    "sg:city":"Mumpf",
    "sg:orig_category":"G\u00fcterbef\u00f6rderung im Strassenverkehr",
    "sg:phone":"+41 62 873 23 34",
    "sg:postcode":"4322",
    "sg:province":"Aargau",
    "wof:name":"Marcel Suri Transporte",
    "wof:placetype":"venue"
},
  "geometry": {"coordinates":[7.9226732254,47.5448989868],"type":"Point"}
}