{
  "type": "Feature",
  "properties": {
    "iso:country":"CH",
    "sg:address":"Saint-fran\u00e7ois Place 1003 Lausanne Case Postale 48",
    "sg:city":"Lausanne",
    "sg:orig_category":"Betrieb von Sportanlagen",
    "sg:phone":"+41 21 784 13 23",
    "sg:postcode":"1003",
    "sg:province":"Vaud",
    "wof:name":"Pra Roman Sa",
    "wof:placetype":"venue"
},
  "geometry": {"coordinates":[6.634835,46.519707],"type":"Point"}
}