{
  "type": "Feature",
  "properties": {
    "iso:country":"CH",
    "sg:address":"Absyte 7",
    "sg:city":"Grenchen",
    "sg:orig_category":"F\u00fcrsorge\u00e4mter",
    "sg:phone":"+41 71 224 50 37",
    "sg:postcode":"2540",
    "sg:province":"Solothurn",
    "wof:name":"St\u00e4dtisches F\u00fcrsorgeamt",
    "wof:placetype":"venue"
},
  "geometry": {"coordinates":[9.3776102066,47.4258003235],"type":"Point"}
}