{
  "type": "Feature",
  "properties": {
    "addr:full":"Neugasse 155 8005 Z\u00fcrich. Postfach 7372 Z\u00fcrich Z\u00fcrich 8023",
    "addr:housenumber":"155",
    "addr:postcode":"8005 zuerich. postfach 7372;8023",
    "addr:street":"Neugasse",
    "iso:country":"CH",
    "sg:address":"Neugasse 155 8005 Z\u00fcrich. Postfach 7372",
    "sg:city":"Z\u00fcrich",
    "sg:orig_category":"Bau U Wohngenossenschaften",
    "sg:phone":"+41 12726767",
    "sg:postcode":"8023",
    "sg:province":"Z\u00fcrich",
    "wof:name":"Eisenbahner-baugen.dreispitz",
    "wof:placetype":"venue"
},
  "geometry": {"coordinates":[8.523777,47.384903],"type":"Point"}
}