{
  "type": "Feature",
  "properties": {
    "iso:country":"CH",
    "sg:address":"Rue Abraham -gevray 1 1200 Gen\u00e8ve. Postfach",
    "sg:city":"Gen\u00e8ve",
    "sg:orig_category":"Reiseb\u00fcros U Reiseveranstalter",
    "sg:postcode":"1201",
    "sg:province":"Gen\u00e8ve",
    "wof:name":"Iperial Travel Services, De Sousa-azevedo Yvonne",
    "wof:placetype":"venue"
},
  "geometry": {"coordinates":[6.1495947838,46.210559845],"type":"Point"}
}