{
  "type": "Feature",
  "properties": {
    "iso:country":"CH",
    "sg:address":"Via Baraggie 35",
    "sg:city":"Ascona",
    "sg:orig_category":"Gartenbau Landschaftsplanungsb\u00fcros U Gartenarchitekturb\u00fcros",
    "sg:phone":"+41 91 791 95 05",
    "sg:postcode":"6612",
    "sg:province":"Ticino",
    "wof:name":"Ivano Cotta Giardiniere Paesaggista",
    "wof:placetype":"venue"
},
  "geometry": {"coordinates":[8.773150444,46.1583328247],"type":"Point"}
}