{
  "type": "Feature",
  "properties": {
    "iso:country":"CH",
    "sg:address":"B\u00e4umligasse 12",
    "sg:city":"Riehen",
    "sg:orig_category":"Softwareentwicklung U beratung Sonstige mit der Informatik verbundene T\u00e4tigkeiten",
    "sg:phone":"+41 21 636 48 18",
    "sg:postcode":"4125",
    "sg:province":"Basel-Stadt",
    "wof:name":"Olivier Sattiva Ofs Informatique",
    "wof:placetype":"venue"
},
  "geometry": {"coordinates":[6.595954895,46.5391426086],"type":"Point"}
}