{
  "type": "Feature",
  "properties": {
    "iso:country":"CH",
    "sg:address":"Rte De Lavaux 49",
    "sg:city":"Corseaux",
    "sg:classifiers":[
        {
            "category":"Professional",
            "subcategory":"Printing & Photocopies",
            "type":"Services"
        }
    ],
    "sg:phone":"+41 21 925 92 50",
    "sg:postcode":"1802",
    "sg:province":"Vaud",
    "sg:tags":[
        "paper",
        "raw",
        "material",
        "-",
        "cardboard"
    ],
    "wof:name":"Adoc Sa",
    "wof:placetype":"venue"
},
  "geometry": {"coordinates":[6.821939,46.469791],"type":"Point"}
}