{
  "type": "Feature",
  "properties": {
    "iso:country":"CH",
    "sg:address":"6276",
    "sg:city":"Hohenrain",
    "sg:orig_category":"Institutionen f\u00fcr Behinderte Sonderschulen",
    "sg:phone":"+41 27 474 99 11",
    "sg:postcode":"6276",
    "sg:province":"Luzern",
    "wof:name":"Kinderdorf St.antonius",
    "wof:placetype":"venue"
},
  "geometry": {"coordinates":[7.6346597672,46.3163299561],"type":"Point"}
}