{
  "type": "Feature",
  "properties": {
    "iso:country":"CH",
    "sg:address":"Glockentalstrasse 33",
    "sg:city":"Steffisburg",
    "sg:orig_category":"Grosshandel mit Eisenwaren sowie Installationsbedarf f\u00fcr Gas, Wasser U Heizung",
    "sg:phone":"+41 22 797 33 30",
    "sg:postcode":"3612",
    "sg:province":"Bern",
    "wof:name":"Quincaillerie Du Lignon Sa",
    "wof:placetype":"venue"
},
  "geometry": {"coordinates":[6.09892416,46.2072715759],"type":"Point"}
}