{
  "type": "Feature",
  "properties": {
    "iso:country":"CH",
    "sg:address":"Via Alla Moderna 3 6500 Bellinzona. Postfach",
    "sg:city":"Bellinzona",
    "sg:orig_category":"Elektroinstallation",
    "sg:postcode":"6500",
    "sg:province":"Ticino",
    "wof:name":"Studio Fallet",
    "wof:placetype":"venue"
},
  "geometry": {"coordinates":[9.0292673111,46.1987380981],"type":"Point"}
}