{
  "type": "Feature",
  "properties": {
    "iso:country":"CH",
    "sg:address":"Industriestr. 20",
    "sg:city":"Embrach",
    "sg:classifiers":[
        {
            "category":"Professional",
            "type":"Services"
        }
    ],
    "sg:phone":"+41 4118663010",
    "sg:postcode":"8424",
    "sg:province":"Z\u00fcrich",
    "sg:tags":[
        "transport",
        "road"
    ],
    "wof:name":"B\u00dchler Concept Ag",
    "wof:placetype":"venue"
},
  "geometry": {"coordinates":[8.5972795486,47.5165061951],"type":"Point"}
}