{
  "type": "Feature",
  "properties": {
    "iso:country":"CH",
    "sg:address":"Holderenstrasse 29",
    "sg:city":"Rehetobel",
    "sg:orig_category":"Mechanische Werkst\u00e4tten",
    "sg:phone":"+41 71 877 24 14",
    "sg:postcode":"9038",
    "sg:province":"Appenzell Ausserrhoden",
    "wof:name":"Albert Z\u00e4hner Automaten-dreherei",
    "wof:placetype":"venue"
},
  "geometry": {"coordinates":[9.4799432755,47.4255142212],"type":"Point"}
}