{
  "type": "Feature",
  "properties": {
    "iso:country":"CH",
    "sg:address":"B\u00e4lliz 64",
    "sg:city":"Thun",
    "sg:orig_category":"Datenverarbeitungsdienste",
    "sg:phone":"+41 33 223 47 32",
    "sg:postcode":"3600",
    "sg:province":"Bern",
    "wof:name":"Ebsto Helmut Stoller Edv-beratung",
    "wof:placetype":"venue"
},
  "geometry": {"coordinates":[7.629881,46.757122],"type":"Point"}
}