{
  "type": "Feature",
  "properties": {
    "iso:country":"CH",
    "sg:address":"Zentralstrasse 5",
    "sg:city":"Luzern",
    "sg:orig_category":"Reiseb\u00fcros U Reiseveranstalter",
    "sg:phone":"+41 51 227 33 81",
    "sg:postcode":"6003",
    "sg:province":"Luzern",
    "wof:name":"Railaway Ag",
    "wof:placetype":"venue"
},
  "geometry": {"coordinates":[8.309548378,47.0497817993],"type":"Point"}
}