{
  "type": "Feature",
  "properties": {
    "iso:country":"CH",
    "sg:address":"Staffeleggstrasse 227",
    "sg:city":"Asp",
    "sg:classifiers":[
        {
            "category":"Restaurant",
            "type":"Food & Drink"
        }
    ],
    "sg:phone":"+41 62 878 16 88",
    "sg:postcode":"5025",
    "sg:province":"Aargau",
    "wof:name":"Restaurant Staffelegg",
    "wof:placetype":"venue"
},
  "geometry": {"coordinates":[8.0540599823,47.4455718994],"type":"Point"}
}