{
  "type": "Feature",
  "properties": {
    "iso:country":"CH",
    "sg:address":"Seestrasse 990 8706 Meilen. Postfach 231",
    "sg:city":"Meilen",
    "sg:orig_category":"Herstellung von B\u00fcro U Ladenm\u00f6beln",
    "sg:phone":"+41 19236262",
    "sg:postcode":"8706",
    "sg:province":"Z\u00fcrich",
    "wof:name":"Parabello Shopdesign Ag",
    "wof:placetype":"venue"
},
  "geometry": {"coordinates":[8.652130127,47.2653999329],"type":"Point"}
}