{
  "type": "Feature",
  "properties": {
    "iso:country":"CH",
    "sg:address":"Zone Industrielle",
    "sg:city":"Collombey",
    "sg:orig_category":"Pensionskassen",
    "sg:postcode":"1868",
    "sg:province":"Valais",
    "wof:name":"Fondation En Faveur Du Personnel Du Groupe Tamoil",
    "wof:placetype":"venue"
},
  "geometry": {"coordinates":[6.945827961,46.2704734802],"type":"Point"}
}