{
  "type": "Feature",
  "properties": {
    "iso:country":"CH",
    "sg:address":"Solothurnerstrasse 17",
    "sg:city":"Olten",
    "sg:classifiers":[
        {
            "category":"Restaurant",
            "type":"Food & Drink"
        }
    ],
    "sg:phone":"+41 71 911 07 98",
    "sg:postcode":"4600",
    "sg:province":"Solothurn",
    "wof:name":"Restaurant Blume",
    "wof:placetype":"venue"
},
  "geometry": {"coordinates":[9.0461912155,47.4631118774],"type":"Point"}
}