{
  "type": "Feature",
  "properties": {
    "iso:country":"CH",
    "sg:address":"Bruggerstrasse 164",
    "sg:city":"Baden",
    "sg:orig_category":"Instandhaltung U Reparatur von Automobilen",
    "sg:phone":"+41 56 221 13 20",
    "sg:postcode":"5400",
    "sg:province":"Aargau",
    "wof:name":"D & E Automobile Gmbh",
    "wof:placetype":"venue"
},
  "geometry": {"coordinates":[8.2837553024,47.4835777283],"type":"Point"}
}