{
  "type": "Feature",
  "properties": {
    "iso:country":"CH",
    "sg:address":"Haselweg 16.",
    "sg:city":"Lenzburg",
    "sg:orig_category":"Betrieb von Taxis",
    "sg:postcode":"5600",
    "sg:province":"Aargau",
    "wof:name":"Sch\u00e4rz Taxi Und Carreisen.",
    "wof:placetype":"venue"
},
  "geometry": {"coordinates":[8.178861,47.380463],"type":"Point"}
}