{
  "type": "Feature",
  "properties": {
    "addr:full":"Zypressenstrasse 123 Z\u00fcrich Z\u00fcrich 8004",
    "addr:housenumber":"123",
    "addr:postcode":"8004",
    "addr:street":"Zypressenstrasse",
    "iso:country":"CH",
    "sg:address":"Zypressenstrasse 123",
    "sg:city":"Z\u00fcrich",
    "sg:orig_category":"Betrieb von Taxis",
    "sg:phone":"+41 12413709",
    "sg:postcode":"8004",
    "sg:province":"Z\u00fcrich",
    "wof:name":"Gm Taxi-josh Gmbh",
    "wof:placetype":"venue"
},
  "geometry": {"coordinates":[8.516955,47.380436],"type":"Point"}
}