{
  "type": "Feature",
  "properties": {
    "iso:country":"CH",
    "sg:address":"Welschd\u00f6rfli 5",
    "sg:city":"Chur",
    "sg:orig_category":"Diskotheken, Dancings, Night Clubs",
    "sg:phone":"+41 81 252 28 10",
    "sg:postcode":"7000",
    "sg:province":"Graubunden",
    "wof:name":"Disco Felsenbar",
    "wof:placetype":"venue"
},
  "geometry": {"coordinates":[9.5287542343,46.8475914001],"type":"Point"}
}