{
  "type": "Feature",
  "properties": {
    "iso:country":"CH",
    "sg:address":"Montedato",
    "sg:city":"Riazzino",
    "sg:classifiers":[
        {
            "category":"Restaurant",
            "type":"Food & Drink"
        }
    ],
    "sg:phone":"+41 91 859 14 87",
    "sg:postcode":"6595",
    "sg:province":"Ticino",
    "wof:name":"Grotto Montedato",
    "wof:placetype":"venue"
},
  "geometry": {"coordinates":[8.897600174,46.1745605469],"type":"Point"}
}