{
  "type": "Feature",
  "properties": {
    "iso:country":"CH",
    "sg:address":"Schl\u00f6sslistrasse 21",
    "sg:city":"Ebikon",
    "sg:orig_category":"Einbau von Schreinerwaren Elektroinstallation",
    "sg:phone":"+41 55 442 33 84",
    "sg:postcode":"6030",
    "sg:province":"Luzern",
    "wof:name":"Kuriger \u00ac Montagen",
    "wof:placetype":"venue"
},
  "geometry": {"coordinates":[8.8482999802,47.188369751],"type":"Point"}
}