{
  "type": "Feature",
  "properties": {
    "iso:country":"CH",
    "sg:address":"3213",
    "sg:city":"Liebistorf",
    "sg:orig_category":"Non-Classified Establishments",
    "sg:postcode":"3213",
    "sg:province":"Fribourg",
    "wof:name":"Bc Bieli Consulting Gmbh",
    "wof:placetype":"venue"
},
  "geometry": {"coordinates":[7.1932702065,46.9079818726],"type":"Point"}
}