{
  "type": "Feature",
  "properties": {
    "iso:country":"CH",
    "sg:address":"Wettackerhof",
    "sg:city":"Hornussen",
    "sg:orig_category":"Sportvereine Motorrad Sportvereine Velo Rad-& Motorfahrer-Bund SRB",
    "sg:phone":"+41 62 771 40 84",
    "sg:postcode":"5075",
    "sg:province":"Aargau",
    "wof:name":"Rad-& Motorfahrerver.leutwil",
    "wof:placetype":"venue"
},
  "geometry": {"coordinates":[8.1777420044,47.2571220398],"type":"Point"}
}