{
  "type": "Feature",
  "properties": {
    "iso:country":"CH",
    "sg:address":"Sandstrasse 12 A",
    "sg:city":"Moosseedorf",
    "sg:orig_category":"Non-Classified Establishments",
    "sg:phone":"+41 31 859 62 44",
    "sg:postcode":"3302",
    "sg:province":"Bern",
    "wof:name":"Marcone Consulting Gmbh",
    "wof:placetype":"venue"
},
  "geometry": {"coordinates":[7.4828271866,47.0155296326],"type":"Point"}
}