{
  "type": "Feature",
  "properties": {
    "iso:country":"CH",
    "sg:address":"Ursprungstrasse 104",
    "sg:city":"M\u00fcnchenbuchsee",
    "sg:orig_category":"Grosshandel mit Datenverarbeitungsger\u00e4ten Softwareentwicklung U beratung",
    "sg:phone":"+41 56 441 35 66",
    "sg:postcode":"3053",
    "sg:province":"Bern",
    "wof:name":"Devidata Ag",
    "wof:placetype":"venue"
},
  "geometry": {"coordinates":[8.2269802094,47.4968261719],"type":"Point"}
}