{
  "type": "Feature",
  "properties": {
    "iso:country":"CH",
    "sg:address":"Martigny-croix",
    "sg:city":"Martigny-croix",
    "sg:orig_category":"Handel mit Automobilen",
    "sg:postcode":"1921",
    "sg:province":"Valais",
    "wof:name":"Export Autos Abdulkarim",
    "wof:placetype":"venue"
},
  "geometry": {"coordinates":[7.0548019409,46.0871009827],"type":"Point"}
}