{
  "type": "Feature",
  "properties": {
    "iso:country":"CH",
    "sg:address":"Chemin Du Crochet",
    "sg:city":"Cho\u00ebx",
    "sg:orig_category":"Vereine Dramatische and Theater",
    "sg:postcode":"1871",
    "sg:province":"Valais",
    "wof:name":"Assoc.des Tr\u00e9taux De La Vi\u00e8ze",
    "wof:placetype":"venue"
},
  "geometry": {"coordinates":[6.9631857872,46.2387428284],"type":"Point"}
}