{
  "type": "Feature",
  "properties": {
    "iso:country":"CH",
    "sg:address":"Sonnenstrasse 6",
    "sg:city":"Waltenschwil",
    "sg:orig_category":"G\u00fcterbef\u00f6rderung im Strassenverkehr",
    "sg:postcode":"5622",
    "sg:province":"Aargau",
    "wof:name":"Hunn Transport",
    "wof:placetype":"venue"
},
  "geometry": {"coordinates":[8.3072862625,47.3349761963],"type":"Point"}
}