{
  "type": "Feature",
  "properties": {
    "iso:country":"CH",
    "sg:address":"Marais Chemin Des 117",
    "sg:city":"Veyrier",
    "sg:orig_category":"Detektivb\u00fcros U \u00dcberwachung",
    "sg:postcode":"1255",
    "sg:province":"Gen\u00e8ve",
    "wof:name":"Heh Agency, Hans-erich Holzer",
    "wof:placetype":"venue"
},
  "geometry": {"coordinates":[6.185324192,46.1668891907],"type":"Point"}
}