{
  "type": "Feature",
  "properties": {
    "iso:country":"CH",
    "sg:address":"Ring 1 2500 Biel/bienne. Postfach",
    "sg:city":"Biel/bienne",
    "sg:orig_category":"Kauf U Verkauf von Immobilien auf eigene Rechnung",
    "sg:postcode":"2502",
    "sg:province":"Bern",
    "wof:name":"Bachofner Ursula",
    "wof:placetype":"venue"
},
  "geometry": {"coordinates":[7.2463569641,47.1415519714],"type":"Point"}
}