{
  "type": "Feature",
  "properties": {
    "iso:country":"CH",
    "sg:address":"Furlenstrasse 3",
    "sg:city":"Lausen",
    "sg:orig_category":"Herstellung von sonstigen M\u00f6beln",
    "sg:phone":"+41 61 921 30 00",
    "sg:postcode":"4415",
    "sg:province":"Basel-Landschaft",
    "wof:name":"Bega Gartenm\u00f6bel-center Ag, Lausen",
    "wof:placetype":"venue"
},
  "geometry": {"coordinates":[7.7602210045,47.4705238342],"type":"Point"}
}