{
  "type": "Feature",
  "properties": {
    "iso:country":"CH",
    "sg:address":"Schwabstrasse 35",
    "sg:city":"Bern",
    "sg:orig_category":"Unclassifiable Establishments",
    "sg:postcode":"3018",
    "sg:province":"Bern",
    "wof:name":"Kessler Bautechnische Dienstleistungen",
    "wof:placetype":"venue"
},
  "geometry": {"coordinates":[7.394780159,46.9448242188],"type":"Point"}
}