{
  "type": "Feature",
  "properties": {
    "iso:country":"CH",
    "sg:address":"Speiserstrasse 46",
    "sg:city":"Olten",
    "sg:classifiers":[
        {
            "category":"Professional",
            "subcategory":"Employment Agencies",
            "type":"Services"
        }
    ],
    "sg:phone":"+41 62 296 36 33",
    "sg:postcode":"4600",
    "sg:province":"Solothurn",
    "sg:tags":[
        "personal",
        "u",
        "stellenvermittlung"
    ],
    "wof:name":"Midi Au-pair-stellenvermittlung Kunz-hofmann B.",
    "wof:placetype":"venue"
},
  "geometry": {"coordinates":[7.9207091331,47.3456420898],"type":"Point"}
}