{
  "type": "Feature",
  "properties": {
    "iso:country":"CH",
    "sg:address":"Grand-rue 37 1350 Orbe. Postfach",
    "sg:city":"Orbe",
    "sg:orig_category":"Softwareentwicklung U beratung",
    "sg:postcode":"1350",
    "sg:province":"Vaud",
    "wof:name":"Arone Maffini & Jakob",
    "wof:placetype":"venue"
},
  "geometry": {"coordinates":[6.5319199562,46.7259178162],"type":"Point"}
}