{
  "type": "Feature",
  "properties": {
    "iso:country":"CH",
    "sg:address":"Sous Les Colons 4",
    "sg:city":"Malleray",
    "sg:orig_category":"G\u00fcterbef\u00f6rderung im Strassenverkehr",
    "sg:phone":"+41 32 492 12 45",
    "sg:postcode":"2735",
    "sg:province":"Bern",
    "wof:name":"Francis Blanchard Camionnage Cff",
    "wof:placetype":"venue"
},
  "geometry": {"coordinates":[7.2708301544,47.2405548096],"type":"Point"}
}