{
  "type": "Feature",
  "properties": {
    "iso:country":"CH",
    "sg:address":"Weberstrasse 11a",
    "sg:city":"Aarburg",
    "sg:orig_category":"Detailhandel mit Textilien",
    "sg:phone":"+41 21 922 85 75",
    "sg:postcode":"4663",
    "sg:province":"Aargau",
    "wof:name":"Plum'propres Claude Fuchs",
    "wof:placetype":"venue"
},
  "geometry": {"coordinates":[6.8432750702,46.4621353149],"type":"Point"}
}