{
  "type": "Feature",
  "properties": {
    "addr:full":"Cantonale Via 4 6963 Pregassona Case Postale 69 Pregassona Ticino 6963",
    "addr:postcode":"6963;69;6963",
    "addr:street":"Via 4;Postale",
    "iso:country":"CH",
    "sg:address":"Cantonale Via 4 6963 Pregassona Case Postale 69",
    "sg:city":"Pregassona",
    "sg:orig_category":"Allgemeiner Hoch U Tiefbau",
    "sg:phone":"+41 91 945 34 85",
    "sg:postcode":"6963",
    "sg:province":"Ticino",
    "wof:name":"Mottis Sa Costruzioni Generali",
    "wof:placetype":"venue"
},
  "geometry": {"coordinates":[8.97205,46.017918],"type":"Point"}
}