{
  "type": "Feature",
  "properties": {
    "iso:country":"CH",
    "sg:address":"Guisan Av. Du G\u00e9n\u00e9ral 19 3960 Sierre. Postfach",
    "sg:city":"Sierre",
    "sg:orig_category":"Softwareentwicklung U beratung",
    "sg:postcode":"3960",
    "sg:province":"Valais",
    "wof:name":"White-port Software S\u00e0rl Services, Conseils En Mati\u00e8re D'informatique Etc",
    "wof:placetype":"venue"
},
  "geometry": {"coordinates":[7.5300970078,46.2921524048],"type":"Point"}
}