{
  "type": "Feature",
  "properties": {
    "iso:country":"CH",
    "sg:address":"3700",
    "sg:city":"Spiez",
    "sg:orig_category":"Arbeitnehmerverb\u00e4nde",
    "sg:phone":"+41 18303831",
    "sg:postcode":"3700",
    "sg:province":"Bern",
    "wof:name":"Angestelltenverband Der Radio/tv Und Multimediabrache",
    "wof:placetype":"venue"
},
  "geometry": {"coordinates":[7.674855,46.68985],"type":"Point"}
}