{
  "type": "Feature",
  "properties": {
    "iso:country":"CH",
    "sg:address":"Ile-aux-bois Route De L'",
    "sg:city":"Monthey",
    "sg:orig_category":"Vermietung U Verpachtung von eigenen Immobilien",
    "sg:postcode":"1870",
    "sg:province":"Valais",
    "wof:name":"Soci\u00e9t\u00e9 Fruiti\u00e8re Du Rh\u00f4ne Sa",
    "wof:placetype":"venue"
},
  "geometry": {"coordinates":[4.3307628632,45.7873840332],"type":"Point"}
}