{
  "type": "Feature",
  "properties": {
    "iso:country":"CH",
    "sg:address":"L\u00e4ttenstrasse 6a",
    "sg:city":"Winkel",
    "sg:orig_category":"Sonstiges Versicherungsgewerbe",
    "sg:phone":"+41 61 753 19 66",
    "sg:postcode":"8185",
    "sg:province":"Z\u00fcrich",
    "wof:name":"Ibs Friedli Versicherungsvermittlung",
    "wof:placetype":"venue"
},
  "geometry": {"coordinates":[7.5975060463,47.4683036804],"type":"Point"}
}