{
  "type": "Feature",
  "properties": {
    "iso:country":"CH",
    "sg:address":"Kreuzbuchstrasse 88",
    "sg:city":"Meggen",
    "sg:orig_category":"Handels-H\u00e4user U Gesellschaften",
    "sg:postcode":"6045",
    "sg:province":"Luzern",
    "wof:name":"Dora Handels Und Beteiligungs Ag",
    "wof:placetype":"venue"
},
  "geometry": {"coordinates":[8.3669309616,47.0499229431],"type":"Point"}
}