{
  "type": "Feature",
  "properties": {
    "iso:country":"CH",
    "sg:address":"Industriestrasse 7",
    "sg:city":"Dietlikon",
    "sg:orig_category":"Herstellung von Metallkonstruktionen Stahl U Leichtmetallbau",
    "sg:phone":"+41 13186070",
    "sg:postcode":"8305",
    "sg:province":"Z\u00fcrich",
    "wof:name":"Schneebeli Metallbau Ag",
    "wof:placetype":"venue"
},
  "geometry": {"coordinates":[8.6248493195,47.4156036377],"type":"Point"}
}