{
  "type": "Feature",
  "properties": {
    "addr:full":"Grubenstrasse Sch\u00f6nried Bern 3778",
    "addr:postcode":"3778",
    "addr:street":"Grubenstrasse",
    "iso:country":"CH",
    "sg:address":"Grubenstrasse",
    "sg:city":"Sch\u00f6nried",
    "sg:orig_category":"Bauschreinerei Innenausbau",
    "sg:phone":"+41 79 439 74 10",
    "sg:postcode":"3778",
    "sg:province":"Bern",
    "wof:name":"Frautschi Holzbau",
    "wof:placetype":"venue"
},
  "geometry": {"coordinates":[7.291941,46.500267],"type":"Point"}
}