{
  "type": "Feature",
  "properties": {
    "iso:country":"CH",
    "sg:address":"Municipio",
    "sg:city":"Quinto",
    "sg:orig_category":"Wasserversorgung",
    "sg:postcode":"6777",
    "sg:province":"Ticino",
    "wof:name":"Azienda Acqua Potabile Comune Di Sala Capriasca",
    "wof:placetype":"venue"
},
  "geometry": {"coordinates":[8.9564599991,46.0654716492],"type":"Point"}
}