{
  "type": "Feature",
  "properties": {
    "iso:country":"CH",
    "sg:address":"Sonneggstrasse 5",
    "sg:city":"St.gallen",
    "sg:orig_category":"Sonstige pers\u00f6nliche Dienstleistungen",
    "sg:postcode":"9000",
    "sg:province":"St. Gallen",
    "wof:name":"Astro Line, Lagan\u00e0 Daniel",
    "wof:placetype":"venue"
},
  "geometry": {"coordinates":[9.397231102,47.4327087402],"type":"Point"}
}