{
  "type": "Feature",
  "properties": {
    "iso:country":"CH",
    "sg:address":"Simen Via Rinaldo 6600 Locarno. Postfach",
    "sg:city":"Locarno",
    "sg:orig_category":"Tankstellen",
    "sg:postcode":"6600",
    "sg:province":"Ticino",
    "wof:name":"Esso Affoltern A. A. Sommer Michael",
    "wof:placetype":"venue"
},
  "geometry": {"coordinates":[8.442199707,47.273059845],"type":"Point"}
}