{
  "type": "Feature",
  "properties": {
    "iso:country":"CH",
    "sg:address":"Route Du Signal 40",
    "sg:city":"Lausanne",
    "sg:orig_category":"Diskotheken, Dancings, Night Clubs",
    "sg:phone":"+41 21 312 23 12",
    "sg:postcode":"1018",
    "sg:province":"Vaud",
    "wof:name":"Restaurant Chalet Suisse & Dancing La Tomate",
    "wof:placetype":"venue"
},
  "geometry": {"coordinates":[6.640004158,46.5322685242],"type":"Point"}
}