{
  "type": "Feature",
  "properties": {
    "iso:country":"CH",
    "sg:address":"Sch\u00fctzenmattweg",
    "sg:city":"Olten",
    "sg:orig_category":"Detailhandel mit Zeitungen U Zeitschriften Kioske",
    "sg:phone":"+41 62 212 19 72",
    "sg:postcode":"4600",
    "sg:province":"Solothurn",
    "wof:name":"Restaurant Zum Strandbad",
    "wof:placetype":"venue"
},
  "geometry": {"coordinates":[7.9028921127,47.3489646912],"type":"Point"}
}