{
  "type": "Feature",
  "properties": {
    "addr:full":"Hauptstrasse 46 Glarus Glarus 8750",
    "addr:housenumber":"46",
    "addr:postcode":"8750",
    "addr:street":"Hauptstrasse",
    "iso:country":"CH",
    "sg:address":"Hauptstrasse 46",
    "sg:city":"Glarus",
    "sg:orig_category":"Detailhandel mit B\u00fcromaschinen U einrichtungen Detailhandel mit Schreib U Papeteriewaren",
    "sg:phone":"+41 17616124",
    "sg:postcode":"8750",
    "sg:province":"Glarus",
    "wof:name":"Fritz Kunz Papeterie B\u00fcromaschinen",
    "wof:placetype":"venue"
},
  "geometry": {"coordinates":[8.453384,47.277107],"type":"Point"}
}