{
  "type": "Feature",
  "properties": {
    "iso:country":"CH",
    "sg:address":"Masanserstrasse 161",
    "sg:city":"Chur",
    "sg:orig_category":"Vorschulen, Kinderg\u00e4rten",
    "sg:phone":"+41 81 353 31 27",
    "sg:postcode":"7000",
    "sg:province":"Graubunden",
    "wof:name":"St\u00e4dtischer Kindergarten Heiligkreuz",
    "wof:placetype":"venue"
},
  "geometry": {"coordinates":[9.534942627,46.8642539978],"type":"Point"}
}