{
  "type": "Feature",
  "properties": {
    "iso:country":"CH",
    "sg:address":"Frenkenstrasse 14",
    "sg:city":"Liestal",
    "sg:orig_category":"Non-Classified Establishments",
    "sg:postcode":"4410",
    "sg:province":"Basel-Landschaft",
    "wof:name":"Damenriege Niederdorf",
    "wof:placetype":"venue"
},
  "geometry": {"coordinates":[7.7412199974,47.478313446],"type":"Point"}
}