{
  "type": "Feature",
  "properties": {
    "iso:country":"CH",
    "sg:address":"7516",
    "sg:city":"Maloja",
    "sg:orig_category":"Campingpl\u00e4tze Detailhandel mit Zeitungen U Zeitschriften Kioske",
    "sg:phone":"+41 81 824 31 81",
    "sg:postcode":"7516",
    "sg:province":"Graubunden",
    "wof:name":"Tcs-campingplatz Plan Curtinac",
    "wof:placetype":"venue"
},
  "geometry": {"coordinates":[9.69527,46.401001],"type":"Point"}
}