{
  "type": "Feature",
  "properties": {
    "iso:country":"CH",
    "sg:address":"Chemin De Beausobre 4",
    "sg:city":"Morges",
    "sg:orig_category":"Interessenvertretungen",
    "sg:phone":"+41 21 802 43 93",
    "sg:postcode":"1110",
    "sg:province":"Vaud",
    "wof:name":"Fondation Du Conservatoire De Musique De Morges Et Environs",
    "wof:placetype":"venue"
},
  "geometry": {"coordinates":[6.4903941154,46.5137634277],"type":"Point"}
}