{
  "type": "Feature",
  "properties": {
    "iso:country":"CH",
    "sg:address":"Route De Lausanne 16",
    "sg:city":"Rolle",
    "sg:orig_category":"Verwertung von Milch",
    "sg:postcode":"1180",
    "sg:province":"Vaud",
    "wof:name":"Soci\u00e9t\u00e9 De Laiterie Et D'agriculture De Rolle.",
    "wof:placetype":"venue"
},
  "geometry": {"coordinates":[6.3462400436,46.4625473022],"type":"Point"}
}