{
  "type": "Feature",
  "properties": {
    "iso:country":"CH",
    "sg:address":"St. Alban-graben 8 4051 Basel. Postfach",
    "sg:city":"Basel",
    "sg:classifiers":[
        {
            "category":"Education",
            "subcategory":"Library",
            "type":"Public Place"
        }
    ],
    "sg:phone":"+41 61 272 18 55",
    "sg:postcode":"4001",
    "sg:province":"Basel-Stadt",
    "sg:tags":[
        "u",
        "bibliotheken",
        "archive"
    ],
    "wof:name":"Bibliothek Der Basler Handelskammer",
    "wof:placetype":"venue"
},
  "geometry": {"coordinates":[7.593252,47.554111],"type":"Point"}
}