{
  "type": "Feature",
  "properties": {
    "iso:country":"CH",
    "sg:address":"Av. G\u00e9n\u00e9ral Guisan 29",
    "sg:city":"Sierre",
    "sg:classifiers":[
        {
            "category":"Banks & Credit Unions",
            "subcategory":"Bank",
            "type":"Services"
        }
    ],
    "sg:phone":"+41 27554444",
    "sg:postcode":"3960",
    "sg:province":"Valais",
    "wof:name":"Banque Cantonale Du Valais",
    "wof:placetype":"venue"
},
  "geometry": {"coordinates":[7.528845,46.291779],"type":"Point"}
}