{
  "type": "Feature",
  "properties": {
    "addr:full":"Av. G\u00e9n\u00e9ral Guisan 29 Sierre Valais 3960",
    "addr:housenumber":"29",
    "addr:postcode":"3960",
    "addr:street":"Av. Ge\u0301Ne\u0301Ral Guisan",
    "iso:country":"CH",
    "sg:address":"Av. G\u00e9n\u00e9ral Guisan 29",
    "sg:city":"Sierre",
    "sg:classifiers":[
        {
            "category":"Banks & Credit Unions",
            "subcategory":"Bank",
            "type":"Services"
        }
    ],
    "sg:phone":"+41 27554444",
    "sg:postcode":"3960",
    "sg:province":"Valais",
    "wof:name":"Banque Cantonale Du Valais",
    "wof:placetype":"venue"
},
  "geometry": {"coordinates":[7.528845,46.291779],"type":"Point"}
}