{
  "type": "Feature",
  "properties": {
    "iso:country":"CH",
    "sg:address":"Hartbertstrasse 1",
    "sg:city":"Chur",
    "sg:orig_category":"Unclassifiable Establishments",
    "sg:phone":"+41 81 252 36 16",
    "sg:postcode":"7000",
    "sg:province":"Graubunden",
    "wof:name":"Rhenus Finanz Und Beteiligungs Ag",
    "wof:placetype":"venue"
},
  "geometry": {"coordinates":[9.5323934555,46.8526191711],"type":"Point"}
}