{
  "type": "Feature",
  "properties": {
    "iso:country":"CH",
    "sg:address":"Binzm\u00fchlestrasse 48a",
    "sg:city":"Z\u00fcrich",
    "sg:orig_category":"Physiotherapie",
    "sg:phone":"+41 13028988",
    "sg:postcode":"8050",
    "sg:province":"Z\u00fcrich",
    "wof:name":"Matthias & Karin Heiniger Physiotherapie",
    "wof:placetype":"venue"
},
  "geometry": {"coordinates":[8.5451107025,47.4139976501],"type":"Point"}
}