{
  "type": "Feature",
  "properties": {
    "iso:country":"CH",
    "sg:address":"Richtstrasse 19 7000 Chur. Postfach",
    "sg:city":"Chur",
    "sg:classifiers":[
        {
            "category":"Travel",
            "subcategory":"Hotels & Motels",
            "type":"Entertainment"
        }
    ],
    "sg:phone":"+41 81 252 60 60",
    "sg:postcode":"7007",
    "sg:province":"Graubunden",
    "sg:tags":[
        "hotels",
        "mit",
        "restaurant"
    ],
    "wof:name":"Churotel Pyramid Sa",
    "wof:placetype":"venue"
},
  "geometry": {"coordinates":[9.5119009018,46.8458518982],"type":"Point"}
}