{
  "type": "Feature",
  "properties": {
    "iso:country":"CH",
    "sg:address":"Bonnstrasse 53",
    "sg:city":"Guin",
    "sg:orig_category":"Kauf U Verkauf von Immobilien auf eigene Rechnung Vermietung U Verpachtung von eigenen Immobilien",
    "sg:phone":"+41 71 222 39 36",
    "sg:postcode":"3186",
    "sg:province":"Fribourg",
    "wof:name":"K&t Ingenieure Ag",
    "wof:placetype":"venue"
},
  "geometry": {"coordinates":[9.3854389191,47.4268264771],"type":"Point"}
}