{
  "type": "Feature",
  "properties": {
    "iso:country":"CH",
    "sg:address":"Rennweg 30",
    "sg:city":"Herrliberg",
    "sg:orig_category":"Wirtschaftspr\u00fcfung, Steuerberatung U Treuhand",
    "sg:phone":"+41 19151711",
    "sg:postcode":"8704",
    "sg:province":"Z\u00fcrich",
    "wof:name":"P. + K. G\u00fcbeli, Treuhandb\u00fcro",
    "wof:placetype":"venue"
},
  "geometry": {"coordinates":[8.6169090271,47.2857398987],"type":"Point"}
}