{
  "type": "Feature",
  "properties": {
    "iso:country":"CH",
    "sg:address":"Poststrasse 18",
    "sg:city":"St.gallen",
    "sg:orig_category":"Erschliessung von Grundst\u00fccken",
    "sg:postcode":"9000",
    "sg:province":"St. Gallen",
    "wof:name":"Gefa Genossenschaft Eigentum F\u00fcr Alle",
    "wof:placetype":"venue"
},
  "geometry": {"coordinates":[8.9997320175,47.4772071838],"type":"Point"}
}