{
  "type": "Feature",
  "properties": {
    "iso:country":"CH",
    "sg:address":"Lindenplatz 1",
    "sg:city":"Allschwil",
    "sg:orig_category":"Non-Classified Establishments",
    "sg:postcode":"4123",
    "sg:province":"Basel-Landschaft",
    "wof:name":"Dmp Sonne Gmbh",
    "wof:placetype":"venue"
},
  "geometry": {"coordinates":[7.5596418381,47.5576591492],"type":"Point"}
}