{
  "type": "Feature",
  "properties": {
    "iso:country":"CH",
    "sg:address":"Via Verbano 17",
    "sg:city":"Minusio",
    "sg:orig_category":"Handelsvermittlung U Grosshandel",
    "sg:phone":"+41 91 743 00 05",
    "sg:postcode":"6648",
    "sg:province":"Ticino",
    "wof:name":"Romex Sagl",
    "wof:placetype":"venue"
},
  "geometry": {"coordinates":[8.8324956894,46.1810760498],"type":"Point"}
}