{
  "type": "Feature",
  "properties": {
    "iso:country":"CH",
    "sg:address":"Engelgasse 8",
    "sg:city":"St.gallen",
    "sg:orig_category":"Sonstige pers\u00f6nliche Dienstleistungen",
    "sg:phone":"+41 71 220 41 41",
    "sg:postcode":"9000",
    "sg:province":"St. Gallen",
    "wof:name":"Office Outsource By Isenring Nicole",
    "wof:placetype":"venue"
},
  "geometry": {"coordinates":[9.3750257492,47.4262695312],"type":"Point"}
}