{
  "type": "Feature",
  "properties": {
    "iso:country":"CH",
    "sg:address":"Grand-rue 49",
    "sg:city":"Villeneuve",
    "sg:classifiers":[
        {
            "category":"Banks & Credit Unions",
            "subcategory":"Bank",
            "type":"Services"
        }
    ],
    "sg:phone":"+41 21 960 13 32",
    "sg:postcode":"1844",
    "sg:province":"Vaud",
    "wof:name":"Caisse Raiffeisen De Villeneuve",
    "wof:placetype":"venue"
},
  "geometry": {"coordinates":[6.92413,46.396301],"type":"Point"}
}