{
  "type": "Feature",
  "properties": {
    "iso:country":"CH",
    "sg:address":"1874",
    "sg:city":"Champ\u00e9ry",
    "sg:orig_category":"Allgemeinbildende weiterf\u00fchrende Schulen",
    "sg:postcode":"1874",
    "sg:province":"Valais",
    "wof:name":"Ecole Nouvelle Alpina Sa",
    "wof:placetype":"venue"
},
  "geometry": {"coordinates":[6.870686,46.179405],"type":"Point"}
}