{
  "type": "Feature",
  "properties": {
    "iso:country":"CH",
    "sg:address":"Jassbach",
    "sg:city":"Linden",
    "sg:classifiers":[
        {
            "category":"Manufacturing",
            "subcategory":"Motor Vehicles & Parts",
            "type":"Manufacturing & Wholesale Goods"
        }
    ],
    "sg:phone":"+41 31 771 12 63",
    "sg:postcode":"3673",
    "sg:province":"Bern",
    "sg:tags":[
        "engine",
        "machine",
        "engineering",
        "-",
        "mechanical"
    ],
    "wof:name":"Hybag Automationen Ag",
    "wof:placetype":"venue"
},
  "geometry": {"coordinates":[7.7005500793,46.8489990234],"type":"Point"}
}