{
  "type": "Feature",
  "properties": {
    "iso:country":"CH",
    "sg:address":"Rue De Moillebeau 3c",
    "sg:city":"Gen\u00e8ve",
    "sg:classifiers":[
        {
            "category":"Organizations",
            "subcategory":"Political Organization",
            "type":"Services"
        }
    ],
    "sg:phone":"+41 22 734 12 16",
    "sg:postcode":"1209",
    "sg:province":"Gen\u00e8ve",
    "sg:tags":[
        "environmental",
        "energy",
        "consulting"
    ],
    "wof:name":"Axis Gmbh",
    "wof:placetype":"venue"
},
  "geometry": {"coordinates":[6.1279702187,46.221118927],"type":"Point"}
}