{
  "type": "Feature",
  "properties": {
    "iso:country":"CH",
    "sg:address":"Waldeggstr. 32",
    "sg:city":"Rotkreuz",
    "sg:classifiers":[
        {
            "category":"Banks & Credit Unions",
            "subcategory":"Bank",
            "type":"Services"
        }
    ],
    "sg:phone":"+41 41 790 17 28",
    "sg:postcode":"6343",
    "sg:province":"Zug",
    "wof:name":"Raiffeisenbank Risch-rotkreuz",
    "wof:placetype":"venue"
},
  "geometry": {"coordinates":[8.433177,47.140411],"type":"Point"}
}