{
  "type": "Feature",
  "properties": {
    "iso:country":"CH",
    "sg:address":"L\u00fcmpenenstrasse 20",
    "sg:city":"Alpthal",
    "sg:orig_category":"Sanit\u00e4rinstallation",
    "sg:phone":"+41 55 412 41 09",
    "sg:postcode":"8849",
    "sg:province":"Schwyz",
    "wof:name":"Werner Steiner Sanit\u00e4re Anlagen Heizungen",
    "wof:placetype":"venue"
},
  "geometry": {"coordinates":[8.7022666931,47.05052948],"type":"Point"}
}