{
  "type": "Feature",
  "properties": {
    "iso:country":"CH",
    "sg:address":"Industrie Rue De L' 21",
    "sg:city":"Grolley",
    "sg:orig_category":"Tankstellen",
    "sg:postcode":"1772",
    "sg:province":"Fribourg",
    "wof:name":"Riedo G. - Station - Classic",
    "wof:placetype":"venue"
},
  "geometry": {"coordinates":[7.0583848953,46.8314971924],"type":"Point"}
}