{
  "type": "Feature",
  "properties": {
    "iso:country":"CH",
    "sg:address":"Luzernerstrasse 109",
    "sg:city":"Littau",
    "sg:orig_category":"Maler U Glasergewerbe Malerei",
    "sg:phone":"+41 41 250 52 72",
    "sg:postcode":"6014",
    "sg:province":"Luzern",
    "wof:name":"Maler Kantor",
    "wof:placetype":"venue"
},
  "geometry": {"coordinates":[8.2701501846,47.05052948],"type":"Point"}
}