{
  "type": "Feature",
  "properties": {
    "iso:country":"CH",
    "sg:address":"Aliothstrasse 60",
    "sg:city":"M\u00fcnchenstein",
    "sg:orig_category":"Fernmeldedienste",
    "sg:phone":"+41 61 413 13 13",
    "sg:postcode":"4142",
    "sg:province":"Basel-Landschaft",
    "wof:name":"Magnet Com Ag",
    "wof:placetype":"venue"
},
  "geometry": {"coordinates":[7.6139888763,47.5092506409],"type":"Point"}
}