{
  "type": "Feature",
  "properties": {
    "iso:country":"CH",
    "sg:address":"Landstrasse 20",
    "sg:city":"Wettingen",
    "sg:orig_category":"Kosmetikinstitute Sonstige Aktivit\u00e4ten der nicht-\u00e4rztlichen Medizinalberufe",
    "sg:phone":"+41 56 426 44 50",
    "sg:postcode":"5430",
    "sg:province":"Aargau",
    "wof:name":"Vitamed Schneider W.",
    "wof:placetype":"venue"
},
  "geometry": {"coordinates":[8.3187484741,47.4692420959],"type":"Point"}
}