{
  "type": "Feature",
  "properties": {
    "iso:country":"CH",
    "sg:address":"R\u00fctistrasse 6",
    "sg:city":"Adliswil",
    "sg:orig_category":"Fotografische Ateliers",
    "sg:phone":"+41 17103806",
    "sg:postcode":"8134",
    "sg:province":"Z\u00fcrich",
    "wof:name":"Leonard Zubler Fotografisches Atelier",
    "wof:placetype":"venue"
},
  "geometry": {"coordinates":[8.5259714127,47.3047981262],"type":"Point"}
}