{
  "type": "Feature",
  "properties": {
    "iso:country":"CH",
    "sg:address":"Rue De Livron 19bis 1217 Meyrin. Postfach",
    "sg:city":"Meyrin",
    "sg:orig_category":"Tankstellen",
    "sg:phone":"+41 56 470 38 12",
    "sg:postcode":"1217",
    "sg:province":"Gen\u00e8ve",
    "wof:name":"O. Vonlanthen Gmbh Shell-tankstelle",
    "wof:placetype":"venue"
},
  "geometry": {"coordinates":[8.2828149796,47.4562072754],"type":"Point"}
}