{
  "type": "Feature",
  "properties": {
    "iso:country":"CH",
    "sg:address":"Poststrasse 24",
    "sg:city":"Sulgen",
    "sg:orig_category":"Institutionen f\u00fcr Suchtkranke Institutionen f\u00fcr psychosoziale F\u00e4lle",
    "sg:phone":"+41 71 642 38 65",
    "sg:postcode":"8583",
    "sg:province":"Thurgau",
    "wof:name":"Haus Zur Quelle",
    "wof:placetype":"venue"
},
  "geometry": {"coordinates":[9.1842212677,47.543006897],"type":"Point"}
}