{
  "type": "Feature",
  "properties": {
    "iso:country":"CH",
    "sg:address":"B\u00fcndtenweg 13b",
    "sg:city":"Maisprach",
    "sg:orig_category":"Grosshandel mit Schreibwaren, B\u00fcchern U Zeitungen",
    "sg:phone":"+41 79 644 46 32",
    "sg:postcode":"4464",
    "sg:province":"Basel-Landschaft",
    "wof:name":"Ren\u00e9 Andr\u00e9 Verlagsvertretungen",
    "wof:placetype":"venue"
},
  "geometry": {"coordinates":[7.8488640785,47.5246696472],"type":"Point"}
}