{
  "type": "Feature",
  "properties": {
    "iso:country":"CH",
    "sg:address":"G\u00fcterstrasse 138",
    "sg:city":"Basel",
    "sg:orig_category":"Fast-Foodrestaurants",
    "sg:phone":"+41 61 361 48 79",
    "sg:postcode":"4053",
    "sg:province":"Basel-Stadt",
    "wof:name":"Typisch Thai Take Away",
    "wof:placetype":"venue"
},
  "geometry": {"coordinates":[7.5892128944,47.544719696],"type":"Point"}
}