{
  "type": "Feature",
  "properties": {
    "iso:country":"CH",
    "sg:address":"Village Chemin Du 15 1012 Lausanne. Postfach",
    "sg:city":"Lausanne",
    "sg:orig_category":"Handel mit Motorr\u00e4dern, Teilen U Zubeh\u00f6r Instandhaltung U Reparatur von Motorr\u00e4dern",
    "sg:postcode":"1003",
    "sg:province":"Vaud",
    "wof:name":"Cycles Et Motos, Baudet Andr\u00e9. Cycles Et Motos; Comm., R\u00e9paration.",
    "wof:placetype":"venue"
},
  "geometry": {"coordinates":[6.6568899155,46.526309967],"type":"Point"}
}