{
  "type": "Feature",
  "properties": {
    "iso:country":"CH",
    "sg:address":"6579",
    "sg:city":"Piazzogna",
    "sg:classifiers":[
        {
            "category":"Restaurant",
            "type":"Food & Drink"
        }
    ],
    "sg:phone":"+41 91 795 22 87",
    "sg:postcode":"6579",
    "sg:province":"Ticino",
    "wof:name":"Osteria Tamaro",
    "wof:placetype":"venue"
},
  "geometry": {"coordinates":[8.8294000626,46.1273612976],"type":"Point"}
}