{
  "type": "Feature",
  "properties": {
    "iso:country":"CH",
    "sg:address":"Hauptstrasse 32",
    "sg:city":"Binningen",
    "sg:orig_category":"Bestattungswesen",
    "sg:phone":"+41 61 281 22 32",
    "sg:postcode":"4102",
    "sg:province":"Basel-Landschaft",
    "wof:name":"Bestattungen Hans Heinis Ag",
    "wof:placetype":"venue"
},
  "geometry": {"coordinates":[7.574336,47.542229],"type":"Point"}
}