{
  "type": "Feature",
  "properties": {
    "iso:country":"CH",
    "sg:address":"Heuberg 6",
    "sg:city":"Basel",
    "sg:orig_category":"Bibliotheken U Archive Interessenvertretungen",
    "sg:phone":"+41 17166060",
    "sg:postcode":"4051",
    "sg:province":"Basel-Stadt",
    "wof:name":"Spital Sanitas",
    "wof:placetype":"venue"
},
  "geometry": {"coordinates":[8.535985,47.320427],"type":"Point"}
}