{
  "type": "Feature",
  "properties": {
    "iso:country":"CH",
    "sg:address":"Seidengasse 51",
    "sg:city":"Obermeilen",
    "sg:orig_category":"Innendekorationsateliers",
    "sg:phone":"+41 19230443",
    "sg:postcode":"8706",
    "sg:province":"Z\u00fcrich",
    "wof:name":"Peter Strausak Innendekoration",
    "wof:placetype":"venue"
},
  "geometry": {"coordinates":[8.6553602219,47.2670631409],"type":"Point"}
}