{
  "type": "Feature",
  "properties": {
    "iso:country":"CH",
    "sg:address":"B\u00fcnishoferstrasse 214",
    "sg:city":"Meilen",
    "sg:orig_category":"Sonstiger Grosshandel",
    "sg:postcode":"8706",
    "sg:province":"Z\u00fcrich",
    "wof:name":"Strickler R.k.",
    "wof:placetype":"venue"
},
  "geometry": {"coordinates":[8.6281728745,47.2834205627],"type":"Point"}
}