{
  "type": "Feature",
  "properties": {
    "iso:country":"CH",
    "sg:address":"Gewerbestrasse 5",
    "sg:city":"Cham",
    "sg:orig_category":"Unternehmensberatung",
    "sg:phone":"+41 90572020",
    "sg:postcode":"6330",
    "sg:province":"Zug",
    "wof:name":"Mancon Ag",
    "wof:placetype":"venue"
},
  "geometry": {"coordinates":[8.4734659195,47.1885452271],"type":"Point"}
}