{
  "type": "Feature",
  "properties": {
    "iso:country":"CH",
    "sg:address":"Krummeneichstrasse 17 4133 Pratteln. Postfach",
    "sg:city":"Pratteln",
    "sg:orig_category":"RESTAURANTS: TEA-ROOMS",
    "sg:postcode":"4133",
    "sg:province":"Basel-Landschaft",
    "wof:name":"G.t.c. Ag",
    "wof:placetype":"venue"
},
  "geometry": {"coordinates":[7.7036128044,47.5237503052],"type":"Point"}
}