{
  "type": "Feature",
  "properties": {
    "iso:country":"CH",
    "sg:address":"Wydimatt",
    "sg:city":"Bigenthal",
    "sg:orig_category":"Primarschulen",
    "sg:phone":"+41 34 461 25 97",
    "sg:postcode":"3513",
    "sg:province":"Bern",
    "wof:name":"Primarschule",
    "wof:placetype":"venue"
},
  "geometry": {"coordinates":[7.6249351501,46.9669532776],"type":"Point"}
}