{
  "type": "Feature",
  "properties": {
    "iso:country":"CH",
    "sg:address":"Zentralplatz 3",
    "sg:city":"Mellingen",
    "sg:orig_category":"Detailhandel mit Radio U Fernsehger\u00e4ten Detailhandel mit elektrischen Haushalts-,Radio U Fernsehger\u00e4",
    "sg:postcode":"5507",
    "sg:province":"Aargau",
    "wof:name":"Karl Pabst",
    "wof:placetype":"venue"
},
  "geometry": {"coordinates":[8.2745037079,47.419506073],"type":"Point"}
}