{
  "type": "Feature",
  "properties": {
    "iso:country":"CH",
    "sg:address":"6995 Molinazzo. Postfach Caselle Postale 231",
    "sg:city":"Lugano",
    "sg:orig_category":"Herstellung von Kunststoffwaren Herstellung von Mess U Kontrollinstrumenten U vorrichtungen",
    "sg:phone":"+41 91 608 19 51",
    "sg:postcode":"6903",
    "sg:province":"Ticino",
    "wof:name":"Repo Sa",
    "wof:placetype":"venue"
},
  "geometry": {"coordinates":[8.8205404282,45.990020752],"type":"Point"}
}