{
  "type": "Feature",
  "properties": {
    "iso:country":"CH",
    "sg:address":"Im Tobel 17a",
    "sg:city":"Feldmeilen",
    "sg:orig_category":"Kosmetikinstitute",
    "sg:phone":"+41 19233069",
    "sg:postcode":"8706",
    "sg:province":"Z\u00fcrich",
    "wof:name":"Ruth Koller Kosmetikinstitut Charmante",
    "wof:placetype":"venue"
},
  "geometry": {"coordinates":[8.618642807,47.2828216553],"type":"Point"}
}