{
  "type": "Feature",
  "properties": {
    "iso:country":"CH",
    "sg:address":"Aspstrasse 6",
    "sg:city":"Spreitenbach",
    "sg:orig_category":"Handel mit Automobilteilen U Zubeh\u00f6r",
    "sg:phone":"+41 56 402 00 40",
    "sg:postcode":"8957",
    "sg:province":"Aargau",
    "wof:name":"Maxspeed Gmbh",
    "wof:placetype":"venue"
},
  "geometry": {"coordinates":[8.3815469742,47.4151535034],"type":"Point"}
}