{
  "type": "Feature",
  "properties": {
    "iso:country":"CH",
    "sg:address":"Anshelmstrasse 18",
    "sg:city":"Bern",
    "sg:orig_category":"Detailhandel mit Brot, Back U S\u00fcsswaren",
    "sg:phone":"+41 31 351 82 80",
    "sg:postcode":"3005",
    "sg:province":"Bern",
    "wof:name":"Andreas & Ines R\u00f6thlisberger B\u00e4ckerei-konditorei",
    "wof:placetype":"venue"
},
  "geometry": {"coordinates":[7.448109,46.938862],"type":"Point"}
}