{
  "type": "Feature",
  "properties": {
    "iso:country":"CH",
    "sg:address":"6152",
    "sg:city":"H\u00fcswil",
    "sg:orig_category":"Sportvereine Flug Aero-Club",
    "sg:postcode":"6152",
    "sg:province":"Luzern",
    "wof:name":"Ae.c.s.modellfluggruppe H\u00fcswil",
    "wof:placetype":"venue"
},
  "geometry": {"coordinates":[7.90625,47.1237602234],"type":"Point"}
}