{
  "type": "Feature",
  "properties": {
    "iso:country":"CH",
    "sg:address":"Casa Parasana",
    "sg:city":"Gordevio",
    "sg:classifiers":[
        {
            "category":"Home & Garden",
            "subcategory":"Household Appliances",
            "type":"Retail Goods"
        }
    ],
    "sg:phone":"+41 91 753 24 44",
    "sg:postcode":"6672",
    "sg:province":"Ticino",
    "sg:tags":[
        "stove",
        "chimney"
    ],
    "wof:name":"R\u00f6thlisberger Camini Sagl",
    "wof:placetype":"venue"
},
  "geometry": {"coordinates":[8.742335,46.225155],"type":"Point"}
}