{
  "type": "Feature",
  "properties": {
    "iso:country":"CH",
    "sg:address":"Innere G\u00fcterstrasse 2",
    "sg:city":"Zug",
    "sg:orig_category":"Fernmeldedienste",
    "sg:phone":"+41 21 921 66 00",
    "sg:postcode":"6300",
    "sg:province":"Zug",
    "wof:name":"Ici T\u00e9l\u00e9vision Sa",
    "wof:placetype":"venue"
},
  "geometry": {"coordinates":[5.1808700562,45.8973388672],"type":"Point"}
}