{
  "type": "Feature",
  "properties": {
    "iso:country":"CH",
    "sg:address":"Dorfstrasse 20",
    "sg:city":"Itingen",
    "sg:orig_category":"Bauschreinerei Herstellung von Konstruktionsteilen, Fertigbauteilen U Ausbauelementen aus Holz",
    "sg:phone":"+41 61 971 47 97",
    "sg:postcode":"4452",
    "sg:province":"Basel-Landschaft",
    "wof:name":"Fredi Buser",
    "wof:placetype":"venue"
},
  "geometry": {"coordinates":[7.784744,47.465324],"type":"Point"}
}