{
  "type": "Feature",
  "properties": {
    "iso:country":"CH",
    "sg:address":"Bahnhofstrasse 10",
    "sg:city":"Horgen",
    "sg:orig_category":"Interessenvertretungen",
    "sg:phone":"+41 41 870 51 88",
    "sg:postcode":"8810",
    "sg:province":"Z\u00fcrich",
    "wof:name":"Sch\u00f6n Alfred-stiftung.",
    "wof:placetype":"venue"
},
  "geometry": {"coordinates":[8.6375150681,46.8814125061],"type":"Point"}
}