{
  "type": "Feature",
  "properties": {
    "iso:country":"CH",
    "sg:address":"Anh\u00f6heweg 8 8626 Ottikon. Postfach",
    "sg:city":"Ottikon",
    "sg:orig_category":"Unternehmensberatung",
    "sg:postcode":"8626",
    "sg:province":"Z\u00fcrich",
    "wof:name":"Schugg Consulting",
    "wof:placetype":"venue"
},
  "geometry": {"coordinates":[8.7794399261,47.2937316895],"type":"Point"}
}