{
  "type": "Feature",
  "properties": {
    "iso:country":"CH",
    "sg:address":"Hinterburgstrasse 6345 Neuheim. Postfach 11",
    "sg:city":"Neuheim",
    "sg:orig_category":"Giessereiindustrie Herstellung von Metallerzeugnissen ohne Maschinenbau",
    "sg:phone":"+41 18440340",
    "sg:postcode":"6345",
    "sg:province":"Zug",
    "wof:name":"Blockmetall Ag",
    "wof:placetype":"venue"
},
  "geometry": {"coordinates":[8.4380941391,47.4535331726],"type":"Point"}
}