{
  "type": "Feature",
  "properties": {
    "iso:country":"CH",
    "sg:address":"Del\u00e9mont Route De",
    "sg:city":"Soyhi\u00e8res",
    "sg:orig_category":"Tankstellen",
    "sg:postcode":"2805",
    "sg:province":"Jura",
    "wof:name":"Alimentation Bellerive S\u00e0rl Magasin Et Station D'essence Etc",
    "wof:placetype":"venue"
},
  "geometry": {"coordinates":[7.369204998,47.3905067444],"type":"Point"}
}