{
  "type": "Feature",
  "properties": {
    "iso:country":"CH",
    "sg:address":"Toggenburgerstrasse 3",
    "sg:city":"Ganterschwil",
    "sg:orig_category":"Autogaragen",
    "sg:phone":"+41 71 983 23 93",
    "sg:postcode":"9608",
    "sg:province":"St. Gallen",
    "wof:name":"Bernhard R\u00fcegg Garage",
    "wof:placetype":"venue"
},
  "geometry": {"coordinates":[9.089221,47.380676],"type":"Point"}
}