{
  "type": "Feature",
  "properties": {
    "iso:country":"CH",
    "sg:address":"Champ Faudin 44",
    "sg:city":"Montagne-moutier",
    "sg:orig_category":"Herstellung von Seifen, Wasch U Reinigungsmitteln",
    "sg:phone":"+41 32 493 19 44",
    "sg:postcode":"2740",
    "sg:province":"Bern",
    "wof:name":"Messerli, Mme Alice, Milimo",
    "wof:placetype":"venue"
},
  "geometry": {"coordinates":[7.3746762276,47.2764358521],"type":"Point"}
}