{
  "type": "Feature",
  "properties": {
    "iso:country":"CH",
    "sg:address":"Baarerstrasse 8 6300 Zug. Postfach",
    "sg:city":"Zug",
    "sg:orig_category":"Unclassifiable Establishments",
    "sg:phone":"+41 19335450",
    "sg:postcode":"6300",
    "sg:province":"Zug",
    "wof:name":"Global Wood Technologies Ag",
    "wof:placetype":"venue"
},
  "geometry": {"coordinates":[8.7868356705,47.323387146],"type":"Point"}
}