{
  "type": "Feature",
  "properties": {
    "iso:country":"CH",
    "sg:address":"Ringstrasse 25",
    "sg:city":"Langenthal",
    "sg:orig_category":"Notariate",
    "sg:phone":"+41 79 401 10 53",
    "sg:postcode":"4900",
    "sg:province":"Bern",
    "wof:name":"Etienne Favre Etude D'avocat & Notaire",
    "wof:placetype":"venue"
},
  "geometry": {"coordinates":[6.9937758446,46.2955665588],"type":"Point"}
}