{
  "type": "Feature",
  "properties": {
    "iso:country":"CH",
    "sg:address":"Alter Seeweg 6b",
    "sg:city":"Maur",
    "sg:orig_category":"D\u00e4mmung gegen K\u00e4lte, W\u00e4rme, Schall U Ersch\u00fctterung",
    "sg:postcode":"8124",
    "sg:province":"Z\u00fcrich",
    "wof:name":"Growabau Ag",
    "wof:placetype":"venue"
},
  "geometry": {"coordinates":[8.6732187271,47.3393287659],"type":"Point"}
}