{
  "type": "Feature",
  "properties": {
    "iso:country":"CH",
    "sg:address":"Pilgerweg 97 8802 Kilchberg Zh. Postfach",
    "sg:city":"Z\u00fcrich",
    "sg:orig_category":"Hardwareberatung",
    "sg:postcode":"8021",
    "sg:province":"Z\u00fcrich",
    "wof:name":"Ebn - Communications-installationen Ebn\u00f6ther",
    "wof:placetype":"venue"
},
  "geometry": {"coordinates":[8.5538930893,47.3154525757],"type":"Point"}
}