{
  "type": "Feature",
  "properties": {
    "iso:country":"CH",
    "sg:address":"Rue De La Gare 6 1030 Bussigny-lausanne Case Postale 315",
    "sg:city":"Bussigny-lausanne",
    "sg:orig_category":"G\u00fcterbef\u00f6rderung im Strassenverkehr Reiseb\u00fcros U Reiseveranstalter",
    "sg:phone":"+41 21 702 31 61",
    "sg:postcode":"1030",
    "sg:province":"Vaud",
    "wof:name":"Mega Voyages, Anstett Christian",
    "wof:placetype":"venue"
},
  "geometry": {"coordinates":[6.5531392097,46.5483703613],"type":"Point"}
}