{
  "type": "Feature",
  "properties": {
    "iso:country":"CH",
    "sg:address":"Bubenbergstrasse 30",
    "sg:city":"Thun",
    "sg:orig_category":"Elektroinstallation",
    "sg:phone":"+41 33 336 65 27",
    "sg:postcode":"3604",
    "sg:province":"Bern",
    "wof:name":"Peter Christ Kommunikations-inst.-service",
    "wof:placetype":"venue"
},
  "geometry": {"coordinates":[7.6162748337,46.7346343994],"type":"Point"}
}