{
  "type": "Feature",
  "properties": {
    "iso:country":"CH",
    "sg:address":"Aspstrasse 6",
    "sg:city":"Spreitenbach",
    "sg:orig_category":"Malerei",
    "sg:phone":"+41 56 401 60 60",
    "sg:postcode":"8957",
    "sg:province":"Aargau",
    "wof:name":"Dante Quirici Malergesch\u00e4ft",
    "wof:placetype":"venue"
},
  "geometry": {"coordinates":[8.3815469742,47.4151535034],"type":"Point"}
}