{
  "type": "Feature",
  "properties": {
    "iso:country":"CH",
    "sg:address":"Dorfstrasse 15",
    "sg:city":"Urdorf",
    "sg:orig_category":"Sanit\u00e4r, Heizungs U L\u00fcftungsinstallation Schmieden",
    "sg:phone":"+41 17343159",
    "sg:postcode":"8902",
    "sg:province":"Z\u00fcrich",
    "wof:name":"Ryser Jakob & Heidi, Heizungen",
    "wof:placetype":"venue"
},
  "geometry": {"coordinates":[8.4170360565,47.3902053833],"type":"Point"}
}