{
  "type": "Feature",
  "properties": {
    "iso:country":"CH",
    "sg:address":"Weissm\u00fchlestrasse 11 8840 Einsiedeln. Postfach",
    "sg:city":"Einsiedeln",
    "sg:orig_category":"Fussboden, Fliesen U Plattenlegerei, Tapeziererei",
    "sg:postcode":"8840",
    "sg:province":"Schwyz",
    "wof:name":"Gamboni L. Plattenlegergesch\u00e4ft",
    "wof:placetype":"venue"
},
  "geometry": {"coordinates":[8.7440738678,47.1336402893],"type":"Point"}
}