{
  "type": "Feature",
  "properties": {
    "iso:country":"CH",
    "sg:address":"Spitzackerweg 20",
    "sg:city":"Niederscherli",
    "sg:orig_category":"Sportvereine Turnen Vereine Damen",
    "sg:postcode":"3145",
    "sg:province":"Bern",
    "wof:name":"Damenturnver.stv Niederscherli",
    "wof:placetype":"venue"
},
  "geometry": {"coordinates":[7.3881320953,46.8867721558],"type":"Point"}
}