{
  "type": "Feature",
  "properties": {
    "iso:country":"CH",
    "sg:address":"Waldmannstrasse 68",
    "sg:city":"Bern",
    "sg:orig_category":"Bau U Wohngenossenschaften",
    "sg:phone":"+41 31 996 20 20",
    "sg:postcode":"3027",
    "sg:province":"Bern",
    "wof:name":"Kio Bau-& Wohngenoss.bern",
    "wof:placetype":"venue"
},
  "geometry": {"coordinates":[7.383771,46.949059],"type":"Point"}
}