{
  "type": "Feature",
  "properties": {
    "iso:country":"CH",
    "sg:address":"Oberdorfstrasse 2",
    "sg:city":"Riehen",
    "sg:orig_category":"RESTAURANTS: TEA-ROOMS",
    "sg:phone":"+41 61 641 11 39",
    "sg:postcode":"4125",
    "sg:province":"Basel-Stadt",
    "wof:name":"Restaurant S\u00e4ngerst\u00fcbli, Kasa B.",
    "wof:placetype":"venue"
},
  "geometry": {"coordinates":[7.6532402039,47.5867424011],"type":"Point"}
}