{
  "type": "Feature",
  "properties": {
    "addr:full":"Blegistrasse 13 Baar Zug 6340",
    "addr:housenumber":"13",
    "addr:postcode":"6340",
    "addr:street":"Blegistrasse;Zug",
    "iso:country":"CH",
    "sg:address":"Blegistrasse 13",
    "sg:city":"Baar",
    "sg:classifiers":[
        {
            "category":"Shopping",
            "subcategory":"Stationery & Office Supplies",
            "type":"Retail Goods"
        }
    ],
    "sg:phone":"+41 41 766 82 82",
    "sg:postcode":"6340",
    "sg:province":"Zug",
    "sg:tags":[
        "cardboard"
    ],
    "wof:name":"M-real Schweiz Ag",
    "wof:placetype":"venue"
},
  "geometry": {"coordinates":[8.569244,47.215687],"type":"Point"}
}