{
  "type": "Feature",
  "properties": {
    "iso:country":"CH",
    "sg:address":"3919",
    "sg:city":"Blatten(l\u00f6tschen)",
    "sg:orig_category":"Interessenvertretungen",
    "sg:phone":"+41 71 994 18 87",
    "sg:postcode":"3919",
    "sg:province":"Valais",
    "wof:name":"Stiftung Blaukreuzferienheim Heimetli",
    "wof:placetype":"venue"
},
  "geometry": {"coordinates":[9.1993598938,47.2241897583],"type":"Point"}
}