{
  "type": "Feature",
  "properties": {
    "addr:full":"R\u00fctiweg 5 Derendingen Solothurn 4552",
    "addr:housenumber":"5",
    "addr:postcode":"4552",
    "addr:street":"Ruetiweg",
    "iso:country":"CH",
    "sg:address":"R\u00fctiweg 5",
    "sg:city":"Derendingen",
    "sg:orig_category":"Bestattungswesen",
    "sg:phone":"+41 32 682 21 12",
    "sg:postcode":"4552",
    "sg:province":"Solothurn",
    "wof:name":"Stampfli Bestattungen Ag",
    "wof:placetype":"venue"
},
  "geometry": {"coordinates":[7.593549,47.200802],"type":"Point"}
}