{
  "type": "Feature",
  "properties": {
    "iso:country":"CH",
    "sg:address":"Industriestrasse 3 8610 Uster. Postfach",
    "sg:city":"Uster",
    "sg:orig_category":"Grosshandel mit B\u00fcromaschinen U einrichtungen Herstellung von Metallerzeugnissen ohne Maschinenbau",
    "sg:phone":"+41 79 227 45 78",
    "sg:postcode":"8610",
    "sg:province":"Z\u00fcrich",
    "wof:name":"M. Willi Ag",
    "wof:placetype":"venue"
},
  "geometry": {"coordinates":[8.0635585785,47.3991699219],"type":"Point"}
}