{
  "type": "Feature",
  "properties": {
    "iso:country":"CH",
    "sg:address":"Schachenstrasse 11",
    "sg:city":"Ebikon",
    "sg:orig_category":"Primarschulen Vorschulen, Kinderg\u00e4rten",
    "sg:phone":"+41 41 420 64 32",
    "sg:postcode":"6030",
    "sg:province":"Luzern",
    "wof:name":"Aktiengesellschaft Vormals Rey Schule",
    "wof:placetype":"venue"
},
  "geometry": {"coordinates":[8.3176803589,47.0680046082],"type":"Point"}
}