{
  "type": "Feature",
  "properties": {
    "iso:country":"CH",
    "sg:address":"Hauptstr. 125 5742 K\u00f6lliken. Postfach",
    "sg:city":"K\u00f6lliken",
    "sg:orig_category":"Mechanik",
    "sg:phone":"+41 62 723 99 11",
    "sg:postcode":"5742",
    "sg:province":"Aargau",
    "wof:name":"Heinz M\u00f6ri",
    "wof:placetype":"venue"
},
  "geometry": {"coordinates":[8.0233335495,47.3294296265],"type":"Point"}
}