{
  "type": "Feature",
  "properties": {
    "iso:country":"CH",
    "sg:address":"L\u00f6berenstrasse 8",
    "sg:city":"Zug",
    "sg:orig_category":"Verlegen von Fliesen U Platten",
    "sg:phone":"+41 27 761 18 07",
    "sg:postcode":"6300",
    "sg:province":"Zug",
    "wof:name":"Guy Bochatay Chemin\u00e9es De Salon & Carrelage",
    "wof:placetype":"venue"
},
  "geometry": {"coordinates":[7.020275116,46.1201057434],"type":"Point"}
}