{
  "type": "Feature",
  "properties": {
    "iso:country":"CH",
    "sg:address":"Bahnhof",
    "sg:city":"Aathal-seegr\u00e4ben",
    "sg:orig_category":"Ingenieurb\u00fcros Geologie Ingenieurb\u00fcros Umwelttechnik and \u00d6kologie",
    "sg:phone":"+41 19335360",
    "sg:postcode":"8607",
    "sg:province":"Z\u00fcrich",
    "wof:name":"Wanner Ag Geologie & Umweltfragen",
    "wof:placetype":"venue"
},
  "geometry": {"coordinates":[8.7684850693,47.3358840942],"type":"Point"}
}