{
  "type": "Feature",
  "properties": {
    "iso:country":"CH",
    "sg:address":"Pilgerweg 29 8803 R\u00fcschlikon. Postfach",
    "sg:city":"R\u00fcschlikon",
    "sg:orig_category":"Landesverteidigung, Sozialversicherung \u00d6ffentliche Verwaltung",
    "sg:phone":"+41 31 809 02 30",
    "sg:postcode":"8803",
    "sg:province":"Z\u00fcrich",
    "wof:name":"Zivilschutzstelle R\u00fcti Bei Riggisberg",
    "wof:placetype":"venue"
},
  "geometry": {"coordinates":[7.4485859871,46.7816314697],"type":"Point"}
}