{
  "type": "Feature",
  "properties": {
    "iso:country":"CH",
    "sg:address":"Z\u00fcnackerstrasse 372",
    "sg:city":"Oberbuchsiten",
    "sg:orig_category":"Sportvereine Velo Rad-& Motorfahrer-Bund SRB",
    "sg:postcode":"4625",
    "sg:province":"Solothurn",
    "wof:name":"Velo-moto-club Oberbuchsiten",
    "wof:placetype":"venue"
},
  "geometry": {"coordinates":[7.7718839645,47.3074302673],"type":"Point"}
}