{
  "type": "Feature",
  "properties": {
    "iso:country":"CH",
    "sg:address":"Sonnenh\u00fcgelstrasse 51",
    "sg:city":"Arbon",
    "sg:classifiers":[
        {
            "category":"Bars & Pubs",
            "type":"Food & Drink"
        }
    ],
    "sg:postcode":"9320",
    "sg:province":"Thurgau",
    "wof:name":"Artigel Italienische Spezialit\u00e4ten De Giorgi D.",
    "wof:placetype":"venue"
},
  "geometry": {"coordinates":[9.424448,47.51556],"type":"Point"}
}