{
  "type": "Feature",
  "properties": {
    "iso:country":"CH",
    "sg:address":"Gurzelenstrasse 14 4512 Bellach. Postfach 416",
    "sg:city":"Bellach",
    "sg:orig_category":"Herstellung von Metallerzeugnissen ohne Maschinenbau Herstellung von sonstigen Maschinen f\u00fcr unspezi",
    "sg:phone":"+41 71 393 30 22",
    "sg:postcode":"4512",
    "sg:province":"Solothurn",
    "wof:name":"Lenz-apparatebau Ag",
    "wof:placetype":"venue"
},
  "geometry": {"coordinates":[9.2117004395,47.4424667358],"type":"Point"}
}