{
  "type": "Feature",
  "properties": {
    "iso:country":"CH",
    "sg:address":"Hauptstrasse 92",
    "sg:city":"Kreuzlingen",
    "sg:orig_category":"Gartenbau Interessenvertretungen",
    "sg:phone":"+41 79 352 40 15",
    "sg:postcode":"8280",
    "sg:province":"Thurgau",
    "wof:name":"Natur Konkret Guido Leutenegger",
    "wof:placetype":"venue"
},
  "geometry": {"coordinates":[9.1774091721,47.6457328796],"type":"Point"}
}