{
  "type": "Feature",
  "properties": {
    "iso:country":"CH",
    "sg:address":"Plantaz Chemin Des 34 1260 Nyon. Postfach",
    "sg:city":"Nyon",
    "sg:orig_category":"Sonstige mit der Informatik verbundene T\u00e4tigkeiten",
    "sg:postcode":"1260",
    "sg:province":"Vaud",
    "wof:name":"Sattar Aamer Services Informatique; Conseils Et Programmation",
    "wof:placetype":"venue"
},
  "geometry": {"coordinates":[6.2390799522,46.3823661804],"type":"Point"}
}