{
  "type": "Feature",
  "properties": {
    "iso:country":"CH",
    "sg:address":"8213",
    "sg:city":"Neunkirch",
    "sg:orig_category":"Schulpflegen",
    "sg:phone":"+41 52 681 13 02",
    "sg:postcode":"8213",
    "sg:province":"Schaffhausen",
    "wof:name":"Schulrat Der Gemeinde Neunkirch",
    "wof:placetype":"venue"
},
  "geometry": {"coordinates":[8.4984369278,47.6893463135],"type":"Point"}
}