{
  "type": "Feature",
  "properties": {
    "iso:country":"CH",
    "sg:address":"S\u00e4genstrasse 7000 Chur. Postfach",
    "sg:city":"Chur",
    "sg:orig_category":"Sonstige mit der Informatik verbundene T\u00e4tigkeiten",
    "sg:postcode":"7000",
    "sg:province":"Graubunden",
    "wof:name":"Exigo Informationstechnologie; Dienstleistungen",
    "wof:placetype":"venue"
},
  "geometry": {"coordinates":[9.5255203247,46.8481750488],"type":"Point"}
}