{
  "type": "Feature",
  "properties": {
    "iso:country":"CH",
    "sg:address":"Schwertstrasse 9",
    "sg:city":"Schaffhausen",
    "sg:orig_category":"Sonstige pers\u00f6nliche Dienstleistungen",
    "sg:postcode":"8202",
    "sg:province":"Schaffhausen",
    "wof:name":"T\u00e4towierungs Atelier Pfister",
    "wof:placetype":"venue"
},
  "geometry": {"coordinates":[7.1084527969,46.9252319336],"type":"Point"}
}