{
  "type": "Feature",
  "properties": {
    "iso:country":"CH",
    "sg:address":"Grosszelgstrasse 5436 W\u00fcrenlos. Postfach 83",
    "sg:city":"W\u00fcrenlos",
    "sg:orig_category":"Grosshandel mit sonstigen Maschinen U Ausr\u00fcstungen f\u00fcr Industrie, Handel U Schiffahrt",
    "sg:postcode":"5436",
    "sg:province":"Aargau",
    "wof:name":"Ak-handels Ag",
    "wof:placetype":"venue"
},
  "geometry": {"coordinates":[8.3578014374,47.4452819824],"type":"Point"}
}