{
  "type": "Feature",
  "properties": {
    "iso:country":"CH",
    "sg:address":"Baumgarten",
    "sg:city":"Heimenschwand",
    "sg:orig_category":"Herstellung von Reiseartikeln, Leder U Sattlerwaren",
    "sg:phone":"+41 33 453 14 46",
    "sg:postcode":"3615",
    "sg:province":"Bern",
    "wof:name":"Werner J\u00f6hr Sattlerei",
    "wof:placetype":"venue"
},
  "geometry": {"coordinates":[7.6969451904,46.8286209106],"type":"Point"}
}