{
  "type": "Feature",
  "properties": {
    "iso:country":"CH",
    "sg:address":"Rengglochstrasse 25",
    "sg:city":"Obernau",
    "sg:orig_category":"Herstellung von Elektrizit\u00e4tsverteilungs U schalteinrichtungen Herstellung von elektronischen Bauele",
    "sg:phone":"+41 41 320 41 83",
    "sg:postcode":"6012",
    "sg:province":"Luzern",
    "wof:name":"Berger P. Elektro-tableaux",
    "wof:placetype":"venue"
},
  "geometry": {"coordinates":[8.255030632,47.0333824158],"type":"Point"}
}