{
  "type": "Feature",
  "properties": {
    "iso:country":"CH",
    "sg:address":"Dorfstrasse",
    "sg:city":"Z\u00fcberwangen",
    "sg:orig_category":"Sanit\u00e4r U Heizungsinstallation Sanit\u00e4rinstallation",
    "sg:phone":"+41 71 944 17 70",
    "sg:postcode":"9523",
    "sg:province":"St. Gallen",
    "wof:name":"Marcel L\u00e4ber Heizungen & Sanit\u00e4ranlagen",
    "wof:placetype":"venue"
},
  "geometry": {"coordinates":[9.0906352997,47.4664611816],"type":"Point"}
}