{
  "type": "Feature",
  "properties": {
    "iso:country":"CH",
    "sg:address":"Rue De L'industrie 18",
    "sg:city":"Ros\u00e9",
    "sg:orig_category":"Allgemeiner Hoch U Tiefbau",
    "sg:phone":"+41 26 660 07 67",
    "sg:postcode":"1754",
    "sg:province":"Fribourg",
    "wof:name":"Villalu Sa",
    "wof:placetype":"venue"
},
  "geometry": {"coordinates":[7.057565,46.7812],"type":"Point"}
}