{
  "type": "Feature",
  "properties": {
    "iso:country":"CH",
    "sg:address":"Schulhausstrasse 1",
    "sg:city":"Horw",
    "sg:orig_category":"Non-Classified Establishments",
    "sg:postcode":"6048",
    "sg:province":"Luzern",
    "wof:name":"H. Bollmann, Gartenbau, Weberei",
    "wof:placetype":"venue"
},
  "geometry": {"coordinates":[9.0147800446,47.4218406677],"type":"Point"}
}