{
  "type": "Feature",
  "properties": {
    "iso:country":"CH",
    "sg:address":"Haini-rennhasstrasse 9",
    "sg:city":"Goldach",
    "sg:orig_category":"Vermietung U Verpachtung von eigenen Immobilien Verwaltung von Immobilien",
    "sg:phone":"+41 71 841 05 35",
    "sg:postcode":"9403",
    "sg:province":"St. Gallen",
    "wof:name":"Tilia Ag",
    "wof:placetype":"venue"
},
  "geometry": {"coordinates":[9.4627752304,47.4781646729],"type":"Point"}
}