{
  "type": "Feature",
  "properties": {
    "iso:country":"CH",
    "sg:address":"Promenade St-antoine 20 1200 Genf. Postfach",
    "sg:city":"Gen\u00e8ve",
    "sg:orig_category":"Erschliessung von Grundst\u00fccken",
    "sg:postcode":"1204",
    "sg:province":"Gen\u00e8ve",
    "wof:name":"Association Nicolas Bogueret",
    "wof:placetype":"venue"
},
  "geometry": {"coordinates":[6.1497020721,46.1990852356],"type":"Point"}
}