{
  "type": "Feature",
  "properties": {
    "iso:country":"CH",
    "sg:address":"Poststrasse 9",
    "sg:city":"Niederurnen",
    "sg:orig_category":"Selbst\u00e4ndige bildende K\u00fcnstler",
    "sg:phone":"+41 55 610 17 65",
    "sg:postcode":"8867",
    "sg:province":"Glarus",
    "wof:name":"Hans Schlittler Jun. Bildhauergesch\u00e4ft",
    "wof:placetype":"venue"
},
  "geometry": {"coordinates":[9.0547924042,47.1254043579],"type":"Point"}
}