{
  "type": "Feature",
  "properties": {
    "iso:country":"CH",
    "sg:address":"Suhrenringweg 10",
    "sg:city":"Oberentfelden",
    "sg:orig_category":"Detailhandel mit Haustieren U zoologischem Bedarf",
    "sg:phone":"+41 62 723 35 14",
    "sg:postcode":"5036",
    "sg:province":"Aargau",
    "wof:name":"Karl Urban Aquarien & Zoohandlung",
    "wof:placetype":"venue"
},
  "geometry": {"coordinates":[8.048664093,47.3607978821],"type":"Point"}
}