{
  "type": "Feature",
  "properties": {
    "iso:country":"CH",
    "sg:address":"Grand-places 14",
    "sg:city":"Fribourg",
    "sg:orig_category":"Unclassifiable Establishments",
    "sg:phone":"+41 55 222 86 00",
    "sg:postcode":"1700",
    "sg:province":"Fribourg",
    "wof:name":"Holdertrade Sa",
    "wof:placetype":"venue"
},
  "geometry": {"coordinates":[7.153151989,46.8025512695],"type":"Point"}
}