{
  "type": "Feature",
  "properties": {
    "iso:country":"CH",
    "sg:address":"R\u00f6merweg 29",
    "sg:city":"Kloten",
    "sg:orig_category":"Zahnarztpraxen",
    "sg:phone":"+41 18143251",
    "sg:postcode":"8302",
    "sg:province":"Z\u00fcrich",
    "wof:name":"Dr. Med. Dent. Dieter Thommen Zahnarzt",
    "wof:placetype":"venue"
},
  "geometry": {"coordinates":[8.5823383331,47.4474868774],"type":"Point"}
}