{
  "type": "Feature",
  "properties": {
    "addr:full":"Tiefenweg 294 Wilchingen Schaffhausen 8217",
    "addr:housenumber":"294",
    "addr:postcode":"8217",
    "addr:street":"Tiefenweg",
    "iso:country":"CH",
    "sg:address":"Tiefenweg 294",
    "sg:city":"Wilchingen",
    "sg:orig_category":"Bauschreinerei Zimmerei, Dachdeckerei, Bauspenglerei U Abdichtung",
    "sg:phone":"+41 52 681 27 36",
    "sg:postcode":"8217",
    "sg:province":"Schaffhausen",
    "wof:name":"Thomi Holzbau Ag",
    "wof:placetype":"venue"
},
  "geometry": {"coordinates":[8.464345,47.669582],"type":"Point"}
}