{
  "type": "Feature",
  "properties": {
    "iso:country":"CH",
    "sg:address":"7155",
    "sg:city":"Ladir",
    "sg:orig_category":"Sportvereine Sch\u00fctzen",
    "sg:postcode":"7155",
    "sg:province":"Graubunden",
    "wof:name":"Societad De Tir Muotta",
    "wof:placetype":"venue"
},
  "geometry": {"coordinates":[9.1978302002,46.8012619019],"type":"Point"}
}