{
  "type": "Feature",
  "properties": {
    "iso:country":"CH",
    "sg:address":"R\u00fctschelenstrasse 15",
    "sg:city":"Lotzwil",
    "sg:orig_category":"Duplex Pipe Fittings",
    "sg:phone":"+41 62 923 16 55",
    "sg:postcode":"4932",
    "sg:province":"Bern",
    "wof:name":"Devinco Ag",
    "wof:placetype":"venue"
},
  "geometry": {"coordinates":[7.7875580788,47.1876792908],"type":"Point"}
}