{
  "type": "Feature",
  "properties": {
    "iso:country":"CH",
    "sg:address":"Solothurnstrasse 28",
    "sg:city":"Sch\u00f6nb\u00fchl-urtenen",
    "sg:classifiers":[
        {
            "category":"Shopping",
            "subcategory":"Computers & Home Electronics",
            "type":"Retail Goods"
        }
    ],
    "sg:phone":"+41 31 858 23 23",
    "sg:postcode":"3322",
    "sg:province":"Bern",
    "sg:tags":[
        "individual",
        "software"
    ],
    "wof:name":"Five Informatik Ag",
    "wof:placetype":"venue"
},
  "geometry": {"coordinates":[7.5015320778,47.0241241455],"type":"Point"}
}