{
  "type": "Feature",
  "properties": {
    "iso:country":"CH",
    "sg:address":"Route De La Gare De Satigny 31",
    "sg:city":"Satigny",
    "sg:orig_category":"Grosshandel mit Bekleidung",
    "sg:phone":"+41 22 753 38 10",
    "sg:postcode":"1242",
    "sg:province":"Gen\u00e8ve",
    "wof:name":"Silkan Sa",
    "wof:placetype":"venue"
},
  "geometry": {"coordinates":[6.0364117622,46.2145233154],"type":"Point"}
}