{
  "type": "Feature",
  "properties": {
    "iso:country":"CH",
    "sg:address":"Kupfergasse 18",
    "sg:city":"Chur",
    "sg:classifiers":[
        {
            "category":"Travel",
            "subcategory":"Hotels & Motels",
            "type":"Entertainment"
        }
    ],
    "sg:phone":"+41 81 252 12 61",
    "sg:postcode":"7000",
    "sg:province":"Graubunden",
    "sg:tags":[
        "hotels",
        "mit",
        "restaurant"
    ],
    "wof:name":"Hotel Franziskaner",
    "wof:placetype":"venue"
},
  "geometry": {"coordinates":[9.5298805237,46.8483352661],"type":"Point"}
}