{
  "type": "Feature",
  "properties": {
    "iso:country":"CH",
    "sg:address":"Weidli",
    "sg:city":"Diegten",
    "sg:orig_category":"Wohnheime f\u00fcr Kinder U Jugendliche",
    "sg:phone":"+41 71 755 71 98",
    "sg:postcode":"4457",
    "sg:province":"Basel-Landschaft",
    "wof:name":"Pfadiheim St.michael",
    "wof:placetype":"venue"
},
  "geometry": {"coordinates":[9.5337934494,47.3808364868],"type":"Point"}
}