{
  "type": "Feature",
  "properties": {
    "iso:country":"CH",
    "sg:address":"Hirschenweg 5",
    "sg:city":"Heerbrugg",
    "sg:orig_category":"Architekturb\u00fcros",
    "sg:phone":"+41 41 260 23 25",
    "sg:postcode":"9435",
    "sg:province":"St. Gallen",
    "wof:name":"Willy Imfeld Architekturb\u00fcro",
    "wof:placetype":"venue"
},
  "geometry": {"coordinates":[8.274789,47.077187],"type":"Point"}
}