{
  "type": "Feature",
  "properties": {
    "iso:country":"CH",
    "sg:address":"Ringstrasse 18",
    "sg:city":"Chur",
    "sg:orig_category":"Versicherungen Generalagenturen",
    "sg:phone":"+41 81 286 71 11",
    "sg:postcode":"7000",
    "sg:province":"Graubunden",
    "wof:name":"Generali Versicherungen",
    "wof:placetype":"venue"
},
  "geometry": {"coordinates":[9.5136032104,46.8509635925],"type":"Point"}
}