{
  "type": "Feature",
  "properties": {
    "iso:country":"CH",
    "sg:address":"Solothurnstrasse 79",
    "sg:city":"Kr\u00e4iligen",
    "sg:orig_category":"Fischzucht, Teichwirtschaft",
    "sg:postcode":"3315",
    "sg:province":"Bern",
    "wof:name":"Forellenzucht Kr\u00e4iligen Gmbh",
    "wof:placetype":"venue"
},
  "geometry": {"coordinates":[7.5328431129,47.1434364319],"type":"Point"}
}