{
  "type": "Feature",
  "properties": {
    "iso:country":"CH",
    "sg:address":"B\u00fcchelistr./lindenstr. 2",
    "sg:city":"Liestal",
    "sg:orig_category":"Non-Classified Establishments",
    "sg:postcode":"4410",
    "sg:province":"Basel-Landschaft",
    "wof:name":"Fosbel Intellectual Ag",
    "wof:placetype":"venue"
},
  "geometry": {"coordinates":[8.778793335,47.2024002075],"type":"Point"}
}