{
  "type": "Feature",
  "properties": {
    "iso:country":"CH",
    "sg:address":"Ringstrasse 18",
    "sg:city":"Chur",
    "sg:orig_category":"Finanzierungsinstitutionen",
    "sg:phone":"+41 81 250 39 98",
    "sg:postcode":"7000",
    "sg:province":"Graubunden",
    "wof:name":"Unifin 98 Ag",
    "wof:placetype":"venue"
},
  "geometry": {"coordinates":[9.5136032104,46.8509635925],"type":"Point"}
}