{
  "type": "Feature",
  "properties": {
    "iso:country":"CH",
    "sg:address":"Weinbergstrasse 49 8006 Z\u00fcrich. Postfach",
    "sg:city":"Z\u00fcrich",
    "sg:orig_category":"Verlagsgewerbe",
    "sg:phone":"+41 55 224 25 25",
    "sg:postcode":"8023",
    "sg:province":"Z\u00fcrich",
    "wof:name":"Verlag Meyer Ag",
    "wof:placetype":"venue"
},
  "geometry": {"coordinates":[8.8423900604,47.2252693176],"type":"Point"}
}