{
  "type": "Feature",
  "properties": {
    "iso:country":"CH",
    "sg:address":"Bahnhofstrasse 118",
    "sg:city":"M\u00f6hlin",
    "sg:orig_category":"Kauf U Verkauf von Immobilien auf eigene Rechnung",
    "sg:phone":"+41 71 311 27 34",
    "sg:postcode":"4313",
    "sg:province":"Aargau",
    "wof:name":"Provita - Trading, Stadelmann Kurt Dienstleistungen, Bes. Beratungen Im Bereiche Des Liegenschaftenverwaltungssektors Usw",
    "wof:placetype":"venue"
},
  "geometry": {"coordinates":[9.3184289932,47.4064064026],"type":"Point"}
}