{
  "type": "Feature",
  "properties": {
    "iso:country":"CH",
    "sg:address":"1981",
    "sg:city":"Vex",
    "sg:orig_category":"Campingpl\u00e4tze",
    "sg:postcode":"1981",
    "sg:province":"Valais",
    "wof:name":"Rudaz & Cie",
    "wof:placetype":"venue"
},
  "geometry": {"coordinates":[7.39541,46.205479],"type":"Point"}
}