{
  "type": "Feature",
  "properties": {
    "iso:country":"CH",
    "sg:address":"Au Village 73",
    "sg:city":"Autigny",
    "sg:orig_category":"Detailhandel mit Milcherzeugnissen U Eiern Herstellung von K\u00e4se",
    "sg:phone":"+41 26 477 11 84",
    "sg:postcode":"1742",
    "sg:province":"Fribourg",
    "wof:name":"Ren\u00e9 & J\u00e9r\u00f4me Raemy Laiterie",
    "wof:placetype":"venue"
},
  "geometry": {"coordinates":[7.0206508636,46.7363510132],"type":"Point"}
}