{
  "type": "Feature",
  "properties": {
    "iso:country":"CH",
    "sg:address":"Erlen 16",
    "sg:city":"Wauwil",
    "sg:orig_category":"Gartenbau",
    "sg:phone":"+41 79 241 45 94",
    "sg:postcode":"6242",
    "sg:province":"Luzern",
    "wof:name":"Peter Arnold Gmbh",
    "wof:placetype":"venue"
},
  "geometry": {"coordinates":[8.0355653763,47.1862335205],"type":"Point"}
}