{
  "type": "Feature",
  "properties": {
    "iso:country":"CH",
    "sg:address":"Lindenstrasse 5",
    "sg:city":"Th\u00f6rigen",
    "sg:orig_category":"Elektroinstallation",
    "sg:phone":"+41 62 771 42 32",
    "sg:postcode":"3367",
    "sg:province":"Bern",
    "wof:name":"Elektro Ag 5734 Reinach",
    "wof:placetype":"venue"
},
  "geometry": {"coordinates":[8.1829795837,47.2511024475],"type":"Point"}
}