{
  "type": "Feature",
  "properties": {
    "iso:country":"CH",
    "sg:address":"Obere Steingrubenstrasse 2 4500 Solothurn. Postfach",
    "sg:city":"Solothurn",
    "sg:orig_category":"Nationale Postdienste",
    "sg:phone":"+41 71 222 74 90",
    "sg:postcode":"4504",
    "wof:name":"Die Schweizerische Post St. Gallen 3 Linseb\u00fchl",
    "wof:placetype":"venue"
},
  "geometry": {"coordinates":[9.3850870132,47.4258880615],"type":"Point"}
}