{
  "type": "Feature",
  "properties": {
    "iso:country":"CH",
    "sg:address":"Rue D'aarberg 68",
    "sg:city":"Biel/bienne",
    "sg:orig_category":"Bauingenieurb\u00fcros Eisenbetonbau Bauingenieurb\u00fcros allgemein",
    "sg:phone":"+41 32 322 66 30",
    "sg:postcode":"2503",
    "sg:province":"Bern",
    "wof:name":"Allemand Jeanneret Schmid Sa Bureau D'ing\u00e9nieurs",
    "wof:placetype":"venue"
},
  "geometry": {"coordinates":[7.239907,47.1315],"type":"Point"}
}