{
  "type": "Feature",
  "properties": {
    "iso:country":"CH",
    "sg:address":"Birsstrasse 15",
    "sg:city":"Muttenz",
    "sg:orig_category":"Bauspenglerei Sanit\u00e4rinstallation",
    "sg:phone":"+41 79 913 26 82",
    "sg:postcode":"4132",
    "sg:province":"Basel-Landschaft",
    "wof:name":"Schaub Sa Installations Sanitaires",
    "wof:placetype":"venue"
},
  "geometry": {"coordinates":[6.821938,47.101994],"type":"Point"}
}