{
  "type": "Feature",
  "properties": {
    "iso:country":"CH",
    "sg:address":"8301 Glattzentrum. Postfach",
    "sg:city":"Glattzentrum",
    "sg:orig_category":"Detailhandel mit Radio U Fernsehger\u00e4ten Detailhandel mit fotografischen Artikeln",
    "sg:phone":"+41 18831001",
    "sg:postcode":"8301",
    "sg:province":"Z\u00fcrich",
    "wof:name":"Interdiscount Ag Hi-fi Video Photo Radio",
    "wof:placetype":"venue"
},
  "geometry": {"coordinates":[8.5951404572,47.4236717224],"type":"Point"}
}