{
  "type": "Feature",
  "properties": {
    "iso:country":"CH",
    "sg:address":"8957 Spreitenbach. Postfach",
    "sg:city":"Spreitenbach",
    "sg:orig_category":"Sportvereine Turnen",
    "sg:phone":"+41 56 401 38 51",
    "sg:postcode":"8957",
    "sg:province":"Aargau",
    "wof:name":"Turnverein Spreitenbach",
    "wof:placetype":"venue"
},
  "geometry": {"coordinates":[8.3656835556,47.4180450439],"type":"Point"}
}