{
  "type": "Feature",
  "properties": {
    "iso:country":"CH",
    "sg:address":"Scheuchzerstr 18",
    "sg:city":"Z\u00fcrich",
    "sg:classifiers":[
        {
            "category":"Professional",
            "subcategory":"Advertising",
            "type":"Services"
        }
    ],
    "sg:phone":"+41 21 635 16 81",
    "sg:postcode":"8023",
    "sg:province":"Z\u00fcrich",
    "sg:tags":[
        "information",
        "medium",
        "communication"
    ],
    "wof:name":"Editions Probatima Sarl",
    "wof:placetype":"venue"
},
  "geometry": {"coordinates":[6.595955,46.539143],"type":"Point"}
}