{
  "type": "Feature",
  "properties": {
    "iso:country":"CH",
    "sg:address":"Alte Landstrasse 2",
    "sg:city":"Zunzgen",
    "sg:orig_category":"Finanzierungsinstitutionen",
    "sg:postcode":"4455",
    "sg:province":"Basel-Landschaft",
    "wof:name":"Oppliger C. Cop-beratung",
    "wof:placetype":"venue"
},
  "geometry": {"coordinates":[7.8076958656,47.4493980408],"type":"Point"}
}