{
  "type": "Feature",
  "properties": {
    "iso:country":"CH",
    "sg:address":"Jordils 1",
    "sg:city":"Lugnorre",
    "sg:orig_category":"Grosshandel mit Nahrungsmitteln, Getr\u00e4nken U Tabakwaren ohne ausgepr\u00e4gten Schwerpunkt",
    "sg:phone":"+41 79 353 63 09",
    "sg:postcode":"1789",
    "sg:province":"Fribourg",
    "wof:name":"Imhoof Marc",
    "wof:placetype":"venue"
},
  "geometry": {"coordinates":[7.0704421997,46.9510688782],"type":"Point"}
}