{
  "type": "Feature",
  "properties": {
    "addr:full":"7537 M\u00fcstair Graubunden 7537",
    "addr:housenumber":"7537",
    "addr:postcode":"7537",
    "addr:street":"Muestair Graubunden",
    "iso:country":"CH",
    "sg:address":"7537",
    "sg:city":"M\u00fcstair",
    "sg:orig_category":"Bibliotheken U Archive Wohnheime",
    "sg:phone":"+41 81 858 52 65",
    "sg:postcode":"7537",
    "sg:province":"Graubunden",
    "wof:name":"Frauenkloster St.johann",
    "wof:placetype":"venue"
},
  "geometry": {"coordinates":[10.445798,46.624424],"type":"Point"}
}