{
  "type": "Feature",
  "properties": {
    "iso:country":"CH",
    "sg:address":"Solothurnstrasse 8",
    "sg:city":"Grenchen",
    "sg:classifiers":[
        {
            "category":"Restaurant",
            "type":"Food & Drink"
        }
    ],
    "sg:phone":"+41 32 653 05 93",
    "sg:postcode":"2540",
    "sg:province":"Solothurn",
    "sg:tags":[
        "tea-rooms",
        "restaurants"
    ],
    "wof:name":"Art Caf\u00e9, Borer Peter",
    "wof:placetype":"venue"
},
  "geometry": {"coordinates":[7.3964018822,47.1922340393],"type":"Point"}
}