{
  "type": "Feature",
  "properties": {
    "iso:country":"CH",
    "sg:address":"Ahornstrasse 16 4055 Basel. Postfach",
    "sg:city":"Basel",
    "sg:orig_category":"Datenverarbeitungsdienste",
    "sg:phone":"+41 61 302 57 37",
    "sg:postcode":"4009",
    "sg:province":"Basel-Stadt",
    "wof:name":"Cbis Christian Burkhalter Informatik Systeme",
    "wof:placetype":"venue"
},
  "geometry": {"coordinates":[7.573468,47.557606],"type":"Point"}
}