{
  "type": "Feature",
  "properties": {
    "iso:country":"CH",
    "sg:address":"Alpenhof Zermatt 3920 Zermatt. Postfach",
    "sg:city":"Zermatt",
    "sg:classifiers":[
        {
            "category":"Travel",
            "subcategory":"Hotels & Motels",
            "type":"Entertainment"
        }
    ],
    "sg:phone":"+41 27 966 55 55",
    "sg:postcode":"3920",
    "sg:province":"Valais",
    "sg:tags":[
        "hotels",
        "mit",
        "restaurant"
    ],
    "wof:name":"Alpenhof Zermatt Ag Hotels U. Hotelbeteiligungen, Gastgewerbebetrieben Usw.; Erwerb, Betrieb, F\u00f6rderung U. Verkauf",
    "wof:placetype":"venue"
},
  "geometry": {"coordinates":[7.7539248466,46.0301589966],"type":"Point"}
}