{
  "type": "Feature",
  "properties": {
    "iso:country":"CH",
    "sg:address":"7482",
    "sg:city":"Preda",
    "sg:orig_category":"Pensionen mit Restaurant RESTAURANTS: TEA-ROOMS",
    "sg:phone":"+41 71 377 11 60",
    "sg:postcode":"7482",
    "sg:province":"Graubunden",
    "wof:name":"Restaurant Pension Frohheim B\u00fcchel M.",
    "wof:placetype":"venue"
},
  "geometry": {"coordinates":[9.1766519547,47.3010787964],"type":"Point"}
}