{
  "type": "Feature",
  "properties": {
    "iso:country":"CH",
    "sg:address":"Untere Halten 559",
    "sg:city":"B\u00fchler",
    "sg:orig_category":"Detailhandel mit Getr\u00e4nken",
    "sg:phone":"+41 21 922 47 22",
    "sg:postcode":"9055",
    "sg:province":"Appenzell Ausserrhoden",
    "wof:name":"Siegenthaler Fr\u00e8res Commerce De Vins",
    "wof:placetype":"venue"
},
  "geometry": {"coordinates":[5.6025900841,45.9854125977],"type":"Point"}
}