{
  "type": "Feature",
  "properties": {
    "iso:country":"CH",
    "sg:address":"Orpundstrasse 2",
    "sg:city":"Biel/bienne",
    "sg:orig_category":"Fachdetailhandel in Verkaufsr\u00e4umen",
    "sg:postcode":"2500",
    "sg:province":"Bern",
    "wof:name":"B\u00e4nziger's Sport Und Freizeit Shop",
    "wof:placetype":"venue"
},
  "geometry": {"coordinates":[8.4358453751,47.352191925],"type":"Point"}
}