{
  "type": "Feature",
  "properties": {
    "iso:country":"CH",
    "sg:address":"Rue Caroline 11",
    "sg:city":"Lausanne",
    "sg:classifiers":[
        {
            "category":"Restaurant",
            "type":"Food & Drink"
        }
    ],
    "sg:phone":"+41 22 343 73 87",
    "sg:postcode":"1003",
    "sg:province":"Vaud",
    "wof:name":"Restaurant Au Boccalino",
    "wof:placetype":"venue"
},
  "geometry": {"coordinates":[6.1392621994,46.1802635193],"type":"Point"}
}