{
  "type": "Feature",
  "properties": {
    "iso:country":"CH",
    "sg:address":"Poststrasse 15",
    "sg:city":"St.gallen",
    "sg:orig_category":"Arztpraxen",
    "sg:phone":"+41 71 222 80 40",
    "sg:postcode":"9000",
    "sg:province":"St. Gallen",
    "wof:name":"Dres Med.p. Mehmann & P.hofer Spezial\u00e4rzte Fmh",
    "wof:placetype":"venue"
},
  "geometry": {"coordinates":[9.372641,47.424427],"type":"Point"}
}