{
  "type": "Feature",
  "properties": {
    "addr:full":"Feldstrasse 80 B\u00fclach Z\u00fcrich 8180",
    "addr:housenumber":"80",
    "addr:postcode":"8180",
    "addr:street":"Feldstrasse;Zuerich",
    "iso:country":"CH",
    "sg:address":"Feldstrasse 80",
    "sg:city":"B\u00fclach",
    "sg:orig_category":"Datenverarbeitungsdienste Softwareentwicklung U beratung",
    "sg:phone":"+41 18641020",
    "sg:postcode":"8180",
    "sg:province":"Z\u00fcrich",
    "wof:name":"Pci Informatik Ag",
    "wof:placetype":"venue"
},
  "geometry": {"coordinates":[8.538889,47.509377],"type":"Point"}
}