{
  "type": "Feature",
  "properties": {
    "iso:country":"CH",
    "sg:address":"Haldenstrasse 54",
    "sg:city":"Kloten",
    "sg:orig_category":"Unternehmensberatung",
    "sg:phone":"+41 18143007",
    "sg:postcode":"8302",
    "sg:province":"Z\u00fcrich",
    "wof:name":"Msb Consulting Heinrich Br\u00fcgger",
    "wof:placetype":"venue"
},
  "geometry": {"coordinates":[8.5939540863,47.4563713074],"type":"Point"}
}