{
  "type": "Feature",
  "properties": {
    "addr:full":"Chemin Rey 13 1283 La Plaine Case Postale 22 Dardagny 1282",
    "addr:housenumber":"13;22;1282",
    "addr:postcode":"1283",
    "addr:street":"Chemin Rey;La Plaine Case Postale",
    "iso:country":"CH",
    "sg:address":"Chemin Rey 13 1283 La Plaine Case Postale 22",
    "sg:city":"Dardagny",
    "sg:orig_category":"Detailhandel mit Brennstoffen U Heizmaterial Herstellung von Automobilen",
    "sg:phone":"+41 22 754 12 66",
    "sg:postcode":"1282",
    "wof:name":"Beck Jean-pierre Sa",
    "wof:placetype":"venue"
},
  "geometry": {"coordinates":[5.999302,46.177849],"type":"Point"}
}