{
  "type": "Feature",
  "properties": {
    "iso:country":"CH",
    "sg:address":"Farngutweg 8",
    "sg:city":"Villmergen",
    "sg:orig_category":"Sportvereine Ballsport Tennis",
    "sg:phone":"+41 56 622 99 31",
    "sg:postcode":"5612",
    "sg:province":"Aargau",
    "wof:name":"Tc Wohlen",
    "wof:placetype":"venue"
},
  "geometry": {"coordinates":[8.2571716309,47.3466415405],"type":"Point"}
}