{
  "type": "Feature",
  "properties": {
    "iso:country":"CH",
    "sg:address":"Dornacherstrasse 7 4500 Solothurn. Postfach",
    "sg:city":"Solothurn",
    "sg:classifiers":[
        {
            "category":"Professional",
            "subcategory":"Employment Agencies",
            "type":"Services"
        }
    ],
    "sg:phone":"+41 32 626 35 35",
    "sg:postcode":"4500",
    "sg:province":"Solothurn",
    "sg:tags":[
        "personal",
        "u",
        "stellenvermittlung"
    ],
    "wof:name":"Allbecon Personalmanagement Solothurn Ag Dienstleistungen Im Bereich Personal Und Unternehmensberatung. Arbeitsvermittlung, Personalverleih F\u00fcr Kaufm\u00e4nnische Und Technische Berufe",
    "wof:placetype":"venue"
},
  "geometry": {"coordinates":[7.5375499725,47.2044944763],"type":"Point"}
}