{
  "type": "Feature",
  "properties": {
    "iso:country":"CH",
    "sg:address":"Eglisporweg 2 3506 Grossh\u00f6chstetten. Postfach",
    "sg:city":"Grossh\u00f6chstetten",
    "sg:orig_category":"Architekturb\u00fcros",
    "sg:phone":"+41 31 711 14 93",
    "sg:postcode":"3506",
    "sg:province":"Bern",
    "wof:name":"Kurt R\u00f6thlisberger Architekturb\u00fcro",
    "wof:placetype":"venue"
},
  "geometry": {"coordinates":[7.637254,46.908363],"type":"Point"}
}