{
  "type": "Feature",
  "properties": {
    "iso:country":"CH",
    "sg:address":"Seestrasse 2 3700 Spiez. Postfach 415",
    "sg:city":"Spiez",
    "sg:orig_category":"Advokaturb\u00fcros",
    "sg:phone":"+41 71 228 08 10",
    "sg:postcode":"3700",
    "sg:province":"Bern",
    "wof:name":"Frischknecht, F\u00e4ssler & Schmid Advokaturb\u00fcro",
    "wof:placetype":"venue"
},
  "geometry": {"coordinates":[9.37544,47.422901],"type":"Point"}
}