{
  "type": "Feature",
  "properties": {
    "iso:country":"CH",
    "sg:address":"Oberdorfstrasse 23 3303 Jegenstorf. Postfach",
    "sg:city":"Jegenstorf",
    "sg:orig_category":"Bau U Wohngenossenschaften",
    "sg:postcode":"3303",
    "sg:province":"Bern",
    "wof:name":"Wohnbaugen.hasle",
    "wof:placetype":"venue"
},
  "geometry": {"coordinates":[8.04994,46.97921],"type":"Point"}
}