{
  "type": "Feature",
  "properties": {
    "iso:country":"CH",
    "sg:address":"Auf Der Mauer 1",
    "sg:city":"Langenbruck",
    "sg:orig_category":"G\u00fcterbef\u00f6rderung im Strassenverkehr",
    "sg:phone":"+41 62 390 19 15",
    "sg:postcode":"4438",
    "sg:province":"Basel-Landschaft",
    "wof:name":"Probst Gustav",
    "wof:placetype":"venue"
},
  "geometry": {"coordinates":[7.7644290924,47.3521728516],"type":"Point"}
}