{
  "type": "Feature",
  "properties": {
    "iso:country":"CH",
    "sg:address":"Kantonsstrasse 2",
    "sg:city":"Uffikon",
    "sg:orig_category":"Mechanik Schlossereien",
    "sg:phone":"+41 62 756 18 51",
    "sg:postcode":"6253",
    "sg:province":"Luzern",
    "wof:name":"Staffelbach Stefan + Gassmann Beat",
    "wof:placetype":"venue"
},
  "geometry": {"coordinates":[8.0214738846,47.210269928],"type":"Point"}
}