{
  "type": "Feature",
  "properties": {
    "iso:country":"CH",
    "sg:address":"2832",
    "sg:city":"Rebeuvelier",
    "sg:orig_category":"Primarschulen",
    "sg:phone":"+41 32 431 14 22",
    "sg:postcode":"2832",
    "sg:province":"Jura",
    "wof:name":"Ecole Primaire",
    "wof:placetype":"venue"
},
  "geometry": {"coordinates":[7.4151668549,47.3245697021],"type":"Point"}
}