{
  "type": "Feature",
  "properties": {
    "iso:country":"CH",
    "sg:address":"Nassa Via",
    "sg:city":"Lugano",
    "sg:orig_category":"Handels-H\u00e4user U Gesellschaften",
    "sg:phone":"+41 91 922 91 11",
    "sg:postcode":"6900",
    "sg:province":"Ticino",
    "wof:name":"Interfa Ltd, Londra, Succursale Di Lugano",
    "wof:placetype":"venue"
},
  "geometry": {"coordinates":[8.9496250153,46.0020637512],"type":"Point"}
}