{
  "type": "Feature",
  "properties": {
    "iso:country":"CH",
    "sg:address":"C\u00e4cilienstrasse 27",
    "sg:city":"Bern",
    "sg:orig_category":"Wohnheime",
    "sg:postcode":"3007",
    "sg:province":"Bern",
    "wof:name":"Viva-stiftung Bern",
    "wof:placetype":"venue"
},
  "geometry": {"coordinates":[7.4280381203,46.9406051636],"type":"Point"}
}