{
  "type": "Feature",
  "properties": {
    "iso:country":"CH",
    "sg:address":"Rue Voltaire 30 1201 Gen\u00e8ve. Postfach",
    "sg:city":"Gen\u00e8ve",
    "sg:orig_category":"Fachdetailhandel mit pharmazeutischen Produkten",
    "sg:phone":"+41 22 344 73 80",
    "sg:postcode":"1201",
    "sg:province":"Gen\u00e8ve",
    "wof:name":"Pharmacie Voltaire, Knecht-pouit Pascale",
    "wof:placetype":"venue"
},
  "geometry": {"coordinates":[6.1356329918,46.2083625793],"type":"Point"}
}