{
  "type": "Feature",
  "properties": {
    "iso:country":"CH",
    "sg:address":"Birch 45",
    "sg:city":"Gontenschwil",
    "sg:orig_category":"Politische Parteien SP",
    "sg:phone":"+41 71 385 42 16",
    "sg:postcode":"5728",
    "sg:province":"Aargau",
    "wof:name":"Sp Ortspartei Gossau Sg",
    "wof:placetype":"venue"
},
  "geometry": {"coordinates":[9.2548904419,47.4220199585],"type":"Point"}
}