{
  "type": "Feature",
  "properties": {
    "addr:full":"Strada Cantonale Bedigliora Ticino 6981",
    "addr:postcode":"6981",
    "addr:street":"Strada Cantonale;Ticino",
    "iso:country":"CH",
    "sg:address":"Strada Cantonale",
    "sg:city":"Bedigliora",
    "sg:orig_category":"Bezirks, Sekundar, Realschulen, Oberstufe der Primarschulen",
    "sg:phone":"+41 91 608 26 16",
    "sg:postcode":"6981",
    "sg:province":"Ticino",
    "wof:name":"Scuola Media",
    "wof:placetype":"venue"
},
  "geometry": {"coordinates":[8.841117,46.011433],"type":"Point"}
}