{
  "type": "Feature",
  "properties": {
    "iso:country":"CH",
    "sg:address":"Glattalstrasse 76/l3 8052 Z\u00fcrich. Postfach",
    "sg:city":"Seebach",
    "sg:orig_category":"Mit dem Versicherungsgewerbe verbundene T\u00e4tigkeiten",
    "sg:postcode":"8052",
    "sg:province":"Z\u00fcrich",
    "wof:name":"Salmina, Neutrale Versicherungsberatung",
    "wof:placetype":"venue"
},
  "geometry": {"coordinates":[8.5387096405,47.4295196533],"type":"Point"}
}