{
  "type": "Feature",
  "properties": {
    "iso:country":"CH",
    "sg:address":"3951",
    "sg:city":"Agarn",
    "sg:orig_category":"Architektur U Ingenieurb\u00fcros",
    "sg:postcode":"3951",
    "sg:province":"Valais",
    "wof:name":"Zimmerli Niklaus, Architekt Jbz",
    "wof:placetype":"venue"
},
  "geometry": {"coordinates":[7.663592,46.296951],"type":"Point"}
}