{
  "type": "Feature",
  "properties": {
    "iso:country":"CH",
    "sg:address":"Brunniweg 7",
    "sg:city":"Wimmis",
    "sg:orig_category":"Elektroinstallation",
    "sg:phone":"+41 33 657 16 94",
    "sg:postcode":"3752",
    "sg:province":"Bern",
    "wof:name":"Hermann Kunz",
    "wof:placetype":"venue"
},
  "geometry": {"coordinates":[7.6375370026,46.68201828],"type":"Point"}
}