{
  "type": "Feature",
  "properties": {
    "iso:country":"CH",
    "sg:address":"Obergrundstrasse 3",
    "sg:city":"Luzern",
    "sg:orig_category":"Erwachsenenbildung U Unterricht",
    "sg:postcode":"6003",
    "sg:province":"Luzern",
    "wof:name":"E.l.m. Ecole De Langues Modernes, School Of Modern Languages, Mme Dumusque A.",
    "wof:placetype":"venue"
},
  "geometry": {"coordinates":[6.8650789261,46.449962616],"type":"Point"}
}