{
  "type": "Feature",
  "properties": {
    "iso:country":"CH",
    "sg:address":"Auf Der Schanz 61",
    "sg:city":"Kaiseraugst",
    "sg:orig_category":"Softwareentwicklung U beratung",
    "sg:phone":"+41 79 209 37 74",
    "sg:postcode":"4303",
    "sg:province":"Aargau",
    "wof:name":"Gwb Software",
    "wof:placetype":"venue"
},
  "geometry": {"coordinates":[7.7272391319,47.536403656],"type":"Point"}
}