{
  "type": "Feature",
  "properties": {
    "iso:country":"CH",
    "sg:address":"Gyseneggli",
    "sg:city":"Braunwald",
    "sg:orig_category":"Jugendherbergen U H\u00fctten",
    "sg:phone":"+41 55 643 13 56",
    "sg:postcode":"8784",
    "sg:province":"Glarus",
    "wof:name":"Jugendherberge Sjh",
    "wof:placetype":"venue"
},
  "geometry": {"coordinates":[8.99127388,46.9422721863],"type":"Point"}
}