{
  "type": "Feature",
  "properties": {
    "iso:country":"CH",
    "sg:address":"Fehrenstrasse 1",
    "sg:city":"Breitenbach",
    "sg:classifiers":[
        {
            "category":"Travel",
            "subcategory":"Hotels & Motels",
            "type":"Entertainment"
        }
    ],
    "sg:phone":"+41 61 781 15 50",
    "sg:postcode":"4226",
    "sg:province":"Solothurn",
    "sg:tags":[
        "hotels",
        "mit",
        "restaurant"
    ],
    "wof:name":"Landgasthof Weisses Kreuz",
    "wof:placetype":"venue"
},
  "geometry": {"coordinates":[7.5440940857,47.408290863],"type":"Point"}
}