{
  "type": "Feature",
  "properties": {
    "iso:country":"CH",
    "sg:address":"Feldmattstrasse 16",
    "sg:city":"Emmen",
    "sg:orig_category":"Herstellung von \u00d6fen U Brennern",
    "sg:phone":"+41 41 260 55 44",
    "sg:postcode":"6032",
    "sg:province":"Luzern",
    "wof:name":"Schreiber-tarag Ag, Thermische Anlagen Und Tankrevisionen",
    "wof:placetype":"venue"
},
  "geometry": {"coordinates":[8.3240776062,47.1082611084],"type":"Point"}
}