{
  "type": "Feature",
  "properties": {
    "iso:country":"CH",
    "sg:address":"Hauptstrasse 77",
    "sg:city":"Hornussen",
    "sg:classifiers":[
        {
            "category":"Restaurant",
            "type":"Food & Drink"
        }
    ],
    "sg:phone":"+41 71 633 12 03",
    "sg:postcode":"5075",
    "sg:province":"Aargau",
    "wof:name":"Restaurant Schwert",
    "wof:placetype":"venue"
},
  "geometry": {"coordinates":[9.1531019211,47.5486946106],"type":"Point"}
}