{
  "type": "Feature",
  "properties": {
    "iso:country":"CH",
    "sg:address":"Samaritaine Rue De La 12",
    "sg:city":"Freiburg",
    "sg:orig_category":"Unclassifiable Establishments",
    "sg:postcode":"1700",
    "sg:province":"Fribourg",
    "wof:name":"Carat Holding Sa",
    "wof:placetype":"venue"
},
  "geometry": {"coordinates":[6.9989409447,47.2110595703],"type":"Point"}
}