{
  "type": "Feature",
  "properties": {
    "iso:country":"CH",
    "sg:address":"Milieu Rue Du 14c 2502 Biel/bienne. Postfach",
    "sg:city":"Biel/bienne",
    "sg:orig_category":"Herstellung von Verbrennungsmotoren U Turbinen ohne Motoren f\u00fcr Luft U Strassenfahrzeuge",
    "sg:postcode":"2502",
    "sg:province":"Bern",
    "wof:name":"Lindauer Tuning Auto-tuning",
    "wof:placetype":"venue"
},
  "geometry": {"coordinates":[8.531414032,47.1997032166],"type":"Point"}
}