{
  "type": "Feature",
  "properties": {
    "iso:country":"CH",
    "sg:address":"Langackerweg 8 8155 Niederhasli. Postfach",
    "sg:city":"Niederhasli",
    "sg:orig_category":"Fachdetailhandel in Verkaufsr\u00e4umen",
    "sg:postcode":"8155",
    "sg:province":"Z\u00fcrich",
    "wof:name":"Rewil Shop Willi R. Party, Geschenkartikel; Verkauf. Partyservice",
    "wof:placetype":"venue"
},
  "geometry": {"coordinates":[8.4866685867,47.4826698303],"type":"Point"}
}