{
  "type": "Feature",
  "properties": {
    "iso:country":"CH",
    "sg:address":"Dorfstrasse 88",
    "sg:city":"Wiesendangen",
    "sg:orig_category":"Hafner Kaminbau",
    "sg:phone":"+41 52 337 19 43",
    "sg:postcode":"8542",
    "sg:province":"Z\u00fcrich",
    "wof:name":"Robert Erne Dachdecker-& Kaminfegergesch.",
    "wof:placetype":"venue"
},
  "geometry": {"coordinates":[8.7931022644,47.5211868286],"type":"Point"}
}