{
  "type": "Feature",
  "properties": {
    "iso:country":"CH",
    "sg:address":"Zeughausgasse 9",
    "sg:city":"Bern",
    "sg:classifiers":[
        {
            "category":"Travel",
            "subcategory":"Travel Agent",
            "type":"Entertainment"
        }
    ],
    "sg:phone":"+41 4131329222",
    "sg:postcode":"3011",
    "sg:province":"Bern",
    "wof:name":"Hotel Bern",
    "wof:placetype":"venue"
},
  "geometry": {"coordinates":[7.4464859962,46.9486465454],"type":"Point"}
}