{
  "type": "Feature",
  "properties": {
    "iso:country":"CH",
    "sg:address":"Siewerdtstrasse 75",
    "sg:city":"Z\u00fcrich",
    "sg:orig_category":"Ausbaugewerbe",
    "sg:phone":"+41 13130075",
    "sg:postcode":"8050",
    "sg:province":"Z\u00fcrich",
    "wof:name":"Wss-ag Bauaustrocknungen",
    "wof:placetype":"venue"
},
  "geometry": {"coordinates":[8.554939,47.412354],"type":"Point"}
}