{
  "type": "Feature",
  "properties": {
    "iso:country":"CH",
    "sg:address":"Reussstrasse 51",
    "sg:city":"Attinghausen",
    "sg:orig_category":"Instandhaltung U Reparatur von Automobilen",
    "sg:phone":"+41 41 870 68 01",
    "sg:postcode":"6468",
    "sg:province":"Uri",
    "wof:name":"Jakob Zurfluh Reuss-garage",
    "wof:placetype":"venue"
},
  "geometry": {"coordinates":[8.6306552887,46.865737915],"type":"Point"}
}