{
  "type": "Feature",
  "properties": {
    "iso:country":"CH",
    "sg:address":"Aarestrasse 28",
    "sg:city":"Unterseen",
    "sg:orig_category":"Herstellung von Tanks U Sammelbeh\u00e4ltern aus Metall Sanit\u00e4r U Heizungsinstallation",
    "sg:phone":"+41 33 822 56 84",
    "sg:postcode":"3800",
    "sg:province":"Bern",
    "wof:name":"Rolf Glaus Zentralheizungen Tankbau",
    "wof:placetype":"venue"
},
  "geometry": {"coordinates":[7.8512001038,46.6857299805],"type":"Point"}
}