{
  "type": "Feature",
  "properties": {
    "iso:country":"CH",
    "sg:address":"Ahornstrasse 3",
    "sg:city":"Frutigen",
    "sg:orig_category":"Sonstige Aktivit\u00e4ten der nicht-\u00e4rztlichen Medizinalberufe",
    "sg:phone":"+41 33 671 25 05",
    "sg:postcode":"3714",
    "sg:province":"Bern",
    "wof:name":"Annemarie Habegger Atemtherapie",
    "wof:placetype":"venue"
},
  "geometry": {"coordinates":[7.6364622116,46.5856056213],"type":"Point"}
}