{
  "type": "Feature",
  "properties": {
    "iso:country":"CH",
    "sg:address":"Winterthurerstrasse 2 5080 Laufenburg. Postfach",
    "sg:city":"Laufenburg",
    "sg:orig_category":"Regionalbanken U Sparkassen",
    "sg:phone":"+41 62 869 45 45",
    "sg:postcode":"5080",
    "sg:province":"Aargau",
    "wof:name":"Neue Aargauer Bank",
    "wof:placetype":"venue"
},
  "geometry": {"coordinates":[8.0614128113,47.5602912903],"type":"Point"}
}