{
  "type": "Feature",
  "properties": {
    "iso:country":"CH",
    "sg:address":"3150 Schwarzenburg. Postfach 15",
    "sg:city":"Schwarzenburg",
    "sg:orig_category":"Sportvereine Eissport Eishockey",
    "sg:postcode":"3150",
    "sg:province":"Bern",
    "wof:name":"Eishockey-club Schwarzenburg",
    "wof:placetype":"venue"
},
  "geometry": {"coordinates":[7.3419790268,46.8187294006],"type":"Point"}
}