{
  "type": "Feature",
  "properties": {
    "iso:country":"CH",
    "sg:address":"St. Georgen-strasse 46",
    "sg:city":"Winterthur",
    "sg:orig_category":"Psychotherapie",
    "sg:phone":"+41 52 213 41 12",
    "sg:postcode":"8400",
    "sg:province":"Z\u00fcrich",
    "wof:name":"Markus F\u00e4h Psychotherapie",
    "wof:placetype":"venue"
},
  "geometry": {"coordinates":[8.7353219986,47.5025978088],"type":"Point"}
}