{
  "type": "Feature",
  "properties": {
    "iso:country":"CH",
    "sg:address":"Etzelstrasse 22",
    "sg:city":"Richterswil",
    "sg:orig_category":"Vorschulen, Kinderg\u00e4rten",
    "sg:phone":"+41 17840733",
    "sg:postcode":"8805",
    "sg:province":"Z\u00fcrich",
    "wof:name":"Kindergarten Etzelstrasse",
    "wof:placetype":"venue"
},
  "geometry": {"coordinates":[8.7020835876,47.2060546875],"type":"Point"}
}