{
  "type": "Feature",
  "properties": {
    "iso:country":"CH",
    "sg:address":"Kirchweg 1 5400 Baden. Postfach 2088",
    "sg:city":"Baden",
    "sg:orig_category":"Rechtsberatung",
    "sg:phone":"+41 56 222 92 88",
    "sg:postcode":"5400",
    "sg:province":"Aargau",
    "wof:name":"Kurt Josef M\u00fcller, Notar",
    "wof:placetype":"venue"
},
  "geometry": {"coordinates":[8.307477951,47.471912384],"type":"Point"}
}