{
  "type": "Feature",
  "properties": {
    "iso:country":"CH",
    "sg:address":"Eggrainweg 13 4402 Frenkendorf. Postfach",
    "sg:city":"Frenkendorf",
    "sg:orig_category":"Fachdetailhandel in Verkaufsr\u00e4umen",
    "sg:postcode":"4402",
    "sg:province":"Basel-Landschaft",
    "wof:name":"Brunschwig Hockey 2000 Sportartikel; Kauf, Verkauf",
    "wof:placetype":"venue"
},
  "geometry": {"coordinates":[7.7176399231,47.5079345703],"type":"Point"}
}