{
  "type": "Feature",
  "properties": {
    "iso:country":"CH",
    "sg:address":"7543",
    "sg:city":"Lavin",
    "sg:orig_category":"Schulpflegen",
    "sg:postcode":"7543",
    "sg:province":"Graubunden",
    "wof:name":"Schulrat Der Gemeinde Lavin",
    "wof:placetype":"venue"
},
  "geometry": {"coordinates":[10.1114444733,46.7686805725],"type":"Point"}
}