{
  "type": "Feature",
  "properties": {
    "iso:country":"CH",
    "sg:address":"1971",
    "sg:city":"Grimisuat",
    "sg:orig_category":"RESTAURANTS: TEA-ROOMS",
    "sg:phone":"+41 27 398 56 25",
    "sg:postcode":"1971",
    "sg:province":"Valais",
    "wof:name":"Balet Alfred",
    "wof:placetype":"venue"
},
  "geometry": {"coordinates":[7.3788700104,46.2545089722],"type":"Point"}
}