{
  "type": "Feature",
  "properties": {
    "iso:country":"CH",
    "sg:address":"Hummelwaldstrasse 28 8865 Bilten. Postfach",
    "sg:city":"Bilten",
    "sg:orig_category":"Allgemeiner Hochbau Vermietung von Baumaschinen U ger\u00e4ten mit Bedienungspersonal",
    "sg:phone":"+41 55 619 65 15",
    "sg:postcode":"8865",
    "sg:province":"Glarus",
    "wof:name":"Feldmann Pneukran + Transport Ag Pneukranarbeiten, Spezial- U. Schwertransporte Usw.",
    "wof:placetype":"venue"
},
  "geometry": {"coordinates":[9.02058,47.150715],"type":"Point"}
}