{
  "type": "Feature",
  "properties": {
    "iso:country":"CH",
    "sg:address":"Marktgasse 13-15",
    "sg:city":"Winterthur",
    "sg:orig_category":"Wirtschaftspr\u00fcfung, Steuerberatung U Treuhand",
    "sg:postcode":"8400",
    "sg:province":"Z\u00fcrich",
    "wof:name":"Walter Hubert K., Bau-partner + Treuhand",
    "wof:placetype":"venue"
},
  "geometry": {"coordinates":[8.5775709152,47.3268013],"type":"Point"}
}