{
  "type": "Feature",
  "properties": {
    "iso:country":"CH",
    "sg:address":"Moosweg 3",
    "sg:city":"Grossh\u00f6chstetten",
    "sg:orig_category":"Kaminfeger",
    "sg:phone":"+41 79 209 72 94",
    "sg:postcode":"3506",
    "sg:province":"Bern",
    "wof:name":"Heinz Eggenberger Kaminfegergesch\u00e4ft",
    "wof:placetype":"venue"
},
  "geometry": {"coordinates":[8.5534105301,47.31615448],"type":"Point"}
}