{
  "type": "Feature",
  "properties": {
    "iso:country":"CH",
    "sg:address":"Appisbergstrasse 2",
    "sg:city":"M\u00e4nnedorf",
    "sg:orig_category":"Gesundheitswesen",
    "sg:phone":"+41 19227050",
    "sg:postcode":"8708",
    "sg:province":"Z\u00fcrich",
    "wof:name":"Praxis Winkler Gina Ag",
    "wof:placetype":"venue"
},
  "geometry": {"coordinates":[8.6950016022,47.2596626282],"type":"Point"}
}