{
  "type": "Feature",
  "properties": {
    "iso:country":"CH",
    "sg:address":"Hauptstr. 53 4441 Th\u00fcrnen. Postfach",
    "sg:city":"Th\u00fcrnen",
    "sg:orig_category":"Pensionskassen",
    "sg:postcode":"4441",
    "sg:province":"Basel-Landschaft",
    "wof:name":"Personalf\u00fcrsorgestiftung Der Kistenfabrik Und Holzhandels Ag",
    "wof:placetype":"venue"
},
  "geometry": {"coordinates":[7.8296871185,47.4552764893],"type":"Point"}
}