{
  "type": "Feature",
  "properties": {
    "iso:country":"CH",
    "sg:address":"Adlikerstrasse 46 8105 Regensdorf. Postfach",
    "sg:city":"Regensdorf",
    "sg:orig_category":"Kosmetikinstitute Sonstiges K\u00f6rperpflegegewerbe",
    "sg:phone":"+41 41 870 28 28",
    "sg:postcode":"8105",
    "sg:province":"Z\u00fcrich",
    "wof:name":"Moras Paola, Kosmetik Und Parf\u00fcmerie",
    "wof:placetype":"venue"
},
  "geometry": {"coordinates":[8.6508302689,46.8718147278],"type":"Point"}
}