{
  "type": "Feature",
  "properties": {
    "iso:country":"CH",
    "sg:address":"Via Al Ponte 27",
    "sg:city":"Massagno",
    "sg:classifiers":[
        {
            "category":"Restaurant",
            "type":"Food & Drink"
        }
    ],
    "sg:phone":"+41 91 966 28 65",
    "sg:postcode":"6900",
    "sg:province":"Ticino",
    "wof:name":"Osteria Del Ponte",
    "wof:placetype":"venue"
},
  "geometry": {"coordinates":[8.9440937042,46.00938797],"type":"Point"}
}