{
  "type": "Feature",
  "properties": {
    "iso:country":"CH",
    "sg:address":"Brandstrasse 24",
    "sg:city":"Schlieren",
    "sg:classifiers":[
        {
            "category":"Manufacturing",
            "subcategory":"Motor Vehicles & Parts",
            "type":"Manufacturing & Wholesale Goods"
        }
    ],
    "sg:phone":"+41 17327111",
    "sg:postcode":"8952",
    "sg:province":"Z\u00fcrich",
    "sg:tags":[
        "machine",
        "replacement"
    ],
    "wof:name":"H. A. Schlatter Ag",
    "wof:placetype":"venue"
},
  "geometry": {"coordinates":[8.4440879822,47.4014778137],"type":"Point"}
}