{
  "type": "Feature",
  "properties": {
    "iso:country":"CH",
    "sg:address":"Aarbergergasse 10 3011 Bern. Postfach",
    "sg:city":"Bern",
    "sg:orig_category":"Unclassifiable Establishments",
    "sg:postcode":"3005",
    "sg:province":"Bern",
    "wof:name":"Kosmetik-institut Esther, Esther Niederer Kosmetik-institut",
    "wof:placetype":"venue"
},
  "geometry": {"coordinates":[7.4437332153,46.9495010376],"type":"Point"}
}