{
  "type": "Feature",
  "properties": {
    "iso:country":"CH",
    "sg:address":"Brauereiweg 5",
    "sg:city":"Balsthal",
    "sg:classifiers":[
        {
            "category":"Restaurant",
            "type":"Food & Drink"
        }
    ],
    "sg:phone":"+41 41 480 13 78",
    "sg:postcode":"4710",
    "sg:province":"Solothurn",
    "wof:name":"Restaurant Brauerei",
    "wof:placetype":"venue"
},
  "geometry": {"coordinates":[8.0501499176,46.9792861938],"type":"Point"}
}