{
  "type": "Feature",
  "properties": {
    "iso:country":"CH",
    "sg:address":"Tischenloostr. 75",
    "sg:city":"Thalwil",
    "sg:classifiers":[
        {
            "category":"Manufacturing",
            "subcategory":"Wood Products",
            "type":"Manufacturing & Wholesale Goods"
        }
    ],
    "sg:phone":"+41 4117228111",
    "sg:postcode":"8800",
    "sg:province":"Z\u00fcrich",
    "sg:tags":[
        "professional",
        "furniture"
    ],
    "wof:name":"Hunziker Ag Thalwil",
    "wof:placetype":"venue"
},
  "geometry": {"coordinates":[8.5643692017,47.2865943909],"type":"Point"}
}