{
  "type": "Feature",
  "properties": {
    "iso:country":"CH",
    "sg:address":"Bitziring 7 9220 Bischofszell. Postfach",
    "sg:city":"Bischofszell",
    "sg:orig_category":"Softwareentwicklung U beratung",
    "sg:postcode":"9220",
    "sg:province":"Thurgau",
    "wof:name":"B\u00fceler Edv Engineering",
    "wof:placetype":"venue"
},
  "geometry": {"coordinates":[9.2453012466,47.4962539673],"type":"Point"}
}