{
  "type": "Feature",
  "properties": {
    "iso:country":"CH",
    "sg:address":"Gewerbehaus Langmatt",
    "sg:city":"Ormalingen",
    "sg:orig_category":"Herstellung von industriellen Prozesssteuerungsanlagen",
    "sg:postcode":"4466",
    "sg:province":"Basel-Landschaft",
    "wof:name":"Maire W. Sps-steuerungen Sps-steuerungen; Planung, Fabrikation U. Inbetriebnahme",
    "wof:placetype":"venue"
},
  "geometry": {"coordinates":[7.3721818924,47.1777496338],"type":"Point"}
}