{
  "type": "Feature",
  "properties": {
    "iso:country":"CH",
    "sg:address":"Rue Du Canal 11",
    "sg:city":"Cheseaux-nor\u00e9az",
    "sg:orig_category":"Grosshandel mit Eisenwaren sowie Installationsbedarf f\u00fcr Gas, Wasser U Heizung",
    "sg:postcode":"1400",
    "sg:province":"Vaud",
    "wof:name":"Techno Chemin Air S\u00e0rl",
    "wof:placetype":"venue"
},
  "geometry": {"coordinates":[6.6414198875,46.7786331177],"type":"Point"}
}