{
  "type": "Feature",
  "properties": {
    "iso:country":"CH",
    "sg:address":"Arbonerstrasse 10",
    "sg:city":"Amriswil",
    "sg:orig_category":"Gesundheitswesen",
    "sg:postcode":"8580",
    "sg:province":"Thurgau",
    "wof:name":"Der Weg Zur Gesundheit Gamba Z.",
    "wof:placetype":"venue"
},
  "geometry": {"coordinates":[9.3008232117,47.5447158813],"type":"Point"}
}