{
  "type": "Feature",
  "properties": {
    "iso:country":"CH",
    "sg:address":"Br\u00e4menhalden 5",
    "sg:city":"Hirzel",
    "sg:orig_category":"G\u00fcterbef\u00f6rderung im Strassenverkehr",
    "sg:phone":"+41 17299193",
    "sg:postcode":"8816",
    "sg:province":"Z\u00fcrich",
    "wof:name":"Staub Gebr. Transport Ag",
    "wof:placetype":"venue"
},
  "geometry": {"coordinates":[8.6077365875,47.2151069641],"type":"Point"}
}