{
  "type": "Feature",
  "properties": {
    "iso:country":"CH",
    "sg:address":"3368",
    "sg:city":"Bleienbach",
    "sg:orig_category":"Sportvereine Sch\u00fctzen",
    "sg:phone":"+41 62 926 23 26",
    "sg:postcode":"3368",
    "sg:province":"Bern",
    "wof:name":"Sch\u00fctzengesellschaft",
    "wof:placetype":"venue"
},
  "geometry": {"coordinates":[7.756289959,47.1852073669],"type":"Point"}
}