{
  "type": "Feature",
  "properties": {
    "iso:country":"CH",
    "sg:address":"Via Alla Chiesa",
    "sg:city":"Tesserete",
    "sg:orig_category":"Detailhandel mit Brot, Back U S\u00fcsswaren",
    "sg:phone":"+41 91 943 22 17",
    "sg:postcode":"6950",
    "sg:province":"Ticino",
    "wof:name":"Patrick Chiffelle Pasticceria Sport",
    "wof:placetype":"venue"
},
  "geometry": {"coordinates":[8.965389,46.06781],"type":"Point"}
}