{
  "type": "Feature",
  "properties": {
    "iso:country":"CH",
    "sg:address":"G\u00f6bliweg 7",
    "sg:city":"M\u00fcnchenstein",
    "sg:orig_category":"Hardwareberatung",
    "sg:phone":"+41 61 411 66 11",
    "sg:postcode":"4142",
    "sg:province":"Basel-Landschaft",
    "wof:name":"Stauffer Informatik Ag",
    "wof:placetype":"venue"
},
  "geometry": {"coordinates":[7.6220588684,47.5101509094],"type":"Point"}
}