{
  "type": "Feature",
  "properties": {
    "iso:country":"CH",
    "sg:address":"Bachg\u00e4ssli 31",
    "sg:city":"Schnottwil",
    "sg:orig_category":"Detailhandel mit Metallwaren, Anstrichmitteln, Glaswaren, Bau U Heimwerkerbedarf Herstellung von ind",
    "sg:phone":"+41 32 353 11 88",
    "sg:postcode":"3253",
    "sg:province":"Solothurn",
    "wof:name":"Feb Eberhard Automation Gmbh",
    "wof:placetype":"venue"
},
  "geometry": {"coordinates":[7.3855757713,47.1108932495],"type":"Point"}
}