{
  "type": "Feature",
  "properties": {
    "addr:full":"B\u00fcrgerheim 40 Seengen Aargau 5707",
    "addr:housenumber":"40",
    "addr:postcode":"5707",
    "addr:street":"Buergerheim",
    "iso:country":"CH",
    "sg:address":"B\u00fcrgerheim 40",
    "sg:city":"Seengen",
    "sg:classifiers":[
        {
            "category":"Social Services",
            "subcategory":"Retirement Home",
            "type":"Services"
        }
    ],
    "sg:phone":"+41 62 777 16 62",
    "sg:postcode":"5707",
    "sg:province":"Aargau",
    "sg:tags":[
        "pflegeheime",
        "u",
        "alters"
    ],
    "wof:name":"B\u00fcrgerheim",
    "wof:placetype":"venue"
},
  "geometry": {"coordinates":[8.20418,47.326351],"type":"Point"}
}