{
  "type": "Feature",
  "properties": {
    "iso:country":"CH",
    "sg:address":"Buchserstrasse 11",
    "sg:city":"Niederhasli",
    "sg:classifiers":[
        {
            "category":"Restaurant",
            "type":"Food & Drink"
        }
    ],
    "sg:phone":"+41 18501020",
    "sg:postcode":"8155",
    "sg:province":"Z\u00fcrich",
    "wof:name":"Restaurant M\u00fchlehalden",
    "wof:placetype":"venue"
},
  "geometry": {"coordinates":[8.4713802338,47.4653015137],"type":"Point"}
}