{
  "type": "Feature",
  "properties": {
    "iso:country":"CH",
    "sg:address":"Kirchberger Str. 6",
    "sg:city":"G\u00e4hwil",
    "sg:classifiers":[
        {
            "category":"Banks & Credit Unions",
            "subcategory":"Bank",
            "type":"Services"
        }
    ],
    "sg:phone":"+41 71 931 41 81",
    "sg:postcode":"9534",
    "sg:province":"St. Gallen",
    "wof:name":"Spar- Und Leihkasse Kirchberg Sg, Agentur",
    "wof:placetype":"venue"
},
  "geometry": {"coordinates":[9.002021,47.397396],"type":"Point"}
}