{
  "type": "Feature",
  "properties": {
    "iso:country":"CH",
    "sg:address":"Schneidergasse 6",
    "sg:city":"Basel",
    "sg:orig_category":"Kosmetikinstitute",
    "sg:phone":"+41 61 271 51 01",
    "sg:postcode":"4051",
    "sg:province":"Basel-Stadt",
    "wof:name":"Kosmetikinstitut Riva Caroline",
    "wof:placetype":"venue"
},
  "geometry": {"coordinates":[7.5865969658,47.5584602356],"type":"Point"}
}