{
  "type": "Feature",
  "properties": {
    "addr:full":"Hauptstrasse 60 Erlen Thurgau 8586",
    "addr:housenumber":"60",
    "addr:postcode":"8586",
    "addr:street":"Hauptstrasse",
    "iso:country":"CH",
    "sg:address":"Hauptstrasse 60",
    "sg:city":"Erlen",
    "sg:orig_category":"Detailhandel mit Blumen U Pflanzen Fachdetailhandel in Verkaufsr\u00e4umen",
    "sg:phone":"+41 71 648 21 12",
    "sg:postcode":"8586",
    "sg:province":"Thurgau",
    "wof:name":"Weibel Christa, Christa's Blumen",
    "wof:placetype":"venue"
},
  "geometry": {"coordinates":[9.230079,47.54771],"type":"Point"}
}