{
  "type": "Feature",
  "properties": {
    "iso:country":"CH",
    "sg:address":"Hasli",
    "sg:city":"Riggisberg",
    "sg:classifiers":[
        {
            "category":"Restaurant",
            "type":"Food & Drink"
        }
    ],
    "sg:phone":"+41 31 809 01 17",
    "sg:postcode":"3132",
    "sg:province":"Bern",
    "wof:name":"Restaurant R\u00f6ssli",
    "wof:placetype":"venue"
},
  "geometry": {"coordinates":[7.4761800766,46.8206291199],"type":"Point"}
}