{
  "type": "Feature",
  "properties": {
    "iso:country":"CH",
    "sg:address":"St. Johanns-vorstadt 78",
    "sg:city":"Basel",
    "sg:orig_category":"Pensionskassen",
    "sg:phone":"+41 61 272 94 00",
    "sg:postcode":"4056",
    "sg:province":"Basel-Stadt",
    "wof:name":"St. Albanstift",
    "wof:placetype":"venue"
},
  "geometry": {"coordinates":[7.5832309723,47.5653038025],"type":"Point"}
}