{
  "type": "Feature",
  "properties": {
    "iso:country":"CH",
    "sg:address":"Barf\u00fcsserplatz 3 4051 Basel. Postfach",
    "sg:city":"Basel",
    "sg:classifiers":[
        {
            "category":"Professional",
            "subcategory":"Employment Agencies",
            "type":"Services"
        }
    ],
    "sg:phone":"+41 61 271 54 54",
    "sg:postcode":"4051",
    "sg:province":"Basel-Stadt",
    "sg:tags":[
        "personal",
        "u",
        "stellenvermittlung"
    ],
    "wof:name":"Manpower Holding Ag Personalvermittlung Usw",
    "wof:placetype":"venue"
},
  "geometry": {"coordinates":[7.5895748138,47.5551719666],"type":"Point"}
}