{
  "type": "Feature",
  "properties": {
    "iso:country":"CH",
    "sg:address":"Washingtonstrasse 39a",
    "sg:city":"Rorschach",
    "sg:orig_category":"Fachdetailhandel in Verkaufsr\u00e4umen",
    "sg:phone":"+41 71 845 34 27",
    "sg:postcode":"9400",
    "sg:province":"St. Gallen",
    "wof:name":"Markus Hartmeier Velo Nach Wunsch",
    "wof:placetype":"venue"
},
  "geometry": {"coordinates":[9.4895896912,47.4729690552],"type":"Point"}
}