{
  "type": "Feature",
  "properties": {
    "iso:country":"CH",
    "sg:address":"La Cond\u00e9mine",
    "sg:city":"Vuadens",
    "sg:orig_category":"Herstellung von Konstruktionsteilen, Fertigbauteilen U Ausbauelementen aus Holz",
    "sg:phone":"+41 21 635 43 19",
    "sg:postcode":"1628",
    "sg:province":"Fribourg",
    "wof:name":"D\u00e9praz Christian",
    "wof:placetype":"venue"
},
  "geometry": {"coordinates":[6.5957298279,46.5257606506],"type":"Point"}
}