{
  "type": "Feature",
  "properties": {
    "iso:country":"CH",
    "sg:address":"Posthof 7 8200 Schaffhausen. Postfach",
    "sg:city":"Schaffhausen",
    "sg:orig_category":"Detailhandel mit Pelzwaren",
    "sg:phone":"+41 52 624 42 28",
    "sg:postcode":"8201",
    "sg:province":"Schaffhausen",
    "wof:name":"Otto Stemmler Inh.edith B\u00f6ni Pelzmode",
    "wof:placetype":"venue"
},
  "geometry": {"coordinates":[8.632566452,47.6970252991],"type":"Point"}
}