{
  "type": "Feature",
  "properties": {
    "iso:country":"CH",
    "sg:address":"Mittelmatte",
    "sg:city":"Grindelwald",
    "sg:orig_category":"Detailhandel mit Metallwaren, Anstrichmitteln, Glaswaren, Bau U Heimwerkerbedarf",
    "sg:phone":"+41 33 855 15 45",
    "sg:postcode":"3818",
    "sg:province":"Bern",
    "wof:name":"Samuel G. Wyss Ag",
    "wof:placetype":"venue"
},
  "geometry": {"coordinates":[8.0237426758,46.6302757263],"type":"Point"}
}