{
  "type": "Feature",
  "properties": {
    "iso:country":"CH",
    "sg:address":"Erlenstrasse 18",
    "sg:city":"Frauenfeld",
    "sg:orig_category":"Detailhandel mit Musikinstrumenten",
    "sg:phone":"+41 52 720 37 65",
    "sg:postcode":"8500",
    "sg:province":"Thurgau",
    "wof:name":"Andr\u00e9 Schmid Musikalienhandel",
    "wof:placetype":"venue"
},
  "geometry": {"coordinates":[8.8836660385,47.554058075],"type":"Point"}
}