{
  "type": "Feature",
  "properties": {
    "iso:country":"CH",
    "sg:address":"Rue Des Voisins 8",
    "sg:city":"Gen\u00e8ve",
    "sg:orig_category":"Erbringung von Dienstleistungen f\u00fcr Unternehmen Satzherstellung U Reproduktion",
    "sg:phone":"+41 14002477",
    "sg:postcode":"1205",
    "sg:province":"Gen\u00e8ve",
    "wof:name":"Heavy Graphics Gmbh",
    "wof:placetype":"venue"
},
  "geometry": {"coordinates":[8.455909729,47.3601608276],"type":"Point"}
}