{
  "type": "Feature",
  "properties": {
    "iso:country":"CH",
    "sg:address":"Place Du Midi 40 1950 Sion Case Postale 850",
    "sg:city":"Sion",
    "sg:orig_category":"Vermittlung von Immobilien Verwaltung von Immobilien",
    "sg:phone":"+41 27 322 06 91",
    "sg:postcode":"1951",
    "sg:province":"Valais",
    "wof:name":"Pricewaterhousecoopers Ag",
    "wof:placetype":"venue"
},
  "geometry": {"coordinates":[7.3618750572,46.2315254211],"type":"Point"}
}