{
  "type": "Feature",
  "properties": {
    "iso:country":"CH",
    "sg:address":"1373",
    "sg:city":"Chavornay",
    "sg:orig_category":"R\u00fcckgewinnung U Vorbereitung f\u00fcr die Wiederverwertung Recycling von Schrott",
    "sg:phone":"+41 24 441 44 22",
    "sg:postcode":"1373",
    "sg:province":"Vaud",
    "wof:name":"Perret Sa, Successeur De Viglino J.j., Auto-d\u00e9molition Sa",
    "wof:placetype":"venue"
},
  "geometry": {"coordinates":[6.5702109337,46.7084541321],"type":"Point"}
}