{
  "type": "Feature",
  "properties": {
    "iso:country":"CH",
    "sg:address":"Wegackerstrasse 6",
    "sg:city":"Z\u00fcrich",
    "sg:orig_category":"Unternehmensberatung",
    "sg:postcode":"8041",
    "sg:province":"Z\u00fcrich",
    "wof:name":"Gaedicke Rainer Consulting Betriebsberatung, Marketing, Organisation F. Industr., Gewerbe, Handel",
    "wof:placetype":"venue"
},
  "geometry": {"coordinates":[8.5158376694,47.3352928162],"type":"Point"}
}