{
  "type": "Feature",
  "properties": {
    "iso:country":"CH",
    "sg:address":"S\u00e4lihalde 11",
    "sg:city":"Luzern",
    "sg:orig_category":"Vermietung U Verpachtung von eigenen Immobilien",
    "sg:postcode":"6005",
    "sg:province":"Luzern",
    "wof:name":"Immobilien Ag Neues Heim Luzern",
    "wof:placetype":"venue"
},
  "geometry": {"coordinates":[8.2968149185,47.0456542969],"type":"Point"}
}