{
  "type": "Feature",
  "properties": {
    "iso:country":"CH",
    "sg:address":"Kempttalstrasse 103",
    "sg:city":"Illnau",
    "sg:classifiers":[
        {
            "category":"Manufacturing",
            "subcategory":"Wood Products",
            "type":"Manufacturing & Wholesale Goods"
        }
    ],
    "sg:phone":"+41 52 346 14 23",
    "sg:postcode":"8308",
    "sg:province":"Z\u00fcrich",
    "sg:tags":[
        "lumber"
    ],
    "wof:name":"S\u00e4gerei Ag Illnau",
    "wof:placetype":"venue"
},
  "geometry": {"coordinates":[8.7184972763,47.4177131653],"type":"Point"}
}