{
  "type": "Feature",
  "properties": {
    "iso:country":"CH",
    "sg:address":"Place De La Tour",
    "sg:city":"Chalais",
    "sg:orig_category":"Detailhandel mit Musikinstrumenten Detailhandel mit Uhren U Schmuck",
    "sg:phone":"+41 27 455 50 30",
    "sg:postcode":"3966",
    "sg:province":"Valais",
    "wof:name":"Edmond Zufferey Instr.de Musique Orf\u00e8vrerie",
    "wof:placetype":"venue"
},
  "geometry": {"coordinates":[7.5089120865,46.2664527893],"type":"Point"}
}