{
  "type": "Feature",
  "properties": {
    "iso:country":"CH",
    "sg:address":"Sur Menu\u00e9 1",
    "sg:city":"Montagne-moutier",
    "sg:orig_category":"Unclassifiable Establishments",
    "sg:phone":"+41 32 493 73 52",
    "sg:postcode":"2740",
    "sg:province":"Bern",
    "wof:name":"Technospeed 3000 S.a.",
    "wof:placetype":"venue"
},
  "geometry": {"coordinates":[7.3596801758,47.2694854736],"type":"Point"}
}