{
  "type": "Feature",
  "properties": {
    "iso:country":"CH",
    "sg:address":"Hofenstrasse 82c 8708 M\u00e4nnedorf. Postfach",
    "sg:city":"M\u00e4nnedorf",
    "sg:orig_category":"Unternehmensberatung Wirtschaftspr\u00fcfung, Steuerberatung U Treuhand",
    "sg:phone":"+41 17901963",
    "sg:postcode":"8708",
    "sg:province":"Z\u00fcrich",
    "wof:name":"Crn Treuhand + Consulting N\u00f6tzli Conrado, Lic. Oec. Hsg",
    "wof:placetype":"venue"
},
  "geometry": {"coordinates":[8.6945009232,47.2579574585],"type":"Point"}
}