{
  "type": "Feature",
  "properties": {
    "iso:country":"CH",
    "sg:address":"Unterfeld",
    "sg:city":"Buochs",
    "sg:orig_category":"Herstellung von Werkzeugen",
    "sg:phone":"+41 19403420",
    "sg:postcode":"6374",
    "sg:province":"Nidwalden",
    "wof:name":"Bodenmann Heinz Werkzeugbau Ag",
    "wof:placetype":"venue"
},
  "geometry": {"coordinates":[8.7096347809,47.351398468],"type":"Point"}
}