{
  "type": "Feature",
  "properties": {
    "iso:country":"CH",
    "sg:address":"3532",
    "sg:city":"Z\u00e4ziwil",
    "sg:orig_category":"Herstellung von k\u00e4lte U lufttechnischen Erzeugnissen f\u00fcr gewerbliche Zwecke",
    "sg:postcode":"3532",
    "sg:province":"Bern",
    "wof:name":"Klimag Ag, Filiale Mirchel",
    "wof:placetype":"venue"
},
  "geometry": {"coordinates":[7.6618599892,46.9018783569],"type":"Point"}
}