{
  "type": "Feature",
  "properties": {
    "iso:country":"CH",
    "sg:address":"Agassiz Avenue 2 1003 Lausanne. Postfach",
    "sg:city":"Lausanne",
    "sg:orig_category":"Pensionskassen",
    "sg:phone":"+41 21 319 71 11",
    "sg:postcode":"1003",
    "sg:province":"Vaud",
    "wof:name":"Fonds De Pr\u00e9voyance Du Centre Patronal",
    "wof:placetype":"venue"
},
  "geometry": {"coordinates":[6.631734848,46.518119812],"type":"Point"}
}