{
  "type": "Feature",
  "properties": {
    "iso:country":"CH",
    "sg:address":"Dorfstrasse 28",
    "sg:city":"Thierachern",
    "sg:orig_category":"Softwareentwicklung U beratung",
    "sg:postcode":"3634",
    "sg:province":"Bern",
    "wof:name":"F & E Freizeit Erlebnis Gmbh",
    "wof:placetype":"venue"
},
  "geometry": {"coordinates":[7.5738430023,46.7531738281],"type":"Point"}
}