{
  "type": "Feature",
  "properties": {
    "iso:country":"CH",
    "sg:address":"Loostrasse 6",
    "sg:city":"Braunau",
    "sg:orig_category":"D\u00e4mmung gegen K\u00e4lte, W\u00e4rme, Schall U Ersch\u00fctterung Herstellung von Holz U Zellstoff",
    "sg:phone":"+41 77592920",
    "sg:postcode":"9502",
    "sg:province":"Thurgau",
    "wof:name":"Leo Hasler Zellstoffisolationen",
    "wof:placetype":"venue"
},
  "geometry": {"coordinates":[9.0714797974,47.5016822815],"type":"Point"}
}