{
  "type": "Feature",
  "properties": {
    "iso:country":"CH",
    "sg:address":"Stationsstrasse 2 3628 Uttigen. Postfach",
    "sg:city":"Uttigen",
    "sg:orig_category":"Herstellung von Teppichen",
    "sg:postcode":"3628",
    "sg:province":"Bern",
    "wof:name":"Dea Import S\u00e0rl",
    "wof:placetype":"venue"
},
  "geometry": {"coordinates":[6.803756237,47.0897903442],"type":"Point"}
}