{
  "type": "Feature",
  "properties": {
    "iso:country":"CH",
    "sg:address":"3957",
    "sg:city":"Bratsch",
    "sg:classifiers":[
        {
            "category":"Restaurant",
            "type":"Food & Drink"
        }
    ],
    "sg:phone":"+41 27 932 11 92",
    "sg:postcode":"3957",
    "sg:province":"Valais",
    "wof:name":"Restaurant Weisshornblick",
    "wof:placetype":"venue"
},
  "geometry": {"coordinates":[7.7069091797,46.3210601807],"type":"Point"}
}