{
  "type": "Feature",
  "properties": {
    "iso:country":"CH",
    "sg:address":"Kirchstr. 3",
    "sg:city":"Bellach",
    "sg:orig_category":"Unclassifiable Establishments",
    "sg:postcode":"4512",
    "sg:province":"Solothurn",
    "wof:name":"Scheidegger & Partner",
    "wof:placetype":"venue"
},
  "geometry": {"coordinates":[7.4973797798,47.2143135071],"type":"Point"}
}