{
  "type": "Feature",
  "properties": {
    "iso:country":"CH",
    "sg:address":"Monthoux Rue De 21 1201 Gen\u00e8ve. Postfach",
    "sg:city":"Gen\u00e8ve",
    "sg:orig_category":"Herstellung von Lederbekleidung",
    "sg:postcode":"1201",
    "sg:province":"Gen\u00e8ve",
    "wof:name":"Valenti Cuir Distribution, Titulaire Serdar Camoglu",
    "wof:placetype":"venue"
},
  "geometry": {"coordinates":[6.1483302116,46.2104644775],"type":"Point"}
}