{
  "type": "Feature",
  "properties": {
    "iso:country":"CH",
    "sg:address":"Paluds Chemin Des 15",
    "sg:city":"Perroy",
    "sg:orig_category":"Sonstige pers\u00f6nliche Dienstleistungen",
    "sg:postcode":"1166",
    "sg:province":"Vaud",
    "wof:name":"Crystalline S\u00e0rl",
    "wof:placetype":"venue"
},
  "geometry": {"coordinates":[6.3654952049,46.467716217],"type":"Point"}
}