{
  "type": "Feature",
  "properties": {
    "iso:country":"CH",
    "sg:address":"Uttwiler Strasse 3",
    "sg:city":"Dozwil",
    "sg:orig_category":"Herstellung von Kunststoffwaren",
    "sg:phone":"+41 71 414 52 22",
    "sg:postcode":"8580",
    "sg:province":"Thurgau",
    "wof:name":"Ejot Kunststofftechnik Dozwil Ag",
    "wof:placetype":"venue"
},
  "geometry": {"coordinates":[9.2995681763,47.54504776],"type":"Point"}
}