{
  "type": "Feature",
  "properties": {
    "iso:country":"CH",
    "sg:address":"Hopfenweg 21 3007 Bern. Postfach 5775",
    "sg:city":"Bern",
    "sg:orig_category":"Arbeitnehmerverb\u00e4nde",
    "sg:phone":"+41 71 744 50 38",
    "sg:postcode":"3001",
    "sg:province":"Bern",
    "wof:name":"Club Der Berufs- & Gesch\u00e4fts- Frauen St. Gallen/appenzell",
    "wof:placetype":"venue"
},
  "geometry": {"coordinates":[9.63706,47.451038],"type":"Point"}
}