{
  "type": "Feature",
  "properties": {
    "addr:full":"Emmentalstrasse 60 3414 Oberburg. Postfach Oberburg Bern 3414",
    "addr:housenumber":"60",
    "addr:postcode":"3414;3414",
    "addr:street":"Emmentalstrasse",
    "iso:country":"CH",
    "sg:address":"Emmentalstrasse 60 3414 Oberburg. Postfach",
    "sg:city":"Oberburg",
    "sg:orig_category":"Bauschreinerei Innenausbau",
    "sg:phone":"+41 27 722 63 15",
    "sg:postcode":"3414",
    "sg:province":"Bern",
    "wof:name":"Fournier Daniel",
    "wof:placetype":"venue"
},
  "geometry": {"coordinates":[7.085235,46.108364],"type":"Point"}
}