{
  "type": "Feature",
  "properties": {
    "iso:country":"CH",
    "sg:address":"Via Francesco Somaini 5",
    "sg:city":"Lugano",
    "sg:orig_category":"Vermietung U Verpachtung von eigenen Immobilien",
    "sg:postcode":"6900",
    "sg:province":"Ticino",
    "wof:name":"Artimo Ag Immobiliengesellschaft",
    "wof:placetype":"venue"
},
  "geometry": {"coordinates":[9.0657310486,47.4643783569],"type":"Point"}
}