{
  "type": "Feature",
  "properties": {
    "iso:country":"CH",
    "sg:address":"Saumstrasse 7 8003 Z\u00fcrich. Postfach",
    "sg:city":"Z\u00fcrich",
    "sg:orig_category":"Werbung",
    "sg:postcode":"8003",
    "sg:province":"Z\u00fcrich",
    "wof:name":"Smartconnection, Frick Natalie Dienstleistungen Im Bereich Der Projektbezogenen Werbeberatung",
    "wof:placetype":"venue"
},
  "geometry": {"coordinates":[8.5138883591,47.3706092834],"type":"Point"}
}