{
  "type": "Feature",
  "properties": {
    "addr:full":"Via Magazzini Generali 7 6828 Balerna. Postfach Caselle Postale 880 Chiasso Ticino 6830",
    "addr:housenumber":"7",
    "addr:postcode":"6828 balerna. postfach caselle postale 880;6830",
    "addr:street":"Via Magazzini;Ticino",
    "iso:country":"CH",
    "sg:address":"Via Magazzini Generali 7 6828 Balerna. Postfach Caselle Postale 880",
    "sg:city":"Chiasso",
    "sg:orig_category":"Autotransporte M\u00f6bel Autotransporte international",
    "sg:phone":"+41 91 683 25 12",
    "sg:postcode":"6830",
    "sg:province":"Ticino",
    "wof:name":"Bernasconi Fratelli Trasporti Sa",
    "wof:placetype":"venue"
},
  "geometry": {"coordinates":[9.017122,45.839218],"type":"Point"}
}