{
  "type": "Feature",
  "properties": {
    "iso:country":"CH",
    "sg:address":"Rue Des Moulins 7",
    "sg:city":"Neuch\u00e2tel",
    "sg:orig_category":"Detailhandel mit Herrenbekleidung",
    "sg:phone":"+41 32 725 15 12",
    "sg:postcode":"2000",
    "sg:province":"Neuch\u00e2tel",
    "wof:name":"Boutique Paolini",
    "wof:placetype":"venue"
},
  "geometry": {"coordinates":[6.9283099174,46.99193573],"type":"Point"}
}