{
  "type": "Feature",
  "properties": {
    "iso:country":"CH",
    "sg:address":"B\u00fcrenstrasse 1",
    "sg:city":"Meinisberg",
    "sg:orig_category":"Fachdetailhandel in Verkaufsr\u00e4umen Grosshandel mit Blumen U Pflanzen",
    "sg:phone":"+41 52 763 42 52",
    "sg:postcode":"2554",
    "sg:province":"Bern",
    "wof:name":"Besmer Blumenhandel",
    "wof:placetype":"venue"
},
  "geometry": {"coordinates":[9.0043506622,47.5985298157],"type":"Point"}
}