{
  "type": "Feature",
  "properties": {
    "iso:country":"CH",
    "sg:address":"Ziegelgutstrasse 22",
    "sg:city":"Oberburg",
    "sg:orig_category":"Betrieb von Sportanlagen",
    "sg:phone":"+41 34 424 10 30",
    "sg:postcode":"3414",
    "sg:province":"Bern",
    "wof:name":"Golfschule Oberburg Ag",
    "wof:placetype":"venue"
},
  "geometry": {"coordinates":[7.633597,47.028744],"type":"Point"}
}