{
  "type": "Feature",
  "properties": {
    "iso:country":"CH",
    "sg:address":"Kreuzlinger Strasse 59",
    "sg:city":"Oberaach",
    "sg:orig_category":"Herstellung von sonstigen landwirtschaftlichen Maschinen Mechanische Werkst\u00e4tten",
    "sg:phone":"+41 71 411 67 48",
    "sg:postcode":"8587",
    "sg:province":"Thurgau",
    "wof:name":"Geissb\u00fchler Agrardienst Ag",
    "wof:placetype":"venue"
},
  "geometry": {"coordinates":[9.2697353363,47.5536956787],"type":"Point"}
}