{
  "type": "Feature",
  "properties": {
    "iso:country":"CH",
    "sg:address":"Rue Des Moulins 2",
    "sg:city":"Del\u00e9mont",
    "sg:orig_category":"Herstellung von Elektromotoren, Generatoren U Transformatoren",
    "sg:postcode":"2800",
    "sg:province":"Jura",
    "wof:name":"Edj Energie Du Jura Sa",
    "wof:placetype":"venue"
},
  "geometry": {"coordinates":[7.344976902,47.3653640747],"type":"Point"}
}