{
  "type": "Feature",
  "properties": {
    "iso:country":"CH",
    "sg:address":"Friedhofstrasse 112",
    "sg:city":"Z\u00fcrich",
    "sg:orig_category":"Fachdetailhandel in Verkaufsr\u00e4umen",
    "sg:postcode":"8048",
    "sg:province":"Z\u00fcrich",
    "wof:name":"Br\u00fcgger Collection Modische Artikel, Modeschmuck; Handel",
    "wof:placetype":"venue"
},
  "geometry": {"coordinates":[8.4742002487,47.3828010559],"type":"Point"}
}