{
  "type": "Feature",
  "properties": {
    "iso:country":"CH",
    "sg:address":"Hirschenweg 9",
    "sg:city":"Magden",
    "sg:orig_category":"Organisationen des Gesundheitswesen",
    "sg:phone":"+41 61 841 26 00",
    "sg:postcode":"4312",
    "sg:province":"Aargau",
    "wof:name":"Haus-& Krankenpflegeverein Magden",
    "wof:placetype":"venue"
},
  "geometry": {"coordinates":[7.8148469925,47.5274200439],"type":"Point"}
}