{
  "type": "Feature",
  "properties": {
    "iso:country":"CH",
    "sg:address":"Breisacherstrasse 54 4057 Basel. Postfach",
    "sg:city":"Basel",
    "sg:orig_category":"Herstellung von k\u00e4lte U lufttechnischen Erzeugnissen f\u00fcr gewerbliche Zwecke Sanit\u00e4r U Heizungsinstal",
    "sg:phone":"+41 71 755 39 15",
    "sg:postcode":"4007",
    "sg:province":"Basel-Stadt",
    "wof:name":"Ulmann Franz Ag",
    "wof:placetype":"venue"
},
  "geometry": {"coordinates":[9.5575857162,47.3783836365],"type":"Point"}
}