{
  "type": "Feature",
  "properties": {
    "iso:country":"CH",
    "sg:address":"Dorf 62",
    "sg:city":"Heimenschwand",
    "sg:orig_category":"Verwertung von Milch",
    "sg:phone":"+41 33 453 16 65",
    "sg:postcode":"3615",
    "sg:province":"Bern",
    "wof:name":"Hofer Johann",
    "wof:placetype":"venue"
},
  "geometry": {"coordinates":[7.6989898682,46.8285522461],"type":"Point"}
}