{
  "type": "Feature",
  "properties": {
    "iso:country":"CH",
    "sg:address":"Morand Rue Marc 22",
    "sg:city":"Martigny",
    "sg:orig_category":"Non-Classified Establishments",
    "sg:phone":"+41 31 931 95 14",
    "sg:postcode":"1920",
    "sg:province":"Valais",
    "wof:name":"Fondation Certitude, Servitude",
    "wof:placetype":"venue"
},
  "geometry": {"coordinates":[7.0713381767,46.1046218872],"type":"Point"}
}