{
  "type": "Feature",
  "properties": {
    "iso:country":"CH",
    "sg:address":"Grand'rue 1 1510 Moudon Case Postale 214",
    "sg:city":"Moudon",
    "sg:orig_category":"Detailhandel mit Waren verschiedener Art, Hauptrichtung Nichtnahrungsmittel Warenh\u00e4user",
    "sg:phone":"+41 21 905 17 91",
    "sg:postcode":"1510",
    "sg:province":"Vaud",
    "wof:name":"Grands Magasins La Placette C. Bladt Sa Succursale De Moudon",
    "wof:placetype":"venue"
},
  "geometry": {"coordinates":[6.7962222099,46.6697273254],"type":"Point"}
}