{
  "type": "Feature",
  "properties": {
    "iso:country":"CH",
    "sg:address":"Strecia Di Ruggia",
    "sg:city":"Morcote",
    "sg:orig_category":"Grosshandel mit sonstigen Maschinen U Ausr\u00fcstungen f\u00fcr Industrie, Handel U Schiffahrt",
    "sg:phone":"+41 79 621 58 03",
    "sg:postcode":"6922",
    "sg:province":"Ticino",
    "wof:name":"R.e.s.l.consulting Di E.romano Rappresentanze Industriali",
    "wof:placetype":"venue"
},
  "geometry": {"coordinates":[8.915895462,45.9227638245],"type":"Point"}
}