{
  "type": "Feature",
  "properties": {
    "iso:country":"CH",
    "sg:address":"Saatlenstrasse 13",
    "sg:city":"Z\u00fcrich",
    "sg:orig_category":"Geb\u00e4ude, Wohnungsreinigung Sonstiges Reinigungsgewerbe",
    "sg:postcode":"8000",
    "sg:province":"Z\u00fcrich",
    "wof:name":"A Plus Reinigungen Gmbh B\u00fcro- Wohnungs-& Autoreinigung",
    "wof:placetype":"venue"
},
  "geometry": {"coordinates":[8.7992839813,47.2014427185],"type":"Point"}
}