{
  "type": "Feature",
  "properties": {
    "iso:country":"CH",
    "sg:address":"Lachenstrasse 1",
    "sg:city":"Kriessern",
    "sg:classifiers":[
        {
            "category":"Government",
            "subcategory":"Post Office",
            "type":"Public Place"
        }
    ],
    "sg:phone":"+41 71 755 10 35",
    "sg:postcode":"9451",
    "sg:province":"St. Gallen",
    "sg:tags":[
        "caf\u00e9s",
        "tea-rooms"
    ],
    "wof:name":"Caf\u00e9 Pony",
    "wof:placetype":"venue"
},
  "geometry": {"coordinates":[9.6066637039,47.366645813],"type":"Point"}
}