{
  "type": "Feature",
  "properties": {
    "iso:country":"CH",
    "sg:address":"Kirchstrasse 17 8274 Gottlieben. Postfach 254",
    "sg:city":"Gottlieben",
    "sg:orig_category":"Grosshandel mit Flachglas, Sanit\u00e4rkeramik U Anstrichmitteln Maler U Glasergewerbe",
    "sg:phone":"+41 81 756 23 93",
    "sg:postcode":"8274",
    "sg:province":"Thurgau",
    "wof:name":"Farben Tischhauser Ag",
    "wof:placetype":"venue"
},
  "geometry": {"coordinates":[9.4709978104,47.1644134521],"type":"Point"}
}