{
  "type": "Feature",
  "properties": {
    "iso:country":"CH",
    "sg:address":"Route Blonay",
    "sg:city":"Brent",
    "sg:orig_category":"Detailhandel mit Waren verschiedener Art, Hauptrichtung Nahrungsmittel",
    "sg:phone":"+41 21 964 34 19",
    "sg:postcode":"1817",
    "sg:province":"Vaud",
    "wof:name":"Jacqueline Cochard Epicerie",
    "wof:placetype":"venue"
},
  "geometry": {"coordinates":[6.9008097649,46.4588394165],"type":"Point"}
}