{
  "type": "Feature",
  "properties": {
    "iso:country":"CH",
    "sg:address":"Chemin Baconni\u00e8re 49",
    "sg:city":"Boudry",
    "sg:orig_category":"Automaten Herstellung Ingenieurb\u00fcros Maschinenbau",
    "sg:phone":"+41 32 841 78 00",
    "sg:postcode":"2017",
    "sg:province":"Neuch\u00e2tel",
    "wof:name":"Patric Concept Sa Automation",
    "wof:placetype":"venue"
},
  "geometry": {"coordinates":[6.840211,46.95673],"type":"Point"}
}