{
  "type": "Feature",
  "properties": {
    "iso:country":"CH",
    "sg:address":"Asylstrasse 84",
    "sg:city":"M\u00e4nnedorf",
    "sg:orig_category":"Non-Classified Establishments",
    "sg:postcode":"8708",
    "sg:province":"Z\u00fcrich",
    "wof:name":"Greve Hanselmann & Partner Marcom Services Gmbh",
    "wof:placetype":"venue"
},
  "geometry": {"coordinates":[8.70291996,47.2493400574],"type":"Point"}
}