{
  "type": "Feature",
  "properties": {
    "iso:country":"CH",
    "sg:address":"Avenue De La Gare 37",
    "sg:city":"Gueuroz",
    "sg:orig_category":"Fussreflexzonenmassage",
    "sg:phone":"+41 27 722 00 55",
    "sg:postcode":"1920",
    "sg:province":"Valais",
    "wof:name":"Raymond An\u00e7ay R\u00e9flexoth\u00e9rapie",
    "wof:placetype":"venue"
},
  "geometry": {"coordinates":[7.0729198456,46.1013793945],"type":"Point"}
}