{
  "type": "Feature",
  "properties": {
    "iso:country":"CH",
    "sg:address":"Allenwinden",
    "sg:city":"Baar",
    "sg:orig_category":"Allgemeiner Hoch U Tiefbau",
    "sg:postcode":"6340",
    "sg:province":"Zug",
    "wof:name":"Arnold A., Baugesch\u00e4ft",
    "wof:placetype":"venue"
},
  "geometry": {"coordinates":[8.549694,47.175728],"type":"Point"}
}