{
  "type": "Feature",
  "properties": {
    "iso:country":"CH",
    "sg:address":"Untere Rebgasse 22 4005 Basel. Postfach 323",
    "sg:city":"Basel",
    "sg:orig_category":"Grosshandel mit elektrischen Haushaltsger\u00e4ten Herstellung von elektrischen Lampen U Leuchten",
    "sg:phone":"+41 61 373 34 40",
    "sg:postcode":"4005",
    "sg:province":"Basel-Stadt",
    "wof:name":"Lightmaster Systems, Reiniger Und Partner",
    "wof:placetype":"venue"
},
  "geometry": {"coordinates":[7.5921750069,47.5629272461],"type":"Point"}
}