{
  "type": "Feature",
  "properties": {
    "iso:country":"CH",
    "sg:address":"Untere Bahnhofstrasse 12",
    "sg:city":"Bonaduz",
    "sg:orig_category":"RESTAURANTS: TEA-ROOMS",
    "sg:phone":"+41 81 641 17 87",
    "sg:postcode":"7402",
    "sg:province":"Graubunden",
    "wof:name":"Stiefenhofer Franz.",
    "wof:placetype":"venue"
},
  "geometry": {"coordinates":[9.3978767395,46.8109016418],"type":"Point"}
}