{
  "type": "Feature",
  "properties": {
    "iso:country":"CH",
    "sg:address":"Rue De L'arc-en-ciel 10",
    "sg:city":"Bussigny-lausanne",
    "sg:orig_category":"Architektur U Ingenieurb\u00fcros Datenverarbeitungsdienste",
    "sg:phone":"+41 13715471",
    "sg:postcode":"1030",
    "sg:province":"Vaud",
    "wof:name":"Business Images Cgd Ag Computer-graphics",
    "wof:placetype":"venue"
},
  "geometry": {"coordinates":[8.249986,47.459435],"type":"Point"}
}