{
  "type": "Feature",
  "properties": {
    "iso:country":"CH",
    "sg:address":"La C\u00e9zille",
    "sg:city":"Begnins",
    "sg:classifiers":[
        {
            "category":"Restaurant",
            "type":"Food & Drink"
        }
    ],
    "sg:phone":"+41 22 366 11 68",
    "sg:postcode":"1268",
    "sg:province":"Vaud",
    "wof:name":"Restaurant Du Moulin",
    "wof:placetype":"venue"
},
  "geometry": {"coordinates":[6.2470698357,46.4407958984],"type":"Point"}
}