{
  "type": "Feature",
  "properties": {
    "iso:country":"CH",
    "sg:address":"Gemeindehausstrasse 1 6010 Kriens. Postfach 1436",
    "sg:city":"Kriens",
    "sg:orig_category":"Weiterbildungskurse and Seminar Anbieter",
    "sg:phone":"+41 19306696",
    "sg:postcode":"6011",
    "sg:province":"Luzern",
    "wof:name":"S&b Ag Schulung & Beratung",
    "wof:placetype":"venue"
},
  "geometry": {"coordinates":[8.7994213104,47.3266601562],"type":"Point"}
}