{
  "type": "Feature",
  "properties": {
    "iso:country":"CH",
    "sg:address":"Weissensteinstrasse 20",
    "sg:city":"Langendorf",
    "sg:orig_category":"Detailhandel mit elektrischen Haushalts, Radio U Fernsehger\u00e4ten ohne ausgepr\u00e4gten Schwerpunkt",
    "sg:phone":"+41 32 621 49 15",
    "sg:postcode":"4513",
    "sg:province":"Solothurn",
    "wof:name":"Hans Zaugg Elektro Ag",
    "wof:placetype":"venue"
},
  "geometry": {"coordinates":[7.5151309967,47.2205886841],"type":"Point"}
}