{
  "type": "Feature",
  "properties": {
    "iso:country":"CH",
    "sg:address":"B\u00fcntgasse 12",
    "sg:city":"N\u00e4fels",
    "sg:orig_category":"Sonstiger spezialisierter Hoch U Tiefbau",
    "sg:postcode":"8752",
    "sg:province":"Glarus",
    "wof:name":"Landolt Roman",
    "wof:placetype":"venue"
},
  "geometry": {"coordinates":[9.0601987839,47.0980415344],"type":"Point"}
}