{
  "type": "Feature",
  "properties": {
    "iso:country":"CH",
    "sg:address":"Kr\u00e4hb\u00fchlstrasse 90",
    "sg:city":"Z\u00fcrich",
    "sg:orig_category":"Saunas Solarien",
    "sg:phone":"+41 19346060",
    "sg:postcode":"8044",
    "sg:province":"Z\u00fcrich",
    "wof:name":"Sun World Ag",
    "wof:placetype":"venue"
},
  "geometry": {"coordinates":[8.7938747406,47.3109474182],"type":"Point"}
}