{
  "type": "Feature",
  "properties": {
    "iso:country":"CH",
    "sg:address":"Grienbachstrasse",
    "sg:city":"Baar",
    "sg:orig_category":"Pensionskassen",
    "sg:phone":"+41 41 767 10 00",
    "sg:postcode":"6340",
    "sg:province":"Zug",
    "wof:name":"Pensionskasse-stiftung Der Rittmeyer Ag",
    "wof:placetype":"venue"
},
  "geometry": {"coordinates":[8.5310630798,47.1825485229],"type":"Point"}
}