{
  "type": "Feature",
  "properties": {
    "addr:full":"Stadthausstrasse 87 Winterthur Z\u00fcrich 8400",
    "addr:housenumber":"87",
    "addr:postcode":"8400",
    "addr:street":"Stadthausstrasse",
    "iso:country":"CH",
    "sg:address":"Stadthausstrasse 87",
    "sg:city":"Winterthur",
    "sg:orig_category":"Detailhandel mit Damenbekleidung",
    "sg:phone":"+41 52 203 23 04",
    "sg:postcode":"8400",
    "sg:province":"Z\u00fcrich",
    "wof:name":"Bea Werz Secondhandladen 5",
    "wof:placetype":"venue"
},
  "geometry": {"coordinates":[8.728653,47.500046],"type":"Point"}
}