{
  "type": "Feature",
  "properties": {
    "iso:country":"CH",
    "sg:address":"Avenue Du G\u00e9n\u00e9ral-guisan 53",
    "sg:city":"Fribourg",
    "sg:orig_category":"Primarschulen",
    "sg:postcode":"1700",
    "sg:province":"Fribourg",
    "wof:name":"Ecole Primaire Du Jura A",
    "wof:placetype":"venue"
},
  "geometry": {"coordinates":[7.1496701241,46.8116226196],"type":"Point"}
}