{
  "type": "Feature",
  "properties": {
    "iso:country":"CH",
    "sg:address":"Avenue Du Midi 7",
    "sg:city":"Fribourg",
    "sg:classifiers":[
        {
            "category":"Restaurant",
            "type":"Food & Drink"
        }
    ],
    "sg:phone":"+41 55 286 26 90",
    "sg:postcode":"1700",
    "sg:province":"Fribourg",
    "sg:tags":[
        "tea-rooms",
        "restaurants"
    ],
    "wof:name":"Caf\u00e9-restaurant M\u00fcrtschen Marty",
    "wof:placetype":"venue"
},
  "geometry": {"coordinates":[8.9213428497,47.2407341003],"type":"Point"}
}