{
  "type": "Feature",
  "properties": {
    "iso:country":"CH",
    "sg:address":"Z\u00fcrcherstrasse 208",
    "sg:city":"Frauenfeld",
    "sg:orig_category":"Sonstige Institutionen des Sozialwesens ohne Beherbergung",
    "sg:phone":"+41 52 721 77 48",
    "sg:postcode":"8500",
    "sg:province":"Thurgau",
    "wof:name":"Erziehungs-& Eheberatungs- Stelle",
    "wof:placetype":"venue"
},
  "geometry": {"coordinates":[8.8999500275,47.5579948425],"type":"Point"}
}