{
  "type": "Feature",
  "properties": {
    "iso:country":"CH",
    "sg:address":"Route De Gen\u00e8ve 10",
    "sg:city":"Crassier",
    "sg:orig_category":"Detailhandel mit Waren verschiedener Art, Hauptrichtung Nahrungsmittel Herstellung von sonstigen Nah",
    "sg:phone":"+41 22 367 16 27",
    "sg:postcode":"1263",
    "sg:province":"Vaud",
    "wof:name":"Graziano-ercolani Angela",
    "wof:placetype":"venue"
},
  "geometry": {"coordinates":[6.1637058258,46.3733787537],"type":"Point"}
}