{
  "type": "Feature",
  "properties": {
    "iso:country":"CH",
    "sg:address":"M\u00e4henriedweg 2",
    "sg:city":"Dietlikon",
    "sg:orig_category":"Grosshandel mit Parf\u00fcmerieartikeln U K\u00f6rperpflegemitteln Parf\u00fcmerien U sonstiger Detailhandel mit ko",
    "sg:phone":"+41 56 442 44 33",
    "sg:postcode":"8305",
    "sg:province":"Z\u00fcrich",
    "wof:name":"Alrodo Ag Parfum-& Kosmetikhandel",
    "wof:placetype":"venue"
},
  "geometry": {"coordinates":[8.2079238892,47.4831848145],"type":"Point"}
}