{
  "type": "Feature",
  "properties": {
    "iso:country":"CH",
    "sg:address":"Kirchgasse 2",
    "sg:city":"Chur",
    "sg:orig_category":"Finanzierungsinstitutionen",
    "sg:phone":"+41 81 252 63 96",
    "sg:postcode":"7000",
    "sg:province":"Graubunden",
    "wof:name":"Capital Contor Ag Chur",
    "wof:placetype":"venue"
},
  "geometry": {"coordinates":[9.532579422,46.8479385376],"type":"Point"}
}