{
  "type": "Feature",
  "properties": {
    "iso:country":"CH",
    "sg:address":"6676",
    "sg:city":"Bignasco",
    "sg:orig_category":"Sportvereine Eissport Eishockey",
    "sg:postcode":"6676",
    "sg:province":"Ticino",
    "wof:name":"Hockey Club Bignasco",
    "wof:placetype":"venue"
},
  "geometry": {"coordinates":[8.6071300507,46.3385009766],"type":"Point"}
}