{
  "type": "Feature",
  "properties": {
    "iso:country":"CH",
    "sg:address":"Fries Rue Hans- 1",
    "sg:city":"Freiburg",
    "sg:orig_category":"Handelsvermittlung von Nahrungsmitteln, Getr\u00e4nken U Tabakwaren",
    "sg:postcode":"1700",
    "sg:province":"Fribourg",
    "wof:name":"Lhtw Sa",
    "wof:placetype":"venue"
},
  "geometry": {"coordinates":[7.1527738571,46.8000068665],"type":"Point"}
}