{
  "type": "Feature",
  "properties": {
    "iso:country":"CH",
    "sg:address":"Remisbergstrasse 11",
    "sg:city":"Kreuzlingen",
    "sg:orig_category":"Gartenbau",
    "sg:phone":"+41 71 688 20 10",
    "sg:postcode":"8280",
    "sg:province":"Thurgau",
    "wof:name":"Hans Zollinger G\u00e4rtnerei",
    "wof:placetype":"venue"
},
  "geometry": {"coordinates":[9.180891037,47.6434288025],"type":"Point"}
}