{
  "type": "Feature",
  "properties": {
    "iso:country":"CH",
    "sg:address":"Nelkenweg 3 9410 Heiden. Postfach 41",
    "sg:city":"Heiden",
    "sg:orig_category":"Bauschreinerei Herstellung von Konstruktionsteilen, Fertigbauteilen U Ausbauelementen aus Holz",
    "sg:phone":"+41 71 891 12 37",
    "sg:postcode":"9410",
    "sg:province":"Appenzell Ausserrhoden",
    "wof:name":"Bach Heiden Ag",
    "wof:placetype":"venue"
},
  "geometry": {"coordinates":[9.52743,47.447372],"type":"Point"}
}