{
  "type": "Feature",
  "properties": {
    "addr:full":"Chemin De La Vallombreuse 39 Lausanne Vaud 1004",
    "addr:housenumber":"39",
    "addr:postcode":"1004",
    "addr:street":"Chemin De La Vallombreuse",
    "iso:country":"CH",
    "sg:address":"Chemin De La Vallombreuse 39",
    "sg:city":"Lausanne",
    "sg:orig_category":"Bauspenglerei Sanit\u00e4rinstallation",
    "sg:phone":"+41 21 646 23 00",
    "sg:postcode":"1004",
    "sg:province":"Vaud",
    "wof:name":"Ren\u00e9 Hunziker Ferblanterie & Appareillage",
    "wof:placetype":"venue"
},
  "geometry": {"coordinates":[6.613798,46.533688],"type":"Point"}
}