{
  "type": "Feature",
  "properties": {
    "iso:country":"CH",
    "sg:address":"Amthausgasse 9 4242 Laufen. Postfach",
    "sg:city":"Laufen",
    "sg:orig_category":"Architekturb\u00fcros",
    "sg:phone":"+41 61 761 33 49",
    "sg:postcode":"4242",
    "sg:province":"Basel-Landschaft",
    "wof:name":"Hanspeter Karrer Architekturb\u00fcro",
    "wof:placetype":"venue"
},
  "geometry": {"coordinates":[7.500977,47.423084],"type":"Point"}
}