{
  "type": "Feature",
  "properties": {
    "iso:country":"CH",
    "sg:address":"Hertensteinstrasse 12",
    "sg:city":"Luzern",
    "sg:orig_category":"Zahnarztpraxen",
    "sg:phone":"+41 41 410 57 77",
    "sg:postcode":"6004",
    "sg:province":"Luzern",
    "wof:name":"Dr. Med. Dent. Markus B\u00fcel Zahnarzt",
    "wof:placetype":"venue"
},
  "geometry": {"coordinates":[8.3100500107,47.0554466248],"type":"Point"}
}