{
  "type": "Feature",
  "properties": {
    "iso:country":"CH",
    "sg:address":"Im Chrummenacher 4",
    "sg:city":"Illnau",
    "sg:orig_category":"Fahrschulen, Flugschulen",
    "sg:phone":"+41 52 346 29 74",
    "sg:postcode":"8308",
    "sg:province":"Z\u00fcrich",
    "wof:name":"Stefano Wagner Amf Auto & Motorrad Fahrschule",
    "wof:placetype":"venue"
},
  "geometry": {"coordinates":[8.7191638947,47.40417099],"type":"Point"}
}