{
  "type": "Feature",
  "properties": {
    "iso:country":"CH",
    "sg:address":"Martin Rue Frank- 8-10 1204 Gen\u00e8ve. Postfach",
    "sg:city":"Gen\u00e8ve",
    "sg:orig_category":"Finanzierungsinstitutionen",
    "sg:postcode":"1201",
    "sg:province":"Gen\u00e8ve",
    "wof:name":"Delfacto Ag",
    "wof:placetype":"venue"
},
  "geometry": {"coordinates":[8.3107671738,46.9828834534],"type":"Point"}
}