{
  "type": "Feature",
  "properties": {
    "iso:country":"CH",
    "sg:address":"C\u00f4te Rue De La 85",
    "sg:city":"Neuch\u00e2tel",
    "sg:orig_category":"Fachdetailhandel in Verkaufsr\u00e4umen",
    "sg:postcode":"2000",
    "sg:province":"Neuch\u00e2tel",
    "wof:name":"Aquarium Benz",
    "wof:placetype":"venue"
},
  "geometry": {"coordinates":[9.3252897263,47.4245796204],"type":"Point"}
}