{
  "type": "Feature",
  "properties": {
    "iso:country":"CH",
    "sg:address":"B\u00fcmplizstrasse 69",
    "sg:city":"Bern",
    "sg:orig_category":"Emergency Generator Plant Planning, Consulting, Development",
    "sg:phone":"+41 31 997 84 11",
    "sg:postcode":"3018",
    "sg:province":"Bern",
    "wof:name":"Hans Hodel Ag",
    "wof:placetype":"venue"
},
  "geometry": {"coordinates":[7.3924021721,46.9454231262],"type":"Point"}
}