{
  "type": "Feature",
  "properties": {
    "iso:country":"CH",
    "sg:address":"6563 Mesocco. Postfach",
    "sg:city":"Mesocco",
    "sg:classifiers":[
        {
            "category":"Bars & Pubs",
            "type":"Food & Drink"
        }
    ],
    "sg:postcode":"6563",
    "sg:province":"Graubunden",
    "wof:name":"Barella Fasani C. Sagl Bar, Ristoranti, Alberghi Ecc",
    "wof:placetype":"venue"
},
  "geometry": {"coordinates":[9.2329,46.391632],"type":"Point"}
}