{
  "type": "Feature",
  "properties": {
    "iso:country":"CH",
    "sg:address":"Gandegg 4",
    "sg:city":"Schattdorf",
    "sg:orig_category":"Grosshandel mit sonstigen Gebrauchs U Verbrauchsg\u00fctern",
    "sg:postcode":"6467",
    "sg:province":"Uri",
    "wof:name":"Gisler Walter Sprengtechnik",
    "wof:placetype":"venue"
},
  "geometry": {"coordinates":[8.6474342346,46.8606109619],"type":"Point"}
}