{
  "type": "Feature",
  "properties": {
    "iso:country":"CH",
    "sg:address":"G\u00fcterstrasse 141 4053 Basel. Postfach",
    "sg:city":"Basel",
    "sg:orig_category":"Architektur U Ingenieurb\u00fcros",
    "sg:postcode":"4051",
    "sg:province":"Basel-Stadt",
    "wof:name":"Jaquet Claude-eric",
    "wof:placetype":"venue"
},
  "geometry": {"coordinates":[6.872165,47.128548],"type":"Point"}
}