{
  "type": "Feature",
  "properties": {
    "iso:country":"CH",
    "sg:address":"In Der Luberzen 1",
    "sg:city":"Urdorf",
    "sg:orig_category":"Pensionskassen",
    "sg:postcode":"8902",
    "sg:province":"Z\u00fcrich",
    "wof:name":"Wohlfahrtsfonds Der D\u00c4twyler Holding Ag",
    "wof:placetype":"venue"
},
  "geometry": {"coordinates":[8.639749527,46.8880310059],"type":"Point"}
}