{
  "type": "Feature",
  "properties": {
    "iso:country":"CH",
    "sg:address":"Coremmo Via 14a 6900 Lugano. Postfach",
    "sg:city":"Lugano",
    "sg:orig_category":"Grosshandel mit Getr\u00e4nken",
    "sg:postcode":"6900",
    "sg:province":"Ticino",
    "wof:name":"Oenotriae Vinum Sa",
    "wof:placetype":"venue"
},
  "geometry": {"coordinates":[8.9450063705,46.0080451965],"type":"Point"}
}