{
  "type": "Feature",
  "properties": {
    "iso:country":"CH",
    "sg:address":"Baumgartenstrasse 6",
    "sg:city":"M\u00e4genwil",
    "sg:orig_category":"Steuerberatung Wirtschaftspr\u00fcfung, Steuerberatung U Treuhand",
    "sg:phone":"+41 62 896 00 20",
    "sg:postcode":"5506",
    "sg:province":"Aargau",
    "wof:name":"Magra Steuer Und Finanzoptimierung Graber Martin",
    "wof:placetype":"venue"
},
  "geometry": {"coordinates":[8.2294845581,47.4120979309],"type":"Point"}
}