{
  "type": "Feature",
  "properties": {
    "iso:country":"CH",
    "sg:address":"Kantonsstrasse 64",
    "sg:city":"Freienbach",
    "sg:orig_category":"Handel mit Motorr\u00e4dern, Teilen U Zubeh\u00f6r Instandhaltung U Reparatur von Motorr\u00e4dern",
    "sg:phone":"+41 55 410 35 88",
    "sg:postcode":"8807",
    "sg:province":"Schwyz",
    "wof:name":"Rowe Moto's Zweiradsport Rothenberger",
    "wof:placetype":"venue"
},
  "geometry": {"coordinates":[8.7539272308,47.2066802979],"type":"Point"}
}