{
  "type": "Feature",
  "properties": {
    "iso:country":"CH",
    "sg:address":"Mettlengasse 133a",
    "sg:city":"Wattenwil",
    "sg:orig_category":"Bauschreinerei",
    "sg:phone":"+41 33 356 14 90",
    "sg:postcode":"3665",
    "sg:province":"Bern",
    "wof:name":"Heinz Rohrer & Peter Schmid Schreinerei",
    "wof:placetype":"venue"
},
  "geometry": {"coordinates":[7.510547,46.759583],"type":"Point"}
}