{
  "type": "Feature",
  "properties": {
    "iso:country":"CH",
    "sg:address":"Sackstrasse 18",
    "sg:city":"Wernetshausen",
    "sg:orig_category":"Herstellung von keramischen Wand U Bodenfliesen U platten Verlegen von Fliesen U Platten",
    "sg:phone":"+41 71 633 10 89",
    "sg:postcode":"8342",
    "sg:province":"Z\u00fcrich",
    "wof:name":"Haller Erich",
    "wof:placetype":"venue"
},
  "geometry": {"coordinates":[9.1571493149,47.5481681824],"type":"Point"}
}