{
  "type": "Feature",
  "properties": {
    "iso:country":"CH",
    "sg:address":"Zugerstrasse 34 6314 Unter\u00e4geri. Postfach 40",
    "sg:city":"Unter\u00e4geri",
    "sg:orig_category":"Detailhandel mit Radio U Fernsehger\u00e4ten Herstellung von Radio U Fernsehger\u00e4ten sowie phono U videote",
    "sg:postcode":"6314",
    "sg:province":"Zug",
    "wof:name":"Cellular Products, Mauro Lazzarini",
    "wof:placetype":"venue"
},
  "geometry": {"coordinates":[8.5789403915,47.1379699707],"type":"Point"}
}