{
  "type": "Feature",
  "properties": {
    "iso:country":"CH",
    "sg:address":"Hertistrasse 326",
    "sg:city":"Wallisellen",
    "sg:orig_category":"Unternehmensberatung",
    "sg:phone":"+41 18833322",
    "sg:postcode":"8304",
    "sg:province":"Z\u00fcrich",
    "wof:name":"Milestone International Ag",
    "wof:placetype":"venue"
},
  "geometry": {"coordinates":[8.5770902634,47.4148788452],"type":"Point"}
}