{
  "type": "Feature",
  "properties": {
    "iso:country":"CH",
    "sg:address":"Via Adamini 28",
    "sg:city":"Lugano",
    "sg:classifiers":[
        {
            "category":"Government",
            "subcategory":"Post Office",
            "type":"Public Place"
        }
    ],
    "sg:phone":"+41 91 994 40 94",
    "sg:postcode":"6900",
    "sg:province":"Ticino",
    "sg:tags":[
        "caf\u00e9s",
        "tea-rooms"
    ],
    "wof:name":"Tea-room El Cid",
    "wof:placetype":"venue"
},
  "geometry": {"coordinates":[8.9435796738,45.997428894],"type":"Point"}
}