{
  "type": "Feature",
  "properties": {
    "iso:country":"CH",
    "sg:address":"Avenue De Provence 82",
    "sg:city":"Lausanne",
    "sg:orig_category":"Allgemeiner Hochbau Strassenbau",
    "sg:phone":"+41 21 623 47 01",
    "sg:postcode":"1007",
    "sg:province":"Vaud",
    "wof:name":"Aeschlimann Ag Strassenbau & Asphaltierungen",
    "wof:placetype":"venue"
},
  "geometry": {"coordinates":[6.61136,46.523411],"type":"Point"}
}