{
  "type": "Feature",
  "properties": {
    "iso:country":"CH",
    "sg:address":"F\u00fcrstenlandstrasse 99",
    "sg:city":"St.gallen",
    "sg:orig_category":"Unternehmensberatung Vermittlung von Immobilien",
    "sg:phone":"+41 71 231 48 48",
    "sg:postcode":"9000",
    "sg:province":"St. Gallen",
    "wof:name":"Kb Immoservice Ag",
    "wof:placetype":"venue"
},
  "geometry": {"coordinates":[9.3477201462,47.4136199951],"type":"Point"}
}