{
  "type": "Feature",
  "properties": {
    "iso:country":"CH",
    "sg:address":"Heuigstrasse 295",
    "sg:city":"B\u00f6zen",
    "sg:orig_category":"Dachdeckerei",
    "sg:phone":"+41 62 876 12 31",
    "sg:postcode":"5076",
    "sg:province":"Aargau",
    "wof:name":"Rudolf Pfister Bedachungen",
    "wof:placetype":"venue"
},
  "geometry": {"coordinates":[8.085347,47.49741],"type":"Point"}
}