{
  "type": "Feature",
  "properties": {
    "addr:full":"Heuigstrasse 295 B\u00f6zen Aargau 5076",
    "addr:housenumber":"295",
    "addr:postcode":"5076",
    "addr:street":"Heuigstrasse",
    "iso:country":"CH",
    "sg:address":"Heuigstrasse 295",
    "sg:city":"B\u00f6zen",
    "sg:orig_category":"Dachdeckerei",
    "sg:phone":"+41 62 876 12 31",
    "sg:postcode":"5076",
    "sg:province":"Aargau",
    "wof:name":"Rudolf Pfister Bedachungen",
    "wof:placetype":"venue"
},
  "geometry": {"coordinates":[8.085347,47.49741],"type":"Point"}
}