{
  "type": "Feature",
  "properties": {
    "iso:country":"CH",
    "sg:address":"Mellingerstrasse 138",
    "sg:city":"Baden",
    "sg:orig_category":"Sonstige mit der Informatik verbundene T\u00e4tigkeiten",
    "sg:phone":"+41 56 210 31 00",
    "sg:postcode":"5400",
    "sg:province":"Aargau",
    "wof:name":"Bommeli Comsupport",
    "wof:placetype":"venue"
},
  "geometry": {"coordinates":[8.2940759659,47.4675521851],"type":"Point"}
}