{
  "type": "Feature",
  "properties": {
    "iso:country":"CH",
    "sg:address":"Wildbachstrasse 8",
    "sg:city":"Winterthur",
    "sg:orig_category":"Massagestudios",
    "sg:phone":"+41 52 232 32 06",
    "sg:postcode":"8400",
    "sg:province":"Z\u00fcrich",
    "wof:name":"Max Frei Massagen",
    "wof:placetype":"venue"
},
  "geometry": {"coordinates":[8.7316503525,47.4950218201],"type":"Point"}
}