{
  "type": "Feature",
  "properties": {
    "iso:country":"CH",
    "sg:address":"T\u00f6sstalstrasse 34",
    "sg:city":"Turbenthal",
    "sg:orig_category":"Detailhandel mit elektrischen Haushalts-,Radio U Fernsehger\u00e4ten sowie Musikinstrumenten",
    "sg:phone":"+41 33 783 18 19",
    "sg:postcode":"8488",
    "sg:province":"Z\u00fcrich",
    "wof:name":"Radio Tv, Heimberg M.",
    "wof:placetype":"venue"
},
  "geometry": {"coordinates":[7.4417681694,46.6581420898],"type":"Point"}
}