{
  "type": "Feature",
  "properties": {
    "iso:country":"CH",
    "sg:address":"Hauptstrasse 63",
    "sg:city":"Zuchwil",
    "sg:orig_category":"Detailhandel mit Brot, Back U S\u00fcsswaren",
    "sg:phone":"+41 32 685 15 14",
    "sg:postcode":"4528",
    "sg:province":"Solothurn",
    "wof:name":"Werner R\u00fcegsegger B\u00e4ckerei-konditorei",
    "wof:placetype":"venue"
},
  "geometry": {"coordinates":[7.556562,47.203411],"type":"Point"}
}