{
  "type": "Feature",
  "properties": {
    "iso:country":"CH",
    "sg:address":"Maihofstrasse 4",
    "sg:city":"Luzern",
    "sg:classifiers":[
        {
            "category":"Restaurant",
            "type":"Food & Drink"
        }
    ],
    "sg:phone":"+41 41 420 10 13",
    "sg:postcode":"6004",
    "sg:province":"Luzern",
    "wof:name":"Restaurant Felsenegg",
    "wof:placetype":"venue"
},
  "geometry": {"coordinates":[8.3090543747,47.0612754822],"type":"Point"}
}