{
  "type": "Feature",
  "properties": {
    "iso:country":"CH",
    "sg:address":"Place Bel-air 1",
    "sg:city":"Lausanne",
    "sg:orig_category":"Detailhandel mit Radio U Fernsehger\u00e4ten Detailhandel mit fotografischen Artikeln",
    "sg:phone":"+41 21 351 00 91",
    "sg:postcode":"1003",
    "sg:province":"Vaud",
    "wof:name":"Interdiscount Ag Hi-fi Video Photo Radio",
    "wof:placetype":"venue"
},
  "geometry": {"coordinates":[6.6292219162,46.5220947266],"type":"Point"}
}