{
  "type": "Feature",
  "properties": {
    "iso:country":"CH",
    "sg:address":"Bahnhofstrasse 25",
    "sg:city":"Wallisellen",
    "sg:classifiers":[
        {
            "category":"Building & Trades",
            "subcategory":"Cleaning & Sanitation",
            "type":"Services"
        }
    ],
    "sg:phone":"+41 18306166",
    "sg:postcode":"8304",
    "sg:province":"Z\u00fcrich",
    "sg:tags":[
        "carpet"
    ],
    "wof:name":"Yavuz Textil Handels Gmbh",
    "wof:placetype":"venue"
},
  "geometry": {"coordinates":[8.59238,47.413136],"type":"Point"}
}