{
  "type": "Feature",
  "properties": {
    "iso:country":"CH",
    "sg:address":"St. Annaweg 14 4112 B\u00e4ttwil-fl\u00fch. Postfach",
    "sg:city":"Fl\u00fch",
    "sg:orig_category":"Unternehmensberatung",
    "sg:phone":"+41 61 733 93 10",
    "sg:postcode":"4112",
    "sg:province":"Solothurn",
    "wof:name":"Polek Quality Systems",
    "wof:placetype":"venue"
},
  "geometry": {"coordinates":[7.4943919182,47.4825057983],"type":"Point"}
}