{
  "type": "Feature",
  "properties": {
    "iso:country":"CH",
    "sg:address":"Chemin Des Grandes-vies",
    "sg:city":"Porrentruy",
    "sg:orig_category":"Sonstige Kultur U Unterhaltungseinrichtungen",
    "sg:phone":"+41 32 466 37 06",
    "sg:postcode":"2900",
    "sg:province":"Jura",
    "wof:name":"Cirque Starlight S\u00e0rl",
    "wof:placetype":"venue"
},
  "geometry": {"coordinates":[7.0812220573,47.4309806824],"type":"Point"}
}