{
  "type": "Feature",
  "properties": {
    "iso:country":"CH",
    "sg:address":"Wyd\u00e4ckerring 59",
    "sg:city":"Z\u00fcrich",
    "sg:orig_category":"Herstellung von Tanks U Sammelbeh\u00e4ltern aus Metall Sonstiger spezialisierter Hoch U Tiefbau",
    "sg:phone":"+41 14916768",
    "sg:postcode":"8047",
    "sg:province":"Z\u00fcrich",
    "wof:name":"Protank Ag",
    "wof:placetype":"venue"
},
  "geometry": {"coordinates":[8.4945850372,47.370803833],"type":"Point"}
}