{
  "type": "Feature",
  "properties": {
    "iso:country":"CH",
    "sg:address":"Technikumstrasse 14",
    "sg:city":"Buchs",
    "sg:classifiers":[
        {
            "category":"Professional",
            "subcategory":"Management & Consulting",
            "type":"Services"
        }
    ],
    "sg:phone":"+41 81 756 12 60",
    "sg:postcode":"9470",
    "sg:province":"St. Gallen",
    "sg:tags":[
        "consultancy"
    ],
    "wof:name":"Atw Management Ag",
    "wof:placetype":"venue"
},
  "geometry": {"coordinates":[9.476811409,47.1692123413],"type":"Point"}
}