{
  "type": "Feature",
  "properties": {
    "iso:country":"CH",
    "sg:address":"Einhornstrasse 7a",
    "sg:city":"H\u00fcnenberg",
    "sg:orig_category":"Dienstleistungen von Beteiligungsgesellschaften",
    "sg:postcode":"6331",
    "sg:province":"Zug",
    "wof:name":"Marketing Information & Communication Services, Inc., Dover, H\u00fcnenberg Branch",
    "wof:placetype":"venue"
},
  "geometry": {"coordinates":[8.4254722595,47.1761741638],"type":"Point"}
}