{
  "type": "Feature",
  "properties": {
    "iso:country":"CH",
    "sg:address":"Sch\u00f6nblickstrasse 3",
    "sg:city":"Meggen",
    "sg:orig_category":"Non-Classified Establishments",
    "sg:postcode":"6045",
    "sg:province":"Luzern",
    "wof:name":"Nspm Ag Project Management In Business & Marketing",
    "wof:placetype":"venue"
},
  "geometry": {"coordinates":[8.3690500259,47.0445365906],"type":"Point"}
}