{
  "type": "Feature",
  "properties": {
    "iso:country":"CH",
    "sg:address":"Luzernerstrasse 55a 6030 Ebikon. Postfach 145",
    "sg:city":"Ebikon",
    "sg:orig_category":"Malerei",
    "sg:phone":"+41 41 420 84 00",
    "sg:postcode":"6031",
    "sg:province":"Luzern",
    "wof:name":"B\u00f6sch & Co Auto-& M\u00f6belspritzerei",
    "wof:placetype":"venue"
},
  "geometry": {"coordinates":[8.3237943649,47.0713768005],"type":"Point"}
}