{
  "type": "Feature",
  "properties": {
    "iso:country":"CH",
    "sg:address":"Rebgartenstrasse 9 4124 Sch\u00f6nenbuch. Postfach 82",
    "sg:city":"Sch\u00f6nenbuch",
    "sg:orig_category":"Sanit\u00e4r U Heizungsinstallation Sanit\u00e4rinstallation",
    "sg:phone":"+41 79 219 77 47",
    "sg:postcode":"4124",
    "sg:province":"Basel-Landschaft",
    "wof:name":"S\u00fctterlin Patrick W\u00e4rmetechnik",
    "wof:placetype":"venue"
},
  "geometry": {"coordinates":[7.5036931038,47.5373573303],"type":"Point"}
}