{
  "type": "Feature",
  "properties": {
    "iso:country":"CH",
    "sg:address":"St-fran\u00e7ois Avenue",
    "sg:city":"Veyras",
    "sg:orig_category":"M\u00f6belschreinereien",
    "sg:phone":"+41 27 456 12 16",
    "sg:postcode":"3968",
    "sg:province":"Valais",
    "wof:name":"Donati Graziano",
    "wof:placetype":"venue"
},
  "geometry": {"coordinates":[7.5378551483,46.3040618896],"type":"Point"}
}