{
  "type": "Feature",
  "properties": {
    "iso:country":"CH",
    "sg:address":"Seestrasse 75 8820 W\u00e4denswil. Postfach",
    "sg:city":"W\u00e4denswil",
    "sg:orig_category":"Grosshandel mit Holz U Baustoffen",
    "sg:phone":"+41 17807358",
    "sg:postcode":"8820",
    "sg:province":"Z\u00fcrich",
    "wof:name":"Landis Bruno Leichtbau, Trockenbau, Trennwand Und Deckenmontagen",
    "wof:placetype":"venue"
},
  "geometry": {"coordinates":[8.6768140793,47.2268257141],"type":"Point"}
}