{
  "type": "Feature",
  "properties": {
    "iso:country":"CH",
    "sg:address":"Matten",
    "sg:city":"Gams",
    "sg:orig_category":"Vereine Musik/Blasmusik",
    "sg:phone":"+41 71 243 38 24",
    "sg:postcode":"9473",
    "sg:province":"St. Gallen",
    "wof:name":"B\u00fcrgermusik Gossau",
    "wof:placetype":"venue"
},
  "geometry": {"coordinates":[9.2548904419,47.4220199585],"type":"Point"}
}