{
  "type": "Feature",
  "properties": {
    "iso:country":"CH",
    "sg:address":"L\u00e4ttichstrasse 4a",
    "sg:city":"Baar",
    "sg:orig_category":"Herstellung von sonstigen Maschinen f\u00fcr bestimmte Verwendung",
    "sg:phone":"+41 41 750 49 72",
    "sg:postcode":"6340",
    "sg:province":"Zug",
    "wof:name":"3 D Ag Hologramme Usw.; Entwicklung, Produktion, Handel U. Maschinenherstellung",
    "wof:placetype":"venue"
},
  "geometry": {"coordinates":[8.5394067764,47.1984939575],"type":"Point"}
}