{
  "type": "Feature",
  "properties": {
    "iso:country":"CH",
    "sg:address":"Sch\u00fcrmattstrasse 6-8",
    "sg:city":"G\u00fcmligen",
    "sg:classifiers":[
        {
            "category":"Government",
            "subcategory":"Fire Station",
            "type":"Public Place"
        }
    ],
    "sg:phone":"+41 31 951 49 68",
    "sg:postcode":"3073",
    "sg:province":"Bern",
    "sg:tags":[
        "shutdown",
        "emergency",
        "system"
    ],
    "wof:name":"Jl-technik (schweiz) Gmbh",
    "wof:placetype":"venue"
},
  "geometry": {"coordinates":[7.497086,46.935043],"type":"Point"}
}