{
  "type": "Feature",
  "properties": {
    "iso:country":"CH",
    "sg:address":"Bahnhofstrasse 13",
    "sg:city":"Dulliken",
    "sg:orig_category":"Arztpraxen",
    "sg:phone":"+41 62 295 70 80",
    "sg:postcode":"4657",
    "sg:province":"Solothurn",
    "wof:name":"Dr.med. Dominique Aubry Praxis F\u00fcr Klass.hom\u00f6opathie",
    "wof:placetype":"venue"
},
  "geometry": {"coordinates":[7.946535,47.351269],"type":"Point"}
}