{
  "type": "Feature",
  "properties": {
    "iso:country":"CH",
    "sg:address":"Maienstrasse 9-11",
    "sg:city":"Z\u00fcrich",
    "sg:orig_category":"Primarschulen",
    "sg:phone":"+41 13126644",
    "sg:postcode":"8050",
    "sg:province":"Z\u00fcrich",
    "wof:name":"Primarschule K\u00fcgeliloo",
    "wof:placetype":"venue"
},
  "geometry": {"coordinates":[8.5286846161,47.4104537964],"type":"Point"}
}