{
  "type": "Feature",
  "properties": {
    "iso:country":"CH",
    "sg:address":"Kropfackerstrasse 2",
    "sg:city":"Berneck",
    "sg:orig_category":"Mechanische Werkst\u00e4tten",
    "sg:phone":"+41 71 744 66 16",
    "sg:postcode":"9442",
    "sg:province":"St. Gallen",
    "wof:name":"Armin Keller Ag Pr\u00e4zisionsmechanik",
    "wof:placetype":"venue"
},
  "geometry": {"coordinates":[9.617518425,47.4264945984],"type":"Point"}
}