{
  "type": "Feature",
  "properties": {
    "iso:country":"CH",
    "sg:address":"Rue De Eglise Catholique 6",
    "sg:city":"Montreux",
    "sg:orig_category":"Detailhandel mit Blumen U Pflanzen",
    "sg:phone":"+41 21 963 01 01",
    "sg:postcode":"1820",
    "sg:province":"Vaud",
    "wof:name":"Fleurid\u00e9es Marianne Martin",
    "wof:placetype":"venue"
},
  "geometry": {"coordinates":[6.911324,46.431038],"type":"Point"}
}