{
  "type": "Feature",
  "properties": {
    "iso:country":"CH",
    "sg:address":"Kirchstrasse 72",
    "sg:city":"K\u00f6niz",
    "sg:orig_category":"Maturit\u00e4tsschulen, Lehrerseminarien",
    "sg:phone":"+41 31 972 00 77",
    "sg:postcode":"3098",
    "sg:province":"Bern",
    "wof:name":"Gymnasium K\u00f6niz Lerbermatt Sekretariat",
    "wof:placetype":"venue"
},
  "geometry": {"coordinates":[7.4353709221,46.9308433533],"type":"Point"}
}