{
  "type": "Feature",
  "properties": {
    "iso:country":"CH",
    "sg:address":"Alte Bernstrasse 6",
    "sg:city":"Solothurn",
    "sg:orig_category":"Elektroinstallation Herstellung von Elektromotoren, Generatoren U Transformatoren",
    "sg:phone":"+41 32 625 70 80",
    "sg:postcode":"4500",
    "sg:province":"Solothurn",
    "wof:name":"Elektro-schmid.",
    "wof:placetype":"venue"
},
  "geometry": {"coordinates":[7.537320137,47.2023658752],"type":"Point"}
}