{
  "type": "Feature",
  "properties": {
    "iso:country":"CH",
    "sg:address":"Hauptstrasse 403",
    "sg:city":"Rohrbach",
    "sg:orig_category":"Grosshandel mit Holz U Bauelementen aus Holz",
    "sg:phone":"+41 62 965 22 00",
    "sg:postcode":"4938",
    "sg:province":"Bern",
    "wof:name":"Hiag Handel Bern Ag Steimle & Grob",
    "wof:placetype":"venue"
},
  "geometry": {"coordinates":[7.8179411888,47.1333045959],"type":"Point"}
}