{
  "type": "Feature",
  "properties": {
    "addr:full":"Oeleweg 1a Attiswil Bern 4536",
    "addr:housenumber":"1a",
    "addr:postcode":"4536",
    "addr:street":"Oeleweg",
    "iso:country":"CH",
    "sg:address":"Oeleweg 1a",
    "sg:city":"Attiswil",
    "sg:orig_category":"Allgemeiner Hoch U Tiefbau Hoch U Tiefbau",
    "sg:phone":"+41 32 637 23 91",
    "sg:postcode":"4536",
    "sg:province":"Bern",
    "wof:name":"Max Meyer Ag",
    "wof:placetype":"venue"
},
  "geometry": {"coordinates":[7.612924,47.248051],"type":"Point"}
}