{
  "type": "Feature",
  "properties": {
    "iso:country":"CH",
    "sg:address":"Hauptstrasse 164",
    "sg:city":"Recherswil",
    "sg:orig_category":"Grosshandel mit Blumen U Pflanzen Herstellung von sonstigen keramischen Erzeugnissen f\u00fcr technische ",
    "sg:phone":"+41 32 675 25 15",
    "sg:postcode":"4565",
    "sg:province":"Solothurn",
    "wof:name":"Freba Ag",
    "wof:placetype":"venue"
},
  "geometry": {"coordinates":[7.5931148529,47.1582374573],"type":"Point"}
}