{
  "type": "Feature",
  "properties": {
    "iso:country":"CH",
    "sg:address":"8784",
    "sg:city":"Braunwald",
    "sg:orig_category":"Landw. Genossenschaften Viehzucht",
    "sg:phone":"+41 55 643 13 28",
    "sg:postcode":"8784",
    "sg:province":"Glarus",
    "wof:name":"Viehzuchtgenossenschaft",
    "wof:placetype":"venue"
},
  "geometry": {"coordinates":[8.9982004166,46.9389533997],"type":"Point"}
}