{
  "type": "Feature",
  "properties": {
    "iso:country":"CH",
    "sg:address":"Steinhofstrasse 10",
    "sg:city":"Luzern",
    "sg:orig_category":"Gesundheitswesen",
    "sg:phone":"+41 71 911 56 37",
    "sg:postcode":"6005",
    "sg:province":"Luzern",
    "wof:name":"Stadler Andrea",
    "wof:placetype":"venue"
},
  "geometry": {"coordinates":[9.0451850891,47.4632034302],"type":"Point"}
}