{
  "type": "Feature",
  "properties": {
    "addr:full":"Alexanderweg 27 Naters Valais 3904",
    "addr:housenumber":"27",
    "addr:postcode":"3904",
    "addr:street":"Alexanderweg",
    "iso:country":"CH",
    "sg:address":"Alexanderweg 27",
    "sg:city":"Naters",
    "sg:orig_category":"Grosshandel mit elektrischen Haushaltsger\u00e4ten Rechtsberatung",
    "sg:phone":"+41 22 343 81 30",
    "sg:postcode":"3904",
    "sg:province":"Valais",
    "wof:name":"Aprotec Sa",
    "wof:placetype":"venue"
},
  "geometry": {"coordinates":[6.136423,46.18354],"type":"Point"}
}