{
  "type": "Feature",
  "properties": {
    "iso:country":"CH",
    "sg:address":"Bruggackerstrasse 17",
    "sg:city":"Felben",
    "sg:orig_category":"Bauschreinerei Herstellung von Konstruktionsteilen, Fertigbauteilen U Ausbauelementen aus Holz",
    "sg:phone":"+41 52 765 12 96",
    "sg:postcode":"8552",
    "sg:province":"Thurgau",
    "wof:name":"Schmid Albert",
    "wof:placetype":"venue"
},
  "geometry": {"coordinates":[8.94254,47.579632],"type":"Point"}
}