{
  "type": "Feature",
  "properties": {
    "iso:country":"CH",
    "sg:address":"1898",
    "sg:city":"St-gingolph",
    "sg:orig_category":"Schulpflegen",
    "sg:postcode":"1898",
    "sg:province":"Valais",
    "wof:name":"Commission Scolaire De L'\u00e9cole Secondaire",
    "wof:placetype":"venue"
},
  "geometry": {"coordinates":[7.2124481201,46.0804595947],"type":"Point"}
}