{
  "type": "Feature",
  "properties": {
    "iso:country":"CH",
    "sg:address":"En Bocherens",
    "sg:city":"Assens",
    "sg:orig_category":"Architektur U Ingenieurb\u00fcros Unterhalt U Reparatur im Hoch U Tiefbau",
    "sg:phone":"+41 21 882 58 17",
    "sg:postcode":"1042",
    "sg:province":"Vaud",
    "wof:name":"G. Colaone Ma\u00e7onnerie S\u00e0rl",
    "wof:placetype":"venue"
},
  "geometry": {"coordinates":[6.6212,46.614136],"type":"Point"}
}