{
  "type": "Feature",
  "properties": {
    "iso:country":"CH",
    "sg:address":"Via Campagna 2a",
    "sg:city":"Lugano",
    "sg:orig_category":"Grosshandel mit Holz U Baustoffen Grosshandel mit sonstigen Maschinen U Ausr\u00fcstungen f\u00fcr Industrie, ",
    "sg:phone":"+41 71 311 46 56",
    "sg:postcode":"6900",
    "sg:province":"Ticino",
    "wof:name":"Verma Theuretzbacher Handelsfirma F.bau & Industrie",
    "wof:placetype":"venue"
},
  "geometry": {"coordinates":[9.3183336258,47.4162940979],"type":"Point"}
}