{
  "type": "Feature",
  "properties": {
    "iso:country":"CH",
    "sg:address":"Rue De L'ath\u00e9n\u00e9e 26",
    "sg:city":"Gen\u00e8ve",
    "sg:orig_category":"Herstellung von Spirituosen",
    "sg:phone":"+41 22 347 13 64",
    "sg:postcode":"1206",
    "sg:province":"Gen\u00e8ve",
    "wof:name":"Perroud Raymond",
    "wof:placetype":"venue"
},
  "geometry": {"coordinates":[6.1527919769,46.1954917908],"type":"Point"}
}