{
  "type": "Feature",
  "properties": {
    "iso:country":"CH",
    "sg:address":"Rue Du Chalet 41",
    "sg:city":"Tramlingen",
    "sg:orig_category":"Non-Classified Establishments",
    "sg:postcode":"2720",
    "sg:province":"Bern",
    "wof:name":"Dealmathec Mathez Philippe",
    "wof:placetype":"venue"
},
  "geometry": {"coordinates":[7.0953121185,47.2243537903],"type":"Point"}
}