{
  "type": "Feature",
  "properties": {
    "iso:country":"CH",
    "sg:address":"General Wille-strasse 96 8706 Feldmeilen. Postfach",
    "sg:city":"Feldmeilen",
    "sg:orig_category":"Herstellung von nachrichtentechnischen Ger\u00e4ten U Einrichtungen",
    "sg:phone":"+41 19232274",
    "sg:postcode":"8706",
    "sg:province":"Z\u00fcrich",
    "wof:name":"Oranjetrade Gmbh Mobilkommunikationszubeh\u00f6r, Waren; Im, Export, Handel",
    "wof:placetype":"venue"
},
  "geometry": {"coordinates":[8.6153907776,47.2786636353],"type":"Point"}
}