{
  "type": "Feature",
  "properties": {
    "iso:country":"CH",
    "sg:address":"Tramstrasse 77",
    "sg:city":"Z\u00fcrich",
    "sg:orig_category":"Grosshandel mit Erzen U Metallen",
    "sg:phone":"+41 13117774",
    "sg:postcode":"8050",
    "sg:province":"Z\u00fcrich",
    "wof:name":"Oskar Meyer Stahl & Elektroden Ag",
    "wof:placetype":"venue"
},
  "geometry": {"coordinates":[8.5545911789,47.4082489014],"type":"Point"}
}