{
  "type": "Feature",
  "properties": {
    "iso:country":"CH",
    "sg:address":"Eggiwilstrasse 29 A",
    "sg:city":"Signau",
    "sg:orig_category":"Pensionskassen",
    "sg:postcode":"3534",
    "sg:province":"Bern",
    "wof:name":"Personalf\u00fcrsorgestiftung Der Wk-paletten Ag",
    "wof:placetype":"venue"
},
  "geometry": {"coordinates":[7.7470221519,46.9219589233],"type":"Point"}
}