{
  "type": "Feature",
  "properties": {
    "iso:country":"CH",
    "sg:address":"Limmattalstrasse 157",
    "sg:city":"Z\u00fcrich",
    "sg:orig_category":"Kinderkrippen U horte",
    "sg:phone":"+41 13416393",
    "sg:postcode":"8049",
    "sg:province":"Z\u00fcrich",
    "wof:name":"Kinderkrippe Des Frauenvereins H\u00f6ngg",
    "wof:placetype":"venue"
},
  "geometry": {"coordinates":[8.5013475418,47.4011535645],"type":"Point"}
}