{
  "type": "Feature",
  "properties": {
    "iso:country":"CH",
    "sg:address":"Bahnhofstrasse 9 6410 Goldau. Postfach 275",
    "sg:city":"Goldau",
    "sg:orig_category":"Zahnarztpraxen",
    "sg:phone":"+41 79 689 30 60",
    "sg:postcode":"6410",
    "sg:province":"Schwyz",
    "wof:name":"Dr. Med. Dent. Lado Razinger Zahnarzt",
    "wof:placetype":"venue"
},
  "geometry": {"coordinates":[8.54728508,47.0493125916],"type":"Point"}
}