{
  "type": "Feature",
  "properties": {
    "iso:country":"CH",
    "sg:address":"Burgstrasse 33",
    "sg:city":"Thun",
    "sg:orig_category":"W\u00e4schereien",
    "sg:phone":"+41 81 833 49 46",
    "sg:postcode":"3600",
    "sg:province":"Bern",
    "wof:name":"Ermanno Bombardieri W\u00e4scherei & Gl\u00e4tterei",
    "wof:placetype":"venue"
},
  "geometry": {"coordinates":[9.8367233276,46.4875907898],"type":"Point"}
}