{
  "type": "Feature",
  "properties": {
    "iso:country":"CH",
    "sg:address":"Laufenstrasse 4",
    "sg:city":"R\u00f6schenz",
    "sg:orig_category":"Bauschreinerei Herstellung von Konstruktionsteilen, Fertigbauteilen U Ausbauelementen aus Holz",
    "sg:phone":"+41 61 761 36 02",
    "sg:postcode":"4244",
    "sg:province":"Basel-Landschaft",
    "wof:name":"M. Wehrli, Schreinerei + Parkett",
    "wof:placetype":"venue"
},
  "geometry": {"coordinates":[7.480342,47.423107],"type":"Point"}
}