{
  "type": "Feature",
  "properties": {
    "iso:country":"CH",
    "sg:address":"Friedhofweg 5",
    "sg:city":"Niederg\u00f6sgen",
    "sg:orig_category":"Handel mit Motorr\u00e4dern, Teilen U Zubeh\u00f6r Instandhaltung U Reparatur von Motorr\u00e4dern",
    "sg:postcode":"5013",
    "sg:province":"Solothurn",
    "wof:name":"Velo-shop Zimmermann P.",
    "wof:placetype":"venue"
},
  "geometry": {"coordinates":[7.987953186,47.3746376038],"type":"Point"}
}