{
  "type": "Feature",
  "properties": {
    "addr:full":"M\u00fchleport 3770 Zweisimmen. Postfach 268 Zweisimmen Bern 3770",
    "addr:housenumber":"268",
    "addr:postcode":"3770;3770",
    "addr:street":"Zweisimmen. Postfach",
    "iso:country":"CH",
    "sg:address":"M\u00fchleport 3770 Zweisimmen. Postfach 268",
    "sg:city":"Zweisimmen",
    "sg:orig_category":"Berufliche Weiterbildung, Erwachsenenbildung",
    "sg:phone":"+41 33 722 28 92",
    "sg:postcode":"3770",
    "sg:province":"Bern",
    "wof:name":"Regionales Zivilschutz- Ausbildungszentrum",
    "wof:placetype":"venue"
},
  "geometry": {"coordinates":[7.369931,46.552574],"type":"Point"}
}