{
  "type": "Feature",
  "properties": {
    "iso:country":"CH",
    "sg:address":"Alte Landstrasse 1",
    "sg:city":"M\u00e4nnedorf",
    "sg:orig_category":"RESTAURANTS: TEA-ROOMS",
    "sg:phone":"+41 19200318",
    "sg:postcode":"8708",
    "sg:province":"Z\u00fcrich",
    "wof:name":"Restaurant Bahnh\u00f6fli, Zilkic",
    "wof:placetype":"venue"
},
  "geometry": {"coordinates":[8.6794490814,47.2592582703],"type":"Point"}
}