{
  "type": "Feature",
  "properties": {
    "iso:country":"CH",
    "sg:address":"Im Zentrum 18",
    "sg:city":"Volketswil",
    "sg:orig_category":"Detailhandel mit Bekleidung",
    "sg:phone":"+41 19463931",
    "sg:postcode":"8604",
    "sg:province":"Z\u00fcrich",
    "wof:name":"Boutique 4 Jahreszeiten Jaggi Doris",
    "wof:placetype":"venue"
},
  "geometry": {"coordinates":[8.68109,47.388134],"type":"Point"}
}