{
  "type": "Feature",
  "properties": {
    "iso:country":"CH",
    "sg:address":"Schulstrasse 19",
    "sg:city":"Schlieren",
    "sg:orig_category":"Kinderkrippen U horte",
    "sg:phone":"+41 17308885",
    "sg:postcode":"8952",
    "sg:province":"Z\u00fcrich",
    "wof:name":"Kinderhort N\u00e4hh\u00fcsli",
    "wof:placetype":"venue"
},
  "geometry": {"coordinates":[8.4520816803,47.3971252441],"type":"Point"}
}