{
  "type": "Feature",
  "properties": {
    "iso:country":"CH",
    "sg:address":"Mooshofstrasse 10",
    "sg:city":"Berom\u00fcnster",
    "sg:orig_category":"Vermittlung von Immobilien Verwaltung von Immobilien",
    "sg:phone":"+41 62 771 74 44",
    "sg:postcode":"6215",
    "sg:province":"Luzern",
    "wof:name":"Pemag Treuhand Ag",
    "wof:placetype":"venue"
},
  "geometry": {"coordinates":[8.198217392,47.2030677795],"type":"Point"}
}