{
  "type": "Feature",
  "properties": {
    "iso:country":"CH",
    "sg:address":"Hammerstrasse 6 8180 B\u00fclach. Postfach",
    "sg:city":"B\u00fclach",
    "sg:orig_category":"Finanzierungsinstitutionen",
    "sg:phone":"+41 18725757",
    "sg:postcode":"8180",
    "sg:province":"Z\u00fcrich",
    "wof:name":"Fx-consulting Ag Handel Mit Devisen",
    "wof:placetype":"venue"
},
  "geometry": {"coordinates":[8.5388822556,47.5084877014],"type":"Point"}
}