{
  "type": "Feature",
  "properties": {
    "iso:country":"CH",
    "sg:address":"Bl\u00e4siring 49 4057 Basel. Postfach",
    "sg:city":"Basel",
    "sg:orig_category":"Fussboden, Fliesen U Plattenlegerei, Tapeziererei",
    "sg:phone":"+41 81 834 90 83",
    "sg:postcode":"4051",
    "sg:province":"Basel-Stadt",
    "wof:name":"Del Curto - Meichtry Gmbh Wand- U. Bodenbel\u00e4ge; Kauf, Verkauf Usw",
    "wof:placetype":"venue"
},
  "geometry": {"coordinates":[9.838391304,46.4998817444],"type":"Point"}
}