{
  "type": "Feature",
  "properties": {
    "iso:country":"CH",
    "sg:address":"Pradafenz",
    "sg:city":"Churwalden",
    "sg:orig_category":"Interessenvertretungen",
    "sg:postcode":"7075",
    "sg:province":"Graubunden",
    "wof:name":"Stiftung F\u00fcr Wahrnehmungsbehinderte Menschen In Graub\u00fcnden",
    "wof:placetype":"venue"
},
  "geometry": {"coordinates":[9.5434303284,46.7792053223],"type":"Point"}
}