{
  "type": "Feature",
  "properties": {
    "iso:country":"CH",
    "sg:address":"Seematt 17 6314 Unter\u00e4geri. Postfach",
    "sg:city":"Unter\u00e4geri",
    "sg:orig_category":"Unternehmensberatung",
    "sg:postcode":"6314",
    "sg:province":"Zug",
    "wof:name":"Sch\u00f6nenberger Paul",
    "wof:placetype":"venue"
},
  "geometry": {"coordinates":[7.5159811974,47.475692749],"type":"Point"}
}