{
  "type": "Feature",
  "properties": {
    "iso:country":"CH",
    "sg:address":"3770",
    "sg:city":"Zweisimmen",
    "sg:orig_category":"Schwimmb\u00e4der",
    "sg:phone":"+41 33 722 10 81",
    "sg:postcode":"3770",
    "sg:province":"Bern",
    "wof:name":"Schwimmbad Zweisimmen",
    "wof:placetype":"venue"
},
  "geometry": {"coordinates":[7.3726348877,46.5528755188],"type":"Point"}
}