{
  "type": "Feature",
  "properties": {
    "iso:country":"CH",
    "sg:address":"Franz-rittmeyer-weg 3",
    "sg:city":"Zug",
    "sg:orig_category":"Unclassifiable Establishments",
    "sg:postcode":"6300",
    "sg:province":"Zug",
    "wof:name":"Resistronic-produktions-gmbh",
    "wof:placetype":"venue"
},
  "geometry": {"coordinates":[8.5264616013,47.1828308105],"type":"Point"}
}