{
  "type": "Feature",
  "properties": {
    "iso:country":"CH",
    "sg:address":"Gibelhalde 2",
    "sg:city":"Herisau",
    "sg:orig_category":"Naturheil\u00e4rzte and Heilpraktiker",
    "sg:phone":"+41 71 352 46 78",
    "sg:postcode":"9100",
    "sg:province":"Appenzell Ausserrhoden",
    "wof:name":"Sonja Widmer Natur\u00e4rztin",
    "wof:placetype":"venue"
},
  "geometry": {"coordinates":[9.2930936813,47.3895950317],"type":"Point"}
}