{
  "type": "Feature",
  "properties": {
    "iso:country":"CH",
    "sg:address":"Hummelstrasse 1",
    "sg:city":"Frauenfeld",
    "sg:orig_category":"B\u00e4ckereien Konditoreien",
    "sg:phone":"+41 52 720 84 90",
    "sg:postcode":"8500",
    "sg:province":"Thurgau",
    "wof:name":"Beda Th\u00f6ni B\u00e4ckerei-konditorei",
    "wof:placetype":"venue"
},
  "geometry": {"coordinates":[8.883713,47.562164],"type":"Point"}
}