{
  "type": "Feature",
  "properties": {
    "iso:country":"CH",
    "sg:address":"Schmittenackerstrasse 10",
    "sg:city":"Wallisellen",
    "sg:orig_category":"Malerei",
    "sg:phone":"+41 79 221 27 89",
    "sg:postcode":"8304",
    "sg:province":"Z\u00fcrich",
    "wof:name":"Lukas Schwarz Malergesch\u00e4ft",
    "wof:placetype":"venue"
},
  "geometry": {"coordinates":[8.594203949,47.4189872742],"type":"Point"}
}