{
  "type": "Feature",
  "properties": {
    "iso:country":"CH",
    "sg:address":"Forchwaldstrasse 23 6318 Walchwil. Postfach 82",
    "sg:city":"Walchwil",
    "sg:orig_category":"Herstellung von Metallerzeugnissen ohne Maschinenbau Herstellung von Werkzeugen",
    "sg:phone":"+41 41 758 10 80",
    "sg:postcode":"6318",
    "sg:province":"Zug",
    "wof:name":"Chaco-produkte Ag",
    "wof:placetype":"venue"
},
  "geometry": {"coordinates":[8.514632225,47.1030044556],"type":"Point"}
}