{
  "type": "Feature",
  "properties": {
    "iso:country":"CH",
    "sg:address":"Oberdorfstrasse 27",
    "sg:city":"Mollis",
    "sg:orig_category":"Maler U Glasergewerbe",
    "sg:postcode":"8753",
    "sg:province":"Glarus",
    "wof:name":"Hansruedi Holzer",
    "wof:placetype":"venue"
},
  "geometry": {"coordinates":[7.8617801666,49.1125106812],"type":"Point"}
}