{
  "type": "Feature",
  "properties": {
    "iso:country":"CH",
    "sg:address":"Viale S. Franscini 28",
    "sg:city":"Bellinzona",
    "sg:orig_category":"Herstellung von Papier, Karton U Pappe Herstellung von Wellpapier U pappe sowie von Verpackungsmitte",
    "sg:phone":"+41 91 825 23 82",
    "sg:postcode":"6500",
    "sg:province":"Ticino",
    "wof:name":"Saica Sa Industria Cartonaggi Carte Di Pizzo E Goffrate, Piatti E Dischi Di Cartone Ecc; Fabbr",
    "wof:placetype":"venue"
},
  "geometry": {"coordinates":[9.0142116547,46.1924209595],"type":"Point"}
}