{
  "type": "Feature",
  "properties": {
    "iso:country":"CH",
    "sg:address":"6676",
    "sg:city":"Bignasco",
    "sg:orig_category":"Detailhandel mit Damenbekleidung Detailhandel mit Herrenbekleidung",
    "sg:phone":"+41 55 416 71 11",
    "sg:postcode":"6676",
    "sg:province":"Ticino",
    "wof:name":"V\u00f6gele Charles Mode Ag Waren, Bes. Bekleidung; Handel Usw",
    "wof:placetype":"venue"
},
  "geometry": {"coordinates":[8.4757022858,47.1930885315],"type":"Point"}
}