{
  "type": "Feature",
  "properties": {
    "iso:country":"CH",
    "sg:address":"7444",
    "sg:city":"Ausserferrera",
    "sg:orig_category":"Gemeindeverwaltungen",
    "sg:phone":"+41 81 661 15 85",
    "sg:postcode":"7444",
    "sg:province":"Graubunden",
    "wof:name":"Gemeindeverwaltung Ausserferrera",
    "wof:placetype":"venue"
},
  "geometry": {"coordinates":[9.4392499924,46.5571403503],"type":"Point"}
}