{
  "type": "Feature",
  "properties": {
    "iso:country":"CH",
    "sg:address":"Soleil Levant Ruelle Du 6 1170 Aubonne. Postfach",
    "sg:city":"Aubonne",
    "sg:orig_category":"Unclassifiable Establishments",
    "sg:phone":"+41 21 807 13 93",
    "sg:postcode":"1170",
    "sg:province":"Vaud",
    "wof:name":"Virtua S\u00e0rl",
    "wof:placetype":"venue"
},
  "geometry": {"coordinates":[6.3911728859,46.4960899353],"type":"Point"}
}