{
  "type": "Feature",
  "properties": {
    "iso:country":"CH",
    "sg:address":"Post Terminus 1",
    "sg:city":"Weggis",
    "sg:orig_category":"Vermietung U Verpachtung von eigenen Immobilien",
    "sg:phone":"+41 41 390 25 86",
    "sg:postcode":"6353",
    "sg:province":"Luzern",
    "wof:name":"V. Michel Immobilien Ag",
    "wof:placetype":"venue"
},
  "geometry": {"coordinates":[8.4343938828,47.0322952271],"type":"Point"}
}