{
  "type": "Feature",
  "properties": {
    "iso:country":"CH",
    "sg:address":"Avenue De Lavaux 90",
    "sg:city":"Pully",
    "sg:orig_category":"Kosmetikinstitute",
    "sg:phone":"+41 32 631 23 52",
    "sg:postcode":"1009",
    "sg:province":"Vaud",
    "wof:name":"Doris Aebi Kosmetikinstitut",
    "wof:placetype":"venue"
},
  "geometry": {"coordinates":[7.6569471359,47.233165741],"type":"Point"}
}