{
  "type": "Feature",
  "properties": {
    "iso:country":"CH",
    "sg:address":"Place Bel-air 1",
    "sg:city":"Lausanne",
    "sg:orig_category":"Hochschulen U h\u00f6here Ausbildung",
    "sg:phone":"+41 21 312 25 80",
    "sg:postcode":"1003",
    "sg:province":"Vaud",
    "wof:name":"Ecole Medica Sa Enseignement Et Formation Professionelle",
    "wof:placetype":"venue"
},
  "geometry": {"coordinates":[6.6292219162,46.5220947266],"type":"Point"}
}