{
  "type": "Feature",
  "properties": {
    "iso:country":"CH",
    "sg:address":"Plantamour Rue Philippe- 19 1201 Gen\u00e8ve. Postfach",
    "sg:city":"Gen\u00e8ve",
    "sg:orig_category":"Detailhandel mit Bekleidung",
    "sg:postcode":"1201",
    "sg:province":"Gen\u00e8ve",
    "wof:name":"R.g. Distribution, Mme Penna",
    "wof:placetype":"venue"
},
  "geometry": {"coordinates":[6.149316,46.210171],"type":"Point"}
}