{
  "type": "Feature",
  "properties": {
    "iso:country":"CH",
    "sg:address":"Flaachtalstr. 14 8413 Neftenbach. Postfach",
    "sg:city":"H\u00fcnikon",
    "sg:orig_category":"Sonstiger Grosshandel",
    "sg:postcode":"8412",
    "sg:province":"Z\u00fcrich",
    "wof:name":"Moravia Import Export Agentur Marthaler Zuzana",
    "wof:placetype":"venue"
},
  "geometry": {"coordinates":[8.6629867554,47.5539855957],"type":"Point"}
}