{
  "type": "Feature",
  "properties": {
    "iso:country":"CH",
    "sg:address":"Schaffhauserstrasse 232",
    "sg:city":"Neunkirch",
    "sg:orig_category":"Pensionskassen",
    "sg:postcode":"8213",
    "sg:province":"Schaffhausen",
    "wof:name":"Pensionskasse Der Ssi Sch\u00e4fer Ag",
    "wof:placetype":"venue"
},
  "geometry": {"coordinates":[8.5051813126,47.6891174316],"type":"Point"}
}