{
  "type": "Feature",
  "properties": {
    "iso:country":"CH",
    "sg:address":"Place Du Temple 12 1304 Cossonay-ville. Postfach",
    "sg:city":"Allens",
    "sg:orig_category":"Architektur U Ingenieurb\u00fcros",
    "sg:postcode":"1304",
    "sg:province":"Vaud",
    "wof:name":"Baudet J.-p.",
    "wof:placetype":"venue"
},
  "geometry": {"coordinates":[6.487557,46.600582],"type":"Point"}
}