{
  "type": "Feature",
  "properties": {
    "addr:full":"Marzilistrasse 23 Bern Bern 3005",
    "addr:housenumber":"23",
    "addr:postcode":"3005",
    "addr:street":"Marzilistrasse",
    "iso:country":"CH",
    "sg:address":"Marzilistrasse 23",
    "sg:city":"Bern",
    "sg:orig_category":"Detailhandel mit Damenbekleidung",
    "sg:phone":"+41 56 622 74 53",
    "sg:postcode":"3005",
    "sg:province":"Bern",
    "wof:name":"Marianne Hollinger Secondhand",
    "wof:placetype":"venue"
},
  "geometry": {"coordinates":[8.277151,47.349827],"type":"Point"}
}