{
  "type": "Feature",
  "properties": {
    "iso:country":"CH",
    "sg:address":"En Bovery B",
    "sg:city":"Collombey",
    "sg:orig_category":"G\u00fcterbef\u00f6rderung im Strassenverkehr",
    "sg:phone":"+41 77234492",
    "sg:postcode":"1868",
    "sg:province":"Valais",
    "wof:name":"Antonio Saporita Transports",
    "wof:placetype":"venue"
},
  "geometry": {"coordinates":[6.9432849884,46.2826385498],"type":"Point"}
}