{
  "type": "Feature",
  "properties": {
    "iso:country":"CH",
    "sg:address":"6579",
    "sg:city":"Piazzogna",
    "sg:orig_category":"Detailhandel mit Waren verschiedener Art, Hauptrichtung Nahrungsmittel",
    "sg:phone":"+41 19355600",
    "sg:postcode":"6579",
    "sg:province":"Ticino",
    "wof:name":"Feinschmeckeregge",
    "wof:placetype":"venue"
},
  "geometry": {"coordinates":[8.7636137009,47.3022003174],"type":"Point"}
}