{
  "type": "Feature",
  "properties": {
    "iso:country":"CH",
    "sg:address":"Obere Zollgasse 72",
    "sg:city":"Ostermundigen",
    "sg:orig_category":"Non-Classified Establishments",
    "sg:phone":"+41 31 932 17 57",
    "sg:postcode":"3072",
    "sg:province":"Bern",
    "wof:name":"Farine Daniel Filmsekretariat",
    "wof:placetype":"venue"
},
  "geometry": {"coordinates":[7.4846448898,46.9499778748],"type":"Point"}
}