{
  "type": "Feature",
  "properties": {
    "iso:country":"CH",
    "sg:address":"Haldenweg 24 3250 Lyss. Postfach",
    "sg:city":"Lyss",
    "sg:orig_category":"Installation von Heizungs, L\u00fcftungs U Klimaanlagen",
    "sg:phone":"+41 32 384 10 16",
    "sg:postcode":"3250",
    "sg:province":"Bern",
    "wof:name":"Klaus-dieter St\u00fcckrad Klima-& K\u00fchltechnik",
    "wof:placetype":"venue"
},
  "geometry": {"coordinates":[7.3157920837,47.069568634],"type":"Point"}
}