{
  "type": "Feature",
  "properties": {
    "iso:country":"CH",
    "sg:address":"Turnerstrasse 5",
    "sg:city":"Basel",
    "sg:orig_category":"Religi\u00f6se Vereinigungen divers Vereine Gemeinn\u00fctzige",
    "sg:postcode":"4058",
    "sg:province":"Basel-Stadt",
    "wof:name":"Bund Partnerschaftl.christen",
    "wof:placetype":"venue"
},
  "geometry": {"coordinates":[7.6000699997,47.5616340637],"type":"Point"}
}