{
  "type": "Feature",
  "properties": {
    "iso:country":"CH",
    "sg:address":"Eglistrasse 8 8004 Z\u00fcrich. Postfach",
    "sg:city":"Z\u00fcrich",
    "sg:orig_category":"Verlag von bespielten Tontr\u00e4gern",
    "sg:phone":"+41 14919682",
    "sg:postcode":"8022",
    "sg:province":"Z\u00fcrich",
    "wof:name":"Edition Moderne David Basler",
    "wof:placetype":"venue"
},
  "geometry": {"coordinates":[8.5108528137,47.3837356567],"type":"Point"}
}