{
  "type": "Feature",
  "properties": {
    "iso:country":"CH",
    "sg:address":"Gundeldingerstrasse 474 4053 Basel. Postfach 474",
    "sg:city":"Basel",
    "sg:orig_category":"Detailhandel mit Radio U Fernsehger\u00e4ten",
    "sg:phone":"+41 61 331 84 40",
    "sg:postcode":"4018",
    "sg:province":"Basel-Stadt",
    "wof:name":"Audio Cina",
    "wof:placetype":"venue"
},
  "geometry": {"coordinates":[7.6022071838,47.5372390747],"type":"Point"}
}