{
  "type": "Feature",
  "properties": {
    "iso:country":"CH",
    "sg:address":"Guggenb\u00fchl 8 9215 Buhwil. Postfach 27",
    "sg:city":"Buhwil",
    "sg:orig_category":"Grosshandel mit sonstigen Getr\u00e4nken",
    "sg:phone":"+41 71 633 21 90",
    "sg:postcode":"9215",
    "sg:province":"Thurgau",
    "wof:name":"Ruag-getr\u00e4nke Drink Master Rudolf G\u00e4hler",
    "wof:placetype":"venue"
},
  "geometry": {"coordinates":[9.1991796494,47.5216598511],"type":"Point"}
}