{
  "type": "Feature",
  "properties": {
    "iso:country":"CH",
    "sg:address":"Zur Kirche",
    "sg:city":"M\u00f6rel",
    "sg:classifiers":[
        {
            "category":"Government",
            "subcategory":"Post Office",
            "type":"Public Place"
        }
    ],
    "sg:phone":"+41 27 927 18 25",
    "sg:postcode":"3983",
    "sg:province":"Valais",
    "sg:tags":[
        "caf\u00e9s",
        "tea-rooms"
    ],
    "wof:name":"Tea-room Zur Kirche",
    "wof:placetype":"venue"
},
  "geometry": {"coordinates":[8.045340538,46.3555603027],"type":"Point"}
}