{
  "type": "Feature",
  "properties": {
    "iso:country":"CH",
    "sg:address":"1933",
    "sg:city":"Sembrancher",
    "sg:orig_category":"Grosshandel mit Nahrungsmitteln, Getr\u00e4nken U Tabakwaren ohne ausgepr\u00e4gten Schwerpunkt Handelsvermitt",
    "sg:phone":"+41 27 785 11 09",
    "sg:postcode":"1933",
    "sg:province":"Valais",
    "wof:name":"Frimago Ag Primo Concordia Alimentation",
    "wof:placetype":"venue"
},
  "geometry": {"coordinates":[7.1504249573,46.0785903931],"type":"Point"}
}