{
  "type": "Feature",
  "properties": {
    "iso:country":"CH",
    "sg:address":"R\u00f6merstrasse 19 2555 Br\u00fcgg Be. Postfach",
    "sg:city":"Biel/bienne",
    "sg:orig_category":"Instandhaltung U Reparatur von Automobilen",
    "sg:postcode":"2503",
    "sg:province":"Bern",
    "wof:name":"Pisan Car Gmbh",
    "wof:placetype":"venue"
},
  "geometry": {"coordinates":[7.2603640556,47.1212997437],"type":"Point"}
}