{
  "type": "Feature",
  "properties": {
    "iso:country":"CH",
    "sg:address":"Murgstr. 25",
    "sg:city":"W\u00e4ngi",
    "sg:classifiers":[
        {
            "category":"Home & Garden",
            "subcategory":"Furniture",
            "type":"Retail Goods"
        }
    ],
    "sg:phone":"+41 61 726 24 24",
    "sg:postcode":"9545",
    "sg:province":"Thurgau",
    "sg:tags":[
        "household",
        "wood"
    ],
    "wof:name":"Hasena Ag",
    "wof:placetype":"venue"
},
  "geometry": {"coordinates":[7.5176329613,47.5032577515],"type":"Point"}
}