{
  "type": "Feature",
  "properties": {
    "iso:country":"CH",
    "sg:address":"Puidoux",
    "sg:city":"Chexbres",
    "sg:classifiers":[
        {
            "category":"Restaurant",
            "type":"Food & Drink"
        }
    ],
    "sg:phone":"+41 21 946 10 85",
    "sg:postcode":"1071",
    "sg:province":"Vaud",
    "sg:tags":[
        "tea-rooms",
        "restaurants"
    ],
    "wof:name":"Caf\u00e9 De La Buritaz Sa",
    "wof:placetype":"venue"
},
  "geometry": {"coordinates":[6.776239872,46.4821128845],"type":"Point"}
}