{
  "type": "Feature",
  "properties": {
    "iso:country":"CH",
    "sg:address":"Riva Via Alla 3a",
    "sg:city":"Minusio",
    "sg:orig_category":"Werbung",
    "sg:postcode":"6648",
    "sg:province":"Ticino",
    "wof:name":"Deag Sa",
    "wof:placetype":"venue"
},
  "geometry": {"coordinates":[8.811709404,46.1722297668],"type":"Point"}
}