{
  "type": "Feature",
  "properties": {
    "iso:country":"CH",
    "sg:address":"Via Vallemaggia 1",
    "sg:city":"Locarno",
    "sg:orig_category":"P\u00e9dicure",
    "sg:phone":"+41 91 751 65 21",
    "sg:postcode":"6600",
    "sg:province":"Ticino",
    "wof:name":"Gaby Meier Pedicure Da Gaby",
    "wof:placetype":"venue"
},
  "geometry": {"coordinates":[8.7901315689,46.1696624756],"type":"Point"}
}