{
  "type": "Feature",
  "properties": {
    "iso:country":"CH",
    "sg:address":"Zinsli",
    "sg:city":"Thalkirch",
    "sg:orig_category":"Jugendherbergen U H\u00fctten",
    "sg:phone":"+41 81 332 22 38",
    "sg:postcode":"7109",
    "sg:province":"Graubunden",
    "wof:name":"Ferienlager",
    "wof:placetype":"venue"
},
  "geometry": {"coordinates":[9.8141937256,46.9671554565],"type":"Point"}
}