{
  "type": "Feature",
  "properties": {
    "iso:country":"CH",
    "sg:address":"Warpelstrasse 5 3186 D\u00fcdingen. Postfach 242",
    "sg:city":"D\u00fcdingen",
    "sg:orig_category":"Instandhaltung U Reparatur von Automobilen",
    "sg:phone":"+41 26 493 18 33",
    "sg:postcode":"3186",
    "sg:province":"Fribourg",
    "wof:name":"Garage Und Carrosserie Warpel Ag",
    "wof:placetype":"venue"
},
  "geometry": {"coordinates":[7.202434063,46.8609580994],"type":"Point"}
}