{
  "type": "Feature",
  "properties": {
    "iso:country":"CH",
    "sg:address":"Kirchenfeldstrasse 29",
    "sg:city":"Bern",
    "sg:orig_category":"Chiropraktik",
    "sg:phone":"+41 62 771 66 44",
    "sg:postcode":"3005",
    "sg:province":"Bern",
    "wof:name":"Dr.felix S. Halter Chiropraktor",
    "wof:placetype":"venue"
},
  "geometry": {"coordinates":[8.185136,47.254185],"type":"Point"}
}