{
  "type": "Feature",
  "properties": {
    "iso:country":"CH",
    "sg:address":"Stationsstrasse 19 Liebefeld 3098 K\u00f6niz. Postfach",
    "sg:city":"Liebefeld",
    "sg:orig_category":"Herstellung von Verpackungsmittelnaus Holz",
    "sg:postcode":"3097",
    "sg:province":"Bern",
    "wof:name":"Rolvo Holzkistchen V\u00f6gtli",
    "wof:placetype":"venue"
},
  "geometry": {"coordinates":[7.414276123,46.9228744507],"type":"Point"}
}