{
  "type": "Feature",
  "properties": {
    "iso:country":"CH",
    "sg:address":"Lochstrasse 18",
    "sg:city":"Schaffhausen",
    "sg:orig_category":"Herstellung von Reiseartikeln, Leder U Sattlerwaren Instandhaltung U Reparatur von Automobilen",
    "sg:phone":"+41 52 625 97 44",
    "sg:postcode":"8200",
    "sg:province":"Schaffhausen",
    "wof:name":"Franz Kammermann",
    "wof:placetype":"venue"
},
  "geometry": {"coordinates":[8.6280250549,47.7079734802],"type":"Point"}
}