{
  "type": "Feature",
  "properties": {
    "iso:country":"CH",
    "sg:address":"3954",
    "sg:city":"Leukerbad",
    "sg:orig_category":"RESTAURANTS: TEA-ROOMS",
    "sg:phone":"+41 52 741 22 14",
    "sg:postcode":"3954",
    "sg:province":"Valais",
    "wof:name":"Restaurant Weinberg",
    "wof:placetype":"venue"
},
  "geometry": {"coordinates":[8.8581762314,47.6575393677],"type":"Point"}
}