{
  "type": "Feature",
  "properties": {
    "iso:country":"CH",
    "sg:address":"Eisengasse 2",
    "sg:city":"Brunnen",
    "sg:orig_category":"RESTAURANTS: TEA-ROOMS",
    "sg:postcode":"6440",
    "sg:province":"Schwyz",
    "wof:name":"Rest. Krone, Major A.",
    "wof:placetype":"venue"
},
  "geometry": {"coordinates":[8.6051473618,46.9942970276],"type":"Point"}
}