{
  "type": "Feature",
  "properties": {
    "iso:country":"CH",
    "sg:address":"Hinterdorf",
    "sg:city":"Altwis",
    "sg:orig_category":"Verarbeitung von Milch Verwertung von Milch",
    "sg:phone":"+41 71 385 84 83",
    "sg:postcode":"6286",
    "sg:province":"Luzern",
    "wof:name":"K\u00e4sereigenossenschaft Andwil",
    "wof:placetype":"venue"
},
  "geometry": {"coordinates":[9.2750005722,47.4446105957],"type":"Point"}
}