{
  "type": "Feature",
  "properties": {
    "iso:country":"CH",
    "sg:address":"Bubendorfstr. 9a",
    "sg:city":"Arboldswil",
    "sg:orig_category":"Fachdetailhandel in Verkaufsr\u00e4umen",
    "sg:phone":"+41 61 931 17 75",
    "sg:postcode":"4424",
    "sg:province":"Basel-Landschaft",
    "wof:name":"Gdf Golden Dog Food Gmbh",
    "wof:placetype":"venue"
},
  "geometry": {"coordinates":[7.7187829018,47.4156646729],"type":"Point"}
}