{
  "type": "Feature",
  "properties": {
    "iso:country":"CH",
    "sg:address":"Neuweilerstrasse 29 4054 Basel. Postfach",
    "sg:city":"Basel",
    "sg:orig_category":"Grosshandel mit Nahrungsmitteln, Getr\u00e4nken U Tabakwaren ohne ausgepr\u00e4gten Schwerpunkt",
    "sg:postcode":"4051",
    "sg:province":"Basel-Stadt",
    "wof:name":"Thai Tip Gmbh",
    "wof:placetype":"venue"
},
  "geometry": {"coordinates":[7.561811924,47.5462532043],"type":"Point"}
}