{
  "type": "Feature",
  "properties": {
    "iso:country":"CH",
    "sg:address":"Palmenstrasse 22 4055 Basel. Postfach",
    "sg:city":"Basel",
    "sg:orig_category":"Maschinen-Fabrikation",
    "sg:postcode":"4051",
    "sg:province":"Basel-Stadt",
    "wof:name":"Orbitech Gmbh",
    "wof:placetype":"venue"
},
  "geometry": {"coordinates":[7.5734949112,47.5565795898],"type":"Point"}
}