{
  "type": "Feature",
  "properties": {
    "iso:country":"CH",
    "sg:address":"Inwilerstrasse 3",
    "sg:city":"Baar",
    "sg:orig_category":"Advokaturb\u00fcros",
    "sg:phone":"+41 41 761 32 31",
    "sg:postcode":"6340",
    "sg:province":"Zug",
    "wof:name":"Kurt Schwengeler Advokaturb\u00fcro",
    "wof:placetype":"venue"
},
  "geometry": {"coordinates":[8.526764,47.193871],"type":"Point"}
}