{
  "type": "Feature",
  "properties": {
    "iso:country":"CH",
    "sg:address":"Chemin De La Distillerie 4",
    "sg:city":"Bernex",
    "sg:orig_category":"Elektroinstallation",
    "sg:phone":"+41 22 757 66 50",
    "sg:postcode":"1233",
    "sg:province":"Gen\u00e8ve",
    "wof:name":"Ece, Etudes, Coordination Electrotechniques Sa",
    "wof:placetype":"venue"
},
  "geometry": {"coordinates":[6.0773091316,46.1777534485],"type":"Point"}
}