{
  "type": "Feature",
  "properties": {
    "iso:country":"CH",
    "sg:address":"Chemin Des Grands-buissons 5",
    "sg:city":"Bernex",
    "sg:classifiers":[
        {
            "category":"Restaurant",
            "type":"Food & Drink"
        }
    ],
    "sg:phone":"+41 22 757 21 08",
    "sg:postcode":"1233",
    "sg:province":"Gen\u00e8ve",
    "wof:name":"Caf\u00e9-restaurant Fontaine",
    "wof:placetype":"venue"
},
  "geometry": {"coordinates":[6.0568389893,46.1634292603],"type":"Point"}
}