{
  "type": "Feature",
  "properties": {
    "iso:country":"CH",
    "sg:address":"Schanzengasse 14",
    "sg:city":"Z\u00fcrich",
    "sg:orig_category":"Pensionskassen",
    "sg:postcode":"8001",
    "sg:province":"Z\u00fcrich",
    "wof:name":"Personalvorsorgestiftung Der Albert Fl\u00fcckiger Ag",
    "wof:placetype":"venue"
},
  "geometry": {"coordinates":[7.5000801086,46.936832428],"type":"Point"}
}