{
  "type": "Feature",
  "properties": {
    "iso:country":"CH",
    "sg:address":"Dorfstr. 14 5315 B\u00f6ttstein. Postfach",
    "sg:city":"Kleind\u00f6ttingen",
    "sg:orig_category":"Herstellung von Teilen U Zubeh\u00f6r f\u00fcr Automobile",
    "sg:postcode":"5314",
    "sg:province":"Aargau",
    "wof:name":"Mas Export Gebr. Knechtli",
    "wof:placetype":"venue"
},
  "geometry": {"coordinates":[8.2478055954,47.569152832],"type":"Point"}
}