{
  "type": "Feature",
  "properties": {
    "iso:country":"CH",
    "sg:address":"Z\u00fcrcherstrasse 227",
    "sg:city":"Frauenfeld",
    "sg:orig_category":"Detailhandel mit Waren verschiedener Art, Hauptrichtung Nahrungsmittel",
    "sg:phone":"+41 52 721 46 41",
    "sg:postcode":"8500",
    "sg:province":"Thurgau",
    "wof:name":"Migros-markt Zeughausstrasse",
    "wof:placetype":"venue"
},
  "geometry": {"coordinates":[8.9010896683,47.5594711304],"type":"Point"}
}