{
  "type": "Feature",
  "properties": {
    "iso:country":"CH",
    "sg:address":"Orient-ville Rue 4",
    "sg:city":"Lausanne",
    "sg:orig_category":"Softwareentwicklung U beratung",
    "sg:phone":"+41 21 351 07 40",
    "sg:postcode":"1005",
    "sg:province":"Vaud",
    "wof:name":"Hot Pot, Tinguely L.",
    "wof:placetype":"venue"
},
  "geometry": {"coordinates":[6.6429438591,46.5171508789],"type":"Point"}
}