{
  "type": "Feature",
  "properties": {
    "iso:country":"CH",
    "sg:address":"Friesstrasse 12",
    "sg:city":"Z\u00fcrich",
    "sg:orig_category":"Non-Classified Establishments",
    "sg:postcode":"8050",
    "sg:province":"Z\u00fcrich",
    "wof:name":"Imbiss Zupa 2, F. Zeher",
    "wof:placetype":"venue"
},
  "geometry": {"coordinates":[8.5468454361,47.4141235352],"type":"Point"}
}