{
  "type": "Feature",
  "properties": {
    "iso:country":"CH",
    "sg:address":"Scie Route De La 5",
    "sg:city":"Estavayer-le-lac",
    "sg:orig_category":"Instandhaltung U Reparatur von Automobilen",
    "sg:phone":"+41 26 660 41 26",
    "sg:postcode":"1470",
    "sg:province":"Fribourg",
    "wof:name":"Carrosserie Johnny Sa",
    "wof:placetype":"venue"
},
  "geometry": {"coordinates":[6.8926100731,46.8147010803],"type":"Point"}
}