{
  "type": "Feature",
  "properties": {
    "iso:country":"CH",
    "sg:address":"Austrasse 36",
    "sg:city":"Neuenegg",
    "sg:orig_category":"RESTAURANTS: TEA-ROOMS",
    "sg:phone":"+41 31 741 03 75",
    "sg:postcode":"3176",
    "sg:province":"Bern",
    "wof:name":"Tennis Bistro Sportinn",
    "wof:placetype":"venue"
},
  "geometry": {"coordinates":[7.30919981,46.89427948],"type":"Point"}
}