{
  "type": "Feature",
  "properties": {
    "iso:country":"CH",
    "sg:address":"Calunastrasse 11 7000 Chur. Postfach",
    "sg:city":"Chur",
    "sg:orig_category":"Unclassifiable Establishments",
    "sg:postcode":"7000",
    "sg:province":"Graubunden",
    "wof:name":"Gadiscio Sa.",
    "wof:placetype":"venue"
},
  "geometry": {"coordinates":[9.5394792557,46.8622512817],"type":"Point"}
}