{
  "type": "Feature",
  "properties": {
    "iso:country":"CH",
    "sg:address":"Bahnhofstrasse 32",
    "sg:city":"Frauenfeld",
    "sg:orig_category":"Primarschulen",
    "sg:phone":"+41 52 720 18 10",
    "sg:postcode":"8500",
    "sg:province":"Thurgau",
    "wof:name":"Primarschule Ergaten",
    "wof:placetype":"venue"
},
  "geometry": {"coordinates":[8.8898639679,47.5544090271],"type":"Point"}
}