{
  "type": "Feature",
  "properties": {
    "iso:country":"CH",
    "sg:address":"Pal\u00e9zieux Route De 35",
    "sg:city":"Oron-la-ville",
    "sg:orig_category":"Zimmerei, Dachdeckerei, Bauspenglerei U Abdichtung",
    "sg:phone":"+41 21 907 77 73",
    "sg:postcode":"1610",
    "sg:province":"Vaud",
    "wof:name":"Frei Jean-paul",
    "wof:placetype":"venue"
},
  "geometry": {"coordinates":[6.8307509422,46.5692138672],"type":"Point"}
}