{
  "type": "Feature",
  "properties": {
    "iso:country":"CH",
    "sg:address":"M\u00fchleweg 78",
    "sg:city":"Aedermannsdorf",
    "sg:orig_category":"Wohnheime",
    "sg:phone":"+41 62 394 10 66",
    "sg:postcode":"4714",
    "sg:province":"Solothurn",
    "wof:name":"Asylantenwohnung",
    "wof:placetype":"venue"
},
  "geometry": {"coordinates":[7.6106719971,47.3037147522],"type":"Point"}
}