{
  "type": "Feature",
  "properties": {
    "iso:country":"CH",
    "sg:address":"3671",
    "sg:city":"Herbligen",
    "sg:orig_category":"Bauschreinerei Herstellung von Konstruktionsteilen, Fertigbauteilen U Ausbauelementen aus Holz",
    "sg:phone":"+41 31 771 00 74",
    "sg:postcode":"3671",
    "sg:province":"Bern",
    "wof:name":"Martin Sigrist",
    "wof:placetype":"venue"
},
  "geometry": {"coordinates":[7.61342,46.821739],"type":"Point"}
}