{
  "type": "Feature",
  "properties": {
    "addr:full":"Obertorplatz 1 Rheinfelden Aargau 4310",
    "addr:housenumber":"1",
    "addr:postcode":"4310",
    "addr:street":"Obertorplatz",
    "iso:country":"CH",
    "sg:address":"Obertorplatz 1",
    "sg:city":"Rheinfelden",
    "sg:classifiers":[
        {
            "category":"Banks & Credit Unions",
            "subcategory":"Bank",
            "type":"Services"
        }
    ],
    "sg:phone":"+41 61 831 52 20",
    "sg:postcode":"4310",
    "sg:province":"Aargau",
    "wof:name":"Schweiz. Mobiliar",
    "wof:placetype":"venue"
},
  "geometry": {"coordinates":[7.794943,47.553856],"type":"Point"}
}