{
  "type": "Feature",
  "properties": {
    "iso:country":"CH",
    "sg:address":"1126",
    "sg:city":"Vaux-sur-morges",
    "sg:orig_category":"Mechanische Werkst\u00e4tten Schlossereien",
    "sg:phone":"+41 21 803 64 68",
    "sg:postcode":"1126",
    "sg:province":"Vaud",
    "wof:name":"Jean-fran\u00e7ois Liardet D\u00e9pannage La Solution",
    "wof:placetype":"venue"
},
  "geometry": {"coordinates":[6.4615101814,46.5378608704],"type":"Point"}
}