{
  "type": "Feature",
  "properties": {
    "iso:country":"CH",
    "sg:address":"Gewerbestrasse 28",
    "sg:city":"Kleind\u00f6ttingen",
    "sg:orig_category":"Herstellung von Bettwaren Herstellung von Matratzen",
    "sg:phone":"+41 56 245 20 94",
    "sg:postcode":"5314",
    "sg:province":"Aargau",
    "wof:name":"Obrist + Stalder Ag Innendekorationen Polsterei",
    "wof:placetype":"venue"
},
  "geometry": {"coordinates":[8.2471151352,47.5709953308],"type":"Point"}
}