{
  "type": "Feature",
  "properties": {
    "iso:country":"CH",
    "sg:address":"Aarwangenstrasse 2",
    "sg:city":"Bannwil",
    "sg:classifiers":[
        {
            "category":"Retail",
            "subcategory":"Emissions Testing",
            "type":"Services"
        }
    ],
    "sg:phone":"+41 62 963 00 11",
    "sg:postcode":"4913",
    "sg:province":"Bern",
    "sg:tags":[
        "biological",
        "analytics"
    ],
    "wof:name":"Microbact Ag",
    "wof:placetype":"venue"
},
  "geometry": {"coordinates":[7.73503,47.23785],"type":"Point"}
}