{
  "type": "Feature",
  "properties": {
    "iso:country":"CH",
    "sg:address":"Waisenhausstrasse 2",
    "sg:city":"Thun",
    "sg:orig_category":"Kauf U Verkauf von Immobilien auf eigene Rechnung",
    "sg:postcode":"3600",
    "sg:province":"Bern",
    "wof:name":"Aurum Immobilien Ag",
    "wof:placetype":"venue"
},
  "geometry": {"coordinates":[7.4333019257,46.975353241],"type":"Point"}
}