{
  "type": "Feature",
  "properties": {
    "iso:country":"CH",
    "sg:address":"Schulgemeinde 8722 Kaltbrunn. Postfach 122",
    "sg:city":"Kaltbrunn",
    "sg:classifiers":[
        {
            "category":"Education",
            "subcategory":"Vocational School",
            "type":"Public Place"
        }
    ],
    "sg:postcode":"8722",
    "sg:province":"St. Gallen",
    "sg:tags":[
        "koch-",
        "haushaltschulen"
    ],
    "wof:name":"Haushaltungsschule",
    "wof:placetype":"venue"
},
  "geometry": {"coordinates":[9.0251646042,47.213218689],"type":"Point"}
}