{
  "type": "Feature",
  "properties": {
    "iso:country":"CH",
    "sg:address":"Quai Jeanrenaud 4",
    "sg:city":"Neuch\u00e2tel",
    "sg:orig_category":"Diskotheken, Dancings, Night Clubs",
    "sg:phone":"+41 32 731 55 31",
    "sg:postcode":"2000",
    "sg:province":"Neuch\u00e2tel",
    "wof:name":"Cabaret Le Flirt Night Lila",
    "wof:placetype":"venue"
},
  "geometry": {"coordinates":[6.9000787735,46.980594635],"type":"Point"}
}