{
  "type": "Feature",
  "properties": {
    "iso:country":"CH",
    "sg:address":"Staffelackerstrasse 20",
    "sg:city":"Dietikon",
    "sg:orig_category":"Allgemeiner Hochbau Stukkateurgewerbe, Gipserei U Verputzerei",
    "sg:phone":"+41 17407158",
    "sg:postcode":"8953",
    "sg:province":"Z\u00fcrich",
    "wof:name":"Mazzotta & Guccione Gipsergesch\u00e4ft",
    "wof:placetype":"venue"
},
  "geometry": {"coordinates":[8.389726,47.403343],"type":"Point"}
}