{
  "type": "Feature",
  "properties": {
    "addr:full":"Dorfstr. 149 Kilchberg Z\u00fcrich 8802",
    "addr:housenumber":"149",
    "addr:postcode":"8802",
    "addr:street":"Dorfstr.",
    "iso:country":"CH",
    "sg:address":"Dorfstr. 149",
    "sg:city":"Kilchberg",
    "sg:orig_category":"Agriculture and Livestock Construction and Public Works Horticulture",
    "sg:phone":"+41 4117161818",
    "sg:postcode":"8802",
    "sg:province":"Z\u00fcrich",
    "wof:name":"Berger Gartenbau",
    "wof:placetype":"venue"
},
  "geometry": {"coordinates":[8.539211,47.315403],"type":"Point"}
}