{
  "type": "Feature",
  "properties": {
    "iso:country":"CH",
    "sg:address":"Usterstrasse 20",
    "sg:city":"Illnau",
    "sg:classifiers":[
        {
            "category":"Restaurant",
            "type":"Food & Drink"
        }
    ],
    "sg:phone":"+41 52 346 25 55",
    "sg:postcode":"8308",
    "sg:province":"Z\u00fcrich",
    "wof:name":"Ristorante-pizzeria Zur Illnauer Schmitte",
    "wof:placetype":"venue"
},
  "geometry": {"coordinates":[8.7237234116,47.4074707031],"type":"Point"}
}