{
  "type": "Feature",
  "properties": {
    "iso:country":"CH",
    "sg:address":"Baarerstrasse 77",
    "sg:city":"Zug",
    "sg:orig_category":"Chemico-Technical Articles",
    "sg:phone":"+41 41 711 20 84",
    "sg:postcode":"6300",
    "sg:province":"Zug",
    "wof:name":"Chemsearch Nch Ag",
    "wof:placetype":"venue"
},
  "geometry": {"coordinates":[8.517647,47.177101],"type":"Point"}
}