{
  "type": "Feature",
  "properties": {
    "iso:country":"CH",
    "sg:address":"Bifangstrasse 22",
    "sg:city":"Oensingen",
    "sg:orig_category":"Grosshandel mit Erzen U Metallen R\u00fcckgewinnung U Vorbereitung f\u00fcr die Wiederverwertung Recycling",
    "sg:phone":"+41 62 396 21 22",
    "sg:postcode":"4702",
    "sg:province":"Solothurn",
    "wof:name":"Terracomp Bioerdenwerk Ag",
    "wof:placetype":"venue"
},
  "geometry": {"coordinates":[7.7298388481,47.2888755798],"type":"Point"}
}