{
  "type": "Feature",
  "properties": {
    "addr:full":"Gr\u00fcebletzweg 2 Densb\u00fcren Aargau 5026",
    "addr:housenumber":"2",
    "addr:postcode":"5026",
    "addr:street":"Grueebletzweg",
    "iso:country":"CH",
    "sg:address":"Gr\u00fcebletzweg 2",
    "sg:city":"Densb\u00fcren",
    "sg:orig_category":"Bauspenglerei Sanit\u00e4rinstallation",
    "sg:phone":"+41 31 879 00 24",
    "sg:postcode":"5026",
    "sg:province":"Aargau",
    "wof:name":"Ulrich Jakob Sanit\u00e4re Anlagen & Spenglerei",
    "wof:placetype":"venue"
},
  "geometry": {"coordinates":[7.41534,47.058842],"type":"Point"}
}