{
  "type": "Feature",
  "properties": {
    "iso:country":"CH",
    "sg:address":"Dornacherstrasse 8",
    "sg:city":"Olten",
    "sg:orig_category":"Reiseb\u00fcros U Reiseveranstalter",
    "sg:phone":"+41 62 212 77 50",
    "sg:postcode":"4600",
    "sg:province":"Solothurn",
    "wof:name":"Swiss Sakura Travel Gmbh",
    "wof:placetype":"venue"
},
  "geometry": {"coordinates":[7.9015350342,47.351524353],"type":"Point"}
}