{
  "type": "Feature",
  "properties": {
    "iso:country":"CH",
    "sg:address":"Schlossbergstrasse 6",
    "sg:city":"Erstfeld",
    "sg:orig_category":"Arztpraxen",
    "sg:phone":"+41 41 880 13 21",
    "sg:postcode":"6472",
    "sg:province":"Uri",
    "wof:name":"Dr.med.reto Rechsteiner Arzt F.allgemeine Medizin Fmh",
    "wof:placetype":"venue"
},
  "geometry": {"coordinates":[8.648369,46.820019],"type":"Point"}
}