{
  "type": "Feature",
  "properties": {
    "iso:country":"CH",
    "sg:address":"Affolternstrasse 21",
    "sg:city":"Ottenbach",
    "sg:orig_category":"Arztpraxen",
    "sg:phone":"+41 17611319",
    "sg:postcode":"8913",
    "sg:province":"Z\u00fcrich",
    "wof:name":"Dr.med.urs Glenck Arzt F\u00fcr Allgemeine Medizin",
    "wof:placetype":"venue"
},
  "geometry": {"coordinates":[8.404925,47.279434],"type":"Point"}
}