{
  "type": "Feature",
  "properties": {
    "iso:country":"CH",
    "sg:address":"Staatsstrasse 54",
    "sg:city":"Grabs",
    "sg:orig_category":"Detailhandel mit Haustieren U zoologischem Bedarf",
    "sg:phone":"+41 81 771 63 97",
    "sg:postcode":"9472",
    "sg:province":"St. Gallen",
    "wof:name":"Ernst Brauchli Ernst's Hundeshop",
    "wof:placetype":"venue"
},
  "geometry": {"coordinates":[9.4480438232,47.1796417236],"type":"Point"}
}