{
  "type": "Feature",
  "properties": {
    "iso:country":"CH",
    "sg:address":"Ackerstrasse 44",
    "sg:city":"Z\u00fcrich",
    "sg:orig_category":"Hochschulen U h\u00f6here Ausbildung",
    "sg:phone":"+41 12720771",
    "sg:postcode":"8005",
    "sg:province":"Z\u00fcrich",
    "wof:name":"Focus Mathematik Hardy Dr. G.",
    "wof:placetype":"venue"
},
  "geometry": {"coordinates":[8.532699585,47.3828849792],"type":"Point"}
}