{
  "type": "Feature",
  "properties": {
    "iso:country":"CH",
    "sg:address":"Hohreutistrasse 4 Au",
    "sg:city":"Kradolf",
    "sg:orig_category":"Haltung von Schweinen",
    "sg:phone":"+41 71 642 16 71",
    "sg:postcode":"9214",
    "sg:province":"Thurgau",
    "wof:name":"Wiedmer Alfred",
    "wof:placetype":"venue"
},
  "geometry": {"coordinates":[9.2017002106,47.5242195129],"type":"Point"}
}