{
  "type": "Feature",
  "properties": {
    "iso:country":"CH",
    "sg:address":"Allmendweg 61",
    "sg:city":"Laufen",
    "sg:orig_category":"Datenverarbeitungsdienste Hardwareberatung",
    "sg:phone":"+41 61 761 71 07",
    "sg:postcode":"4242",
    "sg:province":"Basel-Landschaft",
    "wof:name":"Nbb Netzwerk Beratung & Betreuung",
    "wof:placetype":"venue"
},
  "geometry": {"coordinates":[7.4963049889,47.4219818115],"type":"Point"}
}