{
  "type": "Feature",
  "properties": {
    "iso:country":"CH",
    "sg:address":"Rue Robert-c\u00e9ard 11",
    "sg:city":"Gen\u00e8ve",
    "sg:orig_category":"Detailhandel mit Geschenkartikeln U Souvenirs Detailhandel mit elektrischen Haushalts-,Radio U Ferns",
    "sg:phone":"+41 22 311 31 51",
    "sg:postcode":"1204",
    "sg:province":"Gen\u00e8ve",
    "wof:name":"Benimex, Beniflah Jaime",
    "wof:placetype":"venue"
},
  "geometry": {"coordinates":[6.148660183,46.2027511597],"type":"Point"}
}