{
  "type": "Feature",
  "properties": {
    "iso:country":"CH",
    "sg:address":"Schluchen",
    "sg:city":"Filzbach",
    "sg:orig_category":"Verarbeitung von Milch Verwertung von Milch",
    "sg:postcode":"8757",
    "sg:province":"Glarus",
    "wof:name":"Milchproduzentengenossenschaft Filzbach",
    "wof:placetype":"venue"
},
  "geometry": {"coordinates":[9.1239519119,47.1167030334],"type":"Point"}
}