{
  "type": "Feature",
  "properties": {
    "iso:country":"CH",
    "sg:address":"Steinest 831",
    "sg:city":"Triesenberg",
    "sg:orig_category":"Verlegen von Fliesen U Platten",
    "sg:phone":"+423 264 10 22",
    "sg:postcode":"9497",
    "wof:name":"Sch\u00e4dler Ag Ofenbau & Plattenbel\u00e4ge",
    "wof:placetype":"venue"
},
  "geometry": {"coordinates":[9.5488176346,47.1141662598],"type":"Point"}
}