{
  "type": "Feature",
  "properties": {
    "iso:country":"CH",
    "sg:address":"Luzernstrasse 9 4528 Zuchwil. Postfach 158",
    "sg:city":"Solothurn",
    "sg:orig_category":"Datenverarbeitungsdienste",
    "sg:phone":"+41 32 686 81 81",
    "sg:postcode":"4501",
    "sg:province":"Solothurn",
    "wof:name":"Bvi Consult Ag Informatik-dienstleistungen",
    "wof:placetype":"venue"
},
  "geometry": {"coordinates":[7.548036,47.205299],"type":"Point"}
}