{
  "type": "Feature",
  "properties": {
    "iso:country":"CH",
    "sg:address":"Bahnhofstrasse 127",
    "sg:city":"Niederbuchsiten",
    "sg:orig_category":"Giessereiindustrie Herstellung von Metallerzeugnissen ohne Maschinenbau",
    "sg:phone":"+41 62 393 13 32",
    "sg:postcode":"4626",
    "sg:province":"Solothurn",
    "wof:name":"Koguss Ag Aluminiumgiesserei",
    "wof:placetype":"venue"
},
  "geometry": {"coordinates":[7.7695040703,47.298789978],"type":"Point"}
}