{
  "type": "Feature",
  "properties": {
    "iso:country":"CH",
    "sg:address":"1029",
    "sg:city":"Villars-ste-croix",
    "sg:orig_category":"Sanit\u00e4r, Heizungs U L\u00fcftungsinstallation",
    "sg:phone":"+41 27 957 19 16",
    "sg:postcode":"1029",
    "sg:province":"Vaud",
    "wof:name":"Lombra, Lomatter & Brantschen",
    "wof:placetype":"venue"
},
  "geometry": {"coordinates":[7.933672905,46.1117172241],"type":"Point"}
}