{
  "type": "Feature",
  "properties": {
    "iso:country":"CH",
    "sg:address":"Schlossackerstrasse 16",
    "sg:city":"Oberneunforn",
    "sg:orig_category":"Sonstige mit der Informatik verbundene T\u00e4tigkeiten",
    "sg:phone":"+41 52 745 23 07",
    "sg:postcode":"8526",
    "sg:province":"Thurgau",
    "wof:name":"Hostettler Edv Gmbh",
    "wof:placetype":"venue"
},
  "geometry": {"coordinates":[8.76907444,47.6072502136],"type":"Point"}
}