{
  "type": "Feature",
  "properties": {
    "iso:country":"CH",
    "sg:address":"Grand-rue 14",
    "sg:city":"Porrentruy",
    "sg:orig_category":"Fachdetailhandel in Verkaufsr\u00e4umen",
    "sg:postcode":"2900",
    "sg:province":"Jura",
    "wof:name":"B\u00fchler Pierre-alain",
    "wof:placetype":"venue"
},
  "geometry": {"coordinates":[7.0750951767,47.4161262512],"type":"Point"}
}