{
  "type": "Feature",
  "properties": {
    "iso:country":"CH",
    "sg:address":"Fabrikstrasse",
    "sg:city":"Sirnach",
    "sg:orig_category":"D\u00e4mmung gegen K\u00e4lte, W\u00e4rme, Schall U Ersch\u00fctterung Herstellung von sonstigen Produkten aus nichtmeta",
    "sg:phone":"+41 71 966 30 08",
    "sg:postcode":"8370",
    "sg:province":"Thurgau",
    "wof:name":"Santi Ficarra Plexiglas-isolierungen",
    "wof:placetype":"venue"
},
  "geometry": {"coordinates":[8.9924545288,47.4623260498],"type":"Point"}
}