{
  "type": "Feature",
  "properties": {
    "iso:country":"CH",
    "sg:address":"5615",
    "sg:city":"Fahrwangen",
    "sg:classifiers":[
        {
            "category":"Education",
            "subcategory":"Vocational School",
            "type":"Public Place"
        }
    ],
    "sg:phone":"+41 56 633 22 10",
    "sg:postcode":"5615",
    "sg:province":"Aargau",
    "sg:tags":[
        "koch-",
        "haushaltschulen"
    ],
    "wof:name":"Haushaltungsschule",
    "wof:placetype":"venue"
},
  "geometry": {"coordinates":[8.3444499969,47.3506698608],"type":"Point"}
}