{
  "type": "Feature",
  "properties": {
    "iso:country":"CH",
    "sg:address":"R\u00fcegerholzstrasse 20",
    "sg:city":"Frauenfeld",
    "sg:orig_category":"Malerei",
    "sg:phone":"+41 91 794 23 26",
    "sg:postcode":"8500",
    "sg:province":"Thurgau",
    "wof:name":"Alfredo Taddei Impresa Di Pittura",
    "wof:placetype":"venue"
},
  "geometry": {"coordinates":[8.7835540771,46.1219673157],"type":"Point"}
}