{
  "type": "Feature",
  "properties": {
    "iso:country":"CH",
    "sg:address":"Gen\u00e8ve Rue De 97 1004 Lausanne. Postfach",
    "sg:city":"Lausanne",
    "sg:orig_category":"Non-Classified Establishments",
    "sg:postcode":"1003",
    "sg:province":"Vaud",
    "wof:name":"Camo Transporte, Buchs",
    "wof:placetype":"venue"
},
  "geometry": {"coordinates":[8.0799570084,47.3945617676],"type":"Point"}
}