{
  "type": "Feature",
  "properties": {
    "iso:country":"CH",
    "sg:address":"Bahnhofstrasse 2",
    "sg:city":"Gelterkinden",
    "sg:orig_category":"Detailhandel mit Radio U Fernsehger\u00e4ten",
    "sg:phone":"+41 61 971 40 37",
    "sg:postcode":"4460",
    "sg:province":"Basel-Landschaft",
    "wof:name":"Maurer Radio Television Ag Video",
    "wof:placetype":"venue"
},
  "geometry": {"coordinates":[7.8498120308,47.4658088684],"type":"Point"}
}