{
  "type": "Feature",
  "properties": {
    "iso:country":"CH",
    "sg:address":"Rue De Glarey 33",
    "sg:city":"Sierre",
    "sg:classifiers":[
        {
            "category":"Insurance",
            "subcategory":"Insurance Agent",
            "type":"Services"
        }
    ],
    "sg:phone":"+41 27 456 35 40",
    "sg:postcode":"3960",
    "sg:province":"Valais",
    "sg:tags":[
        "versicherungsagenturen",
        "-broker"
    ],
    "wof:name":"Coop Assurances",
    "wof:placetype":"venue"
},
  "geometry": {"coordinates":[7.5400629044,46.2982444763],"type":"Point"}
}