{
  "type": "Feature",
  "properties": {
    "iso:country":"CH",
    "sg:address":"Chemin De La Gravi\u00e8re 16",
    "sg:city":"Echandens",
    "sg:orig_category":"Maurerarbeiten Sonstiger spezialisierter Hoch U Tiefbau",
    "sg:phone":"+41 21 701 28 03",
    "sg:postcode":"1026",
    "sg:province":"Vaud",
    "wof:name":"Morel F., Ma\u00e7onnerie Et B\u00e9ton Arm\u00e9",
    "wof:placetype":"venue"
},
  "geometry": {"coordinates":[6.5447330475,46.5334777832],"type":"Point"}
}