{
  "type": "Feature",
  "properties": {
    "iso:country":"CH",
    "sg:address":"Dufour Rue Du G\u00e9n\u00e9ral- 11 1204 Gen\u00e8ve. Postfach",
    "sg:city":"Gen\u00e8ve",
    "sg:orig_category":"Sonstige mit Sport verbundene T\u00e4tigkeiten",
    "sg:postcode":"1204",
    "sg:province":"Gen\u00e8ve",
    "wof:name":"M.b.f. S\u00e0rl",
    "wof:placetype":"venue"
},
  "geometry": {"coordinates":[6.1418390274,46.2013626099],"type":"Point"}
}