{
  "type": "Feature",
  "properties": {
    "iso:country":"CH",
    "sg:address":"Cheminet Le 35",
    "sg:city":"Penthalaz",
    "sg:orig_category":"Handel mit Motorr\u00e4dern, Teilen U Zubeh\u00f6r Instandhaltung U Reparatur von Motorr\u00e4dern",
    "sg:phone":"+41 21 861 08 88",
    "sg:postcode":"1305",
    "sg:province":"Vaud",
    "wof:name":"Sd Motos, Dupuis S\u00e9bastien",
    "wof:placetype":"venue"
},
  "geometry": {"coordinates":[6.5252871513,46.6116981506],"type":"Point"}
}