{
  "type": "Feature",
  "properties": {
    "iso:country":"CH",
    "sg:address":"Theodorshofweg 12 4310 Rheinfelden. Postfach",
    "sg:city":"Rheinfelden",
    "sg:orig_category":"Non-Classified Establishments",
    "sg:postcode":"4310",
    "sg:province":"Aargau",
    "wof:name":"Albert Luss Ag",
    "wof:placetype":"venue"
},
  "geometry": {"coordinates":[7.8057851791,47.564125061],"type":"Point"}
}