{
  "type": "Feature",
  "properties": {
    "iso:country":"CH",
    "sg:address":"S\u00e4genstrasse 111",
    "sg:city":"Chur",
    "sg:orig_category":"Grosshandel mit Flachglas, Sanit\u00e4rkeramik U Anstrichmitteln Maler U Glasergewerbe",
    "sg:phone":"+41 32 751 17 07",
    "sg:postcode":"7000",
    "sg:province":"Graubunden",
    "wof:name":"Sevicolor S\u00e0rl",
    "wof:placetype":"venue"
},
  "geometry": {"coordinates":[7.0917701721,47.0628929138],"type":"Point"}
}