{
  "type": "Feature",
  "properties": {
    "iso:country":"CH",
    "sg:address":"Unterheid 3857 Unterbach Be. Postfach 251",
    "sg:city":"Meiringen",
    "sg:orig_category":"Sportvereine Ski",
    "sg:phone":"+41 33 971 30 62",
    "sg:postcode":"3860",
    "sg:province":"Bern",
    "wof:name":"Skiclub Unterbach",
    "wof:placetype":"venue"
},
  "geometry": {"coordinates":[8.1095075607,46.7373352051],"type":"Point"}
}