{
  "type": "Feature",
  "properties": {
    "iso:country":"CH",
    "sg:address":"Hans-huber-strasse 41",
    "sg:city":"Solothurn",
    "sg:orig_category":"Softwareentwicklung U beratung",
    "sg:postcode":"4500",
    "sg:province":"Solothurn",
    "wof:name":"Unicom Uzdilli",
    "wof:placetype":"venue"
},
  "geometry": {"coordinates":[7.5283122063,47.2009010315],"type":"Point"}
}