{
  "type": "Feature",
  "properties": {
    "iso:country":"CH",
    "sg:address":"Mitteldorfstrasse 39b",
    "sg:city":"Ober\u00e4geri",
    "sg:orig_category":"Non-Classified Establishments",
    "sg:postcode":"6315",
    "sg:province":"Zug",
    "wof:name":"Meier & Partner Ag, Rotkreuz, Zweigniederlassung Ober\u00e4geri",
    "wof:placetype":"venue"
},
  "geometry": {"coordinates":[8.6072797775,47.1372947693],"type":"Point"}
}