{
  "type": "Feature",
  "properties": {
    "iso:country":"CH",
    "sg:address":"Rue Des Tilleuls 4",
    "sg:city":"Porrentruy",
    "sg:orig_category":"Grosshandel mit sonstigen Halbwaren",
    "sg:phone":"+41 32 466 44 55",
    "sg:postcode":"2900",
    "sg:province":"Jura",
    "wof:name":"Cartona, Juillard & Cie.",
    "wof:placetype":"venue"
},
  "geometry": {"coordinates":[7.0734491348,47.4142456055],"type":"Point"}
}