{
  "type": "Feature",
  "properties": {
    "iso:country":"CH",
    "sg:address":"Rue Maunoir 6",
    "sg:city":"Gen\u00e8ve",
    "sg:orig_category":"Instandhaltung U Reparatur von Automobilen",
    "sg:phone":"+41 22 735 23 77",
    "sg:postcode":"1207",
    "sg:province":"Gen\u00e8ve",
    "wof:name":"Auto-service De La Rue Maunoir, L. Dori",
    "wof:placetype":"venue"
},
  "geometry": {"coordinates":[6.1594939232,46.2042350769],"type":"Point"}
}