{
  "type": "Feature",
  "properties": {
    "iso:country":"CH",
    "sg:address":"Adlibogenstrasse 4",
    "sg:city":"Niederhasli",
    "sg:orig_category":"Fernmeldedienste",
    "sg:phone":"+41 18510610",
    "sg:postcode":"8155",
    "sg:province":"Z\u00fcrich",
    "wof:name":"Onda Com",
    "wof:placetype":"venue"
},
  "geometry": {"coordinates":[8.4950866699,47.4811935425],"type":"Point"}
}