{
  "type": "Feature",
  "properties": {
    "iso:country":"CH",
    "sg:address":"Via Della Posta 44",
    "sg:city":"Locarno",
    "sg:orig_category":"Arztpraxen",
    "sg:phone":"+41 91 751 33 22",
    "sg:postcode":"6600",
    "sg:province":"Ticino",
    "wof:name":"Dres Med.a. Sury & R. Schwarz Medici Generici Fmh",
    "wof:placetype":"venue"
},
  "geometry": {"coordinates":[8.801592,46.16201],"type":"Point"}
}