{
  "type": "Feature",
  "properties": {
    "iso:country":"CH",
    "sg:address":"Kirchgasse 5 3860 Meiringen. Postfach 528",
    "sg:city":"Meiringen",
    "sg:orig_category":"Detailhandel mit M\u00f6beln U Haushaltsgegenst\u00e4nden Verlegen von Fussboden",
    "sg:phone":"+41 79 311 16 38",
    "sg:postcode":"3860",
    "sg:province":"Bern",
    "wof:name":"Huber Und Jossi Ag",
    "wof:placetype":"venue"
},
  "geometry": {"coordinates":[8.187374115,46.7278823853],"type":"Point"}
}