{
  "type": "Feature",
  "properties": {
    "iso:country":"CH",
    "sg:address":"Blumenbergstrasse 13 8633 Wolfhausen. Postfach",
    "sg:city":"F\u00e4gswil",
    "sg:orig_category":"Werbung",
    "sg:postcode":"8630",
    "sg:province":"Z\u00fcrich",
    "wof:name":"Gubser - Marketing Services",
    "wof:placetype":"venue"
},
  "geometry": {"coordinates":[8.7929582596,47.2551765442],"type":"Point"}
}