{
  "type": "Feature",
  "properties": {
    "iso:country":"CH",
    "sg:address":"Dietrichsguet 9424 Rheineck. Postfach",
    "sg:city":"Rheineck",
    "sg:orig_category":"Instandhaltung U Reparatur von Automobilen",
    "sg:postcode":"9424",
    "sg:province":"St. Gallen",
    "wof:name":"L.a.c. Carosserie Gmbh",
    "wof:placetype":"venue"
},
  "geometry": {"coordinates":[9.5842399597,47.476146698],"type":"Point"}
}