{
  "type": "Feature",
  "properties": {
    "iso:country":"CH",
    "sg:address":"Bifangweg 16",
    "sg:city":"Kappelen",
    "sg:orig_category":"Elektroinstallation",
    "sg:phone":"+41 32 392 29 29",
    "sg:postcode":"3273",
    "sg:province":"Bern",
    "wof:name":"Elektro Gerber Ag",
    "wof:placetype":"venue"
},
  "geometry": {"coordinates":[7.267329216,47.0577507019],"type":"Point"}
}