{
  "type": "Feature",
  "properties": {
    "iso:country":"CH",
    "sg:address":"Sennhof 10",
    "sg:city":"Russikon",
    "sg:orig_category":"Kauf U Verkauf von Immobilien auf eigene Rechnung",
    "sg:phone":"+41 19542373",
    "sg:postcode":"8332",
    "sg:province":"Z\u00fcrich",
    "wof:name":"Brunschweiler-huser Heidi + Anton, Liegenschaften",
    "wof:placetype":"venue"
},
  "geometry": {"coordinates":[8.7785396576,47.3929595947],"type":"Point"}
}