{
  "type": "Feature",
  "properties": {
    "iso:country":"CH",
    "sg:address":"Zilstrasse 33",
    "sg:city":"Gr\u00e4nichen",
    "sg:orig_category":"Kosmetikinstitute",
    "sg:phone":"+41 62 842 21 00",
    "sg:postcode":"5722",
    "sg:province":"Aargau",
    "wof:name":"Silvia Suter Kosmetikinstitut",
    "wof:placetype":"venue"
},
  "geometry": {"coordinates":[8.1050453186,47.3625793457],"type":"Point"}
}