{
  "type": "Feature",
  "properties": {
    "iso:country":"CH",
    "sg:address":"Rue D'orm\u00f4ne",
    "sg:city":"Chandolin-savi\u00e8se",
    "sg:orig_category":"Mechanik",
    "sg:postcode":"1965",
    "sg:province":"Valais",
    "wof:name":"Debruge Jean",
    "wof:placetype":"venue"
},
  "geometry": {"coordinates":[6.2603201866,46.5135612488],"type":"Point"}
}