{
  "type": "Feature",
  "properties": {
    "iso:country":"CH",
    "sg:address":"Chesa Muntanella",
    "sg:city":"Champf\u00e8r",
    "sg:orig_category":"Steuerberatung",
    "sg:phone":"+41 81 837 30 41",
    "sg:postcode":"7512",
    "sg:province":"Graubunden",
    "wof:name":"H\u00e4berli & Partner Steuerrechtspraxis",
    "wof:placetype":"venue"
},
  "geometry": {"coordinates":[9.8110704422,46.4780006409],"type":"Point"}
}