{
  "type": "Feature",
  "properties": {
    "iso:country":"CH",
    "sg:address":"Alte T\u00f6sstalstrasse 40a",
    "sg:city":"R\u00e4mism\u00fchle",
    "sg:orig_category":"G\u00fcterbef\u00f6rderung im Strassenverkehr",
    "sg:phone":"+41 52 383 26 28",
    "sg:postcode":"8487",
    "sg:province":"Z\u00fcrich",
    "wof:name":"Gian Hort Transporte",
    "wof:placetype":"venue"
},
  "geometry": {"coordinates":[8.8197402954,47.4398117065],"type":"Point"}
}