{
  "type": "Feature",
  "properties": {
    "iso:country":"CH",
    "sg:address":"3863",
    "sg:city":"Nessental",
    "sg:orig_category":"Sportvereine Sch\u00fctzen",
    "sg:postcode":"3863",
    "sg:province":"Bern",
    "wof:name":"Feldsch\u00fctzengesellschaft",
    "wof:placetype":"venue"
},
  "geometry": {"coordinates":[7.5159797668,47.4756889343],"type":"Point"}
}