{
  "type": "Feature",
  "properties": {
    "iso:country":"CH",
    "sg:address":"Grand-rue 32",
    "sg:city":"Courcelon",
    "sg:orig_category":"Sportvereine Wassersport Kanu",
    "sg:phone":"+41 32 422 50 47",
    "sg:postcode":"2823",
    "sg:province":"Jura",
    "wof:name":"Club De Cano\u00eb Du Jura",
    "wof:placetype":"venue"
},
  "geometry": {"coordinates":[7.3953027725,47.3630828857],"type":"Point"}
}