{
  "type": "Feature",
  "properties": {
    "iso:country":"CH",
    "sg:address":"Hauptstrasse 8c",
    "sg:city":"Frieswil",
    "sg:orig_category":"Vereine Harmonika and Akkordeon",
    "sg:phone":"+41 31 825 62 50",
    "sg:postcode":"3035",
    "sg:province":"Bern",
    "wof:name":"Harmonikaclub Aarberg-kallnach",
    "wof:placetype":"venue"
},
  "geometry": {"coordinates":[7.2831091881,46.9952507019],"type":"Point"}
}