{
  "type": "Feature",
  "properties": {
    "iso:country":"CH",
    "sg:address":"Hauptstrasse 9",
    "sg:city":"Tann",
    "sg:orig_category":"Reiseb\u00fcros U Reiseveranstalter",
    "sg:phone":"+41 55 241 17 27",
    "sg:postcode":"8632",
    "sg:province":"Z\u00fcrich",
    "wof:name":"Efa Tour, Degirmenler & Cevikel",
    "wof:placetype":"venue"
},
  "geometry": {"coordinates":[8.8514022827,47.2610931396],"type":"Point"}
}