{
  "type": "Feature",
  "properties": {
    "iso:country":"CH",
    "sg:address":"L\u00f6wenstrasse 20 8001 Z\u00fcrich. Postfach",
    "sg:city":"Z\u00fcrich",
    "sg:orig_category":"Vermietung U Verpachtung von eigenen Immobilien",
    "sg:postcode":"8002",
    "sg:province":"Z\u00fcrich",
    "wof:name":"Krina Sa",
    "wof:placetype":"venue"
},
  "geometry": {"coordinates":[9.0045003891,46.0516586304],"type":"Point"}
}