{
  "type": "Feature",
  "properties": {
    "iso:country":"CH",
    "sg:address":"Gladbachstrasse 6",
    "sg:city":"Z\u00fcrich",
    "sg:orig_category":"Grosshandel mit Nahrungsmitteln, Getr\u00e4nken U Tabakwaren ohne ausgepr\u00e4gten Schwerpunkt",
    "sg:phone":"+41 13622277",
    "sg:postcode":"8006",
    "sg:province":"Z\u00fcrich",
    "wof:name":"Abava Gmbh",
    "wof:placetype":"venue"
},
  "geometry": {"coordinates":[8.5499105453,47.3830375671],"type":"Point"}
}