{
  "type": "Feature",
  "properties": {
    "addr:full":"Sch\u00fctzenweg 1 Rohr Aargau 5032",
    "addr:housenumber":"1",
    "addr:postcode":"5032",
    "addr:street":"Schuetzenweg",
    "iso:country":"CH",
    "sg:address":"Sch\u00fctzenweg 1",
    "sg:city":"Rohr",
    "sg:classifiers":[
        {
            "category":"Banks & Credit Unions",
            "subcategory":"Bank",
            "type":"Services"
        }
    ],
    "sg:phone":"+41 4164249175",
    "sg:postcode":"5032",
    "sg:province":"Aargau",
    "wof:name":"Schweiz. Mobiliar",
    "wof:placetype":"venue"
},
  "geometry": {"coordinates":[8.086794,47.405132],"type":"Point"}
}