{
  "type": "Feature",
  "properties": {
    "addr:full":"Im Bungert 2 Oetwil Z\u00fcrich 8955",
    "addr:housenumber":"2",
    "addr:postcode":"8955",
    "addr:street":"Im Bungert",
    "iso:country":"CH",
    "sg:address":"Im Bungert 2",
    "sg:city":"Oetwil",
    "sg:orig_category":"Datenverarbeitungsdienste Detailhandel mit Computern U Software",
    "sg:postcode":"8955",
    "sg:province":"Z\u00fcrich",
    "wof:name":"Swissbyte Gmbh",
    "wof:placetype":"venue"
},
  "geometry": {"coordinates":[8.392165,47.429562],"type":"Point"}
}