{
  "type": "Feature",
  "properties": {
    "addr:full":"Via Peschiera Agno Ticino 6982",
    "addr:postcode":"6982",
    "addr:street":"Via Peschiera",
    "iso:country":"CH",
    "sg:address":"Via Peschiera",
    "sg:city":"Agno",
    "sg:classifiers":[
        {
            "category":"Social Services",
            "subcategory":"Retirement Home",
            "type":"Services"
        }
    ],
    "sg:phone":"+41 91 604 50 55",
    "sg:postcode":"6982",
    "sg:province":"Ticino",
    "sg:tags":[
        "pflegeheime",
        "u",
        "alters"
    ],
    "wof:name":"Casa Di Riposo Anziani Agno",
    "wof:placetype":"venue"
},
  "geometry": {"coordinates":[8.903475,45.997623],"type":"Point"}
}