{
  "type": "Feature",
  "properties": {
    "iso:country":"CH",
    "sg:address":"B\u00e4ckerstrasse 40",
    "sg:city":"Z\u00fcrich",
    "sg:orig_category":"Detailhandel mit Damenbekleidung Detailhandel mit Herrenbekleidung",
    "sg:phone":"+41 12429092",
    "sg:postcode":"8004",
    "sg:province":"Z\u00fcrich",
    "wof:name":"Dimetrius Ag Mode F\u00fcr M\u00e4nner & Frauen",
    "wof:placetype":"venue"
},
  "geometry": {"coordinates":[8.5290031433,47.3750839233],"type":"Point"}
}