{
  "type": "Feature",
  "properties": {
    "iso:country":"CH",
    "sg:address":"Rue Gilbert 38 1217 Meyrin. Postfach",
    "sg:city":"Meyrin",
    "sg:orig_category":"Interessenvertretungen",
    "sg:postcode":"1217",
    "sg:province":"Gen\u00e8ve",
    "wof:name":"Acad\u00e9mie Europ\u00e9enne De Dentisterie Esth\u00e9tique",
    "wof:placetype":"venue"
},
  "geometry": {"coordinates":[6.0829110146,46.2294540405],"type":"Point"}
}