{
  "type": "Feature",
  "properties": {
    "iso:country":"CH",
    "sg:address":"Z\u00fcrichstrasse 44 8306 Br\u00fcttisellen. Postfach",
    "sg:city":"Winterthur",
    "sg:orig_category":"RESTAURANTS: TEA-ROOMS",
    "sg:postcode":"8406",
    "sg:province":"Z\u00fcrich",
    "wof:name":"Fischbacher Fritz",
    "wof:placetype":"venue"
},
  "geometry": {"coordinates":[9.3096017838,47.4271774292],"type":"Point"}
}