{
  "type": "Feature",
  "properties": {
    "iso:country":"CH",
    "sg:address":"Gartenweg 1",
    "sg:city":"W\u00fcrenlos",
    "sg:orig_category":"Druck ohne Zeitungsdruck",
    "sg:phone":"+41 56 424 19 23",
    "sg:postcode":"5436",
    "sg:province":"Aargau",
    "wof:name":"Brader-nydegger Bruno, Drucksachenberatung",
    "wof:placetype":"venue"
},
  "geometry": {"coordinates":[8.3670167923,47.4414291382],"type":"Point"}
}