{
  "type": "Feature",
  "properties": {
    "iso:country":"CH",
    "sg:address":"Collonges Avenue 1 1004 Lausanne. Postfach",
    "sg:city":"Lausanne",
    "sg:orig_category":"RESTAURANTS: TEA-ROOMS",
    "sg:postcode":"1003",
    "sg:province":"Vaud",
    "wof:name":"Pietrini Monique Bar \u00e0 Caf\u00e9",
    "wof:placetype":"venue"
},
  "geometry": {"coordinates":[6.6215958595,46.5273933411],"type":"Point"}
}