{
  "type": "Feature",
  "properties": {
    "iso:country":"CH",
    "sg:address":"Zur Kreuzstr. 110",
    "sg:city":"Hettlingen",
    "sg:orig_category":"Unclassifiable Establishments",
    "sg:postcode":"8442",
    "sg:province":"Z\u00fcrich",
    "wof:name":"Agro Architektur Und Ingenieurb\u00fcro Walter Herter",
    "wof:placetype":"venue"
},
  "geometry": {"coordinates":[8.7085199356,47.547328949],"type":"Point"}
}