{
  "type": "Feature",
  "properties": {
    "iso:country":"CH",
    "sg:address":"Poststrasse 7b",
    "sg:city":"Geroldswil",
    "sg:orig_category":"Vereine Gesang",
    "sg:phone":"+41 71 966 42 24",
    "sg:postcode":"8954",
    "sg:province":"Z\u00fcrich",
    "wof:name":"Reformierter Kirchenchor",
    "wof:placetype":"venue"
},
  "geometry": {"coordinates":[8.9705295563,47.4648666382],"type":"Point"}
}