{
  "type": "Feature",
  "properties": {
    "iso:country":"CH",
    "sg:address":"8783",
    "sg:city":"Linthal",
    "sg:orig_category":"Allgemeiner Hoch U Tiefbau",
    "sg:phone":"+41 79 448 84 65",
    "sg:postcode":"8783",
    "sg:province":"Glarus",
    "wof:name":"Zweifel-k\u00fcttel Fritz",
    "wof:placetype":"venue"
},
  "geometry": {"coordinates":[8.99894,46.919571],"type":"Point"}
}