{
  "type": "Feature",
  "properties": {
    "iso:country":"CH",
    "sg:address":"Talstrasse 2",
    "sg:city":"Zollikon",
    "sg:orig_category":"Aktivit\u00e4ten der Generalunternehmen im Baugewerbe Allgemeiner Hoch U Tiefbau",
    "sg:phone":"+41 13837722",
    "sg:postcode":"8702",
    "sg:province":"Z\u00fcrich",
    "wof:name":"Fit Planungs Ag",
    "wof:placetype":"venue"
},
  "geometry": {"coordinates":[8.585052,47.351418],"type":"Point"}
}