{
  "type": "Feature",
  "properties": {
    "iso:country":"CH",
    "sg:address":"Sonnhaldenweg 24",
    "sg:city":"M\u00fcnsingen",
    "sg:orig_category":"Detektivb\u00fcros U \u00dcberwachung",
    "sg:postcode":"3110",
    "sg:province":"Bern",
    "wof:name":"Sigure Guggisberg Ren\u00e9",
    "wof:placetype":"venue"
},
  "geometry": {"coordinates":[7.5680370331,46.8795967102],"type":"Point"}
}