{
  "type": "Feature",
  "properties": {
    "addr:full":"Studenrain 6 Binz Z\u00fcrich 8122",
    "addr:housenumber":"6",
    "addr:postcode":"8122",
    "addr:street":"Studenrain",
    "iso:country":"CH",
    "sg:address":"Studenrain 6",
    "sg:city":"Binz",
    "sg:orig_category":"Dachdeckerei D\u00e4mmung gegen K\u00e4lte, W\u00e4rme, Schall U Ersch\u00fctterung",
    "sg:postcode":"8122",
    "sg:province":"Z\u00fcrich",
    "wof:name":"Gyr-dachservice Gmbh",
    "wof:placetype":"venue"
},
  "geometry": {"coordinates":[8.626898,47.355087],"type":"Point"}
}