{
  "type": "Feature",
  "properties": {
    "iso:country":"CH",
    "sg:address":"K\u00e4sernstrasse 2",
    "sg:city":"Aadorf",
    "sg:orig_category":"Sanit\u00e4rinstallation",
    "sg:phone":"+41 52 365 32 50",
    "sg:postcode":"8355",
    "sg:province":"Thurgau",
    "wof:name":"Marcel Sonderegger Sanit\u00e4r Service",
    "wof:placetype":"venue"
},
  "geometry": {"coordinates":[8.9023122787,47.489315033],"type":"Point"}
}