{
  "type": "Feature",
  "properties": {
    "iso:country":"CH",
    "sg:address":"Route De Corcelles 7",
    "sg:city":"Payerne",
    "sg:orig_category":"Lagerung",
    "sg:postcode":"1530",
    "sg:province":"Vaud",
    "wof:name":"Centre Collecteur Des C\u00e9r\u00e9ales De Payerne Et Environs.",
    "wof:placetype":"venue"
},
  "geometry": {"coordinates":[6.9453802109,46.8228187561],"type":"Point"}
}