{
  "type": "Feature",
  "properties": {
    "iso:country":"CH",
    "sg:address":"Gottardo Via San 56",
    "sg:city":"Minusio",
    "sg:orig_category":"RESTAURANTS: TEA-ROOMS",
    "sg:postcode":"6648",
    "sg:province":"Ticino",
    "wof:name":"Robi Sa",
    "wof:placetype":"venue"
},
  "geometry": {"coordinates":[8.8110456467,46.1753959656],"type":"Point"}
}