{
  "type": "Feature",
  "properties": {
    "addr:full":"Hengelenweg 673 Degersheim St. Gallen 9113",
    "addr:housenumber":"673;st.",
    "addr:postcode":"9113",
    "addr:street":"Degersheim",
    "iso:country":"CH",
    "sg:address":"Hengelenweg 673",
    "sg:city":"Degersheim",
    "sg:orig_category":"Allgemeiner Hoch U Tiefbau",
    "sg:postcode":"9113",
    "sg:province":"St. Gallen",
    "wof:name":"Gz Bau Gmbh",
    "wof:placetype":"venue"
},
  "geometry": {"coordinates":[9.206383,47.373932],"type":"Point"}
}