{
  "type": "Feature",
  "properties": {
    "iso:country":"CH",
    "sg:address":"Rue Du V\u00e9lodrome 4",
    "sg:city":"Gen\u00e8ve",
    "sg:orig_category":"Grafikateliers, Design Werbung",
    "sg:phone":"+41 22 328 38 50",
    "sg:postcode":"1205",
    "sg:province":"Gen\u00e8ve",
    "wof:name":"Castella Gilbert Publicit\u00e9",
    "wof:placetype":"venue"
},
  "geometry": {"coordinates":[6.1301031113,46.2001304626],"type":"Point"}
}