{
  "type": "Feature",
  "properties": {
    "iso:country":"CH",
    "sg:address":"Weiherstrasse 366",
    "sg:city":"K\u00fcnten",
    "sg:orig_category":"Unternehmensberatung",
    "sg:postcode":"5444",
    "sg:province":"Aargau",
    "wof:name":"Niederberger Hans Peter",
    "wof:placetype":"venue"
},
  "geometry": {"coordinates":[8.3326101303,47.3871192932],"type":"Point"}
}