{
  "type": "Feature",
  "properties": {
    "iso:country":"CH",
    "sg:address":"Bahnhofstr 26",
    "sg:city":"Zug",
    "sg:classifiers":[
        {
            "category":"Banks & Credit Unions",
            "subcategory":"Bank",
            "type":"Services"
        }
    ],
    "sg:phone":"+41 4142228575",
    "sg:postcode":"6301",
    "sg:province":"Zug",
    "wof:name":"Schweiz. Bankgesellschaft",
    "wof:placetype":"venue"
},
  "geometry": {"coordinates":[8.515909,47.169979],"type":"Point"}
}