{
  "type": "Feature",
  "properties": {
    "iso:country":"CH",
    "sg:address":"Rue Edmond-de-reynier 2",
    "sg:city":"Neuch\u00e2tel",
    "sg:orig_category":"Kinderkrippen U horte",
    "sg:phone":"+41 32 721 17 79",
    "sg:postcode":"2000",
    "sg:province":"Neuch\u00e2tel",
    "wof:name":"Garderie D'enfants Les Nanous",
    "wof:placetype":"venue"
},
  "geometry": {"coordinates":[6.940267086,46.9962806702],"type":"Point"}
}