{
  "type": "Feature",
  "properties": {
    "iso:country":"CH",
    "sg:address":"Fontanettes Chemin Des 4",
    "sg:city":"Blonay",
    "sg:orig_category":"Erwachsenenbildung U Unterricht",
    "sg:phone":"+41 21 943 32 11",
    "sg:postcode":"1807",
    "sg:province":"Vaud",
    "wof:name":"Comunicare, Marcel Boner",
    "wof:placetype":"venue"
},
  "geometry": {"coordinates":[6.8950920105,46.4786224365],"type":"Point"}
}