{
  "type": "Feature",
  "properties": {
    "iso:country":"CH",
    "sg:address":"Quellenstrasse 6",
    "sg:city":"Z\u00fcrich",
    "sg:orig_category":"RESTAURANTS: TEA-ROOMS",
    "sg:phone":"+41 71 222 86 83",
    "sg:postcode":"8005",
    "sg:province":"Z\u00fcrich",
    "wof:name":"Netts Sch\u00fctzengarten, K\u00f6bi Nett",
    "wof:placetype":"venue"
},
  "geometry": {"coordinates":[9.3752880096,47.4233665466],"type":"Point"}
}