{
  "type": "Feature",
  "properties": {
    "iso:country":"CH",
    "sg:address":"Neptunstrasse 88",
    "sg:city":"Z\u00fcrich",
    "sg:orig_category":"Sonstige Vermietung U Verpachtung von eigenen Immobilien Verwaltung von Immobilien",
    "sg:phone":"+41 13803390",
    "sg:postcode":"8032",
    "sg:province":"Z\u00fcrich",
    "wof:name":"Neptun Immobilien Gmbh Administrative U. Techn. Liegenschaftenverwaltung",
    "wof:placetype":"venue"
},
  "geometry": {"coordinates":[8.5581674576,47.3647689819],"type":"Point"}
}