{
  "type": "Feature",
  "properties": {
    "iso:country":"CH",
    "sg:address":"Seestrasse 11",
    "sg:city":"Z\u00fcrich",
    "sg:orig_category":"Detailhandel mit Antiquit\u00e4ten Kunsthandel",
    "sg:phone":"+41 12024445",
    "sg:postcode":"8002",
    "sg:province":"Z\u00fcrich",
    "wof:name":"Peter Valsangiacomo Alte Galerie Enge",
    "wof:placetype":"venue"
},
  "geometry": {"coordinates":[8.531676,47.365063],"type":"Point"}
}