{
  "type": "Feature",
  "properties": {
    "iso:country":"CH",
    "sg:address":"Gare Avenue De La 10",
    "sg:city":"Lausanne",
    "sg:orig_category":"Softwareentwicklung U beratung",
    "sg:postcode":"1003",
    "sg:province":"Vaud",
    "wof:name":"Online, J. Luis Alvarez",
    "wof:placetype":"venue"
},
  "geometry": {"coordinates":[8.2784233093,46.9417533875],"type":"Point"}
}