{
  "type": "Feature",
  "properties": {
    "iso:country":"CH",
    "sg:address":"Wissenhusen",
    "sg:city":"Sch\u00f6tz",
    "sg:orig_category":"Vermietung U Verpachtung von eigenen Immobilien",
    "sg:postcode":"6247",
    "sg:province":"Luzern",
    "wof:name":"Gsp Invest Ag",
    "wof:placetype":"venue"
},
  "geometry": {"coordinates":[7.9924650192,47.1720657349],"type":"Point"}
}