{
  "type": "Feature",
  "properties": {
    "addr:full":"Bleienbachstrasse 1a Lotzwil Bern 4932",
    "addr:housenumber":"1a",
    "addr:postcode":"4932",
    "addr:street":"Bleienbachstrasse",
    "iso:country":"CH",
    "sg:address":"Bleienbachstrasse 1a",
    "sg:city":"Lotzwil",
    "sg:orig_category":"Architektur U Ingenieurb\u00fcros",
    "sg:phone":"+41 56 496 61 04",
    "sg:postcode":"4932",
    "sg:province":"Bern",
    "wof:name":"Sch\u00fcpbach Ingenieure Ag",
    "wof:placetype":"venue"
},
  "geometry": {"coordinates":[8.07563,47.388069],"type":"Point"}
}