{
  "type": "Feature",
  "properties": {
    "iso:country":"CH",
    "sg:address":"Rorschacherstrasse 1970",
    "sg:city":"L\u00fcchingen",
    "sg:orig_category":"Zimmerei, Dachdeckerei, Bauspenglerei U Abdichtung",
    "sg:phone":"+41 71 755 40 60",
    "sg:postcode":"9450",
    "sg:province":"St. Gallen",
    "wof:name":"Eugster Holzbau Ag, Altst\u00e4tten",
    "wof:placetype":"venue"
},
  "geometry": {"coordinates":[9.5629196167,47.3894386292],"type":"Point"}
}