{
  "type": "Feature",
  "properties": {
    "iso:country":"CH",
    "sg:address":"Frontenex Avenue De 57 1207 Gen\u00e8ve. Postfach",
    "sg:city":"Gen\u00e8ve",
    "sg:orig_category":"Sonstige mit der Informatik verbundene T\u00e4tigkeiten",
    "sg:phone":"+41 22 786 65 15",
    "sg:postcode":"1201",
    "sg:province":"Gen\u00e8ve",
    "wof:name":"Astrabacos S\u00e0rl",
    "wof:placetype":"venue"
},
  "geometry": {"coordinates":[6.1654090881,46.2029075623],"type":"Point"}
}