{
  "type": "Feature",
  "properties": {
    "iso:country":"CH",
    "sg:address":"Wengistrasse 7",
    "sg:city":"Z\u00fcrich",
    "sg:orig_category":"Rechtsberatung",
    "sg:phone":"+41 12421010",
    "sg:postcode":"8004",
    "sg:province":"Z\u00fcrich",
    "wof:name":"Kern-haus Ag",
    "wof:placetype":"venue"
},
  "geometry": {"coordinates":[8.52298069,47.3749923706],"type":"Point"}
}