{
  "type": "Feature",
  "properties": {
    "iso:country":"CH",
    "sg:address":"Kirchstrasse 9",
    "sg:city":"Lausen",
    "sg:orig_category":"Autotransporte international",
    "sg:phone":"+41 21 960 15 82",
    "sg:postcode":"4415",
    "sg:province":"Basel-Landschaft",
    "wof:name":"Gilbert Borloz Transports Internationaux",
    "wof:placetype":"venue"
},
  "geometry": {"coordinates":[6.925848,46.397488],"type":"Point"}
}