{
  "type": "Feature",
  "properties": {
    "iso:country":"CH",
    "sg:address":"Chemin Des Comballes",
    "sg:city":"Fully",
    "sg:orig_category":"Abbruch U Sprenggewerbe, Erdbewegungsarbeiten",
    "sg:postcode":"1926",
    "sg:province":"Valais",
    "wof:name":"Boson Serge",
    "wof:placetype":"venue"
},
  "geometry": {"coordinates":[7.13684,46.153198],"type":"Point"}
}