{
  "type": "Feature",
  "properties": {
    "iso:country":"CH",
    "sg:address":"1042",
    "sg:city":"Assens",
    "sg:orig_category":"Blumen U Zierpflanzenbau Gem\u00fcsebau",
    "sg:phone":"+41 21 881 25 81",
    "sg:postcode":"1042",
    "sg:province":"Vaud",
    "wof:name":"Andr\u00e9fleurs Assens Sa",
    "wof:placetype":"venue"
},
  "geometry": {"coordinates":[6.6212,46.614136],"type":"Point"}
}