{
  "type": "Feature",
  "properties": {
    "iso:country":"CH",
    "sg:address":"Bourdines Chemin Des 7 1617 Remaufens. Postfach",
    "sg:city":"Remaufens",
    "sg:orig_category":"Mechanik",
    "sg:postcode":"1617",
    "sg:province":"Fribourg",
    "wof:name":"Service-ouverture-serrures Bonzon Bernard",
    "wof:placetype":"venue"
},
  "geometry": {"coordinates":[7.0150179863,46.2777519226],"type":"Point"}
}