{
  "type": "Feature",
  "properties": {
    "addr:full":"Schmidhof Baar Zug 6340",
    "addr:postcode":"6340",
    "addr:street":"Schmidhof;Zug",
    "iso:country":"CH",
    "sg:address":"Schmidhof",
    "sg:city":"Baar",
    "sg:classifiers":[
        {
            "category":"Professional",
            "subcategory":"Art Services",
            "type":"Services"
        }
    ],
    "sg:phone":"+41 41 760 46 80",
    "sg:postcode":"6340",
    "sg:province":"Zug",
    "sg:tags":[
        "print"
    ],
    "wof:name":"Siebdruckatelier Andermatt-g\u00fcntensperger Ag",
    "wof:placetype":"venue"
},
  "geometry": {"coordinates":[8.520215,47.197041],"type":"Point"}
}