{
  "type": "Feature",
  "properties": {
    "iso:country":"CH",
    "sg:address":"Indipendenza Piazza 2",
    "sg:city":"Bellinzona",
    "sg:orig_category":"Sonstiger Grosshandel",
    "sg:phone":"+41 91 826 47 66",
    "sg:postcode":"6500",
    "sg:province":"Ticino",
    "wof:name":"Waterfile Sagl",
    "wof:placetype":"venue"
},
  "geometry": {"coordinates":[9.0226621628,46.1900367737],"type":"Point"}
}