{
  "type": "Feature",
  "properties": {
    "iso:country":"CH",
    "sg:address":"Chantemerle Route De 58 1763 Granges-paccot. Postfach",
    "sg:city":"Granges-paccot",
    "sg:orig_category":"Sonstige pers\u00f6nliche Dienstleistungen",
    "sg:postcode":"1763",
    "sg:province":"Fribourg",
    "wof:name":"First Film Partners S\u00e0rl Conseil \u00e0 L'industrie Cin\u00e9matographique",
    "wof:placetype":"venue"
},
  "geometry": {"coordinates":[7.140182972,46.820224762],"type":"Point"}
}