{
  "type": "Feature",
  "properties": {
    "iso:country":"CH",
    "sg:address":"Bernstrasse 107",
    "sg:city":"Steffisburg",
    "sg:classifiers":[
        {
            "category":"Social Services",
            "subcategory":"Retirement Home",
            "type":"Services"
        }
    ],
    "sg:phone":"+41 33 251 12 25",
    "sg:postcode":"3613",
    "sg:province":"Bern",
    "sg:tags":[
        "pflegeheime",
        "u",
        "alters"
    ],
    "wof:name":"B\u00e4rgrueh Betagten-& Pflegeheim",
    "wof:placetype":"venue"
},
  "geometry": {"coordinates":[7.69909,46.719727],"type":"Point"}
}