{
  "type": "Feature",
  "properties": {
    "iso:country":"CH",
    "sg:address":"Z\u00fcrcherstrasse 137",
    "sg:city":"Oberengstringen",
    "sg:orig_category":"Elektroinstallation",
    "sg:phone":"+41 17504423",
    "sg:postcode":"8102",
    "sg:province":"Z\u00fcrich",
    "wof:name":"Daniel Weber Eldasa",
    "wof:placetype":"venue"
},
  "geometry": {"coordinates":[8.4602527618,47.4098167419],"type":"Point"}
}