{
  "type": "Feature",
  "properties": {
    "iso:country":"CH",
    "sg:address":"Watterstrasse 59",
    "sg:city":"Regensdorf",
    "sg:orig_category":"Arztpraxen",
    "sg:phone":"+41 18400303",
    "sg:postcode":"8105",
    "sg:province":"Z\u00fcrich",
    "wof:name":"Dr.med.silvan Br\u00fcschweiler Spezialarzt Fmh",
    "wof:placetype":"venue"
},
  "geometry": {"coordinates":[8.466801,47.432247],"type":"Point"}
}