{
  "type": "Feature",
  "properties": {
    "iso:country":"CH",
    "sg:address":"Talackerstrasse 8 8274 T\u00e4gerwilen. Postfach",
    "sg:city":"T\u00e4gerwilen",
    "sg:orig_category":"Herstellung von Betonerzeugnissen f\u00fcr den Bau Herstellung von Transportbeton",
    "sg:phone":"+41 71 669 13 55",
    "sg:postcode":"8274",
    "sg:province":"Thurgau",
    "wof:name":"Kies Und Beton Seegau T\u00e4gerwilen Ag",
    "wof:placetype":"venue"
},
  "geometry": {"coordinates":[9.1334905624,47.6565895081],"type":"Point"}
}