{
  "type": "Feature",
  "properties": {
    "iso:country":"CH",
    "sg:address":"Le Noyer Amey",
    "sg:city":"Domdidier",
    "sg:orig_category":"Bauschreinerei",
    "sg:phone":"+41 26 675 50 28",
    "sg:postcode":"1564",
    "sg:province":"Fribourg",
    "wof:name":"Andr\u00e9 Waser S\u00e0rl Charpentes En Bois",
    "wof:placetype":"venue"
},
  "geometry": {"coordinates":[7.015135,46.865307],"type":"Point"}
}