{
  "type": "Feature",
  "properties": {
    "iso:country":"CH",
    "sg:address":"Alte Feldeggstrasse 12/14",
    "sg:city":"Z\u00fcrich",
    "sg:orig_category":"Werbegrafikateliers",
    "sg:phone":"+41 13837640",
    "sg:postcode":"8008",
    "sg:province":"Z\u00fcrich",
    "wof:name":"Piroska Morocz Atelier Im Hinterhof",
    "wof:placetype":"venue"
},
  "geometry": {"coordinates":[8.5500383377,47.3595199585],"type":"Point"}
}