{
  "type": "Feature",
  "properties": {
    "iso:country":"CH",
    "sg:address":"Augraben 10",
    "sg:city":"Bremgarten",
    "sg:classifiers":[
        {
            "category":"Communications",
            "subcategory":"Newspaper",
            "type":"Services"
        }
    ],
    "sg:phone":"+41 56 633 38 88",
    "sg:postcode":"5620",
    "sg:province":"Aargau",
    "sg:tags":[
        "material",
        "-",
        "packaging",
        "raw",
        "paper",
        "cardboard"
    ],
    "wof:name":"Karton & Papierfabrik Ag",
    "wof:placetype":"venue"
},
  "geometry": {"coordinates":[8.3369493484,47.3528862],"type":"Point"}
}