{
  "type": "Feature",
  "properties": {
    "iso:country":"CH",
    "sg:address":"Hofwiesenweg 10",
    "sg:city":"H\u00fcttikon",
    "sg:orig_category":"Fussboden, Fliesen U Plattenlegerei, Tapeziererei Verlegen von Fliesen U Platten",
    "sg:phone":"+41 18443126",
    "sg:postcode":"8115",
    "sg:province":"Z\u00fcrich",
    "wof:name":"Huber Anton",
    "wof:placetype":"venue"
},
  "geometry": {"coordinates":[8.3857917786,47.447227478],"type":"Point"}
}