{
  "type": "Feature",
  "properties": {
    "iso:country":"CH",
    "sg:address":"1891",
    "sg:city":"V\u00e9rossaz",
    "sg:orig_category":"Sanit\u00e4r U Heizungsinstallation Sanit\u00e4rinstallation",
    "sg:phone":"+41 79 355 40 76",
    "sg:postcode":"1891",
    "sg:province":"Valais",
    "wof:name":"Mottola Claude",
    "wof:placetype":"venue"
},
  "geometry": {"coordinates":[6.9876022339,46.2100830078],"type":"Point"}
}