{
  "type": "Feature",
  "properties": {
    "iso:country":"CH",
    "sg:address":"Stutzstrasse 5",
    "sg:city":"Niederwichtrach",
    "sg:orig_category":"Non-Classified Establishments",
    "sg:postcode":"3114",
    "sg:province":"Bern",
    "wof:name":"Immoaqua Ag",
    "wof:placetype":"venue"
},
  "geometry": {"coordinates":[7.579264164,46.8500366211],"type":"Point"}
}