{
  "type": "Feature",
  "properties": {
    "iso:country":"CH",
    "sg:address":"Im Eichli 25",
    "sg:city":"Ober\u00e4geri",
    "sg:orig_category":"Grosshandel mit sonstigen Maschinen U Ausr\u00fcstungen f\u00fcr Industrie, Handel U Schiffahrt",
    "sg:phone":"+41 41 750 67 77",
    "sg:postcode":"6315",
    "sg:province":"Zug",
    "wof:name":"Seagull Gmbh",
    "wof:placetype":"venue"
},
  "geometry": {"coordinates":[8.6304159164,47.1347198486],"type":"Point"}
}