{
  "type": "Feature",
  "properties": {
    "addr:full":"Lochbachstrasse 2 Oberburg 3400 Burgdorf. Postfach Oberburg Bern 3414",
    "addr:housenumber":"2",
    "addr:postcode":"3400 burgdorf. postfach;3414",
    "addr:street":"Lochbachstrasse",
    "iso:country":"CH",
    "sg:address":"Lochbachstrasse 2 Oberburg 3400 Burgdorf. Postfach",
    "sg:city":"Oberburg",
    "sg:orig_category":"Allgemeiner Hoch U Tiefbau",
    "sg:phone":"+41 34 422 97 77",
    "sg:postcode":"3414",
    "sg:province":"Bern",
    "wof:name":"Jenni Liegenschaften Ag",
    "wof:placetype":"venue"
},
  "geometry": {"coordinates":[7.624515,47.054844],"type":"Point"}
}