{
  "type": "Feature",
  "properties": {
    "iso:country":"CH",
    "sg:address":"Solothurnerstrasse 121 4600 Olten. Postfach",
    "sg:city":"Olten",
    "sg:orig_category":"Werbeagenturen",
    "sg:phone":"+41 62 205 90 40",
    "sg:postcode":"4601",
    "sg:province":"Solothurn",
    "wof:name":"Brandl & Sch\u00e4rer Ag",
    "wof:placetype":"venue"
},
  "geometry": {"coordinates":[7.8935160637,47.3509864807],"type":"Point"}
}