{
  "type": "Feature",
  "properties": {
    "iso:country":"CH",
    "sg:address":"Caraa Servetta 36",
    "sg:city":"Losone",
    "sg:orig_category":"Erbringung von Dienstleistungen f\u00fcr Unternehmen",
    "sg:phone":"+41 91 791 39 33",
    "sg:postcode":"6616",
    "sg:province":"Ticino",
    "wof:name":"Hgs Productions Doering Harald",
    "wof:placetype":"venue"
},
  "geometry": {"coordinates":[8.7598142624,46.1632728577],"type":"Point"}
}