{
  "type": "Feature",
  "properties": {
    "iso:country":"CH",
    "sg:address":"B\u00e4ndlistrasse 62 8064 Z\u00fcrich. Postfach",
    "sg:city":"Z\u00fcrich",
    "sg:orig_category":"Reinigungsgewerbe",
    "sg:phone":"+41 14328275",
    "sg:postcode":"8064",
    "sg:province":"Z\u00fcrich",
    "wof:name":"Julia Aliu, Reinigungsinstitut Und Baurenovationen",
    "wof:placetype":"venue"
},
  "geometry": {"coordinates":[8.4835538864,47.3970565796],"type":"Point"}
}