{
  "type": "Feature",
  "properties": {
    "addr:full":"Dorfplatz 6 6383 Dallenwil. Postfach Dallenwil Nidwalden 6383",
    "addr:housenumber":"6",
    "addr:postcode":"6383 dallenwil. postfach;6383",
    "addr:street":"Dorfplatz",
    "iso:country":"CH",
    "sg:address":"Dorfplatz 6 6383 Dallenwil. Postfach",
    "sg:city":"Dallenwil",
    "sg:orig_category":"Architektur U Ingenieurb\u00fcros Architekturb\u00fcros",
    "sg:phone":"+41 26 670 10 09",
    "sg:postcode":"6383",
    "sg:province":"Nidwalden",
    "wof:name":"Architekturb\u00fcro Jungi Fritz",
    "wof:placetype":"venue"
},
  "geometry": {"coordinates":[7.108453,46.925232],"type":"Point"}
}