{
  "type": "Feature",
  "properties": {
    "iso:country":"CH",
    "sg:address":"Aarburgerstrasse 17/37 4800 Zofingen. Postfach",
    "sg:city":"Zofingen",
    "sg:classifiers":[
        {
            "category":"Communications",
            "subcategory":"Radio Station",
            "type":"Services"
        }
    ],
    "sg:phone":"+41 62 797 57 58",
    "sg:postcode":"4800",
    "sg:province":"Aargau",
    "sg:tags":[
        "fernsehanstalten",
        "u"
    ],
    "wof:name":"Videocompany",
    "wof:placetype":"venue"
},
  "geometry": {"coordinates":[7.9404129982,47.2926368713],"type":"Point"}
}