{
  "type": "Feature",
  "properties": {
    "addr:full":"Wartgutstrasse 16 8413 Neftenbach. Postfach 214 Neftenbach Z\u00fcrich 8413",
    "addr:housenumber":"16;214",
    "addr:postcode":"8413;8413",
    "addr:street":"Wartgutstrasse;Postfach",
    "iso:country":"CH",
    "sg:address":"Wartgutstrasse 16 8413 Neftenbach. Postfach 214",
    "sg:city":"Neftenbach",
    "sg:orig_category":"Allgemeiner Hoch U Tiefbau Allgemeiner Hochbau",
    "sg:phone":"+41 52 315 41 16",
    "sg:postcode":"8413",
    "sg:province":"Z\u00fcrich",
    "wof:name":"Walter Melere Ag Baugesch\u00e4ft",
    "wof:placetype":"venue"
},
  "geometry": {"coordinates":[8.664387,47.528519],"type":"Point"}
}