{
  "type": "Feature",
  "properties": {
    "iso:country":"CH",
    "sg:address":"Stalden 316 3419 Biembach. Postfach",
    "sg:city":"Biembach",
    "sg:orig_category":"Grosshandel mit Nahrungsmitteln, Getr\u00e4nken U Tabakwaren ohne ausgepr\u00e4gten Schwerpunkt",
    "sg:postcode":"3419",
    "sg:province":"Bern",
    "wof:name":"Rindisbacher-gerber Barbara",
    "wof:placetype":"venue"
},
  "geometry": {"coordinates":[7.628308773,47.0022506714],"type":"Point"}
}