{
  "type": "Feature",
  "properties": {
    "iso:country":"CH",
    "sg:address":"Morgartenstrasse 17 6003 Luzern. Postfach",
    "sg:city":"Luzern",
    "sg:orig_category":"Reinigungsgewerbe",
    "sg:phone":"+41 41 210 77 77",
    "sg:postcode":"6003",
    "sg:province":"Luzern",
    "wof:name":"Iss Hospital Service Ag Dienstleistungen Im Krankenhausbereich. Raum- U. Bodenpflege Usw",
    "wof:placetype":"venue"
},
  "geometry": {"coordinates":[8.3090372086,47.0482826233],"type":"Point"}
}