{
  "type": "Feature",
  "properties": {
    "iso:country":"CH",
    "sg:address":"Avenue De Jurigoz 20 B 1000 Lausanne. Postfach",
    "sg:city":"Lausanne",
    "sg:orig_category":"RESTAURANTS: TEA-ROOMS",
    "sg:postcode":"1003",
    "sg:province":"Vaud",
    "wof:name":"Djerba La Douce, Jemmali M",
    "wof:placetype":"venue"
},
  "geometry": {"coordinates":[6.6369729042,46.5114517212],"type":"Point"}
}