{
  "type": "Feature",
  "properties": {
    "iso:country":"CH",
    "sg:address":"Beatengasse 4",
    "sg:city":"Z\u00fcrich",
    "sg:orig_category":"Detailhandel mit Bekleidung Public-Relations-Agenturen",
    "sg:phone":"+41 12104080",
    "sg:postcode":"8001",
    "sg:province":"Z\u00fcrich",
    "wof:name":"White Room Gmbh",
    "wof:placetype":"venue"
},
  "geometry": {"coordinates":[8.540035,47.375961],"type":"Point"}
}