{
  "type": "Feature",
  "properties": {
    "iso:country":"CH",
    "sg:address":"B\u00e4raugrundstrasse 5",
    "sg:city":"B\u00e4rau",
    "sg:orig_category":"Betrieb von Taxis",
    "sg:phone":"+41 55 240 22 45",
    "sg:postcode":"3552",
    "sg:province":"Bern",
    "wof:name":"Fritz Hiltbrand Funk-taxi",
    "wof:placetype":"venue"
},
  "geometry": {"coordinates":[8.853125,47.266693],"type":"Point"}
}