{
  "type": "Feature",
  "properties": {
    "iso:country":"CH",
    "sg:address":"4118",
    "sg:city":"Rodersdorf",
    "sg:orig_category":"Herstellung von Konstruktionsteilen, Fertigbauteilen U Ausbauelementen aus Holz",
    "sg:postcode":"4118",
    "sg:province":"Solothurn",
    "wof:name":"Hasler S\u00f6hne.",
    "wof:placetype":"venue"
},
  "geometry": {"coordinates":[7.4459300041,47.4844207764],"type":"Point"}
}