{
  "type": "Feature",
  "properties": {
    "iso:country":"CH",
    "sg:address":"Steinbachstrasse 23",
    "sg:city":"Belp",
    "sg:orig_category":"RESTAURANTS: TEA-ROOMS",
    "sg:phone":"+41 31 819 55 37",
    "sg:postcode":"3123",
    "sg:province":"Bern",
    "wof:name":"Caf\u00e9 Treffpunkt, M\u00fcller Peter",
    "wof:placetype":"venue"
},
  "geometry": {"coordinates":[7.4933371544,46.8957214355],"type":"Point"}
}