{
  "type": "Feature",
  "properties": {
    "iso:country":"CH",
    "sg:address":"Chemin De Maisonneuve 5",
    "sg:city":"Ch\u00e2telaine",
    "sg:orig_category":"Nationale Postdienste",
    "sg:phone":"+41 22 796 41 22",
    "sg:postcode":"1219",
    "sg:province":"Gen\u00e8ve",
    "wof:name":"La Poste Suisse",
    "wof:placetype":"venue"
},
  "geometry": {"coordinates":[6.1121311188,46.2116546631],"type":"Point"}
}