{
  "type": "Feature",
  "properties": {
    "iso:country":"CH",
    "sg:address":"Av. De Collonge 38",
    "sg:city":"Montreux",
    "sg:orig_category":"Sonstiges Versicherungsgewerbe",
    "sg:phone":"+41 21 963 70 80",
    "sg:postcode":"1820",
    "sg:province":"Vaud",
    "wof:name":"Yersin Edmond",
    "wof:placetype":"venue"
},
  "geometry": {"coordinates":[6.9248838425,46.4264831543],"type":"Point"}
}