{
  "type": "Feature",
  "properties": {
    "iso:country":"CH",
    "sg:address":"Route De Vernier 144",
    "sg:city":"Vernier",
    "sg:orig_category":"Erbringung von Dienstleistungen f\u00fcr Unternehmen Grosshandel mit Datenverarbeitungsger\u00e4ten",
    "sg:phone":"+41 22 346 04 20",
    "sg:postcode":"1214",
    "sg:province":"Gen\u00e8ve",
    "wof:name":"Scripto Documentation Sa",
    "wof:placetype":"venue"
},
  "geometry": {"coordinates":[6.1570091248,46.1906967163],"type":"Point"}
}