{
  "type": "Feature",
  "properties": {
    "iso:country":"CH",
    "sg:address":"Winzerstrasse 26",
    "sg:city":"Z\u00fcrich",
    "sg:orig_category":"Bauschreinerei",
    "sg:phone":"+41 13417251",
    "sg:postcode":"8049",
    "sg:province":"Z\u00fcrich",
    "wof:name":"Walter Maurer Mechanische Schreinerei",
    "wof:placetype":"venue"
},
  "geometry": {"coordinates":[8.49206,47.400955],"type":"Point"}
}