{
  "type": "Feature",
  "properties": {
    "iso:country":"CH",
    "sg:address":"Brunnenweg 4 3186 D\u00fcdingen. Postfach 100",
    "sg:city":"D\u00fcdingen",
    "sg:orig_category":"Vermietung U Verpachtung von eigenen Immobilien Vermittlung von Immobilien",
    "sg:phone":"+41 26 493 45 20",
    "sg:postcode":"3186",
    "sg:province":"Fribourg",
    "wof:name":"Jfag Immobilien Ag",
    "wof:placetype":"venue"
},
  "geometry": {"coordinates":[7.1902799606,46.8497772217],"type":"Point"}
}