{
  "type": "Feature",
  "properties": {
    "iso:country":"CH",
    "sg:address":"Feldmattstrasse 38",
    "sg:city":"Emmen",
    "sg:orig_category":"Mechanik Mechanische Werkst\u00e4tten",
    "sg:postcode":"6032",
    "sg:province":"Luzern",
    "wof:name":"Felder Hanspeter",
    "wof:placetype":"venue"
},
  "geometry": {"coordinates":[8.3233098984,47.1097564697],"type":"Point"}
}