{
  "type": "Feature",
  "properties": {
    "iso:country":"CH",
    "sg:address":"L\u00f6wenstrasse 16",
    "sg:city":"Kreuzlingen",
    "sg:orig_category":"Versicherungen Generalagenturen",
    "sg:phone":"+41 71 677 95 15",
    "sg:postcode":"8280",
    "sg:province":"Thurgau",
    "wof:name":"Rentenanstalt/swiss Life Generalagentur Daniel Staub",
    "wof:placetype":"venue"
},
  "geometry": {"coordinates":[9.171790123,47.6478843689],"type":"Point"}
}