{
  "type": "Feature",
  "properties": {
    "iso:country":"CH",
    "sg:address":"Hauptstrasse 1",
    "sg:city":"Hermrigen",
    "sg:orig_category":"Sportvereine Triathlon Laufen, Schwimmen, Velo",
    "sg:phone":"+41 71 245 36 16",
    "sg:postcode":"3274",
    "sg:province":"Bern",
    "wof:name":"Tri Club St.gallen-appenzell",
    "wof:placetype":"venue"
},
  "geometry": {"coordinates":[9.3832406998,47.4339561462],"type":"Point"}
}