{
  "type": "Feature",
  "properties": {
    "iso:country":"CH",
    "sg:address":"Rue De Rive 51",
    "sg:city":"Nyon",
    "sg:orig_category":"D\u00e4mmung gegen K\u00e4lte, W\u00e4rme, Schall U Ersch\u00fctterung Herstellung von sonstigen Metallwaren",
    "sg:phone":"+41 81 756 17 82",
    "sg:postcode":"1260",
    "sg:province":"Vaud",
    "wof:name":"M\u00fcller Ronny Isolierungen Ag",
    "wof:placetype":"venue"
},
  "geometry": {"coordinates":[9.4682731628,47.1664657593],"type":"Point"}
}