{
  "type": "Feature",
  "properties": {
    "iso:country":"CH",
    "sg:address":"Drahtzugstrasse 47",
    "sg:city":"Basel",
    "sg:orig_category":"Unclassifiable Establishments",
    "sg:phone":"+41 61 681 36 63",
    "sg:postcode":"4057",
    "sg:province":"Basel-Stadt",
    "wof:name":"Xinox Ag",
    "wof:placetype":"venue"
},
  "geometry": {"coordinates":[7.596560955,47.5637969971],"type":"Point"}
}