{
  "type": "Feature",
  "properties": {
    "iso:country":"CH",
    "sg:address":"Chemin De Grange-collomb 6",
    "sg:city":"Grand-lancy",
    "sg:orig_category":"Grosshandel mit Getr\u00e4nken Grosshandel mit Wein U Spirituosen",
    "sg:phone":"+41 22 342 27 28",
    "sg:postcode":"1212",
    "sg:province":"Gen\u00e8ve",
    "wof:name":"Vilaclara Jr & Co",
    "wof:placetype":"venue"
},
  "geometry": {"coordinates":[6.1333007812,46.1755561829],"type":"Point"}
}