{
  "type": "Feature",
  "properties": {
    "iso:country":"CH",
    "sg:address":"Waaggasse 5 8001 Z\u00fcrich. Postfach",
    "sg:city":"Z\u00fcrich",
    "sg:orig_category":"Aktivit\u00e4t der Bankinstitute",
    "sg:phone":"+41 12083711",
    "sg:postcode":"8027",
    "sg:province":"Z\u00fcrich",
    "wof:name":"Banque Edouard Constant S.a.",
    "wof:placetype":"venue"
},
  "geometry": {"coordinates":[8.539983,47.37006],"type":"Point"}
}