{
  "type": "Feature",
  "properties": {
    "iso:country":"CH",
    "sg:address":"Cantonale Via",
    "sg:city":"Contone",
    "sg:orig_category":"Instandhaltung U Reparatur von Automobilen",
    "sg:phone":"+41 19305650",
    "sg:postcode":"6594",
    "sg:province":"Ticino",
    "wof:name":"Garage Di Paolo Ag",
    "wof:placetype":"venue"
},
  "geometry": {"coordinates":[8.7970104218,47.3322944641],"type":"Point"}
}