{
  "type": "Feature",
  "properties": {
    "iso:country":"CH",
    "sg:address":"6442",
    "sg:city":"Gersau",
    "sg:orig_category":"Schulpflegen",
    "sg:phone":"+41 41 850 62 50",
    "sg:postcode":"6442",
    "sg:province":"Schwyz",
    "wof:name":"Schulrat Des Bezirks K\u00fcssnacht Am Rigi",
    "wof:placetype":"venue"
},
  "geometry": {"coordinates":[8.4415683746,47.0812110901],"type":"Point"}
}