{
  "type": "Feature",
  "properties": {
    "addr:full":"Chemin Franconis 9 Versoix Gen\u00e8ve 1290",
    "addr:housenumber":"9",
    "addr:postcode":"1290",
    "addr:street":"Chemin Franconis",
    "iso:country":"CH",
    "sg:address":"Chemin Franconis 9",
    "sg:city":"Versoix",
    "sg:orig_category":"Datenverarbeitungsdienste",
    "sg:phone":"+41 22 755 50 57",
    "sg:postcode":"1290",
    "sg:province":"Gen\u00e8ve",
    "wof:name":"Cerisa Conseils Etudes & R\u00e9alisations Informatique Sa",
    "wof:placetype":"venue"
},
  "geometry": {"coordinates":[6.155014,46.285831],"type":"Point"}
}