{
  "type": "Feature",
  "properties": {
    "addr:full":"Friedhofstrasse 10 Birsfelden Basel-Landschaft 4127",
    "addr:housenumber":"10",
    "addr:postcode":"4127",
    "addr:street":"Friedhofstrasse",
    "iso:country":"CH",
    "sg:address":"Friedhofstrasse 10",
    "sg:city":"Birsfelden",
    "sg:orig_category":"Bauschreinerei Innenausbau",
    "sg:phone":"+41 61 312 56 37",
    "sg:postcode":"4127",
    "sg:province":"Basel-Landschaft",
    "wof:name":"Adolf B\u00e4ttig M\u00f6belwerkst\u00e4tte Innenausbau",
    "wof:placetype":"venue"
},
  "geometry": {"coordinates":[7.625973,47.555035],"type":"Point"}
}