{
  "type": "Feature",
  "properties": {
    "iso:country":"CH",
    "sg:address":"Hausenstrasse",
    "sg:city":"Meiringen",
    "sg:orig_category":"Abwasserreinigung",
    "sg:phone":"+41 71 766 11 72",
    "sg:postcode":"3860",
    "sg:province":"Bern",
    "wof:name":"Abwasserreinigungsanlage",
    "wof:placetype":"venue"
},
  "geometry": {"coordinates":[9.55123,47.301189],"type":"Point"}
}