{
  "type": "Feature",
  "properties": {
    "iso:country":"CH",
    "sg:address":"Bergacher 1",
    "sg:city":"Krauchthal",
    "sg:orig_category":"Wirtschaftspr\u00fcfung, Steuerberatung U Treuhand",
    "sg:postcode":"3326",
    "sg:province":"Bern",
    "wof:name":"Procontas, U. + F. Born",
    "wof:placetype":"venue"
},
  "geometry": {"coordinates":[7.5581898689,47.0334701538],"type":"Point"}
}