{
  "type": "Feature",
  "properties": {
    "addr:full":"Werkstrasse 2 Chur Graubunden 7000",
    "addr:housenumber":"2",
    "addr:postcode":"7000",
    "addr:street":"Werkstrasse",
    "iso:country":"CH",
    "sg:address":"Werkstrasse 2",
    "sg:city":"Chur",
    "sg:orig_category":"Bauingenieurb\u00fcros Eisenbetonbau Bauingenieurb\u00fcros allgemein",
    "sg:phone":"+41 81 284 30 57",
    "sg:postcode":"7000",
    "sg:province":"Graubunden",
    "wof:name":"Thomas Deplazes Ingenieurb\u00fcro",
    "wof:placetype":"venue"
},
  "geometry": {"coordinates":[9.526788,46.85601],"type":"Point"}
}