{
  "type": "Feature",
  "properties": {
    "iso:country":"CH",
    "sg:address":"Bahnhofstrasse 20",
    "sg:city":"Baar",
    "sg:orig_category":"Herstellung von Konstruktionsteilen, Fertigbauteilen U Ausbauelementen aus Holz",
    "sg:phone":"+41 41 761 15 49",
    "sg:postcode":"6340",
    "sg:province":"Zug",
    "wof:name":"Wettach Hans, Schreinerei, Stuhl Und Tischfabrikation",
    "wof:placetype":"venue"
},
  "geometry": {"coordinates":[8.5230808258,47.1940765381],"type":"Point"}
}