{
  "type": "Feature",
  "properties": {
    "addr:full":"Gassacherstrasse 7 8488 Turbenthal. Postfach 60 Turbenthal Z\u00fcrich 8488",
    "addr:housenumber":"7;60",
    "addr:postcode":"8488 turbenthal.;8488",
    "addr:street":"Gassacherstrasse;Postfach",
    "iso:country":"CH",
    "sg:address":"Gassacherstrasse 7 8488 Turbenthal. Postfach 60",
    "sg:city":"Turbenthal",
    "sg:orig_category":"Detailhandel mit Computern U Software Softwareentwicklung U beratung",
    "sg:phone":"+41 52 385 39 45",
    "sg:postcode":"8488",
    "sg:province":"Z\u00fcrich",
    "wof:name":"Cda Informatik Und Electronic Ag",
    "wof:placetype":"venue"
},
  "geometry": {"coordinates":[8.844438,47.444256],"type":"Point"}
}