{
  "type": "Feature",
  "properties": {
    "iso:country":"CH",
    "sg:address":"3159",
    "sg:city":"Riedst\u00e4tt",
    "sg:classifiers":[
        {
            "category":"Restaurant",
            "type":"Food & Drink"
        }
    ],
    "sg:phone":"+41 31 735 51 39",
    "sg:postcode":"3159",
    "sg:province":"Bern",
    "wof:name":"Restaurant D\u00f6rfli",
    "wof:placetype":"venue"
},
  "geometry": {"coordinates":[7.3200678825,46.7836265564],"type":"Point"}
}