{
  "type": "Feature",
  "properties": {
    "iso:country":"CH",
    "sg:address":"St. Karli-strasse 65",
    "sg:city":"Luzern",
    "sg:orig_category":"Malerei",
    "sg:phone":"+41 41 240 03 66",
    "sg:postcode":"6004",
    "sg:province":"Luzern",
    "wof:name":"Bruno Bl\u00e4ttler Malergesch\u00e4ft",
    "wof:placetype":"venue"
},
  "geometry": {"coordinates":[8.2884922028,47.0568733215],"type":"Point"}
}