{
  "type": "Feature",
  "properties": {
    "iso:country":"CH",
    "sg:address":"Rue De La Poste 4 1040 Echallens Case Postale",
    "sg:city":"Echallens",
    "sg:orig_category":"Elektroinstallation",
    "sg:phone":"+41 21 883 01 16",
    "sg:postcode":"1040",
    "sg:province":"Vaud",
    "wof:name":"Eleco Electro Conseils Sa",
    "wof:placetype":"venue"
},
  "geometry": {"coordinates":[6.635286808,46.6408691406],"type":"Point"}
}