{
  "type": "Feature",
  "properties": {
    "iso:country":"CH",
    "sg:address":"Route D'illens",
    "sg:city":"Magnedens",
    "sg:orig_category":"Non-Classified Establishments",
    "sg:phone":"+41 26 411 16 56",
    "sg:postcode":"1727",
    "sg:province":"Fribourg",
    "wof:name":"Dominique Amoroso",
    "wof:placetype":"venue"
},
  "geometry": {"coordinates":[7.0942320824,46.7414321899],"type":"Point"}
}