{
  "type": "Feature",
  "properties": {
    "iso:country":"CH",
    "sg:address":"Rte De Pr\u00e9-bois 20",
    "sg:city":"Meyrin",
    "sg:orig_category":"Vermietung von Luftfahrzeugen",
    "sg:phone":"+41 91 835 02 50",
    "sg:postcode":"1217",
    "sg:province":"Gen\u00e8ve",
    "wof:name":"Corporate Aircraft Sa",
    "wof:placetype":"venue"
},
  "geometry": {"coordinates":[9.128364563,46.2376060486],"type":"Point"}
}