{
  "type": "Feature",
  "properties": {
    "iso:country":"CH",
    "sg:address":"Althardstrasse 185",
    "sg:city":"Regensdorf",
    "sg:orig_category":"Schnelldruck U Kopierservice",
    "sg:phone":"+41 18706000",
    "sg:postcode":"8105",
    "sg:province":"Z\u00fcrich",
    "wof:name":"Ro-li's Copy-factory",
    "wof:placetype":"venue"
},
  "geometry": {"coordinates":[8.4651727676,47.4419403076],"type":"Point"}
}