{
  "type": "Feature",
  "properties": {
    "iso:country":"CH",
    "sg:address":"Imbisb\u00fchlstrasse 80",
    "sg:city":"Z\u00fcrich",
    "sg:orig_category":"Primarschulen",
    "sg:phone":"+41 13416377",
    "sg:postcode":"8049",
    "sg:province":"Z\u00fcrich",
    "wof:name":"Primarschule Lachenzelg",
    "wof:placetype":"venue"
},
  "geometry": {"coordinates":[8.4891490936,47.4047241211],"type":"Point"}
}