{
  "type": "Feature",
  "properties": {
    "iso:country":"CH",
    "sg:address":"M\u00fchlegasse 18 6340 Baar. Postfach",
    "sg:city":"Baar",
    "sg:orig_category":"Herstellung von Konstruktionsteilen, Fertigbauteilen U Ausbauelementen aus Holz",
    "sg:postcode":"6340",
    "sg:province":"Zug",
    "wof:name":"Libraxit Belagstechnik Gmbh",
    "wof:placetype":"venue"
},
  "geometry": {"coordinates":[8.5264730453,47.1992111206],"type":"Point"}
}