{
  "type": "Feature",
  "properties": {
    "addr:full":"Residenza Betulle Tesserete Ticino 6950",
    "addr:postcode":"6950",
    "iso:country":"CH",
    "sg:address":"Residenza Betulle",
    "sg:city":"Tesserete",
    "sg:orig_category":"Arztpraxen",
    "sg:phone":"+41 91 943 13 02",
    "sg:postcode":"6950",
    "sg:province":"Ticino",
    "wof:name":"Dott.med.gualtiero Storni Specialista Fmh",
    "wof:placetype":"venue"
},
  "geometry": {"coordinates":[8.96653,46.068443],"type":"Point"}
}