{
  "type": "Feature",
  "properties": {
    "iso:country":"CH",
    "sg:address":"Via Cantonale",
    "sg:city":"Arogno",
    "sg:orig_category":"G\u00fcterbef\u00f6rderung im Strassenverkehr",
    "sg:phone":"+41 91 649 73 66",
    "sg:postcode":"6822",
    "sg:province":"Ticino",
    "wof:name":"Alberto Gilardoni Trasporti",
    "wof:placetype":"venue"
},
  "geometry": {"coordinates":[8.9831724167,45.9532089233],"type":"Point"}
}