{
  "type": "Feature",
  "properties": {
    "iso:country":"CH",
    "sg:address":"Steinegg 3",
    "sg:city":"Herisau",
    "sg:orig_category":"Unclassifiable Establishments",
    "sg:phone":"+41 71 351 11 93",
    "sg:postcode":"9100",
    "sg:province":"Appenzell Ausserrhoden",
    "wof:name":"Steinegg Aktiengesellschaft",
    "wof:placetype":"venue"
},
  "geometry": {"coordinates":[9.2875452042,47.3850784302],"type":"Point"}
}