{
  "type": "Feature",
  "properties": {
    "iso:country":"CH",
    "sg:address":"Grossfeldstr. 71",
    "sg:city":"Sargans",
    "sg:classifiers":[
        {
            "category":"Professional",
            "subcategory":"Engineering",
            "type":"Services"
        }
    ],
    "sg:phone":"+41 81 725 01 01",
    "sg:postcode":"7320",
    "sg:province":"St. Gallen",
    "sg:tags":[
        "machine",
        "-",
        "mechanical"
    ],
    "wof:name":"St\u00c4ubli Sargans Ag",
    "wof:placetype":"venue"
},
  "geometry": {"coordinates":[9.4339675903,47.0463027954],"type":"Point"}
}