{
  "type": "Feature",
  "properties": {
    "iso:country":"CH",
    "sg:address":"Waldhofstrasse 22",
    "sg:city":"Uzwil",
    "sg:orig_category":"Elektroinstallation",
    "sg:phone":"+41 71 913 99 11",
    "sg:postcode":"9240",
    "sg:province":"St. Gallen",
    "wof:name":"Steinlin Und Partner Ag",
    "wof:placetype":"venue"
},
  "geometry": {"coordinates":[9.1213188171,47.4423179626],"type":"Point"}
}