{
  "type": "Feature",
  "properties": {
    "addr:full":"Vicolo Della Azalee 6 Locarno Ticino 6605",
    "addr:housenumber":"6",
    "addr:postcode":"6605",
    "addr:street":"Vicolo Della Azalee;Ticino",
    "iso:country":"CH",
    "sg:address":"Vicolo Della Azalee 6",
    "sg:city":"Locarno",
    "sg:orig_category":"Architekturb\u00fcros",
    "sg:phone":"+41 91 751 59 05",
    "sg:postcode":"6605",
    "sg:province":"Ticino",
    "wof:name":"Alberto Spoerri Studio D'architettura",
    "wof:placetype":"venue"
},
  "geometry": {"coordinates":[8.785031,46.172264],"type":"Point"}
}