{
  "type": "Feature",
  "properties": {
    "iso:country":"CH",
    "sg:address":"Sch\u00fcrstrasse 46 6020 Emmenbr\u00fccke. Postfach",
    "sg:city":"Emmenbr\u00fccke",
    "sg:orig_category":"Kauf U Verkauf von Immobilien auf eigene Rechnung",
    "sg:phone":"+41 41 280 73 78",
    "sg:postcode":"6020",
    "sg:province":"Luzern",
    "wof:name":"Marti Liegenschaften Ag Luzern, Zweigniederlassung Emmen",
    "wof:placetype":"venue"
},
  "geometry": {"coordinates":[8.2700586319,47.087928772],"type":"Point"}
}