{
  "type": "Feature",
  "properties": {
    "iso:country":"CH",
    "sg:address":"Gewerbestrasse 11",
    "sg:city":"Cham",
    "sg:orig_category":"Unternehmensberatung",
    "sg:postcode":"6330",
    "sg:province":"Zug",
    "wof:name":"B\u00f6sch Consulting",
    "wof:placetype":"venue"
},
  "geometry": {"coordinates":[8.5402946472,47.3326530457],"type":"Point"}
}