{
  "type": "Feature",
  "properties": {
    "iso:country":"CH",
    "sg:address":"Avenue De Savoie 61",
    "sg:city":"Vouvry",
    "sg:orig_category":"Herstellung von Metallerzeugnissen ohne Maschinenbau Maschinenbau",
    "sg:phone":"+41 24 482 01 10",
    "sg:postcode":"1896",
    "sg:province":"Valais",
    "wof:name":"Automation Industrielle Sa",
    "wof:placetype":"venue"
},
  "geometry": {"coordinates":[6.8887720108,46.3434028625],"type":"Point"}
}