{
  "type": "Feature",
  "properties": {
    "addr:full":"Industriestrasse 15 Liestal Basel-Landschaft 4410",
    "addr:housenumber":"15",
    "addr:postcode":"4410",
    "addr:street":"Industriestrasse",
    "iso:country":"CH",
    "sg:address":"Industriestrasse 15",
    "sg:city":"Liestal",
    "sg:orig_category":"Detailhandel mit Bekleidung Grosshandel mit Textilien",
    "sg:phone":"+41 61 901 24 34",
    "sg:postcode":"4410",
    "sg:province":"Basel-Landschaft",
    "wof:name":"Tuna Textiles, Seker Haci I.",
    "wof:placetype":"venue"
},
  "geometry": {"coordinates":[7.721051,47.49353],"type":"Point"}
}