{
  "type": "Feature",
  "properties": {
    "iso:country":"CH",
    "sg:address":"Via Iragna 33",
    "sg:city":"Biasca",
    "sg:orig_category":"Sonstiger Detailhandel mit Metallwaren, Anstrichmitteln, Glaswaren, Bau U Heimwerkerbedarf",
    "sg:phone":"+41 91 862 42 41",
    "sg:postcode":"6710",
    "sg:province":"Ticino",
    "wof:name":"Do It Lugano Sa",
    "wof:placetype":"venue"
},
  "geometry": {"coordinates":[8.9642076492,46.3543357849],"type":"Point"}
}