{
  "type": "Feature",
  "properties": {
    "iso:country":"CH",
    "sg:address":"Avenue Dapples 9",
    "sg:city":"Lausanne",
    "sg:orig_category":"Unternehmensberatung",
    "sg:phone":"+41 21 601 26 88",
    "sg:postcode":"1006",
    "sg:province":"Vaud",
    "wof:name":"Anabell Lares Analog",
    "wof:placetype":"venue"
},
  "geometry": {"coordinates":[6.628267765,46.5141944885],"type":"Point"}
}