{
  "type": "Feature",
  "properties": {
    "iso:country":"CH",
    "sg:address":"Albisriederstrasse 92",
    "sg:city":"Z\u00fcrich",
    "sg:orig_category":"Architekturb\u00fcros",
    "sg:phone":"+41 14014755",
    "sg:postcode":"8003",
    "sg:province":"Z\u00fcrich",
    "wof:name":"Martin Hodel Architekturb\u00fcro",
    "wof:placetype":"venue"
},
  "geometry": {"coordinates":[8.503752,47.378086],"type":"Point"}
}