{
  "type": "Feature",
  "properties": {
    "iso:country":"CH",
    "sg:address":"Bahnh\u00f6heweg 36",
    "sg:city":"Bern",
    "sg:orig_category":"Fernmeldedienste Hardwareberatung",
    "sg:phone":"+41 31 984 10 10",
    "sg:postcode":"3018",
    "sg:province":"Bern",
    "wof:name":"Comset Ag",
    "wof:placetype":"venue"
},
  "geometry": {"coordinates":[7.3995947838,46.9403991699],"type":"Point"}
}