{
  "type": "Feature",
  "properties": {
    "iso:country":"CH",
    "sg:address":"Rue De Rive 49",
    "sg:city":"Nyon",
    "sg:classifiers":[
        {
            "category":"Travel",
            "subcategory":"Hotels & Motels",
            "type":"Entertainment"
        }
    ],
    "sg:phone":"+41 22 716 66 66",
    "sg:postcode":"1260",
    "sg:province":"Vaud",
    "sg:tags":[
        "hotels",
        "mit",
        "restaurant"
    ],
    "wof:name":"H\u00f4tel Beau-rivage",
    "wof:placetype":"venue"
},
  "geometry": {"coordinates":[6.1498999596,46.2090911865],"type":"Point"}
}