{
  "type": "Feature",
  "properties": {
    "iso:country":"CH",
    "sg:address":"Eichwaldstrasse 7",
    "sg:city":"Luzern",
    "sg:orig_category":"Softwareentwicklung U beratung",
    "sg:phone":"+41 41 631 07 20",
    "sg:postcode":"6005",
    "sg:province":"Luzern",
    "wof:name":"Expertix Control Ag",
    "wof:placetype":"venue"
},
  "geometry": {"coordinates":[8.3145446777,46.9892692566],"type":"Point"}
}