{
  "type": "Feature",
  "properties": {
    "iso:country":"CH",
    "sg:address":"Tecknauerstrasse 29",
    "sg:city":"Gelterkinden",
    "sg:orig_category":"Detailhandel mit Getr\u00e4nken Grosshandel mit Getr\u00e4nken",
    "sg:phone":"+41 71 278 09 10",
    "sg:postcode":"4460",
    "sg:province":"Basel-Landschaft",
    "wof:name":"Vinothek Roge Partner Gmbh",
    "wof:placetype":"venue"
},
  "geometry": {"coordinates":[9.3340015411,47.4070472717],"type":"Point"}
}