{
  "type": "Feature",
  "properties": {
    "iso:country":"CH",
    "sg:address":"Pestalozzistrasse 22 4051 Basel. Postfach",
    "sg:city":"Basel",
    "sg:orig_category":"Laboratorien chemisch Universit\u00e4tsspit\u00e4ler, Spit\u00e4ler f\u00fcr allgemeine Pflege",
    "sg:phone":"+41 61 267 31 11",
    "sg:postcode":"4004",
    "sg:province":"Basel-Stadt",
    "wof:name":"Institut F\u00fcr Rechtsmedizin",
    "wof:placetype":"venue"
},
  "geometry": {"coordinates":[7.5794692039,47.5644035339],"type":"Point"}
}