{
  "type": "Feature",
  "properties": {
    "iso:country":"CH",
    "sg:address":"W\u00e4ngistrasse 5",
    "sg:city":"Wittenwil",
    "sg:classifiers":[
        {
            "category":"Restaurant",
            "type":"Food & Drink"
        }
    ],
    "sg:phone":"+41 52 365 36 60",
    "sg:postcode":"9547",
    "sg:province":"Thurgau",
    "wof:name":"Restaurant R\u00f6ssli",
    "wof:placetype":"venue"
},
  "geometry": {"coordinates":[8.922668457,47.5034599304],"type":"Point"}
}