{
  "type": "Feature",
  "properties": {
    "iso:country":"CH",
    "sg:address":"Im Uerschli 36",
    "sg:city":"Bauma",
    "sg:orig_category":"Grosshandel mit Getr\u00e4nken",
    "sg:phone":"+41 52 386 29 64",
    "sg:postcode":"8494",
    "sg:province":"Z\u00fcrich",
    "wof:name":"Civetta - Weine Von Gunten",
    "wof:placetype":"venue"
},
  "geometry": {"coordinates":[8.8657236099,47.3726577759],"type":"Point"}
}