{
  "type": "Feature",
  "properties": {
    "iso:country":"CH",
    "sg:address":"Poststrasse 6 9443 Widnau. Postfach 264",
    "sg:city":"Widnau",
    "sg:orig_category":"Herstellung von keramischen Wand U Bodenfliesen U platten",
    "sg:phone":"+41 71 722 64 66",
    "sg:postcode":"9443",
    "sg:province":"St. Gallen",
    "wof:name":"Adrian Fiechter",
    "wof:placetype":"venue"
},
  "geometry": {"coordinates":[9.6352186203,47.4032211304],"type":"Point"}
}