{
  "type": "Feature",
  "properties": {
    "iso:country":"CH",
    "sg:address":"Langenthalstrasse 58",
    "sg:city":"Aarwangen",
    "sg:orig_category":"Herstellung von Kunststoffwaren",
    "sg:phone":"+41 56 619 94 94",
    "sg:postcode":"4912",
    "sg:province":"Bern",
    "wof:name":"Howag Kunststoffe Ag",
    "wof:placetype":"venue"
},
  "geometry": {"coordinates":[8.270907402,47.3580284119],"type":"Point"}
}