{
  "type": "Feature",
  "properties": {
    "addr:full":"G\u00e4ssli 4 Bolligen Bern 3065",
    "addr:housenumber":"4",
    "addr:postcode":"3065",
    "addr:street":"Gaessli",
    "iso:country":"CH",
    "sg:address":"G\u00e4ssli 4",
    "sg:city":"Bolligen",
    "sg:orig_category":"Bauschreinerei Herstellung von M\u00f6beln verschiedener Art",
    "sg:phone":"+41 31 921 34 19",
    "sg:postcode":"3065",
    "sg:province":"Bern",
    "wof:name":"Hanspeter Jaiser Bau-& M\u00f6belschreinerei",
    "wof:placetype":"venue"
},
  "geometry": {"coordinates":[7.497906,46.984276],"type":"Point"}
}