{
  "type": "Feature",
  "properties": {
    "iso:country":"CH",
    "sg:address":"Avenue Sainte-luce 16 1000 Lausanne. Postfach",
    "sg:city":"Lausanne",
    "sg:orig_category":"Herstellung von medizinischen U chirurgischen Ger\u00e4ten sowie orthop\u00e4dischen Vorrichtungen",
    "sg:postcode":"1003",
    "sg:province":"Vaud",
    "wof:name":"Mador Petre",
    "wof:placetype":"venue"
},
  "geometry": {"coordinates":[6.6334791183,46.5175170898],"type":"Point"}
}