{
  "type": "Feature",
  "properties": {
    "iso:country":"CH",
    "sg:address":"Jonenstrasse 32",
    "sg:city":"Ottenbach",
    "sg:orig_category":"Instandhaltung U Reparatur von Automobilen Tankstellen",
    "sg:phone":"+41 71 744 14 82",
    "sg:postcode":"8913",
    "sg:province":"Z\u00fcrich",
    "wof:name":"Amacker Jakob Platz-garage Ag",
    "wof:placetype":"venue"
},
  "geometry": {"coordinates":[9.6312742233,47.4531478882],"type":"Point"}
}