{
  "type": "Feature",
  "properties": {
    "iso:country":"CH",
    "sg:address":"R\u00e4uchlisberg 44",
    "sg:city":"Amriswil",
    "sg:orig_category":"Haltung von Schweinen",
    "sg:phone":"+41 71 411 12 10",
    "sg:postcode":"8580",
    "sg:province":"Thurgau",
    "wof:name":"Emu Schweinezucht Ag",
    "wof:placetype":"venue"
},
  "geometry": {"coordinates":[9.2866363525,47.5356063843],"type":"Point"}
}