{
  "type": "Feature",
  "properties": {
    "iso:country":"CH",
    "sg:address":"Vogelsangstrasse 6 8307 Effretikon. Postfach",
    "sg:city":"Effretikon",
    "sg:orig_category":"Bau von Strassen, Sportanlagen U Bahnverkehrsstrecken",
    "sg:phone":"+41 52 354 70 70",
    "sg:postcode":"8307",
    "sg:province":"Z\u00fcrich",
    "wof:name":"M\u00fcller J. Ag, Maschineller Geleiseunterhalt",
    "wof:placetype":"venue"
},
  "geometry": {"coordinates":[8.683808,47.421494],"type":"Point"}
}