{
  "type": "Feature",
  "properties": {
    "iso:country":"CH",
    "sg:address":"Bahnhof Sbb",
    "sg:city":"Steinen",
    "sg:orig_category":"Interessenvertretungen",
    "sg:phone":"+41 41 832 18 46",
    "sg:postcode":"6422",
    "sg:province":"Schwyz",
    "wof:name":"Stiftung Signalhalle Steinen",
    "wof:placetype":"venue"
},
  "geometry": {"coordinates":[8.6067008972,47.0484008789],"type":"Point"}
}