{
  "type": "Feature",
  "properties": {
    "addr:full":"F\u00f6rlibuckweg 3 8302 Kloten. Postfach Kloten Z\u00fcrich 8302",
    "addr:housenumber":"3",
    "addr:postcode":"8302 kloten. postfach;8302",
    "addr:street":"Foerlibuckweg",
    "iso:country":"CH",
    "sg:address":"F\u00f6rlibuckweg 3 8302 Kloten. Postfach",
    "sg:city":"Kloten",
    "sg:orig_category":"Architektur U Ingenieurb\u00fcros",
    "sg:postcode":"8302",
    "sg:province":"Z\u00fcrich",
    "wof:name":"Kmd-design Droz Architektur U. Internetdesign",
    "wof:placetype":"venue"
},
  "geometry": {"coordinates":[8.584645,47.446457],"type":"Point"}
}