{
  "type": "Feature",
  "properties": {
    "iso:country":"CH",
    "sg:address":"Ipsachstrasse 11",
    "sg:city":"Ipsach",
    "sg:orig_category":"Unclassifiable Establishments",
    "sg:postcode":"2563",
    "sg:province":"Bern",
    "wof:name":"Restaurant Schl\u00f6ssli Ipsach Gbmh",
    "wof:placetype":"venue"
},
  "geometry": {"coordinates":[7.236784935,47.117149353],"type":"Point"}
}