{
  "type": "Feature",
  "properties": {
    "iso:country":"CH",
    "sg:address":"Gubelstrasse 41",
    "sg:city":"Z\u00fcrich",
    "sg:orig_category":"Sportvereine Turnen Vereine Damen",
    "sg:phone":"+41 13114860",
    "sg:postcode":"8050",
    "sg:province":"Z\u00fcrich",
    "wof:name":"Damenturnverein Oerlikon",
    "wof:placetype":"venue"
},
  "geometry": {"coordinates":[8.5429677963,47.4086151123],"type":"Point"}
}