{
  "type": "Feature",
  "properties": {
    "iso:country":"CH",
    "sg:address":"Hauptstrasse 42 Postfach 145",
    "sg:city":"Hochdorf",
    "sg:classifiers":[
        {
            "category":"Professional",
            "subcategory":"Advertising",
            "type":"Services"
        }
    ],
    "sg:phone":"+41 41 914 09 14",
    "sg:postcode":"6281",
    "sg:province":"Luzern",
    "sg:tags":[
        "communication",
        "medium"
    ],
    "wof:name":"Seetal Medien Ag",
    "wof:placetype":"venue"
},
  "geometry": {"coordinates":[-96.687996,30.149364],"type":"Point"}
}