{
  "type": "Feature",
  "properties": {
    "iso:country":"CH",
    "sg:address":"6930",
    "sg:city":"Bedano",
    "sg:orig_category":"Detailhandel mit Brot, Back U S\u00fcsswaren",
    "sg:phone":"+41 32 631 18 38",
    "sg:postcode":"6930",
    "sg:province":"Ticino",
    "wof:name":"Alex Anderegg B\u00e4ckerei-konditorei",
    "wof:placetype":"venue"
},
  "geometry": {"coordinates":[7.655811,47.234077],"type":"Point"}
}