{
  "type": "Feature",
  "properties": {
    "iso:country":"CH",
    "sg:address":"\u00dcberlandstrasse 391/38 8000 Z\u00fcrich. Postfach",
    "sg:city":"Z\u00fcrich",
    "sg:orig_category":"Sonstige Kurierdienste",
    "sg:postcode":"8051",
    "sg:province":"Z\u00fcrich",
    "wof:name":"Swiss Xpress Kurierdienst Ghiasi Ali",
    "wof:placetype":"venue"
},
  "geometry": {"coordinates":[8.5861768723,47.4076690674],"type":"Point"}
}