{
  "type": "Feature",
  "properties": {
    "iso:country":"CH",
    "sg:address":"Lindenplatz 3",
    "sg:city":"Elgg",
    "sg:classifiers":[
        {
            "category":"Banks & Credit Unions",
            "subcategory":"Bank",
            "type":"Services"
        }
    ],
    "sg:phone":"+41 4152352250",
    "sg:postcode":"8353",
    "sg:province":"Z\u00fcrich",
    "wof:name":"Z\u00fcrcher, Kantonalbank",
    "wof:placetype":"venue"
},
  "geometry": {"coordinates":[8.773896,47.458031],"type":"Point"}
}