{
  "type": "Feature",
  "properties": {
    "iso:country":"CH",
    "sg:address":"Parkstr. 1",
    "sg:city":"Frenkendorf",
    "sg:classifiers":[
        {
            "category":"Government",
            "subcategory":"Department Of Motor Vehicles",
            "type":"Public Place"
        }
    ],
    "sg:phone":"+41 61 901 17 26",
    "sg:postcode":"4402",
    "sg:province":"Basel-Landschaft",
    "sg:tags":[
        "equipment",
        "industrial",
        "transport",
        "motor-cars"
    ],
    "wof:name":"Gr\u00d6flin Ag",
    "wof:placetype":"venue"
},
  "geometry": {"coordinates":[7.7206311226,47.5007019043],"type":"Point"}
}