{
  "type": "Feature",
  "properties": {
    "iso:country":"CH",
    "sg:address":"Pfauengasse 3 6370 Stans. Postfach",
    "sg:city":"Freiburg",
    "sg:orig_category":"Wirtschaftspr\u00fcfung, Steuerberatung U Treuhand",
    "sg:postcode":"1700",
    "sg:province":"Fribourg",
    "wof:name":"Tech S.a.",
    "wof:placetype":"venue"
},
  "geometry": {"coordinates":[8.3682689667,46.9565620422],"type":"Point"}
}