{
  "type": "Feature",
  "properties": {
    "iso:country":"CH",
    "sg:address":"Hubstrasse 6",
    "sg:city":"Romanshorn",
    "sg:orig_category":"Vereine Radio, Film and Foto",
    "sg:phone":"+41 71 622 87 59",
    "sg:postcode":"8590",
    "sg:province":"Thurgau",
    "wof:name":"Eisenbahner-foto-amateure",
    "wof:placetype":"venue"
},
  "geometry": {"coordinates":[9.3673200607,47.5658416748],"type":"Point"}
}