{
  "type": "Feature",
  "properties": {
    "iso:country":"CH",
    "sg:address":"Marktplatz 4",
    "sg:city":"St.gallen",
    "sg:orig_category":"Fachdetailhandel in Verkaufsr\u00e4umen Grosshandel mit Spielwaren",
    "sg:phone":"+41 61 401 53 50",
    "sg:postcode":"9000",
    "sg:province":"St. Gallen",
    "wof:name":"Active People",
    "wof:placetype":"venue"
},
  "geometry": {"coordinates":[7.5606012344,47.5174026489],"type":"Point"}
}