{
  "type": "Feature",
  "properties": {
    "iso:country":"CH",
    "sg:address":"Grellingerstrasse 75",
    "sg:city":"Basel",
    "sg:classifiers":[
        {
            "category":"Banks & Credit Unions",
            "subcategory":"Financial Services",
            "type":"Services"
        }
    ],
    "sg:phone":"+41 61 317 37 37",
    "sg:postcode":"4020",
    "sg:province":"Basel-Stadt",
    "sg:tags":[
        "banking",
        "finance",
        "insurance"
    ],
    "wof:name":"Compagnie Descomptes Financiers Cef Sa",
    "wof:placetype":"venue"
},
  "geometry": {"coordinates":[7.605408,47.548584],"type":"Point"}
}