{
  "type": "Feature",
  "properties": {
    "iso:country":"CH",
    "sg:address":"2108",
    "sg:city":"Couvet",
    "sg:orig_category":"Erschliessung von Grundst\u00fccken",
    "sg:postcode":"2108",
    "sg:province":"Neuch\u00e2tel",
    "wof:name":"Soci\u00e9t\u00e9 Coop\u00e9rative Immobili\u00e8re Les Oeuches",
    "wof:placetype":"venue"
},
  "geometry": {"coordinates":[-112.009475708,43.5343589783],"type":"Point"}
}