{
  "type": "Feature",
  "properties": {
    "iso:country":"CH",
    "sg:address":"Moosguetstrasse 7a",
    "sg:city":"Ruswil",
    "sg:orig_category":"Unclassifiable Establishments",
    "sg:postcode":"6017",
    "sg:province":"Luzern",
    "wof:name":"Walter Schaller Carrosserie - Spritzwerk - Fahrzeugbau",
    "wof:placetype":"venue"
},
  "geometry": {"coordinates":[8.1093912125,47.0871582031],"type":"Point"}
}