{
  "type": "Feature",
  "properties": {
    "iso:country":"CH",
    "sg:address":"Avenue De La Sallaz 51 1010 Lausanne Case Postale 140",
    "sg:city":"Lausanne",
    "sg:orig_category":"Reiseb\u00fcros U Reiseveranstalter",
    "sg:phone":"+41 21 653 51 71",
    "sg:postcode":"1010",
    "sg:province":"Vaud",
    "wof:name":"Voyages Sol (la Sallaz) S\u00e0rl",
    "wof:placetype":"venue"
},
  "geometry": {"coordinates":[6.6467728615,46.5330085754],"type":"Point"}
}