{
  "type": "Feature",
  "properties": {
    "addr:full":"Chamerstrasse 30 6300 Zug. Postfach Zug Zug 6300",
    "addr:housenumber":"30",
    "addr:postcode":"6300;postfach;6300",
    "addr:street":"Chamerstrasse;Zug",
    "iso:country":"CH",
    "sg:address":"Chamerstrasse 30 6300 Zug. Postfach",
    "sg:city":"Zug",
    "sg:orig_category":"Aktivit\u00e4ten der Generalunternehmen im Baugewerbe Allgemeiner Hoch U Tiefbau",
    "sg:phone":"+41 41 711 14 24",
    "sg:postcode":"6300",
    "sg:province":"Zug",
    "wof:name":"See-immobilien Gmbh Generalunternehmung. Immobilien Usw",
    "wof:placetype":"venue"
},
  "geometry": {"coordinates":[8.508935,47.17284],"type":"Point"}
}