{
  "type": "Feature",
  "properties": {
    "addr:full":"Curtibergstrasse 14 8646 Wagen. Postfach Wagen St. Gallen 8646",
    "addr:housenumber":"14",
    "addr:postcode":"8646 wagen. postfach;8646",
    "addr:street":"Curtibergstrasse;Wagen",
    "iso:country":"CH",
    "sg:address":"Curtibergstrasse 14 8646 Wagen. Postfach",
    "sg:city":"Wagen",
    "sg:orig_category":"Allgemeiner Hoch U Tiefbau",
    "sg:phone":"+41 55 212 43 14",
    "sg:postcode":"8646",
    "sg:province":"St. Gallen",
    "wof:name":"Demmel Bauleitungen + Beratungen",
    "wof:placetype":"venue"
},
  "geometry": {"coordinates":[8.886289,47.232353],"type":"Point"}
}