{
  "type": "Feature",
  "properties": {
    "iso:country":"CH",
    "sg:address":"Bergstrasse 17a",
    "sg:city":"Kreuzlingen",
    "sg:orig_category":"Kauf U Verkauf von Immobilien auf eigene Rechnung",
    "sg:phone":"+41 71 672 84 61",
    "sg:postcode":"8280",
    "sg:province":"Thurgau",
    "wof:name":"Cesa, Clean Energy Sa",
    "wof:placetype":"venue"
},
  "geometry": {"coordinates":[9.1704835892,47.6426391602],"type":"Point"}
}