{
  "type": "Feature",
  "properties": {
    "iso:country":"CH",
    "sg:address":"Spissenstrasse 2",
    "sg:city":"Meggen",
    "sg:orig_category":"Herstellung von sonstigen landwirtschaftlichen Maschinen",
    "sg:phone":"+41 41 377 16 93",
    "sg:postcode":"6045",
    "sg:province":"Luzern",
    "wof:name":"Alois Schmidli Landw.maschinen",
    "wof:placetype":"venue"
},
  "geometry": {"coordinates":[8.3727607727,47.0497665405],"type":"Point"}
}