{
  "type": "Feature",
  "properties": {
    "addr:full":"8058 Z\u00fcrich. Postfach 1358 Z\u00fcrich Z\u00fcrich 8058",
    "addr:housenumber":"8058",
    "addr:postcode":"1358;8058",
    "addr:street":"Zuerich. Postfach",
    "iso:country":"CH",
    "sg:address":"8058 Z\u00fcrich. Postfach 1358",
    "sg:city":"Z\u00fcrich",
    "sg:orig_category":"Betrieb von Taxis",
    "sg:phone":"+41 18031919",
    "sg:postcode":"8058",
    "sg:province":"Z\u00fcrich",
    "wof:name":"Allround Business Limousine Service Gmbh",
    "wof:placetype":"venue"
},
  "geometry": {"coordinates":[8.53801,47.369091],"type":"Point"}
}