{
  "type": "Feature",
  "properties": {
    "iso:country":"CH",
    "sg:address":"S\u00e4gestrasse 27 3097 Liebefeld. Postfach",
    "sg:city":"Liebefeld",
    "sg:classifiers":[
        {
            "category":"Professional",
            "subcategory":"Employment Agencies",
            "type":"Services"
        }
    ],
    "sg:phone":"+41 31 971 94 35",
    "sg:postcode":"3097",
    "sg:province":"Bern",
    "sg:tags":[
        "personal",
        "u",
        "stellenvermittlung"
    ],
    "wof:name":"Henzi Mina",
    "wof:placetype":"venue"
},
  "geometry": {"coordinates":[7.4215040207,46.9318389893],"type":"Point"}
}