{
  "type": "Feature",
  "properties": {
    "iso:country":"CH",
    "sg:address":"Kermely Chemin 3 1206 Gen\u00e8ve. Postfach",
    "sg:city":"Gen\u00e8ve",
    "sg:orig_category":"Non-Classified Establishments",
    "sg:postcode":"1201",
    "sg:province":"Gen\u00e8ve",
    "wof:name":"F.c.o. Participations Sa",
    "wof:placetype":"venue"
},
  "geometry": {"coordinates":[6.1554851532,46.1896743774],"type":"Point"}
}