{
  "type": "Feature",
  "properties": {
    "iso:country":"CH",
    "sg:address":"Dorfstrasse 12",
    "sg:city":"Bauma",
    "sg:orig_category":"Detailhandel mit Brot, Back U S\u00fcsswaren Detailhandel mit Waren verschiedener Art, Hauptrichtung Nahr",
    "sg:phone":"+41 52 386 10 95",
    "sg:postcode":"8494",
    "sg:province":"Z\u00fcrich",
    "wof:name":"Hartmann David",
    "wof:placetype":"venue"
},
  "geometry": {"coordinates":[8.876386,47.367622],"type":"Point"}
}