{
  "type": "Feature",
  "properties": {
    "iso:country":"CH",
    "sg:address":"Baslerstrasse 50 8048 Z\u00fcrich. Postfach",
    "sg:city":"Z\u00fcrich",
    "sg:orig_category":"Fachdetailhandel mit pharmazeutischen Produkten",
    "sg:phone":"+41 395925",
    "sg:postcode":"8066",
    "sg:province":"Z\u00fcrich",
    "wof:name":"Landolt Dr. H.p., Apotheke Letzi-park",
    "wof:placetype":"venue"
},
  "geometry": {"coordinates":[8.4980716705,47.3861312866],"type":"Point"}
}