{
  "type": "Feature",
  "properties": {
    "iso:country":"CH",
    "sg:address":"Gewerbestrasse 1 8606 N\u00e4nikon. Postfach",
    "sg:city":"N\u00e4nikon",
    "sg:orig_category":"Softwareentwicklung U beratung",
    "sg:postcode":"8606",
    "sg:province":"Z\u00fcrich",
    "wof:name":"Innovativ Soft Ag",
    "wof:placetype":"venue"
},
  "geometry": {"coordinates":[8.677529335,47.365234375],"type":"Point"}
}