{
  "type": "Feature",
  "properties": {
    "iso:country":"CH",
    "sg:address":"Hauptstrasse 9",
    "sg:city":"Nenzlingen",
    "sg:orig_category":"Fernmeldedienste",
    "sg:postcode":"4224",
    "sg:province":"Basel-Landschaft",
    "wof:name":"Fernsehgenossenschaft Uf Egg Nenzlingen",
    "wof:placetype":"venue"
},
  "geometry": {"coordinates":[7.5615959167,47.447227478],"type":"Point"}
}