{
  "type": "Feature",
  "properties": {
    "iso:country":"CH",
    "sg:address":"General-guisanstrasse 16-18",
    "sg:city":"Interlaken",
    "sg:orig_category":"Detailhandel mit elektrischen Haushaltsger\u00e4ten Elektroinstallation",
    "sg:phone":"+41 33 828 10 10",
    "sg:postcode":"3800",
    "sg:province":"Bern",
    "wof:name":"Elektro Wyler Ag",
    "wof:placetype":"venue"
},
  "geometry": {"coordinates":[7.8552308083,46.6825828552],"type":"Point"}
}