{
  "type": "Feature",
  "properties": {
    "iso:country":"CH",
    "sg:address":"Puiserande Rue De La 9 1205 Gen\u00e8ve. Postfach",
    "sg:city":"Gen\u00e8ve",
    "sg:orig_category":"Druck ohne Zeitungsdruck",
    "sg:phone":"+41 22 329 81 14",
    "sg:postcode":"1205",
    "sg:province":"Gen\u00e8ve",
    "wof:name":"Imprimerie-service, G. Ackermann",
    "wof:placetype":"venue"
},
  "geometry": {"coordinates":[6.1314578056,46.2016792297],"type":"Point"}
}