{
  "type": "Feature",
  "properties": {
    "iso:country":"CH",
    "sg:address":"Hohliberg Im Giebel",
    "sg:city":"Gachnang",
    "sg:orig_category":"Herstellung von keramischen Wand U Bodenfliesen U platten",
    "sg:phone":"+41 56 633 30 74",
    "sg:postcode":"8547",
    "sg:province":"Thurgau",
    "wof:name":"Keram. Wand Und Bodenbel\u00e4ge Edgar Stadelmann",
    "wof:placetype":"venue"
},
  "geometry": {"coordinates":[8.3501434326,47.3486709595],"type":"Point"}
}