{
  "type": "Feature",
  "properties": {
    "iso:country":"CH",
    "sg:address":"Wilbrunnenstrasse 7 6314 Unter\u00e4geri. Postfach 44",
    "sg:city":"Unter\u00e4geri",
    "sg:orig_category":"G\u00fcterbef\u00f6rderung im Strassenverkehr Herstellung von sonstigen chemischen Erzeugnissen",
    "sg:phone":"+41 56 496 45 45",
    "sg:postcode":"6314",
    "sg:province":"Zug",
    "wof:name":"Prelit Ag Produkte F. D. Oberfl\u00e4chenbehandlung, Abwasseraufbereitungsanlagen; Verkauf",
    "wof:placetype":"venue"
},
  "geometry": {"coordinates":[8.3137807846,47.4074058533],"type":"Point"}
}