{
  "type": "Feature",
  "properties": {
    "iso:country":"CH",
    "sg:address":"Weltpoststrasse 4",
    "sg:city":"Bern",
    "sg:classifiers":[
        {
            "category":"Professional",
            "subcategory":"Advertising",
            "type":"Services"
        }
    ],
    "sg:phone":"+41 31 356 73 00",
    "sg:postcode":"3015",
    "sg:province":"Bern",
    "sg:tags":[
        "agency"
    ],
    "wof:name":"Burson-marsteller Ag",
    "wof:placetype":"venue"
},
  "geometry": {"coordinates":[7.473208,46.939064],"type":"Point"}
}