{
  "type": "Feature",
  "properties": {
    "iso:country":"CH",
    "sg:address":"Stapfackerstrasse 994c",
    "sg:city":"Goldswil",
    "sg:orig_category":"Bauspenglerei Sanit\u00e4rinstallation U Spenglerei",
    "sg:phone":"+41 33 823 13 30",
    "sg:postcode":"3805",
    "sg:province":"Bern",
    "wof:name":"H. Oberli Ag Spenglerei",
    "wof:placetype":"venue"
},
  "geometry": {"coordinates":[7.880584,46.698723],"type":"Point"}
}