{
  "type": "Feature",
  "properties": {
    "iso:country":"CH",
    "sg:address":"Gutenbergstrasse 19 3000 Bern. Postfach",
    "sg:city":"Bern",
    "sg:orig_category":"Unternehmensberatung",
    "sg:postcode":"3005",
    "sg:province":"Bern",
    "wof:name":"Inbetween Organisationsentwicklungs Gmbh",
    "wof:placetype":"venue"
},
  "geometry": {"coordinates":[7.4353551865,46.9444618225],"type":"Point"}
}