{
  "type": "Feature",
  "properties": {
    "iso:country":"CH",
    "sg:address":"Place Du Village 8",
    "sg:city":"Boussens",
    "sg:orig_category":"Technische, physikalische U chemische Untersuchung",
    "sg:phone":"+41 21 882 53 53",
    "sg:postcode":"1034",
    "sg:province":"Vaud",
    "wof:name":"Acepsa Analyses, Conseils Et Production Sa",
    "wof:placetype":"venue"
},
  "geometry": {"coordinates":[6.5826702118,46.603553772],"type":"Point"}
}