{
  "type": "Feature",
  "properties": {
    "iso:country":"CH",
    "sg:address":"Dornacherstrasse 82",
    "sg:city":"Basel",
    "sg:orig_category":"Erbringung von Dienstleistungen f\u00fcr Unternehmen Werbegrafikateliers",
    "sg:phone":"+41 61 362 05 50",
    "sg:postcode":"4052",
    "sg:province":"Basel-Stadt",
    "wof:name":"Regio Grafik Spengler",
    "wof:placetype":"venue"
},
  "geometry": {"coordinates":[7.5873398781,47.5439567566],"type":"Point"}
}