{
  "type": "Feature",
  "properties": {
    "iso:country":"CH",
    "sg:address":"Rue Des Echelettes 9",
    "sg:city":"Lausanne",
    "sg:orig_category":"Sportvereine Unihockey",
    "sg:phone":"+41 21 624 37 64",
    "sg:postcode":"1004",
    "sg:province":"Vaud",
    "wof:name":"Uhc Hornets Yens",
    "wof:placetype":"venue"
},
  "geometry": {"coordinates":[6.6245188713,46.5250816345],"type":"Point"}
}