{
  "type": "Feature",
  "properties": {
    "iso:country":"CH",
    "sg:address":"Kasernenstrasse 4",
    "sg:city":"Bachenb\u00fclach",
    "sg:orig_category":"Instandhaltung U Reparatur von Automobilen",
    "sg:phone":"+41 18861599",
    "sg:postcode":"8184",
    "sg:province":"Z\u00fcrich",
    "wof:name":"L & M Moto-racing, M\u00fchlethaler & Lutz",
    "wof:placetype":"venue"
},
  "geometry": {"coordinates":[8.5359649658,47.5032196045],"type":"Point"}
}