{
  "type": "Feature",
  "properties": {
    "iso:country":"CH",
    "sg:address":"B\u00fcndtenweg 1a",
    "sg:city":"Selzach",
    "sg:orig_category":"Fussreflexzonenmassage P\u00e9dicure",
    "sg:phone":"+41 71 220 32 10",
    "sg:postcode":"2545",
    "sg:province":"Solothurn",
    "wof:name":"Tina R\u00fcegsegger Fusspflege",
    "wof:placetype":"venue"
},
  "geometry": {"coordinates":[9.37449646,47.4219779968],"type":"Point"}
}