{
  "type": "Feature",
  "properties": {
    "iso:country":"CH",
    "sg:address":"Riedl\u00f6serstrasse 7302 Landquart. Postfach",
    "sg:city":"Landquart",
    "sg:orig_category":"Herstellung von Werkzeugen",
    "sg:phone":"+41 81 300 66 00",
    "sg:postcode":"7302",
    "sg:province":"Graubunden",
    "wof:name":"Gfeller Arnold Ag",
    "wof:placetype":"venue"
},
  "geometry": {"coordinates":[9.5626602173,46.9677810669],"type":"Point"}
}