{
  "type": "Feature",
  "properties": {
    "iso:country":"CH",
    "sg:address":"Rue De Lausanne 91 1700 Fribourg Case Postale 525",
    "sg:city":"Fribourg",
    "sg:orig_category":"Advokaturb\u00fcros",
    "sg:phone":"+41 26 672 92 72",
    "sg:postcode":"1701",
    "sg:province":"Fribourg",
    "wof:name":"Pascal Friolet Advokaturb\u00fcro",
    "wof:placetype":"venue"
},
  "geometry": {"coordinates":[7.108453,46.925232],"type":"Point"}
}