{
  "type": "Feature",
  "properties": {
    "iso:country":"CH",
    "sg:address":"In Der Breite 15",
    "sg:city":"Steinmaur",
    "sg:orig_category":"Vereine Frauen Vereine Gemeinn\u00fctzige",
    "sg:phone":"+41 55 240 22 25",
    "sg:postcode":"8162",
    "sg:province":"Z\u00fcrich",
    "wof:name":"Frauenverein Tann-r\u00fcti",
    "wof:placetype":"venue"
},
  "geometry": {"coordinates":[8.8467683792,47.2521324158],"type":"Point"}
}