{
  "type": "Feature",
  "properties": {
    "iso:country":"CH",
    "sg:address":"Route De Bertigny 17",
    "sg:city":"Fribourg",
    "sg:orig_category":"Maler U Glasergewerbe",
    "sg:phone":"+41 32 731 77 02",
    "sg:postcode":"1700",
    "sg:province":"Fribourg",
    "wof:name":"Gaisch Peinture",
    "wof:placetype":"venue"
},
  "geometry": {"coordinates":[6.8612399101,46.98828125],"type":"Point"}
}