{
  "type": "Feature",
  "properties": {
    "iso:country":"CH",
    "sg:address":"Ruelle Du Bas 9",
    "sg:city":"Biel/bienne",
    "sg:orig_category":"RESTAURANTS: TEA-ROOMS",
    "sg:postcode":"2500",
    "sg:province":"Bern",
    "wof:name":"Caprara Marco",
    "wof:placetype":"venue"
},
  "geometry": {"coordinates":[7.2461810112,47.1413497925],"type":"Point"}
}