{
  "type": "Feature",
  "properties": {
    "iso:country":"CH",
    "sg:address":"Rue De La Servette 13",
    "sg:city":"Gen\u00e8ve",
    "sg:orig_category":"Herstellung von elektronischen Bauelementen Softwareentwicklung U beratung",
    "sg:phone":"+41 22 734 29 30",
    "sg:postcode":"1201",
    "sg:province":"Gen\u00e8ve",
    "wof:name":"Loisirs \u00e9lectroniques Servette Lesa Sa",
    "wof:placetype":"venue"
},
  "geometry": {"coordinates":[6.1384801865,46.2095375061],"type":"Point"}
}