{
  "type": "Feature",
  "properties": {
    "iso:country":"CH",
    "sg:address":"Haus Viktoria",
    "sg:city":"Zermatt",
    "sg:orig_category":"Saunas, Solarien, Fitnesszentren U \u00e4hnliches",
    "sg:phone":"+41 56 493 37 63",
    "sg:postcode":"3920",
    "sg:province":"Valais",
    "wof:name":"Fitness-training Baregg Ag",
    "wof:placetype":"venue"
},
  "geometry": {"coordinates":[8.2843389511,47.4559783936],"type":"Point"}
}