{
  "type": "Feature",
  "properties": {
    "iso:country":"CH",
    "sg:address":"Bettenhausenstrasse 40",
    "sg:city":"Herzogenbuchsee",
    "sg:orig_category":"Unclassifiable Establishments",
    "sg:postcode":"3360",
    "sg:province":"Bern",
    "wof:name":"Voicedata Gmbh",
    "wof:placetype":"venue"
},
  "geometry": {"coordinates":[7.7066650391,47.1838493347],"type":"Point"}
}