{
  "type": "Feature",
  "properties": {
    "iso:country":"CH",
    "sg:address":"Grand-champ",
    "sg:city":"Syens",
    "sg:orig_category":"Abbruch U Sprenggewerbe, Erdbewegungsarbeiten Erdbewegungsarbeiten",
    "sg:phone":"+41 21 905 14 85",
    "sg:postcode":"1510",
    "sg:province":"Vaud",
    "wof:name":"L\u00e9onardo Costantini Sa Terrassements & Ma\u00e7onnerie",
    "wof:placetype":"venue"
},
  "geometry": {"coordinates":[6.773851,46.637135],"type":"Point"}
}