{
  "type": "Feature",
  "properties": {
    "iso:country":"CH",
    "sg:address":"Lehn",
    "sg:city":"Entlebuch",
    "sg:orig_category":"Instandhaltung U Reparatur von Automobilen",
    "sg:phone":"+41 55 246 41 93",
    "sg:postcode":"6162",
    "sg:province":"Luzern",
    "wof:name":"Lustenberger Ren\u00e9 Dorf-garage",
    "wof:placetype":"venue"
},
  "geometry": {"coordinates":[8.9413003922,47.2884101868],"type":"Point"}
}