{
  "type": "Feature",
  "properties": {
    "iso:country":"CH",
    "sg:address":"S\u00fcdstrasse 1",
    "sg:city":"M\u00fcnsingen",
    "sg:orig_category":"Detailhandel mit M\u00f6beln Herstellung von B\u00fcro U Ladenm\u00f6beln",
    "sg:phone":"+41 31 724 13 13",
    "sg:postcode":"3110",
    "sg:province":"Bern",
    "wof:name":"Umdasch Shop-concept Ag",
    "wof:placetype":"venue"
},
  "geometry": {"coordinates":[7.5633740425,46.868724823],"type":"Point"}
}