{
  "type": "Feature",
  "properties": {
    "iso:country":"CH",
    "sg:address":"Piazza Molino Nuovo 3",
    "sg:city":"Lugano",
    "sg:orig_category":"Detailhandel mit Zeitungen U Zeitschriften Kioske",
    "sg:phone":"+41 91 922 89 53",
    "sg:postcode":"6900",
    "sg:province":"Ticino",
    "wof:name":"Odette Porrini Edicola",
    "wof:placetype":"venue"
},
  "geometry": {"coordinates":[8.9547224045,46.0118789673],"type":"Point"}
}