{
  "type": "Feature",
  "properties": {
    "iso:country":"CH",
    "sg:address":"Ruelle Du Petit-port 4",
    "sg:city":"Auvernier",
    "sg:orig_category":"Malerei Stukkateurgewerbe, Gipserei U Verputzerei",
    "sg:phone":"+41 32 731 26 86",
    "sg:postcode":"2012",
    "sg:province":"Neuch\u00e2tel",
    "wof:name":"Jean-pierre Gamba Gypserie & Peinture",
    "wof:placetype":"venue"
},
  "geometry": {"coordinates":[6.8789381981,46.975528717],"type":"Point"}
}