{
  "type": "Feature",
  "properties": {
    "iso:country":"CH",
    "sg:address":"Unterdorf",
    "sg:city":"Maschwanden",
    "sg:orig_category":"RESTAURANTS: TEA-ROOMS",
    "sg:postcode":"8933",
    "sg:province":"Z\u00fcrich",
    "wof:name":"Restaurant H\u00f6rnli Wyss Helene",
    "wof:placetype":"venue"
},
  "geometry": {"coordinates":[8.4227552414,47.2335700989],"type":"Point"}
}