{
  "type": "Feature",
  "properties": {
    "iso:country":"CH",
    "sg:address":"Dorfstrasse 16",
    "sg:city":"Baar",
    "sg:classifiers":[
        {
            "category":"Shopping Center",
            "type":"Public Place"
        }
    ],
    "sg:phone":"+41 41 767 46 56",
    "sg:postcode":"6341",
    "sg:province":"Zug",
    "sg:tags":[
        "aluminium",
        "casting"
    ],
    "wof:name":"Belog Ag",
    "wof:placetype":"venue"
},
  "geometry": {"coordinates":[8.52484,47.19421],"type":"Point"}
}