{
  "type": "Feature",
  "properties": {
    "iso:country":"CH",
    "sg:address":"Ey 104",
    "sg:city":"Bigenthal",
    "sg:orig_category":"G\u00fcterbef\u00f6rderung im Strassenverkehr Spezieller Tiefbau",
    "sg:phone":"+41 26 670 22 78",
    "sg:postcode":"3513",
    "sg:province":"Bern",
    "wof:name":"Ab Marti Ag",
    "wof:placetype":"venue"
},
  "geometry": {"coordinates":[7.1084527969,46.9252319336],"type":"Point"}
}