{
  "type": "Feature",
  "properties": {
    "iso:country":"CH",
    "sg:address":"Bahnhofstrasse 1",
    "sg:city":"Netstal",
    "sg:orig_category":"Politische Parteien CVP",
    "sg:phone":"+41 55 640 15 81",
    "sg:postcode":"8754",
    "sg:province":"Glarus",
    "wof:name":"Cvp Ortspartei Netstal",
    "wof:placetype":"venue"
},
  "geometry": {"coordinates":[9.0577430725,47.0637969971],"type":"Point"}
}