{
  "type": "Feature",
  "properties": {
    "addr:full":"Sch\u00fctzengasse 5 Z\u00fcrich Z\u00fcrich 8001",
    "addr:housenumber":"5",
    "addr:postcode":"8001",
    "addr:street":"Schuetzengasse",
    "iso:country":"CH",
    "sg:address":"Sch\u00fctzengasse 5",
    "sg:city":"Z\u00fcrich",
    "sg:classifiers":[
        {
            "category":"Bars & Pubs",
            "type":"Food & Drink"
        }
    ],
    "sg:phone":"+41 12211065",
    "sg:postcode":"8001",
    "sg:province":"Z\u00fcrich",
    "sg:tags":[
        "restaurant"
    ],
    "wof:name":"Restaurant Rebe & Bacchus-bar",
    "wof:placetype":"venue"
},
  "geometry": {"coordinates":[8.540415,47.376076],"type":"Point"}
}