{
  "type": "Feature",
  "properties": {
    "iso:country":"CH",
    "sg:address":"Grabenweg 5",
    "sg:city":"Willisau",
    "sg:orig_category":"RESTAURANTS: TEA-ROOMS",
    "sg:phone":"+41 41 970 12 89",
    "sg:postcode":"6130",
    "sg:province":"Luzern",
    "wof:name":"Restaurant Taube",
    "wof:placetype":"venue"
},
  "geometry": {"coordinates":[7.9911022186,47.1212501526],"type":"Point"}
}