{
  "type": "Feature",
  "properties": {
    "iso:country":"CH",
    "sg:address":"Rue Karl-neuhaus 21",
    "sg:city":"Biel/bienne",
    "sg:orig_category":"Non-Classified Establishments",
    "sg:postcode":"2500",
    "sg:province":"Bern",
    "wof:name":"Clunemore Ag",
    "wof:placetype":"venue"
},
  "geometry": {"coordinates":[7.2439460754,47.1375694275],"type":"Point"}
}