{
  "type": "Feature",
  "properties": {
    "addr:full":"Bahnhofstrasse 11 Flawil St. Gallen 9230",
    "addr:housenumber":"11",
    "addr:postcode":"9230",
    "addr:street":"Bahnhofstrasse",
    "iso:country":"CH",
    "sg:address":"Bahnhofstrasse 11",
    "sg:city":"Flawil",
    "sg:orig_category":"Berufsberatungen",
    "sg:phone":"+41 71 393 46 26",
    "sg:postcode":"9230",
    "sg:province":"St. Gallen",
    "wof:name":"Berufs-& Laufbahnberatung Untertoggenburg",
    "wof:placetype":"venue"
},
  "geometry": {"coordinates":[9.187572,47.413944],"type":"Point"}
}