{
  "type": "Feature",
  "properties": {
    "iso:country":"CH",
    "sg:address":"Villa Mignola Les Raveyres",
    "sg:city":"Villars-ste-croix",
    "sg:orig_category":"Malerei Stukkateurgewerbe, Gipserei U Verputzerei",
    "sg:phone":"+41 21 701 34 95",
    "sg:postcode":"1029",
    "sg:province":"Vaud",
    "wof:name":"G.& A. Mini Sa Pl\u00e2trerie & Peinture",
    "wof:placetype":"venue"
},
  "geometry": {"coordinates":[6.5617370605,46.5680274963],"type":"Point"}
}