{
  "type": "Feature",
  "properties": {
    "iso:country":"CH",
    "sg:address":"3855",
    "sg:city":"Schwanden-brienz",
    "sg:orig_category":"Sportvereine Sch\u00fctzen",
    "sg:phone":"+41 26 672 18 15",
    "sg:postcode":"3855",
    "sg:province":"Bern",
    "wof:name":"Sch\u00fctzengesellschaft",
    "wof:placetype":"venue"
},
  "geometry": {"coordinates":[8.036860466,46.7545661926],"type":"Point"}
}