{
  "type": "Feature",
  "properties": {
    "addr:full":"Chemin De La Gare 51 Porrentruy Jura 2900",
    "addr:housenumber":"51",
    "addr:postcode":"2900",
    "addr:street":"Chemin De La Gare;Jura",
    "iso:country":"CH",
    "sg:address":"Chemin De La Gare 51",
    "sg:city":"Porrentruy",
    "sg:classifiers":[
        {
            "category":"Banks & Credit Unions",
            "subcategory":"Bank",
            "type":"Services"
        }
    ],
    "sg:phone":"+41 4166665588",
    "sg:postcode":"2900",
    "sg:province":"Jura",
    "wof:name":"Banque Cantonale Du Jura",
    "wof:placetype":"venue"
},
  "geometry": {"coordinates":[7.079447,47.420479],"type":"Point"}
}