{
  "type": "Feature",
  "properties": {
    "iso:country":"CH",
    "sg:address":"T\u00f6distrasse 16",
    "sg:city":"Jona",
    "sg:orig_category":"Detailhandel mit B\u00fcchern, Zeitungen, Schreib U Papeteriewaren",
    "sg:phone":"+41 55 210 10 00",
    "sg:postcode":"8645",
    "sg:province":"St. Gallen",
    "wof:name":"Bouvard Roger",
    "wof:placetype":"venue"
},
  "geometry": {"coordinates":[8.835111,47.226688],"type":"Point"}
}