{
  "type": "Feature",
  "properties": {
    "iso:country":"CH",
    "sg:address":"Via San Rocco 6928 Manno. Postfach",
    "sg:city":"Manno",
    "sg:orig_category":"Sonstige mit der Informatik verbundene T\u00e4tigkeiten",
    "sg:postcode":"6928",
    "sg:province":"Ticino",
    "wof:name":"Ailuc Sagl",
    "wof:placetype":"venue"
},
  "geometry": {"coordinates":[8.919005394,46.0345535278],"type":"Point"}
}