{
  "type": "Feature",
  "properties": {
    "iso:country":"CH",
    "sg:address":"Di V\u00e8len 4",
    "sg:city":"Camorino",
    "sg:orig_category":"Wirtschaftspr\u00fcfung, Steuerberatung U Treuhand",
    "sg:postcode":"6528",
    "sg:province":"Ticino",
    "wof:name":"Revitours Sagl",
    "wof:placetype":"venue"
},
  "geometry": {"coordinates":[9.0054998398,46.1631546021],"type":"Point"}
}