{
  "type": "Feature",
  "properties": {
    "addr:full":"Kohlestrasse 12b Schlieren Z\u00fcrich 8952",
    "addr:housenumber":"12b",
    "addr:postcode":"8952",
    "addr:street":"Kohlestrasse",
    "iso:country":"CH",
    "sg:address":"Kohlestrasse 12b",
    "sg:city":"Schlieren",
    "sg:orig_category":"Betrieb von Sportanlagen Sonstige Kultur U Unterhaltungseinrichtungen",
    "sg:phone":"+41 17310282",
    "sg:postcode":"8952",
    "sg:province":"Z\u00fcrich",
    "wof:name":"Kletterzentrum Gaswerk Ag",
    "wof:placetype":"venue"
},
  "geometry": {"coordinates":[8.462033,47.401745],"type":"Point"}
}