{
  "type": "Feature",
  "properties": {
    "iso:country":"CH",
    "sg:address":"Baarerstrasse 42",
    "sg:city":"Zug",
    "sg:orig_category":"Fotografische Ateliers Werbevermittlung",
    "sg:phone":"+41 41 711 97 47",
    "sg:postcode":"6300",
    "sg:province":"Zug",
    "wof:name":"Harry Burst Fotografie & Grafik",
    "wof:placetype":"venue"
},
  "geometry": {"coordinates":[8.517332077,47.174659729],"type":"Point"}
}