{
  "type": "Feature",
  "properties": {
    "iso:country":"CH",
    "sg:address":"Via Nassa 6900 Lugano Casella Postale 2552",
    "sg:city":"Lugano",
    "sg:orig_category":"Detailhandel mit Bekleidung Grosshandel mit Bekleidung",
    "sg:phone":"+41 22 908 30 66",
    "sg:postcode":"6900",
    "sg:province":"Ticino",
    "wof:name":"Gamtex Sa",
    "wof:placetype":"venue"
},
  "geometry": {"coordinates":[6.132673,46.205853],"type":"Point"}
}