{
  "type": "Feature",
  "properties": {
    "iso:country":"CH",
    "sg:address":"St\u00e4dtchen 24",
    "sg:city":"Uznach",
    "sg:classifiers":[
        {
            "category":"Restaurant",
            "type":"Food & Drink"
        }
    ],
    "sg:phone":"+41 55 280 60 06",
    "sg:postcode":"8730",
    "sg:province":"St. Gallen",
    "wof:name":"Restaurant Obertor",
    "wof:placetype":"venue"
},
  "geometry": {"coordinates":[8.9863967896,47.2252655029],"type":"Point"}
}