{
  "type": "Feature",
  "properties": {
    "iso:country":"CH",
    "sg:address":"Gulmmatt 6340 Baar. Postfach 2451",
    "sg:city":"Baar",
    "sg:orig_category":"Grosshandel mit Sportartikeln Sonstiger Grosshandel",
    "sg:phone":"+41 41 766 11 88",
    "sg:postcode":"6342",
    "sg:province":"Zug",
    "wof:name":"Tanega Ag",
    "wof:placetype":"venue"
},
  "geometry": {"coordinates":[8.5095748901,47.2093353271],"type":"Point"}
}