{
  "type": "Feature",
  "properties": {
    "iso:country":"CH",
    "sg:address":"Grand Rue 92",
    "sg:city":"Montreux",
    "sg:orig_category":"G\u00fcterbef\u00f6rderung im Strassenverkehr",
    "sg:phone":"+41 21 963 28 50",
    "sg:postcode":"1820",
    "sg:province":"Vaud",
    "wof:name":"Montreux Cal\u00e8che S\u00e0rl",
    "wof:placetype":"venue"
},
  "geometry": {"coordinates":[6.9084148407,46.4371528625],"type":"Point"}
}