{
  "type": "Feature",
  "properties": {
    "iso:country":"CH",
    "sg:address":"Obere Bahnhofstrasse 13",
    "sg:city":"Frutigen",
    "sg:orig_category":"Arztpraxen",
    "sg:phone":"+41 33 671 40 85",
    "sg:postcode":"3714",
    "sg:province":"Bern",
    "wof:name":"Dr.med.ursula Schafroth Spezial\u00e4rztin Fmh",
    "wof:placetype":"venue"
},
  "geometry": {"coordinates":[7.648594,46.589245],"type":"Point"}
}