{
  "type": "Feature",
  "properties": {
    "iso:country":"CH",
    "sg:address":"Morgenstrasse 123 3018 Bern. Postfach",
    "sg:city":"Bern",
    "sg:orig_category":"Satzherstellung U Reproduktion Sonstiges Druckgewerbe",
    "sg:phone":"+41 31 994 10 10",
    "sg:postcode":"3018",
    "sg:province":"Bern",
    "wof:name":"X-print Ag",
    "wof:placetype":"venue"
},
  "geometry": {"coordinates":[7.3902111053,46.9352378845],"type":"Point"}
}