{
  "type": "Feature",
  "properties": {
    "iso:country":"CH",
    "sg:address":"Chemin Du Bochet 37",
    "sg:city":"Romanel-s-lausanne",
    "sg:orig_category":"Detailhandel mit Textilien Verlegen von Fussboden",
    "sg:phone":"+41 21 647 63 50",
    "sg:postcode":"1032",
    "sg:province":"Vaud",
    "wof:name":"Meystre Pierre-alain, D\u00e9coration D'int\u00e9rieur.",
    "wof:placetype":"venue"
},
  "geometry": {"coordinates":[6.5973501205,46.5634651184],"type":"Point"}
}