{
  "type": "Feature",
  "properties": {
    "iso:country":"CH",
    "sg:address":"Route Des Daillettes 6 1700 Fribourg. Postfach",
    "sg:city":"Fribourg",
    "sg:orig_category":"Hardwareberatung Sonstige mit der Informatik verbundene T\u00e4tigkeiten",
    "sg:postcode":"1700",
    "sg:province":"Fribourg",
    "wof:name":"Tlk (services) Sa Fourniture De Mat\u00e9riel, Logiciels (software) Et Services Dans Le Domaine De L'informatique Et Des T\u00e9l\u00e9communications Etc",
    "wof:placetype":"venue"
},
  "geometry": {"coordinates":[7.146944046,46.7933959961],"type":"Point"}
}