{
  "type": "Feature",
  "properties": {
    "iso:country":"CH",
    "sg:address":"Rue Du Grand-pont 12",
    "sg:city":"Lausanne",
    "sg:orig_category":"Detailhandel mit Damenbekleidung",
    "sg:phone":"+41 56 441 96 65",
    "sg:postcode":"1003",
    "sg:province":"Vaud",
    "wof:name":"Jeanne Geissmann Couture",
    "wof:placetype":"venue"
},
  "geometry": {"coordinates":[8.207868,47.4804],"type":"Point"}
}