{
  "type": "Feature",
  "properties": {
    "iso:country":"CH",
    "sg:address":"Vuarpilli\u00e8re Ch. De La 31",
    "sg:city":"Nyon",
    "sg:orig_category":"Herstellung von medizinischen U chirurgischen Ger\u00e4ten sowie orthop\u00e4dischen Vorrichtungen",
    "sg:phone":"+41 56 282 45 66",
    "sg:postcode":"1260",
    "sg:province":"Vaud",
    "wof:name":"Eadolg Ag",
    "wof:placetype":"venue"
},
  "geometry": {"coordinates":[8.2924947739,47.4877624512],"type":"Point"}
}