{
  "type": "Feature",
  "properties": {
    "iso:country":"CH",
    "sg:address":"Le Cr\u00eat-du-lac.",
    "sg:city":"Vaumarcus",
    "sg:orig_category":"Betrieb U technische Hilfsdienste des Kultur U Unterhaltungswesens",
    "sg:postcode":"2028",
    "sg:province":"Neuch\u00e2tel",
    "wof:name":"Les Productions Canthus S\u00e0rl",
    "wof:placetype":"venue"
},
  "geometry": {"coordinates":[6.547739,46.515575],"type":"Point"}
}