{
  "type": "Feature",
  "properties": {
    "iso:country":"CH",
    "sg:address":"Holtenstrasse 26",
    "sg:city":"Gr\u00e4nichen",
    "sg:orig_category":"Grosshandel mit sonstigen Gebrauchs U Verbrauchsg\u00fctern",
    "sg:postcode":"5722",
    "sg:province":"Aargau",
    "wof:name":"Acc Globe Gmbh",
    "wof:placetype":"venue"
},
  "geometry": {"coordinates":[8.0978307724,47.3674736023],"type":"Point"}
}