{
  "type": "Feature",
  "properties": {
    "iso:country":"CH",
    "sg:address":"Leemattenstrasse 14b",
    "sg:city":"Fislisbach",
    "sg:orig_category":"Fahrschulen, Flugschulen",
    "sg:phone":"+41 79 357 32 62",
    "sg:postcode":"5442",
    "sg:province":"Aargau",
    "wof:name":"Josef Eberhard Autofahrschule",
    "wof:placetype":"venue"
},
  "geometry": {"coordinates":[8.2885370255,47.4373168945],"type":"Point"}
}