{
  "type": "Feature",
  "properties": {
    "iso:country":"CH",
    "sg:address":"Duggelistrasse 12",
    "sg:city":"Cham",
    "sg:orig_category":"G\u00fcterbef\u00f6rderung im Strassenverkehr",
    "sg:phone":"+41 55 442 22 24",
    "sg:postcode":"6330",
    "sg:province":"Zug",
    "wof:name":"Josef Z\u00fcger Transporte",
    "wof:placetype":"venue"
},
  "geometry": {"coordinates":[8.8624124527,47.1891212463],"type":"Point"}
}