{
  "type": "Feature",
  "properties": {
    "iso:country":"CH",
    "sg:address":"Via Belvedere 4",
    "sg:city":"Canobbio",
    "sg:orig_category":"Instandhaltung U Reparatur von Automobilen",
    "sg:phone":"+41 91 942 69 14",
    "sg:postcode":"6952",
    "sg:province":"Ticino",
    "wof:name":"Dr Trafic Sa",
    "wof:placetype":"venue"
},
  "geometry": {"coordinates":[8.9686899185,46.0301094055],"type":"Point"}
}