{
  "type": "Feature",
  "properties": {
    "iso:country":"CH",
    "sg:address":"Gotthardstrasse 96",
    "sg:city":"Hospental",
    "sg:orig_category":"Wohnheime",
    "sg:postcode":"6493",
    "sg:province":"Uri",
    "wof:name":"Gautschi-stiftung F\u00fcr Das Parit\u00e4tische Alters Und Pflegeheim, St. Margrethen",
    "wof:placetype":"venue"
},
  "geometry": {"coordinates":[9.6220798492,47.4559402466],"type":"Point"}
}