{
  "type": "Feature",
  "properties": {
    "iso:country":"CH",
    "sg:address":"1997 Haute-nendaz 1997 Haute-nendaz. Postfach",
    "sg:city":"Haute-nendaz",
    "sg:orig_category":"Detailhandel mit Brot, Back U S\u00fcsswaren",
    "sg:postcode":"1997",
    "sg:province":"Valais",
    "wof:name":"Quartier, Boulangerie-p\u00e2tisserie Du Village",
    "wof:placetype":"venue"
},
  "geometry": {"coordinates":[7.295837,46.186962],"type":"Point"}
}