{
  "type": "Feature",
  "properties": {
    "iso:country":"CH",
    "sg:address":"Rte St-nicolas-de-fl\u00fce 6a",
    "sg:city":"Fribourg",
    "sg:orig_category":"Erbringung von Dienstleistungen f\u00fcr Unternehmen",
    "sg:postcode":"1700",
    "sg:province":"Fribourg",
    "wof:name":"Graphismes, Baeriswyl Anne-marie",
    "wof:placetype":"venue"
},
  "geometry": {"coordinates":[7.1494169235,46.7938804626],"type":"Point"}
}