{
  "type": "Feature",
  "properties": {
    "iso:country":"CH",
    "sg:address":"F\u00f6hrenstrasse 3",
    "sg:city":"M\u00f6hlin",
    "sg:orig_category":"Erbringung von Dienstleistungen f\u00fcr Unternehmen",
    "sg:phone":"+41 61 851 09 82",
    "sg:postcode":"4313",
    "sg:province":"Aargau",
    "wof:name":"Merz Rolf Airbrush Und Grafik-atelier",
    "wof:placetype":"venue"
},
  "geometry": {"coordinates":[7.8394761086,47.5599479675],"type":"Point"}
}