{
  "type": "Feature",
  "properties": {
    "iso:country":"CH",
    "sg:address":"Neustrasse 20",
    "sg:city":"Romanshorn",
    "sg:orig_category":"Landesverteidigung, Sozialversicherung \u00d6ffentliche Verwaltung",
    "sg:phone":"+41 71 463 24 53",
    "sg:postcode":"8590",
    "sg:province":"Thurgau",
    "wof:name":"Zivilschutzstelle Romanshorn",
    "wof:placetype":"venue"
},
  "geometry": {"coordinates":[9.3788900375,47.5627288818],"type":"Point"}
}