{
  "type": "Feature",
  "properties": {
    "iso:country":"CH",
    "sg:address":"Ch. Des Perry",
    "sg:city":"Valeyres-montagny",
    "sg:orig_category":"Druck ohne Zeitungsdruck",
    "sg:phone":"+41 24 446 16 61",
    "sg:postcode":"1441",
    "sg:province":"Vaud",
    "wof:name":"Pamoffset, Millioud Pierre-alain",
    "wof:placetype":"venue"
},
  "geometry": {"coordinates":[6.6112980843,46.7984695435],"type":"Point"}
}