{
  "type": "Feature",
  "properties": {
    "iso:country":"CH",
    "sg:address":"Bielstrasse 9",
    "sg:city":"Lyss",
    "sg:orig_category":"Sonstiger Detailhandel mit Metallwaren, Anstrichmitteln, Glaswaren, Bau U Heimwerkerbedarf",
    "sg:phone":"+41 32 384 31 41",
    "sg:postcode":"3250",
    "sg:province":"Bern",
    "wof:name":"Migros-markt Zentrum Seeland",
    "wof:placetype":"venue"
},
  "geometry": {"coordinates":[7.3056387901,47.0748672485],"type":"Point"}
}