{
  "type": "Feature",
  "properties": {
    "iso:country":"CH",
    "sg:address":"St. Martinsplatz 8",
    "sg:city":"Chur",
    "sg:orig_category":"Unclassifiable Establishments",
    "sg:phone":"+41 81 250 08 86",
    "sg:postcode":"7000",
    "sg:province":"Graubunden",
    "wof:name":"Global Aviation Holding Ag",
    "wof:placetype":"venue"
},
  "geometry": {"coordinates":[9.5323343277,46.8481216431],"type":"Point"}
}