{
  "type": "Feature",
  "properties": {
    "iso:country":"CH",
    "sg:address":"1312",
    "sg:city":"Ecl\u00e9pens",
    "sg:orig_category":"Abwasserreinigung Wasserversorgung",
    "sg:phone":"+41 21 866 75 32",
    "sg:postcode":"1312",
    "sg:province":"Vaud",
    "wof:name":"Service Des Eaux De La Commune D'ecl\u00e9pens",
    "wof:placetype":"venue"
},
  "geometry": {"coordinates":[6.54448,46.652199],"type":"Point"}
}