{
  "type": "Feature",
  "properties": {
    "iso:country":"CH",
    "sg:address":"Rue De La Terrassi\u00e8re 27",
    "sg:city":"Gen\u00e8ve",
    "sg:orig_category":"Detailhandel mit Waren verschiedener Art, Hauptrichtung Nahrungsmittel",
    "sg:phone":"+41 22 736 44 55",
    "sg:postcode":"1207",
    "sg:province":"Gen\u00e8ve",
    "wof:name":"Migros Villereuse",
    "wof:placetype":"venue"
},
  "geometry": {"coordinates":[6.1586608887,46.2007064819],"type":"Point"}
}