{
  "type": "Feature",
  "properties": {
    "iso:country":"CH",
    "sg:address":"Industriestrasse 13",
    "sg:city":"Lengnau",
    "sg:classifiers":[
        {
            "category":"Shopping Center",
            "type":"Public Place"
        }
    ],
    "sg:phone":"+41 32 652 41 06",
    "sg:postcode":"2543",
    "sg:province":"Bern",
    "sg:tags":[
        "case",
        "clock"
    ],
    "wof:name":"H. Finger Sa",
    "wof:placetype":"venue"
},
  "geometry": {"coordinates":[7.361762,47.175453],"type":"Point"}
}