{
  "type": "Feature",
  "properties": {
    "iso:country":"CH",
    "sg:address":"Chemin Du Milieu 8",
    "sg:city":"V\u00e9troz",
    "sg:orig_category":"Zimmerei, Dachdeckerei, Bauspenglerei U Abdichtung",
    "sg:phone":"+41 27 327 30 20",
    "sg:postcode":"1963",
    "sg:province":"Valais",
    "wof:name":"Bornet Fr\u00e8res Sa",
    "wof:placetype":"venue"
},
  "geometry": {"coordinates":[7.2790122032,46.2217330933],"type":"Point"}
}