{
  "type": "Feature",
  "properties": {
    "iso:country":"CH",
    "sg:address":"Allenmoosstrasse 89",
    "sg:city":"Z\u00fcrich",
    "sg:orig_category":"Sonderschulen Wohnheime f\u00fcr Kinder U Jugendliche",
    "sg:phone":"+41 13120314",
    "sg:postcode":"8057",
    "sg:province":"Z\u00fcrich",
    "wof:name":"St\u00e4dt. Sprachheilkindergarten",
    "wof:placetype":"venue"
},
  "geometry": {"coordinates":[8.5428771973,47.4053001404],"type":"Point"}
}