{
  "type": "Feature",
  "properties": {
    "iso:country":"CH",
    "sg:address":"Metallstrasse 9a",
    "sg:city":"Zug",
    "sg:orig_category":"Sonstige pers\u00f6nliche Dienstleistungen",
    "sg:phone":"+41 71 222 55 03",
    "sg:postcode":"6300",
    "sg:province":"Zug",
    "wof:name":"Unterwegs Zum Du Marlene Van Ieperen Partnervermittlung",
    "wof:placetype":"venue"
},
  "geometry": {"coordinates":[9.3745412827,47.4256896973],"type":"Point"}
}