{
  "type": "Feature",
  "properties": {
    "iso:country":"CH",
    "sg:address":"6616 Losone. Postfach Caselle Postale 1164",
    "sg:city":"Losone",
    "sg:orig_category":"Campingpl\u00e4tze Detailhandel mit Zeitungen U Zeitschriften Kioske",
    "sg:phone":"+41 91 791 10 50",
    "sg:postcode":"6616",
    "sg:province":"Ticino",
    "wof:name":"Campeggio Zandone Gi\u00e0 Stern Gustavo Candolfi",
    "wof:placetype":"venue"
},
  "geometry": {"coordinates":[8.759752,46.165249],"type":"Point"}
}