{
  "type": "Feature",
  "properties": {
    "iso:country":"CH",
    "sg:address":"Untere Fabrik 20 9102 Herisau. Postfach",
    "sg:city":"Arbon",
    "sg:orig_category":"Sonstiger Grosshandel",
    "sg:postcode":"9320",
    "sg:province":"Thurgau",
    "wof:name":"Kempf Logistik Gmbh Warenhandel",
    "wof:placetype":"venue"
},
  "geometry": {"coordinates":[9.2696695328,47.3914451599],"type":"Point"}
}