{
  "type": "Feature",
  "properties": {
    "iso:country":"CH",
    "sg:address":"Avenue Coderey 6 Bis 1110 Morges. Postfach",
    "sg:city":"Morges",
    "sg:orig_category":"Herstellung von Konstruktionsteilen, Fertigbauteilen U Ausbauelementen aus Holz",
    "sg:postcode":"1110",
    "sg:province":"Vaud",
    "wof:name":"Agenca Bardinet L.",
    "wof:placetype":"venue"
},
  "geometry": {"coordinates":[6.4894170761,46.5161437988],"type":"Point"}
}