{
  "type": "Feature",
  "properties": {
    "iso:country":"CH",
    "sg:address":"3860 Meiringen. Postfach 668",
    "sg:city":"Meiringen",
    "sg:orig_category":"Sportvereine Ballsport Fussball",
    "sg:phone":"+41 61 601 11 17",
    "sg:postcode":"3860",
    "sg:province":"Bern",
    "wof:name":"Sv Muttenz",
    "wof:placetype":"venue"
},
  "geometry": {"coordinates":[7.6478300095,47.5212211609],"type":"Point"}
}