{
  "type": "Feature",
  "properties": {
    "iso:country":"CH",
    "sg:address":"Z\u00fcrichstrasse 211 8124 Maur. Postfach",
    "sg:city":"Maur",
    "sg:orig_category":"Architektur U Ingenieurb\u00fcros",
    "sg:phone":"+41 19822020",
    "sg:postcode":"8124",
    "sg:province":"Z\u00fcrich",
    "wof:name":"Hausammann + Partner Architekten Htl Ag",
    "wof:placetype":"venue"
},
  "geometry": {"coordinates":[8.665198,47.341267],"type":"Point"}
}