{
  "type": "Feature",
  "properties": {
    "iso:country":"CH",
    "sg:address":"Paulus-weg 10",
    "sg:city":"Biel/bienne",
    "sg:classifiers":[
        {
            "category":"Utilities",
            "subcategory":"Electric",
            "type":"Services"
        }
    ],
    "sg:phone":"+41 32 365 08 25",
    "sg:postcode":"2503",
    "sg:province":"Bern",
    "sg:tags":[
        "electroplating"
    ],
    "wof:name":"Rolf Helbling Metallveredlung",
    "wof:placetype":"venue"
},
  "geometry": {"coordinates":[7.254744,47.131348],"type":"Point"}
}