{
  "type": "Feature",
  "properties": {
    "iso:country":"CH",
    "sg:address":"Hauptstrasse 18",
    "sg:city":"Meggen",
    "sg:orig_category":"Interessenvertretungen",
    "sg:postcode":"6045",
    "sg:province":"Luzern",
    "wof:name":"Margueron Bernard Et Laurette",
    "wof:placetype":"venue"
},
  "geometry": {"coordinates":[7.0663948059,46.6079711914],"type":"Point"}
}