{
  "type": "Feature",
  "properties": {
    "iso:country":"CH",
    "sg:address":"Im Isisb\u00fcel 1",
    "sg:city":"Thalwil",
    "sg:orig_category":"Sportvereine Ski",
    "sg:phone":"+41 17202656",
    "sg:postcode":"8800",
    "sg:province":"Z\u00fcrich",
    "wof:name":"Skiclub Nsk R\u00fcschlikon",
    "wof:placetype":"venue"
},
  "geometry": {"coordinates":[8.5675210953,47.2932281494],"type":"Point"}
}