{
  "type": "Feature",
  "properties": {
    "iso:country":"CH",
    "sg:address":"Burgerstrasse 2",
    "sg:city":"Luzern",
    "sg:orig_category":"Allgemeiner Hoch U Tiefbau Hoch U Tiefbau",
    "sg:phone":"+41 41 240 53 40",
    "sg:postcode":"6003",
    "sg:province":"Luzern",
    "wof:name":"Humatec Gmbh Renovationen Mauerentfeuchtung",
    "wof:placetype":"venue"
},
  "geometry": {"coordinates":[8.302877,47.050842],"type":"Point"}
}