{
  "type": "Feature",
  "properties": {
    "iso:country":"CH",
    "sg:address":"Talackerstrasse 43",
    "sg:city":"Glattbrugg",
    "sg:orig_category":"Grosshandel mit B\u00fcromaschinen Grosshandel mit chemischen Erzeugnissen",
    "sg:phone":"+41 18110379",
    "sg:postcode":"8152",
    "sg:province":"Z\u00fcrich",
    "wof:name":"Khan Enterprise",
    "wof:placetype":"venue"
},
  "geometry": {"coordinates":[8.5615329742,47.4267845154],"type":"Point"}
}