{
  "type": "Feature",
  "properties": {
    "iso:country":"CH",
    "sg:address":"Gr\u00fcnauring 41",
    "sg:city":"Z\u00fcrich",
    "sg:orig_category":"Dachdeckerei",
    "sg:phone":"+41 32 913 36 17",
    "sg:postcode":"8064",
    "sg:province":"Z\u00fcrich",
    "wof:name":"Francis Nussbaum Entreprise De Couverture",
    "wof:placetype":"venue"
},
  "geometry": {"coordinates":[6.812138,47.091423],"type":"Point"}
}