{
  "type": "Feature",
  "properties": {
    "iso:country":"CH",
    "sg:address":"Rue De La Poste 2 1350 Orbe Case Postale 164",
    "sg:city":"Orbe",
    "sg:orig_category":"Verkehrs- and Tourismusb\u00fcros",
    "sg:phone":"+41 24 441 31 15",
    "sg:postcode":"1350",
    "sg:province":"Vaud",
    "wof:name":"Office De Tourisme D'orbe Et Environs",
    "wof:placetype":"venue"
},
  "geometry": {"coordinates":[6.531129837,46.7242164612],"type":"Point"}
}