{
  "type": "Feature",
  "properties": {
    "iso:country":"CH",
    "sg:address":"Tichelr\u00fctistrasse 26 8044 Gockhausen. Postfach",
    "sg:city":"Gockhausen",
    "sg:orig_category":"Erwachsenenbildung U Unterricht",
    "sg:postcode":"8044",
    "sg:province":"Z\u00fcrich",
    "wof:name":"Campus Hr-training, Feldmann Joachim",
    "wof:placetype":"venue"
},
  "geometry": {"coordinates":[8.6030664444,47.3802871704],"type":"Point"}
}