{
  "type": "Feature",
  "properties": {
    "iso:country":"CH",
    "sg:address":"7130 Ilanz. Postfach 119",
    "sg:city":"Ilanz",
    "sg:orig_category":"D\u00e4mmung gegen K\u00e4lte, W\u00e4rme, Schall U Ersch\u00fctterung Stukkateurgewerbe, Gipserei U Verputzerei",
    "sg:phone":"+41 81 925 21 77",
    "sg:postcode":"7130",
    "sg:province":"Graubunden",
    "wof:name":"H\u00fcco Ag Gipserei & Aussenisolationen",
    "wof:placetype":"venue"
},
  "geometry": {"coordinates":[9.2045469284,46.7744483948],"type":"Point"}
}