{
  "type": "Feature",
  "properties": {
    "iso:country":"CH",
    "sg:address":"Im Ziegel\u00e4gerten",
    "sg:city":"Dietikon",
    "sg:orig_category":"R\u00fcckgewinnung U Vorbereitung f\u00fcr die Wiederverwertung Recycling von Schrott",
    "sg:postcode":"8953",
    "sg:province":"Z\u00fcrich",
    "wof:name":"Gerber Alteisen + Abbr\u00fcche Ag, Zweigniederlassung Dietikon",
    "wof:placetype":"venue"
},
  "geometry": {"coordinates":[8.388915062,47.4087600708],"type":"Point"}
}