{
  "type": "Feature",
  "properties": {
    "iso:country":"CH",
    "sg:address":"Hofackerstrasse 36",
    "sg:city":"Z\u00fcrich",
    "sg:orig_category":"Architektur U Ingenieurb\u00fcros",
    "sg:phone":"+41 14229246",
    "sg:postcode":"8032",
    "sg:province":"Z\u00fcrich",
    "wof:name":"Ingenieurb\u00fcro Chvojka, Dipl. Ing. Eth Ingenieurb\u00fcro F. Betriebsorganisation U. F\u00f6rdertechnik",
    "wof:placetype":"venue"
},
  "geometry": {"coordinates":[8.564627,47.361305],"type":"Point"}
}