{
  "type": "Feature",
  "properties": {
    "iso:country":"CH",
    "sg:address":"1026",
    "sg:city":"Echandens",
    "sg:orig_category":"Verwertung von Milch",
    "sg:postcode":"1026",
    "sg:province":"Vaud",
    "wof:name":"Soci\u00e9t\u00e9 De Laiterie D'echandens",
    "wof:placetype":"venue"
},
  "geometry": {"coordinates":[6.5371398926,46.5320205688],"type":"Point"}
}