{
  "type": "Feature",
  "properties": {
    "iso:country":"CH",
    "sg:address":"H\u00f6henweg 7",
    "sg:city":"Deitingen",
    "sg:orig_category":"Malerei-Gipserei Stukkateurgewerbe, Gipserei U Verputzerei",
    "sg:phone":"+41 71 744 28 52",
    "sg:postcode":"4543",
    "sg:province":"Solothurn",
    "wof:name":"Hans Sch\u00e4llebaum Gipsergesch\u00e4ft",
    "wof:placetype":"venue"
},
  "geometry": {"coordinates":[9.6237106323,47.4552841187],"type":"Point"}
}