{
  "type": "Feature",
  "properties": {
    "iso:country":"CH",
    "sg:address":"Via Bernardino Luini 18",
    "sg:city":"Locarno",
    "sg:orig_category":"Sonstiges Textilgewerbe",
    "sg:postcode":"6600",
    "sg:province":"Ticino",
    "wof:name":"Locarno Tessili Sagl",
    "wof:placetype":"venue"
},
  "geometry": {"coordinates":[8.7969169617,46.1682472229],"type":"Point"}
}