{
  "type": "Feature",
  "properties": {
    "iso:country":"CH",
    "sg:address":"Langackerstrasse 13 4142 M\u00fcnchenstein. Postfach",
    "sg:city":"M\u00fcnchenstein",
    "sg:orig_category":"Unclassifiable Establishments",
    "sg:phone":"+41 61 411 44 12",
    "sg:postcode":"4142",
    "sg:province":"Basel-Landschaft",
    "wof:name":"Ihr Partner Beim Ladenbau Gmbh Beratung, Konzeption, Planung Im Bereich Des Ladenbaus Usw",
    "wof:placetype":"venue"
},
  "geometry": {"coordinates":[7.6167869568,47.5230827332],"type":"Point"}
}