{
  "type": "Feature",
  "properties": {
    "iso:country":"CH",
    "sg:address":"Weekendweg 7",
    "sg:city":"Einigen",
    "sg:orig_category":"Architektur U Ingenieurb\u00fcros",
    "sg:phone":"+41 33 654 80 84",
    "sg:postcode":"3646",
    "sg:province":"Bern",
    "wof:name":"Agitech Ag F\u00fcr Industrielle Technik Ingenieurb\u00fcro",
    "wof:placetype":"venue"
},
  "geometry": {"coordinates":[7.639764,46.712955],"type":"Point"}
}