{
  "type": "Feature",
  "properties": {
    "iso:country":"CH",
    "sg:address":"Sunneweg 5",
    "sg:city":"Glattfelden",
    "sg:orig_category":"Datenverarbeitungsdienste Wirtschaftspr\u00fcfung, Steuerberatung U Treuhand",
    "sg:phone":"+41 18674185",
    "sg:postcode":"8192",
    "sg:province":"Z\u00fcrich",
    "wof:name":"Merki Und Henseler Treuhand Ag",
    "wof:placetype":"venue"
},
  "geometry": {"coordinates":[8.503308,47.560612],"type":"Point"}
}