{
  "type": "Feature",
  "properties": {
    "iso:country":"CH",
    "sg:address":"Zollstrasse 6",
    "sg:city":"Landquart",
    "sg:orig_category":"Bauspenglerei Sanit\u00e4rinstallation",
    "sg:phone":"+41 26 496 18 32",
    "sg:postcode":"7302",
    "sg:province":"Graubunden",
    "wof:name":"Alfred Reber Sanit\u00e4re Anlagen & Spenglerei",
    "wof:placetype":"venue"
},
  "geometry": {"coordinates":[7.243837,46.852383],"type":"Point"}
}