{
  "type": "Feature",
  "properties": {
    "iso:country":"CH",
    "sg:address":"La Solitude",
    "sg:city":"Peney-le-jorat",
    "sg:orig_category":"Sportvereine Sch\u00fctzen",
    "sg:phone":"+41 32 853 65 65",
    "sg:postcode":"1059",
    "sg:province":"Vaud",
    "wof:name":"St\u00e9 De Tir Les Patriotes",
    "wof:placetype":"venue"
},
  "geometry": {"coordinates":[6.9875998497,47.0987815857],"type":"Point"}
}