{
  "type": "Feature",
  "properties": {
    "iso:country":"CH",
    "sg:address":"Route De Chandolan 1",
    "sg:city":"Villars-sur-gl\u00e2ne",
    "sg:classifiers":[
        {
            "category":"Utilities",
            "subcategory":"Natural Gas",
            "type":"Services"
        }
    ],
    "sg:phone":"+41 26 409 72 10",
    "sg:postcode":"1752",
    "sg:province":"Fribourg",
    "sg:tags":[
        "boiler",
        "central",
        "fired",
        "heating"
    ],
    "wof:name":"Vaillant S.\u00e0.r.l.",
    "wof:placetype":"venue"
},
  "geometry": {"coordinates":[7.12257,46.800106],"type":"Point"}
}