{
  "type": "Feature",
  "properties": {
    "iso:country":"CH",
    "sg:address":"Ronchi Via Ai 18",
    "sg:city":"Muzzano",
    "sg:orig_category":"Grosshandel mit Nahrungsmitteln, Getr\u00e4nken U Tabakwaren ohne ausgepr\u00e4gten Schwerpunkt",
    "sg:postcode":"6933",
    "sg:province":"Ticino",
    "wof:name":"Cabian Sagl",
    "wof:placetype":"venue"
},
  "geometry": {"coordinates":[8.9219303131,45.9981193542],"type":"Point"}
}