{
  "type": "Feature",
  "properties": {
    "iso:country":"CH",
    "sg:address":"Kaspar-koppstrasse 99",
    "sg:city":"Ebikon",
    "sg:orig_category":"Hoch U Tiefbau",
    "sg:phone":"+41 41 440 34 34",
    "sg:postcode":"6030",
    "sg:province":"Luzern",
    "wof:name":"Konrad Fassbind Baugesch\u00e4ft",
    "wof:placetype":"venue"
},
  "geometry": {"coordinates":[8.3198642731,47.0703086853],"type":"Point"}
}