{
  "type": "Feature",
  "properties": {
    "iso:country":"CH",
    "sg:address":"H\u00e4dilochstrasse 48",
    "sg:city":"Niederurnen",
    "sg:orig_category":"Seilbahnen",
    "sg:phone":"+41 27 956 13 25",
    "sg:postcode":"8867",
    "sg:province":"Glarus",
    "wof:name":"Seilbahngenossenschaft Jungen Hugo Gruber",
    "wof:placetype":"venue"
},
  "geometry": {"coordinates":[7.7986898422,46.1720733643],"type":"Point"}
}