{
  "type": "Feature",
  "properties": {
    "iso:country":"CH",
    "sg:address":"Fontaines Blanches Immeubles 1875 Morgins. Postfach",
    "sg:city":"Morgins",
    "sg:orig_category":"Non-Classified Establishments",
    "sg:postcode":"1875",
    "sg:province":"Valais",
    "wof:name":"Fontaines Blanches - Morgins Sa",
    "wof:placetype":"venue"
},
  "geometry": {"coordinates":[6.8587532043,46.2375221252],"type":"Point"}
}