{
  "type": "Feature",
  "properties": {
    "iso:country":"CH",
    "sg:address":"Chemin Du Lac-de-br\u00eat 1070 Puidoux. Postfach",
    "sg:city":"Puidoux",
    "sg:orig_category":"Architektur U Ingenieurb\u00fcros",
    "sg:postcode":"1070",
    "sg:province":"Vaud",
    "wof:name":"Bbt Br\u00e9laz Bureau Technique Entreprises; Gestion. Chantiers; Surveillance. Direction De Travaux Dans Le Domaine De La Construction",
    "wof:placetype":"venue"
},
  "geometry": {"coordinates":[6.772238,46.506653],"type":"Point"}
}