{
  "type": "Feature",
  "properties": {
    "iso:country":"CH",
    "sg:address":"Im Staubeweidli 15",
    "sg:city":"W\u00e4denswil",
    "sg:orig_category":"Innendekorationsateliers",
    "sg:phone":"+41 17806836",
    "sg:postcode":"8820",
    "sg:province":"Z\u00fcrich",
    "wof:name":"Monika Fiechter Vorhang-atelier",
    "wof:placetype":"venue"
},
  "geometry": {"coordinates":[8.687710762,47.2208213806],"type":"Point"}
}