{
  "type": "Feature",
  "properties": {
    "iso:country":"CH",
    "sg:address":"Via Cantonale 20",
    "sg:city":"Lugano",
    "sg:orig_category":"Werbegrafikateliers",
    "sg:phone":"+41 91 923 90 49",
    "sg:postcode":"6900",
    "sg:province":"Ticino",
    "wof:name":"Franco Cavani Studio Grafico",
    "wof:placetype":"venue"
},
  "geometry": {"coordinates":[8.9505558014,46.0065765381],"type":"Point"}
}