{
  "type": "Feature",
  "properties": {
    "iso:country":"CH",
    "sg:address":"Baarerstrasse 2",
    "sg:city":"Zug",
    "sg:orig_category":"Finanzierungsinstitutionen",
    "sg:postcode":"6300",
    "sg:province":"Zug",
    "wof:name":"Allianz Handels- U. Finanz Ag",
    "wof:placetype":"venue"
},
  "geometry": {"coordinates":[8.5161046982,47.1706962585],"type":"Point"}
}