{
  "type": "Feature",
  "properties": {
    "iso:country":"CH",
    "sg:address":"Rossmarktplatz 12 4500 Solothurn. Postfach",
    "sg:city":"Solothurn",
    "sg:orig_category":"Vermittlung von Immobilien Wirtschaftspr\u00fcfung, Steuerberatung U Treuhand",
    "sg:phone":"+41 32 622 21 55",
    "sg:postcode":"4502",
    "sg:province":"Solothurn",
    "wof:name":"Affolter Treuhand",
    "wof:placetype":"venue"
},
  "geometry": {"coordinates":[7.5373277664,47.2044906616],"type":"Point"}
}