{
  "type": "Feature",
  "properties": {
    "iso:country":"CH",
    "sg:address":"Bielstrasse 1",
    "sg:city":"Grenchen",
    "sg:orig_category":"Gymnastik U Fitnesszentren Saunas, Solarien, Fitnesszentren U \u00e4hnliches",
    "sg:phone":"+41 32 652 66 21",
    "sg:postcode":"2540",
    "sg:province":"Solothurn",
    "wof:name":"City-fit Brunner",
    "wof:placetype":"venue"
},
  "geometry": {"coordinates":[7.3957109451,47.1921310425],"type":"Point"}
}