{
  "type": "Feature",
  "properties": {
    "iso:country":"CH",
    "sg:address":"Steinenweg 71",
    "sg:city":"Zunzgen",
    "sg:orig_category":"Fernmeldedienste",
    "sg:phone":"+41 61 971 53 90",
    "sg:postcode":"4455",
    "sg:province":"Basel-Landschaft",
    "wof:name":"Messmer Christian Telekommunikation",
    "wof:placetype":"venue"
},
  "geometry": {"coordinates":[7.8037137985,47.4556617737],"type":"Point"}
}