{
  "type": "Feature",
  "properties": {
    "iso:country":"CH",
    "sg:address":"Hauptstrasse 29",
    "sg:city":"L\u00fcscherz",
    "sg:classifiers":[
        {
            "category":"Restaurant",
            "type":"Food & Drink"
        }
    ],
    "sg:phone":"+41 32 377 10 70",
    "sg:postcode":"2576",
    "sg:province":"Bern",
    "wof:name":"Restaurant 3 Sapins",
    "wof:placetype":"venue"
},
  "geometry": {"coordinates":[7.3409099579,47.1887245178],"type":"Point"}
}