{
  "type": "Feature",
  "properties": {
    "iso:country":"CH",
    "sg:address":"Mariabergstrasse 2 9400 Rorschach. Postfach 242",
    "sg:city":"Rorschach",
    "sg:orig_category":"Detailhandel mit elektrischen Haushalts-,Radio U Fernsehger\u00e4ten sowie Musikinstrumenten Detailhandel",
    "sg:phone":"+41 71 841 13 58",
    "sg:postcode":"9401",
    "sg:province":"St. Gallen",
    "wof:name":"Keller Baby-hus & N\u00e4hmaschinen",
    "wof:placetype":"venue"
},
  "geometry": {"coordinates":[9.4928245544,47.4781761169],"type":"Point"}
}