{
  "type": "Feature",
  "properties": {
    "iso:country":"CH",
    "sg:address":"Tannegg 8376 Fischingen. Postfach",
    "sg:city":"Dussnang",
    "sg:orig_category":"Webereien, Webwaren",
    "sg:postcode":"8374",
    "sg:province":"Thurgau",
    "wof:name":"Oberholzer H.",
    "wof:placetype":"venue"
},
  "geometry": {"coordinates":[8.9484758377,47.4275588989],"type":"Point"}
}