{
  "type": "Feature",
  "properties": {
    "iso:country":"CH",
    "sg:address":"H\u00f6heweg 135",
    "sg:city":"Interlaken",
    "sg:orig_category":"Detailhandel mit Geschenkartikeln U Souvenirs",
    "sg:phone":"+41 33 822 93 22",
    "sg:postcode":"3800",
    "sg:province":"Bern",
    "wof:name":"Guido Rodi Souvenirs",
    "wof:placetype":"venue"
},
  "geometry": {"coordinates":[7.8625178337,46.6886138916],"type":"Point"}
}