{
  "type": "Feature",
  "properties": {
    "iso:country":"CH",
    "sg:address":"Wanderstr. 77",
    "sg:city":"Basel",
    "sg:orig_category":"Vermietung von Automobilen",
    "sg:phone":"+41 61 302 57 75",
    "sg:postcode":"4054",
    "sg:province":"Basel-Stadt",
    "wof:name":"Air Traffic Promotion Group Research Unit Commercial Aviation",
    "wof:placetype":"venue"
},
  "geometry": {"coordinates":[7.5647068024,47.5521621704],"type":"Point"}
}