{
  "type": "Feature",
  "properties": {
    "iso:country":"CH",
    "sg:address":"La Voie-creuse 16",
    "sg:city":"Gen\u00e8ve",
    "sg:orig_category":"Detailhandel mit Bekleidung Detailhandel mit Geschenkartikeln U Souvenirs",
    "sg:phone":"+41 71 222 21 20",
    "sg:postcode":"1202",
    "sg:province":"Gen\u00e8ve",
    "wof:name":"Leu Boutique, Inh. Helen Oesch-leu",
    "wof:placetype":"venue"
},
  "geometry": {"coordinates":[9.376404,47.426174],"type":"Point"}
}