{
  "type": "Feature",
  "properties": {
    "iso:country":"CH",
    "sg:address":"Dorfstrasse 10 8404 Stadel(winterthur). Postfach 3347",
    "sg:city":"Stadel(winterthur)",
    "sg:orig_category":"Bauschreinerei Herstellung von Konstruktionsteilen, Fertigbauteilen U Ausbauelementen aus Holz",
    "sg:phone":"+41 52 242 13 50",
    "sg:postcode":"8404",
    "sg:province":"Z\u00fcrich",
    "wof:name":"Braun Bruno",
    "wof:placetype":"venue"
},
  "geometry": {"coordinates":[8.758223,47.506569],"type":"Point"}
}