{
  "type": "Feature",
  "properties": {
    "iso:country":"CH",
    "sg:address":"Oberl\u00e4nderstrasse 35",
    "sg:city":"Muttenz",
    "sg:orig_category":"Herstellung von sonstigen Produkten aus nichtmetallischen Mineralien",
    "sg:postcode":"4132",
    "sg:province":"Basel-Landschaft",
    "wof:name":"Insulflex Ag",
    "wof:placetype":"venue"
},
  "geometry": {"coordinates":[7.8714570999,47.3417015076],"type":"Point"}
}