{
  "type": "Feature",
  "properties": {
    "iso:country":"CH",
    "sg:address":"Rosenbergh\u00f6he 4",
    "sg:city":"Luzern",
    "sg:orig_category":"Architekturb\u00fcros",
    "sg:phone":"+41 41 420 92 52",
    "sg:postcode":"6004",
    "sg:province":"Luzern",
    "wof:name":"Hans-peter Rey Dipl. Architekt Eth/sia",
    "wof:placetype":"venue"
},
  "geometry": {"coordinates":[8.305451,47.061169],"type":"Point"}
}