{
  "type": "Feature",
  "properties": {
    "iso:country":"CH",
    "sg:address":"Chemin Nicolas-junker 5",
    "sg:city":"Moutier",
    "sg:orig_category":"Herstellung von Schrauben, Nieten, Ketten U Federn Mechanische Werkst\u00e4tten",
    "sg:phone":"+41 32 493 29 91",
    "sg:postcode":"2740",
    "sg:province":"Bern",
    "wof:name":"Daniel Stalder Sa Atelier De D\u00e9colletage",
    "wof:placetype":"venue"
},
  "geometry": {"coordinates":[7.3618650436,47.272151947],"type":"Point"}
}