{
  "type": "Feature",
  "properties": {
    "iso:country":"CH",
    "sg:address":"Freudenberg",
    "sg:city":"Stettfurt",
    "sg:classifiers":[
        {
            "category":"Restaurant",
            "type":"Food & Drink"
        }
    ],
    "sg:phone":"+41 71 966 24 04",
    "sg:postcode":"9507",
    "sg:province":"Thurgau",
    "wof:name":"Restaurant Freudenberg",
    "wof:placetype":"venue"
},
  "geometry": {"coordinates":[8.9804754257,47.4736633301],"type":"Point"}
}