{
  "type": "Feature",
  "properties": {
    "iso:country":"CH",
    "sg:address":"Schaffhauserstrasse 102",
    "sg:city":"Z\u00fcrich",
    "sg:orig_category":"Non-Classified Establishments",
    "sg:postcode":"8057",
    "sg:province":"Z\u00fcrich",
    "wof:name":"Standartz Productions O.f.ph. Frey",
    "wof:placetype":"venue"
},
  "geometry": {"coordinates":[8.5400066376,47.3950157166],"type":"Point"}
}