{
  "type": "Feature",
  "properties": {
    "iso:country":"CH",
    "sg:address":"Q 8408 Winterthur. Postfach 226",
    "sg:city":"Winterthur",
    "sg:orig_category":"Offsetdruck Verlagsgewerbe",
    "sg:phone":"+41 22 918 08 50",
    "sg:postcode":"8408",
    "sg:province":"Z\u00fcrich",
    "wof:name":"Unitexte Sa Imprimerie",
    "wof:placetype":"venue"
},
  "geometry": {"coordinates":[6.1352438927,46.2122764587],"type":"Point"}
}