{
  "type": "Feature",
  "properties": {
    "iso:country":"CH",
    "sg:address":"Ringstrasse 25",
    "sg:city":"Regensdorf",
    "sg:orig_category":"G\u00fcterbef\u00f6rderung im Strassenverkehr",
    "sg:phone":"+41 18411241",
    "sg:postcode":"8105",
    "sg:province":"Z\u00fcrich",
    "wof:name":"M\u00fcller Roland Transporte",
    "wof:placetype":"venue"
},
  "geometry": {"coordinates":[8.4710550308,47.4362983704],"type":"Point"}
}