{
  "type": "Feature",
  "properties": {
    "iso:country":"CH",
    "sg:address":"Bachstrasse 41",
    "sg:city":"Obfelden",
    "sg:orig_category":"Herstellung von Mess U Kontrollinstrumenten U vorrichtungen Mechanische Werkst\u00e4tten",
    "sg:phone":"+41 17616450",
    "sg:postcode":"8912",
    "sg:province":"Z\u00fcrich",
    "wof:name":"Schoch Engineering Ag",
    "wof:placetype":"venue"
},
  "geometry": {"coordinates":[8.4219732285,47.2680130005],"type":"Point"}
}