{
  "type": "Feature",
  "properties": {
    "iso:country":"CH",
    "sg:address":"Menzbergstrasse 9 6130 Willisau. Postfach",
    "sg:city":"Willisau",
    "sg:orig_category":"Architektur U Ingenieurb\u00fcros Architekturb\u00fcros",
    "sg:phone":"+41 41 871 22 15",
    "sg:postcode":"6130",
    "sg:province":"Luzern",
    "wof:name":"Cas, Chappuis Aregger Sol\u00e8r Ag, Dipl. Architekten Eth Htl, Zweigniederlassung Altdorf",
    "wof:placetype":"venue"
},
  "geometry": {"coordinates":[8.638051,46.883484],"type":"Point"}
}