{
  "type": "Feature",
  "properties": {
    "iso:country":"CH",
    "sg:address":"Route De Mon-id\u00e9e 51",
    "sg:city":"Th\u00f4nex",
    "sg:orig_category":"Detailhandel mit Waren verschiedener Art, Hauptrichtung Nahrungsmittel",
    "sg:phone":"+41 22 349 25 77",
    "sg:postcode":"1226",
    "sg:province":"Gen\u00e8ve",
    "wof:name":"Allimentation Notaro Denner Satellite",
    "wof:placetype":"venue"
},
  "geometry": {"coordinates":[6.2184019089,46.206867218],"type":"Point"}
}