{
  "type": "Feature",
  "properties": {
    "addr:full":"Route De Lausanne 3 Penthalaz Vaud 1305",
    "addr:housenumber":"3",
    "addr:postcode":"1305",
    "addr:street":"Route De Lausanne",
    "iso:country":"CH",
    "sg:address":"Route De Lausanne 3",
    "sg:city":"Penthalaz",
    "sg:classifiers":[
        {
            "category":"Bars & Pubs",
            "type":"Food & Drink"
        }
    ],
    "sg:phone":"+41 21 861 10 72",
    "sg:postcode":"1305",
    "sg:province":"Vaud",
    "wof:name":"Favre St\u00e9phane",
    "wof:placetype":"venue"
},
  "geometry": {"coordinates":[6.528642,46.604599],"type":"Point"}
}