{
  "type": "Feature",
  "properties": {
    "addr:full":"Kasinostrasse 30 Aarau Aargau 5000",
    "addr:housenumber":"30",
    "addr:postcode":"5000",
    "addr:street":"Kasinostrasse",
    "iso:country":"CH",
    "sg:address":"Kasinostrasse 30",
    "sg:city":"Aarau",
    "sg:orig_category":"Detailhandel mit Brot, Back U S\u00fcsswaren",
    "sg:phone":"+41 62 824 50 60",
    "sg:postcode":"5000",
    "sg:province":"Aargau",
    "wof:name":"Landbeck Ag",
    "wof:placetype":"venue"
},
  "geometry": {"coordinates":[8.046836,47.391975],"type":"Point"}
}