{
  "type": "Feature",
  "properties": {
    "iso:country":"CH",
    "sg:address":"Boulevard De Saint-georges 60",
    "sg:city":"Gen\u00e8ve",
    "sg:orig_category":"Detailhandel mit Radio U Fernsehger\u00e4ten Detailhandel mit elektrischen Haushalts-,Radio U Fernsehger\u00e4",
    "sg:phone":"+41 21 845 57 06",
    "sg:postcode":"1205",
    "sg:province":"Gen\u00e8ve",
    "wof:name":"Audemars Claude",
    "wof:placetype":"venue"
},
  "geometry": {"coordinates":[6.2120537758,46.582359314],"type":"Point"}
}