{
  "type": "Feature",
  "properties": {
    "iso:country":"CH",
    "sg:address":"Meikirchstrasse 3 3042 Ortschwaben. Postfach",
    "sg:city":"Ortschwaben",
    "sg:orig_category":"Wirtschaftspr\u00fcfung, Steuerberatung U Treuhand",
    "sg:postcode":"3042",
    "sg:province":"Bern",
    "wof:name":"Mz Office Zimmerling Monika",
    "wof:placetype":"venue"
},
  "geometry": {"coordinates":[7.3982467651,46.9912147522],"type":"Point"}
}