{
  "type": "Feature",
  "properties": {
    "iso:country":"CH",
    "sg:address":"Thunstrasse 20",
    "sg:city":"Bern",
    "sg:classifiers":[
        {
            "category":"Professional",
            "subcategory":"Advertising",
            "type":"Services"
        }
    ],
    "sg:phone":"+41 31 964 44 44",
    "sg:postcode":"3005",
    "sg:province":"Bern",
    "sg:tags":[
        "agency"
    ],
    "wof:name":"Panache Ag",
    "wof:placetype":"venue"
},
  "geometry": {"coordinates":[7.453472,46.942154],"type":"Point"}
}