{
  "type": "Feature",
  "properties": {
    "addr:full":"Ancien-battoir Croy Vaud 1322",
    "addr:postcode":"1322",
    "addr:street":"Croy",
    "iso:country":"CH",
    "sg:address":"Ancien-battoir",
    "sg:city":"Croy",
    "sg:orig_category":"Allgemeiner Hoch U Tiefbau Erdbewegungsarbeiten",
    "sg:phone":"+41 79 401 35 00",
    "sg:postcode":"1322",
    "sg:province":"Vaud",
    "wof:name":"Ami Berthoud Sa",
    "wof:placetype":"venue"
},
  "geometry": {"coordinates":[6.476411,46.695667],"type":"Point"}
}