{
  "type": "Feature",
  "properties": {
    "iso:country":"CH",
    "sg:address":"Rue De Rive 21",
    "sg:city":"Nyon",
    "sg:orig_category":"Kunsthandel Museen",
    "sg:phone":"+41 22 300 17 43",
    "sg:postcode":"1260",
    "sg:province":"Vaud",
    "wof:name":"Galerie Saint-victor Sa",
    "wof:placetype":"venue"
},
  "geometry": {"coordinates":[6.1405282021,46.1846656799],"type":"Point"}
}