{
  "type": "Feature",
  "properties": {
    "iso:country":"CH",
    "sg:address":"St\u00e4gbachweg 9 6283 Baldegg. Postfach",
    "sg:city":"Baldegg",
    "sg:orig_category":"Detailhandel mit M\u00f6beln U Haushaltsgegenst\u00e4nden",
    "sg:phone":"+41 41 910 44 30",
    "sg:postcode":"6283",
    "sg:province":"Luzern",
    "wof:name":"Mobex Ag Baldegg",
    "wof:placetype":"venue"
},
  "geometry": {"coordinates":[8.2800922394,47.1839942932],"type":"Point"}
}