{
  "type": "Feature",
  "properties": {
    "iso:country":"CH",
    "sg:address":"Aubrigstrasse 3",
    "sg:city":"Horgen",
    "sg:orig_category":"Vereine Fasnacht",
    "sg:phone":"+41 17250041",
    "sg:postcode":"8810",
    "sg:province":"Z\u00fcrich",
    "wof:name":"Fasnachtsges.plattenhofzunft",
    "wof:placetype":"venue"
},
  "geometry": {"coordinates":[8.5908699036,47.2611312866],"type":"Point"}
}