{
  "type": "Feature",
  "properties": {
    "iso:country":"CH",
    "sg:address":"Via Giacometti 1",
    "sg:city":"Lugano",
    "sg:orig_category":"Architekturb\u00fcros",
    "sg:phone":"+41 91 923 59 79",
    "sg:postcode":"6900",
    "sg:province":"Ticino",
    "wof:name":"Gian Giuseppe Enderlin Studio D'architettura",
    "wof:placetype":"venue"
},
  "geometry": {"coordinates":[8.955469,46.007412],"type":"Point"}
}