{
  "type": "Feature",
  "properties": {
    "iso:country":"CH",
    "sg:address":"Chemin Des Meules 7",
    "sg:city":"Mont-sur-lausanne",
    "sg:orig_category":"Bauschreinerei Herstellung von K\u00fcchenm\u00f6beln",
    "sg:phone":"+41 21 657 14 82",
    "sg:postcode":"1052",
    "sg:province":"Vaud",
    "wof:name":"Espace Bois Menuiserie S\u00e0rl",
    "wof:placetype":"venue"
},
  "geometry": {"coordinates":[6.640886,46.562847],"type":"Point"}
}