{
  "type": "Feature",
  "properties": {
    "iso:country":"CH",
    "sg:address":"Vogelsangstrasse 27",
    "sg:city":"Z\u00fcrich",
    "sg:orig_category":"Grosshandel mit Nahrungsmitteln, Getr\u00e4nken U Tabakwaren",
    "sg:phone":"+41 13644500",
    "sg:postcode":"8006",
    "sg:province":"Z\u00fcrich",
    "wof:name":"Konstantinos Spiroudis Import & Export",
    "wof:placetype":"venue"
},
  "geometry": {"coordinates":[8.5492973328,47.3828010559],"type":"Point"}
}