{
  "type": "Feature",
  "properties": {
    "addr:full":"6213 Knutwil Luzern 6213",
    "addr:postcode":"6213;6213",
    "iso:country":"CH",
    "sg:address":"6213",
    "sg:city":"Knutwil",
    "sg:orig_category":"Bauschreinerei Grosshandel mit Holz U Bauelementen aus Holz",
    "sg:phone":"+41 41 921 11 24",
    "sg:postcode":"6213",
    "sg:province":"Luzern",
    "wof:name":"Hodel Mobile Trennwandsysteme Schreinerei",
    "wof:placetype":"venue"
},
  "geometry": {"coordinates":[8.072375,47.199112],"type":"Point"}
}