{
  "type": "Feature",
  "properties": {
    "iso:country":"CH",
    "sg:address":"Route De Montsevelier",
    "sg:city":"Mervelier",
    "sg:orig_category":"Mechanische Werkst\u00e4tten",
    "sg:phone":"+41 32 438 81 15",
    "sg:postcode":"2827",
    "sg:province":"Bern",
    "wof:name":"R\u00e9my Kottelat Atelier M\u00e9canique",
    "wof:placetype":"venue"
},
  "geometry": {"coordinates":[7.5004029274,47.3450546265],"type":"Point"}
}