{
  "type": "Feature",
  "properties": {
    "iso:country":"CH",
    "sg:address":"Clarastrasse 56 4058 Basel. Postfach",
    "sg:city":"Basel",
    "sg:orig_category":"Fachdetailhandel mit pharmazeutischen Produkten Grosshandel mit pharmazeutischen Erzeugnissen",
    "sg:phone":"+41 61 693 11 22",
    "sg:postcode":"4058",
    "sg:province":"Basel-Stadt",
    "wof:name":"Alwer Pharma Ag Arzneimittel; Grosshandel Usw",
    "wof:placetype":"venue"
},
  "geometry": {"coordinates":[7.5986618996,47.5632247925],"type":"Point"}
}