{
  "type": "Feature",
  "properties": {
    "iso:country":"CH",
    "sg:address":"Rue Centrale 91 2500 Biel/bienne. Postfach",
    "sg:city":"Biel/bienne",
    "sg:orig_category":"RESTAURANTS: TEA-ROOMS",
    "sg:postcode":"2502",
    "sg:province":"Bern",
    "wof:name":"Giglio Spampinato Filippo Et Madeleine",
    "wof:placetype":"venue"
},
  "geometry": {"coordinates":[7.249560833,47.1342544556],"type":"Point"}
}