{
  "type": "Feature",
  "properties": {
    "iso:country":"CH",
    "sg:address":"Rue De L'industrie 21",
    "sg:city":"Del\u00e9mont",
    "sg:orig_category":"Chemische Reinigung W\u00e4schereien",
    "sg:phone":"+41 32 841 16 15",
    "sg:postcode":"2800",
    "sg:province":"Jura",
    "wof:name":"Blanchisserie Jenni Succ.ir\u00e9n\u00e9e Pasquier",
    "wof:placetype":"venue"
},
  "geometry": {"coordinates":[6.860592,46.966118],"type":"Point"}
}