{
  "type": "Feature",
  "properties": {
    "iso:country":"CH",
    "sg:address":"Avenue De La Gare",
    "sg:city":"Montana-vermala",
    "sg:orig_category":"Detailhandel mit Damenbekleidung Detailhandel mit Herrenbekleidung",
    "sg:phone":"+41 27 481 25 30",
    "sg:postcode":"3962",
    "wof:name":"Marianne Bonvin Boutique Scooter",
    "wof:placetype":"venue"
},
  "geometry": {"coordinates":[7.483520031,46.3125],"type":"Point"}
}