{
  "type": "Feature",
  "properties": {
    "iso:country":"CH",
    "sg:address":"Les Vuattes",
    "sg:city":"Crassier",
    "sg:orig_category":"Grosshandel mit Blumen U Pflanzen",
    "sg:postcode":"1263",
    "sg:province":"Vaud",
    "wof:name":"Delta 9 S\u00e0rl",
    "wof:placetype":"venue"
},
  "geometry": {"coordinates":[6.1315588951,46.1918029785],"type":"Point"}
}