{
  "type": "Feature",
  "properties": {
    "iso:country":"CH",
    "sg:address":"Brandschenkestrasse 167",
    "sg:city":"Z\u00fcrich",
    "sg:orig_category":"Installation von Heizungs, L\u00fcftungs U Klimaanlagen",
    "sg:phone":"+41 12029218",
    "sg:postcode":"8002",
    "sg:province":"Z\u00fcrich",
    "wof:name":"Airmont Gmbh. Montage V. Klima- U. Bel\u00fcftungsanlagen.",
    "wof:placetype":"venue"
},
  "geometry": {"coordinates":[8.5268507004,47.3637123108],"type":"Point"}
}