{
  "type": "Feature",
  "properties": {
    "iso:country":"CH",
    "sg:address":"Bundesstrasse 15",
    "sg:city":"Zug",
    "sg:classifiers":[
        {
            "category":"Banks & Credit Unions",
            "subcategory":"Bank",
            "type":"Services"
        }
    ],
    "sg:postcode":"6300",
    "sg:province":"Zug",
    "wof:name":"C & C Holding Sa",
    "wof:placetype":"venue"
},
  "geometry": {"coordinates":[7.139192,46.811642],"type":"Point"}
}