{
  "type": "Feature",
  "properties": {
    "addr:full":"Steinackerstrasse 2 Glattbrugg Z\u00fcrich 8152",
    "addr:housenumber":"2",
    "addr:postcode":"8152",
    "addr:street":"Steinackerstrasse",
    "iso:country":"CH",
    "sg:address":"Steinackerstrasse 2",
    "sg:city":"Glattbrugg",
    "sg:orig_category":"Architektur U Ingenieurb\u00fcros",
    "sg:phone":"+41 19971727",
    "sg:postcode":"8152",
    "sg:province":"Z\u00fcrich",
    "wof:name":"Innotronic Ingenieurb\u00fcro Markus Meier",
    "wof:placetype":"venue"
},
  "geometry": {"coordinates":[8.565892,47.429085],"type":"Point"}
}