{
  "type": "Feature",
  "properties": {
    "iso:country":"CH",
    "sg:address":"Ausserdorf 236",
    "sg:city":"Hallau",
    "sg:classifiers":[
        {
            "category":"Bars & Pubs",
            "type":"Food & Drink"
        }
    ],
    "sg:phone":"+41 52 681 33 19",
    "sg:postcode":"8215",
    "sg:province":"Schaffhausen",
    "wof:name":"Bar Krug",
    "wof:placetype":"venue"
},
  "geometry": {"coordinates":[8.462385,47.697384],"type":"Point"}
}