{
  "type": "Feature",
  "properties": {
    "iso:country":"CH",
    "sg:address":"Via Tinelle 4",
    "sg:city":"Pedrinate",
    "sg:orig_category":"Non-Classified Establishments",
    "sg:postcode":"6832",
    "sg:province":"Ticino",
    "wof:name":"Alfredo Bossert",
    "wof:placetype":"venue"
},
  "geometry": {"coordinates":[9.0131673813,45.8255844116],"type":"Point"}
}