{
  "type": "Feature",
  "properties": {
    "iso:country":"CH",
    "sg:address":"Burstwiesenstrasse 58 8055 Z\u00fcrich. Postfach",
    "sg:city":"Z\u00fcrich",
    "sg:orig_category":"Detailhandel mit Teppichen Verlegen von Fussboden",
    "sg:phone":"+41 14613420",
    "sg:postcode":"8055",
    "sg:province":"Z\u00fcrich",
    "wof:name":"Aldo Ravaioli Teppiche & Bodenbel\u00e4ge",
    "wof:placetype":"venue"
},
  "geometry": {"coordinates":[8.5040082932,47.3701934814],"type":"Point"}
}