{
  "type": "Feature",
  "properties": {
    "addr:full":"M\u00fchlegasse 22 Burgdorf Bern 3400",
    "addr:housenumber":"22",
    "addr:postcode":"3400",
    "addr:street":"Muehlegasse",
    "iso:country":"CH",
    "sg:address":"M\u00fchlegasse 22",
    "sg:city":"Burgdorf",
    "sg:orig_category":"Architektur U Ingenieurb\u00fcros",
    "sg:phone":"+41 34 422 39 66",
    "sg:postcode":"3400",
    "sg:province":"Bern",
    "wof:name":"Kaufmann Architekten Ag",
    "wof:placetype":"venue"
},
  "geometry": {"coordinates":[7.625807,47.058117],"type":"Point"}
}