{
  "type": "Feature",
  "properties": {
    "addr:full":"Untertal Walchwil Zug 6318",
    "addr:postcode":"6318",
    "addr:street":"Untertal;Zug",
    "iso:country":"CH",
    "sg:address":"Untertal",
    "sg:city":"Walchwil",
    "sg:orig_category":"Bauschreinerei Herstellung von Konstruktionsteilen, Fertigbauteilen U Ausbauelementen aus Holz",
    "sg:phone":"+41 41 758 26 79",
    "sg:postcode":"6318",
    "sg:province":"Zug",
    "wof:name":"Roth P. Holzbau",
    "wof:placetype":"venue"
},
  "geometry": {"coordinates":[8.508564,47.117516],"type":"Point"}
}