{
  "type": "Feature",
  "properties": {
    "iso:country":"CH",
    "sg:address":"3533",
    "sg:city":"Bowil",
    "sg:orig_category":"Wasserversorgung",
    "sg:phone":"+41 31 711 01 46",
    "sg:postcode":"3533",
    "sg:province":"Bern",
    "wof:name":"Wasserversorgung Der Gemeinde Bowil",
    "wof:placetype":"venue"
},
  "geometry": {"coordinates":[7.694881916,46.8934135437],"type":"Point"}
}