{
  "type": "Feature",
  "properties": {
    "iso:country":"CH",
    "sg:address":"2882",
    "sg:city":"St-ursanne",
    "sg:orig_category":"Grosshandel mit pharmazeutischen Erzeugnissen, medizinischen U orthop\u00e4dischen Artikeln",
    "sg:phone":"+41 32 461 35 85",
    "sg:postcode":"2882",
    "sg:province":"Jura",
    "wof:name":"Iseli Rosanne",
    "wof:placetype":"venue"
},
  "geometry": {"coordinates":[7.1536798477,47.3645629883],"type":"Point"}
}