{
  "type": "Feature",
  "properties": {
    "iso:country":"CH",
    "sg:address":"M\u00fchlematt 17",
    "sg:city":"Emmenbr\u00fccke",
    "sg:orig_category":"D\u00e4mmung gegen K\u00e4lte, W\u00e4rme, Schall U Ersch\u00fctterung",
    "sg:phone":"+41 41 280 60 36",
    "sg:postcode":"6020",
    "sg:province":"Luzern",
    "wof:name":"Walter Ineichen Isolierungen",
    "wof:placetype":"venue"
},
  "geometry": {"coordinates":[8.2720069885,47.0884017944],"type":"Point"}
}