{
  "type": "Feature",
  "properties": {
    "iso:country":"CH",
    "sg:address":"Mooshaldenstrasse 24",
    "sg:city":"M\u00e4nnedorf",
    "sg:orig_category":"Fotografische Ateliers",
    "sg:phone":"+41 19201940",
    "sg:postcode":"8708",
    "sg:province":"Z\u00fcrich",
    "wof:name":"Birgit Hemmi Fotografisches Atelier",
    "wof:placetype":"venue"
},
  "geometry": {"coordinates":[8.7037448883,47.2502746582],"type":"Point"}
}