{
  "type": "Feature",
  "properties": {
    "iso:country":"CH",
    "sg:address":"Hauptstrasse 51",
    "sg:city":"M\u00fcnchenstein",
    "sg:orig_category":"Erbringung von Dienstleistungen f\u00fcr Unternehmen Innendekorationsateliers",
    "sg:phone":"+41 61 411 35 26",
    "sg:postcode":"4142",
    "sg:province":"Basel-Landschaft",
    "wof:name":"Wohndekor Forlin Marco Und V\u00f6gtli Ren\u00e9",
    "wof:placetype":"venue"
},
  "geometry": {"coordinates":[7.6210517883,47.5104789734],"type":"Point"}
}