{
  "type": "Feature",
  "properties": {
    "iso:country":"CH",
    "sg:address":"Allmend 4",
    "sg:city":"Rottenschwil",
    "sg:orig_category":"Herstellung von sonstigen Maschinen f\u00fcr bestimmte Verwendung",
    "sg:postcode":"8919",
    "sg:province":"Aargau",
    "wof:name":"Weckerle Cosmetics Sa",
    "wof:placetype":"venue"
},
  "geometry": {"coordinates":[6.7467451096,47.056476593],"type":"Point"}
}