{
  "type": "Feature",
  "properties": {
    "iso:country":"CH",
    "sg:address":"Ifangstrasse 52",
    "sg:city":"R\u00fcmlang",
    "sg:orig_category":"Vereine Vogel-& Naturschutz",
    "sg:phone":"+41 79 454 45 21",
    "sg:postcode":"8153",
    "sg:province":"Z\u00fcrich",
    "wof:name":"Ornithologischer Verein",
    "wof:placetype":"venue"
},
  "geometry": {"coordinates":[7.6810369492,46.6101570129],"type":"Point"}
}