{
  "type": "Feature",
  "properties": {
    "iso:country":"CH",
    "sg:address":"K\u00f6nizstrasse 194 3097 Liebefeld. Postfach",
    "sg:city":"Liebefeld",
    "sg:orig_category":"Unclassifiable Establishments",
    "sg:postcode":"3097",
    "sg:province":"Bern",
    "wof:name":"Wsg-innenausbau Ges.m.b.h., Rangersdorf, Zweigniederlassung St. Moritz",
    "wof:placetype":"venue"
},
  "geometry": {"coordinates":[9.8381910324,46.4970664978],"type":"Point"}
}