{
  "type": "Feature",
  "properties": {
    "iso:country":"CH",
    "sg:address":"Bernstrasse 135",
    "sg:city":"Zollikofen",
    "sg:orig_category":"Interessenvertretungen",
    "sg:postcode":"3052",
    "sg:province":"Bern",
    "wof:name":"Schweizerische Vereinigung F\u00fcr F\u00fchrungsausbildung Svf",
    "wof:placetype":"venue"
},
  "geometry": {"coordinates":[8.8218421936,47.2283248901],"type":"Point"}
}