{
  "type": "Feature",
  "properties": {
    "iso:country":"CH",
    "sg:address":"Sch\u00f6nb\u00fchlring 5",
    "sg:city":"Luzern",
    "sg:orig_category":"Fahrschulen, Flugschulen",
    "sg:phone":"+41 41 360 27 54",
    "sg:postcode":"6005",
    "sg:province":"Luzern",
    "wof:name":"Josef Grob Autofahrschule",
    "wof:placetype":"venue"
},
  "geometry": {"coordinates":[8.3260250092,47.0384902954],"type":"Point"}
}