{
  "type": "Feature",
  "properties": {
    "iso:country":"CH",
    "sg:address":"Spielhofweg 12",
    "sg:city":"Oberrieden",
    "sg:orig_category":"Aktivit\u00e4ten der Krankenschwestern U Hebammen, Hauspflege Organisationen des Gesundheitswesen",
    "sg:phone":"+41 17201182",
    "sg:postcode":"8942",
    "sg:province":"Z\u00fcrich",
    "wof:name":"Spitex,haus-& Krankenpflege- Verein Oberrieden",
    "wof:placetype":"venue"
},
  "geometry": {"coordinates":[8.574383,47.277958],"type":"Point"}
}