{
  "type": "Feature",
  "properties": {
    "iso:country":"CH",
    "sg:address":"5423",
    "sg:city":"Freienwil",
    "sg:orig_category":"Schulpflegen",
    "sg:phone":"+41 56 222 35 40",
    "sg:postcode":"5423",
    "sg:province":"Aargau",
    "wof:name":"Primarschulpflege Der Gemeinde Freienwil",
    "wof:placetype":"venue"
},
  "geometry": {"coordinates":[8.314209938,47.4982414246],"type":"Point"}
}