{
  "type": "Feature",
  "properties": {
    "iso:country":"CH",
    "sg:address":"Adlergasse 10",
    "sg:city":"Feuerthalen",
    "sg:orig_category":"Detailhandel mit Brot, Back U S\u00fcsswaren",
    "sg:phone":"+41 52 659 39 04",
    "sg:postcode":"8245",
    "sg:province":"Z\u00fcrich",
    "wof:name":"Georg Gisler B\u00e4ckerei",
    "wof:placetype":"venue"
},
  "geometry": {"coordinates":[8.640919,47.693218],"type":"Point"}
}