{
  "type": "Feature",
  "properties": {
    "iso:country":"CH",
    "sg:address":"R\u00fcmikerstrasse",
    "sg:city":"R\u00e4terschen",
    "sg:orig_category":"Grosshandel mit sonstigen Maschinen U Ausr\u00fcstungen f\u00fcr Industrie, Handel U Schiffahrt",
    "sg:postcode":"8352",
    "sg:province":"Z\u00fcrich",
    "wof:name":"Elmag",
    "wof:placetype":"venue"
},
  "geometry": {"coordinates":[8.7831258774,47.5043525696],"type":"Point"}
}