{
  "type": "Feature",
  "properties": {
    "iso:country":"CH",
    "sg:address":"Dorfstrasse 16",
    "sg:city":"Gansingen",
    "sg:orig_category":"Herstellung von k\u00e4lte U lufttechnischen Erzeugnissen f\u00fcr gewerbliche Zwecke Kaminfeger",
    "sg:phone":"+41 62 875 31 15",
    "sg:postcode":"5272",
    "sg:province":"Aargau",
    "wof:name":"Kilian Jegen, Kaminfegergesch\u00e4ft",
    "wof:placetype":"venue"
},
  "geometry": {"coordinates":[8.1333799362,47.5437316895],"type":"Point"}
}