{
  "type": "Feature",
  "properties": {
    "iso:country":"CH",
    "sg:address":"Im Knebel 4",
    "sg:city":"Mannenbach-salenst",
    "sg:orig_category":"Elektroinstallation",
    "sg:phone":"+41 71 664 10 08",
    "sg:postcode":"8268",
    "sg:province":"Thurgau",
    "wof:name":"Fehr Heinz",
    "wof:placetype":"venue"
},
  "geometry": {"coordinates":[9.0510101318,47.6720275879],"type":"Point"}
}