{
  "type": "Feature",
  "properties": {
    "iso:country":"CH",
    "sg:address":"Ziegelstrasse 7",
    "sg:city":"Basel",
    "sg:orig_category":"Non-Classified Establishments",
    "sg:postcode":"4055",
    "sg:province":"Basel-Stadt",
    "wof:name":"Polat",
    "wof:placetype":"venue"
},
  "geometry": {"coordinates":[7.5635299683,47.5655784607],"type":"Point"}
}