{
  "type": "Feature",
  "properties": {
    "iso:country":"CH",
    "sg:address":"Wahlackerstrasse 3",
    "sg:city":"Zollikofen",
    "sg:orig_category":"Vermittlung von Immobilien Verwaltung von Immobilien",
    "sg:phone":"+41 71 912 26 12",
    "sg:postcode":"3052",
    "sg:province":"Bern",
    "wof:name":"Genossenschaft Des Gewerbes Gdg",
    "wof:placetype":"venue"
},
  "geometry": {"coordinates":[9.0686321259,47.4653205872],"type":"Point"}
}