{
  "type": "Feature",
  "properties": {
    "iso:country":"CH",
    "sg:address":"2572",
    "sg:city":"Sutz",
    "sg:orig_category":"Gewinnung von Kies U Sand",
    "sg:phone":"+41 32 397 00 30",
    "sg:postcode":"2572",
    "sg:province":"Bern",
    "wof:name":"Hurni Kies Und Betonwerk Ag",
    "wof:placetype":"venue"
},
  "geometry": {"coordinates":[7.2185702324,47.1009101868],"type":"Point"}
}