{
  "type": "Feature",
  "properties": {
    "iso:country":"CH",
    "sg:address":"Bahnhofstr. Pf 236",
    "sg:city":"Netstal",
    "sg:classifiers":[
        {
            "category":"Communications",
            "subcategory":"Newspaper",
            "type":"Services"
        }
    ],
    "sg:phone":"+41 55 646 26 26",
    "sg:postcode":"8754",
    "sg:province":"Glarus",
    "sg:tags":[
        "material",
        "-",
        "packaging",
        "raw",
        "paper",
        "cardboard"
    ],
    "wof:name":"Tschudi & Cie Ag / Feinpappen",
    "wof:placetype":"venue"
},
  "geometry": {"coordinates":[9.057393074,47.0656394958],"type":"Point"}
}