{
  "type": "Feature",
  "properties": {
    "iso:country":"CH",
    "sg:address":"Webergasse 151",
    "sg:city":"Schupfart",
    "sg:orig_category":"Organisationen des Gesundheitswesen",
    "sg:postcode":"4325",
    "sg:province":"Aargau",
    "wof:name":"Samariterverein Schupfart",
    "wof:placetype":"venue"
},
  "geometry": {"coordinates":[7.9622840881,47.5134773254],"type":"Point"}
}