{
  "type": "Feature",
  "properties": {
    "iso:country":"CH",
    "sg:address":"Besmerstrasse 22 8280 Kreuzlingen. Postfach 78",
    "sg:city":"Kreuzlingen",
    "sg:orig_category":"Institutionen f\u00fcr Behinderte Wohnheime",
    "sg:phone":"+41 71 688 77 38",
    "sg:postcode":"8280",
    "sg:province":"Thurgau",
    "wof:name":"Besmerhuus Wohn-& Werkheim F\u00fcr Behinderte",
    "wof:placetype":"venue"
},
  "geometry": {"coordinates":[9.1860866547,47.6410102844],"type":"Point"}
}