{
  "type": "Feature",
  "properties": {
    "iso:country":"CH",
    "sg:address":"5424",
    "sg:city":"Unterehrendingen",
    "sg:orig_category":"Schulpflegen",
    "sg:postcode":"5424",
    "wof:name":"Primarschulpflege Der Gemeinde Unterehrendingen",
    "wof:placetype":"venue"
},
  "geometry": {"coordinates":[8.3552303314,47.4961013794],"type":"Point"}
}