{
  "type": "Feature",
  "properties": {
    "iso:country":"CH",
    "sg:address":"R\u00fctistrasse 41",
    "sg:city":"Jona",
    "sg:orig_category":"Detailhandel mit M\u00f6beln U Haushaltsgegenst\u00e4nden Detailhandel mit Textilien",
    "sg:phone":"+41 55 211 94 80",
    "sg:postcode":"8645",
    "sg:province":"St. Gallen",
    "wof:name":"Format 41 Raumgestaltung",
    "wof:placetype":"venue"
},
  "geometry": {"coordinates":[8.8244695663,47.2393836975],"type":"Point"}
}