{
  "type": "Feature",
  "properties": {
    "iso:country":"CH",
    "sg:address":"Vordergasseasse 51",
    "sg:city":"Wermatswil",
    "sg:orig_category":"Vereine Z\u00fcnfte",
    "sg:postcode":"8615",
    "sg:province":"Z\u00fcrich",
    "wof:name":"Z\u00fcnfte Z.gerwe & Schuhmachern",
    "wof:placetype":"venue"
},
  "geometry": {"coordinates":[8.7467126846,47.3621635437],"type":"Point"}
}