{
  "type": "Feature",
  "properties": {
    "iso:country":"CH",
    "sg:address":"Erlenstrasse 4b",
    "sg:city":"Rotkreuz",
    "sg:orig_category":"Reiseb\u00fcros U Reiseveranstalter",
    "sg:postcode":"6343",
    "sg:province":"Zug",
    "wof:name":"Transaero Tours & Business Travel Ag",
    "wof:placetype":"venue"
},
  "geometry": {"coordinates":[8.430431366,47.1490135193],"type":"Point"}
}