{
  "type": "Feature",
  "properties": {
    "iso:country":"CH",
    "sg:address":"Waldheim 16",
    "sg:city":"Olten",
    "sg:orig_category":"Unternehmensberatung Wirtschaftspr\u00fcfung, Steuerberatung U Treuhand",
    "sg:phone":"+41 62 296 02 35",
    "sg:postcode":"4600",
    "sg:province":"Solothurn",
    "wof:name":"Oltenia Treuhand Gmbh",
    "wof:placetype":"venue"
},
  "geometry": {"coordinates":[7.9202198982,47.3508911133],"type":"Point"}
}