{
  "type": "Feature",
  "properties": {
    "iso:country":"CH",
    "sg:address":"Birmensdorferstrasse 427",
    "sg:city":"Z\u00fcrich",
    "sg:classifiers":[
        {
            "category":"Restaurant",
            "type":"Food & Drink"
        }
    ],
    "sg:phone":"+41 14620727",
    "sg:postcode":"8055",
    "sg:province":"Z\u00fcrich",
    "wof:name":"Restaurant Z. Blumenau",
    "wof:placetype":"venue"
},
  "geometry": {"coordinates":[8.5015497208,47.3687171936],"type":"Point"}
}