{
  "type": "Feature",
  "properties": {
    "iso:country":"CH",
    "sg:address":"Industriestrasse 4b 8604 Volketswil. Postfach 260",
    "sg:city":"Volketswil",
    "sg:orig_category":"Wirtschaftspr\u00fcfung, Steuerberatung U Treuhand",
    "sg:phone":"+41 19456289",
    "sg:postcode":"8604",
    "sg:province":"Z\u00fcrich",
    "wof:name":"Tresta-treuhand Ag",
    "wof:placetype":"venue"
},
  "geometry": {"coordinates":[8.6657476425,47.3822364807],"type":"Point"}
}