{
  "type": "Feature",
  "properties": {
    "iso:country":"CH",
    "sg:address":"Ifangstrasse 8 8952 Schlieren. Postfach",
    "sg:city":"Schlieren",
    "sg:orig_category":"Vermietung von Automobilen",
    "sg:phone":"+41 12428484",
    "sg:postcode":"8952",
    "sg:province":"Z\u00fcrich",
    "wof:name":"Hertz Ag",
    "wof:placetype":"venue"
},
  "geometry": {"coordinates":[8.4548492432,47.4007530212],"type":"Point"}
}