{
  "type": "Feature",
  "properties": {
    "addr:full":"Via Ludovico Ariosto 6 Lugano Ticino 6900",
    "addr:housenumber":"6",
    "addr:postcode":"6900",
    "addr:street":"Via Ludovico Ariosto",
    "iso:country":"CH",
    "sg:address":"Via Ludovico Ariosto 6",
    "sg:city":"Lugano",
    "sg:orig_category":"Advokaturb\u00fcros Notariate",
    "sg:phone":"+41 91 913 39 11",
    "sg:postcode":"6900",
    "sg:province":"Ticino",
    "wof:name":"Dott.theobald Brun Studio Legale & Notarile",
    "wof:placetype":"venue"
},
  "geometry": {"coordinates":[8.95091,46.005936],"type":"Point"}
}