{
  "type": "Feature",
  "properties": {
    "iso:country":"CH",
    "sg:address":"1462",
    "sg:city":"Yvonand",
    "sg:orig_category":"Unclassifiable Establishments",
    "sg:postcode":"1462",
    "sg:province":"Vaud",
    "wof:name":"Si Montchoisi Yvonand Sa",
    "wof:placetype":"venue"
},
  "geometry": {"coordinates":[6.7450752258,46.7997283936],"type":"Point"}
}