{
  "type": "Feature",
  "properties": {
    "iso:country":"CH",
    "sg:address":"1607",
    "sg:city":"Pal\u00e9zieux-gare",
    "sg:orig_category":"Mechanik",
    "sg:postcode":"1607",
    "sg:province":"Vaud",
    "wof:name":"Stucki Walter",
    "wof:placetype":"venue"
},
  "geometry": {"coordinates":[6.8379130363,46.5426216125],"type":"Point"}
}