{
  "type": "Feature",
  "properties": {
    "iso:country":"CH",
    "sg:address":"Risi 15",
    "sg:city":"N\u00e4fels",
    "sg:orig_category":"Sportvereine Flug Aero-Club",
    "sg:phone":"+41 55 640 20 38",
    "sg:postcode":"8752",
    "sg:province":"Glarus",
    "wof:name":"Ae.c.s.modellflugg.glarnerland",
    "wof:placetype":"venue"
},
  "geometry": {"coordinates":[9.0625753403,47.0999641418],"type":"Point"}
}