{
  "type": "Feature",
  "properties": {
    "iso:country":"CH",
    "sg:address":"Rue Du Milieu 47",
    "sg:city":"Yverdon-les-bains",
    "sg:classifiers":[
        {
            "category":"Restaurant",
            "type":"Food & Drink"
        }
    ],
    "sg:phone":"+41 24 425 27 63",
    "sg:postcode":"1400",
    "sg:province":"Vaud",
    "wof:name":"Caf\u00e9 Des Sports",
    "wof:placetype":"venue"
},
  "geometry": {"coordinates":[6.6379938126,46.779094696],"type":"Point"}
}