{
  "type": "Feature",
  "properties": {
    "iso:country":"CH",
    "sg:address":"1854",
    "sg:city":"Leysin",
    "sg:orig_category":"Interessenvertretungen",
    "sg:postcode":"1854",
    "sg:province":"Vaud",
    "wof:name":"Fondation Mocellin-rigazio Dominique",
    "wof:placetype":"venue"
},
  "geometry": {"coordinates":[7.0130829811,46.3435630798],"type":"Point"}
}