{
  "type": "Feature",
  "properties": {
    "iso:country":"CH",
    "sg:address":"Baumackerstrasse 9 8050 Z\u00fcrich",
    "sg:city":"Zust",
    "sg:orig_category":"Grosshandel mit Getr\u00e4nken",
    "sg:postcode":"50",
    "wof:name":"Neuenschwander R., Goutte D'or.",
    "wof:placetype":"venue"
},
  "geometry": {"coordinates":[7.4876909256,46.9300346375],"type":"Point"}
}