{
  "type": "Feature",
  "properties": {
    "addr:full":"Glattalstrasse 156 R\u00fcmlang Z\u00fcrich 8153",
    "addr:housenumber":"156",
    "addr:postcode":"8153",
    "addr:street":"Glattalstrasse;Zuerich",
    "iso:country":"CH",
    "sg:address":"Glattalstrasse 156",
    "sg:city":"R\u00fcmlang",
    "sg:orig_category":"Detailhandel mit Beleuchtungs U Haushaltsgegenst\u00e4nden Detailhandel mit elektrischen Haushalts-,Radio",
    "sg:phone":"+41 13444020",
    "sg:postcode":"8153",
    "sg:province":"Z\u00fcrich",
    "wof:name":"Nyffenegger & Partner Ag Kauf U. Verkauf Von Anlagen, Maschinen U. G\u00fctern In Den Bereichen Haushalt, Gewerbe, Industrie Usw",
    "wof:placetype":"venue"
},
  "geometry": {"coordinates":[8.527867,47.453335],"type":"Point"}
}