{
  "type": "Feature",
  "properties": {
    "addr:full":"Avenue De Florimont 11 Lausanne Vaud 1006",
    "addr:housenumber":"11",
    "addr:postcode":"1006",
    "addr:street":"Avenue De Florimont",
    "iso:country":"CH",
    "sg:address":"Avenue De Florimont 11",
    "sg:city":"Lausanne",
    "sg:orig_category":"Advokaturb\u00fcros",
    "sg:phone":"+41 21 320 78 22",
    "sg:postcode":"1006",
    "sg:province":"Vaud",
    "wof:name":"Jean-pierre Wiswald Etude D'avocat",
    "wof:placetype":"venue"
},
  "geometry": {"coordinates":[6.639023,46.515511],"type":"Point"}
}