{
  "type": "Feature",
  "properties": {
    "addr:full":"Bachwiesstrasse 9100 Herisau. Postfach Herisau Appenzell Ausserrhoden 9102",
    "addr:postcode":"9100 herisau. postfach;9102",
    "addr:street":"Bachwiesstrasse;Ausserrhoden",
    "iso:country":"CH",
    "sg:address":"Bachwiesstrasse 9100 Herisau. Postfach",
    "sg:city":"Herisau",
    "sg:orig_category":"Abwasserreinigung",
    "sg:phone":"+41 71 351 43 58",
    "sg:postcode":"9102",
    "sg:province":"Appenzell Ausserrhoden",
    "wof:name":"Abwasserreinigungsanlage",
    "wof:placetype":"venue"
},
  "geometry": {"coordinates":[9.267285,47.392937],"type":"Point"}
}