{
  "type": "Feature",
  "properties": {
    "addr:full":"Gen\u00e8ve Gen\u00e8ve Gen\u00e8ve 1211",
    "addr:postcode":"1211",
    "iso:country":"CH",
    "sg:address":"Gen\u00e8ve",
    "sg:city":"Gen\u00e8ve",
    "sg:classifiers":[
        {
            "category":"Banks & Credit Unions",
            "subcategory":"Bank",
            "type":"Services"
        }
    ],
    "sg:postcode":"1211",
    "sg:province":"Gen\u00e8ve",
    "wof:name":"Si Patac Sa",
    "wof:placetype":"venue"
},
  "geometry": {"coordinates":[6.142701,46.208359],"type":"Point"}
}