{
  "type": "Feature",
  "properties": {
    "iso:country":"CH",
    "sg:address":"Moos",
    "sg:city":"Matten(st.stephan)",
    "sg:orig_category":"Herstellung von sonstigen landwirtschaftlichen Maschinen",
    "sg:postcode":"3773",
    "sg:province":"Bern",
    "wof:name":"Werner Gr\u00fcnenwald",
    "wof:placetype":"venue"
},
  "geometry": {"coordinates":[7.4226021767,46.4971046448],"type":"Point"}
}