{
  "type": "Feature",
  "properties": {
    "iso:country":"CH",
    "sg:address":"Kantonsstrasse 13",
    "sg:city":"Visp",
    "sg:orig_category":"Betrieb von Taxis",
    "sg:postcode":"3930",
    "sg:province":"Valais",
    "wof:name":"Opahl Transport Ag",
    "wof:placetype":"venue"
},
  "geometry": {"coordinates":[7.88211,46.292332],"type":"Point"}
}