{
  "type": "Feature",
  "properties": {
    "iso:country":"CH",
    "sg:address":"Oberibergerstrasse 10",
    "sg:city":"Unteriberg",
    "sg:orig_category":"Non-Classified Establishments",
    "sg:postcode":"8842",
    "sg:province":"Schwyz",
    "wof:name":"Fuchs Motosport",
    "wof:placetype":"venue"
},
  "geometry": {"coordinates":[8.8009061813,47.0590705872],"type":"Point"}
}