{
  "type": "Feature",
  "properties": {
    "iso:country":"CH",
    "sg:address":"Neustrasse 44",
    "sg:city":"Romanshorn",
    "sg:orig_category":"Immobilienwesen",
    "sg:phone":"+41 51 220 36 96",
    "sg:postcode":"8590",
    "sg:province":"Thurgau",
    "wof:name":"Schweizerische Bundesbahnen - Liegenschaften",
    "wof:placetype":"venue"
},
  "geometry": {"coordinates":[7.4370012283,46.9479560852],"type":"Point"}
}