{
  "type": "Feature",
  "properties": {
    "iso:country":"CH",
    "sg:address":"1926",
    "sg:city":"Fully",
    "sg:orig_category":"RESTAURANTS: TEA-ROOMS",
    "sg:phone":"+41 26 652 14 43",
    "sg:postcode":"1926",
    "sg:province":"Valais",
    "wof:name":"Restaurant De L' Ecureuil",
    "wof:placetype":"venue"
},
  "geometry": {"coordinates":[6.9533801079,46.6943054199],"type":"Point"}
}