{
  "type": "Feature",
  "properties": {
    "iso:country":"CH",
    "sg:address":"Rue Des Sources 2",
    "sg:city":"Tavannes",
    "sg:orig_category":"Vorschulen, Kinderg\u00e4rten",
    "sg:phone":"+41 32 913 10 83",
    "sg:postcode":"2710",
    "sg:province":"Bern",
    "wof:name":"Ecole Enfantine",
    "wof:placetype":"venue"
},
  "geometry": {"coordinates":[6.8170647621,47.1014595032],"type":"Point"}
}