{
  "type": "Feature",
  "properties": {
    "iso:country":"CH",
    "sg:address":"Sonnhalde 15 9050 Appenzell. Postfach",
    "sg:city":"Appenzell",
    "sg:orig_category":"Herstellung von sonstigen landwirtschaftlichen Maschinen",
    "sg:postcode":"9050",
    "sg:province":"Appenzell Innerhoden",
    "wof:name":"Fritsche Martin Landmaschinen Gmbh",
    "wof:placetype":"venue"
},
  "geometry": {"coordinates":[9.4118385315,47.3354225159],"type":"Point"}
}