{
  "type": "Feature",
  "properties": {
    "iso:country":"CH",
    "sg:address":"Sch\u00f6nmattstrasse 6",
    "sg:city":"Inwil",
    "sg:orig_category":"Installation von Heizungs, L\u00fcftungs U Klimaanlagen",
    "sg:phone":"+41 41 448 34 76",
    "sg:postcode":"6034",
    "sg:province":"Luzern",
    "wof:name":"Martin Schaffner K\u00e4lte-& Klimatechnik",
    "wof:placetype":"venue"
},
  "geometry": {"coordinates":[8.344461441,47.1230354309],"type":"Point"}
}