{
  "type": "Feature",
  "properties": {
    "iso:country":"CH",
    "sg:address":"Fabrikstrasse 35",
    "sg:city":"Bern",
    "sg:orig_category":"Herstellung von Tanks U Sammelbeh\u00e4ltern aus Metall Sonstiger spezialisierter Hoch U Tiefbau",
    "sg:phone":"+41 26 652 93 60",
    "sg:postcode":"3012",
    "sg:province":"Bern",
    "wof:name":"Cibusa, Revision Et Nettoyage De Citernes Sa",
    "wof:placetype":"venue"
},
  "geometry": {"coordinates":[6.9340162277,46.7040786743],"type":"Point"}
}