{
  "type": "Feature",
  "properties": {
    "iso:country":"CH",
    "sg:address":"R\u00f6merstrasse 1",
    "sg:city":"Balsthal",
    "sg:classifiers":[
        {
            "category":"Restaurant",
            "type":"Food & Drink"
        }
    ],
    "sg:phone":"+41 71 911 25 88",
    "sg:postcode":"4710",
    "sg:province":"Solothurn",
    "wof:name":"Restaurant Neu-toggenburg",
    "wof:placetype":"venue"
},
  "geometry": {"coordinates":[9.0433483124,47.465221405],"type":"Point"}
}