{
  "type": "Feature",
  "properties": {
    "iso:country":"CH",
    "sg:address":"Langstrasse 187 8005 Z\u00fcrich. Postfach",
    "sg:city":"Z\u00fcrich",
    "sg:orig_category":"Interessenvertretungen",
    "sg:postcode":"8005",
    "sg:province":"Z\u00fcrich",
    "wof:name":"Ecumenical News International (eni)",
    "wof:placetype":"venue"
},
  "geometry": {"coordinates":[6.1265501976,46.2295875549],"type":"Point"}
}