{
  "type": "Feature",
  "properties": {
    "iso:country":"CH",
    "sg:address":"Hauptstrasse 25",
    "sg:city":"Menziken",
    "sg:orig_category":"Vermietung U Verpachtung von eigenen Immobilien",
    "sg:postcode":"5737",
    "sg:province":"Aargau",
    "wof:name":"Guidi Ag",
    "wof:placetype":"venue"
},
  "geometry": {"coordinates":[8.18724823,47.2436943054],"type":"Point"}
}