{
  "type": "Feature",
  "properties": {
    "iso:country":"CH",
    "sg:address":"Bahnhofstrasse 28",
    "sg:city":"M\u00f6rschwil",
    "sg:orig_category":"S\u00e4gewerke Zimmerei, Dachdeckerei, Bauspenglerei U Abdichtung",
    "sg:phone":"+41 71 866 12 43",
    "sg:postcode":"9402",
    "sg:province":"St. Gallen",
    "wof:name":"Keiser Kurt",
    "wof:placetype":"venue"
},
  "geometry": {"coordinates":[9.4184074402,47.4709892273],"type":"Point"}
}