{
  "type": "Feature",
  "properties": {
    "iso:country":"CH",
    "sg:address":"6901 Lugano. Postfach Caselle Postale 2105",
    "sg:city":"Lugano",
    "sg:orig_category":"Sportvereine Ballsport Basketball",
    "sg:postcode":"6901",
    "sg:province":"Ticino",
    "wof:name":"Bc Moutier",
    "wof:placetype":"venue"
},
  "geometry": {"coordinates":[7.3724598885,47.2787208557],"type":"Point"}
}