{
  "type": "Feature",
  "properties": {
    "iso:country":"CH",
    "sg:address":"Spitalgasse 1",
    "sg:city":"Winterthur",
    "sg:orig_category":"Detailhandel mit Bekleidung Detailhandel mit Geschenkartikeln U Souvenirs",
    "sg:phone":"+41 52 212 08 60",
    "sg:postcode":"8400",
    "sg:province":"Z\u00fcrich",
    "wof:name":"El Tumi Ag",
    "wof:placetype":"venue"
},
  "geometry": {"coordinates":[8.727464,47.498932],"type":"Point"}
}