{
  "type": "Feature",
  "properties": {
    "iso:country":"CH",
    "sg:address":"Petitot Rue Jean- 15 1204 Gen\u00e8ve. Postfach",
    "sg:city":"Gen\u00e8ve",
    "sg:orig_category":"Interessenvertretungen",
    "sg:phone":"+41 21 944 33 88",
    "sg:postcode":"1201",
    "sg:province":"Gen\u00e8ve",
    "wof:name":"Fondation Fesquet",
    "wof:placetype":"venue"
},
  "geometry": {"coordinates":[6.8547339439,46.4530982971],"type":"Point"}
}