{
  "type": "Feature",
  "properties": {
    "iso:country":"CH",
    "sg:address":"Hauptstrasse 9",
    "sg:city":"Unterseen",
    "sg:orig_category":"Non-Classified Establishments",
    "sg:postcode":"3800",
    "sg:province":"Bern",
    "wof:name":"Duss Peter Holding Ag",
    "wof:placetype":"venue"
},
  "geometry": {"coordinates":[7.849216938,46.6856994629],"type":"Point"}
}