{
  "type": "Feature",
  "properties": {
    "iso:country":"CH",
    "sg:address":"Sur-le-ch\u00eane",
    "sg:city":"Vullierens",
    "sg:orig_category":"Grosshandel mit Getr\u00e4nken Grosshandel mit Wein U Spirituosen",
    "sg:phone":"+41 22 910 32 10",
    "sg:postcode":"1115",
    "sg:province":"Vaud",
    "wof:name":"Cavallero",
    "wof:placetype":"venue"
},
  "geometry": {"coordinates":[6.1398639679,46.210395813],"type":"Point"}
}