{
  "type": "Feature",
  "properties": {
    "iso:country":"CH",
    "sg:address":"Uetlibergstrasse 23",
    "sg:city":"Z\u00fcrich",
    "sg:classifiers":[
        {
            "category":"Home & Garden",
            "subcategory":"Carpets & Floor Coverings",
            "type":"Retail Goods"
        }
    ],
    "sg:phone":"+41 14508181",
    "sg:postcode":"8045",
    "sg:province":"Z\u00fcrich",
    "sg:tags":[
        "workshop",
        "sewing"
    ],
    "wof:name":"Veratex Ag",
    "wof:placetype":"venue"
},
  "geometry": {"coordinates":[8.520893,47.364216],"type":"Point"}
}