{
  "type": "Feature",
  "properties": {
    "iso:country":"CH",
    "sg:address":"Kantonsstrasse 45 8862 Sch\u00fcbelbach. Postfach",
    "sg:city":"Sch\u00fcbelbach",
    "sg:orig_category":"Sonstiger Fachdetailhandel mit Nahrungsmitteln, Getr\u00e4nken U Tabak in Verkaufsr\u00e4umen",
    "sg:phone":"+41 34 402 51 72",
    "sg:postcode":"8862",
    "sg:province":"Schwyz",
    "wof:name":"Monika Steck Pfifouter Naturprodukte",
    "wof:placetype":"venue"
},
  "geometry": {"coordinates":[7.757589817,46.9491271973],"type":"Point"}
}