{
  "type": "Feature",
  "properties": {
    "iso:country":"CH",
    "sg:address":"Schnetzenschachen",
    "sg:city":"Ramsei",
    "sg:orig_category":"G\u00fcterbef\u00f6rderung im Strassenverkehr",
    "sg:phone":"+41 34 496 82 37",
    "sg:postcode":"3435",
    "sg:province":"Bern",
    "wof:name":"Ueli & Renate Pfister Transporte",
    "wof:placetype":"venue"
},
  "geometry": {"coordinates":[7.7030239105,46.9979171753],"type":"Point"}
}