{
  "type": "Feature",
  "properties": {
    "iso:country":"CH",
    "sg:address":"Marzilistrasse 29",
    "sg:city":"Bern",
    "sg:orig_category":"Schwimmb\u00e4der",
    "sg:phone":"+41 31 311 36 18",
    "sg:postcode":"3005",
    "sg:province":"Bern",
    "wof:name":"Freibad Marzili",
    "wof:placetype":"venue"
},
  "geometry": {"coordinates":[7.4432229996,46.9422264099],"type":"Point"}
}