{
  "type": "Feature",
  "properties": {
    "iso:country":"CH",
    "sg:address":"Rue De Tramelan 51",
    "sg:city":"Tavannes",
    "sg:orig_category":"Bauschreinerei Herstellung von M\u00f6beln verschiedener Art",
    "sg:phone":"+41 32 481 29 15",
    "sg:postcode":"2710",
    "sg:province":"Bern",
    "wof:name":"Eb\u00e9nisterie Boegli Sa",
    "wof:placetype":"venue"
},
  "geometry": {"coordinates":[7.189195,47.222736],"type":"Point"}
}