{
  "type": "Feature",
  "properties": {
    "iso:country":"CH",
    "sg:address":"Sonnenbergstrasse 10",
    "sg:city":"Kreuzlingen",
    "sg:orig_category":"Herstellung von Teilen U Zubeh\u00f6r f\u00fcr Automobile",
    "sg:phone":"+41 71 688 18 86",
    "sg:postcode":"8280",
    "sg:province":"Thurgau",
    "wof:name":"Lagros Ag",
    "wof:placetype":"venue"
},
  "geometry": {"coordinates":[9.1916379929,47.6359825134],"type":"Point"}
}