{
  "type": "Feature",
  "properties": {
    "iso:country":"CH",
    "sg:address":"Seestrasse 157",
    "sg:city":"Steckborn",
    "sg:orig_category":"Non-Classified Establishments",
    "sg:phone":"+41 79 423 32 20",
    "sg:postcode":"8266",
    "sg:province":"Thurgau",
    "wof:name":"Hess Gartenbau Gmbh",
    "wof:placetype":"venue"
},
  "geometry": {"coordinates":[8.9774694443,47.6631851196],"type":"Point"}
}