{
  "type": "Feature",
  "properties": {
    "iso:country":"CH",
    "sg:address":"Tunnelweg 2",
    "sg:city":"Oberarth",
    "sg:orig_category":"Architekturb\u00fcros",
    "sg:phone":"+41 41 855 53 55",
    "sg:postcode":"6414",
    "sg:province":"Schwyz",
    "wof:name":"T\u00e4nnler & Partner Gmbh Architekturb\u00fcro",
    "wof:placetype":"venue"
},
  "geometry": {"coordinates":[8.538278,47.054745],"type":"Point"}
}