{
  "type": "Feature",
  "properties": {
    "iso:country":"CH",
    "sg:address":"Feldblumenstrasse 153",
    "sg:city":"Adliswil",
    "sg:orig_category":"Grosshandel mit Getr\u00e4nken",
    "sg:phone":"+41 17108448",
    "sg:postcode":"8134",
    "sg:province":"Z\u00fcrich",
    "wof:name":"Murel Wy-su Ag",
    "wof:placetype":"venue"
},
  "geometry": {"coordinates":[8.5115938187,47.3219146729],"type":"Point"}
}