{
  "type": "Feature",
  "properties": {
    "iso:country":"CH",
    "sg:address":"Gartenstrasse 3 6300 Zug. Postfach 4754",
    "sg:city":"Zug",
    "sg:orig_category":"Grosshandel mit Maschinen U Ausr\u00fcstungen Handelsvermittlung von Brennstoffen, Erzen, Metallen U Chem",
    "sg:phone":"+41 41 240 19 22",
    "sg:postcode":"6304",
    "sg:province":"Zug",
    "wof:name":"Romal Sa",
    "wof:placetype":"venue"
},
  "geometry": {"coordinates":[8.302693367,47.0474357605],"type":"Point"}
}