{
  "type": "Feature",
  "properties": {
    "iso:country":"CH",
    "sg:address":"B\u00f6llistrasse 19",
    "sg:city":"Niederlenz",
    "sg:orig_category":"Sportvereine Turnen",
    "sg:phone":"+41 62 891 25 24",
    "sg:postcode":"5702",
    "sg:province":"Aargau",
    "wof:name":"Satus M\u00f6riken-wildegg",
    "wof:placetype":"venue"
},
  "geometry": {"coordinates":[8.1709413528,47.3987045288],"type":"Point"}
}