{
  "type": "Feature",
  "properties": {
    "iso:country":"CH",
    "sg:address":"Klettgauerstrasse 62 8212 Neuhausen. Postfach",
    "sg:city":"Neuhausen",
    "sg:orig_category":"Erbringung von Dienstleistungen f\u00fcr Unternehmen",
    "sg:postcode":"8212",
    "sg:province":"Schaffhausen",
    "wof:name":"Artefix Gmbh",
    "wof:placetype":"venue"
},
  "geometry": {"coordinates":[8.6117267609,47.6853218079],"type":"Point"}
}