{
  "type": "Feature",
  "properties": {
    "iso:country":"CH",
    "sg:address":"Dorfstrasse 111",
    "sg:city":"Obfelden",
    "sg:orig_category":"Vereine Gesang",
    "sg:phone":"+41 17617883",
    "sg:postcode":"8912",
    "sg:province":"Z\u00fcrich",
    "wof:name":"Coro Stella Alpina",
    "wof:placetype":"venue"
},
  "geometry": {"coordinates":[8.4091806412,47.2632522583],"type":"Point"}
}