{
  "type": "Feature",
  "properties": {
    "iso:country":"CH",
    "sg:address":"M\u00fchlegasse 17 8001 Z\u00fcrich. Postfach",
    "sg:city":"Z\u00fcrich",
    "sg:orig_category":"HOTELS: OHNE RESTAURANT",
    "sg:phone":"+41 12518795",
    "sg:postcode":"8025",
    "wof:name":"Hotel Scheuble Garni",
    "wof:placetype":"venue"
},
  "geometry": {"coordinates":[8.5447893143,47.3743782043],"type":"Point"}
}