{
  "type": "Feature",
  "properties": {
    "iso:country":"CH",
    "sg:address":"3792",
    "sg:city":"Saanen",
    "sg:orig_category":"Detailhandel mit Textilien",
    "sg:phone":"+41 52 741 21 24",
    "sg:postcode":"3792",
    "sg:province":"Bern",
    "wof:name":"Manufactura Gmbh Fachgesch\u00e4ft F. Mercerie, Textilien Usw",
    "wof:placetype":"venue"
},
  "geometry": {"coordinates":[8.8593168259,47.6592712402],"type":"Point"}
}