{
  "type": "Feature",
  "properties": {
    "iso:country":"CH",
    "sg:address":"F\u00f6hrenweg 1",
    "sg:city":"Einsiedeln",
    "sg:orig_category":"Sportvereine Alpinismus",
    "sg:phone":"+41 34 402 53 50",
    "sg:postcode":"8840",
    "sg:province":"Schwyz",
    "wof:name":"Sac Sektion Emmental",
    "wof:placetype":"venue"
},
  "geometry": {"coordinates":[7.757589817,46.9491271973],"type":"Point"}
}