{
  "type": "Feature",
  "properties": {
    "iso:country":"CH",
    "sg:address":"Kemisstrasse 40x",
    "sg:city":"Bowil",
    "sg:orig_category":"Detailhandel mit Computern U Software",
    "sg:phone":"+41 31 710 45 45",
    "sg:postcode":"3533",
    "sg:province":"Bern",
    "wof:name":"Compucorp Ag Computer & Software",
    "wof:placetype":"venue"
},
  "geometry": {"coordinates":[7.69558,46.903011],"type":"Point"}
}