{
  "type": "Feature",
  "properties": {
    "iso:country":"CH",
    "sg:address":"Villars-les-joncs 107 1700 Fribourg. Postfach",
    "sg:city":"Fribourg",
    "sg:orig_category":"K\u00fcnstlerische U schriftstellerische T\u00e4tigkeiten U Darbietungen",
    "sg:postcode":"1700",
    "sg:province":"Fribourg",
    "wof:name":"Dupont Mme Th\u00e9r\u00e8se Atelier De Conservation Et De Restauration Atelier De Conservation Et De Restauration D'oeuvres D'art Etc",
    "wof:placetype":"venue"
},
  "geometry": {"coordinates":[7.1759600639,46.8137817383],"type":"Point"}
}