{
  "type": "Feature",
  "properties": {
    "iso:country":"CH",
    "sg:address":"Goldacherstrasse 7",
    "sg:city":"T\u00fcbach",
    "sg:orig_category":"Grosshandel mit Holz U Baustoffen Hobel U Holzimpr\u00e4gnierwerke",
    "sg:phone":"+41 71 841 85 85",
    "sg:postcode":"9327",
    "sg:province":"St. Gallen",
    "wof:name":"Eichmann Holz Ag.",
    "wof:placetype":"venue"
},
  "geometry": {"coordinates":[9.4566030502,47.4858932495],"type":"Point"}
}