{
  "type": "Feature",
  "properties": {
    "iso:country":"CH",
    "sg:address":"Kontrollstrasse 12 2503 Biel/bienne. Postfach",
    "sg:city":"Biel/bienne",
    "sg:orig_category":"Fotografische Ateliers Fotografisches Gewerbe U fotografische Laboratorien",
    "sg:phone":"+41 32 325 17 17",
    "sg:postcode":"2503",
    "sg:province":"Bern",
    "wof:name":"Photo B\u00f6gli Stephan Photostudio F\u00fcr Werbezwecke",
    "wof:placetype":"venue"
},
  "geometry": {"coordinates":[7.2480421066,47.1365814209],"type":"Point"}
}