{
  "type": "Feature",
  "properties": {
    "iso:country":"CH",
    "sg:address":"Blandonnet Chemin De 4",
    "sg:city":"Vernier",
    "sg:orig_category":"Fahrschulen, Flugschulen",
    "sg:phone":"+41 79 631 34 30",
    "sg:postcode":"1214",
    "sg:province":"Gen\u00e8ve",
    "wof:name":"Theo Bachmann Autofahrschule",
    "wof:placetype":"venue"
},
  "geometry": {"coordinates":[7.3716697693,47.1830406189],"type":"Point"}
}