{
  "type": "Feature",
  "properties": {
    "addr:full":"Rathausgasse 8 Zofingen Aargau 4800",
    "addr:housenumber":"8",
    "addr:postcode":"4800",
    "addr:street":"Rathausgasse",
    "iso:country":"CH",
    "sg:address":"Rathausgasse 8",
    "sg:city":"Zofingen",
    "sg:orig_category":"Detailhandel mit B\u00fcchern Detailhandel mit B\u00fcchern, Zeitungen, Schreib U Papeteriewaren",
    "sg:phone":"+41 62 751 89 86",
    "sg:postcode":"4800",
    "sg:province":"Aargau",
    "wof:name":"Purzelbaum B\u00fccher Und Spiele Gmbh",
    "wof:placetype":"venue"
},
  "geometry": {"coordinates":[7.946397,47.287838],"type":"Point"}
}