{
  "type": "Feature",
  "properties": {
    "iso:country":"CH",
    "sg:address":"La Crettaz",
    "sg:city":"Haute-nendaz",
    "sg:orig_category":"Bauschreinerei Herstellung von Konstruktionsteilen, Fertigbauteilen U Ausbauelementen aus Holz",
    "sg:phone":"+41 27 288 24 91",
    "sg:postcode":"1997",
    "sg:province":"Valais",
    "wof:name":"Les Artisans Du Bois, Deleze-lathion-fournier Sa",
    "wof:placetype":"venue"
},
  "geometry": {"coordinates":[7.298112,46.184158],"type":"Point"}
}