{
  "type": "Feature",
  "properties": {
    "iso:country":"CH",
    "sg:address":"Hinterdorfstrasse 4",
    "sg:city":"Dielsdorf",
    "sg:orig_category":"Herstellung von Drahtwaren",
    "sg:phone":"+41 61 751 27 19",
    "sg:postcode":"8157",
    "sg:province":"Z\u00fcrich",
    "wof:name":"Weiser Rudolf",
    "wof:placetype":"venue"
},
  "geometry": {"coordinates":[7.6004829407,47.4786376953],"type":"Point"}
}