{
  "type": "Feature",
  "properties": {
    "iso:country":"CH",
    "sg:address":"Baselstrasse 66",
    "sg:city":"Muttenz",
    "sg:orig_category":"Detailhandel mit Damenbekleidung Herstellung von Oberbekleidung",
    "sg:phone":"+41 61 461 81 00",
    "sg:postcode":"4132",
    "sg:province":"Basel-Landschaft",
    "wof:name":"Jung Nina Alta Moda",
    "wof:placetype":"venue"
},
  "geometry": {"coordinates":[7.6375951767,47.5265579224],"type":"Point"}
}