{
  "type": "Feature",
  "properties": {
    "iso:country":"CH",
    "sg:address":"Oberdorf",
    "sg:city":"Kleinwangen",
    "sg:orig_category":"Erbringung von Dienstleistungen f\u00fcr Unternehmen Verlagsgewerbe",
    "sg:phone":"+41 41 910 38 23",
    "sg:postcode":"6277",
    "sg:province":"Luzern",
    "wof:name":"Informator Verlags Ag Verlag Und Unternehmensberatung F\u00fcr Marketing, Pr Und Kommunikation",
    "wof:placetype":"venue"
},
  "geometry": {"coordinates":[8.2985229492,47.2076644897],"type":"Point"}
}