{
  "type": "Feature",
  "properties": {
    "addr:full":"Rue Centrale 15 Bex Vaud 1880",
    "addr:housenumber":"15",
    "addr:postcode":"1880",
    "addr:street":"Rue Centrale",
    "iso:country":"CH",
    "sg:address":"Rue Centrale 15",
    "sg:city":"Bex",
    "sg:orig_category":"Detailhandel mit Brot, Back U S\u00fcsswaren",
    "sg:phone":"+41 24 463 32 94",
    "sg:postcode":"1880",
    "sg:province":"Vaud",
    "wof:name":"Christian Schmid Boulangerie & P\u00e2tisserie",
    "wof:placetype":"venue"
},
  "geometry": {"coordinates":[7.013988,46.251301],"type":"Point"}
}