{
  "type": "Feature",
  "properties": {
    "iso:country":"CH",
    "sg:address":"Route De Planafin 9",
    "sg:city":"Marly",
    "sg:orig_category":"Museen",
    "sg:phone":"+41 26 436 19 19",
    "sg:postcode":"1723",
    "sg:province":"Fribourg",
    "wof:name":"Mus\u00e9e Gutenberg",
    "wof:placetype":"venue"
},
  "geometry": {"coordinates":[7.165471077,46.7726707458],"type":"Point"}
}