{
  "type": "Feature",
  "properties": {
    "iso:country":"CH",
    "sg:address":"Via St. Franscini 30 6612 Ascona. Postfach",
    "sg:city":"Ascona",
    "sg:orig_category":"Architektur U Ingenieurb\u00fcros",
    "sg:postcode":"6612",
    "sg:province":"Ticino",
    "wof:name":"Architettura Vogel Sagl",
    "wof:placetype":"venue"
},
  "geometry": {"coordinates":[8.776355,46.155704],"type":"Point"}
}