{
  "type": "Feature",
  "properties": {
    "iso:country":"CH",
    "sg:address":"Trachslauerstrasse 68",
    "sg:city":"Einsiedeln",
    "sg:orig_category":"Detailhandel mit Metallwaren, Anstrichmitteln, Glaswaren, Bau U Heimwerkerbedarf Grosshandel mit Eis",
    "sg:phone":"+41 62 291 31 00",
    "sg:postcode":"8840",
    "sg:province":"Schwyz",
    "wof:name":"Mws Werkzeuge Ag",
    "wof:placetype":"venue"
},
  "geometry": {"coordinates":[7.9798369408,47.3542823792],"type":"Point"}
}