{
  "type": "Feature",
  "properties": {
    "iso:country":"CH",
    "sg:address":"Seidenbaum 9478 Azmoos. Postfach",
    "sg:city":"Tr\u00fcbbach",
    "sg:orig_category":"Fachdetailhandel in Verkaufsr\u00e4umen",
    "sg:postcode":"9477",
    "sg:province":"St. Gallen",
    "wof:name":"Hardli Eggenberger Sfh Seidenbaum",
    "wof:placetype":"venue"
},
  "geometry": {"coordinates":[9.4854249954,47.0806655884],"type":"Point"}
}