{
  "type": "Feature",
  "properties": {
    "iso:country":"CH",
    "sg:address":"Grenzstrasse 24",
    "sg:city":"Lyss",
    "sg:orig_category":"Architektur U Ingenieurb\u00fcros",
    "sg:phone":"+41 32 392 60 62",
    "sg:postcode":"3250",
    "sg:province":"Bern",
    "wof:name":"Nivo Ag",
    "wof:placetype":"venue"
},
  "geometry": {"coordinates":[7.291411,47.068096],"type":"Point"}
}