{
  "type": "Feature",
  "properties": {
    "iso:country":"CH",
    "sg:address":"Hauptstrasse 14",
    "sg:city":"L\u00e4ufelfingen",
    "sg:orig_category":"Grosshandel mit Nahrungsmitteln, Getr\u00e4nken U Tabakwaren ohne ausgepr\u00e4gten Schwerpunkt",
    "sg:phone":"+41 62 299 23 21",
    "sg:postcode":"4448",
    "sg:province":"Basel-Landschaft",
    "wof:name":"Visavis-lebensmittel Mohler P.",
    "wof:placetype":"venue"
},
  "geometry": {"coordinates":[7.8554182053,47.395072937],"type":"Point"}
}