{
  "type": "Feature",
  "properties": {
    "iso:country":"CH",
    "sg:address":"Via Cadepiano 24",
    "sg:city":"Barbengo",
    "sg:orig_category":"Fachdetailhandel mit pharmazeutischen Produkten Grosshandel mit pharmazeutischen Erzeugnissen",
    "sg:phone":"+41 91 985 26 40",
    "sg:postcode":"6917",
    "sg:province":"Ticino",
    "wof:name":"Bigmar Pharmaceuticals Sa",
    "wof:placetype":"venue"
},
  "geometry": {"coordinates":[8.9250659943,45.9669761658],"type":"Point"}
}