{
  "type": "Feature",
  "properties": {
    "iso:country":"CH",
    "sg:address":"Loogartenstrasse 15",
    "sg:city":"Z\u00fcrich",
    "sg:orig_category":"Sportvereine Velo Rad-& Motorfahrer-Bund SRB",
    "sg:postcode":"8048",
    "sg:province":"Z\u00fcrich",
    "wof:name":"Gentl.sportcl.bioco Z\u00fcrich",
    "wof:placetype":"venue"
},
  "geometry": {"coordinates":[8.4744367599,47.3895988464],"type":"Point"}
}