{
  "type": "Feature",
  "properties": {
    "iso:country":"CH",
    "sg:address":"3971",
    "sg:city":"Chermignon-bas",
    "sg:orig_category":"Verlegen von Fliesen U Platten",
    "sg:phone":"+41 27 483 23 04",
    "sg:postcode":"3971",
    "sg:province":"Valais",
    "wof:name":"Marc Bagnoud Entreprise De Carrelage",
    "wof:placetype":"venue"
},
  "geometry": {"coordinates":[7.4784898758,46.2839508057],"type":"Point"}
}