{
  "type": "Feature",
  "properties": {
    "iso:country":"CH",
    "sg:address":"Peter Merian-strasse 49 4052 Basel. Postfach",
    "sg:city":"Basel",
    "sg:orig_category":"Interessenvertretungen Sonstige pers\u00f6nliche Dienstleistungen",
    "sg:phone":"+41 61 273 23 13",
    "sg:postcode":"4051",
    "sg:province":"Basel-Stadt",
    "wof:name":"Hdl Hau Den Lukas Kontakt Und Beratungsstelle F\u00fcr Jungen Und M\u00e4nner In Krisensituationen Iannuzzi Giancarlo",
    "wof:placetype":"venue"
},
  "geometry": {"coordinates":[7.5943760872,47.5470848083],"type":"Point"}
}