{
  "type": "Feature",
  "properties": {
    "iso:country":"CH",
    "sg:address":"Z\u00fcrcherstrasse 6",
    "sg:city":"Stadel",
    "sg:orig_category":"Detailhandel mit Fleisch U Fleischwaren",
    "sg:phone":"+41 18582684",
    "sg:postcode":"8174",
    "sg:province":"Z\u00fcrich",
    "wof:name":"Meier Baumgartner Ag Metzgerei",
    "wof:placetype":"venue"
},
  "geometry": {"coordinates":[8.4665727615,47.528011322],"type":"Point"}
}