{
  "type": "Feature",
  "properties": {
    "addr:full":"Rastatterstrasse 9 Basel Basel-Stadt 4057",
    "addr:housenumber":"9",
    "addr:postcode":"4057",
    "addr:street":"Rastatterstrasse",
    "iso:country":"CH",
    "sg:address":"Rastatterstrasse 9",
    "sg:city":"Basel",
    "sg:classifiers":[
        {
            "category":"Utilities",
            "subcategory":"Cable",
            "type":"Services"
        }
    ],
    "sg:phone":"+41 61 631 35 55",
    "sg:postcode":"4057",
    "sg:province":"Basel-Stadt",
    "sg:tags":[
        "drum"
    ],
    "wof:name":"Automag Ag",
    "wof:placetype":"venue"
},
  "geometry": {"coordinates":[7.58904,47.579319],"type":"Point"}
}