{
  "type": "Feature",
  "properties": {
    "addr:full":"Weideggstrasse 21 Flawil St. Gallen 9230",
    "addr:housenumber":"21",
    "addr:postcode":"9230",
    "addr:street":"Weideggstrasse",
    "iso:country":"CH",
    "sg:address":"Weideggstrasse 21",
    "sg:city":"Flawil",
    "sg:orig_category":"Architektur U Ingenieurb\u00fcros Arztpraxen",
    "sg:phone":"+41 81 756 20 01",
    "sg:postcode":"9230",
    "sg:province":"St. Gallen",
    "wof:name":"Andreas Eggenberger Gmbh",
    "wof:placetype":"venue"
},
  "geometry": {"coordinates":[9.477129,47.166088],"type":"Point"}
}