{
  "type": "Feature",
  "properties": {
    "iso:country":"CH",
    "sg:address":"Lindenstrasse 20",
    "sg:city":"Niederhasli",
    "sg:orig_category":"Malerei",
    "sg:phone":"+41 18503681",
    "sg:postcode":"8155",
    "sg:province":"Z\u00fcrich",
    "wof:name":"Eugen Baumgartner Malergesch\u00e4ft",
    "wof:placetype":"venue"
},
  "geometry": {"coordinates":[8.4885082245,47.483505249],"type":"Point"}
}