{
  "type": "Feature",
  "properties": {
    "iso:country":"CH",
    "sg:address":"Zelgliweg 4",
    "sg:city":"N\u00fcrensdorf",
    "sg:orig_category":"Grosshandel mit Software Softwareentwicklung U beratung",
    "sg:phone":"+41 18626996",
    "sg:postcode":"8309",
    "sg:province":"Z\u00fcrich",
    "wof:name":"Synet Gmbh Novell Business Partner",
    "wof:placetype":"venue"
},
  "geometry": {"coordinates":[8.6601581573,47.4615402222],"type":"Point"}
}