{
  "type": "Feature",
  "properties": {
    "iso:country":"CH",
    "sg:address":"Friedhofweg 4",
    "sg:city":"Jegenstorf",
    "sg:orig_category":"Detailhandel mit Sportartikeln Fachdetailhandel in Verkaufsr\u00e4umen",
    "sg:phone":"+41 56 664 34 33",
    "sg:postcode":"3303",
    "sg:province":"Bern",
    "wof:name":"Huwiler Sport Ag",
    "wof:placetype":"venue"
},
  "geometry": {"coordinates":[8.3174819946,47.2825775146],"type":"Point"}
}