{
  "type": "Feature",
  "properties": {
    "iso:country":"CH",
    "sg:address":"Weineggstrasse 64",
    "sg:city":"Z\u00fcrich",
    "sg:orig_category":"Berufsberatungen",
    "sg:phone":"+41 13813031",
    "sg:postcode":"8008",
    "sg:province":"Z\u00fcrich",
    "wof:name":"Regula H\u00e4feli Berufsberatung",
    "wof:placetype":"venue"
},
  "geometry": {"coordinates":[8.567032,47.357681],"type":"Point"}
}