{
  "type": "Feature",
  "properties": {
    "iso:country":"CH",
    "sg:address":"Thannerstrasse 55",
    "sg:city":"Basel",
    "sg:orig_category":"Sonstiger Grosshandel",
    "sg:postcode":"4054",
    "sg:province":"Basel-Stadt",
    "wof:name":"Singh G., Travels Und Import-export",
    "wof:placetype":"venue"
},
  "geometry": {"coordinates":[8.7269964218,47.2649307251],"type":"Point"}
}