{
  "type": "Feature",
  "properties": {
    "iso:country":"CH",
    "sg:address":"7412",
    "sg:city":"Scharans",
    "sg:orig_category":"Primarschulen",
    "sg:phone":"+41 81 651 23 91",
    "sg:postcode":"7412",
    "sg:province":"Graubunden",
    "wof:name":"Primarschule",
    "wof:placetype":"venue"
},
  "geometry": {"coordinates":[9.4579324722,46.7170257568],"type":"Point"}
}