{
  "type": "Feature",
  "properties": {
    "iso:country":"CH",
    "sg:address":"Hauptstrasse 80",
    "sg:city":"Kreuzlingen",
    "sg:orig_category":"Pensionskassen",
    "sg:phone":"+41 71 672 33 33",
    "sg:postcode":"8280",
    "sg:province":"Thurgau",
    "wof:name":"Personalf\u00fcrsorgestiftung Der Zecchinel-transport Ag",
    "wof:placetype":"venue"
},
  "geometry": {"coordinates":[9.1760787964,47.646522522],"type":"Point"}
}