{
  "type": "Feature",
  "properties": {
    "iso:country":"CH",
    "sg:address":"Sattelstrasse 13 6315 Morgarten. Postfach",
    "sg:city":"Morgarten",
    "sg:orig_category":"Schiffs U Bootsbau Schiffsbau ohne Boots U Yachtbau",
    "sg:phone":"+41 41 750 29 20",
    "sg:postcode":"6315",
    "sg:province":"Zug",
    "wof:name":"Lang Nautic Gmbh Boote, Wassersportzubeh\u00f6r; Verkauf",
    "wof:placetype":"venue"
},
  "geometry": {"coordinates":[8.6390542984,47.1020317078],"type":"Point"}
}