{
  "type": "Feature",
  "properties": {
    "iso:country":"CH",
    "sg:address":"Unterdorfstrasse 60",
    "sg:city":"Seon",
    "sg:orig_category":"Vereine Briefmarkensammler",
    "sg:postcode":"5703",
    "sg:province":"Aargau",
    "wof:name":"Philatelistenverein O.w.s.",
    "wof:placetype":"venue"
},
  "geometry": {"coordinates":[8.160317421,47.3508415222],"type":"Point"}
}