{
  "type": "Feature",
  "properties": {
    "iso:country":"CH",
    "sg:address":"Gottardo Via S. 107",
    "sg:city":"Minusio",
    "sg:orig_category":"Erbringung von Dienstleistungen f\u00fcr Unternehmen",
    "sg:postcode":"6648",
    "sg:province":"Ticino",
    "wof:name":"Icmt Consulting Sagl",
    "wof:placetype":"venue"
},
  "geometry": {"coordinates":[8.8141899109,46.1773147583],"type":"Point"}
}