{
  "type": "Feature",
  "properties": {
    "iso:country":"CH",
    "sg:address":"Schlossbergplatz 3",
    "sg:city":"Baden",
    "sg:orig_category":"RESTAURANTS: TEA-ROOMS",
    "sg:postcode":"5400",
    "sg:province":"Aargau",
    "wof:name":"Restaurant Stadttor Lusser Marc",
    "wof:placetype":"venue"
},
  "geometry": {"coordinates":[8.3076992035,47.4731636047],"type":"Point"}
}