{
  "type": "Feature",
  "properties": {
    "iso:country":"CH",
    "sg:address":"Wandele 6106 Werthenstein. Postfach",
    "sg:city":"Werthenstein",
    "sg:orig_category":"Verwertung von Milch",
    "sg:postcode":"6106",
    "sg:province":"Luzern",
    "wof:name":"K\u00e4sereigenossenschaft Werthenstein-unterdorf",
    "wof:placetype":"venue"
},
  "geometry": {"coordinates":[8.1030015945,47.0553703308],"type":"Point"}
}