{
  "type": "Feature",
  "properties": {
    "iso:country":"CH",
    "sg:address":"Bolletstrasse 6",
    "sg:city":"Mettmenstetten",
    "sg:orig_category":"Vereine Vogel-& Naturschutz",
    "sg:phone":"+41 17670772",
    "sg:postcode":"8932",
    "sg:province":"Z\u00fcrich",
    "wof:name":"Naturschutzgruppe",
    "wof:placetype":"venue"
},
  "geometry": {"coordinates":[8.4682006836,47.2416267395],"type":"Point"}
}