{
  "type": "Feature",
  "properties": {
    "iso:country":"CH",
    "sg:address":"Zentralstrasse 20 6030 Ebikon. Postfach 476",
    "sg:city":"Ebikon",
    "sg:orig_category":"Grossbanken",
    "sg:phone":"+41 56 621 22 01",
    "sg:postcode":"6031",
    "sg:province":"Luzern",
    "wof:name":"Credit Suisse",
    "wof:placetype":"venue"
},
  "geometry": {"coordinates":[8.2765369415,47.3493309021],"type":"Point"}
}