{
  "type": "Feature",
  "properties": {
    "iso:country":"CH",
    "sg:address":"Rue Des Champs 5",
    "sg:city":"Echallens",
    "sg:orig_category":"W\u00e4schereien",
    "sg:phone":"+41 21 882 17 66",
    "sg:postcode":"1040",
    "sg:province":"Vaud",
    "wof:name":"Speedy Blanchisserie",
    "wof:placetype":"venue"
},
  "geometry": {"coordinates":[6.6360368729,46.6378211975],"type":"Point"}
}