{
  "type": "Feature",
  "properties": {
    "iso:country":"CH",
    "sg:address":"Au Pralet",
    "sg:city":"Oron-la-ville",
    "sg:orig_category":"G\u00fcterbef\u00f6rderung im Strassenverkehr",
    "sg:postcode":"1610",
    "sg:province":"Vaud",
    "wof:name":"Etter Jean-louis Succursale D'oron-la-ville",
    "wof:placetype":"venue"
},
  "geometry": {"coordinates":[6.8186268806,46.5721855164],"type":"Point"}
}