{
  "type": "Feature",
  "properties": {
    "iso:country":"CH",
    "sg:address":"Via Como 7",
    "sg:city":"Pedrinate",
    "sg:orig_category":"Tankstellen",
    "sg:phone":"+41 91 682 31 38",
    "sg:postcode":"6832",
    "sg:province":"Ticino",
    "wof:name":"Piccadilly Sa",
    "wof:placetype":"venue"
},
  "geometry": {"coordinates":[9.0146226883,45.8261032104],"type":"Point"}
}