{
  "type": "Feature",
  "properties": {
    "iso:country":"CH",
    "sg:address":"Grenzweg 33",
    "sg:city":"Oberentfelden",
    "sg:orig_category":"Betrieb von Sportanlagen",
    "sg:postcode":"5036",
    "sg:province":"Aargau",
    "wof:name":"Frei Und Hallenbad Entfelden",
    "wof:placetype":"venue"
},
  "geometry": {"coordinates":[8.036834,47.364479],"type":"Point"}
}