{
  "type": "Feature",
  "properties": {
    "iso:country":"CH",
    "sg:address":"Neuackerweg 1",
    "sg:city":"K\u00e4nerkinden",
    "sg:orig_category":"Herstellung von k\u00e4lte U lufttechnischen Erzeugnissen f\u00fcr gewerbliche Zwecke",
    "sg:phone":"+41 62 299 51 76",
    "sg:postcode":"4447",
    "sg:province":"Basel-Landschaft",
    "wof:name":"Clima Net Ag K\u00e4lte- U. Klimatechnik Servicestelle Nordwestschweiz",
    "wof:placetype":"venue"
},
  "geometry": {"coordinates":[7.8383002281,47.4145126343],"type":"Point"}
}