{
  "type": "Feature",
  "properties": {
    "iso:country":"CH",
    "sg:address":"Rouges-terres 61",
    "sg:city":"Hauterive",
    "sg:classifiers":[
        {
            "category":"Manufacturing",
            "subcategory":"Metals",
            "type":"Manufacturing & Wholesale Goods"
        }
    ],
    "sg:phone":"+41 43 377 78 78",
    "sg:postcode":"2068",
    "sg:province":"Neuch\u00e2tel",
    "sg:tags":[
        "-",
        "machine",
        "equipment",
        "engineering",
        "machinery",
        "mechanical"
    ],
    "wof:name":"W Schneider & Co Ag",
    "wof:placetype":"venue"
},
  "geometry": {"coordinates":[8.5410490036,47.2884750366],"type":"Point"}
}