{
  "type": "Feature",
  "properties": {
    "iso:country":"CH",
    "sg:address":"Herzbergstrasse 4",
    "sg:city":"Asp",
    "sg:orig_category":"Herstellung von Werkzeugen",
    "sg:phone":"+41 62 878 11 55",
    "sg:postcode":"5025",
    "sg:province":"Aargau",
    "wof:name":"Wernli Elektro-hydraulik & Werkzeugbau",
    "wof:placetype":"venue"
},
  "geometry": {"coordinates":[8.0485200882,47.4426422119],"type":"Point"}
}