{
  "type": "Feature",
  "properties": {
    "iso:country":"CH",
    "sg:address":"Holdenstrasse 33",
    "sg:city":"Bellikon",
    "sg:orig_category":"Edp Projects",
    "sg:phone":"+41 56 496 84 60",
    "sg:postcode":"5454",
    "sg:province":"Aargau",
    "wof:name":"Orgalink Gmbh",
    "wof:placetype":"venue"
},
  "geometry": {"coordinates":[8.348197937,47.3876876831],"type":"Point"}
}