{
  "type": "Feature",
  "properties": {
    "iso:country":"CH",
    "sg:address":"Alpenstrasse 3 3178 B\u00f6singen. Postfach",
    "sg:city":"B\u00f6singen",
    "sg:orig_category":"G\u00fcterbef\u00f6rderung im Strassenverkehr",
    "sg:phone":"+41 31 747 88 50",
    "sg:postcode":"3178",
    "sg:province":"Fribourg",
    "wof:name":"Cge Goods Enterprise Ag",
    "wof:placetype":"venue"
},
  "geometry": {"coordinates":[7.2281918526,46.8906822205],"type":"Point"}
}