{
  "type": "Feature",
  "properties": {
    "iso:country":"CH",
    "sg:address":"Weissensteinweg 11 2554 Meinisberg. Postfach 47",
    "sg:city":"Meinisberg",
    "sg:orig_category":"Mit dem Versicherungsgewerbe verbundene T\u00e4tigkeiten",
    "sg:phone":"+41 32 378 14 15",
    "sg:postcode":"2554",
    "sg:province":"Bern",
    "wof:name":"Ad Vitam Jean Lehmann Gmbh",
    "wof:placetype":"venue"
},
  "geometry": {"coordinates":[7.3467102051,47.1572799683],"type":"Point"}
}