{
  "type": "Feature",
  "properties": {
    "iso:country":"CH",
    "sg:address":"H\u00fcttmattstrasse 6",
    "sg:city":"Schafisheim",
    "sg:orig_category":"Unclassifiable Establishments",
    "sg:postcode":"5503",
    "sg:province":"Aargau",
    "wof:name":"R\u00fcetschi & Co",
    "wof:placetype":"venue"
},
  "geometry": {"coordinates":[8.1448831558,47.3782844543],"type":"Point"}
}