{
  "type": "Feature",
  "properties": {
    "iso:country":"CH",
    "sg:address":"Le Cernil",
    "sg:city":"Tramelan",
    "sg:orig_category":"Verwertung von Milch",
    "sg:postcode":"2720",
    "sg:province":"Bern",
    "wof:name":"Soci\u00e9t\u00e9 De Laiterie De Le Cernil",
    "wof:placetype":"venue"
},
  "geometry": {"coordinates":[7.0708551407,47.230178833],"type":"Point"}
}