{
  "type": "Feature",
  "properties": {
    "iso:country":"CH",
    "sg:address":"Jungfraustrasse 20",
    "sg:city":"Uetendorf",
    "sg:orig_category":"Reiseb\u00fcros U Reiseveranstalter",
    "sg:phone":"+41 33 345 30 56",
    "sg:postcode":"3661",
    "sg:province":"Bern",
    "wof:name":"L\u00fcdi B. Reisen Gmbh",
    "wof:placetype":"venue"
},
  "geometry": {"coordinates":[7.5951042175,46.7788276672],"type":"Point"}
}