{
  "type": "Feature",
  "properties": {
    "iso:country":"CH",
    "sg:address":"Waldheimstrasse 30",
    "sg:city":"Bern",
    "sg:orig_category":"Hardwareberatung",
    "sg:phone":"+41 31 301 10 05",
    "sg:postcode":"3012",
    "sg:province":"Bern",
    "wof:name":"Pc-fran Barcia Farina Francisco",
    "wof:placetype":"venue"
},
  "geometry": {"coordinates":[7.4246401787,46.9523353577],"type":"Point"}
}