{
  "type": "Feature",
  "properties": {
    "iso:country":"CH",
    "sg:address":"Via A. Rinaldi 6864 Arzo. Postfach",
    "sg:city":"Arzo",
    "sg:orig_category":"Sonstiger spezialisierter Hoch U Tiefbau",
    "sg:postcode":"6864",
    "sg:province":"Ticino",
    "wof:name":"Lc Camini Sagl",
    "wof:placetype":"venue"
},
  "geometry": {"coordinates":[8.9419975281,45.8769035339],"type":"Point"}
}