{
  "type": "Feature",
  "properties": {
    "iso:country":"CH",
    "sg:address":"Obergrundstrasse 4",
    "sg:city":"Sins",
    "sg:orig_category":"Malerei",
    "sg:phone":"+41 41 787 13 10",
    "sg:postcode":"5643",
    "sg:province":"Aargau",
    "wof:name":"Jakob H. Aeberhard Malergesch\u00e4ft",
    "wof:placetype":"venue"
},
  "geometry": {"coordinates":[8.393863678,47.1923599243],"type":"Point"}
}