{
  "type": "Feature",
  "properties": {
    "iso:country":"CH",
    "sg:address":"Hauptstr. 31",
    "sg:city":"Wollerau",
    "sg:classifiers":[
        {
            "category":"Banks & Credit Unions",
            "subcategory":"Bank",
            "type":"Services"
        }
    ],
    "sg:phone":"+41 17840530",
    "sg:postcode":"8832",
    "sg:province":"Schwyz",
    "wof:name":"Kantonalbank Schwyz",
    "wof:placetype":"venue"
},
  "geometry": {"coordinates":[8.719097,47.195431],"type":"Point"}
}