{
  "type": "Feature",
  "properties": {
    "iso:country":"CH",
    "sg:address":"Freisch\u00fctzgasse 14",
    "sg:city":"Z\u00fcrich",
    "sg:classifiers":[
        {
            "category":"Restaurant",
            "type":"Food & Drink"
        }
    ],
    "sg:phone":"+41 12419294",
    "sg:postcode":"8004",
    "sg:province":"Z\u00fcrich",
    "wof:name":"Restaurant Rincao",
    "wof:placetype":"venue"
},
  "geometry": {"coordinates":[8.5331840515,47.3774223328],"type":"Point"}
}