{
  "type": "Feature",
  "properties": {
    "iso:country":"CH",
    "sg:address":"M\u00fchlegasse",
    "sg:city":"K\u00fcblis",
    "sg:orig_category":"G\u00fcterbef\u00f6rderung im Strassenverkehr",
    "sg:postcode":"7240",
    "sg:province":"Graubunden",
    "wof:name":"Brunner-weber J.",
    "wof:placetype":"venue"
},
  "geometry": {"coordinates":[9.7778701782,46.9137802124],"type":"Point"}
}