{
  "type": "Feature",
  "properties": {
    "iso:country":"CH",
    "sg:address":"Seidenweg 14",
    "sg:city":"Bern",
    "sg:orig_category":"Sonstige mit der Informatik verbundene T\u00e4tigkeiten",
    "sg:postcode":"3012",
    "sg:province":"Bern",
    "wof:name":"Zwahlen Consulting",
    "wof:placetype":"venue"
},
  "geometry": {"coordinates":[7.432199955,46.9544372559],"type":"Point"}
}