{
  "type": "Feature",
  "properties": {
    "iso:country":"CH",
    "sg:address":"1925",
    "sg:city":"Finhaut",
    "sg:orig_category":"Verkehrs- and Tourismusb\u00fcros",
    "sg:phone":"+41 27 768 12 78",
    "sg:postcode":"1925",
    "sg:province":"Valais",
    "wof:name":"Office Du Tourisme",
    "wof:placetype":"venue"
},
  "geometry": {"coordinates":[6.9743900299,46.082359314],"type":"Point"}
}