{
  "type": "Feature",
  "properties": {
    "iso:country":"CH",
    "sg:address":"Via Del Teatro 6600 Locarno. Postfach Casa Postale",
    "sg:city":"Locarno",
    "sg:orig_category":"Sonstige Kultur U Unterhaltungseinrichtungen",
    "sg:postcode":"6600",
    "sg:province":"Ticino",
    "wof:name":"Casin\u00d2 Kursaal Locarno Sa Giochi A Vincita Ecc",
    "wof:placetype":"venue"
},
  "geometry": {"coordinates":[8.7907819748,46.1548156738],"type":"Point"}
}