{
  "type": "Feature",
  "properties": {
    "iso:country":"CH",
    "sg:address":"Dufourstrasse 165",
    "sg:city":"Z\u00fcrich",
    "sg:orig_category":"W\u00e4scherei U chemische Reinigung",
    "sg:phone":"+41 14220529",
    "sg:postcode":"8008",
    "sg:province":"Z\u00fcrich",
    "wof:name":"Ruetex Textil-reinigung R\u00fcdis\u00fchli K.",
    "wof:placetype":"venue"
},
  "geometry": {"coordinates":[8.5551462173,47.3547325134],"type":"Point"}
}