{
  "type": "Feature",
  "properties": {
    "iso:country":"CH",
    "sg:address":"G\u00e4sslistrasse 21",
    "sg:city":"Tuggen",
    "sg:orig_category":"Bauschreinerei Herstellung von Konstruktionsteilen, Fertigbauteilen U Ausbauelementen aus Holz",
    "sg:phone":"+41 55 445 18 24",
    "sg:postcode":"8856",
    "sg:province":"Schwyz",
    "wof:name":"Gebr. Egli Ag",
    "wof:placetype":"venue"
},
  "geometry": {"coordinates":[8.94531,47.206184],"type":"Point"}
}