{
  "type": "Feature",
  "properties": {
    "iso:country":"CH",
    "sg:address":"Im Tiergarten 54",
    "sg:city":"Z\u00fcrich",
    "sg:orig_category":"Datenbanken Softwareentwicklung U beratung",
    "sg:phone":"+41 14543010",
    "sg:postcode":"8055",
    "sg:province":"Z\u00fcrich",
    "wof:name":"Lcc Consulting Ag",
    "wof:placetype":"venue"
},
  "geometry": {"coordinates":[8.511508,47.365314],"type":"Point"}
}