{
  "type": "Feature",
  "properties": {
    "iso:country":"CH",
    "sg:address":"R. De L'ancien Stand 1 Case Postale",
    "sg:city":"Yverdon",
    "sg:classifiers":[
        {
            "category":"Utilities",
            "subcategory":"Electric",
            "type":"Services"
        }
    ],
    "sg:phone":"+41 24 423 65 55",
    "sg:postcode":"1401",
    "sg:province":"Vaud",
    "sg:tags":[
        "electricity",
        "raw",
        "energy",
        "material"
    ],
    "wof:name":"Service Des Energies",
    "wof:placetype":"venue"
},
  "geometry": {"coordinates":[-75.4186096191,39.145198822],"type":"Point"}
}