{
  "type": "Feature",
  "properties": {
    "iso:country":"CH",
    "sg:address":"Kolinplatz 2 6300 Zug. Postfach",
    "sg:city":"Zug",
    "sg:orig_category":"Unclassifiable Establishments",
    "sg:postcode":"6300",
    "sg:province":"Zug",
    "wof:name":"Regal Trust Ltd Beteiligungen Usw",
    "wof:placetype":"venue"
},
  "geometry": {"coordinates":[8.515376091,47.1663856506],"type":"Point"}
}