{
  "type": "Feature",
  "properties": {
    "addr:full":"Ehrendingerstrasse 78b Ennetbaden Aargau 5408",
    "addr:housenumber":"78b",
    "addr:postcode":"5408",
    "addr:street":"Ehrendingerstrasse",
    "iso:country":"CH",
    "sg:address":"Ehrendingerstrasse 78b",
    "sg:city":"Ennetbaden",
    "sg:orig_category":"Datenverarbeitungsdienste Sonstige mit der Informatik verbundene T\u00e4tigkeiten",
    "sg:phone":"+41 41 460 41 88",
    "sg:postcode":"5408",
    "sg:province":"Aargau",
    "wof:name":"Arnold Consulting Ag",
    "wof:placetype":"venue"
},
  "geometry": {"coordinates":[8.223583,47.131149],"type":"Point"}
}