{
  "type": "Feature",
  "properties": {
    "iso:country":"CH",
    "sg:address":"Dunkerstrasse 50",
    "sg:city":"Bern",
    "sg:orig_category":"Erwachsenenbildung U Unterricht",
    "sg:postcode":"3006",
    "sg:province":"Bern",
    "wof:name":"Coderey M.",
    "wof:placetype":"venue"
},
  "geometry": {"coordinates":[6.5809869766,46.5380935669],"type":"Point"}
}