{
  "type": "Feature",
  "properties": {
    "iso:country":"CH",
    "sg:address":"Postw\u00e4ldli 5 8807 Freienbach. Postfach",
    "sg:city":"Freienbach",
    "sg:orig_category":"Vermietung U Verpachtung von eigenen Immobilien",
    "sg:postcode":"8807",
    "sg:province":"Schwyz",
    "wof:name":"Telmo Immobilien Gmbh",
    "wof:placetype":"venue"
},
  "geometry": {"coordinates":[8.7531747818,47.2060508728],"type":"Point"}
}