{
  "type": "Feature",
  "properties": {
    "iso:country":"CH",
    "sg:address":"6963",
    "sg:city":"Cureggia",
    "sg:orig_category":"Malerei",
    "sg:phone":"+41 91 941 96 71",
    "sg:postcode":"6963",
    "sg:province":"Ticino",
    "wof:name":"Anna Eggemann Impresa Pittura Color-studio",
    "wof:placetype":"venue"
},
  "geometry": {"coordinates":[8.9781703949,46.0223617554],"type":"Point"}
}