{
  "type": "Feature",
  "properties": {
    "iso:country":"CH",
    "sg:address":"Rue De Eglise Catholique 1",
    "sg:city":"Montreux",
    "sg:orig_category":"Non-Classified Establishments",
    "sg:phone":"+41 21 965 16 80",
    "sg:postcode":"1820",
    "sg:province":"Vaud",
    "wof:name":"Tourelles Sa",
    "wof:placetype":"venue"
},
  "geometry": {"coordinates":[6.9110898972,46.4312896729],"type":"Point"}
}