{
  "type": "Feature",
  "properties": {
    "iso:country":"CH",
    "sg:address":"Impasse Des Cerisiers 1",
    "sg:city":"Farvagny",
    "sg:orig_category":"Arztpraxen",
    "sg:phone":"+41 26 411 38 31",
    "sg:postcode":"1726",
    "sg:province":"Fribourg",
    "wof:name":"Dr M\u00e9d. Philippe Ducrest M\u00e9decin G\u00e9n\u00e9raliste Fmh",
    "wof:placetype":"venue"
},
  "geometry": {"coordinates":[7.064444,46.71814],"type":"Point"}
}