{
  "type": "Feature",
  "properties": {
    "iso:country":"CH",
    "sg:address":"M\u00f6sle 2665",
    "sg:city":"Herisau",
    "sg:orig_category":"Unclassifiable Establishments",
    "sg:postcode":"9100",
    "sg:province":"Appenzell Ausserrhoden",
    "wof:name":"Gartenbau Schlup H.",
    "wof:placetype":"venue"
},
  "geometry": {"coordinates":[7.404540062,47.1506614685],"type":"Point"}
}