{
  "type": "Feature",
  "properties": {
    "iso:country":"CH",
    "sg:address":"Gliserallee 139",
    "sg:city":"Glis",
    "sg:orig_category":"Nationale Postdienste",
    "sg:phone":"+41 27 923 15 45",
    "sg:postcode":"3902",
    "sg:province":"Valais",
    "wof:name":"Die Schweizerische Post",
    "wof:placetype":"venue"
},
  "geometry": {"coordinates":[7.9793038368,46.3113327026],"type":"Point"}
}