{
  "type": "Feature",
  "properties": {
    "iso:country":"CH",
    "sg:address":"Dornierstrasse 9c",
    "sg:city":"Altenrhein",
    "sg:orig_category":"Architekturb\u00fcros",
    "sg:phone":"+41 71 850 00 10",
    "sg:postcode":"9423",
    "sg:province":"St. Gallen",
    "wof:name":"Hubert M\u00e4der Architekturb\u00fcro",
    "wof:placetype":"venue"
},
  "geometry": {"coordinates":[9.55569,47.488914],"type":"Point"}
}