{
  "type": "Feature",
  "properties": {
    "addr:full":"Sch\u00fctzenhausstrasse 56 Embrach Z\u00fcrich 8424",
    "addr:housenumber":"56",
    "addr:postcode":"8424",
    "addr:street":"Schuetzenhausstrasse",
    "iso:country":"CH",
    "sg:address":"Sch\u00fctzenhausstrasse 56",
    "sg:city":"Embrach",
    "sg:orig_category":"Architekturb\u00fcros",
    "sg:phone":"+41 18652228",
    "sg:postcode":"8424",
    "sg:province":"Z\u00fcrich",
    "wof:name":"Hans Keller Architekturb\u00fcro",
    "wof:placetype":"venue"
},
  "geometry": {"coordinates":[8.596051,47.506809],"type":"Point"}
}