{
  "type": "Feature",
  "properties": {
    "addr:full":"Grossacher 34a Krauchthal Bern 3326",
    "addr:housenumber":"34a",
    "addr:postcode":"3326",
    "addr:street":"Grossacher",
    "iso:country":"CH",
    "sg:address":"Grossacher 34a",
    "sg:city":"Krauchthal",
    "sg:orig_category":"Architekturb\u00fcros Baugewerbe",
    "sg:phone":"+41 55 286 20 90",
    "sg:postcode":"3326",
    "sg:province":"Bern",
    "wof:name":"H\u00e4ssig Gresch Partner Gmbh Architektur - Bauleitung - Bauberatung",
    "wof:placetype":"venue"
},
  "geometry": {"coordinates":[8.932289,47.240231],"type":"Point"}
}