{
  "type": "Feature",
  "properties": {
    "iso:country":"CH",
    "sg:address":"Laveggio Via 21 6850 Mendrisio. Postfach",
    "sg:city":"Mendrisio",
    "sg:orig_category":"Fachdetailhandel in Verkaufsr\u00e4umen",
    "sg:postcode":"6850",
    "sg:province":"Ticino",
    "wof:name":"Boat Service Di Capoferri Roberto Motoscafi; Vendita, Riparazioni, Invernaggi",
    "wof:placetype":"venue"
},
  "geometry": {"coordinates":[8.9780750275,45.8785362244],"type":"Point"}
}