{
  "type": "Feature",
  "properties": {
    "iso:country":"CH",
    "sg:address":"Pletschengasse 3953 Leuk Stadt. Postfach",
    "sg:city":"Susten",
    "sg:orig_category":"Sanit\u00e4r, Heizungs U L\u00fcftungsinstallation",
    "sg:postcode":"3952",
    "sg:province":"Valais",
    "wof:name":"Wyssen Aldo Heizungen Sant. Installationen",
    "wof:placetype":"venue"
},
  "geometry": {"coordinates":[7.6360478401,46.2967147827],"type":"Point"}
}