{
  "type": "Feature",
  "properties": {
    "iso:country":"CH",
    "sg:address":"Wampflenstrasse 40",
    "sg:city":"Meilen",
    "sg:orig_category":"Wirtschaftspr\u00fcfung, Steuerberatung U Treuhand",
    "sg:phone":"+41 19234358",
    "sg:postcode":"8706",
    "sg:province":"Z\u00fcrich",
    "wof:name":"Weba Treuhand & Consulting, Bernhard A. Wegier",
    "wof:placetype":"venue"
},
  "geometry": {"coordinates":[8.6437606812,47.2747650146],"type":"Point"}
}