{
  "type": "Feature",
  "properties": {
    "iso:country":"CH",
    "sg:address":"Riedstrasse",
    "sg:city":"Zermatt",
    "sg:orig_category":"Unternehmensberatung",
    "sg:postcode":"3920",
    "sg:province":"Valais",
    "wof:name":"Nbt New Best Time Management S\u00e0rl",
    "wof:placetype":"venue"
},
  "geometry": {"coordinates":[7.7495670319,46.017906189],"type":"Point"}
}