{
  "type": "Feature",
  "properties": {
    "iso:country":"CH",
    "sg:address":"Haldenstrasse 12",
    "sg:city":"Luzern",
    "sg:orig_category":"Architektur U Ingenieurb\u00fcros Forstwirtschaft ohne Dienstleistungen in der Forstwirtschaft",
    "sg:phone":"+41 41 419 03 20",
    "sg:postcode":"6006",
    "sg:province":"Luzern",
    "wof:name":"Kronotec Ag",
    "wof:placetype":"venue"
},
  "geometry": {"coordinates":[8.320439,47.055328],"type":"Point"}
}