{
  "type": "Feature",
  "properties": {
    "iso:country":"CH",
    "sg:address":"Rumelingsstrasse 3969 Varen. Postfach",
    "sg:city":"Varen",
    "sg:orig_category":"Grosshandel mit Getr\u00e4nken",
    "sg:postcode":"3969",
    "wof:name":"Bayard Hans, Soleil De Varone Weinkellerei",
    "wof:placetype":"venue"
},
  "geometry": {"coordinates":[32.143699646,-27.3739700317],"type":"Point"}
}