{
  "type": "Feature",
  "properties": {
    "iso:country":"CH",
    "sg:address":"Chemin Des Pi\u00e8cettes 6",
    "sg:city":"Mont-sur-lausanne",
    "sg:orig_category":"Herstellung von Konstruktionsteilen, Fertigbauteilen U Ausbauelementen aus Holz",
    "sg:postcode":"1052",
    "sg:province":"Vaud",
    "wof:name":"Marchon Gilbert.",
    "wof:placetype":"venue"
},
  "geometry": {"coordinates":[6.6356940269,46.5425071716],"type":"Point"}
}