{
  "type": "Feature",
  "properties": {
    "iso:country":"CH",
    "sg:address":"Rosengasse 7",
    "sg:city":"Niederg\u00f6sgen",
    "sg:orig_category":"Detailhandel Reparatur von Gebrauchsg\u00fctern Wirtschaftspr\u00fcfung, Steuerberatung U Treuhand",
    "sg:phone":"+41 62 849 46 17",
    "sg:postcode":"5013",
    "sg:province":"Solothurn",
    "wof:name":"Divaria Gmbh",
    "wof:placetype":"venue"
},
  "geometry": {"coordinates":[7.9961848259,47.3722763062],"type":"Point"}
}