{
  "type": "Feature",
  "properties": {
    "iso:country":"CH",
    "sg:address":"Hortinweg 18",
    "sg:city":"Thun",
    "sg:orig_category":"Organisationen des Gesundheitswesen",
    "sg:phone":"+41 33 222 10 38",
    "sg:postcode":"3600",
    "sg:province":"Bern",
    "wof:name":"Samariterverein Thun",
    "wof:placetype":"venue"
},
  "geometry": {"coordinates":[7.6115779877,46.7513580322],"type":"Point"}
}