{
  "type": "Feature",
  "properties": {
    "iso:country":"CH",
    "sg:address":"Avenue Gare-des-eaux-vives 2",
    "sg:city":"Gen\u00e8ve",
    "sg:orig_category":"Rechtsberatung Unternehmensberatung",
    "sg:phone":"+41 22 707 08 70",
    "sg:postcode":"1207",
    "sg:province":"Gen\u00e8ve",
    "wof:name":"Jacobacci & Partners Sa",
    "wof:placetype":"venue"
},
  "geometry": {"coordinates":[6.1660060883,46.2002906799],"type":"Point"}
}