{
  "type": "Feature",
  "properties": {
    "iso:country":"CH",
    "sg:address":"Kreuzstrasse Eggerstanden",
    "sg:city":"Appenzell",
    "sg:orig_category":"S\u00e4gewerke",
    "sg:phone":"+41 56 668 18 33",
    "sg:postcode":"9050",
    "sg:province":"Appenzell Innerhoden",
    "wof:name":"Johann Meienberg S\u00e4gerei",
    "wof:placetype":"venue"
},
  "geometry": {"coordinates":[8.3383264542,47.2404975891],"type":"Point"}
}