{
  "type": "Feature",
  "properties": {
    "iso:country":"CH",
    "sg:address":"Campanile Via Al 13a",
    "sg:city":"Viganello",
    "sg:orig_category":"Unclassifiable Establishments",
    "sg:postcode":"6962",
    "sg:province":"Ticino",
    "wof:name":"Q Point Sa",
    "wof:placetype":"venue"
},
  "geometry": {"coordinates":[8.9708967209,46.0149879456],"type":"Point"}
}