{
  "type": "Feature",
  "properties": {
    "iso:country":"CH",
    "sg:address":"Hauptgasse 11",
    "sg:city":"Solothurn",
    "sg:orig_category":"Herstellung von Karosserien U Anh\u00e4ngern",
    "sg:phone":"+41 32 954 18 18",
    "sg:postcode":"4500",
    "sg:province":"Solothurn",
    "wof:name":"Sauser Fr\u00e8res Sa",
    "wof:placetype":"venue"
},
  "geometry": {"coordinates":[6.9591398239,47.1862602234],"type":"Point"}
}