{
  "type": "Feature",
  "properties": {
    "iso:country":"CH",
    "sg:address":"Landstrasse 105 5412 Gebenstorf. Postfach",
    "sg:city":"Gebenstorf",
    "sg:orig_category":"Unclassifiable Establishments",
    "sg:phone":"+41 56 223 02 52",
    "sg:postcode":"5412",
    "sg:province":"Aargau",
    "wof:name":"Transport Merz Ag",
    "wof:placetype":"venue"
},
  "geometry": {"coordinates":[8.2324676514,47.479511261],"type":"Point"}
}