{
  "type": "Feature",
  "properties": {
    "iso:country":"CH",
    "sg:address":"Grabenstrasse 32 6300 Zug. Postfach",
    "sg:city":"Zug",
    "sg:orig_category":"Interessenvertretungen",
    "sg:postcode":"6300",
    "sg:province":"Zug",
    "wof:name":"Stiftung Der B\u00e4r-gruppe",
    "wof:placetype":"venue"
},
  "geometry": {"coordinates":[8.5146417618,47.1651420593],"type":"Point"}
}