{
  "type": "Feature",
  "properties": {
    "iso:country":"CH",
    "sg:address":"L\u00e4nggasse 55",
    "sg:city":"Biel/bienne",
    "sg:orig_category":"Erschliessung von Grundst\u00fccken",
    "sg:phone":"+41 32 342 64 60",
    "sg:postcode":"2504",
    "sg:province":"Bern",
    "wof:name":"Baugenossenschaft Friedheim",
    "wof:placetype":"venue"
},
  "geometry": {"coordinates":[7.2742052078,47.1532554626],"type":"Point"}
}