{
  "type": "Feature",
  "properties": {
    "iso:country":"CH",
    "sg:address":"Rue Des Vergers 9 1950 Sion Case Postale 102",
    "sg:city":"Sion",
    "sg:orig_category":"Sonstige mit der \u00f6ffentlichen Verwaltung verbundene T\u00e4tigkeiten",
    "sg:phone":"+41 27 606 46 00",
    "sg:postcode":"1951",
    "sg:province":"Valais",
    "wof:name":"Archives Cantonales",
    "wof:placetype":"venue"
},
  "geometry": {"coordinates":[7.3586969376,46.2314682007],"type":"Point"}
}