{
  "type": "Feature",
  "properties": {
    "iso:country":"CH",
    "sg:address":"Lenzb\u00fcel 2",
    "sg:city":"Sirnach",
    "sg:orig_category":"Instandhaltung U Reparatur von Automobilen",
    "sg:postcode":"8370",
    "sg:province":"Thurgau",
    "wof:name":"Auto Und Carrosserie Brunner Gmbh",
    "wof:placetype":"venue"
},
  "geometry": {"coordinates":[9.0339641571,47.4515991211],"type":"Point"}
}