{
  "type": "Feature",
  "properties": {
    "addr:full":"Im Birkenhof Illhart Thurgau 8558",
    "addr:postcode":"8558",
    "addr:street":"Im Birkenhof",
    "iso:country":"CH",
    "sg:address":"Im Birkenhof",
    "sg:city":"Illhart",
    "sg:orig_category":"Allgemeiner Hoch U Tiefbau Strassenbau",
    "sg:phone":"+41 52 763 15 65",
    "sg:postcode":"8558",
    "sg:province":"Thurgau",
    "wof:name":"Betrag Tiefbau Ag",
    "wof:placetype":"venue"
},
  "geometry": {"coordinates":[9.0369,47.617699],"type":"Point"}
}