{
  "type": "Feature",
  "properties": {
    "iso:country":"CH",
    "sg:address":"Grand-pont Escaliers Du 5",
    "sg:city":"Lausanne",
    "sg:classifiers":[
        {
            "category":"Education",
            "subcategory":"Library",
            "type":"Public Place"
        }
    ],
    "sg:phone":"+41 21 312 96 66",
    "sg:postcode":"1003",
    "sg:province":"Vaud",
    "sg:tags":[
        "u",
        "bibliotheken",
        "archive"
    ],
    "wof:name":"Fondation Vallotton F\u00e9lix",
    "wof:placetype":"venue"
},
  "geometry": {"coordinates":[6.631241,46.51989],"type":"Point"}
}