{
  "type": "Feature",
  "properties": {
    "iso:country":"CH",
    "sg:address":"Hauptstrasse 60 4450 Sissach. Postfach",
    "sg:city":"Sissach",
    "sg:orig_category":"Architekturb\u00fcros",
    "sg:phone":"+41 61 971 41 44",
    "sg:postcode":"4450",
    "sg:province":"Basel-Landschaft",
    "wof:name":"Robert H\u00e4felfinger Architekturb\u00fcro",
    "wof:placetype":"venue"
},
  "geometry": {"coordinates":[7.8120598793,47.464176178],"type":"Point"}
}