{
  "type": "Feature",
  "properties": {
    "addr:full":"Vernier Route De 211 Vernier Gen\u00e8ve 1214",
    "addr:housenumber":"211",
    "addr:postcode":"1214",
    "addr:street":"Route De",
    "iso:country":"CH",
    "sg:address":"Vernier Route De 211",
    "sg:city":"Vernier",
    "sg:orig_category":"Detailhandel mit Brot, Back U S\u00fcsswaren",
    "sg:phone":"+41 22 341 26 26",
    "sg:postcode":"1214",
    "sg:province":"Gen\u00e8ve",
    "wof:name":"Da Silva Maria",
    "wof:placetype":"venue"
},
  "geometry": {"coordinates":[6.080475,46.212345],"type":"Point"}
}