{
  "type": "Feature",
  "properties": {
    "iso:country":"CH",
    "sg:address":"Neulen 6",
    "sg:city":"Seon",
    "sg:orig_category":"Sportvereine Unihockey",
    "sg:phone":"+41 62 775 19 82",
    "sg:postcode":"5703",
    "sg:province":"Aargau",
    "wof:name":"Satus Lenzburg",
    "wof:placetype":"venue"
},
  "geometry": {"coordinates":[8.162612915,47.3527030945],"type":"Point"}
}