{
  "type": "Feature",
  "properties": {
    "iso:country":"CH",
    "sg:address":"Austrasse 37 9490 Vaduz. Postfach 2",
    "sg:city":"Vaduz",
    "sg:orig_category":"Unternehmensberatung",
    "sg:phone":"+423 235 50 00",
    "sg:postcode":"9490",
    "wof:name":"Abf Treuhand Ag",
    "wof:placetype":"venue"
},
  "geometry": {"coordinates":[9.5231208801,47.1295852661],"type":"Point"}
}