{
  "type": "Feature",
  "properties": {
    "iso:country":"CH",
    "sg:address":"Germaniastrasse 64 8006 Z\u00fcrich. Postfach",
    "sg:city":"Z\u00fcrich",
    "sg:orig_category":"Unternehmensberatung",
    "sg:phone":"+41 14923452",
    "sg:postcode":"8001",
    "sg:province":"Z\u00fcrich",
    "wof:name":"Giacometti Laurent Ag",
    "wof:placetype":"venue"
},
  "geometry": {"coordinates":[8.5524425507,47.3867759705],"type":"Point"}
}