{
  "type": "Feature",
  "properties": {
    "iso:country":"CH",
    "sg:address":"Rainstrasse 46",
    "sg:city":"Safnern",
    "sg:classifiers":[
        {
            "category":"Professional",
            "subcategory":"Credit Reporting & Collection",
            "type":"Services"
        }
    ],
    "sg:phone":"+41 32 933 93 93",
    "sg:postcode":"2553",
    "sg:province":"Bern",
    "sg:tags":[
        "dial"
    ],
    "wof:name":"Metalem S.a.",
    "wof:placetype":"venue"
},
  "geometry": {"coordinates":[6.757024,47.060974],"type":"Point"}
}