{
  "type": "Feature",
  "properties": {
    "iso:country":"CH",
    "sg:address":"Obere Plessurstrasse 39",
    "sg:city":"Chur",
    "sg:orig_category":"Architektur U Ingenieurb\u00fcros",
    "sg:postcode":"7000",
    "sg:province":"Graubunden",
    "wof:name":"Institut F\u00fcr Die Pr\u00fcfung Von Betonstahl Gmbh",
    "wof:placetype":"venue"
},
  "geometry": {"coordinates":[9.52663,46.849678],"type":"Point"}
}