{
  "type": "Feature",
  "properties": {
    "iso:country":"CH",
    "sg:address":"Rue Gourgas 25",
    "sg:city":"Gen\u00e8ve",
    "sg:orig_category":"Herstellung von Schreibwaren U B\u00fcrobedarf aus Papier, Karton U Pappe Herstellung von sonstigen Waren",
    "sg:phone":"+41 32 968 11 28",
    "sg:postcode":"1205",
    "sg:province":"Gen\u00e8ve",
    "wof:name":"Michel Feron Parel & Cie M. Feron Succ",
    "wof:placetype":"venue"
},
  "geometry": {"coordinates":[6.8276081085,47.1069221497],"type":"Point"}
}