{
  "type": "Feature",
  "properties": {
    "iso:country":"CH",
    "sg:address":"Seminarstrasse 102",
    "sg:city":"Wettingen",
    "sg:orig_category":"HERSTELLUNG VON GER\u00c4TEN DER ELEKTRIZIT\u00c4TSERZEUGUNG, -VERTEILUNG U.\u00c4",
    "sg:phone":"+41 55 240 25 31",
    "sg:postcode":"5430",
    "sg:province":"Aargau",
    "wof:name":"Ribolla Ag",
    "wof:placetype":"venue"
},
  "geometry": {"coordinates":[8.856803894,47.2583999634],"type":"Point"}
}