{
  "type": "Feature",
  "properties": {
    "iso:country":"CH",
    "sg:address":"Chesa Seraina 7457 Bivio. Postfach",
    "sg:city":"Bivio",
    "sg:orig_category":"Elektroinstallation",
    "sg:phone":"+41 22 342 45 00",
    "sg:postcode":"7457",
    "sg:province":"Graubunden",
    "wof:name":"Electro-alarme Installations \u00e9lectriques",
    "wof:placetype":"venue"
},
  "geometry": {"coordinates":[6.1339879036,46.1868667603],"type":"Point"}
}