{
  "type": "Feature",
  "properties": {
    "iso:country":"CH",
    "sg:address":"Schaffhauserstrasse 150",
    "sg:city":"Winterthur",
    "sg:orig_category":"Detailhandel mit Haustieren U zoologischem Bedarf Fachdetailhandel in Verkaufsr\u00e4umen",
    "sg:phone":"+41 32 913 88 55",
    "sg:postcode":"8400",
    "sg:province":"Z\u00fcrich",
    "wof:name":"Oisellerie De La Tour, Piaget B.",
    "wof:placetype":"venue"
},
  "geometry": {"coordinates":[6.8283901215,47.1009979248],"type":"Point"}
}