{
  "type": "Feature",
  "properties": {
    "iso:country":"CH",
    "sg:address":"Glasacker 16",
    "sg:city":"Dulliken",
    "sg:orig_category":"Detailhandel mit Metallwaren, Anstrichmitteln, Glaswaren, Bau U Heimwerkerbedarf",
    "sg:phone":"+41 62 295 04 05",
    "sg:postcode":"4657",
    "sg:province":"Solothurn",
    "wof:name":"Damont Engineering & Distribution P. Haefeli",
    "wof:placetype":"venue"
},
  "geometry": {"coordinates":[7.9411029816,47.3520698547],"type":"Point"}
}