{
  "type": "Feature",
  "properties": {
    "iso:country":"CH",
    "sg:address":"Langenthalstrasse 68",
    "sg:city":"Aarwangen",
    "sg:orig_category":"Mechanik Mechanische Werkst\u00e4tten",
    "sg:phone":"+41 62 923 96 80",
    "sg:postcode":"4912",
    "sg:province":"Bern",
    "wof:name":"Aebi",
    "wof:placetype":"venue"
},
  "geometry": {"coordinates":[7.7747850418,47.2333984375],"type":"Point"}
}