{
  "type": "Feature",
  "properties": {
    "iso:country":"CH",
    "sg:address":"La Tuor",
    "sg:city":"Scharans",
    "sg:orig_category":"Unternehmensberatung",
    "sg:postcode":"7412",
    "sg:province":"Graubunden",
    "wof:name":"Tuor Consulting Gmbh",
    "wof:placetype":"venue"
},
  "geometry": {"coordinates":[9.4577522278,46.7175254822],"type":"Point"}
}