{
  "type": "Feature",
  "properties": {
    "iso:country":"CH",
    "sg:address":"Im Herrengarten 8",
    "sg:city":"Pfeffingen",
    "sg:orig_category":"Unclassifiable Establishments",
    "sg:postcode":"4148",
    "sg:province":"Basel-Landschaft",
    "wof:name":"B\u00e4rlocher Toni, Consulting",
    "wof:placetype":"venue"
},
  "geometry": {"coordinates":[7.5893158913,47.4574623108],"type":"Point"}
}