{
  "type": "Feature",
  "properties": {
    "iso:country":"CH",
    "sg:address":"B\u00e4chlistrasse",
    "sg:city":"Lufingen",
    "sg:orig_category":"Gewinnung von Kies U Sand",
    "sg:phone":"+41 18143818",
    "sg:postcode":"8426",
    "sg:province":"Z\u00fcrich",
    "wof:name":"Kieswerk Lufingen Ag",
    "wof:placetype":"venue"
},
  "geometry": {"coordinates":[8.601975441,47.4920692444],"type":"Point"}
}