{
  "type": "Feature",
  "properties": {
    "iso:country":"CH",
    "sg:address":"Dorf",
    "sg:city":"Linden",
    "sg:orig_category":"Detailhandel mit Fleisch U Fleischwaren",
    "sg:phone":"+41 31 771 03 06",
    "sg:postcode":"3673",
    "sg:province":"Bern",
    "wof:name":"L\u00fcthi Paul",
    "wof:placetype":"venue"
},
  "geometry": {"coordinates":[7.6778001785,46.8477287292],"type":"Point"}
}