{
  "type": "Feature",
  "properties": {
    "iso:country":"CH",
    "sg:address":"Riedstrasse 7 6362 Stansstad. Postfach",
    "sg:city":"Stansstad",
    "sg:orig_category":"Instandhaltung U Reparatur von Automobilen",
    "sg:postcode":"6362",
    "sg:province":"Nidwalden",
    "wof:name":"Newia Handels Ag Fahrzeuge, Futtermittelprodukte; Vermittlung, Verkauf, Kauf. Beteiligungen Usw",
    "wof:placetype":"venue"
},
  "geometry": {"coordinates":[8.3378400803,46.9763526917],"type":"Point"}
}