{
  "type": "Feature",
  "properties": {
    "iso:country":"CH",
    "sg:address":"Altmattweg 57",
    "sg:city":"Olten",
    "sg:classifiers":[
        {
            "category":"Professional",
            "subcategory":"Art Services",
            "type":"Services"
        }
    ],
    "sg:phone":"+41 62 212 95 71",
    "sg:postcode":"4600",
    "sg:province":"Solothurn",
    "sg:tags":[
        "business",
        "brochures",
        "matters",
        "printed",
        "advertisement",
        "designing"
    ],
    "wof:name":"Dado Gmbh",
    "wof:placetype":"venue"
},
  "geometry": {"coordinates":[7.890937,47.349167],"type":"Point"}
}