{
  "type": "Feature",
  "properties": {
    "iso:country":"CH",
    "sg:address":"Stationsstrasse 4 6373 Ennetb\u00fcrgen. Postfach",
    "sg:city":"Ennetb\u00fcrgen",
    "sg:orig_category":"Elektroinstallation",
    "sg:postcode":"6373",
    "sg:province":"Nidwalden",
    "wof:name":"Elektro Odermatt Markus Gbmh Elektroinstallationen; Plaung Usw",
    "wof:placetype":"venue"
},
  "geometry": {"coordinates":[8.4143657684,46.9854354858],"type":"Point"}
}