{
  "type": "Feature",
  "properties": {
    "iso:country":"CH",
    "sg:address":"Remensberg",
    "sg:city":"Wuppenau",
    "sg:orig_category":"Detailhandel mit Milcherzeugnissen U Eiern Verarbeitung von Milch",
    "sg:phone":"+41 71 633 13 74",
    "sg:postcode":"9514",
    "sg:province":"Thurgau",
    "wof:name":"Werner Scherrer K\u00e4serei",
    "wof:placetype":"venue"
},
  "geometry": {"coordinates":[9.1146202087,47.5087089539],"type":"Point"}
}