{
  "type": "Feature",
  "properties": {
    "iso:country":"CH",
    "sg:address":"Via Dei Lauri 17",
    "sg:city":"Vacallo",
    "sg:orig_category":"Gymnastik U Fitnesszentren",
    "sg:phone":"+41 91 683 89 05",
    "sg:postcode":"6833",
    "sg:province":"Ticino",
    "wof:name":"Kfc Sa Centro Sportivo & Fitness",
    "wof:placetype":"venue"
},
  "geometry": {"coordinates":[9.0368499756,45.8425064087],"type":"Point"}
}