{
  "type": "Feature",
  "properties": {
    "iso:country":"CH",
    "sg:address":"Landstrasse 27",
    "sg:city":"M\u00f6hlin",
    "sg:orig_category":"Sanit\u00e4r U Heizungsinstallation Sanit\u00e4r, Heizungs U L\u00fcftungsinstallation",
    "sg:phone":"+41 61 841 25 75",
    "sg:postcode":"4313",
    "sg:province":"Aargau",
    "wof:name":"Fiechter Heizungen Ag",
    "wof:placetype":"venue"
},
  "geometry": {"coordinates":[7.8465509415,47.5534629822],"type":"Point"}
}