{
  "type": "Feature",
  "properties": {
    "iso:country":"CH",
    "sg:address":"Heidenlochstrasse 46",
    "sg:city":"Liestal",
    "sg:orig_category":"Grosshandel mit Nahrungsmitteln, Getr\u00e4nken U Tabakwaren ohne ausgepr\u00e4gten Schwerpunkt",
    "sg:postcode":"4410",
    "sg:province":"Basel-Landschaft",
    "wof:name":"Mago Smiljkovic",
    "wof:placetype":"venue"
},
  "geometry": {"coordinates":[7.7468519211,47.4833106995],"type":"Point"}
}