{
  "type": "Feature",
  "properties": {
    "iso:country":"CH",
    "sg:address":"Alte Bernstrasse 161",
    "sg:city":"Steffisburg",
    "sg:orig_category":"Herstellung von keramischen Haushaltswaren U Ziergegenst\u00e4nden",
    "sg:phone":"+41 33 437 33 81",
    "sg:postcode":"3613",
    "sg:province":"Bern",
    "wof:name":"Daniel St\u00e4hli T\u00f6pferei",
    "wof:placetype":"venue"
},
  "geometry": {"coordinates":[7.6158900261,46.77684021],"type":"Point"}
}