{
  "type": "Feature",
  "properties": {
    "iso:country":"CH",
    "sg:address":"Alte Landstrasse 130",
    "sg:city":"Zollikon",
    "sg:orig_category":"RESTAURANTS: TEA-ROOMS",
    "sg:postcode":"8702",
    "sg:province":"Z\u00fcrich",
    "wof:name":"Macola Ag",
    "wof:placetype":"venue"
},
  "geometry": {"coordinates":[8.5785903931,47.3335800171],"type":"Point"}
}