{
  "type": "Feature",
  "properties": {
    "iso:country":"CH",
    "sg:address":"Stapferstrasse 18",
    "sg:city":"Z\u00fcrich",
    "sg:orig_category":"Architektur U Ingenieurb\u00fcros",
    "sg:phone":"+41 79 207 42 51",
    "sg:postcode":"8006",
    "sg:province":"Z\u00fcrich",
    "wof:name":"Denecke + Partner Ag",
    "wof:placetype":"venue"
},
  "geometry": {"coordinates":[9.412686,47.432083],"type":"Point"}
}