{
  "type": "Feature",
  "properties": {
    "iso:country":"CH",
    "sg:address":"Badstrasse 2",
    "sg:city":"Ersigen",
    "sg:classifiers":[
        {
            "category":"Restaurant",
            "type":"Food & Drink"
        }
    ],
    "sg:phone":"+41 34 445 23 38",
    "sg:postcode":"3423",
    "sg:province":"Bern",
    "wof:name":"Restaurant Rudswilbad",
    "wof:placetype":"venue"
},
  "geometry": {"coordinates":[7.6085290909,47.0996246338],"type":"Point"}
}