{
  "type": "Feature",
  "properties": {
    "iso:country":"CH",
    "sg:address":"Industriestrasse 9 3210 Kerzers Case Postale. Postfach",
    "sg:city":"Kerzers",
    "sg:orig_category":"Grosshandel mit Obst U Gem\u00fcse",
    "sg:phone":"+41 31 750 11 11",
    "sg:postcode":"3210",
    "sg:province":"Fribourg",
    "wof:name":"Spavetti Ag Gem\u00fcse Engros",
    "wof:placetype":"venue"
},
  "geometry": {"coordinates":[7.1856460571,46.9694023132],"type":"Point"}
}