{
  "type": "Feature",
  "properties": {
    "iso:country":"CH",
    "sg:address":"M\u00fchlebachstrasse 52 8008 Z\u00fcrich. Postfach",
    "sg:city":"Z\u00fcrich",
    "sg:orig_category":"Public-Relations-Agenturen",
    "sg:phone":"+41 71 750 09 75",
    "sg:postcode":"8032",
    "sg:province":"Z\u00fcrich",
    "wof:name":"Jolanda Spirig-z\u00fcnd Medienarbeit",
    "wof:placetype":"venue"
},
  "geometry": {"coordinates":[9.5574560165,47.377986908],"type":"Point"}
}