{
  "type": "Feature",
  "properties": {
    "iso:country":"CH",
    "sg:address":"Haula",
    "sg:city":"Gurmels",
    "sg:orig_category":"Fahrschulen, Flugschulen",
    "sg:phone":"+41 79 222 46 65",
    "sg:postcode":"3212",
    "sg:province":"Fribourg",
    "wof:name":"Bruno Rawyler Autofahrschule",
    "wof:placetype":"venue"
},
  "geometry": {"coordinates":[7.267100811,47.1246185303],"type":"Point"}
}