{
  "type": "Feature",
  "properties": {
    "iso:country":"CH",
    "sg:address":"Bahnhofstrasse 8",
    "sg:city":"Oberuzwil",
    "sg:orig_category":"Grosshandel mit Textilien Grosshandel mit sonstigen Konsumg\u00fctern",
    "sg:phone":"+41 79 207 76 66",
    "sg:postcode":"9242",
    "sg:province":"St. Gallen",
    "wof:name":"Ek Trading Keller Erich",
    "wof:placetype":"venue"
},
  "geometry": {"coordinates":[9.1239624023,47.4311447144],"type":"Point"}
}