{
  "type": "Feature",
  "properties": {
    "iso:country":"CH",
    "sg:address":"Marzilistrasse 27",
    "sg:city":"Bern",
    "sg:orig_category":"B\u00e4ckereien Konditoreien",
    "sg:phone":"+41 31 311 75 55",
    "sg:postcode":"3005",
    "sg:province":"Bern",
    "wof:name":"F\u00fcrst Ag Feinb\u00e4ckerei-konditorei",
    "wof:placetype":"venue"
},
  "geometry": {"coordinates":[7.443608,46.942711],"type":"Point"}
}