{
  "type": "Feature",
  "properties": {
    "iso:country":"CH",
    "sg:address":"Ror\u00e4ckerstrasse 5",
    "sg:city":"Frauenfeld",
    "sg:orig_category":"Tierheime",
    "sg:phone":"+41 52 720 65 22",
    "sg:postcode":"8500",
    "sg:province":"Thurgau",
    "wof:name":"R\u00f6sli H\u00e4usermann Katzenheim",
    "wof:placetype":"venue"
},
  "geometry": {"coordinates":[8.8418512344,47.5662193298],"type":"Point"}
}