{
  "type": "Feature",
  "properties": {
    "iso:country":"CH",
    "sg:address":"B\u00e4lliz 36 3600 Thun. Postfach",
    "sg:city":"Thun",
    "sg:orig_category":"Grossbanken",
    "sg:phone":"+41 91 640 56 00",
    "sg:postcode":"3601",
    "sg:province":"Bern",
    "wof:name":"Credit Suisse",
    "wof:placetype":"venue"
},
  "geometry": {"coordinates":[8.8414697647,46.1437950134],"type":"Point"}
}