{
  "type": "Feature",
  "properties": {
    "iso:country":"CH",
    "sg:address":"R\u00fceggisingerstrasse 29",
    "sg:city":"Emmenbr\u00fccke",
    "sg:classifiers":[
        {
            "category":"Military Area",
            "subcategory":"Air Force Base",
            "type":"Public Place"
        }
    ],
    "sg:phone":"+41 41 269 01 11",
    "sg:postcode":"6020",
    "sg:province":"Luzern",
    "sg:tags":[
        "injection",
        "infusion",
        "pump"
    ],
    "wof:name":"B. Braun Medical Ag",
    "wof:placetype":"venue"
},
  "geometry": {"coordinates":[8.2775802612,47.0785865784],"type":"Point"}
}