{
  "type": "Feature",
  "properties": {
    "iso:country":"CH",
    "sg:address":"Route Des Roches",
    "sg:city":"Assens",
    "sg:orig_category":"Architektur U Ingenieurb\u00fcros Architekturb\u00fcros",
    "sg:phone":"+41 21 881 63 23",
    "sg:postcode":"1042",
    "sg:province":"Vaud",
    "wof:name":"Atelier D'architecture Favre J.-f. Et Pelet D. Sa",
    "wof:placetype":"venue"
},
  "geometry": {"coordinates":[6.62249,46.613049],"type":"Point"}
}