{
  "type": "Feature",
  "properties": {
    "iso:country":"CH",
    "sg:address":"1376 Goumoens-la-ville Case Postale 21",
    "sg:city":"Goumoens-la-ville",
    "sg:orig_category":"Non-Classified Establishments",
    "sg:phone":"+41 21 881 35 21",
    "sg:postcode":"1376",
    "sg:province":"Vaud",
    "wof:name":"Banque Raiffeisen Talent-menthue",
    "wof:placetype":"venue"
},
  "geometry": {"coordinates":[6.6045541763,46.6579742432],"type":"Point"}
}