{
  "type": "Feature",
  "properties": {
    "iso:country":"CH",
    "sg:address":"Kirschweg 9",
    "sg:city":"Arlesheim",
    "sg:orig_category":"Pensionskassen",
    "sg:phone":"+41 61 701 23 23",
    "sg:postcode":"4144",
    "sg:province":"Basel-Landschaft",
    "wof:name":"Vorsorgeeinrichtung Des Vereins F\u00fcr Krebsforschung.",
    "wof:placetype":"venue"
},
  "geometry": {"coordinates":[7.6135859489,47.4940719604],"type":"Point"}
}