{
  "type": "Feature",
  "properties": {
    "iso:country":"CH",
    "sg:address":"Obere Spichermatt 37",
    "sg:city":"Stans",
    "sg:orig_category":"Mit dem Versicherungsgewerbe verbundene T\u00e4tigkeiten",
    "sg:phone":"+41 41 611 11 11",
    "sg:postcode":"6370",
    "sg:province":"Nidwalden",
    "wof:name":"Jota Consult R.ambauen Neutrale Versicherungsberatung",
    "wof:placetype":"venue"
},
  "geometry": {"coordinates":[8.3589429855,46.9647903442],"type":"Point"}
}