{
  "type": "Feature",
  "properties": {
    "iso:country":"CH",
    "sg:address":"Bernex Rue De 293",
    "sg:city":"Bernex",
    "sg:orig_category":"Sonstige pers\u00f6nliche Dienstleistungen",
    "sg:postcode":"1233",
    "sg:province":"Gen\u00e8ve",
    "wof:name":"Keysign Sa",
    "wof:placetype":"venue"
},
  "geometry": {"coordinates":[6.0737948418,46.17552948],"type":"Point"}
}