{
  "type": "Feature",
  "properties": {
    "iso:country":"CH",
    "sg:address":"Via Vallemaggia 54 6600 Solduno Casella Postale",
    "sg:city":"Locarno",
    "sg:orig_category":"Bauschreinerei Herstellung von M\u00f6beln verschiedener Art",
    "sg:phone":"+41 91 791 16 43",
    "sg:postcode":"6604",
    "sg:province":"Ticino",
    "wof:name":"Pietro Zibetti Mobili Antichi & Restauri",
    "wof:placetype":"venue"
},
  "geometry": {"coordinates":[8.77772,46.170029],"type":"Point"}
}