{
  "type": "Feature",
  "properties": {
    "addr:full":"Hinterdorfstrasse 20 Mosnang St. Gallen 9607",
    "addr:housenumber":"20;st.",
    "addr:postcode":"9607",
    "addr:street":"Hinterdorfstrasse",
    "iso:country":"CH",
    "sg:address":"Hinterdorfstrasse 20",
    "sg:city":"Mosnang",
    "sg:orig_category":"Allgemeiner Hoch U Tiefbau Hoch U Tiefbau",
    "sg:phone":"+41 79 404 76 54",
    "sg:postcode":"9607",
    "sg:province":"St. Gallen",
    "wof:name":"Damian Oberh\u00e4nsli Bauunternehmung",
    "wof:placetype":"venue"
},
  "geometry": {"coordinates":[9.036442,47.363037],"type":"Point"}
}