{
  "type": "Feature",
  "properties": {
    "iso:country":"CH",
    "sg:address":"Solenbergstrasse 33",
    "sg:city":"Schaffhausen",
    "sg:classifiers":[
        {
            "category":"Taxi",
            "type":"Transportation"
        }
    ],
    "sg:phone":"+41 52 643 22 32",
    "sg:postcode":"8207",
    "sg:province":"Schaffhausen",
    "sg:tags":[
        "furniture"
    ],
    "wof:name":"Eichtrans Gmbh",
    "wof:placetype":"venue"
},
  "geometry": {"coordinates":[8.6715307236,47.7187843323],"type":"Point"}
}