{
  "type": "Feature",
  "properties": {
    "iso:country":"CH",
    "sg:address":"Grienbachstrasse 36 6300 Zug. Postfach",
    "sg:city":"Zug",
    "sg:orig_category":"Unclassifiable Establishments",
    "sg:phone":"+41 41 711 23 60",
    "sg:postcode":"6300",
    "sg:province":"Zug",
    "wof:name":"M & M Management & Marketing Ag",
    "wof:placetype":"venue"
},
  "geometry": {"coordinates":[8.5259389877,47.182144165],"type":"Point"}
}