{
  "type": "Feature",
  "properties": {
    "iso:country":"CH",
    "sg:address":"Zugerstrasse 31",
    "sg:city":"Cham",
    "sg:orig_category":"Architektur U Ingenieurb\u00fcros",
    "sg:phone":"+41 41 780 34 34",
    "sg:postcode":"6330",
    "sg:province":"Zug",
    "wof:name":"Meyer Rolf Architekturb\u00fcro Ag",
    "wof:placetype":"venue"
},
  "geometry": {"coordinates":[8.46359,47.181755],"type":"Point"}
}