{
  "type": "Feature",
  "properties": {
    "iso:country":"CH",
    "sg:address":"Furtstrasse 3",
    "sg:city":"Brunnadern",
    "sg:orig_category":"Grosshandel mit Getreide, Saatgut U Futtermitteln",
    "sg:phone":"+41 71 374 26 32",
    "sg:postcode":"9125",
    "sg:province":"St. Gallen",
    "wof:name":"As Studer A. Gmbh",
    "wof:placetype":"venue"
},
  "geometry": {"coordinates":[9.1378231049,47.3289299011],"type":"Point"}
}