{
  "type": "Feature",
  "properties": {
    "iso:country":"CH",
    "sg:address":"Im Oberen Letten 1",
    "sg:city":"Duggingen",
    "sg:orig_category":"Fachdetailhandel in Verkaufsr\u00e4umen",
    "sg:phone":"+41 61 751 41 52",
    "sg:postcode":"4202",
    "sg:province":"Basel-Landschaft",
    "wof:name":"Hiltbrunner Peter R. Numismatik",
    "wof:placetype":"venue"
},
  "geometry": {"coordinates":[7.609910965,47.4539871216],"type":"Point"}
}