{
  "type": "Feature",
  "properties": {
    "iso:country":"CH",
    "sg:address":"Cygnes Chemin Des 21",
    "sg:city":"Sugiez",
    "sg:orig_category":"Sonstige mit der Informatik verbundene T\u00e4tigkeiten",
    "sg:postcode":"1786",
    "sg:province":"Fribourg",
    "wof:name":"Vision Computer Consulting S\u00e0rl",
    "wof:placetype":"venue"
},
  "geometry": {"coordinates":[7.1079277992,46.957408905],"type":"Point"}
}