{
  "type": "Feature",
  "properties": {
    "iso:country":"CH",
    "sg:address":"Chemin De Roches 1",
    "sg:city":"Gen\u00e8ve",
    "sg:orig_category":"Zahnarztpraxen",
    "sg:phone":"+41 22 736 07 67",
    "sg:postcode":"1208",
    "sg:province":"Gen\u00e8ve",
    "wof:name":"Dr M\u00e9d.dent.rosa Maria Serrano M\u00e9decin-dentiste",
    "wof:placetype":"venue"
},
  "geometry": {"coordinates":[6.1618008614,46.199760437],"type":"Point"}
}