{
  "type": "Feature",
  "properties": {
    "iso:country":"CH",
    "sg:address":"Zelgstrasse",
    "sg:city":"Blankenburg",
    "sg:orig_category":"Sportvereine Turnen Vereine Damen",
    "sg:postcode":"3771",
    "sg:province":"Bern",
    "wof:name":"Damenturnverein Stv Zweisimmen",
    "wof:placetype":"venue"
},
  "geometry": {"coordinates":[7.3848590851,46.5467681885],"type":"Point"}
}