{
  "type": "Feature",
  "properties": {
    "addr:full":"Birmensdorferstrasse 140 Z\u00fcrich Z\u00fcrich 8003",
    "addr:housenumber":"140",
    "addr:postcode":"8003",
    "addr:street":"Birmensdorferstrasse",
    "iso:country":"CH",
    "sg:address":"Birmensdorferstrasse 140",
    "sg:city":"Z\u00fcrich",
    "sg:orig_category":"Wirtschaft U Handel, Arbeit, Allgemeines zum Thema Arbeit",
    "sg:phone":"+41 14519111",
    "sg:postcode":"8003",
    "sg:province":"Z\u00fcrich",
    "wof:name":"Boch Partner Die Schweizer Informatik Personalberatung",
    "wof:placetype":"venue"
},
  "geometry": {"coordinates":[8.520369,47.369858],"type":"Point"}
}