{
  "type": "Feature",
  "properties": {
    "iso:country":"CH",
    "sg:address":"Insstrasse 67",
    "sg:city":"M\u00fcntschemier",
    "sg:orig_category":"Einbau von Schreinerwaren",
    "sg:phone":"+41 32 313 70 30",
    "sg:postcode":"3225",
    "sg:province":"Bern",
    "wof:name":"Nightlife Ag",
    "wof:placetype":"venue"
},
  "geometry": {"coordinates":[7.1424818039,46.9959793091],"type":"Point"}
}