{
  "type": "Feature",
  "properties": {
    "iso:country":"CH",
    "sg:address":"Vignascia Via",
    "sg:city":"Agno",
    "sg:orig_category":"Detailhandel mit Waren verschiedener Art, Hauptrichtung Nichtnahrungsmittel",
    "sg:phone":"+41 91 605 25 73",
    "sg:postcode":"6982",
    "sg:province":"Ticino",
    "wof:name":"Zanovello Sagl",
    "wof:placetype":"venue"
},
  "geometry": {"coordinates":[8.9036550522,46.0112266541],"type":"Point"}
}