{
  "type": "Feature",
  "properties": {
    "iso:country":"CH",
    "sg:address":"Dammstrasse 36",
    "sg:city":"Solothurn",
    "sg:orig_category":"D\u00e4mmung gegen K\u00e4lte, W\u00e4rme, Schall U Ersch\u00fctterung",
    "sg:phone":"+41 32 622 64 36",
    "sg:postcode":"4500",
    "sg:province":"Solothurn",
    "wof:name":"Rolf Bloch K\u00e4lte-d\u00e4mmtechnik",
    "wof:placetype":"venue"
},
  "geometry": {"coordinates":[7.5318369865,47.2063102722],"type":"Point"}
}