{
  "type": "Feature",
  "properties": {
    "iso:country":"CH",
    "sg:address":"Contrada Maggiore 15",
    "sg:city":"Ascona",
    "sg:orig_category":"Detailhandel mit Geschenkartikeln U Souvenirs",
    "sg:phone":"+41 91 791 60 89",
    "sg:postcode":"6612",
    "sg:province":"Ticino",
    "wof:name":"Irene Calame Boutique Orientale",
    "wof:placetype":"venue"
},
  "geometry": {"coordinates":[8.7681837082,46.1551628113],"type":"Point"}
}