{
  "type": "Feature",
  "properties": {
    "iso:country":"CH",
    "sg:address":"Schaffhauserstrasse 499",
    "sg:city":"Z\u00fcrich",
    "sg:orig_category":"Detailhandel mit Waren verschiedener Art, Hauptrichtung Nahrungsmittel",
    "sg:phone":"+41 12020805",
    "sg:postcode":"8052",
    "sg:province":"Z\u00fcrich",
    "wof:name":"Pick Pay Betriebs Ag",
    "wof:placetype":"venue"
},
  "geometry": {"coordinates":[8.5498390198,47.4215698242],"type":"Point"}
}