{
  "type": "Feature",
  "properties": {
    "iso:country":"CH",
    "sg:address":"Rue Des Vergers 38",
    "sg:city":"Chippis",
    "sg:orig_category":"Maurerarbeiten",
    "sg:phone":"+41 27 455 07 02",
    "sg:postcode":"3965",
    "sg:province":"Valais",
    "wof:name":"Andr\u00e9 Burket Entreprise De Ma\u00e7onnerie",
    "wof:placetype":"venue"
},
  "geometry": {"coordinates":[7.5358939171,46.2802734375],"type":"Point"}
}