{
  "type": "Feature",
  "properties": {
    "iso:country":"CH",
    "sg:address":"Bahnhofstrasse 29 6300 Zug. Postfach",
    "sg:city":"Zug",
    "sg:orig_category":"Herstellung von k\u00e4lte U lufttechnischen Erzeugnissen f\u00fcr gewerbliche Zwecke",
    "sg:postcode":"6300",
    "sg:province":"Zug",
    "wof:name":"Klimont Gmbh",
    "wof:placetype":"venue"
},
  "geometry": {"coordinates":[8.5156650543,47.1704330444],"type":"Point"}
}