{
  "type": "Feature",
  "properties": {
    "iso:country":"CH",
    "sg:address":"Hauptgasse 7",
    "sg:city":"Lichtensteig",
    "sg:orig_category":"Detailhandel mit Uhren U Schmuck Fachdetailhandel in Verkaufsr\u00e4umen",
    "sg:phone":"+41 71 988 14 64",
    "sg:postcode":"9620",
    "sg:province":"St. Gallen",
    "wof:name":"Perret Ag Lichtensteig",
    "wof:placetype":"venue"
},
  "geometry": {"coordinates":[9.0874204636,47.3235321045],"type":"Point"}
}