{
  "type": "Feature",
  "properties": {
    "iso:country":"CH",
    "sg:address":"Thalerstrasse 8",
    "sg:city":"Rheineck",
    "sg:orig_category":"Detailhandel mit Brot, Back U S\u00fcsswaren",
    "sg:phone":"+41 32 753 27 75",
    "sg:postcode":"9424",
    "sg:province":"St. Gallen",
    "wof:name":"Bachmann Patrick",
    "wof:placetype":"venue"
},
  "geometry": {"coordinates":[6.960664,47.008167],"type":"Point"}
}