{
  "type": "Feature",
  "properties": {
    "iso:country":"CH",
    "sg:address":"Lammi",
    "sg:city":"Meiringen",
    "sg:orig_category":"RESTAURANTS: TEA-ROOMS",
    "sg:postcode":"3860",
    "sg:province":"Bern",
    "wof:name":"Adolf Schild-ast",
    "wof:placetype":"venue"
},
  "geometry": {"coordinates":[8.186214447,46.7278556824],"type":"Point"}
}