{
  "type": "Feature",
  "properties": {
    "addr:full":"Schneggenrain Schongau Luzern 6288",
    "addr:postcode":"6288",
    "addr:street":"Schneggenrain Schongau",
    "iso:country":"CH",
    "sg:address":"Schneggenrain",
    "sg:city":"Schongau",
    "sg:classifiers":[
        {
            "category":"Cinema",
            "subcategory":"Movie Rental",
            "type":"Entertainment"
        }
    ],
    "sg:phone":"+41 41 455 21 41",
    "sg:postcode":"6288",
    "sg:province":"Luzern",
    "sg:tags":[
        "film",
        "computer",
        "video",
        "animation",
        "cinematic"
    ],
    "wof:name":"Screenimage Gmbh",
    "wof:placetype":"venue"
},
  "geometry": {"coordinates":[8.390105,47.115139],"type":"Point"}
}