{
  "type": "Feature",
  "properties": {
    "iso:country":"CH",
    "sg:address":"Im Lee 11",
    "sg:city":"St\u00e4fa",
    "sg:orig_category":"Grosshandel mit Werkzeugmaschinen",
    "sg:phone":"+41 19532020",
    "sg:postcode":"8712",
    "sg:province":"Z\u00fcrich",
    "wof:name":"Schweiz. Maschinen Import Ag",
    "wof:placetype":"venue"
},
  "geometry": {"coordinates":[8.7689609528,47.3644218445],"type":"Point"}
}