{
  "type": "Feature",
  "properties": {
    "iso:country":"CH",
    "sg:address":"Mainaustrasse 24",
    "sg:city":"Z\u00fcrich",
    "sg:orig_category":"HOTELS: MIT RESTAURANT Kurhotels mit Restaurant",
    "sg:phone":"+41 12524270",
    "sg:postcode":"8008",
    "sg:province":"Z\u00fcrich",
    "wof:name":"Frauenhotel Ag",
    "wof:placetype":"venue"
},
  "geometry": {"coordinates":[8.5500650406,47.3604011536],"type":"Point"}
}