{
  "type": "Feature",
  "properties": {
    "iso:country":"CH",
    "sg:address":"Route Gd Lancy 109",
    "sg:city":"Grand Lancy",
    "sg:orig_category":"Dienstleistungen, Sicherheit",
    "sg:phone":"+41 22 793 51 71",
    "sg:postcode":"1212",
    "sg:province":"Gen\u00e8ve",
    "wof:name":"Pema Sicherheit Sa",
    "wof:placetype":"venue"
},
  "geometry": {"coordinates":[6.112628,46.18018],"type":"Point"}
}