{
  "type": "Feature",
  "properties": {
    "iso:country":"CH",
    "sg:address":"Hochhaus 6060 Sarnen. Postfach",
    "sg:city":"Sarnen",
    "sg:orig_category":"Maler U Glasergewerbe",
    "sg:phone":"+41 41 660 67 29",
    "sg:postcode":"6060",
    "sg:province":"Obwalden",
    "wof:name":"Malergesch\u00e4ft Schleiss",
    "wof:placetype":"venue"
},
  "geometry": {"coordinates":[8.246049881,46.9038887024],"type":"Point"}
}