{
  "type": "Feature",
  "properties": {
    "iso:country":"CH",
    "sg:address":"Wispel",
    "sg:city":"Grabs",
    "sg:orig_category":"Mahl U Sch\u00e4lm\u00fchlen",
    "sg:phone":"+41 81 771 60 77",
    "sg:postcode":"9472",
    "sg:province":"St. Gallen",
    "wof:name":"Stricker & Cie Ag Handels-& Kundenm\u00fchle",
    "wof:placetype":"venue"
},
  "geometry": {"coordinates":[9.4352235794,47.1794586182],"type":"Point"}
}