{
  "type": "Feature",
  "properties": {
    "iso:country":"CH",
    "sg:address":"Wilerstrasse 84",
    "sg:city":"Sirnach",
    "sg:orig_category":"Mechanik",
    "sg:postcode":"8370",
    "sg:province":"Thurgau",
    "wof:name":"Schneeberger F.",
    "wof:placetype":"venue"
},
  "geometry": {"coordinates":[9.0180597305,47.4634819031],"type":"Point"}
}