{
  "type": "Feature",
  "properties": {
    "iso:country":"CH",
    "sg:address":"Birkenweg 23 3902 Glis. Postfach",
    "sg:city":"Glis",
    "sg:orig_category":"Architektur U Ingenieurb\u00fcros",
    "sg:postcode":"3902",
    "sg:province":"Valais",
    "wof:name":"Architekturb\u00fcro Theler Remo",
    "wof:placetype":"venue"
},
  "geometry": {"coordinates":[7.971133,46.306496],"type":"Point"}
}