{
  "type": "Feature",
  "properties": {
    "iso:country":"CH",
    "sg:address":"Schulstrasse 11",
    "sg:city":"Islikon",
    "sg:orig_category":"Non-Classified Establishments",
    "sg:postcode":"8546",
    "sg:province":"Thurgau",
    "wof:name":"Dyneos Ag",
    "wof:placetype":"venue"
},
  "geometry": {"coordinates":[8.8418302536,47.5454711914],"type":"Point"}
}