{
  "type": "Feature",
  "properties": {
    "iso:country":"CH",
    "sg:address":"Obere Rebhalde 23",
    "sg:city":"Baar",
    "sg:orig_category":"Pensionskassen",
    "sg:phone":"+41 61 961 09 04",
    "sg:postcode":"6340",
    "sg:province":"Zug",
    "wof:name":"Bvg-stiftung Der Firma Thommen & Pergher Ag",
    "wof:placetype":"venue"
},
  "geometry": {"coordinates":[7.7480387688,47.3968696594],"type":"Point"}
}