{
  "type": "Feature",
  "properties": {
    "iso:country":"CH",
    "sg:address":"Tr\u00fcebebach",
    "sg:city":"Sch\u00fcpfheim",
    "sg:orig_category":"Grosshandel mit Nahrungsmitteln, Getr\u00e4nken U Tabakwaren ohne ausgepr\u00e4gten Schwerpunkt",
    "sg:postcode":"6170",
    "sg:province":"Luzern",
    "wof:name":"Portmann-bieri Hans Lebensmittel",
    "wof:placetype":"venue"
},
  "geometry": {"coordinates":[8.0177154541,46.9497261047],"type":"Point"}
}