{
  "type": "Feature",
  "properties": {
    "iso:country":"CH",
    "sg:address":"Via Alle Scuole",
    "sg:city":"Taverne",
    "sg:orig_category":"Detailhandel mit M\u00f6beln Detailhandel mit M\u00f6beln U Haushaltsgegenst\u00e4nden",
    "sg:phone":"+41 91 945 26 68",
    "sg:postcode":"6807",
    "sg:province":"Ticino",
    "wof:name":"Prince Fernand",
    "wof:placetype":"venue"
},
  "geometry": {"coordinates":[8.9333286285,46.0671730042],"type":"Point"}
}