{
  "type": "Feature",
  "properties": {
    "iso:country":"CH",
    "sg:address":"Wiesenstrasse 2",
    "sg:city":"Dussnang",
    "sg:orig_category":"Wirtschaftspr\u00fcfung, Steuerberatung U Treuhand",
    "sg:phone":"+41 71 913 33 77",
    "sg:postcode":"8374",
    "sg:province":"Thurgau",
    "wof:name":"Uv-treuhand F\u00fcr Landwirtschaft & Gewerbe",
    "wof:placetype":"venue"
},
  "geometry": {"coordinates":[8.9615926743,47.4358024597],"type":"Point"}
}