{
  "type": "Feature",
  "properties": {
    "iso:country":"CH",
    "sg:address":"Friedenstrasse 15",
    "sg:city":"Arbon",
    "sg:orig_category":"Installation von Heizungs, L\u00fcftungs U Klimaanlagen Sanit\u00e4r U Heizungsinstallation",
    "sg:phone":"+41 71 688 23 23",
    "sg:postcode":"9320",
    "sg:province":"Thurgau",
    "wof:name":"H\u00e4lg & Co Ag Heizung Feuerung Klima K\u00e4lte Heizung Klima",
    "wof:placetype":"venue"
},
  "geometry": {"coordinates":[9.4320287704,47.5160102844],"type":"Point"}
}