{
  "type": "Feature",
  "properties": {
    "iso:country":"CH",
    "sg:address":"Im B\u00fcel 10 9548 Matzingen. Postfach",
    "sg:city":"Matzingen",
    "sg:orig_category":"Hochschulen U h\u00f6here Ausbildung",
    "sg:postcode":"9548",
    "sg:province":"Thurgau",
    "wof:name":"Praxis F\u00fcr Therapie + Schulung M\u00fcller Patrick",
    "wof:placetype":"venue"
},
  "geometry": {"coordinates":[8.9341287613,47.5199813843],"type":"Point"}
}