{
  "type": "Feature",
  "properties": {
    "iso:country":"CH",
    "sg:address":"Unter-neuhus 11",
    "sg:city":"Ruswil",
    "sg:orig_category":"Detailhandel mit Metallwaren, Anstrichmitteln, Glaswaren, Bau U Heimwerkerbedarf",
    "sg:phone":"+41 79 418 37 68",
    "sg:postcode":"6017",
    "sg:province":"Luzern",
    "wof:name":"Wermelinger A. Ag",
    "wof:placetype":"venue"
},
  "geometry": {"coordinates":[8.1145648956,47.0873565674],"type":"Point"}
}