{
  "type": "Feature",
  "properties": {
    "iso:country":"CH",
    "sg:address":"Arboner Strasse 25",
    "sg:city":"Amriswil",
    "sg:orig_category":"Grosshandel mit chemischen Erzeugnissen Grosshandel mit medizinischen U orthop\u00e4dischen Artikeln",
    "sg:phone":"+41 71 410 08 70",
    "sg:postcode":"8580",
    "sg:province":"Thurgau",
    "wof:name":"Pangas-center Amriswil Gas-fachmarkt & Lieferstelle",
    "wof:placetype":"venue"
},
  "geometry": {"coordinates":[9.3032827377,47.5446128845],"type":"Point"}
}