{
  "type": "Feature",
  "properties": {
    "iso:country":"CH",
    "sg:address":"Delfterstrasse 41",
    "sg:city":"Aarau",
    "sg:orig_category":"Fachdetailhandel in Verkaufsr\u00e4umen",
    "sg:phone":"+41 62 824 17 03",
    "sg:postcode":"5004",
    "sg:province":"Aargau",
    "wof:name":"Triff Ag",
    "wof:placetype":"venue"
},
  "geometry": {"coordinates":[8.0617198944,47.402381897],"type":"Point"}
}