{
  "type": "Feature",
  "properties": {
    "iso:country":"CH",
    "sg:address":"Schwarztorstrasse 11",
    "sg:city":"Bern",
    "sg:orig_category":"RESTAURANTS: TEA-ROOMS",
    "sg:postcode":"3007",
    "sg:province":"Bern",
    "wof:name":"Witsch Ana-maria Und Helmut",
    "wof:placetype":"venue"
},
  "geometry": {"coordinates":[7.4360451698,46.9428901672],"type":"Point"}
}