{
  "type": "Feature",
  "properties": {
    "iso:country":"CH",
    "sg:address":"B\u00fchlerstrasse 24",
    "sg:city":"Wettswil",
    "sg:orig_category":"Unternehmensberatung",
    "sg:postcode":"8907",
    "sg:province":"Z\u00fcrich",
    "wof:name":"Ccm Services S\u00e0rl Conseils D'entreprise Et R\u00e9daction D'ouvrages Et Articles",
    "wof:placetype":"venue"
},
  "geometry": {"coordinates":[6.1182661057,46.2307548523],"type":"Point"}
}