{
  "type": "Feature",
  "properties": {
    "iso:country":"CH",
    "sg:address":"Parkstrasse 16",
    "sg:city":"Brunnen",
    "sg:classifiers":[
        {
            "category":"Bars & Pubs",
            "type":"Food & Drink"
        }
    ],
    "sg:phone":"+41 41 820 30 30",
    "sg:postcode":"6440",
    "sg:province":"Schwyz",
    "wof:name":"Idris Kulac, Restaurationsbetriebe",
    "wof:placetype":"venue"
},
  "geometry": {"coordinates":[8.604782,46.998184],"type":"Point"}
}