{
  "type": "Feature",
  "properties": {
    "iso:country":"CH",
    "sg:address":"Industriestrasse 620",
    "sg:city":"Oberbuchsiten",
    "sg:orig_category":"G\u00fcterbef\u00f6rderung im Strassenverkehr",
    "sg:phone":"+41 62 389 66 44",
    "sg:postcode":"4625",
    "sg:province":"Solothurn",
    "wof:name":"G. Leclerc Transport Ag",
    "wof:placetype":"venue"
},
  "geometry": {"coordinates":[7.7769799232,47.308139801],"type":"Point"}
}