{
  "type": "Feature",
  "properties": {
    "iso:country":"CH",
    "sg:address":"Dorfstrasse",
    "sg:city":"Halden",
    "sg:orig_category":"Malerei",
    "sg:phone":"+41 79 645 06 47",
    "sg:postcode":"9223",
    "sg:province":"Thurgau",
    "wof:name":"Karl K\u00fcng Malergesch\u00e4ft",
    "wof:placetype":"venue"
},
  "geometry": {"coordinates":[7.54164505,47.5082244873],"type":"Point"}
}