{
  "type": "Feature",
  "properties": {
    "iso:country":"CH",
    "sg:address":"Obere Gasse 14a",
    "sg:city":"Felsberg",
    "sg:orig_category":"Maler U Glasergewerbe Malerei",
    "sg:phone":"+41 79 620 61 11",
    "sg:postcode":"7012",
    "sg:province":"Graubunden",
    "wof:name":"Camastral Gmbh Felsberg",
    "wof:placetype":"venue"
},
  "geometry": {"coordinates":[9.4698438644,46.8456954956],"type":"Point"}
}