{
  "type": "Feature",
  "properties": {
    "iso:country":"CH",
    "sg:address":"Gysulastrasse 25",
    "sg:city":"Aarau",
    "sg:classifiers":[
        {
            "category":"Insurance",
            "subcategory":"Insurance Agent",
            "type":"Services"
        }
    ],
    "sg:phone":"+41 62 822 61 85",
    "sg:postcode":"5000",
    "sg:province":"Aargau",
    "sg:tags":[
        "versicherungsagenturen",
        "-broker"
    ],
    "wof:name":"Rudolf Neuenschwander Winterthur-versicherungen",
    "wof:placetype":"venue"
},
  "geometry": {"coordinates":[8.0432319641,47.3994407654],"type":"Point"}
}