{
  "type": "Feature",
  "properties": {
    "iso:country":"CH",
    "sg:address":"T\u00f6sstalstrasse 8",
    "sg:city":"Wallenwil",
    "sg:orig_category":"Einbau von Schreinerwaren Herstellung von K\u00fcchenm\u00f6beln",
    "sg:phone":"+41 41 210 55 67",
    "sg:postcode":"8360",
    "sg:province":"Thurgau",
    "wof:name":"Hansar-k\u00fcchen Ag",
    "wof:placetype":"venue"
},
  "geometry": {"coordinates":[8.3059444427,47.0454063416],"type":"Point"}
}