{
  "type": "Feature",
  "properties": {
    "iso:country":"CH",
    "sg:address":"Bahnhofstrasse 20",
    "sg:city":"Subingen",
    "sg:classifiers":[
        {
            "category":"Restaurant",
            "type":"Food & Drink"
        }
    ],
    "sg:phone":"+41 32 614 16 08",
    "sg:postcode":"4553",
    "sg:province":"Solothurn",
    "wof:name":"Restaurant Bahnhof",
    "wof:placetype":"venue"
},
  "geometry": {"coordinates":[7.6122360229,47.1933822632],"type":"Point"}
}