{
  "type": "Feature",
  "properties": {
    "iso:country":"CH",
    "sg:address":"Untere Z\u00e4une 3 8001 Z\u00fcrich. Postfach",
    "sg:city":"Z\u00fcrich",
    "sg:orig_category":"Sonstige pers\u00f6nliche Dienstleistungen",
    "sg:postcode":"8001",
    "sg:province":"Z\u00fcrich",
    "wof:name":"Bba Nonwovens Asia-pacific Ag",
    "wof:placetype":"venue"
},
  "geometry": {"coordinates":[8.5468902588,47.370967865],"type":"Point"}
}