{
  "type": "Feature",
  "properties": {
    "iso:country":"CH",
    "sg:address":"Fellerstrasse 28",
    "sg:city":"Bern",
    "sg:orig_category":"Sportschulen Fern\u00f6stliche Kampfsportarten",
    "sg:phone":"+41 31 311 44 52",
    "sg:postcode":"3027",
    "sg:province":"Bern",
    "wof:name":"Traditionel Schotokan Karate Schweiz",
    "wof:placetype":"venue"
},
  "geometry": {"coordinates":[7.3899168968,46.94713974],"type":"Point"}
}