{
  "type": "Feature",
  "properties": {
    "iso:country":"CH",
    "sg:address":"Hauptstrasse 6a",
    "sg:city":"Kradolf",
    "sg:orig_category":"Innendekorationsateliers",
    "sg:phone":"+41 71 642 14 49",
    "sg:postcode":"9214",
    "sg:province":"Thurgau",
    "wof:name":"Louis & Trudy Feller Wohnstudio",
    "wof:placetype":"venue"
},
  "geometry": {"coordinates":[9.200097084,47.5249443054],"type":"Point"}
}