{
  "type": "Feature",
  "properties": {
    "iso:country":"CH",
    "sg:address":"Schaffhauserstrasse 110",
    "sg:city":"Glattbrugg",
    "sg:orig_category":"Verlagsgewerbe",
    "sg:phone":"+41 18101231",
    "sg:postcode":"8152",
    "sg:province":"Z\u00fcrich",
    "wof:name":"Thema Cards Verlag Theophil Maag",
    "wof:placetype":"venue"
},
  "geometry": {"coordinates":[8.5657157898,47.4332313538],"type":"Point"}
}