{
  "type": "Feature",
  "properties": {
    "iso:country":"CH",
    "sg:address":"Stockackerstrasse 8 4142 M\u00fcnchenstein. Postfach",
    "sg:city":"M\u00fcnchenstein",
    "sg:orig_category":"Reparatur von Schuhen U Lederwaren",
    "sg:postcode":"4142",
    "sg:province":"Basel-Landschaft",
    "wof:name":"Asel Gmbh",
    "wof:placetype":"venue"
},
  "geometry": {"coordinates":[7.606938839,47.5207977295],"type":"Point"}
}