{
  "type": "Feature",
  "properties": {
    "iso:country":"CH",
    "sg:address":"Plazzet 22",
    "sg:city":"Samedan",
    "sg:classifiers":[
        {
            "category":"Government",
            "subcategory":"Post Office",
            "type":"Public Place"
        }
    ],
    "sg:phone":"+41 81 852 36 34",
    "sg:postcode":"7503",
    "sg:province":"Graubunden",
    "sg:tags":[
        "caf\u00e9s",
        "tea-rooms"
    ],
    "wof:name":"Caf\u00e9 Laager",
    "wof:placetype":"venue"
},
  "geometry": {"coordinates":[9.8729295731,46.535861969],"type":"Point"}
}