{
  "type": "Feature",
  "properties": {
    "iso:country":"CH",
    "sg:address":"Sch\u00f6neggstrasse 10",
    "sg:city":"Biel/bienne",
    "sg:orig_category":"Reiseb\u00fcros U Reiseveranstalter",
    "sg:postcode":"2502",
    "sg:province":"Bern",
    "wof:name":"Ademas Sa",
    "wof:placetype":"venue"
},
  "geometry": {"coordinates":[7.248524189,47.131477356],"type":"Point"}
}