{
  "type": "Feature",
  "properties": {
    "iso:country":"CH",
    "sg:address":"Dorfstrasse 17",
    "sg:city":"Goldingen",
    "sg:orig_category":"Gemeindeverwaltungen",
    "sg:phone":"+41 55 284 62 00",
    "sg:postcode":"8638",
    "sg:province":"St. Gallen",
    "wof:name":"Gemeindeverwaltung Goldingen",
    "wof:placetype":"venue"
},
  "geometry": {"coordinates":[8.9647817612,47.2630195618],"type":"Point"}
}