{
  "type": "Feature",
  "properties": {
    "iso:country":"CH",
    "sg:address":"Chemin De Cocagne 61",
    "sg:city":"Bussigny-lausanne",
    "sg:orig_category":"Sportvereine Flug Delta",
    "sg:phone":"+41 26 470 03 04",
    "sg:postcode":"1030",
    "sg:province":"Vaud",
    "wof:name":"Club De Vol Libre De La Gruy\u00e8re",
    "wof:placetype":"venue"
},
  "geometry": {"coordinates":[7.0232000351,46.6070785522],"type":"Point"}
}