{
  "type": "Feature",
  "properties": {
    "iso:country":"CH",
    "sg:address":"Z\u00fcrichstrasse 7",
    "sg:city":"Luzern",
    "sg:orig_category":"Immobilien U Baugewerbe, Sonstige Immobiliendienstleistungen",
    "sg:phone":"+41 41 410 31 17",
    "sg:postcode":"6004",
    "sg:province":"Luzern",
    "wof:name":"Lbb L\u00f6wen Bau Und Betriebs Ag",
    "wof:placetype":"venue"
},
  "geometry": {"coordinates":[8.31031,47.05658],"type":"Point"}
}