{
  "type": "Feature",
  "properties": {
    "iso:country":"CH",
    "sg:address":"Chr\u00e4enbachstrasse 4",
    "sg:city":"Zufikon",
    "sg:orig_category":"Herstellung von Margarine u.\u00e4. Nahrungsfetten Herstellung von raffinierten \u00d6len U Fetten",
    "sg:postcode":"5621",
    "sg:province":"Aargau",
    "wof:name":"Hans Kaspar Ag Produkte F. Backstube & K\u00fcche",
    "wof:placetype":"venue"
},
  "geometry": {"coordinates":[8.3512201309,47.3447189331],"type":"Point"}
}