{
  "type": "Feature",
  "properties": {
    "iso:country":"CH",
    "sg:address":"Oberdorfstrasse 14",
    "sg:city":"B\u00fctschwil",
    "sg:orig_category":"Detailhandel mit Brot, Back U S\u00fcsswaren Detailhandel mit Waren verschiedener Art, Hauptrichtung Nahr",
    "sg:phone":"+41 71 983 16 48",
    "sg:postcode":"9606",
    "sg:province":"St. Gallen",
    "wof:name":"Senn Erwin, B\u00e4ckerei-lebensmittel",
    "wof:placetype":"venue"
},
  "geometry": {"coordinates":[9.07017,47.358768],"type":"Point"}
}