{
  "type": "Feature",
  "properties": {
    "iso:country":"CH",
    "sg:address":"La Sarvaz",
    "sg:city":"Saillon",
    "sg:orig_category":"Herstellung von Metallkonstruktionen",
    "sg:phone":"+41 79 414 94 73",
    "sg:postcode":"1913",
    "sg:province":"Valais",
    "wof:name":"Actu-metal S\u00e0rl",
    "wof:placetype":"venue"
},
  "geometry": {"coordinates":[6.8369669914,47.103767395],"type":"Point"}
}