{
  "type": "Feature",
  "properties": {
    "iso:country":"CH",
    "sg:address":"Fliederweg 4",
    "sg:city":"W\u00fcrenlingen",
    "sg:orig_category":"Sanit\u00e4r U Heizungsinstallation Sanit\u00e4rinstallation",
    "sg:phone":"+41 56 281 24 00",
    "sg:postcode":"5303",
    "sg:province":"Aargau",
    "wof:name":"Bruno Schneider San.installationen & Heizungen",
    "wof:placetype":"venue"
},
  "geometry": {"coordinates":[8.2501049042,47.5275001526],"type":"Point"}
}