{
  "type": "Feature",
  "properties": {
    "iso:country":"CH",
    "sg:address":"Grynaustrasse 21",
    "sg:city":"Uznach",
    "sg:orig_category":"Autogaragen Handel mit Automobilen",
    "sg:phone":"+41 71 388 78 68",
    "sg:postcode":"8730",
    "sg:province":"St. Gallen",
    "wof:name":"Secar Automobile Ag",
    "wof:placetype":"venue"
},
  "geometry": {"coordinates":[9.253769,47.416912],"type":"Point"}
}