{
  "type": "Feature",
  "properties": {
    "iso:country":"CH",
    "sg:address":"3970",
    "sg:city":"Salgesch",
    "sg:orig_category":"Campingpl\u00e4tze",
    "sg:phone":"+41 27 455 11 21",
    "sg:postcode":"3970",
    "sg:province":"Valais",
    "wof:name":"Camping Les Mazots Roland Dalliard",
    "wof:placetype":"venue"
},
  "geometry": {"coordinates":[7.569615,46.311401],"type":"Point"}
}