{
  "type": "Feature",
  "properties": {
    "iso:country":"CH",
    "sg:address":"Surseestrasse 55",
    "sg:city":"Neuenkirch",
    "sg:orig_category":"Herstellung von Maschinen f\u00fcr die Nahrungsmittel, Getr\u00e4nkeherstellung U die Tabakverarbeitung",
    "sg:phone":"+41 41 468 05 50",
    "sg:postcode":"6206",
    "sg:province":"Luzern",
    "wof:name":"Gelamatic Ag",
    "wof:placetype":"venue"
},
  "geometry": {"coordinates":[8.2011356354,47.1034812927],"type":"Point"}
}