{
  "type": "Feature",
  "properties": {
    "iso:country":"CH",
    "sg:address":"Hardturmstrasse 185",
    "sg:city":"Z\u00fcrich",
    "sg:orig_category":"Grosshandel mit Obst U Gem\u00fcse",
    "sg:phone":"+41 71 755 57 35",
    "sg:postcode":"8005",
    "sg:province":"Z\u00fcrich",
    "wof:name":"Buschor E.",
    "wof:placetype":"venue"
},
  "geometry": {"coordinates":[9.5401906967,47.3775520325],"type":"Point"}
}