{
  "type": "Feature",
  "properties": {
    "iso:country":"CH",
    "sg:address":"Gottfried Keller-strasse 5",
    "sg:city":"Z\u00fcrich",
    "sg:orig_category":"Werbung",
    "sg:postcode":"8001",
    "sg:province":"Z\u00fcrich",
    "wof:name":"Aktiebolaget Leng, Tenhult, Zweigniederlassung Z\u00fcrich. Reklame; Verkauf. Maschinen; Herst., Verkauf",
    "wof:placetype":"venue"
},
  "geometry": {"coordinates":[8.547044754,47.3661766052],"type":"Point"}
}