{
  "type": "Feature",
  "properties": {
    "iso:country":"CH",
    "sg:address":"Entfelderstrasse 16 5000 Aarau. Postfach",
    "sg:city":"Aarau",
    "sg:orig_category":"Umwelt\u00e4mter",
    "sg:phone":"+41 41 872 12 05",
    "sg:postcode":"5001",
    "sg:province":"Aargau",
    "wof:name":"Kant. Amt F\u00fcr Umweltschutz",
    "wof:placetype":"venue"
},
  "geometry": {"coordinates":[8.6527042389,46.8747024536],"type":"Point"}
}