{
  "type": "Feature",
  "properties": {
    "iso:country":"CH",
    "sg:address":"Schachenstrasse 77",
    "sg:city":"Jona",
    "sg:orig_category":"Interessenvertretungen",
    "sg:postcode":"8645",
    "sg:province":"St. Gallen",
    "wof:name":"Geberit-stiftung F\u00fcr Kultur",
    "wof:placetype":"venue"
},
  "geometry": {"coordinates":[8.8163518906,47.2262649536],"type":"Point"}
}