{
  "type": "Feature",
  "properties": {
    "iso:country":"CH",
    "sg:address":"Mattenstrasse 3",
    "sg:city":"Grenchen",
    "sg:orig_category":"Pensionskassen",
    "sg:phone":"+41 71 244 29 29",
    "sg:postcode":"2540",
    "sg:province":"Solothurn",
    "wof:name":"Personalf\u00fcrsorgefond Der Foto Gross Ag",
    "wof:placetype":"venue"
},
  "geometry": {"coordinates":[9.3922424316,47.4305686951],"type":"Point"}
}