{
  "type": "Feature",
  "properties": {
    "iso:country":"CH",
    "sg:address":"1532",
    "sg:city":"F\u00e9tigny",
    "sg:orig_category":"Vorschulen, Kinderg\u00e4rten",
    "sg:phone":"+41 26 660 25 11",
    "sg:postcode":"1532",
    "sg:province":"Fribourg",
    "wof:name":"Ecole Enfantine",
    "wof:placetype":"venue"
},
  "geometry": {"coordinates":[6.9136800766,46.7945709229],"type":"Point"}
}