{
  "type": "Feature",
  "properties": {
    "iso:country":"CH",
    "sg:address":"Windm\u00fclistrasse 3",
    "sg:city":"G\u00fcttingen",
    "sg:orig_category":"Softwareentwicklung U beratung",
    "sg:phone":"+41 71 690 06 60",
    "sg:postcode":"8594",
    "sg:province":"Thurgau",
    "wof:name":"Omw-informatik, Wetzel O.",
    "wof:placetype":"venue"
},
  "geometry": {"coordinates":[9.2848777771,47.6067047119],"type":"Point"}
}