{
  "type": "Feature",
  "properties": {
    "iso:country":"CH",
    "sg:address":"Neumattstrasse 29 5000 Aarau. Postfach",
    "sg:city":"Aarau",
    "sg:orig_category":"Lagerh\u00e4user, G\u00fcterumschlag, Verteilzentren",
    "sg:postcode":"5004",
    "sg:province":"Aargau",
    "wof:name":"Hangartner Terminal Ag Bau, Erstellung, Betrieb Des Kombiterminals Domo 2 Usw",
    "wof:placetype":"venue"
},
  "geometry": {"coordinates":[8.0653171539,47.4002723694],"type":"Point"}
}