{
  "type": "Feature",
  "properties": {
    "iso:country":"CH",
    "sg:address":"Langacker 141",
    "sg:city":"Ruggell",
    "sg:orig_category":"Erdbewegungsarbeiten G\u00fcterbef\u00f6rderung im Strassenverkehr",
    "sg:phone":"+41 79 696 65 24",
    "sg:postcode":"9491",
    "wof:name":"Eugen B\u00fcchel Ag Transporte Baggerbetrieb",
    "wof:placetype":"venue"
},
  "geometry": {"coordinates":[9.5237340927,47.2355422974],"type":"Point"}
}