{
  "type": "Feature",
  "properties": {
    "iso:country":"CH",
    "sg:address":"Grienstrasse 12",
    "sg:city":"Niederlenz",
    "sg:orig_category":"Unclassifiable Establishments",
    "sg:phone":"+41 62 891 57 73",
    "sg:postcode":"5702",
    "sg:province":"Aargau",
    "wof:name":"Blatter-simmen",
    "wof:placetype":"venue"
},
  "geometry": {"coordinates":[8.1731309891,47.4024848938],"type":"Point"}
}