{
  "type": "Feature",
  "properties": {
    "iso:country":"CH",
    "sg:address":"3714 Frutigen. Postfach 73",
    "sg:city":"Frutigen",
    "sg:orig_category":"Sportvereine Ballsport Fussball",
    "sg:phone":"+41 32 653 14 68",
    "sg:postcode":"3714",
    "sg:province":"Bern",
    "wof:name":"Fc Fulgor",
    "wof:placetype":"venue"
},
  "geometry": {"coordinates":[7.3994002342,47.1928787231],"type":"Point"}
}