{
  "type": "Feature",
  "properties": {
    "iso:country":"CH",
    "sg:address":"B\u00fcntenackerweg 19",
    "sg:city":"Ziefen",
    "sg:orig_category":"Geb\u00e4ude, Wohnungsreinigung Reinigungsgewerbe",
    "sg:phone":"+41 61 931 37 57",
    "sg:postcode":"4417",
    "sg:province":"Basel-Landschaft",
    "wof:name":"Miru-clean Gmbh Neubaureinigungen",
    "wof:placetype":"venue"
},
  "geometry": {"coordinates":[7.6991472244,47.4271583557],"type":"Point"}
}