{
  "type": "Feature",
  "properties": {
    "iso:country":"CH",
    "sg:address":"Ergolzstrasse 4",
    "sg:city":"Pratteln",
    "sg:orig_category":"G\u00fcterbef\u00f6rderung im Strassenverkehr",
    "sg:postcode":"4133",
    "sg:province":"Basel-Landschaft",
    "wof:name":"Walter Eugster",
    "wof:placetype":"venue"
},
  "geometry": {"coordinates":[7.7130379677,47.530632019],"type":"Point"}
}