{
  "type": "Feature",
  "properties": {
    "iso:country":"CH",
    "sg:address":"Neudorfstrasse 33 8820 W\u00e4denswil. Postfach 467",
    "sg:city":"W\u00e4denswil",
    "sg:orig_category":"Architekturb\u00fcros",
    "sg:phone":"+41 31 839 60 66",
    "sg:postcode":"8820",
    "sg:province":"Z\u00fcrich",
    "wof:name":"J\u00fcrg Mauerhofer Architekturb\u00fcro",
    "wof:placetype":"venue"
},
  "geometry": {"coordinates":[7.56338,46.929745],"type":"Point"}
}