{
  "type": "Feature",
  "properties": {
    "iso:country":"CH",
    "sg:address":"Via Pierino Tatti 3",
    "sg:city":"Bellinzona",
    "sg:orig_category":"Grosshandel mit B\u00fcromaschinen Grosshandel mit Datenverarbeitungsger\u00e4ten",
    "sg:phone":"+41 91 826 41 72",
    "sg:postcode":"6500",
    "sg:province":"Ticino",
    "wof:name":"Studio Informatica 3000 Sa",
    "wof:placetype":"venue"
},
  "geometry": {"coordinates":[9.0141372681,46.1892318726],"type":"Point"}
}