{
  "type": "Feature",
  "properties": {
    "iso:country":"CH",
    "sg:address":"Nusshaldenstrasse 19",
    "sg:city":"D\u00f6ttingen",
    "sg:orig_category":"Sonstige mit der Informatik verbundene T\u00e4tigkeiten",
    "sg:postcode":"5312",
    "sg:province":"Aargau",
    "wof:name":"Vid Vigh Informatik-dienstleistungen",
    "wof:placetype":"venue"
},
  "geometry": {"coordinates":[8.2609376907,47.5742378235],"type":"Point"}
}