{
  "type": "Feature",
  "properties": {
    "iso:country":"CH",
    "sg:address":"2610",
    "sg:city":"St-imier",
    "sg:orig_category":"Unclassifiable Establishments",
    "sg:postcode":"2610",
    "sg:province":"Bern",
    "wof:name":"Socomoso",
    "wof:placetype":"venue"
},
  "geometry": {"coordinates":[6.9958171844,47.1520423889],"type":"Point"}
}