{
  "type": "Feature",
  "properties": {
    "iso:country":"CH",
    "sg:address":"Grand'clos Chemin Du 3",
    "sg:city":"Vouvry",
    "sg:orig_category":"Vermietung U Verpachtung von eigenen Immobilien",
    "sg:postcode":"1896",
    "sg:province":"Valais",
    "wof:name":"Jardil Sa",
    "wof:placetype":"venue"
},
  "geometry": {"coordinates":[6.8297801018,47.1029129028],"type":"Point"}
}