{
  "type": "Feature",
  "properties": {
    "iso:country":"CH",
    "sg:address":"Bergstrasse 8",
    "sg:city":"Adlikon",
    "sg:classifiers":[
        {
            "category":"Insurance",
            "subcategory":"Insurance Agent",
            "type":"Services"
        }
    ],
    "sg:phone":"+41 61 751 47 45",
    "sg:postcode":"8452",
    "sg:province":"Z\u00fcrich",
    "sg:tags":[
        "versicherungsagenturen",
        "-broker"
    ],
    "wof:name":"Winterthur-leben Vorsorgeberatung",
    "wof:placetype":"venue"
},
  "geometry": {"coordinates":[7.5973057747,47.4679832458],"type":"Point"}
}