{
  "type": "Feature",
  "properties": {
    "iso:country":"CH",
    "sg:address":"Cresciano",
    "sg:city":"Cresciano",
    "sg:classifiers":[
        {
            "category":"Banks & Credit Unions",
            "subcategory":"Bank",
            "type":"Services"
        }
    ],
    "sg:phone":"+41 91 735 16 40",
    "sg:postcode":"6705",
    "sg:province":"Ticino",
    "wof:name":"Banca Raiffeisen Gordola E Valle Verzasca",
    "wof:placetype":"venue"
},
  "geometry": {"coordinates":[8.86042,46.180931],"type":"Point"}
}