{
  "type": "Feature",
  "properties": {
    "iso:country":"CH",
    "sg:address":"W\u00fclflingerstrasse 59 8400 Winterthur. Postfach 33",
    "sg:city":"Winterthur",
    "sg:orig_category":"Architektur U Ingenieurb\u00fcros Grosshandel mit sonstigen Maschinen U Ausr\u00fcstungen f\u00fcr Industrie, Hande",
    "sg:phone":"+41 52 222 72 25",
    "sg:postcode":"8407",
    "wof:name":"Befag Verfahrenstechnik Ag",
    "wof:placetype":"venue"
},
  "geometry": {"coordinates":[8.713571,47.506474],"type":"Point"}
}