{
  "type": "Feature",
  "properties": {
    "iso:country":"CH",
    "sg:address":"Vogelsangstrasse 14",
    "sg:city":"Effretikon",
    "sg:orig_category":"Herstellung von Bergwerks U Baumaschinen Herstellung von elektrischen Lampen U Leuchten",
    "sg:phone":"+41 52 355 12 33",
    "sg:postcode":"8307",
    "sg:province":"Z\u00fcrich",
    "wof:name":"Neofas Ag",
    "wof:placetype":"venue"
},
  "geometry": {"coordinates":[8.6825590134,47.4201507568],"type":"Point"}
}