{
  "type": "Feature",
  "properties": {
    "iso:country":"CH",
    "sg:address":"Rue Du Concert 6",
    "sg:city":"Neuch\u00e2tel",
    "sg:orig_category":"Herstellung von Uhren",
    "sg:postcode":"2000",
    "sg:province":"Neuch\u00e2tel",
    "wof:name":"Compset Sa",
    "wof:placetype":"venue"
},
  "geometry": {"coordinates":[6.9306921959,46.991355896],"type":"Point"}
}