{
  "type": "Feature",
  "properties": {
    "iso:country":"CH",
    "sg:address":"Zi Nord Le Piollet 27",
    "sg:city":"Estavayer-le-lac",
    "sg:orig_category":"Bauschreinerei Zimmerei, Dachdeckerei, Bauspenglerei U Abdichtung",
    "sg:phone":"+41 26 663 30 04",
    "sg:postcode":"1470",
    "sg:province":"Fribourg",
    "wof:name":"Staviabois Sa",
    "wof:placetype":"venue"
},
  "geometry": {"coordinates":[6.851187,46.842686],"type":"Point"}
}