{
  "type": "Feature",
  "properties": {
    "iso:country":"CH",
    "sg:address":"M\u00fchlentalstrasse 5",
    "sg:city":"Schaffhausen",
    "sg:orig_category":"Fotografisches Gewerbe U fotografische Laboratorien",
    "sg:phone":"+41 52 625 59 53",
    "sg:postcode":"8200",
    "sg:province":"Schaffhausen",
    "wof:name":"Hasler Heinz Gmbh",
    "wof:placetype":"venue"
},
  "geometry": {"coordinates":[8.6314573288,47.6995353699],"type":"Point"}
}