{
  "type": "Feature",
  "properties": {
    "iso:country":"CH",
    "sg:address":"Schmidgass 2",
    "sg:city":"Sch\u00fcpfheim",
    "sg:orig_category":"Wirtschaftspr\u00fcfung, Steuerberatung U Treuhand",
    "sg:postcode":"6170",
    "sg:province":"Luzern",
    "wof:name":"Pt Portmann Treuhand",
    "wof:placetype":"venue"
},
  "geometry": {"coordinates":[8.0182466507,46.953125],"type":"Point"}
}