{
  "type": "Feature",
  "properties": {
    "iso:country":"CH",
    "sg:address":"Rue Des Chenevi\u00e8res 1a",
    "sg:city":"Courroux",
    "sg:orig_category":"Detailhandel mit elektrischen Haushalts-,Radio U Fernsehger\u00e4ten sowie Musikinstrumenten",
    "sg:phone":"+41 32 422 81 39",
    "sg:postcode":"2822",
    "sg:province":"Jura",
    "wof:name":"Discovery, Ventura & Montavon",
    "wof:placetype":"venue"
},
  "geometry": {"coordinates":[7.3702402115,47.364730835],"type":"Point"}
}