{
  "type": "Feature",
  "properties": {
    "iso:country":"CH",
    "sg:address":"Fola Via 6963 Pregassona. Postfach",
    "sg:city":"Pregassona",
    "sg:orig_category":"Vermietung U Verpachtung von eigenen Immobilien",
    "sg:postcode":"6963",
    "sg:province":"Ticino",
    "wof:name":"Siseg Ii",
    "wof:placetype":"venue"
},
  "geometry": {"coordinates":[6.1685729027,46.2022781372],"type":"Point"}
}