{
  "type": "Feature",
  "properties": {
    "iso:country":"CH",
    "sg:address":"Route Cantonale 65",
    "sg:city":"V\u00e9troz",
    "sg:orig_category":"Architektur U Ingenieurb\u00fcros",
    "sg:phone":"+41 27 346 10 56",
    "sg:postcode":"1963",
    "sg:province":"Valais",
    "wof:name":"Paul Germanier Bureau D'ing\u00e9nieur",
    "wof:placetype":"venue"
},
  "geometry": {"coordinates":[7.284941,46.225628],"type":"Point"}
}