{
  "type": "Feature",
  "properties": {
    "iso:country":"CH",
    "sg:address":"Pilatusstrasse 11",
    "sg:city":"Luzern",
    "sg:orig_category":"Parf\u00fcmerien U sonstiger Detailhandel mit kosmetischen Artikeln U K\u00f6rperpflegemitteln",
    "sg:phone":"+41 56 631 11 65",
    "sg:postcode":"6003",
    "sg:province":"Luzern",
    "wof:name":"Alrodo Ag",
    "wof:placetype":"venue"
},
  "geometry": {"coordinates":[8.3488235474,47.3519325256],"type":"Point"}
}