{
  "type": "Feature",
  "properties": {
    "iso:country":"CH",
    "sg:address":"Riedhalde",
    "sg:city":"Churwalden",
    "sg:orig_category":"Reinigungsgewerbe",
    "sg:phone":"+41 79 605 84 48",
    "sg:postcode":"7075",
    "sg:province":"Graubunden",
    "wof:name":"Schmid Ren\u00e9, Rs-reinigungen",
    "wof:placetype":"venue"
},
  "geometry": {"coordinates":[9.543800354,46.7785453796],"type":"Point"}
}