{
  "type": "Feature",
  "properties": {
    "iso:country":"CH",
    "sg:address":"Reiterstrasse 1 4054 Basel. Postfach",
    "sg:city":"Basel",
    "sg:classifiers":[
        {
            "category":"Travel",
            "subcategory":"Hotels & Motels",
            "type":"Entertainment"
        }
    ],
    "sg:phone":"+41 81 832 11 75",
    "sg:postcode":"4015",
    "sg:province":"Basel-Stadt",
    "sg:tags":[
        "hotels",
        "mit",
        "restaurant"
    ],
    "wof:name":"Hotel Europa Ag St. Moritz",
    "wof:placetype":"venue"
},
  "geometry": {"coordinates":[9.8381910324,46.4970664978],"type":"Point"}
}