{
  "type": "Feature",
  "properties": {
    "iso:country":"CH",
    "sg:address":"Sonnenbergstrasse 6",
    "sg:city":"Sarnen",
    "sg:orig_category":"Forschung U Entwicklung im Bereich der Naturwissenschaften Grosshandel mit sonstigen Nahrungsmitteln",
    "sg:phone":"+41 41 662 22 62",
    "sg:postcode":"6060",
    "sg:province":"Obwalden",
    "wof:name":"Mohs Development",
    "wof:placetype":"venue"
},
  "geometry": {"coordinates":[8.2403764725,46.896282196],"type":"Point"}
}