{
  "type": "Feature",
  "properties": {
    "addr:full":"Rue De La Baye 5 Montreux Vaud 1820",
    "addr:housenumber":"5",
    "addr:postcode":"1820",
    "addr:street":"Rue De La Baye",
    "iso:country":"CH",
    "sg:address":"Rue De La Baye 5",
    "sg:city":"Montreux",
    "sg:orig_category":"Berufsbildende weiterf\u00fchrende Schulen",
    "sg:phone":"+41 22 735 93 88",
    "sg:postcode":"1820",
    "sg:province":"Vaud",
    "wof:name":"Ecole Professionnelle Par Correspondance Sa",
    "wof:placetype":"venue"
},
  "geometry": {"coordinates":[6.917396,46.433933],"type":"Point"}
}