{
  "type": "Feature",
  "properties": {
    "iso:country":"CH",
    "sg:address":"Alte Zurzacherstrasse 34",
    "sg:city":"Tegerfelden",
    "sg:orig_category":"Instandhaltung U Reparatur von Automobilen",
    "sg:phone":"+41 56 245 36 38",
    "sg:postcode":"5306",
    "sg:province":"Aargau",
    "wof:name":"Minet Roger Garage. Fahrzeuge; Handel U. Reparatur",
    "wof:placetype":"venue"
},
  "geometry": {"coordinates":[8.2869338989,47.564907074],"type":"Point"}
}