{
  "type": "Feature",
  "properties": {
    "iso:country":"CH",
    "sg:address":"Tannacker 5",
    "sg:city":"Jens",
    "sg:orig_category":"Unternehmensberatung",
    "sg:phone":"+41 32 333 20 01",
    "sg:postcode":"2565",
    "sg:province":"Bern",
    "wof:name":"Praecept Management Gmbh",
    "wof:placetype":"venue"
},
  "geometry": {"coordinates":[7.2616548538,47.1016159058],"type":"Point"}
}