{
  "type": "Feature",
  "properties": {
    "iso:country":"CH",
    "sg:address":"Dytikerhof 4",
    "sg:city":"Dielsdorf",
    "sg:orig_category":"Bauschreinerei Glaserei",
    "sg:phone":"+41 18531913",
    "sg:postcode":"8157",
    "sg:province":"Z\u00fcrich",
    "wof:name":"Walter Vontobel Schreinerei & Glaserei",
    "wof:placetype":"venue"
},
  "geometry": {"coordinates":[8.450453,47.471359],"type":"Point"}
}