{
  "type": "Feature",
  "properties": {
    "iso:country":"CH",
    "sg:address":"Aegertenstrasse 11a",
    "sg:city":"Brugg",
    "sg:orig_category":"Aluminium-Glass Fa\u00e7ades",
    "sg:phone":"+41 56 441 43 41",
    "sg:postcode":"5200",
    "sg:province":"Aargau",
    "wof:name":"Delfosse Ag",
    "wof:placetype":"venue"
},
  "geometry": {"coordinates":[8.224749,47.493038],"type":"Point"}
}