{
  "type": "Feature",
  "properties": {
    "iso:country":"CH",
    "sg:address":"Eichstrasse 39 6330 Cham. Postfach 564",
    "sg:city":"Cham",
    "sg:orig_category":"Grosshandel mit Erzen U Metallen",
    "sg:phone":"+41 41 780 46 55",
    "sg:postcode":"6330",
    "sg:province":"Zug",
    "wof:name":"Wieland (schweiz) Ag",
    "wof:placetype":"venue"
},
  "geometry": {"coordinates":[8.4721908569,47.1845283508],"type":"Point"}
}