{
  "type": "Feature",
  "properties": {
    "iso:country":"CH",
    "sg:address":"Im Blatt D",
    "sg:city":"Neuheim",
    "sg:orig_category":"Maschinen-Fabrikation",
    "sg:postcode":"6345",
    "sg:province":"Zug",
    "wof:name":"Magtra Ag",
    "wof:placetype":"venue"
},
  "geometry": {"coordinates":[8.5742845535,47.1988143921],"type":"Point"}
}