{
  "type": "Feature",
  "properties": {
    "iso:country":"CH",
    "sg:address":"8754 Netstal. Postfach 176",
    "sg:city":"Netstal",
    "sg:orig_category":"Kauf U Verkauf von Immobilien auf eigene Rechnung Vermittlung von Immobilien",
    "sg:phone":"+41 56 633 08 88",
    "sg:postcode":"8754",
    "sg:province":"Glarus",
    "wof:name":"Stefo Immobilien + Verwaltung P. Stettler",
    "wof:placetype":"venue"
},
  "geometry": {"coordinates":[8.3559093475,47.354675293],"type":"Point"}
}