{
  "type": "Feature",
  "properties": {
    "iso:country":"CH",
    "sg:address":"Bahnhofstrasse 30",
    "sg:city":"Flums",
    "sg:orig_category":"Fachdetailhandel mit pharmazeutischen Produkten",
    "sg:phone":"+41 81 733 44 88",
    "sg:postcode":"8890",
    "sg:province":"St. Gallen",
    "wof:name":"Sonnen-apotheke, Rou\u00e8che Christophe",
    "wof:placetype":"venue"
},
  "geometry": {"coordinates":[9.3448324203,47.0934486389],"type":"Point"}
}