{
  "type": "Feature",
  "properties": {
    "iso:country":"CH",
    "sg:address":"6386",
    "sg:city":"Wolfenschiessen",
    "sg:orig_category":"Wasserversorgung",
    "sg:postcode":"6386",
    "sg:province":"Nidwalden",
    "wof:name":"Wasserversorgungsgenossenschaft D\u00f6rfli, Wolfenschiessen.",
    "wof:placetype":"venue"
},
  "geometry": {"coordinates":[8.3956546783,46.9103431702],"type":"Point"}
}