{
  "type": "Feature",
  "properties": {
    "iso:country":"CH",
    "sg:address":"Industriestrasse 1",
    "sg:city":"Aadorf",
    "sg:orig_category":"Instandhaltung U Reparatur von Automobilen",
    "sg:phone":"+41 52 365 44 44",
    "sg:postcode":"8355",
    "sg:province":"Thurgau",
    "wof:name":"Carrosserie Fisch",
    "wof:placetype":"venue"
},
  "geometry": {"coordinates":[8.9028940201,47.4967079163],"type":"Point"}
}