{
  "type": "Feature",
  "properties": {
    "iso:country":"CH",
    "sg:address":"Insstrasse 2",
    "sg:city":"M\u00fcntschemier",
    "sg:orig_category":"Gem\u00fcsebau",
    "sg:phone":"+41 32 313 27 82",
    "sg:postcode":"3225",
    "sg:province":"Bern",
    "wof:name":"Wilhelm L\u00f6ffel-k\u00f6nig Gem\u00fcsebau",
    "wof:placetype":"venue"
},
  "geometry": {"coordinates":[7.1419811249,46.9963111877],"type":"Point"}
}