{
  "type": "Feature",
  "properties": {
    "iso:country":"CH",
    "sg:address":"Zentweg 11 3000 Bern. Postfach 745",
    "sg:city":"Bern",
    "sg:orig_category":"Herstellung von k\u00e4lte U lufttechnischen Erzeugnissen f\u00fcr gewerbliche Zwecke",
    "sg:phone":"+41 31 331 97 97",
    "sg:postcode":"3014",
    "sg:province":"Bern",
    "wof:name":"St\u00e4fa Wirz Ventilator Ag Bern",
    "wof:placetype":"venue"
},
  "geometry": {"coordinates":[7.4739279747,46.9574546814],"type":"Point"}
}