{
  "type": "Feature",
  "properties": {
    "iso:country":"CH",
    "sg:address":"Ch. Des Prises 3",
    "sg:city":"Couvet",
    "sg:orig_category":"Zimmerei, Dachdeckerei, Bauspenglerei U Abdichtung",
    "sg:phone":"+41 32 863 27 57",
    "sg:postcode":"2108",
    "sg:province":"Neuch\u00e2tel",
    "wof:name":"Simonin P. & Fils S\u00e0rl",
    "wof:placetype":"venue"
},
  "geometry": {"coordinates":[6.6364278793,46.9242401123],"type":"Point"}
}