{
  "type": "Feature",
  "properties": {
    "addr:full":"Luzernerstrasse 57 Ebikon Luzern 6030",
    "addr:housenumber":"57",
    "addr:postcode":"6030",
    "addr:street":"Luzernerstrasse",
    "iso:country":"CH",
    "sg:address":"Luzernerstrasse 57",
    "sg:city":"Ebikon",
    "sg:classifiers":[
        {
            "category":"Manufacturing",
            "subcategory":"Motor Vehicles & Parts",
            "type":"Manufacturing & Wholesale Goods"
        }
    ],
    "sg:phone":"+41 41 420 75 00",
    "sg:postcode":"6030",
    "sg:province":"Luzern",
    "sg:tags":[
        "body",
        "car"
    ],
    "wof:name":"Rotsee Automobile Ag",
    "wof:placetype":"venue"
},
  "geometry": {"coordinates":[8.323519,47.071236],"type":"Point"}
}