{
  "type": "Feature",
  "properties": {
    "iso:country":"CH",
    "sg:address":"Berne Rue De 7 1201 Gen\u00e8ve Case Postale 1642",
    "sg:city":"Gen\u00e8ve",
    "sg:orig_category":"Softwareentwicklung U beratung",
    "sg:phone":"+41 71 750 02 31",
    "sg:postcode":"1201",
    "sg:province":"Gen\u00e8ve",
    "wof:name":"Infopart Ag",
    "wof:placetype":"venue"
},
  "geometry": {"coordinates":[9.5398769379,47.3772697449],"type":"Point"}
}