{
  "type": "Feature",
  "properties": {
    "iso:country":"CH",
    "sg:address":"Hottingerstrasse 38",
    "sg:city":"Z\u00fcrich",
    "sg:orig_category":"Detailhandel mit Damenbekleidung",
    "sg:phone":"+41 12510104",
    "sg:postcode":"8032",
    "sg:province":"Z\u00fcrich",
    "wof:name":"Kleiderb\u00f6rse Agnes",
    "wof:placetype":"venue"
},
  "geometry": {"coordinates":[8.553923,47.369274],"type":"Point"}
}