{
  "type": "Feature",
  "properties": {
    "iso:country":"CH",
    "sg:address":"Route De Certoux 155",
    "sg:city":"Perly",
    "sg:classifiers":[
        {
            "category":"Utilities",
            "subcategory":"Cable",
            "type":"Services"
        }
    ],
    "sg:phone":"+41 22 771 26 65",
    "sg:postcode":"1258",
    "sg:province":"Gen\u00e8ve",
    "sg:tags":[
        "glazing"
    ],
    "wof:name":"Atelverre Imp\u00e9ratori Sa",
    "wof:placetype":"venue"
},
  "geometry": {"coordinates":[6.0784101486,46.1570053101],"type":"Point"}
}