{
  "type": "Feature",
  "properties": {
    "iso:country":"CH",
    "sg:address":"Lindenbergstrasse 6a",
    "sg:city":"H\u00fcnenberg",
    "sg:orig_category":"Erwachsenenbildung U Unterricht",
    "sg:phone":"+41 41 780 40 17",
    "sg:postcode":"6331",
    "sg:province":"Zug",
    "wof:name":"Trinler Peter, Project Management",
    "wof:placetype":"venue"
},
  "geometry": {"coordinates":[8.4268226624,47.1792488098],"type":"Point"}
}