{
  "type": "Feature",
  "properties": {
    "iso:country":"CH",
    "sg:address":"Weiherwiesstrasse 6",
    "sg:city":"Arnegg",
    "sg:orig_category":"Hoch U Tiefbau",
    "sg:phone":"+41 71 385 80 66",
    "sg:postcode":"9212",
    "sg:province":"St. Gallen",
    "wof:name":"Bruno Wider Baugesch\u00e4ft",
    "wof:placetype":"venue"
},
  "geometry": {"coordinates":[9.257144928,47.4390106201],"type":"Point"}
}