{
  "type": "Feature",
  "properties": {
    "iso:country":"CH",
    "sg:address":"Saumstrasse 11",
    "sg:city":"Z\u00fcrich",
    "sg:orig_category":"Detailhandel mit Radio U Fernsehger\u00e4ten",
    "sg:phone":"+41 14630777",
    "sg:postcode":"8003",
    "sg:province":"Z\u00fcrich",
    "wof:name":"Peter Kaufmann Hi-fi-anlagen",
    "wof:placetype":"venue"
},
  "geometry": {"coordinates":[8.513551712,47.3708114624],"type":"Point"}
}