{
  "type": "Feature",
  "properties": {
    "iso:country":"CH",
    "sg:address":"Allmendstrasse 28",
    "sg:city":"Interlaken",
    "sg:orig_category":"Grosshandel mit medizinischen U orthop\u00e4dischen Artikeln",
    "sg:phone":"+41 33 823 28 88",
    "sg:postcode":"3800",
    "sg:province":"Bern",
    "wof:name":"Werner Ritschard Ritschard Servotec Instruments",
    "wof:placetype":"venue"
},
  "geometry": {"coordinates":[7.8694009781,46.6864700317],"type":"Point"}
}