{
  "type": "Feature",
  "properties": {
    "iso:country":"CH",
    "sg:address":"Leimen",
    "sg:city":"Eggiwil",
    "sg:orig_category":"Detailhandel mit Bekleidung Detailhandel mit Spielwaren",
    "sg:phone":"+41 55 210 40 15",
    "sg:postcode":"3537",
    "sg:province":"Bern",
    "wof:name":"Schlitner I.",
    "wof:placetype":"venue"
},
  "geometry": {"coordinates":[8.816008,47.226009],"type":"Point"}
}