{
  "type": "Feature",
  "properties": {
    "iso:country":"CH",
    "sg:address":"P\u00e4chterriedstrasse 75",
    "sg:city":"Watt",
    "sg:orig_category":"Primarschulen",
    "sg:phone":"+41 33 733 34 30",
    "sg:postcode":"8105",
    "sg:province":"Z\u00fcrich",
    "wof:name":"Primarschule P\u00f6schenried",
    "wof:placetype":"venue"
},
  "geometry": {"coordinates":[7.46434021,46.4307403564],"type":"Point"}
}