{
  "type": "Feature",
  "properties": {
    "iso:country":"CH",
    "sg:address":"6930",
    "sg:city":"Bedano",
    "sg:orig_category":"RESTAURANTS: TEA-ROOMS",
    "sg:postcode":"6930",
    "sg:province":"Ticino",
    "wof:name":"Paltenghi E Sabbioni.",
    "wof:placetype":"venue"
},
  "geometry": {"coordinates":[8.917090416,46.0536994934],"type":"Point"}
}