{
  "type": "Feature",
  "properties": {
    "iso:country":"CH",
    "sg:address":"Bahnhofstrasse",
    "sg:city":"T\u00e4sch",
    "sg:orig_category":"Grosshandel mit Nahrungsmitteln, Getr\u00e4nken U Tabakwaren ohne ausgepr\u00e4gten Schwerpunkt",
    "sg:phone":"+41 27 967 36 06",
    "sg:postcode":"3929",
    "sg:province":"Valais",
    "wof:name":"Imboden Franz",
    "wof:placetype":"venue"
},
  "geometry": {"coordinates":[7.7768750191,46.0669593811],"type":"Point"}
}