{
  "type": "Feature",
  "properties": {
    "iso:country":"CH",
    "sg:address":"Schauenburgerstrasse 8",
    "sg:city":"Frenkendorf",
    "sg:orig_category":"Berufliche Weiterbildung, Erwachsenenbildung Erwachsenenbildung U Unterricht",
    "sg:phone":"+41 61 901 20 64",
    "sg:postcode":"4402",
    "sg:province":"Basel-Landschaft",
    "wof:name":"Georges Grob Ag F\u00fchrungsseminare",
    "wof:placetype":"venue"
},
  "geometry": {"coordinates":[7.713109,47.502907],"type":"Point"}
}