{
  "type": "Feature",
  "properties": {
    "iso:country":"CH",
    "sg:address":"Etraz Rue 5 1003 Lausanne. Postfach",
    "sg:city":"Lausanne",
    "sg:orig_category":"Unclassifiable Establishments",
    "sg:postcode":"1003",
    "sg:province":"Vaud",
    "wof:name":"Soci\u00e9t\u00e9 Fonci\u00e8re Palud B Sa",
    "wof:placetype":"venue"
},
  "geometry": {"coordinates":[6.6384949684,46.519493103],"type":"Point"}
}