{
  "type": "Feature",
  "properties": {
    "iso:country":"CH",
    "sg:address":"Alleeweg 24a",
    "sg:city":"Rheinfelden",
    "sg:orig_category":"Wirtschaftspr\u00fcfung, Steuerberatung U Treuhand",
    "sg:phone":"+41 61 831 29 61",
    "sg:postcode":"4310",
    "sg:province":"Aargau",
    "wof:name":"Hirzel Treuhand Gmbh",
    "wof:placetype":"venue"
},
  "geometry": {"coordinates":[7.7921900749,47.5492095947],"type":"Point"}
}