{
  "type": "Feature",
  "properties": {
    "addr:full":"Gfennstrasse 16 8603 Schwerzenbach. Postfach Schwerzenbach Z\u00fcrich 8603",
    "addr:housenumber":"16",
    "addr:postcode":"8603 schwerzenbach. postfach;8603",
    "addr:street":"Gfennstrasse",
    "iso:country":"CH",
    "sg:address":"Gfennstrasse 16 8603 Schwerzenbach. Postfach",
    "sg:city":"Schwerzenbach",
    "sg:orig_category":"Chemische Industrie Herstellung von sonstigen organischen Grundstoffen U Chemikalien",
    "sg:phone":"+41 18252080",
    "sg:postcode":"8603",
    "sg:province":"Z\u00fcrich",
    "wof:name":"Ferrovit Ag",
    "wof:placetype":"venue"
},
  "geometry": {"coordinates":[8.649197,47.383694],"type":"Point"}
}