{
  "type": "Feature",
  "properties": {
    "iso:country":"CH",
    "sg:address":"Friedheimweg 24 /1",
    "sg:city":"Weggis",
    "sg:orig_category":"Innenarchitekturb\u00fcros",
    "sg:phone":"+41 41 390 38 88",
    "sg:postcode":"6353",
    "sg:province":"Luzern",
    "wof:name":"Raum-harmonie Gmbh",
    "wof:placetype":"venue"
},
  "geometry": {"coordinates":[8.4216995239,47.032409668],"type":"Point"}
}