{
  "type": "Feature",
  "properties": {
    "iso:country":"CH",
    "sg:address":"9494",
    "sg:city":"Schaan",
    "sg:orig_category":"Vereine Vogel-& Naturschutz",
    "sg:postcode":"9494",
    "wof:name":"Ornitholog.verein.vaduz",
    "wof:placetype":"venue"
},
  "geometry": {"coordinates":[9.5097951889,47.1668434143],"type":"Point"}
}