{
  "type": "Feature",
  "properties": {
    "iso:country":"CH",
    "sg:address":"Benknerstrasse 25",
    "sg:city":"Kaltbrunn",
    "sg:orig_category":"Bauspenglerei Sanit\u00e4rinstallation",
    "sg:phone":"+41 55 283 16 50",
    "sg:postcode":"8722",
    "sg:province":"St. Gallen",
    "wof:name":"Konrad Jud Spenglerei & Sanit\u00e4re Anlagen",
    "wof:placetype":"venue"
},
  "geometry": {"coordinates":[9.024244,47.210785],"type":"Point"}
}