{
  "type": "Feature",
  "properties": {
    "iso:country":"CH",
    "sg:address":"Bahnhofplatz",
    "sg:city":"Engelberg",
    "sg:orig_category":"Erbringung von sonstigen Dienstleistungen f\u00fcr Unterhaltung, Erholung U Freizeit",
    "sg:phone":"+41 41 611 14 41",
    "sg:postcode":"6390",
    "sg:province":"Obwalden",
    "wof:name":"Outventure Ag Bungy Jumping, Canyoning",
    "wof:placetype":"venue"
},
  "geometry": {"coordinates":[8.4030704498,46.8194961548],"type":"Point"}
}