{
  "type": "Feature",
  "properties": {
    "iso:country":"CH",
    "sg:address":"Parkweg 5",
    "sg:city":"Biel/bienne",
    "sg:orig_category":"Chiropraktik Gesundheitswesen",
    "sg:phone":"+41 31 302 43 43",
    "sg:postcode":"2502",
    "sg:province":"Bern",
    "wof:name":"Praxis Dr. Stefan Streit Chiropraktiker",
    "wof:placetype":"venue"
},
  "geometry": {"coordinates":[7.43401,46.975521],"type":"Point"}
}