{
  "type": "Feature",
  "properties": {
    "iso:country":"CH",
    "sg:address":"5645",
    "sg:city":"Aettenschwil",
    "sg:classifiers":[
        {
            "category":"Restaurant",
            "type":"Food & Drink"
        }
    ],
    "sg:phone":"+41 41 988 12 15",
    "sg:postcode":"5645",
    "sg:province":"Aargau",
    "wof:name":"Restaurant Krone",
    "wof:placetype":"venue"
},
  "geometry": {"coordinates":[7.9087600708,47.1533203125],"type":"Point"}
}