{
  "type": "Feature",
  "properties": {
    "iso:country":"CH",
    "sg:address":"Lindenweg 1",
    "sg:city":"Turbenthal",
    "sg:orig_category":"Hardwareberatung",
    "sg:phone":"+41 52 394 20 90",
    "sg:postcode":"8488",
    "sg:province":"Z\u00fcrich",
    "wof:name":"Pc Help + Hardware Wenger Peter",
    "wof:placetype":"venue"
},
  "geometry": {"coordinates":[8.8475217819,47.4361457825],"type":"Point"}
}