{
  "type": "Feature",
  "properties": {
    "iso:country":"CH",
    "sg:address":"Kirchgasse 1",
    "sg:city":"Erstfeld",
    "sg:orig_category":"Herstellung von Fenstern U T\u00fcren aus Holz Herstellung von Konstruktionsteilen, Fertigbauteilen U Aus",
    "sg:phone":"+41 41 880 19 70",
    "sg:postcode":"6472",
    "sg:province":"Uri",
    "wof:name":"P\u00fcntener Fenster Gmbh",
    "wof:placetype":"venue"
},
  "geometry": {"coordinates":[8.644364357,46.820941925],"type":"Point"}
}