{
  "type": "Feature",
  "properties": {
    "iso:country":"CH",
    "sg:address":"Zugerstrasse 17",
    "sg:city":"Cham",
    "sg:orig_category":"Chiropraktik",
    "sg:phone":"+41 21 923 67 68",
    "sg:postcode":"6330",
    "sg:province":"Zug",
    "wof:name":"Dr. Lorenzo Tiani Chiropracticien",
    "wof:placetype":"venue"
},
  "geometry": {"coordinates":[6.843275,46.462135],"type":"Point"}
}