{
  "type": "Feature",
  "properties": {
    "iso:country":"CH",
    "sg:address":"Therwilerstrasse 26",
    "sg:city":"Bottmingen",
    "sg:orig_category":"Maler U Glasergewerbe Malerei",
    "sg:phone":"+41 61 401 19 56",
    "sg:postcode":"4103",
    "sg:province":"Basel-Landschaft",
    "wof:name":"D\u00fcblin Ag Malergesch\u00e4ft",
    "wof:placetype":"venue"
},
  "geometry": {"coordinates":[7.5703849792,47.5221939087],"type":"Point"}
}