{
  "type": "Feature",
  "properties": {
    "addr:full":"Kramenweg 14 Jona St. Gallen 8645",
    "addr:housenumber":"14;st.",
    "addr:postcode":"8645",
    "addr:street":"Kramenweg;Jona",
    "iso:country":"CH",
    "sg:address":"Kramenweg 14",
    "sg:city":"Jona",
    "sg:orig_category":"Bau von Strassen, Sportanlagen U Bahnverkehrsstrecken",
    "sg:phone":"+41 55 212 29 09",
    "sg:postcode":"8645",
    "sg:province":"St. Gallen",
    "wof:name":"Batigroup Ag",
    "wof:placetype":"venue"
},
  "geometry": {"coordinates":[8.847202,47.230846],"type":"Point"}
}