{
  "type": "Feature",
  "properties": {
    "iso:country":"CH",
    "sg:address":"Schmiedgasse 3 9320 Arbon. Postfach",
    "sg:city":"Arbon",
    "sg:orig_category":"RESTAURANTS: TEA-ROOMS",
    "sg:phone":"+41 71 446 15 77",
    "sg:postcode":"9320",
    "sg:province":"Thurgau",
    "wof:name":"Sonderegger P.",
    "wof:placetype":"venue"
},
  "geometry": {"coordinates":[9.4355459213,47.5163955688],"type":"Point"}
}