{
  "type": "Feature",
  "properties": {
    "iso:country":"CH",
    "sg:address":"Seestrasse 27",
    "sg:city":"Horgen",
    "sg:orig_category":"Vermietung U Verpachtung von eigenen Immobilien",
    "sg:phone":"+41 14828383",
    "sg:postcode":"8810",
    "sg:province":"Z\u00fcrich",
    "wof:name":"Primobau Immobilien Ag",
    "wof:placetype":"venue"
},
  "geometry": {"coordinates":[8.5879335403,47.2680244446],"type":"Point"}
}