{
  "type": "Feature",
  "properties": {
    "iso:country":"CH",
    "sg:address":"Rue De Morges 3",
    "sg:city":"Crissier",
    "sg:orig_category":"Autospenglereien",
    "sg:phone":"+41 21 635 87 74",
    "sg:postcode":"1023",
    "sg:province":"Vaud",
    "wof:name":"Carrosserie Du Chablais J.-m.bocherens & D.nikl\u00e8s",
    "wof:placetype":"venue"
},
  "geometry": {"coordinates":[6.57049,46.55125],"type":"Point"}
}