{
  "type": "Feature",
  "properties": {
    "iso:country":"CH",
    "sg:address":"3919",
    "sg:city":"Blatten(l\u00f6tschen)",
    "sg:orig_category":"Darlehenskassen U Raiffeisenbanken",
    "sg:phone":"+41 27 939 19 33",
    "sg:postcode":"3919",
    "sg:province":"Valais",
    "wof:name":"Raiffeisenbank",
    "wof:placetype":"venue"
},
  "geometry": {"coordinates":[7.819157,46.419476],"type":"Point"}
}