{
  "type": "Feature",
  "properties": {
    "iso:country":"CH",
    "sg:address":"Moosgrabenstrasse 14",
    "sg:city":"Altnau",
    "sg:orig_category":"Allgemeiner Hoch U Tiefbau",
    "sg:phone":"+41 71 688 16 30",
    "sg:postcode":"8595",
    "sg:province":"Thurgau",
    "wof:name":"Schwegler Roland Gmbh",
    "wof:placetype":"venue"
},
  "geometry": {"coordinates":[9.26673,47.617191],"type":"Point"}
}