{
  "type": "Feature",
  "properties": {
    "iso:country":"CH",
    "sg:address":"Hirschistrasse 27",
    "sg:city":"Schwyz",
    "sg:orig_category":"Bauspenglerei Sanit\u00e4rinstallation U Spenglerei",
    "sg:phone":"+41 41 811 11 56",
    "sg:postcode":"6430",
    "sg:province":"Schwyz",
    "wof:name":"Spenglerei Blum Gmbh",
    "wof:placetype":"venue"
},
  "geometry": {"coordinates":[8.650714,47.022636],"type":"Point"}
}