{
  "type": "Feature",
  "properties": {
    "iso:country":"CH",
    "sg:address":"Engestrasse 54a 3012 Bern. Postfach",
    "sg:city":"Bern",
    "sg:classifiers":[
        {
            "category":"Travel",
            "subcategory":"Hotels & Motels",
            "type":"Entertainment"
        }
    ],
    "sg:phone":"+41 31 302 53 53",
    "sg:postcode":"3005",
    "sg:province":"Bern",
    "sg:tags":[
        "hotels",
        "mit",
        "restaurant"
    ],
    "wof:name":"Hbs Hotel Management Ag Managements I.d. Hotel- U. Wirtebranche Usw.",
    "wof:placetype":"venue"
},
  "geometry": {"coordinates":[7.4392051697,46.9607963562],"type":"Point"}
}