{
  "type": "Feature",
  "properties": {
    "iso:country":"CH",
    "sg:address":"Neugasse 11 8001 Z\u00fcrich. Postfach",
    "sg:city":"Z\u00fcrich",
    "sg:orig_category":"Pensionskassen",
    "sg:phone":"+41 12717077",
    "sg:postcode":"8001",
    "sg:province":"Z\u00fcrich",
    "wof:name":"Pensionskasse Verein Z\u00fcrcher Brockenhaus",
    "wof:placetype":"venue"
},
  "geometry": {"coordinates":[8.5459108353,47.3728103638],"type":"Point"}
}