{
  "type": "Feature",
  "properties": {
    "iso:country":"CH",
    "sg:address":"Dittingerstrasse 41 4053 Basel. Postfach",
    "sg:city":"Basel",
    "sg:orig_category":"K\u00fcnstlerische U schriftstellerische T\u00e4tigkeiten U Darbietungen",
    "sg:phone":"+41 61 361 46 31",
    "sg:postcode":"4051",
    "sg:province":"Basel-Stadt",
    "wof:name":"Ludwig Epstein Kunsthandwerkl. Gegenst\u00e4nde; Handel.",
    "wof:placetype":"venue"
},
  "geometry": {"coordinates":[7.5881299973,47.5402755737],"type":"Point"}
}