{
  "type": "Feature",
  "properties": {
    "iso:country":"CH",
    "sg:address":"M\u00fchlegasse 10 8353 Elgg. Postfach",
    "sg:city":"Elgg",
    "sg:orig_category":"Herstellung von Konstruktionsteilen, Fertigbauteilen U Ausbauelementen aus Holz",
    "sg:phone":"+41 52 364 12 40",
    "sg:postcode":"8353",
    "sg:province":"Z\u00fcrich",
    "wof:name":"K\u00e4gi Beat Fenstertechnik Fenster-montage",
    "wof:placetype":"venue"
},
  "geometry": {"coordinates":[8.8653535843,47.4919967651],"type":"Point"}
}