{
  "type": "Feature",
  "properties": {
    "addr:full":"6838 Muggio Ticino 6838",
    "addr:housenumber":"6838;6838",
    "addr:street":"Muggio Ticino",
    "iso:country":"CH",
    "sg:address":"6838",
    "sg:city":"Muggio",
    "sg:orig_category":"Darlehenskassen U Raiffeisenbanken",
    "sg:phone":"+41 91 684 15 49",
    "sg:postcode":"6838",
    "sg:province":"Ticino",
    "wof:name":"Banca Raiffeisen",
    "wof:placetype":"venue"
},
  "geometry": {"coordinates":[9.042943,45.901527],"type":"Point"}
}