{
  "type": "Feature",
  "properties": {
    "iso:country":"CH",
    "sg:address":"Sch\u00fctzenmattstrasse 10",
    "sg:city":"Emmenbr\u00fccke",
    "sg:orig_category":"Bauschreinerei S\u00e4ge, Hobel U Holzimpr\u00e4gnierwerke",
    "sg:phone":"+41 76 540 70 76",
    "sg:postcode":"6020",
    "sg:province":"Luzern",
    "wof:name":"P. Hecht Holz-atelier",
    "wof:placetype":"venue"
},
  "geometry": {"coordinates":[8.282357,47.071705],"type":"Point"}
}