{
  "type": "Feature",
  "properties": {
    "iso:country":"CH",
    "sg:address":"Marktgasse 59",
    "sg:city":"Bern",
    "sg:orig_category":"Detailhandel mit Bekleidung Detailhandel mit Damenbekleidung",
    "sg:phone":"+41 31 311 81 88",
    "sg:postcode":"3011",
    "sg:province":"Bern",
    "wof:name":"Tsolakidis Pia, Daphnis",
    "wof:placetype":"venue"
},
  "geometry": {"coordinates":[7.444418,46.947994],"type":"Point"}
}