{
  "type": "Feature",
  "properties": {
    "iso:country":"CH",
    "sg:address":"Lenzhardstrasse 15",
    "sg:city":"Lenzburg",
    "sg:orig_category":"D\u00e4mmung gegen K\u00e4lte, W\u00e4rme, Schall U Ersch\u00fctterung Malerei",
    "sg:phone":"+41 79 337 28 90",
    "sg:postcode":"5600",
    "sg:province":"Aargau",
    "wof:name":"Dario Decristophoris Impresa Pittura & Isolazioni",
    "wof:placetype":"venue"
},
  "geometry": {"coordinates":[9.1212053299,46.2333908081],"type":"Point"}
}