{
  "type": "Feature",
  "properties": {
    "iso:country":"CH",
    "sg:address":"1711",
    "sg:city":"Schwarzsee",
    "sg:classifiers":[
        {
            "category":"Restaurant",
            "type":"Food & Drink"
        }
    ],
    "sg:phone":"+41 71 222 11 74",
    "sg:postcode":"1711",
    "wof:name":"B\u00e4umli Schmiedgasse Restaurant",
    "wof:placetype":"venue"
},
  "geometry": {"coordinates":[9.3757638931,47.4240875244],"type":"Point"}
}