{
  "type": "Feature",
  "properties": {
    "iso:country":"CH",
    "sg:address":"Wyd\u00e4ckerring 73",
    "sg:city":"Z\u00fcrich",
    "sg:orig_category":"Softwareentwicklung U beratung",
    "sg:phone":"+41 14931219",
    "sg:postcode":"8047",
    "sg:province":"Z\u00fcrich",
    "wof:name":"Metrolight, Schurter D.",
    "wof:placetype":"venue"
},
  "geometry": {"coordinates":[8.4953260422,47.3704910278],"type":"Point"}
}