{
  "type": "Feature",
  "properties": {
    "iso:country":"CH",
    "sg:address":"Cerisiers Avenue Des 37",
    "sg:city":"Pully",
    "sg:orig_category":"Non-Classified Establishments",
    "sg:phone":"+41 26 322 60 06",
    "sg:postcode":"1009",
    "sg:province":"Vaud",
    "wof:name":"Terinter Sa",
    "wof:placetype":"venue"
},
  "geometry": {"coordinates":[6.6598000526,46.5102577209],"type":"Point"}
}