{
  "type": "Feature",
  "properties": {
    "iso:country":"CH",
    "sg:address":"Schulstrasse 27",
    "sg:city":"Wiesendangen",
    "sg:classifiers":[
        {
            "category":"Education",
            "subcategory":"Library",
            "type":"Public Place"
        }
    ],
    "sg:phone":"+41 52 337 20 72",
    "sg:postcode":"8542",
    "sg:province":"Z\u00fcrich",
    "sg:tags":[
        "u",
        "bibliotheken",
        "archive"
    ],
    "wof:name":"Schul-& Gemeindebibliothek",
    "wof:placetype":"venue"
},
  "geometry": {"coordinates":[8.790075,47.522388],"type":"Point"}
}