{
  "type": "Feature",
  "properties": {
    "iso:country":"CH",
    "sg:address":"Rue De Carouge 72-74",
    "sg:city":"Gen\u00e8ve",
    "sg:orig_category":"Detailhandel mit Geschenkartikeln U Souvenirs",
    "sg:phone":"+41 32 931 69 40",
    "sg:postcode":"1205",
    "sg:province":"Gen\u00e8ve",
    "wof:name":"Alice Fleury Boutique Sans Complexe",
    "wof:placetype":"venue"
},
  "geometry": {"coordinates":[6.7506651878,47.0598487854],"type":"Point"}
}