{
  "type": "Feature",
  "properties": {
    "iso:country":"CH",
    "sg:address":"Via Codeborgo 7",
    "sg:city":"Bellinzona",
    "sg:orig_category":"Detailhandel mit Blumen U Pflanzen Fachdetailhandel in Verkaufsr\u00e4umen",
    "sg:phone":"+41 62 771 14 22",
    "sg:postcode":"6500",
    "sg:province":"Ticino",
    "wof:name":"Artfloral Roth-kellerhals E. Blumengesch\u00e4ft",
    "wof:placetype":"venue"
},
  "geometry": {"coordinates":[8.183178,47.251091],"type":"Point"}
}