{
  "type": "Feature",
  "properties": {
    "addr:full":"Z\u00fcrcherstrasse 63 Embrach Z\u00fcrich 8424",
    "addr:housenumber":"63",
    "addr:postcode":"8424",
    "addr:street":"Zuercherstrasse",
    "iso:country":"CH",
    "sg:address":"Z\u00fcrcherstrasse 63",
    "sg:city":"Embrach",
    "sg:orig_category":"Arztpraxen",
    "sg:phone":"+41 18650266",
    "sg:postcode":"8424",
    "sg:province":"Z\u00fcrich",
    "wof:name":"Dr.med.johannes Hirsig Spezialarzt Fmh",
    "wof:placetype":"venue"
},
  "geometry": {"coordinates":[8.595672,47.498878],"type":"Point"}
}