{
  "type": "Feature",
  "properties": {
    "iso:country":"CH",
    "sg:address":"Kanzleistrasse 53 8004 Z\u00fcrich. Postfach",
    "sg:city":"Z\u00fcrich",
    "sg:orig_category":"Grosshandel mit Getr\u00e4nken",
    "sg:postcode":"8004",
    "sg:province":"Z\u00fcrich",
    "wof:name":"Vinkop Andreas Steffen",
    "wof:placetype":"venue"
},
  "geometry": {"coordinates":[8.5258779526,47.3749771118],"type":"Point"}
}