{
  "type": "Feature",
  "properties": {
    "iso:country":"CH",
    "sg:address":"Stalderain 6215 Berom\u00fcnster. Postfach",
    "sg:city":"Berom\u00fcnster",
    "sg:orig_category":"Detailhandel mit Waren verschiedener Art, Hauptrichtung Nahrungsmittel Grosshandel mit Nahrungsmitte",
    "sg:phone":"+41 41 930 18 18",
    "sg:postcode":"6215",
    "sg:province":"Luzern",
    "wof:name":"Estermann Blanka Epa Superdiscount",
    "wof:placetype":"venue"
},
  "geometry": {"coordinates":[8.1892271042,47.2067070007],"type":"Point"}
}