{
  "type": "Feature",
  "properties": {
    "iso:country":"CH",
    "sg:address":"Sonnenbergstrasse 5",
    "sg:city":"Jona",
    "sg:orig_category":"Organisationen des Gesundheitswesen",
    "sg:phone":"+41 55 210 61 39",
    "sg:postcode":"8645",
    "sg:province":"St. Gallen",
    "wof:name":"Schweizer Kneippverband",
    "wof:placetype":"venue"
},
  "geometry": {"coordinates":[8.8213996887,47.2421913147],"type":"Point"}
}