{
  "type": "Feature",
  "properties": {
    "addr:full":"Hauptstrasse Tinizong Graubunden 7453",
    "addr:postcode":"7453",
    "addr:street":"Hauptstrasse;Graubunden",
    "iso:country":"CH",
    "sg:address":"Hauptstrasse",
    "sg:city":"Tinizong",
    "sg:orig_category":"Bauschreinerei Herstellung von Fenstern U T\u00fcren aus Holz",
    "sg:phone":"+41 21 960 24 71",
    "sg:postcode":"7453",
    "sg:province":"Graubunden",
    "wof:name":"Puenzieux Sa",
    "wof:placetype":"venue"
},
  "geometry": {"coordinates":[6.931413,46.352783],"type":"Point"}
}