{
  "type": "Feature",
  "properties": {
    "iso:country":"CH",
    "sg:address":"Weinstrasse 2",
    "sg:city":"Kreuzlingen",
    "sg:orig_category":"Non-Classified Establishments",
    "sg:postcode":"8280",
    "sg:province":"Thurgau",
    "wof:name":"Connact 2000 M. Maag",
    "wof:placetype":"venue"
},
  "geometry": {"coordinates":[9.183180809,47.6462059021],"type":"Point"}
}