{
  "type": "Feature",
  "properties": {
    "iso:country":"CH",
    "sg:address":"Reichenbachstrasse 32",
    "sg:city":"Zollikofen",
    "sg:orig_category":"Politische Parteien FDP",
    "sg:phone":"+41 31 911 45 60",
    "sg:postcode":"3052",
    "sg:province":"Bern",
    "wof:name":"Fdp Ortspartei Zollikofen",
    "wof:placetype":"venue"
},
  "geometry": {"coordinates":[7.45246315,46.9910430908],"type":"Point"}
}