{
  "type": "Feature",
  "properties": {
    "iso:country":"CH",
    "sg:address":"8862",
    "sg:city":"Sch\u00fcbelbach",
    "sg:classifiers":[
        {
            "category":"Social Services",
            "subcategory":"Retirement Home",
            "type":"Services"
        }
    ],
    "sg:phone":"+41 55 440 11 86",
    "sg:postcode":"8862",
    "sg:province":"Schwyz",
    "sg:tags":[
        "pflegeheime",
        "u",
        "alters"
    ],
    "wof:name":"Altersheim Der Gemeinde",
    "wof:placetype":"venue"
},
  "geometry": {"coordinates":[8.92993,47.17651],"type":"Point"}
}