{
  "type": "Feature",
  "properties": {
    "iso:country":"CH",
    "sg:address":"Schwarztorstrasse 56 3007 Bern. Postfach",
    "sg:city":"Bern",
    "sg:orig_category":"Softwareentwicklung U beratung",
    "sg:phone":"+41 31 390 45 45",
    "sg:postcode":"3007",
    "sg:province":"Bern",
    "wof:name":"Arsis Informatik Dr. A. D. Ropelato",
    "wof:placetype":"venue"
},
  "geometry": {"coordinates":[7.430270195,46.9449577332],"type":"Point"}
}