{
  "type": "Feature",
  "properties": {
    "iso:country":"CH",
    "sg:address":"Amtshausweg 3",
    "sg:city":"Tafers",
    "sg:classifiers":[
        {
            "category":"Insurance",
            "subcategory":"Insurance Agent",
            "type":"Services"
        }
    ],
    "sg:phone":"+41 26 418 21 17",
    "sg:postcode":"1712",
    "sg:province":"Fribourg",
    "sg:tags":[
        "versicherungsagenturen",
        "-broker"
    ],
    "wof:name":"Winterthur-leben Agentur",
    "wof:placetype":"venue"
},
  "geometry": {"coordinates":[7.2164330482,46.814704895],"type":"Point"}
}