{
  "type": "Feature",
  "properties": {
    "iso:country":"CH",
    "sg:address":"2608",
    "sg:city":"Courtelary",
    "sg:orig_category":"Detailhandel mit Waren verschiedener Art, Hauptrichtung Nahrungsmittel",
    "sg:phone":"+41 32 944 14 93",
    "sg:postcode":"2608",
    "sg:province":"Bern",
    "wof:name":"Coop Neuch\u00e2tel-jura",
    "wof:placetype":"venue"
},
  "geometry": {"coordinates":[7.0733680725,47.1785583496],"type":"Point"}
}