{
  "type": "Feature",
  "properties": {
    "iso:country":"CH",
    "sg:address":"Horwerstrasse 47",
    "sg:city":"Luzern",
    "sg:orig_category":"Malerei",
    "sg:phone":"+41 41 310 95 30",
    "sg:postcode":"6005",
    "sg:province":"Luzern",
    "wof:name":"Alois Wendelgass Malergesch\u00e4ft",
    "wof:placetype":"venue"
},
  "geometry": {"coordinates":[8.3026866913,47.0367546082],"type":"Point"}
}