{
  "type": "Feature",
  "properties": {
    "iso:country":"CH",
    "sg:address":"Wilgasse 51",
    "sg:city":"Lenzburg",
    "sg:orig_category":"P\u00e9dicure",
    "sg:phone":"+41 79 456 73 22",
    "sg:postcode":"5600",
    "sg:province":"Aargau",
    "wof:name":"Silvia B\u00fcrgi P\u00e9dicure",
    "wof:placetype":"venue"
},
  "geometry": {"coordinates":[8.1757564545,47.3782119751],"type":"Point"}
}