{
  "type": "Feature",
  "properties": {
    "iso:country":"CH",
    "sg:address":"Quartier De La Prairie 3",
    "sg:city":"Yverdon-les-bains",
    "sg:orig_category":"Herstellung von chemischen Grundstoffen Ingenieurb\u00fcros divers",
    "sg:phone":"+41 24 425 38 66",
    "sg:postcode":"1400",
    "sg:province":"Vaud",
    "wof:name":"Sbit Engineering S\u00e0rl",
    "wof:placetype":"venue"
},
  "geometry": {"coordinates":[6.6497020721,46.7755432129],"type":"Point"}
}