{
  "type": "Feature",
  "properties": {
    "iso:country":"CH",
    "sg:address":"Pensione Graziella 6614 Brissago. Postfach Casa Postale",
    "sg:city":"Brissago",
    "sg:orig_category":"RESTAURANTS: TEA-ROOMS",
    "sg:postcode":"6614",
    "sg:province":"Ticino",
    "wof:name":"Mathis Adelaide Pensione-ristorante Graziella",
    "wof:placetype":"venue"
},
  "geometry": {"coordinates":[8.7102975845,46.118976593],"type":"Point"}
}