{
  "type": "Feature",
  "properties": {
    "iso:country":"CH",
    "sg:address":"Sarmenstorferstrasse 16",
    "sg:city":"Fahrwangen",
    "sg:orig_category":"RESTAURANTS: TEA-ROOMS",
    "sg:postcode":"5615",
    "sg:province":"Aargau",
    "wof:name":"Ellensohn & Co",
    "wof:placetype":"venue"
},
  "geometry": {"coordinates":[9.2480916977,47.4153137207],"type":"Point"}
}