{
  "type": "Feature",
  "properties": {
    "iso:country":"CH",
    "sg:address":"Bifang 8",
    "sg:city":"Oftringen",
    "sg:orig_category":"Handel mit Automobilen",
    "sg:postcode":"4665",
    "sg:province":"Aargau",
    "wof:name":"Gall-racing Gmbh",
    "wof:placetype":"venue"
},
  "geometry": {"coordinates":[7.9376349449,47.3131484985],"type":"Point"}
}