{
  "type": "Feature",
  "properties": {
    "iso:country":"CH",
    "sg:address":"Rotfarb",
    "sg:city":"Uznach",
    "sg:orig_category":"Herstellung von Elektromotoren, Generatoren U Transformatoren",
    "sg:phone":"+41 55 285 86 01",
    "sg:postcode":"8730",
    "sg:province":"St. Gallen",
    "wof:name":"Holzer Energieconsulting",
    "wof:placetype":"venue"
},
  "geometry": {"coordinates":[8.9852361679,47.2249984741],"type":"Point"}
}