{
  "type": "Feature",
  "properties": {
    "iso:country":"CH",
    "sg:address":"Nonnenweg 20",
    "sg:city":"Basel",
    "sg:orig_category":"Arztpraxen",
    "sg:phone":"+41 61 271 69 69",
    "sg:postcode":"4055",
    "sg:province":"Basel-Stadt",
    "wof:name":"Dr.med.christian Weber Arzt F.allgemeine Medizin Fmh",
    "wof:placetype":"venue"
},
  "geometry": {"coordinates":[7.576822,47.557369],"type":"Point"}
}