{
  "type": "Feature",
  "properties": {
    "iso:country":"CH",
    "sg:address":"4222 Zwingen. Postfach 133",
    "sg:city":"Zwingen",
    "sg:orig_category":"Sportvereine Ballsport Fussball",
    "sg:phone":"+41 61 781 27 54",
    "sg:postcode":"4222",
    "sg:province":"Basel-Landschaft",
    "wof:name":"Fc Zwingen",
    "wof:placetype":"venue"
},
  "geometry": {"coordinates":[7.5277500153,47.4357681274],"type":"Point"}
}