{
  "type": "Feature",
  "properties": {
    "iso:country":"CH",
    "sg:address":"Witikonerstrasse 397",
    "sg:city":"Z\u00fcrich",
    "sg:orig_category":"Non-Classified Establishments",
    "sg:postcode":"8053",
    "sg:province":"Z\u00fcrich",
    "wof:name":"Looren-apotheke Ag",
    "wof:placetype":"venue"
},
  "geometry": {"coordinates":[8.5934810638,47.3597450256],"type":"Point"}
}