{
  "type": "Feature",
  "properties": {
    "iso:country":"CH",
    "sg:address":"B\u00e4derstrasse 11",
    "sg:city":"Baden",
    "sg:orig_category":"Non-Classified Establishments",
    "sg:postcode":"5400",
    "sg:province":"Aargau",
    "wof:name":"Lumi\u00e8re Kosmetik Gmbh",
    "wof:placetype":"venue"
},
  "geometry": {"coordinates":[8.3109264374,47.4783973694],"type":"Point"}
}