{
  "type": "Feature",
  "properties": {
    "iso:country":"CH",
    "sg:address":"Erlenstr. 8.",
    "sg:city":"Emmen",
    "sg:orig_category":"RESTAURANTS: TEA-ROOMS",
    "sg:phone":"+41 41 280 50 70",
    "sg:postcode":"6032",
    "sg:province":"Luzern",
    "wof:name":"Lercher Franz, Tea Room Sprengi",
    "wof:placetype":"venue"
},
  "geometry": {"coordinates":[8.2712602615,47.0803985596],"type":"Point"}
}