{
  "type": "Feature",
  "properties": {
    "iso:country":"CH",
    "sg:address":"Niederholzstrasse 46",
    "sg:city":"Riehen",
    "sg:orig_category":"Grafikateliers, Design",
    "sg:phone":"+41 18450506",
    "sg:postcode":"4125",
    "sg:province":"Basel-Stadt",
    "wof:name":"Albert Lauber Schriftenmalerei & Standbau",
    "wof:placetype":"venue"
},
  "geometry": {"coordinates":[8.4348936081,47.4583244324],"type":"Point"}
}