{
  "type": "Feature",
  "properties": {
    "addr:full":"Rickenbachstrasse 24 6430 Schwyz. Postfach 260 Schwyz Schwyz 6431",
    "addr:housenumber":"24;260",
    "addr:postcode":"6430;6431",
    "addr:street":"Rickenbachstrasse;Postfach",
    "iso:country":"CH",
    "sg:address":"Rickenbachstrasse 24 6430 Schwyz. Postfach 260",
    "sg:city":"Schwyz",
    "sg:classifiers":[
        {
            "category":"Education",
            "subcategory":"Library",
            "type":"Public Place"
        }
    ],
    "sg:phone":"+41 41 819 11 24",
    "sg:postcode":"6431",
    "sg:province":"Schwyz",
    "sg:tags":[
        "u",
        "bibliotheken",
        "archive"
    ],
    "wof:name":"Kantonsbibliothek Schwyz",
    "wof:placetype":"venue"
},
  "geometry": {"coordinates":[8.655251,47.0215],"type":"Point"}
}