{
  "type": "Feature",
  "properties": {
    "addr:full":"Via Dei Pedroni 3 Chiasso Ticino 6830",
    "addr:housenumber":"3",
    "addr:postcode":"6830",
    "addr:street":"Via Dei Pedroni;Ticino",
    "iso:country":"CH",
    "sg:address":"Via Dei Pedroni 3",
    "sg:city":"Chiasso",
    "sg:orig_category":"Bestattungswesen Detailhandel mit Blumen U Pflanzen",
    "sg:phone":"+41 91 682 68 13",
    "sg:postcode":"6830",
    "sg:province":"Ticino",
    "wof:name":"Onoranze Funebri Lorenzo Mella Sa",
    "wof:placetype":"venue"
},
  "geometry": {"coordinates":[9.035586,45.836491],"type":"Point"}
}