{
  "type": "Feature",
  "properties": {
    "iso:country":"CH",
    "sg:address":"Finsterwaldstrasse 94",
    "sg:city":"Schaffhausen",
    "sg:orig_category":"Detailhandel mit Brot, Back U S\u00fcsswaren",
    "sg:phone":"+41 32 622 12 29",
    "sg:postcode":"8200",
    "sg:province":"Schaffhausen",
    "wof:name":"Andr\u00e9 Riesen B\u00e4ckerei",
    "wof:placetype":"venue"
},
  "geometry": {"coordinates":[7.503362,47.230076],"type":"Point"}
}