{
  "type": "Feature",
  "properties": {
    "iso:country":"CH",
    "sg:address":"Bellevuestrasse 12",
    "sg:city":"Wettingen",
    "sg:orig_category":"Herstellung von elektrischen Lampen U Leuchten",
    "sg:postcode":"5430",
    "sg:province":"Aargau",
    "wof:name":"Sp\u00f6rri Veranstaltungstechnik",
    "wof:placetype":"venue"
},
  "geometry": {"coordinates":[8.3401527405,47.4621582031],"type":"Point"}
}