{
  "type": "Feature",
  "properties": {
    "iso:country":"CH",
    "sg:address":"Schulstrasse 14",
    "sg:city":"Steinach",
    "sg:orig_category":"Darlehenskassen U Raiffeisenbanken",
    "sg:phone":"+41 71 447 18 47",
    "sg:postcode":"9323",
    "sg:province":"St. Gallen",
    "wof:name":"Raiffeisenbank Steinach-berg-freidorf",
    "wof:placetype":"venue"
},
  "geometry": {"coordinates":[9.44154,47.502151],"type":"Point"}
}