{
  "type": "Feature",
  "properties": {
    "iso:country":"CH",
    "sg:address":"Pfingstweidstrasse 31b 8005 Z\u00fcrich. Postfach 113",
    "sg:city":"Z\u00fcrich",
    "sg:orig_category":"Alters U Hinterlassenenversicherung AHV, Invalidenversicherung IV, Arbeitslosenversicherung ALV",
    "sg:phone":"+41 12713217",
    "sg:postcode":"8031",
    "sg:province":"Z\u00fcrich",
    "wof:name":"Ausgleichskasse Der Migros-betriebe",
    "wof:placetype":"venue"
},
  "geometry": {"coordinates":[8.516705,47.388191],"type":"Point"}
}