{
  "type": "Feature",
  "properties": {
    "iso:country":"CH",
    "sg:address":"Simplon Rue Du 112",
    "sg:city":"Martigny",
    "sg:orig_category":"Instandhaltung U Reparatur von Automobilen",
    "sg:phone":"+41 79 235 18 17",
    "sg:postcode":"1920",
    "sg:province":"Valais",
    "wof:name":"Carrosserie Du Simplon Martigny Sa",
    "wof:placetype":"venue"
},
  "geometry": {"coordinates":[7.0862421989,46.106590271],"type":"Point"}
}