{
  "type": "Feature",
  "properties": {
    "iso:country":"CH",
    "sg:address":"Chemin Gustave-rochette 5",
    "sg:city":"Onex",
    "sg:orig_category":"Grosshandel mit lebenden Tieren Sonstige mit Sport verbundene T\u00e4tigkeiten",
    "sg:phone":"+41 22 792 16 88",
    "sg:postcode":"1213",
    "sg:province":"Gen\u00e8ve",
    "wof:name":"Man\u00e8ge D'onex S\u00e0rl",
    "wof:placetype":"venue"
},
  "geometry": {"coordinates":[6.1018061638,46.1831550598],"type":"Point"}
}