{
  "type": "Feature",
  "properties": {
    "iso:country":"CH",
    "sg:address":"M\u00fclhauserstrasse 81 4056 Basel. Postfach",
    "sg:city":"Basel",
    "sg:orig_category":"Herstellung von Konstruktionsteilen, Fertigbauteilen U Ausbauelementen aus Holz",
    "sg:postcode":"4051",
    "sg:province":"Basel-Stadt",
    "wof:name":"Portner B. Schreinereimontagen Und Teppichverlegeservice Schreinereimontagen, Teppichverlegeservice",
    "wof:placetype":"venue"
},
  "geometry": {"coordinates":[7.5784888268,47.5676689148],"type":"Point"}
}