{
  "type": "Feature",
  "properties": {
    "iso:country":"CH",
    "sg:address":"Lupsingerstrasse 224",
    "sg:city":"Ziefen",
    "sg:orig_category":"Herstellung von sonstigen landwirtschaftlichen Maschinen",
    "sg:phone":"+41 61 931 33 10",
    "sg:postcode":"4417",
    "sg:province":"Basel-Landschaft",
    "wof:name":"D\u00dcrr-agro Gmbh",
    "wof:placetype":"venue"
},
  "geometry": {"coordinates":[7.7021899223,47.4327697754],"type":"Point"}
}