{
  "type": "Feature",
  "properties": {
    "iso:country":"CH",
    "sg:address":"Rue Du Vidollet 16",
    "sg:city":"Gen\u00e8ve",
    "sg:classifiers":[
        {
            "category":"Restaurant",
            "type":"Food & Drink"
        }
    ],
    "sg:phone":"+41 22 733 01 98",
    "sg:postcode":"1202",
    "sg:province":"Gen\u00e8ve",
    "wof:name":"Caf\u00e9 Domino",
    "wof:placetype":"venue"
},
  "geometry": {"coordinates":[6.1363511086,46.2173538208],"type":"Point"}
}