{
  "type": "Feature",
  "properties": {
    "iso:country":"CH",
    "sg:address":"Innere Margarethenstrasse 7",
    "sg:city":"Basel",
    "sg:classifiers":[
        {
            "category":"Manufacturing",
            "subcategory":"Metals",
            "type":"Manufacturing & Wholesale Goods"
        }
    ],
    "sg:phone":"+41 61 227 77 77",
    "sg:postcode":"4051",
    "sg:province":"Basel-Stadt",
    "sg:tags":[
        "steel",
        "carbon"
    ],
    "wof:name":"Arcelor Long Commercial Schweiz Ag",
    "wof:placetype":"venue"
},
  "geometry": {"coordinates":[7.58709,47.550426],"type":"Point"}
}