{
  "type": "Feature",
  "properties": {
    "iso:country":"CH",
    "sg:address":"Via Tesserete 67",
    "sg:city":"Savosa",
    "sg:orig_category":"Unclassifiable Establishments",
    "sg:postcode":"6942",
    "sg:province":"Ticino",
    "wof:name":"Cvs Holding Sa",
    "wof:placetype":"venue"
},
  "geometry": {"coordinates":[8.9505434036,46.0234375],"type":"Point"}
}