{
  "type": "Feature",
  "properties": {
    "iso:country":"CH",
    "sg:address":"Via Prati 24",
    "sg:city":"Caslano",
    "sg:orig_category":"Unclassifiable Establishments",
    "sg:postcode":"6987",
    "sg:province":"Ticino",
    "wof:name":"W\u00e4lti Gilberto",
    "wof:placetype":"venue"
},
  "geometry": {"coordinates":[8.8829164505,45.9757041931],"type":"Point"}
}