{
  "type": "Feature",
  "properties": {
    "iso:country":"CH",
    "sg:address":"Chemin Du Fau-blanc 8",
    "sg:city":"Pully",
    "sg:orig_category":"Arztpraxen",
    "sg:phone":"+41 27 207 16 58",
    "sg:postcode":"1009",
    "sg:province":"Vaud",
    "wof:name":"Dr M\u00e9d. Catherine Monod M\u00e9decin G\u00e9n\u00e9raliste",
    "wof:placetype":"venue"
},
  "geometry": {"coordinates":[6.662153,46.513252],"type":"Point"}
}