{
  "type": "Feature",
  "properties": {
    "iso:country":"CH",
    "sg:address":"Clos De St-bonnet Bursinel Route De 1195 Dully. Postfach",
    "sg:city":"Dully",
    "sg:orig_category":"Vermietung U Verpachtung von eigenen Immobilien",
    "sg:postcode":"1195",
    "sg:province":"Vaud",
    "wof:name":"Mariotti Sa",
    "wof:placetype":"venue"
},
  "geometry": {"coordinates":[6.3020720482,46.4363937378],"type":"Point"}
}