{
  "type": "Feature",
  "properties": {
    "iso:country":"CH",
    "sg:address":"6932",
    "sg:city":"Breganzona",
    "sg:orig_category":"Unternehmensberatung",
    "sg:phone":"+41 21 622 05 05",
    "sg:postcode":"6932",
    "sg:province":"Ticino",
    "wof:name":"Dun & Bradstreet (svizzera) Sa Ufficio D'informazioni",
    "wof:placetype":"venue"
},
  "geometry": {"coordinates":[8.9279298782,46.0091590881],"type":"Point"}
}