{
  "type": "Feature",
  "properties": {
    "addr:full":"Stapfenstrasse 1 K\u00f6niz Bern 3098",
    "addr:housenumber":"1",
    "addr:postcode":"3098",
    "addr:street":"Stapfenstrasse",
    "iso:country":"CH",
    "sg:address":"Stapfenstrasse 1",
    "sg:city":"K\u00f6niz",
    "sg:classifiers":[
        {
            "category":"Banks & Credit Unions",
            "subcategory":"Bank",
            "type":"Services"
        }
    ],
    "sg:phone":"+41 31 972 37 47",
    "sg:postcode":"3098",
    "sg:province":"Bern",
    "wof:name":"Berner Kantonalbank",
    "wof:placetype":"venue"
},
  "geometry": {"coordinates":[7.414795,46.923016],"type":"Point"}
}