{
  "type": "Feature",
  "properties": {
    "iso:country":"CH",
    "sg:address":"Birrenstrasse - Schindellegi",
    "sg:city":"Feusisberg",
    "sg:orig_category":"Haltung von Rindern",
    "sg:postcode":"8835",
    "sg:province":"Schwyz",
    "wof:name":"Viehzuchtgenossenschaft Feutersoey",
    "wof:placetype":"venue"
},
  "geometry": {"coordinates":[7.2674098015,46.3868637085],"type":"Point"}
}