{
  "type": "Feature",
  "properties": {
    "iso:country":"CH",
    "sg:address":"Zugerstrasse 1",
    "sg:city":"Cham",
    "sg:orig_category":"Arztpraxen",
    "sg:phone":"+41 41 781 32 81",
    "sg:postcode":"6330",
    "sg:province":"Zug",
    "wof:name":"Dr.med.ralph Huwyler Spezialarzt Fmh",
    "wof:placetype":"venue"
},
  "geometry": {"coordinates":[8.459464,47.181416],"type":"Point"}
}