{
  "type": "Feature",
  "properties": {
    "iso:country":"CH",
    "sg:address":"Place Du March\u00e9 18bis",
    "sg:city":"Payerne",
    "sg:orig_category":"Architektur U Ingenieurb\u00fcros",
    "sg:phone":"+41 26 660 12 00",
    "sg:postcode":"1530",
    "sg:province":"Vaud",
    "wof:name":"Aba-g\u00e9ol Sa",
    "wof:placetype":"venue"
},
  "geometry": {"coordinates":[6.936579,46.820576],"type":"Point"}
}