{
  "type": "Feature",
  "properties": {
    "iso:country":"CH",
    "sg:address":"Bienenstrasse 21",
    "sg:city":"Niederuzwil",
    "sg:orig_category":"Architektur U Ingenieurb\u00fcros",
    "sg:phone":"+41 71 951 39 85",
    "sg:postcode":"9244",
    "sg:province":"St. Gallen",
    "wof:name":"Eisenring Markus Engineering.",
    "wof:placetype":"venue"
},
  "geometry": {"coordinates":[9.145606,47.447147],"type":"Point"}
}