{
  "type": "Feature",
  "properties": {
    "iso:country":"CH",
    "sg:address":"Boulevard De P\u00e9rolles 8 1700 Fribourg. Postfach",
    "sg:city":"Fribourg",
    "sg:orig_category":"Detailhandel mit Uhren U Schmuck Reparatur von Uhren U Schmuck",
    "sg:phone":"+41 22 311 37 63",
    "sg:postcode":"1701",
    "sg:province":"Fribourg",
    "wof:name":"Boutique Malbuisson Fedco Sa",
    "wof:placetype":"venue"
},
  "geometry": {"coordinates":[6.1465110779,46.2043228149],"type":"Point"}
}