{
  "type": "Feature",
  "properties": {
    "iso:country":"CH",
    "sg:address":"Meisenweg 19 3110 M\u00fcnsingen. Postfach 1415",
    "sg:city":"M\u00fcnsingen",
    "sg:orig_category":"Herstellung von Medikamenten U sonstigen pharmazeutischen Erzeugnissen Herstellung von pharmazeutisc",
    "sg:phone":"+41 31 721 01 15",
    "sg:postcode":"3110",
    "sg:province":"Bern",
    "wof:name":"Ballmer & Co Ag",
    "wof:placetype":"venue"
},
  "geometry": {"coordinates":[7.5699491501,46.8722724915],"type":"Point"}
}