{
  "type": "Feature",
  "properties": {
    "iso:country":"CH",
    "sg:address":"Boulevard De P\u00e9rolles 22 1700 Fribourg Case Postale 196",
    "sg:city":"Fribourg",
    "sg:orig_category":"Wirtschaftspr\u00fcfung, Steuerberatung U Treuhand",
    "sg:phone":"+41 21 921 55 35",
    "sg:postcode":"1701",
    "sg:province":"Fribourg",
    "wof:name":"Soci\u00e9t\u00e9 De Contr\u00f4le Fiduciaire Sa",
    "wof:placetype":"venue"
},
  "geometry": {"coordinates":[5.1808700562,45.8973388672],"type":"Point"}
}