{
  "type": "Feature",
  "properties": {
    "iso:country":"CH",
    "sg:address":"Hauptstrasse 7402 Bonaduz. Postfach",
    "sg:city":"Bonaduz",
    "sg:orig_category":"Herstellung von Betonerzeugnissen f\u00fcr den Bau",
    "sg:postcode":"7402",
    "sg:province":"Graubunden",
    "wof:name":"Steinharmonie Schmed",
    "wof:placetype":"venue"
},
  "geometry": {"coordinates":[9.4020233154,46.8212013245],"type":"Point"}
}