{
  "type": "Feature",
  "properties": {
    "addr:full":"Theaterplatz 2 Bern Bern 3011",
    "addr:housenumber":"2",
    "addr:postcode":"3011",
    "addr:street":"Theaterplatz",
    "iso:country":"CH",
    "sg:address":"Theaterplatz 2",
    "sg:city":"Bern",
    "sg:orig_category":"Arztpraxen",
    "sg:phone":"+41 31 311 40 65",
    "sg:postcode":"3011",
    "sg:province":"Bern",
    "wof:name":"Dr.med.richard Zimmermann Arzt F\u00fcr Allgemeine Medizin",
    "wof:placetype":"venue"
},
  "geometry": {"coordinates":[7.447299,46.94783],"type":"Point"}
}