{
  "type": "Feature",
  "properties": {
    "iso:country":"CH",
    "sg:address":"Blumattstrasse 9",
    "sg:city":"Ennetb\u00fcrgen",
    "sg:orig_category":"Sonstiger spezialisierter Hoch U Tiefbau",
    "sg:postcode":"6373",
    "sg:province":"Nidwalden",
    "wof:name":"Pamo Paul Kasper",
    "wof:placetype":"venue"
},
  "geometry": {"coordinates":[8.4098682404,46.9829673767],"type":"Point"}
}