{
  "type": "Feature",
  "properties": {
    "addr:full":"Sonnmatt Ranfl\u00fch Bern 3439",
    "addr:postcode":"3439",
    "iso:country":"CH",
    "sg:address":"Sonnmatt",
    "sg:city":"Ranfl\u00fch",
    "sg:orig_category":"Architekturb\u00fcros",
    "sg:phone":"+41 34 496 96 96",
    "sg:postcode":"3439",
    "sg:province":"Bern",
    "wof:name":"Theodor Zaugg Architekturb\u00fcro",
    "wof:placetype":"venue"
},
  "geometry": {"coordinates":[7.737332,46.988441],"type":"Point"}
}