{
  "type": "Feature",
  "properties": {
    "iso:country":"CH",
    "sg:address":"Luggwegstrasse 60 8048 Z\u00fcrich. Postfach",
    "sg:city":"Winterthur",
    "sg:orig_category":"Sonstige mit der Informatik verbundene T\u00e4tigkeiten",
    "sg:phone":"+41 76 365 38 29",
    "sg:postcode":"8411",
    "sg:province":"Z\u00fcrich",
    "wof:name":"J\u00f6rger Informatik - Beratung & Schulung",
    "wof:placetype":"venue"
},
  "geometry": {"coordinates":[8.4898519516,47.3859939575],"type":"Point"}
}