{
  "type": "Feature",
  "properties": {
    "iso:country":"CH",
    "sg:address":"Madeleine Rue De La 7",
    "sg:city":"Gen\u00e8ve",
    "sg:orig_category":"Fachdetailhandel in Verkaufsr\u00e4umen",
    "sg:phone":"+41 22 311 52 85",
    "sg:postcode":"1204",
    "sg:province":"Gen\u00e8ve",
    "wof:name":"Gallery Jeans, Singer M. Et Mme Casual Wear",
    "wof:placetype":"venue"
},
  "geometry": {"coordinates":[6.1484498978,46.2024230957],"type":"Point"}
}