{
  "type": "Feature",
  "properties": {
    "iso:country":"CH",
    "sg:address":"Obere Rainstrasse",
    "sg:city":"Neuheim",
    "sg:orig_category":"Herstellung von Hebezeugen U F\u00f6rdermitteln",
    "sg:phone":"+41 41 755 08 36",
    "sg:postcode":"6345",
    "sg:province":"Zug",
    "wof:name":"Gewatra Ag",
    "wof:placetype":"venue"
},
  "geometry": {"coordinates":[8.5756597519,47.2038459778],"type":"Point"}
}