{
  "type": "Feature",
  "properties": {
    "iso:country":"CH",
    "sg:address":"Fehraltorferstrasse 24",
    "sg:city":"Russikon",
    "sg:orig_category":"D\u00fcngemittel Grosshandel",
    "sg:phone":"+41 19956735",
    "sg:postcode":"8332",
    "sg:province":"Z\u00fcrich",
    "wof:name":"Green Wave Gmbh",
    "wof:placetype":"venue"
},
  "geometry": {"coordinates":[8.7710151672,47.3915596008],"type":"Point"}
}