{
  "type": "Feature",
  "properties": {
    "addr:full":"Z\u00e4pfehusstr. 1 9533 Kirchberg Sg. Postfach Bazenheid St. Gallen 9602",
    "addr:housenumber":"1;9602",
    "addr:postcode":"9533",
    "addr:street":"Zaepfehusstr.;Bazenheid",
    "iso:country":"CH",
    "sg:address":"Z\u00e4pfehusstr. 1 9533 Kirchberg Sg. Postfach",
    "sg:city":"Bazenheid",
    "sg:orig_category":"Allgemeiner Hoch U Tiefbau",
    "sg:postcode":"9602",
    "sg:province":"St. Gallen",
    "wof:name":"Thalmann Werner",
    "wof:placetype":"venue"
},
  "geometry": {"coordinates":[9.040159,47.41066],"type":"Point"}
}