{
  "type": "Feature",
  "properties": {
    "iso:country":"CH",
    "sg:address":"Champs Derri\u00e8re",
    "sg:city":"Buchillon",
    "sg:orig_category":"Vermietung U Verpachtung von eigenen Immobilien",
    "sg:postcode":"1164",
    "sg:province":"Vaud",
    "wof:name":"Si Les Champs-clairs",
    "wof:placetype":"venue"
},
  "geometry": {"coordinates":[6.4212551117,46.4699859619],"type":"Point"}
}