{
  "type": "Feature",
  "properties": {
    "iso:country":"CH",
    "sg:address":"7307",
    "sg:city":"Jenins",
    "sg:orig_category":"Sportvereine Sch\u00fctzen Pistolen-& Gewehr",
    "sg:postcode":"7307",
    "sg:province":"Graubunden",
    "wof:name":"Ortssch\u00fctzengesellschaft",
    "wof:placetype":"venue"
},
  "geometry": {"coordinates":[9.554523468,47.0008049011],"type":"Point"}
}