{
  "type": "Feature",
  "properties": {
    "iso:country":"CH",
    "sg:address":"Haus Kreuz",
    "sg:city":"Unterterzen",
    "sg:orig_category":"Grosshandel mit Holz U Bauelementen aus Holz",
    "sg:phone":"+41 79 408 06 55",
    "sg:postcode":"8882",
    "sg:province":"St. Gallen",
    "wof:name":"Walser Ag Quarten Holzhandel",
    "wof:placetype":"venue"
},
  "geometry": {"coordinates":[9.2530403137,47.1135139465],"type":"Point"}
}