{
  "type": "Feature",
  "properties": {
    "iso:country":"CH",
    "sg:address":"Stetterstrasse 43",
    "sg:city":"Mellingen",
    "sg:orig_category":"Bauschreinerei Zimmerei, Dachdeckerei, Bauspenglerei U Abdichtung",
    "sg:phone":"+41 56 491 31 13",
    "sg:postcode":"5507",
    "sg:province":"Aargau",
    "wof:name":"Zimmerei-schreinerei Wendel Gmbh",
    "wof:placetype":"venue"
},
  "geometry": {"coordinates":[8.281363,47.418098],"type":"Point"}
}