{
  "type": "Feature",
  "properties": {
    "iso:country":"CH",
    "sg:address":"Schipfe 7",
    "sg:city":"Z\u00fcrich",
    "sg:orig_category":"Grosshandel mit Getr\u00e4nken",
    "sg:postcode":"8001",
    "sg:province":"Z\u00fcrich",
    "wof:name":"Lobkov Z\u00fcrich Gmbh, Lobkov Zurich Ltd Liab Co",
    "wof:placetype":"venue"
},
  "geometry": {"coordinates":[8.5413646698,47.3719367981],"type":"Point"}
}