{
  "type": "Feature",
  "properties": {
    "iso:country":"CH",
    "sg:address":"Kirchgasse 1",
    "sg:city":"Bettlach",
    "sg:orig_category":"Detailhandel mit Brot, Back U S\u00fcsswaren",
    "sg:phone":"+41 32 645 18 83",
    "sg:postcode":"2544",
    "sg:province":"Solothurn",
    "wof:name":"Erich Gutmann B\u00e4ckerei-konditorei",
    "wof:placetype":"venue"
},
  "geometry": {"coordinates":[7.424334,47.204128],"type":"Point"}
}