{
  "type": "Feature",
  "properties": {
    "iso:country":"CH",
    "sg:address":"Hagenwilerstrasse 11 8580 Amriswil. Postfach",
    "sg:city":"Amriswil",
    "sg:orig_category":"Zimmerei, Dachdeckerei, Bauspenglerei U Abdichtung",
    "sg:postcode":"8580",
    "sg:province":"Thurgau",
    "wof:name":"K\u00fcnzle Zimmerei - Innenausbau",
    "wof:placetype":"venue"
},
  "geometry": {"coordinates":[9.2863397598,47.5432929993],"type":"Point"}
}