{
  "type": "Feature",
  "properties": {
    "iso:country":"CH",
    "sg:address":"Niederaach",
    "sg:city":"Oberaach",
    "sg:classifiers":[
        {
            "category":"Restaurant",
            "type":"Food & Drink"
        }
    ],
    "sg:phone":"+41 71 411 19 46",
    "sg:postcode":"8587",
    "sg:province":"Thurgau",
    "wof:name":"Restaurant National",
    "wof:placetype":"venue"
},
  "geometry": {"coordinates":[9.2735595703,47.5579185486],"type":"Point"}
}