{
  "type": "Feature",
  "properties": {
    "iso:country":"CH",
    "sg:address":"Greifengasse 10",
    "sg:city":"Basel",
    "sg:orig_category":"Herstellung von Medikamenten U sonstigen pharmazeutischen Erzeugnissen Parf\u00fcmerien U sonstiger Detai",
    "sg:phone":"+41 61 681 57 07",
    "sg:postcode":"4058",
    "sg:province":"Basel-Stadt",
    "wof:name":"Alrodo Ag",
    "wof:placetype":"venue"
},
  "geometry": {"coordinates":[7.5917057991,47.5608520508],"type":"Point"}
}