{
  "type": "Feature",
  "properties": {
    "addr:full":"Route De L'ileau-bois Monthey Valais 1870",
    "addr:postcode":"1870",
    "addr:street":"Route De L'Ileau-Bois",
    "iso:country":"CH",
    "sg:address":"Route De L'ileau-bois",
    "sg:city":"Monthey",
    "sg:orig_category":"Architektur U Ingenieurb\u00fcros",
    "sg:postcode":"1870",
    "sg:province":"Valais",
    "wof:name":"Avanti Switzerland (monthey) Sa",
    "wof:placetype":"venue"
},
  "geometry": {"coordinates":[6.958321,46.253651],"type":"Point"}
}