{
  "type": "Feature",
  "properties": {
    "iso:country":"CH",
    "sg:address":"Matthofstrand 8",
    "sg:city":"Luzern",
    "sg:orig_category":"Handels-H\u00e4user U Gesellschaften",
    "sg:phone":"+41 41 368 10 85",
    "sg:postcode":"6005",
    "sg:province":"Luzern",
    "wof:name":"Studhalter Handels Ag",
    "wof:placetype":"venue"
},
  "geometry": {"coordinates":[8.3324298859,47.0359840393],"type":"Point"}
}