{
  "type": "Feature",
  "properties": {
    "iso:country":"CH",
    "sg:address":"Heidenerstrasse 14",
    "sg:city":"Rehetobel",
    "sg:classifiers":[
        {
            "category":"Travel",
            "subcategory":"Hotels & Motels",
            "type":"Entertainment"
        }
    ],
    "sg:postcode":"9038",
    "sg:province":"Appenzell Ausserrhoden",
    "sg:tags":[
        "hotels",
        "mit",
        "restaurant"
    ],
    "wof:name":"Tobler K & L, Gasthaus \u00abl\u00f6wen\u00bb",
    "wof:placetype":"venue"
},
  "geometry": {"coordinates":[9.4866724014,47.42527771],"type":"Point"}
}