{
  "type": "Feature",
  "properties": {
    "iso:country":"CH",
    "sg:address":"Winkelgass 10 9494 Schaan. Postfach 416",
    "sg:city":"Schaan",
    "sg:orig_category":"Gartenbau Geb\u00e4ude, Wohnungsreinigung",
    "sg:phone":"+423 233 17 66",
    "sg:postcode":"9494",
    "wof:name":"Lisag Liegenschafts-service Ag",
    "wof:placetype":"venue"
},
  "geometry": {"coordinates":[9.5096673965,47.1625480652],"type":"Point"}
}