{
  "type": "Feature",
  "properties": {
    "iso:country":"CH",
    "sg:address":"Rue Micheli-du-crest 22",
    "sg:city":"Gen\u00e8ve",
    "sg:orig_category":"Physiotherapie",
    "sg:phone":"+41 55 283 26 24",
    "sg:postcode":"1205",
    "sg:province":"Gen\u00e8ve",
    "wof:name":"Avril A. Bill Physiotherapie",
    "wof:placetype":"venue"
},
  "geometry": {"coordinates":[9.0090179443,47.1988868713],"type":"Point"}
}