{
  "type": "Feature",
  "properties": {
    "iso:country":"CH",
    "sg:address":"Schlossstrasse 15",
    "sg:city":"Nidau",
    "sg:classifiers":[
        {
            "category":"Manufacturing",
            "subcategory":"Tools & Machinery",
            "type":"Manufacturing & Wholesale Goods"
        }
    ],
    "sg:phone":"+41 32 331 31 08",
    "sg:postcode":"2560",
    "sg:province":"Bern",
    "sg:tags":[
        "construction",
        "container",
        "apparatus"
    ],
    "wof:name":"Fink & Sohn Pr\u00e4zisionsmechanik",
    "wof:placetype":"venue"
},
  "geometry": {"coordinates":[7.235977,47.127369],"type":"Point"}
}