{
  "type": "Feature",
  "properties": {
    "iso:country":"CH",
    "sg:address":"L\u00f6hrenweg 63",
    "sg:city":"Biel/bienne",
    "sg:orig_category":"Unclassifiable Establishments",
    "sg:postcode":"2504",
    "sg:province":"Bern",
    "wof:name":"Agence Du Grand Sud, Werner R\u00fcdlinger",
    "wof:placetype":"venue"
},
  "geometry": {"coordinates":[7.2840371132,47.1434631348],"type":"Point"}
}