{
  "type": "Feature",
  "properties": {
    "iso:country":"CH",
    "sg:address":"Rue Eug\u00e8ne-marziano 17a",
    "sg:city":"Gen\u00e8ve",
    "sg:orig_category":"Datenbanken",
    "sg:postcode":"1200",
    "sg:province":"Gen\u00e8ve",
    "wof:name":"Voxline Communications Sa",
    "wof:placetype":"venue"
},
  "geometry": {"coordinates":[6.131559,46.191803],"type":"Point"}
}