{
  "type": "Feature",
  "properties": {
    "iso:country":"CH",
    "sg:address":"Nefenstrasse 15",
    "sg:city":"Heerbrugg",
    "sg:orig_category":"Sportvereine Ballsport Tennis",
    "sg:phone":"+41 71 966 32 13",
    "sg:postcode":"9435",
    "sg:province":"St. Gallen",
    "wof:name":"Tennis-club Hinterthurgau",
    "wof:placetype":"venue"
},
  "geometry": {"coordinates":[8.9941520691,47.4877128601],"type":"Point"}
}