{
  "type": "Feature",
  "properties": {
    "iso:country":"CH",
    "sg:address":"Goldgrubenweg 26 2504 Biel/bienne. Postfach",
    "sg:city":"Biel/bienne",
    "sg:orig_category":"Unclassifiable Establishments",
    "sg:phone":"+41 32 341 81 40",
    "sg:postcode":"2502",
    "sg:province":"Bern",
    "wof:name":"Gianotta Arbeitssicherheit Beratungen, Schulungen U. Weiterbildung Von Sicherheitsfachleuten U. Sicherheitsingenieuren",
    "wof:placetype":"venue"
},
  "geometry": {"coordinates":[7.2812972069,47.1492004395],"type":"Point"}
}