{
  "type": "Feature",
  "properties": {
    "iso:country":"CH",
    "sg:address":"Chemin Grands-champs 45",
    "sg:city":"Cheseaux-lausanne",
    "sg:orig_category":"Vereine Musik/Blasmusik",
    "sg:phone":"+41 21 731 42 15",
    "sg:postcode":"1033",
    "sg:province":"Vaud",
    "wof:name":"Union Musicale",
    "wof:placetype":"venue"
},
  "geometry": {"coordinates":[6.6125020981,46.5834388733],"type":"Point"}
}