{
  "type": "Feature",
  "properties": {
    "iso:country":"CH",
    "sg:address":"Kreuzstrasse 20",
    "sg:city":"Kriens",
    "sg:orig_category":"Detailhandel mit Spielwaren Erbringung von Dienstleistungen f\u00fcr Unternehmen",
    "sg:phone":"+41 41 340 08 07",
    "sg:postcode":"6010",
    "sg:province":"Luzern",
    "wof:name":"Delta Modellbau Patrick Gernet",
    "wof:placetype":"venue"
},
  "geometry": {"coordinates":[8.3005571365,47.0217666626],"type":"Point"}
}