{
  "type": "Feature",
  "properties": {
    "iso:country":"CH",
    "sg:address":"Canton L\u00e0",
    "sg:city":"Arzo",
    "sg:orig_category":"Sonstiger Grosshandel",
    "sg:phone":"+41 91 646 73 37",
    "sg:postcode":"6864",
    "sg:province":"Ticino",
    "wof:name":"Raimondo Imholz",
    "wof:placetype":"venue"
},
  "geometry": {"coordinates":[8.939863205,45.8755455017],"type":"Point"}
}