{
  "type": "Feature",
  "properties": {
    "iso:country":"CH",
    "sg:address":"Rue Des Granges 2",
    "sg:city":"Monthey",
    "sg:orig_category":"Arztpraxen",
    "sg:phone":"+41 24 471 26 33",
    "sg:postcode":"1870",
    "sg:province":"Valais",
    "wof:name":"Dr M\u00e9d. Daniel Wildhaber M\u00e9decin G\u00e9n\u00e9raliste Fmh",
    "wof:placetype":"venue"
},
  "geometry": {"coordinates":[6.94627,46.250751],"type":"Point"}
}