{
  "type": "Feature",
  "properties": {
    "iso:country":"CH",
    "sg:address":"Kirchrainweg 4 6010 Kriens. Postfach 505",
    "sg:city":"Kriens",
    "sg:orig_category":"Herstellung von Werkzeugen",
    "sg:phone":"+41 55 442 78 77",
    "sg:postcode":"6011",
    "sg:province":"Luzern",
    "wof:name":"Bouquet Schweiz Russo Paul Gmbh",
    "wof:placetype":"venue"
},
  "geometry": {"coordinates":[8.8495960236,47.1912193298],"type":"Point"}
}