{
  "type": "Feature",
  "properties": {
    "iso:country":"CH",
    "sg:address":"Allmendstrasse 71",
    "sg:city":"Grenchen",
    "sg:orig_category":"Reparatur von Uhren U Schmuck",
    "sg:phone":"+41 32 652 56 07",
    "sg:postcode":"2540",
    "sg:province":"Solothurn",
    "wof:name":"J\u00fcrg Schneider Uhrenreparaturservice",
    "wof:placetype":"venue"
},
  "geometry": {"coordinates":[7.3964557648,47.2030143738],"type":"Point"}
}