{
  "type": "Feature",
  "properties": {
    "iso:country":"CH",
    "sg:address":"Postweg 16 8754 Netstal. Postfach",
    "sg:city":"Netstal",
    "sg:orig_category":"Allgemeiner Hoch U Tiefbau",
    "sg:postcode":"8754",
    "sg:province":"Glarus",
    "wof:name":"Schnyder Festzelte Ag",
    "wof:placetype":"venue"
},
  "geometry": {"coordinates":[9.05663,47.063835],"type":"Point"}
}