{
  "type": "Feature",
  "properties": {
    "addr:full":"Buckstrasse 6 W\u00e4denswil Z\u00fcrich 8820",
    "addr:housenumber":"6",
    "addr:postcode":"8820",
    "addr:street":"Buckstrasse;Zuerich",
    "iso:country":"CH",
    "sg:address":"Buckstrasse 6",
    "sg:city":"W\u00e4denswil",
    "sg:orig_category":"Architektur U Ingenieurb\u00fcros",
    "sg:phone":"+41 56 424 19 84",
    "sg:postcode":"8820",
    "sg:province":"Z\u00fcrich",
    "wof:name":"Ruef + Albisser Ag",
    "wof:placetype":"venue"
},
  "geometry": {"coordinates":[8.293079,47.447739],"type":"Point"}
}