{
  "type": "Feature",
  "properties": {
    "iso:country":"CH",
    "sg:address":"Schanzeneggstrasse 1",
    "sg:city":"Z\u00fcrich",
    "sg:orig_category":"Patentverwertung",
    "sg:phone":"+41 12018467",
    "sg:postcode":"8002",
    "sg:province":"Z\u00fcrich",
    "wof:name":"Scropas Ag",
    "wof:placetype":"venue"
},
  "geometry": {"coordinates":[8.5346384048,47.369354248],"type":"Point"}
}