{
  "type": "Feature",
  "properties": {
    "iso:country":"CH",
    "sg:address":"Werkhofstrasse 8",
    "sg:city":"Unterentfelden",
    "sg:orig_category":"Reinigungsgewerbe",
    "sg:phone":"+41 62 723 42 26",
    "sg:postcode":"5035",
    "sg:province":"Aargau",
    "wof:name":"Adex Gomringer E.",
    "wof:placetype":"venue"
},
  "geometry": {"coordinates":[8.0449924469,47.3647384644],"type":"Point"}
}