{
  "type": "Feature",
  "properties": {
    "iso:country":"CH",
    "sg:address":"Via Scer",
    "sg:city":"Corteglia",
    "sg:orig_category":"Herstellung von Metallkonstruktionen Stahl U Leichtmetallbau",
    "sg:phone":"+41 91 646 81 11",
    "sg:postcode":"6873",
    "sg:province":"Ticino",
    "wof:name":"Tecnoser Sa",
    "wof:placetype":"venue"
},
  "geometry": {"coordinates":[8.9946975708,45.8618507385],"type":"Point"}
}