{
  "type": "Feature",
  "properties": {
    "iso:country":"CH",
    "sg:address":"Wartstrasse 5",
    "sg:city":"Winterthur",
    "sg:orig_category":"Pers\u00f6nliche Dienstleistungen",
    "sg:phone":"+41 79 642 19 88",
    "sg:postcode":"8400",
    "sg:province":"Z\u00fcrich",
    "wof:name":"Emchi Choenzom Thai Therapeutin",
    "wof:placetype":"venue"
},
  "geometry": {"coordinates":[8.722319603,47.5006866455],"type":"Point"}
}