{
  "type": "Feature",
  "properties": {
    "iso:country":"CH",
    "sg:address":"Buchenweg 11",
    "sg:city":"Gattikon",
    "sg:orig_category":"Grosshandel mit B\u00fcromaschinen Herstellung von Radio U Fernsehger\u00e4ten sowie phono U videotechnischen ",
    "sg:phone":"+41 14003003",
    "sg:postcode":"8136",
    "sg:province":"Z\u00fcrich",
    "wof:name":"Amix Microsystems Ag",
    "wof:placetype":"venue"
},
  "geometry": {"coordinates":[8.5490446091,47.2831687927],"type":"Point"}
}