{
  "type": "Feature",
  "properties": {
    "iso:country":"CH",
    "sg:address":"Geerenhag 5",
    "sg:city":"Unterehrendingen",
    "sg:orig_category":"Architektur U Ingenieurb\u00fcros",
    "sg:phone":"+41 19103725",
    "sg:postcode":"5424",
    "wof:name":"Barbara Weber Dipl. Architektin Eth/sia Bruno Oertli Architekt Htl",
    "wof:placetype":"venue"
},
  "geometry": {"coordinates":[8.582559,47.329037],"type":"Point"}
}