{
  "type": "Feature",
  "properties": {
    "iso:country":"CH",
    "sg:address":"Ebnetstrasse 1",
    "sg:city":"Adligenswil",
    "sg:orig_category":"Unclassifiable Establishments",
    "sg:postcode":"6043",
    "sg:province":"Luzern",
    "wof:name":"Josef Sigrist Ag",
    "wof:placetype":"venue"
},
  "geometry": {"coordinates":[8.3594865799,47.0741767883],"type":"Point"}
}