{
  "type": "Feature",
  "properties": {
    "iso:country":"CH",
    "sg:address":"Kl\u00f6sterliallmend 7",
    "sg:city":"Meggen",
    "sg:orig_category":"Sportschulen Wassersport",
    "sg:phone":"+41 41 377 37 32",
    "sg:postcode":"6045",
    "sg:province":"Luzern",
    "wof:name":"Schwimmklub Luzern Schwimmschule",
    "wof:placetype":"venue"
},
  "geometry": {"coordinates":[8.3701477051,47.0489349365],"type":"Point"}
}