{
  "type": "Feature",
  "properties": {
    "addr:full":"Luzernerstr. 5 Sch\u00f6tz Luzern 6247",
    "addr:housenumber":"5",
    "addr:postcode":"6247",
    "addr:street":"Luzernerstr.",
    "iso:country":"CH",
    "sg:address":"Luzernerstr. 5",
    "sg:city":"Sch\u00f6tz",
    "sg:classifiers":[
        {
            "category":"Banks & Credit Unions",
            "subcategory":"Bank",
            "type":"Services"
        }
    ],
    "sg:phone":"+41 41 984 00 42",
    "sg:postcode":"6247",
    "sg:province":"Luzern",
    "wof:name":"Luzerner Kantonalbank, Kassenstelle",
    "wof:placetype":"venue"
},
  "geometry": {"coordinates":[7.989899,47.170368],"type":"Point"}
}