{
  "type": "Feature",
  "properties": {
    "iso:country":"CH",
    "sg:address":"Chamerstrasse 170",
    "sg:city":"Zug",
    "sg:orig_category":"Unclassifiable Establishments",
    "sg:postcode":"6300",
    "sg:province":"Zug",
    "wof:name":"Cogit8 Gmbh",
    "wof:placetype":"venue"
},
  "geometry": {"coordinates":[8.4854402542,47.1810264587],"type":"Point"}
}