{
  "type": "Feature",
  "properties": {
    "iso:country":"CH",
    "sg:address":"Badenerstrasse 332 8004 Z\u00fcrich. Postfach",
    "sg:city":"Z\u00fcrich",
    "sg:orig_category":"Herstellung von medizinischen U chirurgischen Ger\u00e4ten sowie orthop\u00e4dischen Vorrichtungen Zahntechnis",
    "sg:phone":"+41 79 449 62 02",
    "sg:postcode":"8040",
    "sg:province":"Z\u00fcrich",
    "wof:name":"Morard Claude",
    "wof:placetype":"venue"
},
  "geometry": {"coordinates":[6.9474520683,46.2524032593],"type":"Point"}
}