{
  "type": "Feature",
  "properties": {
    "iso:country":"CH",
    "sg:address":"M\u00fcller-friedbergstrasse 37",
    "sg:city":"Rorschach",
    "sg:classifiers":[
        {
            "category":"Insurance",
            "subcategory":"Insurance Agent",
            "type":"Services"
        }
    ],
    "sg:phone":"+41 62 756 15 50",
    "sg:postcode":"9400",
    "sg:province":"St. Gallen",
    "sg:tags":[
        "versicherungsagenturen",
        "-broker"
    ],
    "wof:name":"Alfred Hauri Versicherungsagenturen",
    "wof:placetype":"venue"
},
  "geometry": {"coordinates":[8.0367860794,47.2027702332],"type":"Point"}
}