{
  "type": "Feature",
  "properties": {
    "iso:country":"CH",
    "sg:address":"Martinstrasse 5",
    "sg:city":"Galgenen",
    "sg:orig_category":"Hardwareberatung",
    "sg:postcode":"8854",
    "sg:province":"Schwyz",
    "wof:name":"K & L Office, Lachmayer K.",
    "wof:placetype":"venue"
},
  "geometry": {"coordinates":[8.8130741119,47.3344726562],"type":"Point"}
}