{
  "type": "Feature",
  "properties": {
    "iso:country":"CH",
    "sg:address":"Stadelstrasse 2 6373 Ennetb\u00fcrgen. Postfach",
    "sg:city":"Ennetb\u00fcrgen",
    "sg:orig_category":"Herstellung von Sportger\u00e4ten",
    "sg:postcode":"6373",
    "sg:province":"Nidwalden",
    "wof:name":"Fan-artic, Enderli Exclusive Fanartikel F\u00fcr Sportvereine",
    "wof:placetype":"venue"
},
  "geometry": {"coordinates":[8.4085025787,46.9862365723],"type":"Point"}
}