{
  "type": "Feature",
  "properties": {
    "iso:country":"CH",
    "sg:address":"S\u00e4genstrasse 68 7000 Chur. Postfach",
    "sg:city":"Chur",
    "sg:orig_category":"Softwareentwicklung U beratung",
    "sg:phone":"+41 81 250 13 11",
    "sg:postcode":"7001",
    "sg:province":"Graubunden",
    "wof:name":"Mgb Data Ag",
    "wof:placetype":"venue"
},
  "geometry": {"coordinates":[9.5255489349,46.8482017517],"type":"Point"}
}