{
  "type": "Feature",
  "properties": {
    "iso:country":"CH",
    "sg:address":"Via Della Stazione 6a",
    "sg:city":"Locarno",
    "sg:orig_category":"Detailhandel mit M\u00f6beln U Haushaltsgegenst\u00e4nden",
    "sg:postcode":"6600",
    "sg:province":"Ticino",
    "wof:name":"Tapimport Gmbh",
    "wof:placetype":"venue"
},
  "geometry": {"coordinates":[8.7970972061,46.1684646606],"type":"Point"}
}