{
  "type": "Feature",
  "properties": {
    "iso:country":"CH",
    "sg:address":"Route De Bottire 30",
    "sg:city":"Sierre",
    "sg:orig_category":"G\u00fcterbef\u00f6rderung im Strassenverkehr",
    "sg:phone":"+41 27 455 16 63",
    "sg:postcode":"3960",
    "sg:province":"Valais",
    "wof:name":"Entreprise De Transport Fournier G\u00e9rald.",
    "wof:placetype":"venue"
},
  "geometry": {"coordinates":[7.5356240273,46.2974243164],"type":"Point"}
}