{
  "type": "Feature",
  "properties": {
    "iso:country":"CH",
    "sg:address":"Lenggenwil-n.",
    "sg:city":"Niederhelfenschwil",
    "sg:orig_category":"S\u00e4ge, Hobel U Holzimpr\u00e4gnierwerke",
    "sg:postcode":"9527",
    "sg:province":"St. Gallen",
    "wof:name":"Br\u00fchwiler Otto",
    "wof:placetype":"venue"
},
  "geometry": {"coordinates":[9.1876983643,47.4777603149],"type":"Point"}
}