{
  "type": "Feature",
  "properties": {
    "iso:country":"CH",
    "sg:address":"Aabachstrasse 22",
    "sg:city":"Seon",
    "sg:classifiers":[
        {
            "category":"Community Center",
            "subcategory":"Social",
            "type":"Public Place"
        }
    ],
    "sg:phone":"+41 62 769 62 00",
    "sg:postcode":"5703",
    "sg:province":"Aargau",
    "sg:tags":[
        "turning",
        "cnc"
    ],
    "wof:name":"Emil Suter Maschinenfabrik Ag",
    "wof:placetype":"venue"
},
  "geometry": {"coordinates":[8.165153,47.353207],"type":"Point"}
}