{
  "type": "Feature",
  "properties": {
    "iso:country":"CH",
    "sg:address":"Chemin Saint-hubert",
    "sg:city":"Sion",
    "sg:orig_category":"Grosshandel mit Obst U Gem\u00fcse",
    "sg:phone":"+41 27 323 41 44",
    "sg:postcode":"1950",
    "sg:province":"Valais",
    "wof:name":"Erwin Kalbermatten Primeurs Engros",
    "wof:placetype":"venue"
},
  "geometry": {"coordinates":[7.3525881767,46.222492218],"type":"Point"}
}