{
  "type": "Feature",
  "properties": {
    "iso:country":"CH",
    "sg:address":"Via Foce",
    "sg:city":"Lugano",
    "sg:orig_category":"Sportvereine Wassersport Rudern",
    "sg:phone":"+41 91 971 23 98",
    "sg:postcode":"6900",
    "sg:province":"Ticino",
    "wof:name":"Club Canottieri Lugano",
    "wof:placetype":"venue"
},
  "geometry": {"coordinates":[8.9616441727,46.0032424927],"type":"Point"}
}