{
  "type": "Feature",
  "properties": {
    "iso:country":"CH",
    "sg:address":"Route Du Chablais 58",
    "sg:city":"Massongex",
    "sg:orig_category":"Elektroinstallation",
    "sg:phone":"+41 24 471 38 40",
    "sg:postcode":"1869",
    "sg:province":"Valais",
    "wof:name":"Gay Gilbert Electricit\u00e9 Sa",
    "wof:placetype":"venue"
},
  "geometry": {"coordinates":[6.983727932,46.243888855],"type":"Point"}
}