{
  "type": "Feature",
  "properties": {
    "iso:country":"CH",
    "sg:address":"Lausanne Rue De 26",
    "sg:city":"Fribourg",
    "sg:orig_category":"Herstellung von Radio U Fernsehger\u00e4ten sowie phono U videotechnischen Ger\u00e4ten",
    "sg:phone":"+41 26 321 13 40",
    "sg:postcode":"1700",
    "sg:province":"Fribourg",
    "wof:name":"T\u00e9l\u00e9communication, Alibashe Ahmed Yusuf",
    "wof:placetype":"venue"
},
  "geometry": {"coordinates":[7.159705162,46.8057098389],"type":"Point"}
}