{
  "type": "Feature",
  "properties": {
    "iso:country":"CH",
    "sg:address":"Bl\u00fcmlisalpstrasse 26",
    "sg:city":"Heimberg",
    "sg:orig_category":"Herstellung von konfektionierten Textilwaren ohne Bekleidung",
    "sg:phone":"+41 41 850 31 77",
    "sg:postcode":"3627",
    "sg:province":"Bern",
    "wof:name":"Sonne-regen Ag",
    "wof:placetype":"venue"
},
  "geometry": {"coordinates":[8.4417686462,47.0834770203],"type":"Point"}
}