{
  "type": "Feature",
  "properties": {
    "iso:country":"CH",
    "sg:address":"Underm\u00fclistrasse 25",
    "sg:city":"Fehraltorf",
    "sg:orig_category":"Herstellung von Kunststoffwaren Schlossereien",
    "sg:phone":"+41 19550501",
    "sg:postcode":"8320",
    "sg:province":"Z\u00fcrich",
    "wof:name":"Kunstoplex W.sonanini",
    "wof:placetype":"venue"
},
  "geometry": {"coordinates":[8.7414999008,47.3903923035],"type":"Point"}
}