{
  "type": "Feature",
  "properties": {
    "iso:country":"CH",
    "sg:address":"Biderstrasse 50",
    "sg:city":"Bern",
    "sg:orig_category":"Bauschreinerei Detailhandel mit M\u00f6beln U Haushaltsgegenst\u00e4nden",
    "sg:phone":"+41 31 931 12 48",
    "sg:postcode":"3006",
    "sg:province":"Bern",
    "wof:name":"W\u00e4lchli & Co",
    "wof:placetype":"venue"
},
  "geometry": {"coordinates":[7.479333,46.957066],"type":"Point"}
}