{
  "type": "Feature",
  "properties": {
    "iso:country":"CH",
    "sg:address":"Weidstrasse 23",
    "sg:city":"Rotkreuz",
    "sg:orig_category":"Unternehmensberatung Wirtschaftspr\u00fcfung, Steuerberatung U Treuhand",
    "sg:phone":"+41 41 790 25 44",
    "sg:postcode":"6343",
    "sg:province":"Zug",
    "wof:name":"Eduran Ag",
    "wof:placetype":"venue"
},
  "geometry": {"coordinates":[8.4297609329,47.135887146],"type":"Point"}
}