{
  "type": "Feature",
  "properties": {
    "iso:country":"CH",
    "sg:address":"Seuzacherstrasse 100",
    "sg:city":"Dinhard",
    "sg:orig_category":"Herstellung von Frucht U Gem\u00fcses\u00e4ften Herstellung von Obst U Fruchtweinen",
    "sg:phone":"+41 52 336 10 77",
    "sg:postcode":"8474",
    "sg:province":"Z\u00fcrich",
    "wof:name":"Ernst Bachmann Mosterei",
    "wof:placetype":"venue"
},
  "geometry": {"coordinates":[8.7528905869,47.5552444458],"type":"Point"}
}