{
  "type": "Feature",
  "properties": {
    "iso:country":"CH",
    "sg:address":"Ringstrasse 46",
    "sg:city":"Lyssach",
    "sg:orig_category":"Architektur U Ingenieurb\u00fcros",
    "sg:phone":"+41 34 445 51 32",
    "sg:postcode":"3421",
    "sg:province":"Bern",
    "wof:name":"Jaussi Beratungen",
    "wof:placetype":"venue"
},
  "geometry": {"coordinates":[7.580442,47.078384],"type":"Point"}
}