{
  "type": "Feature",
  "properties": {
    "iso:country":"CH",
    "sg:address":"Hauptstrasse 67",
    "sg:city":"Zurzach",
    "sg:orig_category":"Detailhandel mit Geschenkartikeln U Souvenirs Detailhandel mit Metallwaren, Anstrichmitteln, Glaswar",
    "sg:phone":"+41 17814202",
    "sg:postcode":"5330",
    "sg:province":"Aargau",
    "wof:name":"Akelei, R\u00fcttimann Anna-marie",
    "wof:placetype":"venue"
},
  "geometry": {"coordinates":[8.6493587494,47.2459144592],"type":"Point"}
}