{
  "type": "Feature",
  "properties": {
    "iso:country":"CH",
    "sg:address":"Zeughausgasse 11",
    "sg:city":"Zug",
    "sg:orig_category":"Herstellung von sonstigen Metallwaren Schmieden",
    "sg:phone":"+41 41 710 55 62",
    "sg:postcode":"6300",
    "sg:province":"Zug",
    "wof:name":"Giovanni Sergi Schuhmacherei Beim Hirschenpl.",
    "wof:placetype":"venue"
},
  "geometry": {"coordinates":[8.5163469315,47.1667327881],"type":"Point"}
}