{
  "type": "Feature",
  "properties": {
    "iso:country":"CH",
    "sg:address":"Chancy Route De 59 1213 Petit-lancy. Postfach",
    "sg:city":"Meyrin",
    "sg:orig_category":"Unclassifiable Establishments",
    "sg:phone":"+41 22 341 67 27",
    "sg:postcode":"1217",
    "sg:province":"Gen\u00e8ve",
    "wof:name":"Soci\u00e9t\u00e9 Immobili\u00e8re 7 Place Du Molard",
    "wof:placetype":"venue"
},
  "geometry": {"coordinates":[6.1001057625,46.1837158203],"type":"Point"}
}