{
  "type": "Feature",
  "properties": {
    "iso:country":"CH",
    "sg:address":"Porrentruy Route De 82",
    "sg:city":"Del\u00e9mont",
    "sg:orig_category":"Kauf U Verkauf von Immobilien auf eigene Rechnung",
    "sg:postcode":"2800",
    "sg:province":"Jura",
    "wof:name":"Golatte Sa",
    "wof:placetype":"venue"
},
  "geometry": {"coordinates":[7.3348441124,47.3605232239],"type":"Point"}
}