{
  "type": "Feature",
  "properties": {
    "iso:country":"CH",
    "sg:address":"Rue Des Parcs 28",
    "sg:city":"Neuch\u00e2tel",
    "sg:orig_category":"Kunsthandel",
    "sg:phone":"+41 79 417 69 35",
    "sg:postcode":"2000",
    "sg:province":"Neuch\u00e2tel",
    "wof:name":"Brocante Michel Michel Deb\u00e9ly",
    "wof:placetype":"venue"
},
  "geometry": {"coordinates":[6.921541214,46.9930725098],"type":"Point"}
}