{
  "type": "Feature",
  "properties": {
    "iso:country":"CH",
    "sg:address":"Avenue G\u00e9n\u00e9ral-guisan 15",
    "sg:city":"Vevey",
    "sg:orig_category":"Detailhandel mit Uhren U Schmuck",
    "sg:phone":"+41 21 922 98 27",
    "sg:postcode":"1800",
    "sg:province":"Vaud",
    "wof:name":"Monique Benamo Bijouterie Le Palmier D'or",
    "wof:placetype":"venue"
},
  "geometry": {"coordinates":[6.8409929276,46.4634170532],"type":"Point"}
}