{
  "type": "Feature",
  "properties": {
    "addr:full":"D\u00e4hlenweg 1 Sch\u00fcpfen Bern 3054",
    "addr:housenumber":"1",
    "addr:postcode":"3054",
    "addr:street":"Daehlenweg",
    "iso:country":"CH",
    "sg:address":"D\u00e4hlenweg 1",
    "sg:city":"Sch\u00fcpfen",
    "sg:orig_category":"Alters U Pflegeheime Wohnheime",
    "sg:phone":"+41 31 879 21 02",
    "sg:postcode":"3054",
    "sg:province":"Bern",
    "wof:name":"Senioren-pension M\u00e4rli-villa B.oppliger & B.m\u00fcller",
    "wof:placetype":"venue"
},
  "geometry": {"coordinates":[7.383484,47.042866],"type":"Point"}
}