{
  "type": "Feature",
  "properties": {
    "addr:full":"Hauptstr. 1 Brugg Aargau 5201",
    "addr:housenumber":"1",
    "addr:postcode":"5201",
    "addr:street":"Hauptstr.",
    "iso:country":"CH",
    "sg:address":"Hauptstr. 1",
    "sg:city":"Brugg",
    "sg:classifiers":[
        {
            "category":"Banks & Credit Unions",
            "subcategory":"Bank",
            "type":"Services"
        }
    ],
    "sg:phone":"+41 4156327111",
    "sg:postcode":"5201",
    "sg:province":"Aargau",
    "wof:name":"Neue Aargauer Bank",
    "wof:placetype":"venue"
},
  "geometry": {"coordinates":[8.207345,47.483406],"type":"Point"}
}