{
  "type": "Feature",
  "properties": {
    "iso:country":"CH",
    "sg:address":"Rte De Ch\u00e2tel-saint-denis",
    "sg:city":"St-l\u00e9gier",
    "sg:classifiers":[
        {
            "category":"Restaurant",
            "type":"Food & Drink"
        }
    ],
    "sg:phone":"+41 21 943 12 28",
    "sg:postcode":"1806",
    "sg:province":"Vaud",
    "wof:name":"Caf\u00e9 De La Veveyse",
    "wof:placetype":"venue"
},
  "geometry": {"coordinates":[6.9043269157,46.5099601746],"type":"Point"}
}