{
  "type": "Feature",
  "properties": {
    "iso:country":"CH",
    "sg:address":"Jurastrasse 18",
    "sg:city":"Langenthal",
    "sg:classifiers":[
        {
            "category":"Bars & Pubs",
            "type":"Food & Drink"
        }
    ],
    "sg:phone":"+41 62 923 41 61",
    "sg:postcode":"4900",
    "sg:province":"Bern",
    "sg:tags":[
        "restaurant"
    ],
    "wof:name":"Brasserie & Bar Turm",
    "wof:placetype":"venue"
},
  "geometry": {"coordinates":[7.789712,47.21344],"type":"Point"}
}