{
  "type": "Feature",
  "properties": {
    "iso:country":"CH",
    "sg:address":"Reinacherstrasse 67",
    "sg:city":"Basel",
    "sg:orig_category":"Grosshandel mit M\u00f6beln, Wohnbedarf, Teppichen U Bodenbel\u00e4gen",
    "sg:phone":"+41 61 331 05 26",
    "sg:postcode":"4053",
    "sg:province":"Basel-Stadt",
    "wof:name":"Micasa Migros",
    "wof:placetype":"venue"
},
  "geometry": {"coordinates":[7.6034941673,47.5390892029],"type":"Point"}
}