{
  "type": "Feature",
  "properties": {
    "iso:country":"CH",
    "sg:address":"Kolinplatz 8",
    "sg:city":"Zug",
    "sg:orig_category":"Unclassifiable Establishments",
    "sg:phone":"+41 91 730 16 00",
    "sg:postcode":"6300",
    "sg:province":"Zug",
    "wof:name":"Enetmaster Ag",
    "wof:placetype":"venue"
},
  "geometry": {"coordinates":[8.515206337,47.1661148071],"type":"Point"}
}