{
  "type": "Feature",
  "properties": {
    "iso:country":"CH",
    "sg:address":"Casinoplatz 7",
    "sg:city":"Chur",
    "sg:classifiers":[
        {
            "category":"Professional",
            "subcategory":"Employment Agencies",
            "type":"Services"
        }
    ],
    "sg:postcode":"7000",
    "sg:province":"Graubunden",
    "sg:tags":[
        "personal",
        "u",
        "stellenvermittlung"
    ],
    "wof:name":"Voneschen Personalservice",
    "wof:placetype":"venue"
},
  "geometry": {"coordinates":[9.5318603516,46.8488616943],"type":"Point"}
}