{
  "type": "Feature",
  "properties": {
    "iso:country":"CH",
    "sg:address":"7477",
    "sg:city":"Filisur",
    "sg:orig_category":"Polizei",
    "sg:phone":"+41 81 404 12 77",
    "sg:postcode":"7477",
    "sg:province":"Graubunden",
    "wof:name":"Kantonale Polizei",
    "wof:placetype":"venue"
},
  "geometry": {"coordinates":[9.6858797073,46.6734809875],"type":"Point"}
}