{
  "type": "Feature",
  "properties": {
    "iso:country":"CH",
    "sg:address":"3647",
    "sg:city":"Reutigen",
    "sg:orig_category":"Vereine Musik/Blasmusik",
    "sg:phone":"+41 33 437 20 77",
    "sg:postcode":"3647",
    "sg:province":"Bern",
    "wof:name":"Musikgesellschaft",
    "wof:placetype":"venue"
},
  "geometry": {"coordinates":[7.6230797768,46.6927680969],"type":"Point"}
}