{
  "type": "Feature",
  "properties": {
    "iso:country":"CH",
    "sg:address":"B\u00fcttenbergstrasse 4 2500 Biel/bienne. Postfach",
    "sg:city":"Biel/bienne",
    "sg:orig_category":"Detailhandel mit B\u00fcchern, Zeitungen, Schreib U Papeteriewaren",
    "sg:postcode":"2504",
    "sg:province":"Bern",
    "wof:name":"Paci Erika Und Carmelo",
    "wof:placetype":"venue"
},
  "geometry": {"coordinates":[7.289361,47.146812],"type":"Point"}
}