{
  "type": "Feature",
  "properties": {
    "addr:full":"Zollstrasse 104 Osterfingen Schaffhausen 8218",
    "addr:housenumber":"104",
    "addr:postcode":"8218",
    "addr:street":"Zollstrasse",
    "iso:country":"CH",
    "sg:address":"Zollstrasse 104",
    "sg:city":"Osterfingen",
    "sg:orig_category":"Autoreiseunternehmen",
    "sg:phone":"+41 52 681 30 26",
    "sg:postcode":"8218",
    "sg:province":"Schaffhausen",
    "wof:name":"Hatt Reisedienst Gmbh Transporte & Reisen",
    "wof:placetype":"venue"
},
  "geometry": {"coordinates":[8.491831,47.663029],"type":"Point"}
}