{
  "type": "Feature",
  "properties": {
    "iso:country":"CH",
    "sg:address":"Aarestrasse 13",
    "sg:city":"Turgi",
    "sg:orig_category":"Giessereiindustrie Leichtmetallgiesserei",
    "sg:phone":"+41 56 223 12 23",
    "sg:postcode":"5300",
    "sg:province":"Aargau",
    "wof:name":"A. Ehrensperger Ag, Metallgiesserei, Vogelsang Bei Turgi",
    "wof:placetype":"venue"
},
  "geometry": {"coordinates":[8.2528953552,47.4935798645],"type":"Point"}
}