{
  "type": "Feature",
  "properties": {
    "iso:country":"CH",
    "sg:address":"Dorfstrasse 2",
    "sg:city":"Kemptthal",
    "sg:orig_category":"Vereine Vogel-& Naturschutz",
    "sg:phone":"+41 79 643 45 01",
    "sg:postcode":"8310",
    "sg:province":"Z\u00fcrich",
    "wof:name":"Ornithologischer Verein",
    "wof:placetype":"venue"
},
  "geometry": {"coordinates":[8.7018356323,47.4466323853],"type":"Point"}
}