{
  "type": "Feature",
  "properties": {
    "iso:country":"CH",
    "sg:address":"Tittwiesenstrasse 70",
    "sg:city":"Chur",
    "sg:orig_category":"Gartenbau",
    "sg:phone":"+41 31 331 74 41",
    "sg:postcode":"7000",
    "sg:province":"Graubunden",
    "wof:name":"Iso-gart Ag, Garten Und Landschaftsbau",
    "wof:placetype":"venue"
},
  "geometry": {"coordinates":[7.450712204,46.9593658447],"type":"Point"}
}