{
  "type": "Feature",
  "properties": {
    "addr:full":"Chemin De Lavasson 14 Gland Vaud 1196",
    "addr:housenumber":"14",
    "addr:postcode":"1196",
    "addr:street":"Chemin De Lavasson",
    "iso:country":"CH",
    "sg:address":"Chemin De Lavasson 14",
    "sg:city":"Gland",
    "sg:orig_category":"Allgemeiner Hoch U Tiefbau",
    "sg:phone":"+41 22 364 66 40",
    "sg:postcode":"1196",
    "sg:province":"Vaud",
    "wof:name":"Bello Sa",
    "wof:placetype":"venue"
},
  "geometry": {"coordinates":[6.272379,46.42503],"type":"Point"}
}