{
  "type": "Feature",
  "properties": {
    "addr:full":"Ruchstuckstrasse 19 Br\u00fcttisellen Z\u00fcrich 8306",
    "addr:housenumber":"19",
    "addr:postcode":"8306",
    "addr:street":"Ruchstuckstrasse;Zuerich",
    "iso:country":"CH",
    "sg:address":"Ruchstuckstrasse 19",
    "sg:city":"Br\u00fcttisellen",
    "sg:orig_category":"Bauingenieurb\u00fcros Heizung L\u00fcftung Klima",
    "sg:phone":"+41 18335020",
    "sg:postcode":"8306",
    "sg:province":"Z\u00fcrich",
    "wof:name":"Ernst Disler Ingenieurb\u00fcro",
    "wof:placetype":"venue"
},
  "geometry": {"coordinates":[8.630707,47.417439],"type":"Point"}
}