{
  "type": "Feature",
  "properties": {
    "iso:country":"CH",
    "sg:address":"Belle-maison Place De La 3",
    "sg:city":"Lucens",
    "sg:orig_category":"Non-Classified Establishments",
    "sg:postcode":"1522",
    "sg:province":"Vaud",
    "wof:name":"Wellness Concept Amatuzzi & Cie",
    "wof:placetype":"venue"
},
  "geometry": {"coordinates":[6.8381280899,46.7094726562],"type":"Point"}
}