{
  "type": "Feature",
  "properties": {
    "iso:country":"CH",
    "sg:address":"Rue De Veyrot 12 1217 Meyrin. Postfach 377",
    "sg:city":"Meyrin",
    "sg:orig_category":"Sonstige Finanzierungsinstitutionen",
    "sg:phone":"+41 22 719 32 00",
    "sg:postcode":"1217",
    "sg:province":"Gen\u00e8ve",
    "wof:name":"Blanc & Paiche Holding Sa",
    "wof:placetype":"venue"
},
  "geometry": {"coordinates":[6.0630807877,46.2277374268],"type":"Point"}
}