{
  "type": "Feature",
  "properties": {
    "iso:country":"CH",
    "sg:address":"Bettenstrasse 68",
    "sg:city":"Allschwil",
    "sg:orig_category":"Detailhandel mit Teppichen Verlegen von Fussboden",
    "sg:phone":"+41 56 633 21 82",
    "sg:postcode":"4123",
    "sg:province":"Basel-Landschaft",
    "wof:name":"Horat Innendekorationen Ag",
    "wof:placetype":"venue"
},
  "geometry": {"coordinates":[8.3404684067,47.3465538025],"type":"Point"}
}