{
  "type": "Feature",
  "properties": {
    "iso:country":"CH",
    "sg:address":"Unterf\u00fchrungsstrasse 7",
    "sg:city":"Grenchen",
    "sg:orig_category":"Grosshandel mit elektrischen Haushaltsger\u00e4ten Herstellung von elektrischen Lampen U Leuchten",
    "sg:phone":"+41 32 645 27 47",
    "sg:postcode":"2540",
    "sg:province":"Solothurn",
    "wof:name":"Tesla-lampen Gmbh",
    "wof:placetype":"venue"
},
  "geometry": {"coordinates":[7.3982691765,47.1876907349],"type":"Point"}
}