{
  "type": "Feature",
  "properties": {
    "iso:country":"CH",
    "sg:address":"9602 Bazenheid. Postfach",
    "sg:city":"Bazenheid",
    "sg:orig_category":"Vereine Musik/Blasmusik",
    "sg:postcode":"9602",
    "sg:province":"St. Gallen",
    "wof:name":"Musikgesellschaft",
    "wof:placetype":"venue"
},
  "geometry": {"coordinates":[9.0685997009,47.4126701355],"type":"Point"}
}