{
  "type": "Feature",
  "properties": {
    "iso:country":"CH",
    "sg:address":"Lindenhofstrasse 8 3048 Worblaufen. Postfach",
    "sg:city":"Worblaufen",
    "sg:orig_category":"Informatikdienste Logistikberatung",
    "sg:phone":"+41 31 921 98 43",
    "sg:postcode":"3048",
    "sg:province":"Bern",
    "wof:name":"Papaya Media Gmbh",
    "wof:placetype":"venue"
},
  "geometry": {"coordinates":[7.4599409103,46.979724884],"type":"Point"}
}