{
  "type": "Feature",
  "properties": {
    "iso:country":"CH",
    "sg:address":"Espace De L'europe 8",
    "sg:city":"Neuch\u00e2tel",
    "sg:orig_category":"Nationale Postdienste",
    "sg:phone":"+41 32 725 36 95",
    "sg:postcode":"2000",
    "sg:province":"Neuch\u00e2tel",
    "wof:name":"La Poste Suisse Neuch\u00e2tel 5 La Cassarde",
    "wof:placetype":"venue"
},
  "geometry": {"coordinates":[6.9290919304,46.9975242615],"type":"Point"}
}