{
  "type": "Feature",
  "properties": {
    "iso:country":"CH",
    "sg:address":"Neumattweg 6",
    "sg:city":"Horw",
    "sg:orig_category":"Unclassifiable Establishments",
    "sg:postcode":"6048",
    "sg:province":"Luzern",
    "wof:name":"Felder & Partner Produktionsconsulting",
    "wof:placetype":"venue"
},
  "geometry": {"coordinates":[8.3145751953,47.0161895752],"type":"Point"}
}