{
  "type": "Feature",
  "properties": {
    "iso:country":"CH",
    "sg:address":"Seestrasse 154",
    "sg:city":"Horgen",
    "sg:orig_category":"Detailhandel mit Schuhen",
    "sg:phone":"+41 17254013",
    "sg:postcode":"8810",
    "sg:province":"Z\u00fcrich",
    "wof:name":"Dosenbach Schuhe",
    "wof:placetype":"venue"
},
  "geometry": {"coordinates":[8.5983610153,47.2600746155],"type":"Point"}
}