{
  "type": "Feature",
  "properties": {
    "iso:country":"CH",
    "sg:address":"Z\u00fcrcherstrasse 30b",
    "sg:city":"Siebnen",
    "sg:orig_category":"Handel mit Automobilen",
    "sg:postcode":"8854",
    "sg:province":"Schwyz",
    "wof:name":"Gm-cars R. Jaeggi",
    "wof:placetype":"venue"
},
  "geometry": {"coordinates":[8.8935775757,47.1761512756],"type":"Point"}
}