{
  "type": "Feature",
  "properties": {
    "iso:country":"CH",
    "sg:address":"Rue De La Boulangerie 3",
    "sg:city":"Gen\u00e8ve",
    "sg:orig_category":"Diskotheken, Dancings, Night Clubs",
    "sg:phone":"+41 22 310 55 98",
    "sg:postcode":"1204",
    "sg:province":"Gen\u00e8ve",
    "wof:name":"Dancing Byblos",
    "wof:placetype":"venue"
},
  "geometry": {"coordinates":[6.1458778381,46.2016105652],"type":"Point"}
}