{
  "type": "Feature",
  "properties": {
    "iso:country":"CH",
    "sg:address":"Baldeggstrasse 2 6280 Hochdorf. Postfach 861",
    "sg:city":"Hochdorf",
    "sg:orig_category":"Reiseb\u00fcros U Reiseveranstalter",
    "sg:phone":"+41 41 910 66 33",
    "sg:postcode":"6281",
    "sg:province":"Luzern",
    "wof:name":"Arrow Tours Hochdorf Felder Edith",
    "wof:placetype":"venue"
},
  "geometry": {"coordinates":[8.2875013351,47.169834137],"type":"Point"}
}