{
  "type": "Feature",
  "properties": {
    "addr:full":"Steinfeldstrasse 15 R\u00fcmlang Z\u00fcrich 8153",
    "addr:housenumber":"15",
    "addr:postcode":"8153",
    "addr:street":"Steinfeldstrasse;Zuerich",
    "iso:country":"CH",
    "sg:address":"Steinfeldstrasse 15",
    "sg:city":"R\u00fcmlang",
    "sg:orig_category":"Freizeit, Musik",
    "sg:phone":"+41 41018180646",
    "sg:postcode":"8153",
    "sg:province":"Z\u00fcrich",
    "wof:name":"Michael Dinner Panfl\u00f6ten",
    "wof:placetype":"venue"
},
  "geometry": {"coordinates":[8.527242,47.453712],"type":"Point"}
}