{
  "type": "Feature",
  "properties": {
    "iso:country":"CH",
    "sg:address":"B\u00fcrenstrasse 30",
    "sg:city":"Dotzigen",
    "sg:orig_category":"Sonstiger spezialisierter Hoch U Tiefbau",
    "sg:phone":"+41 32 351 20 24",
    "sg:postcode":"3293",
    "sg:province":"Bern",
    "wof:name":"Bekag Kamine Ag",
    "wof:placetype":"venue"
},
  "geometry": {"coordinates":[7.3485841751,47.1293334961],"type":"Point"}
}