{
  "type": "Feature",
  "properties": {
    "iso:country":"CH",
    "sg:address":"Oberfeldweg 17",
    "sg:city":"Hochdorf",
    "sg:orig_category":"Malerei",
    "sg:phone":"+41 41 910 65 30",
    "sg:postcode":"6280",
    "sg:province":"Luzern",
    "wof:name":"Hans V\u00f6geli Malergesch\u00e4ft",
    "wof:placetype":"venue"
},
  "geometry": {"coordinates":[8.3000221252,47.1658058167],"type":"Point"}
}