{
  "type": "Feature",
  "properties": {
    "iso:country":"CH",
    "sg:address":"Marignanostrasse 51",
    "sg:city":"Basel",
    "sg:orig_category":"Kauf U Verkauf von Immobilien auf eigene Rechnung",
    "sg:postcode":"4059",
    "sg:province":"Basel-Stadt",
    "wof:name":"Couss Trois Immobilien Ag",
    "wof:placetype":"venue"
},
  "geometry": {"coordinates":[9.3625650406,47.4164161682],"type":"Point"}
}