{
  "type": "Feature",
  "properties": {
    "iso:country":"CH",
    "sg:address":"Walligrund 3 Eyholz 3930 Visp. Postfach",
    "sg:city":"Eyholz",
    "sg:orig_category":"Maler U Glasergewerbe",
    "sg:postcode":"3931",
    "sg:province":"Valais",
    "wof:name":"Kundenmaler Pfaffen Pascal",
    "wof:placetype":"venue"
},
  "geometry": {"coordinates":[7.8827300072,46.2922286987],"type":"Point"}
}