{
  "type": "Feature",
  "properties": {
    "iso:country":"CH",
    "sg:address":"Baarerstrasse 86",
    "sg:city":"Zug",
    "sg:orig_category":"Unclassifiable Establishments",
    "sg:phone":"+41 19361717",
    "sg:postcode":"6300",
    "sg:province":"Zug",
    "wof:name":"Olivier Gerdamarie Physiotherapie Im Riet",
    "wof:placetype":"venue"
},
  "geometry": {"coordinates":[8.7510004044,47.3058815002],"type":"Point"}
}