{
  "type": "Feature",
  "properties": {
    "iso:country":"CH",
    "sg:address":"Auenring 23 8303 Bassersdorf. Postfach",
    "sg:city":"Bassersdorf",
    "sg:orig_category":"Versandhandel",
    "sg:postcode":"8303",
    "sg:province":"Z\u00fcrich",
    "wof:name":"Classic Versand Calo & Co",
    "wof:placetype":"venue"
},
  "geometry": {"coordinates":[8.6217565536,47.441192627],"type":"Point"}
}