{
  "type": "Feature",
  "properties": {
    "addr:full":"Trevano Via 39 Lugano Ticino 6900",
    "addr:housenumber":"39",
    "addr:postcode":"6900",
    "addr:street":"Via",
    "iso:country":"CH",
    "sg:address":"Trevano Via 39",
    "sg:city":"Lugano",
    "sg:orig_category":"Allgemeiner Hoch U Tiefbau",
    "sg:phone":"+41 91 972 38 07",
    "sg:postcode":"6900",
    "sg:province":"Ticino",
    "wof:name":"Socedil Engineering Sa",
    "wof:placetype":"venue"
},
  "geometry": {"coordinates":[8.955422,46.016144],"type":"Point"}
}