{
  "type": "Feature",
  "properties": {
    "addr:full":"Route De La Conversion 154 Lutry Vaud 1095",
    "addr:housenumber":"154",
    "addr:postcode":"1095",
    "addr:street":"Route De La Conversion",
    "iso:country":"CH",
    "sg:address":"Route De La Conversion 154",
    "sg:city":"Lutry",
    "sg:classifiers":[
        {
            "category":"Shopping",
            "subcategory":"Books",
            "type":"Retail Goods"
        }
    ],
    "sg:phone":"+41 21 792 14 92",
    "sg:postcode":"1095",
    "sg:province":"Vaud",
    "wof:name":"Delacour Sa",
    "wof:placetype":"venue"
},
  "geometry": {"coordinates":[6.682821,46.50906],"type":"Point"}
}