{
  "type": "Feature",
  "properties": {
    "iso:country":"CH",
    "sg:address":"Burgdorfstrasse 30",
    "sg:city":"Oberdiessbach",
    "sg:orig_category":"Wasserversorgung",
    "sg:postcode":"3672",
    "sg:province":"Bern",
    "wof:name":"Wasserversorgungsgenossenschaft Oberhofen (wvgo)",
    "wof:placetype":"venue"
},
  "geometry": {"coordinates":[7.6695899963,46.7359695435],"type":"Point"}
}