{
  "type": "Feature",
  "properties": {
    "iso:country":"CH",
    "sg:address":"Marktgasse 26",
    "sg:city":"Rheinfelden",
    "sg:orig_category":"Detailhandel mit M\u00f6beln U Haushaltsgegenst\u00e4nden Detailhandel mit Teppichen",
    "sg:phone":"+41 61 831 50 80",
    "sg:postcode":"4310",
    "sg:province":"Aargau",
    "wof:name":"Pars Orient Gmbh Teppichverkauf",
    "wof:placetype":"venue"
},
  "geometry": {"coordinates":[7.7927498817,47.5553474426],"type":"Point"}
}