{
  "type": "Feature",
  "properties": {
    "iso:country":"CH",
    "sg:address":"Roman-burri-strasse 12",
    "sg:city":"Sursee",
    "sg:orig_category":"Sonstiger Grosshandel",
    "sg:phone":"+41 41 710 24 74",
    "sg:postcode":"6210",
    "sg:province":"Luzern",
    "wof:name":"Wibera Ag",
    "wof:placetype":"venue"
},
  "geometry": {"coordinates":[8.295838356,47.4870529175],"type":"Point"}
}