{
  "type": "Feature",
  "properties": {
    "iso:country":"CH",
    "sg:address":"Im Grund 1 6130 Willisau. Postfach",
    "sg:city":"Willisau",
    "sg:orig_category":"Herstellung von Betonerzeugnissen f\u00fcr den Bau Sonstiger Detailhandel mit Metallwaren, Anstrichmittel",
    "sg:phone":"+41 41 970 36 09",
    "sg:postcode":"6130",
    "sg:province":"Luzern",
    "wof:name":"Lisbeth Bossert Bowi Bastelparadies",
    "wof:placetype":"venue"
},
  "geometry": {"coordinates":[7.9877181053,47.1202011108],"type":"Point"}
}