{
  "type": "Feature",
  "properties": {
    "iso:country":"CH",
    "sg:address":"Rue De Neuch\u00e2tel 15",
    "sg:city":"Peseux",
    "sg:orig_category":"Autospenglereien",
    "sg:phone":"+41 33 676 20 66",
    "sg:postcode":"2034",
    "sg:province":"Neuch\u00e2tel",
    "wof:name":"Anton Schlapbach Carrosserie",
    "wof:placetype":"venue"
},
  "geometry": {"coordinates":[7.663501,46.607971],"type":"Point"}
}