{
  "type": "Feature",
  "properties": {
    "iso:country":"CH",
    "sg:address":"Rue Du Levant 145",
    "sg:city":"Martigny",
    "sg:orig_category":"Detailhandel mit Schreib U Papeteriewaren Geschenk- and Werbeartikel Grosshandel",
    "sg:phone":"+41 27 722 60 22",
    "sg:postcode":"1920",
    "sg:province":"Valais",
    "wof:name":"Shop Service S\u00e0rl",
    "wof:placetype":"venue"
},
  "geometry": {"coordinates":[7.0894479752,46.102809906],"type":"Point"}
}