{
  "type": "Feature",
  "properties": {
    "iso:country":"CH",
    "sg:address":"Chemin De La Morgette 6",
    "sg:city":"Chigny",
    "sg:orig_category":"Herstellung von Brot U Backwaren Herstellung von Dauerbackwaren",
    "sg:phone":"+41 21 801 95 81",
    "sg:postcode":"1134",
    "sg:province":"Vaud",
    "wof:name":"Sofapain Sa",
    "wof:placetype":"venue"
},
  "geometry": {"coordinates":[6.4801669121,46.5182571411],"type":"Point"}
}