{
  "type": "Feature",
  "properties": {
    "iso:country":"CH",
    "sg:address":"7184",
    "sg:city":"Curaglia",
    "sg:orig_category":"Autogaragen",
    "sg:phone":"+41 56 622 75 87",
    "sg:postcode":"7184",
    "sg:province":"Graubunden",
    "wof:name":"Paul Wyder Autoreparaturwerkst\u00e4tte",
    "wof:placetype":"venue"
},
  "geometry": {"coordinates":[8.276541,47.349686],"type":"Point"}
}