{
  "type": "Feature",
  "properties": {
    "iso:country":"CH",
    "sg:address":"Piazza Motta",
    "sg:city":"Melano",
    "sg:orig_category":"Detailhandel mit Fleisch U Fleischwaren",
    "sg:phone":"+41 91 648 26 37",
    "sg:postcode":"6818",
    "sg:province":"Ticino",
    "wof:name":"Luca Manzocchi Macelleria-salumeria",
    "wof:placetype":"venue"
},
  "geometry": {"coordinates":[8.9860553741,45.9217758179],"type":"Point"}
}