{
  "type": "Feature",
  "properties": {
    "iso:country":"CH",
    "sg:address":"Im Stogelacher 3",
    "sg:city":"Uster",
    "sg:orig_category":"Detailhandel mit Getr\u00e4nken Grosshandel mit Getr\u00e4nken",
    "sg:phone":"+41 19406368",
    "sg:postcode":"8610",
    "sg:province":"Z\u00fcrich",
    "wof:name":"Staubli A., Getr\u00e4nke Uster",
    "wof:placetype":"venue"
},
  "geometry": {"coordinates":[8.6941843033,47.3480987549],"type":"Point"}
}