{
  "type": "Feature",
  "properties": {
    "iso:country":"CH",
    "sg:address":"Emanuel B\u00fcchel-strasse 8",
    "sg:city":"Basel",
    "sg:orig_category":"Vermietung U Verpachtung von eigenen Immobilien",
    "sg:phone":"+41 61 302 40 44",
    "sg:postcode":"4052",
    "sg:province":"Basel-Stadt",
    "wof:name":"Dschobor Ag",
    "wof:placetype":"venue"
},
  "geometry": {"coordinates":[7.6134982109,47.5500297546],"type":"Point"}
}