{
  "type": "Feature",
  "properties": {
    "iso:country":"CH",
    "sg:address":"Grederstrasse 1",
    "sg:city":"Bellach",
    "sg:orig_category":"Detailhandel mit Gebrauchtwaren in Verkaufsr\u00e4umen",
    "sg:phone":"+41 32 618 17 82",
    "sg:postcode":"4512",
    "sg:province":"Solothurn",
    "wof:name":"Italia M\u00f6belgesch\u00e4ft",
    "wof:placetype":"venue"
},
  "geometry": {"coordinates":[7.5067048073,47.2112197876],"type":"Point"}
}