{
  "type": "Feature",
  "properties": {
    "iso:country":"CH",
    "sg:city":"Reinach",
    "sg:orig_category":"Shopping U Fachgesch\u00e4fte, Nahrungs- U Genu\u00dfmittel",
    "sg:postcode":"5734",
    "sg:province":"Aargau",
    "wof:name":"B\u00e4ckerei Konditorei Schulz",
    "wof:placetype":"venue"
},
  "geometry": {"coordinates":[8.18298,47.251102],"type":"Point"}
}