{
  "type": "Feature",
  "properties": {
    "iso:country":"CH",
    "sg:address":"Hauptstrasse 21",
    "sg:city":"Tr\u00fcbbach",
    "sg:orig_category":"Vereine Gesang",
    "sg:phone":"+41 81 783 28 52",
    "sg:postcode":"9477",
    "sg:province":"St. Gallen",
    "wof:name":"M\u00e4nnerchor Oberschan",
    "wof:placetype":"venue"
},
  "geometry": {"coordinates":[9.4818754196,47.0752906799],"type":"Point"}
}