{
  "type": "Feature",
  "properties": {
    "iso:country":"CH",
    "sg:address":"R\u00fctihaldenstrasse 5",
    "sg:city":"Killwangen",
    "sg:orig_category":"G\u00fcterbef\u00f6rderung im Strassenverkehr",
    "sg:phone":"+41 56 401 15 18",
    "sg:postcode":"8956",
    "sg:province":"Aargau",
    "wof:name":"Oberholzer Transporte Gmbh Waren; Transport",
    "wof:placetype":"venue"
},
  "geometry": {"coordinates":[8.3472824097,47.431602478],"type":"Point"}
}