{
  "type": "Feature",
  "properties": {
    "iso:country":"CH",
    "sg:address":"Crappun 18",
    "sg:city":"Samedan",
    "sg:orig_category":"RESTAURANTS: TEA-ROOMS",
    "sg:phone":"+41 81 852 53 53",
    "sg:postcode":"7503",
    "sg:province":"Graubunden",
    "wof:name":"Pianto Cleto",
    "wof:placetype":"venue"
},
  "geometry": {"coordinates":[9.8709907532,46.533531189],"type":"Point"}
}