{
  "type": "Feature",
  "properties": {
    "iso:country":"CH",
    "sg:address":"Gerlisbergstrasse 83",
    "sg:city":"Bassersdorf",
    "sg:orig_category":"Sonstige Aktivit\u00e4ten der nicht-\u00e4rztlichen Medizinalberufe",
    "sg:phone":"+41 18366257",
    "sg:postcode":"8303",
    "sg:province":"Z\u00fcrich",
    "wof:name":"Silvia Fehr Kinesiologie",
    "wof:placetype":"venue"
},
  "geometry": {"coordinates":[8.619228363,47.4517021179],"type":"Point"}
}