{
  "type": "Feature",
  "properties": {
    "iso:country":"CH",
    "sg:address":"Haberweidstrasse 36 8610 Uster. Postfach",
    "sg:city":"Uster",
    "sg:orig_category":"Public-Relations-Agenturen",
    "sg:phone":"+41 19417369",
    "sg:postcode":"8610",
    "sg:province":"Z\u00fcrich",
    "wof:name":"Smartcom Itc-authors Gmbh Dienstleistungen In Den Bereichen Kommunikation, Journalismus, Textherstellung, Public Relation. Warenhandel Usw",
    "wof:placetype":"venue"
},
  "geometry": {"coordinates":[8.7121419907,47.362323761],"type":"Point"}
}