{
  "type": "Feature",
  "properties": {
    "iso:country":"CH",
    "sg:address":"2875",
    "sg:city":"Montfaucon",
    "sg:orig_category":"Instandhaltung U Reparatur von Automobilen",
    "sg:phone":"+41 71 761 11 43",
    "sg:postcode":"2875",
    "sg:province":"Jura",
    "wof:name":"Garage Benz Ag",
    "wof:placetype":"venue"
},
  "geometry": {"coordinates":[9.564620018,47.3203887939],"type":"Point"}
}