{
  "type": "Feature",
  "properties": {
    "iso:country":"CH",
    "sg:address":"Kronenwiese 1",
    "sg:city":"Wattwil",
    "sg:orig_category":"Alters U Pflegeheime Institutionen f\u00fcr Behinderte",
    "sg:phone":"+41 71 988 58 11",
    "sg:postcode":"9630",
    "sg:province":"St. Gallen",
    "wof:name":"Rehabilitationspflegeheim Wis",
    "wof:placetype":"venue"
},
  "geometry": {"coordinates":[9.086835,47.299656],"type":"Point"}
}