{
  "type": "Feature",
  "properties": {
    "iso:country":"CH",
    "sg:address":"Weissenb\u00fchlweg 45",
    "sg:city":"Bern",
    "sg:orig_category":"Herstellung von Reiseartikeln, Leder U Sattlerwaren Innendekorationsateliers",
    "sg:phone":"+41 56 284 16 65",
    "sg:postcode":"3007",
    "sg:province":"Bern",
    "wof:name":"Kurt L\u00e4uchli Sattler & Tapezierer",
    "wof:placetype":"venue"
},
  "geometry": {"coordinates":[8.2057304382,47.5097732544],"type":"Point"}
}