{
  "type": "Feature",
  "properties": {
    "iso:country":"CH",
    "sg:address":"Piotta",
    "sg:city":"Piotta",
    "sg:classifiers":[
        {
            "category":"Banks & Credit Unions",
            "subcategory":"Bank",
            "type":"Services"
        }
    ],
    "sg:phone":"+41 4194891341",
    "sg:postcode":"6776",
    "sg:province":"Ticino",
    "wof:name":"Banca Raiffeisen, Di Quinto-airolo-bedretto",
    "wof:placetype":"venue"
},
  "geometry": {"coordinates":[8.67743,46.512798],"type":"Point"}
}