{
  "type": "Feature",
  "properties": {
    "iso:country":"CH",
    "sg:address":"Wylerstrasse 22",
    "sg:city":"Bern",
    "sg:orig_category":"Saunas, Solarien, Fitnesszentren U \u00e4hnliches",
    "sg:phone":"+41 31 333 81 33",
    "sg:postcode":"3014",
    "sg:province":"Bern",
    "wof:name":"Schweizerische Yoga Gesellschaft (syg), Berufsverband Der Yogalehrer Und Yogalehrerinnen",
    "wof:placetype":"venue"
},
  "geometry": {"coordinates":[7.4497652054,46.9590835571],"type":"Point"}
}