{
  "type": "Feature",
  "properties": {
    "iso:country":"CH",
    "sg:address":"Furkastrasse 1 3900 Brig. Postfach",
    "sg:city":"Brig",
    "sg:orig_category":"Detailhandel mit Damenbekleidung Detailhandel mit Herrenbekleidung",
    "sg:phone":"+41 27 923 10 84",
    "sg:postcode":"3900",
    "sg:province":"Valais",
    "wof:name":"Zur Stadt Paris Ag Generalunternehmung In Den Bereichen Bauen U. Planen U. Handel Mit Immobilien",
    "wof:placetype":"venue"
},
  "geometry": {"coordinates":[7.9879670143,46.3165550232],"type":"Point"}
}