{
  "type": "Feature",
  "properties": {
    "addr:full":"Haus Auf Dem Fels Churwalden Graubunden 7075",
    "addr:postcode":"7075",
    "addr:street":"Dem Fels;Graubunden",
    "iso:country":"CH",
    "sg:address":"Haus Auf Dem Fels",
    "sg:city":"Churwalden",
    "sg:orig_category":"Architektur U Ingenieurb\u00fcros",
    "sg:postcode":"7075",
    "sg:province":"Graubunden",
    "wof:name":"Wettstein Hans-ulrich",
    "wof:placetype":"venue"
},
  "geometry": {"coordinates":[9.5438,46.778545],"type":"Point"}
}