{
  "type": "Feature",
  "properties": {
    "iso:country":"CH",
    "sg:address":"Wasserfallstrasse",
    "sg:city":"Engelberg",
    "sg:orig_category":"Herstellung von k\u00e4lte U lufttechnischen Erzeugnissen f\u00fcr gewerbliche Zwecke",
    "sg:postcode":"6390",
    "sg:province":"Obwalden",
    "wof:name":"Tr\u00fcssel + Cadlini Ag, Zweigniederlassung Engelberg",
    "wof:placetype":"venue"
},
  "geometry": {"coordinates":[8.425863266,46.8091812134],"type":"Point"}
}