{
  "type": "Feature",
  "properties": {
    "iso:country":"CH",
    "sg:address":"Am Wald 88",
    "sg:city":"Auswil",
    "sg:orig_category":"Gartenbau Mechanische Werkst\u00e4tten",
    "sg:phone":"+41 62 965 10 11",
    "sg:postcode":"4944",
    "sg:province":"Bern",
    "wof:name":"Samuel & Verena Lanz Schleifservice & G\u00e4rtnerei",
    "wof:placetype":"venue"
},
  "geometry": {"coordinates":[7.8394107819,47.1390304565],"type":"Point"}
}