{
  "type": "Feature",
  "properties": {
    "iso:country":"CH",
    "sg:address":"Pelzgasse 4",
    "sg:city":"Aarau",
    "sg:orig_category":"Detailhandel mit Brot, Back U S\u00fcsswaren",
    "sg:phone":"+41 62 822 82 41",
    "sg:postcode":"5000",
    "sg:province":"Aargau",
    "wof:name":"Hans Widmer",
    "wof:placetype":"venue"
},
  "geometry": {"coordinates":[8.044309,47.392822],"type":"Point"}
}