{
  "type": "Feature",
  "properties": {
    "iso:country":"CH",
    "sg:address":"G\u00fcterstrasse 50 3008 Bern. Postfach",
    "sg:city":"Bern",
    "sg:orig_category":"Instandhaltung U Reparatur von Automobilen",
    "sg:phone":"+41 22 796 52 35",
    "sg:postcode":"3008",
    "sg:province":"Bern",
    "wof:name":"Carrosserie Ls, D. Langenstein",
    "wof:placetype":"venue"
},
  "geometry": {"coordinates":[6.1009688377,46.205329895],"type":"Point"}
}