{
  "type": "Feature",
  "properties": {
    "iso:country":"CH",
    "sg:address":"Zollhaus",
    "sg:city":"Eschikofen",
    "sg:orig_category":"Betrieb U technische Hilfsdienste des Kultur U Unterhaltungswesens Sonstige Kultur U Unterhaltungsei",
    "sg:postcode":"8554",
    "sg:province":"Thurgau",
    "wof:name":"Zirkus Stey Ag",
    "wof:placetype":"venue"
},
  "geometry": {"coordinates":[9.043525,47.582523],"type":"Point"}
}