{
  "type": "Feature",
  "properties": {
    "iso:country":"CH",
    "sg:address":"Rue Liotard 69 1200 Genf. Postfach",
    "sg:city":"Gen\u00e8ve",
    "sg:orig_category":"Sonstige mit Sport verbundene T\u00e4tigkeiten",
    "sg:postcode":"1203",
    "sg:province":"Gen\u00e8ve",
    "wof:name":"Imaf (suisse)",
    "wof:placetype":"venue"
},
  "geometry": {"coordinates":[6.1260890961,46.2137069702],"type":"Point"}
}