{
  "type": "Feature",
  "properties": {
    "iso:country":"CH",
    "sg:address":"Grand-rue 34",
    "sg:city":"Ch\u00e9zard-st-martin",
    "sg:classifiers":[
        {
            "category":"Travel",
            "subcategory":"Hotels & Motels",
            "type":"Entertainment"
        }
    ],
    "sg:phone":"+41 32 853 20 88",
    "sg:postcode":"2054",
    "sg:province":"Neuch\u00e2tel",
    "sg:tags":[
        "hotels",
        "mit",
        "restaurant"
    ],
    "wof:name":"H\u00f4tel De La Croix D'or",
    "wof:placetype":"venue"
},
  "geometry": {"coordinates":[6.9214792252,47.0638961792],"type":"Point"}
}