{
  "type": "Feature",
  "properties": {
    "iso:country":"CH",
    "sg:address":"Domaine Des Loveresses",
    "sg:city":"Yens-sur-morges",
    "sg:classifiers":[
        {
            "category":"Farming",
            "subcategory":"Crops",
            "type":"Manufacturing & Wholesale Goods"
        }
    ],
    "sg:phone":"+41 21 800 30 39",
    "sg:postcode":"1137",
    "sg:tags":[
        "vegetable",
        "fruit",
        "agriculture",
        "livestock"
    ],
    "wof:name":"Michel Cornu Sa",
    "wof:placetype":"venue"
},
  "geometry": {"coordinates":[6.41617,46.518372],"type":"Point"}
}