{
  "type": "Feature",
  "properties": {
    "addr:full":"Fangh\u00f6fli 14 Littau Luzern 6014",
    "addr:housenumber":"14",
    "addr:postcode":"6014",
    "addr:street":"Fanghoefli",
    "iso:country":"CH",
    "sg:address":"Fangh\u00f6fli 14",
    "sg:city":"Littau",
    "sg:orig_category":"Reagent Test Sets",
    "sg:phone":"+41 41 250 44 80",
    "sg:postcode":"6014",
    "sg:province":"Luzern",
    "wof:name":"Tosoh Bioscience Sa",
    "wof:placetype":"venue"
},
  "geometry": {"coordinates":[8.261656,47.049667],"type":"Point"}
}