{
  "type": "Feature",
  "properties": {
    "iso:country":"CH",
    "sg:address":"Haselweg 9",
    "sg:city":"Sch\u00f6nenwerd",
    "sg:orig_category":"Vereine Damen",
    "sg:postcode":"5012",
    "sg:province":"Solothurn",
    "wof:name":"Hc Sch\u00f6nenwerd Hcs",
    "wof:placetype":"venue"
},
  "geometry": {"coordinates":[8.0024852753,47.3660430908],"type":"Point"}
}