{
  "type": "Feature",
  "properties": {
    "iso:country":"CH",
    "sg:address":"La M\u00e9traude",
    "sg:city":"Savigny",
    "sg:orig_category":"Verwertung von Milch",
    "sg:postcode":"1073",
    "sg:province":"Vaud",
    "wof:name":"Soci\u00e9t\u00e9 De La Laiterie De La Claie-aux-moines.",
    "wof:placetype":"venue"
},
  "geometry": {"coordinates":[6.7232398987,46.5412902832],"type":"Point"}
}