{
  "type": "Feature",
  "properties": {
    "iso:country":"CH",
    "sg:address":"Lyssstrasse 46a",
    "sg:city":"Nidau",
    "sg:orig_category":"Sportvereine Turnen",
    "sg:phone":"+41 62 212 37 08",
    "sg:postcode":"2560",
    "sg:province":"Bern",
    "wof:name":"Arbeiterturnverein",
    "wof:placetype":"venue"
},
  "geometry": {"coordinates":[7.8679261208,47.3391494751],"type":"Point"}
}