{
  "type": "Feature",
  "properties": {
    "iso:country":"CH",
    "sg:address":"Vorstadtplatz 2",
    "sg:city":"Laufen",
    "sg:orig_category":"Allgemeine \u00f6ffentliche Verwaltung Sonstige mit der \u00f6ffentlichen Verwaltung verbundene T\u00e4tigkeiten",
    "sg:phone":"+41 61 766 33 33",
    "sg:postcode":"4242",
    "sg:province":"Basel-Landschaft",
    "wof:name":"Gemeindeverwaltung Laufen",
    "wof:placetype":"venue"
},
  "geometry": {"coordinates":[7.500376,47.420692],"type":"Point"}
}