{
  "type": "Feature",
  "properties": {
    "iso:country":"CH",
    "sg:address":"Rue De Fin-de-praz 22",
    "sg:city":"St-aubin-sauges",
    "sg:classifiers":[
        {
            "category":"Restaurant",
            "type":"Food & Drink"
        }
    ],
    "sg:phone":"+41 32 835 19 79",
    "sg:postcode":"2024",
    "sg:province":"Neuch\u00e2tel",
    "wof:name":"Caf\u00e9 Relais Des Mille-pattes",
    "wof:placetype":"venue"
},
  "geometry": {"coordinates":[6.7794499397,46.8963546753],"type":"Point"}
}