{
  "type": "Feature",
  "properties": {
    "iso:country":"CH",
    "sg:address":"1946",
    "sg:city":"Bourg-st-pierre",
    "sg:orig_category":"Autogaragen",
    "sg:phone":"+41 27 787 11 24",
    "sg:postcode":"1946",
    "sg:province":"Valais",
    "wof:name":"Garage Tunnel Du Gd-st-bernard",
    "wof:placetype":"venue"
},
  "geometry": {"coordinates":[7.208062,45.950157],"type":"Point"}
}