{
  "type": "Feature",
  "properties": {
    "iso:country":"CH",
    "sg:address":"Imhofstrasse 31",
    "sg:city":"Aarau",
    "sg:orig_category":"Tabakverarbeitung",
    "sg:postcode":"5000",
    "sg:province":"Aargau",
    "wof:name":"Cigarrenfabrik Gloor",
    "wof:placetype":"venue"
},
  "geometry": {"coordinates":[8.05838871,47.3850059509],"type":"Point"}
}