{
  "type": "Feature",
  "properties": {
    "iso:country":"CH",
    "sg:address":"Rue Du G\u00e9n\u00e9ral Castella 1a",
    "sg:city":"Bulle",
    "sg:orig_category":"Landw. Genossenschaften Pferdezucht Landw. Genossenschaften Viehzucht",
    "sg:phone":"+41 26 912 38 61",
    "sg:postcode":"1630",
    "sg:province":"Fribourg",
    "wof:name":"Syndicat Chevalin De La Gruy\u00e8re Marie Morand",
    "wof:placetype":"venue"
},
  "geometry": {"coordinates":[7.0641570091,46.6236419678],"type":"Point"}
}