{
  "type": "Feature",
  "properties": {
    "iso:country":"CH",
    "sg:address":"Kirchstrasse 6",
    "sg:city":"Killwangen",
    "sg:orig_category":"Primarschulen",
    "sg:phone":"+41 71 923 34 17",
    "sg:postcode":"8956",
    "sg:province":"Aargau",
    "wof:name":"Primarschule",
    "wof:placetype":"venue"
},
  "geometry": {"coordinates":[9.034948349,47.4527549744],"type":"Point"}
}