{
  "type": "Feature",
  "properties": {
    "iso:country":"CH",
    "sg:address":"Avenue Max Huber 2 3960 Sierre Case Postale 582",
    "sg:city":"Sierre",
    "sg:classifiers":[
        {
            "category":"Insurance",
            "subcategory":"Insurance Agent",
            "type":"Services"
        }
    ],
    "sg:phone":"+41 27 451 91 11",
    "sg:postcode":"3960",
    "sg:province":"Valais",
    "sg:tags":[
        "versicherungsagenturen",
        "-broker"
    ],
    "wof:name":"Zurich-assurances Agence",
    "wof:placetype":"venue"
},
  "geometry": {"coordinates":[7.5344581604,46.2934913635],"type":"Point"}
}