{
  "type": "Feature",
  "properties": {
    "iso:country":"CH",
    "sg:address":"Sonnenbergstrasse 45",
    "sg:city":"Schwerzenbach",
    "sg:orig_category":"Grosshandel mit Parf\u00fcmerieartikeln U K\u00f6rperpflegemitteln Herstellung von Duft U K\u00f6rperpflegemitteln",
    "sg:phone":"+41 18251530",
    "sg:postcode":"8603",
    "sg:province":"Z\u00fcrich",
    "wof:name":"Crn Cosmetic R.nolting",
    "wof:placetype":"venue"
},
  "geometry": {"coordinates":[8.6512107849,47.3851737976],"type":"Point"}
}