{
  "type": "Feature",
  "properties": {
    "iso:country":"CH",
    "sg:address":"Krieg Avenue 46 1208 Gen\u00e8ve. Postfach",
    "sg:city":"Gen\u00e8ve",
    "sg:orig_category":"Verwaltung von Immobilien",
    "sg:postcode":"1201",
    "sg:province":"Gen\u00e8ve",
    "wof:name":"Soci\u00e9t\u00e9 Mobili\u00e8re Et Immobili\u00e8re Nalbourg",
    "wof:placetype":"venue"
},
  "geometry": {"coordinates":[6.1620202065,46.1946487427],"type":"Point"}
}