{
  "type": "Feature",
  "properties": {
    "iso:country":"CH",
    "sg:address":"Ewiges Wegli 10",
    "sg:city":"Kloten",
    "sg:orig_category":"Sonstiges Versicherungsgewerbe",
    "sg:phone":"+41 18135390",
    "sg:postcode":"8302",
    "sg:province":"Z\u00fcrich",
    "wof:name":"Aerosana Krankenkasse",
    "wof:placetype":"venue"
},
  "geometry": {"coordinates":[8.5904245377,47.4530487061],"type":"Point"}
}