{
  "type": "Feature",
  "properties": {
    "iso:country":"CH",
    "sg:address":"Rue Du Bourg 45",
    "sg:city":"Martigny",
    "sg:orig_category":"Architektur U Ingenieurb\u00fcros Architekturb\u00fcros",
    "sg:phone":"+41 71 971 13 38",
    "sg:postcode":"1920",
    "sg:province":"Valais",
    "wof:name":"Schalch + Aeschbacher Ag Eschlikon",
    "wof:placetype":"venue"
},
  "geometry": {"coordinates":[8.96635,47.463814],"type":"Point"}
}