{
  "type": "Feature",
  "properties": {
    "iso:country":"CH",
    "sg:address":"3928",
    "sg:city":"Randa",
    "sg:orig_category":"RESTAURANTS: TEA-ROOMS",
    "sg:postcode":"3928",
    "sg:province":"Valais",
    "wof:name":"Restaurant Alpenrose, Fux-stricker Ursula",
    "wof:placetype":"venue"
},
  "geometry": {"coordinates":[7.7803549767,46.0985984802],"type":"Point"}
}