{
  "type": "Feature",
  "properties": {
    "iso:country":"CH",
    "sg:address":"Coulouvreni\u00e8re Rue De La 19 1204 Gen\u00e8ve. Postfach",
    "sg:city":"Gen\u00e8ve",
    "sg:orig_category":"Herstellung von Uhren",
    "sg:phone":"+41 32 968 04 44",
    "sg:postcode":"1204",
    "sg:province":"Gen\u00e8ve",
    "wof:name":"Calame Et Cie Sa",
    "wof:placetype":"venue"
},
  "geometry": {"coordinates":[6.8280611038,47.1088371277],"type":"Point"}
}