{
  "type": "Feature",
  "properties": {
    "iso:country":"CH",
    "sg:address":"Gundeldingerrain 181",
    "sg:city":"Basel",
    "sg:orig_category":"Geb\u00e4ude, Wohnungsreinigung",
    "sg:phone":"+41 61 712 22 02",
    "sg:postcode":"4059",
    "sg:province":"Basel-Stadt",
    "wof:name":"Top-hauswartung R.richner",
    "wof:placetype":"venue"
},
  "geometry": {"coordinates":[7.589673996,47.4886474609],"type":"Point"}
}