{
  "type": "Feature",
  "properties": {
    "addr:full":"7176 Cumpadials Graubunden 7176",
    "addr:housenumber":"7176",
    "addr:postcode":"7176",
    "addr:street":"Cumpadials Graubunden",
    "iso:country":"CH",
    "sg:address":"7176",
    "sg:city":"Cumpadials",
    "sg:orig_category":"Darlehenskassen U Raiffeisenbanken",
    "sg:phone":"+41 81 943 25 35",
    "sg:postcode":"7176",
    "sg:province":"Graubunden",
    "wof:name":"Banca Raiffeisen",
    "wof:placetype":"venue"
},
  "geometry": {"coordinates":[8.92364,46.722969],"type":"Point"}
}