{
  "type": "Feature",
  "properties": {
    "iso:country":"CH",
    "sg:address":"Haldenstrasse 63 8045 Z\u00fcrich 45 Zust. Postfach 8045 Z\u00fcrich",
    "sg:city":"Zust",
    "sg:orig_category":"Detailhandel mit M\u00f6beln U Haushaltsgegenst\u00e4nden",
    "sg:phone":"+41 14632754",
    "sg:postcode":"45",
    "wof:name":"Pf Production Felix Peter M\u00f6bel U. Design-produkte; Handel, Design, Vermarktung, Entwicklung, Beratung",
    "wof:placetype":"venue"
},
  "geometry": {"coordinates":[8.5118503571,47.3567810059],"type":"Point"}
}