{
  "type": "Feature",
  "properties": {
    "iso:country":"CH",
    "sg:address":"Spiracher 162",
    "sg:city":"Oberb\u00f6zberg",
    "sg:orig_category":"Herstellung von Frucht U Gem\u00fcses\u00e4ften Mechanik",
    "sg:phone":"+41 56 441 83 94",
    "sg:postcode":"5225",
    "sg:province":"Aargau",
    "wof:name":"Frei Hansruedi",
    "wof:placetype":"venue"
},
  "geometry": {"coordinates":[8.1579627991,47.4988327026],"type":"Point"}
}