{
  "type": "Feature",
  "properties": {
    "iso:country":"CH",
    "sg:address":"Seestrasse 24 3600 Thun. Postfach",
    "sg:city":"Thun",
    "sg:orig_category":"Installation von Heizungs, L\u00fcftungs U Klimaanlagen",
    "sg:phone":"+41 56 622 89 79",
    "sg:postcode":"3602",
    "sg:province":"Bern",
    "wof:name":"Guido Weilenmann Heizungen & Montagen",
    "wof:placetype":"venue"
},
  "geometry": {"coordinates":[8.2663440704,47.3478431702],"type":"Point"}
}