{
  "type": "Feature",
  "properties": {
    "iso:country":"CH",
    "sg:address":"Bahnhofstrasse 53",
    "sg:city":"Aarau",
    "sg:orig_category":"Arztpraxen",
    "sg:phone":"+41 62 822 46 20",
    "sg:postcode":"5000",
    "sg:province":"Aargau",
    "wof:name":"Dr.med.eva Vrbka Voramwald Spezial\u00e4rztin Fmh",
    "wof:placetype":"venue"
},
  "geometry": {"coordinates":[8.04903,47.391586],"type":"Point"}
}