{
  "type": "Feature",
  "properties": {
    "iso:country":"CH",
    "sg:address":"Rue Des Terreaux 13 1003 Lausanne. Postfach",
    "sg:city":"Lausanne",
    "sg:orig_category":"Datenverarbeitungsdienste",
    "sg:phone":"+41 21 320 22 06",
    "sg:postcode":"1002",
    "sg:province":"Vaud",
    "wof:name":"Pragma Support Logiciel",
    "wof:placetype":"venue"
},
  "geometry": {"coordinates":[6.628206,46.522472],"type":"Point"}
}