{
  "type": "Feature",
  "properties": {
    "iso:country":"CH",
    "sg:address":"Chemin Des Amandiers 12",
    "sg:city":"Sion",
    "sg:orig_category":"Non-Classified Establishments",
    "sg:postcode":"1950",
    "sg:province":"Valais",
    "wof:name":"Spn Filippini Andr\u00e9",
    "wof:placetype":"venue"
},
  "geometry": {"coordinates":[7.3521709442,46.2321548462],"type":"Point"}
}