{
  "type": "Feature",
  "properties": {
    "iso:country":"CH",
    "sg:address":"Carteret Rue Antoine- 7 1202 Gen\u00e8ve. Postfach",
    "sg:city":"Gen\u00e8ve",
    "sg:orig_category":"Reinigungsgewerbe",
    "sg:postcode":"1202",
    "sg:province":"Gen\u00e8ve",
    "wof:name":"Perriard Francis",
    "wof:placetype":"venue"
},
  "geometry": {"coordinates":[6.1322312355,46.211643219],"type":"Point"}
}