{
  "type": "Feature",
  "properties": {
    "iso:country":"CH",
    "sg:address":"H\u00e4berlig 444 4624 H\u00e4rkingen. Postfach",
    "sg:city":"H\u00e4rkingen",
    "sg:orig_category":"Fachdetailhandel in Verkaufsr\u00e4umen",
    "sg:postcode":"4624",
    "sg:province":"Solothurn",
    "wof:name":"Bloom`s Kiefer Irma Blumendesign Usw",
    "wof:placetype":"venue"
},
  "geometry": {"coordinates":[7.8133997917,47.3054199219],"type":"Point"}
}