{
  "type": "Feature",
  "properties": {
    "iso:country":"CH",
    "sg:address":"Oristalstrasse 89 4410 Liestal. Postfach",
    "sg:city":"Liestal",
    "sg:orig_category":"Interessenvertretungen",
    "sg:postcode":"4410",
    "sg:province":"Basel-Landschaft",
    "wof:name":"Degirmenkaya-stiftung Hilft Den In Not Geratenen Personen Usw",
    "wof:placetype":"venue"
},
  "geometry": {"coordinates":[7.7260551453,47.4759864807],"type":"Point"}
}