{
  "type": "Feature",
  "properties": {
    "iso:country":"CH",
    "sg:address":"Walkestrasse 31 8400 Winterthur. Postfach",
    "sg:city":"Winterthur",
    "sg:orig_category":"Grosshandel mit Textilien",
    "sg:phone":"+41 17374085",
    "sg:postcode":"8400",
    "sg:province":"Z\u00fcrich",
    "wof:name":"Keller Ingrid",
    "wof:placetype":"venue"
},
  "geometry": {"coordinates":[8.4449748993,47.3588447571],"type":"Point"}
}