{
  "type": "Feature",
  "properties": {
    "iso:country":"CH",
    "sg:address":"Griesernweg 50",
    "sg:city":"Z\u00fcrich",
    "sg:orig_category":"Detailhandel mit M\u00f6beln U Haushaltsgegenst\u00e4nden",
    "sg:phone":"+41 12730403",
    "sg:postcode":"8037",
    "sg:province":"Z\u00fcrich",
    "wof:name":"J\u00e4ggi Beat",
    "wof:placetype":"venue"
},
  "geometry": {"coordinates":[8.5159397125,47.3974456787],"type":"Point"}
}