{
  "type": "Feature",
  "properties": {
    "iso:country":"CH",
    "sg:address":"Mon-id\u00e9e Route De 24",
    "sg:city":"Puplinge",
    "sg:orig_category":"Finanzierungsinstitutionen",
    "sg:phone":"+41 61 701 41 77",
    "sg:postcode":"1241",
    "sg:province":"Gen\u00e8ve",
    "wof:name":"Wistaria Ag, Luxembourg, Succursale De Puplinge",
    "wof:placetype":"venue"
},
  "geometry": {"coordinates":[6.2219228745,46.2052116394],"type":"Point"}
}