{
  "type": "Feature",
  "properties": {
    "iso:country":"CH",
    "sg:address":"Rue De L'ecluse 15",
    "sg:city":"Neuenburg",
    "sg:orig_category":"Fachdetailhandel in Verkaufsr\u00e4umen",
    "sg:postcode":"2000",
    "sg:province":"Neuch\u00e2tel",
    "wof:name":"Id\u00e9es Couleurs, Marcacci & Steiner",
    "wof:placetype":"venue"
},
  "geometry": {"coordinates":[6.9266061783,46.9929084778],"type":"Point"}
}