{
  "type": "Feature",
  "properties": {
    "iso:country":"CH",
    "sg:address":"Langenthalerstrasse 16 4802 Strengelbach. Postfach",
    "sg:city":"Strengelbach",
    "sg:orig_category":"M\u00f6belschreinereien",
    "sg:phone":"+41 22 301 28 30",
    "sg:postcode":"4802",
    "sg:province":"Aargau",
    "wof:name":"Roch Pascal",
    "wof:placetype":"venue"
},
  "geometry": {"coordinates":[6.1399431229,46.179309845],"type":"Point"}
}