{
  "type": "Feature",
  "properties": {
    "iso:country":"CH",
    "sg:address":"Hauptstrasse 31",
    "sg:city":"Worben",
    "sg:orig_category":"Detailhandel mit Blumen U Pflanzen Gartenbau",
    "sg:phone":"+41 32 384 11 58",
    "sg:postcode":"3252",
    "sg:province":"Bern",
    "wof:name":"Peter Beyeler Blumengesch\u00e4ft",
    "wof:placetype":"venue"
},
  "geometry": {"coordinates":[7.290539,47.09811],"type":"Point"}
}