{
  "type": "Feature",
  "properties": {
    "iso:country":"CH",
    "sg:address":"Wasserloch",
    "sg:city":"Dagmersellen",
    "sg:orig_category":"Sportvereine Sch\u00fctzen",
    "sg:phone":"+41 62 756 33 30",
    "sg:postcode":"6252",
    "sg:province":"Luzern",
    "wof:name":"Feldsch\u00fctzengesellschaft",
    "wof:placetype":"venue"
},
  "geometry": {"coordinates":[7.9890551567,47.213054657],"type":"Point"}
}