{
  "type": "Feature",
  "properties": {
    "iso:country":"CH",
    "sg:address":"St. Galler-ring 55",
    "sg:city":"Basel",
    "sg:orig_category":"Unclassifiable Establishments",
    "sg:postcode":"4055",
    "sg:province":"Basel-Stadt",
    "wof:name":"F\u00e1brica De Salsa Gonzalez Avil\u00e9s & Tomaschett",
    "wof:placetype":"venue"
},
  "geometry": {"coordinates":[7.5673260689,47.5583076477],"type":"Point"}
}