{
  "type": "Feature",
  "properties": {
    "addr:full":"Kirchgasse 56 7000 Chur. Postfach Chur Graubunden 7000",
    "addr:housenumber":"56",
    "addr:postcode":"7000;postfach;7000",
    "addr:street":"Kirchgasse",
    "iso:country":"CH",
    "sg:address":"Kirchgasse 56 7000 Chur. Postfach",
    "sg:city":"Chur",
    "sg:orig_category":"Architektur U Ingenieurb\u00fcros",
    "sg:postcode":"7000",
    "sg:province":"Graubunden",
    "wof:name":"Natter Architektur + Baumanagement",
    "wof:placetype":"venue"
},
  "geometry": {"coordinates":[9.53321,46.848042],"type":"Point"}
}