{
  "type": "Feature",
  "properties": {
    "iso:country":"CH",
    "sg:address":"Neuhofstrasse",
    "sg:city":"Baar",
    "sg:orig_category":"Non-Classified Establishments",
    "sg:phone":"+41 17870202",
    "sg:postcode":"6340",
    "sg:province":"Zug",
    "wof:name":"Proscom Holding Ag",
    "wof:placetype":"venue"
},
  "geometry": {"coordinates":[8.5141296387,47.1906776428],"type":"Point"}
}