{
  "type": "Feature",
  "properties": {
    "iso:country":"CH",
    "sg:address":"Libellenweg 24",
    "sg:city":"Bern",
    "sg:orig_category":"Grosshandel mit Erzen U Metallen Schlossereien",
    "sg:phone":"+41 31 332 54 60",
    "sg:postcode":"3006",
    "sg:province":"Bern",
    "wof:name":"Krummenacher & Cie., Nachfolger Tanner & Jenni Inhaber Fritz Tanner",
    "wof:placetype":"venue"
},
  "geometry": {"coordinates":[7.4739928246,46.9547309875],"type":"Point"}
}