{
  "type": "Feature",
  "properties": {
    "iso:country":"CH",
    "sg:address":"Hasenlehnmattestrasse 1",
    "sg:city":"Trubschachen",
    "sg:orig_category":"Herstellung von keramischen Haushaltswaren U Ziergegenst\u00e4nden",
    "sg:phone":"+41 34 495 60 29",
    "sg:postcode":"3555",
    "sg:province":"Bern",
    "wof:name":"Markus Aebi Schaut\u00f6pferei",
    "wof:placetype":"venue"
},
  "geometry": {"coordinates":[7.8423261642,46.9221038818],"type":"Point"}
}