{
  "type": "Feature",
  "properties": {
    "iso:country":"CH",
    "sg:address":"Zugerstrasse 11",
    "sg:city":"Ebikon",
    "sg:orig_category":"Informatikdienste Wirtschaftspr\u00fcfung, Steuerberatung U Treuhand",
    "sg:phone":"+41 41 850 59 38",
    "sg:postcode":"6030",
    "sg:province":"Luzern",
    "wof:name":"Awr Solutions Gmbh Dienstleistungen In Den Bereichen Rechnungswesen, Buchf\u00fchrung. Personalwesen Usw",
    "wof:placetype":"venue"
},
  "geometry": {"coordinates":[8.4417686462,47.0834770203],"type":"Point"}
}