{
  "type": "Feature",
  "properties": {
    "iso:country":"CH",
    "sg:address":"Herzogengasse 1",
    "sg:city":"Weiach",
    "sg:orig_category":"Autogaragen",
    "sg:phone":"+41 71 622 20 80",
    "sg:postcode":"8187",
    "sg:province":"Z\u00fcrich",
    "wof:name":"Gebr\u00fcder Huber Garage",
    "wof:placetype":"venue"
},
  "geometry": {"coordinates":[9.138185,47.566669],"type":"Point"}
}