{
  "type": "Feature",
  "properties": {
    "iso:country":"CH",
    "sg:address":"Austrasse 12",
    "sg:city":"Basel",
    "sg:orig_category":"Unclassifiable Establishments",
    "sg:postcode":"4051",
    "sg:province":"Basel-Stadt",
    "wof:name":"Grapha Management & Consulting Ag",
    "wof:placetype":"venue"
},
  "geometry": {"coordinates":[8.3074598312,46.9915618896],"type":"Point"}
}