{
  "type": "Feature",
  "properties": {
    "iso:country":"CH",
    "sg:address":"Hammerstrasse 44",
    "sg:city":"Basel",
    "sg:orig_category":"Geb\u00e4ude, Wohnungsreinigung Reinigungsgewerbe",
    "sg:phone":"+41 79 333 51 18",
    "sg:postcode":"4058",
    "sg:province":"Basel-Stadt",
    "wof:name":"Friedlin Reinigungen Ag",
    "wof:placetype":"venue"
},
  "geometry": {"coordinates":[7.5975198746,47.561542511],"type":"Point"}
}