{
  "type": "Feature",
  "properties": {
    "iso:country":"CH",
    "sg:address":"St\u00e4dtle 27",
    "sg:city":"Vaduz",
    "sg:orig_category":"Detailhandel mit Waren verschiedener Art, Hauptrichtung Nahrungsmittel Fachdetailhandel mit Nahrungs",
    "sg:phone":"+423 232 25 51",
    "sg:postcode":"9490",
    "wof:name":"Karl D\u00fcrr Delikatessen Fr\u00fcchte",
    "wof:placetype":"venue"
},
  "geometry": {"coordinates":[9.5227956772,47.1396484375],"type":"Point"}
}