{
  "type": "Feature",
  "properties": {
    "iso:country":"CH",
    "sg:address":"Claragraben 135 4000 Basel. Postfach",
    "sg:city":"Basel",
    "sg:orig_category":"Erbringung von Dienstleistungen f\u00fcr Unternehmen",
    "sg:postcode":"4051",
    "sg:province":"Basel-Stadt",
    "wof:name":"Handstand Tschudin",
    "wof:placetype":"venue"
},
  "geometry": {"coordinates":[7.5923199654,47.5647354126],"type":"Point"}
}