{
  "type": "Feature",
  "properties": {
    "iso:country":"CH",
    "sg:address":"Wabernstrasse 61",
    "sg:city":"Bern",
    "sg:orig_category":"Religi\u00f6se Vereinigungen divers",
    "sg:phone":"+41 31 371 80 88",
    "sg:postcode":"3007",
    "sg:province":"Bern",
    "wof:name":"Evangelische Allianz Bern",
    "wof:placetype":"venue"
},
  "geometry": {"coordinates":[7.4389138222,46.938331604],"type":"Point"}
}