{
  "type": "Feature",
  "properties": {
    "iso:country":"CH",
    "sg:address":"Les Bioux 1344 L'abbaye. Postfach",
    "sg:city":"L'abbaye",
    "sg:orig_category":"Herstellung von Uhren",
    "sg:postcode":"1344",
    "sg:province":"Vaud",
    "wof:name":"Berney & Pittet Sa",
    "wof:placetype":"venue"
},
  "geometry": {"coordinates":[6.259950161,46.6153488159],"type":"Point"}
}