{
  "type": "Feature",
  "properties": {
    "iso:country":"CH",
    "sg:address":"Vordere Fl\u00fchrainmatte",
    "sg:city":"Ursenbach",
    "sg:orig_category":"Fernmeldedienste",
    "sg:postcode":"4937",
    "sg:province":"Bern",
    "wof:name":"Fernsehgenossenschaft Ursenbach",
    "wof:placetype":"venue"
},
  "geometry": {"coordinates":[7.7732357979,47.1376609802],"type":"Point"}
}