{
  "type": "Feature",
  "properties": {
    "iso:country":"CH",
    "sg:address":"Maiholzstrasse 19",
    "sg:city":"Frauenfeld",
    "sg:orig_category":"Wirtschaftspr\u00fcfung, Steuerberatung U Treuhand",
    "sg:phone":"+41 32 954 18 53",
    "sg:postcode":"8500",
    "sg:province":"Thurgau",
    "wof:name":"Alexandre Gigandet Bureau Fiduciaire",
    "wof:placetype":"venue"
},
  "geometry": {"coordinates":[6.9993290901,47.211227417],"type":"Point"}
}