{
  "type": "Feature",
  "properties": {
    "iso:country":"CH",
    "sg:address":"Zum Landhaus",
    "sg:city":"Walenstadt",
    "sg:orig_category":"RESTAURANTS: TEA-ROOMS",
    "sg:postcode":"8880",
    "sg:province":"St. Gallen",
    "wof:name":"Wildhaber Oskar, Wirtschaft Zum Landhaus",
    "wof:placetype":"venue"
},
  "geometry": {"coordinates":[9.3131351471,47.1246147156],"type":"Point"}
}