{
  "type": "Feature",
  "properties": {
    "iso:country":"CH",
    "sg:address":"Achernstrasse 2",
    "sg:city":"Siebnen",
    "sg:orig_category":"Papier U Kartongewerbe R\u00fcckgewinnung U Vorbereitung f\u00fcr die Wiederverwertung Recycling von nichtmeta",
    "sg:phone":"+41 79 691 51 12",
    "sg:postcode":"8854",
    "sg:province":"Schwyz",
    "wof:name":"K\u00fcng & Kessler",
    "wof:placetype":"venue"
},
  "geometry": {"coordinates":[8.8913049698,47.1764678955],"type":"Point"}
}