{
  "type": "Feature",
  "properties": {
    "iso:country":"CH",
    "sg:address":"Luzernerstrasse 131 6014 Littau. Postfach 164",
    "sg:city":"Littau",
    "sg:orig_category":"Grosshandel mit B\u00fcromaschinen Papier Grosshandel",
    "sg:phone":"+41 56 484 19 84",
    "sg:postcode":"6014",
    "sg:province":"Luzern",
    "wof:name":"Herlitz Ag Schreib-& Papierwaren",
    "wof:placetype":"venue"
},
  "geometry": {"coordinates":[8.2869291306,47.4561080933],"type":"Point"}
}