{
  "type": "Feature",
  "properties": {
    "iso:country":"CH",
    "sg:address":"Flecken 27",
    "sg:city":"Rothenburg",
    "sg:orig_category":"Malerei-Gipserei Stukkateurgewerbe, Gipserei U Verputzerei",
    "sg:phone":"+41 91 870 12 78",
    "sg:postcode":"6023",
    "sg:province":"Luzern",
    "wof:name":"Walter Woerndli Gipsergesch\u00e4ft",
    "wof:placetype":"venue"
},
  "geometry": {"coordinates":[8.2718219757,47.0943183899],"type":"Point"}
}