{
  "type": "Feature",
  "properties": {
    "iso:country":"CH",
    "sg:address":"Kilchbergstrasse 28",
    "sg:city":"Z\u00fcrich",
    "sg:orig_category":"Primarschulen",
    "sg:phone":"+41 14821964",
    "sg:postcode":"8038",
    "sg:province":"Z\u00fcrich",
    "wof:name":"Primarschule Hans Asper",
    "wof:placetype":"venue"
},
  "geometry": {"coordinates":[8.5343542099,47.3414306641],"type":"Point"}
}