{
  "type": "Feature",
  "properties": {
    "addr:full":"Feldstrasse 32c Grosswangen Luzern 6022",
    "addr:housenumber":"32c",
    "addr:postcode":"6022",
    "addr:street":"Feldstrasse",
    "iso:country":"CH",
    "sg:address":"Feldstrasse 32c",
    "sg:city":"Grosswangen",
    "sg:orig_category":"Aktivit\u00e4ten der Generalunternehmen im Baugewerbe Vermittlung von Immobilien",
    "sg:phone":"+41 41 980 66 06",
    "sg:postcode":"6022",
    "sg:province":"Luzern",
    "wof:name":"Cerutti Partner Architekten Ag Architekturb\u00fcro Filiale Grosswangen",
    "wof:placetype":"venue"
},
  "geometry": {"coordinates":[8.045204,47.129429],"type":"Point"}
}