{
  "type": "Feature",
  "properties": {
    "iso:country":"CH",
    "sg:address":"Seefeldstrasse 333",
    "sg:city":"Z\u00fcrich",
    "sg:orig_category":"Druck ohne Zeitungsdruck",
    "sg:phone":"+41 14227772",
    "sg:postcode":"8008",
    "sg:province":"Z\u00fcrich",
    "wof:name":"Offsetdruckerei Ernst Ag",
    "wof:placetype":"venue"
},
  "geometry": {"coordinates":[8.5651321411,47.3467063904],"type":"Point"}
}