{
  "type": "Feature",
  "properties": {
    "iso:country":"CH",
    "sg:address":"Seemattstrasse 11",
    "sg:city":"B\u00fclach",
    "sg:orig_category":"Grosshandel mit Baumaschinen",
    "sg:phone":"+41 18604024",
    "sg:postcode":"8180",
    "sg:province":"Z\u00fcrich",
    "wof:name":"E. Blum Ag Arbeitsschutz",
    "wof:placetype":"venue"
},
  "geometry": {"coordinates":[8.5442304611,47.5189628601],"type":"Point"}
}