{
  "type": "Feature",
  "properties": {
    "iso:country":"CH",
    "sg:address":"Hungerb\u00fchlstrasse 22",
    "sg:city":"Frauenfeld",
    "sg:orig_category":"Grosshandel mit sonstigen Halbwaren Herstellung von sonstigen Waren aus Papier, Karton U Pappe",
    "sg:phone":"+41 52 720 80 00",
    "sg:postcode":"8500",
    "sg:province":"Thurgau",
    "wof:name":"Mactac Ag",
    "wof:placetype":"venue"
},
  "geometry": {"coordinates":[8.8715353012,47.5634002686],"type":"Point"}
}