{
  "type": "Feature",
  "properties": {
    "iso:country":"CH",
    "sg:address":"Pr\u00e9-l\u00e9derey 26",
    "sg:city":"Collombey",
    "sg:orig_category":"Fotografisches Gewerbe U fotografische Laboratorien",
    "sg:postcode":"1868",
    "sg:province":"Valais",
    "wof:name":"Fournier Monique, Labo Couleurs",
    "wof:placetype":"venue"
},
  "geometry": {"coordinates":[6.9487400055,46.2795295715],"type":"Point"}
}