{
  "type": "Feature",
  "properties": {
    "iso:country":"CH",
    "sg:address":"Rue Des C\u00e8dres 10",
    "sg:city":"Sion",
    "sg:orig_category":"Datenverarbeitungsdienste",
    "sg:phone":"+41 27 327 30 39",
    "sg:postcode":"1950",
    "sg:province":"Valais",
    "wof:name":"Info Services Sa Informatique",
    "wof:placetype":"venue"
},
  "geometry": {"coordinates":[7.360728,46.230206],"type":"Point"}
}