{
  "type": "Feature",
  "properties": {
    "iso:country":"CH",
    "sg:address":"Avenue Du Simplon 36c",
    "sg:city":"Monthey",
    "sg:orig_category":"Herstellung von Tanks U Sammelbeh\u00e4ltern aus Metall Reinigungsgewerbe",
    "sg:phone":"+41 24 471 60 83",
    "sg:postcode":"1870",
    "sg:province":"Valais",
    "wof:name":"Natale Scimone R\u00e9vision De Citernes",
    "wof:placetype":"venue"
},
  "geometry": {"coordinates":[6.9557938576,46.2482261658],"type":"Point"}
}