{
  "type": "Feature",
  "properties": {
    "iso:country":"CH",
    "sg:address":"1964",
    "sg:city":"Conthey",
    "sg:orig_category":"G\u00fcterbef\u00f6rderung im Strassenverkehr",
    "sg:phone":"+41 27 346 17 06",
    "sg:postcode":"1964",
    "sg:province":"Valais",
    "wof:name":"Germanier Guy",
    "wof:placetype":"venue"
},
  "geometry": {"coordinates":[7.302670002,46.2224006653],"type":"Point"}
}