{
  "type": "Feature",
  "properties": {
    "iso:country":"CH",
    "sg:address":"Unterrain 16",
    "sg:city":"Teufen",
    "sg:classifiers":[
        {
            "category":"Banks & Credit Unions",
            "subcategory":"Bank",
            "type":"Services"
        }
    ],
    "sg:phone":"+41 4171334477",
    "sg:postcode":"9053",
    "sg:province":"Appenzell Ausserrhoden",
    "wof:name":"Schweiz. Mobiliar",
    "wof:placetype":"venue"
},
  "geometry": {"coordinates":[9.381928,47.391289],"type":"Point"}
}