{
  "type": "Feature",
  "properties": {
    "iso:country":"CH",
    "sg:address":"Via Canevascini 24",
    "sg:city":"Lugano",
    "sg:orig_category":"Betrieb von Taxis",
    "sg:phone":"+41 91 966 79 12",
    "sg:postcode":"6900",
    "sg:province":"Ticino",
    "wof:name":"William Ceresola Tassi",
    "wof:placetype":"venue"
},
  "geometry": {"coordinates":[8.936558,46.008526],"type":"Point"}
}