{
  "type": "Feature",
  "properties": {
    "iso:country":"CH",
    "sg:address":"3773",
    "sg:city":"Matten(st.stephan)",
    "sg:orig_category":"Landw. Genossenschaften Viehzucht",
    "sg:postcode":"3773",
    "sg:province":"Bern",
    "wof:name":"Fleckviehzuchtgenossenschaft Matten I.s.",
    "wof:placetype":"venue"
},
  "geometry": {"coordinates":[7.4226021767,46.4971046448],"type":"Point"}
}