{
  "type": "Feature",
  "properties": {
    "iso:country":"CH",
    "sg:address":"6853",
    "sg:city":"Ligornetto",
    "sg:orig_category":"Detailhandel mit elektrischen Haushalts-,Radio U Fernsehger\u00e4ten sowie Musikinstrumenten",
    "sg:phone":"+41 91 647 12 69",
    "sg:postcode":"6853",
    "sg:province":"Ticino",
    "wof:name":"Croci Torti Sandro",
    "wof:placetype":"venue"
},
  "geometry": {"coordinates":[8.9537200928,45.8623580933],"type":"Point"}
}