{
  "type": "Feature",
  "properties": {
    "iso:country":"CH",
    "sg:address":"Am Bach 1",
    "sg:city":"Tamins",
    "sg:orig_category":"RESTAURANTS: TEA-ROOMS",
    "sg:postcode":"7015",
    "sg:province":"Graubunden",
    "wof:name":"Depeder Claudio",
    "wof:placetype":"venue"
},
  "geometry": {"coordinates":[9.4069318771,46.830078125],"type":"Point"}
}