{
  "type": "Feature",
  "properties": {
    "iso:country":"CH",
    "sg:address":"M\u00f6sli",
    "sg:city":"Winistorf",
    "sg:classifiers":[
        {
            "category":"Restaurant",
            "type":"Food & Drink"
        }
    ],
    "sg:phone":"+41 26 494 11 07",
    "sg:postcode":"4558",
    "sg:province":"Solothurn",
    "wof:name":"Restaurant Zum Goldenen Kreuz",
    "wof:placetype":"venue"
},
  "geometry": {"coordinates":[7.2181448936,46.7901916504],"type":"Point"}
}