{
  "type": "Feature",
  "properties": {
    "iso:country":"CH",
    "sg:address":"Aegeristrasse 9 6417 Sattel. Postfach",
    "sg:city":"Sattel",
    "sg:orig_category":"Grosshandel mit Nahrungsmitteln, Getr\u00e4nken U Tabakwaren ohne ausgepr\u00e4gten Schwerpunkt",
    "sg:postcode":"6417",
    "sg:province":"Schwyz",
    "wof:name":"Schuler Christa Lebensmittel, Bes. Frischprodukte; Handel",
    "wof:placetype":"venue"
},
  "geometry": {"coordinates":[8.6289701462,47.0812606812],"type":"Point"}
}