{
  "type": "Feature",
  "properties": {
    "iso:country":"CH",
    "sg:address":"Riedstrasse 14",
    "sg:city":"Ennetb\u00fcrgen",
    "sg:orig_category":"Kauf U Verkauf von Immobilien auf eigene Rechnung",
    "sg:postcode":"6373",
    "sg:province":"Nidwalden",
    "wof:name":"Gut Verwaltungs Ag",
    "wof:placetype":"venue"
},
  "geometry": {"coordinates":[8.4155187607,46.9821434021],"type":"Point"}
}