{
  "type": "Feature",
  "properties": {
    "iso:country":"CH",
    "sg:address":"Schmidhusen 32",
    "sg:city":"Herisau",
    "sg:orig_category":"Grosshandel mit Getr\u00e4nken",
    "sg:postcode":"9100",
    "sg:province":"Appenzell Ausserrhoden",
    "wof:name":"Giezendanner-weine Vinecon",
    "wof:placetype":"venue"
},
  "geometry": {"coordinates":[9.2637252808,47.3803977966],"type":"Point"}
}