{
  "type": "Feature",
  "properties": {
    "iso:country":"CH",
    "sg:address":"L\u00e4rchenweg 9",
    "sg:city":"Bilten",
    "sg:orig_category":"Allgemeiner Hochbau Verlegen von Fliesen U Platten",
    "sg:phone":"+41 55 615 22 22",
    "sg:postcode":"8865",
    "sg:province":"Glarus",
    "wof:name":"Ryter Gmbh",
    "wof:placetype":"venue"
},
  "geometry": {"coordinates":[9.019236,47.148781],"type":"Point"}
}