{
  "type": "Feature",
  "properties": {
    "iso:country":"CH",
    "sg:address":"Hauptstr. 9. 9436 Balgach. Postfach",
    "sg:city":"Balgach",
    "sg:orig_category":"Zimmerei, Dachdeckerei, Bauspenglerei U Abdichtung",
    "sg:phone":"+41 71 755 26 62",
    "sg:postcode":"9436",
    "sg:province":"St. Gallen",
    "wof:name":"Dietrich Hans-j\u00f6rg",
    "wof:placetype":"venue"
},
  "geometry": {"coordinates":[9.5333528519,47.3790283203],"type":"Point"}
}