{
  "type": "Feature",
  "properties": {
    "iso:country":"CH",
    "sg:address":"Ruttigerstrasse 6",
    "sg:city":"Aarburg",
    "sg:orig_category":"Instandhaltung U Reparatur von Automobilen",
    "sg:phone":"+41 62 216 22 11",
    "sg:postcode":"4663",
    "sg:province":"Aargau",
    "wof:name":"Garage Benz U. + H. Gmbh",
    "wof:placetype":"venue"
},
  "geometry": {"coordinates":[7.9031591415,47.3305549622],"type":"Point"}
}