{
  "type": "Feature",
  "properties": {
    "iso:country":"CH",
    "sg:address":"Alte Poststrasse 16",
    "sg:city":"Seuzach",
    "sg:orig_category":"Detailhandel mit Brot, Back U S\u00fcsswaren",
    "sg:phone":"+41 52 335 22 57",
    "sg:postcode":"8472",
    "sg:province":"Z\u00fcrich",
    "wof:name":"Walter Hollenstein B\u00e4ckerei-konditorei",
    "wof:placetype":"venue"
},
  "geometry": {"coordinates":[8.729252,47.538132],"type":"Point"}
}