{
  "type": "Feature",
  "properties": {
    "iso:country":"CH",
    "sg:address":"Gfennstrasse 50",
    "sg:city":"D\u00fcbendorf",
    "sg:orig_category":"Elektroinstallation Herstellung von Elektromotoren, Generatoren U Transformatoren",
    "sg:phone":"+41 79 446 73 18",
    "sg:postcode":"8600",
    "sg:province":"Z\u00fcrich",
    "wof:name":"Langbauer Ag",
    "wof:placetype":"venue"
},
  "geometry": {"coordinates":[8.6285171509,47.3929824829],"type":"Point"}
}