{
  "type": "Feature",
  "properties": {
    "iso:country":"CH",
    "sg:address":"Grafschaftstrasse 78",
    "sg:city":"Niederglatt",
    "sg:classifiers":[
        {
            "category":"Manufacturing",
            "subcategory":"Signs",
            "type":"Manufacturing & Wholesale Goods"
        }
    ],
    "sg:phone":"+41 18506768",
    "sg:postcode":"8172",
    "sg:province":"Z\u00fcrich",
    "sg:tags":[
        "car",
        "lettering"
    ],
    "wof:name":"Rogoll Siebdruck Ag",
    "wof:placetype":"venue"
},
  "geometry": {"coordinates":[8.499472,47.495918],"type":"Point"}
}