{
  "type": "Feature",
  "properties": {
    "iso:country":"CH",
    "sg:address":"Mattenweg 4",
    "sg:city":"Niederlenz",
    "sg:orig_category":"Malerei",
    "sg:phone":"+41 62 891 88 08",
    "sg:postcode":"5702",
    "sg:province":"Aargau",
    "wof:name":"Bruno B\u00fchler Malergesch\u00e4ft",
    "wof:placetype":"venue"
},
  "geometry": {"coordinates":[8.1723251343,47.4072036743],"type":"Point"}
}