{
  "type": "Feature",
  "properties": {
    "iso:country":"CH",
    "sg:address":"Dorfstrasse 51",
    "sg:city":"Kaiseraugst",
    "sg:orig_category":"Religi\u00f6se Vereinigungen divers Vereine Gemeinn\u00fctzige",
    "sg:phone":"+41 61 811 23 64",
    "sg:postcode":"4303",
    "sg:province":"Aargau",
    "wof:name":"Christkath.frauenverein",
    "wof:placetype":"venue"
},
  "geometry": {"coordinates":[7.7255239487,47.5409088135],"type":"Point"}
}