{
  "type": "Feature",
  "properties": {
    "iso:country":"CH",
    "sg:address":"Le Prunier F Chemin Du Planet",
    "sg:city":"Gimel",
    "sg:orig_category":"Blumen U Zierpflanzenbau Gem\u00fcsebau",
    "sg:phone":"+41 21 828 41 42",
    "sg:postcode":"1188",
    "sg:province":"Vaud",
    "wof:name":"Maurice Roseng Production De Fleurs",
    "wof:placetype":"venue"
},
  "geometry": {"coordinates":[6.307616,46.50872],"type":"Point"}
}