{
  "type": "Feature",
  "properties": {
    "iso:country":"CH",
    "sg:address":"Wangenstrasse 80 3360 Herzogenbuchsee. Postfach",
    "sg:city":"Herzogenbuchsee",
    "sg:orig_category":"Herstellung von sonstigen Maschinen f\u00fcr unspezifische Verwendung",
    "sg:postcode":"3360",
    "sg:province":"Bern",
    "wof:name":"Iat Industrielle Anlagentechnik Ag",
    "wof:placetype":"venue"
},
  "geometry": {"coordinates":[7.700360775,47.1952590942],"type":"Point"}
}