{
  "type": "Feature",
  "properties": {
    "iso:country":"CH",
    "sg:address":"Felsenaustrasse 5",
    "sg:city":"Chur",
    "sg:classifiers":[
        {
            "category":"Taxi",
            "type":"Transportation"
        }
    ],
    "sg:phone":"+41 81 286 30 00",
    "sg:postcode":"7000",
    "sg:province":"Graubunden",
    "sg:tags":[
        "furniture"
    ],
    "wof:name":"Gebr\u00fcder Kuoni Chur Ag",
    "wof:placetype":"venue"
},
  "geometry": {"coordinates":[9.5166482925,46.8541030884],"type":"Point"}
}