{
  "type": "Feature",
  "properties": {
    "iso:country":"CH",
    "sg:address":"M\u00e4ttelistrasse 5",
    "sg:city":"Meggen",
    "sg:orig_category":"Detailhandel mit Metallwaren, Anstrichmitteln, Glaswaren, Bau U Heimwerkerbedarf",
    "sg:phone":"+41 41 377 04 77",
    "sg:postcode":"6045",
    "sg:province":"Luzern",
    "wof:name":"Zai Peter",
    "wof:placetype":"venue"
},
  "geometry": {"coordinates":[8.3822841644,47.0502853394],"type":"Point"}
}