{
  "type": "Feature",
  "properties": {
    "iso:country":"CH",
    "sg:address":"Grafenauweg 8 6300 Zug. Postfach 4763",
    "sg:city":"Zug",
    "sg:orig_category":"Vermittlung von Immobilien Verwaltung von Immobilien",
    "sg:phone":"+41 71 224 81 11",
    "sg:postcode":"6304",
    "sg:province":"Zug",
    "wof:name":"Pricewaterhousecoopers Ag",
    "wof:placetype":"venue"
},
  "geometry": {"coordinates":[9.3759222031,47.425743103],"type":"Point"}
}