{
  "type": "Feature",
  "properties": {
    "iso:country":"CH",
    "sg:address":"Wilhofweg 3 6275 Ballwil. Postfach 112",
    "sg:city":"Ballwil",
    "sg:orig_category":"Herstellung von Metallkonstruktionen Stahl U Leichtmetallbau",
    "sg:phone":"+41 41 448 29 55",
    "sg:postcode":"6275",
    "sg:province":"Luzern",
    "wof:name":"Melva Plan Ag",
    "wof:placetype":"venue"
},
  "geometry": {"coordinates":[8.3168992996,47.1541213989],"type":"Point"}
}