{
  "type": "Feature",
  "properties": {
    "iso:country":"CH",
    "sg:address":"Frankfurt-strasse 90",
    "sg:city":"Basel",
    "sg:classifiers":[
        {
            "category":"Home & Garden",
            "subcategory":"Carpets & Floor Coverings",
            "type":"Retail Goods"
        }
    ],
    "sg:phone":"+41 61 416 37 00",
    "sg:postcode":"4053",
    "sg:province":"Basel-Stadt",
    "sg:tags":[
        "mattress"
    ],
    "wof:name":"Robusta Ag",
    "wof:placetype":"venue"
},
  "geometry": {"coordinates":[7.607216835,47.5344085693],"type":"Point"}
}