{
  "type": "Feature",
  "properties": {
    "iso:country":"CH",
    "sg:address":"Avenue Dumas 23",
    "sg:city":"Gen\u00e8ve",
    "sg:orig_category":"Vorschulen, Kinderg\u00e4rten",
    "sg:postcode":"1206",
    "sg:province":"Gen\u00e8ve",
    "wof:name":"Jardin D'enfants Nursery Le Manoir,mme Renate Muller",
    "wof:placetype":"venue"
},
  "geometry": {"coordinates":[6.1570091248,46.1906967163],"type":"Point"}
}