{
  "type": "Feature",
  "properties": {
    "iso:country":"CH",
    "sg:address":"Gossauerstrasse 61",
    "sg:city":"Herisau",
    "sg:orig_category":"Zahnarztpraxen",
    "sg:phone":"+41 71 351 29 70",
    "sg:postcode":"9100",
    "sg:province":"Appenzell Ausserrhoden",
    "wof:name":"Dr. Med. Dent. Albert Staub Zahnarzt",
    "wof:placetype":"venue"
},
  "geometry": {"coordinates":[9.27460289,47.3882980347],"type":"Point"}
}