{
  "type": "Feature",
  "properties": {
    "iso:country":"CH",
    "sg:address":"Via Case Albertini 2",
    "sg:city":"Losone",
    "sg:orig_category":"Fachdetailhandel in Verkaufsr\u00e4umen",
    "sg:phone":"+41 91 791 81 39",
    "sg:postcode":"6616",
    "sg:province":"Ticino",
    "wof:name":"Kalas Bea Sport",
    "wof:placetype":"venue"
},
  "geometry": {"coordinates":[8.7584648132,46.168762207],"type":"Point"}
}