{
  "type": "Feature",
  "properties": {
    "iso:country":"CH",
    "sg:address":"Ringstr. 11",
    "sg:city":"Neuenhof",
    "sg:classifiers":[
        {
            "category":"Manufacturing",
            "subcategory":"Metals",
            "type":"Manufacturing & Wholesale Goods"
        }
    ],
    "sg:phone":"+41 56 406 13 55",
    "sg:postcode":"5432",
    "sg:province":"Aargau",
    "sg:tags":[
        "metallurgy",
        "metalworking",
        "processing"
    ],
    "wof:name":"Meba Ledergerber & Duffner Ag",
    "wof:placetype":"venue"
},
  "geometry": {"coordinates":[8.3291692734,47.4538002014],"type":"Point"}
}