{
  "type": "Feature",
  "properties": {
    "iso:country":"CH",
    "sg:address":"Akazienstrasse 4",
    "sg:city":"Herisau",
    "sg:orig_category":"Autoreiseunternehmen",
    "sg:phone":"+41 71 351 14 22",
    "sg:postcode":"9100",
    "sg:province":"Appenzell Ausserrhoden",
    "wof:name":"Ren\u00e9 Signer Kleinbusbetrieb",
    "wof:placetype":"venue"
},
  "geometry": {"coordinates":[9.282287,47.38905],"type":"Point"}
}