{
  "type": "Feature",
  "properties": {
    "iso:country":"CH",
    "sg:address":"Franklinstrasse 31a",
    "sg:city":"Rorschach",
    "sg:orig_category":"Weiterbildungskurse and Seminar Anbieter",
    "sg:phone":"+41 71 244 25 58",
    "sg:postcode":"9400",
    "sg:province":"St. Gallen",
    "wof:name":"Stiftung Eag",
    "wof:placetype":"venue"
},
  "geometry": {"coordinates":[9.489112854,47.4723815918],"type":"Point"}
}