{
  "type": "Feature",
  "properties": {
    "iso:country":"CH",
    "sg:address":"Boniswilerstrasse 2",
    "sg:city":"Leutwil",
    "sg:orig_category":"Handel mit Motorr\u00e4dern, Teilen U Zubeh\u00f6r Instandhaltung U Reparatur von Motorr\u00e4dern Mechanische Werk",
    "sg:phone":"+41 62 777 17 29",
    "sg:postcode":"5725",
    "sg:province":"Aargau",
    "wof:name":"Max Aeschbach",
    "wof:placetype":"venue"
},
  "geometry": {"coordinates":[8.1751403809,47.3115730286],"type":"Point"}
}