{
  "type": "Feature",
  "properties": {
    "iso:country":"CH",
    "sg:address":"Hirschenweg 99 4312 Magden. Postfach",
    "sg:city":"Magden",
    "sg:orig_category":"Wohnheime",
    "sg:postcode":"4312",
    "sg:province":"Aargau",
    "wof:name":"Stiftung Alterswohnheim Hirschen Magden",
    "wof:placetype":"venue"
},
  "geometry": {"coordinates":[7.8152499199,47.527141571],"type":"Point"}
}