{
  "type": "Feature",
  "properties": {
    "iso:country":"CH",
    "sg:address":"Rue De L'envol 19",
    "sg:city":"Sion",
    "sg:classifiers":[
        {
            "category":"Restaurant",
            "type":"Food & Drink"
        }
    ],
    "sg:phone":"+41 27 322 29 97",
    "sg:postcode":"1950",
    "sg:province":"Valais",
    "wof:name":"Caf\u00e9 Terrasse",
    "wof:placetype":"venue"
},
  "geometry": {"coordinates":[7.2931518555,46.2272949219],"type":"Point"}
}