{
  "type": "Feature",
  "properties": {
    "addr:full":"Asylstrasse 130 Z\u00fcrich Z\u00fcrich 8032",
    "addr:housenumber":"130",
    "addr:postcode":"8032",
    "addr:street":"Asylstrasse",
    "iso:country":"CH",
    "sg:address":"Asylstrasse 130",
    "sg:city":"Z\u00fcrich",
    "sg:classifiers":[
        {
            "category":"Social Services",
            "subcategory":"Retirement Home",
            "type":"Services"
        }
    ],
    "sg:phone":"+41 13882222",
    "sg:postcode":"8032",
    "sg:province":"Z\u00fcrich",
    "sg:tags":[
        "pflegeheime",
        "u",
        "alters"
    ],
    "wof:name":"St\u00e4dt.altersheim Klusplatz",
    "wof:placetype":"venue"
},
  "geometry": {"coordinates":[8.56462,47.365028],"type":"Point"}
}