{
  "type": "Feature",
  "properties": {
    "iso:country":"CH",
    "sg:address":"Bifangstrasse 10",
    "sg:city":"Rombach",
    "sg:orig_category":"Grosshandel mit Textilien",
    "sg:phone":"+41 62 827 18 18",
    "sg:postcode":"5022",
    "sg:province":"Aargau",
    "wof:name":"Emak Gmbh Modeagentur",
    "wof:placetype":"venue"
},
  "geometry": {"coordinates":[8.0430736542,47.4019927979],"type":"Point"}
}