{
  "type": "Feature",
  "properties": {
    "iso:country":"CH",
    "sg:address":"Chemin Du Pr\u00e9-rond 1",
    "sg:city":"Bevaix",
    "sg:classifiers":[
        {
            "category":"Professional",
            "subcategory":"Employment Agencies",
            "type":"Services"
        }
    ],
    "sg:phone":"+41 32 846 15 78",
    "sg:postcode":"2022",
    "sg:province":"Neuch\u00e2tel",
    "sg:tags":[
        "personal",
        "u",
        "stellenvermittlung"
    ],
    "wof:name":"Ren\u00e9 Descombes Placement De Personnes",
    "wof:placetype":"venue"
},
  "geometry": {"coordinates":[6.8142399788,46.9352340698],"type":"Point"}
}