{
  "type": "Feature",
  "properties": {
    "iso:country":"CH",
    "sg:address":"Webergutstrasse 12",
    "sg:city":"Zollikofen",
    "sg:orig_category":"Allgemeiner Hoch U Tiefbau",
    "sg:phone":"+41 31 911 50 50",
    "sg:postcode":"3052",
    "sg:province":"Bern",
    "wof:name":"Hofstetter & Bezzola Ag",
    "wof:placetype":"venue"
},
  "geometry": {"coordinates":[7.440394,47.00246],"type":"Point"}
}