{
  "type": "Feature",
  "properties": {
    "iso:country":"CH",
    "sg:address":"Busenhardstrasse 5 8704 Herrliberg. Postfach 369",
    "sg:city":"Herrliberg",
    "sg:orig_category":"Non-Classified Establishments",
    "sg:phone":"+41 19150381",
    "sg:postcode":"8704",
    "sg:province":"Z\u00fcrich",
    "wof:name":"Mwr, Andreas Mayer",
    "wof:placetype":"venue"
},
  "geometry": {"coordinates":[8.6104536057,47.2915534973],"type":"Point"}
}