{
  "type": "Feature",
  "properties": {
    "iso:country":"CH",
    "sg:address":"Rue Du Petit-ch\u00eane 18 1003 Lausanne Case Postale 3409",
    "sg:city":"Lausanne",
    "sg:orig_category":"Advokaturb\u00fcros",
    "sg:phone":"+41 21 323 06 31",
    "sg:postcode":"1002",
    "sg:province":"Vaud",
    "wof:name":"Narbel Del Boca & Burnet Etude D'avocat",
    "wof:placetype":"venue"
},
  "geometry": {"coordinates":[6.630285,46.51899],"type":"Point"}
}