{
  "type": "Feature",
  "properties": {
    "iso:country":"CH",
    "sg:address":"Kalchb\u00fchlstrasse 44",
    "sg:city":"Z\u00fcrich",
    "sg:orig_category":"Instandhaltung U Reparatur von Automobilen",
    "sg:phone":"+41 14823535",
    "sg:postcode":"8038",
    "sg:province":"Z\u00fcrich",
    "wof:name":"Kalchb\u00fchl-garage Ag Z\u00fcrich Autoreparatur-werkst\u00e4tte. Einstellgarage. Automobile; Handel",
    "wof:placetype":"venue"
},
  "geometry": {"coordinates":[8.531539917,47.3394584656],"type":"Point"}
}