{
  "type": "Feature",
  "properties": {
    "iso:country":"CH",
    "sg:address":"Conradin Zschokkerstrasse 10",
    "sg:city":"D\u00f6ttingen",
    "sg:orig_category":"Maschinen-Fabrikation",
    "sg:postcode":"5312",
    "sg:province":"Aargau",
    "wof:name":"Mia Montagen + Service In Und Ausland G. Berchtold",
    "wof:placetype":"venue"
},
  "geometry": {"coordinates":[8.2568798065,47.5695724487],"type":"Point"}
}