{
  "type": "Feature",
  "properties": {
    "iso:country":"CH",
    "sg:address":"Dorfplatz 3 3110 M\u00fcnsingen. Postfach 1325",
    "sg:city":"M\u00fcnsingen",
    "sg:orig_category":"Architekturb\u00fcros",
    "sg:phone":"+41 31 721 42 89",
    "sg:postcode":"3110",
    "sg:province":"Bern",
    "wof:name":"Thomas Rieder Architekturb\u00fcro",
    "wof:placetype":"venue"
},
  "geometry": {"coordinates":[7.56277,46.874821],"type":"Point"}
}