{
  "type": "Feature",
  "properties": {
    "iso:country":"CH",
    "sg:address":"Sonville 11",
    "sg:city":"Orvin",
    "sg:orig_category":"Grosshandel mit B\u00fcromaschinen Grosshandel mit Datenverarbeitungsger\u00e4ten",
    "sg:phone":"+41 32 358 11 59",
    "sg:postcode":"2534",
    "sg:province":"Bern",
    "wof:name":"Lem L\u00e9chot Electronique & Micro-informat.",
    "wof:placetype":"venue"
},
  "geometry": {"coordinates":[7.2125368118,47.1602745056],"type":"Point"}
}