{
  "type": "Feature",
  "properties": {
    "iso:country":"CH",
    "sg:address":"Holzh\u00e4usernstrasse 1",
    "sg:city":"Risch",
    "sg:orig_category":"Unternehmensberatung Wirtschaftspr\u00fcfung, Steuerberatung U Treuhand",
    "sg:phone":"+41 21 636 20 55",
    "sg:postcode":"6343",
    "sg:province":"Zug",
    "wof:name":"Demson Sa",
    "wof:placetype":"venue"
},
  "geometry": {"coordinates":[6.5815048218,46.5326690674],"type":"Point"}
}