{
  "type": "Feature",
  "properties": {
    "iso:country":"CH",
    "sg:address":"Via Del Tiglio 19a",
    "sg:city":"Locarno",
    "sg:orig_category":"Wirtschaftspr\u00fcfung, Steuerberatung U Treuhand",
    "sg:postcode":"6605",
    "sg:province":"Ticino",
    "wof:name":"Fiduciaria Trinit\u00e0 Sa",
    "wof:placetype":"venue"
},
  "geometry": {"coordinates":[8.7852516174,46.1734580994],"type":"Point"}
}