{
  "type": "Feature",
  "properties": {
    "iso:country":"CH",
    "sg:address":"Gl\u00e4rnischstrasse 2",
    "sg:city":"Richterswil",
    "sg:orig_category":"Arztpraxen",
    "sg:phone":"+41 17848155",
    "sg:postcode":"8805",
    "sg:province":"Z\u00fcrich",
    "wof:name":"Dr.med.sabine Batzer Aerztin F\u00fcr Allg.medizin Fmh",
    "wof:placetype":"venue"
},
  "geometry": {"coordinates":[8.69765,47.20974],"type":"Point"}
}