{
  "type": "Feature",
  "properties": {
    "iso:country":"CH",
    "sg:address":"Bachstrasse 10 8200 Schaffhausen. Postfach",
    "sg:city":"Schaffhausen",
    "sg:orig_category":"Unclassifiable Establishments",
    "sg:postcode":"8202",
    "sg:province":"Schaffhausen",
    "wof:name":"Filmunion Danieli",
    "wof:placetype":"venue"
},
  "geometry": {"coordinates":[8.638428688,47.6960754395],"type":"Point"}
}