{
  "type": "Feature",
  "properties": {
    "iso:country":"CH",
    "sg:address":"Klosterstrasse 12",
    "sg:city":"Luzern",
    "sg:orig_category":"Schreib U \u00dcbersetzungsb\u00fcros",
    "sg:phone":"+41 26 411 35 31",
    "sg:postcode":"6003",
    "sg:province":"Luzern",
    "wof:name":"Sciboz Anne-marie",
    "wof:placetype":"venue"
},
  "geometry": {"coordinates":[7.0834698677,46.7041091919],"type":"Point"}
}