{
  "type": "Feature",
  "properties": {
    "iso:country":"CH",
    "sg:address":"Via Al Vallone 1",
    "sg:city":"Sementina",
    "sg:orig_category":"Allgemeiner Hochbau Strassenbau",
    "sg:phone":"+41 91 857 68 76",
    "sg:postcode":"6514",
    "sg:province":"Ticino",
    "wof:name":"Gms Sa",
    "wof:placetype":"venue"
},
  "geometry": {"coordinates":[8.993762,46.18483],"type":"Point"}
}