{
  "type": "Feature",
  "properties": {
    "iso:country":"CH",
    "sg:address":"Zeughausstrasse 67",
    "sg:city":"Z\u00fcrich",
    "sg:orig_category":"S\u00e4ge, Hobel U Holzimpr\u00e4gnierwerke",
    "sg:postcode":"8004",
    "sg:province":"Z\u00fcrich",
    "wof:name":"Eckert Holzjobs",
    "wof:placetype":"venue"
},
  "geometry": {"coordinates":[8.5288581848,47.3765640259],"type":"Point"}
}