{
  "type": "Feature",
  "properties": {
    "iso:country":"CH",
    "sg:address":"Steinh\u00fcgelstrasse 40",
    "sg:city":"Berikon",
    "sg:orig_category":"Unternehmensberatung",
    "sg:phone":"+41 56 633 35 76",
    "sg:postcode":"8965",
    "sg:province":"Aargau",
    "wof:name":"Alliera.com Gmbh",
    "wof:placetype":"venue"
},
  "geometry": {"coordinates":[8.3640565872,47.3631134033],"type":"Point"}
}