{
  "type": "Feature",
  "properties": {
    "iso:country":"CH",
    "sg:address":"Br\u00fcderhofweg 29 8000 Z\u00fcrich. Postfach",
    "sg:city":"Z\u00fcrich",
    "sg:orig_category":"Interessenvertretungen",
    "sg:postcode":"8057",
    "sg:province":"Z\u00fcrich",
    "wof:name":"Schweizerischer Verband Der Beratungsstellen F\u00fcr Partnersuchende",
    "wof:placetype":"venue"
},
  "geometry": {"coordinates":[8.5387954712,47.4001541138],"type":"Point"}
}