{
  "type": "Feature",
  "properties": {
    "iso:country":"CH",
    "sg:address":"Hausmattstrasse 14",
    "sg:city":"Arni-islisberg",
    "sg:orig_category":"Elektroinstallation",
    "sg:phone":"+41 56 649 90 90",
    "sg:postcode":"8905",
    "sg:province":"Aargau",
    "wof:name":"Elektro Stutz M.",
    "wof:placetype":"venue"
},
  "geometry": {"coordinates":[8.4385900497,47.3217391968],"type":"Point"}
}