{
  "type": "Feature",
  "properties": {
    "iso:country":"CH",
    "sg:address":"Limmatquai 80",
    "sg:city":"Z\u00fcrich",
    "sg:orig_category":"Arztpraxen",
    "sg:phone":"+41 12521180",
    "sg:postcode":"8001",
    "sg:province":"Z\u00fcrich",
    "wof:name":"Dr.med.thomas Jundt Spezialarzt Fmh",
    "wof:placetype":"venue"
},
  "geometry": {"coordinates":[8.542886,47.373341],"type":"Point"}
}