{
  "type": "Feature",
  "properties": {
    "iso:country":"CH",
    "sg:address":"Rietstrasse 28",
    "sg:city":"Zollikon",
    "sg:orig_category":"Sonstiger Grosshandel",
    "sg:phone":"+41 13920341",
    "sg:postcode":"8702",
    "sg:province":"Z\u00fcrich",
    "wof:name":"Hallauer S. B. & Co",
    "wof:placetype":"venue"
},
  "geometry": {"coordinates":[8.5756969452,47.3444976807],"type":"Point"}
}