{
  "type": "Feature",
  "properties": {
    "iso:country":"CH",
    "sg:address":"Wittenwilerstrasse 25 8355 Aadorf. Postfach",
    "sg:city":"Aadorf",
    "sg:orig_category":"Vermietung U Verpachtung von eigenen Immobilien",
    "sg:postcode":"8355",
    "sg:province":"Thurgau",
    "wof:name":"Dutly Immobilien Ag",
    "wof:placetype":"venue"
},
  "geometry": {"coordinates":[8.9024896622,47.4961395264],"type":"Point"}
}