{
  "type": "Feature",
  "properties": {
    "iso:country":"CH",
    "sg:address":"Cantonale Via",
    "sg:city":"Vernate",
    "sg:orig_category":"Interessenvertretungen",
    "sg:postcode":"6992",
    "sg:province":"Ticino",
    "wof:name":"Etable En Consortage De Mission",
    "wof:placetype":"venue"
},
  "geometry": {"coordinates":[7.5885829926,46.1904907227],"type":"Point"}
}