{
  "type": "Feature",
  "properties": {
    "iso:country":"CH",
    "sg:address":"Mettmenhaslistrasse 254",
    "sg:city":"Niederhasli",
    "sg:classifiers":[
        {
            "category":"Restaurant",
            "type":"Food & Drink"
        }
    ],
    "sg:phone":"+41 18501163",
    "sg:postcode":"8155",
    "sg:province":"Z\u00fcrich",
    "wof:name":"Restaurant Neuhaus",
    "wof:placetype":"venue"
},
  "geometry": {"coordinates":[8.50344944,47.4758300781],"type":"Point"}
}