{
  "type": "Feature",
  "properties": {
    "iso:country":"CH",
    "sg:address":"Rue Des Bouchers 6",
    "sg:city":"Fribourg",
    "sg:orig_category":"Detailhandel mit Getr\u00e4nken",
    "sg:phone":"+41 26 323 18 18",
    "sg:postcode":"1700",
    "sg:province":"Fribourg",
    "wof:name":"Jean-claude Potier Le J\u00e9roboam Vins & Spiritueux",
    "wof:placetype":"venue"
},
  "geometry": {"coordinates":[7.1646528244,46.8056945801],"type":"Point"}
}