{
  "type": "Feature",
  "properties": {
    "iso:country":"CH",
    "sg:address":"Rue Du Simplon 40",
    "sg:city":"Martigny",
    "sg:orig_category":"Ladies' Shoes",
    "sg:phone":"+41 27 722 16 72",
    "sg:postcode":"1920",
    "sg:province":"Valais",
    "wof:name":"Alpina S.a.",
    "wof:placetype":"venue"
},
  "geometry": {"coordinates":[7.0810718536,46.1041107178],"type":"Point"}
}