{
  "type": "Feature",
  "properties": {
    "iso:country":"CH",
    "sg:address":"Stampfenbachplatz 4",
    "sg:city":"Z\u00fcrich",
    "sg:orig_category":"Grosshandel mit chemischen Erzeugnissen",
    "sg:phone":"+41 79 471 69 94",
    "sg:postcode":"8006",
    "sg:province":"Z\u00fcrich",
    "wof:name":"Jacques Kupfer Produits D'entretien",
    "wof:placetype":"venue"
},
  "geometry": {"coordinates":[6.1088137627,46.1930503845],"type":"Point"}
}