{
  "type": "Feature",
  "properties": {
    "iso:country":"CH",
    "sg:address":"Weberstrasse 8",
    "sg:city":"Thalwil",
    "sg:orig_category":"Handelsvermittlung U Grosshandel Sonstiger Grosshandel",
    "sg:phone":"+41 17221828",
    "sg:postcode":"8800",
    "sg:province":"Z\u00fcrich",
    "wof:name":"Focus Fitness, Styffe J.",
    "wof:placetype":"venue"
},
  "geometry": {"coordinates":[8.561548233,47.3002433777],"type":"Point"}
}