{
  "type": "Feature",
  "properties": {
    "iso:country":"CH",
    "sg:address":"Wallstrasse 27",
    "sg:city":"Solothurn",
    "sg:orig_category":"Grosshandel mit lebenden Tieren",
    "sg:phone":"+41 32 622 90 93",
    "sg:postcode":"4500",
    "sg:province":"Solothurn",
    "wof:name":"B\u00fcttler Roland, Pferdehandlung",
    "wof:placetype":"venue"
},
  "geometry": {"coordinates":[7.5348768234,47.2025146484],"type":"Point"}
}