{
  "type": "Feature",
  "properties": {
    "iso:country":"CH",
    "sg:address":"Sch\u00fctzeng\u00fctlistrasse 2",
    "sg:city":"Bischofszell",
    "sg:orig_category":"Non-Classified Establishments",
    "sg:phone":"+41 71 424 22 66",
    "sg:postcode":"9220",
    "sg:province":"Thurgau",
    "wof:name":"Molkerei Biedermann Ag",
    "wof:placetype":"venue"
},
  "geometry": {"coordinates":[9.2408246994,47.4942245483],"type":"Point"}
}