{
  "type": "Feature",
  "properties": {
    "iso:country":"CH",
    "sg:address":"Coin D'en Bas 3 1092 Belmont-lausanne. Postfach",
    "sg:city":"Belmont-lausanne",
    "sg:orig_category":"Non-Classified Establishments",
    "sg:postcode":"1092",
    "sg:province":"Vaud",
    "wof:name":"M\u00e9traux Transports Sa Succursale De Belmont-sur-lausanne Entreprise De Transports",
    "wof:placetype":"venue"
},
  "geometry": {"coordinates":[6.6363019943,46.552772522],"type":"Point"}
}