{
  "type": "Feature",
  "properties": {
    "iso:country":"CH",
    "sg:address":"Feldeggstrasse 65",
    "sg:city":"Z\u00fcrich",
    "sg:orig_category":"Arztpraxen",
    "sg:phone":"+41 13820117",
    "sg:postcode":"8008",
    "sg:province":"Z\u00fcrich",
    "wof:name":"Dr.med.peter Baumann Spezialarzt Fmh",
    "wof:placetype":"venue"
},
  "geometry": {"coordinates":[8.553748,47.361126],"type":"Point"}
}