{
  "type": "Feature",
  "properties": {
    "iso:country":"CH",
    "sg:address":"Rigistrasse 171b 6340 Baar. Postfach 1040",
    "sg:city":"Baar",
    "sg:orig_category":"Handelsvermittlung U Grosshandel",
    "sg:phone":"+41 41 760 14 04",
    "sg:postcode":"6341",
    "sg:province":"Zug",
    "wof:name":"Hf Mebag Handels-& Finanz Ag",
    "wof:placetype":"venue"
},
  "geometry": {"coordinates":[8.5305099487,47.1919517517],"type":"Point"}
}