{
  "type": "Feature",
  "properties": {
    "addr:full":"Vergers Rue Des 1 Yvonand Vaud 1462",
    "addr:postcode":"1462",
    "addr:street":"Rue Des 1",
    "iso:country":"CH",
    "sg:address":"Vergers Rue Des 1",
    "sg:city":"Yvonand",
    "sg:orig_category":"Herstellung von Karosserien U Anh\u00e4ngern",
    "sg:phone":"+41 24 430 26 26",
    "sg:postcode":"1462",
    "sg:province":"Vaud",
    "wof:name":"Locatentes S\u00e0rl",
    "wof:placetype":"venue"
},
  "geometry": {"coordinates":[6.744295,46.798267],"type":"Point"}
}