{
  "type": "Feature",
  "properties": {
    "iso:country":"CH",
    "sg:address":"Kalchb\u00fchlstrasse 18",
    "sg:city":"Chur",
    "sg:orig_category":"HERSTELLUNG VON GER\u00c4TEN DER ELEKTRIZIT\u00c4TSERZEUGUNG, -VERTEILUNG U.\u00c4 Herstellung von Elektrizit\u00e4tsver",
    "sg:phone":"+41 81 252 60 06",
    "sg:postcode":"7000",
    "sg:province":"Graubunden",
    "wof:name":"N\u00e4geli P.",
    "wof:placetype":"venue"
},
  "geometry": {"coordinates":[9.5095748901,46.8463973999],"type":"Point"}
}