{
  "type": "Feature",
  "properties": {
    "iso:country":"CH",
    "sg:address":"Wangenstrasse 32",
    "sg:city":"Herzogenbuchsee",
    "sg:orig_category":"Reparatur von Schuhen U Lederwaren",
    "sg:phone":"+41 62 961 53 04",
    "sg:postcode":"3360",
    "sg:province":"Bern",
    "wof:name":"Christian Meyer Schuhmacherei",
    "wof:placetype":"venue"
},
  "geometry": {"coordinates":[7.7048220634,47.1899871826],"type":"Point"}
}