{
  "type": "Feature",
  "properties": {
    "iso:country":"CH",
    "sg:address":"Hintergasse 7",
    "sg:city":"Schaffhausen",
    "sg:orig_category":"Arztpraxen",
    "sg:phone":"+41 52 624 26 94",
    "sg:postcode":"8203",
    "sg:province":"Schaffhausen",
    "wof:name":"Dr.med.peter Theiler Arzt F.allgemeine Medizin Fmh",
    "wof:placetype":"venue"
},
  "geometry": {"coordinates":[8.656255,47.697365],"type":"Point"}
}