{
  "type": "Feature",
  "properties": {
    "addr:full":"Neue Bahnhofstrasse 8 M\u00fcnsingen Bern 3110",
    "addr:housenumber":"8",
    "addr:postcode":"3110",
    "addr:street":"Neue Bahnhofstrasse",
    "iso:country":"CH",
    "sg:address":"Neue Bahnhofstrasse 8",
    "sg:city":"M\u00fcnsingen",
    "sg:orig_category":"Arztpraxen",
    "sg:phone":"+41 31 721 97 77",
    "sg:postcode":"3110",
    "sg:province":"Bern",
    "wof:name":"Dr.med.andrea C. Gantenbein Spezial\u00e4rztin Fmh",
    "wof:placetype":"venue"
},
  "geometry": {"coordinates":[7.561311,46.874454],"type":"Point"}
}