{
  "type": "Feature",
  "properties": {
    "iso:country":"CH",
    "sg:address":"Erlistrasse 3",
    "sg:city":"Sattel",
    "sg:orig_category":"Instandhaltung U Reparatur von Automobilen",
    "sg:phone":"+41 41 835 14 14",
    "sg:postcode":"6417",
    "sg:province":"Schwyz",
    "wof:name":"Walter Hotz Howa Autospritzwerk",
    "wof:placetype":"venue"
},
  "geometry": {"coordinates":[8.6275444031,47.0740394592],"type":"Point"}
}