{
  "type": "Feature",
  "properties": {
    "addr:full":"Wehntalerstrasse 11 Sch\u00f6fflisdorf Z\u00fcrich 8165",
    "addr:housenumber":"11",
    "addr:postcode":"8165",
    "addr:street":"Wehntalerstrasse;Zuerich",
    "iso:country":"CH",
    "sg:address":"Wehntalerstrasse 11",
    "sg:city":"Sch\u00f6fflisdorf",
    "sg:classifiers":[
        {
            "category":"Banks & Credit Unions",
            "subcategory":"Bank",
            "type":"Services"
        }
    ],
    "sg:phone":"+41 18561866",
    "sg:postcode":"8165",
    "sg:province":"Z\u00fcrich",
    "wof:name":"Schweiz. Mobiliar",
    "wof:placetype":"venue"
},
  "geometry": {"coordinates":[8.417586,47.499588],"type":"Point"}
}