{
  "type": "Feature",
  "properties": {
    "addr:full":"Forchstrasse 135 Z\u00fcrich Z\u00fcrich 8032",
    "addr:housenumber":"135",
    "addr:postcode":"8032",
    "addr:street":"Forchstrasse",
    "iso:country":"CH",
    "sg:address":"Forchstrasse 135",
    "sg:city":"Z\u00fcrich",
    "sg:classifiers":[
        {
            "category":"Professional",
            "subcategory":"Advertising",
            "type":"Services"
        }
    ],
    "sg:phone":"+41 13818888",
    "sg:postcode":"8032",
    "sg:province":"Z\u00fcrich",
    "sg:tags":[
        "poster"
    ],
    "wof:name":"Herbst Druck Ag",
    "wof:placetype":"venue"
},
  "geometry": {"coordinates":[8.562914,47.360725],"type":"Point"}
}