{
  "type": "Feature",
  "properties": {
    "iso:country":"CH",
    "sg:address":"Bergstrasse 2",
    "sg:city":"Freidorf",
    "sg:classifiers":[
        {
            "category":"Shopping Center",
            "type":"Public Place"
        }
    ],
    "sg:phone":"+41 71 455 17 40",
    "sg:postcode":"9306",
    "sg:province":"Thurgau",
    "sg:tags":[
        "aluminium",
        "casting"
    ],
    "wof:name":"Kurt Huhn Ag",
    "wof:placetype":"venue"
},
  "geometry": {"coordinates":[9.398849,47.482948],"type":"Point"}
}