{
  "type": "Feature",
  "properties": {
    "iso:country":"CH",
    "sg:address":"7075",
    "sg:city":"Churwalden",
    "sg:classifiers":[
        {
            "category":"Travel",
            "subcategory":"Hotels & Motels",
            "type":"Entertainment"
        }
    ],
    "sg:postcode":"7075",
    "sg:province":"Graubunden",
    "sg:tags":[
        "hotels",
        "mit",
        "restaurant"
    ],
    "wof:name":"Livers-janssen L.",
    "wof:placetype":"venue"
},
  "geometry": {"coordinates":[9.543800354,46.7785453796],"type":"Point"}
}