{
  "type": "Feature",
  "properties": {
    "iso:country":"CH",
    "sg:address":"Scheibenstrasse 19a",
    "sg:city":"Bern",
    "sg:orig_category":"Kinderg\u00e4rten, Vor U Grundschulen Kinderkrippen U horte",
    "sg:phone":"+41 31 331 43 04",
    "sg:postcode":"3014",
    "sg:province":"Bern",
    "wof:name":"Verein Kindertagesbetreuung Viki",
    "wof:placetype":"venue"
},
  "geometry": {"coordinates":[7.453772068,46.960521698],"type":"Point"}
}