{
  "type": "Feature",
  "properties": {
    "iso:country":"CH",
    "sg:address":"Jeu-de-l'arc Rue Du 9 1207 Gen\u00e8ve. Postfach",
    "sg:city":"Gen\u00e8ve",
    "sg:orig_category":"Sonstiger Grosshandel",
    "sg:postcode":"1201",
    "sg:province":"Gen\u00e8ve",
    "wof:name":"Fafi Football Agency & Financial Services Sa",
    "wof:placetype":"venue"
},
  "geometry": {"coordinates":[6.2349047661,46.4098243713],"type":"Point"}
}