{
  "type": "Feature",
  "properties": {
    "iso:country":"CH",
    "sg:address":"Midi Place Du 40",
    "sg:city":"Sion",
    "sg:orig_category":"Unclassifiable Establishments",
    "sg:postcode":"1950",
    "sg:province":"Valais",
    "wof:name":"Seedy Sa",
    "wof:placetype":"venue"
},
  "geometry": {"coordinates":[7.3588571548,46.2280921936],"type":"Point"}
}