{
  "type": "Feature",
  "properties": {
    "iso:country":"CH",
    "sg:address":"Kirchstr. 10",
    "sg:city":"Horn",
    "sg:classifiers":[
        {
            "category":"Manufacturing",
            "subcategory":"Textiles",
            "type":"Manufacturing & Wholesale Goods"
        }
    ],
    "sg:phone":"+41 71 243 30 60",
    "sg:postcode":"9326",
    "sg:province":"Thurgau",
    "sg:tags":[
        "linen",
        "clothing",
        "fabric"
    ],
    "wof:name":"Engelbert E Stieger Ag",
    "wof:placetype":"venue"
},
  "geometry": {"coordinates":[9.3760499954,47.4264793396],"type":"Point"}
}