{
  "type": "Feature",
  "properties": {
    "iso:country":"CH",
    "sg:address":"R\u00fcefaweg",
    "sg:city":"Klosters",
    "sg:classifiers":[
        {
            "category":"Travel",
            "subcategory":"Hotels & Motels",
            "type":"Entertainment"
        }
    ],
    "sg:phone":"+41 81 422 26 68",
    "sg:postcode":"7250",
    "sg:province":"Graubunden",
    "sg:tags":[
        "hotels",
        "mit",
        "restaurant"
    ],
    "wof:name":"Jost Thomas",
    "wof:placetype":"venue"
},
  "geometry": {"coordinates":[9.8787622452,46.8801193237],"type":"Point"}
}