{
  "type": "Feature",
  "properties": {
    "iso:country":"CH",
    "sg:address":"Zugerstrasse 46",
    "sg:city":"Unter\u00e4geri",
    "sg:orig_category":"Detailhandel mit Metallwaren, Anstrichmitteln, Glaswaren, Bau U Heimwerkerbedarf",
    "sg:phone":"+41 17151973",
    "sg:postcode":"6314",
    "sg:province":"Zug",
    "wof:name":"Plattner Trading",
    "wof:placetype":"venue"
},
  "geometry": {"coordinates":[8.5539112091,47.3170318604],"type":"Point"}
}