{
  "type": "Feature",
  "properties": {
    "iso:country":"CH",
    "sg:address":"Route Du Ch\u00e2telet 8",
    "sg:city":"Fribourg",
    "sg:orig_category":"Sportvereine Motorrad",
    "sg:phone":"+41 79 230 60 28",
    "sg:postcode":"1700",
    "sg:province":"Fribourg",
    "wof:name":"Moto-sportclub Fribourg",
    "wof:placetype":"venue"
},
  "geometry": {"coordinates":[7.1435098648,46.7971343994],"type":"Point"}
}