{
  "type": "Feature",
  "properties": {
    "iso:country":"CH",
    "sg:address":"Poststrasse 6",
    "sg:city":"Chur",
    "sg:orig_category":"RESTAURANTS: TEA-ROOMS",
    "sg:postcode":"7000",
    "sg:province":"Graubunden",
    "wof:name":"Patigler J. P.",
    "wof:placetype":"venue"
},
  "geometry": {"coordinates":[9.5319375992,46.8501243591],"type":"Point"}
}