{
  "type": "Feature",
  "properties": {
    "iso:country":"CH",
    "sg:address":"Rue Lac 119",
    "sg:city":"Clarens",
    "sg:orig_category":"Abwasserreinigung",
    "sg:phone":"+41 21 925 82 82",
    "sg:postcode":"1815",
    "sg:province":"Vaud",
    "wof:name":"Station D'\u00e9puration Des Eaux Intercommunale Du Pierrier",
    "wof:placetype":"venue"
},
  "geometry": {"coordinates":[6.890106,46.441097],"type":"Point"}
}