{
  "type": "Feature",
  "properties": {
    "iso:country":"CH",
    "sg:address":"Rudolf Diesel-strasse 2",
    "sg:city":"Winterthur",
    "sg:classifiers":[
        {
            "category":"Manufacturing",
            "subcategory":"Motor Vehicles & Parts",
            "type":"Manufacturing & Wholesale Goods"
        }
    ],
    "sg:phone":"+41 52 235 17 17",
    "sg:postcode":"8404",
    "sg:province":"Z\u00fcrich",
    "sg:tags":[
        "automobile",
        "tool",
        "tools"
    ],
    "wof:name":"Tch - The Car House Ag",
    "wof:placetype":"venue"
},
  "geometry": {"coordinates":[8.752846,47.495506],"type":"Point"}
}