{
  "type": "Feature",
  "properties": {
    "iso:country":"CH",
    "sg:address":"Morystrasse 88",
    "sg:city":"Riehen",
    "sg:orig_category":"Maler U Glasergewerbe Malerei",
    "sg:phone":"+41 33 676 28 20",
    "sg:postcode":"4125",
    "sg:province":"Basel-Stadt",
    "wof:name":"Werner D\u00fcnneisen Malergesch\u00e4ft",
    "wof:placetype":"venue"
},
  "geometry": {"coordinates":[7.6830301285,46.6123580933],"type":"Point"}
}