{
  "type": "Feature",
  "properties": {
    "iso:country":"CH",
    "sg:address":"1782",
    "sg:city":"Belfaux",
    "sg:orig_category":"Vereine Musik/Blasmusik",
    "sg:postcode":"1782",
    "sg:province":"Fribourg",
    "wof:name":"Fanfare La Lyre",
    "wof:placetype":"venue"
},
  "geometry": {"coordinates":[7.1060299873,46.8202896118],"type":"Point"}
}