{
  "type": "Feature",
  "properties": {
    "iso:country":"CH",
    "sg:address":"Industriestrasse 1",
    "sg:city":"Thun",
    "sg:orig_category":"Instandhaltung U Reparatur von Automobilen",
    "sg:postcode":"3600",
    "sg:province":"Bern",
    "wof:name":"Auto-garage Hasanaj I.",
    "wof:placetype":"venue"
},
  "geometry": {"coordinates":[7.6154952049,46.756893158],"type":"Point"}
}