{
  "type": "Feature",
  "properties": {
    "iso:country":"CH",
    "sg:address":"Hauptstrasse 37",
    "sg:city":"Ziefen",
    "sg:orig_category":"Herstellung von Metallerzeugnissen ohne Maschinenbau",
    "sg:phone":"+41 61 931 25 55",
    "sg:postcode":"4417",
    "sg:province":"Basel-Landschaft",
    "wof:name":"Frenke Siebdruck-ger\u00e4te, E. Ardioli",
    "wof:placetype":"venue"
},
  "geometry": {"coordinates":[7.7148828506,47.4331817627],"type":"Point"}
}