{
  "type": "Feature",
  "properties": {
    "iso:country":"CH",
    "sg:address":"Ferrenberg",
    "sg:city":"Wynigen",
    "sg:orig_category":"Verwertung von Milch",
    "sg:postcode":"3472",
    "sg:province":"Bern",
    "wof:name":"K\u00e4sereigenossenschaft Ferrenberg Bei Wynigen",
    "wof:placetype":"venue"
},
  "geometry": {"coordinates":[7.7146139145,47.1067504883],"type":"Point"}
}