{
  "type": "Feature",
  "properties": {
    "iso:country":"CH",
    "sg:address":"Unterdorf 17",
    "sg:city":"Altb\u00fcron",
    "sg:orig_category":"Herstellung von Bergwerks U Baumaschinen",
    "sg:phone":"+41 79 439 74 52",
    "sg:postcode":"6147",
    "sg:province":"Luzern",
    "wof:name":"Bernet Heinz",
    "wof:placetype":"venue"
},
  "geometry": {"coordinates":[7.8795189857,47.1813774109],"type":"Point"}
}