{
  "type": "Feature",
  "properties": {
    "iso:country":"CH",
    "sg:address":"Hausmatt 10",
    "sg:city":"Seftigen",
    "sg:classifiers":[
        {
            "category":"Banks & Credit Unions",
            "subcategory":"Bank",
            "type":"Services"
        }
    ],
    "sg:phone":"+41 33453757",
    "sg:postcode":"3136",
    "wof:name":"Schweiz. Mobiliar",
    "wof:placetype":"venue"
},
  "geometry": {"coordinates":[145.28149400000001,-37.791809],"type":"Point"}
}