{
  "type": "Feature",
  "properties": {
    "iso:country":"CH",
    "sg:address":"Parkstrasse 4",
    "sg:city":"Wallisellen",
    "sg:orig_category":"Arztpraxen",
    "sg:phone":"+41 18300054",
    "sg:postcode":"8304",
    "sg:province":"Z\u00fcrich",
    "wof:name":"Dr.med.rolf M\u00fcller Spezialarzt Fmh",
    "wof:placetype":"venue"
},
  "geometry": {"coordinates":[8.589812,47.415977],"type":"Point"}
}