{
  "type": "Feature",
  "properties": {
    "addr:full":"Sch\u00fctzengasse 17 2540 Grenchen. Postfach Grenchen Solothurn 2540",
    "addr:housenumber":"17",
    "addr:postcode":"2540 grenchen. postfach;2540",
    "addr:street":"Schuetzengasse",
    "iso:country":"CH",
    "sg:address":"Sch\u00fctzengasse 17 2540 Grenchen. Postfach",
    "sg:city":"Grenchen",
    "sg:orig_category":"Aktivit\u00e4ten der Generalunternehmen im Baugewerbe Allgemeiner Hoch U Tiefbau",
    "sg:phone":"+41 32 654 21 31",
    "sg:postcode":"2540",
    "sg:province":"Solothurn",
    "wof:name":"Baderpartner Ag Planen Bauen Nutzen",
    "wof:placetype":"venue"
},
  "geometry": {"coordinates":[7.392318,47.193596],"type":"Point"}
}