{
  "type": "Feature",
  "properties": {
    "iso:country":"CH",
    "sg:address":"Winterthurerstrasse",
    "sg:city":"Gutenswil",
    "sg:orig_category":"Vorschulen, Kinderg\u00e4rten",
    "sg:phone":"+41 19455767",
    "sg:postcode":"8605",
    "sg:province":"Z\u00fcrich",
    "wof:name":"Kindergarten Pavillon",
    "wof:placetype":"venue"
},
  "geometry": {"coordinates":[8.7172327042,47.3818321228],"type":"Point"}
}