{
  "type": "Feature",
  "properties": {
    "iso:country":"CH",
    "sg:address":"Kirchbergstrasse 237 3400 Burgdorf. Postfach 6652",
    "sg:city":"Bern",
    "sg:orig_category":"Unclassifiable Establishments",
    "sg:phone":"+41 34 422 32 88",
    "sg:postcode":"3001",
    "sg:province":"Bern",
    "wof:name":"Mcdonald's Restaurant Burgdorf",
    "wof:placetype":"venue"
},
  "geometry": {"coordinates":[7.6002511978,47.0687599182],"type":"Point"}
}