{
  "type": "Feature",
  "properties": {
    "iso:country":"CH",
    "sg:address":"Rue Du Ch\u00e2teau 8 1616 Attalens Case Postale 21",
    "sg:city":"Attalens",
    "sg:orig_category":"Maurerarbeiten Stukkateurgewerbe, Gipserei U Verputzerei",
    "sg:phone":"+41 21 947 41 15",
    "sg:postcode":"1616",
    "sg:province":"Fribourg",
    "wof:name":"Genoud & Cottet Entreprise De Ma\u00e7onnerie",
    "wof:placetype":"venue"
},
  "geometry": {"coordinates":[6.8478388786,46.5086784363],"type":"Point"}
}