{
  "type": "Feature",
  "properties": {
    "addr:full":"Waisenhausplatz 19 3011 Bern. Postfach Bern Bern 3001",
    "addr:housenumber":"19",
    "addr:postcode":"3011;postfach;3001",
    "addr:street":"Waisenhausplatz",
    "iso:country":"CH",
    "sg:address":"Waisenhausplatz 19 3011 Bern. Postfach",
    "sg:city":"Bern",
    "sg:orig_category":"Detailhandel mit B\u00fcchern Vermietung von Gebrauchsg\u00fctern",
    "sg:phone":"+41 31 311 00 70",
    "sg:postcode":"3001",
    "sg:province":"Bern",
    "wof:name":"Jos\u00e9 Ferrero",
    "wof:placetype":"venue"
},
  "geometry": {"coordinates":[7.443993,46.948921],"type":"Point"}
}