{
  "type": "Feature",
  "properties": {
    "iso:country":"CH",
    "sg:address":"Wirtschaft Kreuz",
    "sg:city":"M\u00fchlethurnen",
    "sg:orig_category":"RESTAURANTS: TEA-ROOMS",
    "sg:postcode":"3127",
    "sg:province":"Bern",
    "wof:name":"Imper Louis, Wirtschaft Kreuz",
    "wof:placetype":"venue"
},
  "geometry": {"coordinates":[7.5075750351,46.8137397766],"type":"Point"}
}