{
  "type": "Feature",
  "properties": {
    "iso:country":"CH",
    "sg:address":"Haubenstrasse 4",
    "sg:city":"Oberdiessbach",
    "sg:orig_category":"Politische Parteien FDP",
    "sg:phone":"+41 31 771 08 59",
    "sg:postcode":"3672",
    "sg:province":"Bern",
    "wof:name":"Fdp Sektion Oberdiessbach",
    "wof:placetype":"venue"
},
  "geometry": {"coordinates":[7.6159567833,46.8391571045],"type":"Point"}
}