{
  "type": "Feature",
  "properties": {
    "iso:country":"CH",
    "sg:address":"3952",
    "sg:city":"Susten",
    "sg:orig_category":"Vermietung von Baumaschinen U ger\u00e4ten",
    "sg:phone":"+41 27 473 34 14",
    "sg:postcode":"3952",
    "sg:province":"Valais",
    "wof:name":"Meinrad Arnold Erben Kranvermietung",
    "wof:placetype":"venue"
},
  "geometry": {"coordinates":[7.6420202255,46.3115081787],"type":"Point"}
}