{
  "type": "Feature",
  "properties": {
    "iso:country":"CH",
    "sg:address":"Bachtobelstrasse 26",
    "sg:city":"Ebmatingen",
    "sg:orig_category":"Detailhandel mit medizinischen U orthop\u00e4dischen Artikeln",
    "sg:phone":"+41 18877364",
    "sg:postcode":"8123",
    "sg:province":"Z\u00fcrich",
    "wof:name":"Ernst Bl\u00e4ttler Sport Orthop\u00e4die",
    "wof:placetype":"venue"
},
  "geometry": {"coordinates":[8.6396389008,47.3542747498],"type":"Point"}
}