{
  "type": "Feature",
  "properties": {
    "iso:country":"CH",
    "sg:address":"Hallenstrasse 9",
    "sg:city":"D\u00fcbendorf",
    "sg:orig_category":"Kaminfeger",
    "sg:phone":"+41 18201803",
    "sg:postcode":"8600",
    "sg:province":"Z\u00fcrich",
    "wof:name":"Otto Breitenmoser Kaminfegermeister",
    "wof:placetype":"venue"
},
  "geometry": {"coordinates":[8.6280136108,47.4004096985],"type":"Point"}
}