{
  "type": "Feature",
  "properties": {
    "iso:country":"CH",
    "sg:address":"Hauptstrasse 30",
    "sg:city":"Siblingen",
    "sg:orig_category":"Massagestudios",
    "sg:phone":"+41 52 685 34 43",
    "sg:postcode":"8225",
    "sg:province":"Schaffhausen",
    "wof:name":"Erica Sauzet Praxis F\u00fcr K\u00f6rpermassagen",
    "wof:placetype":"venue"
},
  "geometry": {"coordinates":[8.5229854584,47.7137641907],"type":"Point"}
}