{
  "type": "Feature",
  "properties": {
    "iso:country":"CH",
    "sg:address":"Dorfstrasse 32",
    "sg:city":"Schneisingen",
    "sg:orig_category":"G\u00fcterbef\u00f6rderung im Strassenverkehr",
    "sg:phone":"+41 56 241 19 87",
    "sg:postcode":"5425",
    "sg:province":"Aargau",
    "wof:name":"Robla Transporte Blatti Roger",
    "wof:placetype":"venue"
},
  "geometry": {"coordinates":[8.3629331589,47.5199394226],"type":"Point"}
}