{
  "type": "Feature",
  "properties": {
    "iso:country":"CH",
    "sg:address":"Via Belsoggiorno 3",
    "sg:city":"Bellinzona",
    "sg:orig_category":"Maler U Glasergewerbe Stukkateurgewerbe, Gipserei U Verputzerei",
    "sg:phone":"+41 91 825 22 88",
    "sg:postcode":"6500",
    "sg:province":"Ticino",
    "wof:name":"Remo Weit Sa Impresa Di Pittura",
    "wof:placetype":"venue"
},
  "geometry": {"coordinates":[9.0224208832,46.1855583191],"type":"Point"}
}