{
  "type": "Feature",
  "properties": {
    "iso:country":"CH",
    "sg:address":"3961",
    "sg:city":"Chandolin",
    "sg:classifiers":[
        {
            "category":"Restaurant",
            "type":"Food & Drink"
        }
    ],
    "sg:phone":"+41 79 226 76 09",
    "sg:postcode":"3961",
    "sg:province":"Valais",
    "wof:name":"Restaurant Lac Noir",
    "wof:placetype":"venue"
},
  "geometry": {"coordinates":[7.5976371765,46.25207901],"type":"Point"}
}