{
  "type": "Feature",
  "properties": {
    "iso:country":"CH",
    "sg:address":"G\u00e9n\u00e9ral-guisan Av. Du 46",
    "sg:city":"Freiburg",
    "sg:orig_category":"Non-Classified Establishments",
    "sg:postcode":"1700",
    "sg:province":"Fribourg",
    "wof:name":"Care 4 You Gmbh Pflege, Gesundheitsprodukte; Vertrieb Usw",
    "wof:placetype":"venue"
},
  "geometry": {"coordinates":[8.0708436966,47.38539505],"type":"Point"}
}