{
  "type": "Feature",
  "properties": {
    "iso:country":"CH",
    "sg:address":"Neubruchstrasse 64f 8400 Winterthur. Postfach",
    "sg:city":"Winterthur",
    "sg:orig_category":"Grosshandel mit Textilien",
    "sg:postcode":"8406",
    "sg:province":"Z\u00fcrich",
    "wof:name":"Textil Focus Ag",
    "wof:placetype":"venue"
},
  "geometry": {"coordinates":[9.6363697052,47.4310112],"type":"Point"}
}