{
  "type": "Feature",
  "properties": {
    "iso:country":"CH",
    "sg:address":"B\u00e4ndlistrasse 108 8064 Z\u00fcrich. Postfach",
    "sg:city":"Z\u00fcrich",
    "sg:orig_category":"RESTAURANTS: TEA-ROOMS",
    "sg:postcode":"8064",
    "sg:province":"Z\u00fcrich",
    "wof:name":"Weiss Gastroteam Gmbh",
    "wof:placetype":"venue"
},
  "geometry": {"coordinates":[8.480884552,47.3989295959],"type":"Point"}
}