{
  "type": "Feature",
  "properties": {
    "iso:country":"CH",
    "sg:address":"Oberdorf",
    "sg:city":"Kottwil",
    "sg:orig_category":"Bau U Wohngenossenschaften",
    "sg:phone":"+41 41 980 21 75",
    "sg:postcode":"6217",
    "sg:province":"Luzern",
    "wof:name":"Wohnbaugenossenschaft B\u00e4ren",
    "wof:placetype":"venue"
},
  "geometry": {"coordinates":[8.044743,47.161736],"type":"Point"}
}