{
  "type": "Feature",
  "properties": {
    "iso:country":"CH",
    "sg:address":"Hegistrasse 5",
    "sg:city":"Thal",
    "sg:orig_category":"Architektur U Ingenieurb\u00fcros",
    "sg:phone":"+41 71 755 22 82",
    "sg:postcode":"9425",
    "sg:province":"St. Gallen",
    "wof:name":"Rkl Ingenieurb\u00fcro Ag",
    "wof:placetype":"venue"
},
  "geometry": {"coordinates":[9.574948,47.476601],"type":"Point"}
}