{
  "type": "Feature",
  "properties": {
    "iso:country":"CH",
    "sg:address":"Gundeldingerstrasse 154 4000 Basel. Postfach",
    "sg:city":"Basel",
    "sg:orig_category":"Vermietung U Verpachtung von eigenen Immobilien",
    "sg:postcode":"4051",
    "sg:province":"Basel-Stadt",
    "wof:name":"Dominium Ag",
    "wof:placetype":"venue"
},
  "geometry": {"coordinates":[7.5874900818,47.5417327881],"type":"Point"}
}