{
  "type": "Feature",
  "properties": {
    "iso:country":"CH",
    "sg:address":"Riburgerstrasse 2",
    "sg:city":"M\u00f6hlin",
    "sg:orig_category":"Detailhandel mit Tabakwaren",
    "sg:phone":"+41 61 851 45 44",
    "sg:postcode":"4313",
    "sg:province":"Aargau",
    "wof:name":"Armin Frey Tabakwaren",
    "wof:placetype":"venue"
},
  "geometry": {"coordinates":[7.8409318924,47.5641174316],"type":"Point"}
}