{
  "type": "Feature",
  "properties": {
    "iso:country":"CH",
    "sg:address":"Untergasse 43 7206 Igis. Postfach 10",
    "sg:city":"Igis",
    "sg:orig_category":"Allgemeiner Hoch U Tiefbau Hoch U Tiefbau",
    "sg:phone":"+41 81 322 17 36",
    "sg:postcode":"7206",
    "sg:province":"Graubunden",
    "wof:name":"Tettamanti Georg.",
    "wof:placetype":"venue"
},
  "geometry": {"coordinates":[9.575044,46.947338],"type":"Point"}
}