{
  "type": "Feature",
  "properties": {
    "iso:country":"CH",
    "sg:address":"Melchr\u00fctistrasse 81",
    "sg:city":"Wallisellen",
    "sg:orig_category":"Sonstiger Grosshandel",
    "sg:postcode":"8304",
    "sg:province":"Z\u00fcrich",
    "wof:name":"Import-export, M. Wisniewski",
    "wof:placetype":"venue"
},
  "geometry": {"coordinates":[8.4394712448,47.4551048279],"type":"Point"}
}