{
  "type": "Feature",
  "properties": {
    "addr:full":"Zentrum Hubp\u00fcnt 4 Seengen Aargau 5707",
    "addr:housenumber":"4",
    "addr:postcode":"5707",
    "iso:country":"CH",
    "sg:address":"Zentrum Hubp\u00fcnt 4",
    "sg:city":"Seengen",
    "sg:classifiers":[
        {
            "category":"Education",
            "subcategory":"Library",
            "type":"Public Place"
        }
    ],
    "sg:phone":"+41 79 316 51 44",
    "sg:postcode":"5707",
    "sg:province":"Aargau",
    "sg:tags":[
        "u",
        "bibliotheken",
        "archive"
    ],
    "wof:name":"Ludothek Seengen",
    "wof:placetype":"venue"
},
  "geometry": {"coordinates":[8.205024,47.324631],"type":"Point"}
}