{
  "type": "Feature",
  "properties": {
    "iso:country":"CH",
    "sg:address":"Austrasse 24",
    "sg:city":"Z\u00fcrich",
    "sg:orig_category":"Kinderkrippen U horte",
    "sg:phone":"+41 14633200",
    "sg:postcode":"8045",
    "sg:province":"Z\u00fcrich",
    "wof:name":"Monique Huber-botti Kinder-tagestreff",
    "wof:placetype":"venue"
},
  "geometry": {"coordinates":[8.5196046829,47.3657531738],"type":"Point"}
}