{
  "type": "Feature",
  "properties": {
    "iso:country":"CH",
    "sg:address":"Via Luigi Canonica 3",
    "sg:city":"Lugano",
    "sg:orig_category":"Interessenvertretungen",
    "sg:postcode":"6900",
    "sg:province":"Ticino",
    "wof:name":"Fondazione Pellegrini Piero E Marco E Canevascini Guglielmo.",
    "wof:placetype":"venue"
},
  "geometry": {"coordinates":[8.9560279846,46.0068359375],"type":"Point"}
}