{
  "type": "Feature",
  "properties": {
    "iso:country":"CH",
    "sg:address":"Rast",
    "sg:city":"Unterterzen",
    "sg:orig_category":"Autospenglereien",
    "sg:phone":"+41 81 738 13 78",
    "sg:postcode":"8882",
    "sg:province":"St. Gallen",
    "wof:name":"Martin Gubser Autospenglerei",
    "wof:placetype":"venue"
},
  "geometry": {"coordinates":[9.25304,47.113514],"type":"Point"}
}