{
  "type": "Feature",
  "properties": {
    "iso:country":"CH",
    "sg:address":"Rue De La Lanche Torgon 1895 Vionnaz. Postfach",
    "sg:city":"Torgon",
    "sg:orig_category":"RESTAURANTS: TEA-ROOMS",
    "sg:postcode":"1899",
    "sg:province":"Valais",
    "wof:name":"Ariane Trisconi",
    "wof:placetype":"venue"
},
  "geometry": {"coordinates":[6.8994240761,46.3116989136],"type":"Point"}
}