{
  "type": "Feature",
  "properties": {
    "iso:country":"CH",
    "sg:address":"Poststrasse 11",
    "sg:city":"Widnau",
    "sg:orig_category":"Nationale Postdienste",
    "sg:phone":"+41 62 288 02 88",
    "sg:postcode":"9443",
    "sg:province":"St. Gallen",
    "wof:name":"Die Schweizerische Post",
    "wof:placetype":"venue"
},
  "geometry": {"coordinates":[7.9789910316,47.3558998108],"type":"Point"}
}