{
  "type": "Feature",
  "properties": {
    "iso:country":"CH",
    "sg:address":"Boveresses Avenue Des 33 1010 Lausanne. Postfach",
    "sg:city":"Lausanne",
    "sg:orig_category":"Detailhandel mit Waren verschiedener Art, Hauptrichtung Nahrungsmittel",
    "sg:phone":"+41 21 729 81 22",
    "sg:postcode":"1010",
    "sg:province":"Vaud",
    "wof:name":"Alimentation Service, Rod M. Produits Alimentaires; Comm. Et Livraison",
    "wof:placetype":"venue"
},
  "geometry": {"coordinates":[6.6663098335,46.5380744934],"type":"Point"}
}