{
  "type": "Feature",
  "properties": {
    "iso:country":"CH",
    "sg:address":"1612",
    "sg:city":"Ecoteaux",
    "sg:orig_category":"Bauschreinerei Herstellung von M\u00f6beln verschiedener Art",
    "sg:phone":"+41 21 907 72 01",
    "sg:postcode":"1612",
    "sg:province":"Vaud",
    "wof:name":"Beroud Jean-fran\u00e7ois",
    "wof:placetype":"venue"
},
  "geometry": {"coordinates":[6.861565,46.545197],"type":"Point"}
}