{
  "type": "Feature",
  "properties": {
    "iso:country":"CH",
    "sg:address":"Seminarstrasse 74",
    "sg:city":"Wettingen",
    "sg:orig_category":"G\u00fcterbef\u00f6rderung im Strassenverkehr",
    "sg:phone":"+41 56 426 84 77",
    "sg:postcode":"5430",
    "sg:province":"Aargau",
    "wof:name":"Reto Turner Transporte",
    "wof:placetype":"venue"
},
  "geometry": {"coordinates":[8.3132381439,47.4632225037],"type":"Point"}
}