{
  "type": "Feature",
  "properties": {
    "iso:country":"CH",
    "sg:address":"Baselstrasse 12 4242 Laufen. Postfach",
    "sg:city":"Laufen",
    "sg:orig_category":"Grossbanken",
    "sg:phone":"+41 844 800 844",
    "sg:postcode":"4242",
    "sg:province":"Basel-Landschaft",
    "wof:name":"Credit Suisse",
    "wof:placetype":"venue"
},
  "geometry": {"coordinates":[7.4836120605,46.9562110901],"type":"Point"}
}