{
  "type": "Feature",
  "properties": {
    "iso:country":"CH",
    "sg:address":"Corso Elvezia 21",
    "sg:city":"Lugano",
    "sg:orig_category":"Detailhandel mit M\u00f6beln U Haushaltsgegenst\u00e4nden Innenarchitekturb\u00fcros",
    "sg:phone":"+41 91 921 12 25",
    "sg:postcode":"6900",
    "sg:province":"Ticino",
    "wof:name":"Home & Office Interior Design Sa",
    "wof:placetype":"venue"
},
  "geometry": {"coordinates":[8.9556331635,46.0082817078],"type":"Point"}
}