{
  "type": "Feature",
  "properties": {
    "iso:country":"CH",
    "sg:address":"Aarestrasse 30",
    "sg:city":"Thun",
    "sg:orig_category":"Berufliche Weiterbildung, Erwachsenenbildung",
    "sg:phone":"+41 33 222 23 23",
    "sg:postcode":"3600",
    "sg:province":"Bern",
    "wof:name":"Massage-schule Bodyfeet Herrn Max Sulser",
    "wof:placetype":"venue"
},
  "geometry": {"coordinates":[7.627255,46.757271],"type":"Point"}
}