{
  "type": "Feature",
  "properties": {
    "iso:country":"CH",
    "sg:address":"Lederbach 14",
    "sg:city":"Herisau",
    "sg:orig_category":"Herstellung von keramischen Haushaltswaren U Ziergegenst\u00e4nden",
    "sg:phone":"+41 71 351 14 69",
    "sg:postcode":"9100",
    "sg:province":"Appenzell Ausserrhoden",
    "wof:name":"Edeltraud Kr\u00e4mer T\u00f6pferei",
    "wof:placetype":"venue"
},
  "geometry": {"coordinates":[9.2809944153,47.3787574768],"type":"Point"}
}