{
  "type": "Feature",
  "properties": {
    "iso:country":"CH",
    "sg:address":"Rue Du Cendrier 15 1200 Genf. Postfach",
    "sg:city":"Gen\u00e8ve",
    "sg:orig_category":"Ackerbau",
    "sg:postcode":"1201",
    "sg:province":"Gen\u00e8ve",
    "wof:name":"Agrimer, A. Bouchaara",
    "wof:placetype":"venue"
},
  "geometry": {"coordinates":[6.144313,46.207027],"type":"Point"}
}