{
  "type": "Feature",
  "properties": {
    "iso:country":"CH",
    "sg:address":"B\u00e4renplatz 6",
    "sg:city":"Fahrwangen",
    "sg:orig_category":"Unternehmensberatung",
    "sg:phone":"+41 56 670 11 62",
    "sg:postcode":"5615",
    "sg:province":"Aargau",
    "wof:name":"K-vis Gmbh",
    "wof:placetype":"venue"
},
  "geometry": {"coordinates":[8.2419710159,47.2947845459],"type":"Point"}
}