{
  "type": "Feature",
  "properties": {
    "addr:full":"Furkastrasse Fiesch Valais 3984",
    "addr:postcode":"3984",
    "addr:street":"Furkastrasse",
    "iso:country":"CH",
    "sg:address":"Furkastrasse",
    "sg:city":"Fiesch",
    "sg:classifiers":[
        {
            "category":"Bars & Pubs",
            "type":"Food & Drink"
        }
    ],
    "sg:postcode":"3984",
    "sg:province":"Valais",
    "wof:name":"Tinguely Jacques Black Jack Club House",
    "wof:placetype":"venue"
},
  "geometry": {"coordinates":[7.108453,46.925232],"type":"Point"}
}