{
  "type": "Feature",
  "properties": {
    "iso:country":"CH",
    "sg:address":"Euthalerstrasse 4",
    "sg:city":"Euthal",
    "sg:classifiers":[
        {
            "category":"Restaurant",
            "type":"Food & Drink"
        }
    ],
    "sg:phone":"+41 55 412 25 56",
    "sg:postcode":"8844",
    "sg:province":"Schwyz",
    "wof:name":"Seerestaurant Steinbach",
    "wof:placetype":"venue"
},
  "geometry": {"coordinates":[8.812081337,47.0968933105],"type":"Point"}
}