{
  "type": "Feature",
  "properties": {
    "iso:country":"CH",
    "sg:address":"Schl\u00f6sslistrasse 49",
    "sg:city":"Ebikon",
    "sg:orig_category":"Sonstiger Grosshandel",
    "sg:postcode":"6030",
    "sg:province":"Luzern",
    "wof:name":"Export/import Vinu",
    "wof:placetype":"venue"
},
  "geometry": {"coordinates":[8.3357810974,47.0725440979],"type":"Point"}
}