{
  "type": "Feature",
  "properties": {
    "iso:country":"CH",
    "sg:address":"Fabrikstrasse 2",
    "sg:city":"Lyss",
    "sg:orig_category":"Versicherungen Generalagenturen",
    "sg:phone":"+41 32 323 19 61",
    "sg:postcode":"3250",
    "sg:province":"Bern",
    "wof:name":"Rentenanstalt/swiss Life Generalagentur",
    "wof:placetype":"venue"
},
  "geometry": {"coordinates":[7.3050642014,47.0754432678],"type":"Point"}
}