{
  "type": "Feature",
  "properties": {
    "iso:country":"CH",
    "sg:address":"Via Ung\u00e9",
    "sg:city":"Torricella",
    "sg:orig_category":"Non-Classified Establishments",
    "sg:postcode":"6808",
    "sg:province":"Ticino",
    "wof:name":"Idrosanit Sagl",
    "wof:placetype":"venue"
},
  "geometry": {"coordinates":[8.9257574081,46.0686225891],"type":"Point"}
}