{
  "type": "Feature",
  "properties": {
    "iso:country":"CH",
    "sg:address":"Seestrasse 1",
    "sg:city":"Cham",
    "sg:orig_category":"Unclassifiable Establishments",
    "sg:postcode":"6330",
    "sg:province":"Zug",
    "wof:name":"Gfi Gesellschaft F\u00fcr Industriebeteiligungen Ag",
    "wof:placetype":"venue"
},
  "geometry": {"coordinates":[8.460144043,47.1801681519],"type":"Point"}
}