{
  "type": "Feature",
  "properties": {
    "iso:country":"CH",
    "sg:address":"Ponte Tresa Via 7",
    "sg:city":"Sorengo",
    "sg:orig_category":"Grosshandel mit sonstigen Maschinen U Ausr\u00fcstungen f\u00fcr Industrie, Handel U Schiffahrt",
    "sg:postcode":"6924",
    "sg:province":"Ticino",
    "wof:name":"Savertech Sagl",
    "wof:placetype":"venue"
},
  "geometry": {"coordinates":[8.9396734238,46.0009384155],"type":"Point"}
}