{
  "type": "Feature",
  "properties": {
    "iso:country":"CH",
    "sg:address":"Schlossbergstrasse 16",
    "sg:city":"Zollikon",
    "sg:orig_category":"Architektur U Ingenieurb\u00fcros Architekturb\u00fcros",
    "sg:phone":"+41 41 248 71 71",
    "sg:postcode":"8702",
    "sg:province":"Z\u00fcrich",
    "wof:name":"Erculiani Architekten Gmbh",
    "wof:placetype":"venue"
},
  "geometry": {"coordinates":[8.29277,47.053177],"type":"Point"}
}