{
  "type": "Feature",
  "properties": {
    "iso:country":"CH",
    "sg:address":"Cheggio",
    "sg:city":"Vairano",
    "sg:orig_category":"Allgemeiner Gartenbau Blumen U Zierpflanzenbau",
    "sg:phone":"+41 91 795 18 67",
    "sg:postcode":"6575",
    "sg:province":"Ticino",
    "wof:name":"Otto Eisenhut Orticoltura",
    "wof:placetype":"venue"
},
  "geometry": {"coordinates":[8.80218,46.132244],"type":"Point"}
}