{
  "type": "Feature",
  "properties": {
    "iso:country":"CH",
    "sg:address":"Ramsteinerstrasse 28",
    "sg:city":"Basel",
    "sg:orig_category":"Unclassifiable Establishments",
    "sg:postcode":"4052",
    "sg:province":"Basel-Stadt",
    "wof:name":"Mcarthur And Associates Gmbh",
    "wof:placetype":"venue"
},
  "geometry": {"coordinates":[7.6109280586,47.5549278259],"type":"Point"}
}