{
  "type": "Feature",
  "properties": {
    "iso:country":"CH",
    "sg:address":"Saint-fran\u00e7ois Place 12 Bis 1003 Lausanne. Postfach",
    "sg:city":"Lausanne",
    "sg:orig_category":"Non-Classified Establishments",
    "sg:postcode":"1003",
    "sg:province":"Vaud",
    "wof:name":"Crimar Gmbh Beteiligungen U. Finanzierungen Usw.",
    "wof:placetype":"venue"
},
  "geometry": {"coordinates":[9.0611772537,47.4653282166],"type":"Point"}
}