{
  "type": "Feature",
  "properties": {
    "iso:country":"CH",
    "sg:address":"Franklinstrasse 9",
    "sg:city":"Z\u00fcrich",
    "sg:orig_category":"Erwachsenenbildung U Unterricht Unternehmensberatung",
    "sg:phone":"+41 8782182",
    "sg:postcode":"8050",
    "sg:province":"Z\u00fcrich",
    "wof:name":"Ad Vantis Innovation Ag",
    "wof:placetype":"venue"
},
  "geometry": {"coordinates":[8.6762781143,47.2663574219],"type":"Point"}
}