{
  "type": "Feature",
  "properties": {
    "iso:country":"CH",
    "sg:address":"Aarestrasse 83",
    "sg:city":"Umiken",
    "sg:orig_category":"Verlagsgewerbe",
    "sg:phone":"+41 71 910 08 66",
    "sg:postcode":"5222",
    "sg:province":"Aargau",
    "wof:name":"Infomed-verlags Ag",
    "wof:placetype":"venue"
},
  "geometry": {"coordinates":[9.0486879349,47.462272644],"type":"Point"}
}