{
  "type": "Feature",
  "properties": {
    "iso:country":"CH",
    "sg:address":"Bolgen",
    "sg:city":"Zweisimmen",
    "sg:orig_category":"Vermietung U Verpachtung von eigenen Immobilien",
    "sg:postcode":"3770",
    "sg:province":"Bern",
    "wof:name":"Guggisberg Immobilien Ag",
    "wof:placetype":"venue"
},
  "geometry": {"coordinates":[7.3717370033,46.5559120178],"type":"Point"}
}