{
  "type": "Feature",
  "properties": {
    "iso:country":"CH",
    "sg:address":"St\u00e4dtle 28 9490 Vaduz. Postfach 683",
    "sg:city":"Vaduz",
    "sg:orig_category":"Wirtschaftspr\u00fcfung, Steuerberatung U Treuhand",
    "sg:phone":"+41 75 235 27 55",
    "sg:postcode":"9490",
    "wof:name":"Lgt Audit Revisions Ag",
    "wof:placetype":"venue"
},
  "geometry": {"coordinates":[9.522395134,47.1395454407],"type":"Point"}
}