{
  "type": "Feature",
  "properties": {
    "iso:country":"CH",
    "sg:address":"Thunstrasse 7 3150 Schwarzenburg. Postfach 63",
    "sg:city":"Schwarzenburg",
    "sg:orig_category":"Notariate",
    "sg:phone":"+41 31 731 01 31",
    "sg:postcode":"3150",
    "sg:province":"Bern",
    "wof:name":"Heinz Stampbach Notariatsb\u00fcro",
    "wof:placetype":"venue"
},
  "geometry": {"coordinates":[7.3448839188,46.8186225891],"type":"Point"}
}