{
  "type": "Feature",
  "properties": {
    "iso:country":"CH",
    "sg:address":"Br\u00fchlstrasse 40 4415 Lausen. Postfach",
    "sg:city":"Lausen",
    "sg:orig_category":"Architekturb\u00fcros",
    "sg:phone":"+41 61 921 99 44",
    "sg:postcode":"4415",
    "sg:province":"Basel-Landschaft",
    "wof:name":"Werner Wyss Architekturb\u00fcro",
    "wof:placetype":"venue"
},
  "geometry": {"coordinates":[7.75716,47.473518],"type":"Point"}
}