{
  "type": "Feature",
  "properties": {
    "iso:country":"CH",
    "sg:address":"Kaiser Route Wilhelm- 3",
    "sg:city":"Freiburg",
    "sg:orig_category":"Unclassifiable Establishments",
    "sg:postcode":"1700",
    "sg:province":"Fribourg",
    "wof:name":"Heimoz + Parra, Net System",
    "wof:placetype":"venue"
},
  "geometry": {"coordinates":[7.1543087959,46.7951316833],"type":"Point"}
}