{
  "type": "Feature",
  "properties": {
    "iso:country":"CH",
    "sg:address":"Zugerstrasse 5",
    "sg:city":"Cham",
    "sg:orig_category":"Detailhandel mit Spielwaren Detailhandel mit S\u00e4uglings U Kinderbekleidung",
    "sg:phone":"+41 41 781 10 52",
    "sg:postcode":"6330",
    "sg:province":"Zug",
    "wof:name":"Pinocchio Jessy Andermatt B\u00f6rse & Neu F\u00fcr Das Kind",
    "wof:placetype":"venue"
},
  "geometry": {"coordinates":[8.4598932266,47.1814994812],"type":"Point"}
}