{
  "type": "Feature",
  "properties": {
    "iso:country":"CH",
    "sg:address":"Via Campagna Adorna",
    "sg:city":"Genestrerio",
    "sg:orig_category":"Elektroinstallation",
    "sg:phone":"+41 91 641 64 00",
    "sg:postcode":"6852",
    "sg:province":"Ticino",
    "wof:name":"Mario Pontiggia Sagl Impianti Elettrici",
    "wof:placetype":"venue"
},
  "geometry": {"coordinates":[8.9673109055,45.8573303223],"type":"Point"}
}