{
  "type": "Feature",
  "properties": {
    "iso:country":"CH",
    "sg:address":"Ale Rue De L' 22",
    "sg:city":"Lausanne",
    "sg:orig_category":"Unclassifiable Establishments",
    "sg:postcode":"1003",
    "sg:province":"Vaud",
    "wof:name":"Trajkovic Milovan Transporte Transporte Mittels Kipper-lkw",
    "wof:placetype":"venue"
},
  "geometry": {"coordinates":[8.5168466568,47.4744567871],"type":"Point"}
}