{
  "type": "Feature",
  "properties": {
    "iso:country":"CH",
    "sg:address":"Parkallee 10",
    "sg:city":"Allschwil",
    "sg:orig_category":"Malerei",
    "sg:phone":"+41 79 219 76 74",
    "sg:postcode":"4123",
    "sg:province":"Basel-Landschaft",
    "wof:name":"Heinz Peyer Malergesch\u00e4ft",
    "wof:placetype":"venue"
},
  "geometry": {"coordinates":[7.5533518791,47.554561615],"type":"Point"}
}