{
  "type": "Feature",
  "properties": {
    "iso:country":"CH",
    "sg:address":"Kirchgasse 8",
    "sg:city":"Hohtenn",
    "sg:orig_category":"Herstellung von Wein",
    "sg:postcode":"3949",
    "sg:province":"Valais",
    "wof:name":"Rebbau-genossenschaft Bineneggi",
    "wof:placetype":"venue"
},
  "geometry": {"coordinates":[7.7569518089,46.318813324],"type":"Point"}
}