{
  "type": "Feature",
  "properties": {
    "addr:full":"Ottenbacherstrasse 23 Obfelden Z\u00fcrich 8912",
    "addr:housenumber":"23",
    "addr:postcode":"8912",
    "addr:street":"Ottenbacherstrasse",
    "iso:country":"CH",
    "sg:address":"Ottenbacherstrasse 23",
    "sg:city":"Obfelden",
    "sg:orig_category":"Detailhandel mit Computern U Software Hardwareberatung",
    "sg:phone":"+41 27 722 89 69",
    "sg:postcode":"8912",
    "sg:province":"Z\u00fcrich",
    "wof:name":"Computerlove Sa",
    "wof:placetype":"venue"
},
  "geometry": {"coordinates":[7.064211,46.093143],"type":"Point"}
}