{
  "type": "Feature",
  "properties": {
    "iso:country":"CH",
    "sg:address":"Kapellenweg 3 5600 Lenzburg. Postfach",
    "sg:city":"Lenzburg",
    "sg:orig_category":"Allgemeiner Hoch U Tiefbau",
    "sg:phone":"+41 17302400",
    "sg:postcode":"5600",
    "sg:province":"Aargau",
    "wof:name":"Schaufelberger + Gutknecht Ag",
    "wof:placetype":"venue"
},
  "geometry": {"coordinates":[8.186667,47.39069],"type":"Point"}
}