{
  "type": "Feature",
  "properties": {
    "iso:country":"CH",
    "sg:address":"Schulhausstrasse 33",
    "sg:city":"Worb",
    "sg:orig_category":"Bau U Wohngenossenschaften",
    "sg:postcode":"3076",
    "sg:province":"Bern",
    "wof:name":"Wohnungsbaugen.worb",
    "wof:placetype":"venue"
},
  "geometry": {"coordinates":[7.567537,46.927639],"type":"Point"}
}