{
  "type": "Feature",
  "properties": {
    "iso:country":"CH",
    "sg:address":"Eustrasse 4 6313 Menzingen. Postfach 42",
    "sg:city":"Menzingen",
    "sg:orig_category":"Herstellung von Teppichen Verlegen von Fussboden",
    "sg:phone":"+41 79 353 26 59",
    "sg:postcode":"6313",
    "sg:province":"Zug",
    "wof:name":"Arnold Carl Ag",
    "wof:placetype":"venue"
},
  "geometry": {"coordinates":[8.5905981064,47.1773414612],"type":"Point"}
}