{
  "type": "Feature",
  "properties": {
    "iso:country":"CH",
    "sg:address":"B\u00fcrkliplatz",
    "sg:city":"Z\u00fcrich",
    "sg:orig_category":"Vermietung von Gebrauchsg\u00fctern Vermietung von Wasserfahrzeugen",
    "sg:phone":"+41 12112262",
    "sg:postcode":"8001",
    "sg:province":"Z\u00fcrich",
    "wof:name":"Ren\u00e9 Sutter Bootsvermietung",
    "wof:placetype":"venue"
},
  "geometry": {"coordinates":[8.5416097641,47.3666687012],"type":"Point"}
}