{
  "type": "Feature",
  "properties": {
    "iso:country":"CH",
    "sg:address":"Rue Karl-neuhaus 40 2500 Biel/bienne. Postfach",
    "sg:city":"Biel/bienne",
    "sg:orig_category":"Herstellung von konfektionierten Textilwaren ohne Bekleidung",
    "sg:phone":"+41 32 323 30 71",
    "sg:postcode":"2502",
    "sg:province":"Bern",
    "wof:name":"Campo Nino.",
    "wof:placetype":"venue"
},
  "geometry": {"coordinates":[7.2451238632,47.1357917786],"type":"Point"}
}