{
  "type": "Feature",
  "properties": {
    "iso:country":"CH",
    "sg:address":"Wilstrasse 64",
    "sg:city":"D\u00fcbendorf",
    "sg:orig_category":"Physiotherapie",
    "sg:phone":"+41 18215256",
    "sg:postcode":"8600",
    "sg:province":"Z\u00fcrich",
    "wof:name":"Wybe & Judith Dedden Physiotherapie",
    "wof:placetype":"venue"
},
  "geometry": {"coordinates":[8.6170778275,47.3931121826],"type":"Point"}
}