{
  "type": "Feature",
  "properties": {
    "iso:country":"CH",
    "sg:address":"Logengasse 29a. 2500 Biel/bienne. Postfach",
    "sg:city":"Biel/bienne",
    "sg:orig_category":"Herstellung von Reiseartikeln, Leder U Sattlerwaren",
    "sg:phone":"+41 32 342 64 70",
    "sg:postcode":"2502",
    "sg:province":"Bern",
    "wof:name":"Hofstetter Alfred",
    "wof:placetype":"venue"
},
  "geometry": {"coordinates":[7.2517051697,47.1405410767],"type":"Point"}
}