{
  "type": "Feature",
  "properties": {
    "addr:full":"Hauptstrasse 96 Safnern Bern 2553",
    "addr:housenumber":"96",
    "addr:postcode":"2553",
    "addr:street":"Hauptstrasse",
    "iso:country":"CH",
    "sg:address":"Hauptstrasse 96",
    "sg:city":"Safnern",
    "sg:classifiers":[
        {
            "category":"Banks & Credit Unions",
            "subcategory":"Bank",
            "type":"Services"
        }
    ],
    "sg:phone":"+41 32551033",
    "sg:postcode":"2553",
    "sg:province":"Bern",
    "wof:name":"Schweiz. Mobiliar",
    "wof:placetype":"venue"
},
  "geometry": {"coordinates":[7.328165,47.15303],"type":"Point"}
}