{
  "type": "Feature",
  "properties": {
    "iso:country":"CH",
    "sg:address":"Bohl 49-50",
    "sg:city":"Altdorf",
    "sg:classifiers":[
        {
            "category":"Banks & Credit Unions",
            "subcategory":"Investment Brokerage",
            "type":"Services"
        }
    ],
    "sg:phone":"+41 52 649 27 77",
    "sg:postcode":"8243",
    "sg:province":"Schaffhausen",
    "sg:tags":[
        "development",
        "electronics"
    ],
    "wof:name":"Ren\u00e9 Br\u00fchlmann Gmbh",
    "wof:placetype":"venue"
},
  "geometry": {"coordinates":[8.6579084396,47.7843818665],"type":"Point"}
}