{
  "type": "Feature",
  "properties": {
    "iso:country":"CH",
    "sg:address":"Arquebuse Rue De L' 17bis 1204 Gen\u00e8ve. Postfach",
    "sg:city":"Gen\u00e8ve",
    "sg:orig_category":"Sonstiger Grosshandel",
    "sg:postcode":"1204",
    "sg:province":"Gen\u00e8ve",
    "wof:name":"Sabim Sa.",
    "wof:placetype":"venue"
},
  "geometry": {"coordinates":[6.1555218697,46.1997489929],"type":"Point"}
}