{
  "type": "Feature",
  "properties": {
    "iso:country":"CH",
    "sg:address":"Hauptstr. 85",
    "sg:city":"Bettingen",
    "sg:orig_category":"Grosshandel mit Nahrungsmitteln, Getr\u00e4nken U Tabakwaren ohne ausgepr\u00e4gten Schwerpunkt",
    "sg:postcode":"4126",
    "sg:province":"Basel-Stadt",
    "wof:name":"Kurt Neuschwander",
    "wof:placetype":"venue"
},
  "geometry": {"coordinates":[7.6646609306,47.5707588196],"type":"Point"}
}