{
  "type": "Feature",
  "properties": {
    "iso:country":"CH",
    "sg:address":"Sonnenbergstrasse 83 8032 Z\u00fcrich. Postfach",
    "sg:city":"Z\u00fcrich",
    "sg:orig_category":"G\u00fcterbef\u00f6rderung im Strassenverkehr",
    "sg:phone":"+41 12665252",
    "sg:postcode":"8030",
    "wof:name":"Vpod Verband Des Personals Oeffentl. Dienste",
    "wof:placetype":"venue"
},
  "geometry": {"coordinates":[8.5667314529,47.3710899353],"type":"Point"}
}