{
  "type": "Feature",
  "properties": {
    "iso:country":"CH",
    "sg:address":"Route De Tavel 17",
    "sg:city":"Fribourg",
    "sg:orig_category":"RESTAURANTS: TEA-ROOMS",
    "sg:phone":"+41 26 481 33 66",
    "sg:postcode":"1700",
    "sg:province":"Fribourg",
    "wof:name":"Ristorante Pizzeria Da Vinci Sa",
    "wof:placetype":"venue"
},
  "geometry": {"coordinates":[7.1777892113,46.8108940125],"type":"Point"}
}