{
  "type": "Feature",
  "properties": {
    "iso:country":"CH",
    "sg:address":"Riedmattstrasse",
    "sg:city":"R\u00fcmlang",
    "sg:orig_category":"Instandhaltung U Reparatur von Automobilen",
    "sg:phone":"+41 79 666 46 64",
    "sg:postcode":"8153",
    "sg:province":"Z\u00fcrich",
    "wof:name":"Auto R\u00fcmlang Bracci & Pilla",
    "wof:placetype":"venue"
},
  "geometry": {"coordinates":[8.5220899582,47.4606933594],"type":"Point"}
}