{
  "type": "Feature",
  "properties": {
    "iso:country":"CH",
    "sg:address":"Bernstrasse 160",
    "sg:city":"Rothrist",
    "sg:orig_category":"Handelsvermittlung U Grosshandel Sonstiger Grosshandel",
    "sg:phone":"+41 62 785 10 10",
    "sg:postcode":"4852",
    "sg:province":"Aargau",
    "wof:name":"Galactica Ag",
    "wof:placetype":"venue"
},
  "geometry": {"coordinates":[7.8811001778,47.3052101135],"type":"Point"}
}