{
  "type": "Feature",
  "properties": {
    "iso:country":"CH",
    "sg:address":"Avenue Des Glariers 41 1860 Aigle Case Postale 15",
    "sg:city":"Aigle",
    "sg:orig_category":"Instandhaltung U Reparatur von Automobilen",
    "sg:phone":"+41 24 466 14 21",
    "sg:postcode":"1860",
    "sg:province":"Vaud",
    "wof:name":"Autochablais S\u00e0rl",
    "wof:placetype":"venue"
},
  "geometry": {"coordinates":[6.9727911949,46.3182945251],"type":"Point"}
}