{
  "type": "Feature",
  "properties": {
    "iso:country":"CH",
    "sg:address":"Landstuhl 388",
    "sg:city":"Neuenegg",
    "sg:orig_category":"Zimmerei, Dachdeckerei, Bauspenglerei U Abdichtung",
    "sg:phone":"+41 31 742 02 06",
    "sg:postcode":"3176",
    "sg:province":"Bern",
    "wof:name":"Htech Gmbh",
    "wof:placetype":"venue"
},
  "geometry": {"coordinates":[7.3274440765,46.9032020569],"type":"Point"}
}