{
  "type": "Feature",
  "properties": {
    "iso:country":"CH",
    "sg:address":"Dorfstrasse 49 3123 Belp. Postfach 87",
    "sg:city":"Belp",
    "sg:orig_category":"Detailhandel mit Damenbekleidung Detailhandel mit Herrenbekleidung",
    "sg:phone":"+41 27 957 22 25",
    "sg:postcode":"3123",
    "sg:province":"Bern",
    "wof:name":"Arthur Imseng Mass-& Konfektionsgesch\u00e4ft",
    "wof:placetype":"venue"
},
  "geometry": {"coordinates":[7.933673,46.111717],"type":"Point"}
}