{
  "type": "Feature",
  "properties": {
    "iso:country":"CH",
    "sg:address":"3154 R\u00fcschegg Graben. Postfach",
    "sg:city":"Hirschhorn",
    "sg:orig_category":"Zimmerei, Dachdeckerei, Bauspenglerei U Abdichtung",
    "sg:phone":"+41 71 333 21 22",
    "sg:postcode":"3153",
    "sg:province":"Bern",
    "wof:name":"Hans Schiess Bedachungen Ag",
    "wof:placetype":"venue"
},
  "geometry": {"coordinates":[9.3884706497,47.3888816833],"type":"Point"}
}