{
  "type": "Feature",
  "properties": {
    "iso:country":"CH",
    "sg:address":"Rue De Tarascon 14",
    "sg:city":"Porrentruy",
    "sg:orig_category":"Arztpraxen",
    "sg:phone":"+41 32 466 77 88",
    "sg:postcode":"2900",
    "sg:province":"Jura",
    "wof:name":"Dr M\u00e9d.pierre-olivier Cattin M\u00e9decin Sp\u00e9cialiste Fmh",
    "wof:placetype":"venue"
},
  "geometry": {"coordinates":[7.068861,47.410488],"type":"Point"}
}