{
  "type": "Feature",
  "properties": {
    "iso:country":"CH",
    "sg:address":"Nordringstrasse 9 4702 Oensingen. Postfach",
    "sg:city":"Oensingen",
    "sg:orig_category":"Aktivit\u00e4ten der Generalunternehmen im Baugewerbe",
    "sg:phone":"+41 62 396 21 51",
    "sg:postcode":"4702",
    "sg:province":"Solothurn",
    "wof:name":"Sch\u00e4r Modulbau Gmbh Generalunternehmung Im Bereich An Und Nebenbauten, Garagen Usw",
    "wof:placetype":"venue"
},
  "geometry": {"coordinates":[7.710473,47.281048],"type":"Point"}
}