{
  "type": "Feature",
  "properties": {
    "iso:country":"CH",
    "sg:address":"Via San Giorgio 2",
    "sg:city":"Vacallo",
    "sg:orig_category":"Elektroinstallation Herstellung von nachrichtentechnischen Ger\u00e4ten U Einrichtungen",
    "sg:phone":"+41 91 683 91 36",
    "sg:postcode":"6833",
    "sg:province":"Ticino",
    "wof:name":"Mascetti Mirto Telecom",
    "wof:placetype":"venue"
},
  "geometry": {"coordinates":[9.0295248032,45.8439941406],"type":"Point"}
}