{
  "type": "Feature",
  "properties": {
    "iso:country":"CH",
    "sg:address":"Balmerstrasse 8",
    "sg:city":"Bern",
    "sg:orig_category":"Wirtschaftspr\u00fcfung, Steuerberatung U Treuhand",
    "sg:postcode":"3006",
    "sg:province":"Bern",
    "wof:name":"Marti Gottfried Treuhand Gmbh",
    "wof:placetype":"venue"
},
  "geometry": {"coordinates":[7.4754118919,46.9471817017],"type":"Point"}
}