{
  "type": "Feature",
  "properties": {
    "iso:country":"CH",
    "sg:address":"Wildi",
    "sg:city":"Visp",
    "sg:orig_category":"Technische, physikalische U chemische Untersuchung",
    "sg:phone":"+41 81 756 24 75",
    "sg:postcode":"3930",
    "sg:province":"Valais",
    "wof:name":"Rohrer Dr. E. Ag",
    "wof:placetype":"venue"
},
  "geometry": {"coordinates":[9.4626941681,47.169380188],"type":"Point"}
}