{
  "type": "Feature",
  "properties": {
    "iso:country":"CH",
    "sg:address":"Bahnhof-park 3",
    "sg:city":"Baar",
    "sg:orig_category":"Softwareentwicklung U beratung",
    "sg:postcode":"6340",
    "sg:province":"Zug",
    "wof:name":"Frank's Pc-world F\u00fcr Pc, Mac & Zubeh\u00f6r, Inh. Frank A. Hard- U. Software Usw.; Vertrieb",
    "wof:placetype":"venue"
},
  "geometry": {"coordinates":[7.9529628754,47.5476913452],"type":"Point"}
}