{
  "type": "Feature",
  "properties": {
    "iso:country":"CH",
    "sg:address":"St. Urbanstrasse 3",
    "sg:city":"Langenthal",
    "sg:orig_category":"Detailhandel mit Damenbekleidung Detailhandel mit Herrenbekleidung",
    "sg:phone":"+41 62 916 20 70",
    "sg:postcode":"4900",
    "sg:province":"Bern",
    "wof:name":"Charles V\u00f6gele Mode Ag",
    "wof:placetype":"venue"
},
  "geometry": {"coordinates":[7.7899980545,47.2122573853],"type":"Point"}
}