{
  "type": "Feature",
  "properties": {
    "iso:country":"CH",
    "sg:address":"Aspstrasse 12",
    "sg:city":"Seuzach",
    "sg:orig_category":"Autogaragen",
    "sg:phone":"+41 56 282 56 43",
    "sg:postcode":"8472",
    "sg:province":"Z\u00fcrich",
    "wof:name":"Thomas Keller Garage",
    "wof:placetype":"venue"
},
  "geometry": {"coordinates":[8.278353,47.498287],"type":"Point"}
}