{
  "type": "Feature",
  "properties": {
    "iso:country":"CH",
    "sg:address":"Landstrasse 105 9490 Vaduz. Postfach",
    "sg:city":"Vaduz",
    "sg:orig_category":"Versicherungen Generalagenturen",
    "sg:phone":"+41 75 232 73 76",
    "sg:postcode":"9490",
    "wof:name":"Protekta Rechtsschutz-versich. Repr\u00e4sentanz",
    "wof:placetype":"venue"
},
  "geometry": {"coordinates":[9.5110502243,47.1507873535],"type":"Point"}
}