{
  "type": "Feature",
  "properties": {
    "addr:full":"Les Rennauds Yvorne Vaud 1853",
    "addr:housenumber":"1853",
    "iso:country":"CH",
    "sg:address":"Les Rennauds",
    "sg:city":"Yvorne",
    "sg:orig_category":"Betrieb von Taxis G\u00fcterbef\u00f6rderung im Strassenverkehr",
    "sg:phone":"+41 24 466 64 45",
    "sg:postcode":"1853",
    "sg:province":"Vaud",
    "wof:name":"Echenard Nicole",
    "wof:placetype":"venue"
},
  "geometry": {"coordinates":[6.956691,46.331711],"type":"Point"}
}