{
  "type": "Feature",
  "properties": {
    "iso:country":"CH",
    "sg:address":"Burgstrasse 28 8750 Glarus. Postfach",
    "sg:city":"Glarus",
    "sg:orig_category":"Finanzierungsinstitutionen",
    "sg:postcode":"8750",
    "sg:province":"Glarus",
    "wof:name":"Ehrhardt Dr. Jens Finanz Ag Finanz- U. Anlageberatung, Finanzverwaltung Usw.",
    "wof:placetype":"venue"
},
  "geometry": {"coordinates":[8.5429592133,47.3736686707],"type":"Point"}
}