{
  "type": "Feature",
  "properties": {
    "iso:country":"CH",
    "sg:address":"Kropfackerstrasse 18",
    "sg:city":"Berneck",
    "sg:orig_category":"Organisationen des Gesundheitswesen",
    "sg:phone":"+41 81 756 50 21",
    "sg:postcode":"9442",
    "sg:province":"St. Gallen",
    "wof:name":"Samariterverein",
    "wof:placetype":"venue"
},
  "geometry": {"coordinates":[9.6199302673,47.4253692627],"type":"Point"}
}