{
  "type": "Feature",
  "properties": {
    "iso:country":"CH",
    "sg:address":"Zugerstrasse 51",
    "sg:city":"Horgen",
    "sg:classifiers":[
        {
            "category":"Professional",
            "subcategory":"Engineering",
            "type":"Services"
        }
    ],
    "sg:phone":"+41 17254773",
    "sg:postcode":"8810",
    "sg:province":"Z\u00fcrich",
    "sg:tags":[
        "organizational",
        "information",
        "consulting",
        "technology"
    ],
    "wof:name":"Engert's Erben",
    "wof:placetype":"venue"
},
  "geometry": {"coordinates":[8.6001644135,47.2583885193],"type":"Point"}
}