{
  "type": "Feature",
  "properties": {
    "iso:country":"CH",
    "sg:address":"Cit\u00e9-devant Rue 2 1005 Lausanne. Postfach",
    "sg:city":"Lausanne",
    "sg:orig_category":"Reinigungsgewerbe",
    "sg:phone":"+41 21 320 07 00",
    "sg:postcode":"1005",
    "sg:province":"Vaud",
    "wof:name":"Desinfect-it, Gumy Serge",
    "wof:placetype":"venue"
},
  "geometry": {"coordinates":[6.635283947,46.5229759216],"type":"Point"}
}