{
  "type": "Feature",
  "properties": {
    "iso:country":"CH",
    "sg:address":"Friedhofstrasse 4",
    "sg:city":"Urdorf",
    "sg:classifiers":[
        {
            "category":"Education",
            "subcategory":"Library",
            "type":"Public Place"
        }
    ],
    "sg:phone":"+41 17342253",
    "sg:postcode":"8902",
    "sg:province":"Z\u00fcrich",
    "sg:tags":[
        "u",
        "bibliotheken",
        "archive"
    ],
    "wof:name":"Gemeindebibliothek",
    "wof:placetype":"venue"
},
  "geometry": {"coordinates":[8.422427,47.382732],"type":"Point"}
}