{
  "type": "Feature",
  "properties": {
    "iso:country":"CH",
    "sg:address":"Via Soave 8",
    "sg:city":"Lugano",
    "sg:orig_category":"Detailhandel mit Schuhen Sonstiger Grosshandel",
    "sg:phone":"+41 91 922 02 43",
    "sg:postcode":"6900",
    "sg:province":"Ticino",
    "wof:name":"Altalena Sa",
    "wof:placetype":"venue"
},
  "geometry": {"coordinates":[8.9503679276,46.0045852661],"type":"Point"}
}