{
  "type": "Feature",
  "properties": {
    "addr:full":"Bergstrasse 125 Z\u00fcrich Z\u00fcrich 8032",
    "addr:housenumber":"125",
    "addr:postcode":"8032",
    "addr:street":"Bergstrasse",
    "iso:country":"CH",
    "sg:address":"Bergstrasse 125",
    "sg:city":"Z\u00fcrich",
    "sg:orig_category":"Bauingenieurb\u00fcros Tiefbau Bauingenieurb\u00fcros allgemein",
    "sg:phone":"+41 12514294",
    "sg:postcode":"8032",
    "sg:province":"Z\u00fcrich",
    "wof:name":"Claude Racine Ingenieurb\u00fcro",
    "wof:placetype":"venue"
},
  "geometry": {"coordinates":[8.564859,47.367325],"type":"Point"}
}