{
  "type": "Feature",
  "properties": {
    "iso:country":"CH",
    "sg:address":"Sonderstrasse 4",
    "sg:city":"Eggersriet",
    "sg:classifiers":[
        {
            "category":"Professional",
            "subcategory":"Employment Agencies",
            "type":"Services"
        }
    ],
    "sg:phone":"+41 71 877 34 03",
    "sg:postcode":"9034",
    "sg:province":"St. Gallen",
    "sg:tags":[
        "personal",
        "u",
        "stellenvermittlung"
    ],
    "wof:name":"Stellen-express Boesch",
    "wof:placetype":"venue"
},
  "geometry": {"coordinates":[9.4775266647,47.4409866333],"type":"Point"}
}