{
  "type": "Feature",
  "properties": {
    "iso:country":"CH",
    "sg:address":"Br\u00fcnigstrasse 89",
    "sg:city":"Lungern",
    "sg:orig_category":"Detailhandel mit Blumen U Pflanzen Fachdetailhandel in Verkaufsr\u00e4umen",
    "sg:phone":"+41 41 678 14 69",
    "sg:postcode":"6078",
    "sg:province":"Obwalden",
    "wof:name":"Bluem\u00e4-egg\u00e4, Vogler Maria",
    "wof:placetype":"venue"
},
  "geometry": {"coordinates":[8.159823,46.785862],"type":"Point"}
}