{
  "type": "Feature",
  "properties": {
    "iso:country":"CH",
    "sg:address":"Stadthausstrasse 2 4950 Huttwil. Postfach",
    "sg:city":"Huttwil",
    "sg:orig_category":"Sonstige mit Sport verbundene T\u00e4tigkeiten",
    "sg:postcode":"4950",
    "sg:province":"Bern",
    "wof:name":"Rx Alpha Ag",
    "wof:placetype":"venue"
},
  "geometry": {"coordinates":[7.8676400185,47.3434410095],"type":"Point"}
}