{
  "type": "Feature",
  "properties": {
    "iso:country":"CH",
    "sg:address":"Dreilindenstrasse 6",
    "sg:city":"Meggen",
    "sg:orig_category":"Elektroinstallation",
    "sg:phone":"+41 41 377 12 14",
    "sg:postcode":"6045",
    "sg:province":"Luzern",
    "wof:name":"Krieger Erwin",
    "wof:placetype":"venue"
},
  "geometry": {"coordinates":[8.3709278107,47.0468177795],"type":"Point"}
}