{
  "type": "Feature",
  "properties": {
    "iso:country":"CH",
    "sg:address":"Zweierestrasse 1",
    "sg:city":"Niederrohrdorf",
    "sg:orig_category":"Instandhaltung U Reparatur von Automobilen",
    "sg:phone":"+41 56 496 46 57",
    "sg:postcode":"5443",
    "sg:province":"Aargau",
    "wof:name":"Garage Br\u00e4ndle Autoreparaturwerkst\u00e4tte",
    "wof:placetype":"venue"
},
  "geometry": {"coordinates":[8.3073501587,47.4233131409],"type":"Point"}
}