{
  "type": "Feature",
  "properties": {
    "iso:country":"CH",
    "sg:address":"Fontanasura 30",
    "sg:city":"Tarasp",
    "sg:orig_category":"Allgemeiner Hochbau Br\u00fccken U Tunnelbau",
    "sg:phone":"+41 32 751 12 91",
    "sg:postcode":"7553",
    "sg:province":"Graubunden",
    "wof:name":"Batigroup Ag",
    "wof:placetype":"venue"
},
  "geometry": {"coordinates":[7.092341,47.062595],"type":"Point"}
}