{
  "type": "Feature",
  "properties": {
    "iso:country":"CH",
    "sg:address":"Avenue Jomini 22 1000 Lausanne. Postfach",
    "sg:city":"Lausanne",
    "sg:orig_category":"Betrieb U technische Hilfsdienste des Kultur U Unterhaltungswesens",
    "sg:postcode":"1003",
    "sg:province":"Vaud",
    "wof:name":"Association Funky Chill",
    "wof:placetype":"venue"
},
  "geometry": {"coordinates":[6.627806,46.529202],"type":"Point"}
}