{
  "type": "Feature",
  "properties": {
    "iso:country":"CH",
    "sg:address":"Schw\u00e4rzistrasse 9",
    "sg:city":"N\u00e4fels",
    "sg:orig_category":"Non-Classified Establishments",
    "sg:postcode":"8752",
    "sg:province":"Glarus",
    "wof:name":"Gvn Glarner Volksblatt Ag",
    "wof:placetype":"venue"
},
  "geometry": {"coordinates":[9.0709791183,47.1067047119],"type":"Point"}
}