{
  "type": "Feature",
  "properties": {
    "iso:country":"CH",
    "sg:address":"1892",
    "sg:city":"Lavey-village",
    "sg:orig_category":"Sportvereine Ski",
    "sg:phone":"+41 32 931 35 23",
    "sg:postcode":"1892",
    "sg:province":"Vaud",
    "wof:name":"Ski-club Le Locle",
    "wof:placetype":"venue"
},
  "geometry": {"coordinates":[6.751224041,47.0494384766],"type":"Point"}
}