{
  "type": "Feature",
  "properties": {
    "addr:full":"Route De Poliez-pittet Dommartin Vaud 1041",
    "addr:postcode":"1041",
    "addr:street":"Route De Poliez-Pittet",
    "iso:country":"CH",
    "sg:address":"Route De Poliez-pittet",
    "sg:city":"Dommartin",
    "sg:orig_category":"Dachdeckerei Zimmerei, Dachdeckerei, Bauspenglerei U Abdichtung",
    "sg:phone":"+41 21 881 53 10",
    "sg:postcode":"1041",
    "sg:province":"Vaud",
    "wof:name":"Carrard Alain",
    "wof:placetype":"venue"
},
  "geometry": {"coordinates":[6.691148,46.638432],"type":"Point"}
}