{
  "type": "Feature",
  "properties": {
    "iso:country":"CH",
    "sg:address":"Gundeldingerstrasse 432",
    "sg:city":"Basel",
    "sg:orig_category":"Religi\u00f6se Vereinigungen",
    "sg:postcode":"4053",
    "sg:province":"Basel-Stadt",
    "wof:name":"Verein Anatolisches Informations Und Dokumentationszentrum (vaid)",
    "wof:placetype":"venue"
},
  "geometry": {"coordinates":[7.6000418663,47.5378723145],"type":"Point"}
}