{
  "type": "Feature",
  "properties": {
    "iso:country":"CH",
    "sg:address":"Gewerbepark 5506 M\u00e4genwil. Postfach 109",
    "sg:city":"M\u00e4genwil",
    "sg:orig_category":"Grosshandel mit sonstigen Halbwaren Herstellung von Platten, Folien, Schl\u00e4uchen U Profilen aus Kunst",
    "sg:phone":"+41 62 896 45 45",
    "sg:postcode":"5506",
    "sg:province":"Aargau",
    "wof:name":"Neoplastica Ag",
    "wof:placetype":"venue"
},
  "geometry": {"coordinates":[8.2297153473,47.411441803],"type":"Point"}
}