{
  "type": "Feature",
  "properties": {
    "iso:country":"CH",
    "sg:address":"Hauptstrasse 87 4702 Oensingen. Postfach",
    "sg:city":"Oensingen",
    "sg:orig_category":"RESTAURANTS: TEA-ROOMS",
    "sg:postcode":"4702",
    "sg:province":"Solothurn",
    "wof:name":"Aktas Orhan Restaurant Cartier",
    "wof:placetype":"venue"
},
  "geometry": {"coordinates":[7.7260937691,47.2904548645],"type":"Point"}
}