{
  "type": "Feature",
  "properties": {
    "iso:country":"CH",
    "sg:address":"Hauptstrasse",
    "sg:city":"Wimmis",
    "sg:orig_category":"RESTAURANTS: TEA-ROOMS",
    "sg:phone":"+41 33 657 15 15",
    "sg:postcode":"3752",
    "sg:province":"Bern",
    "wof:name":"Restaurant Niesen, W. Mani",
    "wof:placetype":"venue"
},
  "geometry": {"coordinates":[7.6480197906,46.6789932251],"type":"Point"}
}