{
  "type": "Feature",
  "properties": {
    "iso:country":"CH",
    "sg:address":"Place Du Nord.",
    "sg:city":"Chexbres",
    "sg:orig_category":"RESTAURANTS: TEA-ROOMS",
    "sg:postcode":"1071",
    "sg:province":"Vaud",
    "wof:name":"Burnier Jean-pierre Caf\u00e9-restaurant Le Surf",
    "wof:placetype":"venue"
},
  "geometry": {"coordinates":[6.926030159,46.4337882996],"type":"Point"}
}