{
  "type": "Feature",
  "properties": {
    "iso:country":"CH",
    "sg:address":"6964",
    "sg:city":"Davesco-soragno",
    "sg:orig_category":"Bauspenglerei Sanit\u00e4rinstallation",
    "sg:phone":"+41 91 941 79 48",
    "sg:postcode":"6964",
    "sg:province":"Ticino",
    "wof:name":"Casimiro Alberti Imp.sanitari & Lattoniere",
    "wof:placetype":"venue"
},
  "geometry": {"coordinates":[8.98953,46.032558],"type":"Point"}
}