{
  "type": "Feature",
  "properties": {
    "iso:country":"CH",
    "sg:address":"Hofgraben 5 7000 Chur. Postfach",
    "sg:city":"Chur",
    "sg:orig_category":"Polizei Verwaltung der Rechtspflege, Gerichte",
    "sg:phone":"+41 71 229 37 08",
    "sg:postcode":"7001",
    "sg:province":"Graubunden",
    "wof:name":"Kantonales Justiz-& Polizeidepartement",
    "wof:placetype":"venue"
},
  "geometry": {"coordinates":[9.3743181229,47.4226722717],"type":"Point"}
}