{
  "type": "Feature",
  "properties": {
    "iso:country":"CH",
    "sg:address":"Gerberngasse 23",
    "sg:city":"Bern",
    "sg:orig_category":"Softwareentwicklung U beratung",
    "sg:phone":"+41 55 214 33 33",
    "sg:postcode":"3011",
    "sg:province":"Bern",
    "wof:name":"Cnlab Software Ag",
    "wof:placetype":"venue"
},
  "geometry": {"coordinates":[8.8203449249,47.2257270813],"type":"Point"}
}