{
  "type": "Feature",
  "properties": {
    "iso:country":"CH",
    "sg:address":"Les Monts",
    "sg:city":"Bex",
    "sg:orig_category":"Sportvereine Sch\u00fctzen",
    "sg:postcode":"1880",
    "sg:province":"Vaud",
    "wof:name":"St\u00e9 De Tir Armes De Guerre",
    "wof:placetype":"venue"
},
  "geometry": {"coordinates":[7.039899826,46.2424507141],"type":"Point"}
}