{
  "type": "Feature",
  "properties": {
    "iso:country":"CH",
    "sg:address":"Route De Suisse 97",
    "sg:city":"Versoix",
    "sg:orig_category":"Arztpraxen",
    "sg:phone":"+41 26 912 81 40",
    "sg:postcode":"1290",
    "sg:province":"Gen\u00e8ve",
    "wof:name":"Dr M\u00e9d. Jacques Cardinaux M\u00e9decin Sp\u00e9cialiste Fmh",
    "wof:placetype":"venue"
},
  "geometry": {"coordinates":[7.055702,46.616909],"type":"Point"}
}