{
  "type": "Feature",
  "properties": {
    "iso:country":"CH",
    "sg:address":"Lausanne Route De 13",
    "sg:city":"Echallens",
    "sg:orig_category":"Unclassifiable Establishments",
    "sg:postcode":"1040",
    "sg:province":"Vaud",
    "wof:name":"Fondation Compl\u00e9mentaire De Pr\u00e9voyance Pour La Retraite Anticip\u00e9e En Faveurdu Personnel De La Banque",
    "wof:placetype":"venue"
},
  "geometry": {"coordinates":[6.6343631744,46.6408653259],"type":"Point"}
}