{
  "type": "Feature",
  "properties": {
    "iso:country":"CH",
    "sg:address":"Rue Ami-l\u00e9vrier 15",
    "sg:city":"Gen\u00e8ve",
    "sg:orig_category":"Linienflugverkehr Luftfahrt",
    "sg:phone":"+41 22 731 95 60",
    "sg:postcode":"1201",
    "sg:province":"Gen\u00e8ve",
    "wof:name":"Kuwait Airways Corporation, Kuwait, Succursale De Gen\u00e8ve",
    "wof:placetype":"venue"
},
  "geometry": {"coordinates":[6.1468558311,46.208896637],"type":"Point"}
}