{
  "type": "Feature",
  "properties": {
    "iso:country":"CH",
    "sg:address":"Laubeggstrasse 70",
    "sg:city":"Bern",
    "sg:orig_category":"Sonstige mit Sport verbundene T\u00e4tigkeiten",
    "sg:postcode":"3006",
    "sg:province":"Bern",
    "wof:name":"Stiftung Volksheim Rapperswil",
    "wof:placetype":"venue"
},
  "geometry": {"coordinates":[8.816280365,47.2270050049],"type":"Point"}
}