{
  "type": "Feature",
  "properties": {
    "iso:country":"CH",
    "sg:address":"Hafenstrasse 20",
    "sg:city":"Romanshorn",
    "sg:orig_category":"Schiffs U Bootsbau",
    "sg:phone":"+41 71 463 29 66",
    "sg:postcode":"8590",
    "sg:province":"Thurgau",
    "wof:name":"Yachtwerft Und Nauticprodukte D\u00fctschler W.",
    "wof:placetype":"venue"
},
  "geometry": {"coordinates":[9.3770437241,47.5669403076],"type":"Point"}
}