{
  "type": "Feature",
  "properties": {
    "iso:country":"CH",
    "sg:address":"F\u00e4senstaubstrasse 15",
    "sg:city":"Schaffhausen",
    "sg:orig_category":"Architektur U Ingenieurb\u00fcros",
    "sg:postcode":"8200",
    "sg:province":"Schaffhausen",
    "wof:name":"Beratungsb\u00fcro Waeber Tatiana",
    "wof:placetype":"venue"
},
  "geometry": {"coordinates":[8.627452,47.69479],"type":"Point"}
}