{
  "type": "Feature",
  "properties": {
    "iso:country":"CH",
    "sg:address":"Selnaustrasse 30 8001 Z\u00fcrich. Postfach",
    "sg:city":"Z\u00fcrich",
    "sg:orig_category":"Effekten U Warenterminb\u00f6rsen Effektenvermittlung Broker",
    "sg:phone":"+41 22 703 90 00",
    "sg:postcode":"8021",
    "sg:province":"Z\u00fcrich",
    "wof:name":"Prudential-bache International Ltd., Londres,succle De Gen\u00e8ve",
    "wof:placetype":"venue"
},
  "geometry": {"coordinates":[6.1556987762,46.1962547302],"type":"Point"}
}