{
  "type": "Feature",
  "properties": {
    "iso:country":"CH",
    "sg:address":"Ritterstrasse 9",
    "sg:city":"Littau",
    "sg:orig_category":"Vereine Quartier",
    "sg:phone":"+41 41 250 28 83",
    "sg:postcode":"6014",
    "sg:province":"Luzern",
    "wof:name":"Quartierverein Am Sonnenberg",
    "wof:placetype":"venue"
},
  "geometry": {"coordinates":[8.25963974,47.0514259338],"type":"Point"}
}