{
  "type": "Feature",
  "properties": {
    "iso:country":"CH",
    "sg:address":"G\u00e4rischstrasse 1",
    "sg:city":"Bellach",
    "sg:orig_category":"RESTAURANTS: TEA-ROOMS",
    "sg:postcode":"4512",
    "sg:province":"Solothurn",
    "wof:name":"Knuchel Walter",
    "wof:placetype":"venue"
},
  "geometry": {"coordinates":[9.0534296036,47.4628791809],"type":"Point"}
}