{
  "type": "Feature",
  "properties": {
    "iso:country":"CH",
    "sg:address":"Luzernerstrasse 49",
    "sg:city":"Neudorf",
    "sg:orig_category":"G\u00fcterbef\u00f6rderung im Strassenverkehr Mahl U Sch\u00e4lm\u00fchlen",
    "sg:phone":"+41 79 643 97 83",
    "sg:postcode":"6025",
    "sg:province":"Luzern",
    "wof:name":"Viktor Winiger M\u00fchle & Transporte",
    "wof:placetype":"venue"
},
  "geometry": {"coordinates":[8.2090539932,47.177482605],"type":"Point"}
}