{
  "type": "Feature",
  "properties": {
    "iso:country":"CH",
    "sg:address":"Avenue Des Boveresses 48 1010 Lausanne Case Postale 111",
    "sg:city":"Lausanne",
    "sg:orig_category":"Elektroinstallation Herstellung von Elektromotoren, Generatoren U Transformatoren",
    "sg:phone":"+41 21 651 20 00",
    "sg:postcode":"1010",
    "sg:province":"Vaud",
    "wof:name":"Sedelec Sa Lausanne",
    "wof:placetype":"venue"
},
  "geometry": {"coordinates":[6.666847229,46.5355873108],"type":"Point"}
}