{
  "type": "Feature",
  "properties": {
    "iso:country":"CH",
    "sg:address":"Juch\u00e4cherstrasse 7 8966 Oberwil Ag. Postfach",
    "sg:city":"Lieli",
    "sg:orig_category":"Allgemeiner Hochbau Architektur U Ingenieurb\u00fcros",
    "sg:phone":"+41 56 641 22 22",
    "sg:postcode":"8966",
    "sg:province":"Aargau",
    "wof:name":"Le Soleil Ag",
    "wof:placetype":"venue"
},
  "geometry": {"coordinates":[8.395734,47.341656],"type":"Point"}
}