{
  "type": "Feature",
  "properties": {
    "iso:country":"CH",
    "sg:address":"Merguin Rue Achille- 32",
    "sg:city":"Porrentruy",
    "sg:orig_category":"Architektur U Ingenieurb\u00fcros",
    "sg:phone":"+41 32 466 78 80",
    "sg:postcode":"2900",
    "sg:province":"Jura",
    "wof:name":"Henzelin Germain Sa, Succursale De Porrentruy",
    "wof:placetype":"venue"
},
  "geometry": {"coordinates":[7.070565,47.414566],"type":"Point"}
}