{
  "type": "Feature",
  "properties": {
    "iso:country":"CH",
    "sg:address":"Bodenacherstrasse 67 8121 Benglen. Postfach",
    "sg:city":"Benglen",
    "sg:orig_category":"Pensionskassen",
    "sg:postcode":"8121",
    "sg:province":"Z\u00fcrich",
    "wof:name":"Pensionskasse Der B+l Gruppe",
    "wof:placetype":"venue"
},
  "geometry": {"coordinates":[8.6386899948,47.3619422913],"type":"Point"}
}