{
  "type": "Feature",
  "properties": {
    "iso:country":"CH",
    "sg:address":"Sonnmattstrasse 13",
    "sg:city":"Bottmingen",
    "sg:orig_category":"Detailhandel mit M\u00f6beln Dienstleistungen im Gartenbau",
    "sg:phone":"+41 61 422 19 11",
    "sg:postcode":"4103",
    "sg:province":"Basel-Landschaft",
    "wof:name":"Christian Peter Schmidlin Garten Gestaltung & Pflege",
    "wof:placetype":"venue"
},
  "geometry": {"coordinates":[7.5665769577,47.5285186768],"type":"Point"}
}