{
  "type": "Feature",
  "properties": {
    "iso:country":"CH",
    "sg:address":"1647",
    "sg:city":"Corbi\u00e8res",
    "sg:orig_category":"Herstellung von Reiseartikeln, Leder U Sattlerwaren Innendekorationsateliers",
    "sg:phone":"+41 71 855 18 03",
    "sg:postcode":"1647",
    "sg:province":"Fribourg",
    "wof:name":"Robert Beerli Innenausstattungen Sattlerei",
    "wof:placetype":"venue"
},
  "geometry": {"coordinates":[9.5429334641,47.4775428772],"type":"Point"}
}