{
  "type": "Feature",
  "properties": {
    "addr:full":"Zweierstr. 35 Z\u00fcrich Z\u00fcrich 8022",
    "addr:housenumber":"35",
    "addr:postcode":"8022",
    "addr:street":"Zweierstr.",
    "iso:country":"CH",
    "sg:address":"Zweierstr. 35",
    "sg:city":"Z\u00fcrich",
    "sg:classifiers":[
        {
            "category":"Banks & Credit Unions",
            "subcategory":"Bank",
            "type":"Services"
        }
    ],
    "sg:phone":"+41 12414433",
    "sg:postcode":"8022",
    "sg:province":"Z\u00fcrich",
    "wof:name":"Banco Nacional De Cuba",
    "wof:placetype":"venue"
},
  "geometry": {"coordinates":[8.525621,47.372635],"type":"Point"}
}