{
  "type": "Feature",
  "properties": {
    "iso:country":"CH",
    "sg:address":"Rue Emer-de-vattel 60 2000 Neuenburg. Postfach",
    "sg:city":"Neuenburg",
    "sg:orig_category":"Sonstige mit Sport verbundene T\u00e4tigkeiten",
    "sg:postcode":"2000",
    "sg:province":"Neuch\u00e2tel",
    "wof:name":"Groupe De Vol \u00e0 Moteur De Neuch\u00e2tel",
    "wof:placetype":"venue"
},
  "geometry": {"coordinates":[6.9131917953,46.9931411743],"type":"Point"}
}