{
  "type": "Feature",
  "properties": {
    "iso:country":"CH",
    "sg:address":"Ruessenstrasse 5a",
    "sg:city":"Baar",
    "sg:orig_category":"Grosshandel mit pharmazeutischen Erzeugnissen, medizinischen U orthop\u00e4dischen Artikeln Herstellung v",
    "sg:phone":"+41 41 760 07 45",
    "sg:postcode":"6340",
    "sg:province":"Zug",
    "wof:name":"Somapharm Ag",
    "wof:placetype":"venue"
},
  "geometry": {"coordinates":[8.5635023117,47.2124977112],"type":"Point"}
}