{
  "type": "Feature",
  "properties": {
    "iso:country":"CH",
    "sg:address":"Burgstrasse 1",
    "sg:city":"Merenschwand",
    "sg:orig_category":"Sportvereine Turnen",
    "sg:phone":"+41 56 664 08 71",
    "sg:postcode":"5634",
    "sg:province":"Aargau",
    "wof:name":"Turnverein Stv Auw",
    "wof:placetype":"venue"
},
  "geometry": {"coordinates":[8.3731470108,47.2578315735],"type":"Point"}
}