{
  "type": "Feature",
  "properties": {
    "iso:country":"CH",
    "sg:address":"Via Della Pace 16a",
    "sg:city":"Locarno",
    "sg:orig_category":"Arztpraxen",
    "sg:phone":"+41 79 337 10 52",
    "sg:postcode":"6600",
    "sg:province":"Ticino",
    "wof:name":"Dott.med.lorenzo Bianchetti Specialista Fmh",
    "wof:placetype":"venue"
},
  "geometry": {"coordinates":[8.799188,46.166275],"type":"Point"}
}