{
  "type": "Feature",
  "properties": {
    "iso:country":"CH",
    "sg:address":"Schulhausstrasse 6",
    "sg:city":"Jaberg",
    "sg:orig_category":"Vermittlung von Immobilien",
    "sg:phone":"+41 31 781 12 93",
    "sg:postcode":"3629",
    "sg:province":"Bern",
    "wof:name":"Gugger Unternehmungen",
    "wof:placetype":"venue"
},
  "geometry": {"coordinates":[7.568007946,46.8229103088],"type":"Point"}
}