{
  "type": "Feature",
  "properties": {
    "iso:country":"CH",
    "sg:address":"Avenue Louis-casa\u00ef 27",
    "sg:city":"Vernier",
    "sg:orig_category":"Detailhandel mit B\u00fcchern, Zeitungen, Schreib U Papeteriewaren",
    "sg:postcode":"1214",
    "sg:province":"Gen\u00e8ve",
    "wof:name":"Sht Distribution S\u00e0rl",
    "wof:placetype":"venue"
},
  "geometry": {"coordinates":[6.114336,46.219337],"type":"Point"}
}