{
  "type": "Feature",
  "properties": {
    "iso:country":"CH",
    "sg:address":"Tannholzstrasse 6",
    "sg:city":"Zollikofen",
    "sg:orig_category":"Handel mit Motorr\u00e4dern, Teilen U Zubeh\u00f6r Herstellung von Fahrr\u00e4dern Instandhaltung U Reparatur von M",
    "sg:phone":"+41 31 911 36 44",
    "sg:postcode":"3052",
    "sg:province":"Bern",
    "wof:name":"Blaser Charles Vemo Ag",
    "wof:placetype":"venue"
},
  "geometry": {"coordinates":[7.4435739517,47.0046386719],"type":"Point"}
}