{
  "type": "Feature",
  "properties": {
    "iso:country":"CH",
    "sg:address":"Weidstrasse 25d",
    "sg:city":"Zug",
    "sg:orig_category":"Architekturb\u00fcros",
    "sg:phone":"+41 41 711 68 01",
    "sg:postcode":"6300",
    "sg:province":"Zug",
    "wof:name":"Hugo Sieber Architekturb\u00fcro",
    "wof:placetype":"venue"
},
  "geometry": {"coordinates":[8.52909,47.169609],"type":"Point"}
}