{
  "type": "Feature",
  "properties": {
    "iso:country":"CH",
    "sg:address":"Rue Du V\u00e9lodrome 9",
    "sg:city":"Gen\u00e8ve",
    "sg:orig_category":"Detailhandel mit Geschenkartikeln U Souvenirs",
    "sg:phone":"+41 22 328 63 55",
    "sg:postcode":"1205",
    "sg:province":"Gen\u00e8ve",
    "wof:name":"Boutique Madou Madeleine Tadorian",
    "wof:placetype":"venue"
},
  "geometry": {"coordinates":[6.130715847,46.2004051208],"type":"Point"}
}