{
  "type": "Feature",
  "properties": {
    "iso:country":"CH",
    "sg:address":"Z\u00fcrcherstrasse 17",
    "sg:city":"Schlieren",
    "sg:orig_category":"Detailhandel mit Radio U Fernsehger\u00e4ten Detailhandel mit elektrischen Haushalts-,Radio U Fernsehger\u00e4",
    "sg:phone":"+41 17307721",
    "sg:postcode":"8952",
    "sg:province":"Z\u00fcrich",
    "wof:name":"Siegenthaler A.",
    "wof:placetype":"venue"
},
  "geometry": {"coordinates":[8.4508600235,47.3982086182],"type":"Point"}
}