{
  "type": "Feature",
  "properties": {
    "iso:country":"CH",
    "sg:address":"Dorfstrasse 166",
    "sg:city":"Wenslingen",
    "sg:orig_category":"Grosshandel mit Datenverarbeitungsger\u00e4ten",
    "sg:phone":"+41 21 792 18 12",
    "sg:postcode":"4493",
    "sg:province":"Basel-Landschaft",
    "wof:name":"Dyke Sa Equipement Informatique",
    "wof:placetype":"venue"
},
  "geometry": {"coordinates":[6.6805458069,46.5142631531],"type":"Point"}
}