{
  "type": "Feature",
  "properties": {
    "addr:full":"Alte Eschenbacherstrasse 8 Schmerikon St. Gallen 8716",
    "addr:housenumber":"8",
    "addr:postcode":"8716",
    "addr:street":"Eschenbacherstrasse",
    "iso:country":"CH",
    "sg:address":"Alte Eschenbacherstrasse 8",
    "sg:city":"Schmerikon",
    "sg:orig_category":"Bauingenieurb\u00fcros allgemein",
    "sg:phone":"+41 55 282 12 13",
    "sg:postcode":"8716",
    "sg:province":"St. Gallen",
    "wof:name":"Alfred Fitze Ingenieurb\u00fcro",
    "wof:placetype":"venue"
},
  "geometry": {"coordinates":[8.939444,47.227657],"type":"Point"}
}