{
  "type": "Feature",
  "properties": {
    "addr:full":"Birmensdorferstrasse 140 Urdorf Z\u00fcrich 8902",
    "addr:housenumber":"140",
    "addr:postcode":"8902",
    "addr:street":"Birmensdorferstrasse",
    "iso:country":"CH",
    "sg:address":"Birmensdorferstrasse 140",
    "sg:city":"Urdorf",
    "sg:orig_category":"Autosattlereien",
    "sg:phone":"+41 18440091",
    "sg:postcode":"8902",
    "sg:province":"Z\u00fcrich",
    "wof:name":"Kress Gmbh Autosattlerei",
    "wof:placetype":"venue"
},
  "geometry": {"coordinates":[8.408525,47.447353],"type":"Point"}
}