{
  "type": "Feature",
  "properties": {
    "iso:country":"CH",
    "sg:address":"Thalstr. 35",
    "sg:city":"Balsthal",
    "sg:classifiers":[
        {
            "category":"Wholesale",
            "subcategory":"Meat",
            "type":"Manufacturing & Wholesale Goods"
        }
    ],
    "sg:phone":"+41 62 386 63 63",
    "sg:postcode":"4710",
    "sg:province":"Solothurn",
    "sg:tags":[
        "food",
        "cooked",
        "product",
        "related"
    ],
    "wof:name":"Gehrig Ag",
    "wof:placetype":"venue"
},
  "geometry": {"coordinates":[7.6818289757,47.3117027283],"type":"Point"}
}