{
  "type": "Feature",
  "properties": {
    "iso:country":"CH",
    "sg:address":"Grundstrasse 22b 6343 Rotkreuz. Postfach",
    "sg:city":"Rotkreuz",
    "sg:orig_category":"Non-Classified Establishments",
    "sg:postcode":"6343",
    "sg:province":"Zug",
    "wof:name":"General Disco Gmbh Discothek Usw",
    "wof:placetype":"venue"
},
  "geometry": {"coordinates":[8.430103302,47.1463279724],"type":"Point"}
}