{
  "type": "Feature",
  "properties": {
    "iso:country":"CH",
    "sg:address":"Chemin De L'etang 46 1219 Ch\u00e2telaine Case Postale 1126 1215 Gen\u00e8ve",
    "sg:city":"D\u00e9p\u00f4t",
    "sg:orig_category":"G\u00fcterbef\u00f6rderung im Strassenverkehr",
    "sg:phone":"+41 32 968 00 88",
    "sg:postcode":"15",
    "wof:name":"Jacky Maeder Sa De Transports Internationaux",
    "wof:placetype":"venue"
},
  "geometry": {"coordinates":[6.8428630829,47.1108322144],"type":"Point"}
}