{
  "type": "Feature",
  "properties": {
    "iso:country":"CH",
    "sg:address":"Place Du Midi 25 1950 Sion Case Postale 306",
    "sg:city":"Sion",
    "sg:orig_category":"Reiseb\u00fcros",
    "sg:phone":"+41 27 329 06 30",
    "sg:postcode":"1951",
    "sg:province":"Valais",
    "wof:name":"Mat-evasion & Voyages",
    "wof:placetype":"venue"
},
  "geometry": {"coordinates":[7.3609499931,46.2315254211],"type":"Point"}
}