{
  "type": "Feature",
  "properties": {
    "iso:country":"CH",
    "sg:address":"Samstagernstr. 31",
    "sg:city":"Wollerau",
    "sg:classifiers":[
        {
            "category":"Autos & Motor Vehicles",
            "subcategory":"Automobile Sales",
            "type":"Retail Goods"
        }
    ],
    "sg:phone":"+41 4117874848",
    "sg:postcode":"8832",
    "sg:province":"Schwyz",
    "sg:tags":[
        "equipment",
        "transport"
    ],
    "wof:name":"Sss-f\u00d6rdertechnik Ag",
    "wof:placetype":"venue"
},
  "geometry": {"coordinates":[8.7098865509,47.1902122498],"type":"Point"}
}