{
  "type": "Feature",
  "properties": {
    "iso:country":"CH",
    "sg:address":"Fusterie Place De La 7 1204 Gen\u00e8ve. Postfach",
    "sg:city":"Gen\u00e8ve",
    "sg:orig_category":"Vermietung U Verpachtung von eigenen Immobilien",
    "sg:phone":"+41 32 967 64 13",
    "sg:postcode":"1204",
    "sg:province":"Gen\u00e8ve",
    "wof:name":"Agence Bolliger Immobilier",
    "wof:placetype":"venue"
},
  "geometry": {"coordinates":[6.8297801018,47.1029129028],"type":"Point"}
}