{
  "type": "Feature",
  "properties": {
    "iso:country":"CH",
    "sg:address":"Anwandstrasse 30",
    "sg:city":"Z\u00fcrich",
    "sg:orig_category":"Sonstige pers\u00f6nliche Dienstleistungen Verlag von bespielten Tontr\u00e4gern",
    "sg:phone":"+41 12404410",
    "sg:postcode":"8000",
    "sg:province":"Z\u00fcrich",
    "wof:name":"United Sound Gmbh",
    "wof:placetype":"venue"
},
  "geometry": {"coordinates":[8.5234060287,47.3766899109],"type":"Point"}
}