{
  "type": "Feature",
  "properties": {
    "iso:country":"CH",
    "sg:address":"S\u00e4liweg 2 4852 Rothrist. Postfach",
    "sg:city":"Rothrist",
    "sg:orig_category":"Allgemeiner Hoch U Tiefbau",
    "sg:postcode":"4852",
    "sg:province":"Aargau",
    "wof:name":"Kr\u00e4henb\u00fchl Martin",
    "wof:placetype":"venue"
},
  "geometry": {"coordinates":[7.883563,47.309048],"type":"Point"}
}