{
  "type": "Feature",
  "properties": {
    "iso:country":"CH",
    "sg:address":"Hohlstrasse 192",
    "sg:city":"Z\u00fcrich",
    "sg:orig_category":"Physiotherapie",
    "sg:phone":"+41 12912460",
    "sg:postcode":"8004",
    "sg:province":"Z\u00fcrich",
    "wof:name":"Physiotherapie Hard",
    "wof:placetype":"venue"
},
  "geometry": {"coordinates":[8.5178842545,47.3813781738],"type":"Point"}
}