{
  "type": "Feature",
  "properties": {
    "iso:country":"CH",
    "sg:address":"Moosstrasse 2",
    "sg:city":"Luzern",
    "sg:orig_category":"Interessenvertretungen",
    "sg:postcode":"6003",
    "sg:province":"Luzern",
    "wof:name":"Stiftung Oekologie Helvetia-hungaria, Oehh",
    "wof:placetype":"venue"
},
  "geometry": {"coordinates":[8.3042259216,47.0456771851],"type":"Point"}
}