{
  "type": "Feature",
  "properties": {
    "iso:country":"CH",
    "sg:address":"R\u00f6tibodenstrasse 10",
    "sg:city":"W\u00e4denswil",
    "sg:orig_category":"Interessenvertretungen",
    "sg:postcode":"8820",
    "sg:province":"Z\u00fcrich",
    "wof:name":"Stiftung Kinderheim B\u00fchl",
    "wof:placetype":"venue"
},
  "geometry": {"coordinates":[8.6614046097,47.226776123],"type":"Point"}
}