{
  "type": "Feature",
  "properties": {
    "addr:full":"Solothurnstrasse 35 Oensingen Solothurn 4702",
    "addr:housenumber":"35",
    "addr:postcode":"4702",
    "addr:street":"Solothurnstrasse",
    "iso:country":"CH",
    "sg:address":"Solothurnstrasse 35",
    "sg:city":"Oensingen",
    "sg:orig_category":"Allgemeiner Hoch U Tiefbau",
    "sg:phone":"+41 19361063",
    "sg:postcode":"4702",
    "sg:province":"Solothurn",
    "wof:name":"S\u00f6nnichsen Thomas Hochbauplanung",
    "wof:placetype":"venue"
},
  "geometry": {"coordinates":[8.762422,47.30595],"type":"Point"}
}