{
  "type": "Feature",
  "properties": {
    "iso:country":"CH",
    "sg:address":"Avenue Du Galicien 6",
    "sg:city":"Prilly",
    "sg:orig_category":"G\u00fcterbef\u00f6rderung im Strassenverkehr",
    "sg:phone":"+41 21 625 50 77",
    "sg:postcode":"1008",
    "sg:province":"Vaud",
    "wof:name":"Vincenzo Genito Transports",
    "wof:placetype":"venue"
},
  "geometry": {"coordinates":[6.6064558029,46.5289344788],"type":"Point"}
}