{
  "type": "Feature",
  "properties": {
    "iso:country":"CH",
    "sg:address":"Via Francesco Ballerini 12",
    "sg:city":"Locarno",
    "sg:classifiers":[
        {
            "category":"Manufacturing",
            "subcategory":"Wood Products",
            "type":"Manufacturing & Wholesale Goods"
        }
    ],
    "sg:phone":"+41 91 751 13 21",
    "sg:postcode":"6600",
    "sg:province":"Ticino",
    "sg:tags":[
        "gate",
        "made",
        "door"
    ],
    "wof:name":"Magistra-carelli Sa",
    "wof:placetype":"venue"
},
  "geometry": {"coordinates":[8.7983503342,46.1657791138],"type":"Point"}
}