{
  "type": "Feature",
  "properties": {
    "iso:country":"CH",
    "sg:address":"Vuisse",
    "sg:city":"Pont-de-la-morge",
    "sg:orig_category":"Non-Classified Establishments",
    "sg:postcode":"1962",
    "sg:province":"Valais",
    "wof:name":"Association Swashakthi",
    "wof:placetype":"venue"
},
  "geometry": {"coordinates":[7.3135361671,46.2257194519],"type":"Point"}
}