{
  "type": "Feature",
  "properties": {
    "iso:country":"CH",
    "sg:address":"Allmendstrasse 1",
    "sg:city":"Bellach",
    "sg:orig_category":"Bauschreinerei Herstellung von Konstruktionsteilen, Fertigbauteilen U Ausbauelementen aus Holz",
    "sg:phone":"+41 32 358 18 92",
    "sg:postcode":"4512",
    "sg:province":"Solothurn",
    "wof:name":"Devaux Fr\u00e8res Sarl",
    "wof:placetype":"venue"
},
  "geometry": {"coordinates":[7.21384,47.159199],"type":"Point"}
}