{
  "type": "Feature",
  "properties": {
    "iso:country":"CH",
    "sg:address":"Route De France 36",
    "sg:city":"Boncourt",
    "sg:orig_category":"Dachdeckerei Zimmerei, Dachdeckerei, Bauspenglerei U Abdichtung",
    "sg:phone":"+41 27 785 14 75",
    "sg:postcode":"2926",
    "sg:province":"Jura",
    "wof:name":"Dorsaz Georges",
    "wof:placetype":"venue"
},
  "geometry": {"coordinates":[7.17727,46.091335],"type":"Point"}
}