{
  "type": "Feature",
  "properties": {
    "iso:country":"CH",
    "sg:address":"Fraum\u00fcnsterstrasse 25",
    "sg:city":"Z\u00fcrich",
    "sg:orig_category":"Korrespondenz U Nachrichtenb\u00fcros, selbst\u00e4ndige Journalisten",
    "sg:postcode":"8001",
    "sg:province":"Z\u00fcrich",
    "wof:name":"Ardopress Jacques O. Pelichet",
    "wof:placetype":"venue"
},
  "geometry": {"coordinates":[8.5406160355,47.3692207336],"type":"Point"}
}