{
  "type": "Feature",
  "properties": {
    "iso:country":"CH",
    "sg:address":"Grafschaftstrasse 8",
    "sg:city":"Oberglatt",
    "sg:classifiers":[
        {
            "category":"Home & Garden",
            "subcategory":"Hardware",
            "type":"Retail Goods"
        }
    ],
    "sg:phone":"+41 18502867",
    "sg:postcode":"8154",
    "sg:province":"Z\u00fcrich",
    "sg:tags":[
        "agricultural",
        "implement"
    ],
    "wof:name":"Egli Landmaschinen Ag",
    "wof:placetype":"venue"
},
  "geometry": {"coordinates":[8.52607,47.478992],"type":"Point"}
}