{
  "type": "Feature",
  "properties": {
    "iso:country":"CH",
    "sg:address":"Dorfstrasse 40",
    "sg:city":"W\u00fcnnewil",
    "sg:orig_category":"RESTAURANTS: TEA-ROOMS",
    "sg:phone":"+41 32 351 62 60",
    "sg:postcode":"3184",
    "sg:province":"Fribourg",
    "wof:name":"Von Niederh\u00e4usern & Emch",
    "wof:placetype":"venue"
},
  "geometry": {"coordinates":[7.3719878197,47.1400184631],"type":"Point"}
}