{
  "type": "Feature",
  "properties": {
    "iso:country":"CH",
    "sg:address":"Hauptstrasse 2 4702 Oensingen. Postfach",
    "sg:city":"Oensingen",
    "sg:orig_category":"Gemeindeverwaltungen",
    "sg:phone":"+41 62 396 16 07",
    "sg:postcode":"4702",
    "sg:province":"Solothurn",
    "wof:name":"Gemeindeverwaltung Oensingen",
    "wof:placetype":"venue"
},
  "geometry": {"coordinates":[7.7161459923,47.2901802063],"type":"Point"}
}