{
  "type": "Feature",
  "properties": {
    "iso:country":"CH",
    "sg:address":"Weidenweg 17 4310 Rheinfelden. Postfach",
    "sg:city":"Rheinfelden",
    "sg:orig_category":"Vermietung U Verpachtung von eigenen Immobilien",
    "sg:phone":"+41 61 836 15 00",
    "sg:postcode":"4310",
    "sg:province":"Aargau",
    "wof:name":"Abima Management Ag",
    "wof:placetype":"venue"
},
  "geometry": {"coordinates":[7.7750887871,47.5495529175],"type":"Point"}
}