{
  "type": "Feature",
  "properties": {
    "iso:country":"CH",
    "sg:address":"1131",
    "sg:city":"Tolochenaz",
    "sg:orig_category":"Interessenvertretungen",
    "sg:postcode":"1131",
    "sg:province":"Vaud",
    "wof:name":"Institutions Sociales De L'industrie Vaudoise De La Construction",
    "wof:placetype":"venue"
},
  "geometry": {"coordinates":[6.4742050171,46.5053062439],"type":"Point"}
}