{
  "type": "Feature",
  "properties": {
    "iso:country":"CH",
    "sg:address":"Pumpwerkstrasse 21 8105 Regensdorf 1. Postfach 161",
    "sg:city":"Regensdorf",
    "sg:orig_category":"Offsetdruck",
    "sg:phone":"+41 18434488",
    "sg:postcode":"8105",
    "sg:province":"Z\u00fcrich",
    "wof:name":"H\u00fcrzeler Ag Druckerei F\u00fcr Buchdruck U. Andere Druckverfahren Usw",
    "wof:placetype":"venue"
},
  "geometry": {"coordinates":[8.4592847824,47.4442825317],"type":"Point"}
}