{
  "type": "Feature",
  "properties": {
    "iso:country":"CH",
    "sg:address":"Geeringstrasse 32",
    "sg:city":"Z\u00fcrich",
    "sg:orig_category":"Sonstige pers\u00f6nliche Dienstleistungen",
    "sg:phone":"+41 13423666",
    "sg:postcode":"8049",
    "sg:province":"Z\u00fcrich",
    "wof:name":"Derungs & Partner Intern. Vermittl. V. Dienstleistungen Bes. F. Geld- U. Wertpapiere Usw",
    "wof:placetype":"venue"
},
  "geometry": {"coordinates":[8.4805736542,47.4147644043],"type":"Point"}
}