{
  "type": "Feature",
  "properties": {
    "iso:country":"CH",
    "sg:address":"Ch. De La Rochelle 24",
    "sg:city":"Prilly",
    "sg:orig_category":"Sanit\u00e4r, Heizungs U L\u00fcftungsinstallation",
    "sg:postcode":"1008",
    "sg:province":"Vaud",
    "wof:name":"Sanitaires Services, Ferreras Pedro",
    "wof:placetype":"venue"
},
  "geometry": {"coordinates":[6.6019921303,46.5333061218],"type":"Point"}
}