{
  "type": "Feature",
  "properties": {
    "iso:country":"CH",
    "sg:address":"Obere Erlen 14",
    "sg:city":"Emmenbr\u00fccke",
    "sg:orig_category":"Handelsvermittlung U Grosshandel Sonstiger Grosshandel",
    "sg:phone":"+41 41 280 71 50",
    "sg:postcode":"6020",
    "sg:province":"Luzern",
    "wof:name":"Reichenbach Peter Pr Handelsvertretungen",
    "wof:placetype":"venue"
},
  "geometry": {"coordinates":[8.2606277466,47.0738945007],"type":"Point"}
}