{
  "type": "Feature",
  "properties": {
    "iso:country":"CH",
    "sg:address":"Stockstrasse 399e",
    "sg:city":"Sigriswil",
    "sg:classifiers":[
        {
            "category":"Communications",
            "subcategory":"Radio Station",
            "type":"Services"
        }
    ],
    "sg:postcode":"3655",
    "sg:province":"Bern",
    "sg:tags":[
        "fernsehanstalten",
        "u"
    ],
    "wof:name":"Audiovision M\u00fcller Heinz P.",
    "wof:placetype":"venue"
},
  "geometry": {"coordinates":[7.7350840569,46.7018356323],"type":"Point"}
}