{
  "type": "Feature",
  "properties": {
    "iso:country":"CH",
    "sg:address":"Brenzikofenstrasse 8",
    "sg:city":"Oppligen",
    "sg:orig_category":"Herstellung von K\u00fcchenm\u00f6beln",
    "sg:phone":"+41 31 781 30 20",
    "sg:postcode":"3629",
    "sg:province":"Bern",
    "wof:name":"Kho Ag",
    "wof:placetype":"venue"
},
  "geometry": {"coordinates":[7.5994758606,46.819190979],"type":"Point"}
}