{
  "type": "Feature",
  "properties": {
    "addr:full":"Obere Gasse 43 Chur Graubunden 7000",
    "addr:housenumber":"43",
    "addr:postcode":"7000",
    "addr:street":"Obere Gasse",
    "iso:country":"CH",
    "sg:address":"Obere Gasse 43",
    "sg:city":"Chur",
    "sg:orig_category":"Detailhandel mit Brot, Back U S\u00fcsswaren",
    "sg:phone":"+41 79 218 25 28",
    "sg:postcode":"7000",
    "sg:province":"Graubunden",
    "wof:name":"Gwerder Franz",
    "wof:placetype":"venue"
},
  "geometry": {"coordinates":[9.53014,46.847904],"type":"Point"}
}