{
  "type": "Feature",
  "properties": {
    "iso:country":"CH",
    "sg:address":"Orbe Rue D' 77 1400 Yverdon-les-bains. Postfach",
    "sg:city":"Cuarnens",
    "sg:orig_category":"Detailhandel mit Waren verschiedener Art, Hauptrichtung Nahrungsmittel",
    "sg:postcode":"1309",
    "wof:name":"Lopez Ribera Jos\u00e9-luis Magasin D'alimentation G\u00e9n\u00e9rale",
    "wof:placetype":"venue"
},
  "geometry": {"coordinates":[6.6289792061,46.7540664673],"type":"Point"}
}