{
  "type": "Feature",
  "properties": {
    "iso:country":"CH",
    "sg:address":"Weinfelderstrasse 75",
    "sg:city":"Amriswil",
    "sg:orig_category":"Sportvereine Schwingen",
    "sg:phone":"+41 61 401 02 35",
    "sg:postcode":"8580",
    "sg:province":"Thurgau",
    "wof:name":"Schwingklub Oberwil",
    "wof:placetype":"venue"
},
  "geometry": {"coordinates":[7.5598378181,47.5077896118],"type":"Point"}
}