{
  "type": "Feature",
  "properties": {
    "addr:full":"Kalofen 4 Grosswangen Luzern 6022",
    "addr:housenumber":"4",
    "addr:postcode":"6022",
    "addr:street":"Kalofen",
    "iso:country":"CH",
    "sg:address":"Kalofen 4",
    "sg:city":"Grosswangen",
    "sg:orig_category":"Advokaturb\u00fcros Notariate",
    "sg:phone":"+41 41 980 17 44",
    "sg:postcode":"6022",
    "sg:province":"Luzern",
    "wof:name":"Hans-peter Fischer Advokatur-& Notariatsb\u00fcro",
    "wof:placetype":"venue"
},
  "geometry": {"coordinates":[8.049396,47.128925],"type":"Point"}
}