{
  "type": "Feature",
  "properties": {
    "iso:country":"CH",
    "sg:address":"Albisriederstrasse 5",
    "sg:city":"Z\u00fcrich",
    "sg:orig_category":"Arztpraxen",
    "sg:phone":"+41 43 311 02 22",
    "sg:postcode":"8003",
    "sg:province":"Z\u00fcrich",
    "wof:name":"G. Fassbind & S. Binder Ern\u00e4hrungsberatung",
    "wof:placetype":"venue"
},
  "geometry": {"coordinates":[8.509487,47.378029],"type":"Point"}
}