{
  "type": "Feature",
  "properties": {
    "iso:country":"CH",
    "sg:address":"Route Du L\u00e9man 24",
    "sg:city":"Mayens-de-saxon",
    "sg:orig_category":"Herstellung von elektrischen Haushaltsger\u00e4ten",
    "sg:postcode":"1907",
    "sg:province":"Valais",
    "wof:name":"M\u00e9trailler, Aspirateurs Centralis\u00e9s S\u00e0rl",
    "wof:placetype":"venue"
},
  "geometry": {"coordinates":[-90.41338348390001,46.4930992126],"type":"Point"}
}