{
  "type": "Feature",
  "properties": {
    "iso:country":"CH",
    "sg:address":"Bahnhofstrasse 33",
    "sg:city":"Arbon",
    "sg:orig_category":"P\u00e9dicure",
    "sg:phone":"+41 71 446 55 59",
    "sg:postcode":"9320",
    "sg:province":"Thurgau",
    "wof:name":"Christine Frick P\u00e9dicure",
    "wof:placetype":"venue"
},
  "geometry": {"coordinates":[9.4343757629,47.5132713318],"type":"Point"}
}