{
  "type": "Feature",
  "properties": {
    "iso:country":"CH",
    "sg:address":"Amthausstrasse 15",
    "sg:city":"Dornach",
    "sg:orig_category":"Forst\u00e4mter",
    "sg:phone":"+41 61 706 28 88",
    "sg:postcode":"4143",
    "sg:province":"Solothurn",
    "wof:name":"Kant. Kreisforstamt Dorneck-thierstein",
    "wof:placetype":"venue"
},
  "geometry": {"coordinates":[7.6087441444,47.4882621765],"type":"Point"}
}