{
  "type": "Feature",
  "properties": {
    "iso:country":"CH",
    "sg:address":"Schulhausstrasse 1",
    "sg:city":"Nieder\u00f6nz",
    "sg:orig_category":"Primarschulen",
    "sg:phone":"+41 34 411 06 38",
    "sg:postcode":"3362",
    "sg:province":"Bern",
    "wof:name":"Primarschule",
    "wof:placetype":"venue"
},
  "geometry": {"coordinates":[7.69480896,47.1846008301],"type":"Point"}
}