{
  "type": "Feature",
  "properties": {
    "iso:country":"CH",
    "sg:address":"Gumpelen",
    "sg:city":"Leimiswil",
    "sg:orig_category":"Mechanische Werkst\u00e4tten",
    "sg:phone":"+41 62 965 25 86",
    "sg:postcode":"4935",
    "sg:province":"Bern",
    "wof:name":"Hans Graber Werkzeugschleiferei",
    "wof:placetype":"venue"
},
  "geometry": {"coordinates":[7.772151947,47.1578483582],"type":"Point"}
}