{
  "type": "Feature",
  "properties": {
    "addr:full":"Kanonengasse 30 4051 Basel. Postfach Basel Basel-Stadt 4002",
    "addr:housenumber":"30",
    "addr:postcode":"4051;4002",
    "addr:street":"Kanonengasse;Postfach",
    "iso:country":"CH",
    "sg:address":"Kanonengasse 30 4051 Basel. Postfach",
    "sg:city":"Basel",
    "sg:orig_category":"Sonstiger Grosshandel",
    "sg:phone":"+41 61 271 37 00",
    "sg:postcode":"4002",
    "sg:province":"Basel-Stadt",
    "wof:name":"Qualimat Ag Beratungs- U. Dienstleistungsauftr\u00e4ge Usw",
    "wof:placetype":"venue"
},
  "geometry": {"coordinates":[7.585298,47.553345],"type":"Point"}
}