{
  "type": "Feature",
  "properties": {
    "iso:country":"CH",
    "sg:address":"Baselstrasse 47 6000 Luzern. Postfach",
    "sg:city":"Luzern",
    "sg:orig_category":"Detailhandel mit B\u00fcchern, Zeitungen, Schreib U Papeteriewaren",
    "sg:postcode":"6003",
    "sg:province":"Luzern",
    "wof:name":"Kiosk Sucur",
    "wof:placetype":"venue"
},
  "geometry": {"coordinates":[8.294281,47.053295],"type":"Point"}
}