{
  "type": "Feature",
  "properties": {
    "iso:country":"CH",
    "sg:address":"Casa Amarus",
    "sg:city":"Manno",
    "sg:orig_category":"Herstellung von Teppichen",
    "sg:postcode":"6928",
    "sg:province":"Ticino",
    "wof:name":"Edilpiastrel Di Londino Vincenzo",
    "wof:placetype":"venue"
},
  "geometry": {"coordinates":[8.919005394,46.0345535278],"type":"Point"}
}