{
  "type": "Feature",
  "properties": {
    "iso:country":"CH",
    "sg:address":"Freiestrasse 14",
    "sg:city":"Z\u00fcrich",
    "sg:orig_category":"Detailhandel mit Waren verschiedener Art, Hauptrichtung Nahrungsmittel",
    "sg:phone":"+41 12615827",
    "sg:postcode":"8032",
    "sg:province":"Z\u00fcrich",
    "wof:name":"Coop Laden",
    "wof:placetype":"venue"
},
  "geometry": {"coordinates":[8.5520620346,47.3733520508],"type":"Point"}
}