{
  "type": "Feature",
  "properties": {
    "iso:country":"CH",
    "sg:address":"Freiburgstr. 47 3176 Neuenegg. Postfach",
    "sg:city":"Th\u00f6rishaus",
    "sg:orig_category":"Herstellung von Metallkonstruktionen",
    "sg:postcode":"3174",
    "sg:province":"Bern",
    "wof:name":"H. Ramseier",
    "wof:placetype":"venue"
},
  "geometry": {"coordinates":[7.3381857872,46.8942489624],"type":"Point"}
}