{
  "type": "Feature",
  "properties": {
    "iso:country":"CH",
    "sg:address":"Rue Des Terreaux 4",
    "sg:city":"Lausanne",
    "sg:classifiers":[
        {
            "category":"Banks & Credit Unions",
            "subcategory":"Bureau De Change",
            "type":"Services"
        }
    ],
    "sg:phone":"+41 21 323 25 27",
    "sg:postcode":"1003",
    "sg:province":"Vaud",
    "sg:tags":[
        "revision"
    ],
    "wof:name":"Asfida Sa Bureau Fiduciaire",
    "wof:placetype":"venue"
},
  "geometry": {"coordinates":[6.6284627914,46.5226211548],"type":"Point"}
}