{
  "type": "Feature",
  "properties": {
    "iso:country":"CH",
    "sg:address":"Obere Rainstrase 426",
    "sg:city":"Hirschthal",
    "sg:orig_category":"Politische Parteien SP",
    "sg:phone":"+41 62 721 29 16",
    "sg:postcode":"5042",
    "sg:province":"Aargau",
    "wof:name":"Sp Ortspartei Hirschthal",
    "wof:placetype":"venue"
},
  "geometry": {"coordinates":[8.0612230301,47.3208045959],"type":"Point"}
}