{
  "type": "Feature",
  "properties": {
    "iso:country":"CH",
    "sg:address":"Meientalstrasse 69",
    "sg:city":"Z\u00fcrich",
    "sg:orig_category":"Softwareentwicklung U beratung",
    "sg:postcode":"8048",
    "sg:province":"Z\u00fcrich",
    "wof:name":"Masterpoint Gmbh",
    "wof:placetype":"venue"
},
  "geometry": {"coordinates":[8.4777336121,47.3860282898],"type":"Point"}
}