{
  "type": "Feature",
  "properties": {
    "iso:country":"CH",
    "sg:address":"Hauptstrasse 5b",
    "sg:city":"Oberkulm",
    "sg:orig_category":"Detailhandel mit S\u00e4uglings U Kinderbekleidung",
    "sg:phone":"+41 62 776 39 20",
    "sg:postcode":"5727",
    "sg:province":"Aargau",
    "wof:name":"Ruth Keiser Kinderkleiderb\u00f6rse",
    "wof:placetype":"venue"
},
  "geometry": {"coordinates":[8.1179008484,47.3065185547],"type":"Point"}
}