{
  "type": "Feature",
  "properties": {
    "addr:full":"Untere Kirchgasse 3 Winterthur Z\u00fcrich 8400",
    "addr:housenumber":"3",
    "addr:postcode":"8400",
    "addr:street":"Untere Kirchgasse",
    "iso:country":"CH",
    "sg:address":"Untere Kirchgasse 3",
    "sg:city":"Winterthur",
    "sg:orig_category":"Chemische Reinigung",
    "sg:phone":"+41 52 212 27 24",
    "sg:postcode":"8400",
    "sg:province":"Z\u00fcrich",
    "wof:name":"Texcare",
    "wof:placetype":"venue"
},
  "geometry": {"coordinates":[8.728104,47.49942],"type":"Point"}
}