{
  "type": "Feature",
  "properties": {
    "iso:country":"CH",
    "sg:address":"Tramstrasse 5 5034 Suhr. Postfach",
    "sg:city":"Suhr",
    "sg:orig_category":"Detailhandel mit Lederwaren U Reiseartikeln Detailhandel mit Schuhen U Lederwaren",
    "sg:postcode":"5034",
    "sg:province":"Aargau",
    "wof:name":"W. Sandmeier",
    "wof:placetype":"venue"
},
  "geometry": {"coordinates":[8.1829147339,47.2517738342],"type":"Point"}
}