{
  "type": "Feature",
  "properties": {
    "iso:country":"CH",
    "sg:address":"Diebold-schilling-strasse 51",
    "sg:city":"Bettlach",
    "sg:orig_category":"Herstellung U Zusammensetzung von Uhren Herstellung von sonstigen Metallwaren",
    "sg:phone":"+41 32 914 75 75",
    "sg:postcode":"2544",
    "sg:province":"Solothurn",
    "wof:name":"Cronal C.a. Mosset Gravure Chimique, M\u00e9canique",
    "wof:placetype":"venue"
},
  "geometry": {"coordinates":[6.8209271431,47.1048774719],"type":"Point"}
}