{
  "type": "Feature",
  "properties": {
    "addr:full":"Wildbachstrasse 82 Z\u00fcrich Z\u00fcrich 8008",
    "addr:housenumber":"82",
    "addr:postcode":"8008",
    "addr:street":"Wildbachstrasse",
    "iso:country":"CH",
    "sg:address":"Wildbachstrasse 82",
    "sg:city":"Z\u00fcrich",
    "sg:orig_category":"Architektur U Ingenieurb\u00fcros Architekturb\u00fcros",
    "sg:phone":"+41 12714142",
    "sg:postcode":"8008",
    "sg:province":"Z\u00fcrich",
    "wof:name":"Gautschi Storrer Architekten Ag",
    "wof:placetype":"venue"
},
  "geometry": {"coordinates":[8.559199,47.35397],"type":"Point"}
}