{
  "type": "Feature",
  "properties": {
    "iso:country":"CH",
    "sg:address":"Bahnhofstrasse 46",
    "sg:city":"Widnau",
    "sg:orig_category":"Detailhandel mit Radio U Fernsehger\u00e4ten",
    "sg:phone":"+41 71 720 00 06",
    "sg:postcode":"9443",
    "sg:province":"St. Gallen",
    "wof:name":"Macho-service-center Tv Video",
    "wof:placetype":"venue"
},
  "geometry": {"coordinates":[9.6347808838,47.4045143127],"type":"Point"}
}