{
  "type": "Feature",
  "properties": {
    "iso:country":"CH",
    "sg:address":"Esslenstrasse 30",
    "sg:city":"Kreuzlingen",
    "sg:orig_category":"Softwareentwicklung U beratung",
    "sg:phone":"+41 71 671 24 31",
    "sg:postcode":"8280",
    "sg:province":"Thurgau",
    "wof:name":"Adimsystems Gmbh",
    "wof:placetype":"venue"
},
  "geometry": {"coordinates":[9.156879425,47.6455535889],"type":"Point"}
}