{
  "type": "Feature",
  "properties": {
    "iso:country":"CH",
    "sg:address":"Gottardo Via San 10",
    "sg:city":"Lugano",
    "sg:orig_category":"Dienstleistungen von Beteiligungsgesellschaften",
    "sg:phone":"+41 91 827 17 26",
    "sg:postcode":"6900",
    "sg:province":"Ticino",
    "wof:name":"Starci Sa",
    "wof:placetype":"venue"
},
  "geometry": {"coordinates":[9.128364563,46.2376060486],"type":"Point"}
}