{
  "type": "Feature",
  "properties": {
    "addr:full":"T\u00f6distrasse 63 Horgen Z\u00fcrich 8810",
    "addr:housenumber":"63",
    "addr:postcode":"8810",
    "addr:street":"Toedistrasse",
    "iso:country":"CH",
    "sg:address":"T\u00f6distrasse 63",
    "sg:city":"Horgen",
    "sg:orig_category":"Cnc-Edging Work",
    "sg:phone":"+41 17251504",
    "sg:postcode":"8810",
    "sg:province":"Z\u00fcrich",
    "wof:name":"Christian Gerber",
    "wof:placetype":"venue"
},
  "geometry": {"coordinates":[8.586786,47.258488],"type":"Point"}
}