{
  "type": "Feature",
  "properties": {
    "iso:country":"CH",
    "sg:address":"Vorame Via 98",
    "sg:city":"Ascona",
    "sg:orig_category":"Vermietung U Verpachtung von eigenen Immobilien",
    "sg:postcode":"6612",
    "sg:province":"Ticino",
    "wof:name":"Severo Immobilien Ag",
    "wof:placetype":"venue"
},
  "geometry": {"coordinates":[8.7797241211,46.1590042114],"type":"Point"}
}