{
  "type": "Feature",
  "properties": {
    "iso:country":"CH",
    "sg:address":"San Spiert",
    "sg:city":"Pontresina",
    "sg:orig_category":"Pensionen mit Restaurant",
    "sg:phone":"+41 81 842 63 63",
    "sg:postcode":"7504",
    "sg:province":"Graubunden",
    "wof:name":"Pension Freimann",
    "wof:placetype":"venue"
},
  "geometry": {"coordinates":[9.9063396454,46.4899406433],"type":"Point"}
}