{
  "type": "Feature",
  "properties": {
    "iso:country":"CH",
    "sg:address":"Im Br\u00e4chli 33",
    "sg:city":"Z\u00fcrich",
    "sg:orig_category":"Lichtpause U Reprografiebetriebe Schnelldruck U Kopierservice",
    "sg:phone":"+41 22 738 69 02",
    "sg:postcode":"8053",
    "sg:province":"Z\u00fcrich",
    "wof:name":"Buro 2000",
    "wof:placetype":"venue"
},
  "geometry": {"coordinates":[6.1482610703,46.2103691101],"type":"Point"}
}