{
  "type": "Feature",
  "properties": {
    "iso:country":"CH",
    "sg:address":"Bellariastrasse 7 8002 Z\u00fcrich. Postfach",
    "sg:city":"Z\u00fcrich",
    "sg:orig_category":"Advokaturb\u00fcros",
    "sg:phone":"+41 12025330",
    "sg:postcode":"8027",
    "sg:province":"Z\u00fcrich",
    "wof:name":"Kammermann & Fluri Advokaturb\u00fcro",
    "wof:placetype":"venue"
},
  "geometry": {"coordinates":[8.531274,47.354965],"type":"Point"}
}