{
  "type": "Feature",
  "properties": {
    "iso:country":"CH",
    "sg:address":"L\u00f6wengasse 28 8810 Horgen. Postfach",
    "sg:city":"Horgen",
    "sg:orig_category":"Detailhandel mit Uhren U Schmuck Fachdetailhandel in Verkaufsr\u00e4umen",
    "sg:phone":"+41 17260633",
    "sg:postcode":"8810",
    "sg:province":"Z\u00fcrich",
    "wof:name":"Little Diamond Inh.yvonne Meisser",
    "wof:placetype":"venue"
},
  "geometry": {"coordinates":[8.5989637375,47.2599487305],"type":"Point"}
}