{
  "type": "Feature",
  "properties": {
    "iso:country":"CH",
    "sg:address":"Steinachstrasse 12",
    "sg:city":"St.gallen",
    "sg:classifiers":[
        {
            "category":"Bars & Pubs",
            "type":"Food & Drink"
        }
    ],
    "sg:phone":"+41 71 244 45 35",
    "sg:postcode":"9000",
    "sg:province":"St. Gallen",
    "wof:name":"Bar Baywatch",
    "wof:placetype":"venue"
},
  "geometry": {"coordinates":[9.3841428757,47.4282493591],"type":"Point"}
}