{
  "type": "Feature",
  "properties": {
    "addr:full":"Bachstrasse 28 Obfelden Z\u00fcrich 8912",
    "addr:housenumber":"28",
    "addr:postcode":"8912",
    "addr:street":"Bachstrasse",
    "iso:country":"CH",
    "sg:address":"Bachstrasse 28",
    "sg:city":"Obfelden",
    "sg:classifiers":[
        {
            "category":"Communications",
            "subcategory":"Film & Video Production",
            "type":"Services"
        }
    ],
    "sg:phone":"+41 17614286",
    "sg:postcode":"8912",
    "sg:province":"Z\u00fcrich",
    "sg:tags":[
        "foil",
        "finishing",
        "aluminium"
    ],
    "wof:name":"K\u00e4lin Galvanik Ag",
    "wof:placetype":"venue"
},
  "geometry": {"coordinates":[8.423253,47.266483],"type":"Point"}
}