{
  "type": "Feature",
  "properties": {
    "iso:country":"CH",
    "sg:address":"Solothurnstrasse 28a",
    "sg:city":"Sch\u00f6nb\u00fchl-urtenen",
    "sg:orig_category":"Wirtschaftspr\u00fcfung, Steuerberatung U Treuhand",
    "sg:phone":"+41 79 466 44 15",
    "sg:postcode":"3322",
    "sg:province":"Bern",
    "wof:name":"Pontri Allgemeine B\u00fcrarbeiten",
    "wof:placetype":"venue"
},
  "geometry": {"coordinates":[7.5015320778,47.0241241455],"type":"Point"}
}