{
  "type": "Feature",
  "properties": {
    "iso:country":"CH",
    "sg:address":"In Der Ey 36",
    "sg:city":"Z\u00fcrich",
    "sg:orig_category":"Sonstiger Grosshandel",
    "sg:phone":"+41 14911270",
    "sg:postcode":"8047",
    "sg:province":"Z\u00fcrich",
    "wof:name":"Sarajudin Waren Usw; Vertretungen, Imp., Exp., Handel",
    "wof:placetype":"venue"
},
  "geometry": {"coordinates":[8.4897699356,47.3732872009],"type":"Point"}
}