{
  "type": "Feature",
  "properties": {
    "iso:country":"CH",
    "sg:address":"Beausite Rue 2 3960 Sierre. Postfach",
    "sg:city":"Sierre",
    "sg:orig_category":"Herstellung von W\u00e4sche",
    "sg:phone":"+41 27 456 87 70",
    "sg:postcode":"3960",
    "sg:province":"Valais",
    "wof:name":"Rion Huguette, Boutique Du Soleil Pr\u00eat-\u00e0-porter F\u00e9minin",
    "wof:placetype":"venue"
},
  "geometry": {"coordinates":[7.52724123,46.2930297852],"type":"Point"}
}