{
  "type": "Feature",
  "properties": {
    "iso:country":"CH",
    "sg:address":"Feldblumenweg 35",
    "sg:city":"Z\u00fcrich",
    "sg:orig_category":"Massagestudios P\u00e9dicure",
    "sg:phone":"+41 14333232",
    "sg:postcode":"8048",
    "sg:province":"Z\u00fcrich",
    "wof:name":"S. Kalberer & R. Hager",
    "wof:placetype":"venue"
},
  "geometry": {"coordinates":[8.4849052429,47.3812713623],"type":"Point"}
}