{
  "type": "Feature",
  "properties": {
    "iso:country":"CH",
    "sg:address":"Grundstrasse 30 6430 Schwyz. Postfach 336",
    "sg:city":"Schwyz",
    "sg:orig_category":"Maler U Glasergewerbe Malerei",
    "sg:phone":"+41 41 811 15 85",
    "sg:postcode":"6431",
    "sg:province":"Schwyz",
    "wof:name":"Niederberger Alois, Malergesch\u00e4ft.",
    "wof:placetype":"venue"
},
  "geometry": {"coordinates":[8.6576662064,47.0181732178],"type":"Point"}
}