{
  "type": "Feature",
  "properties": {
    "iso:country":"CH",
    "sg:address":"Huobrain 4d",
    "sg:city":"H\u00fcnenberg",
    "sg:orig_category":"Herstellung von Medikamenten U sonstigen pharmazeutischen Erzeugnissen",
    "sg:postcode":"6331",
    "sg:province":"Zug",
    "wof:name":"Loosli Dominique",
    "wof:placetype":"venue"
},
  "geometry": {"coordinates":[8.4411754608,47.1787223816],"type":"Point"}
}