{
  "type": "Feature",
  "properties": {
    "iso:country":"CH",
    "sg:address":"Schulstrasse 10",
    "sg:city":"Scherzingen",
    "sg:orig_category":"Vorschulen, Kinderg\u00e4rten",
    "sg:postcode":"8596",
    "sg:province":"Thurgau",
    "wof:name":"Kindergarten Primarschulhaus",
    "wof:placetype":"venue"
},
  "geometry": {"coordinates":[9.2255821228,47.6291694641],"type":"Point"}
}