{
  "type": "Feature",
  "properties": {
    "iso:country":"CH",
    "sg:address":"Route De La Gl\u00e2ne 107",
    "sg:city":"Villars-sur-gl\u00e2ne",
    "sg:orig_category":"Finanzierungsinstitutionen Revision",
    "sg:phone":"+41 26 408 74 74",
    "sg:postcode":"1752",
    "sg:province":"Fribourg",
    "wof:name":"Nba Fiduciaire Sa",
    "wof:placetype":"venue"
},
  "geometry": {"coordinates":[7.1429300308,46.7916221619],"type":"Point"}
}