{
  "type": "Feature",
  "properties": {
    "iso:country":"CH",
    "sg:address":"Granzstrasse 6 8280 Kreuzlingen. Postfach",
    "sg:city":"Kreuzlingen",
    "sg:orig_category":"Gesundheitswesen",
    "sg:postcode":"8280",
    "sg:province":"Thurgau",
    "wof:name":"Studio Paradise D\u00d6tterer",
    "wof:placetype":"venue"
},
  "geometry": {"coordinates":[9.1723003387,47.6553993225],"type":"Point"}
}