{
  "type": "Feature",
  "properties": {
    "iso:country":"CH",
    "sg:address":"Neum\u00e4ttli 13",
    "sg:city":"Gempen",
    "sg:orig_category":"Alarm- and Sicherheitsanlagen Grosshandel Elektroinstallation",
    "sg:phone":"+41 61 703 97 45",
    "sg:postcode":"4145",
    "sg:province":"Solothurn",
    "wof:name":"Novasafe Ag Sicherheitstechnik",
    "wof:placetype":"venue"
},
  "geometry": {"coordinates":[7.661359,47.476215],"type":"Point"}
}