{
  "type": "Feature",
  "properties": {
    "iso:country":"CH",
    "sg:address":"Dorfplatz 7",
    "sg:city":"Wattwil",
    "sg:orig_category":"RESTAURANTS: TEA-ROOMS",
    "sg:postcode":"9630",
    "sg:province":"St. Gallen",
    "wof:name":"B\u00f6sch's Imbiss",
    "wof:placetype":"venue"
},
  "geometry": {"coordinates":[9.0882101059,47.3034591675],"type":"Point"}
}