{
  "type": "Feature",
  "properties": {
    "iso:country":"CH",
    "sg:address":"1745",
    "sg:city":"Lentigny",
    "sg:orig_category":"Gemeindeverwaltungen",
    "sg:phone":"+41 27 207 17 10",
    "sg:postcode":"1745",
    "sg:province":"Fribourg",
    "wof:name":"Administration Communale De Les Agettes-la Vernaz",
    "wof:placetype":"venue"
},
  "geometry": {"coordinates":[7.3746399879,46.2108612061],"type":"Point"}
}