{
  "type": "Feature",
  "properties": {
    "iso:country":"CH",
    "sg:address":"Rigiweg 16",
    "sg:city":"Ebikon",
    "sg:orig_category":"Fachdetailhandel in Verkaufsr\u00e4umen",
    "sg:phone":"+41 79 352 92 30",
    "sg:postcode":"6030",
    "sg:province":"Luzern",
    "wof:name":"Atelier Keller",
    "wof:placetype":"venue"
},
  "geometry": {"coordinates":[8.329875946,47.0705566406],"type":"Point"}
}