{
  "type": "Feature",
  "properties": {
    "iso:country":"CH",
    "sg:address":"Br\u00fcggershalten",
    "sg:city":"Kerns",
    "sg:orig_category":"Verwertung von Milch",
    "sg:postcode":"6064",
    "sg:province":"Obwalden",
    "wof:name":"Milchverwertungsgenossenschaft Acheri Kerns",
    "wof:placetype":"venue"
},
  "geometry": {"coordinates":[8.2749996185,46.9008216858],"type":"Point"}
}