{
  "type": "Feature",
  "properties": {
    "iso:country":"CH",
    "sg:address":"Sch\u00fctzenmattstrasse 7 6438 Ibach. Postfach",
    "sg:city":"Ibach",
    "sg:orig_category":"Handel mit Motorr\u00e4dern, Teilen U Zubeh\u00f6r Instandhaltung U Reparatur von Motorr\u00e4dern",
    "sg:postcode":"6438",
    "sg:province":"Schwyz",
    "wof:name":"Velos Motos Helbling, Inh. Patric B\u00fcrcher",
    "wof:placetype":"venue"
},
  "geometry": {"coordinates":[8.6451864243,47.0127792358],"type":"Point"}
}