{
  "type": "Feature",
  "properties": {
    "iso:country":"CH",
    "sg:address":"R\u00fctistrasse 7",
    "sg:city":"Spreitenbach",
    "sg:orig_category":"Instandhaltung U Reparatur von Automobilen",
    "sg:phone":"+41 56 401 56 55",
    "sg:postcode":"8957",
    "sg:province":"Aargau",
    "wof:name":"Heggli Andreas",
    "wof:placetype":"venue"
},
  "geometry": {"coordinates":[8.3733501434,47.420665741],"type":"Point"}
}