{
  "type": "Feature",
  "properties": {
    "iso:country":"CH",
    "sg:address":"Chamerstrasse 63 6300 Zug. Postfach",
    "sg:city":"Zug",
    "sg:orig_category":"Sonstige mit der Informatik verbundene T\u00e4tigkeiten",
    "sg:postcode":"6300",
    "sg:province":"Zug",
    "wof:name":"Want Gmbh Dienstleistungen Im Bereich Der Informations- U. Kommunikationstechnologie Usw. Software-l\u00f6sungen; Entwicklung U. Verkauf",
    "wof:placetype":"venue"
},
  "geometry": {"coordinates":[8.5011100769,47.1760177612],"type":"Point"}
}