{
  "type": "Feature",
  "properties": {
    "iso:country":"CH",
    "sg:address":"Im Lindengarten 5",
    "sg:city":"Oberuzwil",
    "sg:orig_category":"Werbegrafikateliers",
    "sg:phone":"+41 71 940 01 44",
    "sg:postcode":"9242",
    "sg:province":"St. Gallen",
    "wof:name":"Linden-grafik",
    "wof:placetype":"venue"
},
  "geometry": {"coordinates":[9.1287326813,47.4274177551],"type":"Point"}
}