{
  "type": "Feature",
  "properties": {
    "addr:full":"Lengacher Fl\u00fceli-ranft Obwalden 6073",
    "addr:postcode":"6073",
    "iso:country":"CH",
    "sg:address":"Lengacher",
    "sg:city":"Fl\u00fceli-ranft",
    "sg:classifiers":[
        {
            "category":"Building & Trades",
            "subcategory":"Construction",
            "type":"Services"
        }
    ],
    "sg:phone":"+41 41 666 27 80",
    "sg:postcode":"6073",
    "sg:province":"Obwalden",
    "sg:tags":[
        "balcony",
        "add-on"
    ],
    "wof:name":"Josef Rohrer Ag",
    "wof:placetype":"venue"
},
  "geometry": {"coordinates":[8.228328,46.860973],"type":"Point"}
}