{
  "type": "Feature",
  "properties": {
    "iso:country":"CH",
    "sg:address":"6809",
    "sg:city":"Medeglia",
    "sg:classifiers":[
        {
            "category":"Restaurant",
            "type":"Food & Drink"
        }
    ],
    "sg:phone":"+41 91 946 30 19",
    "sg:postcode":"6809",
    "sg:province":"Ticino",
    "wof:name":"Ristorante Corte Del Duca",
    "wof:placetype":"venue"
},
  "geometry": {"coordinates":[8.9684247971,46.1153564453],"type":"Point"}
}