{
  "type": "Feature",
  "properties": {
    "iso:country":"CH",
    "sg:address":"Obere Hinterwies 2",
    "sg:city":"Speicher",
    "sg:orig_category":"Naturheil\u00e4rzte and Heilpraktiker",
    "sg:phone":"+41 71 344 33 49",
    "sg:postcode":"9042",
    "sg:province":"Appenzell Ausserrhoden",
    "wof:name":"Udo F\u00e4hnrich Naturarzt",
    "wof:placetype":"venue"
},
  "geometry": {"coordinates":[9.4347457886,47.4158554077],"type":"Point"}
}