{
  "type": "Feature",
  "properties": {
    "iso:country":"CH",
    "sg:address":"Hauptstrasse 43",
    "sg:city":"Reiden",
    "sg:orig_category":"Tierarztpraxis",
    "sg:phone":"+41 62 758 14 15",
    "sg:postcode":"6260",
    "sg:province":"Luzern",
    "wof:name":"Dres Bl\u00e4ttler & Steinmann Tier\u00e4rzte",
    "wof:placetype":"venue"
},
  "geometry": {"coordinates":[7.9712958336,47.2456703186],"type":"Point"}
}