{
  "type": "Feature",
  "properties": {
    "iso:country":"CH",
    "sg:address":"Piazza Bariani",
    "sg:city":"Genestrerio",
    "sg:orig_category":"Nationale Postdienste",
    "sg:phone":"+41 91 647 13 58",
    "sg:postcode":"6852",
    "sg:province":"Ticino",
    "wof:name":"La Posta Svizzera",
    "wof:placetype":"venue"
},
  "geometry": {"coordinates":[8.9605751038,45.8548202515],"type":"Point"}
}