{
  "type": "Feature",
  "properties": {
    "iso:country":"CH",
    "sg:address":"Schulstrasse 42 8542 Wiesendangen. Postfach 166",
    "sg:city":"Wiesendangen",
    "sg:orig_category":"Sonstiger Grosshandel",
    "sg:phone":"+41 52 337 27 93",
    "sg:postcode":"8542",
    "sg:province":"Z\u00fcrich",
    "wof:name":"Wetraco, Erb D.",
    "wof:placetype":"venue"
},
  "geometry": {"coordinates":[8.7915344238,47.5219993591],"type":"Point"}
}