{
  "type": "Feature",
  "properties": {
    "iso:country":"CH",
    "sg:address":"Z\u00fcrcherstrasse 69",
    "sg:city":"Basel",
    "sg:orig_category":"Unclassifiable Establishments",
    "sg:postcode":"4052",
    "sg:province":"Basel-Stadt",
    "wof:name":"Promedia Werbeberatung Gmbh",
    "wof:placetype":"venue"
},
  "geometry": {"coordinates":[7.6095948219,47.5540504456],"type":"Point"}
}