{
  "type": "Feature",
  "properties": {
    "iso:country":"CH",
    "sg:address":"Bruggm\u00fchlestrasse 9403 Goldach. Postfach",
    "sg:city":"Goldach",
    "sg:orig_category":"Herstellung von Konstruktionsteilen, Fertigbauteilen U Ausbauelementen aus Holz",
    "sg:phone":"+41 71 844 78 44",
    "sg:postcode":"9403",
    "sg:province":"St. Gallen",
    "wof:name":"Npm Ag, Goldach",
    "wof:placetype":"venue"
},
  "geometry": {"coordinates":[9.4617614746,47.4771347046],"type":"Point"}
}