{
  "type": "Feature",
  "properties": {
    "iso:country":"CH",
    "sg:address":"Pfannenstielstrasse 142",
    "sg:city":"Meilen",
    "sg:orig_category":"Elektroinstallation",
    "sg:phone":"+41 17931212",
    "sg:postcode":"8706",
    "sg:province":"Z\u00fcrich",
    "wof:name":"Hersperger E. Elektrotechnik",
    "wof:placetype":"venue"
},
  "geometry": {"coordinates":[8.6558008194,47.2710876465],"type":"Point"}
}