{
  "type": "Feature",
  "properties": {
    "iso:country":"CH",
    "sg:address":"Ibelweg 9",
    "sg:city":"Zug",
    "sg:orig_category":"Sonstiger Grosshandel",
    "sg:phone":"+41 41 763 60 40",
    "sg:postcode":"6300",
    "sg:province":"Zug",
    "wof:name":"Torno Art Collection Ag",
    "wof:placetype":"venue"
},
  "geometry": {"coordinates":[8.5244073868,47.1809158325],"type":"Point"}
}