{
  "type": "Feature",
  "properties": {
    "iso:country":"CH",
    "sg:address":"Baselstrasse 60",
    "sg:city":"Grellingen",
    "sg:orig_category":"Detailhandel mit Metallwaren, Anstrichmitteln, Glaswaren, Bau U Heimwerkerbedarf Mechanische Werkst\u00e4",
    "sg:phone":"+41 61 741 31 41",
    "sg:postcode":"4203",
    "sg:province":"Basel-Landschaft",
    "wof:name":"Technische Werkstatt Amacher Ag",
    "wof:placetype":"venue"
},
  "geometry": {"coordinates":[7.5984539986,47.4432220459],"type":"Point"}
}