{
  "type": "Feature",
  "properties": {
    "iso:country":"CH",
    "sg:address":"Sentiero Delle Vigne 13",
    "sg:city":"Locarno",
    "sg:orig_category":"Sportvereine Eissport Eishockey",
    "sg:phone":"+41 91 756 60 40",
    "sg:postcode":"6605",
    "sg:province":"Ticino",
    "wof:name":"Club Di Pattinaggio Ascona",
    "wof:placetype":"venue"
},
  "geometry": {"coordinates":[8.791633606,46.1718025208],"type":"Point"}
}