{
  "type": "Feature",
  "properties": {
    "iso:country":"CH",
    "sg:address":"Alleestrasse 42",
    "sg:city":"Romanshorn",
    "sg:orig_category":"Detailhandel mit Damenbekleidung Detailhandel mit Textilien",
    "sg:phone":"+41 19501150",
    "sg:postcode":"8590",
    "sg:province":"Thurgau",
    "wof:name":"Modehaus M\u00fchlemann Gmbh",
    "wof:placetype":"venue"
},
  "geometry": {"coordinates":[8.7811584473,47.3688964844],"type":"Point"}
}