{
  "type": "Feature",
  "properties": {
    "iso:country":"CH",
    "sg:address":"Gewerbestrasse 6",
    "sg:city":"Steinmaur",
    "sg:orig_category":"Vermietung U Verpachtung von eigenen Immobilien",
    "sg:postcode":"8162",
    "sg:province":"Z\u00fcrich",
    "wof:name":"Urfer Immobilien Ag, Bad Ragaz",
    "wof:placetype":"venue"
},
  "geometry": {"coordinates":[9.5082798004,47.0070762634],"type":"Point"}
}