{
  "type": "Feature",
  "properties": {
    "iso:country":"CH",
    "sg:address":"Allmengasse 1",
    "sg:city":"Langenthal",
    "sg:orig_category":"Unternehmensberatung",
    "sg:phone":"+41 71 227 29 00",
    "sg:postcode":"4900",
    "sg:province":"Bern",
    "wof:name":"D&a Management Und Beratung Ag",
    "wof:placetype":"venue"
},
  "geometry": {"coordinates":[9.3754863739,47.4248199463],"type":"Point"}
}