{
  "type": "Feature",
  "properties": {
    "iso:country":"CH",
    "sg:address":"Amperestrasse 3",
    "sg:city":"Steinach",
    "sg:orig_category":"Herstellung von sonstigen elektrischen Ausr\u00fcstungen",
    "sg:phone":"+41 71 447 04 47",
    "sg:postcode":"9323",
    "sg:province":"St. Gallen",
    "wof:name":"Tyco Electronics (schweiz) Ag",
    "wof:placetype":"venue"
},
  "geometry": {"coordinates":[9.447791,47.499649],"type":"Point"}
}