{
  "type": "Feature",
  "properties": {
    "iso:country":"CH",
    "sg:address":"6703",
    "sg:city":"Osogna",
    "sg:orig_category":"Gewinnung von Natursteinen f\u00fcr den Bau Herstellung von sonstigen Produkten aus nichtmetallischen Min",
    "sg:phone":"+41 91 863 22 75",
    "sg:postcode":"6703",
    "sg:province":"Ticino",
    "wof:name":"Giuliano Mattioli Industria Granito",
    "wof:placetype":"venue"
},
  "geometry": {"coordinates":[8.9886751175,46.3087654114],"type":"Point"}
}