{
  "type": "Feature",
  "properties": {
    "iso:country":"CH",
    "sg:address":"Libellenstrasse 44 6000 Luzern. Postfach",
    "sg:city":"Luzern",
    "sg:orig_category":"Wirtschaftspr\u00fcfung, Steuerberatung U Treuhand",
    "sg:postcode":"6003",
    "sg:province":"Luzern",
    "wof:name":"Caste Consulting Gmbh",
    "wof:placetype":"venue"
},
  "geometry": {"coordinates":[8.3083763123,47.0637741089],"type":"Point"}
}