{
  "type": "Feature",
  "properties": {
    "iso:country":"CH",
    "sg:address":"Birkenweg 1 8840 Einsiedeln. Postfach",
    "sg:city":"Bennau",
    "sg:orig_category":"G\u00fcterbef\u00f6rderung im Strassenverkehr",
    "sg:postcode":"8836",
    "sg:province":"Schwyz",
    "wof:name":"Cavelti Armin, Transporte",
    "wof:placetype":"venue"
},
  "geometry": {"coordinates":[8.7504091263,47.1321182251],"type":"Point"}
}