{
  "type": "Feature",
  "properties": {
    "iso:country":"CH",
    "sg:address":"Kreuzmattring 7",
    "sg:city":"Kastanienbaum",
    "sg:orig_category":"Wirtschaftspr\u00fcfung, Steuerberatung U Treuhand",
    "sg:phone":"+41 41 340 22 66",
    "sg:postcode":"6047",
    "sg:province":"Luzern",
    "wof:name":"Isler Treuhand Und Buchhaltungsservice",
    "wof:placetype":"venue"
},
  "geometry": {"coordinates":[8.3353910446,47.0131492615],"type":"Point"}
}