{
  "type": "Feature",
  "properties": {
    "iso:country":"CH",
    "sg:address":"Krestisweg 2",
    "sg:city":"Triesen",
    "sg:orig_category":"Maschinen and Apparate divers Grosshandel",
    "sg:phone":"+423 392 41 85",
    "sg:postcode":"9495",
    "wof:name":"Riesen Ag Getr\u00e4nke-systeme",
    "wof:placetype":"venue"
},
  "geometry": {"coordinates":[9.533657074,47.1034355164],"type":"Point"}
}