{
  "type": "Feature",
  "properties": {
    "iso:country":"CH",
    "sg:address":"Looslistrasse 15",
    "sg:city":"Bern",
    "sg:orig_category":"Sonstiger Grosshandel",
    "sg:phone":"+41 31 751 38 80",
    "sg:postcode":"3027",
    "sg:province":"Bern",
    "wof:name":"Plettac Electronics (schweiz) Ag",
    "wof:placetype":"venue"
},
  "geometry": {"coordinates":[7.3990750313,46.9481124878],"type":"Point"}
}