{
  "type": "Feature",
  "properties": {
    "iso:country":"CH",
    "sg:address":"Schlossstrasse 33 4133 Pratteln. Postfach",
    "sg:city":"Pratteln",
    "sg:orig_category":"Herstellung von sonstiger Bekleidung U Bekleidungszubeh\u00f6r",
    "sg:phone":"+41 61 821 13 60",
    "sg:postcode":"4133",
    "sg:province":"Basel-Landschaft",
    "wof:name":"Kalimera Kinderartikelb\u00f6rse Gmbh",
    "wof:placetype":"venue"
},
  "geometry": {"coordinates":[7.6948709488,47.5199317932],"type":"Point"}
}