{
  "type": "Feature",
  "properties": {
    "iso:country":"CH",
    "sg:address":"Albisstrasse 15",
    "sg:city":"Adliswil",
    "sg:orig_category":"Zahnarztpraxen",
    "sg:phone":"+41 17103475",
    "sg:postcode":"8134",
    "sg:province":"Z\u00fcrich",
    "wof:name":"Dr. Med. Dent. Ferenc Bay Zahnarzt",
    "wof:placetype":"venue"
},
  "geometry": {"coordinates":[8.5256528854,47.310798645],"type":"Point"}
}