{
  "type": "Feature",
  "properties": {
    "iso:country":"CH",
    "sg:address":"Unterheid 3857 Unterbach Be. Postfach 276",
    "sg:city":"Meiringen",
    "sg:orig_category":"Grosshandel mit Erzen U Metallen Herstellung von Metallkonstruktionen",
    "sg:phone":"+41 33 971 25 89",
    "sg:postcode":"3860",
    "sg:province":"Bern",
    "wof:name":"A. B. Crivelli Ag",
    "wof:placetype":"venue"
},
  "geometry": {"coordinates":[8.1095075607,46.7373352051],"type":"Point"}
}