{
  "type": "Feature",
  "properties": {
    "iso:country":"CH",
    "sg:address":"Letzigraben 136",
    "sg:city":"Z\u00fcrich",
    "sg:orig_category":"Fotografische Ateliers",
    "sg:phone":"+41 56 664 42 52",
    "sg:postcode":"8047",
    "sg:province":"Z\u00fcrich",
    "wof:name":"Bernhard K\u00e4gi Fotografisches Atelier",
    "wof:placetype":"venue"
},
  "geometry": {"coordinates":[8.5388355255,47.2927474976],"type":"Point"}
}