{
  "type": "Feature",
  "properties": {
    "addr:full":"Im Fennen 9 8867 Niederurnen. Postfach Niederurnen Glarus 8867",
    "addr:housenumber":"9",
    "addr:postcode":"8867 niederurnen. postfach;8867",
    "addr:street":"Im Fennen",
    "iso:country":"CH",
    "sg:address":"Im Fennen 9 8867 Niederurnen. Postfach",
    "sg:city":"Niederurnen",
    "sg:orig_category":"Bauschreinerei Herstellung von Konstruktionsteilen, Fertigbauteilen U Ausbauelementen aus Holz",
    "sg:phone":"+41 55 620 12 60",
    "sg:postcode":"8867",
    "sg:province":"Glarus",
    "wof:name":"Thoma & Noser Gmbh",
    "wof:placetype":"venue"
},
  "geometry": {"coordinates":[9.041468,47.134815],"type":"Point"}
}