{
  "type": "Feature",
  "properties": {
    "addr:full":"1965 Chandolin-savi\u00e8se Valais 1965",
    "addr:housenumber":"1965",
    "addr:postcode":"1965",
    "addr:street":"Chandolin-Savie\u0300Se Valais",
    "iso:country":"CH",
    "sg:address":"1965",
    "sg:city":"Chandolin-savi\u00e8se",
    "sg:orig_category":"Bauspenglerei Dachdeckerei",
    "sg:phone":"+41 27 395 14 62",
    "sg:postcode":"1965",
    "sg:province":"Valais",
    "wof:name":"Dubuis Fernand Entreprise De Chauffage, Installat. Sanitaires, Etc.",
    "wof:placetype":"venue"
},
  "geometry": {"coordinates":[7.338539,46.250473],"type":"Point"}
}