{
  "type": "Feature",
  "properties": {
    "iso:country":"CH",
    "sg:address":"T\u00f6pferstrasse 10",
    "sg:city":"Luzern",
    "sg:orig_category":"Interessenvertretungen",
    "sg:postcode":"6004",
    "sg:province":"Luzern",
    "wof:name":"Tqm Forum",
    "wof:placetype":"venue"
},
  "geometry": {"coordinates":[8.3103466034,47.0553131104],"type":"Point"}
}