{
  "type": "Feature",
  "properties": {
    "iso:country":"CH",
    "sg:address":"Rietwisstrasse 25",
    "sg:city":"Herisau",
    "sg:orig_category":"Vorschulen, Kinderg\u00e4rten",
    "sg:phone":"+41 52 383 25 81",
    "sg:postcode":"9100",
    "sg:province":"Appenzell Ausserrhoden",
    "wof:name":"Kindergarten Rikon",
    "wof:placetype":"venue"
},
  "geometry": {"coordinates":[8.7960557938,47.4453773499],"type":"Point"}
}