{
  "type": "Feature",
  "properties": {
    "iso:country":"CH",
    "sg:address":"R\u00e4mistrasse 101",
    "sg:city":"Z\u00fcrich",
    "sg:orig_category":"Unclassifiable Establishments",
    "sg:postcode":"8006",
    "sg:province":"Z\u00fcrich",
    "wof:name":"Europ\u00e4ische Stiftung F\u00fcr Mathematik",
    "wof:placetype":"venue"
},
  "geometry": {"coordinates":[8.5487222672,47.3760719299],"type":"Point"}
}