{
  "type": "Feature",
  "properties": {
    "iso:country":"CH",
    "sg:address":"Casa Ghielmi 46",
    "sg:city":"Cabbio",
    "sg:orig_category":"Werbegrafikateliers",
    "sg:phone":"+41 400669",
    "sg:postcode":"6838",
    "sg:province":"Ticino",
    "wof:name":"Alfred Bauer Grafisches Atelier",
    "wof:placetype":"venue"
},
  "geometry": {"coordinates":[8.6021375656,47.326839447],"type":"Point"}
}