{
  "type": "Feature",
  "properties": {
    "iso:country":"CH",
    "sg:address":"Crestas Voa 9 7077 Valbella. Postfach",
    "sg:city":"Valbella",
    "sg:orig_category":"Non-Classified Establishments",
    "sg:phone":"+41 81 356 31 31",
    "sg:postcode":"7077",
    "sg:province":"Graubunden",
    "wof:name":"Laundry J.-holding Ag",
    "wof:placetype":"venue"
},
  "geometry": {"coordinates":[9.5432186127,46.752456665],"type":"Point"}
}