{
  "type": "Feature",
  "properties": {
    "iso:country":"CH",
    "sg:address":"Rainweg 15",
    "sg:city":"K\u00fcsnacht",
    "sg:classifiers":[
        {
            "category":"Communications",
            "subcategory":"Film & Video Production",
            "type":"Services"
        }
    ],
    "sg:phone":"+41 19108992",
    "sg:postcode":"8700",
    "sg:province":"Z\u00fcrich",
    "sg:tags":[
        "screens",
        "flat",
        "plasma"
    ],
    "wof:name":"Pmc Peter M\u00fcller Consulting",
    "wof:placetype":"venue"
},
  "geometry": {"coordinates":[8.5914764404,47.3095245361],"type":"Point"}
}