{
  "type": "Feature",
  "properties": {
    "iso:country":"CH",
    "sg:address":"Scheibenb\u00f6hl",
    "sg:city":"Waldstatt",
    "sg:classifiers":[
        {
            "category":"Restaurant",
            "type":"Food & Drink"
        }
    ],
    "sg:phone":"+41 55 410 12 21",
    "sg:postcode":"9104",
    "sg:province":"Appenzell Ausserrhoden",
    "wof:name":"Restaurant R\u00f6ssli",
    "wof:placetype":"venue"
},
  "geometry": {"coordinates":[8.7773323059,47.2009429932],"type":"Point"}
}