{
  "type": "Feature",
  "properties": {
    "iso:country":"CH",
    "sg:address":"Aalmattenweg 46",
    "sg:city":"Nidau",
    "sg:orig_category":"Vorschulen, Kinderg\u00e4rten",
    "sg:phone":"+41 32 331 34 50",
    "sg:postcode":"2560",
    "sg:province":"Bern",
    "wof:name":"Kindergarten Aalmatten I & Ii",
    "wof:placetype":"venue"
},
  "geometry": {"coordinates":[7.2470331192,47.1229515076],"type":"Point"}
}