{
  "type": "Feature",
  "properties": {
    "iso:country":"CH",
    "sg:address":"Bederstrasse 85",
    "sg:city":"Z\u00fcrich",
    "sg:orig_category":"Instandhaltung U Reparatur von Automobilen Tankstellen",
    "sg:phone":"+41 41 870 22 33",
    "sg:postcode":"8002",
    "sg:province":"Z\u00fcrich",
    "wof:name":"Nord-s\u00fcd Garage Ag",
    "wof:placetype":"venue"
},
  "geometry": {"coordinates":[8.6508302689,46.8718147278],"type":"Point"}
}