{
  "type": "Feature",
  "properties": {
    "iso:country":"CH",
    "sg:address":"Bei Der Post",
    "sg:city":"T\u00e4sch",
    "sg:orig_category":"Detailhandel mit Geschenkartikeln U Souvenirs Sonstiger Grosshandel",
    "sg:phone":"+41 27 967 21 28",
    "sg:postcode":"3929",
    "sg:province":"Valais",
    "wof:name":"Boutique Imbo, Theo Imboden",
    "wof:placetype":"venue"
},
  "geometry": {"coordinates":[7.7763252258,46.069694519],"type":"Point"}
}