{
  "type": "Feature",
  "properties": {
    "iso:country":"CH",
    "sg:address":"Industrieplatz 6",
    "sg:city":"Neuhausen",
    "sg:orig_category":"RESTAURANTS: TEA-ROOMS",
    "sg:postcode":"8212",
    "sg:province":"Schaffhausen",
    "wof:name":"Jenny Erika",
    "wof:placetype":"venue"
},
  "geometry": {"coordinates":[8.6185321808,47.6796531677],"type":"Point"}
}