{
  "type": "Feature",
  "properties": {
    "iso:country":"CH",
    "sg:address":"Rosenrain 5",
    "sg:city":"Winterthur",
    "sg:orig_category":"Ingenieurb\u00fcros Umwelttechnik and \u00d6kologie",
    "sg:phone":"+41 52 212 56 15",
    "sg:postcode":"8400",
    "sg:province":"Z\u00fcrich",
    "wof:name":"Ibut Ingenieurberatung F\u00fcr Umwelttechnologien",
    "wof:placetype":"venue"
},
  "geometry": {"coordinates":[8.7248287201,47.5119857788],"type":"Point"}
}