{
  "type": "Feature",
  "properties": {
    "iso:country":"CH",
    "sg:address":"Rue De Fin-de-praz 22 2024 St-aubin-sauges. Postfach",
    "sg:city":"St-aubin-sauges",
    "sg:orig_category":"Fachdetailhandel in Verkaufsr\u00e4umen",
    "sg:postcode":"2024",
    "sg:province":"Neuch\u00e2tel",
    "wof:name":"D\u00e9colletage Tendon S\u00e0rl",
    "wof:placetype":"venue"
},
  "geometry": {"coordinates":[6.7794499397,46.8963546753],"type":"Point"}
}