{
  "type": "Feature",
  "properties": {
    "iso:country":"CH",
    "sg:address":"Rue Des Clos 7",
    "sg:city":"Bevaix",
    "sg:orig_category":"Grosshandel mit Tabakwaren",
    "sg:phone":"+41 32 846 24 54",
    "sg:postcode":"2022",
    "sg:province":"Neuch\u00e2tel",
    "wof:name":"La Cigari\u00e8re Cigares & Tabacs Engros",
    "wof:placetype":"venue"
},
  "geometry": {"coordinates":[6.8176941872,46.931060791],"type":"Point"}
}