{
  "type": "Feature",
  "properties": {
    "iso:country":"CH",
    "sg:address":"Albisriederplatz 3 8003 Z\u00fcrich. Postfach 1618",
    "sg:city":"Z\u00fcrich",
    "sg:classifiers":[
        {
            "category":"Insurance",
            "subcategory":"Insurance Agent",
            "type":"Services"
        }
    ],
    "sg:phone":"+41 14002383",
    "sg:postcode":"8040",
    "sg:province":"Z\u00fcrich",
    "sg:tags":[
        "versicherungsagenturen",
        "-broker"
    ],
    "wof:name":"Vlastimir Milosavljevic Versicherungsberatung",
    "wof:placetype":"venue"
},
  "geometry": {"coordinates":[8.5100393295,47.378074646],"type":"Point"}
}