{
  "type": "Feature",
  "properties": {
    "iso:country":"CH",
    "sg:address":"Bielstrasse 1",
    "sg:city":"Wiedlisbach",
    "sg:orig_category":"RESTAURANTS: TEA-ROOMS",
    "sg:phone":"+41 32 636 27 45",
    "sg:postcode":"4537",
    "sg:province":"Bern",
    "wof:name":"Restaurant Rebstock, E. K\u00e4nzig",
    "wof:placetype":"venue"
},
  "geometry": {"coordinates":[7.6456990242,47.2513504028],"type":"Point"}
}