{
  "type": "Feature",
  "properties": {
    "iso:country":"CH",
    "sg:address":"Bahnhofstrasse 19",
    "sg:city":"Mettmenstetten",
    "sg:orig_category":"Kantonalbanken",
    "sg:phone":"+41 19142010",
    "sg:postcode":"8932",
    "sg:province":"Z\u00fcrich",
    "wof:name":"Z\u00fcrcher Kantonalbank",
    "wof:placetype":"venue"
},
  "geometry": {"coordinates":[8.5915660858,47.3050346375],"type":"Point"}
}