{
  "type": "Feature",
  "properties": {
    "iso:country":"CH",
    "sg:address":"Fischerm\u00e4tteliweg 11",
    "sg:city":"Burgdorf",
    "sg:orig_category":"Unclassifiable Establishments",
    "sg:postcode":"3400",
    "sg:province":"Bern",
    "wof:name":"Cr\u00e9a Comm Esther Gr\u00fcnig-sch\u00f6ni",
    "wof:placetype":"venue"
},
  "geometry": {"coordinates":[7.6387472153,47.0482254028],"type":"Point"}
}