{
  "type": "Feature",
  "properties": {
    "iso:country":"CH",
    "sg:address":"M\u00f6sliweg 6",
    "sg:city":"M\u00fchleberg",
    "sg:classifiers":[
        {
            "category":"Building & Trades",
            "subcategory":"Construction",
            "type":"Services"
        }
    ],
    "sg:phone":"+41 31 751 02 27",
    "sg:postcode":"3203",
    "sg:province":"Bern",
    "sg:tags":[
        "work",
        "public"
    ],
    "wof:name":"Kuster G\u00c4rten",
    "wof:placetype":"venue"
},
  "geometry": {"coordinates":[7.280246,46.961998],"type":"Point"}
}