{
  "type": "Feature",
  "properties": {
    "iso:country":"CH",
    "sg:address":"Beundenstrasse 6",
    "sg:city":"Attiswil",
    "sg:orig_category":"Architekturb\u00fcros",
    "sg:phone":"+41 81 933 12 45",
    "sg:postcode":"4536",
    "sg:province":"Bern",
    "wof:name":"Andr\u00e9 Sax Architekturb\u00fcro",
    "wof:placetype":"venue"
},
  "geometry": {"coordinates":[9.10314,46.75132],"type":"Point"}
}