{
  "type": "Feature",
  "properties": {
    "iso:country":"CH",
    "sg:address":"Burgunderstrasse 36",
    "sg:city":"Basel",
    "sg:orig_category":"Unclassifiable Establishments",
    "sg:postcode":"4051",
    "sg:province":"Basel-Stadt",
    "wof:name":"V Bis F Video Und Filmproduktionen Kempter Und Schl\u00e4pfer",
    "wof:placetype":"venue"
},
  "geometry": {"coordinates":[7.5788521767,47.5529327393],"type":"Point"}
}