{
  "type": "Feature",
  "properties": {
    "iso:country":"CH",
    "sg:address":"Rte De Soleure 145",
    "sg:city":"Bienne",
    "sg:classifiers":[
        {
            "category":"Manufacturing",
            "subcategory":"Metals",
            "type":"Manufacturing & Wholesale Goods"
        }
    ],
    "sg:phone":"+41 32 344 20 60",
    "sg:postcode":"2501",
    "sg:province":"Bern",
    "sg:tags":[
        "-",
        "machine",
        "equipment",
        "engineering",
        "machinery",
        "mechanical"
    ],
    "wof:name":"Scemama Sa",
    "wof:placetype":"venue"
},
  "geometry": {"coordinates":[7.2916121483,47.1642494202],"type":"Point"}
}