{
  "type": "Feature",
  "properties": {
    "iso:country":"CH",
    "sg:address":"Chesa Murter",
    "sg:city":"S-chanf",
    "sg:orig_category":"Interessenvertretungen",
    "sg:postcode":"7525",
    "sg:province":"Graubunden",
    "wof:name":"Schweizerische Skischulstiftung",
    "wof:placetype":"venue"
},
  "geometry": {"coordinates":[9.9831314087,46.6116027832],"type":"Point"}
}