{
  "type": "Feature",
  "properties": {
    "iso:country":"CH",
    "sg:address":"Sporrengasse 2",
    "sg:city":"Schaffhausen",
    "sg:orig_category":"P\u00e9dicure",
    "sg:phone":"+41 19326963",
    "sg:postcode":"8200",
    "sg:province":"Schaffhausen",
    "wof:name":"Melanie-nelly Thalmann P\u00e9dicure & Kosmetik",
    "wof:placetype":"venue"
},
  "geometry": {"coordinates":[8.7992038727,47.3220939636],"type":"Point"}
}