{
  "type": "Feature",
  "properties": {
    "iso:country":"CH",
    "sg:address":"Bahnhofstrasse 22 4950 Huttwil. Postfach",
    "sg:city":"Huttwil",
    "sg:orig_category":"Detailhandel mit B\u00fcchern, Zeitungen, Schreib U Papeteriewaren Detailhandel mit Schreib U Papeteriewa",
    "sg:phone":"+41 32 725 10 74",
    "sg:postcode":"4950",
    "sg:province":"Bern",
    "wof:name":"Bourquin & Cie",
    "wof:placetype":"venue"
},
  "geometry": {"coordinates":[6.92853,46.992588],"type":"Point"}
}