{
  "type": "Feature",
  "properties": {
    "iso:country":"CH",
    "sg:address":"Hinterbergstrasse 86",
    "sg:city":"Z\u00fcrich",
    "sg:orig_category":"Unternehmensberatung Werbeberatung",
    "sg:postcode":"8044",
    "sg:province":"Z\u00fcrich",
    "wof:name":"Welcometickets Ag",
    "wof:placetype":"venue"
},
  "geometry": {"coordinates":[8.5572357178,47.3838768005],"type":"Point"}
}