{
  "type": "Feature",
  "properties": {
    "iso:country":"CH",
    "sg:address":"Hauptgasse 2",
    "sg:city":"H\u00e4rkingen",
    "sg:classifiers":[
        {
            "category":"Restaurant",
            "type":"Food & Drink"
        }
    ],
    "sg:phone":"+41 19153649",
    "sg:postcode":"4624",
    "sg:province":"Solothurn",
    "wof:name":"Restaurant Pflugstein",
    "wof:placetype":"venue"
},
  "geometry": {"coordinates":[8.6081485748,47.2971458435],"type":"Point"}
}