{
  "type": "Feature",
  "properties": {
    "iso:country":"CH",
    "sg:address":"Seestrasse 21",
    "sg:city":"Zollikon",
    "sg:orig_category":"Pensionskassen",
    "sg:phone":"+41 13914930",
    "sg:postcode":"8702",
    "sg:province":"Z\u00fcrich",
    "wof:name":"B\u00fcro Riethmann Ag",
    "wof:placetype":"venue"
},
  "geometry": {"coordinates":[8.567530632,47.3428268433],"type":"Point"}
}