{
  "type": "Feature",
  "properties": {
    "iso:country":"CH",
    "sg:address":"Furkastrasse 64",
    "sg:city":"Naters",
    "sg:orig_category":"R\u00fcckgewinnung U Vorbereitung f\u00fcr die Wiederverwertung Recycling",
    "sg:phone":"+41 32 924 02 77",
    "sg:postcode":"3904",
    "sg:province":"Valais",
    "wof:name":"Traimet Sa Recyglage De M\u00e9taux Pr\u00e9cieux",
    "wof:placetype":"venue"
},
  "geometry": {"coordinates":[6.8299050331,47.102809906],"type":"Point"}
}