{
  "type": "Feature",
  "properties": {
    "iso:country":"CH",
    "sg:address":"H\u00fcnenbergstrasse 17",
    "sg:city":"Cham",
    "sg:orig_category":"Sonstiger Grosshandel",
    "sg:phone":"+41 41 780 52 25",
    "sg:postcode":"6330",
    "sg:province":"Zug",
    "wof:name":"Urit, Ritter Ursula",
    "wof:placetype":"venue"
},
  "geometry": {"coordinates":[8.4545583725,47.1789550781],"type":"Point"}
}