{
  "type": "Feature",
  "properties": {
    "iso:country":"CH",
    "sg:address":"Innere Auenstrasse 14",
    "sg:city":"Bassersdorf",
    "sg:orig_category":"Textilveredlung",
    "sg:phone":"+41 33 243 46 01",
    "sg:postcode":"8303",
    "sg:province":"Z\u00fcrich",
    "wof:name":"Urs Thimm F\u00e4rberei Zum Kl\u00f6sterli",
    "wof:placetype":"venue"
},
  "geometry": {"coordinates":[7.6725668907,46.7302932739],"type":"Point"}
}