{
  "type": "Feature",
  "properties": {
    "iso:country":"CH",
    "sg:address":"Lotzwilstrasse 36",
    "sg:city":"Langenthal",
    "sg:orig_category":"RESTAURANTS: TEA-ROOMS",
    "sg:postcode":"4900",
    "sg:province":"Bern",
    "wof:name":"Althaus-pfenninger + Co.",
    "wof:placetype":"venue"
},
  "geometry": {"coordinates":[7.7837882042,47.2076263428],"type":"Point"}
}