{
  "type": "Feature",
  "properties": {
    "iso:country":"CH",
    "sg:address":"Hortweg 1",
    "sg:city":"Thalwil",
    "sg:orig_category":"Architekturb\u00fcros",
    "sg:phone":"+41 17210914",
    "sg:postcode":"8800",
    "sg:province":"Z\u00fcrich",
    "wof:name":"Thomas Schoch Architekturb\u00fcro",
    "wof:placetype":"venue"
},
  "geometry": {"coordinates":[8.562264,47.294075],"type":"Point"}
}