{
  "type": "Feature",
  "properties": {
    "iso:country":"CH",
    "sg:address":"Chemin De Tirelonge 28",
    "sg:city":"Onex",
    "sg:orig_category":"Grosshandel mit Nahrungsmitteln, Getr\u00e4nken U Tabakwaren Grosshandel mit Parf\u00fcmerieartikeln U K\u00f6rperp",
    "sg:phone":"+41 22 860 19 52",
    "sg:postcode":"1213",
    "sg:province":"Gen\u00e8ve",
    "wof:name":"Bio Top Distribution Sarl",
    "wof:placetype":"venue"
},
  "geometry": {"coordinates":[6.1091752052,46.1833953857],"type":"Point"}
}