{
  "type": "Feature",
  "properties": {
    "iso:country":"CH",
    "sg:address":"Waffenplatzstrasse 78 8001 Z\u00fcrich. Postfach",
    "sg:city":"Z\u00fcrich",
    "sg:orig_category":"Wirtschaftspr\u00fcfung, Steuerberatung U Treuhand",
    "sg:phone":"+41 12021802",
    "sg:postcode":"8001",
    "sg:province":"Z\u00fcrich",
    "wof:name":"Jaminco Services Ag Dienstleistungen Auf D. Gebiet Der Wirtschaftl. Organisation Usw",
    "wof:placetype":"venue"
},
  "geometry": {"coordinates":[8.5267572403,47.3559341431],"type":"Point"}
}