{
  "type": "Feature",
  "properties": {
    "iso:country":"CH",
    "sg:address":"G\u00fctschstrasse 47 8122 Binz. Postfach",
    "sg:city":"Binz",
    "sg:orig_category":"Finanzierungsinstitutionen",
    "sg:postcode":"8122",
    "sg:province":"Z\u00fcrich",
    "wof:name":"Trovato Sandro Finanzoptimierung",
    "wof:placetype":"venue"
},
  "geometry": {"coordinates":[8.6295547485,47.3548355103],"type":"Point"}
}