{
  "type": "Feature",
  "properties": {
    "iso:country":"CH",
    "sg:address":"Wiesentalstrasse 126 7000 Chur. Postfach",
    "sg:city":"Chur",
    "sg:orig_category":"Non-Classified Establishments",
    "sg:phone":"+41 81 353 70 77",
    "sg:postcode":"7000",
    "sg:province":"Graubunden",
    "wof:name":"Verdo Holding Und Verwaltungs Ag",
    "wof:placetype":"venue"
},
  "geometry": {"coordinates":[9.5304498672,46.8637886047],"type":"Point"}
}