{
  "type": "Feature",
  "properties": {
    "iso:country":"CH",
    "sg:address":"M\u00fchlestiegstrasse 34 4125 Riehen. Postfach",
    "sg:city":"Riehen",
    "sg:orig_category":"Interessenvertretungen",
    "sg:postcode":"4125",
    "sg:province":"Basel-Stadt",
    "wof:name":"Stiftung Wohlfahrt Und Soziale Gerechtigkeit F\u00fcr Alle Erforscht Gesellschaftliche U. \u00f6kologische Folgen Aus Der Globalisierten Weltwirtschaft Usw",
    "wof:placetype":"venue"
},
  "geometry": {"coordinates":[7.6482977867,47.5781593323],"type":"Point"}
}