{
  "type": "Feature",
  "properties": {
    "iso:country":"CH",
    "sg:address":"Wolfsmattstrasse 9",
    "sg:city":"Dietikon",
    "sg:orig_category":"Wirtschaftspr\u00fcfung, Steuerberatung U Treuhand",
    "sg:phone":"+41 17411553",
    "sg:postcode":"8953",
    "sg:province":"Z\u00fcrich",
    "wof:name":"Wyss Hans Peter",
    "wof:placetype":"venue"
},
  "geometry": {"coordinates":[8.4090957642,47.400100708],"type":"Point"}
}