{
  "type": "Feature",
  "properties": {
    "iso:country":"CH",
    "sg:address":"Place Centrale 8",
    "sg:city":"Martigny",
    "sg:classifiers":[
        {
            "category":"Banks & Credit Unions",
            "subcategory":"Investment Brokerage",
            "type":"Services"
        }
    ],
    "sg:phone":"+41 41 870 68 76",
    "sg:postcode":"1920",
    "sg:province":"Valais",
    "sg:tags":[
        "caf\u00e9s",
        "tea-rooms",
        "restaurants"
    ],
    "wof:name":"Birrer-huguenin Romy, Caf\u00e9 Kristall",
    "wof:placetype":"venue"
},
  "geometry": {"coordinates":[8.6441907883,46.8816986084],"type":"Point"}
}