{
  "type": "Feature",
  "properties": {
    "iso:country":"CH",
    "sg:address":"Gamschol",
    "sg:city":"Gams",
    "sg:orig_category":"Kalb U Schweine-M\u00e4sterei U Zucht",
    "sg:postcode":"9473",
    "sg:province":"St. Gallen",
    "wof:name":"Schweinemast Hug Gamschol Ag, Gams",
    "wof:placetype":"venue"
},
  "geometry": {"coordinates":[9.4479351044,47.2134361267],"type":"Point"}
}