{
  "type": "Feature",
  "properties": {
    "iso:country":"CH",
    "sg:address":"Via Franchini 5",
    "sg:city":"Mendrisio",
    "sg:classifiers":[
        {
            "category":"Bars & Pubs",
            "type":"Food & Drink"
        }
    ],
    "sg:phone":"+41 91 646 97 96",
    "sg:postcode":"6850",
    "sg:province":"Ticino",
    "wof:name":"Bar La Quercia",
    "wof:placetype":"venue"
},
  "geometry": {"coordinates":[8.980573,45.864853],"type":"Point"}
}