{
  "type": "Feature",
  "properties": {
    "iso:country":"CH",
    "sg:address":"Via Mondine 31a",
    "sg:city":"Losone",
    "sg:classifiers":[
        {
            "category":"Building & Trades",
            "subcategory":"Landscaping Services",
            "type":"Services"
        }
    ],
    "sg:phone":"+41 91 791 45 02",
    "sg:postcode":"6616",
    "sg:province":"Ticino",
    "sg:tags":[
        "horticulture",
        "gardening",
        "landscape"
    ],
    "wof:name":"Giardiniere Flavio Spigaglia Sagl",
    "wof:placetype":"venue"
},
  "geometry": {"coordinates":[8.7574043274,46.1653022766],"type":"Point"}
}