{
  "type": "Feature",
  "properties": {
    "iso:country":"CH",
    "sg:address":"Radm\u00fchlestrasse 16 8916 Jonen. Postfach 20",
    "sg:city":"Jonen",
    "sg:orig_category":"Mit dem Versicherungsgewerbe verbundene T\u00e4tigkeiten",
    "sg:phone":"+41 56 634 47 77",
    "sg:postcode":"8916",
    "sg:province":"Aargau",
    "wof:name":"Swissbroke Ag M\u00fcller & Partner",
    "wof:placetype":"venue"
},
  "geometry": {"coordinates":[8.3913707733,47.301361084],"type":"Point"}
}