{
  "type": "Feature",
  "properties": {
    "iso:country":"CH",
    "sg:address":"Sennweidstrasse 43 6312 Steinhausen. Postfach",
    "sg:city":"Steinhausen",
    "sg:orig_category":"Unclassifiable Establishments",
    "sg:postcode":"6312",
    "sg:province":"Zug",
    "wof:name":"Pyros Holding Ag",
    "wof:placetype":"venue"
},
  "geometry": {"coordinates":[8.483915329,47.1899223328],"type":"Point"}
}