{
  "type": "Feature",
  "properties": {
    "iso:country":"CH",
    "sg:address":"Chemin Du Foron 43",
    "sg:city":"Th\u00f4nex",
    "sg:orig_category":"Schulpflegen",
    "sg:phone":"+41 21 903 31 29",
    "sg:postcode":"1226",
    "sg:province":"Gen\u00e8ve",
    "wof:name":"Commission Scolaire De L'\u00e9cole Primaire & Secondaire",
    "wof:placetype":"venue"
},
  "geometry": {"coordinates":[6.7640500069,46.5876998901],"type":"Point"}
}