{
  "type": "Feature",
  "properties": {
    "iso:country":"CH",
    "sg:address":"Hauptstrasse 14",
    "sg:city":"Erlinsbach",
    "sg:orig_category":"Grosshandel mit Eisenwaren sowie Installationsbedarf f\u00fcr Gas, Wasser U Heizung",
    "sg:postcode":"5018",
    "sg:province":"Solothurn",
    "wof:name":"Willy Roth Ag",
    "wof:placetype":"venue"
},
  "geometry": {"coordinates":[8.0070343018,47.4067344666],"type":"Point"}
}