{
  "type": "Feature",
  "properties": {
    "iso:country":"CH",
    "sg:address":"Neuhus",
    "sg:city":"Ruswil",
    "sg:orig_category":"Konkurs- and Betreibungs\u00e4mter",
    "sg:phone":"+41 41 495 13 49",
    "sg:postcode":"6017",
    "sg:province":"Luzern",
    "wof:name":"Betreibungsamt",
    "wof:placetype":"venue"
},
  "geometry": {"coordinates":[8.1143798828,47.087310791],"type":"Point"}
}