{
  "type": "Feature",
  "properties": {
    "iso:country":"CH",
    "sg:address":"Hauptstrasse 12",
    "sg:city":"K\u00f6lliken",
    "sg:classifiers":[
        {
            "category":"Wholesale",
            "subcategory":"Motor Vehicles",
            "type":"Manufacturing & Wholesale Goods"
        }
    ],
    "sg:phone":"+41 62 723 86 06",
    "sg:postcode":"5742",
    "sg:province":"Aargau",
    "sg:tags":[
        "scooter"
    ],
    "wof:name":"Moto Leu Gmbh",
    "wof:placetype":"venue"
},
  "geometry": {"coordinates":[8.025177002,47.3384094238],"type":"Point"}
}