{
  "type": "Feature",
  "properties": {
    "iso:country":"CH",
    "sg:address":"9436",
    "sg:city":"Balgach",
    "sg:orig_category":"Vereine Gesang",
    "sg:phone":"+41 71 722 19 43",
    "sg:postcode":"9436",
    "sg:province":"St. Gallen",
    "wof:name":"Reformierter Kirchenchor",
    "wof:placetype":"venue"
},
  "geometry": {"coordinates":[9.6091337204,47.4071884155],"type":"Point"}
}