{
  "type": "Feature",
  "properties": {
    "iso:country":"CH",
    "sg:address":"Via Ferruccio Pelli 13",
    "sg:city":"Lugano",
    "sg:orig_category":"Wirtschaftspr\u00fcfung, Steuerberatung U Treuhand",
    "sg:postcode":"6900",
    "sg:province":"Ticino",
    "wof:name":"Fsf Fiduciaire, Fiduciaire Fischer St\u00e9phane",
    "wof:placetype":"venue"
},
  "geometry": {"coordinates":[6.9812169075,46.8884162903],"type":"Point"}
}