{
  "type": "Feature",
  "properties": {
    "iso:country":"CH",
    "sg:address":"Rheinfelderstrasse 1",
    "sg:city":"Sissach",
    "sg:orig_category":"Steuerberatung",
    "sg:phone":"+41 61 971 29 91",
    "sg:postcode":"4450",
    "sg:province":"Basel-Landschaft",
    "wof:name":"Edwin Peter Buser Allfinanz-beratung",
    "wof:placetype":"venue"
},
  "geometry": {"coordinates":[7.8103809357,47.464679718],"type":"Point"}
}