{
  "type": "Feature",
  "properties": {
    "iso:country":"CH",
    "sg:address":"Murerh\u00fcsli 10",
    "sg:city":"Schenkon",
    "sg:orig_category":"Fahrschulen, Flugschulen",
    "sg:phone":"+41 79 224 16 64",
    "sg:postcode":"6214",
    "sg:province":"Luzern",
    "wof:name":"Heinz Looschelders Autofahrschule",
    "wof:placetype":"venue"
},
  "geometry": {"coordinates":[9.0546579361,47.4706573486],"type":"Point"}
}