{
  "type": "Feature",
  "properties": {
    "iso:country":"CH",
    "sg:address":"Haus Gampilz 3945 Gampel. Postfach",
    "sg:city":"Gampel",
    "sg:orig_category":"Advokaturb\u00fcros Notariate",
    "sg:phone":"+41 27 932 28 48",
    "sg:postcode":"3945",
    "sg:province":"Valais",
    "wof:name":"Bernhard Schnyder Advokatur-& Notariatsb\u00fcro",
    "wof:placetype":"venue"
},
  "geometry": {"coordinates":[7.744009,46.316509],"type":"Point"}
}