{
  "type": "Feature",
  "properties": {
    "iso:country":"CH",
    "sg:address":"Dorf",
    "sg:city":"Libingen",
    "sg:orig_category":"Zimmerei, Ingenieurholzbau",
    "sg:phone":"+41 71 983 29 59",
    "sg:postcode":"9614",
    "sg:province":"St. Gallen",
    "wof:name":"Georg Hollenstein Holzbau Ag",
    "wof:placetype":"venue"
},
  "geometry": {"coordinates":[9.0229053497,47.328754425],"type":"Point"}
}