{
  "type": "Feature",
  "properties": {
    "iso:country":"CH",
    "sg:address":"Langenmoos 9",
    "sg:city":"Ossingen",
    "sg:classifiers":[
        {
            "category":"Education",
            "subcategory":"Dance Studio",
            "type":"Public Place"
        }
    ],
    "sg:phone":"+41 33 676 14 44",
    "sg:postcode":"8475",
    "sg:province":"Z\u00fcrich",
    "sg:tags":[
        "pallet"
    ],
    "wof:name":"Kander-paletten Und Holzwerk Ag",
    "wof:placetype":"venue"
},
  "geometry": {"coordinates":[7.6810369492,46.6101570129],"type":"Point"}
}