{
  "type": "Feature",
  "properties": {
    "iso:country":"CH",
    "sg:address":"Dorfstrasse 103",
    "sg:city":"Brunegg",
    "sg:orig_category":"Detailhandel mit Waren verschiedener Art, Hauptrichtung Nahrungsmittel",
    "sg:phone":"+41 62 886 93 33",
    "sg:postcode":"5505",
    "sg:province":"Aargau",
    "wof:name":"Landi Maiengr\u00fcn",
    "wof:placetype":"venue"
},
  "geometry": {"coordinates":[8.217124939,47.4190864563],"type":"Point"}
}