{
  "type": "Feature",
  "properties": {
    "iso:country":"CH",
    "sg:address":"1996",
    "sg:city":"Basse-nendaz",
    "sg:orig_category":"B\u00e4ckereien Konditoreien",
    "sg:phone":"+41 27 288 21 33",
    "sg:postcode":"1996",
    "sg:province":"Valais",
    "wof:name":"Lucien Carthoblaz Boulangerie & P\u00e2tisserie",
    "wof:placetype":"venue"
},
  "geometry": {"coordinates":[7.31218,46.190159],"type":"Point"}
}