{
  "type": "Feature",
  "properties": {
    "iso:country":"CH",
    "sg:address":"Luzernstrasse 20",
    "sg:city":"Neuenkirch",
    "sg:orig_category":"Erbringung von Dienstleistungen f\u00fcr Unternehmen",
    "sg:phone":"+41 79 646 02 80",
    "sg:postcode":"6206",
    "sg:province":"Luzern",
    "wof:name":"Air Brush Art Stingray Gerber",
    "wof:placetype":"venue"
},
  "geometry": {"coordinates":[8.2062950134,47.0978317261],"type":"Point"}
}