{
  "type": "Feature",
  "properties": {
    "iso:country":"CH",
    "sg:address":"Im Ziel 25",
    "sg:city":"Zollikerberg",
    "sg:orig_category":"Grosshandel mit M\u00f6beln, Wohnbedarf, Teppichen U Bodenbel\u00e4gen Sonstige mit der Informatik verbundene ",
    "sg:phone":"+41 13916668",
    "sg:postcode":"8125",
    "sg:province":"Z\u00fcrich",
    "wof:name":"Siegrist B. Ag",
    "wof:placetype":"venue"
},
  "geometry": {"coordinates":[8.594408989,47.346244812],"type":"Point"}
}