{
  "type": "Feature",
  "properties": {
    "iso:country":"CH",
    "sg:address":"2875 Montfaucon. Postfach",
    "sg:city":"Montfaucon",
    "sg:classifiers":[
        {
            "category":"Travel",
            "subcategory":"Hotels & Motels",
            "type":"Entertainment"
        }
    ],
    "sg:postcode":"2875",
    "sg:province":"Jura",
    "sg:tags":[
        "hotels",
        "mit",
        "restaurant"
    ],
    "wof:name":"Relais Beyeler Robert S\u00e0rl H\u00f4tel-restaurant Et Service Traiteur",
    "wof:placetype":"venue"
},
  "geometry": {"coordinates":[7.0542049408,47.2841796875],"type":"Point"}
}