{
  "type": "Feature",
  "properties": {
    "iso:country":"CH",
    "sg:address":"M\u00fcntschmiergasse 28",
    "sg:city":"Ins",
    "sg:orig_category":"Einzelhandel mit Automobilteilen U Zubeh\u00f6r",
    "sg:phone":"+41 19324685",
    "sg:postcode":"3232",
    "sg:province":"Bern",
    "wof:name":"Hans Kaufmann Pneuhaus",
    "wof:placetype":"venue"
},
  "geometry": {"coordinates":[8.7830286026,47.3309593201],"type":"Point"}
}