{
  "type": "Feature",
  "properties": {
    "iso:country":"CH",
    "sg:address":"Wabernstrasse 40",
    "sg:city":"Bern",
    "sg:classifiers":[
        {
            "category":"Utilities",
            "subcategory":"Fuel Oil & Lpg",
            "type":"Services"
        }
    ],
    "sg:phone":"+41 31 378 71 11",
    "sg:postcode":"3007",
    "sg:province":"Bern",
    "sg:tags":[
        "blasting",
        "explosive"
    ],
    "wof:name":"Batigroup Ag",
    "wof:placetype":"venue"
},
  "geometry": {"coordinates":[7.437774,46.938519],"type":"Point"}
}