{
  "type": "Feature",
  "properties": {
    "iso:country":"CH",
    "sg:address":"Chemin De Sus-vellaz",
    "sg:city":"Yens",
    "sg:orig_category":"Fachdetailhandel in Verkaufsr\u00e4umen",
    "sg:phone":"+41 21 800 38 91",
    "sg:postcode":"1137",
    "wof:name":"Diamant Noir, Gehrig Daniel",
    "wof:placetype":"venue"
},
  "geometry": {"coordinates":[6.4184069633,46.5199966431],"type":"Point"}
}