{
  "type": "Feature",
  "properties": {
    "iso:country":"CH",
    "sg:address":"Gampelengasse 20",
    "sg:city":"Ins",
    "sg:orig_category":"RESTAURANTS: TEA-ROOMS",
    "sg:phone":"+41 32 313 15 81",
    "sg:postcode":"3232",
    "sg:province":"Bern",
    "wof:name":"Restaurant Sternen, Hemmann Max",
    "wof:placetype":"venue"
},
  "geometry": {"coordinates":[7.1015601158,47.0061187744],"type":"Point"}
}