{
  "type": "Feature",
  "properties": {
    "iso:country":"CH",
    "sg:address":"Frutigenstrasse 2",
    "sg:city":"Thun",
    "sg:classifiers":[
        {
            "category":"Banks & Credit Unions",
            "subcategory":"Bank",
            "type":"Services"
        }
    ],
    "sg:phone":"+41 33392244",
    "sg:postcode":"3600",
    "sg:province":"Bern",
    "wof:name":"Spar + Leihkasse Steffisburg",
    "wof:placetype":"venue"
},
  "geometry": {"coordinates":[7.629385,46.756325],"type":"Point"}
}