{
  "type": "Feature",
  "properties": {
    "iso:country":"CH",
    "sg:address":"Bundesplatz 8",
    "sg:city":"Zug",
    "sg:orig_category":"Non-Classified Establishments",
    "sg:postcode":"6300",
    "sg:province":"Zug",
    "wof:name":"Malco Holding Ag",
    "wof:placetype":"venue"
},
  "geometry": {"coordinates":[8.5153522491,47.171672821],"type":"Point"}
}