{
  "type": "Feature",
  "properties": {
    "iso:country":"CH",
    "sg:address":"Relli",
    "sg:city":"Turbach",
    "sg:orig_category":"Bauschreinerei Herstellung von Konstruktionsteilen, Fertigbauteilen U Ausbauelementen aus Holz",
    "sg:phone":"+41 33 744 53 94",
    "sg:postcode":"3781",
    "sg:province":"Bern",
    "wof:name":"Romang Hans-peter Service-schreinerei",
    "wof:placetype":"venue"
},
  "geometry": {"coordinates":[7.337287,46.479935],"type":"Point"}
}