{
  "type": "Feature",
  "properties": {
    "iso:country":"CH",
    "sg:address":"D\u00fcrrhalde",
    "sg:city":"Urn\u00e4sch",
    "sg:orig_category":"Geb\u00e4ude, Wohnungsreinigung Reinigungsgewerbe",
    "sg:phone":"+41 71 364 24 12",
    "sg:postcode":"9107",
    "sg:province":"Appenzell Ausserrhoden",
    "wof:name":"Ruma Fontana M.",
    "wof:placetype":"venue"
},
  "geometry": {"coordinates":[9.2783355713,47.3189468384],"type":"Point"}
}