{
  "type": "Feature",
  "properties": {
    "addr:full":"H\u00f6fenstrasse 1 Zug Zug 6300",
    "addr:housenumber":"1",
    "addr:postcode":"6300",
    "addr:street":"Hoefenstrasse;Zug",
    "iso:country":"CH",
    "sg:address":"H\u00f6fenstrasse 1",
    "sg:city":"Zug",
    "sg:orig_category":"Allgemeiner Hoch U Tiefbau Strassenbau",
    "sg:phone":"+41 41 741 35 01",
    "sg:postcode":"6300",
    "sg:province":"Zug",
    "wof:name":"Stocker Tiefbau Ag",
    "wof:placetype":"venue"
},
  "geometry": {"coordinates":[8.499244,47.188854],"type":"Point"}
}