{
  "type": "Feature",
  "properties": {
    "iso:country":"CH",
    "sg:address":"Vert Chemin 7",
    "sg:city":"Corsier-sur-vevey",
    "sg:orig_category":"Zimmerei, Dachdeckerei, Bauspenglerei U Abdichtung",
    "sg:postcode":"1804",
    "sg:province":"Vaud",
    "wof:name":"Vogel Fritz, Ferblanterie - Couverture - Sanitaire",
    "wof:placetype":"venue"
},
  "geometry": {"coordinates":[6.8414001465,46.4704856873],"type":"Point"}
}