{
  "type": "Feature",
  "properties": {
    "iso:country":"CH",
    "sg:address":"Rue Saint Leger 8",
    "sg:city":"Gen\u00e8ve",
    "sg:orig_category":"Reiseb\u00fcros",
    "sg:phone":"+41 22 798 58 88",
    "sg:postcode":"1205",
    "sg:province":"Gen\u00e8ve",
    "wof:name":"Sst Voyages Agence De Voyages",
    "wof:placetype":"venue"
},
  "geometry": {"coordinates":[6.1462478638,46.19764328],"type":"Point"}
}