{
  "type": "Feature",
  "properties": {
    "iso:country":"CH",
    "sg:address":"Hutins Chemin Des 1",
    "sg:city":"Confignon",
    "sg:orig_category":"Stukkateurgewerbe, Gipserei U Verputzerei",
    "sg:phone":"+41 32 675 71 53",
    "sg:postcode":"1232",
    "sg:province":"Gen\u00e8ve",
    "wof:name":"Entreprise Muro",
    "wof:placetype":"venue"
},
  "geometry": {"coordinates":[6.0849947929,46.1737861633],"type":"Point"}
}