{
  "type": "Feature",
  "properties": {
    "addr:full":"Hummelwaldstrasse 28 8865 Bilten. Postfach Bilten Glarus 8865",
    "addr:housenumber":"28",
    "addr:postcode":"8865 bilten. postfach;8865",
    "addr:street":"Hummelwaldstrasse",
    "iso:country":"CH",
    "sg:address":"Hummelwaldstrasse 28 8865 Bilten. Postfach",
    "sg:city":"Bilten",
    "sg:orig_category":"Allgemeiner Hochbau Vermittlung von Immobilien",
    "sg:postcode":"8865",
    "sg:province":"Glarus",
    "wof:name":"Mavilla Construction De Villas",
    "wof:placetype":"venue"
},
  "geometry": {"coordinates":[6.868316,46.457039],"type":"Point"}
}