{
  "type": "Feature",
  "properties": {
    "iso:country":"CH",
    "sg:address":"3184 W\u00fcnnewil. Postfach",
    "sg:city":"Flamatt",
    "sg:orig_category":"Herstellung von Wellpapier U pappe sowie von Verpackungsmitteln aus Papier, Karton U Pappe",
    "sg:phone":"+41 31 744 64 64",
    "sg:postcode":"3175",
    "sg:province":"Fribourg",
    "wof:name":"Bouquet & Cie Cartonnagenfabrik",
    "wof:placetype":"venue"
},
  "geometry": {"coordinates":[7.276140213,46.8746185303],"type":"Point"}
}