{
  "type": "Feature",
  "properties": {
    "iso:country":"CH",
    "sg:address":"Au Village",
    "sg:city":"Essertines-rolle",
    "sg:orig_category":"Non-Classified Establishments",
    "sg:postcode":"1186",
    "sg:province":"Vaud",
    "wof:name":"Michel Grieshaber",
    "wof:placetype":"venue"
},
  "geometry": {"coordinates":[6.3175749779,46.4924201965],"type":"Point"}
}