{
  "type": "Feature",
  "properties": {
    "iso:country":"CH",
    "sg:address":"Boulevard De P\u00e9rolles 12",
    "sg:city":"Fribourg",
    "sg:orig_category":"Grosshandel mit Obst U Gem\u00fcse",
    "sg:postcode":"1700",
    "sg:province":"Fribourg",
    "wof:name":"Massaro, Maria, Vve.",
    "wof:placetype":"venue"
},
  "geometry": {"coordinates":[7.1520280838,46.8014945984],"type":"Point"}
}