{
  "type": "Feature",
  "properties": {
    "iso:country":"CH",
    "sg:address":"Letzigraben 77 8003 Z\u00fcrich. Postfach",
    "sg:city":"Z\u00fcrich",
    "sg:orig_category":"Instandhaltung U Reparatur von Automobilen",
    "sg:phone":"+41 14062222",
    "sg:postcode":"8003",
    "sg:province":"Z\u00fcrich",
    "wof:name":"Gross-garage Letzigraben Ag",
    "wof:placetype":"venue"
},
  "geometry": {"coordinates":[8.4997034073,47.3783836365],"type":"Point"}
}