{
  "type": "Feature",
  "properties": {
    "iso:country":"CH",
    "sg:address":"Marktgasse 7",
    "sg:city":"Thun",
    "sg:orig_category":"Detailhandel mit Damenbekleidung Grosshandel mit Textilien",
    "sg:phone":"+41 33 222 17 17",
    "sg:postcode":"3600",
    "sg:province":"Bern",
    "wof:name":"Mode Wartmann Ag",
    "wof:placetype":"venue"
},
  "geometry": {"coordinates":[7.6278190613,46.7603645325],"type":"Point"}
}