{
  "type": "Feature",
  "properties": {
    "iso:country":"CH",
    "sg:address":"Heuwinkelstrasse 16 8606 N\u00e4nikon. Postfach",
    "sg:city":"N\u00e4nikon",
    "sg:orig_category":"Sonstige mit der Informatik verbundene T\u00e4tigkeiten",
    "sg:postcode":"8606",
    "sg:province":"Z\u00fcrich",
    "wof:name":"Schaier Informatik",
    "wof:placetype":"venue"
},
  "geometry": {"coordinates":[8.4476528168,47.3579139709],"type":"Point"}
}