{
  "type": "Feature",
  "properties": {
    "iso:country":"CH",
    "sg:address":"Sonnenwiesenstrasse 18",
    "sg:city":"Kreuzlingen",
    "sg:orig_category":"Grosshandel mit chemischen Erzeugnissen",
    "sg:phone":"+41 71 686 81 00",
    "sg:postcode":"8280",
    "sg:province":"Thurgau",
    "wof:name":"A.v. Chemie Ag",
    "wof:placetype":"venue"
},
  "geometry": {"coordinates":[9.1917448044,47.6445655823],"type":"Point"}
}