{
  "type": "Feature",
  "properties": {
    "iso:country":"CH",
    "sg:address":"Stadtturmstrasse 19 5400 Baden. Postfach 1930",
    "sg:city":"Baden",
    "sg:orig_category":"Vereine Haus- and Grundeigent\u00fcmer",
    "sg:phone":"+41 56 200 50 50",
    "sg:postcode":"5401",
    "sg:province":"Aargau",
    "wof:name":"Hauseigent\u00fcmerverband Aargau",
    "wof:placetype":"venue"
},
  "geometry": {"coordinates":[8.3055353165,47.4757881165],"type":"Point"}
}