{
  "type": "Feature",
  "properties": {
    "iso:country":"CH",
    "sg:address":"3823",
    "sg:city":"Wengen",
    "sg:orig_category":"HOTELS: MIT RESTAURANT Kongress- and Tagungshotels mit Restaurant",
    "sg:phone":"+41 71 314 71 71",
    "sg:postcode":"3823",
    "sg:province":"Bern",
    "wof:name":"Hotel Sistar",
    "wof:placetype":"venue"
},
  "geometry": {"coordinates":[9.311170578,47.4081382751],"type":"Point"}
}