{
  "type": "Feature",
  "properties": {
    "iso:country":"CH",
    "sg:address":"Dorfstrasse.",
    "sg:city":"Masein",
    "sg:orig_category":"Herstellung von Konstruktionsteilen, Fertigbauteilen U Ausbauelementen aus Holz",
    "sg:phone":"+41 81 651 22 32",
    "sg:postcode":"7425",
    "sg:province":"Graubunden",
    "wof:name":"Feltscher Willi",
    "wof:placetype":"venue"
},
  "geometry": {"coordinates":[9.4267120361,46.7027168274],"type":"Point"}
}