{
  "type": "Feature",
  "properties": {
    "iso:country":"CH",
    "sg:address":"Haldenstrasse 42",
    "sg:city":"Aesch",
    "sg:orig_category":"G\u00fcterbef\u00f6rderung im Strassenverkehr",
    "sg:phone":"+41 17374005",
    "sg:postcode":"8904",
    "sg:province":"Z\u00fcrich",
    "wof:name":"Luigi Caravina Transporte",
    "wof:placetype":"venue"
},
  "geometry": {"coordinates":[8.4445018768,47.3380699158],"type":"Point"}
}