{
  "type": "Feature",
  "properties": {
    "iso:country":"CH",
    "sg:address":"L\u00f6hrstrasse 14",
    "sg:city":"Derendingen",
    "sg:orig_category":"Unternehmensberatung",
    "sg:phone":"+41 52 337 28 25",
    "sg:postcode":"4552",
    "sg:province":"Solothurn",
    "wof:name":"Solventex Ag",
    "wof:placetype":"venue"
},
  "geometry": {"coordinates":[8.7959194183,47.5517463684],"type":"Point"}
}