{
  "type": "Feature",
  "properties": {
    "iso:country":"CH",
    "sg:address":"Birkenstrasse 17",
    "sg:city":"Bergdietikon",
    "sg:orig_category":"Handelsvermittlung U Grosshandel Herstellung von sonstigen Waren aus Papier, Karton U Pappe",
    "sg:phone":"+41 17411260",
    "sg:postcode":"8962",
    "sg:province":"Aargau",
    "wof:name":"Ritrama Ag",
    "wof:placetype":"venue"
},
  "geometry": {"coordinates":[8.3869934082,47.3944473267],"type":"Point"}
}