{
  "type": "Feature",
  "properties": {
    "iso:country":"CH",
    "sg:address":"Spierstrasse 2",
    "sg:city":"Horw",
    "sg:orig_category":"Kauf U Verkauf von Immobilien auf eigene Rechnung",
    "sg:phone":"+41 41 340 32 32",
    "sg:postcode":"6048",
    "sg:province":"Luzern",
    "wof:name":"Spitzgrund Immobilien Ag",
    "wof:placetype":"venue"
},
  "geometry": {"coordinates":[8.3062992096,47.0106925964],"type":"Point"}
}