{
  "type": "Feature",
  "properties": {
    "iso:country":"CH",
    "sg:address":"Malvilliers 2043 Boudevilliers. Postfach",
    "sg:city":"Boudevilliers",
    "sg:orig_category":"Institutionen f\u00fcr Behinderte Sonderschulen",
    "sg:phone":"+41 32 854 22 22",
    "sg:postcode":"2043",
    "sg:province":"Neuch\u00e2tel",
    "wof:name":"Centre P\u00e9dagogique Les Perce-neige",
    "wof:placetype":"venue"
},
  "geometry": {"coordinates":[6.8181872368,47.099773407],"type":"Point"}
}