{
  "type": "Feature",
  "properties": {
    "iso:country":"CH",
    "sg:address":"Seestrasse 4",
    "sg:city":"St\u00e4fa",
    "sg:orig_category":"RESTAURANTS: TEA-ROOMS",
    "sg:phone":"+41 19262303",
    "sg:postcode":"8712",
    "sg:province":"Z\u00fcrich",
    "wof:name":"Hurter's Seehus Restaurant Seehus",
    "wof:placetype":"venue"
},
  "geometry": {"coordinates":[8.7138118744,47.240978241],"type":"Point"}
}