{
  "type": "Feature",
  "properties": {
    "iso:country":"CH",
    "sg:address":"Im Leisib\u00fchl 25 8044 Gockhausen. Postfach",
    "sg:city":"Gockhausen",
    "sg:orig_category":"Gesundheitswesen",
    "sg:postcode":"8044",
    "sg:province":"Z\u00fcrich",
    "wof:name":"Verein Remedur",
    "wof:placetype":"venue"
},
  "geometry": {"coordinates":[8.5936555862,47.3842086792],"type":"Point"}
}