{
  "type": "Feature",
  "properties": {
    "iso:country":"CH",
    "sg:address":"Fasanenstrasse 92",
    "sg:city":"Basel",
    "sg:orig_category":"Non-Classified Establishments",
    "sg:phone":"+41 61 681 12 33",
    "sg:postcode":"4058",
    "sg:province":"Basel-Stadt",
    "wof:name":"F. Gottardi Ag",
    "wof:placetype":"venue"
},
  "geometry": {"coordinates":[7.6080560684,47.5726928711],"type":"Point"}
}