{
  "type": "Feature",
  "properties": {
    "iso:country":"CH",
    "sg:address":"Arsenalstrasse 4 6000 Luzern. Postfach",
    "sg:city":"Reussb\u00fchl",
    "sg:orig_category":"Fernmeldedienste",
    "sg:phone":"+41 41 360 82 91",
    "sg:postcode":"6015",
    "sg:province":"Luzern",
    "wof:name":"Trendcall Telemarketing Gmbh",
    "wof:placetype":"venue"
},
  "geometry": {"coordinates":[8.299489975,47.038356781],"type":"Point"}
}