{
  "type": "Feature",
  "properties": {
    "iso:country":"CH",
    "sg:address":"Brunngasse 1",
    "sg:city":"Z\u00fcrich",
    "sg:orig_category":"Detailhandel mit Fleisch U Fleischwaren",
    "sg:phone":"+41 71 777 11 94",
    "sg:postcode":"8001",
    "sg:province":"Z\u00fcrich",
    "wof:name":"Ottinger Metzgerei",
    "wof:placetype":"venue"
},
  "geometry": {"coordinates":[9.5668964386,47.3923873901],"type":"Point"}
}