{
  "type": "Feature",
  "properties": {
    "iso:country":"CH",
    "sg:address":"Baslerstrasse 198",
    "sg:city":"Allschwil",
    "sg:orig_category":"Non-Classified Establishments",
    "sg:phone":"+41 61 481 49 03",
    "sg:postcode":"4123",
    "sg:province":"Basel-Landschaft",
    "wof:name":"Eclipse Ag Textilreinigung & W\u00e4scherei",
    "wof:placetype":"venue"
},
  "geometry": {"coordinates":[7.5497422218,47.5525398254],"type":"Point"}
}