{
  "type": "Feature",
  "properties": {
    "iso:country":"CH",
    "sg:address":"Rugenparkstrasse 2 3800 Interlaken. Postfach 3",
    "sg:city":"Interlaken",
    "sg:orig_category":"Wirtschaftspr\u00fcfung, Steuerberatung U Treuhand",
    "sg:postcode":"3800",
    "sg:province":"Bern",
    "wof:name":"Stucki B. Treuhand",
    "wof:placetype":"venue"
},
  "geometry": {"coordinates":[7.851556778,46.6819992065],"type":"Point"}
}