{
  "type": "Feature",
  "properties": {
    "iso:country":"CH",
    "sg:address":"Rte Des Jeunes 6",
    "sg:city":"Grand-lancy",
    "sg:orig_category":"Herstellung von Konstruktionsteilen, Fertigbauteilen U Ausbauelementen aus Holz",
    "sg:postcode":"1212",
    "sg:province":"Gen\u00e8ve",
    "wof:name":"Espace Plus, Peris A.",
    "wof:placetype":"venue"
},
  "geometry": {"coordinates":[6.1283998489,46.1792640686],"type":"Point"}
}