{
  "type": "Feature",
  "properties": {
    "iso:country":"CH",
    "sg:address":"Fachstrasse 39",
    "sg:city":"Oberrieden",
    "sg:orig_category":"Sonstige mit der Informatik verbundene T\u00e4tigkeiten",
    "sg:postcode":"8942",
    "sg:province":"Z\u00fcrich",
    "wof:name":"Lazzarini, Logic Design",
    "wof:placetype":"venue"
},
  "geometry": {"coordinates":[8.5798826218,47.2765235901],"type":"Point"}
}