{
  "type": "Feature",
  "properties": {
    "addr:full":"Kleintwann 11 Twann Bern 2513",
    "addr:housenumber":"11",
    "addr:postcode":"2513",
    "addr:street":"Kleintwann",
    "iso:country":"CH",
    "sg:address":"Kleintwann 11",
    "sg:city":"Twann",
    "sg:orig_category":"Dauerkulturbau",
    "sg:phone":"+41 32 315 19 13",
    "sg:postcode":"2513",
    "sg:province":"Bern",
    "wof:name":"Sauser Heinrich",
    "wof:placetype":"venue"
},
  "geometry": {"coordinates":[7.15632,47.09433],"type":"Point"}
}