{
  "type": "Feature",
  "properties": {
    "iso:country":"CH",
    "sg:address":"Avenue De La Gare 2",
    "sg:city":"Lausanne",
    "sg:orig_category":"Herstellung von W\u00e4sche Textilgewerbe",
    "sg:phone":"+41 21 323 04 86",
    "sg:postcode":"1003",
    "sg:province":"Vaud",
    "wof:name":"Jacqueline Dupertuis",
    "wof:placetype":"venue"
},
  "geometry": {"coordinates":[6.6373372078,46.5169372559],"type":"Point"}
}