{
  "type": "Feature",
  "properties": {
    "iso:country":"CH",
    "sg:address":"Bahnhofstrasse 3073 G\u00fcmligen. Postfach",
    "sg:city":"G\u00fcmligen",
    "sg:orig_category":"Allgemeiner Hoch U Tiefbau",
    "sg:postcode":"3073",
    "sg:province":"Bern",
    "wof:name":"Rubin Totalunternehmung Ag",
    "wof:placetype":"venue"
},
  "geometry": {"coordinates":[7.506154,46.934048],"type":"Point"}
}