{
  "type": "Feature",
  "properties": {
    "iso:country":"CH",
    "sg:address":"Fraumattstrasse 47",
    "sg:city":"Liestal",
    "sg:orig_category":"Betrieb von Taxis",
    "sg:phone":"+41 61 921 22 22",
    "sg:postcode":"4410",
    "sg:province":"Basel-Landschaft",
    "wof:name":"Balmer Taxi Gmbh",
    "wof:placetype":"venue"
},
  "geometry": {"coordinates":[7.72743,47.498947],"type":"Point"}
}