{
  "type": "Feature",
  "properties": {
    "iso:country":"CH",
    "sg:address":"Zelgmatt 16",
    "sg:city":"Gr\u00fcningen",
    "sg:orig_category":"Wirtschaftspr\u00fcfung, Steuerberatung U Treuhand",
    "sg:phone":"+41 19351462",
    "sg:postcode":"8627",
    "sg:province":"Z\u00fcrich",
    "wof:name":"Heer Treuhand",
    "wof:placetype":"venue"
},
  "geometry": {"coordinates":[8.755654335,47.2812919617],"type":"Point"}
}