{
  "type": "Feature",
  "properties": {
    "iso:country":"CH",
    "sg:address":"Biberiststrasse 18",
    "sg:city":"Solothurn",
    "sg:orig_category":"Wirtschafts- and Arbeitgeberverb\u00e4nde",
    "sg:phone":"+41 32 623 26 36",
    "sg:postcode":"4500",
    "sg:province":"Solothurn",
    "wof:name":"Aerztegesellschaft Des Kts So Herrn Peter Meier",
    "wof:placetype":"venue"
},
  "geometry": {"coordinates":[7.5423979759,47.2021522522],"type":"Point"}
}