{
  "type": "Feature",
  "properties": {
    "iso:country":"CH",
    "sg:address":"Chalet Les Cerisiers",
    "sg:city":"Ch\u00e2teau-d'oex",
    "sg:orig_category":"Non-Classified Establishments",
    "sg:postcode":"1837",
    "wof:name":"Si Les Buissonnets Sa",
    "wof:placetype":"venue"
},
  "geometry": {"coordinates":[5.9391069412,46.5712165833],"type":"Point"}
}