{
  "type": "Feature",
  "properties": {
    "iso:country":"CH",
    "sg:address":"Erlenstrasse 30",
    "sg:city":"Jona",
    "sg:orig_category":"Non-Classified Establishments",
    "sg:postcode":"8645",
    "sg:province":"St. Gallen",
    "wof:name":"Gebr\u00fcder Baschung Gipserei & Management",
    "wof:placetype":"venue"
},
  "geometry": {"coordinates":[8.8506917953,47.2292289734],"type":"Point"}
}