{
  "type": "Feature",
  "properties": {
    "iso:country":"CH",
    "sg:address":"Industriestrasse 2",
    "sg:city":"Bennau",
    "sg:classifiers":[
        {
            "category":"Home & Garden",
            "subcategory":"Building Materials",
            "type":"Retail Goods"
        }
    ],
    "sg:phone":"+41 55 418 45 45",
    "sg:postcode":"8836",
    "sg:province":"Schwyz",
    "sg:tags":[
        "glass",
        "enclosures",
        "balcony"
    ],
    "wof:name":"Biberbau Ag",
    "wof:placetype":"venue"
},
  "geometry": {"coordinates":[8.729785,47.148445],"type":"Point"}
}