{
  "type": "Feature",
  "properties": {
    "iso:country":"CH",
    "sg:address":"Steinentorstrasse 18",
    "sg:city":"Basel",
    "sg:orig_category":"Herstellung von k\u00e4lte U lufttechnischen Erzeugnissen f\u00fcr gewerbliche Zwecke",
    "sg:postcode":"4051",
    "sg:province":"Basel-Stadt",
    "wof:name":"Md K\u00e4lte- Hausger\u00e4te-service Gmbh",
    "wof:placetype":"venue"
},
  "geometry": {"coordinates":[7.5888671875,47.5516929626],"type":"Point"}
}