{
  "type": "Feature",
  "properties": {
    "iso:country":"CH",
    "sg:address":"Route De Drize 61",
    "sg:city":"Vessy",
    "sg:orig_category":"Sonstige Kultur U Unterhaltungseinrichtungen",
    "sg:phone":"+41 22 300 00 04",
    "sg:postcode":"1234",
    "sg:province":"Gen\u00e8ve",
    "wof:name":"Michel & Tina Perret Th\u00e9\u00e2tre Pannalal's Puppets",
    "wof:placetype":"venue"
},
  "geometry": {"coordinates":[6.1406478882,46.1696205139],"type":"Point"}
}