{
  "type": "Feature",
  "properties": {
    "iso:country":"CH",
    "sg:address":"Vieux-ch\u00e2teau Rue Du 14",
    "sg:city":"Del\u00e9mont",
    "sg:orig_category":"Unternehmensberatung",
    "sg:phone":"+41 32 423 42 25",
    "sg:postcode":"2800",
    "sg:province":"Jura",
    "wof:name":"Vimtech Sa",
    "wof:placetype":"venue"
},
  "geometry": {"coordinates":[7.353869915,47.3709411621],"type":"Point"}
}