{
  "type": "Feature",
  "properties": {
    "iso:country":"CH",
    "sg:address":"Chemin De Mornex 3 1003 Lausanne Case Postale 1375",
    "sg:city":"Lausanne",
    "sg:orig_category":"Wirtschaftspr\u00fcfung, Steuerberatung U Treuhand",
    "sg:phone":"+41 21 320 44 01",
    "sg:postcode":"1001",
    "sg:province":"Vaud",
    "wof:name":"Soci\u00e9t\u00e9 De Contr\u00f4le Fiduciaire Sa",
    "wof:placetype":"venue"
},
  "geometry": {"coordinates":[6.6288371086,46.5181045532],"type":"Point"}
}