{
  "type": "Feature",
  "properties": {
    "iso:country":"CH",
    "sg:address":"Bahnhofstrasse",
    "sg:city":"Zermatt",
    "sg:orig_category":"Detailhandel mit Bekleidung Detailhandel mit Damenbekleidung",
    "sg:phone":"+41 27 966 49 60",
    "sg:postcode":"3920",
    "sg:province":"Valais",
    "wof:name":"Ren\u00e9 Bayard Sport & Mode",
    "wof:placetype":"venue"
},
  "geometry": {"coordinates":[7.74624,46.020145],"type":"Point"}
}