{
  "type": "Feature",
  "properties": {
    "iso:country":"CH",
    "sg:address":"Rheinstrasse 28 B",
    "sg:city":"Pratteln",
    "sg:orig_category":"Binnenschiffahrt",
    "sg:postcode":"4133",
    "sg:province":"Basel-Landschaft",
    "wof:name":"Klein-reederei Rolling-home, Steiner R.",
    "wof:placetype":"venue"
},
  "geometry": {"coordinates":[8.31121,46.983139],"type":"Point"}
}