{
  "type": "Feature",
  "properties": {
    "iso:country":"CH",
    "sg:address":"Hauptstrasse 14",
    "sg:city":"K\u00f6lliken",
    "sg:classifiers":[
        {
            "category":"Travel",
            "subcategory":"Hotels & Motels",
            "type":"Entertainment"
        }
    ],
    "sg:phone":"+41 62 897 12 29",
    "sg:postcode":"5742",
    "sg:province":"Aargau",
    "sg:tags":[
        "hotels",
        "mit",
        "restaurant"
    ],
    "wof:name":"Restaurant Freihof W. Zwyssig",
    "wof:placetype":"venue"
},
  "geometry": {"coordinates":[8.0250253677,47.3380966187],"type":"Point"}
}