{
  "type": "Feature",
  "properties": {
    "iso:country":"CH",
    "sg:address":"Hauptgasse 2",
    "sg:city":"Solothurn",
    "sg:orig_category":"Detailhandel mit Blumen U Pflanzen",
    "sg:phone":"+41 32 623 56 69",
    "sg:postcode":"4500",
    "sg:province":"Solothurn",
    "wof:name":"Martin & Theresia Waibel Blumengesch\u00e4ft",
    "wof:placetype":"venue"
},
  "geometry": {"coordinates":[7.535711,47.206535],"type":"Point"}
}