{
  "type": "Feature",
  "properties": {
    "iso:country":"CH",
    "sg:address":"Langwiesstrasse",
    "sg:city":"Zurzach",
    "sg:orig_category":"Grosshandel mit Textilien",
    "sg:postcode":"5330",
    "sg:province":"Aargau",
    "wof:name":"Krasniqi Export-import",
    "wof:placetype":"venue"
},
  "geometry": {"coordinates":[8.294875145,47.5866394043],"type":"Point"}
}