{
  "type": "Feature",
  "properties": {
    "iso:country":"CH",
    "sg:address":"Vorstadt 50",
    "sg:city":"Nebikon",
    "sg:orig_category":"Vereine Bienenz\u00fcchter",
    "sg:phone":"+41 62 756 43 86",
    "sg:postcode":"6244",
    "sg:province":"Luzern",
    "wof:name":"Imkerverein Zentralwiggertal",
    "wof:placetype":"venue"
},
  "geometry": {"coordinates":[7.9767379761,47.1866035461],"type":"Point"}
}