{
  "type": "Feature",
  "properties": {
    "addr:full":"Seetalstrasse 98 Emmen Luzern 6032",
    "addr:housenumber":"98",
    "addr:postcode":"6032",
    "addr:street":"Seetalstrasse",
    "iso:country":"CH",
    "sg:address":"Seetalstrasse 98",
    "sg:city":"Emmen",
    "sg:orig_category":"Allgemeiner Hoch U Tiefbau",
    "sg:phone":"+41 41 260 06 60",
    "sg:postcode":"6032",
    "sg:province":"Luzern",
    "wof:name":"Eleconstruct & Partner Ag",
    "wof:placetype":"venue"
},
  "geometry": {"coordinates":[8.300539,47.076996],"type":"Point"}
}