{
  "type": "Feature",
  "properties": {
    "iso:country":"CH",
    "sg:address":"Oberstadt 14",
    "sg:city":"Sursee",
    "sg:orig_category":"Detailhandel mit M\u00f6beln U Haushaltsgegenst\u00e4nden",
    "sg:phone":"+41 41 921 52 12",
    "sg:postcode":"6210",
    "sg:province":"Luzern",
    "wof:name":"Oberstadt 14 Kaufmann",
    "wof:placetype":"venue"
},
  "geometry": {"coordinates":[8.1105155945,47.1718864441],"type":"Point"}
}