{
  "type": "Feature",
  "properties": {
    "iso:country":"CH",
    "sg:address":"6866",
    "sg:city":"Meride",
    "sg:classifiers":[
        {
            "category":"Travel",
            "subcategory":"Hotels & Motels",
            "type":"Entertainment"
        }
    ],
    "sg:postcode":"6866",
    "sg:province":"Ticino",
    "sg:tags":[
        "hotels",
        "mit",
        "restaurant"
    ],
    "wof:name":"Baracchi Giordano",
    "wof:placetype":"venue"
},
  "geometry": {"coordinates":[8.955031395,45.8902359009],"type":"Point"}
}