{
  "type": "Feature",
  "properties": {
    "addr:full":"Hauptstrasse 10 Buchrain Luzern 6033",
    "addr:housenumber":"10",
    "addr:postcode":"6033",
    "addr:street":"Hauptstrasse",
    "iso:country":"CH",
    "sg:address":"Hauptstrasse 10",
    "sg:city":"Buchrain",
    "sg:orig_category":"Arztpraxen",
    "sg:phone":"+41 41 440 22 80",
    "sg:postcode":"6033",
    "sg:province":"Luzern",
    "wof:name":"Dr.med.roland Zehnder Arzt F.allgemeine Medizin Fmh",
    "wof:placetype":"venue"
},
  "geometry": {"coordinates":[8.346527,47.094723],"type":"Point"}
}