{
  "type": "Feature",
  "properties": {
    "iso:country":"CH",
    "sg:address":"Gellertstr. 18",
    "sg:city":"Basel",
    "sg:classifiers":[
        {
            "category":"Banks & Credit Unions",
            "subcategory":"Bank",
            "type":"Services"
        }
    ],
    "sg:phone":"+41 61 311 59 49",
    "sg:postcode":"4006",
    "wof:name":"Cantrade Privatbank Ag",
    "wof:placetype":"venue"
},
  "geometry": {"coordinates":[153.31071499999999,-27.586378],"type":"Point"}
}