{
  "type": "Feature",
  "properties": {
    "iso:country":"CH",
    "sg:address":"Haslistrasse 41",
    "sg:city":"Olten",
    "sg:classifiers":[
        {
            "category":"Parking",
            "subcategory":"Lot",
            "type":"Transportation"
        }
    ],
    "sg:phone":"+41 62 287 33 77",
    "sg:postcode":"4600",
    "sg:province":"Solothurn",
    "sg:tags":[
        "pot",
        "cooking",
        "enamelled"
    ],
    "wof:name":"F.g. Ritter Ag",
    "wof:placetype":"venue"
},
  "geometry": {"coordinates":[7.9207429886,47.3634719849],"type":"Point"}
}