{
  "type": "Feature",
  "properties": {
    "iso:country":"CH",
    "sg:address":"Zollhausstrasse 2 6015 Reussb\u00fchl. Postfach",
    "sg:city":"Luzern",
    "sg:orig_category":"Erbringung von Dienstleistungen f\u00fcr Unternehmen Siebdruck",
    "sg:phone":"+41 41 210 31 41",
    "sg:postcode":"6002",
    "sg:province":"Luzern",
    "wof:name":"Studio-werbung Ag",
    "wof:placetype":"venue"
},
  "geometry": {"coordinates":[8.2813673019,47.0650291443],"type":"Point"}
}