{
  "type": "Feature",
  "properties": {
    "iso:country":"CH",
    "sg:address":"Bonnstrasse 22 3186 D\u00fcdingen. Postfach 33",
    "sg:city":"D\u00fcdingen",
    "sg:orig_category":"Elektroinstallation",
    "sg:phone":"+41 26 492 90 90",
    "sg:postcode":"3186",
    "sg:province":"Fribourg",
    "wof:name":"Josef Crottet Ag Elektrische-anlagen",
    "wof:placetype":"venue"
},
  "geometry": {"coordinates":[7.1856598854,46.8577919006],"type":"Point"}
}