{
  "type": "Feature",
  "properties": {
    "iso:country":"CH",
    "sg:address":"4313",
    "sg:city":"M\u00f6hlin",
    "sg:orig_category":"Vereine Gesang",
    "sg:phone":"+41 61 813 70 30",
    "sg:postcode":"4313",
    "sg:province":"Aargau",
    "wof:name":"Arbeiter-m\u00e4nnerchor",
    "wof:placetype":"venue"
},
  "geometry": {"coordinates":[7.8434958458,47.5606918335],"type":"Point"}
}