{
  "type": "Feature",
  "properties": {
    "iso:country":"CH",
    "sg:address":"Route De Chevrens 160",
    "sg:city":"Ani\u00e8res",
    "sg:orig_category":"Rebbau",
    "sg:phone":"+41 79 606 48 49",
    "sg:postcode":"1247",
    "sg:province":"Gen\u00e8ve",
    "wof:name":"Georges Chollet Viticulteur",
    "wof:placetype":"venue"
},
  "geometry": {"coordinates":[6.2413477898,46.28565979],"type":"Point"}
}