{
  "type": "Feature",
  "properties": {
    "iso:country":"CH",
    "sg:address":"Hutgasse 4",
    "sg:city":"Basel",
    "sg:orig_category":"Unclassifiable Establishments",
    "sg:postcode":"4001",
    "sg:province":"Basel-Stadt",
    "wof:name":"Die Wache Wach Und Schliess-aktiengesellschaft",
    "wof:placetype":"venue"
},
  "geometry": {"coordinates":[9.5218658447,47.1378669739],"type":"Point"}
}