{
  "type": "Feature",
  "properties": {
    "iso:country":"CH",
    "sg:address":"Rue De La Veraye 24",
    "sg:city":"Territet-veytaux",
    "sg:orig_category":"Autogaragen",
    "sg:phone":"+41 21 963 31 55",
    "sg:postcode":"1820",
    "sg:province":"Vaud",
    "wof:name":"Garage Atlantic Sa",
    "wof:placetype":"venue"
},
  "geometry": {"coordinates":[6.910506,46.431694],"type":"Point"}
}