{
  "type": "Feature",
  "properties": {
    "iso:country":"CH",
    "sg:address":"Wagnerstrasse 32",
    "sg:city":"Bern",
    "sg:classifiers":[
        {
            "category":"Communications",
            "subcategory":"Film & Video Production",
            "type":"Services"
        }
    ],
    "sg:phone":"+41 31 371 60 40",
    "sg:postcode":"3007",
    "sg:province":"Bern",
    "sg:tags":[
        "videofilmherstellung",
        "u"
    ],
    "wof:name":"Andreas Buser Filmproduktion",
    "wof:placetype":"venue"
},
  "geometry": {"coordinates":[7.4247770309,46.9428787231],"type":"Point"}
}