{
  "type": "Feature",
  "properties": {
    "iso:country":"CH",
    "sg:address":"Chemin De Chamblandes 50",
    "sg:city":"Pully",
    "sg:orig_category":"Fotografisches Gewerbe U fotografische Laboratorien",
    "sg:phone":"+41 21 728 04 66",
    "sg:postcode":"1009",
    "sg:province":"Vaud",
    "wof:name":"Chassot Nicolas",
    "wof:placetype":"venue"
},
  "geometry": {"coordinates":[6.6445288658,46.5085029602],"type":"Point"}
}