{
  "type": "Feature",
  "properties": {
    "iso:country":"CH",
    "sg:address":"Neur\u00fcti",
    "sg:city":"Heldswil",
    "sg:orig_category":"G\u00fcterbef\u00f6rderung im Strassenverkehr",
    "sg:phone":"+41 71 642 27 94",
    "sg:postcode":"9216",
    "sg:province":"Thurgau",
    "wof:name":"Albert R\u00fcegg Transporte",
    "wof:placetype":"venue"
},
  "geometry": {"coordinates":[9.2250452042,47.5072555542],"type":"Point"}
}