{
  "type": "Feature",
  "properties": {
    "iso:country":"CH",
    "sg:address":"Dammweg 6",
    "sg:city":"Adliswil",
    "sg:orig_category":"Detailhandel mit Brennstoffen U Heizmaterial Detailhandel mit Getr\u00e4nken",
    "sg:phone":"+41 17106322",
    "sg:postcode":"8134",
    "sg:province":"Z\u00fcrich",
    "wof:name":"E. Bohli Ag",
    "wof:placetype":"venue"
},
  "geometry": {"coordinates":[8.524217,47.314178],"type":"Point"}
}