{
  "type": "Feature",
  "properties": {
    "iso:country":"CH",
    "sg:address":"Langr\u00fctistrasse 4",
    "sg:city":"Kriens",
    "sg:orig_category":"Elektroinstallation",
    "sg:phone":"+41 71 744 41 59",
    "sg:postcode":"6010",
    "sg:province":"Luzern",
    "wof:name":"Franz Lustenberger Antennenbau",
    "wof:placetype":"venue"
},
  "geometry": {"coordinates":[9.6304626465,47.4343948364],"type":"Point"}
}