{
  "type": "Feature",
  "properties": {
    "iso:country":"CH",
    "sg:address":"Hauptstr. 54 3186 D\u00fcdingen. Postfach",
    "sg:city":"D\u00fcdingen",
    "sg:orig_category":"Gewinnung von Kies U Sand",
    "sg:phone":"+41 26 492 98 85",
    "sg:postcode":"3186",
    "sg:province":"Fribourg",
    "wof:name":"Kieswerk Galmisberg Ag",
    "wof:placetype":"venue"
},
  "geometry": {"coordinates":[7.192802906,46.8521003723],"type":"Point"}
}