{
  "type": "Feature",
  "properties": {
    "iso:country":"CH",
    "sg:address":"Dorfstrasse 40",
    "sg:city":"Schindellegi",
    "sg:orig_category":"Innenarchitekturb\u00fcros Verwaltung von Immobilien",
    "sg:phone":"+41 16877717",
    "sg:postcode":"8834",
    "sg:province":"Schwyz",
    "wof:name":"Interstore Ag Planung Und Projektierung Von Einkaufzentren Und L\u00e4den",
    "wof:placetype":"venue"
},
  "geometry": {"coordinates":[8.7092914581,47.1773719788],"type":"Point"}
}