{
  "type": "Feature",
  "properties": {
    "iso:country":"CH",
    "sg:address":"Grubenstr 104",
    "sg:city":"Schaffhausen",
    "sg:classifiers":[
        {
            "category":"Professional",
            "type":"Services"
        }
    ],
    "sg:phone":"+41 52 624 52 52",
    "sg:postcode":"8201",
    "sg:province":"Schaffhausen",
    "sg:tags":[
        "transport",
        "road"
    ],
    "wof:name":"Gebr\u00dcder Gonzalez M\u00d6beltransporte",
    "wof:placetype":"venue"
},
  "geometry": {"coordinates":[8.6481380463,47.7027359009],"type":"Point"}
}