{
  "type": "Feature",
  "properties": {
    "iso:country":"CH",
    "sg:address":"Via Cancelliere Molo 10",
    "sg:city":"Bellinzona",
    "sg:orig_category":"Vermittlung von Immobilien Wirtschaftspr\u00fcfung, Steuerberatung U Treuhand",
    "sg:phone":"+41 41 410 53 23",
    "sg:postcode":"6500",
    "sg:province":"Ticino",
    "wof:name":"Subtilis Treuhand Ag",
    "wof:placetype":"venue"
},
  "geometry": {"coordinates":[8.3084487915,47.0582008362],"type":"Point"}
}