{
  "type": "Feature",
  "properties": {
    "iso:country":"CH",
    "sg:address":"Rue Caroline 3 1003 Lausanne. Postfach",
    "sg:city":"Lausanne",
    "sg:orig_category":"Physiotherapie",
    "sg:phone":"+41 21 311 88 78",
    "sg:postcode":"1002",
    "sg:province":"Vaud",
    "wof:name":"Val\u00e9rie Von Bredow Physioth\u00e9rapie",
    "wof:placetype":"venue"
},
  "geometry": {"coordinates":[6.6368298531,46.5202064514],"type":"Point"}
}