{
  "type": "Feature",
  "properties": {
    "addr:full":"Avenue Louis-casai 27 Gen\u00e8ve Gen\u00e8ve 1211",
    "addr:housenumber":"27",
    "addr:postcode":"1211",
    "addr:street":"Avenue Louis-Casai",
    "iso:country":"CH",
    "sg:address":"Avenue Louis-casai 27",
    "sg:city":"Gen\u00e8ve",
    "sg:classifiers":[
        {
            "category":"Banks & Credit Unions",
            "subcategory":"Bank",
            "type":"Services"
        }
    ],
    "sg:phone":"+41 22 796 01 55",
    "sg:postcode":"1211",
    "sg:province":"Gen\u00e8ve",
    "wof:name":"Credit Suisse",
    "wof:placetype":"venue"
},
  "geometry": {"coordinates":[6.13993,46.203819],"type":"Point"}
}