{
  "type": "Feature",
  "properties": {
    "iso:country":"CH",
    "sg:address":"Sch\u00f6nenbergstrasse",
    "sg:city":"W\u00e4denswil",
    "sg:orig_category":"Tierheime",
    "sg:phone":"+41 17808055",
    "sg:postcode":"8820",
    "sg:province":"Z\u00fcrich",
    "wof:name":"Tierheim Gerenau Ag",
    "wof:placetype":"venue"
},
  "geometry": {"coordinates":[8.6718301773,47.229511261],"type":"Point"}
}