{
  "type": "Feature",
  "properties": {
    "iso:country":"CH",
    "sg:address":"Br\u00fcderhofweg 10 8057 Z\u00fcrich. Postfach",
    "sg:city":"Z\u00fcrich",
    "sg:orig_category":"Erschliessung von Grundst\u00fccken",
    "sg:phone":"+41 32 365 34 92",
    "sg:postcode":"8057",
    "sg:province":"Z\u00fcrich",
    "wof:name":"Baugenossenschaft Fr\u00f6hlisberg",
    "wof:placetype":"venue"
},
  "geometry": {"coordinates":[7.2557139397,47.1332893372],"type":"Point"}
}