{
  "type": "Feature",
  "properties": {
    "iso:country":"CH",
    "sg:address":"Sion Route De 97 B",
    "sg:city":"Sierre",
    "sg:orig_category":"Erbringung von sonstigen Dienstleistungen f\u00fcr Unterhaltung, Erholung U Freizeit",
    "sg:phone":"+41 22 300 40 25",
    "sg:postcode":"3960",
    "sg:province":"Valais",
    "wof:name":"Feuerstein Daniel",
    "wof:placetype":"venue"
},
  "geometry": {"coordinates":[6.14204216,46.1858139038],"type":"Point"}
}