{
  "type": "Feature",
  "properties": {
    "iso:country":"CH",
    "sg:address":"Bruchstrasse 56",
    "sg:city":"Luzern",
    "sg:orig_category":"Fachdetailhandel in Verkaufsr\u00e4umen Grosshandel mit Spielwaren",
    "sg:phone":"+41 41 240 74 23",
    "sg:postcode":"6003",
    "sg:province":"Luzern",
    "wof:name":"Schloss E. Ag",
    "wof:placetype":"venue"
},
  "geometry": {"coordinates":[8.301440239,47.0483169556],"type":"Point"}
}