{
  "type": "Feature",
  "properties": {
    "iso:country":"CH",
    "sg:address":"Kohlenberg 20",
    "sg:city":"Basel",
    "sg:orig_category":"Interessenvertretungen",
    "sg:postcode":"4051",
    "sg:province":"Basel-Stadt",
    "wof:name":"Verein Jazz-live Basel",
    "wof:placetype":"venue"
},
  "geometry": {"coordinates":[7.5875678062,47.5551834106],"type":"Point"}
}