{
  "type": "Feature",
  "properties": {
    "iso:country":"CH",
    "sg:address":"Schaffhauserstrasse 348",
    "sg:city":"Z\u00fcrich",
    "sg:orig_category":"Detailhandel mit Schuhen",
    "sg:phone":"+41 13102000",
    "sg:postcode":"8050",
    "sg:province":"Z\u00fcrich",
    "wof:name":"Schuhhaus Ochsner Ag",
    "wof:placetype":"venue"
},
  "geometry": {"coordinates":[8.5463104248,47.409450531],"type":"Point"}
}