{
  "type": "Feature",
  "properties": {
    "iso:country":"CH",
    "sg:address":"Schutzengelstrasse 34h",
    "sg:city":"Baar",
    "sg:orig_category":"Softwareentwicklung U beratung",
    "sg:phone":"+41 71 311 61 33",
    "sg:postcode":"6340",
    "sg:province":"Zug",
    "wof:name":"Pfi Felder Peter Informatik",
    "wof:placetype":"venue"
},
  "geometry": {"coordinates":[9.3023853302,47.4044189453],"type":"Point"}
}