{
  "type": "Feature",
  "properties": {
    "iso:country":"CH",
    "sg:address":"1747",
    "sg:city":"Corserey",
    "sg:orig_category":"Vereine Gesang",
    "sg:postcode":"1747",
    "sg:province":"Fribourg",
    "wof:name":"St\u00e9 De Chant La C\u00e9cilienne",
    "wof:placetype":"venue"
},
  "geometry": {"coordinates":[6.9889202118,46.7712287903],"type":"Point"}
}