{
  "type": "Feature",
  "properties": {
    "iso:country":"CH",
    "sg:address":"B\u00e4nkliholzweg 14",
    "sg:city":"Hittnau",
    "sg:orig_category":"Sportvereine Orientierungslauf",
    "sg:phone":"+41 19504766",
    "sg:postcode":"8335",
    "sg:province":"Z\u00fcrich",
    "wof:name":"Olg Pf\u00e4ffikon",
    "wof:placetype":"venue"
},
  "geometry": {"coordinates":[8.8248538971,47.3707046509],"type":"Point"}
}