{
  "type": "Feature",
  "properties": {
    "addr:full":"Sonnwil Emmetten Nidwalden 6376",
    "addr:housenumber":"6376",
    "iso:country":"CH",
    "sg:address":"Sonnwil",
    "sg:city":"Emmetten",
    "sg:orig_category":"Architektur U Ingenieurb\u00fcros",
    "sg:postcode":"6376",
    "sg:province":"Nidwalden",
    "wof:name":"Yasava Aeronautics, Mbanefo Christopher",
    "wof:placetype":"venue"
},
  "geometry": {"coordinates":[8.519867,46.956242],"type":"Point"}
}