{
  "type": "Feature",
  "properties": {
    "iso:country":"CH",
    "sg:address":"Kilchgrundstrasse 25",
    "sg:city":"Ostermundigen",
    "sg:orig_category":"Primarschulen",
    "sg:phone":"+41 32 623 15 76",
    "sg:postcode":"3072",
    "sg:province":"Bern",
    "wof:name":"Primarschule M\u00fchlacker",
    "wof:placetype":"venue"
},
  "geometry": {"coordinates":[7.5015997887,47.2306404114],"type":"Point"}
}