{
  "type": "Feature",
  "properties": {
    "iso:country":"CH",
    "sg:address":"Klybeckstrasse 141 4057 Basel. Postfach",
    "sg:city":"Basel",
    "sg:orig_category":"Sportvereine Ballsport Tischtennis",
    "sg:phone":"+41 61 696 11 11",
    "sg:postcode":"4002",
    "sg:province":"Basel-Stadt",
    "wof:name":"Tischtennisclub Der Novartis Ag",
    "wof:placetype":"venue"
},
  "geometry": {"coordinates":[7.5898628235,47.5712089539],"type":"Point"}
}