{
  "type": "Feature",
  "properties": {
    "iso:country":"CH",
    "sg:address":"Restaurant Fleschen",
    "sg:city":"Bellwald",
    "sg:orig_category":"RESTAURANTS: TEA-ROOMS",
    "sg:postcode":"3997",
    "sg:province":"Valais",
    "wof:name":"Volken-ritz Gmbh",
    "wof:placetype":"venue"
},
  "geometry": {"coordinates":[8.1582765579,46.4262542725],"type":"Point"}
}