{
  "type": "Feature",
  "properties": {
    "iso:country":"CH",
    "sg:address":"Quaderstrasse 7",
    "sg:city":"Chur",
    "sg:orig_category":"Non-Classified Establishments",
    "sg:phone":"+41 81 252 88 28",
    "sg:postcode":"7000",
    "sg:province":"Graubunden",
    "wof:name":"Wetra Ag",
    "wof:placetype":"venue"
},
  "geometry": {"coordinates":[9.5320730209,46.8523750305],"type":"Point"}
}