{
  "type": "Feature",
  "properties": {
    "iso:country":"CH",
    "sg:address":"L\u00e4rchenstrasse 9",
    "sg:city":"Kreuzlingen",
    "sg:orig_category":"Sportschulen Wassersport",
    "sg:phone":"+41 71 688 80 20",
    "sg:postcode":"8280",
    "sg:province":"Thurgau",
    "wof:name":"Kurt Meyer Segel-& Seefahrtsschule",
    "wof:placetype":"venue"
},
  "geometry": {"coordinates":[9.1892242432,47.6369590759],"type":"Point"}
}