{
  "type": "Feature",
  "properties": {
    "iso:country":"CH",
    "sg:address":"Le V\u00e9l\u00e9",
    "sg:city":"Sonceboz-sombeval",
    "sg:orig_category":"Herstellung von keramischen Wand U Bodenfliesen U platten Verlegen von Fliesen U Platten",
    "sg:phone":"+41 32 489 18 44",
    "sg:postcode":"2605",
    "sg:province":"Bern",
    "wof:name":"S. Marchesi & Fils Entreprise De Carrelage",
    "wof:placetype":"venue"
},
  "geometry": {"coordinates":[7.1623139381,47.1957740784],"type":"Point"}
}