{
  "type": "Feature",
  "properties": {
    "iso:country":"CH",
    "sg:address":"Via Del Tiglio 52",
    "sg:city":"Lugano",
    "sg:orig_category":"Grosshandel mit pharmazeutischen Erzeugnissen",
    "sg:phone":"+41 91 971 59 53",
    "sg:postcode":"6900",
    "sg:province":"Ticino",
    "wof:name":"Mondopuro Sa",
    "wof:placetype":"venue"
},
  "geometry": {"coordinates":[8.9692029953,46.0079460144],"type":"Point"}
}