{
  "type": "Feature",
  "properties": {
    "iso:country":"CH",
    "sg:address":"1042",
    "sg:city":"Assens",
    "sg:orig_category":"Herstellung von Konstruktionsteilen, Fertigbauteilen U Ausbauelementen aus Holz Innenausbau",
    "sg:phone":"+41 21 881 13 72",
    "sg:postcode":"1042",
    "sg:province":"Vaud",
    "wof:name":"Despont Florian.",
    "wof:placetype":"venue"
},
  "geometry": {"coordinates":[6.6212000847,46.6141357422],"type":"Point"}
}