{
  "type": "Feature",
  "properties": {
    "iso:country":"CH",
    "sg:address":"Rue De Gen\u00e8ve 117",
    "sg:city":"Th\u00f4nex",
    "sg:orig_category":"Handel mit Motorr\u00e4dern, Teilen U Zubeh\u00f6r Instandhaltung U Reparatur von Motorr\u00e4dern",
    "sg:phone":"+41 22 349 64 47",
    "sg:postcode":"1226",
    "sg:province":"Gen\u00e8ve",
    "wof:name":"Cyclomoteurs Esteban",
    "wof:placetype":"venue"
},
  "geometry": {"coordinates":[6.2021341324,46.1932296753],"type":"Point"}
}