{
  "type": "Feature",
  "properties": {
    "iso:country":"CH",
    "sg:address":"Saint-henri Rue",
    "sg:city":"Delsberg",
    "sg:orig_category":"Pensionskassen",
    "sg:postcode":"2800",
    "sg:province":"Jura",
    "wof:name":"Fondation Patronale De Pr\u00e9voyance En Faveur Des Collaborateurs Du Groupe E.i. Du Pont De Nemours And Company \u00e9tablis En Dehors De Suisse",
    "wof:placetype":"venue"
},
  "geometry": {"coordinates":[6.126830101,46.2368164062],"type":"Point"}
}