{
  "type": "Feature",
  "properties": {
    "iso:country":"CH",
    "sg:address":"Rebbergstrasse 6",
    "sg:city":"Trimbach",
    "sg:orig_category":"Sportvereine Turnen",
    "sg:phone":"+41 62 293 37 01",
    "sg:postcode":"4632",
    "sg:province":"Solothurn",
    "wof:name":"Katholischer Turnverein",
    "wof:placetype":"venue"
},
  "geometry": {"coordinates":[7.8913769722,47.3663711548],"type":"Point"}
}