{
  "type": "Feature",
  "properties": {
    "iso:country":"CH",
    "sg:address":"Rosengartenweg 5",
    "sg:city":"Basel",
    "sg:orig_category":"Softwareentwicklung U beratung",
    "sg:phone":"+41 79 688 39 80",
    "sg:postcode":"4058",
    "sg:province":"Basel-Stadt",
    "wof:name":"Butsch Informatik",
    "wof:placetype":"venue"
},
  "geometry": {"coordinates":[7.6030650139,47.5592384338],"type":"Point"}
}