{
  "type": "Feature",
  "properties": {
    "iso:country":"CH",
    "sg:address":"Stadthausgasse 1 8200 Schaffhausen. Postfach",
    "sg:city":"Schaffhausen",
    "sg:orig_category":"Erbringung von Dienstleistungen f\u00fcr Unternehmen",
    "sg:postcode":"8200",
    "sg:province":"Schaffhausen",
    "wof:name":"Abaco Design Gmbh Einrichtungsgegenst\u00e4nde; Design U. Handel Usw.",
    "wof:placetype":"venue"
},
  "geometry": {"coordinates":[8.6357488632,47.6968803406],"type":"Point"}
}