{
  "type": "Feature",
  "properties": {
    "iso:country":"CH",
    "sg:address":"Weinbergstrasse 93 8006 Z\u00fcrich. Postfach",
    "sg:city":"Z\u00fcrich",
    "sg:orig_category":"Pensionskassen",
    "sg:phone":"+41 71 767 80 00",
    "sg:postcode":"8001",
    "sg:province":"Z\u00fcrich",
    "wof:name":"Wohlfahrtsfonds Der Firma Winterhalter Gastronom Ag",
    "wof:placetype":"venue"
},
  "geometry": {"coordinates":[9.550031662,47.3018035889],"type":"Point"}
}