{
  "type": "Feature",
  "properties": {
    "iso:country":"CH",
    "sg:address":"Ipsachstrasse 16",
    "sg:city":"Nidau",
    "sg:orig_category":"Herstellung von Werkzeugmaschinen Pulvermetallurgie Schmieden, Pressen, Stanzen U Profilwalzen von M",
    "sg:phone":"+41 61 716 94 00",
    "sg:postcode":"2560",
    "sg:province":"Bern",
    "wof:name":"Lasertec Ag",
    "wof:placetype":"venue"
},
  "geometry": {"coordinates":[7.598069191,47.4860992432],"type":"Point"}
}