{
  "type": "Feature",
  "properties": {
    "iso:country":"CH",
    "sg:address":"Oberdorf",
    "sg:city":"Seelisberg",
    "sg:classifiers":[
        {
            "category":"Restaurant",
            "type":"Food & Drink"
        }
    ],
    "sg:phone":"+41 41 820 12 89",
    "sg:postcode":"6377",
    "sg:province":"Uri",
    "sg:tags":[
        "tea-rooms",
        "restaurants"
    ],
    "wof:name":"Aschwanden + Ming, Restaurant Alpenblick",
    "wof:placetype":"venue"
},
  "geometry": {"coordinates":[8.5853796005,46.9748535156],"type":"Point"}
}