{
  "type": "Feature",
  "properties": {
    "iso:country":"CH",
    "sg:address":"Riedern",
    "sg:city":"Diemtigen",
    "sg:orig_category":"Personenbef\u00f6rderung im Linienverkehr zu Land",
    "sg:postcode":"3754",
    "sg:province":"Bern",
    "wof:name":"Skilift Halten-springenboden Ag",
    "wof:placetype":"venue"
},
  "geometry": {"coordinates":[7.56417799,46.6173591614],"type":"Point"}
}