{
  "type": "Feature",
  "properties": {
    "iso:country":"CH",
    "sg:address":"Im Struppen 1",
    "sg:city":"Z\u00fcrich",
    "sg:orig_category":"Arztpraxen",
    "sg:phone":"+41 14313636",
    "sg:postcode":"8048",
    "sg:province":"Z\u00fcrich",
    "wof:name":"Dr.med.walter Kuhn Spezialarzt Fmh",
    "wof:placetype":"venue"
},
  "geometry": {"coordinates":[8.482837,47.388252],"type":"Point"}
}