{
  "type": "Feature",
  "properties": {
    "addr:full":"Lavaterstrasse 61 8002 Z\u00fcrich. Postfach 390 Z\u00fcrich Z\u00fcrich 8027",
    "addr:housenumber":"61;390",
    "addr:postcode":"8002 zuerich.;8027",
    "addr:street":"Lavaterstrasse;Postfach",
    "iso:country":"CH",
    "sg:address":"Lavaterstrasse 61 8002 Z\u00fcrich. Postfach 390",
    "sg:city":"Z\u00fcrich",
    "sg:orig_category":"Advokaturb\u00fcros",
    "sg:phone":"+41 12017047",
    "sg:postcode":"8027",
    "sg:province":"Z\u00fcrich",
    "wof:name":"Dr. Iur. Thomas Merten Advokaturb\u00fcro",
    "wof:placetype":"venue"
},
  "geometry": {"coordinates":[8.532981,47.361465],"type":"Point"}
}