{
  "type": "Feature",
  "properties": {
    "iso:country":"CH",
    "sg:address":"Im M\u00fcsli 16",
    "sg:city":"Uttwil",
    "sg:orig_category":"Sonstiger Grosshandel",
    "sg:phone":"+41 71 460 08 48",
    "sg:postcode":"8592",
    "sg:province":"Thurgau",
    "wof:name":"Dare Import & Handel Brunschweiler Daniel R.",
    "wof:placetype":"venue"
},
  "geometry": {"coordinates":[9.3468103409,47.5832138062],"type":"Point"}
}