{
  "type": "Feature",
  "properties": {
    "iso:country":"CH",
    "sg:address":"B\u00fcrenstrasse 65",
    "sg:city":"L\u00fcsslingen",
    "sg:orig_category":"Sportvereine Ski",
    "sg:phone":"+41 52 741 13 32",
    "sg:postcode":"4574",
    "sg:province":"Solothurn",
    "wof:name":"Skiclub Stein Am Rhein",
    "wof:placetype":"venue"
},
  "geometry": {"coordinates":[8.8609771729,47.6548538208],"type":"Point"}
}