{
  "type": "Feature",
  "properties": {
    "iso:country":"CH",
    "sg:address":"Nordstrasse 350",
    "sg:city":"Z\u00fcrich",
    "sg:orig_category":"Erschliessung von Grundst\u00fccken",
    "sg:phone":"+41 12714850",
    "sg:postcode":"8037",
    "sg:province":"Z\u00fcrich",
    "wof:name":"Baugesellschaft Suwo Ag",
    "wof:placetype":"venue"
},
  "geometry": {"coordinates":[8.5194454193,47.3965606689],"type":"Point"}
}