{
  "type": "Feature",
  "properties": {
    "iso:country":"CH",
    "sg:address":"Place Beaulieu 40",
    "sg:city":"Sierre",
    "sg:orig_category":"Fast-Foodrestaurants Sonstiger Fachdetailhandel mit Nahrungsmitteln, Getr\u00e4nken U Tabak in Verkaufsr\u00e4",
    "sg:phone":"+41 27 456 73 34",
    "sg:postcode":"3960",
    "sg:province":"Valais",
    "wof:name":"Snack Istanbul Sp\u00e9cialit\u00e9s Turques",
    "wof:placetype":"venue"
},
  "geometry": {"coordinates":[7.5295600891,46.2909889221],"type":"Point"}
}