{
  "type": "Feature",
  "properties": {
    "iso:country":"CH",
    "sg:address":"Arneggerstrasse 7",
    "sg:city":"Waldkirch",
    "sg:orig_category":"Bauspenglerei Sanit\u00e4rinstallation",
    "sg:phone":"+41 71 433 15 85",
    "sg:postcode":"9205",
    "sg:province":"St. Gallen",
    "wof:name":"M\u00fcggler Ag Spenglerei-sanit\u00e4r Bauspenglerei, Sanit\u00e4rinstallationsgesch\u00e4ft",
    "wof:placetype":"venue"
},
  "geometry": {"coordinates":[9.28414,47.467846],"type":"Point"}
}