{
  "type": "Feature",
  "properties": {
    "iso:country":"CH",
    "sg:address":"Neuhus 8633 Wolfhausen. Postfach",
    "sg:city":"Wolfhausen",
    "sg:orig_category":"Dienstleistungen im Gartenbau",
    "sg:phone":"+41 79 426 58 26",
    "sg:postcode":"8633",
    "sg:province":"Z\u00fcrich",
    "wof:name":"Hediger Gartenbau Gmbh",
    "wof:placetype":"venue"
},
  "geometry": {"coordinates":[8.8012151718,47.2571754456],"type":"Point"}
}