{
  "type": "Feature",
  "properties": {
    "addr:full":"3110 M\u00fcnsingen Bern 3110",
    "addr:housenumber":"3110",
    "addr:postcode":"3110",
    "addr:street":"Muensingen Bern",
    "iso:country":"CH",
    "sg:address":"3110",
    "sg:city":"M\u00fcnsingen",
    "sg:classifiers":[
        {
            "category":"Social Services",
            "subcategory":"Retirement Home",
            "type":"Services"
        }
    ],
    "sg:phone":"+41 31 721 10 22",
    "sg:postcode":"3110",
    "sg:province":"Bern",
    "sg:tags":[
        "pflegeheime",
        "u",
        "alters"
    ],
    "wof:name":"Alters-& Pflegeheim Stadt Bern",
    "wof:placetype":"venue"
},
  "geometry": {"coordinates":[7.562902,46.874954],"type":"Point"}
}