{
  "type": "Feature",
  "properties": {
    "iso:country":"CH",
    "sg:address":"Breitenstrasse 38 6078 Lungern. Postfach 10",
    "sg:city":"Lungern",
    "sg:orig_category":"Sanit\u00e4r U Heizungsinstallation Sanit\u00e4r, Heizungs U L\u00fcftungsinstallation",
    "sg:phone":"+41 41 678 21 20",
    "sg:postcode":"6078",
    "sg:province":"Obwalden",
    "wof:name":"Heipro Gasser Alex Gmbh",
    "wof:placetype":"venue"
},
  "geometry": {"coordinates":[8.1635780334,46.7888793945],"type":"Point"}
}