{
  "type": "Feature",
  "properties": {
    "iso:country":"CH",
    "sg:address":"Rue De La L\u00e8ch\u00e8re 61",
    "sg:city":"Bulle",
    "sg:orig_category":"Sportvereine Sch\u00fctzen Pistolen-& Gewehr",
    "sg:postcode":"1630",
    "sg:province":"Fribourg",
    "wof:name":"St\u00e9 De Tir Au Pistolet Jorat",
    "wof:placetype":"venue"
},
  "geometry": {"coordinates":[6.7640500069,46.5876998901],"type":"Point"}
}