{
  "type": "Feature",
  "properties": {
    "iso:country":"CH",
    "sg:address":"Hammerstrasse 56",
    "sg:city":"Basel",
    "sg:classifiers":[
        {
            "category":"Restaurant",
            "type":"Food & Drink"
        }
    ],
    "sg:phone":"+41 61 691 69 69",
    "sg:postcode":"4058",
    "sg:province":"Basel-Stadt",
    "wof:name":"Restaurant Clarahof Basler Guttempler",
    "wof:placetype":"venue"
},
  "geometry": {"coordinates":[7.5972108841,47.5621337891],"type":"Point"}
}