{
  "type": "Feature",
  "properties": {
    "iso:country":"CH",
    "sg:address":"Wehntalerstrasse 44 8157 Dielsdorf. Postfach 260",
    "sg:city":"Dielsdorf",
    "sg:orig_category":"Detailhandel mit B\u00fcchern, Zeitungen, Schreib U Papeteriewaren Detailhandel mit Schreib U Papeteriewa",
    "sg:phone":"+41 18530975",
    "sg:postcode":"8157",
    "sg:province":"Z\u00fcrich",
    "wof:name":"Papeterie V\u00f6geli Ag",
    "wof:placetype":"venue"
},
  "geometry": {"coordinates":[8.453928,47.48045],"type":"Point"}
}