{
  "type": "Feature",
  "properties": {
    "iso:country":"CH",
    "sg:address":"3176",
    "sg:city":"Neuenegg",
    "sg:orig_category":"Sportvereine Sch\u00fctzen",
    "sg:phone":"+41 31 741 31 02",
    "sg:postcode":"3176",
    "sg:province":"Bern",
    "wof:name":"Milit\u00e4rsch\u00fctzen Bramberg",
    "wof:placetype":"venue"
},
  "geometry": {"coordinates":[7.3022098541,46.8938751221],"type":"Point"}
}