{
  "type": "Feature",
  "properties": {
    "addr:full":"Wankdorffeldstrasse 102 Bern Bern 3014",
    "addr:housenumber":"102",
    "addr:postcode":"3014",
    "addr:street":"Wankdorffeldstrasse",
    "iso:country":"CH",
    "sg:address":"Wankdorffeldstrasse 102",
    "sg:city":"Bern",
    "sg:orig_category":"Detailhandel mit Computern U Software Hardwareberatung",
    "sg:phone":"+41 31 335 63 83",
    "sg:postcode":"3014",
    "sg:province":"Bern",
    "wof:name":"Seraq Ag Informatik",
    "wof:placetype":"venue"
},
  "geometry": {"coordinates":[7.455762,46.964394],"type":"Point"}
}