{
  "type": "Feature",
  "properties": {
    "iso:country":"CH",
    "sg:address":"Muristrasse 66",
    "sg:city":"Belp",
    "sg:orig_category":"Gartenbau",
    "sg:phone":"+41 31 819 51 31",
    "sg:postcode":"3123",
    "sg:province":"Bern",
    "wof:name":"Gartenbau Filipe",
    "wof:placetype":"venue"
},
  "geometry": {"coordinates":[7.4999060631,46.9016113281],"type":"Point"}
}