{
  "type": "Feature",
  "properties": {
    "iso:country":"CH",
    "sg:address":"Chantemerle 11g",
    "sg:city":"Montagne-moutier",
    "sg:orig_category":"Gesundheitswesen",
    "sg:postcode":"2740",
    "sg:province":"Bern",
    "wof:name":"Gassmann Jean-ren\u00e9",
    "wof:placetype":"venue"
},
  "geometry": {"coordinates":[7.3586091995,47.2784194946],"type":"Point"}
}