{
  "type": "Feature",
  "properties": {
    "iso:country":"CH",
    "sg:address":"Burgunderstrasse 31",
    "sg:city":"Basel",
    "sg:orig_category":"Fotografische Ateliers",
    "sg:phone":"+41 61 271 08 30",
    "sg:postcode":"4051",
    "sg:province":"Basel-Stadt",
    "wof:name":"Bruno Th\u00fcring Fotograf",
    "wof:placetype":"venue"
},
  "geometry": {"coordinates":[7.5789880753,47.5526618958],"type":"Point"}
}