{
  "type": "Feature",
  "properties": {
    "iso:country":"CH",
    "sg:address":"T\u00fcfenbergstrasse 58",
    "sg:city":"Sch\u00f6nengrund",
    "sg:orig_category":"Elektroinstallation",
    "sg:phone":"+41 71 361 11 27",
    "sg:postcode":"9105",
    "sg:province":"Appenzell Ausserrhoden",
    "wof:name":"Knaus Kurt Elektro-installationen Und Planungs Ag",
    "wof:placetype":"venue"
},
  "geometry": {"coordinates":[9.2268896103,47.326499939],"type":"Point"}
}