{
  "type": "Feature",
  "properties": {
    "iso:country":"CH",
    "sg:address":"Grund Ostergau 6130 Willisau. Postfach",
    "sg:city":"Willisau",
    "sg:orig_category":"Herstellung von sonstigen Holzwaren",
    "sg:phone":"+41 41 970 24 65",
    "sg:postcode":"6130",
    "sg:province":"Luzern",
    "wof:name":"Drechslerei B\u00e4ttig Anton Gmbh Drechsler- U. Gravurarbeiten Usw",
    "wof:placetype":"venue"
},
  "geometry": {"coordinates":[8.0130376816,47.1156997681],"type":"Point"}
}