{
  "type": "Feature",
  "properties": {
    "iso:country":"CH",
    "sg:address":"Alte Bremgartenstrasse 8",
    "sg:city":"Rudolfstetten",
    "sg:orig_category":"Nationale Postdienste",
    "sg:phone":"+41 56 249 14 00",
    "sg:postcode":"8964",
    "sg:province":"Aargau",
    "wof:name":"Die Schweizerische Post",
    "wof:placetype":"venue"
},
  "geometry": {"coordinates":[8.321146965,47.5710258484],"type":"Point"}
}