{
  "type": "Feature",
  "properties": {
    "iso:country":"CH",
    "sg:address":"Epine 47",
    "sg:city":"Diesse",
    "sg:orig_category":"Mechanik",
    "sg:phone":"+41 32 315 28 59",
    "sg:postcode":"2517",
    "sg:province":"Bern",
    "wof:name":"Serrurerie De L'epine, M\u00fcller Laurent",
    "wof:placetype":"venue"
},
  "geometry": {"coordinates":[7.1266331673,47.1152458191],"type":"Point"}
}