{
  "type": "Feature",
  "properties": {
    "iso:country":"CH",
    "sg:address":"Corso San Gottardo 89 6830 Chiasso. Postfach",
    "sg:city":"Chiasso",
    "sg:orig_category":"Grosshandel mit Software Softwareentwicklung U beratung",
    "sg:phone":"+41 91 682 29 56",
    "sg:postcode":"6830",
    "sg:province":"Ticino",
    "wof:name":"Goincity Sa Prodotti Software, Immagini Digitali; Progettazione, Sviluppo Ecc",
    "wof:placetype":"venue"
},
  "geometry": {"coordinates":[9.0256509781,45.8360481262],"type":"Point"}
}