{
  "type": "Feature",
  "properties": {
    "addr:full":"Suleggstrasse 6 3600 Thun. Postfach Thun Bern 3607",
    "addr:housenumber":"6",
    "addr:postcode":"3600 thun. postfach;3607",
    "addr:street":"Suleggstrasse",
    "iso:country":"CH",
    "sg:address":"Suleggstrasse 6 3600 Thun. Postfach",
    "sg:city":"Thun",
    "sg:orig_category":"Bau U Wohngenossenschaften",
    "sg:postcode":"3607",
    "sg:province":"Bern",
    "wof:name":"Bau-& Wohngen.hohmad",
    "wof:placetype":"venue"
},
  "geometry": {"coordinates":[7.620188,46.749268],"type":"Point"}
}