{
  "type": "Feature",
  "properties": {
    "iso:country":"CH",
    "sg:address":"Z\u00fcrcherstrasse 32",
    "sg:city":"Feuerthalen",
    "sg:orig_category":"Herstellung von Reiseartikeln, Leder U Sattlerwaren",
    "sg:postcode":"8245",
    "sg:province":"Z\u00fcrich",
    "wof:name":"In-dekorationen Meier Yvonne Polsterarbeiten. Neubez\u00fcge Usw",
    "wof:placetype":"venue"
},
  "geometry": {"coordinates":[8.5492649078,47.3177337646],"type":"Point"}
}