{
  "type": "Feature",
  "properties": {
    "iso:country":"CH",
    "sg:address":"Hauptstr. 72",
    "sg:city":"M\u00fcstair",
    "sg:orig_category":"Grosshandel mit Getr\u00e4nken",
    "sg:phone":"+41 56 622 54 80",
    "sg:postcode":"7537",
    "sg:province":"Graubunden",
    "wof:name":"Schwegler Beat Wein Und Getr\u00e4nkehandlung",
    "wof:placetype":"venue"
},
  "geometry": {"coordinates":[8.2965021133,47.3748435974],"type":"Point"}
}