{
  "type": "Feature",
  "properties": {
    "iso:country":"CH",
    "sg:address":"Gasstrasse 15",
    "sg:city":"Basel",
    "sg:orig_category":"Allgemeiner Hoch U Tiefbau",
    "sg:phone":"+41 61 421 77 30",
    "sg:postcode":"4056",
    "sg:province":"Basel-Stadt",
    "wof:name":"Glanzmann Service Ag",
    "wof:placetype":"venue"
},
  "geometry": {"coordinates":[7.577153,47.570057],"type":"Point"}
}