{
  "type": "Feature",
  "properties": {
    "iso:country":"CH",
    "sg:address":"2740",
    "sg:city":"Montagne-moutier",
    "sg:orig_category":"Pensionskassen",
    "sg:postcode":"2740",
    "sg:province":"Bern",
    "wof:name":"Fonds De Pr\u00e9voyance Compl\u00e9mentaire Des Verreries De Moutier Holding Sa",
    "wof:placetype":"venue"
},
  "geometry": {"coordinates":[7.3724632263,47.2787246704],"type":"Point"}
}