{
  "type": "Feature",
  "properties": {
    "iso:country":"CH",
    "sg:address":"Avenue Du Grand-champsec 30",
    "sg:city":"Sion",
    "sg:classifiers":[
        {
            "category":"Wholesale",
            "subcategory":"Petroleum",
            "type":"Manufacturing & Wholesale Goods"
        }
    ],
    "sg:phone":"+41 27 203 56 83",
    "sg:postcode":"1950",
    "sg:province":"Valais",
    "sg:tags":[
        "swiss",
        "wine"
    ],
    "wof:name":"Fr\u00e9d\u00e9ric Varone Vins Sa",
    "wof:placetype":"venue"
},
  "geometry": {"coordinates":[7.3841128349,46.2314453125],"type":"Point"}
}