{
  "type": "Feature",
  "properties": {
    "iso:country":"CH",
    "sg:address":"Chemin De La Redoute 2",
    "sg:city":"Villars-sur-gl\u00e2ne",
    "sg:orig_category":"Vermietung U Verpachtung von eigenen Immobilien",
    "sg:phone":"+41 26 402 13 34",
    "sg:postcode":"1752",
    "sg:province":"Fribourg",
    "wof:name":"Godel Francis",
    "wof:placetype":"venue"
},
  "geometry": {"coordinates":[7.1348099709,46.8007621765],"type":"Point"}
}