{
  "type": "Feature",
  "properties": {
    "iso:country":"CH",
    "sg:address":"Im Junker 5 8143 Stallikon. Postfach",
    "sg:city":"Stallikon",
    "sg:orig_category":"Hochschulen U h\u00f6here Ausbildung",
    "sg:phone":"+41 17001730",
    "sg:postcode":"8143",
    "sg:province":"Z\u00fcrich",
    "wof:name":"Milne Institute Gmbh Grund- U. Weiterbildungskurse F. K\u00f6rpertherapie",
    "wof:placetype":"venue"
},
  "geometry": {"coordinates":[8.4853038788,47.3423118591],"type":"Point"}
}