{
  "type": "Feature",
  "properties": {
    "iso:country":"CH",
    "sg:address":"Chemin Des Salines 18a",
    "sg:city":"Aigle",
    "sg:orig_category":"Grosshandel mit Baumaschinen Vermietung von Baumaschinen U ger\u00e4ten",
    "sg:postcode":"1860",
    "sg:province":"Vaud",
    "wof:name":"Jean-fran\u00e7ois Grogg S\u00e0rl Machines De Chantiers",
    "wof:placetype":"venue"
},
  "geometry": {"coordinates":[6.960515976,46.3226966858],"type":"Point"}
}