{
  "type": "Feature",
  "properties": {
    "iso:country":"CH",
    "sg:address":"Dorfstrasse 74",
    "sg:city":"Trubschachen",
    "sg:orig_category":"Detailhandel mit Sportartikeln",
    "sg:phone":"+41 34 495 55 11",
    "sg:postcode":"3555",
    "sg:province":"Bern",
    "wof:name":"Atelier Creativ Gleitschirm-service",
    "wof:placetype":"venue"
},
  "geometry": {"coordinates":[7.8369932175,46.9238204956],"type":"Point"}
}