{
  "type": "Feature",
  "properties": {
    "iso:country":"CH",
    "sg:address":"Hintere Grundstrasse 28",
    "sg:city":"Fehraltorf",
    "sg:orig_category":"G\u00fcterbef\u00f6rderung im Strassenverkehr",
    "sg:phone":"+41 19551759",
    "sg:postcode":"8320",
    "sg:province":"Z\u00fcrich",
    "wof:name":"Nicham Christian Transporte",
    "wof:placetype":"venue"
},
  "geometry": {"coordinates":[8.7591104507,47.3862762451],"type":"Point"}
}