{
  "type": "Feature",
  "properties": {
    "iso:country":"CH",
    "sg:address":"Viale Stazione 4",
    "sg:city":"Bellinzona",
    "sg:orig_category":"Gesundheitswesen Physiotherapie",
    "sg:phone":"+41 91 825 62 61",
    "sg:postcode":"6500",
    "sg:province":"Ticino",
    "wof:name":"Cereghetti Ivan",
    "wof:placetype":"venue"
},
  "geometry": {"coordinates":[9.0237903595,46.1918449402],"type":"Point"}
}