{
  "type": "Feature",
  "properties": {
    "iso:country":"CH",
    "sg:address":"Heuberg 42",
    "sg:city":"Basel",
    "sg:orig_category":"Pensionskassen",
    "sg:phone":"+41 71 278 81 61",
    "sg:postcode":"4051",
    "sg:province":"Basel-Stadt",
    "wof:name":"Jubil\u00e4ums-f\u00fcrsorgestiftung 1945 Der Firma Schuster & Co Ag",
    "wof:placetype":"venue"
},
  "geometry": {"coordinates":[9.3363304138,47.4099197388],"type":"Point"}
}