{
  "type": "Feature",
  "properties": {
    "iso:country":"CH",
    "sg:address":"Seebuchtstrasse 1",
    "sg:city":"Buochs",
    "sg:orig_category":"D\u00e4mmung gegen K\u00e4lte, W\u00e4rme, Schall U Ersch\u00fctterung",
    "sg:phone":"+41 76 398 02 81",
    "sg:postcode":"6374",
    "sg:province":"Nidwalden",
    "wof:name":"Christen Brandschutz Ag",
    "wof:placetype":"venue"
},
  "geometry": {"coordinates":[8.4197311401,46.9755706787],"type":"Point"}
}