{
  "type": "Feature",
  "properties": {
    "iso:country":"CH",
    "sg:address":"Neuch\u00e2tel Route De 15a",
    "sg:city":"St-blaise",
    "sg:orig_category":"Unclassifiable Establishments",
    "sg:postcode":"2072",
    "sg:province":"Neuch\u00e2tel",
    "wof:name":"Le Billard.ch, Mm. Pauchon Et Luccarini",
    "wof:placetype":"venue"
},
  "geometry": {"coordinates":[5.1808700562,45.8973388672],"type":"Point"}
}