{
  "type": "Feature",
  "properties": {
    "iso:country":"CH",
    "sg:address":"Pappelweg 5 4800 Zofingen. Postfach",
    "sg:city":"Oftringen",
    "sg:orig_category":"Herstellung von Konstruktionsteilen, Fertigbauteilen U Ausbauelementen aus Holz",
    "sg:phone":"+41 62 797 17 87",
    "sg:postcode":"4665",
    "sg:province":"Aargau",
    "wof:name":"E. Meier-za Schreinerei 4800 Zofingen",
    "wof:placetype":"venue"
},
  "geometry": {"coordinates":[7.9487991333,47.28074646],"type":"Point"}
}