{
  "type": "Feature",
  "properties": {
    "iso:country":"CH",
    "sg:address":"Postplatz",
    "sg:city":"Grosswangen",
    "sg:classifiers":[
        {
            "category":"Banks & Credit Unions",
            "subcategory":"Bank",
            "type":"Services"
        }
    ],
    "sg:phone":"+41 4145712727",
    "sg:postcode":"6022",
    "sg:province":"Luzern",
    "wof:name":"Volksbank Willisau",
    "wof:placetype":"venue"
},
  "geometry": {"coordinates":[8.048565,47.133694],"type":"Point"}
}