{
  "type": "Feature",
  "properties": {
    "iso:country":"CH",
    "sg:address":"Hohr\u00fcti 24b",
    "sg:city":"Speicher",
    "sg:orig_category":"Unternehmensberatung",
    "sg:postcode":"9042",
    "sg:province":"Appenzell Ausserrhoden",
    "wof:name":"K\u00fchne Hanspeter",
    "wof:placetype":"venue"
},
  "geometry": {"coordinates":[9.4394311905,47.4179649353],"type":"Point"}
}