{
  "type": "Feature",
  "properties": {
    "iso:country":"CH",
    "sg:address":"Geissbergstrasse 81",
    "sg:city":"Schaffhausen",
    "sg:orig_category":"Universit\u00e4tsspit\u00e4ler, Spit\u00e4ler f\u00fcr allgemeine Pflege",
    "sg:phone":"+41 17615111",
    "sg:postcode":"8208",
    "sg:province":"Schaffhausen",
    "wof:name":"Kinderspital Z\u00fcrich",
    "wof:placetype":"venue"
},
  "geometry": {"coordinates":[8.4669122696,47.2775802612],"type":"Point"}
}