{
  "type": "Feature",
  "properties": {
    "iso:country":"CH",
    "sg:address":"Amthausgasse 8 3860 Meiringen. Postfach 559",
    "sg:city":"Meiringen",
    "sg:orig_category":"Polizei",
    "sg:phone":"+41 33 971 80 81",
    "sg:postcode":"3860",
    "sg:province":"Bern",
    "wof:name":"Kantonale Polizei",
    "wof:placetype":"venue"
},
  "geometry": {"coordinates":[8.1868906021,46.7301254272],"type":"Point"}
}