{
  "type": "Feature",
  "properties": {
    "iso:country":"CH",
    "sg:address":"1088",
    "sg:city":"Ropraz",
    "sg:orig_category":"S\u00e4ge, Hobel U Holzimpr\u00e4gnierwerke",
    "sg:postcode":"1088",
    "sg:province":"Vaud",
    "wof:name":"Gabella Victor",
    "wof:placetype":"venue"
},
  "geometry": {"coordinates":[6.7550001144,46.6073799133],"type":"Point"}
}