{
  "type": "Feature",
  "properties": {
    "iso:country":"CH",
    "sg:address":"Chemin Des Croisettes 28",
    "sg:city":"Epalinges",
    "sg:orig_category":"Herstellung von Metallerzeugnissen ohne Maschinenbau Herstellung von k\u00e4lte U lufttechnischen Erzeugn",
    "sg:phone":"+41 56 418 13 00",
    "sg:postcode":"1066",
    "sg:province":"Vaud",
    "wof:name":"Orion-al-ko Ag",
    "wof:placetype":"venue"
},
  "geometry": {"coordinates":[6.6587891579,46.5441513062],"type":"Point"}
}