{
  "type": "Feature",
  "properties": {
    "iso:country":"CH",
    "sg:address":"Birmensdorferstrasse 489",
    "sg:city":"Z\u00fcrich",
    "sg:orig_category":"Sonstiger Grosshandel",
    "sg:phone":"+41 79 631 17 80",
    "sg:postcode":"8063",
    "sg:province":"Z\u00fcrich",
    "wof:name":"Zecko Export-import Kahrimanovic",
    "wof:placetype":"venue"
},
  "geometry": {"coordinates":[8.4961948395,47.3673591614],"type":"Point"}
}