{
  "type": "Feature",
  "properties": {
    "iso:country":"CH",
    "sg:address":"H\u00f6chstr\u00e4ss 16 3065 Bolligen. Postfach 326",
    "sg:city":"Bolligen",
    "sg:orig_category":"Finanzierungsinstitutionen",
    "sg:postcode":"3065",
    "sg:province":"Bern",
    "wof:name":"B.i.n.t. Finanzgesellschaft F\u00fcr Holzwerke Ag",
    "wof:placetype":"venue"
},
  "geometry": {"coordinates":[9.8340272903,46.8032302856],"type":"Point"}
}