{
  "type": "Feature",
  "properties": {
    "iso:country":"CH",
    "sg:address":"Lutzertstrasse 40 4132 Muttenz. Postfach",
    "sg:city":"Muttenz",
    "sg:orig_category":"Grosshandel mit Getr\u00e4nken",
    "sg:phone":"+41 61 461 51 10",
    "sg:postcode":"4132",
    "sg:province":"Basel-Landschaft",
    "wof:name":"C & M 2000 Cristobal & Madero Weinhandel",
    "wof:placetype":"venue"
},
  "geometry": {"coordinates":[7.6334428787,47.5340538025],"type":"Point"}
}