{
  "type": "Feature",
  "properties": {
    "iso:country":"CH",
    "sg:address":"Florhofstrasse 7",
    "sg:city":"W\u00e4denswil",
    "sg:orig_category":"Einbau von Schreinerwaren Innenausbau",
    "sg:phone":"+41 17809075",
    "sg:postcode":"8820",
    "sg:province":"Z\u00fcrich",
    "wof:name":"In Szenario Urs Gr\u00fcnenfelder",
    "wof:placetype":"venue"
},
  "geometry": {"coordinates":[8.6709737778,47.23072052],"type":"Point"}
}