{
  "type": "Feature",
  "properties": {
    "iso:country":"CH",
    "sg:address":"La Schmetta Haus Nr. 41/42 7082 Vaz/obervaz. Postfach",
    "sg:city":"Vaz/obervaz",
    "sg:orig_category":"Allgemeiner Hoch U Tiefbau",
    "sg:postcode":"7082",
    "sg:province":"Graubunden",
    "wof:name":"Habl\u00fctzel Bau Ag",
    "wof:placetype":"venue"
},
  "geometry": {"coordinates":[9.532085,46.698975],"type":"Point"}
}