{
  "type": "Feature",
  "properties": {
    "iso:country":"CH",
    "sg:address":"Eichberg 38",
    "sg:city":"Seengen",
    "sg:classifiers":[
        {
            "category":"Travel",
            "subcategory":"Hotels & Motels",
            "type":"Entertainment"
        }
    ],
    "sg:phone":"+41 62 777 23 33",
    "sg:postcode":"5707",
    "sg:province":"Aargau",
    "sg:tags":[
        "hotels",
        "mit",
        "restaurant"
    ],
    "wof:name":"Kurhotel / Restaurant Eichberg",
    "wof:placetype":"venue"
},
  "geometry": {"coordinates":[8.2044906616,47.3391265869],"type":"Point"}
}