{
  "type": "Feature",
  "properties": {
    "iso:country":"CH",
    "sg:address":"Hohengasse 43 3400 Burgdorf. Postfach 93",
    "sg:city":"Burgdorf",
    "sg:orig_category":"Advokaturb\u00fcros",
    "sg:phone":"+41 34 422 45 48",
    "sg:postcode":"3402",
    "sg:province":"Bern",
    "wof:name":"Bruno Lehmann Advokaturb\u00fcro",
    "wof:placetype":"venue"
},
  "geometry": {"coordinates":[7.626732,47.055782],"type":"Point"}
}