{
  "type": "Feature",
  "properties": {
    "iso:country":"CH",
    "sg:address":"1997",
    "sg:city":"Siviez",
    "sg:classifiers":[
        {
            "category":"Restaurant",
            "type":"Food & Drink"
        }
    ],
    "sg:phone":"+41 27 288 18 28",
    "sg:postcode":"1997",
    "sg:province":"Valais",
    "wof:name":"Restaurant Les Bergers",
    "wof:placetype":"venue"
},
  "geometry": {"coordinates":[7.3158597946,46.136051178],"type":"Point"}
}