{
  "type": "Feature",
  "properties": {
    "iso:country":"CH",
    "sg:address":"Marktstr. 8",
    "sg:city":"Frauenfeld",
    "sg:classifiers":[
        {
            "category":"Manufacturing",
            "subcategory":"Printing",
            "type":"Manufacturing & Wholesale Goods"
        }
    ],
    "sg:phone":"+41 52 728 01 01",
    "sg:postcode":"8500",
    "sg:province":"Thurgau",
    "sg:tags":[
        "publishing"
    ],
    "wof:name":"Schletti Ag",
    "wof:placetype":"venue"
},
  "geometry": {"coordinates":[8.9001169205,47.5534706116],"type":"Point"}
}