{
  "type": "Feature",
  "properties": {
    "iso:country":"CH",
    "sg:address":"Bundtacherstr. 46 8124 Maur. Postfach",
    "sg:city":"Forch",
    "sg:orig_category":"Herstellung von Automobilen",
    "sg:postcode":"8127",
    "sg:province":"Z\u00fcrich",
    "wof:name":"Altherr Nutzfahrzeuge-ag",
    "wof:placetype":"venue"
},
  "geometry": {"coordinates":[9.1993598938,47.2241897583],"type":"Point"}
}