{
  "type": "Feature",
  "properties": {
    "iso:country":"CH",
    "sg:address":"Gustav-maurer-strasse 8",
    "sg:city":"Zollikon",
    "sg:orig_category":"Detailhandel mit M\u00f6beln U Haushaltsgegenst\u00e4nden Grosshandel mit M\u00f6beln, Wohnbedarf, Teppichen U Bode",
    "sg:phone":"+41 13915640",
    "sg:postcode":"8702",
    "sg:province":"Z\u00fcrich",
    "wof:name":"Seleform Ag",
    "wof:placetype":"venue"
},
  "geometry": {"coordinates":[8.5747699738,47.3428497314],"type":"Point"}
}