{
  "type": "Feature",
  "properties": {
    "iso:country":"CH",
    "sg:address":"Weissensteinstrasse 146",
    "sg:city":"Oberdorf",
    "sg:classifiers":[
        {
            "category":"Shopping",
            "subcategory":"Luggage & Leather Goods",
            "type":"Retail Goods"
        }
    ],
    "sg:phone":"+41 32 622 66 44",
    "sg:postcode":"4515",
    "sg:province":"Solothurn",
    "sg:tags":[
        "fitting",
        "goods",
        "miscellaneous"
    ],
    "wof:name":"Amiet Ag",
    "wof:placetype":"venue"
},
  "geometry": {"coordinates":[7.4976420403,47.2330970764],"type":"Point"}
}