{
  "type": "Feature",
  "properties": {
    "iso:country":"CH",
    "sg:address":"Forte Via Al 3 6900 Lugano Casella Postale 203",
    "sg:city":"Lugano",
    "sg:orig_category":"Grosshandel mit lebenden Tieren",
    "sg:postcode":"6900",
    "sg:province":"Ticino",
    "wof:name":"Clerc Andr\u00e9",
    "wof:placetype":"venue"
},
  "geometry": {"coordinates":[6.9719400406,46.2053909302],"type":"Point"}
}