{
  "type": "Feature",
  "properties": {
    "iso:country":"CH",
    "sg:address":"Im Unterzelg 21",
    "sg:city":"Berikon",
    "sg:orig_category":"Werbegrafikateliers",
    "sg:phone":"+41 91 647 38 85",
    "sg:postcode":"8965",
    "sg:province":"Aargau",
    "wof:name":"Aldo Luisoni Studio Grafico",
    "wof:placetype":"venue"
},
  "geometry": {"coordinates":[8.9347867966,45.8594551086],"type":"Point"}
}