{
  "type": "Feature",
  "properties": {
    "iso:country":"CH",
    "sg:address":"Rest. Bad Ey 3454 Sumiswald. Postfach",
    "sg:city":"Sumiswald",
    "sg:orig_category":"RESTAURANTS: TEA-ROOMS",
    "sg:postcode":"3454",
    "sg:province":"Bern",
    "wof:name":"Stalder-aebi, Frau V.",
    "wof:placetype":"venue"
},
  "geometry": {"coordinates":[7.7379560471,47.0352745056],"type":"Point"}
}