{
  "type": "Feature",
  "properties": {
    "iso:country":"CH",
    "sg:address":"Chemin Des Chaux",
    "sg:city":"Puidoux",
    "sg:orig_category":"RESTAURANTS: TEA-ROOMS",
    "sg:postcode":"1070",
    "sg:province":"Vaud",
    "wof:name":"Henry Pierre-alain",
    "wof:placetype":"venue"
},
  "geometry": {"coordinates":[6.7948498726,46.5162467957],"type":"Point"}
}