{
  "type": "Feature",
  "properties": {
    "addr:full":"Besmerstr. 49 8280 Kreuzlingen. Postfach Kreuzlingen Thurgau 8280",
    "addr:housenumber":"49",
    "addr:postcode":"8280;postfach;8280",
    "addr:street":"Besmerstr.",
    "iso:country":"CH",
    "sg:address":"Besmerstr. 49 8280 Kreuzlingen. Postfach",
    "sg:city":"Kreuzlingen",
    "sg:orig_category":"Allgemeiner Hoch U Tiefbau",
    "sg:phone":"+41 71 688 18 10",
    "sg:postcode":"8280",
    "sg:province":"Thurgau",
    "wof:name":"Hartmann Herbert Baugesch\u00e4ft",
    "wof:placetype":"venue"
},
  "geometry": {"coordinates":[9.1908,47.638264],"type":"Point"}
}