{
  "type": "Feature",
  "properties": {
    "iso:country":"CH",
    "sg:address":"Affolternstrasse 7 8105 Regensdorf. Postfach",
    "sg:city":"Regensdorf",
    "sg:orig_category":"Reparatur von Schuhen U Lederwaren",
    "sg:postcode":"8105",
    "sg:province":"Z\u00fcrich",
    "wof:name":"N\u00e4f Armin Ag",
    "wof:placetype":"venue"
},
  "geometry": {"coordinates":[9.2849197388,47.1935844421],"type":"Point"}
}