{
  "type": "Feature",
  "properties": {
    "iso:country":"CH",
    "sg:address":"Passage Du Cardinal 2c",
    "sg:city":"Fribourg",
    "sg:orig_category":"Softwareentwicklung U beratung",
    "sg:postcode":"1700",
    "sg:province":"Fribourg",
    "wof:name":"Burch R\u00e9gis",
    "wof:placetype":"venue"
},
  "geometry": {"coordinates":[7.1472411156,46.79870224],"type":"Point"}
}