{
  "type": "Feature",
  "properties": {
    "iso:country":"CH",
    "sg:address":"Winterthurerstrasse 92 8000 Z\u00fcrich. Postfach",
    "sg:city":"Z\u00fcrich",
    "sg:orig_category":"Interessenvertretungen",
    "sg:postcode":"8021",
    "sg:province":"Z\u00fcrich",
    "wof:name":"Art Makers Association",
    "wof:placetype":"venue"
},
  "geometry": {"coordinates":[8.5455560684,47.3912162781],"type":"Point"}
}