{
  "type": "Feature",
  "properties": {
    "iso:country":"CH",
    "sg:address":"Colombettes Chemin Des 15 1202 Gen\u00e8ve. Postfach",
    "sg:city":"Gen\u00e8ve",
    "sg:orig_category":"Herstellung von nachrichtentechnischen Ger\u00e4ten U Einrichtungen",
    "sg:phone":"+41 19327770",
    "sg:postcode":"1202",
    "sg:province":"Gen\u00e8ve",
    "wof:name":"Kleiner Max",
    "wof:placetype":"venue"
},
  "geometry": {"coordinates":[8.7902460098,47.3177566528],"type":"Point"}
}