{
  "type": "Feature",
  "properties": {
    "iso:country":"CH",
    "sg:address":"Schulstrasse 73",
    "sg:city":"Regensdorf",
    "sg:orig_category":"Bezirks, Sekundar, Realschulen, Oberstufe der Primarschulen",
    "sg:phone":"+41 18403502",
    "sg:postcode":"8105",
    "sg:province":"Z\u00fcrich",
    "wof:name":"Oberstufenschule Ruggenacher I",
    "wof:placetype":"venue"
},
  "geometry": {"coordinates":[8.466568,47.434315],"type":"Point"}
}