{
  "type": "Feature",
  "properties": {
    "iso:country":"CH",
    "sg:address":"Conf\u00e9d\u00e9ration Rue De La 8 1204 Gen\u00e8ve. Postfach",
    "sg:city":"Gen\u00e8ve",
    "sg:orig_category":"Pensionskassen",
    "sg:phone":"+41 32 722 15 00",
    "sg:postcode":"1204",
    "sg:province":"Gen\u00e8ve",
    "wof:name":"Fondation De Pr\u00e9voyance En Faveur Du Personnel De La Chambre Neuch\u00e2teloise Du Commerce Et De L'industrie",
    "wof:placetype":"venue"
},
  "geometry": {"coordinates":[6.9331688881,46.9946403503],"type":"Point"}
}