{
  "type": "Feature",
  "properties": {
    "iso:country":"CH",
    "sg:address":"Allmendstrasse 19",
    "sg:city":"Fehraltorf",
    "sg:orig_category":"Wirtschaftspr\u00fcfung, Steuerberatung U Treuhand",
    "sg:phone":"+41 19550202",
    "sg:postcode":"8320",
    "sg:province":"Z\u00fcrich",
    "wof:name":"Saldor Treuhand Ag",
    "wof:placetype":"venue"
},
  "geometry": {"coordinates":[8.7407369614,47.3924446106],"type":"Point"}
}