{
  "type": "Feature",
  "properties": {
    "iso:country":"CH",
    "sg:address":"Breitistrasse 50",
    "sg:city":"Elgg",
    "sg:orig_category":"Unternehmensberatung",
    "sg:postcode":"8353",
    "sg:province":"Z\u00fcrich",
    "wof:name":"Valuepartners Gmbh",
    "wof:placetype":"venue"
},
  "geometry": {"coordinates":[8.8716220856,47.4891662598],"type":"Point"}
}