{
  "type": "Feature",
  "properties": {
    "iso:country":"CH",
    "sg:address":"Bahnhofstrasse 26 6210 Sursee. Postfach",
    "sg:city":"Sursee",
    "sg:orig_category":"Reiseb\u00fcros U Reiseveranstalter",
    "sg:phone":"+41 41 925 70 80",
    "sg:postcode":"6210",
    "sg:province":"Luzern",
    "wof:name":"H\u00e4fliger Reisen Ag",
    "wof:placetype":"venue"
},
  "geometry": {"coordinates":[8.1025733948,47.1726417542],"type":"Point"}
}