{
  "type": "Feature",
  "properties": {
    "addr:full":"Entfelderstrasse 50 Aarau Aargau 5000",
    "addr:housenumber":"50",
    "addr:postcode":"5000",
    "addr:street":"Entfelderstrasse",
    "iso:country":"CH",
    "sg:address":"Entfelderstrasse 50",
    "sg:city":"Aarau",
    "sg:orig_category":"Aktivit\u00e4ten der Krankenschwestern U Hebammen, Hauspflege Gesundheitswesen",
    "sg:phone":"+41 31 991 37 68",
    "sg:postcode":"5000",
    "sg:province":"Aargau",
    "wof:name":"Pro Vita 24 Gmbh",
    "wof:placetype":"venue"
},
  "geometry": {"coordinates":[7.436717,46.956478],"type":"Point"}
}