{
  "type": "Feature",
  "properties": {
    "iso:country":"CH",
    "sg:address":"Sentenstrasse 14 5623 Boswil. Postfach",
    "sg:city":"K\u00fcnten",
    "sg:orig_category":"Vermietung U Verpachtung von eigenen Immobilien",
    "sg:phone":"+41 56 470 15 15",
    "sg:postcode":"5444",
    "sg:province":"Aargau",
    "wof:name":"Mirasch Ag",
    "wof:placetype":"venue"
},
  "geometry": {"coordinates":[8.3120975494,47.2958679199],"type":"Point"}
}