{
  "type": "Feature",
  "properties": {
    "iso:country":"CH",
    "sg:address":"Industriestr. 4",
    "sg:city":"Altst\u00e4tten",
    "sg:classifiers":[
        {
            "category":"Shopping",
            "subcategory":"Bicycles & Sporting Goods",
            "type":"Retail Goods"
        }
    ],
    "sg:phone":"+41 31 332 90 42",
    "sg:postcode":"9450",
    "sg:province":"St. Gallen",
    "sg:tags":[
        "product",
        "sport",
        "miscellaneous"
    ],
    "wof:name":"Universal Sport Gem.",
    "wof:placetype":"venue"
},
  "geometry": {"coordinates":[7.4463338852,46.9563064575],"type":"Point"}
}