{
  "type": "Feature",
  "properties": {
    "iso:country":"CH",
    "sg:address":"Rue Du Vieux-moulin 13b",
    "sg:city":"Court\u00e9telle",
    "sg:orig_category":"Detailhandel mit elektrischen Haushalts-,Radio U Fernsehger\u00e4ten sowie Musikinstrumenten",
    "sg:postcode":"2852",
    "sg:province":"Jura",
    "wof:name":"Othrys Audio Service Othmar Stadelmann",
    "wof:placetype":"venue"
},
  "geometry": {"coordinates":[7.5633797646,46.9297447205],"type":"Point"}
}