{
  "type": "Feature",
  "properties": {
    "iso:country":"CH",
    "sg:address":"Hintermattstrasse 14",
    "sg:city":"Ziefen",
    "sg:orig_category":"Malerei",
    "sg:phone":"+41 61 931 29 89",
    "sg:postcode":"4417",
    "sg:province":"Basel-Landschaft",
    "wof:name":"Willi Hug Malergesch\u00e4ft",
    "wof:placetype":"venue"
},
  "geometry": {"coordinates":[7.7021298409,47.43201828],"type":"Point"}
}