{
  "type": "Feature",
  "properties": {
    "iso:country":"CH",
    "sg:address":"Krippenstrasse 26",
    "sg:city":"Langenthal",
    "sg:orig_category":"Unclassifiable Establishments",
    "sg:phone":"+41 62 922 98 49",
    "sg:postcode":"4900",
    "sg:province":"Bern",
    "wof:name":"Gielnova Gmbh",
    "wof:placetype":"venue"
},
  "geometry": {"coordinates":[7.7824940681,47.210723877],"type":"Point"}
}