{
  "type": "Feature",
  "properties": {
    "iso:country":"CH",
    "sg:address":"Gotthardstrasse 6454 Fl\u00fcelen. Postfach",
    "sg:city":"Fl\u00fcelen",
    "sg:classifiers":[
        {
            "category":"Travel",
            "subcategory":"Hotels & Motels",
            "type":"Entertainment"
        }
    ],
    "sg:phone":"+41 41 632 33 33",
    "sg:postcode":"6454",
    "sg:province":"Uri",
    "sg:tags":[
        "hotels",
        "mit",
        "restaurant"
    ],
    "wof:name":"N\u00e4pflin Ursula, Seehotel Belv\u00e9d\u00e8re",
    "wof:placetype":"venue"
},
  "geometry": {"coordinates":[8.3119716644,46.9836578369],"type":"Point"}
}