{
  "type": "Feature",
  "properties": {
    "iso:country":"CH",
    "sg:address":"Posta Via Della 6900 Lugano. Postfach",
    "sg:city":"Lugano",
    "sg:orig_category":"RESTAURANTS: TEA-ROOMS",
    "sg:postcode":"6900",
    "sg:province":"Ticino",
    "wof:name":"Gastro Planet Sa Esercizi Pubblici Ecc",
    "wof:placetype":"venue"
},
  "geometry": {"coordinates":[8.9525051117,46.0052261353],"type":"Point"}
}