{
  "type": "Feature",
  "properties": {
    "iso:country":"CH",
    "sg:address":"Rue De Vermont 32",
    "sg:city":"Gen\u00e8ve",
    "sg:orig_category":"Bauschreinerei Innenausbau",
    "sg:phone":"+41 56 483 36 00",
    "sg:postcode":"1202",
    "sg:province":"Gen\u00e8ve",
    "wof:name":"Glaeser Innenausbau Ag",
    "wof:placetype":"venue"
},
  "geometry": {"coordinates":[8.2907,47.451805],"type":"Point"}
}