{
  "type": "Feature",
  "properties": {
    "iso:country":"CH",
    "sg:address":"Kl\u00f6sterlistrasse 11a 6010 Kriens. Postfach 296",
    "sg:city":"Kriens",
    "sg:orig_category":"Sportvereine Turnen Vereine Damen",
    "sg:phone":"+41 41 320 94 14",
    "sg:postcode":"6011",
    "sg:province":"Luzern",
    "wof:name":"Turnerinnenverein Stv Kriens",
    "wof:placetype":"venue"
},
  "geometry": {"coordinates":[8.2748823166,47.0301780701],"type":"Point"}
}