{
  "type": "Feature",
  "properties": {
    "addr:full":"Dufourstrasse 5 Basel Basel-Stadt 4052",
    "addr:housenumber":"5",
    "addr:postcode":"4052",
    "addr:street":"Dufourstrasse",
    "iso:country":"CH",
    "sg:address":"Dufourstrasse 5",
    "sg:city":"Basel",
    "sg:orig_category":"Aktivit\u00e4ten der Generalunternehmen im Baugewerbe Architektur U Ingenieurb\u00fcros",
    "sg:phone":"+41 61 206 65 65",
    "sg:postcode":"4052",
    "sg:province":"Basel-Stadt",
    "wof:name":"Jauslin & Stebler Ingenieure Ag",
    "wof:placetype":"venue"
},
  "geometry": {"coordinates":[7.645858,47.529533],"type":"Point"}
}