{
  "type": "Feature",
  "properties": {
    "iso:country":"CH",
    "sg:address":"Bundesgasse 16",
    "sg:city":"Bern",
    "sg:orig_category":"Softwareentwicklung U beratung",
    "sg:phone":"+41 62 771 51 61",
    "sg:postcode":"3011",
    "sg:province":"Bern",
    "wof:name":"Snizek Informatik",
    "wof:placetype":"venue"
},
  "geometry": {"coordinates":[8.1928253174,47.2530403137],"type":"Point"}
}