{
  "type": "Feature",
  "properties": {
    "iso:country":"CH",
    "sg:address":"Letzigraben 106 8047 Z\u00fcrich. Postfach",
    "sg:city":"Z\u00fcrich",
    "sg:orig_category":"Herstellung von elektrischen Haushaltsger\u00e4ten Schlossereien",
    "sg:phone":"+41 14916466",
    "sg:postcode":"8047",
    "sg:province":"Z\u00fcrich",
    "wof:name":"Benetti Ag K\u00fchler, Kotfl\u00fcgel, Karosserien U. Spenglerartikel; Handel Usw.",
    "wof:placetype":"venue"
},
  "geometry": {"coordinates":[8.4982023239,47.3773994446],"type":"Point"}
}