{
  "type": "Feature",
  "properties": {
    "iso:country":"CH",
    "sg:address":"Wasserauen",
    "sg:city":"Weissbad",
    "sg:classifiers":[
        {
            "category":"Travel",
            "subcategory":"Hotels & Motels",
            "type":"Entertainment"
        }
    ],
    "sg:phone":"+41 71 799 11 33",
    "sg:postcode":"9057",
    "sg:province":"Appenzell Innerhoden",
    "sg:tags":[
        "hotels",
        "mit",
        "restaurant"
    ],
    "wof:name":"Berggasthaus Alpenrose",
    "wof:placetype":"venue"
},
  "geometry": {"coordinates":[9.4352722168,47.3014221191],"type":"Point"}
}