{
  "type": "Feature",
  "properties": {
    "iso:country":"CH",
    "sg:address":"Birkenweg 4",
    "sg:city":"Buttwil",
    "sg:orig_category":"Mechanische Werkst\u00e4tten",
    "sg:phone":"+41 56 664 11 81",
    "sg:postcode":"5632",
    "sg:province":"Aargau",
    "wof:name":"Robert Strebel Mechanische Werkst\u00e4tte",
    "wof:placetype":"venue"
},
  "geometry": {"coordinates":[8.3130311966,47.267375946],"type":"Point"}
}