{
  "type": "Feature",
  "properties": {
    "iso:country":"CH",
    "sg:address":"8753",
    "sg:city":"Mollis",
    "sg:orig_category":"Detailhandel mit Schuhen U Lederwaren",
    "sg:postcode":"8753",
    "sg:province":"Glarus",
    "wof:name":"Schuhhaus Schwitter",
    "wof:placetype":"venue"
},
  "geometry": {"coordinates":[9.0745248795,47.0914382935],"type":"Point"}
}