{
  "type": "Feature",
  "properties": {
    "iso:country":"CH",
    "sg:address":"Gr\u00fcnaustrasse 50 3084 Wabern. Postfach",
    "sg:city":"Wabern",
    "sg:orig_category":"Unternehmensberatung Wirtschaftspr\u00fcfung, Steuerberatung U Treuhand",
    "sg:phone":"+41 71 311 34 11",
    "sg:postcode":"3084",
    "sg:province":"Bern",
    "wof:name":"Triade Treuhand Ag",
    "wof:placetype":"venue"
},
  "geometry": {"coordinates":[9.3198986053,47.4267463684],"type":"Point"}
}