{
  "type": "Feature",
  "properties": {
    "iso:country":"CH",
    "sg:address":"Feld 3",
    "sg:city":"Stansstad",
    "sg:orig_category":"Erwachsenenbildung U Unterricht",
    "sg:phone":"+41 41 612 12 66",
    "sg:postcode":"6362",
    "sg:province":"Nidwalden",
    "wof:name":"Intorga Ag",
    "wof:placetype":"venue"
},
  "geometry": {"coordinates":[8.3432559967,46.9744911194],"type":"Point"}
}