{
  "type": "Feature",
  "properties": {
    "iso:country":"CH",
    "sg:address":"Dorfstrasse 72b",
    "sg:city":"Leissigen",
    "sg:orig_category":"Reiseb\u00fcros U Reiseveranstalter",
    "sg:phone":"+41 33 847 13 37",
    "sg:postcode":"3706",
    "sg:province":"Bern",
    "wof:name":"Z-tours, Zundel-sutter K. + A.",
    "wof:placetype":"venue"
},
  "geometry": {"coordinates":[7.7709650993,46.6544075012],"type":"Point"}
}