{
  "type": "Feature",
  "properties": {
    "iso:country":"CH",
    "sg:address":"Seestrandweg 37",
    "sg:city":"Erlach",
    "sg:orig_category":"Abwasserreinigung",
    "sg:phone":"+41 32 338 15 65",
    "sg:postcode":"3235",
    "sg:province":"Bern",
    "wof:name":"Abwasserreinigungsanlage",
    "wof:placetype":"venue"
},
  "geometry": {"coordinates":[7.099609,47.044109],"type":"Point"}
}