{
  "type": "Feature",
  "properties": {
    "addr:full":"Drahtzugstrasse 67a Basel Basel-Stadt 4057",
    "addr:housenumber":"67a",
    "addr:postcode":"4057",
    "addr:street":"Drahtzugstrasse",
    "iso:country":"CH",
    "sg:address":"Drahtzugstrasse 67a",
    "sg:city":"Basel",
    "sg:orig_category":"Architekturb\u00fcros",
    "sg:phone":"+41 32 652 15 77",
    "sg:postcode":"4057",
    "sg:province":"Basel-Stadt",
    "wof:name":"Atelier F.biologisches Bauen",
    "wof:placetype":"venue"
},
  "geometry": {"coordinates":[7.360456,47.177773],"type":"Point"}
}