{
  "type": "Feature",
  "properties": {
    "iso:country":"CH",
    "sg:address":"Noisetiers Chemin Des 3 1004 Lausanne. Postfach",
    "sg:city":"Lausanne",
    "sg:orig_category":"Architektur U Ingenieurb\u00fcros",
    "sg:postcode":"1003",
    "sg:province":"Vaud",
    "wof:name":"Monnier Denis Atelier D'architecture",
    "wof:placetype":"venue"
},
  "geometry": {"coordinates":[6.620509,46.530254],"type":"Point"}
}