{
  "type": "Feature",
  "properties": {
    "iso:country":"CH",
    "sg:address":"Bleikimatt 3",
    "sg:city":"Willisau",
    "sg:orig_category":"Erschliessung von Grundst\u00fccken",
    "sg:postcode":"6130",
    "sg:province":"Luzern",
    "wof:name":"Baugenossenschaft Alberswil",
    "wof:placetype":"venue"
},
  "geometry": {"coordinates":[7.9948439598,47.1175994873],"type":"Point"}
}