{
  "type": "Feature",
  "properties": {
    "iso:country":"CH",
    "sg:address":"Gallusstrasse 26",
    "sg:city":"St.gallen",
    "sg:orig_category":"Unternehmensberatung",
    "sg:phone":"+41 71 222 04 17",
    "sg:postcode":"9000",
    "sg:province":"St. Gallen",
    "wof:name":"Hogatra Hotel, Gastro & Travel Sistek Hans & Co",
    "wof:placetype":"venue"
},
  "geometry": {"coordinates":[9.3758850098,47.4228134155],"type":"Point"}
}