{
  "type": "Feature",
  "properties": {
    "addr:full":"Avenue Maurice-troillet 35 Sion Valais 1950",
    "addr:housenumber":"35",
    "addr:postcode":"1950",
    "addr:street":"Avenue Maurice-Troillet",
    "iso:country":"CH",
    "sg:address":"Avenue Maurice-troillet 35",
    "sg:city":"Sion",
    "sg:orig_category":"Betrieb von Taxis",
    "sg:postcode":"1950",
    "sg:province":"Valais",
    "wof:name":"Taxis, Pralong Albertine",
    "wof:placetype":"venue"
},
  "geometry": {"coordinates":[7.343215,46.227764],"type":"Point"}
}