{
  "type": "Feature",
  "properties": {
    "iso:country":"CH",
    "sg:address":"Breitenstrasse 120",
    "sg:city":"Stans",
    "sg:orig_category":"Satzherstellung U Reproduktion",
    "sg:phone":"+41 41 610 13 19",
    "sg:postcode":"6370",
    "sg:province":"Nidwalden",
    "wof:name":"Silvia Keiser-waser Satzstudio",
    "wof:placetype":"venue"
},
  "geometry": {"coordinates":[8.3815832138,46.9634208679],"type":"Point"}
}