{
  "type": "Feature",
  "properties": {
    "iso:country":"CH",
    "sg:address":"Im Gr\u00fcnen Hof 12 8132 Egg B. Z\u00fcrich. Postfach",
    "sg:city":"Esslingen",
    "sg:orig_category":"Detailhandel mit Metallwaren, Anstrichmitteln, Glaswaren, Bau U Heimwerkerbedarf",
    "sg:postcode":"8133",
    "sg:province":"Z\u00fcrich",
    "wof:name":"Baum R., Techn. Ersatzteile",
    "wof:placetype":"venue"
},
  "geometry": {"coordinates":[8.6900548935,47.3005561829],"type":"Point"}
}