{
  "type": "Feature",
  "properties": {
    "iso:country":"CH",
    "sg:address":"Seestrasse 11",
    "sg:city":"Richterswil",
    "sg:classifiers":[
        {
            "category":"Education",
            "subcategory":"Vocational School",
            "type":"Public Place"
        }
    ],
    "sg:phone":"+41 17861122",
    "sg:postcode":"8805",
    "sg:province":"Z\u00fcrich",
    "sg:tags":[
        "koch-",
        "haushaltschulen"
    ],
    "wof:name":"Institut F\u00fcr Ern\u00e4hrung & Gesundheit Pfyl & Schuhmacher",
    "wof:placetype":"venue"
},
  "geometry": {"coordinates":[8.7094993591,47.2061882019],"type":"Point"}
}