{
  "type": "Feature",
  "properties": {
    "iso:country":"CH",
    "sg:address":"Landstrasse 46",
    "sg:city":"Adelboden",
    "sg:orig_category":"Bauschreinerei",
    "sg:phone":"+41 33 673 14 39",
    "sg:postcode":"3715",
    "sg:province":"Bern",
    "wof:name":"Albert Allenbach Schreinerei",
    "wof:placetype":"venue"
},
  "geometry": {"coordinates":[7.561205,46.490108],"type":"Point"}
}