{
  "type": "Feature",
  "properties": {
    "iso:country":"CH",
    "sg:address":"Wilerstrasse 18",
    "sg:city":"Flawil",
    "sg:orig_category":"Softwareentwicklung U beratung",
    "sg:postcode":"9230",
    "sg:province":"St. Gallen",
    "wof:name":"Stransky-heilkron Philippe",
    "wof:placetype":"venue"
},
  "geometry": {"coordinates":[6.2354798317,46.4775047302],"type":"Point"}
}