{
  "type": "Feature",
  "properties": {
    "iso:country":"CH",
    "sg:address":"Via Bellinzona 37",
    "sg:city":"Giubiasco",
    "sg:orig_category":"Handel mit Automobilen Vermietung von Luftfahrzeugen",
    "sg:phone":"+41 12122520",
    "sg:postcode":"6512",
    "sg:province":"Ticino",
    "wof:name":"Antiqua Trading Ag",
    "wof:placetype":"venue"
},
  "geometry": {"coordinates":[7.7069501877,46.6308898926],"type":"Point"}
}