{
  "type": "Feature",
  "properties": {
    "iso:country":"CH",
    "sg:address":"La Rotta",
    "sg:city":"Rennaz",
    "sg:orig_category":"Instandhaltung U Reparatur von Automobilen",
    "sg:phone":"+41 21 968 24 34",
    "sg:postcode":"1847",
    "sg:province":"Vaud",
    "wof:name":"Garage 5 Etoiles S.a.",
    "wof:placetype":"venue"
},
  "geometry": {"coordinates":[6.923350811,46.3712234497],"type":"Point"}
}