{
  "type": "Feature",
  "properties": {
    "iso:country":"CH",
    "sg:address":"Erlenweg 57 6390 Engelberg. Postfach",
    "sg:city":"Engelberg",
    "sg:orig_category":"Non-Classified Establishments",
    "sg:postcode":"6390",
    "sg:province":"Obwalden",
    "wof:name":"Ormitextal Ag",
    "wof:placetype":"venue"
},
  "geometry": {"coordinates":[8.4040079117,46.8190498352],"type":"Point"}
}