{
  "type": "Feature",
  "properties": {
    "iso:country":"CH",
    "sg:address":"Schwandenbadstrasse 12",
    "sg:city":"Steffisburg",
    "sg:orig_category":"Detailhandel mit Waren verschiedener Art, Hauptrichtung Nahrungsmittel",
    "sg:phone":"+41 33 437 79 27",
    "sg:postcode":"3612",
    "sg:province":"Bern",
    "wof:name":"Peter Br\u00fcgger Nahrungsmittelvertrieb Gmbh",
    "wof:placetype":"venue"
},
  "geometry": {"coordinates":[7.6389107704,46.7728843689],"type":"Point"}
}