{
  "type": "Feature",
  "properties": {
    "iso:country":"CH",
    "sg:address":"Industrie",
    "sg:city":"Pfaffnau",
    "sg:orig_category":"Sonstiges Textilgewerbe Textilgewerbe",
    "sg:phone":"+41 62 754 20 40",
    "sg:postcode":"6264",
    "sg:province":"Luzern",
    "wof:name":"Geralux Gmbh Technische Textilien; Produkteentwicklung, -herstellung, -verkauf Usw",
    "wof:placetype":"venue"
},
  "geometry": {"coordinates":[7.9100341797,47.2336959839],"type":"Point"}
}