{
  "type": "Feature",
  "properties": {
    "iso:country":"CH",
    "sg:address":"Spielmatte 5",
    "sg:city":"Unterseen",
    "sg:orig_category":"Detailhandel mit Bekleidung Sonstiger Grosshandel",
    "sg:phone":"+41 33 823 02 20",
    "sg:postcode":"3800",
    "sg:province":"Bern",
    "wof:name":"Sportb\u00f6rse Zur Alten M\u00fchle Gmbh",
    "wof:placetype":"venue"
},
  "geometry": {"coordinates":[7.851393,46.687138],"type":"Point"}
}