{
  "type": "Feature",
  "properties": {
    "iso:country":"CH",
    "sg:address":"Strada Cantonale",
    "sg:city":"Claro",
    "sg:orig_category":"Autogaragen Autospenglereien",
    "sg:phone":"+41 91 863 14 83",
    "sg:postcode":"6702",
    "sg:province":"Ticino",
    "wof:name":"Alcenso-cars Sa Garage & Carrozzeria",
    "wof:placetype":"venue"
},
  "geometry": {"coordinates":[9.016418,46.265312],"type":"Point"}
}