{
  "type": "Feature",
  "properties": {
    "iso:country":"CH",
    "sg:address":"Wehntalerstrasse 399",
    "sg:city":"Z\u00fcrich",
    "sg:orig_category":"Geb\u00e4ude, Wohnungsreinigung Reinigungsgewerbe",
    "sg:phone":"+41 13710094",
    "sg:postcode":"8046",
    "sg:province":"Z\u00fcrich",
    "wof:name":"Urs Kopp Geb\u00e4udereinigung",
    "wof:placetype":"venue"
},
  "geometry": {"coordinates":[8.5169391632,47.4145011902],"type":"Point"}
}