{
  "type": "Feature",
  "properties": {
    "iso:country":"CH",
    "sg:address":"Grand-rue 2",
    "sg:city":"Morges",
    "sg:orig_category":"Detailhandel mit Brot, Back U S\u00fcsswaren",
    "sg:phone":"+41 17881148",
    "sg:postcode":"1110",
    "sg:province":"Vaud",
    "wof:name":"Alfred St\u00e4ubli B\u00e4ckerei-konditorei",
    "wof:placetype":"venue"
},
  "geometry": {"coordinates":[8.643541,47.193417],"type":"Point"}
}