{
  "type": "Feature",
  "properties": {
    "iso:country":"CH",
    "sg:address":"Oberwilerstrasse 16",
    "sg:city":"Therwil",
    "sg:orig_category":"Detailhandel mit B\u00fcromaschinen U einrichtungen",
    "sg:phone":"+41 79 207 98 40",
    "sg:postcode":"4106",
    "sg:province":"Basel-Landschaft",
    "wof:name":"Fritz Steiger B\u00fcromaschinen",
    "wof:placetype":"venue"
},
  "geometry": {"coordinates":[9.370405,47.420624],"type":"Point"}
}