{
  "type": "Feature",
  "properties": {
    "iso:country":"CH",
    "sg:address":"Poststrasse 2",
    "sg:city":"Niederurnen",
    "sg:orig_category":"Detailhandel mit Schreib U Papeteriewaren Druckweiterverarbeitung",
    "sg:phone":"+41 55 610 26 76",
    "sg:postcode":"8867",
    "sg:province":"Glarus",
    "wof:name":"Fridolin Freuler",
    "wof:placetype":"venue"
},
  "geometry": {"coordinates":[9.0533571243,47.125289917],"type":"Point"}
}