{
  "type": "Feature",
  "properties": {
    "iso:country":"CH",
    "sg:address":"Aarbergstrasse 11",
    "sg:city":"Radelfingen",
    "sg:orig_category":"Grosshandel mit Nahrungsmitteln, Getr\u00e4nken U Tabakwaren ohne ausgepr\u00e4gten Schwerpunkt",
    "sg:postcode":"3271",
    "sg:province":"Bern",
    "wof:name":"Steiner's Ch\u00e4si-l\u00e4deli",
    "wof:placetype":"venue"
},
  "geometry": {"coordinates":[7.2724342346,47.0234489441],"type":"Point"}
}