{
  "type": "Feature",
  "properties": {
    "iso:country":"CH",
    "sg:address":"Dorfstrasse 16",
    "sg:city":"Oberehrendingen",
    "sg:orig_category":"Gemeindeverwaltungen",
    "sg:phone":"+41 56 222 71 31",
    "sg:postcode":"5422",
    "wof:name":"Gemeindeverwaltung Oberehrendingen",
    "wof:placetype":"venue"
},
  "geometry": {"coordinates":[8.3411436081,47.4936332703],"type":"Point"}
}