{
  "type": "Feature",
  "properties": {
    "iso:country":"CH",
    "sg:address":"Alte Landstrasse 17",
    "sg:city":"Unter\u00e4geri",
    "sg:orig_category":"Datenverarbeitungsdienste Wirtschaftspr\u00fcfung, Steuerberatung U Treuhand",
    "sg:phone":"+41 19383050",
    "sg:postcode":"6314",
    "sg:province":"Zug",
    "wof:name":"Schmidt Treuhand Ag",
    "wof:placetype":"venue"
},
  "geometry": {"coordinates":[8.842886,47.300774],"type":"Point"}
}