{
  "type": "Feature",
  "properties": {
    "iso:country":"CH",
    "sg:address":"B\u00fcelhofstrasse 8 8400 Winterthur. Postfach",
    "sg:city":"Winterthur",
    "sg:orig_category":"Finanzierungsinstitutionen",
    "sg:postcode":"8405",
    "sg:province":"Z\u00fcrich",
    "wof:name":"Finanz-gregor",
    "wof:placetype":"venue"
},
  "geometry": {"coordinates":[8.7615394592,47.4846076965],"type":"Point"}
}