{
  "type": "Feature",
  "properties": {
    "iso:country":"CH",
    "sg:address":"Lacuna 7000 Chur. Postfach",
    "sg:city":"Chur",
    "sg:orig_category":"Kantonalbanken",
    "sg:phone":"+41 81 284 56 22",
    "sg:postcode":"7006",
    "sg:province":"Graubunden",
    "wof:name":"Graub\u00fcndner Kantonalbank",
    "wof:placetype":"venue"
},
  "geometry": {"coordinates":[9.5341300964,46.8587760925],"type":"Point"}
}