{
  "type": "Feature",
  "properties": {
    "iso:country":"CH",
    "sg:address":"G\u00fcnzenenstrasse 3a",
    "sg:city":"Steffisburg",
    "sg:orig_category":"Medizinische Artikel Grosshandel Zahnmedizinische Artikel Grosshandel",
    "sg:phone":"+41 33 438 33 63",
    "sg:postcode":"3612",
    "sg:province":"Bern",
    "wof:name":"Harema Samuel Mani, Handelsreisender",
    "wof:placetype":"venue"
},
  "geometry": {"coordinates":[7.6266088486,46.7657737732],"type":"Point"}
}