{
  "type": "Feature",
  "properties": {
    "iso:country":"CH",
    "sg:address":"Arolla 1986 Arolla. Postfach",
    "sg:city":"Arolla",
    "sg:orig_category":"Architektur U Ingenieurb\u00fcros",
    "sg:postcode":"1986",
    "sg:province":"Valais",
    "wof:name":"Atmi, Wanner Jens",
    "wof:placetype":"venue"
},
  "geometry": {"coordinates":[7.48768,46.038712],"type":"Point"}
}