{
  "type": "Feature",
  "properties": {
    "iso:country":"CH",
    "sg:address":"Promenade Du Pin 5",
    "sg:city":"Gen\u00e8ve",
    "sg:orig_category":"Museen",
    "sg:phone":"+41 22 320 78 78",
    "sg:postcode":"1204",
    "sg:province":"Gen\u00e8ve",
    "wof:name":"Cac-voltaire Centre D' Animation Cin\u00e9matographique",
    "wof:placetype":"venue"
},
  "geometry": {"coordinates":[6.1416249275,46.2011299133],"type":"Point"}
}