{
  "type": "Feature",
  "properties": {
    "iso:country":"CH",
    "sg:address":"Vicolo Nassetta 2",
    "sg:city":"Lugano",
    "sg:orig_category":"Wirtschaftspr\u00fcfung, Steuerberatung U Treuhand",
    "sg:phone":"+41 26 413 36 87",
    "sg:postcode":"6900",
    "sg:province":"Ticino",
    "wof:name":"Scd Service Flury Yolande",
    "wof:placetype":"venue"
},
  "geometry": {"coordinates":[7.1524581909,46.757686615],"type":"Point"}
}