{
  "type": "Feature",
  "properties": {
    "iso:country":"CH",
    "sg:address":"1721",
    "sg:city":"Misery",
    "sg:orig_category":"RESTAURANTS: TEA-ROOMS",
    "sg:postcode":"1721",
    "sg:province":"Fribourg",
    "wof:name":"Sr Restaurant De Misery Sa",
    "wof:placetype":"venue"
},
  "geometry": {"coordinates":[7.066619873,46.8517684937],"type":"Point"}
}