{
  "type": "Feature",
  "properties": {
    "iso:country":"CH",
    "sg:address":"Friedhofstrasse 31 4912 Aarwangen. Postfach",
    "sg:city":"Aarwangen",
    "sg:orig_category":"Grosshandel mit Blumen U Pflanzen",
    "sg:phone":"+41 79 213 25 82",
    "sg:postcode":"4912",
    "sg:province":"Bern",
    "wof:name":"Huboma Gmbh G\u00e4rtnereibedarf",
    "wof:placetype":"venue"
},
  "geometry": {"coordinates":[7.2412872314,47.1285018921],"type":"Point"}
}