{
  "type": "Feature",
  "properties": {
    "iso:country":"CH",
    "sg:address":"6822",
    "sg:city":"Arogno",
    "sg:orig_category":"Reiseb\u00fcros U Reiseveranstalter",
    "sg:postcode":"6822",
    "sg:province":"Ticino",
    "wof:name":"Mantegazzi Ariane",
    "wof:placetype":"venue"
},
  "geometry": {"coordinates":[8.9867334366,45.958896637],"type":"Point"}
}