{
  "type": "Feature",
  "properties": {
    "iso:country":"CH",
    "sg:address":"Hauptstrasse 41",
    "sg:city":"Dornach",
    "sg:orig_category":"Detailhandel mit Fleisch U Fleischwaren",
    "sg:phone":"+41 71 966 22 32",
    "sg:postcode":"4143",
    "sg:province":"Solothurn",
    "wof:name":"Meiler Roman.",
    "wof:placetype":"venue"
},
  "geometry": {"coordinates":[8.9954576492,47.4781608582],"type":"Point"}
}