{
  "type": "Feature",
  "properties": {
    "iso:country":"CH",
    "sg:address":"D\u00e4ndlikerweg 48",
    "sg:city":"Bern",
    "sg:orig_category":"Vorschulen, Kinderg\u00e4rten",
    "sg:phone":"+41 31 332 01 43",
    "sg:postcode":"3014",
    "sg:province":"Bern",
    "wof:name":"Kindergarten Wylergut Ii",
    "wof:placetype":"venue"
},
  "geometry": {"coordinates":[7.4484429359,46.9646186829],"type":"Point"}
}