{
  "type": "Feature",
  "properties": {
    "iso:country":"CH",
    "sg:address":"Neubruggweg 2",
    "sg:city":"W\u00e4ngi",
    "sg:orig_category":"Unternehmensberatung",
    "sg:phone":"+41 41 760 22 75",
    "sg:postcode":"9545",
    "sg:province":"Thurgau",
    "wof:name":"Kummrow Consult",
    "wof:placetype":"venue"
},
  "geometry": {"coordinates":[8.9640960693,47.4927825928],"type":"Point"}
}