{
  "type": "Feature",
  "properties": {
    "iso:country":"CH",
    "sg:address":"Schattengasse 43",
    "sg:city":"Klingnau",
    "sg:orig_category":"Non-Classified Establishments",
    "sg:phone":"+41 32536469",
    "sg:postcode":"5313",
    "sg:province":"Aargau",
    "wof:name":"Nail-studio-philadelphia, Nydegger Ruth",
    "wof:placetype":"venue"
},
  "geometry": {"coordinates":[7.2936520576,47.1180267334],"type":"Point"}
}