{
  "type": "Feature",
  "properties": {
    "iso:country":"CH",
    "sg:address":"Impasse De La For\u00eat 22",
    "sg:city":"Fribourg",
    "sg:orig_category":"Sonstige pers\u00f6nliche Dienstleistungen",
    "sg:phone":"+41 26 481 12 53",
    "sg:postcode":"1700",
    "sg:province":"Fribourg",
    "wof:name":"Dom Agence Matrimoniale",
    "wof:placetype":"venue"
},
  "geometry": {"coordinates":[7.1700320244,46.8134727478],"type":"Point"}
}