{
  "type": "Feature",
  "properties": {
    "iso:country":"CH",
    "sg:address":"Rue Centrale 15 1003 Lausanne. Postfach",
    "sg:city":"Lausanne",
    "sg:orig_category":"Werbevermittlung",
    "sg:phone":"+41 71 385 33 23",
    "sg:postcode":"1002",
    "sg:province":"Vaud",
    "wof:name":"Publicitas Ag",
    "wof:placetype":"venue"
},
  "geometry": {"coordinates":[9.2509994507,47.4160690308],"type":"Point"}
}