{
  "type": "Feature",
  "properties": {
    "iso:country":"CH",
    "sg:address":"Hofackerstrasse 42 8032 Z\u00fcrich",
    "sg:city":"Zust",
    "sg:orig_category":"Herstellung von Landwirtschaftstraktoren Herstellung von Metallerzeugnissen ohne Maschinenbau",
    "sg:phone":"+41 22 306 22 11",
    "sg:postcode":"32",
    "wof:name":"Abb S\u00e9cheron Sa",
    "wof:placetype":"venue"
},
  "geometry": {"coordinates":[6.0722160339,46.2284431458],"type":"Point"}
}