{
  "type": "Feature",
  "properties": {
    "iso:country":"CH",
    "sg:address":"Seestrasse 59",
    "sg:city":"Berlingen",
    "sg:orig_category":"Kantonalbanken",
    "sg:phone":"+41 52 745 22 12",
    "sg:postcode":"8267",
    "sg:province":"Thurgau",
    "wof:name":"Thurgauer Kantonalbank",
    "wof:placetype":"venue"
},
  "geometry": {"coordinates":[8.8312902451,47.6252708435],"type":"Point"}
}