{
  "type": "Feature",
  "properties": {
    "addr:full":"Chemin Du Bosquet 1 1030 Bussigny-lausanne. Postfach Bussigny-lausanne Vaud 1030",
    "addr:housenumber":"1",
    "addr:postcode":"1030;1030",
    "addr:street":"Chemin Du Bosquet;Postfach",
    "iso:country":"CH",
    "sg:address":"Chemin Du Bosquet 1 1030 Bussigny-lausanne. Postfach",
    "sg:city":"Bussigny-lausanne",
    "sg:orig_category":"Dachdeckerei Zimmerei, Dachdeckerei, Bauspenglerei U Abdichtung",
    "sg:phone":"+41 71 999 27 17",
    "sg:postcode":"1030",
    "sg:province":"Vaud",
    "wof:name":"Egle Bedachungen Ag",
    "wof:placetype":"venue"
},
  "geometry": {"coordinates":[9.28492,47.193584],"type":"Point"}
}