{
  "type": "Feature",
  "properties": {
    "iso:country":"CH",
    "sg:address":"B\u00fcrgerheim 93",
    "sg:city":"D\u00fcrren\u00e4sch",
    "sg:orig_category":"Verwertung von Milch",
    "sg:postcode":"5724",
    "sg:province":"Aargau",
    "wof:name":"K\u00e4sereigenossenschaft D\u00fcrren\u00e4sch",
    "wof:placetype":"venue"
},
  "geometry": {"coordinates":[8.1578493118,47.3212203979],"type":"Point"}
}