{
  "type": "Feature",
  "properties": {
    "iso:country":"CH",
    "sg:address":"Fellenbergstrasse 5",
    "sg:city":"M\u00fcnchenbuchsee",
    "sg:orig_category":"Notariate",
    "sg:phone":"+41 31 869 00 55",
    "sg:postcode":"3053",
    "sg:province":"Bern",
    "wof:name":"Peter Brand Notariat",
    "wof:placetype":"venue"
},
  "geometry": {"coordinates":[7.4503102303,47.0205307007],"type":"Point"}
}