{
  "type": "Feature",
  "properties": {
    "iso:country":"CH",
    "sg:address":"Weststrasse 119 8003 Z\u00fcrich. Postfach",
    "sg:city":"Z\u00fcrich",
    "sg:classifiers":[
        {
            "category":"Professional",
            "subcategory":"Employment Agencies",
            "type":"Services"
        }
    ],
    "sg:postcode":"8001",
    "sg:province":"Z\u00fcrich",
    "sg:tags":[
        "personal",
        "u",
        "stellenvermittlung"
    ],
    "wof:name":"Rs Promotion, Schoch Ralph Statisten, Fotomodelle In Der Werbebranche; Vermittlung",
    "wof:placetype":"venue"
},
  "geometry": {"coordinates":[8.5196695328,47.3724632263],"type":"Point"}
}