{
  "type": "Feature",
  "properties": {
    "iso:country":"CH",
    "sg:address":"Dorfstrasse",
    "sg:city":"Pfaffnau",
    "sg:classifiers":[
        {
            "category":"Restaurant",
            "type":"Food & Drink"
        }
    ],
    "sg:phone":"+41 62 754 00 61",
    "sg:postcode":"6264",
    "sg:province":"Luzern",
    "wof:name":"Holzofen-pizzeria Kreuz",
    "wof:placetype":"venue"
},
  "geometry": {"coordinates":[7.8969697952,47.2272262573],"type":"Point"}
}