{
  "type": "Feature",
  "properties": {
    "iso:country":"CH",
    "sg:address":"1793",
    "sg:city":"Jeuss",
    "sg:orig_category":"Landesverteidigung, Sozialversicherung \u00d6ffentliche Verwaltung",
    "sg:phone":"+41 26 674 15 54",
    "sg:postcode":"1793",
    "sg:province":"Fribourg",
    "wof:name":"Zivilschutzstelle Jeuss",
    "wof:placetype":"venue"
},
  "geometry": {"coordinates":[7.1673197746,46.9048881531],"type":"Point"}
}