{
  "type": "Feature",
  "properties": {
    "iso:country":"CH",
    "sg:address":"Zwinglistrasse 6",
    "sg:city":"Z\u00fcrich",
    "sg:orig_category":"Detailhandel mit Waren verschiedener Art, Hauptrichtung Nahrungsmittel Grosshandel mit Nahrungsmitte",
    "sg:phone":"+41 12419145",
    "sg:postcode":"8004",
    "sg:province":"Z\u00fcrich",
    "wof:name":"Comestibles Shajirat Karim",
    "wof:placetype":"venue"
},
  "geometry": {"coordinates":[8.5297813416,47.3779411316],"type":"Point"}
}