{
  "type": "Feature",
  "properties": {
    "iso:country":"CH",
    "sg:address":"Spalenberg 14",
    "sg:city":"Basel",
    "sg:orig_category":"Detailhandel mit Beleuchtungs U Haushaltsgegenst\u00e4nden",
    "sg:phone":"+41 61 261 48 26",
    "sg:postcode":"4051",
    "sg:province":"Basel-Stadt",
    "wof:name":"Johann Wanner Weihnachtshaus Warenhandel, Bes. Weihnachtsartikel",
    "wof:placetype":"venue"
},
  "geometry": {"coordinates":[7.58625,47.557301],"type":"Point"}
}