{
  "type": "Feature",
  "properties": {
    "iso:country":"CH",
    "sg:address":"St. Gallerstrasse 17",
    "sg:city":"M\u00f6rschwil",
    "sg:orig_category":"Detailhandel mit Fleisch U Fleischwaren",
    "sg:phone":"+41 71 866 13 31",
    "sg:postcode":"9402",
    "sg:province":"St. Gallen",
    "wof:name":"Metzgerei Ehrbar",
    "wof:placetype":"venue"
},
  "geometry": {"coordinates":[9.4212808609,47.4669303894],"type":"Point"}
}