{
  "type": "Feature",
  "properties": {
    "iso:country":"CH",
    "sg:address":"Muraccio Via 108",
    "sg:city":"Ascona",
    "sg:orig_category":"Fachdetailhandel in Verkaufsr\u00e4umen",
    "sg:postcode":"6612",
    "sg:province":"Ticino",
    "wof:name":"Asconautica Meier",
    "wof:placetype":"venue"
},
  "geometry": {"coordinates":[8.7883062363,46.1533432007],"type":"Point"}
}