{
  "type": "Feature",
  "properties": {
    "iso:country":"CH",
    "sg:address":"Bergstrasse 23 8953 Dietikon. Postfach",
    "sg:city":"Dietikon",
    "sg:orig_category":"Erzeugung U Erstbearbeitung von Aluminium",
    "sg:phone":"+41 31 981 29 39",
    "sg:postcode":"8953",
    "sg:province":"Z\u00fcrich",
    "wof:name":"Schlierholz Eloxal Ag",
    "wof:placetype":"venue"
},
  "geometry": {"coordinates":[7.3755722046,46.9239044189],"type":"Point"}
}