{
  "type": "Feature",
  "properties": {
    "iso:country":"CH",
    "sg:address":"Zeughausgasse 15",
    "sg:city":"Zug",
    "sg:orig_category":"Non-Classified Establishments",
    "sg:postcode":"6300",
    "sg:province":"Zug",
    "wof:name":"Skalina Gmbh Natur-kunststein-montagen",
    "wof:placetype":"venue"
},
  "geometry": {"coordinates":[8.5159826279,47.1666870117],"type":"Point"}
}