{
  "type": "Feature",
  "properties": {
    "iso:country":"CH",
    "sg:address":"Maillefer Chemin De 35 1018 Lausanne. Postfach",
    "sg:city":"Lausanne",
    "sg:orig_category":"Saunas, Solarien, Fitnesszentren U \u00e4hnliches",
    "sg:postcode":"1018",
    "sg:province":"Vaud",
    "wof:name":"Pro-gym Promouvoir La Gymnastique Etc",
    "wof:placetype":"venue"
},
  "geometry": {"coordinates":[6.6313099861,46.54114151],"type":"Point"}
}