{
  "type": "Feature",
  "properties": {
    "iso:country":"CH",
    "sg:address":"Avenue Nestl\u00e9 14",
    "sg:city":"Montreux",
    "sg:classifiers":[
        {
            "category":"Manufacturing",
            "subcategory":"Electronics",
            "type":"Manufacturing & Wholesale Goods"
        }
    ],
    "sg:phone":"+41 21 965 35 00",
    "sg:postcode":"1820",
    "sg:province":"Vaud",
    "sg:tags":[
        "semiconductor",
        "power"
    ],
    "wof:name":"Msc Suisse Sa",
    "wof:placetype":"venue"
},
  "geometry": {"coordinates":[6.912921,46.429432],"type":"Point"}
}