{
  "type": "Feature",
  "properties": {
    "addr:full":"Oberer Haselweg 16 Oberkulm Aargau 5727",
    "addr:housenumber":"16",
    "addr:postcode":"5727",
    "addr:street":"Oberer Haselweg",
    "iso:country":"CH",
    "sg:address":"Oberer Haselweg 16",
    "sg:city":"Oberkulm",
    "sg:orig_category":"Detailhandel mit Beleuchtungs U Haushaltsgegenst\u00e4nden Detailhandel mit Geschenkartikeln U Souvenirs",
    "sg:phone":"+41 62 776 25 21",
    "sg:postcode":"5727",
    "sg:province":"Aargau",
    "wof:name":"Myrtha Steiner Glas & Keramik",
    "wof:placetype":"venue"
},
  "geometry": {"coordinates":[8.122873,47.303669],"type":"Point"}
}