{
  "type": "Feature",
  "properties": {
    "iso:country":"CH",
    "sg:address":"Flormattweg 15",
    "sg:city":"Meggen",
    "sg:orig_category":"Herstellung von sonstigen chemischen Erzeugnissen",
    "sg:phone":"+41 41 377 49 69",
    "sg:postcode":"6045",
    "sg:province":"Luzern",
    "wof:name":"Casanova Biotech",
    "wof:placetype":"venue"
},
  "geometry": {"coordinates":[8.3857860565,47.0596199036],"type":"Point"}
}