{
  "type": "Feature",
  "properties": {
    "iso:country":"CH",
    "sg:address":"Rathausgasse 25",
    "sg:city":"Lenzburg",
    "sg:orig_category":"Eisenwaren Detailhandel",
    "sg:phone":"+41 62 891 66 66",
    "sg:postcode":"5600",
    "sg:province":"Aargau",
    "wof:name":"Schwarz Stahl Ag Eisenwaren",
    "wof:placetype":"venue"
},
  "geometry": {"coordinates":[8.1805801392,47.3874473572],"type":"Point"}
}