{
  "type": "Feature",
  "properties": {
    "iso:country":"CH",
    "sg:address":"Muntersweg 47",
    "sg:city":"Grenchen",
    "sg:orig_category":"P\u00e9dicure",
    "sg:phone":"+41 32 652 07 52",
    "sg:postcode":"2540",
    "sg:province":"Solothurn",
    "wof:name":"Rita Heer Kosmetik & Fusspflege",
    "wof:placetype":"venue"
},
  "geometry": {"coordinates":[7.3921871185,47.1857337952],"type":"Point"}
}