{
  "type": "Feature",
  "properties": {
    "addr:full":"Sattelgasse 2 4051 Basel. Postfach Basel Basel-Stadt 4001",
    "addr:housenumber":"2",
    "addr:postcode":"4051;4001",
    "addr:street":"Sattelgasse;Postfach",
    "iso:country":"CH",
    "sg:address":"Sattelgasse 2 4051 Basel. Postfach",
    "sg:city":"Basel",
    "sg:orig_category":"Architektur U Ingenieurb\u00fcros",
    "sg:phone":"+41 61 261 46 22",
    "sg:postcode":"4001",
    "sg:province":"Basel-Stadt",
    "wof:name":"Eroba Ag Ingenieurb\u00fcro F\u00fcr Kran, Greifer- U. F\u00f6rdertechnik Usw",
    "wof:placetype":"venue"
},
  "geometry": {"coordinates":[7.587417,47.558235],"type":"Point"}
}