{
  "type": "Feature",
  "properties": {
    "iso:country":"CH",
    "sg:address":"Chemin Des Grands-pr\u00e9s 7",
    "sg:city":"Mies-tannay",
    "sg:orig_category":"Grosshandel mit elektrischen Haushaltsger\u00e4ten, Radio U Fernsehger\u00e4ten Herstellung von sonstigen elek",
    "sg:phone":"+41 19343536",
    "sg:postcode":"1295",
    "sg:province":"Vaud",
    "wof:name":"Mdm Elektrosystem Ag",
    "wof:placetype":"venue"
},
  "geometry": {"coordinates":[8.797958374,47.3338279724],"type":"Point"}
}