{
  "type": "Feature",
  "properties": {
    "iso:country":"CH",
    "sg:address":"Sennereigasse 8",
    "sg:city":"Brig",
    "sg:orig_category":"Gartenbau Gartencenter",
    "sg:phone":"+41 21 791 58 75",
    "sg:postcode":"3900",
    "sg:province":"Valais",
    "wof:name":"J.-f. Charmoy Sa Entreprise Paysagiste",
    "wof:placetype":"venue"
},
  "geometry": {"coordinates":[6.7033138275,46.5169525146],"type":"Point"}
}