{
  "type": "Feature",
  "properties": {
    "iso:country":"CH",
    "sg:address":"Bauernhalde 5",
    "sg:city":"M\u00e4nnedorf",
    "sg:orig_category":"Werbeagenturen",
    "sg:phone":"+41 21 635 22 66",
    "sg:postcode":"8708",
    "sg:province":"Z\u00fcrich",
    "wof:name":"Werner Rudin Conseil En Publicit\u00e9",
    "wof:placetype":"venue"
},
  "geometry": {"coordinates":[6.592525959,46.5394897461],"type":"Point"}
}