{
  "type": "Feature",
  "properties": {
    "iso:country":"CH",
    "sg:address":"Rue Liotard 10",
    "sg:city":"Gen\u00e8ve",
    "sg:orig_category":"Architekturb\u00fcros",
    "sg:phone":"+41 22 344 04 16",
    "sg:postcode":"1202",
    "sg:province":"Gen\u00e8ve",
    "wof:name":"Gilbert Croci-torti Bureau D'architecture",
    "wof:placetype":"venue"
},
  "geometry": {"coordinates":[6.133558,46.209812],"type":"Point"}
}