{
  "type": "Feature",
  "properties": {
    "iso:country":"CH",
    "sg:address":"Nieder\u00e4mterstrasse 74",
    "sg:city":"Dulliken",
    "sg:orig_category":"Detailhandel mit Beleuchtungs U Haushaltsgegenst\u00e4nden Detailhandel mit Radio U Fernsehger\u00e4ten",
    "sg:phone":"+41 62 295 04 66",
    "sg:postcode":"4657",
    "sg:province":"Solothurn",
    "wof:name":"New Light Gmbh Radio-tv-natel",
    "wof:placetype":"venue"
},
  "geometry": {"coordinates":[7.946895,47.353397],"type":"Point"}
}