{
  "type": "Feature",
  "properties": {
    "iso:country":"CH",
    "sg:address":"Bahnhofstrasse 4",
    "sg:city":"Hunzenschwil",
    "sg:classifiers":[
        {
            "category":"Manufacturing",
            "subcategory":"Paper Products",
            "type":"Manufacturing & Wholesale Goods"
        }
    ],
    "sg:phone":"+41 62 897 10 42",
    "sg:postcode":"5502",
    "sg:province":"Aargau",
    "sg:tags":[
        "felt",
        "industry",
        "cellulose",
        "woodpulp",
        "cloth",
        "cardboard"
    ],
    "wof:name":"Swifit-textil Ag",
    "wof:placetype":"venue"
},
  "geometry": {"coordinates":[8.1256790161,47.3871574402],"type":"Point"}
}