{
  "type": "Feature",
  "properties": {
    "iso:country":"CH",
    "sg:address":"Sonnenberg 5 Adlikon B. Andelfingen 8106 Adlikon B.regensdf. Postfach",
    "sg:city":"Adlikon",
    "sg:orig_category":"Grosshandel mit sonstigen Gebrauchs U Verbrauchsg\u00fctern",
    "sg:postcode":"8452",
    "sg:province":"Z\u00fcrich",
    "wof:name":"Fashion & Show Events Helg Coreen",
    "wof:placetype":"venue"
},
  "geometry": {"coordinates":[8.4660482407,47.4512748718],"type":"Point"}
}