{
  "type": "Feature",
  "properties": {
    "addr:full":"Bernstrasse 41 Flamatt Fribourg 3175",
    "addr:housenumber":"41",
    "addr:postcode":"3175",
    "addr:street":"Bernstrasse",
    "iso:country":"CH",
    "sg:address":"Bernstrasse 41",
    "sg:city":"Flamatt",
    "sg:orig_category":"Datenbanken",
    "sg:phone":"+41 31 744 21 21",
    "sg:postcode":"3175",
    "sg:province":"Fribourg",
    "wof:name":"Autoscout24 Ag Fahrzeug-datenbank; Aufbau Und Betrieb",
    "wof:placetype":"venue"
},
  "geometry": {"coordinates":[7.320699,46.890354],"type":"Point"}
}