{
  "type": "Feature",
  "properties": {
    "iso:country":"CH",
    "sg:address":"Rueyre Chemin De La 43",
    "sg:city":"Jouxtens-m\u00e9zery",
    "sg:orig_category":"Grosshandel mit Getr\u00e4nken",
    "sg:phone":"+41 21 635 89 13",
    "sg:postcode":"1008",
    "sg:province":"Vaud",
    "wof:name":"Gr-vins Sa",
    "wof:placetype":"venue"
},
  "geometry": {"coordinates":[6.6061439514,46.5340614319],"type":"Point"}
}