{
  "type": "Feature",
  "properties": {
    "iso:country":"CH",
    "sg:address":"Kreuzkappellenweg 2",
    "sg:city":"Wettingen",
    "sg:orig_category":"Non-Classified Establishments",
    "sg:postcode":"5430",
    "sg:province":"Aargau",
    "wof:name":"Offert-line Ag",
    "wof:placetype":"venue"
},
  "geometry": {"coordinates":[8.3404970169,47.4604187012],"type":"Point"}
}