{
  "type": "Feature",
  "properties": {
    "iso:country":"CH",
    "sg:address":"Impasse Des Ecureuils 2",
    "sg:city":"Granges-paccot",
    "sg:orig_category":"Finanzierungsinstitutionen",
    "sg:phone":"+41 26 466 77 77",
    "sg:postcode":"1763",
    "sg:province":"Fribourg",
    "wof:name":"Bl Vision Sa",
    "wof:placetype":"venue"
},
  "geometry": {"coordinates":[7.1384739876,46.8163642883],"type":"Point"}
}