{
  "type": "Feature",
  "properties": {
    "iso:country":"CH",
    "sg:address":"Zentralstrasse 33",
    "sg:city":"Biel/bienne",
    "sg:orig_category":"Architektur U Ingenieurb\u00fcros",
    "sg:phone":"+41 32 323 23 75",
    "sg:postcode":"2502",
    "sg:province":"Bern",
    "wof:name":"Zingg + Partner Ingenieure + Planer Ag",
    "wof:placetype":"venue"
},
  "geometry": {"coordinates":[7.245835,47.137814],"type":"Point"}
}