{
  "type": "Feature",
  "properties": {
    "iso:country":"CH",
    "sg:address":"Strada Regina",
    "sg:city":"Agno",
    "sg:orig_category":"Grosshandel mit sonstigen Maschinen U Ausr\u00fcstungen f\u00fcr Industrie, Handel U Schiffahrt Mechanische We",
    "sg:phone":"+41 91 605 14 12",
    "sg:postcode":"6982",
    "sg:province":"Ticino",
    "wof:name":"Dns Sagl, Agno Officina Meccanica",
    "wof:placetype":"venue"
},
  "geometry": {"coordinates":[8.8985795975,45.9974098206],"type":"Point"}
}