{
  "type": "Feature",
  "properties": {
    "iso:country":"CH",
    "sg:address":"Mittlere Dorfstrasse 2",
    "sg:city":"Suhr",
    "sg:orig_category":"Herstellung von medizinischen U chirurgischen Ger\u00e4ten sowie orthop\u00e4dischen Vorrichtungen",
    "sg:phone":"+41 62 842 64 00",
    "sg:postcode":"5034",
    "sg:province":"Aargau",
    "wof:name":"Gutzwiller Dental",
    "wof:placetype":"venue"
},
  "geometry": {"coordinates":[8.0778427124,47.3749160767],"type":"Point"}
}