{
  "type": "Feature",
  "properties": {
    "iso:country":"CH",
    "sg:address":"Grenzstrasse 26 3250 Lyss. Postfach 192",
    "sg:city":"Lyss",
    "sg:orig_category":"Giessereiindustrie Herstellung von Armaturen",
    "sg:phone":"+41 32 384 34 64",
    "sg:postcode":"3250",
    "sg:province":"Bern",
    "wof:name":"Similor Sa",
    "wof:placetype":"venue"
},
  "geometry": {"coordinates":[7.2911190987,47.0676383972],"type":"Point"}
}