{
  "type": "Feature",
  "properties": {
    "iso:country":"CH",
    "sg:address":"R\u00fcttenerstrasse 75 4513 Langendorf. Postfach 342",
    "sg:city":"Langendorf",
    "sg:orig_category":"Detailhandel mit Metallwaren, Anstrichmitteln, Glaswaren, Bau U Heimwerkerbedarf Grosshandel mit Spi",
    "sg:phone":"+41 31 981 40 11",
    "sg:postcode":"4513",
    "sg:province":"Solothurn",
    "wof:name":"Bastel M\u00fcller Ag",
    "wof:placetype":"venue"
},
  "geometry": {"coordinates":[7.3735599518,46.9211235046],"type":"Point"}
}