{
  "type": "Feature",
  "properties": {
    "iso:country":"CH",
    "sg:address":"Talstrasse 35",
    "sg:city":"Unterengstringen",
    "sg:orig_category":"Autospenglereien",
    "sg:phone":"+41 19325577",
    "sg:postcode":"8103",
    "sg:province":"Z\u00fcrich",
    "wof:name":"Ren\u00e9 & Xaver Fellmann Carrosserie",
    "wof:placetype":"venue"
},
  "geometry": {"coordinates":[8.796222,47.312359],"type":"Point"}
}