{
  "type": "Feature",
  "properties": {
    "iso:country":"CH",
    "sg:address":"Wengen 3822 Lauterbrunnen. Postfach",
    "sg:city":"Wengen",
    "sg:classifiers":[
        {
            "category":"Travel",
            "subcategory":"Hotels & Motels",
            "type":"Entertainment"
        }
    ],
    "sg:postcode":"3823",
    "sg:province":"Bern",
    "sg:tags":[
        "hotels",
        "mit",
        "restaurant"
    ],
    "wof:name":"Meyer's Classic Bar Ag Hotel, Restaurationsunternehmen. F\u00f6rderungen Von Technischen Entwicklungen Im Bereich Des Gastgewerbes",
    "wof:placetype":"venue"
},
  "geometry": {"coordinates":[8.5001001358,47.4968299866],"type":"Point"}
}