{
  "type": "Feature",
  "properties": {
    "iso:country":"CH",
    "sg:address":"Passaroro Via 74",
    "sg:city":"Gordola",
    "sg:orig_category":"Unternehmensberatung",
    "sg:phone":"+41 91 745 41 27",
    "sg:postcode":"6596",
    "sg:province":"Ticino",
    "wof:name":"Jb Consulting Di J\u00fcrgen Bartsch",
    "wof:placetype":"venue"
},
  "geometry": {"coordinates":[8.8604202271,46.180934906],"type":"Point"}
}