{
  "type": "Feature",
  "properties": {
    "iso:country":"CH",
    "sg:address":"Avenue De Tivoli 22",
    "sg:city":"Lausanne",
    "sg:orig_category":"Detailhandel Reparatur von Gebrauchsg\u00fctern Vermietung von Gebrauchsg\u00fctern",
    "sg:phone":"+41 21 320 69 69",
    "sg:postcode":"1007",
    "sg:province":"Vaud",
    "wof:name":"Sex Shop Pink Vid\u00e9oth\u00e8que Shop",
    "wof:placetype":"venue"
},
  "geometry": {"coordinates":[6.6200799942,46.5211791992],"type":"Point"}
}