{
  "type": "Feature",
  "properties": {
    "iso:country":"CH",
    "sg:address":"Blancherie 2",
    "sg:city":"Del\u00e9mont",
    "sg:orig_category":"Betrieb von Sportanlagen",
    "sg:postcode":"2800",
    "sg:province":"Jura",
    "wof:name":"Soci\u00e9t\u00e9 Coop\u00e9rative Du Dojo H\u00e4nni Eric.",
    "wof:placetype":"venue"
},
  "geometry": {"coordinates":[7.341987,47.361137],"type":"Point"}
}