{
  "type": "Feature",
  "properties": {
    "iso:country":"CH",
    "sg:address":"Rue Schaub 47",
    "sg:city":"Gen\u00e8ve",
    "sg:orig_category":"Sonstige Kultur U Unterhaltungseinrichtungen",
    "sg:phone":"+41 22 736 72 71",
    "sg:postcode":"1202",
    "sg:province":"Gen\u00e8ve",
    "wof:name":"Centre De Loisirs Des Eaux-vives",
    "wof:placetype":"venue"
},
  "geometry": {"coordinates":[6.1631889343,46.2018127441],"type":"Point"}
}