{
  "type": "Feature",
  "properties": {
    "iso:country":"CH",
    "sg:address":"Renggerstrasse 60",
    "sg:city":"Z\u00fcrich",
    "sg:orig_category":"Detailhandel mit Damenbekleidung Detailhandel mit Textilien",
    "sg:postcode":"8038",
    "sg:province":"Z\u00fcrich",
    "wof:name":"Buchhandlung Ruth Chautems",
    "wof:placetype":"venue"
},
  "geometry": {"coordinates":[8.5325479507,47.3445358276],"type":"Point"}
}