{
  "type": "Feature",
  "properties": {
    "iso:country":"CH",
    "sg:address":"Poststrasse 14",
    "sg:city":"Widnau",
    "sg:classifiers":[
        {
            "category":"Bars & Pubs",
            "type":"Food & Drink"
        }
    ],
    "sg:phone":"+41 71 722 21 85",
    "sg:postcode":"9443",
    "sg:province":"St. Gallen",
    "wof:name":"T\u00fcrmli Pub",
    "wof:placetype":"venue"
},
  "geometry": {"coordinates":[9.635727,47.401691],"type":"Point"}
}