{
  "type": "Feature",
  "properties": {
    "iso:country":"CH",
    "sg:address":"9056 Gais. Postfach",
    "sg:city":"Gais",
    "sg:orig_category":"Primarschulen",
    "sg:phone":"+41 71 793 13 11",
    "sg:postcode":"9056",
    "sg:province":"Appenzell Ausserrhoden",
    "wof:name":"Primarschule Dorf",
    "wof:placetype":"venue"
},
  "geometry": {"coordinates":[9.4535903931,47.3623428345],"type":"Point"}
}