{
  "type": "Feature",
  "properties": {
    "iso:country":"CH",
    "sg:address":"Stutzstrasse 15",
    "sg:city":"Niederwichtrach",
    "sg:orig_category":"Sonstiger spezialisierter Hoch U Tiefbau",
    "sg:phone":"+41 31 781 33 43",
    "sg:postcode":"3114",
    "sg:province":"Bern",
    "wof:name":"Ariel Gilgen",
    "wof:placetype":"venue"
},
  "geometry": {"coordinates":[7.580537796,46.8499031067],"type":"Point"}
}