{
  "type": "Feature",
  "properties": {
    "iso:country":"CH",
    "sg:address":"Besenrainweg 10 8038 Z\u00fcrich. Postfach",
    "sg:city":"Z\u00fcrich",
    "sg:orig_category":"Sanit\u00e4r, Heizungs U L\u00fcftungsinstallation",
    "sg:phone":"+41 12029808",
    "sg:postcode":"8001",
    "sg:province":"Z\u00fcrich",
    "wof:name":"Werner Herzog, San. Installationen Sanit\u00e4re Installation; Ausf\u00fchrung U. Planung",
    "wof:placetype":"venue"
},
  "geometry": {"coordinates":[8.527803421,47.346282959],"type":"Point"}
}