{
  "type": "Feature",
  "properties": {
    "iso:country":"CH",
    "sg:address":"Schartenstrasse 95",
    "sg:city":"Wettingen",
    "sg:orig_category":"Fachdetailhandel in Verkaufsr\u00e4umen",
    "sg:postcode":"5430",
    "sg:province":"Aargau",
    "wof:name":"Ernst C. Smania",
    "wof:placetype":"venue"
},
  "geometry": {"coordinates":[8.3062534332,46.993522644],"type":"Point"}
}