{
  "type": "Feature",
  "properties": {
    "iso:country":"CH",
    "sg:address":"Rue Du Vingt-trois Juin 23-juin 30",
    "sg:city":"Pruntrut",
    "sg:orig_category":"Unclassifiable Establishments",
    "sg:phone":"+41 19101670",
    "sg:postcode":"2900",
    "sg:province":"Jura",
    "wof:name":"Brasserie-holding Sa",
    "wof:placetype":"venue"
},
  "geometry": {"coordinates":[8.5805740356,47.3144264221],"type":"Point"}
}