{
  "type": "Feature",
  "properties": {
    "iso:country":"CH",
    "sg:address":"Romont Rue De 2",
    "sg:city":"Fribourg",
    "sg:orig_category":"Mit dem Versicherungsgewerbe verbundene T\u00e4tigkeiten",
    "sg:phone":"+41 26 322 88 19",
    "sg:postcode":"1700",
    "sg:province":"Fribourg",
    "wof:name":"Oliveira Constantino",
    "wof:placetype":"venue"
},
  "geometry": {"coordinates":[7.1554617882,46.8049125671],"type":"Point"}
}