{
  "type": "Feature",
  "properties": {
    "iso:country":"CH",
    "sg:address":"Austrasse 10 4437 Waldenburg. Postfach 212",
    "sg:city":"Waldenburg",
    "sg:orig_category":"Verkehrs- and Tourismusb\u00fcros",
    "sg:phone":"+41 61 921 58 07",
    "sg:postcode":"4437",
    "sg:province":"Basel-Landschaft",
    "wof:name":"Verkehrsverein Waldenburg",
    "wof:placetype":"venue"
},
  "geometry": {"coordinates":[7.745912075,47.3782691956],"type":"Point"}
}