{
  "type": "Feature",
  "properties": {
    "iso:country":"CH",
    "sg:address":"Weinbergstrasse 75",
    "sg:city":"Z\u00fcrich",
    "sg:classifiers":[
        {
            "category":"Restaurant",
            "type":"Food & Drink"
        }
    ],
    "sg:phone":"+41 13623900",
    "sg:postcode":"8006",
    "sg:province":"Z\u00fcrich",
    "wof:name":"Restaurant Z\u00fcrihegel",
    "wof:placetype":"venue"
},
  "geometry": {"coordinates":[8.5433158875,47.383354187],"type":"Point"}
}