{
  "type": "Feature",
  "properties": {
    "iso:country":"CH",
    "sg:address":"Via S. Carlo",
    "sg:city":"Figino",
    "sg:orig_category":"Architekturb\u00fcros",
    "sg:phone":"+41 91 980 10 11",
    "sg:postcode":"6918",
    "sg:province":"Ticino",
    "wof:name":"Geba Partner Ag Studio D'architettura",
    "wof:placetype":"venue"
},
  "geometry": {"coordinates":[8.906969,45.952858],"type":"Point"}
}