{
  "type": "Feature",
  "properties": {
    "iso:country":"CH",
    "sg:address":"Winterhaldenstrasse 20",
    "sg:city":"Heimberg",
    "sg:orig_category":"Instandhaltung U Reparatur von Automobilen",
    "sg:phone":"+41 33 437 07 87",
    "sg:postcode":"3627",
    "sg:province":"Bern",
    "wof:name":"Auto-lackiererei J\u00fcrg Ramseier",
    "wof:placetype":"venue"
},
  "geometry": {"coordinates":[7.6022810936,46.7990875244],"type":"Point"}
}