{
  "type": "Feature",
  "properties": {
    "iso:country":"CH",
    "sg:address":"Via Pioda 12",
    "sg:city":"Lugano",
    "sg:orig_category":"Handels-H\u00e4user U Gesellschaften",
    "sg:postcode":"6900",
    "sg:province":"Ticino",
    "wof:name":"Pro Sales Worldwide, Perret, Savoyat Et Walder",
    "wof:placetype":"venue"
},
  "geometry": {"coordinates":[6.1434750557,46.1856079102],"type":"Point"}
}