{
  "type": "Feature",
  "properties": {
    "iso:country":"CH",
    "sg:address":"Wabernstrasse 38 3007 Bern. Postfach",
    "sg:city":"Bern",
    "sg:orig_category":"Architektur U Ingenieurb\u00fcros Architekturb\u00fcros",
    "sg:phone":"+41 31 372 15 25",
    "sg:postcode":"3007",
    "sg:province":"Bern",
    "wof:name":"Technoplan Bern Ag Ingenieur- U. Architekturdienstleistungen. Bauprojekte; Entwicklung",
    "wof:placetype":"venue"
},
  "geometry": {"coordinates":[7.437649,46.938648],"type":"Point"}
}