{
  "type": "Feature",
  "properties": {
    "iso:country":"CH",
    "sg:address":"Via Marcacci 7/9",
    "sg:city":"Locarno",
    "sg:orig_category":"Detailhandel mit Geschenkartikeln U Souvenirs",
    "sg:phone":"+41 71 223 13 55",
    "sg:postcode":"6600",
    "sg:province":"Ticino",
    "wof:name":"Sandra Galvani Exclusive Boutique",
    "wof:placetype":"venue"
},
  "geometry": {"coordinates":[9.3753480911,47.4266891479],"type":"Point"}
}