{
  "type": "Feature",
  "properties": {
    "iso:country":"CH",
    "sg:address":"Innere Kanalstrasse 66",
    "sg:city":"Niederg\u00f6sgen",
    "sg:orig_category":"Finanzierungsinstitutionen",
    "sg:postcode":"5013",
    "sg:province":"Solothurn",
    "wof:name":"Marthaler Consulting",
    "wof:placetype":"venue"
},
  "geometry": {"coordinates":[7.9887871742,47.3685531616],"type":"Point"}
}