{
  "type": "Feature",
  "properties": {
    "iso:country":"CH",
    "sg:address":"Blegistrasse 15",
    "sg:city":"Baar",
    "sg:orig_category":"Finanzierungsinstitutionen",
    "sg:phone":"+41 41 760 30 70",
    "sg:postcode":"6340",
    "sg:province":"Zug",
    "wof:name":"Corisol Holding Ag",
    "wof:placetype":"venue"
},
  "geometry": {"coordinates":[8.5686693192,47.2156143188],"type":"Point"}
}