{
  "type": "Feature",
  "properties": {
    "iso:country":"CH",
    "sg:address":"Ruchonnet Avenue Louis- 18",
    "sg:city":"Lausanne",
    "sg:orig_category":"Architektur U Ingenieurb\u00fcros",
    "sg:postcode":"1003",
    "sg:province":"Vaud",
    "wof:name":"Willemetz Michel Architecte Epfl",
    "wof:placetype":"venue"
},
  "geometry": {"coordinates":[6.625113,46.519077],"type":"Point"}
}