{
  "type": "Feature",
  "properties": {
    "iso:country":"CH",
    "sg:address":"4614",
    "sg:city":"H\u00e4gendorf",
    "sg:orig_category":"Vereine Gesang",
    "sg:phone":"+41 18011090",
    "sg:postcode":"4614",
    "sg:province":"Solothurn",
    "wof:name":"Reformierter Kirchenchor Wangen B.d\u00fcbendorf",
    "wof:placetype":"venue"
},
  "geometry": {"coordinates":[8.6456403732,47.4106483459],"type":"Point"}
}