{
  "type": "Feature",
  "properties": {
    "iso:country":"CH",
    "sg:address":"Gugerhalde 29 8200 Schaffhausen. Postfach",
    "sg:city":"Schaffhausen",
    "sg:orig_category":"Hochschulen U h\u00f6here Ausbildung",
    "sg:phone":"+41 52 643 37 17",
    "sg:postcode":"8207",
    "sg:province":"Schaffhausen",
    "wof:name":"Wullschleger Sonja, Malschule",
    "wof:placetype":"venue"
},
  "geometry": {"coordinates":[8.6655187607,47.725402832],"type":"Point"}
}