{
  "type": "Feature",
  "properties": {
    "iso:country":"CH",
    "sg:address":"6147 Altb\u00fcron. Postfach",
    "sg:city":"Altb\u00fcron",
    "sg:orig_category":"Sportvereine Ballsport Fussball",
    "sg:phone":"+41 41 870 06 44",
    "sg:postcode":"6147",
    "sg:province":"Luzern",
    "wof:name":"Fc Altdorf",
    "wof:placetype":"venue"
},
  "geometry": {"coordinates":[8.639749527,46.8880310059],"type":"Point"}
}