{
  "type": "Feature",
  "properties": {
    "iso:country":"CH",
    "sg:address":"1981",
    "sg:city":"Vex",
    "sg:orig_category":"Gemeindeverwaltungen",
    "sg:phone":"+41 27 207 17 10",
    "sg:postcode":"1981",
    "sg:province":"Valais",
    "wof:name":"Administration Communale De Vex",
    "wof:placetype":"venue"
},
  "geometry": {"coordinates":[7.3954100609,46.2054786682],"type":"Point"}
}