{
  "type": "Feature",
  "properties": {
    "iso:country":"CH",
    "sg:address":"Rue H.f.sandoz 24",
    "sg:city":"Tavannes",
    "sg:orig_category":"Grossbanken",
    "sg:phone":"+41 844 800 844",
    "sg:postcode":"2710",
    "sg:province":"Bern",
    "wof:name":"Credit Suisse",
    "wof:placetype":"venue"
},
  "geometry": {"coordinates":[7.1995558739,47.2196464539],"type":"Point"}
}