{
  "type": "Feature",
  "properties": {
    "iso:country":"CH",
    "sg:address":"Weiningerstr. 31",
    "sg:city":"Unterengstringen",
    "sg:classifiers":[
        {
            "category":"Farming",
            "subcategory":"Farm",
            "type":"Manufacturing & Wholesale Goods"
        }
    ],
    "sg:phone":"+41 4117523131",
    "sg:postcode":"8103",
    "sg:province":"Z\u00fcrich",
    "sg:tags":[
        "horticulture",
        "agriculture",
        "livestock"
    ],
    "wof:name":"Hoffmann Ag",
    "wof:placetype":"venue"
},
  "geometry": {"coordinates":[8.449017,47.412197],"type":"Point"}
}