{
  "type": "Feature",
  "properties": {
    "iso:country":"CH",
    "sg:address":"Lorzendamm 6",
    "sg:city":"Baar",
    "sg:orig_category":"Maler U Glasergewerbe",
    "sg:postcode":"6340",
    "sg:province":"Zug",
    "wof:name":"Kischel Malergesch\u00e4ft",
    "wof:placetype":"venue"
},
  "geometry": {"coordinates":[8.5399799347,47.1947135925],"type":"Point"}
}