{
  "type": "Feature",
  "properties": {
    "iso:country":"CH",
    "sg:address":"Chemin Pierraz",
    "sg:city":"Epalinges",
    "sg:orig_category":"Bauschreinerei Herstellung von M\u00f6beln verschiedener Art",
    "sg:phone":"+41 21 784 29 67",
    "sg:postcode":"1066",
    "sg:province":"Vaud",
    "wof:name":"Roger Bohren Eb\u00e9nisterie",
    "wof:placetype":"venue"
},
  "geometry": {"coordinates":[6.660052,46.555252],"type":"Point"}
}