{
  "type": "Feature",
  "properties": {
    "iso:country":"CH",
    "sg:address":"Kolinplatz 3 6300 Zug. Postfach",
    "sg:city":"Zug",
    "sg:orig_category":"Wirtschaftspr\u00fcfung, Steuerberatung U Treuhand",
    "sg:phone":"+41 41 710 61 67",
    "sg:postcode":"6300",
    "sg:province":"Zug",
    "wof:name":"Trjbu Gmbh Treuhandgesch\u00e4fte Im Ber. Finanz Und Rechnungswesen",
    "wof:placetype":"venue"
},
  "geometry": {"coordinates":[8.5155887604,47.1662330627],"type":"Point"}
}