{
  "type": "Feature",
  "properties": {
    "addr:full":"Le Cr\u00eat De Ch\u00e2ble 3 Villiers Neuch\u00e2tel 2057",
    "addr:housenumber":"3",
    "addr:postcode":"2057",
    "addr:street":"Le Cre\u0302T De Cha\u0302Ble",
    "iso:country":"CH",
    "sg:address":"Le Cr\u00eat De Ch\u00e2ble 3",
    "sg:city":"Villiers",
    "sg:orig_category":"Bauspenglerei Dachdeckerei",
    "sg:phone":"+41 79 240 33 89",
    "sg:postcode":"2057",
    "sg:province":"Neuch\u00e2tel",
    "wof:name":"Philippe Matile Ferblanterie & Couverture",
    "wof:placetype":"venue"
},
  "geometry": {"coordinates":[6.96907,47.076786],"type":"Point"}
}