{
  "type": "Feature",
  "properties": {
    "addr:full":"Jessenenstrasse 12 Oberiberg Schwyz 8843",
    "addr:housenumber":"12",
    "addr:postcode":"8843",
    "addr:street":"Jessenenstrasse;Schwyz",
    "iso:country":"CH",
    "sg:address":"Jessenenstrasse 12",
    "sg:city":"Oberiberg",
    "sg:orig_category":"Autogaragen",
    "sg:phone":"+41 55 414 29 19",
    "sg:postcode":"8843",
    "sg:province":"Schwyz",
    "wof:name":"Dorfgarage Heinz Schindler",
    "wof:placetype":"venue"
},
  "geometry": {"coordinates":[8.780848,47.040901],"type":"Point"}
}