{
  "type": "Feature",
  "properties": {
    "iso:country":"CH",
    "sg:address":"Steinmattstrasse 53",
    "sg:city":"Zermatt",
    "sg:orig_category":"RESTAURANTS: TEA-ROOMS",
    "sg:phone":"+41 27 967 38 84",
    "sg:postcode":"3920",
    "sg:province":"Valais",
    "wof:name":"Restaurant Avena",
    "wof:placetype":"venue"
},
  "geometry": {"coordinates":[7.7489910126,46.0186080933],"type":"Point"}
}