{
  "type": "Feature",
  "properties": {
    "iso:country":"CH",
    "sg:address":"3252",
    "sg:city":"Worben",
    "sg:orig_category":"Detailhandel mit Waren verschiedener Art, Hauptrichtung Nahrungsmittel",
    "sg:postcode":"3252",
    "sg:province":"Bern",
    "wof:name":"Landwirtschaftliche Genossenschaft Worben Und Umgebung",
    "wof:placetype":"venue"
},
  "geometry": {"coordinates":[7.2908759117,47.0987968445],"type":"Point"}
}