{
  "type": "Feature",
  "properties": {
    "iso:country":"CH",
    "sg:address":"Andergia",
    "sg:city":"Mesocco",
    "sg:orig_category":"Detailhandel mit Textilien",
    "sg:phone":"+41 32 652 65 71",
    "sg:postcode":"6563",
    "sg:province":"Graubunden",
    "wof:name":"Marco Bertolla N\u00e4hboutique Elisabeth",
    "wof:placetype":"venue"
},
  "geometry": {"coordinates":[7.3669309616,47.1829528809],"type":"Point"}
}