{
  "type": "Feature",
  "properties": {
    "iso:country":"CH",
    "sg:address":"Bergstrasse 36 8044 Z\u00fcrich. Postfach",
    "sg:city":"Z\u00fcrich",
    "sg:orig_category":"Sonstiger Grosshandel",
    "sg:phone":"+41 12514646",
    "sg:postcode":"8024",
    "sg:province":"Z\u00fcrich",
    "wof:name":"Handelsgesellschaft Z\u00fcrich Hgz",
    "wof:placetype":"venue"
},
  "geometry": {"coordinates":[8.5610589981,47.3739242554],"type":"Point"}
}