{
  "type": "Feature",
  "properties": {
    "iso:country":"CH",
    "sg:address":"Gandaweg",
    "sg:city":"Klosters",
    "sg:orig_category":"Sportvereine Sch\u00fctzen Pistolen-& Gewehr",
    "sg:postcode":"7250",
    "sg:province":"Graubunden",
    "wof:name":"Pistolen-schiessverein",
    "wof:placetype":"venue"
},
  "geometry": {"coordinates":[8.8481006622,47.1913108826],"type":"Point"}
}