{
  "type": "Feature",
  "properties": {
    "iso:country":"CH",
    "sg:address":"B\u00e4renfelserstrasse 3",
    "sg:city":"Basel",
    "sg:orig_category":"Innendekorationsateliers",
    "sg:phone":"+41 61 691 14 55",
    "sg:postcode":"4057",
    "sg:province":"Basel-Stadt",
    "wof:name":"Kasper Innendekoration",
    "wof:placetype":"venue"
},
  "geometry": {"coordinates":[7.5877981186,47.5663337708],"type":"Point"}
}