{
  "type": "Feature",
  "properties": {
    "iso:country":"CH",
    "sg:address":"1938",
    "sg:city":"Champex",
    "sg:orig_category":"Schwimmb\u00e4der",
    "sg:phone":"+41 27 783 26 52",
    "sg:postcode":"1938",
    "sg:province":"Valais",
    "wof:name":"Piscine Chauff\u00e9e De Champex",
    "wof:placetype":"venue"
},
  "geometry": {"coordinates":[7.1182599068,46.0285491943],"type":"Point"}
}