{
  "type": "Feature",
  "properties": {
    "iso:country":"CH",
    "sg:address":"Ziegeleistrasse 13 5070 Frick. Postfach",
    "sg:city":"Frick",
    "sg:orig_category":"Pensionskassen",
    "sg:phone":"+41 41 874 81 81",
    "sg:postcode":"5070",
    "sg:province":"Aargau",
    "wof:name":"Wohlfahrtsfonds Der Firma Bauunternehmung Josef Baumann S\u00f6hne Ag",
    "wof:placetype":"venue"
},
  "geometry": {"coordinates":[8.6355762482,46.886100769],"type":"Point"}
}