{
  "type": "Feature",
  "properties": {
    "addr:full":"Hofmattstrasse 14 Huttwil Bern 4950",
    "addr:housenumber":"14",
    "addr:postcode":"4950",
    "addr:street":"Hofmattstrasse",
    "iso:country":"CH",
    "sg:address":"Hofmattstrasse 14",
    "sg:city":"Huttwil",
    "sg:classifiers":[
        {
            "category":"Professional",
            "subcategory":"Advertising",
            "type":"Services"
        }
    ],
    "sg:phone":"+41 62 962 17 77",
    "sg:postcode":"4950",
    "sg:province":"Bern",
    "sg:tags":[
        "poster"
    ],
    "wof:name":"Druckerei Gr\u00e4nicher",
    "wof:placetype":"venue"
},
  "geometry": {"coordinates":[7.846564,47.1133],"type":"Point"}
}