{
  "type": "Feature",
  "properties": {
    "iso:country":"CH",
    "sg:address":"M\u00f6slistrasse 12",
    "sg:city":"Feldbrunnen",
    "sg:orig_category":"Einzelhandel mit Automobilen Herstellung von Karosserien U Anh\u00e4ngern",
    "sg:phone":"+41 32 622 96 10",
    "sg:postcode":"4532",
    "sg:province":"Solothurn",
    "wof:name":"Moby Campers Gloor K.",
    "wof:placetype":"venue"
},
  "geometry": {"coordinates":[7.5540962219,47.2201347351],"type":"Point"}
}