{
  "type": "Feature",
  "properties": {
    "iso:country":"CH",
    "sg:address":"Ringelweg 31",
    "sg:city":"Tamins",
    "sg:orig_category":"Unclassifiable Establishments",
    "sg:phone":"+41 81 911 38 05",
    "sg:postcode":"7015",
    "sg:province":"Graubunden",
    "wof:name":"Riwa Reinigungen Luginb\u00fchl Walter",
    "wof:placetype":"venue"
},
  "geometry": {"coordinates":[9.4083499908,46.8265075684],"type":"Point"}
}