{
  "type": "Feature",
  "properties": {
    "iso:country":"CH",
    "sg:address":"Unterm\u00fcli 7",
    "sg:city":"Zug",
    "sg:orig_category":"Herstellung von medizinischen U chirurgischen Ger\u00e4ten sowie orthop\u00e4dischen Vorrichtungen Medizinisch",
    "sg:phone":"+41 41 710 10 11",
    "sg:postcode":"6300",
    "sg:province":"Zug",
    "wof:name":"Arcoma Medical Diagnostics Ag",
    "wof:placetype":"venue"
},
  "geometry": {"coordinates":[8.5177021027,47.1804161072],"type":"Point"}
}