{
  "type": "Feature",
  "properties": {
    "iso:country":"CH",
    "sg:address":"Route Principale 53",
    "sg:city":"Vicques",
    "sg:orig_category":"Unclassifiable Establishments",
    "sg:postcode":"2824",
    "sg:province":"Jura",
    "wof:name":"G\u00e9rard Voisard Gfidu",
    "wof:placetype":"venue"
},
  "geometry": {"coordinates":[7.4168448448,47.3490600586],"type":"Point"}
}