{
  "type": "Feature",
  "properties": {
    "addr:full":"Avenue De L'amandolier 22 Gen\u00e8ve Gen\u00e8ve 1208",
    "addr:housenumber":"22",
    "addr:postcode":"1208",
    "addr:street":"Avenue De L'Amandolier",
    "iso:country":"CH",
    "sg:address":"Avenue De L'amandolier 22",
    "sg:city":"Gen\u00e8ve",
    "sg:orig_category":"Architekturb\u00fcros",
    "sg:phone":"+41 22 735 96 33",
    "sg:postcode":"1208",
    "sg:province":"Gen\u00e8ve",
    "wof:name":"Adriano Milone Bureau D'architecture",
    "wof:placetype":"venue"
},
  "geometry": {"coordinates":[6.166781,46.197403],"type":"Point"}
}