{
  "type": "Feature",
  "properties": {
    "iso:country":"CH",
    "sg:address":"Avenue De L'amandolier 22",
    "sg:city":"Gen\u00e8ve",
    "sg:orig_category":"Architekturb\u00fcros",
    "sg:phone":"+41 22 735 96 33",
    "sg:postcode":"1208",
    "sg:province":"Gen\u00e8ve",
    "wof:name":"Adriano Milone Bureau D'architecture",
    "wof:placetype":"venue"
},
  "geometry": {"coordinates":[6.166781,46.197403],"type":"Point"}
}