{
  "type": "Feature",
  "properties": {
    "iso:country":"CH",
    "sg:address":"Pioda Via 14",
    "sg:city":"Lugano",
    "sg:orig_category":"Herstellung von k\u00e4lte U lufttechnischen Erzeugnissen f\u00fcr gewerbliche Zwecke",
    "sg:phone":"+41 91 910 26 70",
    "sg:postcode":"6900",
    "sg:province":"Ticino",
    "wof:name":"M.f.l. Sa, Lussemburgo, Succursale Di Lugano",
    "wof:placetype":"venue"
},
  "geometry": {"coordinates":[8.9513053894,46.0029754639],"type":"Point"}
}