{
  "type": "Feature",
  "properties": {
    "iso:country":"CH",
    "sg:address":"Neur\u00fcti 1491 9052 Niederteufen. Postfach",
    "sg:city":"Niederteufen",
    "sg:orig_category":"Allgemeiner Hoch U Tiefbau",
    "sg:phone":"+41 71 333 33 34",
    "sg:postcode":"9052",
    "sg:province":"Appenzell Ausserrhoden",
    "wof:name":"Corazza Ag",
    "wof:placetype":"venue"
},
  "geometry": {"coordinates":[9.364295,47.393684],"type":"Point"}
}