{
  "type": "Feature",
  "properties": {
    "iso:country":"CH",
    "sg:address":"3901",
    "sg:city":"Gondo",
    "sg:orig_category":"Vorschulen, Kinderg\u00e4rten",
    "sg:phone":"+41 71 351 64 06",
    "sg:postcode":"3901",
    "sg:province":"Valais",
    "wof:name":"Kindergarten Schulhaus",
    "wof:placetype":"venue"
},
  "geometry": {"coordinates":[7.9367241859,46.1232452393],"type":"Point"}
}