{
  "type": "Feature",
  "properties": {
    "iso:country":"CH",
    "sg:address":"Kirchgasse 5",
    "sg:city":"Bretzwil",
    "sg:classifiers":[
        {
            "category":"Education",
            "subcategory":"Library",
            "type":"Public Place"
        }
    ],
    "sg:phone":"+41 61 941 14 71",
    "sg:postcode":"4207",
    "sg:province":"Basel-Landschaft",
    "sg:tags":[
        "u",
        "bibliotheken",
        "archive"
    ],
    "wof:name":"Reformierte Pfarrbibliothek",
    "wof:placetype":"venue"
},
  "geometry": {"coordinates":[7.654564,47.398216],"type":"Point"}
}