{
  "type": "Feature",
  "properties": {
    "iso:country":"CH",
    "sg:address":"Bahnhofstr.24",
    "sg:city":"Aarau",
    "sg:classifiers":[
        {
            "category":"Building & Trades",
            "subcategory":"Construction",
            "type":"Services"
        }
    ],
    "sg:phone":"+41 62 832 04 00",
    "sg:postcode":"5001",
    "sg:province":"Aargau",
    "sg:tags":[
        "work",
        "public"
    ],
    "wof:name":"Zschokke Locher Ag",
    "wof:placetype":"venue"
},
  "geometry": {"coordinates":[8.046761,47.39082],"type":"Point"}
}