{
  "type": "Feature",
  "properties": {
    "iso:country":"CH",
    "sg:address":"Dorfstrasse",
    "sg:city":"Wattenwil",
    "sg:orig_category":"Grosshandel mit sonstigen Maschinen U Ausr\u00fcstungen f\u00fcr Industrie, Handel U Schiffahrt Mechanische We",
    "sg:phone":"+41 33 356 13 06",
    "sg:postcode":"3665",
    "sg:province":"Bern",
    "wof:name":"Garo Beat",
    "wof:placetype":"venue"
},
  "geometry": {"coordinates":[7.5093970299,46.7700538635],"type":"Point"}
}