{
  "type": "Feature",
  "properties": {
    "iso:country":"CH",
    "sg:address":"Weieracherstrasse 7",
    "sg:city":"Bachenb\u00fclach",
    "sg:orig_category":"Herstellung von Metallerzeugnissen ohne Maschinenbau Maschinenbau",
    "sg:phone":"+41 79 437 58 62",
    "sg:postcode":"8184",
    "sg:province":"Z\u00fcrich",
    "wof:name":"Studer Hans Maschinenfabrik Ag.",
    "wof:placetype":"venue"
},
  "geometry": {"coordinates":[8.5378837585,47.5046958923],"type":"Point"}
}