{
  "type": "Feature",
  "properties": {
    "iso:country":"CH",
    "sg:address":"Schwyzerstrasse 11",
    "sg:city":"Brunnen",
    "sg:orig_category":"Autogaragen Einzelhandel mit Automobilen",
    "sg:postcode":"6440",
    "sg:province":"Schwyz",
    "wof:name":"Surer Auto-& Ersatzteil-handel Garage",
    "wof:placetype":"venue"
},
  "geometry": {"coordinates":[7.717415,47.535545],"type":"Point"}
}