{
  "type": "Feature",
  "properties": {
    "iso:country":"CH",
    "sg:address":"3962",
    "sg:city":"Montana",
    "sg:classifiers":[
        {
            "category":"Restaurant",
            "type":"Food & Drink"
        }
    ],
    "sg:phone":"+41 27 481 25 32",
    "sg:postcode":"3962",
    "wof:name":"Caf\u00e9 Plumachit",
    "wof:placetype":"venue"
},
  "geometry": {"coordinates":[-122.67961120610001,45.5516166687],"type":"Point"}
}