{
  "type": "Feature",
  "properties": {
    "addr:full":"Theaterstrasse 2 4051 Basel. Postfach Basel Basel-Stadt 4001",
    "addr:housenumber":"2",
    "addr:postcode":"4051;4001",
    "addr:street":"Theaterstrasse;Postfach",
    "iso:country":"CH",
    "sg:address":"Theaterstrasse 2 4051 Basel. Postfach",
    "sg:city":"Basel",
    "sg:orig_category":"Detailhandel mit Beleuchtungs U Haushaltsgegenst\u00e4nden Detailhandel mit M\u00f6beln",
    "sg:phone":"+41 19312050",
    "sg:postcode":"4001",
    "sg:province":"Basel-Stadt",
    "wof:name":"Interni Innenarchitektur Und Wohngestaltung, Pigagnelli Victor, Dipl. Innenarchitekt",
    "wof:placetype":"venue"
},
  "geometry": {"coordinates":[8.80849,47.331669],"type":"Point"}
}