{
  "type": "Feature",
  "properties": {
    "iso:country":"CH",
    "sg:address":"Sonnenbergstrasse 25 9404 Rorschacherberg. Postfach",
    "sg:city":"Rorschacherberg",
    "sg:orig_category":"Geb\u00e4ude, Wohnungsreinigung",
    "sg:phone":"+41 71 855 04 04",
    "sg:postcode":"9404",
    "sg:province":"St. Gallen",
    "wof:name":"Strebel's Reinigungs-service",
    "wof:placetype":"venue"
},
  "geometry": {"coordinates":[9.5074596405,47.4688644409],"type":"Point"}
}