{
  "type": "Feature",
  "properties": {
    "iso:country":"CH",
    "sg:address":"Somvi 110",
    "sg:city":"M\u00fcstair",
    "sg:orig_category":"Versandhandel",
    "sg:postcode":"7537",
    "sg:province":"Graubunden",
    "wof:name":"Agape Baeder",
    "wof:placetype":"venue"
},
  "geometry": {"coordinates":[10.4459352493,46.6206817627],"type":"Point"}
}