{
  "type": "Feature",
  "properties": {
    "iso:country":"CH",
    "sg:address":"Luegislandstrasse 300",
    "sg:city":"Z\u00fcrich",
    "sg:orig_category":"Kinderkrippen U horte",
    "sg:phone":"+41 13216523",
    "sg:postcode":"8051",
    "sg:province":"Z\u00fcrich",
    "wof:name":"Hort Des Schulamtes Der Stadt Z\u00fcrich",
    "wof:placetype":"venue"
},
  "geometry": {"coordinates":[8.5741996765,47.4088134766],"type":"Point"}
}