{
  "type": "Feature",
  "properties": {
    "iso:country":"CH",
    "sg:address":"Route De Saint-julien 44",
    "sg:city":"Carouge",
    "sg:classifiers":[
        {
            "category":"Building & Trades",
            "subcategory":"Plumbing",
            "type":"Services"
        }
    ],
    "sg:phone":"+41 22 827 10 10",
    "sg:postcode":"1227",
    "sg:province":"Gen\u00e8ve",
    "sg:tags":[
        "supraregional",
        "gas"
    ],
    "wof:name":"A. Schneider S.a.",
    "wof:placetype":"venue"
},
  "geometry": {"coordinates":[6.133035183,46.1768035889],"type":"Point"}
}