{
  "type": "Feature",
  "properties": {
    "iso:country":"CH",
    "sg:address":"Hubstrasse 33",
    "sg:city":"Bassersdorf",
    "sg:orig_category":"Detailhandel mit Waren verschiedener Art, Hauptrichtung Nahrungsmittel Detailhandel mit Waren versch",
    "sg:phone":"+41 18365550",
    "sg:postcode":"8303",
    "sg:province":"Z\u00fcrich",
    "wof:name":"Margrith Marty Volg Laden",
    "wof:placetype":"venue"
},
  "geometry": {"coordinates":[8.6369762421,47.4417572021],"type":"Point"}
}