{
  "type": "Feature",
  "properties": {
    "iso:country":"CH",
    "sg:address":"Alt Strass 17",
    "sg:city":"Trimmis",
    "sg:orig_category":"Detailhandel mit Bekleidung",
    "sg:phone":"+41 81 353 96 59",
    "sg:postcode":"7203",
    "sg:province":"Graubunden",
    "wof:name":"Sepp Fischer Arbeits-& Freizeitbekleidung",
    "wof:placetype":"venue"
},
  "geometry": {"coordinates":[9.560285,46.90855],"type":"Point"}
}