{
  "type": "Feature",
  "properties": {
    "iso:country":"CH",
    "sg:address":"Mattenstrasse 7",
    "sg:city":"Riedholz",
    "sg:orig_category":"Fachdetailhandel in Verkaufsr\u00e4umen",
    "sg:phone":"+41 79 352 20 90",
    "sg:postcode":"4533",
    "sg:province":"Solothurn",
    "wof:name":"K\u00f6nig Design Ag",
    "wof:placetype":"venue"
},
  "geometry": {"coordinates":[9.8381910324,46.4970664978],"type":"Point"}
}