{
  "type": "Feature",
  "properties": {
    "iso:country":"CH",
    "sg:address":"Viale Officina 8 6500 Bellinzona. Postfach Caselle Postale 1024",
    "sg:city":"Bellinzona",
    "sg:orig_category":"Advokaturb\u00fcros",
    "sg:phone":"+41 91 826 36 35",
    "sg:postcode":"6500",
    "sg:province":"Ticino",
    "wof:name":"Giuseppe Gornati Studio Legale",
    "wof:placetype":"venue"
},
  "geometry": {"coordinates":[9.026635,46.196445],"type":"Point"}
}