{
  "type": "Feature",
  "properties": {
    "iso:country":"CH",
    "sg:address":"Sch\u00fctzengasse 18 2540 Grenchen. Postfach 478",
    "sg:city":"Grenchen",
    "sg:orig_category":"Pensionskassen",
    "sg:phone":"+41 32 653 13 53",
    "sg:postcode":"2540",
    "sg:province":"Solothurn",
    "wof:name":"Erg\u00e4nzungsstiftung Felca Ag Und Der Angeschlossenen Unternehmungen",
    "wof:placetype":"venue"
},
  "geometry": {"coordinates":[7.3926692009,47.1940422058],"type":"Point"}
}