{
  "type": "Feature",
  "properties": {
    "iso:country":"CH",
    "sg:address":"G\u00fcmligentalstr. 22",
    "sg:city":"G\u00fcmligen",
    "sg:orig_category":"Dienstleistungen, K\u00f6rper U Pflege",
    "sg:phone":"+41 31 931 41 70",
    "sg:postcode":"3073",
    "sg:province":"Bern",
    "wof:name":"Schreinerei U Schweizer Guemligen G\u00fcmligen Thun Bern",
    "wof:placetype":"venue"
},
  "geometry": {"coordinates":[7.505775,46.93343],"type":"Point"}
}