{
  "type": "Feature",
  "properties": {
    "iso:country":"CH",
    "sg:address":"Einhornplatz 1",
    "sg:city":"Sins",
    "sg:classifiers":[
        {
            "category":"Travel",
            "subcategory":"Hotels & Motels",
            "type":"Entertainment"
        }
    ],
    "sg:phone":"+41 34 461 16 24",
    "sg:postcode":"5643",
    "sg:province":"Aargau",
    "sg:tags":[
        "hotels",
        "mit",
        "restaurant"
    ],
    "wof:name":"Gasthof Emmenbr\u00fccke Ag",
    "wof:placetype":"venue"
},
  "geometry": {"coordinates":[7.6849250793,47.0063858032],"type":"Point"}
}