{
  "type": "Feature",
  "properties": {
    "iso:country":"CH",
    "sg:address":"Chemin Des Moissons 3",
    "sg:city":"Genthod",
    "sg:orig_category":"Bauspenglerei Dachdeckerei",
    "sg:phone":"+41 79 355 40 81",
    "sg:postcode":"1294",
    "sg:province":"Gen\u00e8ve",
    "wof:name":"Domenico Bonito Installation Sanitaire",
    "wof:placetype":"venue"
},
  "geometry": {"coordinates":[6.148672,46.267658],"type":"Point"}
}