{
  "type": "Feature",
  "properties": {
    "addr:full":"Stockhornweg 11 Oberwichtrach Bern 3114",
    "addr:housenumber":"11",
    "addr:postcode":"3114",
    "addr:street":"Stockhornweg",
    "iso:country":"CH",
    "sg:address":"Stockhornweg 11",
    "sg:city":"Oberwichtrach",
    "sg:orig_category":"Bauingenieurb\u00fcros Hochbau Bauingenieurb\u00fcros allgemein",
    "sg:phone":"+41 31 971 27 11",
    "sg:postcode":"3114",
    "sg:province":"Bern",
    "wof:name":"Hansruedi Steiner Ingenieurb\u00fcro",
    "wof:placetype":"venue"
},
  "geometry": {"coordinates":[7.437488,46.927338],"type":"Point"}
}