{
  "type": "Feature",
  "properties": {
    "iso:country":"CH",
    "sg:address":"Seftigenstrasse 29",
    "sg:city":"Belp",
    "sg:orig_category":"Non-Classified Establishments",
    "sg:phone":"+41 31 819 70 36",
    "sg:postcode":"3123",
    "sg:province":"Bern",
    "wof:name":"Michels Sport-schule Buri Michel",
    "wof:placetype":"venue"
},
  "geometry": {"coordinates":[7.489030838,46.8977127075],"type":"Point"}
}