{
  "type": "Feature",
  "properties": {
    "iso:country":"CH",
    "sg:address":"R\u00f6tistrasse 17 4500 Solothurn. Postfach",
    "sg:city":"Solothurn",
    "sg:orig_category":"Forst\u00e4mter",
    "sg:phone":"+41 62 892 22 88",
    "sg:postcode":"4502",
    "sg:province":"Solothurn",
    "wof:name":"St\u00e4dtische Forstverwaltung",
    "wof:placetype":"venue"
},
  "geometry": {"coordinates":[8.1803846359,47.387348175],"type":"Point"}
}