{
  "type": "Feature",
  "properties": {
    "iso:country":"CH",
    "sg:address":"Rue Du Vingt-trois Juin 4",
    "sg:city":"Courroux",
    "sg:orig_category":"Betrieb von Taxis",
    "sg:phone":"+41 32 422 82 83",
    "sg:postcode":"2822",
    "sg:province":"Jura",
    "wof:name":"Michel Becker Sa Garage & Carrosserie",
    "wof:placetype":"venue"
},
  "geometry": {"coordinates":[7.367854,47.361885],"type":"Point"}
}