{
  "type": "Feature",
  "properties": {
    "iso:country":"CH",
    "sg:address":"Les Pichons 1835 Montbovon. Postfach",
    "sg:city":"Montbovon",
    "sg:orig_category":"Detailhandel mit elektrischen Haushalts-,Radio U Fernsehger\u00e4ten sowie Musikinstrumenten",
    "sg:postcode":"1835",
    "wof:name":"Chabloz & Kohler S\u00e0rl",
    "wof:placetype":"venue"
},
  "geometry": {"coordinates":[7.0421199799,46.4857406616],"type":"Point"}
}