{
  "type": "Feature",
  "properties": {
    "iso:country":"CH",
    "sg:address":"Bernstrasse 72",
    "sg:city":"Bern",
    "sg:orig_category":"Fachdetailhandel mit pharmazeutischen Produkten",
    "sg:phone":"+41 56 622 06 22",
    "sg:postcode":"3018",
    "sg:province":"Bern",
    "wof:name":"B\u00fcnz-apotheke Thomas Wullschleger",
    "wof:placetype":"venue"
},
  "geometry": {"coordinates":[8.2780704498,47.3505363464],"type":"Point"}
}