{
  "type": "Feature",
  "properties": {
    "iso:country":"CH",
    "sg:address":"Rue Arnold Winkelried 6",
    "sg:city":"Gen\u00e8ve",
    "sg:orig_category":"Betrieb von Taxis",
    "sg:phone":"+41 22 732 30 32",
    "sg:postcode":"1201",
    "sg:province":"Gen\u00e8ve",
    "wof:name":"Taxis Des Bergues, Bergues Limousine Service, Deberti & Zambrella",
    "wof:placetype":"venue"
},
  "geometry": {"coordinates":[6.146281,46.20723],"type":"Point"}
}