{
  "type": "Feature",
  "properties": {
    "iso:country":"CH",
    "sg:address":"Delle 169",
    "sg:city":"Hallwil",
    "sg:orig_category":"Sonstiger spezialisierter Hoch U Tiefbau",
    "sg:phone":"+41 62 777 20 42",
    "sg:postcode":"5705",
    "sg:province":"Aargau",
    "wof:name":"L\u00fcdi Robert",
    "wof:placetype":"venue"
},
  "geometry": {"coordinates":[8.1811685562,47.323551178],"type":"Point"}
}