{
  "type": "Feature",
  "properties": {
    "iso:country":"CH",
    "sg:address":"Badenerstrasse 701",
    "sg:city":"Z\u00fcrich",
    "sg:orig_category":"Wirtschaftsverb\u00e4nde Industrie, Handel and Gewerbe",
    "sg:phone":"+41 31 351 15 11",
    "sg:postcode":"8048",
    "sg:province":"Z\u00fcrich",
    "wof:name":"Vereinigung Schweizerischer Formular-hersteller",
    "wof:placetype":"venue"
},
  "geometry": {"coordinates":[7.4637980461,46.9459648132],"type":"Point"}
}