{
  "type": "Feature",
  "properties": {
    "iso:country":"CH",
    "sg:address":"Illnauerstrasse 19",
    "sg:city":"Weisslingen",
    "sg:orig_category":"Herstellung von Metallkonstruktionen",
    "sg:phone":"+41 52 394 30 38",
    "sg:postcode":"8484",
    "sg:province":"Z\u00fcrich",
    "wof:name":"Meta-bau Gmbh",
    "wof:placetype":"venue"
},
  "geometry": {"coordinates":[8.7625198364,47.430015564],"type":"Point"}
}