{
  "type": "Feature",
  "properties": {
    "iso:country":"CH",
    "sg:address":"Hauptstrasse 68",
    "sg:city":"Zunzgen",
    "sg:classifiers":[
        {
            "category":"Restaurant",
            "type":"Food & Drink"
        }
    ],
    "sg:phone":"+41 61 961 00 21",
    "sg:postcode":"4455",
    "sg:province":"Basel-Landschaft",
    "wof:name":"Restaurant R\u00f6ssli",
    "wof:placetype":"venue"
},
  "geometry": {"coordinates":[7.7491278648,47.3953666687],"type":"Point"}
}