{
  "type": "Feature",
  "properties": {
    "iso:country":"CH",
    "sg:address":"Grand-rue 4 1462 Yvonand. Postfach",
    "sg:city":"Yvonand",
    "sg:orig_category":"Fachdetailhandel in Verkaufsr\u00e4umen",
    "sg:postcode":"1462",
    "sg:province":"Vaud",
    "wof:name":"Annie-fleurs Broillet M.",
    "wof:placetype":"venue"
},
  "geometry": {"coordinates":[6.7470331192,46.7990646362],"type":"Point"}
}