{
  "type": "Feature",
  "properties": {
    "iso:country":"CH",
    "sg:address":"Poststrasse 16",
    "sg:city":"Jonschwil",
    "sg:orig_category":"Stickerei",
    "sg:phone":"+41 71 877 14 13",
    "sg:postcode":"9243",
    "sg:province":"St. Gallen",
    "wof:name":"Ren\u00e9 Kast Automatenstickerei",
    "wof:placetype":"venue"
},
  "geometry": {"coordinates":[9.4869642258,47.4190826416],"type":"Point"}
}