{
  "type": "Feature",
  "properties": {
    "iso:country":"CH",
    "sg:address":"Straussrain 13",
    "sg:city":"Meierskappel",
    "sg:orig_category":"Gesundheitswesen",
    "sg:phone":"+41 41 790 29 36",
    "sg:postcode":"6344",
    "sg:province":"Luzern",
    "wof:name":"\u00abich-du-er-sie-es\u00bb Lernprogramme Fritze Helmut",
    "wof:placetype":"venue"
},
  "geometry": {"coordinates":[8.445482254,47.1251525879],"type":"Point"}
}