{
  "type": "Feature",
  "properties": {
    "iso:country":"CH",
    "sg:address":"Bottmingerstrasse 50",
    "sg:city":"M\u00fcnchenstein",
    "sg:orig_category":"Fussboden, Fliesen U Plattenlegerei, Tapeziererei",
    "sg:phone":"+41 61 411 19 90",
    "sg:postcode":"4142",
    "sg:province":"Basel-Landschaft",
    "wof:name":"Preziosi Sabino",
    "wof:placetype":"venue"
},
  "geometry": {"coordinates":[7.6047420502,47.5246238708],"type":"Point"}
}