{
  "type": "Feature",
  "properties": {
    "iso:country":"CH",
    "sg:address":"301 Rte De Lausanne",
    "sg:city":"Bellevue",
    "sg:classifiers":[
        {
            "category":"Travel",
            "subcategory":"Hotels & Motels",
            "type":"Entertainment"
        }
    ],
    "sg:phone":"+41 22 959 86 88",
    "sg:postcode":"1293",
    "sg:province":"Gen\u00e8ve",
    "sg:tags":[
        "hotels",
        "business",
        "restaurant"
    ],
    "wof:name":"Hotel La Reserve",
    "wof:placetype":"venue"
},
  "geometry": {"coordinates":[6.150666,46.250156],"type":"Point"}
}