{
  "type": "Feature",
  "properties": {
    "iso:country":"CH",
    "sg:address":"Sorbiers Les 9",
    "sg:city":"Payerne",
    "sg:orig_category":"Non-Classified Establishments",
    "sg:postcode":"1530",
    "sg:province":"Vaud",
    "wof:name":"Evromak S\u00e0rl",
    "wof:placetype":"venue"
},
  "geometry": {"coordinates":[6.9299287796,46.8164978027],"type":"Point"}
}