{
  "type": "Feature",
  "properties": {
    "iso:country":"CH",
    "sg:address":"Wydenweg 2",
    "sg:city":"Winterthur",
    "sg:orig_category":"Chemin\u00e9e- and Ofenbau Sanit\u00e4rkeramik Grosshandel",
    "sg:phone":"+41 52 222 10 40",
    "sg:postcode":"8408",
    "sg:province":"Z\u00fcrich",
    "wof:name":"Erich Hangarter Gmbh Handelsagentur F. Baukeramik",
    "wof:placetype":"venue"
},
  "geometry": {"coordinates":[8.670767,47.515507],"type":"Point"}
}