{
  "type": "Feature",
  "properties": {
    "addr:full":"Hauptstrasse 1 Schmerikon St. Gallen 8716",
    "addr:housenumber":"1",
    "addr:postcode":"8716",
    "addr:street":"Hauptstrasse",
    "iso:country":"CH",
    "sg:address":"Hauptstrasse 1",
    "sg:city":"Schmerikon",
    "sg:orig_category":"Architekturb\u00fcros",
    "sg:phone":"+41 55 282 43 55",
    "sg:postcode":"8716",
    "sg:province":"St. Gallen",
    "wof:name":"Eva Ruhl\u00e9 Architekturb\u00fcro",
    "wof:placetype":"venue"
},
  "geometry": {"coordinates":[8.940843,47.225269],"type":"Point"}
}