{
  "type": "Feature",
  "properties": {
    "iso:country":"CH",
    "sg:address":"Rietacker Alterschwil 9230 Flawil. Postfach",
    "sg:city":"Flawil",
    "sg:orig_category":"Fahrschulen, Flugschulen",
    "sg:phone":"+41 71 393 20 33",
    "sg:postcode":"9230",
    "sg:province":"St. Gallen",
    "wof:name":"Hans B\u00fchler Autofahrschule",
    "wof:placetype":"venue"
},
  "geometry": {"coordinates":[9.1996688843,47.3941726685],"type":"Point"}
}