{
  "type": "Feature",
  "properties": {
    "iso:country":"CH",
    "sg:address":"Vorderuttenberg 29",
    "sg:city":"Knonau",
    "sg:orig_category":"Softwareentwicklung U beratung",
    "sg:postcode":"8934",
    "sg:province":"Z\u00fcrich",
    "wof:name":"G\u00fcrtler Daten-systeme",
    "wof:placetype":"venue"
},
  "geometry": {"coordinates":[8.4497804642,47.2336540222],"type":"Point"}
}