{
  "type": "Feature",
  "properties": {
    "iso:country":"CH",
    "sg:address":"Sous-bougy 20",
    "sg:city":"Aubonne",
    "sg:orig_category":"Unternehmensberatung",
    "sg:phone":"+41 21 320 60 80",
    "sg:postcode":"1170",
    "sg:province":"Vaud",
    "wof:name":"Polydas S\u00e0rl",
    "wof:placetype":"venue"
},
  "geometry": {"coordinates":[5.1808700562,45.8973388672],"type":"Point"}
}