{
  "type": "Feature",
  "properties": {
    "iso:country":"CH",
    "sg:address":"Talstrasse 34 A 7270 Davos Platz. Postfach",
    "sg:city":"Gen\u00e8ve",
    "sg:orig_category":"Handelsvermittlung von Nahrungsmitteln, Getr\u00e4nken U Tabakwaren",
    "sg:postcode":"1207",
    "sg:province":"Gen\u00e8ve",
    "wof:name":"Spierer Freres Et Cie Sa",
    "wof:placetype":"venue"
},
  "geometry": {"coordinates":[9.8289527893,46.7982749939],"type":"Point"}
}