{
  "type": "Feature",
  "properties": {
    "iso:country":"CH",
    "sg:address":"Via Pierino Tatti 3",
    "sg:city":"Bellinzona",
    "sg:orig_category":"Grosshandel mit B\u00fcromaschinen Grosshandel mit Datenverarbeitungsger\u00e4ten",
    "sg:phone":"+41 71 971 24 74",
    "sg:postcode":"6500",
    "sg:province":"Ticino",
    "wof:name":"St\u00e4nz Informatik Ag",
    "wof:placetype":"venue"
},
  "geometry": {"coordinates":[8.9736366272,47.4672927856],"type":"Point"}
}