{
  "type": "Feature",
  "properties": {
    "iso:country":"CH",
    "sg:address":"De-normandie Chemin 14 1206 Gen\u00e8ve. Postfach",
    "sg:city":"Gen\u00e8ve",
    "sg:orig_category":"Unclassifiable Establishments",
    "sg:postcode":"1201",
    "sg:province":"Gen\u00e8ve",
    "wof:name":"Kleeta Holding Sa",
    "wof:placetype":"venue"
},
  "geometry": {"coordinates":[6.1612529755,46.1893043518],"type":"Point"}
}