{
  "type": "Feature",
  "properties": {
    "iso:country":"CH",
    "sg:address":"J. J. Balmer-strasse 5 4053 Basel. Postfach",
    "sg:city":"Basel",
    "sg:orig_category":"Fotografisches Gewerbe U fotografische Laboratorien",
    "sg:postcode":"4051",
    "sg:province":"Basel-Stadt",
    "wof:name":"Interfoto, Weck & Zimmermann Fotoatelier.",
    "wof:placetype":"venue"
},
  "geometry": {"coordinates":[7.5950231552,47.5409431458],"type":"Point"}
}