{
  "type": "Feature",
  "properties": {
    "iso:country":"CH",
    "sg:address":"7130",
    "sg:city":"Ilanz",
    "sg:orig_category":"Sportvereine Ski",
    "sg:postcode":"7130",
    "sg:province":"Graubunden",
    "wof:name":"Skiclub Im Fang",
    "wof:placetype":"venue"
},
  "geometry": {"coordinates":[7.2365999222,46.599521637],"type":"Point"}
}