{
  "type": "Feature",
  "properties": {
    "addr:full":"Z\u00fcrcherstrasse 8 Unterengstringen Z\u00fcrich 8103",
    "addr:housenumber":"8",
    "addr:postcode":"8103",
    "addr:street":"Zuercherstrasse",
    "iso:country":"CH",
    "sg:address":"Z\u00fcrcherstrasse 8",
    "sg:city":"Unterengstringen",
    "sg:orig_category":"Allgemeiner Hoch U Tiefbau",
    "sg:postcode":"8103",
    "sg:province":"Z\u00fcrich",
    "wof:name":"Karadzi A., Gila Gipser Und Leichtbauarbeiten",
    "wof:placetype":"venue"
},
  "geometry": {"coordinates":[8.454533,47.412148],"type":"Point"}
}