{
  "type": "Feature",
  "properties": {
    "iso:country":"CH",
    "sg:address":"Habsburgerstrasse 33",
    "sg:city":"Luzern",
    "sg:orig_category":"Non-Classified Establishments",
    "sg:postcode":"6003",
    "sg:province":"Luzern",
    "wof:name":"Boutique Puzzle, V\u00e9ronika Monney",
    "wof:placetype":"venue"
},
  "geometry": {"coordinates":[5.1808700562,45.8973388672],"type":"Point"}
}