{
  "type": "Feature",
  "properties": {
    "iso:country":"CH",
    "sg:address":"B\u00e4ulistrasse 42",
    "sg:city":"Z\u00fcrich",
    "sg:orig_category":"Interessenvertretungen",
    "sg:postcode":"8049",
    "sg:province":"Z\u00fcrich",
    "wof:name":"Schweizerische Stiftung F\u00fcr Blindentechnische Hilfsmittel",
    "wof:placetype":"venue"
},
  "geometry": {"coordinates":[9.4050226212,47.4377861023],"type":"Point"}
}