{
  "type": "Feature",
  "properties": {
    "iso:country":"CH",
    "sg:address":"Bahnhofbr\u00fccke 1 8001 Z\u00fcrich. Postfach",
    "sg:city":"Z\u00fcrich",
    "sg:orig_category":"Pensionskassen",
    "sg:phone":"+41 12114000",
    "sg:postcode":"8001",
    "sg:province":"Z\u00fcrich",
    "wof:name":"Wohlfahrtsfonds Z\u00fcrich Tourismus",
    "wof:placetype":"venue"
},
  "geometry": {"coordinates":[8.5426282883,47.3767433167],"type":"Point"}
}