{
  "type": "Feature",
  "properties": {
    "iso:country":"CH",
    "sg:address":"Gartematt 1",
    "sg:city":"B\u00fclach",
    "sg:orig_category":"Psychotherapie",
    "sg:phone":"+41 18610766",
    "sg:postcode":"8180",
    "sg:province":"Z\u00fcrich",
    "wof:name":"Peter Allemann Psychotherapie",
    "wof:placetype":"venue"
},
  "geometry": {"coordinates":[8.5430383682,47.518245697],"type":"Point"}
}