{
  "type": "Feature",
  "properties": {
    "iso:country":"CH",
    "sg:address":"Frauenfelderstrasse 27a 8404 Oberwinterthur. Postfach",
    "sg:city":"Winterthur",
    "sg:orig_category":"Vermietung U Verpachtung von eigenen Immobilien",
    "sg:postcode":"8404",
    "sg:province":"Z\u00fcrich",
    "wof:name":"Tanner Immobilien Ag",
    "wof:placetype":"venue"
},
  "geometry": {"coordinates":[8.7583379745,47.5064582825],"type":"Point"}
}