{
  "type": "Feature",
  "properties": {
    "iso:country":"CH",
    "sg:address":"Strada Dal Brugon 1",
    "sg:city":"Pambio-noranco",
    "sg:orig_category":"Herstellung von Tanks U Sammelbeh\u00e4ltern aus Metall Kaminfeger",
    "sg:phone":"+41 91 994 60 61",
    "sg:postcode":"6915",
    "sg:province":"Ticino",
    "wof:name":"Umberto Trogi Puliscarico",
    "wof:placetype":"venue"
},
  "geometry": {"coordinates":[8.9343700409,45.9878463745],"type":"Point"}
}