{
  "type": "Feature",
  "properties": {
    "iso:country":"CH",
    "sg:address":"Quaderstrasse 11",
    "sg:city":"Chur",
    "sg:orig_category":"Non-Classified Establishments",
    "sg:postcode":"7000",
    "sg:province":"Graubunden",
    "wof:name":"Barrings Holding Ag",
    "wof:placetype":"venue"
},
  "geometry": {"coordinates":[9.5324888229,46.8524131775],"type":"Point"}
}