{
  "type": "Feature",
  "properties": {
    "iso:country":"CH",
    "sg:address":"Chaletweg 2",
    "sg:city":"Oftringen",
    "sg:orig_category":"Herstellung von sonstigen Maschinen f\u00fcr unspezifische Verwendung",
    "sg:phone":"+41 62 797 38 71",
    "sg:postcode":"4665",
    "sg:province":"Aargau",
    "wof:name":"Gkp L\u00fcscher R.",
    "wof:placetype":"venue"
},
  "geometry": {"coordinates":[7.9534401894,47.3005447388],"type":"Point"}
}