{
  "type": "Feature",
  "properties": {
    "iso:country":"CH",
    "sg:address":"Jaques-dalcroze Av.e.- 9",
    "sg:city":"Lausanne",
    "sg:orig_category":"Non-Classified Establishments",
    "sg:postcode":"1007",
    "sg:province":"Vaud",
    "wof:name":"Voile D'or Caf\u00e9 S\u00e0rl",
    "wof:placetype":"venue"
},
  "geometry": {"coordinates":[6.6091461182,46.511920929],"type":"Point"}
}