{
  "type": "Feature",
  "properties": {
    "iso:country":"CH",
    "sg:address":"L\u00e4nggasse 51 2500 Biel/bienne. Postfach",
    "sg:city":"Biel/bienne",
    "sg:orig_category":"Grosshandel mit Nahrungsmitteln, Getr\u00e4nken U Tabakwaren ohne ausgepr\u00e4gten Schwerpunkt",
    "sg:postcode":"2504",
    "sg:province":"Bern",
    "wof:name":"Rotsch Daniel",
    "wof:placetype":"venue"
},
  "geometry": {"coordinates":[7.2740440369,47.1533966064],"type":"Point"}
}