{
  "type": "Feature",
  "properties": {
    "iso:country":"CH",
    "sg:address":"Schlossm\u00fchlestrasse 9 8400 Winterthur. Postfach",
    "sg:city":"Winterthur",
    "sg:orig_category":"Sonstiger Grosshandel",
    "sg:phone":"+41 52 204 04 21",
    "sg:postcode":"8408",
    "sg:province":"Z\u00fcrich",
    "wof:name":"Stadelmann J., Trading & Consulting",
    "wof:placetype":"venue"
},
  "geometry": {"coordinates":[8.7129383087,47.5059165955],"type":"Point"}
}