{
  "type": "Feature",
  "properties": {
    "iso:country":"CH",
    "sg:address":"Lindenholz 1",
    "sg:city":"Leimiswil",
    "sg:orig_category":"RESTAURANTS: TEA-ROOMS",
    "sg:phone":"+41 62 965 25 31",
    "sg:postcode":"4935",
    "sg:province":"Bern",
    "wof:name":"Restaurant L\u00f6wen, Alfred R\u00fctti",
    "wof:placetype":"venue"
},
  "geometry": {"coordinates":[7.7899899483,47.1549568176],"type":"Point"}
}