{
  "type": "Feature",
  "properties": {
    "iso:country":"CH",
    "sg:address":"Obertorweg 93",
    "sg:city":"Allschwil",
    "sg:orig_category":"Unternehmensberatung",
    "sg:postcode":"4123",
    "sg:province":"Basel-Landschaft",
    "wof:name":"Fiebig Claus W., Unternehmensberatung",
    "wof:placetype":"venue"
},
  "geometry": {"coordinates":[7.5241360664,47.5495376587],"type":"Point"}
}