{
  "type": "Feature",
  "properties": {
    "iso:country":"CH",
    "sg:address":"Avenue Edmond-vaucher 20",
    "sg:city":"Gen\u00e8ve",
    "sg:classifiers":[
        {
            "category":"Education",
            "subcategory":"Vocational School",
            "type":"Public Place"
        }
    ],
    "sg:postcode":"1203",
    "sg:province":"Gen\u00e8ve",
    "sg:tags":[
        "koch-",
        "haushaltschulen"
    ],
    "wof:name":"Ecole M\u00e9nag\u00e8re Centre Numaz-droz",
    "wof:placetype":"venue"
},
  "geometry": {"coordinates":[6.8268561363,47.1048698425],"type":"Point"}
}