{
  "type": "Feature",
  "properties": {
    "iso:country":"CH",
    "sg:address":"Maulbeerstrasse 61",
    "sg:city":"Basel",
    "sg:orig_category":"Grosshandel mit Nahrungsmitteln, Getr\u00e4nken U Tabakwaren ohne ausgepr\u00e4gten Schwerpunkt",
    "sg:postcode":"4058",
    "sg:province":"Basel-Stadt",
    "wof:name":"Lebensmittelladen Freundschaft Zum Pavkovic",
    "wof:placetype":"venue"
},
  "geometry": {"coordinates":[7.6028571129,47.5678215027],"type":"Point"}
}