{
  "type": "Feature",
  "properties": {
    "iso:country":"CH",
    "sg:address":"Jurastr. 21",
    "sg:city":"Niederg\u00f6sgen",
    "sg:orig_category":"Sanit\u00e4rinstallation U Spenglerei",
    "sg:phone":"+41 32 861 45 43",
    "sg:postcode":"5013",
    "sg:province":"Solothurn",
    "wof:name":"Rocco Pronesti Installations Sanitaires",
    "wof:placetype":"venue"
},
  "geometry": {"coordinates":[6.5601019859,46.9096336365],"type":"Point"}
}