{
  "type": "Feature",
  "properties": {
    "iso:country":"CH",
    "sg:address":"6927",
    "sg:city":"Agra",
    "sg:orig_category":"Malerei",
    "sg:phone":"+41 79 438 61 50",
    "sg:postcode":"6927",
    "sg:province":"Ticino",
    "wof:name":"Enzo Campanelli Entreprise De Peinture",
    "wof:placetype":"venue"
},
  "geometry": {"coordinates":[6.2252488136,46.2644767761],"type":"Point"}
}