{
  "type": "Feature",
  "properties": {
    "iso:country":"CH",
    "sg:address":"Universit\u00e4tstrasse 118",
    "sg:city":"Z\u00fcrich",
    "sg:orig_category":"Reiseb\u00fcros U Reiseveranstalter",
    "sg:postcode":"8000",
    "sg:province":"Z\u00fcrich",
    "wof:name":"Reisen Zurbriggen Gmbh Reisen, Taxifahrten Usw.; Organisation, Durchf\u00fchrung",
    "wof:placetype":"venue"
},
  "geometry": {"coordinates":[7.9573631287,46.0964317322],"type":"Point"}
}