{
  "type": "Feature",
  "properties": {
    "iso:country":"CH",
    "sg:address":"Langstrasse 13 8004 Z\u00fcrich. Postfach",
    "sg:city":"Z\u00fcrich",
    "sg:orig_category":"Rechtsberatung",
    "sg:postcode":"8001",
    "sg:province":"Z\u00fcrich",
    "wof:name":"P. Alvarado Oehri, Rechtsberatung Und Treuhand",
    "wof:placetype":"venue"
},
  "geometry": {"coordinates":[8.5247249603,47.3748550415],"type":"Point"}
}