{
  "type": "Feature",
  "properties": {
    "iso:country":"CH",
    "sg:address":"Galerie De La Gare 18",
    "sg:city":"Nyon",
    "sg:orig_category":"Detailhandel mit Textilien",
    "sg:phone":"+41 22 362 70 72",
    "sg:postcode":"1260",
    "sg:province":"Vaud",
    "wof:name":"Amour De Soie, Hauert-deville Sophie",
    "wof:placetype":"venue"
},
  "geometry": {"coordinates":[6.2371811867,46.3826904297],"type":"Point"}
}