{
  "type": "Feature",
  "properties": {
    "iso:country":"CH",
    "sg:address":"Rebbergstrasse 55a",
    "sg:city":"Wettingen",
    "sg:orig_category":"Architektur U Ingenieurb\u00fcros",
    "sg:phone":"+41 56 426 18 45",
    "sg:postcode":"5430",
    "sg:province":"Aargau",
    "wof:name":"Jacobsen Sidney Beratender Ingenieur",
    "wof:placetype":"venue"
},
  "geometry": {"coordinates":[8.32409,47.472279],"type":"Point"}
}