{
  "type": "Feature",
  "properties": {
    "iso:country":"CH",
    "sg:address":"Wassermatte 1",
    "sg:city":"Sursee",
    "sg:orig_category":"Herstellung von Anstrichmitteln, Druckfarben U Kitten Herstellung von Kunststoff in Prim\u00e4rformen",
    "sg:postcode":"6210",
    "sg:province":"Luzern",
    "wof:name":"Collano Ag Werk Sursee",
    "wof:placetype":"venue"
},
  "geometry": {"coordinates":[8.1068248749,47.1833992004],"type":"Point"}
}