{
  "type": "Feature",
  "properties": {
    "iso:country":"CH",
    "sg:address":"Husacher",
    "sg:city":"Jegenstorf",
    "sg:orig_category":"Sonstige mit der Informatik verbundene T\u00e4tigkeiten",
    "sg:phone":"+41 79 410 22 46",
    "sg:postcode":"3303",
    "sg:province":"Bern",
    "wof:name":"Graber Fredy Ag",
    "wof:placetype":"venue"
},
  "geometry": {"coordinates":[7.5059099197,47.0486793518],"type":"Point"}
}