{
  "type": "Feature",
  "properties": {
    "iso:country":"CH",
    "sg:address":"Chapfstrasse 250",
    "sg:city":"R\u00fcdlingen",
    "sg:orig_category":"Werbung",
    "sg:phone":"+41 18672333",
    "sg:postcode":"8455",
    "sg:province":"Schaffhausen",
    "wof:name":"Werbeagentur Nelly Ledergerber",
    "wof:placetype":"venue"
},
  "geometry": {"coordinates":[8.5720300674,47.5793533325],"type":"Point"}
}