{
  "type": "Feature",
  "properties": {
    "addr:full":"Pl\u00e4nkestrasse 12 2502 Biel/bienne. Postfach Biel/bienne Bern 2502",
    "addr:housenumber":"12",
    "addr:postcode":"2502;postfach;2502",
    "addr:street":"Plaenkestrasse",
    "iso:country":"CH",
    "sg:address":"Pl\u00e4nkestrasse 12 2502 Biel/bienne. Postfach",
    "sg:city":"Biel/bienne",
    "sg:orig_category":"Architektur U Ingenieurb\u00fcros",
    "sg:postcode":"2502",
    "sg:province":"Bern",
    "wof:name":"Bart & Buchhofer Architekten Ag Architekturb\u00fcro Mit Planung, Ausf\u00fchrung, Forschung Usw",
    "wof:placetype":"venue"
},
  "geometry": {"coordinates":[7.243459,47.136536],"type":"Point"}
}