{
  "type": "Feature",
  "properties": {
    "iso:country":"CH",
    "sg:address":"Hauptstrasse 35",
    "sg:city":"D\u00f6ttingen",
    "sg:orig_category":"Non-Classified Establishments",
    "sg:postcode":"5312",
    "sg:province":"Aargau",
    "wof:name":"Image-gastro Gmbh",
    "wof:placetype":"venue"
},
  "geometry": {"coordinates":[8.2563524246,47.5722503662],"type":"Point"}
}