{
  "type": "Feature",
  "properties": {
    "addr:full":"Chemin Du Champ-d'anier 15 Gen\u00e8ve Gen\u00e8ve 1209",
    "addr:housenumber":"15",
    "addr:postcode":"1209",
    "addr:street":"Chemin Du Champ-D'Anier",
    "iso:country":"CH",
    "sg:address":"Chemin Du Champ-d'anier 15",
    "sg:city":"Gen\u00e8ve",
    "sg:orig_category":"B\u00e4ckereien Konditoreien",
    "sg:phone":"+41 22 798 19 34",
    "sg:postcode":"1209",
    "sg:province":"Gen\u00e8ve",
    "wof:name":"Emilio Musio Boulangerie-p\u00e2tisserie",
    "wof:placetype":"venue"
},
  "geometry": {"coordinates":[6.148988,46.246429],"type":"Point"}
}