{
  "type": "Feature",
  "properties": {
    "iso:country":"CH",
    "sg:address":"Piazza San Pietro 5",
    "sg:city":"Ascona",
    "sg:orig_category":"Detailhandel mit Uhren U Schmuck",
    "sg:phone":"+41 91 792 12 65",
    "sg:postcode":"6612",
    "sg:province":"Ticino",
    "wof:name":"Carlo Sello Orefice",
    "wof:placetype":"venue"
},
  "geometry": {"coordinates":[8.7673711777,46.1548614502],"type":"Point"}
}