{
  "type": "Feature",
  "properties": {
    "iso:country":"CH",
    "sg:address":"Hausenstrasse 62a 3860 Meiringen. Postfach 595",
    "sg:city":"Meiringen",
    "sg:orig_category":"Autoreiseunternehmen",
    "sg:phone":"+41 33 971 30 30",
    "sg:postcode":"3860",
    "sg:province":"Bern",
    "wof:name":"Albert M\u00e4der Autoreisen",
    "wof:placetype":"venue"
},
  "geometry": {"coordinates":[8.169805,46.730148],"type":"Point"}
}