{
  "type": "Feature",
  "properties": {
    "iso:country":"CH",
    "sg:address":"Dorfstrasse 7",
    "sg:city":"Grosswangen",
    "sg:orig_category":"Detailhandel mit Fahrr\u00e4dern Detailhandel mit elektrischen Haushaltsger\u00e4ten",
    "sg:phone":"+41 41 980 18 51",
    "sg:postcode":"6022",
    "sg:province":"Luzern",
    "wof:name":"Josef Mehri Velos N\u00e4hmaschinen",
    "wof:placetype":"venue"
},
  "geometry": {"coordinates":[8.0480747223,47.1336593628],"type":"Point"}
}