{
  "type": "Feature",
  "properties": {
    "iso:country":"CH",
    "sg:address":"Geerenweg 11",
    "sg:city":"Bassersdorf",
    "sg:orig_category":"Politische Parteien CVP",
    "sg:phone":"+41 79 636 26 26",
    "sg:postcode":"8303",
    "sg:province":"Z\u00fcrich",
    "wof:name":"Cvp Ortspartei Bassersdorf",
    "wof:placetype":"venue"
},
  "geometry": {"coordinates":[8.6268730164,47.4431533813],"type":"Point"}
}