{
  "type": "Feature",
  "properties": {
    "iso:country":"CH",
    "sg:address":"Rue Jean-pelletier 6",
    "sg:city":"Ch\u00eane-bourg",
    "sg:orig_category":"Herstellung von Seifen, Wasch U Reinigungsmitteln",
    "sg:phone":"+41 22 349 83 64",
    "sg:postcode":"1225",
    "sg:province":"Gen\u00e8ve",
    "wof:name":"Ultratec, Grandjean-perrenoud-contesse Claude",
    "wof:placetype":"venue"
},
  "geometry": {"coordinates":[6.1936540604,46.1938514709],"type":"Point"}
}