{
  "type": "Feature",
  "properties": {
    "iso:country":"CH",
    "sg:address":"Rue Du Puits-godet 12a 2000 Neuch\u00e2tel. Postfach",
    "sg:city":"Neuenburg",
    "sg:orig_category":"Herstellung von optischen Instrumenten",
    "sg:phone":"+41 32 727 75 76",
    "sg:postcode":"2000",
    "sg:province":"Neuch\u00e2tel",
    "wof:name":"Biacore International Sa Instruments Analytiques, Pi\u00e8ces D\u00e9tach\u00e9es, Dans Le Dom. De La Technologie Biosensorielle D'optique Etc.; D\u00e9velopp., Fabr., Commercial.",
    "wof:placetype":"venue"
},
  "geometry": {"coordinates":[6.9125099182,46.9984054565],"type":"Point"}
}