{
  "type": "Feature",
  "properties": {
    "iso:country":"CH",
    "sg:address":"Henric Petri-strasse 15 4051 Basel. Postfach",
    "sg:city":"Basel",
    "sg:orig_category":"Pensionskassen",
    "sg:phone":"+41 61 272 18 18",
    "sg:postcode":"4051",
    "sg:province":"Basel-Stadt",
    "wof:name":"Vbg Vorsorgestiftung Birkh\u00e4user Gbc (bvg)",
    "wof:placetype":"venue"
},
  "geometry": {"coordinates":[7.5927071571,47.5520744324],"type":"Point"}
}