{
  "type": "Feature",
  "properties": {
    "iso:country":"CH",
    "sg:address":"Wehntalerstrasse 22",
    "sg:city":"Sch\u00f6fflisdorf",
    "sg:orig_category":"Detailhandel mit Sportartikeln",
    "sg:phone":"+41 18561375",
    "sg:postcode":"8165",
    "sg:province":"Z\u00fcrich",
    "wof:name":"Maria-klara Pfiffner Reitsportgesch\u00e4ft",
    "wof:placetype":"venue"
},
  "geometry": {"coordinates":[8.4152317047,47.49974823],"type":"Point"}
}