{
  "type": "Feature",
  "properties": {
    "iso:country":"CH",
    "sg:address":"Neugasse 116 8005 Z\u00fcrich. Postfach 830",
    "sg:city":"Z\u00fcrich",
    "sg:orig_category":"Satzherstellung U Reproduktion",
    "sg:phone":"+41 12714211",
    "sg:postcode":"8021",
    "sg:province":"Z\u00fcrich",
    "wof:name":"Lutz Repro Ag Fotolithos, Repros, Clich\u00e9s Usw; Herstellung, Vertrieb",
    "wof:placetype":"venue"
},
  "geometry": {"coordinates":[8.527204,47.383839],"type":"Point"}
}