{
  "type": "Feature",
  "properties": {
    "iso:country":"CH",
    "sg:address":"Avenue De La Sallaz 49 1010 Lausanne. Postfach",
    "sg:city":"Lausanne",
    "sg:orig_category":"Detailhandel mit Geschenkartikeln U Souvenirs",
    "sg:phone":"+41 21 652 90 76",
    "sg:postcode":"1010",
    "sg:province":"Vaud",
    "wof:name":"Christina Luzi Boutique Toison D'or",
    "wof:placetype":"venue"
},
  "geometry": {"coordinates":[6.6466779709,46.5328216553],"type":"Point"}
}