{
  "type": "Feature",
  "properties": {
    "iso:country":"CH",
    "sg:address":"2852",
    "sg:city":"Court\u00e9telle",
    "sg:orig_category":"Vereine Musik/Blasmusik",
    "sg:phone":"+41 32 423 52 20",
    "sg:postcode":"2852",
    "sg:province":"Jura",
    "wof:name":"Fanfare",
    "wof:placetype":"venue"
},
  "geometry": {"coordinates":[7.3167719841,47.3426017761],"type":"Point"}
}