{
  "type": "Feature",
  "properties": {
    "addr:full":"Schaffhauserstrasse 458 Z\u00fcrich Z\u00fcrich 8052",
    "addr:housenumber":"458",
    "addr:postcode":"8052",
    "addr:street":"Schaffhauserstrasse",
    "iso:country":"CH",
    "sg:address":"Schaffhauserstrasse 458",
    "sg:city":"Z\u00fcrich",
    "sg:orig_category":"Detailhandel mit Damenbekleidung",
    "sg:phone":"+41 13026780",
    "sg:postcode":"8052",
    "sg:province":"Z\u00fcrich",
    "wof:name":"Osvaldo Perdono Moda Miranda Textil-verkauf",
    "wof:placetype":"venue"
},
  "geometry": {"coordinates":[8.546911,47.418179],"type":"Point"}
}