{
  "type": "Feature",
  "properties": {
    "iso:country":"CH",
    "sg:address":"Quai Phillipe-godet 16",
    "sg:city":"Neuch\u00e2tel",
    "sg:classifiers":[
        {
            "category":"Restaurant",
            "type":"Food & Drink"
        }
    ],
    "sg:phone":"+41 32 724 42 32",
    "sg:postcode":"2000",
    "sg:province":"Neuch\u00e2tel",
    "wof:name":"Caf\u00e9 L'interlope",
    "wof:placetype":"venue"
},
  "geometry": {"coordinates":[6.9227399826,46.989440918],"type":"Point"}
}