{
  "type": "Feature",
  "properties": {
    "iso:country":"CH",
    "sg:address":"Via Collina 15",
    "sg:city":"Viganello",
    "sg:orig_category":"Allgemeiner Hoch U Tiefbau Hoch U Tiefbau",
    "sg:phone":"+41 91 971 14 67",
    "sg:postcode":"6962",
    "sg:province":"Ticino",
    "wof:name":"Romeo Gilardi",
    "wof:placetype":"venue"
},
  "geometry": {"coordinates":[8.970508,46.013233],"type":"Point"}
}