{
  "type": "Feature",
  "properties": {
    "iso:country":"CH",
    "sg:address":"Holunderweg 71 4500 Solothurn. Postfach",
    "sg:city":"Solothurn",
    "sg:orig_category":"Fachdetailhandel in Verkaufsr\u00e4umen",
    "sg:postcode":"4500",
    "sg:province":"Solothurn",
    "wof:name":"For Motion Trainingsger\u00e4te Gmbh Fitness Und Sportger\u00e4te; Handel",
    "wof:placetype":"venue"
},
  "geometry": {"coordinates":[7.5458049774,47.2030639648],"type":"Point"}
}