{
  "type": "Feature",
  "properties": {
    "iso:country":"CH",
    "sg:address":"Vierjuchartenweg 25",
    "sg:city":"Riehen",
    "sg:orig_category":"Bauingenieurb\u00fcros allgemein",
    "sg:phone":"+41 61 601 06 16",
    "sg:postcode":"4125",
    "sg:province":"Basel-Stadt",
    "wof:name":"Fritz Grenacher Ingenieurb\u00fcro",
    "wof:placetype":"venue"
},
  "geometry": {"coordinates":[7.64576,47.573711],"type":"Point"}
}