{
  "type": "Feature",
  "properties": {
    "iso:country":"CH",
    "sg:address":"Via Nassa 38",
    "sg:city":"Lugano",
    "sg:orig_category":"Advokaturb\u00fcros Notariate",
    "sg:phone":"+41 91 911 30 40",
    "sg:postcode":"6900",
    "sg:province":"Ticino",
    "wof:name":"Ghiringhelli Olgiati & Associati",
    "wof:placetype":"venue"
},
  "geometry": {"coordinates":[8.949476,46.00219],"type":"Point"}
}