{
  "type": "Feature",
  "properties": {
    "iso:country":"CH",
    "sg:address":"Via Borromini 11",
    "sg:city":"Vezia",
    "sg:orig_category":"Architektur U Ingenieurb\u00fcros",
    "sg:phone":"+41 91 966 93 84",
    "sg:postcode":"6943",
    "sg:province":"Ticino",
    "wof:name":"Armando Joss Studio D'ingegneria",
    "wof:placetype":"venue"
},
  "geometry": {"coordinates":[8.935469,46.019638],"type":"Point"}
}