{
  "type": "Feature",
  "properties": {
    "iso:country":"CH",
    "sg:address":"Fischerweg 8",
    "sg:city":"Basel",
    "sg:orig_category":"Grosshandel mit sonstigen Maschinen U Ausr\u00fcstungen f\u00fcr Industrie, Handel U Schiffahrt",
    "sg:phone":"+41 61 683 18 68",
    "sg:postcode":"4058",
    "sg:province":"Basel-Stadt",
    "wof:name":"Am Rhein Investment Gmbh",
    "wof:placetype":"venue"
},
  "geometry": {"coordinates":[7.6025261879,47.5580329895],"type":"Point"}
}