{
  "type": "Feature",
  "properties": {
    "iso:country":"CH",
    "sg:address":"Innere Gr\u00fctstrasse 4 6300 Zug. Postfach",
    "sg:city":"Zug",
    "sg:orig_category":"Reiseb\u00fcros U Reiseveranstalter",
    "sg:postcode":"6300",
    "sg:province":"Zug",
    "wof:name":"Grantourism Hotels & Resorts Service Ag Dienstleistungen, Marktstudien Im Zusammenhang Mit Touristischem Grundbesitz U. Hotels",
    "wof:placetype":"venue"
},
  "geometry": {"coordinates":[8.5169610977,47.1777954102],"type":"Point"}
}