{
  "type": "Feature",
  "properties": {
    "iso:country":"CH",
    "sg:address":"Hilti 10a",
    "sg:city":"Henggart",
    "sg:orig_category":"Reiseb\u00fcros U Reiseveranstalter",
    "sg:postcode":"8444",
    "sg:province":"Z\u00fcrich",
    "wof:name":"Edina Travel Reiseb\u00fcro S. Marti",
    "wof:placetype":"venue"
},
  "geometry": {"coordinates":[8.6847047806,47.5606689453],"type":"Point"}
}