{
  "type": "Feature",
  "properties": {
    "iso:country":"CH",
    "sg:address":"Industriestr. 22",
    "sg:city":"Zunzgen",
    "sg:classifiers":[
        {
            "category":"Home & Garden",
            "subcategory":"Furniture",
            "type":"Retail Goods"
        }
    ],
    "sg:phone":"+41 61 976 76 76",
    "sg:postcode":"4455",
    "sg:province":"Basel-Landschaft",
    "sg:tags":[
        "professional",
        "household",
        "wood"
    ],
    "wof:name":"Bemag Objekteinrichtungen Ag",
    "wof:placetype":"venue"
},
  "geometry": {"coordinates":[7.8097400665,47.4468612671],"type":"Point"}
}