{
  "type": "Feature",
  "properties": {
    "iso:country":"CH",
    "sg:address":"Industriestrasse",
    "sg:city":"Giswil",
    "sg:orig_category":"Unclassifiable Establishments",
    "sg:postcode":"6074",
    "sg:province":"Obwalden",
    "wof:name":"Enz Natursteine Ag",
    "wof:placetype":"venue"
},
  "geometry": {"coordinates":[8.1825437546,46.8419723511],"type":"Point"}
}