{
  "type": "Feature",
  "properties": {
    "iso:country":"CH",
    "sg:address":"Grundstrasse 11",
    "sg:city":"Ossingen",
    "sg:orig_category":"Detailhandel mit elektrischen Haushalts-,Radio U Fernsehger\u00e4ten sowie Musikinstrumenten",
    "sg:phone":"+41 41 342 18 12",
    "sg:postcode":"8475",
    "sg:province":"Z\u00fcrich",
    "wof:name":"Keysound B\u00fctler",
    "wof:placetype":"venue"
},
  "geometry": {"coordinates":[8.3035106659,46.9929122925],"type":"Point"}
}