{
  "type": "Feature",
  "properties": {
    "iso:country":"CH",
    "sg:address":"Bahnhofstrasse 27",
    "sg:city":"Oberuzwil",
    "sg:orig_category":"Instandhaltung U Reparatur von Automobilen",
    "sg:phone":"+41 79 642 30 61",
    "sg:postcode":"9242",
    "sg:province":"St. Gallen",
    "wof:name":"Ignaz Wyser Garage",
    "wof:placetype":"venue"
},
  "geometry": {"coordinates":[9.1256532669,47.4320068359],"type":"Point"}
}