{
  "type": "Feature",
  "properties": {
    "iso:country":"CH",
    "sg:address":"Avenue Weber 18 1208 Gen\u00e8ve. Postfach",
    "sg:city":"Gen\u00e8ve",
    "sg:orig_category":"Kauf U Verkauf von Immobilien auf eigene Rechnung Vermittlung von Immobilien",
    "sg:phone":"+41 22 736 42 23",
    "sg:postcode":"1208",
    "sg:province":"Gen\u00e8ve",
    "wof:name":"Agence Immobili\u00e8re, Quartier-dit-maire Maude",
    "wof:placetype":"venue"
},
  "geometry": {"coordinates":[6.162981987,46.198890686],"type":"Point"}
}