{
  "type": "Feature",
  "properties": {
    "iso:country":"CH",
    "sg:address":"Zurigo Via 25",
    "sg:city":"Lugano",
    "sg:orig_category":"K\u00fcnstlerische U schriftstellerische T\u00e4tigkeiten U Darbietungen",
    "sg:phone":"+41 91 921 47 32",
    "sg:postcode":"6900",
    "sg:province":"Ticino",
    "wof:name":"Ars Labor Di Christina Otth Taha Nafei",
    "wof:placetype":"venue"
},
  "geometry": {"coordinates":[8.9519052505,46.0116462708],"type":"Point"}
}