{
  "type": "Feature",
  "properties": {
    "iso:country":"CH",
    "sg:address":"Principale Route 53",
    "sg:city":"Vicques",
    "sg:orig_category":"Wirtschaftspr\u00fcfung, Steuerberatung U Treuhand",
    "sg:phone":"+41 32 435 65 40",
    "sg:postcode":"2824",
    "sg:province":"Jura",
    "wof:name":"G Fidu, Voisard G\u00e9rard",
    "wof:placetype":"venue"
},
  "geometry": {"coordinates":[7.4168448448,47.3490600586],"type":"Point"}
}