{
  "type": "Feature",
  "properties": {
    "iso:country":"CH",
    "sg:address":"Rue De Longeau 10",
    "sg:city":"Biel/bienne",
    "sg:classifiers":[
        {
            "category":"Manufacturing",
            "subcategory":"Printing",
            "type":"Manufacturing & Wholesale Goods"
        }
    ],
    "sg:phone":"+41 32 342 49 61",
    "sg:postcode":"2504",
    "sg:province":"Bern",
    "sg:tags":[
        "house",
        "book"
    ],
    "wof:name":"Anderegg Guenin Sa",
    "wof:placetype":"venue"
},
  "geometry": {"coordinates":[7.289642,47.162567],"type":"Point"}
}