{
  "type": "Feature",
  "properties": {
    "iso:country":"CH",
    "sg:address":"Bahnhofstrasse 102",
    "sg:city":"Aarau",
    "sg:orig_category":"Sonstige Unterhaltung",
    "sg:phone":"+41 62 823 94 03",
    "sg:postcode":"5000",
    "sg:province":"Aargau",
    "wof:name":"Herzass.ch Atelier Delirius",
    "wof:placetype":"venue"
},
  "geometry": {"coordinates":[8.0541172028,47.3928031921],"type":"Point"}
}