{
  "type": "Feature",
  "properties": {
    "iso:country":"CH",
    "sg:address":"Anton Graff-strasse 17",
    "sg:city":"Winterthur",
    "sg:orig_category":"Herstellung von Datenverarbeitungsger\u00e4ten U einrichtungen Herstellung von elektronischen Bauelemente",
    "sg:phone":"+41 52 202 02 21",
    "sg:postcode":"8400",
    "sg:province":"Z\u00fcrich",
    "wof:name":"System-clinch Internet Services Gmbh",
    "wof:placetype":"venue"
},
  "geometry": {"coordinates":[8.7155981064,47.4987373352],"type":"Point"}
}