{
  "type": "Feature",
  "properties": {
    "iso:country":"CH",
    "sg:address":"Altweg 12",
    "sg:city":"Frauenfeld",
    "sg:orig_category":"Allgemeiner Hoch U Tiefbau",
    "sg:phone":"+41 71 688 41 65",
    "sg:postcode":"8500",
    "sg:province":"Thurgau",
    "wof:name":"Budget Haus Ag",
    "wof:placetype":"venue"
},
  "geometry": {"coordinates":[8.893426,47.554909],"type":"Point"}
}