{
  "type": "Feature",
  "properties": {
    "iso:country":"CH",
    "sg:address":"Nordringstrasse 15 4702 Oensingen. Postfach",
    "sg:city":"Oensingen",
    "sg:orig_category":"Herstellung U Zusammensetzung von Uhren Herstellung von Uhren",
    "sg:phone":"+41 32 957 66 66",
    "sg:postcode":"4702",
    "sg:province":"Solothurn",
    "wof:name":"Aubry Fr\u00e8res Sa",
    "wof:placetype":"venue"
},
  "geometry": {"coordinates":[6.9546117783,47.2242927551],"type":"Point"}
}