{
  "type": "Feature",
  "properties": {
    "iso:country":"CH",
    "sg:address":"Rehweidstrasse 11",
    "sg:city":"Oberuzwil",
    "sg:orig_category":"Gesundheitswesen",
    "sg:phone":"+41 71 950 09 60",
    "sg:postcode":"9242",
    "sg:province":"St. Gallen",
    "wof:name":"Locher Annamaria Malatelier",
    "wof:placetype":"venue"
},
  "geometry": {"coordinates":[9.1225185394,47.4337615967],"type":"Point"}
}