{
  "type": "Feature",
  "properties": {
    "iso:country":"CH",
    "sg:address":"Sinserstrasse 15",
    "sg:city":"Auw",
    "sg:classifiers":[
        {
            "category":"Restaurant",
            "type":"Food & Drink"
        }
    ],
    "sg:phone":"+41 56 668 13 53",
    "sg:postcode":"5644",
    "sg:province":"Aargau",
    "wof:name":"Restaurant Linde",
    "wof:placetype":"venue"
},
  "geometry": {"coordinates":[8.3669281006,47.209941864],"type":"Point"}
}