{
  "type": "Feature",
  "properties": {
    "iso:country":"CH",
    "sg:address":"Avenue Des Alpes 88",
    "sg:city":"Neuch\u00e2tel",
    "sg:orig_category":"Detektivb\u00fcros U \u00dcberwachung",
    "sg:phone":"+41 32 724 69 52",
    "sg:postcode":"2000",
    "sg:province":"Neuch\u00e2tel",
    "wof:name":"Val\u00e9ry Huguelet Securipro Agce De S\u00e9curit\u00e9",
    "wof:placetype":"venue"
},
  "geometry": {"coordinates":[6.919192791,46.9946136475],"type":"Point"}
}