{
  "type": "Feature",
  "properties": {
    "iso:country":"CH",
    "sg:address":"Marktgasse 12",
    "sg:city":"Basel",
    "sg:orig_category":"Herstellung von Kakao, Schokoladeerzeugnissen U Zuckerwaren",
    "sg:phone":"+41 61 261 36 35",
    "sg:postcode":"4051",
    "sg:province":"Basel-Stadt",
    "wof:name":"Tea-room Hans Nussberger",
    "wof:placetype":"venue"
},
  "geometry": {"coordinates":[7.5869932175,47.558971405],"type":"Point"}
}