{
  "type": "Feature",
  "properties": {
    "iso:country":"CH",
    "sg:address":"Hofstrasse 20",
    "sg:city":"Uznach",
    "sg:orig_category":"Architektur U Ingenieurb\u00fcros Architekturb\u00fcros",
    "sg:phone":"+41 55 210 06 00",
    "sg:postcode":"8730",
    "sg:province":"St. Gallen",
    "wof:name":"Reto Eleganti Architekturb\u00fcro",
    "wof:placetype":"venue"
},
  "geometry": {"coordinates":[8.977266,47.229244],"type":"Point"}
}