{
  "type": "Feature",
  "properties": {
    "iso:country":"CH",
    "sg:address":"Gotthardstrasse",
    "sg:city":"G\u00f6schenen",
    "sg:classifiers":[
        {
            "category":"Travel",
            "subcategory":"Hotels & Motels",
            "type":"Entertainment"
        }
    ],
    "sg:phone":"+41 41 885 12 63",
    "sg:postcode":"6487",
    "sg:province":"Uri",
    "sg:tags":[
        "hotels",
        "mit",
        "restaurant"
    ],
    "wof:name":"Hotel Gotthard",
    "wof:placetype":"venue"
},
  "geometry": {"coordinates":[8.5877485275,46.6632766724],"type":"Point"}
}