{
  "type": "Feature",
  "properties": {
    "addr:full":"B\u00e4rengasse 16 Z\u00fcrich Z\u00fcrich 8010",
    "addr:housenumber":"16",
    "addr:postcode":"8010",
    "addr:street":"Baerengasse",
    "iso:country":"CH",
    "sg:address":"B\u00e4rengasse 16",
    "sg:city":"Z\u00fcrich",
    "sg:classifiers":[
        {
            "category":"Banks & Credit Unions",
            "subcategory":"Bank",
            "type":"Services"
        }
    ],
    "sg:postcode":"8010",
    "sg:province":"Z\u00fcrich",
    "wof:name":"Sbsi Holding Ltd",
    "wof:placetype":"venue"
},
  "geometry": {"coordinates":[8.9513,46.002972],"type":"Point"}
}