{
  "type": "Feature",
  "properties": {
    "iso:country":"CH",
    "sg:address":"P\u00fcnt 6",
    "sg:city":"Winkel",
    "sg:orig_category":"Unclassifiable Establishments",
    "sg:phone":"+41 18444193",
    "sg:postcode":"8185",
    "sg:province":"Z\u00fcrich",
    "wof:name":"Z-trans Zimmermann Transporte Mittels Kipper-lkw",
    "wof:placetype":"venue"
},
  "geometry": {"coordinates":[8.4077510834,47.4464225769],"type":"Point"}
}