{
  "type": "Feature",
  "properties": {
    "iso:country":"CH",
    "sg:address":"Dorfstrasse 2 3054 Sch\u00fcpfen. Postfach 99",
    "sg:city":"Sch\u00fcpfen",
    "sg:orig_category":"Architektur U Ingenieurb\u00fcros Architekturb\u00fcros",
    "sg:phone":"+41 19105454",
    "sg:postcode":"3054",
    "sg:province":"Bern",
    "wof:name":"Gerhard Zachs Architekturb\u00fcro",
    "wof:placetype":"venue"
},
  "geometry": {"coordinates":[8.588322,47.30883],"type":"Point"}
}