{
  "type": "Feature",
  "properties": {
    "iso:country":"CH",
    "sg:address":"Schmiedweg 6 3013 Bern. Postfach",
    "sg:city":"Bern",
    "sg:orig_category":"Erbringung von Dienstleistungen f\u00fcr Unternehmen",
    "sg:postcode":"3013",
    "sg:province":"Bern",
    "wof:name":"Wenger Zurfl\u00fch Gestaltungen Gmbh Gestaltungen, Bes. Ausstellungs, Schaufenster, Laden, B\u00fchne, Raumgestaltung, Usw; Entwurf, Planung, Ausf\u00fchrung U. Beratung",
    "wof:placetype":"venue"
},
  "geometry": {"coordinates":[7.4440221786,46.9582138062],"type":"Point"}
}