{
  "type": "Feature",
  "properties": {
    "iso:country":"CH",
    "sg:address":"Grand-champsec Avenue Du 51",
    "sg:city":"Sion",
    "sg:orig_category":"Vermietung U Verpachtung von eigenen Immobilien",
    "sg:phone":"+41 27 203 39 17",
    "sg:postcode":"1950",
    "sg:province":"Valais",
    "wof:name":"Inter Promotion Sa Sion-vissigen.",
    "wof:placetype":"venue"
},
  "geometry": {"coordinates":[7.3827610016,46.2329750061],"type":"Point"}
}