{
  "type": "Feature",
  "properties": {
    "iso:country":"CH",
    "sg:address":"Viale A. Volta 16",
    "sg:city":"Chiasso",
    "sg:orig_category":"Grosshandel mit Textilien",
    "sg:phone":"+41 91 682 14 59",
    "sg:postcode":"6830",
    "sg:province":"Ticino",
    "wof:name":"Solaris Establishment, Vaduz, Succursale Di Chiasso",
    "wof:placetype":"venue"
},
  "geometry": {"coordinates":[9.0336503983,45.8352546692],"type":"Point"}
}