{
  "type": "Feature",
  "properties": {
    "addr:full":"B\u00fcrglistrasse 4 Z\u00fcrich Z\u00fcrich 8002",
    "addr:housenumber":"4",
    "addr:postcode":"8002",
    "addr:street":"Buerglistrasse",
    "iso:country":"CH",
    "sg:address":"B\u00fcrglistrasse 4",
    "sg:city":"Z\u00fcrich",
    "sg:orig_category":"Datenbanken",
    "sg:postcode":"8002",
    "sg:province":"Z\u00fcrich",
    "wof:name":"Getreal Ag",
    "wof:placetype":"venue"
},
  "geometry": {"coordinates":[8.528597,47.363773],"type":"Point"}
}