{
  "type": "Feature",
  "properties": {
    "iso:country":"CH",
    "sg:address":"Sempacherstrasse 30",
    "sg:city":"Z\u00fcrich",
    "sg:orig_category":"Reiseb\u00fcros",
    "sg:phone":"+41 14220659",
    "sg:postcode":"8032",
    "sg:province":"Z\u00fcrich",
    "wof:name":"Die Abreise Ag",
    "wof:placetype":"venue"
},
  "geometry": {"coordinates":[8.5673360825,47.3618202209],"type":"Point"}
}