{
  "type": "Feature",
  "properties": {
    "iso:country":"CH",
    "sg:address":"Gartenstrasse 5",
    "sg:city":"Uster",
    "sg:orig_category":"Detailhandel mit Uhren U Schmuck Kunsthandel",
    "sg:phone":"+41 19416149",
    "sg:postcode":"8610",
    "sg:province":"Z\u00fcrich",
    "wof:name":"Gabriela Hausmann Sibler Schmuck Kunsthandel",
    "wof:placetype":"venue"
},
  "geometry": {"coordinates":[8.7125616074,47.3519287109],"type":"Point"}
}