{
  "type": "Feature",
  "properties": {
    "iso:country":"CH",
    "sg:address":"Mattenstrasse 44",
    "sg:city":"Biel/bienne",
    "sg:orig_category":"Sonstiger Fachdetailhandel in Verkaufsr\u00e4umen Sonstiger Grosshandel",
    "sg:phone":"+41 22 781 41 18",
    "sg:postcode":"2503",
    "sg:province":"Bern",
    "wof:name":"Shaman Gmbh",
    "wof:placetype":"venue"
},
  "geometry": {"coordinates":[7.2492609024,47.1337623596],"type":"Point"}
}