{
  "type": "Feature",
  "properties": {
    "iso:country":"CH",
    "sg:address":"Freihofstrasse 11 8942 Oberrieden. Postfach 124",
    "sg:city":"Oberrieden",
    "sg:orig_category":"Geb\u00e4ude, Wohnungsreinigung",
    "sg:phone":"+41 17203377",
    "sg:postcode":"8942",
    "sg:province":"Z\u00fcrich",
    "wof:name":"Amd Geb\u00e4udemanagement",
    "wof:placetype":"venue"
},
  "geometry": {"coordinates":[8.5759143829,47.2751312256],"type":"Point"}
}