{
  "type": "Feature",
  "properties": {
    "addr:full":"Avenue Des Planches 23 Montreux Vaud 1820",
    "addr:housenumber":"23",
    "addr:postcode":"1820",
    "addr:street":"Avenue Des Planches",
    "iso:country":"CH",
    "sg:address":"Avenue Des Planches 23",
    "sg:city":"Montreux",
    "sg:orig_category":"Architekturb\u00fcros",
    "sg:phone":"+41 21 965 29 15",
    "sg:postcode":"1820",
    "sg:province":"Vaud",
    "wof:name":"Pierre Vincent Sa Atelier D'architecture",
    "wof:placetype":"venue"
},
  "geometry": {"coordinates":[6.913185,46.430828],"type":"Point"}
}