{
  "type": "Feature",
  "properties": {
    "iso:country":"CH",
    "sg:address":"Hans H\u00e4ssig-strasse 19",
    "sg:city":"Aarau",
    "sg:orig_category":"Vorschulen, Kinderg\u00e4rten",
    "sg:postcode":"5000",
    "sg:province":"Aargau",
    "wof:name":"St\u00e4dtischer Kindergarten Binzenhof I & Ii",
    "wof:placetype":"venue"
},
  "geometry": {"coordinates":[8.0486431122,47.3795394897],"type":"Point"}
}