{
  "type": "Feature",
  "properties": {
    "iso:country":"CH",
    "sg:address":"Zentralstrasse 18",
    "sg:city":"Z\u00fcrich",
    "sg:orig_category":"Detailhandel mit elektrischen Haushalts-,Radio U Fernsehger\u00e4ten sowie Musikinstrumenten Detailhandel",
    "sg:phone":"+41 14514411",
    "sg:postcode":"8003",
    "sg:province":"Z\u00fcrich",
    "wof:name":"H. Gelbert Inh.g.luchsinger Pfaff-n\u00e4hmaschinen",
    "wof:placetype":"venue"
},
  "geometry": {"coordinates":[8.520316124,47.3711204529],"type":"Point"}
}