{
  "type": "Feature",
  "properties": {
    "iso:country":"CH",
    "sg:address":"Chemin Du Grand-puits 38",
    "sg:city":"Meyrin",
    "sg:orig_category":"Herstellung von Elektromotoren, Generatoren U Transformatoren Mechanische Werkst\u00e4tten",
    "sg:phone":"+41 22 785 80 12",
    "sg:postcode":"1217",
    "sg:province":"Gen\u00e8ve",
    "wof:name":"Claude Pasche Moteurs \u00e9lectriques",
    "wof:placetype":"venue"
},
  "geometry": {"coordinates":[6.0751681328,46.2254486084],"type":"Point"}
}