{
  "type": "Feature",
  "properties": {
    "iso:country":"CH",
    "sg:address":"Obere Kirchzelg 27",
    "sg:city":"Wettingen",
    "sg:orig_category":"Arbeitnehmerverb\u00e4nde",
    "sg:phone":"+41 56 426 35 02",
    "sg:postcode":"5430",
    "sg:province":"Aargau",
    "wof:name":"Christl.holz-& Bauarbeiter- Verb.sekt.baden,hansruedi Frei",
    "wof:placetype":"venue"
},
  "geometry": {"coordinates":[8.330585,47.468441],"type":"Point"}
}