{
  "type": "Feature",
  "properties": {
    "iso:country":"CH",
    "sg:address":"Engerfeldstrasse 18",
    "sg:city":"Rheinfelden",
    "sg:orig_category":"Bezirks, Sekundar, Realschulen, Oberstufe der Primarschulen",
    "sg:phone":"+41 61 836 86 25",
    "sg:postcode":"4310",
    "sg:province":"Aargau",
    "wof:name":"Realschule Engerfeld",
    "wof:placetype":"venue"
},
  "geometry": {"coordinates":[7.800933,47.548443],"type":"Point"}
}