{
  "type": "Feature",
  "properties": {
    "iso:country":"CH",
    "sg:address":"Gundeldingerstrasse 129",
    "sg:city":"Basel",
    "sg:orig_category":"Markt U Meinungsforschung",
    "sg:phone":"+41 61 363 38 80",
    "sg:postcode":"4053",
    "sg:province":"Basel-Stadt",
    "wof:name":"Js Agentur F\u00fcr Direct-marketing Scherrer J\u00fcrg",
    "wof:placetype":"venue"
},
  "geometry": {"coordinates":[7.5866699219,47.5422897339],"type":"Point"}
}