{
  "type": "Feature",
  "properties": {
    "iso:country":"CH",
    "sg:address":"G\u00e9n\u00e9ral-guisan Av. Du 46",
    "sg:city":"Freiburg",
    "sg:orig_category":"Non-Classified Establishments",
    "sg:postcode":"1700",
    "sg:province":"Fribourg",
    "wof:name":"Cardoso Nettoyages",
    "wof:placetype":"venue"
},
  "geometry": {"coordinates":[7.1466040611,46.8111572266],"type":"Point"}
}