{
  "type": "Feature",
  "properties": {
    "iso:country":"CH",
    "sg:address":"Augustinergasse 44",
    "sg:city":"Z\u00fcrich",
    "sg:orig_category":"Detailhandel mit Metallwaren, Anstrichmitteln, Glaswaren, Bau U Heimwerkerbedarf",
    "sg:phone":"+41 12123326",
    "sg:postcode":"8001",
    "sg:province":"Z\u00fcrich",
    "wof:name":"Anthra Norell Ag Innovative Technologien O. Deren Anwendung; Entw.",
    "wof:placetype":"venue"
},
  "geometry": {"coordinates":[8.5388832092,47.3723831177],"type":"Point"}
}