{
  "type": "Feature",
  "properties": {
    "iso:country":"CH",
    "sg:address":"6915",
    "sg:city":"Pambio-noranco",
    "sg:orig_category":"Vermietung U Verpachtung von eigenen Immobilien",
    "sg:postcode":"6915",
    "sg:province":"Ticino",
    "wof:name":"Canvera 2 Sa",
    "wof:placetype":"venue"
},
  "geometry": {"coordinates":[8.9308004379,45.979850769],"type":"Point"}
}