{
  "type": "Feature",
  "properties": {
    "addr:full":"Chemin Jules-ed.-gottret 12 Veyrier Gen\u00e8ve 1255",
    "addr:housenumber":"12",
    "addr:postcode":"1255",
    "addr:street":"Chemin Jules-Ed.-Gottret",
    "iso:country":"CH",
    "sg:address":"Chemin Jules-ed.-gottret 12",
    "sg:city":"Veyrier",
    "sg:orig_category":"Bauschreinerei Herstellung von M\u00f6beln verschiedener Art",
    "sg:phone":"+41 22 784 17 48",
    "sg:postcode":"1255",
    "sg:province":"Gen\u00e8ve",
    "wof:name":"Maurice Gottret Eb\u00e9nisterie",
    "wof:placetype":"venue"
},
  "geometry": {"coordinates":[6.185165,46.166382],"type":"Point"}
}