{
  "type": "Feature",
  "properties": {
    "iso:country":"CH",
    "sg:address":"Weidstrasse 5",
    "sg:city":"Freienbach",
    "sg:orig_category":"Softwareentwicklung U beratung",
    "sg:postcode":"8807",
    "sg:province":"Schwyz",
    "wof:name":"Rkcp Kn\u00fcssi Rolf",
    "wof:placetype":"venue"
},
  "geometry": {"coordinates":[8.7725896835,47.1959114075],"type":"Point"}
}