{
  "type": "Feature",
  "properties": {
    "iso:country":"CH",
    "sg:address":"Rue De La Gare 25",
    "sg:city":"B\u00f4le",
    "sg:orig_category":"Arztpraxen",
    "sg:phone":"+41 32 842 21 21",
    "sg:postcode":"2014",
    "sg:province":"Neuch\u00e2tel",
    "wof:name":"Dr M\u00e9d. Jean-marc Pessina M\u00e9decin G\u00e9n\u00e9raliste Fmh",
    "wof:placetype":"venue"
},
  "geometry": {"coordinates":[6.838141,46.968464],"type":"Point"}
}