{
  "type": "Feature",
  "properties": {
    "iso:country":"CH",
    "sg:address":"Kaffeegasse 13a",
    "sg:city":"Altnau",
    "sg:orig_category":"Sonstige mit der Informatik verbundene T\u00e4tigkeiten",
    "sg:postcode":"8595",
    "sg:province":"Thurgau",
    "wof:name":"K-automation Kloter",
    "wof:placetype":"venue"
},
  "geometry": {"coordinates":[8.3336191177,47.5209083557],"type":"Point"}
}