{
  "type": "Feature",
  "properties": {
    "iso:country":"CH",
    "sg:address":"Bachstrasse 22",
    "sg:city":"Herisau",
    "sg:orig_category":"Schlossereien Schmieden",
    "sg:phone":"+41 71 351 23 42",
    "sg:postcode":"9100",
    "sg:province":"Appenzell Ausserrhoden",
    "wof:name":"Hans Frei Schmiede & Schlosserei",
    "wof:placetype":"venue"
},
  "geometry": {"coordinates":[9.2815847397,47.386806488],"type":"Point"}
}