{
  "type": "Feature",
  "properties": {
    "iso:country":"CH",
    "sg:address":"Sonnenbergstrasse 35",
    "sg:city":"Jona",
    "sg:orig_category":"Tierarztpraxis",
    "sg:phone":"+41 33 654 36 44",
    "sg:postcode":"8645",
    "sg:province":"St. Gallen",
    "wof:name":"Dr. Med. Vet. Rudolf Lehnherr Tierarzt",
    "wof:placetype":"venue"
},
  "geometry": {"coordinates":[7.7022619247,46.6592292786],"type":"Point"}
}