{
  "type": "Feature",
  "properties": {
    "iso:country":"CH",
    "sg:address":"Zentrum 1 5452 Oberrohrdorf. Postfach",
    "sg:city":"Oberrohrdorf",
    "sg:orig_category":"Regionalbanken U Sparkassen",
    "sg:phone":"+41 56 485 99 00",
    "sg:postcode":"5452",
    "sg:province":"Aargau",
    "wof:name":"Hypothekarbank Lenzburg",
    "wof:placetype":"venue"
},
  "geometry": {"coordinates":[8.3168039322,47.4192733765],"type":"Point"}
}