{
  "type": "Feature",
  "properties": {
    "iso:country":"CH",
    "sg:address":"Breitacker 188 5505 Brunegg Case Postale",
    "sg:city":"Gen\u00e8ve",
    "sg:orig_category":"Detailhandel mit Bekleidung",
    "sg:phone":"+41 62 887 35 35",
    "sg:postcode":"1204",
    "sg:province":"Gen\u00e8ve",
    "wof:name":"C&a Mode Brenninkmeijer & Cie",
    "wof:placetype":"venue"
},
  "geometry": {"coordinates":[8.220568,47.422295],"type":"Point"}
}