{
  "type": "Feature",
  "properties": {
    "iso:country":"CH",
    "sg:address":"Rhonesandstrasse 11",
    "sg:city":"Brig",
    "sg:orig_category":"Detailhandel mit Bekleidung",
    "sg:phone":"+41 27 924 47 70",
    "sg:postcode":"3900",
    "sg:province":"Valais",
    "wof:name":"Boutique Avventura Four Seasons Textil Sa",
    "wof:placetype":"venue"
},
  "geometry": {"coordinates":[7.989461,46.317795],"type":"Point"}
}