{
  "type": "Feature",
  "properties": {
    "iso:country":"CH",
    "sg:address":"Fabrikweg 3",
    "sg:city":"Bellach",
    "sg:orig_category":"Interessenvertretungen",
    "sg:postcode":"4512",
    "sg:province":"Solothurn",
    "wof:name":"Stiftung Islamische Glaubensgemeinschaft, Bremgarten",
    "wof:placetype":"venue"
},
  "geometry": {"coordinates":[8.3492832184,47.3556938171],"type":"Point"}
}