{
  "type": "Feature",
  "properties": {
    "iso:country":"CH",
    "sg:address":"Marais Chemin Des 162 1255 Veyrier. Postfach",
    "sg:city":"Veyrier",
    "sg:orig_category":"Wohnheime",
    "sg:postcode":"1255",
    "sg:province":"Gen\u00e8ve",
    "wof:name":"Association De L'ems R\u00e9sidence Les Pervenches",
    "wof:placetype":"venue"
},
  "geometry": {"coordinates":[6.1358880997,46.1871795654],"type":"Point"}
}