{
  "type": "Feature",
  "properties": {
    "iso:country":"CH",
    "sg:address":"Rigistrasse 33",
    "sg:city":"Baar",
    "sg:orig_category":"Vermietung U Verpachtung von eigenen Immobilien",
    "sg:postcode":"6340",
    "sg:province":"Zug",
    "wof:name":"Terg Immobilien Ag",
    "wof:placetype":"venue"
},
  "geometry": {"coordinates":[8.5312252045,47.1922035217],"type":"Point"}
}