{
  "type": "Feature",
  "properties": {
    "iso:country":"CH",
    "sg:address":"T\u00f6distrasse 2",
    "sg:city":"Hombrechtikon",
    "sg:orig_category":"Maschinen-Fabrikation",
    "sg:phone":"+41 55 244 26 66",
    "sg:postcode":"8634",
    "sg:province":"Z\u00fcrich",
    "wof:name":"Brack Technik",
    "wof:placetype":"venue"
},
  "geometry": {"coordinates":[8.7815408707,47.254573822],"type":"Point"}
}