{
  "type": "Feature",
  "properties": {
    "iso:country":"CH",
    "sg:address":"St\u00e4nzlergasse 3 4051 Basel. Postfach",
    "sg:city":"Basel",
    "sg:orig_category":"Allgemeiner Hoch U Tiefbau Handelsvermittlung U Grosshandel",
    "sg:phone":"+41 61 281 01 09",
    "sg:postcode":"4011",
    "sg:province":"Basel-Stadt",
    "wof:name":"Pss Projects Ag",
    "wof:placetype":"venue"
},
  "geometry": {"coordinates":[7.589029,47.552853],"type":"Point"}
}