{
  "type": "Feature",
  "properties": {
    "iso:country":"CH",
    "sg:address":"Erlenwiesenstrasse 2",
    "sg:city":"Volketswil",
    "sg:orig_category":"Grosshandel mit sonstigen Maschinen U Ausr\u00fcstungen f\u00fcr Industrie, Handel U Schiffahrt",
    "sg:phone":"+41 19475500",
    "sg:postcode":"8604",
    "sg:province":"Z\u00fcrich",
    "wof:name":"Tomra Ag",
    "wof:placetype":"venue"
},
  "geometry": {"coordinates":[8.675444603,47.3782577515],"type":"Point"}
}