{
  "type": "Feature",
  "properties": {
    "iso:country":"CH",
    "sg:address":"Gellertstrasse 224 4052 Basel. Postfach",
    "sg:city":"Basel",
    "sg:orig_category":"Abbruch U Sprenggewerbe Erdbewegungsarbeiten",
    "sg:phone":"+41 61 319 50 50",
    "sg:postcode":"4028",
    "wof:name":"Musfeld Ag Aushub Abbruch & Transporte",
    "wof:placetype":"venue"
},
  "geometry": {"coordinates":[7.61881,47.543934],"type":"Point"}
}