{
  "type": "Feature",
  "properties": {
    "iso:country":"CH",
    "sg:address":"Chemin Du Grand-puits 40",
    "sg:city":"Meyrin",
    "sg:orig_category":"Pulvermetallurgie Schmieden, Pressen, Stanzen U Profilwalzen von Metallen Stahl U Leichtmetallbau",
    "sg:phone":"+41 22 783 03 00",
    "sg:postcode":"1217",
    "sg:province":"Gen\u00e8ve",
    "wof:name":"Givindustrie Sa",
    "wof:placetype":"venue"
},
  "geometry": {"coordinates":[6.0749001503,46.2251319885],"type":"Point"}
}