{
  "type": "Feature",
  "properties": {
    "iso:country":"CH",
    "sg:address":"1568",
    "sg:city":"Portalban",
    "sg:orig_category":"Sonstiger spezialisierter Hoch U Tiefbau",
    "sg:phone":"+41 26 677 12 40",
    "sg:postcode":"1568",
    "sg:province":"Fribourg",
    "wof:name":"Sansonnens Fr\u00e8res, Entreprise De Constructions",
    "wof:placetype":"venue"
},
  "geometry": {"coordinates":[6.9551901817,46.9181594849],"type":"Point"}
}