{
  "type": "Feature",
  "properties": {
    "iso:country":"CH",
    "sg:address":"Brauereistrasse 1",
    "sg:city":"Schaffhausen",
    "sg:orig_category":"Non-Classified Establishments",
    "sg:phone":"+41 52 633 08 88",
    "sg:postcode":"8200",
    "sg:province":"Schaffhausen",
    "wof:name":"Iff Media Ag",
    "wof:placetype":"venue"
},
  "geometry": {"coordinates":[8.6429071426,47.7102890015],"type":"Point"}
}