{
  "type": "Feature",
  "properties": {
    "iso:country":"CH",
    "sg:address":"In Der P\u00fcnt 4",
    "sg:city":"Tagelswangen",
    "sg:orig_category":"Technische B\u00fcros Hoch-& Tiefbau",
    "sg:phone":"+41 52 343 60 80",
    "sg:postcode":"8317",
    "sg:province":"Z\u00fcrich",
    "wof:name":"Entwurf-& Planungsb\u00fcro Ronald Tanner",
    "wof:placetype":"venue"
},
  "geometry": {"coordinates":[8.6740913391,47.4292869568],"type":"Point"}
}