{
  "type": "Feature",
  "properties": {
    "iso:country":"CH",
    "sg:address":"Rue Du Tilleul 13",
    "sg:city":"St-blaise",
    "sg:orig_category":"RESTAURANTS: TEA-ROOMS",
    "sg:phone":"+41 32 753 73 83",
    "sg:postcode":"2072",
    "sg:province":"Neuch\u00e2tel",
    "wof:name":"Restaurant Le Tilleul Saint-blaise S\u00e0rl",
    "wof:placetype":"venue"
},
  "geometry": {"coordinates":[6.9897418022,47.0159034729],"type":"Point"}
}