{
  "type": "Feature",
  "properties": {
    "iso:country":"CH",
    "sg:address":"Blumenweg 6",
    "sg:city":"Jegenstorf",
    "sg:orig_category":"Bauschreinerei",
    "sg:phone":"+41 81 416 40 60",
    "sg:postcode":"3303",
    "sg:province":"Bern",
    "wof:name":"Ernst Pfister Schreinerei",
    "wof:placetype":"venue"
},
  "geometry": {"coordinates":[9.83625,46.803555],"type":"Point"}
}