{
  "type": "Feature",
  "properties": {
    "iso:country":"CH",
    "sg:address":"Bernard Avenue De Grand-st- 34",
    "sg:city":"Martigny",
    "sg:orig_category":"Non-Classified Establishments",
    "sg:postcode":"1920",
    "sg:province":"Valais",
    "wof:name":"Fazit Beratung & Treuhand Ag",
    "wof:placetype":"venue"
},
  "geometry": {"coordinates":[7.524810791,47.1698150635],"type":"Point"}
}