{
  "type": "Feature",
  "properties": {
    "iso:country":"CH",
    "sg:address":"Route De La Versoix 1",
    "sg:city":"Mont-sur-rolle",
    "sg:orig_category":"Bauschreinerei Herstellung von Konstruktionsteilen, Fertigbauteilen U Ausbauelementen aus Holz",
    "sg:phone":"+41 21 825 21 88",
    "sg:postcode":"1185",
    "sg:province":"Vaud",
    "wof:name":"Jean-pierre Pache Charpente & Menuiserie",
    "wof:placetype":"venue"
},
  "geometry": {"coordinates":[6.339516,46.470413],"type":"Point"}
}