{
  "type": "Feature",
  "properties": {
    "iso:country":"CH",
    "sg:address":"Biberiststrasse 16",
    "sg:city":"Solothurn",
    "sg:orig_category":"Finanzierungsinstitutionen",
    "sg:postcode":"4500",
    "sg:province":"Solothurn",
    "wof:name":"Basilisk Gmbh",
    "wof:placetype":"venue"
},
  "geometry": {"coordinates":[7.5422000885,47.2021827698],"type":"Point"}
}