{
  "type": "Feature",
  "properties": {
    "iso:country":"CH",
    "sg:address":"Via Motta 58",
    "sg:city":"Massagno",
    "sg:orig_category":"Ingenieurb\u00fcros Kultur",
    "sg:phone":"+41 91 966 15 04",
    "sg:postcode":"6900",
    "sg:province":"Ticino",
    "wof:name":"Diego Scala Studio D'ingegnere",
    "wof:placetype":"venue"
},
  "geometry": {"coordinates":[8.9455404282,46.0123634338],"type":"Point"}
}