{
  "type": "Feature",
  "properties": {
    "iso:country":"CH",
    "sg:address":"Nassenwilerstrasse 3",
    "sg:city":"Niederhasli",
    "sg:classifiers":[
        {
            "category":"Education",
            "subcategory":"Library",
            "type":"Public Place"
        }
    ],
    "sg:phone":"+41 18510412",
    "sg:postcode":"8155",
    "sg:province":"Z\u00fcrich",
    "sg:tags":[
        "u",
        "bibliotheken",
        "archive"
    ],
    "wof:name":"Bibliothek Schulhaus Rossacker",
    "wof:placetype":"venue"
},
  "geometry": {"coordinates":[8.484956,47.479706],"type":"Point"}
}