{
  "type": "Feature",
  "properties": {
    "iso:country":"CH",
    "sg:address":"Rue De La Croix-d'or 6 1200 Genf. Postfach",
    "sg:city":"Gen\u00e8ve",
    "sg:orig_category":"Finanzierungsinstitutionen",
    "sg:phone":"+41 22 310 25 00",
    "sg:postcode":"1201",
    "sg:province":"Gen\u00e8ve",
    "wof:name":"Vision Capital (europe) S\u00e0rl",
    "wof:placetype":"venue"
},
  "geometry": {"coordinates":[6.0753159523,46.1682472229],"type":"Point"}
}