{
  "type": "Feature",
  "properties": {
    "iso:country":"CH",
    "sg:address":"Hirzbrunnenschanze 42",
    "sg:city":"Basel",
    "sg:orig_category":"Wohnheime",
    "sg:postcode":"4058",
    "sg:province":"Basel-Stadt",
    "wof:name":"Stiftung Zum Gr\u00fcnen Helm",
    "wof:placetype":"venue"
},
  "geometry": {"coordinates":[7.6163301468,47.5666732788],"type":"Point"}
}