{
  "type": "Feature",
  "properties": {
    "iso:country":"CH",
    "sg:address":"Boulevard De Grancy 51",
    "sg:city":"Lausanne",
    "sg:classifiers":[
        {
            "category":"Restaurant",
            "type":"Food & Drink"
        }
    ],
    "sg:phone":"+41 32 968 15 98",
    "sg:postcode":"1006",
    "sg:province":"Vaud",
    "wof:name":"Dany's Bar",
    "wof:placetype":"venue"
},
  "geometry": {"coordinates":[6.8319129944,47.1047821045],"type":"Point"}
}