{
  "type": "Feature",
  "properties": {
    "iso:country":"CH",
    "sg:address":"Palaz Zi",
    "sg:city":"Payerne",
    "sg:orig_category":"Instandhaltung U Reparatur von Automobilen",
    "sg:phone":"+41 79 247 36 32",
    "sg:postcode":"1530",
    "sg:province":"Vaud",
    "wof:name":"Garage Chollet",
    "wof:placetype":"venue"
},
  "geometry": {"coordinates":[6.9332609177,46.8231887817],"type":"Point"}
}