{
  "type": "Feature",
  "properties": {
    "iso:country":"CH",
    "sg:address":"Konradstrasse 31 4600 Olten. Postfach 1106",
    "sg:city":"Olten",
    "sg:orig_category":"Advokaturb\u00fcros",
    "sg:phone":"+41 62 212 46 46",
    "sg:postcode":"4603",
    "sg:province":"Solothurn",
    "wof:name":"Dr.peter Wyss Advokatur-& Notariatsb\u00fcro",
    "wof:placetype":"venue"
},
  "geometry": {"coordinates":[7.899418,47.350388],"type":"Point"}
}