{
  "type": "Feature",
  "properties": {
    "iso:country":"CH",
    "sg:address":"Rue Des Moulins 3 1400 Yverdon-les-bains Case Postale 578",
    "sg:city":"Yverdon",
    "sg:orig_category":"Detailhandel mit Sportartikeln Grosshandel mit Tabakwaren",
    "sg:phone":"+41 24 425 44 62",
    "sg:postcode":"1401",
    "sg:province":"Vaud",
    "wof:name":"Tallichet Robert",
    "wof:placetype":"venue"
},
  "geometry": {"coordinates":[6.6372160912,46.779083252],"type":"Point"}
}