{
  "type": "Feature",
  "properties": {
    "iso:country":"CH",
    "sg:address":"Witimatte",
    "sg:city":"Lauterbrunnen",
    "sg:orig_category":"Zimmerei, Dachdeckerei, Bauspenglerei U Abdichtung",
    "sg:phone":"+41 33 855 19 26",
    "sg:postcode":"3822",
    "sg:province":"Bern",
    "wof:name":"Von Allmen + Bossard Ag",
    "wof:placetype":"venue"
},
  "geometry": {"coordinates":[7.9129180908,46.5918273926],"type":"Point"}
}