{
  "type": "Feature",
  "properties": {
    "iso:country":"CH",
    "sg:address":"Kasimir-pfyffer-strasse 26 6003 Luzern. Postfach 26",
    "sg:city":"Luzern",
    "sg:orig_category":"Polizei",
    "sg:phone":"+41 41 248 81 17",
    "sg:postcode":"6002",
    "sg:province":"Luzern",
    "wof:name":"Polizeikommando Des Kantons Luzern & Kantonspolizei",
    "wof:placetype":"venue"
},
  "geometry": {"coordinates":[8.3001031876,47.0482330322],"type":"Point"}
}