{
  "type": "Feature",
  "properties": {
    "iso:country":"CH",
    "sg:address":"7076",
    "sg:city":"Parpan",
    "sg:orig_category":"Detailhandel mit Zeitungen U Zeitschriften Kioske",
    "sg:phone":"+41 81 382 23 84",
    "sg:postcode":"7076",
    "sg:province":"Graubunden",
    "wof:name":"Andreina Monsch Kiosk Am Skilift Heimberg",
    "wof:placetype":"venue"
},
  "geometry": {"coordinates":[9.5574197769,46.7601356506],"type":"Point"}
}