{
  "type": "Feature",
  "properties": {
    "iso:country":"CH",
    "sg:address":"R\u00f6tistrasse 4",
    "sg:city":"Feldbrunnen",
    "sg:orig_category":"Aktivit\u00e4ten der Generalunternehmen im Baugewerbe Allgemeiner Hoch U Tiefbau",
    "sg:postcode":"4532",
    "sg:province":"Solothurn",
    "wof:name":"Abp Ag",
    "wof:placetype":"venue"
},
  "geometry": {"coordinates":[7.555892,47.220165],"type":"Point"}
}