{
  "type": "Feature",
  "properties": {
    "iso:country":"CH",
    "sg:address":"Biberiststrasse 1",
    "sg:city":"Solothurn",
    "sg:classifiers":[
        {
            "category":"Restaurant",
            "type":"Food & Drink"
        }
    ],
    "sg:phone":"+41 32 622 14 43",
    "sg:postcode":"4500",
    "sg:province":"Solothurn",
    "wof:name":"Caf\u00e9-restaurant Tivoli",
    "wof:placetype":"venue"
},
  "geometry": {"coordinates":[7.5405220985,47.202709198],"type":"Point"}
}