{
  "type": "Feature",
  "properties": {
    "iso:country":"CH",
    "sg:address":"Brandisstrasse 8",
    "sg:city":"Chur",
    "sg:orig_category":"Gesundheitswesen",
    "sg:phone":"+41 81 253 69 09",
    "sg:postcode":"7000",
    "sg:province":"Graubunden",
    "wof:name":"Physiotherapie Derungs-hieber Ursula",
    "wof:placetype":"venue"
},
  "geometry": {"coordinates":[9.5340461731,46.854221344],"type":"Point"}
}