{
  "type": "Feature",
  "properties": {
    "iso:country":"CH",
    "sg:address":"H\u00e4rdlistrasse 17",
    "sg:city":"Spreitenbach",
    "sg:orig_category":"Grosshandel mit B\u00fcromaschinen Grosshandel mit Datenverarbeitungsger\u00e4ten",
    "sg:phone":"+41 56 483 04 00",
    "sg:postcode":"8957",
    "sg:province":"Aargau",
    "wof:name":"Pc Net Ag Lan/wan Netzwerke",
    "wof:placetype":"venue"
},
  "geometry": {"coordinates":[8.2934951782,47.4474258423],"type":"Point"}
}