{
  "type": "Feature",
  "properties": {
    "iso:country":"CH",
    "sg:address":"Talstrasse 42",
    "sg:city":"Etzgen",
    "sg:classifiers":[
        {
            "category":"Restaurant",
            "type":"Food & Drink"
        }
    ],
    "sg:phone":"+41 62 875 11 06",
    "sg:postcode":"5275",
    "sg:province":"Aargau",
    "wof:name":"Restaurant National",
    "wof:placetype":"venue"
},
  "geometry": {"coordinates":[8.1109628677,47.5694351196],"type":"Point"}
}