{
  "type": "Feature",
  "properties": {
    "iso:country":"CH",
    "sg:address":"Hauptstrasse 15",
    "sg:city":"Bilten",
    "sg:orig_category":"Nationale Postdienste",
    "sg:phone":"+41 58 615 23 05",
    "sg:postcode":"8865",
    "sg:province":"Glarus",
    "wof:name":"Die Schweizerische Post",
    "wof:placetype":"venue"
},
  "geometry": {"coordinates":[9.0220813751,47.1481246948],"type":"Point"}
}