{
  "type": "Feature",
  "properties": {
    "iso:country":"CH",
    "sg:address":"Pfarrhaus",
    "sg:city":"Bennwil",
    "sg:orig_category":"Jugendorganisationen",
    "sg:phone":"+41 41 630 13 14",
    "sg:postcode":"4431",
    "sg:province":"Basel-Landschaft",
    "wof:name":"Jungmannschaft",
    "wof:placetype":"venue"
},
  "geometry": {"coordinates":[8.3093471527,46.9918365479],"type":"Point"}
}