{
  "type": "Feature",
  "properties": {
    "iso:country":"CH",
    "sg:address":"Rue Micheli-du-crest 11bis",
    "sg:city":"Gen\u00e8ve",
    "sg:orig_category":"Detailhandel mit Blumen U Pflanzen",
    "sg:phone":"+41 17642014",
    "sg:postcode":"1205",
    "sg:province":"Gen\u00e8ve",
    "wof:name":"Susanne Kehrli Maroff Blumengesch\u00e4ft",
    "wof:placetype":"venue"
},
  "geometry": {"coordinates":[8.533178,47.244781],"type":"Point"}
}