{
  "type": "Feature",
  "properties": {
    "iso:country":"CH",
    "sg:address":"Melchnaustrasse 4",
    "sg:city":"Madiswil",
    "sg:orig_category":"Mechanische Werkst\u00e4tten",
    "sg:phone":"+41 31 879 05 29",
    "sg:postcode":"4934",
    "sg:province":"Bern",
    "wof:name":"Daniel Gimelli Mechanische Werkst\u00e4tte",
    "wof:placetype":"venue"
},
  "geometry": {"coordinates":[7.4280018806,47.0776824951],"type":"Point"}
}