{
  "type": "Feature",
  "properties": {
    "iso:country":"CH",
    "sg:address":"Untere Winkelstrasse 2 5304 Endingen. Postfach",
    "sg:city":"Endingen",
    "sg:orig_category":"Herstellung von Konstruktionsteilen, Fertigbauteilen U Ausbauelementen aus Holz",
    "sg:phone":"+41 56 242 12 18",
    "sg:postcode":"5304",
    "sg:province":"Aargau",
    "wof:name":"Theodor B\u00e4chli, Dipl. Schreinermeister, Beratungen Und Verwaltungen",
    "wof:placetype":"venue"
},
  "geometry": {"coordinates":[8.2909736633,47.5392608643],"type":"Point"}
}