{
  "type": "Feature",
  "properties": {
    "addr:full":"Sch\u00fctzenweg 2d Thusis Graubunden 7430",
    "addr:postcode":"7430",
    "iso:country":"CH",
    "sg:address":"Sch\u00fctzenweg 2d",
    "sg:city":"Thusis",
    "sg:orig_category":"Bestattungswesen",
    "sg:phone":"+41 32 968 22 64",
    "sg:postcode":"7430",
    "sg:province":"Graubunden",
    "wof:name":"W\u00e4lti Arnold.",
    "wof:placetype":"venue"
},
  "geometry": {"coordinates":[6.825428,47.106026],"type":"Point"}
}