{
  "type": "Feature",
  "properties": {
    "iso:country":"CH",
    "sg:address":"Chemin Des Terrasses 1",
    "sg:city":"Morges",
    "sg:orig_category":"Zahnarztpraxen",
    "sg:phone":"+41 21 801 98 83",
    "sg:postcode":"1110",
    "sg:province":"Vaud",
    "wof:name":"Dr M\u00e9d.dent. Bernard Meillaud M\u00e9decin-dentiste",
    "wof:placetype":"venue"
},
  "geometry": {"coordinates":[6.4924721718,46.5120124817],"type":"Point"}
}