{
  "type": "Feature",
  "properties": {
    "iso:country":"CH",
    "sg:address":"Via Ung\u00e8",
    "sg:city":"Torricella",
    "sg:orig_category":"Sportvereine Ballsport Tischtennis",
    "sg:phone":"+41 91 682 02 82",
    "sg:postcode":"6808",
    "sg:province":"Ticino",
    "wof:name":"Stt Chiasso",
    "wof:placetype":"venue"
},
  "geometry": {"coordinates":[9.0169630051,45.8472824097],"type":"Point"}
}