{
  "type": "Feature",
  "properties": {
    "iso:country":"CH",
    "sg:address":"Paradiesweg 9 4710 Balsthal. Postfach",
    "sg:city":"Balsthal",
    "sg:orig_category":"Architektur U Ingenieurb\u00fcros",
    "sg:postcode":"4710",
    "sg:province":"Solothurn",
    "wof:name":"Buxtorf Roland",
    "wof:placetype":"venue"
},
  "geometry": {"coordinates":[7.686485,47.316635],"type":"Point"}
}