{
  "type": "Feature",
  "properties": {
    "iso:country":"CH",
    "sg:address":"Landstrasse 35",
    "sg:city":"Itingen",
    "sg:classifiers":[
        {
            "category":"Restaurant",
            "type":"Food & Drink"
        }
    ],
    "sg:phone":"+41 61 971 64 09",
    "sg:postcode":"4452",
    "sg:province":"Basel-Landschaft",
    "wof:name":"Restaurant Ochsen",
    "wof:placetype":"venue"
},
  "geometry": {"coordinates":[7.7843108177,47.4672431946],"type":"Point"}
}