{
  "type": "Feature",
  "properties": {
    "iso:country":"CH",
    "sg:address":"Langmattweg 7",
    "sg:city":"Mellingen",
    "sg:orig_category":"Maler U Glasergewerbe Malerei",
    "sg:phone":"+41 56 491 11 69",
    "sg:postcode":"5507",
    "sg:province":"Aargau",
    "wof:name":"Huber & Co",
    "wof:placetype":"venue"
},
  "geometry": {"coordinates":[8.2741928101,47.4152870178],"type":"Point"}
}