{
  "type": "Feature",
  "properties": {
    "iso:country":"CH",
    "sg:address":"Solothurnstrasse 50",
    "sg:city":"Biberist",
    "sg:orig_category":"Instandhaltung U Reparatur von Automobilen",
    "sg:phone":"+41 56 621 00 01",
    "sg:postcode":"4562",
    "sg:province":"Solothurn",
    "wof:name":"Auto K\u00e4ppeli Ag",
    "wof:placetype":"venue"
},
  "geometry": {"coordinates":[8.2615947723,47.3514137268],"type":"Point"}
}