{
  "type": "Feature",
  "properties": {
    "iso:country":"CH",
    "sg:address":"Seilerstrasse 27",
    "sg:city":"Bern",
    "sg:orig_category":"Advokaturb\u00fcros",
    "sg:phone":"+41 31 381 32 52",
    "sg:postcode":"3011",
    "sg:province":"Bern",
    "wof:name":"Tobias Winzeler Advokatur & Umweltschutzfragen",
    "wof:placetype":"venue"
},
  "geometry": {"coordinates":[7.434663,46.945183],"type":"Point"}
}