{
  "type": "Feature",
  "properties": {
    "iso:country":"CH",
    "sg:address":"Dieni",
    "sg:city":"Rueras",
    "sg:orig_category":"Sessellifte and Skilifte",
    "sg:phone":"+41 81 949 19 38",
    "sg:postcode":"7189",
    "sg:province":"Graubunden",
    "wof:name":"Bergbahnen Sedrun/rueras Ag",
    "wof:placetype":"venue"
},
  "geometry": {"coordinates":[8.7463703156,46.6724586487],"type":"Point"}
}