{
  "type": "Feature",
  "properties": {
    "iso:country":"CH",
    "sg:address":"Geissgasse 17",
    "sg:city":"Frick",
    "sg:orig_category":"D\u00fcngemittel Grosshandel Herstellung von Werkzeugen",
    "sg:phone":"+41 62 871 81 87",
    "sg:postcode":"5070",
    "sg:province":"Aargau",
    "wof:name":"Arbovitis, Handel Und Gutachten, Erb Martin",
    "wof:placetype":"venue"
},
  "geometry": {"coordinates":[8.0221967697,47.5051078796],"type":"Point"}
}