{
  "type": "Feature",
  "properties": {
    "iso:country":"CH",
    "sg:address":"Stationsstrasse 11",
    "sg:city":"Br\u00fcttisellen",
    "sg:orig_category":"Zahnarztpraxen",
    "sg:phone":"+41 18333708",
    "sg:postcode":"8306",
    "sg:province":"Z\u00fcrich",
    "wof:name":"Dr. Med. Dent. Wolfgang Buder Zahnarzt",
    "wof:placetype":"venue"
},
  "geometry": {"coordinates":[8.6290779114,47.420085907],"type":"Point"}
}