{
  "type": "Feature",
  "properties": {
    "iso:country":"CH",
    "sg:address":"Oberdorfstrasse 19",
    "sg:city":"Arch",
    "sg:orig_category":"Detailhandel mit Brot, Back U S\u00fcsswaren",
    "sg:phone":"+41 32 679 24 72",
    "sg:postcode":"3296",
    "sg:province":"Bern",
    "wof:name":"Archer Beck Confiserie Tr\u00fcffly",
    "wof:placetype":"venue"
},
  "geometry": {"coordinates":[7.430883,47.164974],"type":"Point"}
}