{
  "type": "Feature",
  "properties": {
    "iso:country":"CH",
    "sg:address":"Kirchgasse 10 3860 Meiringen. Postfach 260",
    "sg:city":"Meiringen",
    "sg:orig_category":"Sanit\u00e4r, Heizungs U L\u00fcftungsinstallation Sanit\u00e4rinstallation",
    "sg:phone":"+41 33 971 52 74",
    "sg:postcode":"3860",
    "sg:province":"Bern",
    "wof:name":"Blumenthal A. Ag",
    "wof:placetype":"venue"
},
  "geometry": {"coordinates":[8.187754631,46.7277755737],"type":"Point"}
}