{
  "type": "Feature",
  "properties": {
    "iso:country":"CH",
    "sg:address":"Feldeggstrasse 38",
    "sg:city":"Z\u00fcrich",
    "sg:orig_category":"Non-Classified Establishments",
    "sg:phone":"+41 14221718",
    "sg:postcode":"8008",
    "sg:province":"Z\u00fcrich",
    "wof:name":"Vm Finance & Holdings Ag",
    "wof:placetype":"venue"
},
  "geometry": {"coordinates":[8.55119133,47.3600273132],"type":"Point"}
}