{
  "type": "Feature",
  "properties": {
    "iso:country":"CH",
    "sg:address":"Lindenhofstrasse 8",
    "sg:city":"Worblaufen",
    "sg:orig_category":"Geb\u00e4ude, Wohnungsreinigung",
    "sg:phone":"+41 31 921 91 81",
    "sg:postcode":"3048",
    "sg:province":"Bern",
    "wof:name":"Bekim Saiti Bs Reinigungen",
    "wof:placetype":"venue"
},
  "geometry": {"coordinates":[7.4599409103,46.979724884],"type":"Point"}
}