{
  "type": "Feature",
  "properties": {
    "iso:country":"CH",
    "sg:address":"Schwertstrasse 4",
    "sg:city":"Schaffhausen",
    "sg:orig_category":"Drogerien",
    "sg:phone":"+41 52 625 71 50",
    "sg:postcode":"8200",
    "sg:province":"Schaffhausen",
    "wof:name":"Hofer Drogerie Ag",
    "wof:placetype":"venue"
},
  "geometry": {"coordinates":[8.633067131,47.697303772],"type":"Point"}
}