{
  "type": "Feature",
  "properties": {
    "iso:country":"CH",
    "sg:address":"Rue De La Gare 11 1860 Aigle Case Postale 443",
    "sg:city":"Aigle",
    "sg:orig_category":"Elektroinstallation",
    "sg:phone":"+41 79 355 40 40",
    "sg:postcode":"1860",
    "sg:province":"Vaud",
    "wof:name":"Battilotti S\u00e0rl",
    "wof:placetype":"venue"
},
  "geometry": {"coordinates":[6.5807981491,46.5382385254],"type":"Point"}
}