{
  "type": "Feature",
  "properties": {
    "iso:country":"CH",
    "sg:address":"Bvd Jaques Dalcroze 5",
    "sg:city":"Gen\u00e8ve",
    "sg:classifiers":[
        {
            "category":"Banks & Credit Unions",
            "subcategory":"Bank",
            "type":"Services"
        }
    ],
    "sg:phone":"+41 22 787 11 11",
    "sg:postcode":"1211",
    "sg:province":"Gen\u00e8ve",
    "wof:name":"Banque Bruxelles Lambert",
    "wof:placetype":"venue"
},
  "geometry": {"coordinates":[6.15334,46.200806],"type":"Point"}
}