{
  "type": "Feature",
  "properties": {
    "iso:country":"CH",
    "sg:address":"Pr\u00e9s Rue Des 126",
    "sg:city":"Biel/bienne",
    "sg:orig_category":"Sonstiger Grosshandel",
    "sg:postcode":"2503",
    "sg:province":"Bern",
    "wof:name":"Murat Market S\u00e0rl",
    "wof:placetype":"venue"
},
  "geometry": {"coordinates":[7.2634902,47.1304397583],"type":"Point"}
}