{
  "type": "Feature",
  "properties": {
    "iso:country":"CH",
    "sg:address":"Rue Vers-croix 1",
    "sg:city":"Chamoson",
    "sg:classifiers":[
        {
            "category":"Banks & Credit Unions",
            "subcategory":"Bank",
            "type":"Services"
        }
    ],
    "sg:phone":"+41 27 306 30 63",
    "sg:postcode":"1955",
    "sg:province":"Valais",
    "wof:name":"Cr\u00e9dit Suisse",
    "wof:placetype":"venue"
},
  "geometry": {"coordinates":[7.22492,46.199787],"type":"Point"}
}