{
  "type": "Feature",
  "properties": {
    "iso:country":"CH",
    "sg:address":"Glis",
    "sg:city":"Brig",
    "sg:orig_category":"Interessenvertretungen",
    "sg:postcode":"3900",
    "sg:province":"Valais",
    "wof:name":"Vecko Genossenschaftsverband Bessere Bedingungen F\u00fcr Die Mitglieder Usw",
    "wof:placetype":"venue"
},
  "geometry": {"coordinates":[7.9876461029,46.3158912659],"type":"Point"}
}