{
  "type": "Feature",
  "properties": {
    "iso:country":"CH",
    "sg:address":"Bodenackerstrasse 10",
    "sg:city":"Breitenbach",
    "sg:classifiers":[
        {
            "category":"Restaurant",
            "type":"Food & Drink"
        }
    ],
    "sg:phone":"+41 61 781 41 45",
    "sg:postcode":"4226",
    "sg:province":"Solothurn",
    "wof:name":"Restaurant S'z\u00e4ni",
    "wof:placetype":"venue"
},
  "geometry": {"coordinates":[7.5446839333,47.4052619934],"type":"Point"}
}