{
  "type": "Feature",
  "properties": {
    "iso:country":"CH",
    "sg:address":"Circonvallazione Via 37",
    "sg:city":"Ascona",
    "sg:orig_category":"Institutionen des Sozialwesens ohne Beherbergung",
    "sg:postcode":"6612",
    "sg:province":"Ticino",
    "wof:name":"Associazione African Smile",
    "wof:placetype":"venue"
},
  "geometry": {"coordinates":[8.7729539871,46.1533241272],"type":"Point"}
}