{
  "type": "Feature",
  "properties": {
    "iso:country":"CH",
    "sg:address":"Obere Kirchstrasse 42 8304 Wallisellen. Postfach 661",
    "sg:city":"Wallisellen",
    "sg:orig_category":"Grosshandel mit Geschenkartikeln U Souvenirs Grosshandel mit Uhren",
    "sg:phone":"+41 18310055",
    "sg:postcode":"8304",
    "sg:province":"Z\u00fcrich",
    "wof:name":"Avap Anzeigenvertretung F\u00fcr Ausl\u00e4ndische Publikationen Hanspeter Iff.",
    "wof:placetype":"venue"
},
  "geometry": {"coordinates":[8.5980739594,47.4175071716],"type":"Point"}
}