{
  "type": "Feature",
  "properties": {
    "iso:country":"CH",
    "sg:address":"Grossm\u00fcnsterplatz 8",
    "sg:city":"Z\u00fcrich",
    "sg:orig_category":"Interessenvertretungen",
    "sg:postcode":"8001",
    "sg:province":"Z\u00fcrich",
    "wof:name":"Erbengemeinschaft Gutscher-christ Johannes Und Meie",
    "wof:placetype":"venue"
},
  "geometry": {"coordinates":[9.2849197388,47.1935806274],"type":"Point"}
}