{
  "type": "Feature",
  "properties": {
    "iso:country":"CH",
    "sg:address":"Lenzhardstrasse 2",
    "sg:city":"Rupperswil",
    "sg:orig_category":"Geb\u00e4ude, Wohnungsreinigung",
    "sg:phone":"+41 79 330 60 36",
    "sg:postcode":"5102",
    "sg:province":"Aargau",
    "wof:name":"Paul L\u00fcthi Reinigungsinstitut",
    "wof:placetype":"venue"
},
  "geometry": {"coordinates":[8.1294050217,47.399433136],"type":"Point"}
}