{
  "type": "Feature",
  "properties": {
    "iso:country":"CH",
    "sg:address":"7554",
    "sg:city":"Sent",
    "sg:orig_category":"Sportvereine Sch\u00fctzen",
    "sg:phone":"+41 13624255",
    "sg:postcode":"7554",
    "sg:province":"Graubunden",
    "wof:name":"Sch\u00fctzenverein",
    "wof:placetype":"venue"
},
  "geometry": {"coordinates":[8.6840496063,47.300491333],"type":"Point"}
}