{
  "type": "Feature",
  "properties": {
    "iso:country":"CH",
    "sg:address":"K\u00f6nizstrasse 70",
    "sg:city":"Bern",
    "sg:orig_category":"Detailhandel mit Geschenkartikeln U Souvenirs",
    "sg:phone":"+41 31 381 98 89",
    "sg:postcode":"3008",
    "sg:province":"Bern",
    "wof:name":"Valerie Bolliger Boutique Brown-corner",
    "wof:placetype":"venue"
},
  "geometry": {"coordinates":[7.4183769226,46.940738678],"type":"Point"}
}