{
  "type": "Feature",
  "properties": {
    "iso:country":"CH",
    "sg:address":"Grundstrasse 18",
    "sg:city":"Rotkreuz",
    "sg:orig_category":"Informatikdienste",
    "sg:phone":"+41 41 799 50 80",
    "sg:postcode":"6343",
    "sg:province":"Zug",
    "wof:name":"Vitress Ag",
    "wof:placetype":"venue"
},
  "geometry": {"coordinates":[8.4306993484,47.14610672],"type":"Point"}
}