{
  "type": "Feature",
  "properties": {
    "iso:country":"CH",
    "sg:address":"In Der Fadmatt 86",
    "sg:city":"Urdorf",
    "sg:orig_category":"Unternehmensberatung",
    "sg:phone":"+41 17340038",
    "sg:postcode":"8902",
    "sg:province":"Z\u00fcrich",
    "wof:name":"H\u00f6dl Manfred Unternehmensberatung Gmbh",
    "wof:placetype":"venue"
},
  "geometry": {"coordinates":[8.427904129,47.383644104],"type":"Point"}
}