{
  "type": "Feature",
  "properties": {
    "iso:country":"CH",
    "sg:address":"Friedheimweg 17",
    "sg:city":"Weggis",
    "sg:orig_category":"Massagestudios",
    "sg:phone":"+41 41 390 00 48",
    "sg:postcode":"6353",
    "sg:province":"Luzern",
    "wof:name":"Laurent Fankhauser Massagen",
    "wof:placetype":"venue"
},
  "geometry": {"coordinates":[8.42116642,47.0320396423],"type":"Point"}
}