{
  "type": "Feature",
  "properties": {
    "iso:country":"CH",
    "sg:address":"Ahornweg 3",
    "sg:city":"Oftringen",
    "sg:orig_category":"Vorschulen, Kinderg\u00e4rten",
    "sg:phone":"+41 62 797 09 39",
    "sg:postcode":"4665",
    "sg:province":"Aargau",
    "wof:name":"Kindergarten K\u00fcngoldingen",
    "wof:placetype":"venue"
},
  "geometry": {"coordinates":[7.9429788589,47.3031578064],"type":"Point"}
}