{
  "type": "Feature",
  "properties": {
    "iso:country":"CH",
    "sg:address":"Vi 377",
    "sg:city":"Scuol",
    "sg:orig_category":"Vermietung U Verpachtung von eigenen Immobilien",
    "sg:postcode":"7550",
    "sg:province":"Graubunden",
    "wof:name":"Bauprodukte Ag",
    "wof:placetype":"venue"
},
  "geometry": {"coordinates":[10.2981033325,46.7979888916],"type":"Point"}
}