{
  "type": "Feature",
  "properties": {
    "iso:country":"CH",
    "sg:address":"Bahnhofstr. Oey.",
    "sg:city":"Diemtigen",
    "sg:orig_category":"Grosshandel mit Getr\u00e4nken",
    "sg:postcode":"3754",
    "sg:province":"Bern",
    "wof:name":"Fritz R\u00fcfenacht",
    "wof:placetype":"venue"
},
  "geometry": {"coordinates":[7.5645580292,46.648235321],"type":"Point"}
}