{
  "type": "Feature",
  "properties": {
    "iso:country":"CH",
    "sg:address":"T\u00e4fernstrasse 28",
    "sg:city":"D\u00e4ttwil",
    "sg:classifiers":[
        {
            "category":"Manufacturing",
            "subcategory":"Soap",
            "type":"Manufacturing & Wholesale Goods"
        }
    ],
    "sg:phone":"+41 56 493 24 24",
    "sg:postcode":"5405",
    "sg:province":"Aargau",
    "sg:tags":[
        "cream"
    ],
    "wof:name":"Puig (suisse) S.a.",
    "wof:placetype":"venue"
},
  "geometry": {"coordinates":[8.294716,47.446819],"type":"Point"}
}