{
  "type": "Feature",
  "properties": {
    "addr:full":"Chemin Du Tr\u00e9si 3 Pr\u00e9verenges Vaud 1028",
    "addr:housenumber":"3",
    "addr:postcode":"1028",
    "addr:street":"Chemin Du Tre\u0301Si",
    "iso:country":"CH",
    "sg:address":"Chemin Du Tr\u00e9si 3",
    "sg:city":"Pr\u00e9verenges",
    "sg:orig_category":"Allgemeiner Hoch U Tiefbau Bauingenieurb\u00fcros Industriebau",
    "sg:phone":"+41 21 802 82 00",
    "sg:postcode":"1028",
    "sg:province":"Vaud",
    "wof:name":"Ami Assainissement Et Maintenance Industrielle Sa",
    "wof:placetype":"venue"
},
  "geometry": {"coordinates":[6.528915,46.522739],"type":"Point"}
}