{
  "type": "Feature",
  "properties": {
    "iso:country":"CH",
    "sg:address":"Johann-renfer-strasse 56",
    "sg:city":"Biel/bienne",
    "sg:classifiers":[
        {
            "category":"Building & Trades",
            "subcategory":"Construction",
            "type":"Services"
        }
    ],
    "sg:phone":"+41 32 341 88 28",
    "sg:postcode":"2504",
    "sg:province":"Bern",
    "sg:tags":[
        "installation",
        "air-conditioning",
        "system"
    ],
    "wof:name":"Racine + Berger Klima Ag",
    "wof:placetype":"venue"
},
  "geometry": {"coordinates":[7.287443,47.157318],"type":"Point"}
}