{
  "type": "Feature",
  "properties": {
    "iso:country":"CH",
    "sg:address":"Kantonsstrasse 115",
    "sg:city":"Freienbach",
    "sg:orig_category":"Autogaragen",
    "sg:phone":"+41 55 410 75 85",
    "sg:postcode":"8807",
    "sg:province":"Schwyz",
    "wof:name":"Ulrich F\u00fcglistaler Ag Garage",
    "wof:placetype":"venue"
},
  "geometry": {"coordinates":[8.758243,47.205616],"type":"Point"}
}