{
  "type": "Feature",
  "properties": {
    "iso:country":"CH",
    "sg:address":"Ittigenstrasse 4c",
    "sg:city":"Ittigen",
    "sg:orig_category":"Allgemeiner Hoch U Tiefbau Strassenbau",
    "sg:phone":"+41 71 911 84 10",
    "sg:postcode":"3063",
    "sg:province":"Bern",
    "wof:name":"Wellauer H. Ag Wil Sg",
    "wof:placetype":"venue"
},
  "geometry": {"coordinates":[9.05483,47.471012],"type":"Point"}
}