{
  "type": "Feature",
  "properties": {
    "iso:country":"CH",
    "sg:address":"Zehntentrottenstrasse 1 8708 M\u00e4nnedorf. Postfach",
    "sg:city":"St\u00e4fa",
    "sg:orig_category":"Architektur U Ingenieurb\u00fcros",
    "sg:postcode":"8712",
    "sg:province":"Z\u00fcrich",
    "wof:name":"Arti Architektur, Schneider L. Architektur- U. Planungsb\u00fcro. Geologische Haus- U. Grundst\u00fcckuntersuchungen Usw",
    "wof:placetype":"venue"
},
  "geometry": {"coordinates":[8.689456,47.254154],"type":"Point"}
}