{
  "type": "Feature",
  "properties": {
    "iso:country":"CH",
    "sg:address":"Albe 3930 Visp. Postfach",
    "sg:city":"Visp",
    "sg:orig_category":"G\u00fcterbef\u00f6rderung im Strassenverkehr",
    "sg:phone":"+41 27 946 31 86",
    "sg:postcode":"3930",
    "sg:province":"Valais",
    "wof:name":"Pius Zenh\u00e4usern Transporte",
    "wof:placetype":"venue"
},
  "geometry": {"coordinates":[7.8316178322,46.2912826538],"type":"Point"}
}