{
  "type": "Feature",
  "properties": {
    "iso:country":"CH",
    "sg:address":"Hauptstrasse 417",
    "sg:city":"Hirschthal",
    "sg:orig_category":"Erbringung von sonstigen Dienstleistungen f\u00fcr Unterhaltung, Erholung U Freizeit",
    "sg:postcode":"5042",
    "sg:province":"Aargau",
    "wof:name":"K\u00fcnstler & Konzert Agentur Petrowall, M. Petrovic",
    "wof:placetype":"venue"
},
  "geometry": {"coordinates":[8.0527610779,47.3178138733],"type":"Point"}
}