{
  "type": "Feature",
  "properties": {
    "iso:country":"CH",
    "sg:address":"Bernstrasse 6 3114 Oberwichtrach. Postfach 261",
    "sg:city":"Oberwichtrach",
    "sg:orig_category":"Detailhandel mit Brot, Back U S\u00fcsswaren",
    "sg:phone":"+41 31 781 09 51",
    "sg:postcode":"3114",
    "sg:province":"Bern",
    "wof:name":"Walter & Therese Bruderer B\u00e4ckerei & Konditorei",
    "wof:placetype":"venue"
},
  "geometry": {"coordinates":[7.576668,46.844601],"type":"Point"}
}