{
  "type": "Feature",
  "properties": {
    "iso:country":"CH",
    "sg:address":"Wartenbergstrasse 21",
    "sg:city":"Bottmingen",
    "sg:orig_category":"Interessenvertretungen Museen",
    "sg:phone":"+41 61 421 54 52",
    "sg:postcode":"4103",
    "sg:province":"Basel-Landschaft",
    "wof:name":"Stiftung Dorfmuseum Bottmingen",
    "wof:placetype":"venue"
},
  "geometry": {"coordinates":[7.5889539719,47.5229301453],"type":"Point"}
}