{
  "type": "Feature",
  "properties": {
    "iso:country":"CH",
    "sg:address":"Horwerstrasse 20",
    "sg:city":"Luzern",
    "sg:orig_category":"Kinderkrippen U horte",
    "sg:phone":"+41 41 310 57 54",
    "sg:postcode":"6005",
    "sg:province":"Luzern",
    "wof:name":"Kinderkrippe Frohheim",
    "wof:placetype":"venue"
},
  "geometry": {"coordinates":[8.3018798828,47.0385551453],"type":"Point"}
}