{
  "type": "Feature",
  "properties": {
    "iso:country":"CH",
    "sg:address":"Chemin Nant-de-cr\u00e8ve-coeur 24",
    "sg:city":"Versoix",
    "sg:orig_category":"Fotografische Laboratorien",
    "sg:phone":"+41 22 755 66 84",
    "sg:postcode":"1290",
    "sg:province":"Gen\u00e8ve",
    "wof:name":"Image Service, Imhof Christian",
    "wof:placetype":"venue"
},
  "geometry": {"coordinates":[6.1628098488,46.2761459351],"type":"Point"}
}