{
  "type": "Feature",
  "properties": {
    "iso:country":"CH",
    "sg:address":"Frohburgstrasse 116",
    "sg:city":"Z\u00fcrich",
    "sg:orig_category":"Reinigungsgewerbe",
    "sg:postcode":"8057",
    "sg:province":"Z\u00fcrich",
    "wof:name":"Geb\u00e4udereinigung B\u00fchlmann Thomas",
    "wof:placetype":"venue"
},
  "geometry": {"coordinates":[8.5517196655,47.3949317932],"type":"Point"}
}