{
  "type": "Feature",
  "properties": {
    "iso:country":"CH",
    "sg:address":"Neuhauserstrasse 45b",
    "sg:city":"Frauenfeld",
    "sg:orig_category":"Markt U Meinungsforschung",
    "sg:phone":"+41 52 721 84 68",
    "sg:postcode":"8500",
    "sg:province":"Thurgau",
    "wof:name":"Bm Consulting Marke Helena",
    "wof:placetype":"venue"
},
  "geometry": {"coordinates":[8.9081268311,47.5543708801],"type":"Point"}
}