{
  "type": "Feature",
  "properties": {
    "iso:country":"CH",
    "sg:address":"Gerechtigkeitsgasse 41 3011 Bern. Postfach",
    "sg:city":"Bern",
    "sg:orig_category":"Detailhandel mit elektrischen Haushalts-,Radio U Fernsehger\u00e4ten sowie Musikinstrumenten",
    "sg:postcode":"3011",
    "sg:province":"Bern",
    "wof:name":"Loveland Media Gmbh Bild, Ton- U. Datentr\u00e4ger; Verkauf, Verleih, Vorf\u00fchrung U. Fabrikation. Druckerzeugnisse Usw.; Handel",
    "wof:placetype":"venue"
},
  "geometry": {"coordinates":[7.4539728165,46.9481925964],"type":"Point"}
}