{
  "type": "Feature",
  "properties": {
    "iso:country":"CH",
    "sg:address":"Bahnhofstrasse 10",
    "sg:city":"Wattwil",
    "sg:orig_category":"Detailhandel mit fotografischen Artikeln",
    "sg:phone":"+41 71 988 10 10",
    "sg:postcode":"9630",
    "sg:province":"St. Gallen",
    "wof:name":"J\u00fcrg Abderhalden Fotogesch\u00e4ft",
    "wof:placetype":"venue"
},
  "geometry": {"coordinates":[9.0852975845,47.3010978699],"type":"Point"}
}