{
  "type": "Feature",
  "properties": {
    "addr:full":"Villenstrasse 6 Sch\u00f6nenwerd Solothurn 5012",
    "addr:housenumber":"6",
    "addr:postcode":"5012",
    "addr:street":"Villenstrasse;Schoenenwerd Solothurn",
    "iso:country":"CH",
    "sg:address":"Villenstrasse 6",
    "sg:city":"Sch\u00f6nenwerd",
    "sg:orig_category":"Arztpraxen",
    "sg:phone":"+41 62 849 27 27",
    "sg:postcode":"5012",
    "sg:province":"Solothurn",
    "wof:name":"Dr.med.kurt Frey Arzt F.allgemeine Medizin Fmh",
    "wof:placetype":"venue"
},
  "geometry": {"coordinates":[8.003943,47.374077],"type":"Point"}
}