{
  "type": "Feature",
  "properties": {
    "iso:country":"CH",
    "sg:address":"Rue De La Cure 5",
    "sg:city":"Ardon",
    "sg:orig_category":"Bauschreinerei Herstellung von M\u00f6beln verschiedener Art",
    "sg:phone":"+41 27 306 15 09",
    "sg:postcode":"1957",
    "sg:province":"Valais",
    "wof:name":"Jean-baptiste Cleusix Eb\u00e9nisterie",
    "wof:placetype":"venue"
},
  "geometry": {"coordinates":[7.255715,46.209255],"type":"Point"}
}