{
  "type": "Feature",
  "properties": {
    "iso:country":"CH",
    "sg:address":"Oberer Aareggweg 40",
    "sg:city":"Bern",
    "sg:orig_category":"Maler U Glasergewerbe",
    "sg:phone":"+41 31 301 59 66",
    "sg:postcode":"3004",
    "sg:province":"Bern",
    "wof:name":"Rawyler H., Malergesch\u00e4ft",
    "wof:placetype":"venue"
},
  "geometry": {"coordinates":[7.4521069527,46.9723205566],"type":"Point"}
}