{
  "type": "Feature",
  "properties": {
    "iso:country":"CH",
    "sg:address":"Chreisacherweg 150",
    "sg:city":"Anwil",
    "sg:orig_category":"Unclassifiable Establishments",
    "sg:phone":"+41 61 993 10 45",
    "sg:postcode":"4469",
    "sg:province":"Basel-Landschaft",
    "wof:name":"Rabatec Engineering Gmbh",
    "wof:placetype":"venue"
},
  "geometry": {"coordinates":[7.9421820641,47.4530906677],"type":"Point"}
}