{
  "type": "Feature",
  "properties": {
    "addr:full":"Grossbachstrasse 57 Gross Schwyz 8841",
    "addr:housenumber":"57",
    "addr:postcode":"8841",
    "addr:street":"Grossbachstrasse",
    "iso:country":"CH",
    "sg:address":"Grossbachstrasse 57",
    "sg:city":"Gross",
    "sg:orig_category":"Architektur U Ingenieurb\u00fcros",
    "sg:postcode":"8841",
    "sg:province":"Schwyz",
    "wof:name":"Elbau-gmbh",
    "wof:placetype":"venue"
},
  "geometry": {"coordinates":[8.77522,47.111649],"type":"Point"}
}