{
  "type": "Feature",
  "properties": {
    "iso:country":"CH",
    "sg:address":"Teufenerstrasse 3",
    "sg:city":"St.gallen",
    "sg:orig_category":"Detailhandel mit elektrischen Haushalts-,Radio U Fernsehger\u00e4ten sowie Musikinstrumenten",
    "sg:postcode":"9000",
    "sg:province":"St. Gallen",
    "wof:name":"M\u00f6ckli E.",
    "wof:placetype":"venue"
},
  "geometry": {"coordinates":[6.6639499664,46.5902061462],"type":"Point"}
}