{
  "type": "Feature",
  "properties": {
    "iso:country":"CH",
    "sg:address":"Betliserstrasse 16",
    "sg:city":"Weesen",
    "sg:classifiers":[
        {
            "category":"Travel",
            "subcategory":"Hotels & Motels",
            "type":"Entertainment"
        }
    ],
    "sg:phone":"+41 55 616 22 60",
    "sg:postcode":"8872",
    "sg:province":"St. Gallen",
    "sg:tags":[
        "hotels",
        "mit",
        "restaurant"
    ],
    "wof:name":"Restaurant Villa Aurum, Silvia Moser",
    "wof:placetype":"venue"
},
  "geometry": {"coordinates":[9.1016149521,47.1361846924],"type":"Point"}
}