{
  "type": "Feature",
  "properties": {
    "iso:country":"CH",
    "sg:address":"Bleichestrasse 40",
    "sg:city":"Kreuzlingen",
    "sg:orig_category":"Wasserversorgung",
    "sg:phone":"+41 71 688 68 88",
    "sg:postcode":"8280",
    "sg:province":"Thurgau",
    "wof:name":"Seewasserwerk",
    "wof:placetype":"venue"
},
  "geometry": {"coordinates":[9.1962966919,47.645362854],"type":"Point"}
}