{
  "type": "Feature",
  "properties": {
    "iso:country":"CH",
    "sg:address":"Route De Sorge 9",
    "sg:city":"Crissier",
    "sg:orig_category":"Herstellung von medizinischen U chirurgischen Ger\u00e4ten sowie orthop\u00e4dischen Vorrichtungen Herstellung",
    "sg:phone":"+41 21 631 92 00",
    "sg:postcode":"1023",
    "sg:province":"Vaud",
    "wof:name":"Braun B. Medical Sa",
    "wof:placetype":"venue"
},
  "geometry": {"coordinates":[6.564871,46.55809],"type":"Point"}
}