{
  "type": "Feature",
  "properties": {
    "iso:country":"CH",
    "sg:address":"Scuole Via Delle 44",
    "sg:city":"Pregassona",
    "sg:orig_category":"RESTAURANTS: TEA-ROOMS",
    "sg:postcode":"6963",
    "sg:province":"Ticino",
    "wof:name":"Roslino Sa",
    "wof:placetype":"venue"
},
  "geometry": {"coordinates":[8.966960907,46.024017334],"type":"Point"}
}