{
  "type": "Feature",
  "properties": {
    "iso:country":"CH",
    "sg:address":"Hohlstrasse 47",
    "sg:city":"Z\u00fcrich",
    "sg:orig_category":"Fernmeldedienste",
    "sg:phone":"+41 12972080",
    "sg:postcode":"8004",
    "sg:province":"Z\u00fcrich",
    "wof:name":"Telefon Corner Tfc Gmbh",
    "wof:placetype":"venue"
},
  "geometry": {"coordinates":[8.5259037018,47.3774185181],"type":"Point"}
}