{
  "type": "Feature",
  "properties": {
    "iso:country":"CH",
    "sg:address":"Vorstatt 8",
    "sg:city":"Nebikon",
    "sg:orig_category":"Fahrschulen, Flugschulen",
    "sg:phone":"+41 62 756 20 52",
    "sg:postcode":"6244",
    "sg:province":"Luzern",
    "wof:name":"Walter Bruppacher Autofahrschule",
    "wof:placetype":"venue"
},
  "geometry": {"coordinates":[7.9731531143,47.1924858093],"type":"Point"}
}