{
  "type": "Feature",
  "properties": {
    "addr:full":"Belalpstrasse 10 3900 Brig. Postfach 48 Brig Valais 3900",
    "addr:housenumber":"10;48",
    "addr:postcode":"3900;3900",
    "addr:street":"Belalpstrasse;Postfach",
    "iso:country":"CH",
    "sg:address":"Belalpstrasse 10 3900 Brig. Postfach 48",
    "sg:city":"Brig",
    "sg:orig_category":"Architektur U Ingenieurb\u00fcros Architekturb\u00fcros",
    "sg:phone":"+41 27 922 44 00",
    "sg:postcode":"3900",
    "sg:province":"Valais",
    "wof:name":"Iab Ag Brig Institut F\u00fcr Architektur & Bautechnologie",
    "wof:placetype":"venue"
},
  "geometry": {"coordinates":[7.989611,46.317928],"type":"Point"}
}