{
  "type": "Feature",
  "properties": {
    "iso:country":"CH",
    "sg:address":"Chuenz",
    "sg:city":"Edlibach",
    "sg:orig_category":"Autolackierereien",
    "sg:phone":"+41 79 224 29 49",
    "sg:postcode":"6313",
    "sg:province":"Zug",
    "wof:name":"Marcel Fuhrer Autospritzwerk",
    "wof:placetype":"venue"
},
  "geometry": {"coordinates":[8.590646,47.178349],"type":"Point"}
}