{
  "type": "Feature",
  "properties": {
    "iso:country":"CH",
    "sg:address":"Rudolfstrasse 10 4054 Basel. Postfach",
    "sg:city":"Basel",
    "sg:orig_category":"Unclassifiable Establishments",
    "sg:postcode":"4054",
    "sg:province":"Basel-Stadt",
    "wof:name":"Inge Brandt Kosmetikstudio",
    "wof:placetype":"venue"
},
  "geometry": {"coordinates":[7.5748300552,47.5553283691],"type":"Point"}
}