{
  "type": "Feature",
  "properties": {
    "iso:country":"CH",
    "sg:address":"Lagerstrasse 1",
    "sg:city":"Z\u00fcrich",
    "sg:orig_category":"Herstellung von Oberbekleidung Textilgewerbe",
    "sg:phone":"+41 79 341 72 62",
    "sg:postcode":"8004",
    "sg:province":"Z\u00fcrich",
    "wof:name":"Goldie Textil-ag",
    "wof:placetype":"venue"
},
  "geometry": {"coordinates":[8.4358510971,47.0760536194],"type":"Point"}
}