{
  "type": "Feature",
  "properties": {
    "iso:country":"CH",
    "sg:address":"Maiackerweg 14",
    "sg:city":"Rudolfstetten",
    "sg:orig_category":"Dienstleistungen von Beteiligungsgesellschaften",
    "sg:phone":"+41 79 438 84 66",
    "sg:postcode":"8964",
    "sg:province":"Aargau",
    "wof:name":"Fidato, Karrer-davatz Helene",
    "wof:placetype":"venue"
},
  "geometry": {"coordinates":[8.3720598221,47.3618125916],"type":"Point"}
}