{
  "type": "Feature",
  "properties": {
    "iso:country":"CH",
    "sg:address":"Ch\u00e2teau 17",
    "sg:city":"Peseux",
    "sg:orig_category":"Softwareentwicklung U beratung",
    "sg:postcode":"2034",
    "sg:province":"Neuch\u00e2tel",
    "wof:name":"Marketing And R & D Product Services Sa",
    "wof:placetype":"venue"
},
  "geometry": {"coordinates":[6.890141964,46.9888572693],"type":"Point"}
}