{
  "type": "Feature",
  "properties": {
    "iso:country":"CH",
    "sg:address":"Rue Chabrey 6",
    "sg:city":"Gen\u00e8ve",
    "sg:orig_category":"Verlagsgewerbe",
    "sg:phone":"+41 22 740 05 80",
    "sg:postcode":"1202",
    "sg:province":"Gen\u00e8ve",
    "wof:name":"Bancassurance Magazine Des Dirigeants De Banque",
    "wof:placetype":"venue"
},
  "geometry": {"coordinates":[6.1302199364,46.2154006958],"type":"Point"}
}