{
  "type": "Feature",
  "properties": {
    "iso:country":"CH",
    "sg:address":"Evian Avenue D' 4 1000 Lausanne. Postfach",
    "sg:city":"Lausanne",
    "sg:orig_category":"Elektroinstallation",
    "sg:postcode":"1003",
    "sg:province":"Vaud",
    "wof:name":"Luque Fran\u00e7ois, Installations \u00e9lectriques Et T\u00e9l\u00e9phoniques",
    "wof:placetype":"venue"
},
  "geometry": {"coordinates":[6.6876702309,46.559551239],"type":"Point"}
}