{
  "type": "Feature",
  "properties": {
    "iso:country":"CH",
    "sg:address":"Place Des Planches 4",
    "sg:city":"Montreux",
    "sg:orig_category":"Detailhandel mit Antiquit\u00e4ten Kunsthandel",
    "sg:phone":"+41 32 968 06 86",
    "sg:postcode":"1820",
    "sg:province":"Vaud",
    "wof:name":"Emile Schnegg Antiquit\u00e9s Brocante",
    "wof:placetype":"venue"
},
  "geometry": {"coordinates":[6.831628,47.105202],"type":"Point"}
}