{
  "type": "Feature",
  "properties": {
    "iso:country":"CH",
    "sg:address":"Jurastrasse 18",
    "sg:city":"Biberist",
    "sg:orig_category":"Fussreflexzonenmassage",
    "sg:phone":"+41 32 672 32 83",
    "sg:postcode":"4562",
    "sg:province":"Solothurn",
    "wof:name":"Margrit Mumenthaler Massagen",
    "wof:placetype":"venue"
},
  "geometry": {"coordinates":[7.5594210625,47.1907272339],"type":"Point"}
}