{
  "type": "Feature",
  "properties": {
    "iso:country":"CH",
    "sg:address":"Fabrikstrasse 498",
    "sg:city":"Welschenrohr",
    "sg:classifiers":[
        {
            "category":"Utilities",
            "subcategory":"Cable",
            "type":"Services"
        }
    ],
    "sg:phone":"+41 32 639 11 51",
    "sg:postcode":"4716",
    "sg:province":"Solothurn",
    "sg:tags":[
        "connector",
        "machine",
        "processing"
    ],
    "wof:name":"Kirsten Solderring Ag",
    "wof:placetype":"venue"
},
  "geometry": {"coordinates":[7.52361,47.281712],"type":"Point"}
}