{
  "type": "Feature",
  "properties": {
    "iso:country":"CH",
    "sg:address":"Fritz-oppliger-strasse 9",
    "sg:city":"Biel/bienne",
    "sg:orig_category":"Mechanik Mechanische Werkst\u00e4tten",
    "sg:phone":"+41 32 341 05 86",
    "sg:postcode":"2504",
    "sg:province":"Bern",
    "wof:name":"Protomec Ti\u00e8che Roland",
    "wof:placetype":"venue"
},
  "geometry": {"coordinates":[7.2833209038,47.1608123779],"type":"Point"}
}