{
  "type": "Feature",
  "properties": {
    "iso:country":"CH",
    "sg:address":"Oltnerstrasse 139",
    "sg:city":"Aarburg",
    "sg:orig_category":"Einzelhandel mit Automobilteilen U Zubeh\u00f6r Herstellung von Bereifungen",
    "sg:phone":"+41 62 216 28 73",
    "sg:postcode":"4663",
    "sg:province":"Aargau",
    "wof:name":"Suter's Pneuservice",
    "wof:placetype":"venue"
},
  "geometry": {"coordinates":[7.8570070267,47.3371276855],"type":"Point"}
}