{
  "type": "Feature",
  "properties": {
    "iso:country":"CH",
    "sg:address":"Kirchackerstrasse 10",
    "sg:city":"Arisdorf",
    "sg:orig_category":"Massagestudios",
    "sg:phone":"+41 61 813 10 80",
    "sg:postcode":"4422",
    "sg:province":"Basel-Landschaft",
    "wof:name":"Massagepraxis Body-relax",
    "wof:placetype":"venue"
},
  "geometry": {"coordinates":[7.7683310509,47.511390686],"type":"Point"}
}