{
  "type": "Feature",
  "properties": {
    "iso:country":"CH",
    "sg:address":"Ch. Du Champ-des-filles 19 1228 Plan-les-ouates. Postfach",
    "sg:city":"Plan-les-ouates",
    "sg:orig_category":"Herstellung von Uhren",
    "sg:phone":"+41 32 935 11 05",
    "sg:postcode":"1228",
    "sg:province":"Gen\u00e8ve",
    "wof:name":"Gentil Michel",
    "wof:placetype":"venue"
},
  "geometry": {"coordinates":[6.6068201065,46.9808044434],"type":"Point"}
}