{
  "type": "Feature",
  "properties": {
    "iso:country":"CH",
    "sg:address":"Weinhaldenstrasse 18",
    "sg:city":"Rorschacherberg",
    "sg:orig_category":"Sonstiger Grosshandel",
    "sg:postcode":"9404",
    "sg:province":"St. Gallen",
    "wof:name":"Epg Handels Gmbh",
    "wof:placetype":"venue"
},
  "geometry": {"coordinates":[9.4908723831,47.4720687866],"type":"Point"}
}