{
  "type": "Feature",
  "properties": {
    "iso:country":"CH",
    "sg:address":"Via Bellinzona 37",
    "sg:city":"Giubiasco",
    "sg:orig_category":"Handel mit Automobilen Vermietung von Automobilen",
    "sg:phone":"+41 800 837 465",
    "sg:postcode":"6512",
    "sg:province":"Ticino",
    "wof:name":"Winteler & Co Sa",
    "wof:placetype":"venue"
},
  "geometry": {"coordinates":[9.013917923,46.1792106628],"type":"Point"}
}