{
  "type": "Feature",
  "properties": {
    "iso:country":"CH",
    "sg:address":"Stationsstrasse 11",
    "sg:city":"N\u00e4nikon",
    "sg:orig_category":"Detailhandel mit Antiquit\u00e4ten",
    "sg:phone":"+41 19413033",
    "sg:postcode":"8606",
    "sg:province":"Z\u00fcrich",
    "wof:name":"Au Vieux Cadran Sa Antiquit\u00e4ten",
    "wof:placetype":"venue"
},
  "geometry": {"coordinates":[8.692671,47.370296],"type":"Point"}
}