{
  "type": "Feature",
  "properties": {
    "addr:full":"Dorfstrasse 175 3792 Saanen. Postfach 64 Saanen Bern 3792",
    "addr:housenumber":"175;64",
    "addr:postcode":"3792 saanen.;3792",
    "addr:street":"Dorfstrasse;Postfach;Bern",
    "iso:country":"CH",
    "sg:address":"Dorfstrasse 175 3792 Saanen. Postfach 64",
    "sg:city":"Saanen",
    "sg:orig_category":"Detailhandel mit B\u00fcchern Detailhandel mit B\u00fcchern, Zeitungen, Schreib U Papeteriewaren",
    "sg:phone":"+41 26 652 22 64",
    "sg:postcode":"3792",
    "sg:province":"Bern",
    "wof:name":"Ayer-demierre, Hoirs De Vve F.",
    "wof:placetype":"venue"
},
  "geometry": {"coordinates":[6.91757,46.696133],"type":"Point"}
}