{
  "type": "Feature",
  "properties": {
    "iso:country":"CH",
    "sg:address":"Cuort",
    "sg:city":"Breil/brigels",
    "sg:orig_category":"Schmieden",
    "sg:phone":"+41 81 941 14 35",
    "sg:postcode":"7165",
    "sg:province":"Graubunden",
    "wof:name":"Rest Giusep Cathomas Kunstschmiede",
    "wof:placetype":"venue"
},
  "geometry": {"coordinates":[9.0614433289,46.7701187134],"type":"Point"}
}