{
  "type": "Feature",
  "properties": {
    "iso:country":"CH",
    "sg:address":"Bubenbergplatz 8",
    "sg:city":"Bern",
    "sg:orig_category":"Kunsthandel",
    "sg:phone":"+41 31 311 63 60",
    "sg:postcode":"3011",
    "sg:province":"Bern",
    "wof:name":"Bijoux Galerie Ernst M\u00f6ri",
    "wof:placetype":"venue"
},
  "geometry": {"coordinates":[7.4385709763,46.9474525452],"type":"Point"}
}