{
  "type": "Feature",
  "properties": {
    "iso:country":"CH",
    "sg:address":"Bielstrasse 73",
    "sg:city":"Solothurn",
    "sg:orig_category":"Sanit\u00e4r, Heizungs U L\u00fcftungsinstallation",
    "sg:phone":"+41 32 622 25 56",
    "sg:postcode":"4500",
    "sg:province":"Solothurn",
    "wof:name":"Peter Walter Ag",
    "wof:placetype":"venue"
},
  "geometry": {"coordinates":[7.5255641937,47.2110404968],"type":"Point"}
}