{
  "type": "Feature",
  "properties": {
    "iso:country":"CH",
    "sg:address":"Alte Chamerstrasse 4 6343 Rotkreuz. Postfach 24",
    "sg:city":"Rotkreuz",
    "sg:orig_category":"Herstellung von Futtermitteln f\u00fcr Nutztiere Mahl U Sch\u00e4lm\u00fchlen",
    "sg:phone":"+41 41 790 14 44",
    "sg:postcode":"6343",
    "sg:province":"Zug",
    "wof:name":"Utro Fikovit Ag Futterm\u00fchle",
    "wof:placetype":"venue"
},
  "geometry": {"coordinates":[8.4296884537,47.1429138184],"type":"Point"}
}