{
  "type": "Feature",
  "properties": {
    "iso:country":"CH",
    "sg:address":"Grand-rue 73",
    "sg:city":"Morges",
    "sg:classifiers":[
        {
            "category":"Banks & Credit Unions",
            "subcategory":"Bank",
            "type":"Services"
        }
    ],
    "sg:phone":"+41 21 803 09 71",
    "sg:postcode":"1110",
    "sg:province":"Vaud",
    "wof:name":"Caisse D'epargne Et De Cr\u00e9dit",
    "wof:placetype":"venue"
},
  "geometry": {"coordinates":[6.498234,46.508751],"type":"Point"}
}