{
  "type": "Feature",
  "properties": {
    "iso:country":"CH",
    "sg:address":"Avenue De La Gare 9",
    "sg:city":"Montagne-moutier",
    "sg:orig_category":"Versicherungen Hauptagenturen",
    "sg:phone":"+41 32 493 45 45",
    "sg:postcode":"2740",
    "sg:province":"Bern",
    "wof:name":"Helvetia Patria Assurances Conseiller \u00e0 La Client\u00e8le",
    "wof:placetype":"venue"
},
  "geometry": {"coordinates":[7.3794498444,47.2810821533],"type":"Point"}
}