{
  "type": "Feature",
  "properties": {
    "iso:country":"CH",
    "sg:address":"Avenue De Sainte-c\u00e9cile 3",
    "sg:city":"Meyrin",
    "sg:orig_category":"Bau von Sportanlagen Gartenbau",
    "sg:phone":"+41 22 782 25 21",
    "sg:postcode":"1217",
    "sg:province":"Gen\u00e8ve",
    "wof:name":"Marcel-albert Aeby Entrepr.jardins & Ma\u00e7onnerie",
    "wof:placetype":"venue"
},
  "geometry": {"coordinates":[6.084803,46.234585],"type":"Point"}
}