{
  "type": "Feature",
  "properties": {
    "iso:country":"CH",
    "sg:address":"De-grenus Place 8 1201 Gen\u00e8ve. Postfach",
    "sg:city":"Gen\u00e8ve",
    "sg:orig_category":"Verwaltung von Immobilien",
    "sg:postcode":"1208",
    "sg:province":"Gen\u00e8ve",
    "wof:name":"Rochat Charles Et Cie",
    "wof:placetype":"venue"
},
  "geometry": {"coordinates":[6.1433529854,46.2069473267],"type":"Point"}
}