{
  "type": "Feature",
  "properties": {
    "iso:country":"CH",
    "sg:address":"Rastatterstrasse 17",
    "sg:city":"Basel",
    "sg:orig_category":"Sonstige Kultur U Unterhaltungseinrichtungen",
    "sg:phone":"+41 61 631 34 13",
    "sg:postcode":"4057",
    "sg:province":"Basel-Stadt",
    "wof:name":"Bruco Gmbh",
    "wof:placetype":"venue"
},
  "geometry": {"coordinates":[7.5893559456,47.5793914795],"type":"Point"}
}