{
  "type": "Feature",
  "properties": {
    "iso:country":"CH",
    "sg:address":"Birseckstrasse 27",
    "sg:city":"Basel",
    "sg:orig_category":"Vereine Fasnacht",
    "sg:phone":"+41 61 331 27 78",
    "sg:postcode":"4059",
    "sg:province":"Basel-Stadt",
    "wof:name":"L\u00e4lli Jungi & Binggis",
    "wof:placetype":"venue"
},
  "geometry": {"coordinates":[7.6016998291,47.5309715271],"type":"Point"}
}