{
  "type": "Feature",
  "properties": {
    "iso:country":"CH",
    "sg:address":"Morgartenstrasse 6 6315 Ober\u00e4geri. Postfach 151",
    "sg:city":"Ober\u00e4geri",
    "sg:orig_category":"Detailhandel mit Textilien",
    "sg:phone":"+41 81 420 40 68",
    "sg:postcode":"6315",
    "sg:province":"Zug",
    "wof:name":"Ida M\u00fcller Diadem N\u00e4hfachgesch\u00e4ft",
    "wof:placetype":"venue"
},
  "geometry": {"coordinates":[9.7130670547,46.703338623],"type":"Point"}
}