{
  "type": "Feature",
  "properties": {
    "iso:country":"CH",
    "sg:address":"Gumpenwiesenstrasse 13",
    "sg:city":"Dielsdorf",
    "sg:orig_category":"Non-Classified Establishments",
    "sg:postcode":"8157",
    "sg:province":"Z\u00fcrich",
    "wof:name":"Erni + Leder Architekten Gmbh",
    "wof:placetype":"venue"
},
  "geometry": {"coordinates":[8.4576187134,47.4782218933],"type":"Point"}
}