{
  "type": "Feature",
  "properties": {
    "iso:country":"CH",
    "sg:address":"Hauptstrasse 33 4542 Luterbach. Postfach",
    "sg:city":"Luterbach",
    "sg:orig_category":"Wirtschaftspr\u00fcfung, Steuerberatung U Treuhand",
    "sg:postcode":"4542",
    "sg:province":"Solothurn",
    "wof:name":"Ka-dar Treuhand Gmbh",
    "wof:placetype":"venue"
},
  "geometry": {"coordinates":[7.585627079,47.2176094055],"type":"Point"}
}