{
  "type": "Feature",
  "properties": {
    "iso:country":"CH",
    "sg:address":"Bergstrasse 27",
    "sg:city":"Rafz",
    "sg:orig_category":"Wirtschaftspr\u00fcfung, Steuerberatung U Treuhand",
    "sg:phone":"+41 18694040",
    "sg:postcode":"8197",
    "sg:province":"Z\u00fcrich",
    "wof:name":"Schwaiger Theres",
    "wof:placetype":"venue"
},
  "geometry": {"coordinates":[8.542930603,47.6200523376],"type":"Point"}
}