{
  "type": "Feature",
  "properties": {
    "iso:country":"CH",
    "sg:address":"Ringstrasse 18",
    "sg:city":"Neuenhof",
    "sg:orig_category":"Druck ohne Zeitungsdruck",
    "sg:phone":"+41 17405167",
    "sg:postcode":"5432",
    "sg:province":"Aargau",
    "wof:name":"Numeriertechnik Zeidler Arthur",
    "wof:placetype":"venue"
},
  "geometry": {"coordinates":[8.3901262283,47.4086799622],"type":"Point"}
}