{
  "type": "Feature",
  "properties": {
    "iso:country":"CH",
    "sg:address":"Rathausstrasse 29",
    "sg:city":"Weinfelden",
    "sg:orig_category":"Detailhandel mit Schuhen",
    "sg:phone":"+41 71 622 50 30",
    "sg:postcode":"8570",
    "sg:province":"Thurgau",
    "wof:name":"Tiefenbacher Schuhhaus Ag",
    "wof:placetype":"venue"
},
  "geometry": {"coordinates":[9.1087036133,47.5667076111],"type":"Point"}
}