{
  "type": "Feature",
  "properties": {
    "iso:country":"CH",
    "sg:address":"Oberr\u00fcttenenstrasse 12",
    "sg:city":"R\u00fcttenen",
    "sg:orig_category":"Non-Classified Establishments",
    "sg:postcode":"4522",
    "sg:province":"Solothurn",
    "wof:name":"Tds Transport-dienst Ren\u00e9 + K\u00e4thi Sch\u00e4rer-klopfstein",
    "wof:placetype":"venue"
},
  "geometry": {"coordinates":[7.5260100365,47.2290382385],"type":"Point"}
}