{
  "type": "Feature",
  "properties": {
    "iso:country":"CH",
    "sg:address":"Bahnhofstrasse 24",
    "sg:city":"Wallisellen",
    "sg:orig_category":"Non-Classified Establishments",
    "sg:postcode":"8304",
    "sg:province":"Z\u00fcrich",
    "wof:name":"We Speak English Hutter, Rohner, Untersander",
    "wof:placetype":"venue"
},
  "geometry": {"coordinates":[9.4986171722,47.0070915222],"type":"Point"}
}