{
  "type": "Feature",
  "properties": {
    "iso:country":"CH",
    "sg:address":"Dohlenweg 24",
    "sg:city":"Uetendorf",
    "sg:orig_category":"Kosmetikinstitute",
    "sg:phone":"+41 33 345 34 54",
    "sg:postcode":"3661",
    "sg:province":"Bern",
    "wof:name":"Sonja Zwygart Kosmetikinstitut Sonja",
    "wof:placetype":"venue"
},
  "geometry": {"coordinates":[7.5733971596,46.7754631042],"type":"Point"}
}