{
  "type": "Feature",
  "properties": {
    "iso:country":"CH",
    "sg:address":"W\u00f6lferstrasse 4",
    "sg:city":"F\u00fcllinsdorf",
    "sg:orig_category":"Herstellung von B\u00fcro U Ladenm\u00f6beln",
    "sg:phone":"+41 55 210 65 07",
    "sg:postcode":"4414",
    "sg:province":"Basel-Landschaft",
    "wof:name":"Shop-design Wittwer",
    "wof:placetype":"venue"
},
  "geometry": {"coordinates":[8.7995347977,47.2133331299],"type":"Point"}
}