{
  "type": "Feature",
  "properties": {
    "iso:country":"CH",
    "sg:address":"Gesellschaftsstrasse 44",
    "sg:city":"Bern",
    "sg:orig_category":"Softwareentwicklung U beratung",
    "sg:phone":"+41 31 333 95 93",
    "sg:postcode":"3012",
    "sg:province":"Bern",
    "wof:name":"Xview Solutions Gmbh",
    "wof:placetype":"venue"
},
  "geometry": {"coordinates":[7.4334640503,46.9545021057],"type":"Point"}
}