{
  "type": "Feature",
  "properties": {
    "iso:country":"CH",
    "sg:address":"Ch. De Corbaz 5",
    "sg:city":"Belmont-lausanne",
    "sg:orig_category":"Markt U Meinungsforschung",
    "sg:postcode":"1092",
    "sg:province":"Vaud",
    "wof:name":"Grobet Didier",
    "wof:placetype":"venue"
},
  "geometry": {"coordinates":[6.678686142,46.5202598572],"type":"Point"}
}