{
  "type": "Feature",
  "properties": {
    "iso:country":"CH",
    "sg:address":"Br\u00fcnnenstrasse 110",
    "sg:city":"Bern",
    "sg:orig_category":"Detailhandel mit Fahrr\u00e4dern Handel mit Motorr\u00e4dern, Teilen U Zubeh\u00f6r Instandhaltung U Reparatur von ",
    "sg:postcode":"3018",
    "sg:province":"Bern",
    "wof:name":"Radrennsport Schaller",
    "wof:placetype":"venue"
},
  "geometry": {"coordinates":[7.3903880119,46.9418296814],"type":"Point"}
}