{
  "type": "Feature",
  "properties": {
    "iso:country":"CH",
    "sg:address":"Loonstrasse 4",
    "sg:city":"Niederrohrdorf",
    "sg:orig_category":"Sportvereine Ballsport Handball",
    "sg:phone":"+41 56 496 21 74",
    "sg:postcode":"5443",
    "sg:province":"Aargau",
    "wof:name":"Sv L\u00e4gern",
    "wof:placetype":"venue"
},
  "geometry": {"coordinates":[8.3068847656,47.4230461121],"type":"Point"}
}