{
  "type": "Feature",
  "properties": {
    "iso:country":"CH",
    "sg:address":"Chemin Des Tilleuls 6",
    "sg:city":"Moutier",
    "sg:orig_category":"Politische Vereinigungen",
    "sg:phone":"+41 32 493 50 16",
    "sg:postcode":"2740",
    "sg:province":"Bern",
    "wof:name":"Parti Socialiste Autonome Psa",
    "wof:placetype":"venue"
},
  "geometry": {"coordinates":[7.3889398575,47.282283783],"type":"Point"}
}