{
  "type": "Feature",
  "properties": {
    "iso:country":"CH",
    "sg:address":"Seefeldstrasse 141 8008 Z\u00fcrich. Postfach",
    "sg:city":"Z\u00fcrich",
    "sg:orig_category":"Detailhandel mit Geschenkartikeln U Souvenirs",
    "sg:phone":"+41 13837015",
    "sg:postcode":"8034",
    "sg:province":"Z\u00fcrich",
    "wof:name":"Boutique H\u00f6schgass Graciela Stoffel",
    "wof:placetype":"venue"
},
  "geometry": {"coordinates":[8.555606842,47.3566627502],"type":"Point"}
}