{
  "type": "Feature",
  "properties": {
    "iso:country":"CH",
    "sg:address":"Schulstrasse 2",
    "sg:city":"Lanterswil",
    "sg:orig_category":"Mechanische Werkst\u00e4tten",
    "sg:phone":"+41 79 411 06 32",
    "sg:postcode":"9503",
    "sg:province":"Thurgau",
    "wof:name":"Erich Blaser Mechanische Werkst\u00e4tte",
    "wof:placetype":"venue"
},
  "geometry": {"coordinates":[9.0960016251,47.5210075378],"type":"Point"}
}