{
  "type": "Feature",
  "properties": {
    "iso:country":"CH",
    "sg:address":"Roeven 25",
    "sg:city":"Zernez",
    "sg:orig_category":"Sportvereine Ballsport Tennis",
    "sg:phone":"+41 81 856 17 24",
    "sg:postcode":"7530",
    "sg:province":"Graubunden",
    "wof:name":"Tc Zernez",
    "wof:placetype":"venue"
},
  "geometry": {"coordinates":[10.0919113159,46.698097229],"type":"Point"}
}