{
  "type": "Feature",
  "properties": {
    "addr:full":"1971 Grimisuat Valais 1971",
    "addr:postcode":"1971;1971",
    "iso:country":"CH",
    "sg:address":"1971",
    "sg:city":"Grimisuat",
    "sg:orig_category":"Alters U Pflegeheime Wohnheime",
    "sg:phone":"+41 27 399 14 11",
    "sg:postcode":"1971",
    "sg:province":"Valais",
    "wof:name":"Home Les Cr\u00eates Foyer Pour Personnes \u00e2g\u00e9es",
    "wof:placetype":"venue"
},
  "geometry": {"coordinates":[7.37887,46.254509],"type":"Point"}
}