{
  "type": "Feature",
  "properties": {
    "iso:country":"CH",
    "sg:address":"Beauregard Avenue 12",
    "sg:city":"Fribourg",
    "sg:orig_category":"Grosshandel mit Textilien",
    "sg:phone":"+41 26 426 36 06",
    "sg:postcode":"1700",
    "sg:province":"Fribourg",
    "wof:name":"Lumatrading S\u00e0rl",
    "wof:placetype":"venue"
},
  "geometry": {"coordinates":[7.1475830078,46.802028656],"type":"Point"}
}