{
  "type": "Feature",
  "properties": {
    "iso:country":"CH",
    "sg:address":"Route Du Jura 37 1700 Fribourg Case Postale 44",
    "sg:city":"Fribourg",
    "sg:orig_category":"Fachdetailhandel mit pharmazeutischen Produkten",
    "sg:phone":"+41 21 801 21 84",
    "sg:postcode":"1706",
    "wof:name":"Pharmacie Tavil Maurice Tavil",
    "wof:placetype":"venue"
},
  "geometry": {"coordinates":[6.4996671677,46.5101661682],"type":"Point"}
}