{
  "type": "Feature",
  "properties": {
    "iso:country":"CH",
    "sg:address":"Bahnhofstrasse 51",
    "sg:city":"Hallau",
    "sg:orig_category":"Offsetdruck Satzherstellung U Reproduktion",
    "sg:phone":"+41 52 681 37 40",
    "sg:postcode":"8215",
    "sg:province":"Schaffhausen",
    "wof:name":"L\u00fcthi Max Csa-print",
    "wof:placetype":"venue"
},
  "geometry": {"coordinates":[8.4576187134,47.6939315796],"type":"Point"}
}