{
  "type": "Feature",
  "properties": {
    "iso:country":"CH",
    "sg:address":"Bahnhofstrasse",
    "sg:city":"Uzwil",
    "sg:orig_category":"Grosshandel mit Eisenwaren sowie Installationsbedarf f\u00fcr Gas, Wasser U Heizung Grosshandel mit Erzen",
    "sg:phone":"+41 71 955 79 00",
    "sg:postcode":"9240",
    "sg:province":"St. Gallen",
    "wof:name":"St\u00fcrm Ag Stahl, Metall, Haustechnik",
    "wof:placetype":"venue"
},
  "geometry": {"coordinates":[9.1519670486,47.4451370239],"type":"Point"}
}