{
  "type": "Feature",
  "properties": {
    "iso:country":"CH",
    "sg:address":"Breitenrainstrasse 14 3013 Bern. Postfach 446",
    "sg:city":"Bern",
    "sg:orig_category":"Instandhaltung U Reparatur von Automobilen",
    "sg:phone":"+41 31 387 42 42",
    "sg:postcode":"3013",
    "sg:province":"Bern",
    "wof:name":"L\u00f6wen-garage Ag Bern",
    "wof:placetype":"venue"
},
  "geometry": {"coordinates":[7.4528589249,46.9582099915],"type":"Point"}
}