{
  "type": "Feature",
  "properties": {
    "iso:country":"CH",
    "sg:address":"Buchenweg 17",
    "sg:city":"Benglen",
    "sg:orig_category":"Grosshandel mit Eisenwaren sowie Installationsbedarf f\u00fcr Gas, Wasser U Heizung Herstellung von k\u00e4lte",
    "sg:phone":"+41 18252076",
    "sg:postcode":"8121",
    "sg:province":"Z\u00fcrich",
    "wof:name":"Marthaler Ag",
    "wof:placetype":"venue"
},
  "geometry": {"coordinates":[8.6346960068,47.3622360229],"type":"Point"}
}