{
  "type": "Feature",
  "properties": {
    "iso:country":"CH",
    "sg:address":"Bernstrasse 30 3250 Lyss. Postfach 64",
    "sg:city":"Lyss",
    "sg:orig_category":"Herstellung von Werkzeugen Pulvermetallurgie Schmieden, Pressen, Stanzen U Profilwalzen von Metallen",
    "sg:phone":"+41 56 618 76 76",
    "sg:postcode":"3250",
    "sg:province":"Bern",
    "wof:name":"Springfix Ag",
    "wof:placetype":"venue"
},
  "geometry": {"coordinates":[8.2618150711,47.3524932861],"type":"Point"}
}