{
  "type": "Feature",
  "properties": {
    "iso:country":"CH",
    "sg:address":"Tannenbodenstrasse 1",
    "sg:city":"Meggen",
    "sg:orig_category":"Sonstige mit der Informatik verbundene T\u00e4tigkeiten",
    "sg:postcode":"6045",
    "sg:province":"Luzern",
    "wof:name":"Informatik & Consulting Portmann (icp)",
    "wof:placetype":"venue"
},
  "geometry": {"coordinates":[8.3723993301,47.0498924255],"type":"Point"}
}