{
  "type": "Feature",
  "properties": {
    "iso:country":"CH",
    "sg:address":"1773",
    "sg:city":"L\u00e9chelles",
    "sg:orig_category":"Instandhaltung U Reparatur von Automobilen Tankstellen",
    "sg:phone":"+41 79 230 67 22",
    "sg:postcode":"1773",
    "sg:province":"Fribourg",
    "wof:name":"Garage Rossy Sa",
    "wof:placetype":"venue"
},
  "geometry": {"coordinates":[7.0170350075,46.8294792175],"type":"Point"}
}