{
  "type": "Feature",
  "properties": {
    "iso:country":"CH",
    "sg:address":"D\u00e4hlh\u00f6lzliweg 3",
    "sg:city":"Bern",
    "sg:orig_category":"Softwareentwicklung U beratung",
    "sg:phone":"+41 31 368 12 80",
    "sg:postcode":"3005",
    "sg:province":"Bern",
    "wof:name":"Medi Informatik Ag",
    "wof:placetype":"venue"
},
  "geometry": {"coordinates":[7.4558849335,46.94165802],"type":"Point"}
}