{
  "type": "Feature",
  "properties": {
    "iso:country":"CH",
    "sg:address":"Via Tuleu",
    "sg:city":"Bonaduz",
    "sg:orig_category":"Bauschreinerei Herstellung von M\u00f6beln verschiedener Art",
    "sg:phone":"+41 81 641 12 12",
    "sg:postcode":"7402",
    "sg:province":"Graubunden",
    "wof:name":"Franz Proyer M\u00f6belschreinerei",
    "wof:placetype":"venue"
},
  "geometry": {"coordinates":[9.386809,46.810467],"type":"Point"}
}