{
  "type": "Feature",
  "properties": {
    "iso:country":"CH",
    "sg:address":"Via Cantonale",
    "sg:city":"Comano",
    "sg:classifiers":[
        {
            "category":"Restaurant",
            "type":"Food & Drink"
        }
    ],
    "sg:phone":"+41 91 941 38 65",
    "sg:postcode":"6949",
    "sg:province":"Ticino",
    "wof:name":"Osteria Del Centro",
    "wof:placetype":"venue"
},
  "geometry": {"coordinates":[8.9549350739,46.0368766785],"type":"Point"}
}