{
  "type": "Feature",
  "properties": {
    "iso:country":"CH",
    "sg:address":"Bernerring 5",
    "sg:city":"Basel",
    "sg:orig_category":"Architekturb\u00fcros",
    "sg:phone":"+41 61 281 32 00",
    "sg:postcode":"4054",
    "sg:province":"Basel-Stadt",
    "wof:name":"Seeger Architekten",
    "wof:placetype":"venue"
},
  "geometry": {"coordinates":[7.574766,47.546352],"type":"Point"}
}