{
  "type": "Feature",
  "properties": {
    "iso:country":"CH",
    "sg:address":"Fronhofenstrasse 8",
    "sg:city":"Stans",
    "sg:orig_category":"Handel mit Automobilteilen U Zubeh\u00f6r Handelsvermittlung U Grosshandel mit Automobilteilen U Zubeh\u00f6r",
    "sg:phone":"+41 56 664 00 75",
    "sg:postcode":"6370",
    "sg:province":"Nidwalden",
    "wof:name":"Manrico Masetta Handel M.oldtimer-ersatzteilen",
    "wof:placetype":"venue"
},
  "geometry": {"coordinates":[8.3174819946,47.2825775146],"type":"Point"}
}