{
  "type": "Feature",
  "properties": {
    "iso:country":"CH",
    "sg:address":"Luzernerring 124",
    "sg:city":"Basel",
    "sg:orig_category":"Bauspenglerei Zimmerei, Dachdeckerei, Bauspenglerei U Abdichtung",
    "sg:phone":"+41 61 321 00 66",
    "sg:postcode":"4056",
    "sg:province":"Basel-Stadt",
    "wof:name":"Senn Ag, Spenglerei Und Sanit\u00e4re Installationen",
    "wof:placetype":"venue"
},
  "geometry": {"coordinates":[7.564462,47.565964],"type":"Point"}
}