{
  "type": "Feature",
  "properties": {
    "addr:full":"Napoleonstrasse 4 Visp Valais 3930",
    "addr:housenumber":"4",
    "addr:postcode":"3930",
    "addr:street":"Napoleonstrasse",
    "iso:country":"CH",
    "sg:address":"Napoleonstrasse 4",
    "sg:city":"Visp",
    "sg:orig_category":"Detailhandel mit Bekleidung Detailhandel mit Damenbekleidung",
    "sg:phone":"+41 27 946 51 35",
    "sg:postcode":"3930",
    "sg:province":"Valais",
    "wof:name":"Boutique Ciao Ciao, Lilo Blatter",
    "wof:placetype":"venue"
},
  "geometry": {"coordinates":[7.881548,46.291656],"type":"Point"}
}