{
  "type": "Feature",
  "properties": {
    "iso:country":"CH",
    "sg:address":"Hauptstrasse 48",
    "sg:city":"Muotathal",
    "sg:classifiers":[
        {
            "category":"Insurance",
            "subcategory":"Insurance Agent",
            "type":"Services"
        }
    ],
    "sg:phone":"+41 41 830 20 10",
    "sg:postcode":"6436",
    "sg:province":"Schwyz",
    "sg:tags":[
        "versicherungsagenturen",
        "-broker"
    ],
    "wof:name":"Z\u00fcrich-versicherungen Agentur Herrn Dominik Heinzer",
    "wof:placetype":"venue"
},
  "geometry": {"coordinates":[8.7577676773,46.9740447998],"type":"Point"}
}