{
  "type": "Feature",
  "properties": {
    "iso:country":"CH",
    "sg:address":"Bernerstrasse Nord 160",
    "sg:city":"Z\u00fcrich",
    "sg:orig_category":"Herstellung von Hebezeugen U F\u00f6rdermitteln",
    "sg:postcode":"8064",
    "sg:province":"Z\u00fcrich",
    "wof:name":"Industrie-service Roth Jakob Transportger\u00e4te; Reperatur, Dienstleistungen",
    "wof:placetype":"venue"
},
  "geometry": {"coordinates":[8.4883346558,47.3947219849],"type":"Point"}
}