{
  "type": "Feature",
  "properties": {
    "addr:full":"Chemin Des Charmettes 9 1003 Lausanne Case Postale 3710 Lausanne Vaud 1002",
    "addr:housenumber":"9",
    "addr:postcode":"1003;3710;1002",
    "addr:street":"Chemin Des Charmettes;Postale",
    "iso:country":"CH",
    "sg:address":"Chemin Des Charmettes 9 1003 Lausanne Case Postale 3710",
    "sg:city":"Lausanne",
    "sg:orig_category":"Advokaturb\u00fcros",
    "sg:phone":"+41 21 320 60 20",
    "sg:postcode":"1002",
    "sg:province":"Vaud",
    "wof:name":"M. Rossinelli & G. Capt",
    "wof:placetype":"venue"
},
  "geometry": {"coordinates":[6.628451,46.519192],"type":"Point"}
}