{
  "type": "Feature",
  "properties": {
    "iso:country":"CH",
    "sg:address":"Albert Oeristrasse 7",
    "sg:city":"Riehen",
    "sg:orig_category":"Alters U Pflegeheime Wohnheime",
    "sg:phone":"+41 61 641 24 94",
    "sg:postcode":"4125",
    "sg:province":"Basel-Stadt",
    "wof:name":"Dominikus-verein Riehen",
    "wof:placetype":"venue"
},
  "geometry": {"coordinates":[7.656103,47.583031],"type":"Point"}
}