{
  "type": "Feature",
  "properties": {
    "iso:country":"CH",
    "sg:address":"La Maisonnette",
    "sg:city":"Villars-sur-ollon",
    "sg:orig_category":"Detailhandel mit Damenbekleidung",
    "sg:phone":"+41 24 495 14 92",
    "sg:postcode":"1884",
    "sg:province":"Vaud",
    "wof:name":"Janine Gendre Couture Janine",
    "wof:placetype":"venue"
},
  "geometry": {"coordinates":[7.055008,46.296967],"type":"Point"}
}