{
  "type": "Feature",
  "properties": {
    "iso:country":"CH",
    "sg:address":"Str. Cantonale Casella Postale",
    "sg:city":"Quartino",
    "sg:classifiers":[
        {
            "category":"Food & Beverages",
            "subcategory":"Groceries & Convenience Stores",
            "type":"Retail Goods"
        }
    ],
    "sg:phone":"+41 91 858 10 09",
    "sg:postcode":"6572",
    "sg:province":"Ticino",
    "sg:tags":[
        "product",
        "related"
    ],
    "wof:name":"Pastinella Ag Stabilimento Trinca",
    "wof:placetype":"venue"
},
  "geometry": {"coordinates":[8.8953781128,46.1506347656],"type":"Point"}
}