{
  "type": "Feature",
  "properties": {
    "iso:country":"CH",
    "sg:address":"8634",
    "sg:city":"Hombrechtikon",
    "sg:orig_category":"Betrieb von Sportanlagen",
    "sg:postcode":"8634",
    "sg:province":"Z\u00fcrich",
    "wof:name":"L\u00fctzelseebad - Genossenschaft",
    "wof:placetype":"venue"
},
  "geometry": {"coordinates":[8.76694,47.250534],"type":"Point"}
}