{
  "type": "Feature",
  "properties": {
    "iso:country":"CH",
    "sg:address":"Rue Principale 27",
    "sg:city":"B\u00e9vilard",
    "sg:orig_category":"Detailhandel mit M\u00f6beln Detailhandel mit M\u00f6beln U Haushaltsgegenst\u00e4nden",
    "sg:phone":"+41 32 492 16 07",
    "sg:postcode":"2735",
    "sg:province":"Bern",
    "wof:name":"Int\u00e9rieur-cr\u00e9ation, Wenger E.",
    "wof:placetype":"venue"
},
  "geometry": {"coordinates":[7.2806749344,47.2372055054],"type":"Point"}
}