{
  "type": "Feature",
  "properties": {
    "addr:full":"S\u00e9prais Montavon Jura 2857",
    "addr:housenumber":"2857",
    "iso:country":"CH",
    "sg:address":"S\u00e9prais",
    "sg:city":"Montavon",
    "sg:orig_category":"Architektur U Ingenieurb\u00fcros Elektroinstallation",
    "sg:phone":"+41 32 426 82 40",
    "sg:postcode":"2857",
    "sg:province":"Jura",
    "wof:name":"Voillat Bureau D'etudes S\u00e0rl R\u00e9alisation De Toutes \u00e9tudes Dans Le Domaine \u00e9lectronique Et Informatique",
    "wof:placetype":"venue"
},
  "geometry": {"coordinates":[7.236435,47.372318],"type":"Point"}
}