{
  "type": "Feature",
  "properties": {
    "iso:country":"CH",
    "sg:address":"Dorf",
    "sg:city":"Marbach",
    "sg:classifiers":[
        {
            "category":"Banks & Credit Unions",
            "subcategory":"Bank",
            "type":"Services"
        }
    ],
    "sg:phone":"+41 34 493 36 26",
    "sg:postcode":"6196",
    "sg:province":"Luzern",
    "wof:name":"Raiffeisenbank Escholzmatt, Filiale Marbach",
    "wof:placetype":"venue"
},
  "geometry": {"coordinates":[7.900251,46.854748],"type":"Point"}
}