{
  "type": "Feature",
  "properties": {
    "iso:country":"CH",
    "sg:address":"Rue Du L\u00e9man 7",
    "sg:city":"Gen\u00e8ve",
    "sg:orig_category":"Detailhandel mit Musikinstrumenten",
    "sg:phone":"+41 79 200 89 64",
    "sg:postcode":"1201",
    "sg:province":"Gen\u00e8ve",
    "wof:name":"Music Store Cornelia Barrada",
    "wof:placetype":"venue"
},
  "geometry": {"coordinates":[6.1515197754,46.2115402222],"type":"Point"}
}