{
  "type": "Feature",
  "properties": {
    "iso:country":"CH",
    "sg:address":"Im D\u00f6rfli 25",
    "sg:city":"Meilen",
    "sg:orig_category":"Softwareentwicklung U beratung",
    "sg:postcode":"8706",
    "sg:province":"Z\u00fcrich",
    "wof:name":"Forsoft, D. Forrer",
    "wof:placetype":"venue"
},
  "geometry": {"coordinates":[8.6640443802,47.2640762329],"type":"Point"}
}