{
  "type": "Feature",
  "properties": {
    "iso:country":"CH",
    "sg:address":"Zunzgerstrasse 8",
    "sg:city":"Sissach",
    "sg:orig_category":"Detailhandel mit Fleisch U Fleischwaren",
    "sg:postcode":"4450",
    "sg:province":"Basel-Landschaft",
    "wof:name":"Metzgerei H\u00f6dl Franz",
    "wof:placetype":"venue"
},
  "geometry": {"coordinates":[8.6776065826,47.2644920349],"type":"Point"}
}