{
  "type": "Feature",
  "properties": {
    "iso:country":"CH",
    "sg:address":"La Fenatte 2942 Alle Case Postale 113",
    "sg:city":"Alle",
    "sg:orig_category":"Herstellung von Metallkonstruktionen Mechanik",
    "sg:phone":"+41 24 471 55 88",
    "sg:postcode":"2942",
    "sg:province":"Jura",
    "wof:name":"Chervaz Roland",
    "wof:placetype":"venue"
},
  "geometry": {"coordinates":[6.9609351158,46.2472343445],"type":"Point"}
}