{
  "type": "Feature",
  "properties": {
    "iso:country":"CH",
    "sg:address":"Thunstrasse 13",
    "sg:city":"Oberdiessbach",
    "sg:orig_category":"Bauschreinerei Detailhandel mit M\u00f6beln U Haushaltsgegenst\u00e4nden",
    "sg:phone":"+41 31 771 01 11",
    "sg:postcode":"3672",
    "sg:province":"Bern",
    "wof:name":"P. Jenni Ag Oberdiessbach",
    "wof:placetype":"venue"
},
  "geometry": {"coordinates":[7.618491,46.837765],"type":"Point"}
}