{
  "type": "Feature",
  "properties": {
    "iso:country":"CH",
    "sg:address":"Spillg\u00e4ssli 2",
    "sg:city":"Eich",
    "sg:orig_category":"Unternehmensberatung",
    "sg:phone":"+41 41 461 06 46",
    "sg:postcode":"6205",
    "sg:province":"Luzern",
    "wof:name":"Judith Wirth Wirth Coaching",
    "wof:placetype":"venue"
},
  "geometry": {"coordinates":[8.1677675247,47.151386261],"type":"Point"}
}