{
  "type": "Feature",
  "properties": {
    "iso:country":"CH",
    "sg:address":"Hauptstrasse 49",
    "sg:city":"B\u00e4ttwil",
    "sg:orig_category":"Detailhandel mit M\u00f6beln U Haushaltsgegenst\u00e4nden Einbau von Schreinerwaren",
    "sg:postcode":"4112",
    "sg:province":"Solothurn",
    "wof:name":"Torrado & Partner Gmbh",
    "wof:placetype":"venue"
},
  "geometry": {"coordinates":[7.5051779747,47.4895515442],"type":"Point"}
}