{
  "type": "Feature",
  "properties": {
    "iso:country":"CH",
    "sg:address":"Via Breganzona 10",
    "sg:city":"Lugano",
    "sg:orig_category":"Fahrschulen, Flugschulen",
    "sg:phone":"+41 91 966 09 47",
    "sg:postcode":"6900",
    "sg:province":"Ticino",
    "wof:name":"Mario Fiscalini Autoscuola",
    "wof:placetype":"venue"
},
  "geometry": {"coordinates":[8.9389324188,46.0081977844],"type":"Point"}
}