{
  "type": "Feature",
  "properties": {
    "iso:country":"CH",
    "sg:address":"Dorfstrasse 67",
    "sg:city":"Spreitenbach",
    "sg:orig_category":"Detailhandel mit Blumen U Pflanzen Fachdetailhandel in Verkaufsr\u00e4umen",
    "sg:phone":"+41 56 401 50 50",
    "sg:postcode":"8957",
    "sg:province":"Aargau",
    "wof:name":"Blumen Muntwyler",
    "wof:placetype":"venue"
},
  "geometry": {"coordinates":[8.364234,47.417793],"type":"Point"}
}