{
  "type": "Feature",
  "properties": {
    "iso:country":"CH",
    "sg:address":"Gewerbestrasse 22",
    "sg:city":"Bern",
    "sg:orig_category":"Fotografische Laboratorien Fotografisches Gewerbe U fotografische Laboratorien",
    "sg:phone":"+41 26 436 51 15",
    "sg:postcode":"3012",
    "sg:province":"Bern",
    "wof:name":"J.m. Diaprint Sa.",
    "wof:placetype":"venue"
},
  "geometry": {"coordinates":[7.1393618584,46.7819786072],"type":"Point"}
}