{
  "type": "Feature",
  "properties": {
    "iso:country":"CH",
    "sg:address":"Nidaugasse 68",
    "sg:city":"Biel/bienne",
    "sg:orig_category":"Detailhandel mit Uhren U Schmuck Reparatur von Uhren U Schmuck",
    "sg:phone":"+41 32 322 47 27",
    "sg:postcode":"2502",
    "sg:province":"Bern",
    "wof:name":"Jacques Tissot Sa Uhren & Bijouterie",
    "wof:placetype":"venue"
},
  "geometry": {"coordinates":[7.2466359138,47.1377830505],"type":"Point"}
}