{
  "type": "Feature",
  "properties": {
    "addr:full":"Schorenstrasse 68 Gwatt Bern 3645",
    "addr:housenumber":"68",
    "addr:postcode":"3645",
    "addr:street":"Schorenstrasse",
    "iso:country":"CH",
    "sg:address":"Schorenstrasse 68",
    "sg:city":"Gwatt",
    "sg:orig_category":"Cnc Cylindrical Profile Grinding",
    "sg:phone":"+41 33 335 44 55",
    "sg:postcode":"3645",
    "sg:province":"Bern",
    "wof:name":"Stecher Ceramicparts Gmbh",
    "wof:placetype":"venue"
},
  "geometry": {"coordinates":[7.618259,46.729176],"type":"Point"}
}