{
  "type": "Feature",
  "properties": {
    "iso:country":"CH",
    "sg:address":"Florentins Place Des 1 1204 Gen\u00e8ve. Postfach",
    "sg:city":"Gen\u00e8ve",
    "sg:orig_category":"Unternehmensberatung",
    "sg:phone":"+41 71 242 62 62",
    "sg:postcode":"1201",
    "sg:province":"Gen\u00e8ve",
    "wof:name":"Ime Management Consulting Ag",
    "wof:placetype":"venue"
},
  "geometry": {"coordinates":[9.3815670013,47.4428215027],"type":"Point"}
}