{
  "type": "Feature",
  "properties": {
    "iso:country":"CH",
    "sg:address":"Zentralstrasse 18/",
    "sg:city":"Uster",
    "sg:orig_category":"Detailhandel mit Waren verschiedener Art, Hauptrichtung Nahrungsmittel",
    "sg:phone":"+41 19414246",
    "sg:postcode":"8610",
    "sg:province":"Z\u00fcrich",
    "wof:name":"Oepfelbaum\u00acgenossenschaft F\u00fcr Organische Produkte",
    "wof:placetype":"venue"
},
  "geometry": {"coordinates":[8.7174978256,47.3470573425],"type":"Point"}
}