{
  "type": "Feature",
  "properties": {
    "iso:country":"CH",
    "sg:address":"Chemin De La Colline 4",
    "sg:city":"Moudon",
    "sg:orig_category":"Sonstiger spezialisierter Hoch U Tiefbau",
    "sg:phone":"+41 21 905 17 96",
    "sg:postcode":"1510",
    "sg:province":"Vaud",
    "wof:name":"Fardel Georges",
    "wof:placetype":"venue"
},
  "geometry": {"coordinates":[6.793484211,46.6738014221],"type":"Point"}
}