{
  "type": "Feature",
  "properties": {
    "iso:country":"CH",
    "sg:address":"Esplanade L\u00e9opold-robert 2",
    "sg:city":"Neuch\u00e2tel",
    "sg:orig_category":"B\u00e4ckereien Konditoreien",
    "sg:phone":"+41 32 725 45 25",
    "sg:postcode":"2000",
    "sg:province":"Neuch\u00e2tel",
    "wof:name":"Boulangerie Du Port",
    "wof:placetype":"venue"
},
  "geometry": {"coordinates":[6.935751,46.991184],"type":"Point"}
}