{
  "type": "Feature",
  "properties": {
    "iso:country":"CH",
    "sg:address":"Industriestrasse 592",
    "sg:city":"Oberbuchsiten",
    "sg:orig_category":"Maschinenbau",
    "sg:postcode":"4625",
    "sg:province":"Solothurn",
    "wof:name":"Probag W\u00e4rmetechnik Heizelemente Elektrisch",
    "wof:placetype":"venue"
},
  "geometry": {"coordinates":[7.7752728462,47.3074302673],"type":"Point"}
}