{
  "type": "Feature",
  "properties": {
    "iso:country":"CH",
    "sg:address":"9472",
    "sg:city":"Grabs",
    "sg:classifiers":[
        {
            "category":"Education",
            "subcategory":"Vocational School",
            "type":"Public Place"
        }
    ],
    "sg:phone":"+41 71 377 12 21",
    "sg:postcode":"9472",
    "sg:province":"St. Gallen",
    "sg:tags":[
        "koch-",
        "haushaltschulen"
    ],
    "wof:name":"Haushaltungsschule",
    "wof:placetype":"venue"
},
  "geometry": {"coordinates":[9.4469852448,47.1806488037],"type":"Point"}
}