{
  "type": "Feature",
  "properties": {
    "iso:country":"CH",
    "sg:address":"Sundgauerstrasse 5 4055 Basel. Postfach",
    "sg:city":"Basel",
    "sg:orig_category":"Elektroinstallation",
    "sg:phone":"+41 61 261 30 00",
    "sg:postcode":"4003",
    "sg:province":"Basel-Stadt",
    "wof:name":"Elektro-locher Ag",
    "wof:placetype":"venue"
},
  "geometry": {"coordinates":[7.5629048347,47.5646324158],"type":"Point"}
}