{
  "type": "Feature",
  "properties": {
    "iso:country":"CH",
    "sg:address":"Leimackerstrasse 22",
    "sg:city":"B\u00f6singen",
    "sg:orig_category":"D\u00e4mmung gegen K\u00e4lte, W\u00e4rme, Schall U Ersch\u00fctterung",
    "sg:phone":"+41 31 747 81 28",
    "sg:postcode":"3178",
    "sg:province":"Fribourg",
    "wof:name":"Plastitherm Flachdachabdichtungen",
    "wof:placetype":"venue"
},
  "geometry": {"coordinates":[7.2326440811,46.8965835571],"type":"Point"}
}