{
  "type": "Feature",
  "properties": {
    "iso:country":"CH",
    "sg:address":"Bahnhofstrasse 8",
    "sg:city":"Stans",
    "sg:orig_category":"Fachdetailhandel in Verkaufsr\u00e4umen Herstellung von Reiseartikeln, Leder U Sattlerwaren",
    "sg:phone":"+41 27 721 65 30",
    "sg:postcode":"6370",
    "sg:province":"Nidwalden",
    "wof:name":"Keller Martigny Sa",
    "wof:placetype":"venue"
},
  "geometry": {"coordinates":[7.090907,46.106747],"type":"Point"}
}