{
  "type": "Feature",
  "properties": {
    "iso:country":"CH",
    "sg:address":"Bahnhofstrasse 3 3860 Meiringen. Postfach 512",
    "sg:city":"Meiringen",
    "sg:orig_category":"Detailhandel mit Bekleidung Herstellung von Sportger\u00e4ten",
    "sg:phone":"+41 33 972 52 72",
    "sg:postcode":"3860",
    "sg:province":"Bern",
    "wof:name":"Glatthard Sport Ag",
    "wof:placetype":"venue"
},
  "geometry": {"coordinates":[8.185506,46.728153],"type":"Point"}
}