{
  "type": "Feature",
  "properties": {
    "iso:country":"CH",
    "sg:address":"Rehb\u00fchlstrasse 17",
    "sg:city":"Uster",
    "sg:orig_category":"Grosshandel mit Datenverarbeitungsger\u00e4ten Grosshandel mit Software",
    "sg:postcode":"8610",
    "sg:province":"Z\u00fcrich",
    "wof:name":"Olivier Naegeli Aon-allservice",
    "wof:placetype":"venue"
},
  "geometry": {"coordinates":[8.7289943695,47.3554382324],"type":"Point"}
}