{
  "type": "Feature",
  "properties": {
    "iso:country":"CH",
    "sg:address":"Gobat Rue Albert- 21",
    "sg:city":"Tramelan",
    "sg:orig_category":"Softwareentwicklung U beratung",
    "sg:phone":"+41 32 487 62 78",
    "sg:postcode":"2720",
    "sg:province":"Bern",
    "wof:name":"Ncplus, Bangarter Markus",
    "wof:placetype":"venue"
},
  "geometry": {"coordinates":[7.1025872231,47.2240447998],"type":"Point"}
}