{
  "type": "Feature",
  "properties": {
    "iso:country":"CH",
    "sg:address":"Pl. De La Concorde",
    "sg:city":"Granges-marnand",
    "sg:orig_category":"RESTAURANTS: TEA-ROOMS",
    "sg:phone":"+41 26 668 21 46",
    "sg:postcode":"1523",
    "sg:province":"Vaud",
    "wof:name":"Woelffel-nendaz M\u00e9lanie",
    "wof:placetype":"venue"
},
  "geometry": {"coordinates":[6.8875250816,46.7635803223],"type":"Point"}
}