{
  "type": "Feature",
  "properties": {
    "iso:country":"CH",
    "sg:address":"H\u00fchnerhubelstrasse 12",
    "sg:city":"Belp",
    "sg:orig_category":"Einbau von Schreinerwaren Herstellung von K\u00fcchenm\u00f6beln",
    "sg:phone":"+41 55 240 73 88",
    "sg:postcode":"3123",
    "sg:province":"Bern",
    "wof:name":"H\u00e4rti-k\u00fcchen Ag",
    "wof:placetype":"venue"
},
  "geometry": {"coordinates":[8.8517036438,47.2601242065],"type":"Point"}
}