{
  "type": "Feature",
  "properties": {
    "iso:country":"CH",
    "sg:address":"Rue Fran\u00e7ois-perr\u00e9ard 4",
    "sg:city":"Ch\u00eane-bourg",
    "sg:orig_category":"Einrahmungen",
    "sg:phone":"+41 22 343 88 32",
    "sg:postcode":"1225",
    "sg:province":"Gen\u00e8ve",
    "wof:name":"Michel Rosso Encadrements",
    "wof:placetype":"venue"
},
  "geometry": {"coordinates":[6.1970257759,46.1952476501],"type":"Point"}
}