{
  "type": "Feature",
  "properties": {
    "addr:full":"Seestrasse 10 8880 Walenstadt. Postfach 135 Walenstadt St. Gallen 8880",
    "addr:housenumber":"10;135;st.",
    "addr:postcode":"8880 walenstadt.;8880",
    "addr:street":"Seestrasse;Postfach;Walenstadt",
    "iso:country":"CH",
    "sg:address":"Seestrasse 10 8880 Walenstadt. Postfach 135",
    "sg:city":"Walenstadt",
    "sg:orig_category":"Detailhandel mit Beleuchtungs U Haushaltsgegenst\u00e4nden Detailhandel mit Sportartikeln",
    "sg:phone":"+41 81 735 12 58",
    "sg:postcode":"8880",
    "sg:province":"St. Gallen",
    "wof:name":"Thaler Caesar, Eisenwaren Haushalt Eisenwaren U. Haushaltartikel; Handel",
    "wof:placetype":"venue"
},
  "geometry": {"coordinates":[9.314336,47.124428],"type":"Point"}
}