{
  "type": "Feature",
  "properties": {
    "iso:country":"CH",
    "sg:address":"Gaselweidstrasse 37",
    "sg:city":"Gasel",
    "sg:orig_category":"Detailhandel mit M\u00f6beln Innenausbau",
    "sg:phone":"+41 34 402 20 12",
    "sg:postcode":"3144",
    "sg:province":"Bern",
    "wof:name":"Stada-m\u00f6bel",
    "wof:placetype":"venue"
},
  "geometry": {"coordinates":[7.757589817,46.9491271973],"type":"Point"}
}