{
  "type": "Feature",
  "properties": {
    "iso:country":"CH",
    "sg:address":"Chemin De La Plage 2 1180 Rolle. Postfach",
    "sg:city":"Rolle",
    "sg:orig_category":"Herstellung von Heizk\u00f6rpern U kesseln f\u00fcr die Zentralheizung",
    "sg:postcode":"1180",
    "sg:province":"Vaud",
    "wof:name":"Z\u00dcrcher Paul S\u00e0rl",
    "wof:placetype":"venue"
},
  "geometry": {"coordinates":[6.3458709717,46.4622459412],"type":"Point"}
}