{
  "type": "Feature",
  "properties": {
    "iso:country":"CH",
    "sg:address":"Sihlquai 244",
    "sg:city":"Z\u00fcrich",
    "sg:orig_category":"Grosshandel mit Sportartikeln",
    "sg:phone":"+41 32 751 17 54",
    "sg:postcode":"8005",
    "sg:province":"Z\u00fcrich",
    "wof:name":"G\u00e9rald Zingre Importation",
    "wof:placetype":"venue"
},
  "geometry": {"coordinates":[7.0628380775,47.0605545044],"type":"Point"}
}