{
  "type": "Feature",
  "properties": {
    "iso:country":"CH",
    "sg:address":"Rosenb\u00fchler 529",
    "sg:city":"Eschen",
    "sg:orig_category":"Aktivit\u00e4ten der Generalunternehmen im Baugewerbe Dienstleistungen von Beteiligungsgesellschaften",
    "sg:phone":"+41 71 911 22 33",
    "sg:postcode":"9492",
    "wof:name":"Habl\u00fctzel Verwaltungen",
    "wof:placetype":"venue"
},
  "geometry": {"coordinates":[9.049265,47.472645],"type":"Point"}
}