{
  "type": "Feature",
  "properties": {
    "iso:country":"CH",
    "sg:address":"Viale Carlo Cattaneo 1",
    "sg:city":"Lugano",
    "sg:orig_category":"Unclassifiable Establishments",
    "sg:postcode":"6900",
    "sg:province":"Ticino",
    "wof:name":"W.b.s. Worldwide Business Services Sa",
    "wof:placetype":"venue"
},
  "geometry": {"coordinates":[8.9559516907,46.0057563782],"type":"Point"}
}