{
  "type": "Feature",
  "properties": {
    "iso:country":"CH",
    "sg:address":"Steinbruchhof 1",
    "sg:city":"Obernau",
    "sg:orig_category":"Allgemeiner Hoch U Tiefbau Hoch U Tiefbau",
    "sg:phone":"+41 41 320 70 60",
    "sg:postcode":"6012",
    "sg:province":"Luzern",
    "wof:name":"Bs Zeier Ag Bausanierungen",
    "wof:placetype":"venue"
},
  "geometry": {"coordinates":[8.255031,47.033382],"type":"Point"}
}