{
  "type": "Feature",
  "properties": {
    "iso:country":"CH",
    "sg:address":"Alte Gerlafingenstrasse 9",
    "sg:city":"Biberist",
    "sg:orig_category":"Non-Classified Establishments",
    "sg:postcode":"4562",
    "sg:province":"Solothurn",
    "wof:name":"T. Z. Automobile, T. Zivkovic",
    "wof:placetype":"venue"
},
  "geometry": {"coordinates":[7.5660281181,47.1791915894],"type":"Point"}
}