{
  "type": "Feature",
  "properties": {
    "iso:country":"CH",
    "sg:address":"Alpenstrasse 5",
    "sg:city":"Zug",
    "sg:orig_category":"Detailhandel mit Schuhen",
    "sg:phone":"+41 41 710 26 01",
    "sg:postcode":"6300",
    "sg:province":"Zug",
    "wof:name":"Laufsteg Heidi R\u00e4ber Arche Schuhe",
    "wof:placetype":"venue"
},
  "geometry": {"coordinates":[8.5142526627,47.172000885],"type":"Point"}
}