{
  "type": "Feature",
  "properties": {
    "iso:country":"CH",
    "sg:address":"Dorfstrasse 24",
    "sg:city":"Arni-islisberg",
    "sg:orig_category":"Verlagsgewerbe",
    "sg:phone":"+41 56 640 10 14",
    "sg:postcode":"8905",
    "sg:province":"Aargau",
    "wof:name":"Garuda Verlag",
    "wof:placetype":"venue"
},
  "geometry": {"coordinates":[8.4412469864,47.323638916],"type":"Point"}
}