{
  "type": "Feature",
  "properties": {
    "iso:country":"CH",
    "sg:address":"Emmentalstrasse 23",
    "sg:city":"Konolfingen",
    "sg:orig_category":"Nationale Postdienste",
    "sg:phone":"+41 31 791 01 00",
    "sg:postcode":"3510",
    "sg:province":"Bern",
    "wof:name":"Die Schweizerische Post",
    "wof:placetype":"venue"
},
  "geometry": {"coordinates":[7.624019146,46.8811187744],"type":"Point"}
}