{
  "type": "Feature",
  "properties": {
    "iso:country":"CH",
    "sg:address":"Basweri 4",
    "sg:city":"Ried-brig",
    "sg:classifiers":[
        {
            "category":"Restaurant",
            "type":"Food & Drink"
        }
    ],
    "sg:phone":"+41 27 923 28 77",
    "sg:postcode":"3911",
    "sg:province":"Valais",
    "wof:name":"Restaurant Waldesrand",
    "wof:placetype":"venue"
},
  "geometry": {"coordinates":[8.0261697769,46.3145141602],"type":"Point"}
}