{
  "type": "Feature",
  "properties": {
    "iso:country":"CH",
    "sg:address":"Postfach 4809 6304 Zug. Postfach 4809",
    "sg:city":"Zug",
    "sg:orig_category":"Grosshandel mit Datenverarbeitungsger\u00e4ten Softwareentwicklung U beratung",
    "sg:phone":"+41 56 241 16 18",
    "sg:postcode":"6304",
    "sg:province":"Zug",
    "wof:name":"Wsinformatik Gmbh",
    "wof:placetype":"venue"
},
  "geometry": {"coordinates":[8.3280220032,47.5251655579],"type":"Point"}
}