{
  "type": "Feature",
  "properties": {
    "iso:country":"CH",
    "sg:address":"Salvatorenstrasse 52 7000 Chur. Postfach",
    "sg:city":"Chur",
    "sg:orig_category":"Grosshandel mit Datenverarbeitungsger\u00e4ten Hardwareberatung",
    "sg:phone":"+41 81 250 15 30",
    "sg:postcode":"7001",
    "sg:province":"Graubunden",
    "wof:name":"Chriba B\u00fcro-& Kommunikations-dienstl.",
    "wof:placetype":"venue"
},
  "geometry": {"coordinates":[9.5187292099,46.849647522],"type":"Point"}
}