{
  "type": "Feature",
  "properties": {
    "iso:country":"CH",
    "sg:address":"Unter Biel",
    "sg:city":"T\u00f6rbel",
    "sg:orig_category":"Herstellung von Reiseartikeln, Leder U Sattlerwaren",
    "sg:phone":"+41 27 973 15 66",
    "sg:postcode":"3923",
    "sg:province":"Valais",
    "wof:name":"Kraft Albin Raumgestaltung.",
    "wof:placetype":"venue"
},
  "geometry": {"coordinates":[8.2618379593,46.4867591858],"type":"Point"}
}