{
  "type": "Feature",
  "properties": {
    "iso:country":"CH",
    "sg:address":"Eiweg 10",
    "sg:city":"Gelterkinden",
    "sg:orig_category":"Siebdruck Sonstiges Druckgewerbe",
    "sg:phone":"+41 56 621 89 00",
    "sg:postcode":"4460",
    "sg:province":"Basel-Landschaft",
    "wof:name":"Copy - Center Roth Vreni",
    "wof:placetype":"venue"
},
  "geometry": {"coordinates":[8.2767076492,47.3470535278],"type":"Point"}
}