{
  "type": "Feature",
  "properties": {
    "iso:country":"CH",
    "sg:address":"Eselweg 280",
    "sg:city":"R\u00fcnenberg",
    "sg:orig_category":"Pensionskassen",
    "sg:phone":"+41 61 981 21 59",
    "sg:postcode":"4497",
    "sg:province":"Basel-Landschaft",
    "wof:name":"Personalf\u00fcrsorgestiftung Der Firma Heinz Bitterlin Ag",
    "wof:placetype":"venue"
},
  "geometry": {"coordinates":[7.878967762,47.4317855835],"type":"Point"}
}