{
  "type": "Feature",
  "properties": {
    "iso:country":"CH",
    "sg:address":"Ringgasse 1",
    "sg:city":"Hinterforst",
    "sg:classifiers":[
        {
            "category":"Restaurant",
            "type":"Food & Drink"
        }
    ],
    "sg:phone":"+41 71 755 55 53",
    "sg:postcode":"9452",
    "sg:province":"St. Gallen",
    "wof:name":"Pizzeria Turi Galati",
    "wof:placetype":"venue"
},
  "geometry": {"coordinates":[9.5322055817,47.3581466675],"type":"Point"}
}