{
  "type": "Feature",
  "properties": {
    "iso:country":"CH",
    "sg:address":"Ridlistrasse 47",
    "sg:city":"Beckenried",
    "sg:orig_category":"G\u00fcterbef\u00f6rderung im Strassenverkehr",
    "sg:phone":"+41 41 620 65 04",
    "sg:postcode":"6375",
    "sg:province":"Nidwalden",
    "wof:name":"Hugo K\u00e4slin Transporte Gmbh",
    "wof:placetype":"venue"
},
  "geometry": {"coordinates":[8.4572706223,46.9695205688],"type":"Point"}
}