{
  "type": "Feature",
  "properties": {
    "iso:country":"CH",
    "sg:address":"Petite Mine",
    "sg:city":"Travers",
    "sg:orig_category":"Grosshandel mit Holz U Baustoffen",
    "sg:phone":"+41 32 863 17 48",
    "sg:postcode":"2105",
    "sg:province":"Neuch\u00e2tel",
    "wof:name":"Wyss Pierre",
    "wof:placetype":"venue"
},
  "geometry": {"coordinates":[6.6732201576,46.9389686584],"type":"Point"}
}