{
  "type": "Feature",
  "properties": {
    "iso:country":"CH",
    "sg:address":"7154",
    "sg:city":"Ruschein",
    "sg:classifiers":[
        {
            "category":"Restaurant",
            "type":"Food & Drink"
        }
    ],
    "sg:phone":"+41 81 925 19 96",
    "sg:postcode":"7154",
    "sg:province":"Graubunden",
    "wof:name":"Ustria Sonne",
    "wof:placetype":"venue"
},
  "geometry": {"coordinates":[9.1933546066,46.784740448],"type":"Point"}
}