{
  "type": "Feature",
  "properties": {
    "iso:country":"CH",
    "sg:address":"Bois-de-la-chapelle Av. 11 1213 Petit-lancy. Postfach",
    "sg:city":"Petit-lancy",
    "sg:orig_category":"Sonstiges Versicherungsgewerbe",
    "sg:phone":"+41 22 793 12 02",
    "sg:postcode":"1213",
    "sg:province":"Gen\u00e8ve",
    "wof:name":"Ads, Cabinet De Courtage, Dominique Dubarry",
    "wof:placetype":"venue"
},
  "geometry": {"coordinates":[6.1077852249,46.1909561157],"type":"Point"}
}