{
  "type": "Feature",
  "properties": {
    "iso:country":"CH",
    "sg:address":"Ursprungstrasse 105",
    "sg:city":"M\u00fcnchenbuchsee",
    "sg:orig_category":"Politische Parteien CVP",
    "sg:phone":"+41 31 351 13 89",
    "sg:postcode":"3053",
    "sg:province":"Bern",
    "wof:name":"Cvp Ortspartei",
    "wof:placetype":"venue"
},
  "geometry": {"coordinates":[7.4577651024,47.0161972046],"type":"Point"}
}