{
  "type": "Feature",
  "properties": {
    "iso:country":"CH",
    "sg:address":"Riedmattweg 5 3250 Lyss. Postfach 245",
    "sg:city":"Lyss",
    "sg:orig_category":"Architekturb\u00fcros",
    "sg:phone":"+41 61 711 73 29",
    "sg:postcode":"3250",
    "sg:province":"Bern",
    "wof:name":"Hans-peter Knaus Architekturb\u00fcro",
    "wof:placetype":"venue"
},
  "geometry": {"coordinates":[7.595527,47.489124],"type":"Point"}
}