{
  "type": "Feature",
  "properties": {
    "iso:country":"CH",
    "sg:address":"Hauptstrasse 42",
    "sg:city":"Bennwil",
    "sg:orig_category":"Elektrizit\u00e4tsversorgung Herstellung von k\u00e4lte U lufttechnischen Erzeugnissen f\u00fcr gewerbliche Zwecke",
    "sg:phone":"+41 61 951 12 54",
    "sg:postcode":"4431",
    "sg:province":"Basel-Landschaft",
    "wof:name":"W\u00e4rmeversorgung Bennwil Ag",
    "wof:placetype":"venue"
},
  "geometry": {"coordinates":[7.7805051804,47.404045105],"type":"Point"}
}