{
  "type": "Feature",
  "properties": {
    "iso:country":"CH",
    "sg:address":"Boulevard De Grancy 24",
    "sg:city":"Lausanne",
    "sg:orig_category":"Detailhandel mit Brot, Back U S\u00fcsswaren",
    "sg:phone":"+41 21 616 27 72",
    "sg:postcode":"1006",
    "sg:province":"Vaud",
    "wof:name":"Tavel M.-h.",
    "wof:placetype":"venue"
},
  "geometry": {"coordinates":[6.629209,46.51561],"type":"Point"}
}