{
  "type": "Feature",
  "properties": {
    "iso:country":"CH",
    "sg:address":"L\u00e4ttichstrasse 25",
    "sg:city":"Baar",
    "sg:orig_category":"Schwimmb\u00e4der",
    "sg:phone":"+41 41 761 51 88",
    "sg:postcode":"6340",
    "sg:province":"Zug",
    "wof:name":"Hallen-& Freibad",
    "wof:placetype":"venue"
},
  "geometry": {"coordinates":[8.537779808,47.2010116577],"type":"Point"}
}