{
  "type": "Feature",
  "properties": {
    "iso:country":"CH",
    "sg:address":"Kirchweg 20",
    "sg:city":"Nunningen",
    "sg:orig_category":"Vorschulen, Kinderg\u00e4rten",
    "sg:phone":"+41 61 791 90 62",
    "sg:postcode":"4208",
    "sg:province":"Solothurn",
    "wof:name":"Kindergarten",
    "wof:placetype":"venue"
},
  "geometry": {"coordinates":[7.615776062,47.3937034607],"type":"Point"}
}