{
  "type": "Feature",
  "properties": {
    "iso:country":"CH",
    "sg:address":"Tanneggstrasse 5",
    "sg:city":"Arbon",
    "sg:orig_category":"Herstellung von sonstigen elektrischen Ausr\u00fcstungen",
    "sg:phone":"+41 71469922",
    "sg:postcode":"9320",
    "sg:province":"Thurgau",
    "wof:name":"Heimelektronik Britschgi & Co.",
    "wof:placetype":"venue"
},
  "geometry": {"coordinates":[9.4209804535,47.5100631714],"type":"Point"}
}