{
  "type": "Feature",
  "properties": {
    "iso:country":"CH",
    "sg:address":"Alte Steinhauserstrasse 21 6330 Cham. Postfach 556",
    "sg:city":"Cham",
    "sg:orig_category":"Grosshandel mit B\u00fcromaschinen Sonstige mit der Informatik verbundene T\u00e4tigkeiten",
    "sg:phone":"+41 41 741 62 10",
    "sg:postcode":"6330",
    "sg:province":"Zug",
    "wof:name":"Zemp Data.",
    "wof:placetype":"venue"
},
  "geometry": {"coordinates":[8.4744729996,47.188709259],"type":"Point"}
}