{
  "type": "Feature",
  "properties": {
    "addr:full":"Eigenstrasse 9 Th\u00f6rigen Bern 3367",
    "addr:housenumber":"9",
    "addr:postcode":"3367",
    "addr:street":"Eigenstrasse",
    "iso:country":"CH",
    "sg:address":"Eigenstrasse 9",
    "sg:city":"Th\u00f6rigen",
    "sg:orig_category":"Architekturb\u00fcros Innenarchitekturb\u00fcros",
    "sg:phone":"+41 62 961 28 26",
    "sg:postcode":"3367",
    "sg:province":"Bern",
    "wof:name":"B. Meister Architektur & Innengestaltung",
    "wof:placetype":"venue"
},
  "geometry": {"coordinates":[7.725511,47.177162],"type":"Point"}
}