{
  "type": "Feature",
  "properties": {
    "iso:country":"CH",
    "sg:address":"Dorfstrasse 76",
    "sg:city":"R\u00fcdlingen",
    "sg:orig_category":"Wirtschaftspr\u00fcfung, Steuerberatung U Treuhand",
    "sg:postcode":"8455",
    "sg:province":"Schaffhausen",
    "wof:name":"Ast Sieber Treuhand Ag",
    "wof:placetype":"venue"
},
  "geometry": {"coordinates":[8.5714426041,47.5809707642],"type":"Point"}
}