{
  "type": "Feature",
  "properties": {
    "iso:country":"CH",
    "sg:address":"Kreuzgasse 3816 Burglauenen. Postfach",
    "sg:city":"Burglauenen",
    "sg:orig_category":"Zimmerei, Dachdeckerei, Bauspenglerei U Abdichtung",
    "sg:postcode":"3816",
    "sg:province":"Bern",
    "wof:name":"Graf Holzbau/s\u00e4gerei",
    "wof:placetype":"venue"
},
  "geometry": {"coordinates":[7.9763259888,46.6364631653],"type":"Point"}
}