{
  "type": "Feature",
  "properties": {
    "iso:country":"CH",
    "sg:address":"Zentralstrasse 52",
    "sg:city":"Biel/bienne",
    "sg:classifiers":[
        {
            "category":"Travel",
            "subcategory":"Hotels & Motels",
            "type":"Entertainment"
        }
    ],
    "sg:postcode":"2500",
    "sg:province":"Bern",
    "sg:tags":[
        "hotels",
        "mit",
        "restaurant"
    ],
    "wof:name":"Nordrest Ag.",
    "wof:placetype":"venue"
},
  "geometry": {"coordinates":[7.2476258278,47.1356925964],"type":"Point"}
}