{
  "type": "Feature",
  "properties": {
    "iso:country":"CH",
    "sg:address":"Spissstrasse 6",
    "sg:city":"Zermatt",
    "sg:orig_category":"Sanit\u00e4r U Heizungsinstallation Sanit\u00e4rinstallation",
    "sg:phone":"+41 27 967 35 87",
    "sg:postcode":"3920",
    "sg:province":"Valais",
    "wof:name":"Andr\u00e9 Arnold Sanit\u00e4re Anlagen & Heizungen",
    "wof:placetype":"venue"
},
  "geometry": {"coordinates":[7.7488360405,46.0244636536],"type":"Point"}
}