{
  "type": "Feature",
  "properties": {
    "iso:country":"CH",
    "sg:address":"Birchh\u00f6lzliweg 18",
    "sg:city":"Gebenstorf",
    "sg:orig_category":"Herstellung von sonstigen elektrischen Ausr\u00fcstungen",
    "sg:postcode":"5412",
    "sg:province":"Aargau",
    "wof:name":"The Harley Organisation S\u00e0rl",
    "wof:placetype":"venue"
},
  "geometry": {"coordinates":[8.2366323471,47.4769592285],"type":"Point"}
}