{
  "type": "Feature",
  "properties": {
    "iso:country":"CH",
    "sg:address":"Gewerbestrasse 6",
    "sg:city":"Unter\u00e4geri",
    "sg:orig_category":"Vermietung U Verpachtung von eigenen Immobilien",
    "sg:phone":"+41 41 754 71 21",
    "sg:postcode":"6314",
    "sg:province":"Zug",
    "wof:name":"Odinga & Partner Gmbh",
    "wof:placetype":"venue"
},
  "geometry": {"coordinates":[8.5735826492,47.1344451904],"type":"Point"}
}