{
  "type": "Feature",
  "properties": {
    "iso:country":"CH",
    "sg:address":"Centrale Place 16",
    "sg:city":"Martigny",
    "sg:orig_category":"RESTAURANTS: TEA-ROOMS",
    "sg:postcode":"1920",
    "sg:province":"Valais",
    "wof:name":"Leroux Thierry",
    "wof:placetype":"venue"
},
  "geometry": {"coordinates":[7.0723800659,46.1011772156],"type":"Point"}
}