{
  "type": "Feature",
  "properties": {
    "iso:country":"CH",
    "sg:address":"Pierre Rue Saint- 8",
    "sg:city":"Fribourg",
    "sg:orig_category":"Allgemeiner Hoch U Tiefbau",
    "sg:phone":"+41 41 462 71 30",
    "sg:postcode":"1700",
    "sg:province":"Fribourg",
    "wof:name":"Krt Engineering + Handel Gmbh",
    "wof:placetype":"venue"
},
  "geometry": {"coordinates":[8.223583,47.131149],"type":"Point"}
}