{
  "type": "Feature",
  "properties": {
    "iso:country":"CH",
    "sg:address":"Rue Jakob-rosius 20 2500 Biel/bienne. Postfach",
    "sg:city":"Biel/bienne",
    "sg:orig_category":"Vermietung U Verpachtung von eigenen Immobilien",
    "sg:postcode":"2502",
    "sg:province":"Bern",
    "wof:name":"Association Immobili\u00e8re De L'union Chr\u00e9tienne De Bienne (aiuc)",
    "wof:placetype":"venue"
},
  "geometry": {"coordinates":[7.2454209328,47.1418304443],"type":"Point"}
}