{
  "type": "Feature",
  "properties": {
    "iso:country":"CH",
    "sg:address":"1981",
    "sg:city":"Vex",
    "sg:orig_category":"Grosshandel mit Nahrungsmitteln, Getr\u00e4nken U Tabakwaren ohne ausgepr\u00e4gten Schwerpunkt",
    "sg:phone":"+41 27 207 27 30",
    "sg:postcode":"1981",
    "sg:province":"Valais",
    "wof:name":"Moix Sylvie",
    "wof:placetype":"venue"
},
  "geometry": {"coordinates":[7.3954100609,46.2054786682],"type":"Point"}
}