{
  "type": "Feature",
  "properties": {
    "iso:country":"CH",
    "sg:address":"R\u00f6merstrasse 3 4600 Olten. Postfach",
    "sg:city":"Olten",
    "sg:orig_category":"Architektur U Ingenieurb\u00fcros Architekturb\u00fcros",
    "sg:phone":"+41 62 212 06 06",
    "sg:postcode":"4603",
    "sg:province":"Solothurn",
    "wof:name":"Stuber Edi Germann Thomas Dipl. Architekten Eth/sia Ag",
    "wof:placetype":"venue"
},
  "geometry": {"coordinates":[7.904237,47.3512],"type":"Point"}
}