{
  "type": "Feature",
  "properties": {
    "iso:country":"CH",
    "sg:address":"Lerzenstr. 12",
    "sg:city":"Dietikon",
    "sg:classifiers":[
        {
            "category":"Wholesale",
            "subcategory":"Machinery & Supplies",
            "type":"Manufacturing & Wholesale Goods"
        }
    ],
    "sg:phone":"+41 4117451515",
    "sg:postcode":"8953",
    "sg:province":"Z\u00fcrich",
    "sg:tags":[
        "equipment",
        "equipement",
        "precision",
        "timekeeping"
    ],
    "wof:name":"Kaba Benzing (schweiz) Ag",
    "wof:placetype":"venue"
},
  "geometry": {"coordinates":[8.3991775513,47.4180335999],"type":"Point"}
}