{
  "type": "Feature",
  "properties": {
    "iso:country":"CH",
    "sg:address":"Florastrasse 8a",
    "sg:city":"Dietikon",
    "sg:orig_category":"Herstellung von Radio U Fernsehger\u00e4ten sowie phono U videotechnischen Ger\u00e4ten",
    "sg:phone":"+41 17744500",
    "sg:postcode":"8953",
    "sg:province":"Z\u00fcrich",
    "wof:name":"Sound Company Trunz A. Ag",
    "wof:placetype":"venue"
},
  "geometry": {"coordinates":[8.4008102417,47.4044837952],"type":"Point"}
}