{
  "type": "Feature",
  "properties": {
    "iso:country":"CH",
    "sg:address":"6983",
    "sg:city":"Magliaso",
    "sg:orig_category":"Pensionskassen",
    "sg:postcode":"6983",
    "sg:province":"Ticino",
    "wof:name":"Fondazione Di Previdenza A Favore Del Personale Della Ditta Fratelli Boscacci Sa",
    "wof:placetype":"venue"
},
  "geometry": {"coordinates":[8.8828201294,45.9825286865],"type":"Point"}
}