{
  "type": "Feature",
  "properties": {
    "iso:country":"CH",
    "sg:address":"Rue De La Moli\u00e8re 13",
    "sg:city":"Del\u00e9mont",
    "sg:orig_category":"Sonstiges Versicherungsgewerbe",
    "sg:phone":"+41 32 422 58 09",
    "sg:postcode":"2800",
    "sg:province":"Jura",
    "wof:name":"Garanta Assurances Agence G\u00e9n\u00e9rale",
    "wof:placetype":"venue"
},
  "geometry": {"coordinates":[7.3481559753,47.3636894226],"type":"Point"}
}