{
  "type": "Feature",
  "properties": {
    "iso:country":"CH",
    "sg:address":"6197",
    "sg:city":"Schangnau",
    "sg:orig_category":"Sessellifte and Skilifte",
    "sg:phone":"+41 34 493 34 75",
    "sg:postcode":"6197",
    "sg:province":"Bern",
    "wof:name":"Skilift-genossenschaft Roseggli-gemeinenw\u00e4ngen",
    "wof:placetype":"venue"
},
  "geometry": {"coordinates":[7.8605628014,46.8275260925],"type":"Point"}
}