{
  "type": "Feature",
  "properties": {
    "iso:country":"CH",
    "sg:address":"Kloosweg 10",
    "sg:city":"Biel/bienne",
    "sg:orig_category":"Architektur U Ingenieurb\u00fcros",
    "sg:postcode":"2500",
    "sg:province":"Bern",
    "wof:name":"Sperandio Ernst",
    "wof:placetype":"venue"
},
  "geometry": {"coordinates":[7.247429,47.145046],"type":"Point"}
}