{
  "type": "Feature",
  "properties": {
    "addr:full":"Shop Ville Bahnhofpassage Z\u00fcrich Z\u00fcrich 8001",
    "addr:postcode":"8001",
    "addr:street":"Bahnhofpassage",
    "iso:country":"CH",
    "sg:address":"Shop Ville Bahnhofpassage",
    "sg:city":"Z\u00fcrich",
    "sg:orig_category":"Detailhandel mit Brot, Back U S\u00fcsswaren",
    "sg:phone":"+41 62 929 16 06",
    "sg:postcode":"8001",
    "sg:province":"Z\u00fcrich",
    "wof:name":"Klosterb\u00e4ckerei Zur M\u00fchle Achermann Edith",
    "wof:placetype":"venue"
},
  "geometry": {"coordinates":[7.839125,47.227325],"type":"Point"}
}