{
  "type": "Feature",
  "properties": {
    "iso:country":"CH",
    "sg:address":"P\u00e9rolles Boulevard De 37 1700 Fribourg. Postfach",
    "sg:city":"Freiburg",
    "sg:orig_category":"Herstellung von k\u00e4lte U lufttechnischen Erzeugnissen f\u00fcr gewerbliche Zwecke",
    "sg:phone":"+41 22 342 85 85",
    "sg:postcode":"1700",
    "sg:province":"Fribourg",
    "wof:name":"Coorditec, Christian Chambaz",
    "wof:placetype":"venue"
},
  "geometry": {"coordinates":[6.136991024,46.1837768555],"type":"Point"}
}