{
  "type": "Feature",
  "properties": {
    "iso:country":"CH",
    "sg:address":"1963",
    "sg:city":"V\u00e9troz",
    "sg:orig_category":"Interessenvertretungen",
    "sg:postcode":"1963",
    "sg:province":"Valais",
    "wof:name":"Fondation Fontannaz D\u00e9l\u00e8ze",
    "wof:placetype":"venue"
},
  "geometry": {"coordinates":[7.2825698853,46.2257461548],"type":"Point"}
}