{
  "type": "Feature",
  "properties": {
    "iso:country":"CH",
    "sg:address":"Blumenweg 1",
    "sg:city":"Kollbrunn",
    "sg:orig_category":"Architekturb\u00fcros",
    "sg:phone":"+41 52 383 17 25",
    "sg:postcode":"8483",
    "sg:province":"Z\u00fcrich",
    "wof:name":"Frank Schneeberger Dipl. Architekt Eth Sia",
    "wof:placetype":"venue"
},
  "geometry": {"coordinates":[8.776263237,47.4558944702],"type":"Point"}
}