{
  "type": "Feature",
  "properties": {
    "iso:country":"CH",
    "sg:address":"Kirchstrasse 118",
    "sg:city":"Wabern",
    "sg:orig_category":"Sportvereine Turnen Vereine Damen",
    "sg:phone":"+41 31 971 62 48",
    "sg:postcode":"3084",
    "sg:province":"Bern",
    "wof:name":"Damen-& Frauenriege",
    "wof:placetype":"venue"
},
  "geometry": {"coordinates":[7.4401569366,46.9296607971],"type":"Point"}
}