{
  "type": "Feature",
  "properties": {
    "iso:country":"CH",
    "sg:address":"Hinter-langmoos",
    "sg:city":"H\u00fctten",
    "sg:orig_category":"Herstellung von Metallkonstruktionen Schlossereien",
    "sg:phone":"+41 17881582",
    "sg:postcode":"8825",
    "sg:province":"Z\u00fcrich",
    "wof:name":"Ernst Landolt Kunstschlosserei & Metallbau",
    "wof:placetype":"venue"
},
  "geometry": {"coordinates":[8.6455507278,47.1739883423],"type":"Point"}
}