{
  "type": "Feature",
  "properties": {
    "iso:country":"CH",
    "sg:address":"Poska 9",
    "sg:city":"Triesen",
    "sg:orig_category":"Einzelhandel mit Automobilteilen U Zubeh\u00f6r",
    "sg:phone":"+41 19304668",
    "sg:postcode":"9495",
    "wof:name":"Vakkas Cil Mega Print Auto-shop",
    "wof:placetype":"venue"
},
  "geometry": {"coordinates":[8.8006277084,47.3266410828],"type":"Point"}
}