{
  "type": "Feature",
  "properties": {
    "iso:country":"CH",
    "sg:address":"Winterthurerstrasse 7",
    "sg:city":"Sirnach",
    "sg:orig_category":"Parf\u00fcmerien U sonstiger Detailhandel mit kosmetischen Artikeln U K\u00f6rperpflegemitteln",
    "sg:phone":"+41 76 376 98 93",
    "sg:postcode":"8370",
    "sg:province":"Thurgau",
    "wof:name":"Philipp M\u00fcggler",
    "wof:placetype":"venue"
},
  "geometry": {"coordinates":[8.9954528809,47.4620285034],"type":"Point"}
}