{
  "type": "Feature",
  "properties": {
    "iso:country":"CH",
    "sg:address":"6664",
    "sg:city":"Vergeletto",
    "sg:orig_category":"Gewinnung von Natursteinen f\u00fcr den Bau Herstellung von sonstigen Produkten aus nichtmetallischen Min",
    "sg:phone":"+41 91 797 15 80",
    "sg:postcode":"6664",
    "sg:province":"Ticino",
    "wof:name":"Lino Candolfi Cava Piano Delle Cascine",
    "wof:placetype":"venue"
},
  "geometry": {"coordinates":[8.6004047394,46.2272758484],"type":"Point"}
}