{
  "type": "Feature",
  "properties": {
    "iso:country":"CH",
    "sg:address":"Florastrasse 18 8953 Dietikon. Postfach",
    "sg:city":"Dietikon",
    "sg:orig_category":"Geb\u00e4ude, Wohnungsreinigung Reinigungsgewerbe",
    "sg:phone":"+41 31 333 65 65",
    "sg:postcode":"8953",
    "sg:province":"Z\u00fcrich",
    "wof:name":"Econom Reinigungen Ag",
    "wof:placetype":"venue"
},
  "geometry": {"coordinates":[7.4436860085,46.9578475952],"type":"Point"}
}