{
  "type": "Feature",
  "properties": {
    "iso:country":"CH",
    "sg:address":"Innere G\u00fcterstrasse 4",
    "sg:city":"Zug",
    "sg:orig_category":"Unclassifiable Establishments",
    "sg:phone":"+41 41 710 41 61",
    "sg:postcode":"6300",
    "sg:province":"Zug",
    "wof:name":"Private Equity Holding Ag",
    "wof:placetype":"venue"
},
  "geometry": {"coordinates":[8.5169610977,47.1777954102],"type":"Point"}
}