{
  "type": "Feature",
  "properties": {
    "iso:country":"CH",
    "sg:address":"1950 Sion Case Postale 202",
    "sg:city":"Sion",
    "sg:orig_category":"Wirtschafts- and Arbeitgeberverb\u00e4nde",
    "sg:postcode":"1951",
    "sg:province":"Valais",
    "wof:name":"F\u00e9d.valaisanne Du Commerce,de L'industrie & De L'agriculture",
    "wof:placetype":"venue"
},
  "geometry": {"coordinates":[7.3633999825,46.2366981506],"type":"Point"}
}