{
  "type": "Feature",
  "properties": {
    "iso:country":"CH",
    "sg:address":"R\u00fctistrasse 2",
    "sg:city":"Baden",
    "sg:orig_category":"Architektur U Ingenieurb\u00fcros",
    "sg:postcode":"5400",
    "sg:province":"Aargau",
    "wof:name":"Part Of The Art Architecture And Design Spirig Marc",
    "wof:placetype":"venue"
},
  "geometry": {"coordinates":[7.497316,47.22929],"type":"Point"}
}