{
  "type": "Feature",
  "properties": {
    "iso:country":"CH",
    "sg:address":"5014",
    "sg:city":"Gretzenbach",
    "sg:orig_category":"Sportvereine Sch\u00fctzen",
    "sg:postcode":"5014",
    "sg:province":"Solothurn",
    "wof:name":"Sch\u00fctzengesellschaft",
    "wof:placetype":"venue"
},
  "geometry": {"coordinates":[7.9965882301,47.3613014221],"type":"Point"}
}