{
  "type": "Feature",
  "properties": {
    "iso:country":"CH",
    "sg:address":"Avenue De La Gare 8 1870 Monthey. Postfach",
    "sg:city":"Monthey",
    "sg:orig_category":"Wirtschaftspr\u00fcfung, Steuerberatung U Treuhand",
    "sg:phone":"+41 24 471 61 51",
    "sg:postcode":"1870",
    "sg:province":"Valais",
    "wof:name":"Fiduciaire Marmillod Daniel Sa Bureau Fiduciaire, Prise De Tous Mandats, Notamm. Tenue De Comptabilit\u00e9 Etc",
    "wof:placetype":"venue"
},
  "geometry": {"coordinates":[6.9482049942,46.2528457642],"type":"Point"}
}