{
  "type": "Feature",
  "properties": {
    "iso:country":"CH",
    "sg:address":"K\u00fcfersberg 28",
    "sg:city":"B\u00fctschwil",
    "sg:orig_category":"Unclassifiable Establishments",
    "sg:postcode":"9606",
    "sg:province":"St. Gallen",
    "wof:name":"Bachmann Architektur Ag",
    "wof:placetype":"venue"
},
  "geometry": {"coordinates":[9.0688838959,47.3599739075],"type":"Point"}
}