{
  "type": "Feature",
  "properties": {
    "iso:country":"CH",
    "sg:address":"Hauptstrasse 46",
    "sg:city":"Wolfenschiessen",
    "sg:classifiers":[
        {
            "category":"Travel",
            "subcategory":"Hotels & Motels",
            "type":"Entertainment"
        }
    ],
    "sg:postcode":"6386",
    "sg:province":"Nidwalden",
    "sg:tags":[
        "hotels",
        "mit",
        "restaurant"
    ],
    "wof:name":"W. Odermatt, Gasthaus Alpina",
    "wof:placetype":"venue"
},
  "geometry": {"coordinates":[8.3937225342,46.9039726257],"type":"Point"}
}