{
  "type": "Feature",
  "properties": {
    "iso:country":"CH",
    "sg:address":"Voa Principala 26",
    "sg:city":"Lenzerheide/lai",
    "sg:orig_category":"Vermittlung von Immobilien",
    "sg:phone":"+41 19104287",
    "sg:postcode":"7078",
    "sg:province":"Graubunden",
    "wof:name":"Hans Sauber Liegenschaften",
    "wof:placetype":"venue"
},
  "geometry": {"coordinates":[8.5980463028,47.3085861206],"type":"Point"}
}