{
  "type": "Feature",
  "properties": {
    "iso:country":"CH",
    "sg:address":"Fbg St Germain 5",
    "sg:city":"Porrentruy",
    "sg:classifiers":[
        {
            "category":"Professional",
            "subcategory":"Engineering",
            "type":"Services"
        }
    ],
    "sg:phone":"+41 32 465 70 70",
    "sg:postcode":"2900",
    "sg:province":"Jura",
    "sg:tags":[
        "machine",
        "-",
        "mechanical"
    ],
    "wof:name":"Ernest Roth Sa",
    "wof:placetype":"venue"
},
  "geometry": {"coordinates":[7.0784888268,47.417755127],"type":"Point"}
}