{
  "type": "Feature",
  "properties": {
    "iso:country":"CH",
    "sg:address":"Dorfbachstrasse 2 4663 Aarburg. Postfach 125",
    "sg:city":"Aarburg",
    "sg:orig_category":"Herstellung von Fenstern U T\u00fcren aus Holz Herstellung von K\u00fcchenm\u00f6beln",
    "sg:phone":"+41 62 787 31 31",
    "sg:postcode":"4663",
    "sg:province":"Aargau",
    "wof:name":"Franke K\u00fcchentechnik Ag",
    "wof:placetype":"venue"
},
  "geometry": {"coordinates":[7.899078846,47.3201904297],"type":"Point"}
}