{
  "type": "Feature",
  "properties": {
    "iso:country":"CH",
    "sg:address":"Haldenstrasse 1b",
    "sg:city":"R\u00fcmlang",
    "sg:orig_category":"Unternehmensberatung",
    "sg:phone":"+41 18180314",
    "sg:postcode":"8153",
    "sg:province":"Z\u00fcrich",
    "wof:name":"Stark G\u00fcnter, Unternehmensberatung",
    "wof:placetype":"venue"
},
  "geometry": {"coordinates":[8.5236644745,47.4456062317],"type":"Point"}
}