{
  "type": "Feature",
  "properties": {
    "iso:country":"CH",
    "sg:address":"Wylihof 11a 4542 Luterbach. Postfach",
    "sg:city":"Luterbach",
    "sg:orig_category":"RESTAURANTS: TEA-ROOMS",
    "sg:phone":"+41 32 682 28 28",
    "sg:postcode":"4542",
    "sg:province":"Solothurn",
    "wof:name":"Kaufmann Gastro Gmbh Gastronomiebetrieb",
    "wof:placetype":"venue"
},
  "geometry": {"coordinates":[7.5903000832,47.2241783142],"type":"Point"}
}