{
  "type": "Feature",
  "properties": {
    "iso:country":"CH",
    "sg:address":"5314",
    "sg:city":"Kleind\u00f6ttingen",
    "sg:orig_category":"Schulpflegen",
    "sg:phone":"+41 62 771 47 57",
    "sg:postcode":"5314",
    "sg:province":"Aargau",
    "wof:name":"Primarschulpflege Der Gemeinde Leimbach",
    "wof:placetype":"venue"
},
  "geometry": {"coordinates":[8.1701097488,47.2744483948],"type":"Point"}
}