{
  "type": "Feature",
  "properties": {
    "addr:full":"Z\u00fcrichstrasse 27 Biel/bienne Bern 2504",
    "addr:housenumber":"27",
    "addr:postcode":"2504",
    "addr:street":"Zuerichstrasse",
    "iso:country":"CH",
    "sg:address":"Z\u00fcrichstrasse 27",
    "sg:city":"Biel/bienne",
    "sg:orig_category":"Architektur U Ingenieurb\u00fcros Herstellung von Metallkonstruktionen",
    "sg:phone":"+41 32 341 26 84",
    "sg:postcode":"2504",
    "sg:province":"Bern",
    "wof:name":"R\u00fcdiger H. Gr\u00fcnert",
    "wof:placetype":"venue"
},
  "geometry": {"coordinates":[7.292536,47.161903],"type":"Point"}
}