{
  "type": "Feature",
  "properties": {
    "iso:country":"CH",
    "sg:address":"Av. De Neuch\u00e2tel 32 St-aubin. 2024 St-aubin-sauges. Postfach",
    "sg:city":"St-aubin-sauges",
    "sg:orig_category":"Zimmerei, Dachdeckerei, Bauspenglerei U Abdichtung",
    "sg:postcode":"2024",
    "sg:province":"Neuch\u00e2tel",
    "wof:name":"Perrenoud Et Fils G.",
    "wof:placetype":"venue"
},
  "geometry": {"coordinates":[6.7632799149,46.8871154785],"type":"Point"}
}