{
  "type": "Feature",
  "properties": {
    "iso:country":"CH",
    "sg:address":"Via Ressiga 2",
    "sg:city":"Giubiasco",
    "sg:orig_category":"Gartenbau Verlegen von Fliesen U Platten",
    "sg:phone":"+41 91 857 62 77",
    "sg:postcode":"6512",
    "sg:province":"Ticino",
    "wof:name":"Buletti Claudio & Co",
    "wof:placetype":"venue"
},
  "geometry": {"coordinates":[9.0053224564,46.1715774536],"type":"Point"}
}