{
  "type": "Feature",
  "properties": {
    "iso:country":"CH",
    "sg:address":"Lindengasse 3 5082 Kaisten. Postfach",
    "sg:city":"Kaisten",
    "sg:orig_category":"Grosshandel mit Sportartikeln Herstellung von Schmuck, Gold U Silberschmiedwaren",
    "sg:phone":"+41 62 874 22 03",
    "sg:postcode":"5082",
    "sg:province":"Aargau",
    "wof:name":"Tony M\u00fcller Sportpreise Ag",
    "wof:placetype":"venue"
},
  "geometry": {"coordinates":[8.0464725494,47.5394630432],"type":"Point"}
}