{
  "type": "Feature",
  "properties": {
    "iso:country":"CH",
    "sg:address":"Bodenacker 46",
    "sg:city":"Dulliken",
    "sg:orig_category":"G\u00fcterbef\u00f6rderung im Strassenverkehr",
    "sg:phone":"+41 33 733 21 71",
    "sg:postcode":"4657",
    "sg:province":"Solothurn",
    "wof:name":"Toni Zb\u00e4ren Transporte",
    "wof:placetype":"venue"
},
  "geometry": {"coordinates":[7.9516167641,47.3512878418],"type":"Point"}
}