{
  "type": "Feature",
  "properties": {
    "iso:country":"CH",
    "sg:address":"Sch\u00f6neggweg 1",
    "sg:city":"Goldau",
    "sg:orig_category":"Non-Classified Establishments",
    "sg:postcode":"6410",
    "sg:province":"Schwyz",
    "wof:name":"Gebr. Kennel Ag",
    "wof:placetype":"venue"
},
  "geometry": {"coordinates":[8.5432167053,47.0471343994],"type":"Point"}
}