{
  "type": "Feature",
  "properties": {
    "iso:country":"CH",
    "sg:address":"Amselweg 1",
    "sg:city":"Utzenstorf",
    "sg:orig_category":"Allgemeiner Hoch U Tiefbau",
    "sg:postcode":"3427",
    "sg:province":"Bern",
    "wof:name":"Wohnpark In Den Linden Ag",
    "wof:placetype":"venue"
},
  "geometry": {"coordinates":[7.560957,47.132656],"type":"Point"}
}