{
  "type": "Feature",
  "properties": {
    "iso:country":"CH",
    "sg:address":"Blegistrasse 13",
    "sg:city":"Baar",
    "sg:orig_category":"Unclassifiable Establishments",
    "sg:phone":"+41 19411814",
    "sg:postcode":"6340",
    "sg:province":"Zug",
    "wof:name":"Aero Consultants Holding Ag",
    "wof:placetype":"venue"
},
  "geometry": {"coordinates":[8.5692443848,47.2156867981],"type":"Point"}
}