{
  "type": "Feature",
  "properties": {
    "addr:full":"Zweierstrasse 139 Z\u00fcrich Z\u00fcrich 8003",
    "addr:housenumber":"139",
    "addr:postcode":"8003",
    "addr:street":"Zweierstrasse",
    "iso:country":"CH",
    "sg:address":"Zweierstrasse 139",
    "sg:city":"Z\u00fcrich",
    "sg:orig_category":"Chemische Reinigung W\u00e4schereien",
    "sg:phone":"+41 14630480",
    "sg:postcode":"8003",
    "sg:province":"Z\u00fcrich",
    "wof:name":"Daniel Graf Textilreinigung",
    "wof:placetype":"venue"
},
  "geometry": {"coordinates":[8.519656,47.370674],"type":"Point"}
}