{
  "type": "Feature",
  "properties": {
    "iso:country":"CH",
    "sg:address":"Furkastrasse 39",
    "sg:city":"Naters",
    "sg:orig_category":"Kauf U Verkauf von Immobilien auf eigene Rechnung",
    "sg:postcode":"3904",
    "sg:province":"Valais",
    "wof:name":"Widerfeld Ag",
    "wof:placetype":"venue"
},
  "geometry": {"coordinates":[7.9928798676,46.3247261047],"type":"Point"}
}