{
  "type": "Feature",
  "properties": {
    "iso:country":"CH",
    "sg:address":"Br\u00fchlgasse 39",
    "sg:city":"St.gallen",
    "sg:orig_category":"Detailhandel mit Textilien Detailhandel mit elektrischen Haushalts-,Radio U Fernsehger\u00e4ten sowie Mus",
    "sg:phone":"+41 71 222 27 26",
    "sg:postcode":"9000",
    "sg:province":"St. Gallen",
    "wof:name":"Brauchle + Co",
    "wof:placetype":"venue"
},
  "geometry": {"coordinates":[9.3788700104,47.4249382019],"type":"Point"}
}