{
  "type": "Feature",
  "properties": {
    "iso:country":"CH",
    "sg:address":"Dorfstrasse 38",
    "sg:city":"Opfikon",
    "sg:orig_category":"Unclassifiable Establishments",
    "sg:postcode":"8152",
    "sg:province":"Z\u00fcrich",
    "wof:name":"Strange Gmbh",
    "wof:placetype":"venue"
},
  "geometry": {"coordinates":[8.5767393112,47.4315032959],"type":"Point"}
}