{
  "type": "Feature",
  "properties": {
    "iso:country":"CH",
    "sg:address":"Zugerstrasse 76b",
    "sg:city":"Baar",
    "sg:orig_category":"Unternehmensberatung",
    "sg:postcode":"6340",
    "sg:province":"Zug",
    "wof:name":"Wiripax Ag",
    "wof:placetype":"venue"
},
  "geometry": {"coordinates":[8.519613266,47.1831130981],"type":"Point"}
}