{
  "type": "Feature",
  "properties": {
    "iso:country":"CH",
    "sg:address":"Via Lungolago Motta 68",
    "sg:city":"Melide",
    "sg:orig_category":"Tankstellen",
    "sg:phone":"+41 91 608 10 45",
    "sg:postcode":"6815",
    "sg:province":"Ticino",
    "wof:name":"Stazione Di Servizio City",
    "wof:placetype":"venue"
},
  "geometry": {"coordinates":[8.8345899582,45.9870796204],"type":"Point"}
}