{
  "type": "Feature",
  "properties": {
    "iso:country":"CH",
    "sg:address":"Seebahnstrasse 145 8003 Z\u00fcrich. Postfach",
    "sg:city":"Z\u00fcrich",
    "sg:orig_category":"Detailhandel mit elektrischen Haushalts-,Radio U Fernsehger\u00e4ten sowie Musikinstrumenten",
    "sg:postcode":"8001",
    "sg:province":"Z\u00fcrich",
    "wof:name":"Hi-fi-service Krebser Hi-fi-ger\u00e4te; Installation, Rep. Usw.",
    "wof:placetype":"venue"
},
  "geometry": {"coordinates":[8.5189990997,47.3739280701],"type":"Point"}
}