{
  "type": "Feature",
  "properties": {
    "iso:country":"CH",
    "sg:address":"Sch\u00fctzenmatte 3a 6362 Stansstad. Postfach",
    "sg:city":"Stansstad",
    "sg:orig_category":"Grosshandel mit chemischen Erzeugnissen",
    "sg:phone":"+41 13919125",
    "sg:postcode":"6362",
    "sg:province":"Nidwalden",
    "wof:name":"Fista Handels-& Recycling Ag",
    "wof:placetype":"venue"
},
  "geometry": {"coordinates":[8.5717277527,47.3325119019],"type":"Point"}
}