{
  "type": "Feature",
  "properties": {
    "iso:country":"CH",
    "sg:address":"Rue St-s\u00e9bastien 20",
    "sg:city":"Del\u00e9mont",
    "sg:orig_category":"Autogaragen G\u00fcterbef\u00f6rderung im Strassenverkehr",
    "sg:phone":"+41 32 422 78 91",
    "sg:postcode":"2800",
    "sg:province":"Jura",
    "wof:name":"Meuret Transport S\u00e0rl",
    "wof:placetype":"venue"
},
  "geometry": {"coordinates":[7.344069,47.352737],"type":"Point"}
}