{
  "type": "Feature",
  "properties": {
    "iso:country":"CH",
    "sg:address":"Nuce Rue De 3",
    "sg:city":"Vouvry",
    "sg:orig_category":"Herstellung von Konstruktionsteilen, Fertigbauteilen U Ausbauelementen aus Holz",
    "sg:postcode":"1896",
    "sg:province":"Valais",
    "wof:name":"Gottfried Gisler, Schreinerei",
    "wof:placetype":"venue"
},
  "geometry": {"coordinates":[8.6637849808,46.8756256104],"type":"Point"}
}