{
  "type": "Feature",
  "properties": {
    "iso:country":"CH",
    "sg:address":"Chemin Du Donjon 2 1470 Estavayer-le-lac. Postfach",
    "sg:city":"Estavayer-le-lac",
    "sg:orig_category":"Herstellung von Konstruktionsteilen, Fertigbauteilen U Ausbauelementen aus Holz",
    "sg:postcode":"1470",
    "sg:province":"Fribourg",
    "wof:name":"Soldati Marco",
    "wof:placetype":"venue"
},
  "geometry": {"coordinates":[6.8495402336,46.8509712219],"type":"Point"}
}