{
  "type": "Feature",
  "properties": {
    "iso:country":"CH",
    "sg:address":"Langfurrenstrasse 14",
    "sg:city":"Regensdorf",
    "sg:orig_category":"Sportvereine Sch\u00fctzen",
    "sg:phone":"+41 18406878",
    "sg:postcode":"8105",
    "sg:province":"Z\u00fcrich",
    "wof:name":"Feldsch\u00fctzenv.zh-neum\u00fcnster",
    "wof:placetype":"venue"
},
  "geometry": {"coordinates":[8.4697780609,47.4280166626],"type":"Point"}
}