{
  "type": "Feature",
  "properties": {
    "iso:country":"CH",
    "sg:address":"Zelglistrasse 15",
    "sg:city":"Aarau",
    "sg:orig_category":"Arztpraxen",
    "sg:phone":"+41 62 822 44 86",
    "sg:postcode":"5000",
    "sg:province":"Aargau",
    "wof:name":"Dr.med.manfred Eichenberger Spezialarzt Fmh",
    "wof:placetype":"venue"
},
  "geometry": {"coordinates":[8.047492,47.386265],"type":"Point"}
}