{
  "type": "Feature",
  "properties": {
    "iso:country":"CH",
    "sg:address":"Schmidtenbaumgarten 8a",
    "sg:city":"Oberlunkhofen",
    "sg:orig_category":"Vereine Musik/Blasmusik",
    "sg:phone":"+41 56 634 28 58",
    "sg:postcode":"8917",
    "sg:province":"Aargau",
    "wof:name":"Musikverein Lunkhofen",
    "wof:placetype":"venue"
},
  "geometry": {"coordinates":[8.3885011673,47.3121795654],"type":"Point"}
}