{
  "type": "Feature",
  "properties": {
    "iso:country":"CH",
    "sg:address":"Route Pierre-ozaire 34",
    "sg:city":"Savigny",
    "sg:orig_category":"Architektur U Ingenieurb\u00fcros",
    "sg:phone":"+41 32 932 40 20",
    "sg:postcode":"1073",
    "sg:province":"Vaud",
    "wof:name":"Nemotek Energy S\u00e0rl",
    "wof:placetype":"venue"
},
  "geometry": {"coordinates":[6.802529,47.041065],"type":"Point"}
}