{
  "type": "Feature",
  "properties": {
    "iso:country":"CH",
    "sg:address":"Pappelweg 25",
    "sg:city":"Bern",
    "sg:orig_category":"Unclassifiable Establishments",
    "sg:phone":"+41 31 922 05 50",
    "sg:postcode":"3013",
    "sg:province":"Bern",
    "wof:name":"Praxis F\u00fcr Nat\u00fcrliche Gesundheit Auderset Sibylle, Dipl. Farbtherapeutin",
    "wof:placetype":"venue"
},
  "geometry": {"coordinates":[7.448141098,46.9587974548],"type":"Point"}
}