{
  "type": "Feature",
  "properties": {
    "iso:country":"CH",
    "sg:address":"Furkastrasse 25",
    "sg:city":"Brig",
    "sg:orig_category":"Grosshandel mit chemischen Erzeugnissen",
    "sg:phone":"+41 21 616 77 51",
    "sg:postcode":"3900",
    "sg:province":"Valais",
    "wof:name":"Comtrade Sa Company For Trading And Clearing",
    "wof:placetype":"venue"
},
  "geometry": {"coordinates":[6.6292500496,46.5132713318],"type":"Point"}
}