{
  "type": "Feature",
  "properties": {
    "iso:country":"CH",
    "sg:address":"Hauptstrasse 6",
    "sg:city":"Ober\u00e4geri",
    "sg:classifiers":[
        {
            "category":"Restaurant",
            "type":"Food & Drink"
        }
    ],
    "sg:phone":"+41 41 750 12 44",
    "sg:postcode":"6315",
    "sg:province":"Zug",
    "wof:name":"Restaurant B\u00e4ren",
    "wof:placetype":"venue"
},
  "geometry": {"coordinates":[8.6136102676,47.1351051331],"type":"Point"}
}