{
  "type": "Feature",
  "properties": {
    "iso:country":"CH",
    "sg:address":"Moosmattstrasse 17 6005 Luzern. Postfach",
    "sg:city":"Luzern",
    "sg:orig_category":"Verwertung von Milch",
    "sg:phone":"+41 41 310 10 44",
    "sg:postcode":"6003",
    "sg:province":"Luzern",
    "wof:name":"Grossenbacher Ulrich Molkerei, Lebensmittel",
    "wof:placetype":"venue"
},
  "geometry": {"coordinates":[8.3036804199,47.040561676],"type":"Point"}
}