{
  "type": "Feature",
  "properties": {
    "iso:country":"CH",
    "sg:address":"Route De La Gare 5",
    "sg:city":"Penthalaz",
    "sg:orig_category":"Installation von Heizungs, L\u00fcftungs U Klimaanlagen",
    "sg:phone":"+41 21 862 12 12",
    "sg:postcode":"1305",
    "sg:province":"Vaud",
    "wof:name":"Ciat Sa",
    "wof:placetype":"venue"
},
  "geometry": {"coordinates":[6.52790308,46.6132354736],"type":"Point"}
}