{
  "type": "Feature",
  "properties": {
    "iso:country":"CH",
    "sg:address":"Bahnhofstrasse 22 8304 Wallisellen. Postfach",
    "sg:city":"Wallisellen",
    "sg:orig_category":"Grosshandel mit keramischen Erzeugnissen,Glaswaren U Tapeten",
    "sg:phone":"+41 18302075",
    "sg:postcode":"8304",
    "sg:province":"Z\u00fcrich",
    "wof:name":"Lekuwa Kurt Ledergerber Betriebseinrichtungen Vertr.",
    "wof:placetype":"venue"
},
  "geometry": {"coordinates":[8.5906982422,47.4141197205],"type":"Point"}
}