{
  "type": "Feature",
  "properties": {
    "iso:country":"CH",
    "sg:address":"Krankenhausstrasse 24",
    "sg:city":"Thun",
    "sg:orig_category":"Erschliessung von Grundst\u00fccken",
    "sg:postcode":"3600",
    "sg:province":"Bern",
    "wof:name":"Igk-kultursiedlung",
    "wof:placetype":"venue"
},
  "geometry": {"coordinates":[7.6310620308,46.7621574402],"type":"Point"}
}