{
  "type": "Feature",
  "properties": {
    "addr:full":"Aeschengraben 20 4051 Basel. Postfach 156 Basel Basel-Stadt 4010",
    "addr:housenumber":"20;156",
    "addr:postcode":"4051;4010",
    "addr:street":"Aeschengraben;Postfach",
    "iso:country":"CH",
    "sg:address":"Aeschengraben 20 4051 Basel. Postfach 156",
    "sg:city":"Basel",
    "sg:orig_category":"Aktivit\u00e4t der Bankinstitute",
    "sg:phone":"+41 848 845 400",
    "sg:postcode":"4010",
    "sg:province":"Basel-Stadt",
    "wof:name":"Banque Migros",
    "wof:placetype":"venue"
},
  "geometry": {"coordinates":[6.627537,46.522739],"type":"Point"}
}