{
  "type": "Feature",
  "properties": {
    "iso:country":"CH",
    "sg:address":"B\u00f6hlstrasse 12",
    "sg:city":"Wolfertswil",
    "sg:orig_category":"Herstellung von Metallkonstruktionen Stahl U Leichtmetallbau",
    "sg:phone":"+41 62 822 51 05",
    "sg:postcode":"9116",
    "sg:province":"St. Gallen",
    "wof:name":"Gurtner Metallbau Ag",
    "wof:placetype":"venue"
},
  "geometry": {"coordinates":[8.0856761932,47.3857765198],"type":"Point"}
}