{
  "type": "Feature",
  "properties": {
    "iso:country":"CH",
    "sg:address":"1239",
    "sg:city":"Collex",
    "sg:orig_category":"Vereine Gesang",
    "sg:phone":"+41 22 758 11 51",
    "sg:postcode":"1239",
    "sg:province":"Gen\u00e8ve",
    "wof:name":"Chorale Catholique",
    "wof:placetype":"venue"
},
  "geometry": {"coordinates":[6.1250801086,46.2722396851],"type":"Point"}
}