{
  "type": "Feature",
  "properties": {
    "iso:country":"CH",
    "sg:address":"6955",
    "sg:city":"Cagiallo",
    "sg:orig_category":"Allgemeiner Hoch U Tiefbau",
    "sg:phone":"+41 91 943 27 68",
    "sg:postcode":"6955",
    "sg:province":"Ticino",
    "wof:name":"Morosoli Francesco",
    "wof:placetype":"venue"
},
  "geometry": {"coordinates":[8.97195,46.066551],"type":"Point"}
}