{
  "type": "Feature",
  "properties": {
    "iso:country":"CH",
    "sg:address":"Route De Lausanne 114",
    "sg:city":"Nyon",
    "sg:orig_category":"Instandhaltung U Reparatur von Automobilen",
    "sg:phone":"+41 22 361 29 02",
    "sg:postcode":"1260",
    "sg:province":"Vaud",
    "wof:name":"Garage Louis Jaques, Eric Jaques Successeur.",
    "wof:placetype":"venue"
},
  "geometry": {"coordinates":[6.2461800575,46.386390686],"type":"Point"}
}