{
  "type": "Feature",
  "properties": {
    "iso:country":"CH",
    "sg:address":"Sch\u00fctzenmattstrasse 3",
    "sg:city":"Lenzburg",
    "sg:classifiers":[
        {
            "category":"Social Services",
            "subcategory":"Retirement Home",
            "type":"Services"
        }
    ],
    "sg:phone":"+41 62 891 42 13",
    "sg:postcode":"5600",
    "sg:province":"Aargau",
    "sg:tags":[
        "pflegeheime",
        "u",
        "alters"
    ],
    "wof:name":"Altersheim Alice H\u00fcnerwadel",
    "wof:placetype":"venue"
},
  "geometry": {"coordinates":[8.181795,47.388786],"type":"Point"}
}