{
  "type": "Feature",
  "properties": {
    "iso:country":"CH",
    "sg:address":"Ebnetrain 7",
    "sg:city":"Meggen",
    "sg:orig_category":"Reiseb\u00fcros",
    "sg:phone":"+41 41 377 44 74",
    "sg:postcode":"6045",
    "sg:province":"Luzern",
    "wof:name":"Trans West Travel",
    "wof:placetype":"venue"
},
  "geometry": {"coordinates":[8.3655519485,47.0474777222],"type":"Point"}
}