{
  "type": "Feature",
  "properties": {
    "iso:country":"CH",
    "sg:address":"Harschwendi 428",
    "sg:city":"Waldstatt",
    "sg:orig_category":"Mechanische Werkst\u00e4tten",
    "sg:phone":"+41 34 445 48 11",
    "sg:postcode":"9104",
    "sg:province":"Appenzell Ausserrhoden",
    "wof:name":"Werner Mathys Elektromechanische Werkst\u00e4tte",
    "wof:placetype":"venue"
},
  "geometry": {"coordinates":[7.568983078,47.0876655579],"type":"Point"}
}