{
  "type": "Feature",
  "properties": {
    "iso:country":"CH",
    "sg:address":"Pestalozzistrasse 5 3007 Bern. Postfach",
    "sg:city":"Bern",
    "sg:orig_category":"Maler U Glasergewerbe",
    "sg:postcode":"3005",
    "sg:province":"Bern",
    "wof:name":"Fernandez David Maler- U. Gipserarbeiten",
    "wof:placetype":"venue"
},
  "geometry": {"coordinates":[7.4255461693,46.9414138794],"type":"Point"}
}