{
  "type": "Feature",
  "properties": {
    "iso:country":"CH",
    "sg:address":"Dorfplatz 3 4418 Reigoldswil. Postfach",
    "sg:city":"Reigoldswil",
    "sg:orig_category":"RESTAURANTS: TEA-ROOMS",
    "sg:postcode":"4418",
    "sg:province":"Basel-Landschaft",
    "wof:name":"Restaurant Siesta",
    "wof:placetype":"venue"
},
  "geometry": {"coordinates":[79.0855331421,25.7877006531],"type":"Point"}
}