{
  "type": "Feature",
  "properties": {
    "iso:country":"CH",
    "sg:address":"Fabrik Im Schiffli",
    "sg:city":"Hirzel",
    "sg:orig_category":"Selbst\u00e4ndige bildende K\u00fcnstler",
    "sg:phone":"+41 17298191",
    "sg:postcode":"8816",
    "sg:province":"Z\u00fcrich",
    "wof:name":"Sonja Eckenstein Bildhauer-atelier",
    "wof:placetype":"venue"
},
  "geometry": {"coordinates":[8.5832166672,47.2113685608],"type":"Point"}
}