{
  "type": "Feature",
  "properties": {
    "addr:full":"Thannerstrasse 36 Basel Basel-Stadt 4054",
    "addr:housenumber":"36",
    "addr:postcode":"4054",
    "addr:street":"Thannerstrasse",
    "iso:country":"CH",
    "sg:address":"Thannerstrasse 36",
    "sg:city":"Basel",
    "sg:classifiers":[
        {
            "category":"Professional",
            "subcategory":"Art Services",
            "type":"Services"
        }
    ],
    "sg:phone":"+41 61 307 55 44",
    "sg:postcode":"4054",
    "sg:province":"Basel-Stadt",
    "sg:tags":[
        "business",
        "brochures",
        "matters",
        "printed",
        "advertisement",
        "designing"
    ],
    "wof:name":"Powerdruck Gmbh",
    "wof:placetype":"venue"
},
  "geometry": {"coordinates":[7.574044,47.554424],"type":"Point"}
}