{
  "type": "Feature",
  "properties": {
    "iso:country":"CH",
    "sg:address":"Schulhausstrasse 6",
    "sg:city":"Cham",
    "sg:orig_category":"Detailhandel mit Sportartikeln",
    "sg:phone":"+41 56 225 17 44",
    "sg:postcode":"6330",
    "sg:province":"Zug",
    "wof:name":"Foebs Billardartikel",
    "wof:placetype":"venue"
},
  "geometry": {"coordinates":[8.2480201721,47.4600563049],"type":"Point"}
}