{
  "type": "Feature",
  "properties": {
    "iso:country":"CH",
    "sg:address":"Duxgass 12",
    "sg:city":"Schaan",
    "sg:orig_category":"Fahrschulen, Flugschulen",
    "sg:phone":"+41 31 829 05 65",
    "sg:postcode":"9494",
    "wof:name":"Peter Pl\u00fcss Autofahrschule",
    "wof:placetype":"venue"
},
  "geometry": {"coordinates":[7.359541893,46.9716949463],"type":"Point"}
}