{
  "type": "Feature",
  "properties": {
    "iso:country":"CH",
    "sg:address":"Q. Des Bergues 11",
    "sg:city":"Gen\u00e8ve",
    "sg:classifiers":[
        {
            "category":"Banks & Credit Unions",
            "subcategory":"Financial Services",
            "type":"Services"
        }
    ],
    "sg:phone":"+41 22 906 21 11",
    "sg:postcode":"1201",
    "sg:province":"Gen\u00e8ve",
    "sg:tags":[
        "banking",
        "finance",
        "insurance"
    ],
    "wof:name":"United European Bank",
    "wof:placetype":"venue"
},
  "geometry": {"coordinates":[6.143882,46.206074],"type":"Point"}
}