{
  "type": "Feature",
  "properties": {
    "iso:country":"CH",
    "sg:address":"Boniswilerstrasse 16",
    "sg:city":"Seengen",
    "sg:classifiers":[
        {
            "category":"Home & Garden",
            "subcategory":"Hardware",
            "type":"Retail Goods"
        }
    ],
    "sg:phone":"+41 62 777 18 71",
    "sg:postcode":"5707",
    "sg:province":"Aargau",
    "sg:tags":[
        "agricultural",
        "implement"
    ],
    "wof:name":"Erismann Ag Seengen",
    "wof:placetype":"venue"
},
  "geometry": {"coordinates":[8.200551,47.324978],"type":"Point"}
}