{
  "type": "Feature",
  "properties": {
    "iso:country":"CH",
    "sg:address":"Rue Du Vieux-coll\u00e8ge 3",
    "sg:city":"Gen\u00e8ve",
    "sg:orig_category":"Detailhandel mit Pelzwaren",
    "sg:phone":"+41 22 310 02 26",
    "sg:postcode":"1204",
    "sg:province":"Gen\u00e8ve",
    "wof:name":"Fourrures Wegm\u00fcller Trav.sur Mesure, Conservation",
    "wof:placetype":"venue"
},
  "geometry": {"coordinates":[6.1504368782,46.2019691467],"type":"Point"}
}