{
  "type": "Feature",
  "properties": {
    "iso:country":"CH",
    "sg:address":"Einsteinstrasse 1-5 8093 Z\u00fcrich. Postfach",
    "sg:city":"Z\u00fcrich",
    "sg:orig_category":"Andere Ausbildungsst\u00e4tten der h\u00f6heren Berufsausbildung",
    "sg:phone":"+41 14314000",
    "sg:postcode":"8093",
    "sg:province":"Z\u00fcrich",
    "wof:name":"Eidg.technische Hochschule Eth Institut F\u00fcr Biotechnologie",
    "wof:placetype":"venue"
},
  "geometry": {"coordinates":[8.506425,47.408249],"type":"Point"}
}