{
  "type": "Feature",
  "properties": {
    "iso:country":"CH",
    "sg:address":"Chemin De Delay 9",
    "sg:city":"Vernier",
    "sg:orig_category":"Instandhaltung U Reparatur von Automobilen",
    "sg:phone":"+41 22 341 02 03",
    "sg:postcode":"1214",
    "sg:province":"Gen\u00e8ve",
    "wof:name":"Pinto Francesco",
    "wof:placetype":"venue"
},
  "geometry": {"coordinates":[6.0775032043,46.2187805176],"type":"Point"}
}