{
  "type": "Feature",
  "properties": {
    "iso:country":"CH",
    "sg:address":"Seestrasse 60",
    "sg:city":"Gersau",
    "sg:orig_category":"Non-Classified Establishments",
    "sg:postcode":"6442",
    "sg:province":"Schwyz",
    "wof:name":"Palmrock Ag",
    "wof:placetype":"venue"
},
  "geometry": {"coordinates":[8.5205698013,46.9934005737],"type":"Point"}
}