{
  "type": "Feature",
  "properties": {
    "addr:full":"R\u00fctihofstrasse 53 8713 Uerikon. Postfach Uerikon Z\u00fcrich 8713",
    "addr:housenumber":"53",
    "addr:postcode":"8713;postfach;8713",
    "addr:street":"Ruetihofstrasse",
    "iso:country":"CH",
    "sg:address":"R\u00fctihofstrasse 53 8713 Uerikon. Postfach",
    "sg:city":"Uerikon",
    "sg:orig_category":"Architektur U Ingenieurb\u00fcros",
    "sg:phone":"+41 61 711 48 44",
    "sg:postcode":"8713",
    "sg:province":"Z\u00fcrich",
    "wof:name":"Schneider Guido, Bpt Belt Processing Technology",
    "wof:placetype":"venue"
},
  "geometry": {"coordinates":[7.587095,47.492817],"type":"Point"}
}