{
  "type": "Feature",
  "properties": {
    "iso:country":"CH",
    "sg:address":"Via Serafino Balestra 27",
    "sg:city":"Lugano",
    "sg:orig_category":"Wirtschaftspr\u00fcfung, Steuerberatung U Treuhand",
    "sg:phone":"+41 21 320 57 83",
    "sg:postcode":"6900",
    "sg:province":"Ticino",
    "wof:name":"Cgs Comptabilit\u00e9 L.spurio",
    "wof:placetype":"venue"
},
  "geometry": {"coordinates":[6.6086969376,46.521736145],"type":"Point"}
}