{
  "type": "Feature",
  "properties": {
    "iso:country":"CH",
    "sg:address":"Urmein",
    "sg:city":"Tschappina",
    "sg:orig_category":"Personenbef\u00f6rderung im Linienverkehr zu Land",
    "sg:phone":"+41 81 651 30 40",
    "sg:postcode":"7428",
    "sg:province":"Graubunden",
    "wof:name":"Skilifte Tschappina-l\u00fcsch-urmein Ag Tschappina",
    "wof:placetype":"venue"
},
  "geometry": {"coordinates":[9.3875331879,46.6871681213],"type":"Point"}
}