{
  "type": "Feature",
  "properties": {
    "iso:country":"CH",
    "sg:address":"H\u00f6fnerstrasse 12",
    "sg:city":"Unter\u00e4geri",
    "sg:orig_category":"Detailhandel mit Schuhen Detailhandel mit Schuhen U Lederwaren",
    "sg:phone":"+41 17463030",
    "sg:postcode":"6314",
    "sg:province":"Zug",
    "wof:name":"Schuhhaus Tiefenbacher Ag",
    "wof:placetype":"venue"
},
  "geometry": {"coordinates":[8.4030780792,47.4045333862],"type":"Point"}
}