{
  "type": "Feature",
  "properties": {
    "iso:country":"CH",
    "sg:address":"Flugplatz",
    "sg:city":"Lommis",
    "sg:orig_category":"Luft U Raumfahrzeugbau",
    "sg:phone":"+41 52 376 15 30",
    "sg:postcode":"9506",
    "sg:province":"Thurgau",
    "wof:name":"H\u00fcrlimann Flugzubeh\u00f6r Ag",
    "wof:placetype":"venue"
},
  "geometry": {"coordinates":[8.9988899231,47.5183448792],"type":"Point"}
}