{
  "type": "Feature",
  "properties": {
    "iso:country":"CH",
    "sg:address":"Rue Des Grandes Rayes 33",
    "sg:city":"Payerne",
    "sg:orig_category":"Organisationen des Gesundheitswesen",
    "sg:phone":"+41 26 660 47 38",
    "sg:postcode":"1530",
    "sg:province":"Vaud",
    "wof:name":"Alliance Suisse D.samaritains Section De Payerne",
    "wof:placetype":"venue"
},
  "geometry": {"coordinates":[6.9430990219,46.8268661499],"type":"Point"}
}