{
  "type": "Feature",
  "properties": {
    "iso:country":"CH",
    "sg:address":"Chatanerie Chemin De La 5",
    "sg:city":"Crissier",
    "sg:orig_category":"RESTAURANTS: TEA-ROOMS",
    "sg:postcode":"1023",
    "sg:province":"Vaud",
    "wof:name":"Apple-pie, Douchet De Rou\u00e8re-mata Sarita Restaurant Apple-pie",
    "wof:placetype":"venue"
},
  "geometry": {"coordinates":[7.2864098549,46.4733848572],"type":"Point"}
}