{
  "type": "Feature",
  "properties": {
    "iso:country":"CH",
    "sg:address":"Grabenstrasse 3",
    "sg:city":"Zug",
    "sg:orig_category":"Grosshandel mit Obst U Gem\u00fcse",
    "sg:phone":"+41 22 343 06 00",
    "sg:postcode":"6300",
    "sg:province":"Zug",
    "wof:name":"Bourgeois Primeurs Carouge Pr\u00e8s De Gen\u00e8ve Sa",
    "wof:placetype":"venue"
},
  "geometry": {"coordinates":[6.1325268745,46.1805953979],"type":"Point"}
}