{
  "type": "Feature",
  "properties": {
    "iso:country":"CH",
    "sg:address":"Vordergasse 14 8353 Elgg. Postfach 148",
    "sg:city":"Elgg",
    "sg:orig_category":"Detailhandel mit Radio U Fernsehger\u00e4ten Elektroinstallation",
    "sg:phone":"+41 52 364 11 11",
    "sg:postcode":"8353",
    "sg:province":"Z\u00fcrich",
    "wof:name":"Antele Ag",
    "wof:placetype":"venue"
},
  "geometry": {"coordinates":[8.8676548004,47.4906387329],"type":"Point"}
}