{
  "type": "Feature",
  "properties": {
    "iso:country":"CH",
    "sg:address":"Gstadstrasse 25",
    "sg:city":"Zollikon",
    "sg:orig_category":"Erschliessung von Grundst\u00fccken",
    "sg:postcode":"8702",
    "sg:province":"Z\u00fcrich",
    "wof:name":"Baugenossenschaft Gstad",
    "wof:placetype":"venue"
},
  "geometry": {"coordinates":[8.5704240799,47.3396949768],"type":"Point"}
}