{
  "type": "Feature",
  "properties": {
    "iso:country":"CH",
    "sg:address":"Palmenstrasse 1",
    "sg:city":"Degersheim",
    "sg:orig_category":"Detailhandel mit Fahrr\u00e4dern Handel mit Motorr\u00e4dern, Teilen U Zubeh\u00f6r Instandhaltung U Reparatur von ",
    "sg:phone":"+41 71 371 12 72",
    "sg:postcode":"9113",
    "sg:province":"St. Gallen",
    "wof:name":"Hans Nussbaumer Velos Motos",
    "wof:placetype":"venue"
},
  "geometry": {"coordinates":[9.1975603104,47.3735313416],"type":"Point"}
}