{
  "type": "Feature",
  "properties": {
    "iso:country":"CH",
    "sg:address":"Via Brogeda 3",
    "sg:city":"Chiasso",
    "sg:orig_category":"Sonstige Verkehrsvermittlung",
    "sg:phone":"+41 91 682 14 82",
    "sg:postcode":"6830",
    "sg:province":"Ticino",
    "wof:name":"Arrighi & Partners Sagl",
    "wof:placetype":"venue"
},
  "geometry": {"coordinates":[9.0354356766,45.8373565674],"type":"Point"}
}