{
  "type": "Feature",
  "properties": {
    "iso:country":"CH",
    "sg:address":"Centre Commercial Magro",
    "sg:city":"Uvrier",
    "sg:orig_category":"Detailhandel mit Geschenkartikeln U Souvenirs Detailhandel mit Spielwaren",
    "sg:phone":"+41 21 960 20 77",
    "sg:postcode":"1958",
    "sg:province":"Valais",
    "wof:name":"Le D\u00e9ballage Du Jouet Cadeaux",
    "wof:placetype":"venue"
},
  "geometry": {"coordinates":[6.9295902252,46.3618087769],"type":"Point"}
}