{
  "type": "Feature",
  "properties": {
    "iso:country":"CH",
    "sg:address":"Chaufour 15",
    "sg:city":"Vicques",
    "sg:orig_category":"Aktivit\u00e4ten der Generalunternehmen im Baugewerbe Architektur U Ingenieurb\u00fcros",
    "sg:phone":"+41 19374355",
    "sg:postcode":"2824",
    "sg:province":"Jura",
    "wof:name":"El Faro Gmbh",
    "wof:placetype":"venue"
},
  "geometry": {"coordinates":[8.842126,47.304134],"type":"Point"}
}