{
  "type": "Feature",
  "properties": {
    "iso:country":"CH",
    "sg:address":"Goldackerweg 15",
    "sg:city":"L\u00f6hningen",
    "sg:orig_category":"Herstellung von Teilen U Zubeh\u00f6r f\u00fcr Automobile",
    "sg:phone":"+41 52 631 20 20",
    "sg:postcode":"8224",
    "sg:province":"Schaffhausen",
    "wof:name":"Escher Enterprises Gmbh",
    "wof:placetype":"venue"
},
  "geometry": {"coordinates":[8.551199913,47.6994628906],"type":"Point"}
}