{
  "type": "Feature",
  "properties": {
    "iso:country":"CH",
    "sg:address":"Rebbergstrasse 24",
    "sg:city":"Geroldswil",
    "sg:orig_category":"RESTAURANTS: TEA-ROOMS",
    "sg:postcode":"8954",
    "sg:province":"Z\u00fcrich",
    "wof:name":"Arena Di Pasta Gmbh",
    "wof:placetype":"venue"
},
  "geometry": {"coordinates":[8.4085731506,47.4257888794],"type":"Point"}
}