{
  "type": "Feature",
  "properties": {
    "iso:country":"CH",
    "sg:address":"Route De Riaz 100 1630 Bulle. Postfach",
    "sg:city":"Bulle",
    "sg:orig_category":"Detailhandel mit M\u00f6beln U Haushaltsgegenst\u00e4nden M\u00f6bel and Gartenm\u00f6bel Grosshandel",
    "sg:phone":"+41 26 919 86 26",
    "sg:postcode":"1630",
    "sg:province":"Fribourg",
    "wof:name":"H & R Meubles Sa Objets Mobiliers; Commerce. Meubles Meublants; Achat, Vente, Importation Etc",
    "wof:placetype":"venue"
},
  "geometry": {"coordinates":[7.0597200394,46.6286087036],"type":"Point"}
}