{
  "type": "Feature",
  "properties": {
    "iso:country":"CH",
    "sg:address":"Rue Mo\u00efse-marcinhes 7",
    "sg:city":"Meyrin",
    "sg:classifiers":[
        {
            "category":"Shopping Center",
            "type":"Public Place"
        }
    ],
    "sg:phone":"+41 22 719 10 70",
    "sg:postcode":"1217",
    "sg:province":"Gen\u00e8ve",
    "sg:tags":[
        "case",
        "clock"
    ],
    "wof:name":"Centror S.a.",
    "wof:placetype":"venue"
},
  "geometry": {"coordinates":[6.062687,46.223019],"type":"Point"}
}