{
  "type": "Feature",
  "properties": {
    "iso:country":"CH",
    "sg:address":"7235",
    "sg:city":"Fideris",
    "sg:orig_category":"Detailhandel mit Waren verschiedener Art, Hauptrichtung Nahrungsmittel",
    "sg:phone":"+41 81 332 14 77",
    "sg:postcode":"7235",
    "sg:province":"Graubunden",
    "wof:name":"Landwirtschaftliche Konsumgenossenschaft Fideris",
    "wof:placetype":"venue"
},
  "geometry": {"coordinates":[9.7427120209,46.9152984619],"type":"Point"}
}