{
  "type": "Feature",
  "properties": {
    "iso:country":"CH",
    "sg:address":"Buenstrasse 14",
    "sg:city":"D\u00fcbendorf",
    "sg:orig_category":"Finanzierungsinstitutionen",
    "sg:phone":"+41 18217163",
    "sg:postcode":"8600",
    "sg:province":"Z\u00fcrich",
    "wof:name":"Doninelli Finanz Und Treuhand Ag",
    "wof:placetype":"venue"
},
  "geometry": {"coordinates":[8.6197805405,47.3895530701],"type":"Point"}
}