{
  "type": "Feature",
  "properties": {
    "iso:country":"CH",
    "sg:address":"Oberdorfstrasse 46",
    "sg:city":"Winterthur",
    "sg:orig_category":"Grafikateliers, Design",
    "sg:phone":"+41 22 345 19 30",
    "sg:postcode":"8408",
    "sg:province":"Z\u00fcrich",
    "wof:name":"Peter Meili Atelier De D\u00e9coration",
    "wof:placetype":"venue"
},
  "geometry": {"coordinates":[6.1634101868,46.2010612488],"type":"Point"}
}