{
  "type": "Feature",
  "properties": {
    "iso:country":"CH",
    "sg:address":"Steinackerstrasse 38",
    "sg:city":"Urdorf",
    "sg:classifiers":[
        {
            "category":"Professional",
            "subcategory":"Employment Agencies",
            "type":"Services"
        }
    ],
    "sg:phone":"+41 17771535",
    "sg:postcode":"8902",
    "sg:province":"Z\u00fcrich",
    "sg:tags":[
        "personal",
        "u",
        "stellenvermittlung"
    ],
    "wof:name":"T\u00e4nnler Personalmanagement Ag",
    "wof:placetype":"venue"
},
  "geometry": {"coordinates":[8.424325943,47.3954811096],"type":"Point"}
}