{
  "type": "Feature",
  "properties": {
    "iso:country":"CH",
    "sg:address":"Route De Satigny 44",
    "sg:city":"Meyrin",
    "sg:orig_category":"Detailhandel mit Waren verschiedener Art, Hauptrichtung Nahrungsmittel Grosshandel mit Getr\u00e4nken",
    "sg:phone":"+41 22 343 91 40",
    "sg:postcode":"1217",
    "sg:province":"Gen\u00e8ve",
    "wof:name":"Ph.& M.-c. Carasso-bossert Sa Commerce De Caf\u00e9 & Th\u00e9",
    "wof:placetype":"venue"
},
  "geometry": {"coordinates":[6.0691370964,46.2185974121],"type":"Point"}
}