{
  "type": "Feature",
  "properties": {
    "iso:country":"CH",
    "sg:address":"Ruelle Du Canal 6",
    "sg:city":"Boncourt",
    "sg:orig_category":"Mechanische Werkst\u00e4tten",
    "sg:phone":"+41 32 475 57 56",
    "sg:postcode":"2926",
    "sg:province":"Jura",
    "wof:name":"Atelier Meusy",
    "wof:placetype":"venue"
},
  "geometry": {"coordinates":[7.0122299194,47.4934921265],"type":"Point"}
}