{
  "type": "Feature",
  "properties": {
    "iso:country":"CH",
    "sg:address":"Lyssachstrasse 44 3400 Burgdorf. Postfach",
    "sg:city":"Burgdorf",
    "sg:orig_category":"Herstellung von Automobilen Herstellung von sonstigen landwirtschaftlichen Maschinen",
    "sg:phone":"+41 19323800",
    "sg:postcode":"3401",
    "sg:province":"Bern",
    "wof:name":"Tecom Communal Ag",
    "wof:placetype":"venue"
},
  "geometry": {"coordinates":[8.7826309204,47.3092765808],"type":"Point"}
}