{
  "type": "Feature",
  "properties": {
    "iso:country":"CH",
    "sg:address":"Ch\u00e2teau-l'ev\u00eaque Route Du 1 1254 Jussy. Postfach",
    "sg:city":"Jussy",
    "sg:orig_category":"Grosshandel mit Holz U Baustoffen",
    "sg:phone":"+41 21 960 22 51",
    "sg:postcode":"1254",
    "sg:province":"Gen\u00e8ve",
    "wof:name":"Seroc Sa",
    "wof:placetype":"venue"
},
  "geometry": {"coordinates":[6.9295902252,46.3618087769],"type":"Point"}
}