{
  "type": "Feature",
  "properties": {
    "iso:country":"CH",
    "sg:address":"Papio Via Bartolomeo 5",
    "sg:city":"Ascona",
    "sg:orig_category":"Interessenvertretungen",
    "sg:phone":"+41 91 792 20 12",
    "sg:postcode":"6612",
    "sg:province":"Ticino",
    "wof:name":"I.s.a.g.-interdisciplinary Strategic Advisory Group Sagl",
    "wof:placetype":"venue"
},
  "geometry": {"coordinates":[8.7700014114,46.1565284729],"type":"Point"}
}