{
  "type": "Feature",
  "properties": {
    "iso:country":"CH",
    "sg:address":"Dorfstr. 4",
    "sg:city":"M\u00fcntschemier",
    "sg:classifiers":[
        {
            "category":"Manufacturing",
            "subcategory":"Tools & Machinery",
            "type":"Manufacturing & Wholesale Goods"
        }
    ],
    "sg:phone":"+41 61 712 11 15",
    "sg:postcode":"3225",
    "sg:province":"Bern",
    "sg:tags":[
        "equipment",
        "measurement",
        "-",
        "precision",
        "instrument"
    ],
    "wof:name":"Bioreba Ag",
    "wof:placetype":"venue"
},
  "geometry": {"coordinates":[7.598573,47.489071],"type":"Point"}
}