{
  "type": "Feature",
  "properties": {
    "iso:country":"CH",
    "sg:address":"Cantonale Route 1897 Bouveret. Postfach",
    "sg:city":"Bouveret",
    "sg:orig_category":"Fachdetailhandel mit pharmazeutischen Produkten",
    "sg:postcode":"1897",
    "sg:province":"Valais",
    "wof:name":"Bacca Marcel-jacques",
    "wof:placetype":"venue"
},
  "geometry": {"coordinates":[6.854364872,46.3833808899],"type":"Point"}
}