{
  "type": "Feature",
  "properties": {
    "iso:country":"CH",
    "sg:address":"Lommiswilerstrasse 29 4512 Bellach. Postfach",
    "sg:city":"Bellach",
    "sg:orig_category":"RESTAURANTS: TEA-ROOMS",
    "sg:postcode":"4512",
    "sg:province":"Solothurn",
    "wof:name":"Berner Joseph",
    "wof:placetype":"venue"
},
  "geometry": {"coordinates":[7.5046958923,47.2158622742],"type":"Point"}
}