{
  "type": "Feature",
  "properties": {
    "iso:country":"CH",
    "sg:address":"Niederb\u00fcrerstrasse 30",
    "sg:city":"Bischofszell",
    "sg:orig_category":"Erbringung von sonstigen Dienstleistungen f\u00fcr Unterhaltung, Erholung U Freizeit",
    "sg:postcode":"9220",
    "sg:province":"Thurgau",
    "wof:name":"Dietrich M. Musikagentur",
    "wof:placetype":"venue"
},
  "geometry": {"coordinates":[9.2340736389,47.489025116],"type":"Point"}
}