{
  "type": "Feature",
  "properties": {
    "iso:country":"CH",
    "sg:address":"Chemin Grosse-pierre 8",
    "sg:city":"Morges",
    "sg:orig_category":"Vermietung U Verpachtung von eigenen Immobilien Vermittlung von Immobilien",
    "sg:phone":"+41 21 801 78 00",
    "sg:postcode":"1110",
    "sg:province":"Vaud",
    "wof:name":"Bureau Immobilier Fiduciaire Et Fiscal Sauvain Philippe",
    "wof:placetype":"venue"
},
  "geometry": {"coordinates":[6.5010428429,46.5185585022],"type":"Point"}
}