{
  "type": "Feature",
  "properties": {
    "iso:country":"CH",
    "sg:address":"T\u00f6distrasse 47",
    "sg:city":"Z\u00fcrich",
    "sg:classifiers":[
        {
            "category":"Banks & Credit Unions",
            "subcategory":"Bank",
            "type":"Services"
        }
    ],
    "sg:phone":"+41 12013982",
    "sg:postcode":"8002",
    "sg:province":"Z\u00fcrich",
    "wof:name":"Privat Kredit Bank",
    "wof:placetype":"venue"
},
  "geometry": {"coordinates":[8.533735,47.36731],"type":"Point"}
}