{
  "type": "Feature",
  "properties": {
    "iso:country":"CH",
    "sg:address":"Oberdorfstrasse 16 8925 Ebertswil. Postfach",
    "sg:city":"Ebertswil",
    "sg:orig_category":"Detailhandel mit Bekleidung",
    "sg:phone":"+41 17640633",
    "sg:postcode":"8925",
    "sg:province":"Z\u00fcrich",
    "wof:name":"Kameleon Ag",
    "wof:placetype":"venue"
},
  "geometry": {"coordinates":[8.54774,47.224831],"type":"Point"}
}