{
  "type": "Feature",
  "properties": {
    "iso:country":"CH",
    "sg:address":"Bahnhofstrasse 95",
    "sg:city":"R\u00fcschlikon",
    "sg:orig_category":"Reinigungsgewerbe",
    "sg:phone":"+41 17243244",
    "sg:postcode":"8803",
    "sg:province":"Z\u00fcrich",
    "wof:name":"D' Putz-t\u00dc\u00dcfeli Barbara M\u00dcller-zehnder",
    "wof:placetype":"venue"
},
  "geometry": {"coordinates":[8.5596170425,47.30311203],"type":"Point"}
}