{
  "type": "Feature",
  "properties": {
    "iso:country":"CH",
    "sg:address":"Neumattweg 14",
    "sg:city":"B\u00f6ttstein",
    "sg:orig_category":"Herstellung von Tanks U Sammelbeh\u00e4ltern aus Metall Reinigungsgewerbe",
    "sg:phone":"+41 56 245 53 68",
    "sg:postcode":"5315",
    "sg:province":"Aargau",
    "wof:name":"Brechb\u00fchl Fritz",
    "wof:placetype":"venue"
},
  "geometry": {"coordinates":[8.2204999924,47.553855896],"type":"Point"}
}