{
  "type": "Feature",
  "properties": {
    "iso:country":"CH",
    "sg:address":"Mittlerfeldweg 34",
    "sg:city":"Sch\u00f6nenbuch",
    "sg:orig_category":"Gartenbau",
    "sg:phone":"+41 61 481 22 34",
    "sg:postcode":"4124",
    "sg:province":"Basel-Landschaft",
    "wof:name":"Paul Zumstein G\u00e4rtnerei",
    "wof:placetype":"venue"
},
  "geometry": {"coordinates":[7.5044999123,47.5357589722],"type":"Point"}
}