{
  "type": "Feature",
  "properties": {
    "iso:country":"CH",
    "sg:address":"1034",
    "sg:city":"Boussens",
    "sg:orig_category":"Instandhaltung U Reparatur von Automobilen",
    "sg:phone":"+41 21 731 13 03",
    "sg:postcode":"1034",
    "sg:province":"Vaud",
    "wof:name":"Marolda Michel, Garage Du Tilleul",
    "wof:placetype":"venue"
},
  "geometry": {"coordinates":[6.5845799446,46.6043014526],"type":"Point"}
}