{
  "type": "Feature",
  "properties": {
    "iso:country":"CH",
    "sg:address":"Ahornweg 3 3005 Bern. Postfach",
    "sg:city":"Bern",
    "sg:orig_category":"Non-Classified Establishments",
    "sg:postcode":"3005",
    "sg:province":"Bern",
    "wof:name":"Kkvi Holding Ag Beteiligungen Usw",
    "wof:placetype":"venue"
},
  "geometry": {"coordinates":[7.4351520538,46.9538383484],"type":"Point"}
}