{
  "type": "Feature",
  "properties": {
    "iso:country":"CH",
    "sg:address":"Ziegelfeldstrasse 112",
    "sg:city":"Olten",
    "sg:orig_category":"Finanzierungsinstitutionen Verm\u00f6gensverwaltung",
    "sg:phone":"+41 62 212 53 52",
    "sg:postcode":"4600",
    "sg:province":"Solothurn",
    "wof:name":"Jakob Thomas C.",
    "wof:placetype":"venue"
},
  "geometry": {"coordinates":[7.8935871124,47.3513526917],"type":"Point"}
}