{
  "type": "Feature",
  "properties": {
    "iso:country":"CH",
    "sg:address":"Via Lepori 33 6900 Lugano. Postfach",
    "sg:city":"Lugano",
    "sg:orig_category":"Unclassifiable Establishments",
    "sg:postcode":"6900",
    "sg:province":"Ticino",
    "wof:name":"Ivax Holdings Ag",
    "wof:placetype":"venue"
},
  "geometry": {"coordinates":[9.3760499954,47.4264793396],"type":"Point"}
}