{
  "type": "Feature",
  "properties": {
    "iso:country":"CH",
    "sg:address":"Kirchstrasse 39 9490 Vaduz. Postfach 632",
    "sg:city":"Vaduz",
    "sg:orig_category":"Wirtschaftspr\u00fcfung, Steuerberatung U Treuhand",
    "sg:phone":"+423 236 09 09",
    "sg:postcode":"9490",
    "wof:name":"Schreiber & Zindel Treuhand-anstalt",
    "wof:placetype":"venue"
},
  "geometry": {"coordinates":[9.5178403854,47.1365699768],"type":"Point"}
}