{
  "type": "Feature",
  "properties": {
    "iso:country":"CH",
    "sg:address":"Bernerweg 541",
    "sg:city":"Jonen",
    "sg:orig_category":"Kunststoff-Produkte",
    "sg:phone":"+41 17370200",
    "sg:postcode":"8916",
    "sg:province":"Aargau",
    "wof:name":"Schmid U. Kunststoffspritzgusswerk",
    "wof:placetype":"venue"
},
  "geometry": {"coordinates":[8.3923196793,47.3016815186],"type":"Point"}
}