{
  "type": "Feature",
  "properties": {
    "iso:country":"CH",
    "sg:address":"Chemin De Villardin 3 1004 Lausanne Case Postale 295",
    "sg:city":"Lausanne",
    "sg:orig_category":"Vereine Quartier",
    "sg:postcode":"1010",
    "sg:province":"Vaud",
    "wof:name":"St\u00e9 De D\u00e9velop.chailly-b\u00e9thusy",
    "wof:placetype":"venue"
},
  "geometry": {"coordinates":[6.6535000801,46.5259170532],"type":"Point"}
}