{
  "type": "Feature",
  "properties": {
    "iso:country":"CH",
    "sg:address":"Riazzino 6595 Riazzino. Postfach",
    "sg:city":"Riazzino",
    "sg:orig_category":"Oberfl\u00e4chenveredlung U W\u00e4rmebehandlung",
    "sg:postcode":"6595",
    "sg:province":"Ticino",
    "wof:name":"Galvanica Riazzino Sagl",
    "wof:placetype":"venue"
},
  "geometry": {"coordinates":[8.8947925568,46.1762199402],"type":"Point"}
}