{
  "type": "Feature",
  "properties": {
    "iso:country":"CH",
    "sg:address":"Haselstrasse 7",
    "sg:city":"Baden",
    "sg:orig_category":"Arztpraxen",
    "sg:phone":"+41 32 721 45 75",
    "sg:postcode":"5400",
    "sg:province":"Aargau",
    "wof:name":"Dr.med. Anne Von Schulthess Spezial\u00e4rztin Fmh",
    "wof:placetype":"venue"
},
  "geometry": {"coordinates":[8.30934,47.478092],"type":"Point"}
}