{
  "type": "Feature",
  "properties": {
    "iso:country":"CH",
    "sg:address":"C. F. Bally-strasse 5012 Sch\u00f6nenwerd. Postfach",
    "sg:city":"Sch\u00f6nenwerd",
    "sg:orig_category":"Sonstiger Grosshandel",
    "sg:postcode":"5012",
    "sg:province":"Solothurn",
    "wof:name":"Scorpiomediagroup Gmbh",
    "wof:placetype":"venue"
},
  "geometry": {"coordinates":[8.0045204163,47.373916626],"type":"Point"}
}