{
  "type": "Feature",
  "properties": {
    "iso:country":"CH",
    "sg:address":"Worbstrasse 324",
    "sg:city":"G\u00fcmligen",
    "sg:orig_category":"Physiotherapie",
    "sg:phone":"+41 18445011",
    "sg:postcode":"3073",
    "sg:province":"Bern",
    "wof:name":"Andr\u00e9 Klinkert Physiotherapie",
    "wof:placetype":"venue"
},
  "geometry": {"coordinates":[8.43937397,47.4580879211],"type":"Point"}
}