{
  "type": "Feature",
  "properties": {
    "iso:country":"CH",
    "sg:address":"Winterhaldenstrasse 13",
    "sg:city":"Heimberg",
    "sg:orig_category":"Gymnastik U Fitnesszentren",
    "sg:phone":"+41 79 343 23 32",
    "sg:postcode":"3627",
    "sg:province":"Bern",
    "wof:name":"Thermo Figura, Zeni",
    "wof:placetype":"venue"
},
  "geometry": {"coordinates":[7.6021962166,46.7985267639],"type":"Point"}
}