{
  "type": "Feature",
  "properties": {
    "iso:country":"CH",
    "sg:address":"St-eloi",
    "sg:city":"Orbe",
    "sg:classifiers":[
        {
            "category":"Farming",
            "subcategory":"Farm & Veterinary Services",
            "type":"Manufacturing & Wholesale Goods"
        }
    ],
    "sg:phone":"+41 24 441 61 21",
    "sg:postcode":"1350",
    "sg:province":"Vaud",
    "sg:tags":[
        "food",
        "product",
        "breeding",
        "animal",
        "related"
    ],
    "wof:name":"Provimi Kliba Sa",
    "wof:placetype":"venue"
},
  "geometry": {"coordinates":[6.533615,46.720169],"type":"Point"}
}