{
  "type": "Feature",
  "properties": {
    "iso:country":"CH",
    "sg:address":"Multertor",
    "sg:city":"St. Gallen",
    "sg:classifiers":[
        {
            "category":"Banks & Credit Unions",
            "subcategory":"Bank",
            "type":"Services"
        }
    ],
    "sg:phone":"+41 32 391 97 11",
    "sg:postcode":"9001",
    "sg:province":"St. Gallen",
    "wof:name":"Swiss Bank Corp.",
    "wof:placetype":"venue"
},
  "geometry": {"coordinates":[7.273984,47.043354],"type":"Point"}
}