{
  "type": "Feature",
  "properties": {
    "iso:country":"CH",
    "sg:address":"Churerstrasse 5 8852 Altendorf. Postfach",
    "sg:city":"Altendorf",
    "sg:orig_category":"Detailhandel mit Waren verschiedener Art, Hauptrichtung Nahrungsmittel",
    "sg:phone":"+41 14924300",
    "sg:postcode":"8852",
    "sg:province":"Schwyz",
    "wof:name":"Spar-markt Bernag Ovag Ag",
    "wof:placetype":"venue"
},
  "geometry": {"coordinates":[8.455909729,47.3601608276],"type":"Point"}
}