{
  "type": "Feature",
  "properties": {
    "iso:country":"CH",
    "sg:address":"Mettlenstrasse 5",
    "sg:city":"Z\u00fcberwangen",
    "sg:orig_category":"Handelsvermittlung U Grosshandel Mechanik",
    "sg:phone":"+41 71 944 10 87",
    "sg:postcode":"9523",
    "sg:province":"St. Gallen",
    "wof:name":"Senn E., Metax-schweisstechnik",
    "wof:placetype":"venue"
},
  "geometry": {"coordinates":[9.0946826935,47.464717865],"type":"Point"}
}