{
  "type": "Feature",
  "properties": {
    "iso:country":"CH",
    "sg:address":"Werkstrasse 71",
    "sg:city":"Lyss",
    "sg:orig_category":"Aktivit\u00e4ten der Generalunternehmen im Baugewerbe Kauf U Verkauf von Immobilien auf eigene Rechnung",
    "sg:phone":"+41 32 387 07 30",
    "sg:postcode":"3250",
    "sg:province":"Bern",
    "wof:name":"Quadro Bau Seeland Ag",
    "wof:placetype":"venue"
},
  "geometry": {"coordinates":[7.294922,47.067535],"type":"Point"}
}