{
  "type": "Feature",
  "properties": {
    "iso:country":"CH",
    "sg:address":"8357",
    "sg:city":"Guntershausen",
    "sg:orig_category":"Detailhandel mit Milcherzeugnissen U Eiern Verarbeitung von Milch",
    "sg:postcode":"8357",
    "sg:province":"Thurgau",
    "wof:name":"K\u00e4sereigenossenschaft Holdern Robert Zimmermann",
    "wof:placetype":"venue"
},
  "geometry": {"coordinates":[8.1540994644,47.2197227478],"type":"Point"}
}