{
  "type": "Feature",
  "properties": {
    "iso:country":"CH",
    "sg:address":"Missionsstrasse 41",
    "sg:city":"Basel",
    "sg:orig_category":"Fotografische Ateliers",
    "sg:phone":"+41 61 382 63 00",
    "sg:postcode":"4055",
    "sg:province":"Basel-Stadt",
    "wof:name":"Roman Eschmann Agentur Krokodil",
    "wof:placetype":"venue"
},
  "geometry": {"coordinates":[7.5762448311,47.5604057312],"type":"Point"}
}