{
  "type": "Feature",
  "properties": {
    "iso:country":"CH",
    "sg:address":"Adolph Saurer-quai 15",
    "sg:city":"Arbon",
    "sg:orig_category":"Arztpraxen",
    "sg:phone":"+41 71 446 08 08",
    "sg:postcode":"9320",
    "sg:province":"Thurgau",
    "wof:name":"Dr.med.daniel Ineichen Arzt F.allgemeine Medizin Fmh",
    "wof:placetype":"venue"
},
  "geometry": {"coordinates":[9.437062,47.513599],"type":"Point"}
}