{
  "type": "Feature",
  "properties": {
    "iso:country":"CH",
    "sg:address":"Kirchgasse 174",
    "sg:city":"Staffelbach",
    "sg:orig_category":"Grosshandel mit Geschenkartikeln U Souvenirs Herstellung von elektrischen Lampen U Leuchten",
    "sg:phone":"+41 62 721 75 12",
    "sg:postcode":"5053",
    "sg:province":"Aargau",
    "wof:name":"Allegre Gmbh Produktion & Grosshandel",
    "wof:placetype":"venue"
},
  "geometry": {"coordinates":[8.0473327637,47.2831993103],"type":"Point"}
}