{
  "type": "Feature",
  "properties": {
    "iso:country":"CH",
    "sg:address":"Chaletweg 752",
    "sg:city":"Gontenschwil",
    "sg:classifiers":[
        {
            "category":"Transit Center",
            "subcategory":"Freight",
            "type":"Transportation"
        }
    ],
    "sg:phone":"+41 62 773 13 49",
    "sg:postcode":"5728",
    "sg:province":"Aargau",
    "sg:tags":[
        "foundry",
        "chill"
    ],
    "wof:name":"Lokoform Ag",
    "wof:placetype":"venue"
},
  "geometry": {"coordinates":[8.14532,47.266659],"type":"Point"}
}