{
  "type": "Feature",
  "properties": {
    "iso:country":"CH",
    "sg:address":"L\u00f6wengraben 4",
    "sg:city":"Luzern",
    "sg:orig_category":"Detailhandel mit Textilien",
    "sg:phone":"+41 41 410 63 03",
    "sg:postcode":"6004",
    "sg:province":"Luzern",
    "wof:name":"Schirm Kummer Schirme, Handschuhe, Accessoires; Verkauf",
    "wof:placetype":"venue"
},
  "geometry": {"coordinates":[8.3055429459,47.0530853271],"type":"Point"}
}