{
  "type": "Feature",
  "properties": {
    "iso:country":"CH",
    "sg:address":"Rautistrasse 12 8047 Z\u00fcrich. Postfach",
    "sg:city":"Z\u00fcrich",
    "sg:orig_category":"Non-Classified Establishments",
    "sg:postcode":"8047",
    "sg:province":"Z\u00fcrich",
    "wof:name":"Web 4 You Turac",
    "wof:placetype":"venue"
},
  "geometry": {"coordinates":[8.4941015244,47.3802604675],"type":"Point"}
}