{
  "type": "Feature",
  "properties": {
    "iso:country":"CH",
    "sg:address":"Belsitostrasse 4",
    "sg:city":"Jona",
    "sg:orig_category":"Einbau von Schreinerwaren",
    "sg:phone":"+41 55 211 88 38",
    "sg:postcode":"8645",
    "sg:province":"St. Gallen",
    "wof:name":"Huber Hermann Gastro-technik",
    "wof:placetype":"venue"
},
  "geometry": {"coordinates":[8.8227453232,47.2395095825],"type":"Point"}
}