{
  "type": "Feature",
  "properties": {
    "iso:country":"CH",
    "sg:address":"6557",
    "sg:city":"Cama",
    "sg:orig_category":"Detailhandel mit Fleisch U Fleischwaren",
    "sg:phone":"+41 27 398 12 66",
    "sg:postcode":"6557",
    "sg:province":"Graubunden",
    "wof:name":"Morard, Clovis.",
    "wof:placetype":"venue"
},
  "geometry": {"coordinates":[7.4068250656,46.2767829895],"type":"Point"}
}