{
  "type": "Feature",
  "properties": {
    "iso:country":"CH",
    "sg:address":"Eggweg 13a 3065 Bolligen. Postfach 415",
    "sg:city":"Bolligen",
    "sg:orig_category":"Vermittlung von Immobilien Verwaltung von Immobilien",
    "sg:phone":"+41 31 921 13 44",
    "sg:postcode":"3065",
    "sg:province":"Bern",
    "wof:name":"Liechti & Zahnd Ag",
    "wof:placetype":"venue"
},
  "geometry": {"coordinates":[7.4985179901,46.9715843201],"type":"Point"}
}