{
  "type": "Feature",
  "properties": {
    "addr:full":"B\u00e4chliweg 2b 9495 Triesen. Postfach 541 Triesen 9495",
    "addr:housenumber":"2b;541",
    "addr:postcode":"9495 triesen.;9495",
    "addr:street":"Baechliweg;Postfach",
    "iso:country":"CH",
    "sg:address":"B\u00e4chliweg 2b 9495 Triesen. Postfach 541",
    "sg:city":"Triesen",
    "sg:orig_category":"Datenverarbeitungsdienste Softwareentwicklung U beratung",
    "sg:phone":"+423 390 07 80",
    "sg:postcode":"9495",
    "wof:name":"Quicksoft Ag",
    "wof:placetype":"venue"
},
  "geometry": {"coordinates":[9.530512,47.113567],"type":"Point"}
}