{
  "type": "Feature",
  "properties": {
    "iso:country":"CH",
    "sg:address":"Mythenquai 353 8038 Z\u00fcrich. Postfach",
    "sg:city":"Z\u00fcrich",
    "sg:orig_category":"Softwareentwicklung U beratung",
    "sg:phone":"+41 13504466",
    "sg:postcode":"8037",
    "sg:province":"Z\u00fcrich",
    "wof:name":"Outerspace Gmbh",
    "wof:placetype":"venue"
},
  "geometry": {"coordinates":[8.5346260071,47.3457107544],"type":"Point"}
}