{
  "type": "Feature",
  "properties": {
    "iso:country":"CH",
    "sg:address":"Vordergasse 3 8200 Schaffhausen. Postfach",
    "sg:city":"Schaffhausen",
    "sg:orig_category":"Detailhandel mit M\u00f6beln U Haushaltsgegenst\u00e4nden",
    "sg:postcode":"8202",
    "sg:province":"Schaffhausen",
    "wof:name":"Wohnshop Hauri",
    "wof:placetype":"venue"
},
  "geometry": {"coordinates":[8.6378498077,47.6957054138],"type":"Point"}
}