{
  "type": "Feature",
  "properties": {
    "iso:country":"CH",
    "sg:address":"Br\u00fcckenstrasse 7",
    "sg:city":"Bern",
    "sg:orig_category":"Technische, physikalische U chemische Untersuchung",
    "sg:phone":"+41 31 318 78 15",
    "sg:postcode":"3005",
    "sg:province":"Bern",
    "wof:name":"Unaltra Hofmann Res",
    "wof:placetype":"venue"
},
  "geometry": {"coordinates":[7.4441580772,46.9446182251],"type":"Point"}
}