{
  "type": "Feature",
  "properties": {
    "addr:full":"Avenue Des Oiseaux 10 Lausanne Vaud 1018",
    "addr:housenumber":"10",
    "addr:postcode":"1018",
    "addr:street":"Avenue Des Oiseaux",
    "iso:country":"CH",
    "sg:address":"Avenue Des Oiseaux 10",
    "sg:city":"Lausanne",
    "sg:orig_category":"Bauspenglerei Zimmerei, Dachdeckerei, Bauspenglerei U Abdichtung",
    "sg:phone":"+41 21 646 84 37",
    "sg:postcode":"1018",
    "sg:province":"Vaud",
    "wof:name":"Marmillod Sa",
    "wof:placetype":"venue"
},
  "geometry": {"coordinates":[6.629674,46.531769],"type":"Point"}
}