{
  "type": "Feature",
  "properties": {
    "iso:country":"CH",
    "sg:address":"Eschenbachstrasse 7",
    "sg:city":"Oetwil",
    "sg:orig_category":"Herstellung von sonstigen elektrischen Ausr\u00fcstungen",
    "sg:phone":"+41 17483896",
    "sg:postcode":"8955",
    "sg:province":"Z\u00fcrich",
    "wof:name":"Erich Gillard",
    "wof:placetype":"venue"
},
  "geometry": {"coordinates":[8.3928852081,47.4272575378],"type":"Point"}
}