{
  "type": "Feature",
  "properties": {
    "iso:country":"CH",
    "sg:address":"Bel-air Chemin De 43",
    "sg:city":"Neuch\u00e2tel",
    "sg:orig_category":"Architektur U Ingenieurb\u00fcros",
    "sg:phone":"+41 32 721 31 13",
    "sg:postcode":"2000",
    "sg:province":"Neuch\u00e2tel",
    "wof:name":"Eusia Sa",
    "wof:placetype":"venue"
},
  "geometry": {"coordinates":[6.931085,46.990334],"type":"Point"}
}