{
  "type": "Feature",
  "properties": {
    "iso:country":"CH",
    "sg:address":"M\u00e4rtplatz 29",
    "sg:city":"Effretikon",
    "sg:orig_category":"Bau\u00e4mter",
    "sg:phone":"+41 52 354 24 72",
    "sg:postcode":"8307",
    "sg:province":"Z\u00fcrich",
    "wof:name":"Bauamt Der Gemeinde Effretikon",
    "wof:placetype":"venue"
},
  "geometry": {"coordinates":[8.686257,47.427307],"type":"Point"}
}