{
  "type": "Feature",
  "properties": {
    "iso:country":"CH",
    "sg:address":"Fluhweg 11",
    "sg:city":"Obermumpf",
    "sg:orig_category":"Handelsvermittlung Unternehmensberatung",
    "sg:phone":"+41 62 873 25 64",
    "sg:postcode":"4324",
    "sg:province":"Aargau",
    "wof:name":"Ren\u00e9 R\u00f6sti Consulting",
    "wof:placetype":"venue"
},
  "geometry": {"coordinates":[7.9371991158,47.5313301086],"type":"Point"}
}