{
  "type": "Feature",
  "properties": {
    "iso:country":"CH",
    "sg:address":"Sunnmatt 5",
    "sg:city":"Zumikon",
    "sg:orig_category":"Non-Classified Establishments",
    "sg:postcode":"8126",
    "sg:province":"Z\u00fcrich",
    "wof:name":"Miniera Ag",
    "wof:placetype":"venue"
},
  "geometry": {"coordinates":[8.6150016785,47.3348236084],"type":"Point"}
}