{
  "type": "Feature",
  "properties": {
    "iso:country":"CH",
    "sg:address":"6853 Ligornetto. Postfach Caselle Postale 6",
    "sg:city":"Ligornetto",
    "sg:orig_category":"Sportvereine Ballsport Fussball",
    "sg:phone":"+41 91 647 39 69",
    "sg:postcode":"6853",
    "sg:province":"Ticino",
    "wof:name":"Fc Ligornetto",
    "wof:placetype":"venue"
},
  "geometry": {"coordinates":[8.9537200928,45.8623580933],"type":"Point"}
}