{
  "type": "Feature",
  "properties": {
    "iso:country":"CH",
    "sg:address":"Ai Campisc",
    "sg:city":"Camorino",
    "sg:orig_category":"Mechanische Werkst\u00e4tten",
    "sg:phone":"+41 91 857 86 71",
    "sg:postcode":"6528",
    "sg:province":"Ticino",
    "wof:name":"J\u00fcrg B\u00e4rtschiger Officina Meccanica",
    "wof:placetype":"venue"
},
  "geometry": {"coordinates":[8.9860601425,46.1608963013],"type":"Point"}
}