{
  "type": "Feature",
  "properties": {
    "addr:full":"Pilatusstrasse 14 Luzern Luzern 6003",
    "addr:housenumber":"14",
    "addr:postcode":"6003",
    "addr:street":"Pilatusstrasse",
    "iso:country":"CH",
    "sg:address":"Pilatusstrasse 14",
    "sg:city":"Luzern",
    "sg:orig_category":"Detailhandel mit Brillen U anderen Sehhilfen Fachdetailhandel in Verkaufsr\u00e4umen",
    "sg:phone":"+41 41 850 64 81",
    "sg:postcode":"6003",
    "sg:province":"Luzern",
    "wof:name":"Looser Optik",
    "wof:placetype":"venue"
},
  "geometry": {"coordinates":[8.440386,47.080822],"type":"Point"}
}