{
  "type": "Feature",
  "properties": {
    "iso:country":"CH",
    "sg:address":"Bifang",
    "sg:city":"Oberschrot",
    "sg:orig_category":"Non-Classified Establishments",
    "sg:postcode":"1716",
    "sg:province":"Fribourg",
    "wof:name":"Dr.med. Paul M\u00fclhauser Spezialarzt Fmh",
    "wof:placetype":"venue"
},
  "geometry": {"coordinates":[7.2914948463,46.7480926514],"type":"Point"}
}