{
  "type": "Feature",
  "properties": {
    "iso:country":"CH",
    "sg:address":"Haldenstrasse 5 6340 Baar. Postfach 2724",
    "sg:city":"Baar",
    "sg:orig_category":"Handelsvermittlung U Grosshandel",
    "sg:phone":"+41 41 766 30 80",
    "sg:postcode":"6342",
    "sg:province":"Zug",
    "wof:name":"Spectratec Ag",
    "wof:placetype":"venue"
},
  "geometry": {"coordinates":[8.5383815765,47.1966171265],"type":"Point"}
}