{
  "type": "Feature",
  "properties": {
    "iso:country":"CH",
    "sg:address":"1562",
    "sg:city":"Corcelles-pr\u00e8s-payerne",
    "sg:classifiers":[
        {
            "category":"Manufacturing",
            "subcategory":"Building Materials",
            "type":"Manufacturing & Wholesale Goods"
        }
    ],
    "sg:phone":"+41 26 662 55 55",
    "sg:postcode":"1562",
    "sg:province":"Vaud",
    "sg:tags":[
        "masonry",
        "brick",
        "fired"
    ],
    "wof:name":"Morandi Fr\u00e8res S.a.",
    "wof:placetype":"venue"
},
  "geometry": {"coordinates":[6.9615449905,46.8308105469],"type":"Point"}
}