{
  "type": "Feature",
  "properties": {
    "addr:full":"Farnigasse 10 Grossaffoltern Bern 3257",
    "addr:housenumber":"10",
    "addr:postcode":"3257",
    "addr:street":"Farnigasse",
    "iso:country":"CH",
    "sg:address":"Farnigasse 10",
    "sg:city":"Grossaffoltern",
    "sg:orig_category":"Autogaragen Autospenglereien",
    "sg:phone":"+41 32 389 14 74",
    "sg:postcode":"3257",
    "sg:province":"Bern",
    "wof:name":"Garage & Carrosserie Aebnit Gebr.m.& S.studer",
    "wof:placetype":"venue"
},
  "geometry": {"coordinates":[7.355751,47.062878],"type":"Point"}
}