{
  "type": "Feature",
  "properties": {
    "iso:country":"CH",
    "sg:address":"Via Cantonale",
    "sg:city":"Porza",
    "sg:orig_category":"Unternehmensberatung",
    "sg:postcode":"6948",
    "sg:province":"Ticino",
    "wof:name":"Brassel Sa",
    "wof:placetype":"venue"
},
  "geometry": {"coordinates":[8.9513950348,46.0242385864],"type":"Point"}
}