{
  "type": "Feature",
  "properties": {
    "iso:country":"CH",
    "sg:address":"Bahnhofstrasse 3 4805 Brittnau. Postfach",
    "sg:city":"Brittnau",
    "sg:orig_category":"Hardwareberatung Sonstige mit der Informatik verbundene T\u00e4tigkeiten",
    "sg:phone":"+41 62 752 87 17",
    "sg:postcode":"4805",
    "sg:province":"Aargau",
    "wof:name":"Compubit Ag",
    "wof:placetype":"venue"
},
  "geometry": {"coordinates":[7.9493398666,47.2600212097],"type":"Point"}
}