{
  "type": "Feature",
  "properties": {
    "iso:country":"CH",
    "sg:address":"Gesigenweg 16",
    "sg:city":"Spiez",
    "sg:orig_category":"Vermietung U Verpachtung von eigenen Immobilien",
    "sg:postcode":"3700",
    "sg:province":"Bern",
    "wof:name":"B\u00fchler H. Ag Spiez",
    "wof:placetype":"venue"
},
  "geometry": {"coordinates":[7.6608781815,46.6926269531],"type":"Point"}
}