{
  "type": "Feature",
  "properties": {
    "iso:country":"CH",
    "sg:address":"Zumhofstrasse 10 6010 Kriens. Postfach 120",
    "sg:city":"Kriens",
    "sg:orig_category":"Architektur U Ingenieurb\u00fcros",
    "sg:phone":"+41 41 320 64 46",
    "sg:postcode":"6011",
    "sg:province":"Luzern",
    "wof:name":"Gritec Institut F\u00fcr Angewandte Technologie Ag",
    "wof:placetype":"venue"
},
  "geometry": {"coordinates":[8.266975,47.035957],"type":"Point"}
}