{
  "type": "Feature",
  "properties": {
    "iso:country":"CH",
    "sg:address":"F\u00f6s",
    "sg:city":"Gurmels",
    "sg:orig_category":"Fahrschulen, Flugschulen",
    "sg:phone":"+41 26 674 18 76",
    "sg:postcode":"3212",
    "sg:province":"Fribourg",
    "wof:name":"Walter Jakob Fahrschule",
    "wof:placetype":"venue"
},
  "geometry": {"coordinates":[7.1731948853,46.8936653137],"type":"Point"}
}