{
  "type": "Feature",
  "properties": {
    "iso:country":"CH",
    "sg:address":"Route Du Simplon 27a",
    "sg:city":"Sierre",
    "sg:orig_category":"Grosshandel mit Eisenwaren sowie Installationsbedarf f\u00fcr Gas, Wasser U Heizung Sanit\u00e4r, Heizungs U L",
    "sg:phone":"+41 12718540",
    "sg:postcode":"3960",
    "sg:province":"Valais",
    "wof:name":"Ctc W\u00e4rme Ag",
    "wof:placetype":"venue"
},
  "geometry": {"coordinates":[7.5416789055,46.2968292236],"type":"Point"}
}