{
  "type": "Feature",
  "properties": {
    "iso:country":"CH",
    "sg:address":"9657",
    "sg:city":"Unterwasser",
    "sg:classifiers":[
        {
            "category":"Travel",
            "subcategory":"Hotels & Motels",
            "type":"Entertainment"
        }
    ],
    "sg:phone":"+41 71 999 11 12",
    "sg:postcode":"9657",
    "sg:province":"St. Gallen",
    "sg:tags":[
        "hotels",
        "mit",
        "restaurant"
    ],
    "wof:name":"Hotel Traube",
    "wof:placetype":"venue"
},
  "geometry": {"coordinates":[9.305970192,47.1969604492],"type":"Point"}
}