{
  "type": "Feature",
  "properties": {
    "addr:full":"Breitlenweg 8 Hombrechtikon Z\u00fcrich 8634",
    "addr:housenumber":"8",
    "addr:postcode":"8634",
    "addr:street":"Breitlenweg",
    "iso:country":"CH",
    "sg:address":"Breitlenweg 8",
    "sg:city":"Hombrechtikon",
    "sg:orig_category":"Dachdeckerei D\u00e4mmung gegen K\u00e4lte, W\u00e4rme, Schall U Ersch\u00fctterung",
    "sg:phone":"+41 55 244 18 88",
    "sg:postcode":"8634",
    "sg:province":"Z\u00fcrich",
    "wof:name":"Bisang & Egli Bedachungen Dachisolierungen",
    "wof:placetype":"venue"
},
  "geometry": {"coordinates":[8.768809,47.252785],"type":"Point"}
}