{
  "type": "Feature",
  "properties": {
    "iso:country":"CH",
    "sg:address":"Unterdorfstrasse 4 9125 Brunnadern. Postfach 17",
    "sg:city":"Brunnadern",
    "sg:orig_category":"Herstellung von sonstigen keramischen Erzeugnissen f\u00fcr technische Zwecke",
    "sg:postcode":"9125",
    "sg:province":"St. Gallen",
    "wof:name":"Altico Sa Prodotti Ceramici Industriali",
    "wof:placetype":"venue"
},
  "geometry": {"coordinates":[9.0190391541,45.856678009],"type":"Point"}
}