{
  "type": "Feature",
  "properties": {
    "iso:country":"CH",
    "sg:address":"Zentralstrasse 9 8212 Neuhausen. Postfach 1212",
    "sg:city":"Neuhausen",
    "sg:classifiers":[
        {
            "category":"Restaurant",
            "type":"Food & Drink"
        }
    ],
    "sg:phone":"+41 52 672 25 11",
    "sg:postcode":"8212",
    "sg:province":"Schaffhausen",
    "wof:name":"Restaurant Centro",
    "wof:placetype":"venue"
},
  "geometry": {"coordinates":[8.6186923981,47.6804962158],"type":"Point"}
}