{
  "type": "Feature",
  "properties": {
    "iso:country":"CH",
    "sg:address":"Bahnhofstrasse 29",
    "sg:city":"Zug",
    "sg:orig_category":"Finanzierungsinstitutionen",
    "sg:postcode":"6300",
    "sg:province":"Zug",
    "wof:name":"Wefinanz Wetli P.",
    "wof:placetype":"venue"
},
  "geometry": {"coordinates":[8.5156650543,47.1704330444],"type":"Point"}
}