{
  "type": "Feature",
  "properties": {
    "iso:country":"CH",
    "sg:address":"Dorfplatz 14",
    "sg:city":"Hergiswil",
    "sg:classifiers":[
        {
            "category":"Banks & Credit Unions",
            "subcategory":"Bank",
            "type":"Services"
        }
    ],
    "sg:postcode":"6052",
    "sg:province":"Nidwalden",
    "wof:name":"Electricit\u00e9 Neuch\u00e2teloise Sa",
    "wof:placetype":"venue"
},
  "geometry": {"coordinates":[7.45507,47.28537],"type":"Point"}
}