{
  "type": "Feature",
  "properties": {
    "iso:country":"CH",
    "sg:address":"Niederstad 6 6053 Alpnachstad. Postfach",
    "sg:city":"Alpnachstad",
    "sg:orig_category":"Campingpl\u00e4tze",
    "sg:phone":"+41 41 671 07 30",
    "sg:postcode":"6053",
    "sg:province":"Obwalden",
    "wof:name":"Camping Bachmattli, Iten Martin",
    "wof:placetype":"venue"
},
  "geometry": {"coordinates":[8.27609,46.953575],"type":"Point"}
}