{
  "type": "Feature",
  "properties": {
    "iso:country":"CH",
    "sg:address":"Avenue Du Mail 21",
    "sg:city":"Gen\u00e8ve",
    "sg:orig_category":"Malerei",
    "sg:phone":"+41 22 328 00 86",
    "sg:postcode":"1205",
    "sg:province":"Gen\u00e8ve",
    "wof:name":"Hans Stacher Entreprise De Peinture",
    "wof:placetype":"venue"
},
  "geometry": {"coordinates":[6.139567852,46.1971931458],"type":"Point"}
}