{
  "type": "Feature",
  "properties": {
    "iso:country":"CH",
    "sg:address":"Sattelbogenstrasse 10 9220 Bischofszell. Postfach",
    "sg:city":"Bischofszell",
    "sg:orig_category":"Grosshandel mit festen Brennstoffen U Mineral\u00f6lerzeugnissen Herstellung von rohen \u00d6len U Fetten",
    "sg:phone":"+41 71 422 27 66",
    "sg:postcode":"9220",
    "sg:province":"Thurgau",
    "wof:name":"Citrup Ag",
    "wof:placetype":"venue"
},
  "geometry": {"coordinates":[9.248134613,47.4968605042],"type":"Point"}
}