{
  "type": "Feature",
  "properties": {
    "iso:country":"CH",
    "sg:address":"Avenue De La Fusion 160",
    "sg:city":"Martigny",
    "sg:orig_category":"Sanit\u00e4r, Heizungs U L\u00fcftungsinstallation",
    "sg:postcode":"1920",
    "sg:province":"Valais",
    "wof:name":"Carroz Sa",
    "wof:placetype":"venue"
},
  "geometry": {"coordinates":[7.2124481201,46.0804595947],"type":"Point"}
}