{
  "type": "Feature",
  "properties": {
    "addr:full":"Industriestrasse 65 Zollikofen Bern 3052",
    "addr:housenumber":"65",
    "addr:postcode":"3052",
    "addr:street":"Industriestrasse",
    "iso:country":"CH",
    "sg:address":"Industriestrasse 65",
    "sg:city":"Zollikofen",
    "sg:orig_category":"Autotransporte international",
    "sg:phone":"+41 848 880 770",
    "sg:postcode":"3052",
    "sg:province":"Bern",
    "wof:name":"Deutsche Post (schweiz) Ag",
    "wof:placetype":"venue"
},
  "geometry": {"coordinates":[7.702582,47.530758],"type":"Point"}
}