{
  "type": "Feature",
  "properties": {
    "iso:country":"CH",
    "sg:address":"Grand-rue 41",
    "sg:city":"Payerne",
    "sg:orig_category":"Detailhandel mit Brot, Back U S\u00fcsswaren",
    "sg:phone":"+41 26 660 57 90",
    "sg:postcode":"1530",
    "sg:province":"Vaud",
    "wof:name":"G\u00e9rard Fornerod Boulangerie & P\u00e2tisserie",
    "wof:placetype":"venue"
},
  "geometry": {"coordinates":[6.936311,46.820984],"type":"Point"}
}