{
  "type": "Feature",
  "properties": {
    "iso:country":"CH",
    "sg:address":"St\u00f6ckenmattstrasse 52",
    "sg:city":"Orpund",
    "sg:orig_category":"Grosshandel mit Holz U Bauelementen aus Holz Grosshandel mit Holz U Baustoffen",
    "sg:phone":"+41 32 355 13 38",
    "sg:postcode":"2552",
    "sg:province":"Bern",
    "wof:name":"Hans Frei Holzhandel Ag",
    "wof:placetype":"venue"
},
  "geometry": {"coordinates":[7.2986750603,47.1381721497],"type":"Point"}
}