{
  "type": "Feature",
  "properties": {
    "iso:country":"CH",
    "sg:address":"1647",
    "sg:city":"Corbi\u00e8res",
    "sg:orig_category":"Herstellung von sonstigen Holzwaren",
    "sg:phone":"+41 26 915 18 60",
    "sg:postcode":"1647",
    "sg:province":"Fribourg",
    "wof:name":"Blanc Roland",
    "wof:placetype":"venue"
},
  "geometry": {"coordinates":[7.1178998947,46.6581192017],"type":"Point"}
}