{
  "type": "Feature",
  "properties": {
    "iso:country":"CH",
    "sg:address":"Hauptstrasse 52 6045 Meggen. Postfach 464",
    "sg:city":"Meggen",
    "sg:orig_category":"Kantonalbanken",
    "sg:phone":"+41 41 206 44 44",
    "sg:postcode":"6045",
    "sg:province":"Luzern",
    "wof:name":"Luzerner Kantonalbank",
    "wof:placetype":"venue"
},
  "geometry": {"coordinates":[8.3738908768,47.0464820862],"type":"Point"}
}