{
  "type": "Feature",
  "properties": {
    "iso:country":"CH",
    "sg:address":"Neugr\u00fct 7 9496 Balzers. Postfach 222",
    "sg:city":"Balzers",
    "sg:orig_category":"Herstellung von optischen Instrumenten",
    "sg:phone":"+41 32 373 33 11",
    "sg:postcode":"9496",
    "wof:name":"Lastec Ag Laserger\u00e4te & -lohnarbeiten",
    "wof:placetype":"venue"
},
  "geometry": {"coordinates":[7.2758579254,47.1247749329],"type":"Point"}
}