{
  "type": "Feature",
  "properties": {
    "iso:country":"CH",
    "sg:address":"Bahnhofstrasse 16 9435 Heerbrugg. Postfach",
    "sg:city":"Heerbrugg",
    "sg:orig_category":"Herstellung von sonstigen elektrischen Ausr\u00fcstungen",
    "sg:phone":"+41 71 722 80 80",
    "sg:postcode":"9435",
    "sg:province":"St. Gallen",
    "wof:name":"Electrade Zimmermann",
    "wof:placetype":"venue"
},
  "geometry": {"coordinates":[9.6269903183,47.4105415344],"type":"Point"}
}