{
  "type": "Feature",
  "properties": {
    "iso:country":"CH",
    "sg:address":"Altkircherstrasse 8 4027 Basel. Postfach 51",
    "sg:city":"Basel",
    "sg:orig_category":"Werbung",
    "sg:phone":"+41 61 308 96 06",
    "sg:postcode":"4027",
    "wof:name":"Neon Sign Gmbh",
    "wof:placetype":"venue"
},
  "geometry": {"coordinates":[7.5705962181,47.5532264709],"type":"Point"}
}