{
  "type": "Feature",
  "properties": {
    "iso:country":"CH",
    "sg:address":"Chemin De La Greube 24",
    "sg:city":"Vernier",
    "sg:orig_category":"G\u00fcterbef\u00f6rderung im Strassenverkehr",
    "sg:phone":"+41 22 341 33 35",
    "sg:postcode":"1214",
    "sg:province":"Gen\u00e8ve",
    "wof:name":"Di Sanza Fr\u00e8res, Di Sanza Elio & Fedele Antonio, Successeurs",
    "wof:placetype":"venue"
},
  "geometry": {"coordinates":[6.081469059,46.2091064453],"type":"Point"}
}