{
  "type": "Feature",
  "properties": {
    "iso:country":"CH",
    "sg:address":"Alte Landstrasse 7",
    "sg:city":"Horgen",
    "sg:classifiers":[
        {
            "category":"Government",
            "subcategory":"Post Office",
            "type":"Public Place"
        }
    ],
    "sg:phone":"+41 71 744 21 16",
    "sg:postcode":"8810",
    "sg:province":"Z\u00fcrich",
    "sg:tags":[
        "caf\u00e9s",
        "tea-rooms"
    ],
    "wof:name":"Dorfkafi",
    "wof:placetype":"venue"
},
  "geometry": {"coordinates":[9.6351919174,47.4310073853],"type":"Point"}
}