{
  "type": "Feature",
  "properties": {
    "iso:country":"CH",
    "sg:address":"Hofuri",
    "sg:city":"Scharnachtal",
    "sg:orig_category":"Praxis f\u00fcr Atlaslogie",
    "sg:phone":"+41 33 676 23 26",
    "sg:postcode":"3722",
    "sg:province":"Bern",
    "wof:name":"Ruedi Zurbr\u00fcgg Praxis F\u00fcr Atlaslogie",
    "wof:placetype":"venue"
},
  "geometry": {"coordinates":[7.6981868744,46.6171684265],"type":"Point"}
}