{
  "type": "Feature",
  "properties": {
    "iso:country":"CH",
    "sg:address":"Chemin De Pr\u00e9-marquis 5d 1241 Puplinge. Postfach",
    "sg:city":"Puplinge",
    "sg:orig_category":"Schreib U \u00dcbersetzungsb\u00fcros",
    "sg:postcode":"1241",
    "sg:province":"Gen\u00e8ve",
    "wof:name":"Tradutech, Heilmann Otto",
    "wof:placetype":"venue"
},
  "geometry": {"coordinates":[6.232339859,46.2131004333],"type":"Point"}
}