{
  "type": "Feature",
  "properties": {
    "iso:country":"CH",
    "sg:address":"Rue De La Gare 28",
    "sg:city":"Aigle",
    "sg:classifiers":[
        {
            "category":"Travel",
            "subcategory":"Hotels & Motels",
            "type":"Entertainment"
        }
    ],
    "sg:postcode":"1860",
    "sg:province":"Vaud",
    "sg:tags":[
        "hotels",
        "mit",
        "restaurant"
    ],
    "wof:name":"Rr Concept Congress Organization Grohe R\u00e9gina",
    "wof:placetype":"venue"
},
  "geometry": {"coordinates":[6.5580701828,46.5100784302],"type":"Point"}
}