{
  "type": "Feature",
  "properties": {
    "iso:country":"CH",
    "sg:address":"Glarnerstrasse 22",
    "sg:city":"Siebnen",
    "sg:orig_category":"Unclassifiable Establishments",
    "sg:phone":"+41 77916665",
    "sg:postcode":"8854",
    "sg:province":"Schwyz",
    "wof:name":"Odermatt Paul",
    "wof:placetype":"venue"
},
  "geometry": {"coordinates":[8.8992977142,47.1748924255],"type":"Point"}
}