{
  "type": "Feature",
  "properties": {
    "iso:country":"CH",
    "sg:address":"Route De Moutier 45",
    "sg:city":"Del\u00e9mont",
    "sg:orig_category":"Grosshandel mit lebenden Tieren",
    "sg:phone":"+41 79 631 17 38",
    "sg:postcode":"2800",
    "sg:province":"Jura",
    "wof:name":"De Toro Nicola",
    "wof:placetype":"venue"
},
  "geometry": {"coordinates":[7.3533368111,47.3629837036],"type":"Point"}
}