{
  "type": "Feature",
  "properties": {
    "iso:country":"CH",
    "sg:address":"Luisenstrasse 40 8005 Z\u00fcrich. Postfach",
    "sg:city":"Z\u00fcrich",
    "sg:orig_category":"RESTAURANTS: TEA-ROOMS",
    "sg:postcode":"8036",
    "sg:province":"Z\u00fcrich",
    "wof:name":"La Cumbia Sa",
    "wof:placetype":"venue"
},
  "geometry": {"coordinates":[6.5032129288,46.8187484741],"type":"Point"}
}