{
  "type": "Feature",
  "properties": {
    "addr:full":"Fontanivas Disentis/must\u00e9r Graubunden 7180",
    "addr:postcode":"7180",
    "iso:country":"CH",
    "sg:address":"Fontanivas",
    "sg:city":"Disentis/must\u00e9r",
    "sg:orig_category":"Campingpl\u00e4tze Detailhandel mit Zeitungen U Zeitschriften Kioske",
    "sg:phone":"+41 81 947 44 22",
    "sg:postcode":"7180",
    "sg:province":"Graubunden",
    "wof:name":"Camping Tcs",
    "wof:placetype":"venue"
},
  "geometry": {"coordinates":[8.853068,46.696613],"type":"Point"}
}