{
  "type": "Feature",
  "properties": {
    "addr:full":"Oberwiesstrasse 50 8645 Jona. Postfach 2225 Jona St. Gallen 8645",
    "addr:housenumber":"50",
    "addr:postcode":"8645;2225;8645",
    "addr:street":"Oberwiesstrasse;Postfach;Jona",
    "iso:country":"CH",
    "sg:address":"Oberwiesstrasse 50 8645 Jona. Postfach 2225",
    "sg:city":"Jona",
    "sg:orig_category":"Grosshandel mit Werkzeugmaschinen Herstellung von Werkzeugmaschinen",
    "sg:phone":"+41 55 212 40 32",
    "sg:postcode":"8645",
    "sg:province":"St. Gallen",
    "wof:name":"Blechbearbeitungs-maschinen Gubler Urs",
    "wof:placetype":"venue"
},
  "geometry": {"coordinates":[8.843248,47.231693],"type":"Point"}
}