{
  "type": "Feature",
  "properties": {
    "iso:country":"CH",
    "sg:address":"Leimenstrasse 29 4051 Basel. Postfach",
    "sg:city":"Basel",
    "sg:orig_category":"Non-Classified Establishments",
    "sg:postcode":"4051",
    "sg:province":"Basel-Stadt",
    "wof:name":"Jays Indian Food Company Gmbh Hauslieferdienste Und Take-away-laden Usw",
    "wof:placetype":"venue"
},
  "geometry": {"coordinates":[7.5826468468,47.5540428162],"type":"Point"}
}