{
  "type": "Feature",
  "properties": {
    "iso:country":"CH",
    "sg:address":"T\u00f6distrasse 47 8002 Z\u00fcrich. Postfach",
    "sg:city":"Z\u00fcrich",
    "sg:orig_category":"Banken sonstige",
    "sg:phone":"+41 12043434",
    "sg:postcode":"8022",
    "sg:province":"Z\u00fcrich",
    "wof:name":"Pkb Privatbank Sa Universalbank Usw",
    "wof:placetype":"venue"
},
  "geometry": {"coordinates":[8.533735,47.36731],"type":"Point"}
}