{
  "type": "Feature",
  "properties": {
    "iso:country":"CH",
    "sg:address":"Kreuzlingerstrasse 23",
    "sg:city":"Weinfelden",
    "sg:orig_category":"RESTAURANTS: TEA-ROOMS",
    "sg:phone":"+41 71 622 30 20",
    "sg:postcode":"8570",
    "sg:province":"Thurgau",
    "wof:name":"Restaurant Engel Inhaber Sch\u00e4r-rhyner U. + H.p.",
    "wof:placetype":"venue"
},
  "geometry": {"coordinates":[9.11947155,47.5666656494],"type":"Point"}
}