{
  "type": "Feature",
  "properties": {
    "iso:country":"CH",
    "sg:address":"Jurastrasse 11",
    "sg:city":"Luterbach",
    "sg:orig_category":"Grosshandel mit Maschinen U Ausr\u00fcstungen Herstellung von Werkzeugmaschinen",
    "sg:phone":"+41 41 787 22 33",
    "sg:postcode":"4542",
    "sg:province":"Solothurn",
    "wof:name":"Kumatec Ag",
    "wof:placetype":"venue"
},
  "geometry": {"coordinates":[8.3536720276,47.1747055054],"type":"Point"}
}