{
  "type": "Feature",
  "properties": {
    "iso:country":"CH",
    "sg:address":"Marterey Rue 3 1005 Lausanne. Postfach",
    "sg:city":"Lausanne",
    "sg:orig_category":"Grosshandel mit sonstigen Maschinen U Ausr\u00fcstungen f\u00fcr Industrie, Handel U Schiffahrt",
    "sg:phone":"+41 21 312 85 37",
    "sg:postcode":"1003",
    "sg:province":"Vaud",
    "wof:name":"Tecomag, Schumacher D. Equipement, Accessoires P Machines-outils Etc; Comm",
    "wof:placetype":"venue"
},
  "geometry": {"coordinates":[6.6375927925,46.5199966431],"type":"Point"}
}