{
  "type": "Feature",
  "properties": {
    "addr:full":"Hauptstrasse 47 M\u00f6hlin Aargau 4313",
    "addr:housenumber":"47",
    "addr:postcode":"4313",
    "addr:street":"Hauptstrasse",
    "iso:country":"CH",
    "sg:address":"Hauptstrasse 47",
    "sg:city":"M\u00f6hlin",
    "sg:orig_category":"Detailhandel mit Blumen U Pflanzen",
    "sg:phone":"+41 61 851 03 13",
    "sg:postcode":"4313",
    "sg:province":"Aargau",
    "wof:name":"Isabel's Bluemeh\u00fcsli Blumengesch\u00e4ft",
    "wof:placetype":"venue"
},
  "geometry": {"coordinates":[7.844153,47.559479],"type":"Point"}
}