{
  "type": "Feature",
  "properties": {
    "iso:country":"CH",
    "sg:address":"Gottfried-reimann-strasse 23a",
    "sg:city":"Biel/bienne",
    "sg:orig_category":"Vorschulen, Kinderg\u00e4rten",
    "sg:phone":"+41 32 342 48 78",
    "sg:postcode":"2504",
    "sg:province":"Bern",
    "wof:name":"Kindergarten",
    "wof:placetype":"venue"
},
  "geometry": {"coordinates":[7.2830080986,47.1491508484],"type":"Point"}
}