{
  "type": "Feature",
  "properties": {
    "iso:country":"CH",
    "sg:address":"Roches Aux 47",
    "sg:city":"Wallenried",
    "sg:orig_category":"Grosshandel mit pharmazeutischen Erzeugnissen, medizinischen U orthop\u00e4dischen Artikeln",
    "sg:postcode":"1784",
    "sg:province":"Fribourg",
    "wof:name":"Etter Agro & Anh\u00e4nger Gmbh",
    "wof:placetype":"venue"
},
  "geometry": {"coordinates":[7.1192002296,46.8845748901],"type":"Point"}
}