{
  "type": "Feature",
  "properties": {
    "iso:country":"CH",
    "sg:address":"Bahnhofstrasse 111",
    "sg:city":"Uzwil",
    "sg:orig_category":"Sonstige Kultur U Unterhaltungseinrichtungen",
    "sg:phone":"+41 71 951 90 72",
    "sg:postcode":"9240",
    "sg:province":"St. Gallen",
    "wof:name":"Kulturzentrum Islamisch-t\u00fcrkisches",
    "wof:placetype":"venue"
},
  "geometry": {"coordinates":[9.1372537613,47.4408416748],"type":"Point"}
}