{
  "type": "Feature",
  "properties": {
    "iso:country":"CH",
    "sg:address":"M\u00fchlegasse 7",
    "sg:city":"Gerlafingen",
    "sg:orig_category":"Maler U Glasergewerbe",
    "sg:phone":"+41 79 411 96 17",
    "sg:postcode":"4563",
    "sg:province":"Solothurn",
    "wof:name":"Weber Thomas",
    "wof:placetype":"venue"
},
  "geometry": {"coordinates":[7.5710492134,47.1705436707],"type":"Point"}
}