{
  "type": "Feature",
  "properties": {
    "iso:country":"CH",
    "sg:address":"Rundbuckstrasse 6",
    "sg:city":"Neuhausen",
    "sg:orig_category":"Detailhandel mit elektrischen Haushalts-,Radio U Fernsehger\u00e4ten sowie Musikinstrumenten",
    "sg:phone":"+41 41 799 02 80",
    "sg:postcode":"8212",
    "sg:province":"Schaffhausen",
    "wof:name":"Pl & T Ag",
    "wof:placetype":"venue"
},
  "geometry": {"coordinates":[8.6040248871,47.6752586365],"type":"Point"}
}