{
  "type": "Feature",
  "properties": {
    "iso:country":"CH",
    "sg:address":"Bahnhof",
    "sg:city":"Arosa",
    "sg:orig_category":"Wirtschafts- and Arbeitgeberverb\u00e4nde",
    "sg:postcode":"7050",
    "sg:province":"Graubunden",
    "wof:name":"Fuhrhalterverband Davos",
    "wof:placetype":"venue"
},
  "geometry": {"coordinates":[9.8141050339,46.7818450928],"type":"Point"}
}