{
  "type": "Feature",
  "properties": {
    "iso:country":"CH",
    "sg:address":"Hauptstrasse 14 8867 Niederurnen. Postfach",
    "sg:city":"Niederurnen",
    "sg:orig_category":"Detailhandel mit Waren verschiedener Art, Hauptrichtung Nahrungsmittel",
    "sg:phone":"+41 55 610 12 50",
    "sg:postcode":"8867",
    "sg:province":"Glarus",
    "wof:name":"Heinz M\u00e4rklin Lebensmittel",
    "wof:placetype":"venue"
},
  "geometry": {"coordinates":[9.0525350571,47.124546051],"type":"Point"}
}