{
  "type": "Feature",
  "properties": {
    "addr:full":"Hauptstrasse 90 Binningen Basel-Landschaft 4102",
    "addr:housenumber":"90",
    "addr:postcode":"4102",
    "addr:street":"Hauptstrasse",
    "iso:country":"CH",
    "sg:address":"Hauptstrasse 90",
    "sg:city":"Binningen",
    "sg:orig_category":"Architektur U Ingenieurb\u00fcros Geometerb\u00fcros",
    "sg:phone":"+41 61 426 94 94",
    "sg:postcode":"4102",
    "sg:province":"Basel-Landschaft",
    "wof:name":"Jermann Ingenieure Und Geometer Ag",
    "wof:placetype":"venue"
},
  "geometry": {"coordinates":[7.572632,47.539566],"type":"Point"}
}