{
  "type": "Feature",
  "properties": {
    "iso:country":"CH",
    "sg:address":"Mythencenterstrasse 16",
    "sg:city":"Ibach",
    "sg:orig_category":"Detailhandel mit Schreib U Papeteriewaren",
    "sg:phone":"+41 41 811 10 55",
    "sg:postcode":"6438",
    "sg:province":"Schwyz",
    "wof:name":"Mc Paperland",
    "wof:placetype":"venue"
},
  "geometry": {"coordinates":[8.6458873749,47.0148544312],"type":"Point"}
}