{
  "type": "Feature",
  "properties": {
    "iso:country":"CH",
    "sg:address":"2042",
    "sg:city":"Valangin",
    "sg:orig_category":"S\u00e4ge, Hobel U Holzimpr\u00e4gnierwerke S\u00e4gewerke",
    "sg:phone":"+41 62 758 40 58",
    "sg:postcode":"2042",
    "sg:province":"Neuch\u00e2tel",
    "wof:name":"Planzer Holz Ag",
    "wof:placetype":"venue"
},
  "geometry": {"coordinates":[7.9477200508,47.2290992737],"type":"Point"}
}