{
  "type": "Feature",
  "properties": {
    "iso:country":"CH",
    "sg:address":"Via Ai Ronchi 1",
    "sg:city":"Breganzona",
    "sg:orig_category":"Bauingenieurb\u00fcros allgemein Markt U Meinungsforschung",
    "sg:phone":"+41 79 620 56 26",
    "sg:postcode":"6932",
    "sg:province":"Ticino",
    "wof:name":"Sch\u00f6nenberger + Partner Sa",
    "wof:placetype":"venue"
},
  "geometry": {"coordinates":[8.93149,46.001801],"type":"Point"}
}