{
  "type": "Feature",
  "properties": {
    "iso:country":"CH",
    "sg:address":"Dorfplatz 11",
    "sg:city":"Gelterkinden",
    "sg:orig_category":"Unclassifiable Establishments",
    "sg:phone":"+41 61 981 32 24",
    "sg:postcode":"4460",
    "sg:province":"Basel-Landschaft",
    "wof:name":"Internet B\u00f6rsen Caf\u00e9 Gmbh",
    "wof:placetype":"venue"
},
  "geometry": {"coordinates":[7.8572001457,47.4646606445],"type":"Point"}
}