{
  "type": "Feature",
  "properties": {
    "iso:country":"CH",
    "sg:address":"Hadlaubstrasse 130",
    "sg:city":"Z\u00fcrich",
    "sg:orig_category":"Interessenvertretungen",
    "sg:postcode":"8006",
    "sg:province":"Z\u00fcrich",
    "wof:name":"Assoziation Montessori (schweiz), Sektion Der Deutschen Und R\u00e4toromanischen Schweiz",
    "wof:placetype":"venue"
},
  "geometry": {"coordinates":[8.5510950089,47.3914680481],"type":"Point"}
}