{
  "type": "Feature",
  "properties": {
    "iso:country":"CH",
    "sg:address":"Hofwiesenstrasse 55",
    "sg:city":"Z\u00fcrich",
    "sg:orig_category":"Detailhandel mit Beleuchtungs U Haushaltsgegenst\u00e4nden Detailhandel mit M\u00f6beln U Haushaltsgegenst\u00e4nde",
    "sg:phone":"+41 13624219",
    "sg:postcode":"8057",
    "sg:province":"Z\u00fcrich",
    "wof:name":"Eugen Mattes Vorh\u00e4nge",
    "wof:placetype":"venue"
},
  "geometry": {"coordinates":[8.536112,47.394939],"type":"Point"}
}