{
  "type": "Feature",
  "properties": {
    "iso:country":"CH",
    "sg:address":"Industriestrasse 2",
    "sg:city":"Romanshorn",
    "sg:orig_category":"Herstellung von sonstigen Nahrungsmitteln Sonstiger Grosshandel",
    "sg:phone":"+41 14045444",
    "sg:postcode":"8590",
    "sg:province":"Thurgau",
    "wof:name":"Rbc Network Gmbh",
    "wof:placetype":"venue"
},
  "geometry": {"coordinates":[8.4728136063,47.3586730957],"type":"Point"}
}