{
  "type": "Feature",
  "properties": {
    "iso:country":"CH",
    "sg:address":"Fachstrasse 39",
    "sg:city":"Oberrieden",
    "sg:orig_category":"Sonstige mit der Informatik verbundene T\u00e4tigkeiten",
    "sg:postcode":"8942",
    "sg:province":"Z\u00fcrich",
    "wof:name":"Ldi, Dutheil Laurent",
    "wof:placetype":"venue"
},
  "geometry": {"coordinates":[6.1395998001,46.1839904785],"type":"Point"}
}