{
  "type": "Feature",
  "properties": {
    "iso:country":"CH",
    "sg:address":"Chemin Du Coteau 12",
    "sg:city":"Pully",
    "sg:orig_category":"Sanit\u00e4r U Heizungsinstallation Sanit\u00e4r, Heizungs U L\u00fcftungsinstallation",
    "sg:phone":"+41 21 729 92 76",
    "sg:postcode":"1009",
    "sg:province":"Vaud",
    "wof:name":"Raphael D'orazio Installations En Chauffages",
    "wof:placetype":"venue"
},
  "geometry": {"coordinates":[6.6547861099,46.5114593506],"type":"Point"}
}