{
  "type": "Feature",
  "properties": {
    "iso:country":"CH",
    "sg:address":"Hauptstrasse 18",
    "sg:city":"Buus",
    "sg:orig_category":"Herstellung von Metallkonstruktionen Schlossereien",
    "sg:phone":"+41 61 841 21 21",
    "sg:postcode":"4463",
    "sg:province":"Basel-Landschaft",
    "wof:name":"Hans Sutter Schmiede Schlosserei Metallbau",
    "wof:placetype":"venue"
},
  "geometry": {"coordinates":[7.8629908562,47.5064811707],"type":"Point"}
}