{
  "type": "Feature",
  "properties": {
    "iso:country":"CH",
    "sg:address":"Buchholzstrasse 52",
    "sg:city":"Glarus",
    "sg:orig_category":"G\u00fcterbef\u00f6rderung im Strassenverkehr",
    "sg:phone":"+41 55 640 24 36",
    "sg:postcode":"8750",
    "sg:province":"Glarus",
    "wof:name":"Baumgartner Jakob.",
    "wof:placetype":"venue"
},
  "geometry": {"coordinates":[9.0638990402,47.0502052307],"type":"Point"}
}