{
  "type": "Feature",
  "properties": {
    "iso:country":"CH",
    "sg:address":"Avenue De La Gare 9",
    "sg:city":"Moutier",
    "sg:orig_category":"Zahntechnische Laboratorien",
    "sg:phone":"+41 32 493 16 42",
    "sg:postcode":"2740",
    "sg:province":"Bern",
    "wof:name":"Fr\u00e9d\u00e9ric Schwab Labor.de Proth\u00e8ses Dentaires",
    "wof:placetype":"venue"
},
  "geometry": {"coordinates":[7.3794498444,47.2810821533],"type":"Point"}
}