{
  "type": "Feature",
  "properties": {
    "iso:country":"CH",
    "sg:address":"Steinstrasse 38a 5406 R\u00fctihof. Postfach",
    "sg:city":"Freienwil",
    "sg:orig_category":"Architektur U Ingenieurb\u00fcros Architekturb\u00fcros",
    "sg:phone":"+41 56 222 01 74",
    "sg:postcode":"5423",
    "sg:province":"Aargau",
    "wof:name":"Blunschi Edwin Architekt",
    "wof:placetype":"venue"
},
  "geometry": {"coordinates":[8.269957,47.438328],"type":"Point"}
}