{
  "type": "Feature",
  "properties": {
    "iso:country":"CH",
    "sg:address":"R\u00f6merstrasse 12",
    "sg:city":"W\u00fcrenlingen",
    "sg:orig_category":"Politische Parteien SP",
    "sg:phone":"+41 56 281 10 46",
    "sg:postcode":"5303",
    "sg:province":"Aargau",
    "wof:name":"Sp Ortspartei W\u00fcrenlingen",
    "wof:placetype":"venue"
},
  "geometry": {"coordinates":[8.2561903,47.537071228],"type":"Point"}
}