{
  "type": "Feature",
  "properties": {
    "iso:country":"CH",
    "sg:address":"Harderstrasse 17",
    "sg:city":"Interlaken",
    "sg:classifiers":[
        {
            "category":"Bars & Pubs",
            "subcategory":"Wine Bar",
            "type":"Food & Drink"
        }
    ],
    "sg:phone":"+41 33 822 12 79",
    "sg:postcode":"3800",
    "sg:province":"Bern",
    "sg:tags":[
        "caf\u00e9s",
        "tea-rooms"
    ],
    "wof:name":"Caf\u00e9 Bar Babajaga Lounge",
    "wof:placetype":"venue"
},
  "geometry": {"coordinates":[7.855015,46.686935],"type":"Point"}
}