{
  "type": "Feature",
  "properties": {
    "addr:full":"Hasli 6 Glash\u00fctten Aargau 4856",
    "addr:housenumber":"6",
    "addr:postcode":"4856",
    "addr:street":"Hasli",
    "iso:country":"CH",
    "sg:address":"Hasli 6",
    "sg:city":"Glash\u00fctten",
    "sg:orig_category":"Datenverarbeitungsdienste Softwareentwicklung U beratung",
    "sg:phone":"+41 52 745 32 32",
    "sg:postcode":"4856",
    "sg:province":"Aargau",
    "wof:name":"Andreas M\u00fcller Msc M\u00fcller",
    "wof:placetype":"venue"
},
  "geometry": {"coordinates":[9.002906,47.607471],"type":"Point"}
}