{
  "type": "Feature",
  "properties": {
    "iso:country":"CH",
    "sg:address":"Mitteldorf 5",
    "sg:city":"Oeschgen",
    "sg:orig_category":"Detailhandel mit Waren verschiedener Art, Hauptrichtung Nahrungsmittel Grosshandel mit Nahrungsmitte",
    "sg:phone":"+41 62 871 33 42",
    "sg:postcode":"5072",
    "sg:province":"Aargau",
    "wof:name":"Dorflade Yvonne Wunderlin-zundel",
    "wof:placetype":"venue"
},
  "geometry": {"coordinates":[8.017870903,47.5185012817],"type":"Point"}
}