{
  "type": "Feature",
  "properties": {
    "iso:country":"CH",
    "sg:address":"Chalet Marin 1053 Cugy Vd. Postfach",
    "sg:city":"Bretigny-morrens",
    "sg:orig_category":"Mit Sport verbundene T\u00e4tigkeiten RESTAURANTS: TEA-ROOMS",
    "sg:phone":"+41 21 731 24 61",
    "sg:postcode":"1041",
    "sg:province":"Vaud",
    "wof:name":"Restaurant Du Ranch S\u00e0rl",
    "wof:placetype":"venue"
},
  "geometry": {"coordinates":[6.6639499664,46.5902061462],"type":"Point"}
}