{
  "type": "Feature",
  "properties": {
    "iso:country":"CH",
    "sg:address":"Kantonsstrasse 43",
    "sg:city":"Visp",
    "sg:orig_category":"Handel mit Automobilen",
    "sg:phone":"+41 27 946 29 02",
    "sg:postcode":"3930",
    "sg:province":"Valais",
    "wof:name":"Venetz F. Ag",
    "wof:placetype":"venue"
},
  "geometry": {"coordinates":[7.8927898407,46.2929611206],"type":"Point"}
}