{
  "type": "Feature",
  "properties": {
    "iso:country":"CH",
    "sg:address":"Lindenplatz 7",
    "sg:city":"Winterthur",
    "sg:orig_category":"Non-Classified Establishments",
    "sg:postcode":"8408",
    "sg:province":"Z\u00fcrich",
    "wof:name":"Pim Music Musikhaus Agentur Unterricht",
    "wof:placetype":"venue"
},
  "geometry": {"coordinates":[8.6935873032,47.5110435486],"type":"Point"}
}