{
  "type": "Feature",
  "properties": {
    "iso:country":"CH",
    "sg:address":"Forchstrasse 149",
    "sg:city":"Egg",
    "sg:orig_category":"Canalisation",
    "sg:phone":"+41 19840878",
    "sg:postcode":"8132",
    "sg:province":"Z\u00fcrich",
    "wof:name":"Gadola Bau Ag",
    "wof:placetype":"venue"
},
  "geometry": {"coordinates":[8.688892,47.302017],"type":"Point"}
}