{
  "type": "Feature",
  "properties": {
    "iso:country":"CH",
    "sg:address":"Bahnhofstrasse 43",
    "sg:city":"Amriswil",
    "sg:orig_category":"Softwareentwicklung U beratung",
    "sg:postcode":"8580",
    "sg:province":"Thurgau",
    "wof:name":"K\u00fcnzler Cad-dienstleistungen",
    "wof:placetype":"venue"
},
  "geometry": {"coordinates":[9.303229332,47.5497131348],"type":"Point"}
}