{
  "type": "Feature",
  "properties": {
    "iso:country":"CH",
    "sg:address":"Ursprungstrasse 104",
    "sg:city":"M\u00fcnchenbuchsee",
    "sg:orig_category":"Sportvereine Turnen Vereine Damen",
    "sg:phone":"+41 31 869 66 18",
    "sg:postcode":"3053",
    "sg:province":"Bern",
    "wof:name":"Damenriege Stv M\u00fcnchenbuchsee",
    "wof:placetype":"venue"
},
  "geometry": {"coordinates":[7.4568719864,47.0165023804],"type":"Point"}
}