{
  "type": "Feature",
  "properties": {
    "iso:country":"CH",
    "sg:address":"Rainacherstrasse 12",
    "sg:city":"Obernau",
    "sg:orig_category":"Hardwareberatung",
    "sg:postcode":"6012",
    "sg:province":"Luzern",
    "wof:name":"E. Lussi Edv Dienstleistungen",
    "wof:placetype":"venue"
},
  "geometry": {"coordinates":[8.250292778,47.0336303711],"type":"Point"}
}