{
  "type": "Feature",
  "properties": {
    "iso:country":"CH",
    "sg:address":"Lindenwiesstrasse 7",
    "sg:city":"Engelburg",
    "sg:orig_category":"Sonstige mit der Informatik verbundene T\u00e4tigkeiten",
    "sg:phone":"+41 71 260 13 18",
    "sg:postcode":"9032",
    "sg:province":"St. Gallen",
    "wof:name":"Martin Lautner M-art-in",
    "wof:placetype":"venue"
},
  "geometry": {"coordinates":[9.3507928848,47.4339294434],"type":"Point"}
}