{
  "type": "Feature",
  "properties": {
    "iso:country":"CH",
    "sg:address":"Lausannestrasee 48",
    "sg:city":"Meyriez",
    "sg:orig_category":"Detailhandel mit Getr\u00e4nken Grosshandel mit Getr\u00e4nken",
    "sg:phone":"+41 27 932 37 86",
    "sg:postcode":"3280",
    "sg:province":"Fribourg",
    "wof:name":"Vinorama Nadine Imboden",
    "wof:placetype":"venue"
},
  "geometry": {"coordinates":[7.7502841949,46.3064918518],"type":"Point"}
}