{
  "type": "Feature",
  "properties": {
    "iso:country":"CH",
    "sg:address":"Zung 18",
    "sg:city":"Gais",
    "sg:orig_category":"S\u00e4ge, Hobel U Holzimpr\u00e4gnierwerke S\u00e4gewerke",
    "sg:phone":"+41 79 629 67 28",
    "sg:postcode":"9056",
    "sg:province":"Appenzell Ausserrhoden",
    "wof:name":"Fredy Solenthaler-broger",
    "wof:placetype":"venue"
},
  "geometry": {"coordinates":[9.455830574,47.362197876],"type":"Point"}
}