{
  "type": "Feature",
  "properties": {
    "iso:country":"CH",
    "sg:address":"8253",
    "sg:city":"Willisdorf",
    "sg:orig_category":"Herstellung von Futtermitteln f\u00fcr Nutztiere Mahl U Sch\u00e4lm\u00fchlen",
    "sg:phone":"+41 52 657 41 51",
    "sg:postcode":"8253",
    "sg:province":"Thurgau",
    "wof:name":"M\u00fchle Bachmann Ag Handels-& Futterwarenm\u00fchle",
    "wof:placetype":"venue"
},
  "geometry": {"coordinates":[8.7360496521,47.6805610657],"type":"Point"}
}