{
  "type": "Feature",
  "properties": {
    "iso:country":"CH",
    "sg:address":"Rue De La Source 1 2822 Courroux Case Postale 5",
    "sg:city":"Courroux",
    "sg:orig_category":"Herstellung von Metallerzeugnissen ohne Maschinenbau Maschinenbau",
    "sg:phone":"+41 71 688 14 75",
    "sg:postcode":"2822",
    "sg:province":"Jura",
    "wof:name":"Alwo Ag Werkzeug & Maschinenbau",
    "wof:placetype":"venue"
},
  "geometry": {"coordinates":[9.1890087128,47.6460075378],"type":"Point"}
}