{
  "type": "Feature",
  "properties": {
    "iso:country":"CH",
    "sg:address":"Ruelle Des Meiliers 3",
    "sg:city":"Cortaillod",
    "sg:orig_category":"Hoch U Tiefbau Sonstiger spezialisierter Hoch U Tiefbau",
    "sg:phone":"+41 32 842 11 90",
    "sg:postcode":"2016",
    "sg:province":"Neuch\u00e2tel",
    "wof:name":"Pizzera Jean-fran\u00e7ois Sa",
    "wof:placetype":"venue"
},
  "geometry": {"coordinates":[6.8451170921,46.9429893494],"type":"Point"}
}