{
  "type": "Feature",
  "properties": {
    "iso:country":"CH",
    "sg:address":"H\u00fcbeliweg 2",
    "sg:city":"Zollikofen",
    "sg:orig_category":"Markt U Meinungsforschung",
    "sg:postcode":"3052",
    "sg:province":"Bern",
    "wof:name":"Dns Die Neue Strategie Schorer Martin",
    "wof:placetype":"venue"
},
  "geometry": {"coordinates":[7.4579229355,46.9838180542],"type":"Point"}
}