{
  "type": "Feature",
  "properties": {
    "iso:country":"CH",
    "sg:address":"Via Piantelli 1",
    "sg:city":"Arbedo",
    "sg:orig_category":"Grafikateliers, Design",
    "sg:phone":"+41 91 829 34 41",
    "sg:postcode":"6517",
    "sg:province":"Ticino",
    "wof:name":"Claudio Brunelli Decorazioni L 26",
    "wof:placetype":"venue"
},
  "geometry": {"coordinates":[9.0470066071,46.2127799988],"type":"Point"}
}