{
  "type": "Feature",
  "properties": {
    "iso:country":"CH",
    "sg:address":"Rathausgasse 82 3011 Bern. Postfach",
    "sg:city":"Bern",
    "sg:orig_category":"Sonstiger Fachdetailhandel mit Nahrungsmitteln, Getr\u00e4nken U Tabak in Verkaufsr\u00e4umen",
    "sg:postcode":"3005",
    "sg:province":"Bern",
    "wof:name":"Heugel D. Zur K\u00e4sh\u00fctte. Molkereiprodukte; Handel",
    "wof:placetype":"venue"
},
  "geometry": {"coordinates":[7.4481449127,46.9486427307],"type":"Point"}
}