{
  "type": "Feature",
  "properties": {
    "iso:country":"CH",
    "sg:address":"D\u00fcnnerstrasse 30",
    "sg:city":"Oensingen",
    "sg:orig_category":"Pensionskassen",
    "sg:phone":"+41 62 388 66 66",
    "sg:postcode":"4702",
    "sg:province":"Solothurn",
    "wof:name":"Wohlfahrtsfonds Der Ssi Sch\u00e4fer-shop Ag, Oensingen",
    "wof:placetype":"venue"
},
  "geometry": {"coordinates":[7.7180380821,47.2825126648],"type":"Point"}
}