{
  "type": "Feature",
  "properties": {
    "iso:country":"CH",
    "sg:address":"Dokterhuus",
    "sg:city":"Lauterbrunnen",
    "sg:orig_category":"Arztpraxen",
    "sg:phone":"+41 33 856 26 26",
    "sg:postcode":"3822",
    "sg:province":"Bern",
    "wof:name":"Dr.med.bruno Durrer Arzt F.allgemeine Medizin Fmh",
    "wof:placetype":"venue"
},
  "geometry": {"coordinates":[7.907548,46.59795],"type":"Point"}
}