{
  "type": "Feature",
  "properties": {
    "iso:country":"CH",
    "sg:address":"Bolacker 6 4564 Obergerlafingen. Postfach 137",
    "sg:city":"Obergerlafingen",
    "sg:orig_category":"Stukkateurgewerbe, Gipserei U Verputzerei",
    "sg:phone":"+41 32 675 45 70",
    "sg:postcode":"4564",
    "sg:province":"Bern",
    "wof:name":"Brand Beat, Gipsergesch\u00e4ft",
    "wof:placetype":"venue"
},
  "geometry": {"coordinates":[7.582007885,47.1596984863],"type":"Point"}
}