{
  "type": "Feature",
  "properties": {
    "iso:country":"CH",
    "sg:address":"Haldenstrasse 26",
    "sg:city":"Wetzikon",
    "sg:classifiers":[
        {
            "category":"Bus Stop",
            "subcategory":"None",
            "type":"Transportation"
        }
    ],
    "sg:phone":"+41 19321735",
    "sg:postcode":"8620",
    "sg:province":"Z\u00fcrich",
    "sg:tags":[
        "marking",
        "road"
    ],
    "wof:name":"Stramark Ag",
    "wof:placetype":"venue"
},
  "geometry": {"coordinates":[8.7851247787,47.3272628784],"type":"Point"}
}