{
  "type": "Feature",
  "properties": {
    "iso:country":"CH",
    "sg:address":"Unterdorf 28.",
    "sg:city":"Berg\u00fcn/bravuogn",
    "sg:orig_category":"Herstellung von Konstruktionsteilen, Fertigbauteilen U Ausbauelementen aus Holz",
    "sg:phone":"+41 81 407 11 05",
    "sg:postcode":"7482",
    "sg:province":"Graubunden",
    "wof:name":"Rozzi U.",
    "wof:placetype":"venue"
},
  "geometry": {"coordinates":[9.7442417145,46.6300315857],"type":"Point"}
}