{
  "type": "Feature",
  "properties": {
    "iso:country":"CH",
    "sg:address":"Gotthardstrasse 24 6410 Goldau. Postfach 166",
    "sg:city":"Goldau",
    "sg:orig_category":"Detailhandel mit Schuhen U Lederwaren Herstellung von Reiseartikeln, Leder U Sattlerwaren",
    "sg:phone":"+41 52 745 12 64",
    "sg:postcode":"6410",
    "sg:province":"Schwyz",
    "wof:name":"Frei Willi",
    "wof:placetype":"venue"
},
  "geometry": {"coordinates":[8.8310098648,47.6255455017],"type":"Point"}
}