{
  "type": "Feature",
  "properties": {
    "iso:country":"CH",
    "sg:address":"Alexanderstrasse 8",
    "sg:city":"Chur",
    "sg:orig_category":"Erschliessung von Grundst\u00fccken",
    "sg:postcode":"7000",
    "sg:province":"Graubunden",
    "wof:name":"Wohnbaugenossenschaft Familia",
    "wof:placetype":"venue"
},
  "geometry": {"coordinates":[9.5315208435,46.8525695801],"type":"Point"}
}