{
  "type": "Feature",
  "properties": {
    "iso:country":"CH",
    "sg:address":"Reuchenettestrasse 80",
    "sg:city":"Biel/bienne",
    "sg:orig_category":"Blumen U Zierpflanzenbau",
    "sg:phone":"+41 32 341 20 53",
    "sg:postcode":"2502",
    "sg:province":"Bern",
    "wof:name":"H. Kees Nachfolger W.signer G\u00e4rtnerei",
    "wof:placetype":"venue"
},
  "geometry": {"coordinates":[7.25986,47.15147],"type":"Point"}
}