{
  "type": "Feature",
  "properties": {
    "iso:country":"CH",
    "sg:address":"Kengelwiesstrasse 15",
    "sg:city":"Tann",
    "sg:orig_category":"Hoch U Tiefbau Sonstige pers\u00f6nliche Dienstleistungen",
    "sg:phone":"+41 55 240 36 60",
    "sg:postcode":"8632",
    "sg:province":"Z\u00fcrich",
    "wof:name":"Bauhag Ag",
    "wof:placetype":"venue"
},
  "geometry": {"coordinates":[8.8526554108,47.2640457153],"type":"Point"}
}