{
  "type": "Feature",
  "properties": {
    "iso:country":"CH",
    "sg:address":"Via Antonio Vanoni 6",
    "sg:city":"Lugano",
    "sg:orig_category":"Non-Classified Establishments",
    "sg:postcode":"6900",
    "sg:province":"Ticino",
    "wof:name":"Inmarcom Sa",
    "wof:placetype":"venue"
},
  "geometry": {"coordinates":[8.9536848068,46.0111961365],"type":"Point"}
}