{
  "type": "Feature",
  "properties": {
    "addr:full":"Route Des Planches 14 Ballaigues Vaud 1338",
    "addr:housenumber":"14",
    "addr:postcode":"1338",
    "addr:street":"Route Des Planches",
    "iso:country":"CH",
    "sg:address":"Route Des Planches 14",
    "sg:city":"Ballaigues",
    "sg:orig_category":"Bauschreinerei Zimmerei, Ingenieurholzbau",
    "sg:phone":"+41 21 843 26 31",
    "sg:postcode":"1338",
    "sg:province":"Vaud",
    "wof:name":"Jaques Fr\u00e8res Menuiserie & Charpenterie",
    "wof:placetype":"venue"
},
  "geometry": {"coordinates":[6.417813,46.730225],"type":"Point"}
}