{
  "type": "Feature",
  "properties": {
    "iso:country":"CH",
    "sg:address":"St\u00e4dtchen 27",
    "sg:city":"Aarburg",
    "sg:orig_category":"Unclassifiable Establishments",
    "sg:postcode":"4663",
    "sg:province":"Aargau",
    "wof:name":"Claudia Marti St\u00e4dtli Coiffeur",
    "wof:placetype":"venue"
},
  "geometry": {"coordinates":[7.8986592293,47.3214073181],"type":"Point"}
}