{
  "type": "Feature",
  "properties": {
    "iso:country":"CH",
    "sg:address":"Rue Emile-gourd 6",
    "sg:city":"Gen\u00e8ve",
    "sg:orig_category":"Vermittlung von Immobilien",
    "sg:phone":"+41 22 346 88 78",
    "sg:postcode":"1206",
    "sg:province":"Gen\u00e8ve",
    "wof:name":"Anna Di Giusto Agence Immobili\u00e8re",
    "wof:placetype":"venue"
},
  "geometry": {"coordinates":[6.1526341438,46.1976394653],"type":"Point"}
}