{
  "type": "Feature",
  "properties": {
    "iso:country":"CH",
    "sg:address":"M\u00f6rsbergerstrasse 54",
    "sg:city":"Basel",
    "sg:orig_category":"Interessenvertretungen",
    "sg:postcode":"4057",
    "sg:province":"Basel-Stadt",
    "wof:name":"Stiftung Gsmba K\u00fcnstlerhaus",
    "wof:placetype":"venue"
},
  "geometry": {"coordinates":[7.5935339928,47.56823349],"type":"Point"}
}