{
  "type": "Feature",
  "properties": {
    "iso:country":"CH",
    "sg:address":"Dorfstrasse 56",
    "sg:city":"Hagendorn",
    "sg:orig_category":"Detailhandel mit Waren verschiedener Art, Hauptrichtung Nahrungsmittel",
    "sg:phone":"+41 32 396 24 23",
    "sg:postcode":"6332",
    "sg:province":"Zug",
    "wof:name":"Maxi Dorfladen Mireille Jenny",
    "wof:placetype":"venue"
},
  "geometry": {"coordinates":[7.1896481514,47.0319061279],"type":"Point"}
}