{
  "type": "Feature",
  "properties": {
    "iso:country":"CH",
    "sg:address":"Marktstrasse 11",
    "sg:city":"Grenchen",
    "sg:orig_category":"Herstellung von Schneidwaren U Bestecken",
    "sg:phone":"+41 32 653 11 32",
    "sg:postcode":"2540",
    "sg:province":"Solothurn",
    "wof:name":"Liechti Martin.",
    "wof:placetype":"venue"
},
  "geometry": {"coordinates":[7.3979239464,47.1939353943],"type":"Point"}
}