{
  "type": "Feature",
  "properties": {
    "iso:country":"CH",
    "sg:address":"Haus De Sepibus",
    "sg:city":"M\u00f6rel",
    "sg:orig_category":"Advokaturb\u00fcros Notariate",
    "sg:phone":"+41 27 927 27 26",
    "sg:postcode":"3983",
    "sg:province":"Valais",
    "wof:name":"Dr.marcel Mangisch Advokatur-& Notariatsb\u00fcro",
    "wof:placetype":"venue"
},
  "geometry": {"coordinates":[8.045341,46.35556],"type":"Point"}
}