{
  "type": "Feature",
  "properties": {
    "iso:country":"CH",
    "sg:address":"B\u00e4lliz 40 3600 Thun. Postfach 1473",
    "sg:city":"Thun",
    "sg:orig_category":"Detailhandel mit Spielwaren",
    "sg:phone":"+41 33 223 34 44",
    "sg:postcode":"3601",
    "sg:province":"Bern",
    "wof:name":"Franz Carl Weber Ag",
    "wof:placetype":"venue"
},
  "geometry": {"coordinates":[7.6270318031,46.7587013245],"type":"Point"}
}