{
  "type": "Feature",
  "properties": {
    "iso:country":"CH",
    "sg:address":"Stampfstrasse 45",
    "sg:city":"Jona",
    "sg:orig_category":"Abwasserreinigung",
    "sg:phone":"+41 55 212 30 49",
    "sg:postcode":"8645",
    "sg:province":"St. Gallen",
    "wof:name":"Kl\u00e4ranlage",
    "wof:placetype":"venue"
},
  "geometry": {"coordinates":[8.84688,47.22538],"type":"Point"}
}