{
  "type": "Feature",
  "properties": {
    "iso:country":"CH",
    "sg:address":"Turnerstrasse 28",
    "sg:city":"Basel",
    "sg:orig_category":"Werbevermittlung Werbung",
    "sg:postcode":"4058",
    "sg:province":"Basel-Stadt",
    "wof:name":"Auer & Partner Ag",
    "wof:placetype":"venue"
},
  "geometry": {"coordinates":[8.2235832214,47.131149292],"type":"Point"}
}