{
  "type": "Feature",
  "properties": {
    "iso:country":"CH",
    "sg:address":"Corso San Gottardo 14 6830 Chiasso. Postfach",
    "sg:city":"Chiasso",
    "sg:orig_category":"Reiseb\u00fcros U Reiseveranstalter",
    "sg:phone":"+41 17613765",
    "sg:postcode":"6830",
    "sg:province":"Ticino",
    "wof:name":"Bike Adventure Tours Affoltern A. A. Gmbh",
    "wof:placetype":"venue"
},
  "geometry": {"coordinates":[8.4495182037,47.2769012451],"type":"Point"}
}