{
  "type": "Feature",
  "properties": {
    "iso:country":"CH",
    "sg:address":"Vial De La Stazion",
    "sg:city":"Poschiavo",
    "sg:orig_category":"Malerei",
    "sg:phone":"+41 81 844 09 01",
    "sg:postcode":"7742",
    "sg:province":"Graubunden",
    "wof:name":"Marco Zala Impresa Di Pittura",
    "wof:placetype":"venue"
},
  "geometry": {"coordinates":[10.0546674728,46.3250541687],"type":"Point"}
}