{
  "type": "Feature",
  "properties": {
    "iso:country":"CH",
    "sg:address":"Rainstrasse 8 6060 Sarnen. Postfach",
    "sg:city":"Sarnen",
    "sg:orig_category":"Non-Classified Establishments",
    "sg:postcode":"6060",
    "sg:province":"Obwalden",
    "wof:name":"Netsupport Halter Internet Und Netzwerk-support, Schulung, Dienstleistungen",
    "wof:placetype":"venue"
},
  "geometry": {"coordinates":[8.2100334167,46.887386322],"type":"Point"}
}