{
  "type": "Feature",
  "properties": {
    "iso:country":"CH",
    "sg:address":"Via Monte Boglia 3",
    "sg:city":"Lugano",
    "sg:orig_category":"Herstellung von Metallerzeugnissen ohne Maschinenbau Herstellung von sonstigen keramischen Erzeugnis",
    "sg:phone":"+41 91 971 01 71",
    "sg:postcode":"6900",
    "sg:province":"Ticino",
    "wof:name":"Servicer Impianti Sa",
    "wof:placetype":"venue"
},
  "geometry": {"coordinates":[8.9578790665,46.0182685852],"type":"Point"}
}