{
  "type": "Feature",
  "properties": {
    "iso:country":"CH",
    "sg:address":"Povr\u00f2 Via 6 6900 Massagno. Postfach",
    "sg:city":"Massagno",
    "sg:orig_category":"Fernmeldedienste",
    "sg:phone":"+41 91 950 05 00",
    "sg:postcode":"6900",
    "sg:province":"Ticino",
    "wof:name":"New-lan Sa",
    "wof:placetype":"venue"
},
  "geometry": {"coordinates":[8.9513053894,46.0029754639],"type":"Point"}
}