{
  "type": "Feature",
  "properties": {
    "iso:country":"CH",
    "sg:address":"Str\u00e4ssler 16",
    "sg:city":"Rafz",
    "sg:orig_category":"Vermietung U Verpachtung von eigenen Immobilien",
    "sg:phone":"+41 18692261",
    "sg:postcode":"8197",
    "sg:province":"Z\u00fcrich",
    "wof:name":"Neukom",
    "wof:placetype":"venue"
},
  "geometry": {"coordinates":[8.5340824127,47.6102333069],"type":"Point"}
}