{
  "type": "Feature",
  "properties": {
    "iso:country":"CH",
    "sg:address":"Sihlbruggstr. 105a",
    "sg:city":"Baar",
    "sg:classifiers":[
        {
            "category":"Manufacturing",
            "subcategory":"Printing",
            "type":"Manufacturing & Wholesale Goods"
        }
    ],
    "sg:phone":"+41 41 767 76 76",
    "sg:postcode":"6341",
    "sg:province":"Zug",
    "sg:tags":[
        "publishing"
    ],
    "wof:name":"Multicolorbring Ag",
    "wof:placetype":"venue"
},
  "geometry": {"coordinates":[8.5587320328,47.2123184204],"type":"Point"}
}