{
  "type": "Feature",
  "properties": {
    "iso:country":"CH",
    "sg:address":"Boulevard Carl-vogt 49",
    "sg:city":"Gen\u00e8ve",
    "sg:orig_category":"Detailhandel mit Brot, Back U S\u00fcsswaren",
    "sg:phone":"+41 22 328 01 24",
    "sg:postcode":"1205",
    "sg:province":"Gen\u00e8ve",
    "wof:name":"Christophe Dubois P\u00e2tisserie-confiserie",
    "wof:placetype":"venue"
},
  "geometry": {"coordinates":[6.13496,46.198685],"type":"Point"}
}