{
  "type": "Feature",
  "properties": {
    "iso:country":"CH",
    "sg:address":"Eglisberg",
    "sg:city":"Buttisholz",
    "sg:orig_category":"Allgemeiner Hoch U Tiefbau",
    "sg:phone":"+41 41 929 59 11",
    "sg:postcode":"6018",
    "sg:province":"Luzern",
    "wof:name":"Huber Leitungsbau Gmbh",
    "wof:placetype":"venue"
},
  "geometry": {"coordinates":[8.09376,47.114414],"type":"Point"}
}