{
  "type": "Feature",
  "properties": {
    "iso:country":"CH",
    "sg:address":"Chesa Costa",
    "sg:city":"Pontresina",
    "sg:orig_category":"G\u00fcterbef\u00f6rderung im Strassenverkehr",
    "sg:postcode":"7504",
    "sg:province":"Graubunden",
    "wof:name":"Roberto Transporte, R. Costa",
    "wof:placetype":"venue"
},
  "geometry": {"coordinates":[9.9050941467,46.4886283875],"type":"Point"}
}