{
  "type": "Feature",
  "properties": {
    "iso:country":"CH",
    "sg:address":"Hammerstrasse 7 6312 Steinhausen. Postfach 431",
    "sg:city":"Steinhausen",
    "sg:orig_category":"Herstellung von Duft U K\u00f6rperpflegemitteln",
    "sg:phone":"+41 41 741 30 61",
    "sg:postcode":"6312",
    "sg:province":"Zug",
    "wof:name":"Spicosa, Spiller M.",
    "wof:placetype":"venue"
},
  "geometry": {"coordinates":[8.4839391708,47.1979560852],"type":"Point"}
}