{
  "type": "Feature",
  "properties": {
    "iso:country":"CH",
    "sg:address":"Dammstrasse 22",
    "sg:city":"M\u00e4nnedorf",
    "sg:orig_category":"G\u00fcterbef\u00f6rderung im Strassenverkehr",
    "sg:phone":"+41 19205763",
    "sg:postcode":"8708",
    "sg:province":"Z\u00fcrich",
    "wof:name":"Walter Sch\u00f6pperle",
    "wof:placetype":"venue"
},
  "geometry": {"coordinates":[8.6902036667,47.2550964355],"type":"Point"}
}