{
  "type": "Feature",
  "properties": {
    "iso:country":"CH",
    "sg:address":"Grienbachstrasse 11",
    "sg:city":"Zug",
    "sg:orig_category":"Unclassifiable Establishments",
    "sg:phone":"+41 41 760 89 19",
    "sg:postcode":"6300",
    "sg:province":"Zug",
    "wof:name":"Cmh Chrome Management Holding Ag",
    "wof:placetype":"venue"
},
  "geometry": {"coordinates":[8.5224514008,47.1836013794],"type":"Point"}
}