{
  "type": "Feature",
  "properties": {
    "iso:country":"CH",
    "sg:address":"Bundesplatz 16 6300 Zug. Postfach 4747",
    "sg:city":"Zug",
    "sg:orig_category":"Advokaturb\u00fcros",
    "sg:phone":"+41 12212920",
    "sg:postcode":"6304",
    "sg:province":"Zug",
    "wof:name":"Raffael J. Weidmann Advokaturb\u00fcro",
    "wof:placetype":"venue"
},
  "geometry": {"coordinates":[8.514885,47.172138],"type":"Point"}
}