{
  "type": "Feature",
  "properties": {
    "iso:country":"CH",
    "sg:address":"Kirchb\u00fchl 23 3400 Burgdorf. Postfach 48",
    "sg:city":"Burgdorf",
    "sg:orig_category":"Polizei",
    "sg:phone":"+41 34 429 92 80",
    "sg:postcode":"3402",
    "sg:province":"Bern",
    "wof:name":"St\u00e4dt. Polizeiinspektorat",
    "wof:placetype":"venue"
},
  "geometry": {"coordinates":[7.6253509521,47.056098938],"type":"Point"}
}