{
  "type": "Feature",
  "properties": {
    "iso:country":"CH",
    "sg:address":"Caratti Via 2",
    "sg:city":"Bellinzona",
    "sg:orig_category":"Herstellung von Schmuck, Gold U Silberschmiedwaren",
    "sg:phone":"+41 32 751 43 38",
    "sg:postcode":"6500",
    "sg:province":"Ticino",
    "wof:name":"Rr Sertissage S\u00e0rl",
    "wof:placetype":"venue"
},
  "geometry": {"coordinates":[7.088947773,47.0624084473],"type":"Point"}
}