{
  "type": "Feature",
  "properties": {
    "iso:country":"CH",
    "sg:address":"Luxburgstrasse 35 9322 Egnach. Postfach",
    "sg:city":"Egnach",
    "sg:orig_category":"Softwareentwicklung U beratung",
    "sg:postcode":"9322",
    "sg:province":"Thurgau",
    "wof:name":"Wmag",
    "wof:placetype":"venue"
},
  "geometry": {"coordinates":[9.3842153549,47.5488204956],"type":"Point"}
}