{
  "type": "Feature",
  "properties": {
    "iso:country":"CH",
    "sg:address":"Wynigenstrasse 19 3400 Burgdorf. Postfach",
    "sg:city":"Burgdorf",
    "sg:orig_category":"Erbringung von Dienstleistungen f\u00fcr Unternehmen",
    "sg:postcode":"3400",
    "sg:province":"Bern",
    "wof:name":"Forum F\u00fcr Design Gmbh",
    "wof:placetype":"venue"
},
  "geometry": {"coordinates":[7.6294078827,47.0581054688],"type":"Point"}
}