{
  "type": "Feature",
  "properties": {
    "iso:country":"CH",
    "sg:address":"L\u00e4ngenb\u00fchl",
    "sg:city":"L\u00e4ngenb\u00fchl",
    "sg:orig_category":"Minigolfpl\u00e4tze",
    "sg:phone":"+41 31 809 31 59",
    "sg:postcode":"3636",
    "sg:province":"Bern",
    "wof:name":"Minigolf Grizzlyb\u00e4r",
    "wof:placetype":"venue"
},
  "geometry": {"coordinates":[7.5294499397,46.7555656433],"type":"Point"}
}