{
  "type": "Feature",
  "properties": {
    "iso:country":"CH",
    "sg:address":"R\u00f6telstr. 18",
    "sg:city":"Z\u00fcrich",
    "sg:classifiers":[
        {
            "category":"Professional",
            "subcategory":"Advertising",
            "type":"Services"
        }
    ],
    "sg:phone":"+41 4113500232",
    "sg:postcode":"8006",
    "sg:province":"Z\u00fcrich",
    "sg:tags":[
        "communication",
        "medium"
    ],
    "wof:name":"Propaganda Z\u00dcrich Ag",
    "wof:placetype":"venue"
},
  "geometry": {"coordinates":[8.537469,47.390591],"type":"Point"}
}