{
  "type": "Feature",
  "properties": {
    "iso:country":"CH",
    "sg:address":"Eschenweg 6",
    "sg:city":"Hettlingen",
    "sg:orig_category":"Herstellung von Papier, Karton U Pappe",
    "sg:postcode":"8442",
    "sg:province":"Z\u00fcrich",
    "wof:name":"Spaefag Ag",
    "wof:placetype":"venue"
},
  "geometry": {"coordinates":[8.7156181335,47.5486068726],"type":"Point"}
}