{
  "type": "Feature",
  "properties": {
    "iso:country":"CH",
    "sg:address":"Insstrasse 17",
    "sg:city":"Br\u00fcttelen",
    "sg:orig_category":"Gem\u00fcsebau",
    "sg:phone":"+41 32 313 21 54",
    "sg:postcode":"2578",
    "wof:name":"Fritz Grau Gem\u00fcsebau",
    "wof:placetype":"venue"
},
  "geometry": {"coordinates":[7.1455979347,47.0187797546],"type":"Point"}
}