{
  "type": "Feature",
  "properties": {
    "iso:country":"CH",
    "sg:address":"Biberstrasse 50 8240 Thayngen. Postfach",
    "sg:city":"Thayngen",
    "sg:orig_category":"Detailhandel mit Schuhen U Lederwaren Grosshandel mit Schuhen",
    "sg:phone":"+41 52 649 16 00",
    "sg:postcode":"8240",
    "sg:province":"Schaffhausen",
    "wof:name":"Schuh - Discount B\u00fcsser Werner Schuhhandel, Schuhimport U. -export",
    "wof:placetype":"venue"
},
  "geometry": {"coordinates":[8.7052774429,47.750415802],"type":"Point"}
}