{
  "type": "Feature",
  "properties": {
    "iso:country":"CH",
    "sg:address":"Tschachenstr. 15",
    "sg:city":"Bilten",
    "sg:classifiers":[
        {
            "category":"Wholesale",
            "subcategory":"Medical Equipment & Supplies",
            "type":"Manufacturing & Wholesale Goods"
        }
    ],
    "sg:phone":"+41 55 615 29 15",
    "sg:postcode":"8865",
    "sg:province":"Glarus",
    "sg:tags":[
        "instrument",
        "health",
        "-",
        "precision"
    ],
    "wof:name":"Mts Maschinenbau Ag",
    "wof:placetype":"venue"
},
  "geometry": {"coordinates":[9.024766922,47.1563148499],"type":"Point"}
}