{
  "type": "Feature",
  "properties": {
    "iso:country":"CH",
    "sg:address":"Flawilerstrasse 52",
    "sg:city":"Oberuzwil",
    "sg:orig_category":"Kaminfeger",
    "sg:phone":"+41 62 822 24 08",
    "sg:postcode":"9242",
    "sg:province":"St. Gallen",
    "wof:name":"Willi Leuzinger Kaminfegermeister",
    "wof:placetype":"venue"
},
  "geometry": {"coordinates":[8.0657749176,47.3911972046],"type":"Point"}
}