{
  "type": "Feature",
  "properties": {
    "iso:country":"CH",
    "sg:address":"Waldstrasse 27",
    "sg:city":"Biberist",
    "sg:orig_category":"Institutionen f\u00fcr Behinderte Sonderschulen",
    "sg:phone":"+41 34 402 47 51",
    "sg:postcode":"4562",
    "sg:province":"Solothurn",
    "wof:name":"Behindertenwerke Oberemmental Wohnheim & Heilp\u00e4d.schule",
    "wof:placetype":"venue"
},
  "geometry": {"coordinates":[7.757589817,46.9491271973],"type":"Point"}
}