{
  "type": "Feature",
  "properties": {
    "iso:country":"CH",
    "sg:address":"Austrasse 7b",
    "sg:city":"Chur",
    "sg:orig_category":"Geb\u00e4ude, Wohnungsreinigung Reinigungsgewerbe",
    "sg:phone":"+41 81 284 66 97",
    "sg:postcode":"7000",
    "sg:province":"Graubunden",
    "wof:name":"Cavegn Reinigungen & Umgebungsarbeiten",
    "wof:placetype":"venue"
},
  "geometry": {"coordinates":[9.5111055374,46.8609466553],"type":"Point"}
}