{
  "type": "Feature",
  "properties": {
    "iso:country":"CH",
    "sg:address":"Seeb\u00fchlstrasse 2a",
    "sg:city":"Seuzach",
    "sg:orig_category":"Tierarztpraxis",
    "sg:phone":"+41 52 335 40 30",
    "sg:postcode":"8472",
    "sg:province":"Z\u00fcrich",
    "wof:name":"Dres Med.vet. Hejl & Di Carlo Tier\u00e4rzte",
    "wof:placetype":"venue"
},
  "geometry": {"coordinates":[8.7289152145,47.5323944092],"type":"Point"}
}