{
  "type": "Feature",
  "properties": {
    "iso:country":"CH",
    "sg:address":"7302 Landquart. Postfach",
    "sg:city":"Landquart",
    "sg:classifiers":[
        {
            "category":"Travel",
            "subcategory":"Hotels & Motels",
            "type":"Entertainment"
        }
    ],
    "sg:postcode":"7302",
    "sg:province":"Graubunden",
    "sg:tags":[
        "hotels",
        "mit",
        "restaurant"
    ],
    "wof:name":"Grischa Gastro Ag",
    "wof:placetype":"venue"
},
  "geometry": {"coordinates":[9.5868701935,46.9626312256],"type":"Point"}
}