{
  "type": "Feature",
  "properties": {
    "iso:country":"CH",
    "sg:address":"Wilerweg 23",
    "sg:city":"Murten",
    "sg:orig_category":"Detailhandel mit Uhren U Schmuck Fachdetailhandel in Verkaufsr\u00e4umen",
    "sg:phone":"+41 26 670 27 16",
    "sg:postcode":"3280",
    "sg:province":"Fribourg",
    "wof:name":"Uhren-bijouterie Allemann Jean-louis",
    "wof:placetype":"venue"
},
  "geometry": {"coordinates":[7.1191978455,46.9238777161],"type":"Point"}
}