{
  "type": "Feature",
  "properties": {
    "iso:country":"CH",
    "sg:address":"Grafenauweg 10",
    "sg:city":"Zug",
    "sg:orig_category":"Sonstige pers\u00f6nliche Dienstleistungen",
    "sg:postcode":"6300",
    "sg:province":"Zug",
    "wof:name":"Astro H",
    "wof:placetype":"venue"
},
  "geometry": {"coordinates":[-65.6866531372,-23.1981296539],"type":"Point"}
}