{
  "type": "Feature",
  "properties": {
    "iso:country":"CH",
    "sg:address":"Heimstrasse 25",
    "sg:city":"Dietikon",
    "sg:orig_category":"Herstellung von k\u00e4lte U lufttechnischen Erzeugnissen f\u00fcr gewerbliche Zwecke Installation von Heizung",
    "sg:phone":"+41 17409777",
    "sg:postcode":"8953",
    "sg:province":"Z\u00fcrich",
    "wof:name":"Klima K\u00e4lte Kopp Ag",
    "wof:placetype":"venue"
},
  "geometry": {"coordinates":[8.4038572311,47.4115028381],"type":"Point"}
}