{
  "type": "Feature",
  "properties": {
    "iso:country":"CH",
    "sg:address":"Weiherstrasse 7",
    "sg:city":"G\u00fcttingen",
    "sg:orig_category":"Oberfl\u00e4chenveredlung U W\u00e4rmebehandlung",
    "sg:postcode":"8594",
    "sg:province":"Thurgau",
    "wof:name":"Mastai Ag G\u00fcttingen",
    "wof:placetype":"venue"
},
  "geometry": {"coordinates":[9.2964010239,47.6075248718],"type":"Point"}
}