{
  "type": "Feature",
  "properties": {
    "iso:country":"CH",
    "sg:address":"Pr\u00e9 De La Vigne 531",
    "sg:city":"Cheyres",
    "sg:orig_category":"Sportvereine Ballsport Tischtennis",
    "sg:phone":"+41 26 663 42 89",
    "sg:postcode":"1468",
    "sg:province":"Fribourg",
    "wof:name":"Ctt Cheyres",
    "wof:placetype":"venue"
},
  "geometry": {"coordinates":[6.7849869728,46.8154296875],"type":"Point"}
}