{
  "type": "Feature",
  "properties": {
    "iso:country":"CH",
    "sg:address":"Scharnagelnstrasse 20",
    "sg:city":"Niederbipp",
    "sg:classifiers":[
        {
            "category":"Restaurant",
            "type":"Food & Drink"
        }
    ],
    "sg:phone":"+41 32 633 14 42",
    "sg:postcode":"4704",
    "sg:province":"Bern",
    "wof:name":"Pfl\u00f6tschu's Blues Beiz",
    "wof:placetype":"venue"
},
  "geometry": {"coordinates":[7.6996741295,47.2640533447],"type":"Point"}
}