{
  "type": "Feature",
  "properties": {
    "iso:country":"CH",
    "sg:address":"Bahnhofplatz 1",
    "sg:city":"Brig",
    "sg:orig_category":"RESTAURANTS: TEA-ROOMS",
    "sg:phone":"+41 27 952 12 07",
    "sg:postcode":"3900",
    "sg:province":"Valais",
    "wof:name":"Bahnhofbuffet Il Buffetto, Gruber Hugo Restaurant",
    "wof:placetype":"venue"
},
  "geometry": {"coordinates":[7.8920350075,46.2011413574],"type":"Point"}
}