{
  "type": "Feature",
  "properties": {
    "iso:country":"CH",
    "sg:address":"Ottigenb\u00fchlstrasse 72 6030 Ebikon. Postfach",
    "sg:city":"Ebikon",
    "sg:orig_category":"Herstellung von sonstigen landwirtschaftlichen Maschinen",
    "sg:phone":"+41 79 276 75 70",
    "sg:postcode":"6030",
    "sg:province":"Luzern",
    "wof:name":"Vertriebsgesellschaft F\u00fcr Landmaschinen Mbh",
    "wof:placetype":"venue"
},
  "geometry": {"coordinates":[8.3557100296,47.08385849],"type":"Point"}
}