{
  "type": "Feature",
  "properties": {
    "iso:country":"CH",
    "sg:address":"2952",
    "sg:city":"Cornol",
    "sg:orig_category":"Bauspenglerei Zimmerei, Dachdeckerei, Bauspenglerei U Abdichtung",
    "sg:phone":"+41 32 462 27 75",
    "sg:postcode":"2952",
    "sg:province":"Jura",
    "wof:name":"Coulon G\u00e9rard.",
    "wof:placetype":"venue"
},
  "geometry": {"coordinates":[7.161395,47.407372],"type":"Point"}
}