{
  "type": "Feature",
  "properties": {
    "iso:country":"CH",
    "sg:address":"Rue Des Oches 5",
    "sg:city":"Blonay",
    "sg:orig_category":"Friedhofs- and Stadtg\u00e4rtnereien",
    "sg:phone":"+41 21 743 36 70",
    "sg:postcode":"1807",
    "sg:province":"Vaud",
    "wof:name":"Administration G\u00e9n\u00e9rale Bureau Technique",
    "wof:placetype":"venue"
},
  "geometry": {"coordinates":[6.8956418037,46.4657325745],"type":"Point"}
}