{
  "type": "Feature",
  "properties": {
    "iso:country":"CH",
    "sg:address":"Seminarstr. 92",
    "sg:city":"Wettingen",
    "sg:classifiers":[
        {
            "category":"Manufacturing",
            "subcategory":"Metals",
            "type":"Manufacturing & Wholesale Goods"
        }
    ],
    "sg:phone":"+41 56 437 82 38",
    "sg:postcode":"5430",
    "sg:province":"Aargau",
    "sg:tags":[
        "metallurgy",
        "metalworking"
    ],
    "wof:name":"Debrunner Ag Wettingen",
    "wof:placetype":"venue"
},
  "geometry": {"coordinates":[8.3141756058,47.4621391296],"type":"Point"}
}