{
  "type": "Feature",
  "properties": {
    "addr:full":"Rue De L'ecluse 38 Neuch\u00e2tel Neuch\u00e2tel 2000",
    "addr:housenumber":"38",
    "addr:postcode":"2000",
    "addr:street":"Rue De L'Ecluse",
    "iso:country":"CH",
    "sg:address":"Rue De L'ecluse 38",
    "sg:city":"Neuch\u00e2tel",
    "sg:orig_category":"Allgemeinbildende weiterf\u00fchrende Schulen Sprachschulen",
    "sg:phone":"+41 32 725 29 81",
    "sg:postcode":"2000",
    "sg:province":"Neuch\u00e2tel",
    "wof:name":"Ecole B\u00e9n\u00e9dict Neuch\u00e2tel S\u00e0rl",
    "wof:placetype":"venue"
},
  "geometry": {"coordinates":[6.925192,46.992565],"type":"Point"}
}