{
  "type": "Feature",
  "properties": {
    "iso:country":"CH",
    "sg:address":"9525",
    "sg:city":"Lenggenwil",
    "sg:orig_category":"Primarschulen",
    "sg:phone":"+41 71 923 14 12",
    "sg:postcode":"9525",
    "sg:province":"St. Gallen",
    "wof:name":"Primarschule",
    "wof:placetype":"venue"
},
  "geometry": {"coordinates":[9.0736904144,47.4390487671],"type":"Point"}
}