{
  "type": "Feature",
  "properties": {
    "iso:country":"CH",
    "sg:address":"Hilfikerstrasse 15",
    "sg:city":"Sarmenstorf",
    "sg:orig_category":"Fahrschulen, Flugschulen",
    "sg:phone":"+41 79 225 85 22",
    "sg:postcode":"5614",
    "sg:province":"Aargau",
    "wof:name":"Richi & Andr\u00e9 M\u00fcller Gmbh Autofahrschule",
    "wof:placetype":"venue"
},
  "geometry": {"coordinates":[8.2465524673,47.3110084534],"type":"Point"}
}