{
  "type": "Feature",
  "properties": {
    "iso:country":"CH",
    "sg:address":"Route Du Pavement 3bis",
    "sg:city":"Lausanne",
    "sg:orig_category":"Sportvereine Billard",
    "sg:phone":"+41 21 647 67 78",
    "sg:postcode":"1018",
    "sg:province":"Vaud",
    "wof:name":"Billard Europa Club",
    "wof:placetype":"venue"
},
  "geometry": {"coordinates":[6.6359620094,46.5302200317],"type":"Point"}
}