{
  "type": "Feature",
  "properties": {
    "iso:country":"CH",
    "sg:address":"Prairie Rue De La 1",
    "sg:city":"B\u00f4le",
    "sg:orig_category":"Markt U Meinungsforschung",
    "sg:phone":"+41 32 841 18 08",
    "sg:postcode":"2014",
    "sg:province":"Neuch\u00e2tel",
    "wof:name":"Max Concept Favretto",
    "wof:placetype":"venue"
},
  "geometry": {"coordinates":[6.841509819,46.9673309326],"type":"Point"}
}