{
  "type": "Feature",
  "properties": {
    "iso:country":"CH",
    "sg:address":"Rebenstrasse 2",
    "sg:city":"Weingarten-kalth",
    "sg:orig_category":"Grosshandel mit B\u00fcromaschinen Grosshandel mit Datenverarbeitungsger\u00e4ten",
    "sg:phone":"+41 52 376 24 32",
    "sg:postcode":"9508",
    "sg:province":"Thurgau",
    "wof:name":"Pyramid Computer Service Gmbh Edv-dienstleistungen",
    "wof:placetype":"venue"
},
  "geometry": {"coordinates":[8.9852485657,47.526763916],"type":"Point"}
}