{
  "type": "Feature",
  "properties": {
    "iso:country":"CH",
    "sg:address":"Villars-centre 1867 Ollon Vd. Postfach",
    "sg:city":"Villars-sur-ollon",
    "sg:orig_category":"Interessenvertretungen",
    "sg:postcode":"1884",
    "sg:province":"Vaud",
    "wof:name":"Fondation Cam\u00e9lia Botnar",
    "wof:placetype":"venue"
},
  "geometry": {"coordinates":[6.9953799248,46.2966117859],"type":"Point"}
}