{
  "type": "Feature",
  "properties": {
    "addr:full":"Brunnhollenweg 11 R\u00f6schenz Basel-Landschaft 4244",
    "addr:housenumber":"11",
    "addr:postcode":"4244",
    "addr:street":"Brunnhollenweg",
    "iso:country":"CH",
    "sg:address":"Brunnhollenweg 11",
    "sg:city":"R\u00f6schenz",
    "sg:orig_category":"Bau von Strassen, Sportanlagen U Bahnverkehrsstrecken Sonstige Herstellung von Konstruktionsteilen, ",
    "sg:phone":"+41 61 761 70 60",
    "sg:postcode":"4244",
    "sg:province":"Basel-Landschaft",
    "wof:name":"Casa Plus, Keller & Schwimmbad Gmbh",
    "wof:placetype":"venue"
},
  "geometry": {"coordinates":[7.469877,47.426205],"type":"Point"}
}