{
  "type": "Feature",
  "properties": {
    "iso:country":"CH",
    "sg:address":"Kreuzbleichestrasse 7",
    "sg:city":"St.gallen",
    "sg:orig_category":"Herstellung von Werkzeugmaschinen",
    "sg:postcode":"9000",
    "sg:province":"St. Gallen",
    "wof:name":"Rebtec Eberhard Gmbh",
    "wof:placetype":"venue"
},
  "geometry": {"coordinates":[9.3566055298,47.4198913574],"type":"Point"}
}