{
  "type": "Feature",
  "properties": {
    "iso:country":"CH",
    "sg:address":"L\u00e4gernstrasse 30",
    "sg:city":"Z\u00fcrich",
    "sg:orig_category":"Architektur U Ingenieurb\u00fcros Architekturb\u00fcros",
    "sg:phone":"+41 13631000",
    "sg:postcode":"8037",
    "sg:province":"Z\u00fcrich",
    "wof:name":"Schuepp + Borner Gmbh Architekten Sia Fsai Architekturb\u00fcro, Baudienstleistungen Usw",
    "wof:placetype":"venue"
},
  "geometry": {"coordinates":[8.532015,47.39521],"type":"Point"}
}