{
  "type": "Feature",
  "properties": {
    "iso:country":"CH",
    "sg:address":"1903",
    "sg:city":"Collonges",
    "sg:orig_category":"Detailhandel mit Waren verschiedener Art, Hauptrichtung Nahrungsmittel",
    "sg:phone":"+41 27 767 12 59",
    "sg:postcode":"1903",
    "sg:province":"Valais",
    "wof:name":"Pierre-alain Zimmerli Epicerie",
    "wof:placetype":"venue"
},
  "geometry": {"coordinates":[7.0344400406,46.1706466675],"type":"Point"}
}