{
  "type": "Feature",
  "properties": {
    "iso:country":"CH",
    "sg:address":"Greifengasse 11",
    "sg:city":"Basel",
    "sg:orig_category":"Unclassifiable Establishments",
    "sg:postcode":"4058",
    "sg:province":"Basel-Stadt",
    "wof:name":"Midas Real Ag",
    "wof:placetype":"venue"
},
  "geometry": {"coordinates":[8.3411808014,47.3511123657],"type":"Point"}
}