{
  "type": "Feature",
  "properties": {
    "iso:country":"CH",
    "sg:address":"Tobel 357",
    "sg:city":"Schwellbrunn",
    "sg:orig_category":"Kauf U Verkauf von Immobilien auf eigene Rechnung",
    "sg:postcode":"9103",
    "sg:province":"Appenzell Ausserrhoden",
    "wof:name":"Landscheide Ag Schwellbrunn",
    "wof:placetype":"venue"
},
  "geometry": {"coordinates":[9.2314605713,47.3416633606],"type":"Point"}
}