{
  "type": "Feature",
  "properties": {
    "iso:country":"CH",
    "sg:address":"Sch\u00f6nauring 104",
    "sg:city":"Z\u00fcrich",
    "sg:orig_category":"Malerei",
    "sg:phone":"+41 13012232",
    "sg:postcode":"8052",
    "sg:province":"Z\u00fcrich",
    "wof:name":"Malergesch\u00e4ft Meier A.",
    "wof:placetype":"venue"
},
  "geometry": {"coordinates":[8.53840065,47.4278182983],"type":"Point"}
}