{
  "type": "Feature",
  "properties": {
    "iso:country":"CH",
    "sg:address":"Bahnhofstrasse 56 8500 Frauenfeld. Postfach",
    "sg:city":"Frauenfeld",
    "sg:orig_category":"Elektroinstallation",
    "sg:phone":"+41 52 722 22 12",
    "sg:postcode":"8500",
    "sg:province":"Thurgau",
    "wof:name":"Eip Technics Ag",
    "wof:placetype":"venue"
},
  "geometry": {"coordinates":[8.8940019608,47.556022644],"type":"Point"}
}