{
  "type": "Feature",
  "properties": {
    "iso:country":"CH",
    "sg:address":"Scheffelweg 2",
    "sg:city":"Thun",
    "sg:orig_category":"Chemin\u00e9e- and Ofenbau",
    "sg:phone":"+41 33 222 98 42",
    "sg:postcode":"3600",
    "sg:province":"Bern",
    "wof:name":"Martin Stauffer Chemin\u00e9ebau",
    "wof:placetype":"venue"
},
  "geometry": {"coordinates":[7.621172,46.75132],"type":"Point"}
}