{
  "type": "Feature",
  "properties": {
    "iso:country":"CH",
    "sg:address":"Bahnplatz 5",
    "sg:city":"Rorschach",
    "sg:orig_category":"RESTAURANTS: TEA-ROOMS",
    "sg:phone":"+41 71 841 14 09",
    "sg:postcode":"9400",
    "sg:province":"St. Gallen",
    "wof:name":"Rest. Du Nord C. Hunziker",
    "wof:placetype":"venue"
},
  "geometry": {"coordinates":[9.4945144653,47.4782752991],"type":"Point"}
}