{
  "type": "Feature",
  "properties": {
    "iso:country":"CH",
    "sg:address":"Ruchstuckstrasse 14",
    "sg:city":"Br\u00fcttisellen",
    "sg:orig_category":"Grosshandel mit B\u00fcromaschinen Grosshandel mit Datenverarbeitungsger\u00e4ten",
    "sg:phone":"+41 41 467 34 33",
    "sg:postcode":"8306",
    "sg:province":"Z\u00fcrich",
    "wof:name":"Asb Data Systeme Boog & Co",
    "wof:placetype":"venue"
},
  "geometry": {"coordinates":[8.2054319382,47.1160049438],"type":"Point"}
}