{
  "type": "Feature",
  "properties": {
    "iso:country":"CH",
    "sg:address":"Alleestrasse 54",
    "sg:city":"Romanshorn",
    "sg:orig_category":"Detailhandel mit Fahrr\u00e4dern Handel mit Motorr\u00e4dern, Teilen U Zubeh\u00f6r Instandhaltung U Reparatur von ",
    "sg:postcode":"8590",
    "sg:province":"Thurgau",
    "wof:name":"Reto Schwab Bike Corner Murten",
    "wof:placetype":"venue"
},
  "geometry": {"coordinates":[7.1084527969,46.9252319336],"type":"Point"}
}