{
  "type": "Feature",
  "properties": {
    "iso:country":"CH",
    "sg:address":"Burggasse 2",
    "sg:city":"Muttenz",
    "sg:classifiers":[
        {
            "category":"Restaurant",
            "type":"Food & Drink"
        }
    ],
    "sg:phone":"+41 61 461 90 41",
    "sg:postcode":"4132",
    "sg:province":"Basel-Landschaft",
    "wof:name":"Wirtshaus Zum Schl\u00fcssel Restaurant",
    "wof:placetype":"venue"
},
  "geometry": {"coordinates":[7.6460700035,47.5217475891],"type":"Point"}
}