{
  "type": "Feature",
  "properties": {
    "addr:full":"Borde Rue De La 26 1018 Lausanne. Postfach Lausanne Vaud 1018",
    "addr:housenumber":"26",
    "addr:postcode":"1018;postfach;1018",
    "addr:street":"Rue De La",
    "iso:country":"CH",
    "sg:address":"Borde Rue De La 26 1018 Lausanne. Postfach",
    "sg:city":"Lausanne",
    "sg:orig_category":"Detailhandel mit B\u00fcchern, Zeitungen, Schreib U Papeteriewaren",
    "sg:postcode":"1018",
    "sg:province":"Vaud",
    "wof:name":"Sb Informatique, Christ",
    "wof:placetype":"venue"
},
  "geometry": {"coordinates":[6.63454,46.538769],"type":"Point"}
}