{
  "type": "Feature",
  "properties": {
    "iso:country":"CH",
    "sg:address":"Rietstrasse 35",
    "sg:city":"Zollikon",
    "sg:orig_category":"Herstellung von sonstigen elektrischen Ausr\u00fcstungen",
    "sg:phone":"+41 13918882",
    "sg:postcode":"8702",
    "sg:province":"Z\u00fcrich",
    "wof:name":"Frauchiger Alex",
    "wof:placetype":"venue"
},
  "geometry": {"coordinates":[8.576294899,47.3435516357],"type":"Point"}
}