{
  "type": "Feature",
  "properties": {
    "iso:country":"CH",
    "sg:address":"Zollstrasse 23",
    "sg:city":"Schaan",
    "sg:orig_category":"Wirtschaftsverb\u00e4nde Gewerbeverb\u00e4nde/-vereine",
    "sg:phone":"+423 233 36 36",
    "sg:postcode":"9494",
    "wof:name":"Gewerbe-& Wirtschaftskammer F. Das F\u00fcrstentum Liechtenstein",
    "wof:placetype":"venue"
},
  "geometry": {"coordinates":[9.5028657913,47.1681785583],"type":"Point"}
}