{
  "type": "Feature",
  "properties": {
    "iso:country":"CH",
    "sg:address":"Gartenstrasse 78",
    "sg:city":"Basel",
    "sg:classifiers":[
        {
            "category":"Restaurant",
            "type":"Food & Drink"
        }
    ],
    "sg:phone":"+41 61 273 09 00",
    "sg:postcode":"4052",
    "sg:province":"Basel-Stadt",
    "wof:name":"Christian Lang Lang's Odeon",
    "wof:placetype":"venue"
},
  "geometry": {"coordinates":[7.5945968628,47.5491790771],"type":"Point"}
}