{
  "type": "Feature",
  "properties": {
    "iso:country":"CH",
    "sg:address":"Malzgasse 16",
    "sg:city":"Basel",
    "sg:orig_category":"Feuerwehr Herstellung von sonstigen elektrischen Ausr\u00fcstungen",
    "sg:phone":"+41 79 423 57 62",
    "sg:postcode":"4052",
    "sg:province":"Basel-Stadt",
    "wof:name":"Regio Brandschutz Marquardt",
    "wof:placetype":"venue"
},
  "geometry": {"coordinates":[7.5974788666,47.5533599854],"type":"Point"}
}