{
  "type": "Feature",
  "properties": {
    "iso:country":"CH",
    "sg:address":"Schutzengelstrasse 38",
    "sg:city":"Baar",
    "sg:orig_category":"Grosshandel mit chemischen Erzeugnissen Grosshandel mit pharmazeutischen Erzeugnissen",
    "sg:phone":"+41 41 760 65 32",
    "sg:postcode":"6340",
    "sg:province":"Zug",
    "wof:name":"Vescor Ag",
    "wof:placetype":"venue"
},
  "geometry": {"coordinates":[8.5367889404,47.1971588135],"type":"Point"}
}