{
  "type": "Feature",
  "properties": {
    "iso:country":"CH",
    "sg:address":"Via Nassa 21 6900 Lugano. Postfach Caselle Postale 3041",
    "sg:city":"Lugano",
    "sg:orig_category":"Advokaturb\u00fcros Notariate",
    "sg:phone":"+41 91 923 58 70",
    "sg:postcode":"6901",
    "sg:province":"Ticino",
    "wof:name":"Claudio Simonetti Studio Legale & Notarile",
    "wof:placetype":"venue"
},
  "geometry": {"coordinates":[8.949594,46.001686],"type":"Point"}
}