{
  "type": "Feature",
  "properties": {
    "iso:country":"CH",
    "sg:address":"8702 Zollikon. Postfach",
    "sg:city":"Zollikon",
    "sg:orig_category":"Bau U Wohngenossenschaften",
    "sg:postcode":"8702",
    "sg:province":"Z\u00fcrich",
    "wof:name":"Siedlungsgen.h\u00f6hestrasse 44 Zollikon Sbgz",
    "wof:placetype":"venue"
},
  "geometry": {"coordinates":[8.57718,47.340801],"type":"Point"}
}