{
  "type": "Feature",
  "properties": {
    "iso:country":"CH",
    "sg:address":"Hauptstrasse 62",
    "sg:city":"Einigen",
    "sg:orig_category":"Baugewerbe Innenausbau",
    "sg:phone":"+41 33 654 84 80",
    "sg:postcode":"3646",
    "sg:province":"Bern",
    "wof:name":"Rudolf Fahrer Innenausbau-montagen",
    "wof:placetype":"venue"
},
  "geometry": {"coordinates":[7.647039,46.708401],"type":"Point"}
}