{
  "type": "Feature",
  "properties": {
    "iso:country":"CH",
    "sg:address":"Hauptgasse 2 5507 Mellingen. Postfach",
    "sg:city":"Mellingen",
    "sg:orig_category":"Detailhandel mit Waren verschiedener Art, Hauptrichtung Nahrungsmittel Grosshandel mit Nahrungsmitte",
    "sg:phone":"+41 27 956 33 00",
    "sg:postcode":"5507",
    "sg:province":"Aargau",
    "wof:name":"Denner-satellit St. Niklaus, Imboden & Volken",
    "wof:placetype":"venue"
},
  "geometry": {"coordinates":[7.8014130592,46.175579071],"type":"Point"}
}