{
  "type": "Feature",
  "properties": {
    "iso:country":"CH",
    "sg:address":"Kyburgerstrasse 1 6210 Sursee. Postfach",
    "sg:city":"Sursee",
    "sg:orig_category":"Detailhandel mit Haustieren U zoologischem Bedarf",
    "sg:phone":"+41 41 921 52 86",
    "sg:postcode":"6210",
    "sg:province":"Luzern",
    "wof:name":"Carmela Vogler Fridolin Hunde-& Katzenshop",
    "wof:placetype":"venue"
},
  "geometry": {"coordinates":[8.1044416428,47.1721343994],"type":"Point"}
}