{
  "type": "Feature",
  "properties": {
    "addr:full":"Dreik\u00f6nigstrasse 7 8002 Z\u00fcrich. Postfach 4088 Z\u00fcrich Z\u00fcrich 8022",
    "addr:housenumber":"7",
    "addr:postcode":"8002 zuerich. postfach 4088;8022",
    "addr:street":"Dreikoenigstrasse",
    "iso:country":"CH",
    "sg:address":"Dreik\u00f6nigstrasse 7 8002 Z\u00fcrich. Postfach 4088",
    "sg:city":"Z\u00fcrich",
    "sg:orig_category":"Advokaturb\u00fcros",
    "sg:phone":"+41 31 311 30 11",
    "sg:postcode":"8022",
    "sg:province":"Z\u00fcrich",
    "wof:name":"Von Graffenried & Sch\u00e4delin Advokaturb\u00fcro",
    "wof:placetype":"venue"
},
  "geometry": {"coordinates":[7.441662,46.946678],"type":"Point"}
}