{
  "type": "Feature",
  "properties": {
    "iso:country":"CH",
    "sg:address":"Ulmenweg 2",
    "sg:city":"Thun",
    "sg:orig_category":"Sanit\u00e4r U Heizungsinstallation Sanit\u00e4r, Heizungs U L\u00fcftungsinstallation",
    "sg:phone":"+41 33 336 42 54",
    "sg:postcode":"3604",
    "sg:province":"Bern",
    "wof:name":"Rohde P., Zentralheizungen",
    "wof:placetype":"venue"
},
  "geometry": {"coordinates":[7.6153907776,46.7390785217],"type":"Point"}
}