{
  "type": "Feature",
  "properties": {
    "iso:country":"CH",
    "sg:address":"Mandachstrasse 52",
    "sg:city":"Niederhasli",
    "sg:orig_category":"Handel mit Automobilteilen U Zubeh\u00f6r",
    "sg:phone":"+41 13441444",
    "sg:postcode":"8155",
    "sg:province":"Z\u00fcrich",
    "wof:name":"Mb Handels Und Finanz Ag",
    "wof:placetype":"venue"
},
  "geometry": {"coordinates":[8.4891872406,47.4798812866],"type":"Point"}
}