{
  "type": "Feature",
  "properties": {
    "iso:country":"CH",
    "sg:address":"Seestrasse 164",
    "sg:city":"Steckborn",
    "sg:orig_category":"Grosshandel mit Geschenkartikeln U Souvenirs Grosshandel mit Lederwaren U Reiseartikeln",
    "sg:phone":"+41 22 798 08 54",
    "sg:postcode":"8266",
    "sg:province":"Thurgau",
    "wof:name":"Atic Sa",
    "wof:placetype":"venue"
},
  "geometry": {"coordinates":[6.1102428436,46.2272834778],"type":"Point"}
}