{
  "type": "Feature",
  "properties": {
    "iso:country":"CH",
    "sg:address":"Hauptstrasse 65",
    "sg:city":"Rorschach",
    "sg:orig_category":"Elektroinstallation",
    "sg:phone":"+41 79 417 45 67",
    "sg:postcode":"9400",
    "sg:province":"St. Gallen",
    "wof:name":"Lutz Elektroplanung, Ingenieurb\u00fcro F\u00fcr Elektrotechnik",
    "wof:placetype":"venue"
},
  "geometry": {"coordinates":[9.4926376343,47.4783744812],"type":"Point"}
}