{
  "type": "Feature",
  "properties": {
    "iso:country":"CH",
    "sg:address":"Venel Rue J.a. 13",
    "sg:city":"Yverdon-les-bains",
    "sg:orig_category":"Non-Classified Establishments",
    "sg:phone":"+41 24 425 41 38",
    "sg:postcode":"1400",
    "sg:province":"Vaud",
    "wof:name":"Cag Diffusion, Claude-andr\u00e9 Gonet",
    "wof:placetype":"venue"
},
  "geometry": {"coordinates":[6.6414198875,46.7786331177],"type":"Point"}
}