{
  "type": "Feature",
  "properties": {
    "iso:country":"CH",
    "sg:address":"Industriestrasse 28",
    "sg:city":"Volketswil",
    "sg:orig_category":"Grosshandel mit Textilien Grosshandel mit sonstigen Konsumg\u00fctern",
    "sg:phone":"+41 21 944 50 44",
    "sg:postcode":"8604",
    "sg:province":"Z\u00fcrich",
    "wof:name":"Emr Textil T.breig",
    "wof:placetype":"venue"
},
  "geometry": {"coordinates":[6.8680491447,46.4606437683],"type":"Point"}
}