{
  "type": "Feature",
  "properties": {
    "iso:country":"CH",
    "sg:address":"Chilefeldstrasse 12",
    "sg:city":"Merenschwand",
    "sg:orig_category":"Sonstige Aktivit\u00e4ten der nicht-\u00e4rztlichen Medizinalberufe",
    "sg:phone":"+41 56 664 54 04",
    "sg:postcode":"5634",
    "sg:province":"Aargau",
    "wof:name":"Agnes Heer Naturheilpraktikerin",
    "wof:placetype":"venue"
},
  "geometry": {"coordinates":[8.3741474152,47.2557144165],"type":"Point"}
}