{
  "type": "Feature",
  "properties": {
    "iso:country":"CH",
    "sg:address":"Bahnhofstrasse 50 6048 Horw. Postfach 172",
    "sg:city":"Horw",
    "sg:classifiers":[
        {
            "category":"Professional",
            "subcategory":"Accounting & Tax Preparation",
            "type":"Services"
        }
    ],
    "sg:phone":"+41 41 340 20 02",
    "sg:postcode":"6048",
    "sg:province":"Luzern",
    "sg:tags":[
        "u",
        "yachtbau",
        "boot"
    ],
    "wof:name":"Caminada Ag Horw",
    "wof:placetype":"venue"
},
  "geometry": {"coordinates":[8.307373,47.017857],"type":"Point"}
}