{
  "type": "Feature",
  "properties": {
    "iso:country":"CH",
    "sg:address":"L\u00e4rchenweg 13",
    "sg:city":"H\u00e4gendorf",
    "sg:orig_category":"Naturheil\u00e4rzte and Heilpraktiker",
    "sg:phone":"+41 62 216 04 14",
    "sg:postcode":"4614",
    "sg:province":"Solothurn",
    "wof:name":"Daniel Kamber Fern\u00f6stliche Heilmethoden",
    "wof:placetype":"venue"
},
  "geometry": {"coordinates":[7.8484139442,47.3372612],"type":"Point"}
}