{
  "type": "Feature",
  "properties": {
    "iso:country":"CH",
    "sg:address":"Einschlagstrasse 11",
    "sg:city":"Neuhausen",
    "sg:orig_category":"Kinderkrippen U horte Sonstige Kultur U Unterhaltungseinrichtungen",
    "sg:phone":"+41 52 672 10 70",
    "sg:postcode":"8212",
    "sg:province":"Schaffhausen",
    "wof:name":"Sch\u00fclerhort & Freizeit- Werkstatt",
    "wof:placetype":"venue"
},
  "geometry": {"coordinates":[8.6173496246,47.6855888367],"type":"Point"}
}