{
  "type": "Feature",
  "properties": {
    "iso:country":"CH",
    "sg:address":"St\u00e4cklihus 6018 Buttisholz. Postfach 123",
    "sg:city":"Buttisholz",
    "sg:orig_category":"Zahnarztpraxen",
    "sg:phone":"+41 41 928 13 16",
    "sg:postcode":"6018",
    "sg:province":"Luzern",
    "wof:name":"Dr. Med. Dent. Daniel Bolfing Zahnarzt",
    "wof:placetype":"venue"
},
  "geometry": {"coordinates":[8.0937595367,47.1144142151],"type":"Point"}
}