{
  "type": "Feature",
  "properties": {
    "addr:full":"Au Village 24 Glovelier Jura 2855",
    "addr:housenumber":"24",
    "addr:postcode":"2855",
    "addr:street":"Au Village;Jura",
    "iso:country":"CH",
    "sg:address":"Au Village 24",
    "sg:city":"Glovelier",
    "sg:classifiers":[
        {
            "category":"Banks & Credit Unions",
            "subcategory":"Bank",
            "type":"Services"
        }
    ],
    "sg:phone":"+41 21 800 37 40",
    "sg:postcode":"2855",
    "sg:province":"Jura",
    "wof:name":"Banque Raiffeisen De La C\u00f4te-est",
    "wof:placetype":"venue"
},
  "geometry": {"coordinates":[6.41617,46.518372],"type":"Point"}
}