{
  "type": "Feature",
  "properties": {
    "iso:country":"CH",
    "sg:address":"2114",
    "sg:city":"Fleurier",
    "sg:orig_category":"Sonstige mit Sport verbundene T\u00e4tigkeiten",
    "sg:phone":"+41 32 861 10 24",
    "sg:postcode":"2114",
    "sg:province":"Neuch\u00e2tel",
    "wof:name":"Fondation Du Dr Edouard Leuba-jequier En Faveur De La Maison De La Ruedu Temple 1 \u00e0 Fleurier Et De L'animation Culturelle Au Val-de-travers",
    "wof:placetype":"venue"
},
  "geometry": {"coordinates":[6.5804052353,46.9023094177],"type":"Point"}
}