{
  "type": "Feature",
  "properties": {
    "iso:country":"CH",
    "sg:address":"Hinterdorf 77 7220 Schiers. Postfach",
    "sg:city":"Schiers",
    "sg:orig_category":"Elektroinstallation Herstellung von Elektromotoren, Generatoren U Transformatoren",
    "sg:phone":"+41 81 328 13 01",
    "sg:postcode":"7220",
    "sg:province":"Graubunden",
    "wof:name":"Frey Christian Elektroanlagen Stark Und Schwachstromanlagen; Installation Und Planung. Elektrische Ger\u00e4te; Verkauf Und Vertrieb",
    "wof:placetype":"venue"
},
  "geometry": {"coordinates":[9.6903123856,46.969619751],"type":"Point"}
}