{
  "type": "Feature",
  "properties": {
    "iso:country":"CH",
    "sg:address":"Chemin De Beausite 15",
    "sg:city":"Tavannes",
    "sg:orig_category":"Abbruch U Sprenggewerbe, Erdbewegungsarbeiten Maurerarbeiten",
    "sg:phone":"+41 21 944 40 54",
    "sg:postcode":"2710",
    "sg:province":"Bern",
    "wof:name":"Granoli V. & Fils Sa",
    "wof:placetype":"venue"
},
  "geometry": {"coordinates":[6.858868,46.454082],"type":"Point"}
}