{
  "type": "Feature",
  "properties": {
    "addr:full":"Alte Schaffhauserstrasse 19 Diessenhofen Thurgau 8253",
    "addr:housenumber":"19",
    "addr:postcode":"8253",
    "addr:street":"Alte Schaffhauserstrasse",
    "iso:country":"CH",
    "sg:address":"Alte Schaffhauserstrasse 19",
    "sg:city":"Diessenhofen",
    "sg:orig_category":"Bau von Strassen, Sportanlagen U Bahnverkehrsstrecken",
    "sg:phone":"+41 52 657 34 97",
    "sg:postcode":"8253",
    "sg:province":"Thurgau",
    "wof:name":"H\u00fcppi Ag Schaffhausen",
    "wof:placetype":"venue"
},
  "geometry": {"coordinates":[8.737331,47.689846],"type":"Point"}
}