{
  "type": "Feature",
  "properties": {
    "iso:country":"CH",
    "sg:address":"2828 Montsevelier. Postfach 1",
    "sg:city":"Montsevelier",
    "sg:orig_category":"Sportvereine Ballsport Fussball",
    "sg:phone":"+41 91 683 40 56",
    "sg:postcode":"2828",
    "sg:province":"Jura",
    "wof:name":"Fc Morbio",
    "wof:placetype":"venue"
},
  "geometry": {"coordinates":[9.0213098526,45.8488502502],"type":"Point"}
}