{
  "type": "Feature",
  "properties": {
    "iso:country":"CH",
    "sg:address":"Eichenweg 51",
    "sg:city":"Embrach",
    "sg:orig_category":"Schulpflegen",
    "sg:phone":"+41 18662555",
    "sg:postcode":"8424",
    "sg:province":"Z\u00fcrich",
    "wof:name":"Schulpflege Der Oberstufen Embrach-lufingen-oberembrach",
    "wof:placetype":"venue"
},
  "geometry": {"coordinates":[8.5945415497,47.5110702515],"type":"Point"}
}