{
  "type": "Feature",
  "properties": {
    "iso:country":"CH",
    "sg:address":"Alleeweg 6",
    "sg:city":"Lotzwil",
    "sg:orig_category":"Instandhaltung U Reparatur von Automobilen",
    "sg:phone":"+41 62 922 15 17",
    "sg:postcode":"4932",
    "sg:province":"Bern",
    "wof:name":"Carrosserie Hoogendoorn L.",
    "wof:placetype":"venue"
},
  "geometry": {"coordinates":[7.7920660973,47.1877288818],"type":"Point"}
}