{
  "type": "Feature",
  "properties": {
    "iso:country":"CH",
    "sg:address":"M\u00fchlemattweg 10",
    "sg:city":"Diepflingen",
    "sg:orig_category":"G\u00fcterbef\u00f6rderung im Strassenverkehr",
    "sg:phone":"+41 61 971 68 26",
    "sg:postcode":"4442",
    "sg:province":"Basel-Landschaft",
    "wof:name":"Moser Stephan Intern. Transporte",
    "wof:placetype":"venue"
},
  "geometry": {"coordinates":[7.8377251625,47.4473419189],"type":"Point"}
}