{
  "type": "Feature",
  "properties": {
    "iso:country":"CH",
    "sg:address":"Thonon Route De 153 1222 V\u00e9senaz. Postfach",
    "sg:city":"V\u00e9senaz",
    "sg:orig_category":"Unclassifiable Establishments",
    "sg:phone":"+41 22 718 55 13",
    "sg:postcode":"1222",
    "sg:province":"Gen\u00e8ve",
    "wof:name":"Reuters Holdings Switzerland Sa",
    "wof:placetype":"venue"
},
  "geometry": {"coordinates":[6.1980051994,46.2396736145],"type":"Point"}
}