{
  "type": "Feature",
  "properties": {
    "iso:country":"CH",
    "sg:address":"Hauptstrasse 5",
    "sg:city":"Hochdorf",
    "sg:orig_category":"Interessenvertretungen",
    "sg:postcode":"6280",
    "sg:province":"Luzern",
    "wof:name":"Ottiger-lang-stiftung, Jakob.",
    "wof:placetype":"venue"
},
  "geometry": {"coordinates":[8.2905950546,47.1663360596],"type":"Point"}
}