{
  "type": "Feature",
  "properties": {
    "iso:country":"CH",
    "sg:address":"H\u00f6heweg 29 3800 Interlaken. Postfach 246",
    "sg:city":"Interlaken",
    "sg:orig_category":"Zahnarztpraxen",
    "sg:phone":"+41 33 822 37 37",
    "sg:postcode":"3800",
    "sg:province":"Bern",
    "wof:name":"Dr. Med. Dent. Kurt M\u00fcller Zahnarzt",
    "wof:placetype":"venue"
},
  "geometry": {"coordinates":[7.8558387756,46.6856193542],"type":"Point"}
}