{
  "type": "Feature",
  "properties": {
    "iso:country":"CH",
    "sg:address":"Pupikoferstrasse 5",
    "sg:city":"Tuttwil",
    "sg:orig_category":"Grosshandel mit Software Optische Ger\u00e4te Grosshandel",
    "sg:phone":"+41 52 366 42 42",
    "sg:postcode":"9546",
    "sg:province":"Thurgau",
    "wof:name":"Optive Gmbh",
    "wof:placetype":"venue"
},
  "geometry": {"coordinates":[8.9457492828,47.4854927063],"type":"Point"}
}