{
  "type": "Feature",
  "properties": {
    "iso:country":"CH",
    "sg:address":"Rue Du Lac 116",
    "sg:city":"Clarens",
    "sg:orig_category":"Personenbef\u00f6rderung im Nahverkehr",
    "sg:phone":"+41 21 964 11 18",
    "sg:postcode":"1815",
    "sg:province":"Vaud",
    "wof:name":"Trolleybus & Autobus Vmcv",
    "wof:placetype":"venue"
},
  "geometry": {"coordinates":[6.8904438019,46.4412345886],"type":"Point"}
}