{
  "type": "Feature",
  "properties": {
    "iso:country":"CH",
    "sg:address":"Eschenmattstrasse 24",
    "sg:city":"M\u00f6hlin",
    "sg:orig_category":"G\u00fcterbef\u00f6rderung im Strassenverkehr",
    "sg:phone":"+41 79 356 01 65",
    "sg:postcode":"4313",
    "sg:province":"Aargau",
    "wof:name":"Methobus M\u00f6hlin Gmbh Carreisen",
    "wof:placetype":"venue"
},
  "geometry": {"coordinates":[7.8399429321,47.5630989075],"type":"Point"}
}