{
  "type": "Feature",
  "properties": {
    "iso:country":"CH",
    "sg:address":"Badenerstrasse 529 8048 Z\u00fcrich. Postfach",
    "sg:city":"Z\u00fcrich",
    "sg:orig_category":"Sanit\u00e4r, Heizungs U L\u00fcftungsinstallation",
    "sg:postcode":"8048",
    "sg:province":"Z\u00fcrich",
    "wof:name":"Rufer Hans, Heizungen",
    "wof:placetype":"venue"
},
  "geometry": {"coordinates":[8.5013504028,47.3821105957],"type":"Point"}
}