{
  "type": "Feature",
  "properties": {
    "iso:country":"CH",
    "sg:address":"6695",
    "sg:city":"Peccia",
    "sg:classifiers":[
        {
            "category":"Restaurant",
            "type":"Food & Drink"
        }
    ],
    "sg:phone":"+41 91 755 11 65",
    "sg:postcode":"6695",
    "sg:province":"Ticino",
    "wof:name":"Osteria Medici",
    "wof:placetype":"venue"
},
  "geometry": {"coordinates":[8.6472396851,46.4081001282],"type":"Point"}
}