{
  "type": "Feature",
  "properties": {
    "iso:country":"CH",
    "sg:address":"Altmannsteinstr. 34",
    "sg:city":"H\u00f6ri",
    "sg:classifiers":[
        {
            "category":"Manufacturing",
            "subcategory":"Rubber & Plastics",
            "type":"Manufacturing & Wholesale Goods"
        }
    ],
    "sg:phone":"+41 4118604401",
    "sg:postcode":"8181",
    "sg:province":"Z\u00fcrich",
    "wof:name":"Royal Co Ag",
    "wof:placetype":"venue"
},
  "geometry": {"coordinates":[8.5181236267,47.5113372803],"type":"Point"}
}