{
  "type": "Feature",
  "properties": {
    "iso:country":"CH",
    "sg:address":"Hanfackerstrasse 1",
    "sg:city":"Niederhasli",
    "sg:orig_category":"Architektur U Ingenieurb\u00fcros",
    "sg:phone":"+41 18503200",
    "sg:postcode":"8155",
    "sg:province":"Z\u00fcrich",
    "wof:name":"Rupert Wirth Ingenieurb\u00fcro",
    "wof:placetype":"venue"
},
  "geometry": {"coordinates":[8.485103,47.481583],"type":"Point"}
}