{
  "type": "Feature",
  "properties": {
    "iso:country":"CH",
    "sg:address":"Sulackerstrasse 4",
    "sg:city":"Frauenfeld",
    "sg:orig_category":"Werbung",
    "sg:postcode":"8500",
    "sg:province":"Thurgau",
    "wof:name":"Visual Rent, Baumann H.",
    "wof:placetype":"venue"
},
  "geometry": {"coordinates":[8.9048728943,47.5624885559],"type":"Point"}
}