{
  "type": "Feature",
  "properties": {
    "iso:country":"CH",
    "sg:address":"3176",
    "sg:city":"Neuenegg",
    "sg:orig_category":"Verwertung von Milch",
    "sg:postcode":"3176",
    "sg:province":"Bern",
    "wof:name":"Milchverwertungsgenossenschaft Buchen Bei Thun",
    "wof:placetype":"venue"
},
  "geometry": {"coordinates":[7.7014198303,46.7793807983],"type":"Point"}
}