{
  "type": "Feature",
  "properties": {
    "iso:country":"CH",
    "sg:address":"Bachtalsteig 6 5408 Ennetbaden. Postfach",
    "sg:city":"Ennetbaden",
    "sg:orig_category":"Grafikateliers, Design Informatikdienste",
    "sg:phone":"+41 56 221 70 27",
    "sg:postcode":"5408",
    "sg:province":"Aargau",
    "wof:name":"Wwware.ch Baumann, Leuthold, Kreyenb\u00fchl",
    "wof:placetype":"venue"
},
  "geometry": {"coordinates":[8.3182325363,47.4796867371],"type":"Point"}
}