{
  "type": "Feature",
  "properties": {
    "iso:country":"CH",
    "sg:address":"Croix-blanche La",
    "sg:city":"Arnex-sur-orbe",
    "sg:orig_category":"Vermietung U Verpachtung von eigenen Immobilien",
    "sg:postcode":"1321",
    "sg:province":"Vaud",
    "wof:name":"Si R\u00e9sidence Les Fleurs De Lys",
    "wof:placetype":"venue"
},
  "geometry": {"coordinates":[6.5189700127,46.6941413879],"type":"Point"}
}