{
  "type": "Feature",
  "properties": {
    "iso:country":"CH",
    "sg:address":"Hufgasse 10",
    "sg:city":"Z\u00fcrich",
    "sg:classifiers":[
        {
            "category":"Banks & Credit Unions",
            "subcategory":"Financial Services",
            "type":"Services"
        }
    ],
    "sg:phone":"+41 16317777",
    "sg:postcode":"8008",
    "sg:province":"Z\u00fcrich",
    "sg:tags":[
        "information"
    ],
    "wof:name":"Reuters S.a.",
    "wof:placetype":"venue"
},
  "geometry": {"coordinates":[8.5490760803,47.3649253845],"type":"Point"}
}