{
  "type": "Feature",
  "properties": {
    "iso:country":"CH",
    "sg:address":"Neumattstrasse 37",
    "sg:city":"R\u00fcdtligen",
    "sg:orig_category":"Detailhandel mit elektrischen Haushalts-,Radio U Fernsehger\u00e4ten sowie Musikinstrumenten",
    "sg:phone":"+41 34 445 20 30",
    "sg:postcode":"3422",
    "sg:province":"Bern",
    "wof:name":"Gerber Apparatebau Gmbh",
    "wof:placetype":"venue"
},
  "geometry": {"coordinates":[7.5646090508,47.0926017761],"type":"Point"}
}