{
  "type": "Feature",
  "properties": {
    "iso:country":"CH",
    "sg:address":"Bodenackerstrasse 22",
    "sg:city":"Wallisellen",
    "sg:orig_category":"Unternehmensberatung",
    "sg:postcode":"8304",
    "sg:province":"Z\u00fcrich",
    "wof:name":"Giulio Meier Management Consulting",
    "wof:placetype":"venue"
},
  "geometry": {"coordinates":[8.5849685669,47.4183082581],"type":"Point"}
}