{
  "type": "Feature",
  "properties": {
    "iso:country":"CH",
    "sg:address":"Franscini Viale 1",
    "sg:city":"Lugano",
    "sg:orig_category":"Non-Classified Establishments",
    "sg:postcode":"6900",
    "sg:province":"Ticino",
    "wof:name":"Pavalon Gmbh Beteiligungen Usw.",
    "wof:placetype":"venue"
},
  "geometry": {"coordinates":[8.8187456131,47.2338638306],"type":"Point"}
}