{
  "type": "Feature",
  "properties": {
    "iso:country":"CH",
    "sg:address":"Im Sydef\u00e4deli 32",
    "sg:city":"Z\u00fcrich",
    "sg:orig_category":"Herstellung von medizinischen U chirurgischen Ger\u00e4ten sowie orthop\u00e4dischen Vorrichtungen",
    "sg:postcode":"8037",
    "sg:province":"Z\u00fcrich",
    "wof:name":"Zahntechnisches-labor D. Orlic",
    "wof:placetype":"venue"
},
  "geometry": {"coordinates":[8.5185394287,47.3947906494],"type":"Point"}
}