{
  "type": "Feature",
  "properties": {
    "iso:country":"CH",
    "sg:address":"Leumattstrasse 10",
    "sg:city":"Luzern",
    "sg:orig_category":"Unternehmensberatung",
    "sg:postcode":"6006",
    "sg:province":"Luzern",
    "wof:name":"Britschgi Projekt- & Datenmanagement",
    "wof:placetype":"venue"
},
  "geometry": {"coordinates":[8.3348503113,47.0553512573],"type":"Point"}
}