{
  "type": "Feature",
  "properties": {
    "iso:country":"CH",
    "sg:address":"Gotthardstrasse 85 6490 Andermatt. Postfach 242",
    "sg:city":"Andermatt",
    "sg:classifiers":[
        {
            "category":"Travel",
            "subcategory":"Hotels & Motels",
            "type":"Entertainment"
        }
    ],
    "sg:phone":"+41 41 887 11 89",
    "sg:postcode":"6490",
    "sg:province":"Uri",
    "sg:tags":[
        "hotels",
        "mit",
        "restaurant"
    ],
    "wof:name":"Sasso Giuseppina Hotel Schweizerhof-central",
    "wof:placetype":"venue"
},
  "geometry": {"coordinates":[8.5971717834,46.6334075928],"type":"Point"}
}