{
  "type": "Feature",
  "properties": {
    "iso:country":"CH",
    "sg:address":"Islikerstrasse 24",
    "sg:city":"Hittnau",
    "sg:orig_category":"Herstellung von Teilen U Zubeh\u00f6r f\u00fcr Automobile Mechanische Werkst\u00e4tten",
    "sg:phone":"+41 19951080",
    "sg:postcode":"8335",
    "sg:province":"Z\u00fcrich",
    "wof:name":"Cr Automotiv Service Ag",
    "wof:placetype":"venue"
},
  "geometry": {"coordinates":[8.8228635788,47.3693885803],"type":"Point"}
}