{
  "type": "Feature",
  "properties": {
    "iso:country":"CH",
    "sg:address":"Rosenweg 38",
    "sg:city":"Bern",
    "sg:orig_category":"Bauschreinerei Herstellung von Fenstern U T\u00fcren aus Holz",
    "sg:phone":"+41 31 379 14 14",
    "sg:postcode":"3006",
    "sg:province":"Bern",
    "wof:name":"Steimle Fenster Ag Fensterfabrik",
    "wof:placetype":"venue"
},
  "geometry": {"coordinates":[7.435018,46.935558],"type":"Point"}
}