{
  "type": "Feature",
  "properties": {
    "iso:country":"CH",
    "sg:address":"5058",
    "sg:city":"Wiliberg",
    "sg:orig_category":"Politische Parteien SVP",
    "sg:postcode":"5058",
    "sg:province":"Aargau",
    "wof:name":"Svp Ortsparteipr\u00e4sident",
    "wof:placetype":"venue"
},
  "geometry": {"coordinates":[8.0169296265,47.266040802],"type":"Point"}
}