{
  "type": "Feature",
  "properties": {
    "iso:country":"CH",
    "sg:address":"Morges Rue De 23",
    "sg:city":"Crissier",
    "sg:orig_category":"Erwachsenenbildung U Unterricht",
    "sg:postcode":"1023",
    "sg:province":"Vaud",
    "wof:name":"Mcdonald's Suisse Management And Services S\u00e0rl",
    "wof:placetype":"venue"
},
  "geometry": {"coordinates":[6.5676541328,46.5467338562],"type":"Point"}
}