{
  "type": "Feature",
  "properties": {
    "iso:country":"CH",
    "sg:address":"S\u00e4gerei 4935 Leimiswil. Postfach",
    "sg:city":"Leimiswil",
    "sg:orig_category":"Herstellung von Verbrennungsmotoren U Turbinen ohne Motoren f\u00fcr Luft U Strassenfahrzeuge",
    "sg:phone":"+41 62 965 19 20",
    "sg:postcode":"4935",
    "sg:province":"Bern",
    "wof:name":"B\u00fchler M. & Co., Motor + Gartenger\u00e4te",
    "wof:placetype":"venue"
},
  "geometry": {"coordinates":[7.7640829086,47.149520874],"type":"Point"}
}