{
  "type": "Feature",
  "properties": {
    "iso:country":"CH",
    "sg:address":"Langenthalstr. 84",
    "sg:city":"Aarwangen",
    "sg:classifiers":[
        {
            "category":"Home & Garden",
            "subcategory":"Furniture",
            "type":"Retail Goods"
        }
    ],
    "sg:phone":"+41 62 922 34 47",
    "sg:postcode":"4912",
    "sg:province":"Bern",
    "sg:tags":[
        "wood"
    ],
    "wof:name":"Jaisli Taefer Und Platten Ag",
    "wof:placetype":"venue"
},
  "geometry": {"coordinates":[7.7755060196,47.2310791016],"type":"Point"}
}