{
  "type": "Feature",
  "properties": {
    "iso:country":"CH",
    "sg:address":"Seestrasse 318",
    "sg:city":"Z\u00fcrich",
    "sg:orig_category":"Hochschulen U h\u00f6here Ausbildung",
    "sg:phone":"+41 14820610",
    "sg:postcode":"8000",
    "sg:province":"Z\u00fcrich",
    "wof:name":"Fluck & Partner Humanagement Consulting Gmbh",
    "wof:placetype":"venue"
},
  "geometry": {"coordinates":[8.5324668884,47.3481407166],"type":"Point"}
}