{
  "type": "Feature",
  "properties": {
    "iso:country":"CH",
    "sg:address":"Aarburgerstrasse 10",
    "sg:city":"Zofingen",
    "sg:classifiers":[
        {
            "category":"Banks & Credit Unions",
            "subcategory":"Investment Brokerage",
            "type":"Services"
        }
    ],
    "sg:phone":"+41 62 788 26 26",
    "sg:postcode":"4800",
    "sg:province":"Aargau",
    "sg:tags":[
        "equestrian",
        "items",
        "accessory",
        "equipment",
        "harness",
        "riding"
    ],
    "wof:name":"Gygax Ag",
    "wof:placetype":"venue"
},
  "geometry": {"coordinates":[7.941806,47.292126],"type":"Point"}
}