{
  "type": "Feature",
  "properties": {
    "iso:country":"CH",
    "sg:address":"1716 Oberschrot. Postfach",
    "sg:city":"Plaffeien",
    "sg:orig_category":"Landesverteidigung, Sozialversicherung \u00d6ffentliche Verwaltung",
    "sg:phone":"+41 26 419 11 57",
    "sg:postcode":"1716",
    "sg:province":"Fribourg",
    "wof:name":"Zivilschutzstelle Oberschrot",
    "wof:placetype":"venue"
},
  "geometry": {"coordinates":[7.2859311104,46.7442588806],"type":"Point"}
}