{
  "type": "Feature",
  "properties": {
    "iso:country":"CH",
    "sg:address":"Piazza Comunale",
    "sg:city":"Poschiavo",
    "sg:classifiers":[
        {
            "category":"Government",
            "subcategory":"Post Office",
            "type":"Public Place"
        }
    ],
    "sg:phone":"+41 81 844 01 18",
    "sg:postcode":"7742",
    "sg:province":"Graubunden",
    "sg:tags":[
        "caf\u00e9s",
        "tea-rooms"
    ],
    "wof:name":"Caff\u00e8 Alpina",
    "wof:placetype":"venue"
},
  "geometry": {"coordinates":[10.0579719543,46.3266944885],"type":"Point"}
}