{
  "type": "Feature",
  "properties": {
    "iso:country":"CH",
    "sg:address":"Ueberlandstrasse 361 8051 Z\u00fcrich. Postfach",
    "sg:city":"Z\u00fcrich",
    "sg:orig_category":"RESTAURANTS: TEA-ROOMS",
    "sg:postcode":"8051",
    "sg:province":"Z\u00fcrich",
    "wof:name":"Resko Restaurations Ag",
    "wof:placetype":"venue"
},
  "geometry": {"coordinates":[8.5833244324,47.4080848694],"type":"Point"}
}