{
  "type": "Feature",
  "properties": {
    "iso:country":"CH",
    "sg:address":"Pedevilla Via 13",
    "sg:city":"Bellinzona",
    "sg:orig_category":"RESTAURANTS: TEA-ROOMS",
    "sg:postcode":"6500",
    "sg:province":"Ticino",
    "wof:name":"Silvestri Sa",
    "wof:placetype":"venue"
},
  "geometry": {"coordinates":[9.0241193771,46.1944618225],"type":"Point"}
}