{
  "type": "Feature",
  "properties": {
    "iso:country":"CH",
    "sg:address":"Industrie Rue De L' 19",
    "sg:city":"Ste-croix",
    "sg:orig_category":"Unclassifiable Establishments",
    "sg:postcode":"1450",
    "sg:province":"Vaud",
    "wof:name":"Si Rue De L'industrie 19 Sa",
    "wof:placetype":"venue"
},
  "geometry": {"coordinates":[6.5032429695,46.8211708069],"type":"Point"}
}