{
  "type": "Feature",
  "properties": {
    "iso:country":"CH",
    "sg:address":"Immeuble Xir\u00e8s-nord",
    "sg:city":"Crans-sur-sierre",
    "sg:orig_category":"Detailhandel mit Tabakwaren",
    "sg:phone":"+41 27 481 39 57",
    "sg:postcode":"3963",
    "sg:province":"Valais",
    "wof:name":"La Tabati\u00e8re Crans Sa",
    "wof:placetype":"venue"
},
  "geometry": {"coordinates":[7.4691519737,46.3059539795],"type":"Point"}
}