{
  "type": "Feature",
  "properties": {
    "iso:country":"CH",
    "sg:address":"Hasenwachtstrasse 10 5737 Menziken. Postfach 91",
    "sg:city":"Menziken",
    "sg:orig_category":"Grosshandel mit Obst U Gem\u00fcse",
    "sg:phone":"+41 62 765 60 30",
    "sg:postcode":"5737",
    "sg:province":"Aargau",
    "wof:name":"Thomann Und Trachsel Ag, Menziken",
    "wof:placetype":"venue"
},
  "geometry": {"coordinates":[8.1860370636,47.2293052673],"type":"Point"}
}