{
  "type": "Feature",
  "properties": {
    "addr:full":"Via Retica 1 Bellinzona Ticino 6500",
    "addr:housenumber":"1",
    "addr:postcode":"6500",
    "addr:street":"Via Retica",
    "iso:country":"CH",
    "sg:address":"Via Retica 1",
    "sg:city":"Bellinzona",
    "sg:orig_category":"Autospenglereien",
    "sg:phone":"+41 91 825 57 78",
    "sg:postcode":"6500",
    "sg:province":"Ticino",
    "wof:name":"Carrozzeria Nord Sagl Hikmet Ozcan",
    "wof:placetype":"venue"
},
  "geometry": {"coordinates":[9.025876,46.198238],"type":"Point"}
}