{
  "type": "Feature",
  "properties": {
    "iso:country":"CH",
    "sg:address":"1733",
    "sg:city":"Treyvaux",
    "sg:orig_category":"Grosshandel mit elektrischen Haushaltsger\u00e4ten Grosshandel mit elektrischen Haushaltsger\u00e4ten, Radio U",
    "sg:phone":"+41 41 630 32 78",
    "sg:postcode":"1733",
    "sg:province":"Fribourg",
    "wof:name":"Gregomatic Ag",
    "wof:placetype":"venue"
},
  "geometry": {"coordinates":[8.3084096909,46.9855194092],"type":"Point"}
}