{
  "type": "Feature",
  "properties": {
    "iso:country":"CH",
    "sg:address":"Fischingerstrasse 4",
    "sg:city":"Sirnach",
    "sg:orig_category":"Druck ohne Zeitungsdruck Offsetdruck",
    "sg:phone":"+41 71 966 16 26",
    "sg:postcode":"8370",
    "sg:province":"Thurgau",
    "wof:name":"Persolf\u00fcrsorgestiftung Der Druckerei Sirnach Ag",
    "wof:placetype":"venue"
},
  "geometry": {"coordinates":[8.9966459274,47.4613647461],"type":"Point"}
}