{
  "type": "Feature",
  "properties": {
    "iso:country":"CH",
    "sg:address":"Grendelstrasse 14",
    "sg:city":"Ennetbaden",
    "sg:orig_category":"Erbringung von sonstigen Dienstleistungen f\u00fcr Unterhaltung, Erholung U Freizeit Sonstige Hilfsdienst",
    "sg:phone":"+41 56 222 22 05",
    "sg:postcode":"5408",
    "sg:province":"Aargau",
    "wof:name":"Tiziana Zeller City-art K\u00fcnstleragentur",
    "wof:placetype":"venue"
},
  "geometry": {"coordinates":[8.3144578934,47.4779586792],"type":"Point"}
}