{
  "type": "Feature",
  "properties": {
    "iso:country":"CH",
    "sg:address":"1716",
    "sg:city":"Oberschrot",
    "sg:orig_category":"Bau U Wohngenossenschaften",
    "sg:phone":"+41 26 419 12 47",
    "sg:postcode":"1716",
    "sg:province":"Fribourg",
    "wof:name":"Wohnbau Oberschrot Ag Dominik Raemy Ag",
    "wof:placetype":"venue"
},
  "geometry": {"coordinates":[7.285931,46.744259],"type":"Point"}
}