{
  "type": "Feature",
  "properties": {
    "iso:country":"CH",
    "sg:address":"Birmensdorferstrasse 122",
    "sg:city":"Urdorf",
    "sg:orig_category":"Autogaragen",
    "sg:phone":"+41 71 333 22 79",
    "sg:postcode":"8902",
    "sg:province":"Z\u00fcrich",
    "wof:name":"Bruno F\u00e4ssler Garage",
    "wof:placetype":"venue"
},
  "geometry": {"coordinates":[9.36713,47.36948],"type":"Point"}
}