{
  "type": "Feature",
  "properties": {
    "iso:country":"CH",
    "sg:address":"Route Monts-de-lavaux 15",
    "sg:city":"Belmont-lausanne",
    "sg:orig_category":"Offsetdruck",
    "sg:phone":"+41 21 729 96 47",
    "sg:postcode":"1092",
    "sg:province":"Vaud",
    "wof:name":"Eric Liardet Imprimerie",
    "wof:placetype":"venue"
},
  "geometry": {"coordinates":[6.6778879166,46.5213165283],"type":"Point"}
}