{
  "type": "Feature",
  "properties": {
    "iso:country":"CH",
    "sg:address":"Stadtturmstrasse 13",
    "sg:city":"Baden",
    "sg:orig_category":"B\u00e4ckereien Detailhandel mit Brot, Back U S\u00fcsswaren",
    "sg:phone":"+41 56 221 00 18",
    "sg:postcode":"5400",
    "sg:province":"Aargau",
    "wof:name":"Brotl\u00e4deli",
    "wof:placetype":"venue"
},
  "geometry": {"coordinates":[8.30604,47.475323],"type":"Point"}
}