{
  "type": "Feature",
  "properties": {
    "addr:full":"Encarden Sagogn Graubunden 7152",
    "addr:postcode":"7152",
    "iso:country":"CH",
    "sg:address":"Encarden",
    "sg:city":"Sagogn",
    "sg:orig_category":"Bauschreinerei Herstellung von Konstruktionsteilen, Fertigbauteilen U Ausbauelementen aus Holz",
    "sg:phone":"+41 19843585",
    "sg:postcode":"7152",
    "sg:province":"Graubunden",
    "wof:name":"Bau Und M\u00f6bel-schreinerei, Glaserei, Ueli Gr\u00e4nicher",
    "wof:placetype":"venue"
},
  "geometry": {"coordinates":[8.6434,47.35635],"type":"Point"}
}