{
  "type": "Feature",
  "properties": {
    "iso:country":"CH",
    "sg:address":"H\u00f6henstrasse Ost 61",
    "sg:city":"Olten",
    "sg:orig_category":"Non-Classified Establishments",
    "sg:postcode":"4600",
    "sg:province":"Solothurn",
    "wof:name":"Tschan Informatik",
    "wof:placetype":"venue"
},
  "geometry": {"coordinates":[7.9211559296,47.3441925049],"type":"Point"}
}