{
  "type": "Feature",
  "properties": {
    "iso:country":"CH",
    "sg:address":"Nassenwil 8155 Niederhasli. Postfach",
    "sg:city":"Niederhasli",
    "sg:orig_category":"Grosshandel mit sonstigen Konsumg\u00fctern",
    "sg:phone":"+41 79 631 80 34",
    "sg:postcode":"8155",
    "sg:province":"Z\u00fcrich",
    "wof:name":"Arthur Schneider Textilagentur",
    "wof:placetype":"venue"
},
  "geometry": {"coordinates":[8.4848089218,47.4798812866],"type":"Point"}
}