{
  "type": "Feature",
  "properties": {
    "iso:country":"CH",
    "sg:address":"Hofgut",
    "sg:city":"G\u00fcmligen",
    "sg:orig_category":"Herstellung von Industriegasen Mineral\u00f6lverarbeitung",
    "sg:phone":"+41 31 950 50 50",
    "sg:postcode":"3073",
    "sg:province":"Bern",
    "wof:name":"Carbagas",
    "wof:placetype":"venue"
},
  "geometry": {"coordinates":[7.5135669708,46.9331359863],"type":"Point"}
}