{
  "type": "Feature",
  "properties": {
    "iso:country":"CH",
    "sg:address":"Sch\u00fctzenmattstrasse 85",
    "sg:city":"Basel",
    "sg:orig_category":"Kosmetikinstitute",
    "sg:phone":"+41 61 272 49 59",
    "sg:postcode":"4051",
    "sg:province":"Basel-Stadt",
    "wof:name":"Verena Witschi Kosmetikinstitut Iris",
    "wof:placetype":"venue"
},
  "geometry": {"coordinates":[7.5775761604,47.5531425476],"type":"Point"}
}