{
  "type": "Feature",
  "properties": {
    "iso:country":"CH",
    "sg:address":"Stampfenmatt 8909 Zwillikon. Postfach",
    "sg:city":"Zwillikon",
    "sg:orig_category":"Herstellung von Kakao, Schokoladeerzeugnissen U Zuckerwaren",
    "sg:postcode":"8909",
    "sg:province":"Z\u00fcrich",
    "wof:name":"Vreni's Marktconfiserie Vollenweider V. Und Schmidiger K.",
    "wof:placetype":"venue"
},
  "geometry": {"coordinates":[8.4343233109,47.2860984802],"type":"Point"}
}