{
  "type": "Feature",
  "properties": {
    "iso:country":"CH",
    "sg:address":"Kreuzfeldstrasse 63",
    "sg:city":"Lotzwil",
    "sg:orig_category":"Interessenvertretungen",
    "sg:postcode":"4932",
    "sg:province":"Bern",
    "wof:name":"Ammon-moor Fonds",
    "wof:placetype":"venue"
},
  "geometry": {"coordinates":[7.7866520882,47.1971664429],"type":"Point"}
}