{
  "type": "Feature",
  "properties": {
    "iso:country":"CH",
    "sg:address":"Florastrasse 24",
    "sg:city":"Dietikon",
    "sg:orig_category":"Sonstiges Versicherungsgewerbe",
    "sg:postcode":"8953",
    "sg:province":"Z\u00fcrich",
    "wof:name":"Jung H., Versicherungsb\u00fcro",
    "wof:placetype":"venue"
},
  "geometry": {"coordinates":[8.4030809402,47.4033966064],"type":"Point"}
}