{
  "type": "Feature",
  "properties": {
    "iso:country":"CH",
    "sg:address":"Rue De L'avenir 2",
    "sg:city":"Corg\u00e9mont",
    "sg:orig_category":"Gartenbau",
    "sg:phone":"+41 17257715",
    "sg:postcode":"2606",
    "sg:province":"Bern",
    "wof:name":"Fink + Meienberger",
    "wof:placetype":"venue"
},
  "geometry": {"coordinates":[8.6055679321,47.2567596436],"type":"Point"}
}