{
  "type": "Feature",
  "properties": {
    "iso:country":"CH",
    "sg:address":"Erlenstrasse 1",
    "sg:city":"Rorschacherberg",
    "sg:orig_category":"Herstellung von Mess U Kontrollinstrumenten U vorrichtungen Mechanische Werkst\u00e4tten",
    "sg:phone":"+41 71 855 56 65",
    "sg:postcode":"9404",
    "sg:province":"St. Gallen",
    "wof:name":"Walter St\u00f6cklin Liwas Pr\u00e4zisions-mechanik",
    "wof:placetype":"venue"
},
  "geometry": {"coordinates":[9.5242891312,47.4759101868],"type":"Point"}
}