{
  "type": "Feature",
  "properties": {
    "addr:full":"Sonnenbergstrasse 37 Embrach Z\u00fcrich 8424",
    "addr:housenumber":"37",
    "addr:postcode":"8424",
    "addr:street":"Sonnenbergstrasse",
    "iso:country":"CH",
    "sg:address":"Sonnenbergstrasse 37",
    "sg:city":"Embrach",
    "sg:orig_category":"Architektur U Ingenieurb\u00fcros",
    "sg:phone":"+41 18651157",
    "sg:postcode":"8424",
    "sg:province":"Z\u00fcrich",
    "wof:name":"Bauberatungen, Holzbau-expertisen, Hans Etter",
    "wof:placetype":"venue"
},
  "geometry": {"coordinates":[8.60655,47.499203],"type":"Point"}
}