{
  "type": "Feature",
  "properties": {
    "iso:country":"CH",
    "sg:address":"Huebstrasse 10 8544 Rickenbach-attikon. Postfach",
    "sg:city":"Attikon",
    "sg:orig_category":"Instandhaltung U Reparatur von Automobilen",
    "sg:postcode":"8544",
    "sg:province":"Z\u00fcrich",
    "wof:name":"Raschle Ueli, Garage Autogarage",
    "wof:placetype":"venue"
},
  "geometry": {"coordinates":[8.797454834,47.5358734131],"type":"Point"}
}