{
  "type": "Feature",
  "properties": {
    "iso:country":"CH",
    "sg:address":"Z\u00fcrcherstrasse 15",
    "sg:city":"Basel",
    "sg:orig_category":"Planer f\u00fcr Energiekonzepte",
    "sg:phone":"+41 61 311 63 23",
    "sg:postcode":"4052",
    "sg:province":"Basel-Stadt",
    "wof:name":"Murat Kaya",
    "wof:placetype":"venue"
},
  "geometry": {"coordinates":[7.6068758965,47.5532836914],"type":"Point"}
}