{
  "type": "Feature",
  "properties": {
    "iso:country":"CH",
    "sg:address":"Hagenbuchstrasse 30c",
    "sg:city":"St.gallen",
    "sg:orig_category":"Herstellung von sonstiger Bekleidung U Bekleidungszubeh\u00f6r",
    "sg:postcode":"9000",
    "sg:province":"St. Gallen",
    "wof:name":"Mascanzoni R.",
    "wof:placetype":"venue"
},
  "geometry": {"coordinates":[9.3995513916,47.4296951294],"type":"Point"}
}