{
  "type": "Feature",
  "properties": {
    "addr:full":"Unterer Rheinweg 52 Basel Basel-Stadt 4057",
    "addr:housenumber":"52",
    "addr:postcode":"4057",
    "addr:street":"Unterer Rheinweg",
    "iso:country":"CH",
    "sg:address":"Unterer Rheinweg 52",
    "sg:city":"Basel",
    "sg:orig_category":"Arztpraxen",
    "sg:phone":"+41 61 683 22 91",
    "sg:postcode":"4057",
    "sg:province":"Basel-Stadt",
    "wof:name":"Prof.dr.med. B. Kellerhals Spezialarzt Fmh",
    "wof:placetype":"venue"
},
  "geometry": {"coordinates":[7.587716,47.564716],"type":"Point"}
}