{
  "type": "Feature",
  "properties": {
    "addr:full":"En Bovery C Collombey Valais 1868",
    "addr:postcode":"1868",
    "iso:country":"CH",
    "sg:address":"En Bovery C",
    "sg:city":"Collombey",
    "sg:classifiers":[
        {
            "category":"Manufacturing",
            "subcategory":"Motor Vehicles & Parts",
            "type":"Manufacturing & Wholesale Goods"
        }
    ],
    "sg:phone":"+41 24 472 74 72",
    "sg:postcode":"1868",
    "sg:province":"Valais",
    "sg:tags":[
        "body",
        "car",
        "fitting"
    ],
    "wof:name":"Dynamic Center",
    "wof:placetype":"venue"
},
  "geometry": {"coordinates":[6.945828,46.270473],"type":"Point"}
}