{
  "type": "Feature",
  "properties": {
    "iso:country":"CH",
    "sg:address":"Isenrietstr. 21",
    "sg:city":"M\u00f6nchaltorf",
    "sg:classifiers":[
        {
            "category":"Manufacturing",
            "subcategory":"Printing",
            "type":"Manufacturing & Wholesale Goods"
        }
    ],
    "sg:phone":"+41 4119494444",
    "sg:postcode":"8617",
    "sg:province":"Z\u00fcrich",
    "sg:tags":[
        "publishing"
    ],
    "wof:name":"Buchbinderei Burkhardt Ag",
    "wof:placetype":"venue"
},
  "geometry": {"coordinates":[8.7186222076,47.304058075],"type":"Point"}
}