{
  "type": "Feature",
  "properties": {
    "iso:country":"CH",
    "sg:address":"Bahnhofstrasse 82",
    "sg:city":"M\u00f6hlin",
    "sg:orig_category":"Sportvereine Turnen Vereine Damen",
    "sg:phone":"+41 61 851 30 41",
    "sg:postcode":"4313",
    "sg:province":"Aargau",
    "wof:name":"Turnverein Stv Zeiningen",
    "wof:placetype":"venue"
},
  "geometry": {"coordinates":[7.8449392319,47.5562019348],"type":"Point"}
}