{
  "type": "Feature",
  "properties": {
    "iso:country":"CH",
    "sg:address":"Aubrigstrasse 5",
    "sg:city":"Jona",
    "sg:orig_category":"Bauschreinerei Zimmerei, Dachdeckerei, Bauspenglerei U Abdichtung",
    "sg:phone":"+41 55 212 38 33",
    "sg:postcode":"8645",
    "sg:province":"St. Gallen",
    "wof:name":"Hansj\u00f6rg Ebinger Holzbau Zimmerei & Schreinerei",
    "wof:placetype":"venue"
},
  "geometry": {"coordinates":[8.83818,47.230526],"type":"Point"}
}