{
  "type": "Feature",
  "properties": {
    "iso:country":"CH",
    "sg:address":"Neumattstrasse 3",
    "sg:city":"Menziken",
    "sg:orig_category":"Pensionskassen",
    "sg:phone":"+41 62 771 17 15",
    "sg:postcode":"5737",
    "sg:province":"Aargau",
    "wof:name":"Personalf\u00fcrsorgestiftung Der Firma Fiechter Ag, Baugesch\u00e4ft, In Menziken",
    "wof:placetype":"venue"
},
  "geometry": {"coordinates":[8.1896247864,47.2381820679],"type":"Point"}
}