{
  "type": "Feature",
  "properties": {
    "iso:country":"CH",
    "sg:address":"Nordstrasse 5 4542 Luterbach. Postfach",
    "sg:city":"Luterbach",
    "sg:orig_category":"Unternehmensberatung Wirtschaftspr\u00fcfung, Steuerberatung U Treuhand",
    "sg:phone":"+41 32 681 30 70",
    "sg:postcode":"4542",
    "sg:province":"Solothurn",
    "wof:name":"Removisa Ag Unternehmens-& Steuerberatung",
    "wof:placetype":"venue"
},
  "geometry": {"coordinates":[7.578098774,47.2166862488],"type":"Point"}
}