{
  "type": "Feature",
  "properties": {
    "iso:country":"CH",
    "sg:address":"Flurstrasse 5",
    "sg:city":"Zizers",
    "sg:orig_category":"Grosshandel mit elektrischen Haushaltsger\u00e4ten, Radio U Fernsehger\u00e4ten",
    "sg:phone":"+41 81 322 48 56",
    "sg:postcode":"7205",
    "sg:province":"Graubunden",
    "wof:name":"Rensch Ag Bauelektrik",
    "wof:placetype":"venue"
},
  "geometry": {"coordinates":[9.5565099716,46.9349594116],"type":"Point"}
}