{
  "type": "Feature",
  "properties": {
    "iso:country":"CH",
    "sg:address":"Langwisstrasse 29 8126 Zumikon. Postfach",
    "sg:city":"Zumikon",
    "sg:orig_category":"Detailhandel mit Metallwaren, Anstrichmitteln, Glaswaren, Bau U Heimwerkerbedarf",
    "sg:phone":"+41 19180392",
    "sg:postcode":"8126",
    "sg:province":"Z\u00fcrich",
    "wof:name":"Ag Preisig Emil",
    "wof:placetype":"venue"
},
  "geometry": {"coordinates":[8.6377954483,47.3325614929],"type":"Point"}
}