{
  "type": "Feature",
  "properties": {
    "addr:full":"Quartier De La Verrerie 59 Moutier Bern 2740",
    "addr:housenumber":"59",
    "addr:postcode":"2740",
    "addr:street":"Quartier De La Verrerie;Bern",
    "iso:country":"CH",
    "sg:address":"Quartier De La Verrerie 59",
    "sg:city":"Moutier",
    "sg:classifiers":[
        {
            "category":"Professional",
            "subcategory":"Engineering",
            "type":"Services"
        }
    ],
    "sg:phone":"+41 32 493 64 14",
    "sg:postcode":"2740",
    "sg:province":"Bern",
    "sg:tags":[
        "machine",
        "breeding",
        "-",
        "animal",
        "mechanical"
    ],
    "wof:name":"Ksm Sa",
    "wof:placetype":"venue"
},
  "geometry": {"coordinates":[7.359412,47.26693],"type":"Point"}
}