{
  "type": "Feature",
  "properties": {
    "iso:country":"CH",
    "sg:address":"Champsec",
    "sg:city":"Verseg\u00e8res",
    "sg:orig_category":"Sanit\u00e4r U Heizungsinstallation Sanit\u00e4rinstallation",
    "sg:phone":"+41 41 497 47 01",
    "sg:postcode":"1947",
    "sg:province":"Valais",
    "wof:name":"Pius Baumgartner Heizung & Sanit\u00e4r",
    "wof:placetype":"venue"
},
  "geometry": {"coordinates":[8.1451807022,47.0359802246],"type":"Point"}
}