{
  "type": "Feature",
  "properties": {
    "iso:country":"CH",
    "sg:address":"Kantonsstrasse 81",
    "sg:city":"Reichenburg",
    "sg:orig_category":"G\u00fcterbef\u00f6rderung im Strassenverkehr",
    "sg:postcode":"8864",
    "sg:province":"Schwyz",
    "wof:name":"Sematrans Gmbh",
    "wof:placetype":"venue"
},
  "geometry": {"coordinates":[8.9830245972,47.1672058105],"type":"Point"}
}