{
  "type": "Feature",
  "properties": {
    "iso:country":"CH",
    "sg:address":"Bahnhofstrasse 24a 6312 Steinhausen. Postfach",
    "sg:city":"Steinhausen",
    "sg:orig_category":"Unclassifiable Establishments",
    "sg:phone":"+41 41 748 81 17",
    "sg:postcode":"6312",
    "sg:province":"Zug",
    "wof:name":"Im + Ex Jans Viktor Waren, Bes. Der Gastronomiebranche; Im- U. Export. Weinhandel",
    "wof:placetype":"venue"
},
  "geometry": {"coordinates":[8.4824752808,47.1967697144],"type":"Point"}
}