{
  "type": "Feature",
  "properties": {
    "iso:country":"CH",
    "sg:address":"Rue Des Moulins 51 2000 Neuch\u00e2tel. Postfach",
    "sg:city":"Neuch\u00e2tel",
    "sg:orig_category":"Herstellung von Duft U K\u00f6rperpflegemitteln P\u00e9dicure",
    "sg:phone":"+41 32 725 25 35",
    "sg:postcode":"2000",
    "sg:province":"Neuch\u00e2tel",
    "wof:name":"Uebersax Feroiu Anne - P\u00e9dicure-podologue",
    "wof:placetype":"venue"
},
  "geometry": {"coordinates":[6.927230835,46.9932136536],"type":"Point"}
}