{
  "type": "Feature",
  "properties": {
    "iso:country":"CH",
    "sg:address":"Graben 4",
    "sg:city":"Grindelwald",
    "sg:orig_category":"RESTAURANTS: TEA-ROOMS",
    "sg:phone":"+41 33 853 26 26",
    "sg:postcode":"3818",
    "sg:province":"Bern",
    "wof:name":"Restaurant Pfingstegg",
    "wof:placetype":"venue"
},
  "geometry": {"coordinates":[8.0447130203,46.6228141785],"type":"Point"}
}