{
  "type": "Feature",
  "properties": {
    "addr:full":"B\u00fcrenstrasse 5 Leuzigen Bern 3297",
    "addr:housenumber":"5",
    "addr:postcode":"3297",
    "addr:street":"Buerenstrasse",
    "iso:country":"CH",
    "sg:address":"B\u00fcrenstrasse 5",
    "sg:city":"Leuzigen",
    "sg:orig_category":"Allgemeiner Hoch U Tiefbau",
    "sg:phone":"+41 71 222 03 66",
    "sg:postcode":"3297",
    "sg:province":"Bern",
    "wof:name":"Kaufmann & Co",
    "wof:placetype":"venue"
},
  "geometry": {"coordinates":[9.366299,47.422737],"type":"Point"}
}