{
  "type": "Feature",
  "properties": {
    "iso:country":"CH",
    "sg:address":"4524",
    "sg:city":"G\u00fcnsberg",
    "sg:orig_category":"Vereine Musik/Blasmusik",
    "sg:postcode":"4524",
    "sg:province":"Solothurn",
    "wof:name":"Musikgesellschaft",
    "wof:placetype":"venue"
},
  "geometry": {"coordinates":[7.5764451027,47.2574691772],"type":"Point"}
}