{
  "type": "Feature",
  "properties": {
    "iso:country":"CH",
    "sg:address":"Ch\u00fceferistrasse 14",
    "sg:city":"Fehraltorf",
    "sg:orig_category":"Wirtschaftsverb\u00e4nde Landwirtschaft",
    "sg:phone":"+41 19550812",
    "sg:postcode":"8320",
    "sg:province":"Z\u00fcrich",
    "wof:name":"Pferdezuchtverband Arabische Mischrassen",
    "wof:placetype":"venue"
},
  "geometry": {"coordinates":[8.7539596558,47.3841629028],"type":"Point"}
}