{
  "type": "Feature",
  "properties": {
    "iso:country":"CH",
    "sg:address":"Marktgasse 11",
    "sg:city":"Olten",
    "sg:orig_category":"Sonstige Hilfs U Nebent\u00e4tigkeiten f\u00fcr die Schiffahrt",
    "sg:postcode":"4600",
    "sg:province":"Solothurn",
    "wof:name":"Bootshausgenossenschaft Sempachersee",
    "wof:placetype":"venue"
},
  "geometry": {"coordinates":[7.9042220116,47.3493003845],"type":"Point"}
}