{
  "type": "Feature",
  "properties": {
    "iso:country":"CH",
    "sg:address":"Bischofszeller Strasse",
    "sg:city":"Arnegg",
    "sg:orig_category":"Vorschulen, Kinderg\u00e4rten",
    "sg:phone":"+41 71 385 54 61",
    "sg:postcode":"9212",
    "sg:province":"St. Gallen",
    "wof:name":"Kindergarten",
    "wof:placetype":"venue"
},
  "geometry": {"coordinates":[9.2425947189,47.4195365906],"type":"Point"}
}