{
  "type": "Feature",
  "properties": {
    "iso:country":"CH",
    "sg:address":"Burstwiesenstrasse 62",
    "sg:city":"Z\u00fcrich",
    "sg:orig_category":"Vermietung U Verpachtung von eigenen Immobilien",
    "sg:phone":"+41 14634895",
    "sg:postcode":"8055",
    "sg:province":"Z\u00fcrich",
    "wof:name":"Immobilien-gesellschaft Gademann Z\u00fcrich Ag",
    "wof:placetype":"venue"
},
  "geometry": {"coordinates":[8.5036754608,47.3701705933],"type":"Point"}
}