{
  "type": "Feature",
  "properties": {
    "iso:country":"CH",
    "sg:address":"Im B\u00f6ndler 9",
    "sg:city":"Andelfingen",
    "sg:orig_category":"Grosshandel mit sonstigen Halbwaren",
    "sg:postcode":"8450",
    "sg:province":"Z\u00fcrich",
    "wof:name":"Riehle Verpackungen",
    "wof:placetype":"venue"
},
  "geometry": {"coordinates":[8.6761608124,47.5887413025],"type":"Point"}
}