{
  "type": "Feature",
  "properties": {
    "iso:country":"CH",
    "sg:address":"2908",
    "sg:city":"Grandfontaine",
    "sg:orig_category":"Bauschreinerei Herstellung von M\u00f6beln verschiedener Art",
    "sg:phone":"+41 32 476 66 82",
    "sg:postcode":"2908",
    "sg:province":"Jura",
    "wof:name":"Plumey Michel Sa",
    "wof:placetype":"venue"
},
  "geometry": {"coordinates":[6.939749,47.390862],"type":"Point"}
}