{
  "type": "Feature",
  "properties": {
    "iso:country":"CH",
    "sg:address":"1422",
    "sg:city":"Grandson",
    "sg:orig_category":"Verwertung von Milch",
    "sg:postcode":"1422",
    "sg:province":"Vaud",
    "wof:name":"Soci\u00e9t\u00e9 De Laiterie Des Tuileries De Grandson",
    "wof:placetype":"venue"
},
  "geometry": {"coordinates":[6.6459851265,46.8093681335],"type":"Point"}
}