{
  "type": "Feature",
  "properties": {
    "iso:country":"CH",
    "sg:address":"Bodenstrasse 11",
    "sg:city":"Wetzikon",
    "sg:classifiers":[
        {
            "category":"Health Services",
            "subcategory":"Medical Lab",
            "type":"Services"
        }
    ],
    "sg:phone":"+41 19302482",
    "sg:postcode":"8623",
    "sg:province":"Z\u00fcrich",
    "sg:tags":[
        "product",
        "diagnostic"
    ],
    "wof:name":"Farmed Spitalbedarf",
    "wof:placetype":"venue"
},
  "geometry": {"coordinates":[8.8102846146,47.3311386108],"type":"Point"}
}