{
  "type": "Feature",
  "properties": {
    "iso:country":"CH",
    "sg:address":"Gare Place De La 1510 Moudon Case Postale 102",
    "sg:city":"Moudon",
    "sg:orig_category":"Druckguss-Werke",
    "sg:phone":"+41 21 905 80 00",
    "sg:postcode":"1510",
    "sg:province":"Vaud",
    "wof:name":"Fonderie De Moudon Gisling Sa",
    "wof:placetype":"venue"
},
  "geometry": {"coordinates":[6.8003668785,46.6674957275],"type":"Point"}
}