{
  "type": "Feature",
  "properties": {
    "iso:country":"CH",
    "sg:address":"Bahnhofstrasse 14",
    "sg:city":"B\u00fcron",
    "sg:orig_category":"Nationale Postdienste",
    "sg:phone":"+41 41 933 24 44",
    "sg:postcode":"6233",
    "sg:province":"Luzern",
    "wof:name":"Die Schweizerische Post",
    "wof:placetype":"venue"
},
  "geometry": {"coordinates":[8.0926532745,47.2127952576],"type":"Point"}
}