{
  "type": "Feature",
  "properties": {
    "iso:country":"CH",
    "sg:address":"Rautistrasse 96",
    "sg:city":"Z\u00fcrich",
    "sg:orig_category":"Non-Classified Establishments",
    "sg:postcode":"8048",
    "sg:province":"Z\u00fcrich",
    "wof:name":"Netconstruction Gmbh",
    "wof:placetype":"venue"
},
  "geometry": {"coordinates":[8.4872598648,47.3826293945],"type":"Point"}
}