{
  "type": "Feature",
  "properties": {
    "iso:country":"CH",
    "sg:address":"L\u00e4rchenweg 9a",
    "sg:city":"Ormalingen",
    "sg:orig_category":"Architektur U Ingenieurb\u00fcros Architekturb\u00fcros",
    "sg:phone":"+41 32 323 29 29",
    "sg:postcode":"4466",
    "sg:province":"Basel-Landschaft",
    "wof:name":"Tschumi & Benoit Sa",
    "wof:placetype":"venue"
},
  "geometry": {"coordinates":[7.252883,47.136513],"type":"Point"}
}