{
  "type": "Feature",
  "properties": {
    "iso:country":"CH",
    "sg:address":"Grubenstrasse 12",
    "sg:city":"Langenthal",
    "sg:orig_category":"Reiseb\u00fcros",
    "sg:phone":"+41 62 919 19 00",
    "sg:postcode":"4900",
    "sg:province":"Bern",
    "wof:name":"Osst Reiseb\u00fcro",
    "wof:placetype":"venue"
},
  "geometry": {"coordinates":[7.7856302261,47.2207450867],"type":"Point"}
}