{
  "type": "Feature",
  "properties": {
    "iso:country":"CH",
    "sg:address":"Cropt Rue Du 20",
    "sg:city":"Bex",
    "sg:classifiers":[
        {
            "category":"Bars & Pubs",
            "type":"Food & Drink"
        }
    ],
    "sg:postcode":"1880",
    "sg:province":"Vaud",
    "wof:name":"Progin Marie-claude",
    "wof:placetype":"venue"
},
  "geometry": {"coordinates":[7.015681,46.250259],"type":"Point"}
}