{
  "type": "Feature",
  "properties": {
    "iso:country":"CH",
    "sg:address":"6945",
    "sg:city":"Origlio",
    "sg:orig_category":"Non-Classified Establishments",
    "sg:postcode":"6945",
    "sg:province":"Ticino",
    "wof:name":"Prema Foundation",
    "wof:placetype":"venue"
},
  "geometry": {"coordinates":[8.9459600449,46.0508499146],"type":"Point"}
}