{
  "type": "Feature",
  "properties": {
    "iso:country":"CH",
    "sg:address":"9428",
    "sg:city":"Walzenhausen",
    "sg:orig_category":"Interessenvertretungen U sonstige Vereinigungen",
    "sg:postcode":"9428",
    "sg:province":"Appenzell Ausserrhoden",
    "wof:name":"Gl.kant.rad-& Motorfahr.verb.",
    "wof:placetype":"venue"
},
  "geometry": {"coordinates":[9.6042127609,47.4506225586],"type":"Point"}
}