{
  "type": "Feature",
  "properties": {
    "iso:country":"CH",
    "sg:address":"Rambach Oberei",
    "sg:city":"S\u00fcderen",
    "sg:orig_category":"Detailhandel mit Getreide, Futtermitteln U Landesprodukten",
    "sg:phone":"+41 71 970 06 90",
    "sg:postcode":"3618",
    "sg:province":"Bern",
    "wof:name":"Fritz Pf\u00e4ndler Swiss Fritz Pferdefutter",
    "wof:placetype":"venue"
},
  "geometry": {"coordinates":[8.97514534,47.4672851562],"type":"Point"}
}