{
  "type": "Feature",
  "properties": {
    "iso:country":"CH",
    "sg:address":"Boissonnet Chemin De 77 1010 Lausanne. Postfach",
    "sg:city":"Lausanne",
    "sg:orig_category":"RESTAURANTS: TEA-ROOMS",
    "sg:postcode":"1010",
    "sg:province":"Vaud",
    "wof:name":"Auberge Sous Bois, Viso Manuel Caf\u00e9-restaurant-pizzeria",
    "wof:placetype":"venue"
},
  "geometry": {"coordinates":[6.6421818733,46.541217804],"type":"Point"}
}