{
  "type": "Feature",
  "properties": {
    "addr:full":"Rosenhaldenstrasse 5 Wangs St. Gallen 7323",
    "addr:housenumber":"5",
    "addr:postcode":"7323",
    "addr:street":"Rosenhaldenstrasse",
    "iso:country":"CH",
    "sg:address":"Rosenhaldenstrasse 5",
    "sg:city":"Wangs",
    "sg:orig_category":"Ausbaugewerbe",
    "sg:phone":"+41 81 723 46 17",
    "sg:postcode":"7323",
    "sg:province":"St. Gallen",
    "wof:name":"Gebr.meinrad & Peter Vesti Ofen-& Chemin\u00e9ebau",
    "wof:placetype":"venue"
},
  "geometry": {"coordinates":[9.429515,47.033577],"type":"Point"}
}