{
  "type": "Feature",
  "properties": {
    "iso:country":"CH",
    "sg:address":"Manno 6928 Manno. Postfach",
    "sg:city":"Manno",
    "sg:orig_category":"Grosshandel mit Erzen U Metallen",
    "sg:postcode":"6928",
    "sg:province":"Ticino",
    "wof:name":"Vasconi Sa",
    "wof:placetype":"venue"
},
  "geometry": {"coordinates":[8.9201698303,46.029838562],"type":"Point"}
}