{
  "type": "Feature",
  "properties": {
    "iso:country":"CH",
    "sg:address":"Via Giuseppe Motta 30",
    "sg:city":"Chiasso",
    "sg:orig_category":"Verwaltung von Immobilien",
    "sg:phone":"+41 91 682 45 09",
    "sg:postcode":"6830",
    "sg:province":"Ticino",
    "wof:name":"Nuovo Bar Di Frigerio Emiliano",
    "wof:placetype":"venue"
},
  "geometry": {"coordinates":[9.0291509628,45.8334999084],"type":"Point"}
}