{
  "type": "Feature",
  "properties": {
    "iso:country":"CH",
    "sg:address":"Hab\u00fcelstrasse 8",
    "sg:city":"Herrliberg",
    "sg:orig_category":"Detailhandel mit Metallwaren, Anstrichmitteln, Glaswaren, Bau U Heimwerkerbedarf",
    "sg:phone":"+41 19151142",
    "sg:postcode":"8704",
    "sg:province":"Z\u00fcrich",
    "wof:name":"Bright Light Showtechnik David Satz",
    "wof:placetype":"venue"
},
  "geometry": {"coordinates":[8.6166982651,47.2874526978],"type":"Point"}
}