{
  "type": "Feature",
  "properties": {
    "addr:full":"Voa Tgiern 12 7077 Valbella. Postfach Valbella Graubunden 7077",
    "addr:housenumber":"12",
    "addr:postcode":"7077 valbella. postfach;7077",
    "addr:street":"Voa Tgiern;Graubunden",
    "iso:country":"CH",
    "sg:address":"Voa Tgiern 12 7077 Valbella. Postfach",
    "sg:city":"Valbella",
    "sg:orig_category":"Architektur U Ingenieurb\u00fcros",
    "sg:postcode":"7077",
    "sg:province":"Graubunden",
    "wof:name":"Theus Tilla Dipl. Arch. Eth Sia Ag",
    "wof:placetype":"venue"
},
  "geometry": {"coordinates":[9.549621,46.751499],"type":"Point"}
}