{
  "type": "Feature",
  "properties": {
    "addr:full":"Gare Rue De La Domdidier Fribourg 1564",
    "addr:postcode":"1564",
    "addr:street":"Rue De La Domdidier",
    "iso:country":"CH",
    "sg:address":"Gare Rue De La",
    "sg:city":"Domdidier",
    "sg:orig_category":"Detailhandel mit B\u00fcchern, Zeitungen, Schreib U Papeteriewaren",
    "sg:phone":"+41 26 675 22 89",
    "sg:postcode":"1564",
    "sg:province":"Fribourg",
    "wof:name":"Kiosque De La Gare, Chardonnens Marianne",
    "wof:placetype":"venue"
},
  "geometry": {"coordinates":[7.015135,46.865307],"type":"Point"}
}