{
  "type": "Feature",
  "properties": {
    "iso:country":"CH",
    "sg:address":"Kirchackerstrasse 5a 8405 Seen. Postfach",
    "sg:city":"Winterthur",
    "sg:orig_category":"Satzherstellung U Reproduktion",
    "sg:phone":"+41 52 232 07 87",
    "sg:postcode":"8405",
    "sg:province":"Z\u00fcrich",
    "wof:name":"Desktopatelier Helbling Beatrice",
    "wof:placetype":"venue"
},
  "geometry": {"coordinates":[8.7647209167,47.4804039001],"type":"Point"}
}