{
  "type": "Feature",
  "properties": {
    "iso:country":"CH",
    "sg:address":"Hintergasse 4",
    "sg:city":"Arbon",
    "sg:orig_category":"Handelsvermittlung U Grosshandel",
    "sg:phone":"+41 71 446 15 11",
    "sg:postcode":"9320",
    "sg:province":"Thurgau",
    "wof:name":"Margrit Wolf Vertretungen Inneneinrichtung",
    "wof:placetype":"venue"
},
  "geometry": {"coordinates":[9.4348840714,47.5165023804],"type":"Point"}
}