{
  "type": "Feature",
  "properties": {
    "iso:country":"CH",
    "sg:address":"Rheinstrasse 28-32",
    "sg:city":"Augst",
    "sg:classifiers":[
        {
            "category":"Health Services",
            "subcategory":"Medical Lab",
            "type":"Services"
        }
    ],
    "sg:phone":"+41 61 811 62 22",
    "sg:postcode":"4302",
    "sg:province":"Basel-Landschaft",
    "sg:tags":[
        "laboratory",
        "bio-technology",
        "biological"
    ],
    "wof:name":"Bma Biomedicals Ag",
    "wof:placetype":"venue"
},
  "geometry": {"coordinates":[7.711254,47.535038],"type":"Point"}
}