{
  "type": "Feature",
  "properties": {
    "addr:full":"6818 Melano Ticino 6818",
    "addr:postcode":"6818;6818",
    "iso:country":"CH",
    "sg:address":"6818",
    "sg:city":"Melano",
    "sg:orig_category":"Campingpl\u00e4tze Detailhandel mit Zeitungen U Zeitschriften Kioske",
    "sg:phone":"+41 91 648 28 63",
    "sg:postcode":"6818",
    "sg:province":"Ticino",
    "wof:name":"Camping Paradiso-lago Melano Sagl",
    "wof:placetype":"venue"
},
  "geometry": {"coordinates":[8.99245,45.921951],"type":"Point"}
}