{
  "type": "Feature",
  "properties": {
    "iso:country":"CH",
    "sg:address":"8926",
    "sg:city":"Uerzlikon",
    "sg:orig_category":"Vorschulen, Kinderg\u00e4rten",
    "sg:phone":"+41 14930288",
    "sg:postcode":"8926",
    "sg:province":"Z\u00fcrich",
    "wof:name":"Kindergarten Uitikon-waldegg",
    "wof:placetype":"venue"
},
  "geometry": {"coordinates":[8.4512519836,47.3729820251],"type":"Point"}
}