{
  "type": "Feature",
  "properties": {
    "iso:country":"CH",
    "sg:address":"Aegeristrasse 24",
    "sg:city":"Baar",
    "sg:orig_category":"Grosshandel mit lebenden Tieren",
    "sg:phone":"+41 41 870 26 30",
    "sg:postcode":"6340",
    "sg:province":"Zug",
    "wof:name":"Arnold Franz",
    "wof:placetype":"venue"
},
  "geometry": {"coordinates":[8.6738700867,46.8778190613],"type":"Point"}
}