{
  "type": "Feature",
  "properties": {
    "iso:country":"CH",
    "sg:address":"Gestadeckplatz 2 4000 Basel. Postfach",
    "sg:city":"Liestal",
    "sg:orig_category":"Pensionskassen",
    "sg:phone":"+41 71773333",
    "sg:postcode":"4410",
    "sg:province":"Basel-Landschaft",
    "wof:name":"Personalvorsorgestiftung Der Betriebe Erb Centralgarage Ag, St. Gallen Und Erb H. Ag Automobile St. Gallen",
    "wof:placetype":"venue"
},
  "geometry": {"coordinates":[9.3363304138,47.4099197388],"type":"Point"}
}