{
  "type": "Feature",
  "properties": {
    "iso:country":"CH",
    "sg:address":"Landstrasse 55 5430 Wettingen. Postfach",
    "sg:city":"Wettingen",
    "sg:orig_category":"Herstellung von Elektromotoren, Generatoren U Transformatoren",
    "sg:postcode":"5430",
    "sg:province":"Aargau",
    "wof:name":"Burkhalter Ernst Ing. Ag, Zweigniederlassung Wettingen",
    "wof:placetype":"venue"
},
  "geometry": {"coordinates":[8.3226356506,47.4676856995],"type":"Point"}
}