{
  "type": "Feature",
  "properties": {
    "iso:country":"CH",
    "sg:address":"St. Johanns-vorstadt 3",
    "sg:city":"Basel",
    "sg:classifiers":[
        {
            "category":"Professional",
            "subcategory":"Art Services",
            "type":"Services"
        }
    ],
    "sg:phone":"+41 61 261 16 46",
    "sg:postcode":"4056",
    "sg:province":"Basel-Stadt",
    "sg:tags":[
        "homepage",
        "designing"
    ],
    "wof:name":"K-webs Internet Network",
    "wof:placetype":"venue"
},
  "geometry": {"coordinates":[7.5849490166,47.5626373291],"type":"Point"}
}