{
  "type": "Feature",
  "properties": {
    "iso:country":"CH",
    "sg:address":"1350",
    "sg:city":"Orbe",
    "sg:orig_category":"Herstellung von Industriegasen",
    "sg:phone":"+41 24 441 31 33",
    "sg:postcode":"1350",
    "sg:province":"Vaud",
    "wof:name":"Urbagaz Soci\u00e9t\u00e9 Anonyme De Distribution Du Gaz Naturel Pour Le District Et La R\u00e9gion D'orbe",
    "wof:placetype":"venue"
},
  "geometry": {"coordinates":[6.5309619904,46.7247772217],"type":"Point"}
}