{
  "type": "Feature",
  "properties": {
    "iso:country":"CH",
    "sg:address":"M\u00fchlemoosstrasse 1",
    "sg:city":"Tuggen",
    "sg:orig_category":"Detailhandel mit Getr\u00e4nken Grosshandel mit Getr\u00e4nken",
    "sg:phone":"+41 55 445 14 69",
    "sg:postcode":"8856",
    "sg:province":"Schwyz",
    "wof:name":"Getr\u00e4nke Huber Ag",
    "wof:placetype":"venue"
},
  "geometry": {"coordinates":[8.9493761063,47.2030906677],"type":"Point"}
}