{
  "type": "Feature",
  "properties": {
    "iso:country":"CH",
    "sg:address":"Sur La C\u00f4te 54k",
    "sg:city":"Courtedoux",
    "sg:orig_category":"Sanit\u00e4r, Heizungs U L\u00fcftungsinstallation",
    "sg:phone":"+41 32 466 49 86",
    "sg:postcode":"2905",
    "sg:province":"Jura",
    "wof:name":"Salomon Yves Sa",
    "wof:placetype":"venue"
},
  "geometry": {"coordinates":[7.0396170616,47.4067306519],"type":"Point"}
}