{
  "type": "Feature",
  "properties": {
    "iso:country":"CH",
    "sg:address":"Bernstrasse 3 3506 Grossh\u00f6chstetten. Postfach",
    "sg:city":"Grossh\u00f6chstetten",
    "sg:orig_category":"Unternehmensberatung",
    "sg:phone":"+41 79 311 05 79",
    "sg:postcode":"3506",
    "sg:province":"Bern",
    "wof:name":"Fritz Haari Gmbh",
    "wof:placetype":"venue"
},
  "geometry": {"coordinates":[7.9618401527,46.7377815247],"type":"Point"}
}