{
  "type": "Feature",
  "properties": {
    "iso:country":"CH",
    "sg:address":"Untere Bahnhofstr. 7",
    "sg:city":"Rapperswil",
    "sg:classifiers":[
        {
            "category":"Banks & Credit Unions",
            "subcategory":"Bank",
            "type":"Services"
        }
    ],
    "sg:phone":"+41 55 222 74 11",
    "sg:postcode":"8640",
    "sg:province":"Schwyz",
    "wof:name":"St. Gallische, Kantonalbank",
    "wof:placetype":"venue"
},
  "geometry": {"coordinates":[8.817088,47.225422],"type":"Point"}
}