{
  "type": "Feature",
  "properties": {
    "iso:country":"CH",
    "sg:address":"Bahnhofplatz 1",
    "sg:city":"Biel/bienne",
    "sg:classifiers":[
        {
            "category":"Restaurant",
            "type":"Food & Drink"
        }
    ],
    "sg:phone":"+41 32 322 78 98",
    "sg:postcode":"2502",
    "sg:province":"Bern",
    "wof:name":"Restaurant Urania",
    "wof:placetype":"venue"
},
  "geometry": {"coordinates":[7.2419171333,47.1340026855],"type":"Point"}
}