{
  "type": "Feature",
  "properties": {
    "iso:country":"CH",
    "sg:address":"Route Des Daillettes 21 1700 Fribourg. Postfach",
    "sg:city":"Fribourg",
    "sg:orig_category":"Revision Steuerberatung",
    "sg:postcode":"1701",
    "sg:province":"Fribourg",
    "wof:name":"Kpmg Fides Wirtschaftspr\u00fcfung U. Beratung",
    "wof:placetype":"venue"
},
  "geometry": {"coordinates":[7.1462688446,46.7925186157],"type":"Point"}
}