{
  "type": "Feature",
  "properties": {
    "iso:country":"CH",
    "sg:address":"Stein\u00e4cker 3",
    "sg:city":"Rupperswil",
    "sg:orig_category":"Sportvereine Turnen",
    "sg:phone":"+41 62 897 04 63",
    "sg:postcode":"5102",
    "sg:province":"Aargau",
    "wof:name":"Turnverein Stv Rupperswil",
    "wof:placetype":"venue"
},
  "geometry": {"coordinates":[8.1251726151,47.3980522156],"type":"Point"}
}