{
  "type": "Feature",
  "properties": {
    "iso:country":"CH",
    "sg:address":"Unterdorf 95",
    "sg:city":"Ramsen",
    "sg:orig_category":"Maurerarbeiten Stukkateurgewerbe, Gipserei U Verputzerei",
    "sg:phone":"+41 52 743 15 94",
    "sg:postcode":"8262",
    "sg:province":"Schaffhausen",
    "wof:name":"Franz Baumgartner Gipser-& Maurergesch\u00e4ft",
    "wof:placetype":"venue"
},
  "geometry": {"coordinates":[8.8121442795,47.7063407898],"type":"Point"}
}