{
  "type": "Feature",
  "properties": {
    "iso:country":"CH",
    "sg:address":"Schnaihalde 51 8455 R\u00fcdlingen. Postfach",
    "sg:city":"R\u00fcdlingen",
    "sg:orig_category":"Herstellung von Konstruktionsteilen, Fertigbauteilen U Ausbauelementen aus Holz",
    "sg:phone":"+41 18672975",
    "sg:postcode":"8455",
    "sg:province":"Schaffhausen",
    "wof:name":"W\u00fcrsten Daniel Gmbh Leistungen Im Baugewerbe, Bes. Im Schreinereigewerbe Usw.",
    "wof:placetype":"venue"
},
  "geometry": {"coordinates":[8.5718898773,47.5799064636],"type":"Point"}
}