{
  "type": "Feature",
  "properties": {
    "iso:country":"CH",
    "sg:address":"Pr\u00e9-fontaine 100",
    "sg:city":"Crissier",
    "sg:orig_category":"Sportvereine Ballsport Handball",
    "sg:phone":"+41 21 635 01 51",
    "sg:postcode":"1023",
    "sg:province":"Vaud",
    "wof:name":"Hbc Chavannes",
    "wof:placetype":"venue"
},
  "geometry": {"coordinates":[6.5769290924,46.5455131531],"type":"Point"}
}