{
  "type": "Feature",
  "properties": {
    "iso:country":"CH",
    "sg:address":"7166",
    "sg:city":"Trun",
    "sg:orig_category":"Kantonalbanken",
    "sg:phone":"+41 81 943 16 07",
    "sg:postcode":"7166",
    "sg:province":"Graubunden",
    "wof:name":"Graub\u00fcndner Kantonalbank",
    "wof:placetype":"venue"
},
  "geometry": {"coordinates":[8.9906148911,46.743106842],"type":"Point"}
}