{
  "type": "Feature",
  "properties": {
    "iso:country":"CH",
    "sg:address":"Place De La Planta",
    "sg:city":"Sion",
    "sg:orig_category":"Verkehrs- and Tourismusb\u00fcros",
    "sg:phone":"+41 24 492 33 58",
    "sg:postcode":"1950",
    "sg:province":"Valais",
    "wof:name":"Office Du Tourisme Des Diablerets",
    "wof:placetype":"venue"
},
  "geometry": {"coordinates":[7.1587100029,46.3500404358],"type":"Point"}
}