{
  "type": "Feature",
  "properties": {
    "iso:country":"CH",
    "sg:address":"Kantonsstrasse 53",
    "sg:city":"Horw",
    "sg:classifiers":[
        {
            "category":"Restaurant",
            "type":"Food & Drink"
        }
    ],
    "sg:phone":"+41 41 342 07 95",
    "sg:postcode":"6048",
    "sg:province":"Luzern",
    "wof:name":"Restaurant Zentrum",
    "wof:placetype":"venue"
},
  "geometry": {"coordinates":[8.3099594116,47.0222358704],"type":"Point"}
}