{
  "type": "Feature",
  "properties": {
    "iso:country":"CH",
    "sg:address":"Elvezia Corso 7",
    "sg:city":"Lugano",
    "sg:orig_category":"Gemischte Landwirtschaft",
    "sg:postcode":"6900",
    "sg:province":"Ticino",
    "wof:name":"Bl\u00f6chlinger-wyss Susanne Landwirtschaftsbetrieb. Landwirtschaftliche Produkte; Herstellung U. Vermarktung. Lohnarbeiten Usw",
    "wof:placetype":"venue"
},
  "geometry": {"coordinates":[9.510140419,46.9800758362],"type":"Point"}
}