{
  "type": "Feature",
  "properties": {
    "iso:country":"CH",
    "sg:address":"Rue De Tr\u00e9velin 4",
    "sg:city":"Aubonne",
    "sg:orig_category":"Schlankheitsinstitute",
    "sg:phone":"+41 21 808 61 38",
    "sg:postcode":"1170",
    "sg:province":"Vaud",
    "wof:name":"Nicole Bussard Salon De Coiffure",
    "wof:placetype":"venue"
},
  "geometry": {"coordinates":[6.3914952278,46.4948616028],"type":"Point"}
}