{
  "type": "Feature",
  "properties": {
    "iso:country":"CH",
    "sg:address":"Kirchstrasse 17",
    "sg:city":"Glarus",
    "sg:orig_category":"Architektur U Ingenieurb\u00fcros",
    "sg:phone":"+41 55 640 48 41",
    "sg:postcode":"8750",
    "sg:province":"Glarus",
    "wof:name":"Ingenieurb\u00fcro Runge Ag",
    "wof:placetype":"venue"
},
  "geometry": {"coordinates":[9.067223,47.040771],"type":"Point"}
}