{
  "type": "Feature",
  "properties": {
    "iso:country":"CH",
    "sg:address":"Grand-rue 13",
    "sg:city":"Lutry",
    "sg:orig_category":"RESTAURANTS: TEA-ROOMS",
    "sg:phone":"+41 21 791 47 23",
    "sg:postcode":"1095",
    "sg:province":"Vaud",
    "wof:name":"Bar \u00e0 Caf\u00e9 Le Kiwi",
    "wof:placetype":"venue"
},
  "geometry": {"coordinates":[6.6846461296,46.5026664734],"type":"Point"}
}