{
  "type": "Feature",
  "properties": {
    "iso:country":"CH",
    "sg:address":"1933",
    "sg:city":"Sembrancher",
    "sg:orig_category":"Unclassifiable Establishments",
    "sg:phone":"+41 27 785 14 89",
    "sg:postcode":"1933",
    "sg:province":"Valais",
    "wof:name":"Exquis Et Luy",
    "wof:placetype":"venue"
},
  "geometry": {"coordinates":[7.1504249573,46.0785903931],"type":"Point"}
}