{
  "type": "Feature",
  "properties": {
    "iso:country":"CH",
    "sg:address":"Herrengasse 17 6430 Schwyz. Postfach 253",
    "sg:city":"Schwyz",
    "sg:orig_category":"Gemeindeverwaltungen",
    "sg:phone":"+41 55 647 30 00",
    "sg:postcode":"6431",
    "sg:province":"Schwyz",
    "wof:name":"Gemeindeverwaltung Schw\u00e4ndi Bei Schwanden",
    "wof:placetype":"venue"
},
  "geometry": {"coordinates":[9.0660219193,47.0060691833],"type":"Point"}
}