{
  "type": "Feature",
  "properties": {
    "iso:country":"CH",
    "sg:address":"Gummweg 99",
    "sg:city":"Steffisburg",
    "sg:orig_category":"Detailhandel mit Beleuchtungs U Haushaltsgegenst\u00e4nden Herstellung von sonstigen elektrischen Ausr\u00fcst",
    "sg:phone":"+41 33 437 14 84",
    "sg:postcode":"3612",
    "sg:province":"Bern",
    "wof:name":"Ela-service Elektroapparate-service",
    "wof:placetype":"venue"
},
  "geometry": {"coordinates":[7.63681,46.778961],"type":"Point"}
}