{
  "type": "Feature",
  "properties": {
    "addr:full":"Route Des Molards 6 Russin Gen\u00e8ve 1281",
    "addr:housenumber":"6",
    "addr:postcode":"1281",
    "addr:street":"Route Des Molards",
    "iso:country":"CH",
    "sg:address":"Route Des Molards 6",
    "sg:city":"Russin",
    "sg:orig_category":"Detailhandel mit Antiquit\u00e4ten Detailhandel mit Beleuchtungs U Haushaltsgegenst\u00e4nden",
    "sg:phone":"+41 22 754 12 32",
    "sg:postcode":"1281",
    "sg:province":"Gen\u00e8ve",
    "wof:name":"La Lampisterie Luminaires & Antiquit\u00e9s",
    "wof:placetype":"venue"
},
  "geometry": {"coordinates":[6.01262,46.188171],"type":"Point"}
}