{
  "type": "Feature",
  "properties": {
    "iso:country":"CH",
    "sg:address":"Feldbergstrasse 51",
    "sg:city":"Basel",
    "sg:orig_category":"RESTAURANTS: TEA-ROOMS",
    "sg:postcode":"4057",
    "sg:province":"Basel-Stadt",
    "wof:name":"Agora, Fatma Ulupinar-sevi",
    "wof:placetype":"venue"
},
  "geometry": {"coordinates":[7.591173172,47.5664291382],"type":"Point"}
}