{
  "type": "Feature",
  "properties": {
    "iso:country":"CH",
    "sg:address":"B\u00e4lliz 16",
    "sg:city":"Thun",
    "sg:orig_category":"Arztpraxen",
    "sg:phone":"+41 33 223 25 00",
    "sg:postcode":"3600",
    "sg:province":"Bern",
    "wof:name":"Dr.med.stephan Michael Engler Spezialarzt Fmh",
    "wof:placetype":"venue"
},
  "geometry": {"coordinates":[7.626491,46.759556],"type":"Point"}
}