{
  "type": "Feature",
  "properties": {
    "iso:country":"CH",
    "sg:address":"Fuchsacker 678",
    "sg:city":"Lutzenberg",
    "sg:orig_category":"Reiseb\u00fcros U Reiseveranstalter",
    "sg:postcode":"9426",
    "sg:province":"Appenzell Ausserrhoden",
    "wof:name":"3 Plus Gmbh",
    "wof:placetype":"venue"
},
  "geometry": {"coordinates":[9.575750351,47.4594497681],"type":"Point"}
}