{
  "type": "Feature",
  "properties": {
    "iso:country":"CH",
    "sg:address":"Chemin Jules-edouard-gottret 6",
    "sg:city":"Veyrier",
    "sg:orig_category":"G\u00fcterbef\u00f6rderung im Strassenverkehr",
    "sg:phone":"+41 22 784 14 03",
    "sg:postcode":"1255",
    "sg:province":"Gen\u00e8ve",
    "wof:name":"Georges Lugrin Transports",
    "wof:placetype":"venue"
},
  "geometry": {"coordinates":[6.185379982,46.1666374207],"type":"Point"}
}