{
  "type": "Feature",
  "properties": {
    "iso:country":"CH",
    "sg:address":"Via Francesco Soave 9 6830 Chiasso. Postfach Caselle Postale 420",
    "sg:city":"Chiasso",
    "sg:orig_category":"Technische, physikalische U chemische Untersuchung",
    "sg:phone":"+41 91 682 83 53",
    "sg:postcode":"6830",
    "sg:province":"Ticino",
    "wof:name":"Rinaldo Kaestner",
    "wof:placetype":"venue"
},
  "geometry": {"coordinates":[9.0299186707,45.8372154236],"type":"Point"}
}