{
  "type": "Feature",
  "properties": {
    "iso:country":"CH",
    "sg:address":"D\u00f6rflistrasse 4",
    "sg:city":"Z\u00fcrich",
    "sg:classifiers":[
        {
            "category":"Autos & Motor Vehicles",
            "subcategory":"Auto Supplies",
            "type":"Retail Goods"
        }
    ],
    "sg:phone":"+41 13126151",
    "sg:postcode":"8057",
    "sg:province":"Z\u00fcrich",
    "sg:tags":[
        "lining",
        "brake"
    ],
    "wof:name":"Hirschgarten-garage",
    "wof:placetype":"venue"
},
  "geometry": {"coordinates":[8.548659,47.403618],"type":"Point"}
}