{
  "type": "Feature",
  "properties": {
    "iso:country":"CH",
    "sg:address":"Weiermattstrasse 2/11",
    "sg:city":"Liestal",
    "sg:orig_category":"Unternehmensberatung",
    "sg:phone":"+41 61 902 13 30",
    "sg:postcode":"4410",
    "sg:province":"Basel-Landschaft",
    "wof:name":"Proserv Gmbh",
    "wof:placetype":"venue"
},
  "geometry": {"coordinates":[7.7252011299,47.4951324463],"type":"Point"}
}