{
  "type": "Feature",
  "properties": {
    "iso:country":"CH",
    "sg:address":"Grand Rue 14",
    "sg:city":"Estavayer-le-lac",
    "sg:orig_category":"Detailhandel mit Bekleidung Detailhandel mit Damenbekleidung",
    "sg:phone":"+41 26 663 10 58",
    "sg:postcode":"1470",
    "sg:province":"Fribourg",
    "wof:name":"Bernet Bernadette, Nouveaut\u00e9s",
    "wof:placetype":"venue"
},
  "geometry": {"coordinates":[6.84798,46.849102],"type":"Point"}
}