{
  "type": "Feature",
  "properties": {
    "iso:country":"CH",
    "sg:address":"Mouline Rue De La 22 1022 Chavannes-renens. Postfach",
    "sg:city":"Chavannes-renens",
    "sg:orig_category":"Erschliessung von Grundst\u00fccken",
    "sg:phone":"+41 21 691 99 00",
    "sg:postcode":"1022",
    "sg:province":"Vaud",
    "wof:name":"Coop\u00e9rative Immobili\u00e8re Du Personnel F\u00e9d\u00e9ral Cipef",
    "wof:placetype":"venue"
},
  "geometry": {"coordinates":[6.5772900581,46.5327987671],"type":"Point"}
}