{
  "type": "Feature",
  "properties": {
    "iso:country":"CH",
    "sg:address":"Thurtalstrasse 19 8478 Thalheim. Postfach",
    "sg:city":"Thalheim",
    "sg:orig_category":"Finanzierungsinstitutionen",
    "sg:postcode":"8478",
    "sg:province":"Z\u00fcrich",
    "wof:name":"Finanzteam Gmbh",
    "wof:placetype":"venue"
},
  "geometry": {"coordinates":[8.753947258,47.5787620544],"type":"Point"}
}