{
  "type": "Feature",
  "properties": {
    "iso:country":"CH",
    "sg:address":"Im Steinenm\u00fcller 4",
    "sg:city":"M\u00fcnchenstein",
    "sg:orig_category":"Public-Relations-Agenturen Werbung",
    "sg:phone":"+41 61 413 13 60",
    "sg:postcode":"4142",
    "sg:province":"Basel-Landschaft",
    "wof:name":"Lemon Marketing & Werbung Gmbh",
    "wof:placetype":"venue"
},
  "geometry": {"coordinates":[7.6109862328,47.5241165161],"type":"Point"}
}