{
  "type": "Feature",
  "properties": {
    "iso:country":"CH",
    "sg:address":"Unterer Mattenweg 47",
    "sg:city":"Zermatt",
    "sg:orig_category":"HOTELS: OHNE RESTAURANT",
    "sg:phone":"+41 27 957 12 52",
    "sg:postcode":"3920",
    "sg:province":"Valais",
    "wof:name":"Hotel Condor",
    "wof:placetype":"venue"
},
  "geometry": {"coordinates":[7.933672905,46.1117172241],"type":"Point"}
}