{
  "type": "Feature",
  "properties": {
    "iso:country":"CH",
    "sg:address":"Via Debarcadero",
    "sg:city":"Brissago",
    "sg:orig_category":"Zoll- and Grenzb\u00fcros",
    "sg:phone":"+41 91 793 12 36",
    "sg:postcode":"6614",
    "sg:province":"Ticino",
    "wof:name":"Dogana Svizzera Lago",
    "wof:placetype":"venue"
},
  "geometry": {"coordinates":[8.7090625763,46.117729187],"type":"Point"}
}