{
  "type": "Feature",
  "properties": {
    "iso:country":"CH",
    "sg:address":"Usterstrasse 4",
    "sg:city":"Volketswil",
    "sg:orig_category":"Saunas, Solarien, Fitnesszentren U \u00e4hnliches",
    "sg:phone":"+41 19461380",
    "sg:postcode":"8604",
    "sg:province":"Z\u00fcrich",
    "wof:name":"Sauna Am Chappeli",
    "wof:placetype":"venue"
},
  "geometry": {"coordinates":[8.674489975,47.3892669678],"type":"Point"}
}