{
  "type": "Feature",
  "properties": {
    "iso:country":"CH",
    "sg:address":"Les Maisons-neuves",
    "sg:city":"Yvorne",
    "sg:orig_category":"Arztpraxen",
    "sg:phone":"+41 24 466 30 51",
    "sg:postcode":"1853",
    "sg:province":"Vaud",
    "wof:name":"Dr M\u00e9d. Jean-fran\u00e7ois Anex M\u00e9decin G\u00e9n\u00e9raliste Fmh",
    "wof:placetype":"venue"
},
  "geometry": {"coordinates":[6.959228,46.330917],"type":"Point"}
}