{
  "type": "Feature",
  "properties": {
    "iso:country":"CH",
    "sg:address":"Viale Villa Foresta 18",
    "sg:city":"Mendrisio",
    "sg:orig_category":"Grosshandel mit pharmazeutischen Erzeugnissen Herstellung von medizinischen U chirurgischen Ger\u00e4ten ",
    "sg:phone":"+41 79 444 20 51",
    "sg:postcode":"6850",
    "sg:province":"Ticino",
    "wof:name":"Thp Sagl",
    "wof:placetype":"venue"
},
  "geometry": {"coordinates":[8.9819602966,45.8623504639],"type":"Point"}
}