{
  "type": "Feature",
  "properties": {
    "iso:country":"CH",
    "sg:address":"Le Daillard",
    "sg:city":"Lignerolle",
    "sg:orig_category":"Herstellung von Metallkonstruktionen",
    "sg:phone":"+41 24 441 92 81",
    "sg:postcode":"1357",
    "sg:province":"Vaud",
    "wof:name":"Jean-jacques Belin Ferronnerie D'art",
    "wof:placetype":"venue"
},
  "geometry": {"coordinates":[6.4356131554,46.7345619202],"type":"Point"}
}