{
  "type": "Feature",
  "properties": {
    "iso:country":"CH",
    "sg:address":"Buechacherweg 11",
    "sg:city":"Gutenswil",
    "sg:orig_category":"Tierheime",
    "sg:phone":"+41 19455250",
    "sg:postcode":"8605",
    "sg:province":"Z\u00fcrich",
    "wof:name":"Dr. Med. Vet. Renate Schr\u00f6ter Tier\u00e4rztin",
    "wof:placetype":"venue"
},
  "geometry": {"coordinates":[8.715924263,47.3870506287],"type":"Point"}
}