{
  "type": "Feature",
  "properties": {
    "iso:country":"CH",
    "sg:address":"Avenue De La Gare 20 1950 Sion Case Postale 677",
    "sg:city":"Sion",
    "sg:orig_category":"Sonstiges Versicherungsgewerbe",
    "sg:phone":"+41 27 327 52 52",
    "sg:postcode":"1951",
    "sg:province":"Valais",
    "wof:name":"Mutuelle Valaisanne Caisse-maladie",
    "wof:placetype":"venue"
},
  "geometry": {"coordinates":[7.3584132195,46.2301025391],"type":"Point"}
}