{
  "type": "Feature",
  "properties": {
    "iso:country":"CH",
    "sg:address":"Riedmattstrasse 4 4500 Solothurn. Postfach 304",
    "sg:city":"Solothurn",
    "sg:orig_category":"Detailhandel mit Bekleidung Detailhandel mit Waren verschiedener Art, Hauptrichtung Nahrungsmittel",
    "sg:postcode":"4501",
    "sg:province":"Solothurn",
    "wof:name":"Hanf-rad Rolf Gasser",
    "wof:placetype":"venue"
},
  "geometry": {"coordinates":[7.522412,47.20462],"type":"Point"}
}