{
  "type": "Feature",
  "properties": {
    "iso:country":"CH",
    "sg:address":"Chemin Du Saux 4",
    "sg:city":"Mont-sur-lausanne",
    "sg:orig_category":"Ausbaugewerbe",
    "sg:postcode":"1052",
    "sg:province":"Vaud",
    "wof:name":"Cbm Chemin\u00e9es Barbecues, Martin B\u00e9atrice.",
    "wof:placetype":"venue"
},
  "geometry": {"coordinates":[6.636549,46.549843],"type":"Point"}
}