{
  "type": "Feature",
  "properties": {
    "iso:country":"CH",
    "sg:address":"Bahnhofstrasse 35a",
    "sg:city":"Kreuzlingen",
    "sg:orig_category":"Erbringung von Dienstleistungen f\u00fcr Unternehmen",
    "sg:postcode":"8280",
    "sg:province":"Thurgau",
    "wof:name":"Fila Design",
    "wof:placetype":"venue"
},
  "geometry": {"coordinates":[9.1672954559,47.6527023315],"type":"Point"}
}