{
  "type": "Feature",
  "properties": {
    "iso:country":"CH",
    "sg:address":"Porcelaine Rue De La 13",
    "sg:city":"Nyon",
    "sg:classifiers":[
        {
            "category":"Travel",
            "subcategory":"Hotels & Motels",
            "type":"Entertainment"
        }
    ],
    "sg:postcode":"1260",
    "sg:province":"Vaud",
    "sg:tags":[
        "hotels",
        "mit",
        "restaurant"
    ],
    "wof:name":"Lambiscott Sa",
    "wof:placetype":"venue"
},
  "geometry": {"coordinates":[6.2422480583,46.3837432861],"type":"Point"}
}