{
  "type": "Feature",
  "properties": {
    "iso:country":"CH",
    "sg:address":"Mittlere Strasse 69",
    "sg:city":"Basel",
    "sg:orig_category":"Sonstige mit der Informatik verbundene T\u00e4tigkeiten",
    "sg:phone":"+41 31 302 11 78",
    "sg:postcode":"4056",
    "sg:province":"Basel-Stadt",
    "wof:name":"Schmid Dr. Hans, Edv-beratungen",
    "wof:placetype":"venue"
},
  "geometry": {"coordinates":[7.4247078896,46.9764404297],"type":"Point"}
}