{
  "type": "Feature",
  "properties": {
    "iso:country":"CH",
    "sg:address":"Corso San Gottardo 54c",
    "sg:city":"Chiasso",
    "sg:orig_category":"Autotransporte international",
    "sg:phone":"+41 71 747 44 66",
    "sg:postcode":"6830",
    "sg:province":"Ticino",
    "wof:name":"Dachser Spedition Ag",
    "wof:placetype":"venue"
},
  "geometry": {"coordinates":[9.641239,47.451584],"type":"Point"}
}