{
  "type": "Feature",
  "properties": {
    "iso:country":"CH",
    "sg:address":"Bahnhofstrasse 12",
    "sg:city":"Turgi",
    "sg:orig_category":"Detailhandel mit Blumen U Pflanzen Fachdetailhandel in Verkaufsr\u00e4umen",
    "sg:phone":"+41 56 223 12 38",
    "sg:postcode":"5300",
    "sg:province":"Aargau",
    "wof:name":"Blumenhaus Monika Bill",
    "wof:placetype":"venue"
},
  "geometry": {"coordinates":[8.253137,47.493004],"type":"Point"}
}