{
  "type": "Feature",
  "properties": {
    "addr:full":"Baselstrasse 60 Arlesheim Basel-Landschaft 4144",
    "addr:housenumber":"60",
    "addr:postcode":"4144",
    "addr:street":"Baselstrasse",
    "iso:country":"CH",
    "sg:address":"Baselstrasse 60",
    "sg:city":"Arlesheim",
    "sg:orig_category":"Arbeitnehmerverb\u00e4nde",
    "sg:phone":"+41 61 701 43 27",
    "sg:postcode":"4144",
    "sg:province":"Basel-Landschaft",
    "wof:name":"Schweiz.eisenbahner-verb.sekt. W\u00e4rterpers.,herrn Edwin Meyer",
    "wof:placetype":"venue"
},
  "geometry": {"coordinates":[7.619716,47.502254],"type":"Point"}
}