{
  "type": "Feature",
  "properties": {
    "iso:country":"CH",
    "sg:address":"Stadacherstrasse 24 8320 Fehraltorf. Postfach",
    "sg:city":"Fehraltorf",
    "sg:orig_category":"Softwareentwicklung U beratung",
    "sg:phone":"+41 19542610",
    "sg:postcode":"8320",
    "sg:province":"Z\u00fcrich",
    "wof:name":"X It-services Gmbh Dienstleistungen Im Systemmanagement, Engineering, Network, Security-bereich Usw",
    "wof:placetype":"venue"
},
  "geometry": {"coordinates":[8.7560195923,47.3840065002],"type":"Point"}
}