{
  "type": "Feature",
  "properties": {
    "iso:country":"CH",
    "sg:address":"Marktweg 10 8800 Thalwil. Postfach",
    "sg:city":"Gattikon",
    "sg:orig_category":"Sonstiger Grosshandel",
    "sg:phone":"+41 79 608 55 65",
    "sg:postcode":"8136",
    "sg:province":"Z\u00fcrich",
    "wof:name":"Comini & Co, Inhaber S. Comini",
    "wof:placetype":"venue"
},
  "geometry": {"coordinates":[8.5572891235,47.284412384],"type":"Point"}
}