{
  "type": "Feature",
  "properties": {
    "iso:country":"CH",
    "sg:address":"Kirchb\u00fchl 2 3400 Burgdorf. Postfach",
    "sg:city":"Burgdorf",
    "sg:orig_category":"Interessenvertretungen",
    "sg:postcode":"3400",
    "sg:province":"Bern",
    "wof:name":"Mine-ex Stiftung Rotary Ch/fl Weltweite Hilfestellung F. Opfer V. Personenminen Usw",
    "wof:placetype":"venue"
},
  "geometry": {"coordinates":[7.6267690659,47.0565109253],"type":"Point"}
}