{
  "type": "Feature",
  "properties": {
    "iso:country":"CH",
    "sg:address":"Montelly Chemin De 48",
    "sg:city":"Lausanne",
    "sg:orig_category":"Satzherstellung U Reproduktion",
    "sg:phone":"+41 22 736 72 52",
    "sg:postcode":"1007",
    "sg:province":"Vaud",
    "wof:name":"Tt Typoteam Sa",
    "wof:placetype":"venue"
},
  "geometry": {"coordinates":[6.1609520912,46.2048454285],"type":"Point"}
}