{
  "type": "Feature",
  "properties": {
    "iso:country":"CH",
    "sg:address":"Petit-cordex",
    "sg:city":"Genolier",
    "sg:orig_category":"Allgemeiner Gartenbau Blumen U Zierpflanzenbau",
    "sg:phone":"+41 22 782 90 12",
    "sg:postcode":"1272",
    "sg:province":"Vaud",
    "wof:name":"E. Ho\u00ebn & E. Eggenberger",
    "wof:placetype":"venue"
},
  "geometry": {"coordinates":[6.073535,46.237583],"type":"Point"}
}