{
  "type": "Feature",
  "properties": {
    "addr:full":"Raindliweg 4 Ober\u00e4geri Zug 6315",
    "addr:housenumber":"4",
    "addr:postcode":"6315",
    "addr:street":"Raindliweg;Zug",
    "iso:country":"CH",
    "sg:address":"Raindliweg 4",
    "sg:city":"Ober\u00e4geri",
    "sg:orig_category":"Blumen U Zierpflanzenbau Detailhandel mit Blumen U Pflanzen",
    "sg:phone":"+41 41 750 15 38",
    "sg:postcode":"6315",
    "sg:province":"Zug",
    "wof:name":"Staub Peter Ag",
    "wof:placetype":"venue"
},
  "geometry": {"coordinates":[8.610251,47.136009],"type":"Point"}
}