{
  "type": "Feature",
  "properties": {
    "iso:country":"CH",
    "sg:address":"Brunnenwiesliweg 12",
    "sg:city":"Horgen",
    "sg:orig_category":"Informatikdienste",
    "sg:phone":"+41 4117255688",
    "sg:postcode":"8810",
    "sg:province":"Z\u00fcrich",
    "wof:name":"Fwd Stefan Ruckstuhl",
    "wof:placetype":"venue"
},
  "geometry": {"coordinates":[8.5915136337,47.2606277466],"type":"Point"}
}