{
  "type": "Feature",
  "properties": {
    "iso:country":"CH",
    "sg:address":"Route Du Pavement 3bis",
    "sg:city":"Lausanne",
    "sg:orig_category":"Sonstiger Detailhandel mit Metallwaren, Anstrichmitteln, Glaswaren, Bau U Heimwerkerbedarf",
    "sg:phone":"+41 21 647 23 56",
    "sg:postcode":"1018",
    "sg:province":"Vaud",
    "wof:name":"Vercol Vernis-couleurs Sa",
    "wof:placetype":"venue"
},
  "geometry": {"coordinates":[6.6359620094,46.5302200317],"type":"Point"}
}