{
  "type": "Feature",
  "properties": {
    "iso:country":"CH",
    "sg:address":"1410",
    "sg:city":"Thierrens",
    "sg:orig_category":"Vorschulen, Kinderg\u00e4rten",
    "sg:postcode":"1410",
    "sg:province":"Vaud",
    "wof:name":"Ecole Enfantine",
    "wof:placetype":"venue"
},
  "geometry": {"coordinates":[6.7543702126,46.7039604187],"type":"Point"}
}