{
  "type": "Feature",
  "properties": {
    "addr:full":"Via Dogana 6 Bellinzona Ticino 6500",
    "addr:housenumber":"6",
    "addr:postcode":"6500",
    "addr:street":"Via Dogana",
    "iso:country":"CH",
    "sg:address":"Via Dogana 6",
    "sg:city":"Bellinzona",
    "sg:orig_category":"Bauspenglerei Sanit\u00e4rinstallation",
    "sg:phone":"+41 91 825 10 42",
    "sg:postcode":"6500",
    "sg:province":"Ticino",
    "wof:name":"Celeste Moreschi Sa",
    "wof:placetype":"venue"
},
  "geometry": {"coordinates":[9.02183,46.190311],"type":"Point"}
}