{
  "type": "Feature",
  "properties": {
    "iso:country":"CH",
    "sg:address":"Rte Des Moulins",
    "sg:city":"Granges-marnand",
    "sg:orig_category":"Architektur U Ingenieurb\u00fcros",
    "sg:postcode":"1523",
    "sg:province":"Vaud",
    "wof:name":"Bureau De Conseils Techniques Nef",
    "wof:placetype":"venue"
},
  "geometry": {"coordinates":[6.882814,46.763332],"type":"Point"}
}