{
  "type": "Feature",
  "properties": {
    "iso:country":"CH",
    "sg:address":"1454",
    "sg:city":"L'auberson",
    "sg:orig_category":"Sportvereine Turnen",
    "sg:phone":"+41 24 454 24 85",
    "sg:postcode":"1454",
    "sg:province":"Vaud",
    "wof:name":"St\u00e9 De Gymnastique L'auberson",
    "wof:placetype":"venue"
},
  "geometry": {"coordinates":[6.4598498344,46.8177909851],"type":"Point"}
}