{
  "type": "Feature",
  "properties": {
    "addr:full":"Wieden 148 Sch\u00f6nholzerswilen Thurgau 8577",
    "addr:housenumber":"148",
    "addr:postcode":"8577",
    "addr:street":"Wieden;Thurgau",
    "iso:country":"CH",
    "sg:address":"Wieden 148",
    "sg:city":"Sch\u00f6nholzerswilen",
    "sg:orig_category":"Detailhandel mit Antiquit\u00e4ten U Gebrauchtwaren in Verkaufsr\u00e4umen",
    "sg:postcode":"8577",
    "sg:province":"Thurgau",
    "wof:name":"Robert Eberhart Altertum Aller Art",
    "wof:placetype":"venue"
},
  "geometry": {"coordinates":[9.132285,47.509705],"type":"Point"}
}