{
  "type": "Feature",
  "properties": {
    "iso:country":"CH",
    "sg:address":"Spalenberg 56 4051 Basel. Postfach",
    "sg:city":"Basel",
    "sg:orig_category":"Verm\u00f6gensverwaltung",
    "sg:phone":"+41 61 643 10 00",
    "sg:postcode":"4001",
    "sg:province":"Basel-Stadt",
    "wof:name":"Swissinvest Verwaltungen",
    "wof:placetype":"venue"
},
  "geometry": {"coordinates":[7.5848870277,47.5569343567],"type":"Point"}
}