{
  "type": "Feature",
  "properties": {
    "iso:country":"CH",
    "sg:address":"Rheinstrasse 55 4410 Liestal. Postfach",
    "sg:city":"Liestal",
    "sg:orig_category":"Zivilschutz",
    "sg:phone":"+41 61 901 45 33",
    "sg:postcode":"4410",
    "sg:province":"Basel-Landschaft",
    "wof:name":"Kant. Amt F\u00fcr Zivilschutz",
    "wof:placetype":"venue"
},
  "geometry": {"coordinates":[7.7251081467,47.4915313721],"type":"Point"}
}