{
  "type": "Feature",
  "properties": {
    "iso:country":"CH",
    "sg:address":"Industriestrasse 42",
    "sg:city":"F\u00e4llanden",
    "sg:orig_category":"Unclassifiable Establishments",
    "sg:phone":"+41 79 457 45 46",
    "sg:postcode":"8117",
    "sg:province":"Z\u00fcrich",
    "wof:name":"Team-at-work Prepress And New Media Krivanek Schlund Michaela",
    "wof:placetype":"venue"
},
  "geometry": {"coordinates":[8.6448335648,47.3785552979],"type":"Point"}
}