{
  "type": "Feature",
  "properties": {
    "iso:country":"CH",
    "sg:address":"Bleienbachstrasse 21",
    "sg:city":"Lotzwil",
    "sg:orig_category":"Innendekorationsateliers",
    "sg:phone":"+41 62 923 17 71",
    "sg:postcode":"4932",
    "sg:province":"Bern",
    "wof:name":"Katharina W\u00e4lchi Polsteratelier",
    "wof:placetype":"venue"
},
  "geometry": {"coordinates":[7.7852191925,47.1886177063],"type":"Point"}
}