{
  "type": "Feature",
  "properties": {
    "iso:country":"CH",
    "sg:address":"Schaffhauserstrasse 62",
    "sg:city":"Winterthur",
    "sg:orig_category":"Grosshandel mit Nahrungsmitteln, Getr\u00e4nken U Tabakwaren ohne ausgepr\u00e4gten Schwerpunkt",
    "sg:postcode":"8400",
    "sg:province":"Z\u00fcrich",
    "wof:name":"Rama Lebensmittel",
    "wof:placetype":"venue"
},
  "geometry": {"coordinates":[8.7218971252,47.5126914978],"type":"Point"}
}