{
  "type": "Feature",
  "properties": {
    "iso:country":"CH",
    "sg:address":"Hermetsloo Str. 75",
    "sg:city":"Z\u00fcrich",
    "sg:classifiers":[
        {
            "category":"Manufacturing",
            "subcategory":"Chemicals & Compounds",
            "type":"Manufacturing & Wholesale Goods"
        }
    ],
    "sg:phone":"+41 4114324466",
    "sg:postcode":"8048",
    "sg:province":"Z\u00fcrich",
    "sg:tags":[
        "pharmaceutical",
        "chemistry",
        "-",
        "by-product"
    ],
    "wof:name":"Kindler Maschinen Ag",
    "wof:placetype":"venue"
},
  "geometry": {"coordinates":[8.474004,47.394112],"type":"Point"}
}