{
  "type": "Feature",
  "properties": {
    "iso:country":"CH",
    "sg:address":"Oberbottigenw.70",
    "sg:city":"Bern",
    "sg:orig_category":"Sanit\u00e4rinstallation",
    "sg:phone":"+41 31 926 15 29",
    "sg:postcode":"3019",
    "sg:province":"Bern",
    "wof:name":"Alfred Grundlehner Sanit\u00e4r Service",
    "wof:placetype":"venue"
},
  "geometry": {"coordinates":[7.3453102112,46.9375801086],"type":"Point"}
}