{
  "type": "Feature",
  "properties": {
    "iso:country":"CH",
    "sg:address":"Bahnhofstrasse 37 8320 Fehraltorf. Postfach 329",
    "sg:city":"Fehraltorf",
    "sg:orig_category":"Caterer Reiseb\u00fcros U Reiseveranstalter",
    "sg:postcode":"8320",
    "sg:province":"Z\u00fcrich",
    "wof:name":"K & O Event Management Charles Krabichler Und Heinz Omlin",
    "wof:placetype":"venue"
},
  "geometry": {"coordinates":[8.75063,47.385479],"type":"Point"}
}