{
  "type": "Feature",
  "properties": {
    "iso:country":"CH",
    "sg:address":"Berglistrasse 47",
    "sg:city":"Arbon",
    "sg:orig_category":"Werbung",
    "sg:phone":"+41 71 446 16 83",
    "sg:postcode":"9320",
    "sg:province":"Thurgau",
    "wof:name":"Octocom Gmbh",
    "wof:placetype":"venue"
},
  "geometry": {"coordinates":[9.4253034592,47.5156555176],"type":"Point"}
}