{
  "type": "Feature",
  "properties": {
    "iso:country":"CH",
    "sg:address":"Bergstrasse 162 8000 Z\u00fcrich. Postfach",
    "sg:city":"Z\u00fcrich",
    "sg:orig_category":"Vermietung U Verpachtung von eigenen Immobilien Vermittlung von Immobilien",
    "sg:phone":"+41 13818464",
    "sg:postcode":"8030",
    "wof:name":"Rentenhaus Ag",
    "wof:placetype":"venue"
},
  "geometry": {"coordinates":[8.5660171509,47.3649330139],"type":"Point"}
}