{
  "type": "Feature",
  "properties": {
    "iso:country":"CH",
    "sg:address":"8913 Ottenbach. Postfach",
    "sg:city":"Ottenbach",
    "sg:orig_category":"G\u00fcterbef\u00f6rderung im Strassenverkehr",
    "sg:phone":"+41 17612175",
    "sg:postcode":"8913",
    "sg:province":"Z\u00fcrich",
    "wof:name":"Zumstein-reisen",
    "wof:placetype":"venue"
},
  "geometry": {"coordinates":[8.408659935,47.2807197571],"type":"Point"}
}