{
  "type": "Feature",
  "properties": {
    "iso:country":"CH",
    "sg:address":"Hausmatten 2",
    "sg:city":"Rottenschwil",
    "sg:orig_category":"Unclassifiable Establishments",
    "sg:postcode":"8919",
    "sg:province":"Aargau",
    "wof:name":"Hoppler Tiefbohrungen Gmbh",
    "wof:placetype":"venue"
},
  "geometry": {"coordinates":[8.3625707626,47.3127822876],"type":"Point"}
}