{
  "type": "Feature",
  "properties": {
    "iso:country":"CH",
    "sg:address":"Hardmatt 434 5082 Kaisten. Postfach",
    "sg:city":"Kaisten",
    "sg:orig_category":"Wasserversorgung",
    "sg:postcode":"5082",
    "sg:province":"Aargau",
    "wof:name":"Ara Kaisten Ag Uebernahme Von Abw\u00e4sser Von Den Angeschlossenen Abwasserverb\u00e4nden Usw",
    "wof:placetype":"venue"
},
  "geometry": {"coordinates":[8.0373182297,47.5439796448],"type":"Point"}
}