{
  "type": "Feature",
  "properties": {
    "iso:country":"CH",
    "sg:address":"Moosgasse 2",
    "sg:city":"Hermrigen",
    "sg:orig_category":"Allgemeiner Hoch U Tiefbau",
    "sg:phone":"+41 32 381 12 77",
    "sg:postcode":"3274",
    "sg:province":"Bern",
    "wof:name":"Paul Wyss Festzelte/bartheken Vermietung",
    "wof:placetype":"venue"
},
  "geometry": {"coordinates":[7.244046,47.080944],"type":"Point"}
}