{
  "type": "Feature",
  "properties": {
    "iso:country":"CH",
    "sg:address":"2947 Charmoille. Postfach",
    "sg:city":"Charmoille",
    "sg:orig_category":"Instandhaltung U Reparatur von Automobilen",
    "sg:postcode":"2947",
    "sg:province":"Jura",
    "wof:name":"Brouze Raymond",
    "wof:placetype":"venue"
},
  "geometry": {"coordinates":[6.9719400406,46.2053909302],"type":"Point"}
}