{
  "type": "Feature",
  "properties": {
    "iso:country":"CH",
    "sg:address":"2207",
    "sg:city":"Coffrane",
    "sg:orig_category":"Herstellung von sonstigen landwirtschaftlichen Maschinen Schmieden",
    "sg:phone":"+41 26 918 72 00",
    "sg:postcode":"2207",
    "sg:province":"Neuch\u00e2tel",
    "wof:name":"Mb Grandjean Sa Forge & Machines Agricoles",
    "wof:placetype":"venue"
},
  "geometry": {"coordinates":[6.9104480743,46.6096229553],"type":"Point"}
}