{
  "type": "Feature",
  "properties": {
    "iso:country":"CH",
    "sg:address":"Margaretenweg 6",
    "sg:city":"Rheinfelden",
    "sg:orig_category":"Unclassifiable Establishments",
    "sg:postcode":"4310",
    "sg:province":"Aargau",
    "wof:name":"Cytac Ag",
    "wof:placetype":"venue"
},
  "geometry": {"coordinates":[7.7889451981,47.5515289307],"type":"Point"}
}