{
  "type": "Feature",
  "properties": {
    "iso:country":"CH",
    "sg:address":"1716",
    "sg:city":"Plaffeien",
    "sg:orig_category":"Mahl U Sch\u00e4lm\u00fchlen",
    "sg:phone":"+41 26 419 11 31",
    "sg:postcode":"1716",
    "sg:province":"Fribourg",
    "wof:name":"Br\u00fcgger Thomas.",
    "wof:placetype":"venue"
},
  "geometry": {"coordinates":[7.2868709564,46.7410163879],"type":"Point"}
}