{
  "type": "Feature",
  "properties": {
    "iso:country":"CH",
    "sg:address":"1529",
    "sg:city":"Cheiry",
    "sg:orig_category":"G\u00fcterbef\u00f6rderung im Strassenverkehr",
    "sg:phone":"+41 26 666 11 44",
    "sg:postcode":"1529",
    "sg:province":"Fribourg",
    "wof:name":"Ren\u00e9 Pythoud Transports & Garage",
    "wof:placetype":"venue"
},
  "geometry": {"coordinates":[6.8391699791,46.7487716675],"type":"Point"}
}