{
  "type": "Feature",
  "properties": {
    "iso:country":"CH",
    "sg:address":"Greyerzstrasse 23",
    "sg:city":"Bern",
    "sg:orig_category":"Sonstiges Versicherungsgewerbe",
    "sg:phone":"+41 31 335 14 14",
    "sg:postcode":"3013",
    "sg:province":"Bern",
    "wof:name":"Kolb Peter",
    "wof:placetype":"venue"
},
  "geometry": {"coordinates":[7.4483737946,46.954990387],"type":"Point"}
}