{
  "type": "Feature",
  "properties": {
    "iso:country":"CH",
    "sg:address":"Chemin De Beausobre 2",
    "sg:city":"Morges",
    "sg:orig_category":"Installation von Heizungs, L\u00fcftungs U Klimaanlagen Sanit\u00e4r U Heizungsinstallation",
    "sg:phone":"+41 21 802 31 45",
    "sg:postcode":"1110",
    "sg:province":"Vaud",
    "wof:name":"Edm Eliano Del Moro Sa Chauffages & Ventilations",
    "wof:placetype":"venue"
},
  "geometry": {"coordinates":[6.4910597801,46.51379776],"type":"Point"}
}