{
  "type": "Feature",
  "properties": {
    "iso:country":"CH",
    "sg:address":"World Trade Center",
    "sg:city":"Agno",
    "sg:orig_category":"Softwareentwicklung U beratung",
    "sg:phone":"+41 52 672 79 64",
    "sg:postcode":"6982",
    "sg:province":"Ticino",
    "wof:name":"Gmo Consulting And Services Gmbh",
    "wof:placetype":"venue"
},
  "geometry": {"coordinates":[8.6605558395,47.7401390076],"type":"Point"}
}