{
  "type": "Feature",
  "properties": {
    "addr:full":"Route De Gen\u00e8ve Morges Vaud 1110",
    "addr:postcode":"1110",
    "addr:street":"Route De Gene\u0300Ve",
    "iso:country":"CH",
    "sg:address":"Route De Gen\u00e8ve",
    "sg:city":"Morges",
    "sg:orig_category":"Campingpl\u00e4tze Detailhandel mit Zeitungen U Zeitschriften Kioske",
    "sg:phone":"+41 21 801 12 70",
    "sg:postcode":"1110",
    "sg:province":"Vaud",
    "wof:name":"Camping Du Tcs Le Petit Bois Michel Vermot",
    "wof:placetype":"venue"
},
  "geometry": {"coordinates":[6.498785,46.508564],"type":"Point"}
}