{
  "type": "Feature",
  "properties": {
    "iso:country":"CH",
    "sg:address":"Arbonerstrasse 1",
    "sg:city":"Salmsach",
    "sg:orig_category":"Instandhaltung U Reparatur von Automobilen",
    "sg:phone":"+41 71 463 35 21",
    "sg:postcode":"8599",
    "sg:province":"Thurgau",
    "wof:name":"Garage Cechmanek - Automobile",
    "wof:placetype":"venue"
},
  "geometry": {"coordinates":[9.3708896637,47.5547409058],"type":"Point"}
}