{
  "type": "Feature",
  "properties": {
    "iso:country":"CH",
    "sg:address":"2114",
    "sg:city":"Fleurier",
    "sg:orig_category":"Organisationen des Gesundheitswesen",
    "sg:postcode":"2114",
    "sg:province":"Neuch\u00e2tel",
    "wof:name":"St\u00e9 Des Samaritains",
    "wof:placetype":"venue"
},
  "geometry": {"coordinates":[6.6068201065,46.9808044434],"type":"Point"}
}