{
  "type": "Feature",
  "properties": {
    "iso:country":"CH",
    "sg:address":"Ahornweg 4",
    "sg:city":"Hunzenschwil",
    "sg:orig_category":"Detailhandel mit Radio U Fernsehger\u00e4ten Elektroinstallation",
    "sg:phone":"+41 62 897 52 22",
    "sg:postcode":"5502",
    "sg:province":"Aargau",
    "wof:name":"Precicom Kommunikationstechnik Urs R.gloor",
    "wof:placetype":"venue"
},
  "geometry": {"coordinates":[8.1165018082,47.3806686401],"type":"Point"}
}