{
  "type": "Feature",
  "properties": {
    "iso:country":"CH",
    "sg:address":"Guggenb\u00fchlstrasse 6 8404 Oberwinterthur. Postfach",
    "sg:city":"Winterthur",
    "sg:classifiers":[
        {
            "category":"Travel",
            "subcategory":"Hotels & Motels",
            "type":"Entertainment"
        }
    ],
    "sg:postcode":"8404",
    "sg:province":"Z\u00fcrich",
    "sg:tags":[
        "hotels",
        "mit",
        "restaurant"
    ],
    "wof:name":"Meier Heinrich",
    "wof:placetype":"venue"
},
  "geometry": {"coordinates":[8.2410306931,47.5176582336],"type":"Point"}
}