{
  "type": "Feature",
  "properties": {
    "iso:country":"CH",
    "sg:address":"Lettenstrasse 14",
    "sg:city":"Z\u00fcrich",
    "sg:orig_category":"Organisationen des Gesundheitswesen",
    "sg:phone":"+41 13645137",
    "sg:postcode":"8037",
    "sg:province":"Z\u00fcrich",
    "wof:name":"Samariterverein Wipkingen",
    "wof:placetype":"venue"
},
  "geometry": {"coordinates":[8.5314445496,47.3897094727],"type":"Point"}
}