{
  "type": "Feature",
  "properties": {
    "iso:country":"CH",
    "sg:address":"\u00dcberlandstrasse 103",
    "sg:city":"D\u00fcbendorf",
    "sg:orig_category":"Softwareentwicklung U beratung",
    "sg:phone":"+41 13684751",
    "sg:postcode":"8600",
    "sg:province":"Z\u00fcrich",
    "wof:name":"Software Ingenieurb\u00fcro Laukemann J.",
    "wof:placetype":"venue"
},
  "geometry": {"coordinates":[8.6078233719,47.4037704468],"type":"Point"}
}