{
  "type": "Feature",
  "properties": {
    "iso:country":"CH",
    "sg:address":"Buchentalstrasse 22a",
    "sg:city":"St.gallen",
    "sg:orig_category":"Malerei Tapeziererei",
    "sg:phone":"+41 71 245 50 63",
    "sg:postcode":"9000",
    "sg:province":"St. Gallen",
    "wof:name":"Gebr. Tinner Gmbh",
    "wof:placetype":"venue"
},
  "geometry": {"coordinates":[9.3964538574,47.4348297119],"type":"Point"}
}