{
  "type": "Feature",
  "properties": {
    "iso:country":"CH",
    "sg:address":"Obermumpferstrasse 70",
    "sg:city":"Schupfart",
    "sg:orig_category":"Detailhandel mit Waren verschiedener Art, Hauptrichtung Nahrungsmittel",
    "sg:phone":"+41 41 910 10 82",
    "sg:postcode":"4325",
    "sg:province":"Aargau",
    "wof:name":"Josef Fuchs Lebensmittel",
    "wof:placetype":"venue"
},
  "geometry": {"coordinates":[8.2451162338,47.1695594788],"type":"Point"}
}