{
  "type": "Feature",
  "properties": {
    "iso:country":"CH",
    "sg:address":"9552",
    "sg:city":"Bronschhofen",
    "sg:orig_category":"Schulpflegen",
    "sg:postcode":"9552",
    "sg:province":"St. Gallen",
    "wof:name":"Schulrat Der Gemeinde Bronschhofen",
    "wof:placetype":"venue"
},
  "geometry": {"coordinates":[9.0359830856,47.4764137268],"type":"Point"}
}