{
  "type": "Feature",
  "properties": {
    "iso:country":"CH",
    "sg:address":"Riedern.",
    "sg:city":"Ueberstorf",
    "sg:orig_category":"Allgemeiner Hoch U Tiefbau",
    "sg:phone":"+41 79 415 23 94",
    "sg:postcode":"3182",
    "sg:province":"Fribourg",
    "wof:name":"Mauron Eduard.",
    "wof:placetype":"venue"
},
  "geometry": {"coordinates":[7.348598,46.886147],"type":"Point"}
}