{
  "type": "Feature",
  "properties": {
    "iso:country":"CH",
    "sg:address":"2852 Court\u00e9telle. Postfach 16",
    "sg:city":"Court\u00e9telle",
    "sg:orig_category":"Sportvereine Ballsport Fussball",
    "sg:phone":"+41 32 423 36 89",
    "sg:postcode":"2852",
    "sg:province":"Jura",
    "wof:name":"Fc Court\u00e9telle",
    "wof:placetype":"venue"
},
  "geometry": {"coordinates":[7.3167719841,47.3426017761],"type":"Point"}
}