{
  "type": "Feature",
  "properties": {
    "iso:country":"CH",
    "sg:address":"Dorfstrasse 14",
    "sg:city":"B\u00fcnzen",
    "sg:orig_category":"Architekturb\u00fcros Innenarchitekturb\u00fcros",
    "sg:postcode":"5624",
    "sg:province":"Aargau",
    "wof:name":"Daniel Muntwyler Architekt Htl",
    "wof:placetype":"venue"
},
  "geometry": {"coordinates":[8.322647,47.310169],"type":"Point"}
}