{
  "type": "Feature",
  "properties": {
    "addr:full":"Monbijoustrasse 39 Bern Bern 3011",
    "addr:housenumber":"39",
    "addr:postcode":"3011",
    "addr:street":"Monbijoustrasse",
    "iso:country":"CH",
    "sg:address":"Monbijoustrasse 39",
    "sg:city":"Bern",
    "sg:orig_category":"Arztpraxen",
    "sg:phone":"+41 71 477 27 27",
    "sg:postcode":"3011",
    "sg:province":"Bern",
    "wof:name":"Dr.med.reto K\u00e4lin Arzt F.allgemeine Medizin Fmh",
    "wof:placetype":"venue"
},
  "geometry": {"coordinates":[9.370994,47.530491],"type":"Point"}
}