{
  "type": "Feature",
  "properties": {
    "iso:country":"CH",
    "sg:address":"Watterstrasse 81 8105 Regensdorf. Postfach",
    "sg:city":"Regensdorf",
    "sg:orig_category":"Vermietung U Verpachtung von eigenen Immobilien",
    "sg:postcode":"8105",
    "sg:province":"Z\u00fcrich",
    "wof:name":"Regent Immobilien Ag",
    "wof:placetype":"venue"
},
  "geometry": {"coordinates":[9.4885902405,47.2080116272],"type":"Point"}
}