{
  "type": "Feature",
  "properties": {
    "iso:country":"CH",
    "sg:address":"Rte De Mouli\u00e8res 10",
    "sg:city":"Vernier",
    "sg:classifiers":[
        {
            "category":"Autos & Motor Vehicles",
            "subcategory":"Automobile Sales",
            "type":"Retail Goods"
        }
    ],
    "sg:phone":"+41 22 939 09 09",
    "sg:postcode":"1214",
    "sg:province":"Gen\u00e8ve",
    "sg:tags":[
        "equipment",
        "transport"
    ],
    "wof:name":"Honda Suisse Sa",
    "wof:placetype":"venue"
},
  "geometry": {"coordinates":[6.0804748535,46.2123451233],"type":"Point"}
}