{
  "type": "Feature",
  "properties": {
    "iso:country":"CH",
    "sg:address":"Untermattweg 8",
    "sg:city":"Bern",
    "sg:orig_category":"Non-Classified Establishments",
    "sg:postcode":"3027",
    "sg:province":"Bern",
    "wof:name":"Galenicare Personalvorsorgestiftung",
    "wof:placetype":"venue"
},
  "geometry": {"coordinates":[7.40020895,46.9491577148],"type":"Point"}
}