{
  "type": "Feature",
  "properties": {
    "iso:country":"CH",
    "sg:address":"F\u00e4rberstr. 19 4000 Basel. Postfach",
    "sg:city":"Basel",
    "sg:orig_category":"Pensionskassen",
    "sg:postcode":"4057",
    "sg:province":"Basel-Stadt",
    "wof:name":"Personalf\u00fcrsorgestiftung Der Fritz Maier, Schreinerei-zimmerei Ag",
    "wof:placetype":"venue"
},
  "geometry": {"coordinates":[7.5929408073,47.5763053894],"type":"Point"}
}