{
  "type": "Feature",
  "properties": {
    "iso:country":"CH",
    "sg:address":"Pfrundhausgasse 9 8200 Schaffhausen. Postfach 3196",
    "sg:city":"Schaffhausen",
    "sg:orig_category":"Advokaturb\u00fcros",
    "sg:phone":"+41 52 624 64 20",
    "sg:postcode":"8201",
    "sg:province":"Schaffhausen",
    "wof:name":"Brandenberger Freivogel & Keiser",
    "wof:placetype":"venue"
},
  "geometry": {"coordinates":[8.636163,47.697388],"type":"Point"}
}