{
  "type": "Feature",
  "properties": {
    "iso:country":"CH",
    "sg:address":"Kantonsstrasse 3902 Glis. Postfach",
    "sg:city":"Glis",
    "sg:orig_category":"Herstellung von sonstigen Produkten aus nichtmetallischen Mineralien",
    "sg:phone":"+41 27 924 23 20",
    "sg:postcode":"3902",
    "sg:province":"Valais",
    "wof:name":"Jordan Steintechnik Ag",
    "wof:placetype":"venue"
},
  "geometry": {"coordinates":[7.9686350822,46.3080215454],"type":"Point"}
}