{
  "type": "Feature",
  "properties": {
    "iso:country":"CH",
    "sg:address":"St.-luzi-strasse 43b 9492 Eschen. Postfach 43",
    "sg:city":"Eschen",
    "sg:orig_category":"Detailhandel mit elektrischen Haushalts, Radio U Fernsehger\u00e4ten ohne ausgepr\u00e4gten Schwerpunkt Elektr",
    "sg:phone":"+423 373 77 88",
    "sg:postcode":"9492",
    "wof:name":"Ewald Hasler Elektro Hasler Anstalt",
    "wof:placetype":"venue"
},
  "geometry": {"coordinates":[9.5222349167,47.2100715637],"type":"Point"}
}