{
  "type": "Feature",
  "properties": {
    "iso:country":"CH",
    "sg:address":"Aabachstrasse 3",
    "sg:city":"Seon",
    "sg:orig_category":"Maler U Glasergewerbe",
    "sg:postcode":"5703",
    "sg:province":"Aargau",
    "wof:name":"Wittwer Hans-rudolf, Malerei",
    "wof:placetype":"venue"
},
  "geometry": {"coordinates":[7.757589817,46.9491271973],"type":"Point"}
}