{
  "type": "Feature",
  "properties": {
    "iso:country":"CH",
    "sg:address":"1974",
    "sg:city":"Arbaz",
    "sg:orig_category":"Regelm\u00e4ssige Personenbef\u00f6rderung im Fernverkehr",
    "sg:phone":"+41 41 460 23 92",
    "sg:postcode":"1974",
    "sg:province":"Valais",
    "wof:name":"Othmar Sidler Postautokurse",
    "wof:placetype":"venue"
},
  "geometry": {"coordinates":[8.2235832214,47.131149292],"type":"Point"}
}