{
  "type": "Feature",
  "properties": {
    "iso:country":"CH",
    "sg:address":"Unter-frittenbach",
    "sg:city":"Zollbr\u00fcck",
    "sg:orig_category":"Herstellung von sonstigen Fahrzeugen Zimmerei, Ingenieurholzbau",
    "sg:phone":"+41 34 496 73 37",
    "sg:postcode":"3436",
    "sg:province":"Bern",
    "wof:name":"Ernst Leuenberger Wagnerei Zimmerei Lebensmittel",
    "wof:placetype":"venue"
},
  "geometry": {"coordinates":[7.7483658791,46.9748382568],"type":"Point"}
}