{
  "type": "Feature",
  "properties": {
    "addr:full":"Kurfirstenstrasse 18 Chur Graubunden 7000",
    "addr:housenumber":"18",
    "addr:postcode":"7000",
    "addr:street":"Kurfirstenstrasse",
    "iso:country":"CH",
    "sg:address":"Kurfirstenstrasse 18",
    "sg:city":"Chur",
    "sg:orig_category":"Architektur U Ingenieurb\u00fcros",
    "sg:phone":"+41 81 356 65 06",
    "sg:postcode":"7000",
    "sg:province":"Graubunden",
    "wof:name":"Ingenieurb\u00fcro Costa Romano",
    "wof:placetype":"venue"
},
  "geometry": {"coordinates":[9.519659,46.858639],"type":"Point"}
}