{
  "type": "Feature",
  "properties": {
    "iso:country":"CH",
    "sg:address":"Chemin Des Vergers 5",
    "sg:city":"St-prex",
    "sg:orig_category":"Verm\u00f6gensverwaltung Wirtschaftspr\u00fcfung, Steuerberatung U Treuhand",
    "sg:phone":"+41 21 806 10 15",
    "sg:postcode":"1162",
    "sg:province":"Vaud",
    "wof:name":"Fiduciaire Gefima Sa Succursale De Saint-prex",
    "wof:placetype":"venue"
},
  "geometry": {"coordinates":[6.4516291618,46.4854354858],"type":"Point"}
}