{
  "type": "Feature",
  "properties": {
    "iso:country":"CH",
    "sg:address":"Landstrasse 1",
    "sg:city":"W\u00e4ngi",
    "sg:orig_category":"D\u00e4mmung gegen K\u00e4lte, W\u00e4rme, Schall U Ersch\u00fctterung Einbau von Schreinerwaren",
    "sg:postcode":"9545",
    "sg:province":"Thurgau",
    "wof:name":"Guido Nef Demo Nsg",
    "wof:placetype":"venue"
},
  "geometry": {"coordinates":[8.2853507996,47.3480987549],"type":"Point"}
}