{
  "type": "Feature",
  "properties": {
    "iso:country":"CH",
    "sg:address":"Neueneggstrasse 2",
    "sg:city":"Flamatt",
    "sg:orig_category":"Tankstellen",
    "sg:phone":"+41 31 741 03 86",
    "sg:postcode":"3175",
    "sg:province":"Fribourg",
    "wof:name":"Esther Borer Aral-tankstelle",
    "wof:placetype":"venue"
},
  "geometry": {"coordinates":[7.3102040291,46.889541626],"type":"Point"}
}