{
  "type": "Feature",
  "properties": {
    "iso:country":"CH",
    "sg:address":"Dorfstrasse 7",
    "sg:city":"Grossh\u00f6chstetten",
    "sg:classifiers":[
        {
            "category":"Travel",
            "subcategory":"Hotels & Motels",
            "type":"Entertainment"
        }
    ],
    "sg:postcode":"3506",
    "sg:province":"Bern",
    "sg:tags":[
        "hotels",
        "mit",
        "restaurant"
    ],
    "wof:name":"Hans-ulrich Bieri",
    "wof:placetype":"venue"
},
  "geometry": {"coordinates":[7.641076088,46.9060058594],"type":"Point"}
}