{
  "type": "Feature",
  "properties": {
    "iso:country":"CH",
    "sg:address":"Avenue De La Gare 45",
    "sg:city":"Lausanne",
    "sg:orig_category":"Detailhandel mit Schuhen Detailhandel mit Schuhen U Lederwaren",
    "sg:phone":"+41 21 351 50 05",
    "sg:postcode":"1003",
    "sg:province":"Vaud",
    "wof:name":"Dansko Helvesko",
    "wof:placetype":"venue"
},
  "geometry": {"coordinates":[6.630715847,46.517074585],"type":"Point"}
}