{
  "type": "Feature",
  "properties": {
    "iso:country":"CH",
    "sg:address":"M\u00fcnstergasse 56",
    "sg:city":"Bern",
    "sg:orig_category":"Fachdetailhandel in Verkaufsr\u00e4umen Kunsthandel",
    "sg:phone":"+41 31 311 78 97",
    "sg:postcode":"3011",
    "sg:province":"Bern",
    "wof:name":"Galerie Hofer, Kunstantiquariat",
    "wof:placetype":"venue"
},
  "geometry": {"coordinates":[7.4494252205,46.9475898743],"type":"Point"}
}