{
  "type": "Feature",
  "properties": {
    "iso:country":"CH",
    "sg:address":"Dorf 39",
    "sg:city":"Zimmerwald",
    "sg:orig_category":"Nationale Postdienste",
    "sg:phone":"+41 31 819 01 04",
    "sg:postcode":"3086",
    "sg:province":"Bern",
    "wof:name":"Die Schweizerische Post",
    "wof:placetype":"venue"
},
  "geometry": {"coordinates":[7.471560955,46.8810958862],"type":"Point"}
}