{
  "type": "Feature",
  "properties": {
    "iso:country":"CH",
    "sg:address":"Dorfplatz 5 3673 Linden. Postfach 10",
    "sg:city":"Linden",
    "sg:orig_category":"Elektroinstallation",
    "sg:phone":"+41 31 771 13 26",
    "sg:postcode":"3673",
    "sg:province":"Bern",
    "wof:name":"Burkhalter H., Elektrische Installationen",
    "wof:placetype":"venue"
},
  "geometry": {"coordinates":[7.6778278351,46.8478927612],"type":"Point"}
}