{
  "type": "Feature",
  "properties": {
    "iso:country":"CH",
    "sg:address":"Dorfstrasse 13 6340 Baar. Postfach",
    "sg:city":"Baar",
    "sg:orig_category":"Herstellung von sonstigen elektrischen Ausr\u00fcstungen Ingenieurb\u00fcros Datenverarbeitung",
    "sg:phone":"+41 878 888 980",
    "sg:postcode":"6340",
    "sg:province":"Zug",
    "wof:name":"Iconet Ag",
    "wof:placetype":"venue"
},
  "geometry": {"coordinates":[8.8524370193,47.2614631653],"type":"Point"}
}