{
  "type": "Feature",
  "properties": {
    "iso:country":"CH",
    "sg:address":"Eulenweg 29",
    "sg:city":"Z\u00fcrich",
    "sg:orig_category":"Betrieb von Taxis",
    "sg:phone":"+41 14314822",
    "sg:postcode":"8048",
    "sg:province":"Z\u00fcrich",
    "wof:name":"Hansj\u00f6rg Rohner Taxameterbetrieb",
    "wof:placetype":"venue"
},
  "geometry": {"coordinates":[8.4814,47.383759],"type":"Point"}
}