{
  "type": "Feature",
  "properties": {
    "iso:country":"CH",
    "sg:address":"Industrie B\u00e4nnli 13",
    "sg:city":"Wolfwil",
    "sg:orig_category":"Cnc Turning, Milling, Boring Centres Combined",
    "sg:phone":"+41 62 926 33 31",
    "sg:postcode":"4628",
    "sg:province":"Solothurn",
    "wof:name":"Angelo Luppi",
    "wof:placetype":"venue"
},
  "geometry": {"coordinates":[7.799469,47.269878],"type":"Point"}
}