{
  "type": "Feature",
  "properties": {
    "iso:country":"CH",
    "sg:address":"3427",
    "sg:city":"Utzenstorf",
    "sg:orig_category":"Landesverteidigung, Sozialversicherung \u00d6ffentliche Verwaltung",
    "sg:phone":"+41 32 665 35 72",
    "sg:postcode":"3427",
    "sg:province":"Bern",
    "wof:name":"Zivilschutzstelle Utzenstorf",
    "wof:placetype":"venue"
},
  "geometry": {"coordinates":[7.5587501526,47.1277503967],"type":"Point"}
}