{
  "type": "Feature",
  "properties": {
    "iso:country":"CH",
    "sg:address":"La Praye 5",
    "sg:city":"Courtelary",
    "sg:orig_category":"Mechanische Werkst\u00e4tten",
    "sg:phone":"+41 32 944 20 40",
    "sg:postcode":"2608",
    "sg:province":"Bern",
    "wof:name":"Svm Schneider & Vergara Microm\u00e9canique",
    "wof:placetype":"venue"
},
  "geometry": {"coordinates":[7.0826411247,47.1807746887],"type":"Point"}
}