{
  "type": "Feature",
  "properties": {
    "iso:country":"CH",
    "sg:address":"Rue Guillaume-farel 22",
    "sg:city":"Neuch\u00e2tel",
    "sg:orig_category":"Zahnarztpraxen",
    "sg:phone":"+41 32 731 25 91",
    "sg:postcode":"2000",
    "sg:province":"Neuch\u00e2tel",
    "wof:name":"Dr M\u00e9d. Dent. Nicole Crestin M\u00e9decin-dentiste",
    "wof:placetype":"venue"
},
  "geometry": {"coordinates":[6.903398037,46.9824447632],"type":"Point"}
}