{
  "type": "Feature",
  "properties": {
    "iso:country":"CH",
    "sg:address":"Aarbergstrasse 14",
    "sg:city":"Radelfingen",
    "sg:orig_category":"Grosshandel mit Getr\u00e4nken",
    "sg:phone":"+41 32 392 16 08",
    "sg:postcode":"3271",
    "sg:province":"Bern",
    "wof:name":"Ernst Heimberg Getr\u00e4nkehandel",
    "wof:placetype":"venue"
},
  "geometry": {"coordinates":[7.2728152275,47.0233154297],"type":"Point"}
}