{
  "type": "Feature",
  "properties": {
    "iso:country":"CH",
    "sg:address":"Fabrikstrasse 9",
    "sg:city":"Oberengstringen",
    "sg:orig_category":"Autolackierereien",
    "sg:phone":"+41 71 278 25 40",
    "sg:postcode":"8102",
    "sg:province":"Z\u00fcrich",
    "wof:name":"Hans Enzler Autolackiererei",
    "wof:placetype":"venue"
},
  "geometry": {"coordinates":[9.352077,47.41861],"type":"Point"}
}