{
  "type": "Feature",
  "properties": {
    "iso:country":"CH",
    "sg:address":"Bahnhofstrasse 23",
    "sg:city":"Zug",
    "sg:orig_category":"Unclassifiable Establishments",
    "sg:phone":"+41 17152332",
    "sg:postcode":"6300",
    "sg:province":"Zug",
    "wof:name":"Gb Cybertech Invest Ag",
    "wof:placetype":"venue"
},
  "geometry": {"coordinates":[8.5156707764,47.1699790955],"type":"Point"}
}