{
  "type": "Feature",
  "properties": {
    "iso:country":"CH",
    "sg:address":"Altismattstrasse 1",
    "sg:city":"Biberist",
    "sg:orig_category":"Sportvereine Turnen",
    "sg:phone":"+41 32 672 31 92",
    "sg:postcode":"4562",
    "sg:province":"Solothurn",
    "wof:name":"M\u00e4nnerturnverein Stv Biberist",
    "wof:placetype":"venue"
},
  "geometry": {"coordinates":[7.5559601784,47.1750488281],"type":"Point"}
}