{
  "type": "Feature",
  "properties": {
    "iso:country":"CH",
    "sg:address":"1148",
    "sg:city":"L'isle",
    "sg:orig_category":"Verarbeitung von Milch Verwertung von Milch",
    "sg:postcode":"1148",
    "sg:province":"Vaud",
    "wof:name":"Soci\u00e9t\u00e9 De Laiterie De L'isle",
    "wof:placetype":"venue"
},
  "geometry": {"coordinates":[-93.47286224370001,46.1380386353],"type":"Point"}
}