{
  "type": "Feature",
  "properties": {
    "iso:country":"CH",
    "sg:address":"Zugerstrasse 76b 6340 Baar. Postfach 653",
    "sg:city":"Baar",
    "sg:orig_category":"Bauingenieurb\u00fcros Heizung L\u00fcftung Klima Sanit\u00e4r, Heizungs U L\u00fcftungsinstallation",
    "sg:phone":"+41 41 767 28 78",
    "sg:postcode":"6341",
    "sg:province":"Zug",
    "wof:name":"Hte Haustechnik Experten Ag",
    "wof:placetype":"venue"
},
  "geometry": {"coordinates":[8.519613,47.183113],"type":"Point"}
}