{
  "type": "Feature",
  "properties": {
    "iso:country":"CH",
    "sg:address":"1274",
    "sg:city":"Grens",
    "sg:orig_category":"G\u00fcterbef\u00f6rderung im Strassenverkehr",
    "sg:phone":"+41 22 361 05 21",
    "sg:postcode":"1274",
    "sg:province":"Vaud",
    "wof:name":"Jean-pierre Jaggi Transporte",
    "wof:placetype":"venue"
},
  "geometry": {"coordinates":[6.1965398788,46.3957290649],"type":"Point"}
}