{
  "type": "Feature",
  "properties": {
    "iso:country":"CH",
    "sg:address":"Route Principale 17",
    "sg:city":"Vicques",
    "sg:orig_category":"Malerei Stukkateurgewerbe, Gipserei U Verputzerei",
    "sg:phone":"+41 32 435 68 72",
    "sg:postcode":"2824",
    "sg:province":"Jura",
    "wof:name":"Am\u00e9d\u00e9 Rion Gypserie & Peinture",
    "wof:placetype":"venue"
},
  "geometry": {"coordinates":[7.4113430977,47.3487091064],"type":"Point"}
}