{
  "type": "Feature",
  "properties": {
    "iso:country":"CH",
    "sg:address":"Rebbergweg 2",
    "sg:city":"Klingnau",
    "sg:orig_category":"Sportvereine Wassersport Schwimmen",
    "sg:postcode":"5313",
    "sg:province":"Aargau",
    "wof:name":"Sk 70 Zurzach Schwimmklub",
    "wof:placetype":"venue"
},
  "geometry": {"coordinates":[8.2574386597,47.5825767517],"type":"Point"}
}