{
  "type": "Feature",
  "properties": {
    "iso:country":"CH",
    "sg:address":"Lothringerstrasse 110",
    "sg:city":"Basel",
    "sg:orig_category":"Kinderkrippen U horte",
    "sg:phone":"+41 61 322 12 32",
    "sg:postcode":"4056",
    "sg:province":"Basel-Stadt",
    "wof:name":"Spielgruppe Aentli Mit Eurythmie",
    "wof:placetype":"venue"
},
  "geometry": {"coordinates":[7.5757141113,47.5703659058],"type":"Point"}
}