{
  "type": "Feature",
  "properties": {
    "iso:country":"CH",
    "sg:address":"Wildenstrasse 1",
    "sg:city":"Neuhausen",
    "sg:orig_category":"Softwareentwicklung U beratung",
    "sg:postcode":"8212",
    "sg:province":"Schaffhausen",
    "wof:name":"Datensysteme Peter Wehrli",
    "wof:placetype":"venue"
},
  "geometry": {"coordinates":[8.6184911728,47.680809021],"type":"Point"}
}