{
  "type": "Feature",
  "properties": {
    "iso:country":"CH",
    "sg:address":"Avry-centre",
    "sg:city":"Avry-sur-matran",
    "sg:orig_category":"Herstellung von Brot U Backwaren Herstellung von Dauerbackwaren",
    "sg:phone":"+41 26 470 15 10",
    "sg:postcode":"1754",
    "sg:province":"Fribourg",
    "wof:name":"Jowa Sa Boulangerie",
    "wof:placetype":"venue"
},
  "geometry": {"coordinates":[7.0721960068,46.7883262634],"type":"Point"}
}