{
  "type": "Feature",
  "properties": {
    "iso:country":"CH",
    "sg:address":"1088",
    "sg:city":"Ropraz",
    "sg:orig_category":"Interessenvertretungen",
    "sg:phone":"+41 21 903 11 73",
    "sg:postcode":"1088",
    "sg:province":"Vaud",
    "wof:name":"Fondation L'estr\u00e9e",
    "wof:placetype":"venue"
},
  "geometry": {"coordinates":[6.7550001144,46.6073799133],"type":"Point"}
}