{
  "type": "Feature",
  "properties": {
    "iso:country":"CH",
    "sg:address":"Hotel Schweizerhof 3818 Grindelwald. Postfach 136",
    "sg:city":"Grindelwald",
    "sg:orig_category":"Wirtschafts- and Arbeitgeberverb\u00e4nde",
    "sg:phone":"+41 33 853 22 02",
    "sg:postcode":"3818",
    "sg:province":"Bern",
    "wof:name":"Hotelierverein Grindelwald",
    "wof:placetype":"venue"
},
  "geometry": {"coordinates":[8.0346326828,46.624370575],"type":"Point"}
}