{
  "type": "Feature",
  "properties": {
    "iso:country":"CH",
    "sg:address":"Spalenring 120",
    "sg:city":"Basel",
    "sg:orig_category":"Sonstige Personenbef\u00f6rderung im Landverkehr",
    "sg:postcode":"4055",
    "sg:province":"Basel-Stadt",
    "wof:name":"Teufer Ag Carreisen",
    "wof:placetype":"venue"
},
  "geometry": {"coordinates":[8.2814674377,47.3501052856],"type":"Point"}
}