{
  "type": "Feature",
  "properties": {
    "iso:country":"CH",
    "sg:address":"Franziskanerplatz 8",
    "sg:city":"Luzern",
    "sg:orig_category":"Detailhandel mit Uhren U Schmuck Herstellung von Schmuck, Gold U Silberschmiedwaren",
    "sg:phone":"+41 41 220 12 22",
    "sg:postcode":"6003",
    "sg:province":"Luzern",
    "wof:name":"Marco Antonio Frasson Goldschmied Bijoutier",
    "wof:placetype":"venue"
},
  "geometry": {"coordinates":[8.3028278351,47.0495109558],"type":"Point"}
}