{
  "type": "Feature",
  "properties": {
    "iso:country":"CH",
    "sg:address":"Sch\u00f6ntalstrasse 4 8586 Erlen. Postfach",
    "sg:city":"Erlen",
    "sg:orig_category":"Sportvereine Turnen",
    "sg:phone":"+41 71 648 33 65",
    "sg:postcode":"8586",
    "sg:province":"Thurgau",
    "wof:name":"Turnverein Stv Erlen",
    "wof:placetype":"venue"
},
  "geometry": {"coordinates":[9.230758667,47.548084259],"type":"Point"}
}