{
  "type": "Feature",
  "properties": {
    "iso:country":"CH",
    "sg:address":"Rue De La Papeterie 10 1896 Vouvry Case Postale 75",
    "sg:city":"Vouvry",
    "sg:orig_category":"Herstellung von Papier, Karton U Pappe Herstellung von Wellpapier U pappe sowie von Verpackungsmitte",
    "sg:phone":"+41 24 481 15 51",
    "sg:postcode":"1896",
    "sg:province":"Valais",
    "wof:name":"Vouvry Cart Sa",
    "wof:placetype":"venue"
},
  "geometry": {"coordinates":[6.8827080727,46.3366394043],"type":"Point"}
}