{
  "type": "Feature",
  "properties": {
    "iso:country":"CH",
    "sg:address":"Weinbergstrasse 106 8400 Winterthur. Postfach",
    "sg:city":"Winterthur",
    "sg:orig_category":"Interessenvertretungen",
    "sg:postcode":"8408",
    "sg:province":"Z\u00fcrich",
    "wof:name":"Verein Aids-informationsstelle Winterthur",
    "wof:placetype":"venue"
},
  "geometry": {"coordinates":[8.704126358,47.5117378235],"type":"Point"}
}