{
  "type": "Feature",
  "properties": {
    "iso:country":"CH",
    "sg:address":"Kinkelstrasse 10 8006 Z\u00fcrich. Postfach",
    "sg:city":"Z\u00fcrich",
    "sg:orig_category":"Fachdetailhandel mit pharmazeutischen Produkten",
    "sg:postcode":"8001",
    "sg:province":"Z\u00fcrich",
    "wof:name":"Pharminform Winkler Dr. W. Pharmazeut. Pr\u00e4parate; Vertretung, Public Relations Usw.",
    "wof:placetype":"venue"
},
  "geometry": {"coordinates":[8.5409297943,47.3863105774],"type":"Point"}
}