{
  "type": "Feature",
  "properties": {
    "iso:country":"CH",
    "sg:address":"Unterer Graben 11-17",
    "sg:city":"Winterthur",
    "sg:orig_category":"Detailhandel mit Sportartikeln Fachdetailhandel in Verkaufsr\u00e4umen",
    "sg:phone":"+41 52 213 23 49",
    "sg:postcode":"8400",
    "sg:province":"Z\u00fcrich",
    "wof:name":"Egli-sport Ag",
    "wof:placetype":"venue"
},
  "geometry": {"coordinates":[8.7307729721,47.4987297058],"type":"Point"}
}