{
  "type": "Feature",
  "properties": {
    "iso:country":"CH",
    "sg:address":"Pr\u00e9s Du Lac 63. 1400 Yverdon-les-bains Case Postale 412",
    "sg:city":"Yverdon-les-bains",
    "sg:orig_category":"Pensionskassen",
    "sg:postcode":"1400",
    "sg:province":"Vaud",
    "wof:name":"Fonds De Pr\u00e9voyance De La Sa De La Manufacture D'horlogerie Audemars Piguet & Cie Et Ses Soci\u00e9t\u00e9s Affili\u00e9es",
    "wof:placetype":"venue"
},
  "geometry": {"coordinates":[6.2120537758,46.582359314],"type":"Point"}
}