{
  "type": "Feature",
  "properties": {
    "iso:country":"CH",
    "sg:address":"Poststrasse 7 6060 Sarnen. Postfach 1354",
    "sg:city":"Sarnen",
    "sg:orig_category":"Detailhandel mit Sportartikeln Grosshandel mit Eisenwaren sowie Installationsbedarf f\u00fcr Gas, Wasser ",
    "sg:phone":"+41 71 761 13 43",
    "sg:postcode":"6060",
    "sg:province":"Obwalden",
    "wof:name":"Loher Eisenwaren Ag",
    "wof:placetype":"venue"
},
  "geometry": {"coordinates":[9.5683374405,47.3241767883],"type":"Point"}
}