{
  "type": "Feature",
  "properties": {
    "iso:country":"CH",
    "sg:address":"Hauptstrasse 24",
    "sg:city":"Treiten",
    "sg:orig_category":"Grosshandel mit Obst U Gem\u00fcse",
    "sg:postcode":"3226",
    "sg:province":"Bern",
    "wof:name":"Gross Gem\u00fcse Gmbh",
    "wof:placetype":"venue"
},
  "geometry": {"coordinates":[7.1599998474,47.0101585388],"type":"Point"}
}