{
  "type": "Feature",
  "properties": {
    "iso:country":"CH",
    "sg:address":"Zeughausstrasse",
    "sg:city":"Mels",
    "sg:orig_category":"Pensionskassen",
    "sg:postcode":"8887",
    "sg:province":"St. Gallen",
    "wof:name":"Personalf\u00fcrsorgestiftung Der Sarganserl\u00e4nder Druck Ag, Mels",
    "wof:placetype":"venue"
},
  "geometry": {"coordinates":[9.4077148438,47.0566482544],"type":"Point"}
}