{
  "type": "Feature",
  "properties": {
    "iso:country":"CH",
    "sg:address":"Usserdorf 12",
    "sg:city":"Haldenstein",
    "sg:orig_category":"Herstellung von \u00d6fen U Brennern Sanit\u00e4r U Heizungsinstallation",
    "sg:phone":"+41 81 322 46 65",
    "sg:postcode":"7023",
    "sg:province":"Graubunden",
    "wof:name":"Gredig Hans",
    "wof:placetype":"venue"
},
  "geometry": {"coordinates":[9.5692586899,46.9843902588],"type":"Point"}
}