{
  "type": "Feature",
  "properties": {
    "iso:country":"CH",
    "sg:address":"Waldmatte 3792 Saanen. Postfach",
    "sg:city":"Sch\u00f6nried",
    "sg:orig_category":"Gesundheitswesen",
    "sg:postcode":"3778",
    "sg:province":"Bern",
    "wof:name":"Praxis F\u00fcr Nat\u00fcrliche Heilmethoden, Perreten A.",
    "wof:placetype":"venue"
},
  "geometry": {"coordinates":[7.2599210739,46.4897918701],"type":"Point"}
}