{
  "type": "Feature",
  "properties": {
    "iso:country":"CH",
    "sg:address":"Zaehringen Rue De 13",
    "sg:city":"Fribourg",
    "sg:orig_category":"Unternehmensberatung",
    "sg:phone":"+41 26 322 06 33",
    "sg:postcode":"1700",
    "sg:province":"Fribourg",
    "wof:name":"Gh-plus Sa",
    "wof:placetype":"venue"
},
  "geometry": {"coordinates":[7.1651778221,46.8052902222],"type":"Point"}
}