{
  "type": "Feature",
  "properties": {
    "iso:country":"CH",
    "sg:address":"Landstrasse 52",
    "sg:city":"Gipf-oberfrick",
    "sg:orig_category":"Herstellung von Tanks U Sammelbeh\u00e4ltern aus Metall Sanit\u00e4r U Heizungsinstallation",
    "sg:phone":"+41 24 471 52 76",
    "sg:postcode":"5073",
    "sg:province":"Aargau",
    "wof:name":"Walter Gisler R\u00e9vision De Citernes",
    "wof:placetype":"venue"
},
  "geometry": {"coordinates":[6.9609351158,46.2472343445],"type":"Point"}
}