{
  "type": "Feature",
  "properties": {
    "iso:country":"CH",
    "sg:address":"Ruelle Du Grand-pont 6",
    "sg:city":"Lausanne",
    "sg:orig_category":"Herstellung von sonstigen Metallwaren",
    "sg:phone":"+41 21 320 46 06",
    "sg:postcode":"1003",
    "sg:province":"Vaud",
    "wof:name":"Roland Blanc Encadrements & Gravures",
    "wof:placetype":"venue"
},
  "geometry": {"coordinates":[6.6306300163,46.5213737488],"type":"Point"}
}