{
  "type": "Feature",
  "properties": {
    "iso:country":"CH",
    "sg:address":"Binningerstrasse 191",
    "sg:city":"Allschwil",
    "sg:orig_category":"Reiseb\u00fcros U Reiseveranstalter",
    "sg:phone":"+41 61 303 11 88",
    "sg:postcode":"4123",
    "sg:province":"Basel-Landschaft",
    "wof:name":"Travitur Reiseb\u00fcro",
    "wof:placetype":"venue"
},
  "geometry": {"coordinates":[7.5553021431,47.5464286804],"type":"Point"}
}