{
  "type": "Feature",
  "properties": {
    "iso:country":"CH",
    "sg:address":"Industrieweg 32 4852 Rothrist. Postfach",
    "sg:city":"Rothrist",
    "sg:orig_category":"Grosshandel mit Nahrungsmitteln, Getr\u00e4nken U Tabakwaren ohne ausgepr\u00e4gten Schwerpunkt Handelsvermitt",
    "sg:phone":"+41 62 794 01 30",
    "sg:postcode":"4852",
    "sg:province":"Aargau",
    "wof:name":"Gostivar Handels Gmbh Lebensmittel U. Waren; Handel Usw",
    "wof:placetype":"venue"
},
  "geometry": {"coordinates":[7.8686790466,47.3036499023],"type":"Point"}
}