{
  "type": "Feature",
  "properties": {
    "iso:country":"CH",
    "sg:address":"Bellerivestrasse 214",
    "sg:city":"Z\u00fcrich",
    "sg:orig_category":"RESTAURANTS: TEA-ROOMS",
    "sg:phone":"+41 14220252",
    "sg:postcode":"8008",
    "sg:province":"Z\u00fcrich",
    "wof:name":"Benz & Wetter, Restaurationsbetriebe",
    "wof:placetype":"venue"
},
  "geometry": {"coordinates":[8.5581998825,47.3520469666],"type":"Point"}
}