{
  "type": "Feature",
  "properties": {
    "iso:country":"CH",
    "sg:address":"Hauptstrasse 45",
    "sg:city":"K\u00f6lliken",
    "sg:orig_category":"Detailhandel mit Waren verschiedener Art, Hauptrichtung Nahrungsmittel",
    "sg:phone":"+41 62 723 23 21",
    "sg:postcode":"5742",
    "sg:province":"Aargau",
    "wof:name":"Coop Center Birkenhof",
    "wof:placetype":"venue"
},
  "geometry": {"coordinates":[8.0247840881,47.3340034485],"type":"Point"}
}