{
  "type": "Feature",
  "properties": {
    "iso:country":"CH",
    "sg:address":"Route De Sugnens",
    "sg:city":"Poliez-le-grand",
    "sg:orig_category":"Verwaltung von Immobilien Wirtschaftspr\u00fcfung, Steuerberatung U Treuhand",
    "sg:phone":"+41 21 887 72 60",
    "sg:postcode":"1041",
    "sg:province":"Vaud",
    "wof:name":"Favre Philippe",
    "wof:placetype":"venue"
},
  "geometry": {"coordinates":[6.6645698547,46.6371917725],"type":"Point"}
}