{
  "type": "Feature",
  "properties": {
    "iso:country":"CH",
    "sg:address":"S\u00e4ntisstrasse 13",
    "sg:city":"Brunnadern",
    "sg:orig_category":"Werbegrafikateliers",
    "sg:phone":"+41 19292288",
    "sg:postcode":"9125",
    "sg:province":"St. Gallen",
    "wof:name":"Werner B\u00fchler Visuelle Gestaltung",
    "wof:placetype":"venue"
},
  "geometry": {"coordinates":[8.7233800888,47.2748260498],"type":"Point"}
}