{
  "type": "Feature",
  "properties": {
    "iso:country":"CH",
    "sg:address":"Industriestrasse 38",
    "sg:city":"Flamatt",
    "sg:orig_category":"Druck ohne Zeitungsdruck",
    "sg:phone":"+41 32 866 16 76",
    "sg:postcode":"3175",
    "sg:province":"Fribourg",
    "wof:name":"Graphisme, Cabriolu Gwendolyn",
    "wof:placetype":"venue"
},
  "geometry": {"coordinates":[6.4833798409,46.9059715271],"type":"Point"}
}