{
  "type": "Feature",
  "properties": {
    "addr:full":"Gugenstrasse 20 Trimbach Solothurn 4632",
    "addr:housenumber":"20",
    "addr:postcode":"4632",
    "addr:street":"Gugenstrasse",
    "iso:country":"CH",
    "sg:address":"Gugenstrasse 20",
    "sg:city":"Trimbach",
    "sg:orig_category":"Betrieb U technische Hilfsdienste des Kultur U Unterhaltungswesens",
    "sg:phone":"+41 62 293 40 21",
    "sg:postcode":"4632",
    "sg:province":"Solothurn",
    "wof:name":"Nsp Hinteregger Benedict",
    "wof:placetype":"venue"
},
  "geometry": {"coordinates":[7.903736,47.359688],"type":"Point"}
}