{
  "type": "Feature",
  "properties": {
    "iso:country":"CH",
    "sg:address":"D\u00fcrrbergstrasse 27",
    "sg:city":"Aarburg",
    "sg:orig_category":"Fahrschulen, Flugschulen",
    "sg:phone":"+41 81 416 20 20",
    "sg:postcode":"4663",
    "sg:province":"Aargau",
    "wof:name":"Martin Fl\u00fctsch Autofahrschule",
    "wof:placetype":"venue"
},
  "geometry": {"coordinates":[9.8327646255,46.7996635437],"type":"Point"}
}