{
  "type": "Feature",
  "properties": {
    "iso:country":"CH",
    "sg:address":"Sch\u00fctzenstrasse 33 4127 Birsfelden. Postfach",
    "sg:city":"Birsfelden",
    "sg:orig_category":"Hardwareberatung",
    "sg:postcode":"4127",
    "sg:province":"Basel-Landschaft",
    "wof:name":"Danisoft, Christ Computerzubeh\u00f6r, Komplettsysteme; Handel",
    "wof:placetype":"venue"
},
  "geometry": {"coordinates":[7.6259760857,47.5533332825],"type":"Point"}
}