{
  "type": "Feature",
  "properties": {
    "iso:country":"CH",
    "sg:address":"Alfred Escher-strasse 10 8002 Z\u00fcrich. Postfach",
    "sg:city":"Z\u00fcrich",
    "sg:orig_category":"Wirtschaftspr\u00fcfung, Steuerberatung U Treuhand",
    "sg:phone":"+41 12022527",
    "sg:postcode":"8027",
    "sg:province":"Z\u00fcrich",
    "wof:name":"Saldex Treuhand",
    "wof:placetype":"venue"
},
  "geometry": {"coordinates":[8.5323467255,47.3649215698],"type":"Point"}
}