{
  "type": "Feature",
  "properties": {
    "iso:country":"CH",
    "sg:address":"Hauptstrasse 46",
    "sg:city":"Rheineck",
    "sg:orig_category":"Detailhandel mit Tabakwaren",
    "sg:phone":"+41 71 888 16 57",
    "sg:postcode":"9424",
    "sg:province":"St. Gallen",
    "wof:name":"Mangeng Tabak Ag",
    "wof:placetype":"venue"
},
  "geometry": {"coordinates":[9.5913763046,47.464630127],"type":"Point"}
}