{
  "type": "Feature",
  "properties": {
    "iso:country":"CH",
    "sg:address":"Industriestrasse 10 8152 Glattbrugg. Postfach",
    "sg:city":"Glattbrugg",
    "sg:orig_category":"Autotransporte international Sonstige Kurierdienste",
    "sg:phone":"+41 22 910 00 80",
    "sg:postcode":"8152",
    "sg:province":"Z\u00fcrich",
    "wof:name":"Imx Switzerland Sa",
    "wof:placetype":"venue"
},
  "geometry": {"coordinates":[6.142701,46.208359],"type":"Point"}
}