{
  "type": "Feature",
  "properties": {
    "iso:country":"CH",
    "sg:address":"Telmoos 18a",
    "sg:city":"Plaffeien",
    "sg:orig_category":"Fachdetailhandel in Verkaufsr\u00e4umen",
    "sg:phone":"+41 26 419 20 32",
    "sg:postcode":"1716",
    "sg:province":"Fribourg",
    "wof:name":"Mahu Bike Und Sportshop, Corminboeuf + Raemy",
    "wof:placetype":"venue"
},
  "geometry": {"coordinates":[7.2922449112,46.7359848022],"type":"Point"}
}