{
  "type": "Feature",
  "properties": {
    "addr:full":"Melserstrasse 2 Wangs St. Gallen 7323",
    "addr:housenumber":"2",
    "addr:postcode":"7323",
    "addr:street":"Melserstrasse",
    "iso:country":"CH",
    "sg:address":"Melserstrasse 2",
    "sg:city":"Wangs",
    "sg:orig_category":"Allgemeiner Hoch U Tiefbau Wasserversorgung",
    "sg:phone":"+41 81 723 29 19",
    "sg:postcode":"7323",
    "sg:province":"St. Gallen",
    "wof:name":"Gr\u00fcnenfelder Gebr. Ag, Bauunternehmung, Wangs",
    "wof:placetype":"venue"
},
  "geometry": {"coordinates":[9.431375,47.03442],"type":"Point"}
}