{
  "type": "Feature",
  "properties": {
    "addr:full":"Ch. Du Creux De Corsy La Conv Ch\u00e2telard-lutry Vaud 1095",
    "addr:postcode":"1095",
    "addr:street":"Ch. Du Creux De Corsy La Conv Cha\u0302Telard-Lutry",
    "iso:country":"CH",
    "sg:address":"Ch. Du Creux De Corsy La Conv",
    "sg:city":"Ch\u00e2telard-lutry",
    "sg:orig_category":"Architektur U Ingenieurb\u00fcros",
    "sg:postcode":"1095",
    "sg:province":"Vaud",
    "wof:name":"Pitteloud Sandra",
    "wof:placetype":"venue"
},
  "geometry": {"coordinates":[7.33646,46.185768],"type":"Point"}
}