{
  "type": "Feature",
  "properties": {
    "iso:country":"CH",
    "sg:address":"Stutz",
    "sg:city":"Praden",
    "sg:orig_category":"Technische B\u00fcros Heizung, L\u00fcftung, Klima",
    "sg:phone":"+41 81 284 87 08",
    "sg:postcode":"7063",
    "sg:province":"Graubunden",
    "wof:name":"Caspar Riffel B\u00fcro F\u00fcr W\u00e4rmetechnik",
    "wof:placetype":"venue"
},
  "geometry": {"coordinates":[9.5831260681,46.8251533508],"type":"Point"}
}