{
  "type": "Feature",
  "properties": {
    "iso:country":"CH",
    "sg:address":"162",
    "sg:city":"Miecourt",
    "sg:orig_category":"Industrie, Chemie U Biologie",
    "sg:phone":"+41 79 667 21 59",
    "sg:postcode":"2946",
    "sg:province":"Jura",
    "wof:name":"Laubscher Labs Chromatographie",
    "wof:placetype":"venue"
},
  "geometry": {"coordinates":[7.173224,47.43008],"type":"Point"}
}