{
  "type": "Feature",
  "properties": {
    "iso:country":"CH",
    "sg:address":"Riedtwilstrasse 8 3472 Wynigen. Postfach 191",
    "sg:city":"Wynigen",
    "sg:orig_category":"Detailhandel mit Blumen U Pflanzen",
    "sg:phone":"+41 34 415 19 17",
    "sg:postcode":"3472",
    "sg:province":"Bern",
    "wof:name":"Elisabeth Rothenb\u00fchler Blumen-dekorationen",
    "wof:placetype":"venue"
},
  "geometry": {"coordinates":[7.667716,47.107704],"type":"Point"}
}