{
  "type": "Feature",
  "properties": {
    "iso:country":"CH",
    "sg:address":"Alpenstrasse 12",
    "sg:city":"Zug",
    "sg:orig_category":"Detailhandel mit Brot, Back U S\u00fcsswaren",
    "sg:phone":"+41 41 711 38 88",
    "sg:postcode":"6300",
    "sg:province":"Zug",
    "wof:name":"Caf\u00e9 Speck",
    "wof:placetype":"venue"
},
  "geometry": {"coordinates":[8.514944,47.172508],"type":"Point"}
}