{
  "type": "Feature",
  "properties": {
    "iso:country":"CH",
    "sg:address":"Buchmatt 2",
    "sg:city":"Seftigen",
    "sg:orig_category":"Gartenbau",
    "sg:phone":"+41 18691505",
    "sg:postcode":"3662",
    "sg:province":"Bern",
    "wof:name":"Rapp Gartengestaltung",
    "wof:placetype":"venue"
},
  "geometry": {"coordinates":[8.5015201569,47.6061706543],"type":"Point"}
}