{
  "type": "Feature",
  "properties": {
    "iso:country":"CH",
    "sg:address":"D\u00fcrrenburgstrasse 8",
    "sg:city":"Walchwil",
    "sg:orig_category":"Herstellung von Konstruktionsteilen, Fertigbauteilen U Ausbauelementen aus Holz",
    "sg:postcode":"6318",
    "sg:province":"Zug",
    "wof:name":"Betschart Paul Schreinerei",
    "wof:placetype":"venue"
},
  "geometry": {"coordinates":[8.5128602982,47.107963562],"type":"Point"}
}