{
  "type": "Feature",
  "properties": {
    "addr:full":"Passage De La Blancherie 2 Payerne Vaud 1530",
    "addr:housenumber":"2",
    "addr:postcode":"1530",
    "addr:street":"Passage De La Blancherie",
    "iso:country":"CH",
    "sg:address":"Passage De La Blancherie 2",
    "sg:city":"Payerne",
    "sg:orig_category":"Architektur U Ingenieurb\u00fcros Architekturb\u00fcros",
    "sg:phone":"+41 26 660 21 50",
    "sg:postcode":"1530",
    "sg:province":"Vaud",
    "wof:name":"Atelier D'architecture Willommet P. + Sartori D. Sa.",
    "wof:placetype":"venue"
},
  "geometry": {"coordinates":[6.939068,46.816803],"type":"Point"}
}