{
  "type": "Feature",
  "properties": {
    "iso:country":"CH",
    "sg:address":"Bahnhofstrasse 22 8200 Schaffhausen. Postfach 682",
    "sg:city":"Schaffhausen",
    "sg:orig_category":"Vermietung U Verpachtung von eigenen Immobilien",
    "sg:postcode":"8200",
    "sg:province":"Schaffhausen",
    "wof:name":"Sch\u00f6nb\u00fchl-immobilien Ag",
    "wof:placetype":"venue"
},
  "geometry": {"coordinates":[8.6322898865,47.6974601746],"type":"Point"}
}