{
  "type": "Feature",
  "properties": {
    "iso:country":"CH",
    "sg:address":"Forchstrasse 180",
    "sg:city":"Zollikerberg",
    "sg:orig_category":"Detailhandel mit Waren verschiedener Art, Hauptrichtung Nahrungsmittel",
    "sg:phone":"+41 13916030",
    "sg:postcode":"8125",
    "sg:province":"Z\u00fcrich",
    "wof:name":"Coop Z\u00fcrich",
    "wof:placetype":"venue"
},
  "geometry": {"coordinates":[8.6023015976,47.3460922241],"type":"Point"}
}