{
  "type": "Feature",
  "properties": {
    "iso:country":"CH",
    "sg:address":"Via Pellandini 2",
    "sg:city":"Bellinzona",
    "sg:orig_category":"Fachdetailhandel in Verkaufsr\u00e4umen Herstellung von optischen Instrumenten",
    "sg:phone":"+41 91 835 47 65",
    "sg:postcode":"6500",
    "sg:province":"Ticino",
    "wof:name":"Rcm Consulting Engineering Sa",
    "wof:placetype":"venue"
},
  "geometry": {"coordinates":[9.0254096985,46.1943244934],"type":"Point"}
}