{
  "type": "Feature",
  "properties": {
    "iso:country":"CH",
    "sg:address":"Weingartenstrasse 21",
    "sg:city":"Naters",
    "sg:orig_category":"R\u00fcckgewinnung U Vorbereitung f\u00fcr die Wiederverwertung Recycling von nichtmetallischen Altmaterialien",
    "sg:postcode":"3904",
    "sg:province":"Valais",
    "wof:name":"Ewo Imstepf Ernest",
    "wof:placetype":"venue"
},
  "geometry": {"coordinates":[8.0010471344,46.3266716003],"type":"Point"}
}