{
  "type": "Feature",
  "properties": {
    "iso:country":"CH",
    "sg:address":"5237",
    "sg:city":"M\u00f6nthal",
    "sg:orig_category":"Gewinnung von Natursteinen f\u00fcr den Bau Herstellung von sonstigen Produkten aus nichtmetallischen Min",
    "sg:phone":"+41 71 761 12 31",
    "sg:postcode":"5237",
    "sg:province":"Aargau",
    "wof:name":"K\u00f6nig Robert Ag Steinbruch Und Hartschotterwerk",
    "wof:placetype":"venue"
},
  "geometry": {"coordinates":[9.5505933762,47.3121299744],"type":"Point"}
}