{
  "type": "Feature",
  "properties": {
    "addr:full":"Reitergasse 1 8004 Z\u00fcrich. Postfach Z\u00fcrich Z\u00fcrich 8021",
    "addr:housenumber":"1",
    "addr:postcode":"8004 zuerich. postfach;8021",
    "addr:street":"Reitergasse",
    "iso:country":"CH",
    "sg:address":"Reitergasse 1 8004 Z\u00fcrich. Postfach",
    "sg:city":"Z\u00fcrich",
    "sg:orig_category":"Datenverarbeitungsdienste Unternehmensberatung",
    "sg:phone":"+41 12959090",
    "sg:postcode":"8021",
    "sg:province":"Z\u00fcrich",
    "wof:name":"H & P Beratungen Ag",
    "wof:placetype":"venue"
},
  "geometry": {"coordinates":[8.532891,47.37672],"type":"Point"}
}