{
  "type": "Feature",
  "properties": {
    "iso:country":"CH",
    "sg:address":"Bachtobelstrasse 3",
    "sg:city":"Horgen",
    "sg:orig_category":"Unclassifiable Establishments",
    "sg:postcode":"8810",
    "sg:province":"Z\u00fcrich",
    "wof:name":"Dow Europe Gmbh",
    "wof:placetype":"venue"
},
  "geometry": {"coordinates":[8.6176748276,47.2503967285],"type":"Point"}
}