{
  "type": "Feature",
  "properties": {
    "iso:country":"CH",
    "sg:address":"Nefenstrasse 30 9435 Heerbrugg. Postfach",
    "sg:city":"Heerbrugg",
    "sg:orig_category":"Pensionskassen",
    "sg:postcode":"9435",
    "sg:province":"St. Gallen",
    "wof:name":"Patronale Stiftung Der Sfs-gruppe",
    "wof:placetype":"venue"
},
  "geometry": {"coordinates":[9.6203422546,47.4066009521],"type":"Point"}
}