{
  "type": "Feature",
  "properties": {
    "iso:country":"CH",
    "sg:address":"Campagna Via 6934 Bioggio. Postfach",
    "sg:city":"Paradiso",
    "sg:orig_category":"Herstellung von Duft U K\u00f6rperpflegemitteln",
    "sg:postcode":"6900",
    "sg:province":"Ticino",
    "wof:name":"C.i.d. Cosmetics International Distribution Sa, Lussemburgo, Succursale Di Bioggio",
    "wof:placetype":"venue"
},
  "geometry": {"coordinates":[8.9113054276,46.0094184875],"type":"Point"}
}