{
  "type": "Feature",
  "properties": {
    "iso:country":"CH",
    "sg:address":"Sch\u00f6nenstrasse 17",
    "sg:city":"R\u00fcschlikon",
    "sg:orig_category":"Erwachsenenbildung U Unterricht Unternehmensberatung",
    "sg:phone":"+41 17242858",
    "sg:postcode":"8803",
    "sg:province":"Z\u00fcrich",
    "wof:name":"Wyser Walter, Mbs Marketing-beratung Und Schulung",
    "wof:placetype":"venue"
},
  "geometry": {"coordinates":[8.5518827438,47.3121948242],"type":"Point"}
}