{
  "type": "Feature",
  "properties": {
    "iso:country":"CH",
    "sg:address":"Ballyweg 13c",
    "sg:city":"Dottikon",
    "sg:orig_category":"Unclassifiable Establishments",
    "sg:postcode":"5605",
    "sg:province":"Aargau",
    "wof:name":"Iberia-immobilien",
    "wof:placetype":"venue"
},
  "geometry": {"coordinates":[8.2327547073,47.3772697449],"type":"Point"}
}