{
  "type": "Feature",
  "properties": {
    "iso:country":"CH",
    "sg:address":"Rue Du Stade 20",
    "sg:city":"Sion",
    "sg:orig_category":"Elektroinstallation",
    "sg:phone":"+41 27 722 25 60",
    "sg:postcode":"1950",
    "sg:province":"Valais",
    "wof:name":"Vallotton \u00e9lectricit\u00e9",
    "wof:placetype":"venue"
},
  "geometry": {"coordinates":[7.0589408875,46.087146759],"type":"Point"}
}