{
  "type": "Feature",
  "properties": {
    "iso:country":"CH",
    "sg:address":"Rinkenbach 39",
    "sg:city":"Appenzell",
    "sg:orig_category":"Instandhaltung U Reparatur von Automobilen",
    "sg:phone":"+41 71 787 47 57",
    "sg:postcode":"9050",
    "sg:province":"Appenzell Innerhoden",
    "wof:name":"Bruno Frehner, Auto Und Designlackierung",
    "wof:placetype":"venue"
},
  "geometry": {"coordinates":[9.3983011246,47.331741333],"type":"Point"}
}