{
  "type": "Feature",
  "properties": {
    "iso:country":"CH",
    "sg:address":"1063",
    "sg:city":"Chapelle-s-moudon",
    "sg:orig_category":"Herstellung von Spielwaren",
    "sg:postcode":"1063",
    "sg:province":"Vaud",
    "wof:name":"Gleis-tech Gr\u00f6bli",
    "wof:placetype":"venue"
},
  "geometry": {"coordinates":[9.3909835815,47.4301605225],"type":"Point"}
}