{
  "type": "Feature",
  "properties": {
    "iso:country":"CH",
    "sg:address":"Fichtenstrasse 22",
    "sg:city":"Wittenbach",
    "sg:orig_category":"Detailhandel mit Beleuchtungs U Haushaltsgegenst\u00e4nden",
    "sg:phone":"+41 71 298 24 34",
    "sg:postcode":"9303",
    "wof:name":"Robert Rotach Haushaltartikel",
    "wof:placetype":"venue"
},
  "geometry": {"coordinates":[9.389631,47.456272],"type":"Point"}
}