{
  "type": "Feature",
  "properties": {
    "iso:country":"CH",
    "sg:address":"Hauptstrasse 17",
    "sg:city":"Balgach",
    "sg:orig_category":"W\u00e4scherei U chemische Reinigung",
    "sg:phone":"+41 71 722 12 23",
    "sg:postcode":"9436",
    "sg:province":"St. Gallen",
    "wof:name":"Abc Textilreinigung Ulrich Rotermund",
    "wof:placetype":"venue"
},
  "geometry": {"coordinates":[9.6110191345,47.4075584412],"type":"Point"}
}