{
  "type": "Feature",
  "properties": {
    "addr:full":"Luzernerstrasse 51a Kriens Luzern 6010",
    "addr:housenumber":"51a",
    "addr:postcode":"6010",
    "addr:street":"Luzernerstrasse",
    "iso:country":"CH",
    "sg:address":"Luzernerstrasse 51a",
    "sg:city":"Kriens",
    "sg:orig_category":"Advokaturb\u00fcros Wirtschaftspr\u00fcfung, Steuerberatung U Treuhand",
    "sg:phone":"+41 41 310 40 50",
    "sg:postcode":"6010",
    "sg:province":"Luzern",
    "wof:name":"Kanzlei Ag",
    "wof:placetype":"venue"
},
  "geometry": {"coordinates":[8.288647,47.035118],"type":"Point"}
}