{
  "type": "Feature",
  "properties": {
    "iso:country":"CH",
    "sg:address":"Route De L'usine-\u00e0-gaz 16",
    "sg:city":"A\u00efre",
    "sg:orig_category":"Zahnkliniken",
    "sg:phone":"+41 22 796 51 33",
    "sg:postcode":"1219",
    "sg:province":"Gen\u00e8ve",
    "wof:name":"Clinique Dentaire Ecole Des Libellules",
    "wof:placetype":"venue"
},
  "geometry": {"coordinates":[6.0969829559,49.6145744324],"type":"Point"}
}