{
  "type": "Feature",
  "properties": {
    "iso:country":"CH",
    "sg:address":"Holzgasse 36",
    "sg:city":"Wiedlisbach",
    "sg:orig_category":"Grosshandel mit Blumen U Pflanzen",
    "sg:phone":"+41 32 636 10 30",
    "sg:postcode":"4537",
    "sg:province":"Bern",
    "wof:name":"Jost Pflanzenkulturen Ag",
    "wof:placetype":"venue"
},
  "geometry": {"coordinates":[7.6522297859,47.2494010925],"type":"Point"}
}