{
  "type": "Feature",
  "properties": {
    "iso:country":"CH",
    "sg:address":"Kohliberg 325",
    "sg:city":"Zuzgen",
    "sg:orig_category":"Unclassifiable Establishments",
    "sg:postcode":"4315",
    "sg:province":"Aargau",
    "wof:name":"Susanna Pagano Nagelstudio",
    "wof:placetype":"venue"
},
  "geometry": {"coordinates":[8.8543481827,47.260017395],"type":"Point"}
}