{
  "type": "Feature",
  "properties": {
    "iso:country":"CH",
    "sg:address":"Chamerstrasse 14 6300 Zug. Postfach",
    "sg:city":"Zug",
    "sg:orig_category":"Non-Classified Establishments",
    "sg:postcode":"6300",
    "sg:province":"Zug",
    "wof:name":"Canbras Invest + Finance Ag",
    "wof:placetype":"venue"
},
  "geometry": {"coordinates":[8.5113306046,47.1718902588],"type":"Point"}
}