{
  "type": "Feature",
  "properties": {
    "iso:country":"CH",
    "sg:address":"Austrasse 54 3176 Neuenegg. Postfach",
    "sg:city":"Neuenegg",
    "sg:orig_category":"Aktivit\u00e4ten der Generalunternehmen im Baugewerbe Architektur U Ingenieurb\u00fcros",
    "sg:phone":"+41 31 741 07 77",
    "sg:postcode":"3176",
    "sg:province":"Bern",
    "wof:name":"Bap Architekten Ag Architektur- U. Bauplanungsarbeiten Usw",
    "wof:placetype":"venue"
},
  "geometry": {"coordinates":[7.311758,46.894428],"type":"Point"}
}