{
  "type": "Feature",
  "properties": {
    "iso:country":"CH",
    "sg:address":"Via Canonica 7 6900 Lugano Casella Postale",
    "sg:city":"Lugano",
    "sg:orig_category":"Handel mit Motorr\u00e4dern, Teilen U Zubeh\u00f6r Instandhaltung U Reparatur von Motorr\u00e4dern",
    "sg:phone":"+41 55 210 23 77",
    "sg:postcode":"6901",
    "sg:province":"Ticino",
    "wof:name":"Gertsch A., Velos/mofas",
    "wof:placetype":"venue"
},
  "geometry": {"coordinates":[8.8280715942,47.2293167114],"type":"Point"}
}