{
  "type": "Feature",
  "properties": {
    "iso:country":"CH",
    "sg:address":"Bielstrasse 69",
    "sg:city":"Solothurn",
    "sg:classifiers":[
        {
            "category":"Professional",
            "subcategory":"Advertising",
            "type":"Services"
        }
    ],
    "sg:phone":"+41 32 622 55 88",
    "sg:postcode":"4500",
    "sg:province":"Solothurn",
    "sg:tags":[
        "postcard"
    ],
    "wof:name":"Ros Offset- Service Ag",
    "wof:placetype":"venue"
},
  "geometry": {"coordinates":[7.52592,47.210869],"type":"Point"}
}