{
  "type": "Feature",
  "properties": {
    "iso:country":"CH",
    "sg:address":"Dreinepperstr. 20",
    "sg:city":"M\u00e4nnedorf",
    "sg:orig_category":"Unclassifiable Establishments",
    "sg:phone":"+41 19211269",
    "sg:postcode":"8708",
    "sg:province":"Z\u00fcrich",
    "wof:name":"Kobel Hansueli Gartengestaltung Und H\u00e4cksel-service",
    "wof:placetype":"venue"
},
  "geometry": {"coordinates":[8.6895837784,47.2575111389],"type":"Point"}
}