{
  "type": "Feature",
  "properties": {
    "iso:country":"CH",
    "sg:address":"Bernstrasse 70",
    "sg:city":"Lyss",
    "sg:orig_category":"Herstellung von sonstigen elektrischen Ausr\u00fcstungen",
    "sg:phone":"+41 21 803 12 33",
    "sg:postcode":"3250",
    "sg:province":"Bern",
    "wof:name":"Selectronics, Stoll Erwin",
    "wof:placetype":"venue"
},
  "geometry": {"coordinates":[6.4671559334,46.5077934265],"type":"Point"}
}