{
  "type": "Feature",
  "properties": {
    "iso:country":"CH",
    "sg:address":"Lerchenweg 23",
    "sg:city":"Obergerlafingen",
    "sg:orig_category":"Maurerarbeiten Sonstiger spezialisierter Hoch U Tiefbau",
    "sg:phone":"+41 79 631 71 82",
    "sg:postcode":"4564",
    "sg:province":"Bern",
    "wof:name":"Peter Guazzini Maurergesch\u00e4ft",
    "wof:placetype":"venue"
},
  "geometry": {"coordinates":[7.5863528252,47.1640663147],"type":"Point"}
}