{
  "type": "Feature",
  "properties": {
    "iso:country":"CH",
    "sg:address":"Kreuzstrasse 16",
    "sg:city":"K\u00e4giswil",
    "sg:classifiers":[
        {
            "category":"Manufacturing",
            "subcategory":"Glass & Minerals",
            "type":"Manufacturing & Wholesale Goods"
        }
    ],
    "sg:phone":"+41 41 660 32 33",
    "sg:postcode":"6056",
    "sg:province":"Obwalden",
    "sg:tags":[
        "industrial",
        "working"
    ],
    "wof:name":"Gafner Gmbh",
    "wof:placetype":"venue"
},
  "geometry": {"coordinates":[8.2567024231,46.9141998291],"type":"Point"}
}