{
  "type": "Feature",
  "properties": {
    "iso:country":"CH",
    "sg:address":"Route De La Gruy\u00e8re 10",
    "sg:city":"Fribourg",
    "sg:orig_category":"Bau U Wohngenossenschaften",
    "sg:postcode":"1700",
    "sg:province":"Fribourg",
    "wof:name":"St\u00e9 Coop.d'hab.champs D.font.",
    "wof:placetype":"venue"
},
  "geometry": {"coordinates":[7.142138,46.795319],"type":"Point"}
}