{
  "type": "Feature",
  "properties": {
    "iso:country":"CH",
    "sg:address":"Tschamerie 25",
    "sg:city":"Hasle-r\u00fcegsau",
    "sg:classifiers":[
        {
            "category":"Shopping",
            "subcategory":"Pharmacy",
            "type":"Retail Goods"
        }
    ],
    "sg:phone":"+41 34 460 22 11",
    "sg:postcode":"3415",
    "sg:province":"Bern",
    "sg:tags":[
        "herbal",
        "pharmaceutical"
    ],
    "wof:name":"Phytomed Ag",
    "wof:placetype":"venue"
},
  "geometry": {"coordinates":[7.6364388466,47.0253753662],"type":"Point"}
}