{
  "type": "Feature",
  "properties": {
    "iso:country":"CH",
    "sg:address":"Pilgerstrasse 4",
    "sg:city":"Basel",
    "sg:orig_category":"Detailhandel mit Brot, Back U S\u00fcsswaren",
    "sg:phone":"+41 61 381 20 27",
    "sg:postcode":"4055",
    "sg:province":"Basel-Stadt",
    "wof:name":"K\u00fcbler Backwaren Ag B\u00e4ckerei-konditorei",
    "wof:placetype":"venue"
},
  "geometry": {"coordinates":[7.577309,47.559658],"type":"Point"}
}