{
  "type": "Feature",
  "properties": {
    "iso:country":"CH",
    "sg:address":"Wydackerstrasse 3",
    "sg:city":"Glattbrugg",
    "sg:orig_category":"Kaminbau",
    "sg:phone":"+41 71 659 04 44",
    "sg:postcode":"8152",
    "sg:province":"Z\u00fcrich",
    "wof:name":"Plustec Gmbh Kaminbau",
    "wof:placetype":"venue"
},
  "geometry": {"coordinates":[8.5674104691,47.4297485352],"type":"Point"}
}