{
  "type": "Feature",
  "properties": {
    "addr:full":"Hauptgasse 51 Murten Fribourg 3280",
    "addr:housenumber":"51",
    "addr:postcode":"3280",
    "addr:street":"Hauptgasse",
    "iso:country":"CH",
    "sg:address":"Hauptgasse 51",
    "sg:city":"Murten",
    "sg:classifiers":[
        {
            "category":"Bars & Pubs",
            "type":"Food & Drink"
        }
    ],
    "sg:phone":"+41 26 670 25 65",
    "sg:postcode":"3280",
    "sg:province":"Fribourg",
    "sg:tags":[
        "restaurant"
    ],
    "wof:name":"Restaurant Channe Valaisanne",
    "wof:placetype":"venue"
},
  "geometry": {"coordinates":[7.117971,46.928944],"type":"Point"}
}