{
  "type": "Feature",
  "properties": {
    "iso:country":"CH",
    "sg:address":"Belpstrasse 67 3007 Bern. Postfach",
    "sg:city":"Bern",
    "sg:orig_category":"Herstellung von sonstigen M\u00f6beln",
    "sg:phone":"+41 31 352 56 03",
    "sg:postcode":"3005",
    "sg:province":"Bern",
    "wof:name":"Fritz B\u00fchler Rahmen; Fabr. Bilderhandel. Papeterie.",
    "wof:placetype":"venue"
},
  "geometry": {"coordinates":[7.4312791824,46.9418754578],"type":"Point"}
}