{
  "type": "Feature",
  "properties": {
    "iso:country":"CH",
    "sg:address":"Altes Schulhaus",
    "sg:city":"Niederscherli",
    "sg:orig_category":"Vorschulen, Kinderg\u00e4rten",
    "sg:phone":"+41 31 849 16 37",
    "sg:postcode":"3145",
    "sg:province":"Bern",
    "wof:name":"Kindergarten",
    "wof:placetype":"venue"
},
  "geometry": {"coordinates":[7.3885068893,46.8849906921],"type":"Point"}
}