{
  "type": "Feature",
  "properties": {
    "iso:country":"CH",
    "sg:address":"Kirchackerstrasse 3",
    "sg:city":"Riniken",
    "sg:orig_category":"Softwareentwicklung U beratung Sonstige mit der Informatik verbundene T\u00e4tigkeiten",
    "sg:phone":"+41 56 450 11 35",
    "sg:postcode":"5223",
    "sg:province":"Aargau",
    "wof:name":"Sonderegger Markus Mapa Informatik",
    "wof:placetype":"venue"
},
  "geometry": {"coordinates":[8.187046051,47.4851837158],"type":"Point"}
}