{
  "type": "Feature",
  "properties": {
    "iso:country":"CH",
    "sg:address":"Restaurant Roggengratbad",
    "sg:city":"Wyssachen",
    "sg:orig_category":"Non-Classified Establishments",
    "sg:postcode":"4954",
    "sg:province":"Bern",
    "wof:name":"Heidi Jost",
    "wof:placetype":"venue"
},
  "geometry": {"coordinates":[7.8300428391,47.0758209229],"type":"Point"}
}