{
  "type": "Feature",
  "properties": {
    "iso:country":"CH",
    "sg:address":"Via San Gottardo 17c 6500 Bellinzona Casella Postale 1670",
    "sg:city":"Bellinzona",
    "sg:orig_category":"Automaten Herstellung Elektroinstallation",
    "sg:phone":"+41 91 820 62 62",
    "sg:postcode":"6500",
    "sg:province":"Ticino",
    "wof:name":"Atel Elettroimpianti Ticino Sa",
    "wof:placetype":"venue"
},
  "geometry": {"coordinates":[9.024119,46.194462],"type":"Point"}
}