{
  "type": "Feature",
  "properties": {
    "iso:country":"CH",
    "sg:address":"Rue De Gruy\u00e8res 103",
    "sg:city":"Bulle",
    "sg:orig_category":"Malerei Stukkateurgewerbe, Gipserei U Verputzerei",
    "sg:phone":"+41 26 912 75 62",
    "sg:postcode":"1630",
    "sg:province":"Fribourg",
    "wof:name":"Cl. Marchina & J.-l. Morand Gypserie & Peinture",
    "wof:placetype":"venue"
},
  "geometry": {"coordinates":[7.060874939,46.6126441956],"type":"Point"}
}