{
  "type": "Feature",
  "properties": {
    "iso:country":"CH",
    "sg:address":"Rheinweg 4 8200 Schaffhausen. Postfach 1512",
    "sg:city":"Schaffhausen",
    "sg:orig_category":"Herstellung von sonstigen elektrischen Ausr\u00fcstungen",
    "sg:phone":"+41 81 723 09 80",
    "sg:postcode":"8201",
    "sg:province":"Schaffhausen",
    "wof:name":"Teval Ag Elektronische Ger\u00e4te; Entwicklung, Produktion, Vertrieb Usw.",
    "wof:placetype":"venue"
},
  "geometry": {"coordinates":[9.4189567566,47.0568618774],"type":"Point"}
}