{
  "type": "Feature",
  "properties": {
    "iso:country":"CH",
    "sg:address":"Hardstr. 16 8304 Wallisellen. Postfach",
    "sg:city":"Wallisellen",
    "sg:orig_category":"Reinigungsgewerbe",
    "sg:postcode":"8304",
    "sg:province":"Z\u00fcrich",
    "wof:name":"Grob Paul Ag, Tankrevisionen",
    "wof:placetype":"venue"
},
  "geometry": {"coordinates":[8.5892505646,47.4222068787],"type":"Point"}
}