{
  "type": "Feature",
  "properties": {
    "iso:country":"CH",
    "sg:address":"Winterthurerstrasse 190",
    "sg:city":"Z\u00fcrich",
    "sg:orig_category":"Museen",
    "sg:phone":"+41 12575411",
    "sg:postcode":"8006",
    "sg:province":"Z\u00fcrich",
    "wof:name":"Anthropologisches Museum Der Universit\u00e4t",
    "wof:placetype":"venue"
},
  "geometry": {"coordinates":[8.5450496674,47.3937797546],"type":"Point"}
}