{
  "type": "Feature",
  "properties": {
    "iso:country":"CH",
    "sg:address":"Ariesbach",
    "sg:city":"Fideris",
    "sg:orig_category":"Gewinnung von Kies U Sand Herstellung von sonstigen Produkten aus nichtmetallischen Mineralien",
    "sg:phone":"+41 81 332 11 89",
    "sg:postcode":"7235",
    "sg:province":"Graubunden",
    "wof:name":"Kieswerk Fideris Ag",
    "wof:placetype":"venue"
},
  "geometry": {"coordinates":[9.7427120209,46.9152984619],"type":"Point"}
}