{
  "type": "Feature",
  "properties": {
    "iso:country":"CH",
    "sg:address":"Neue Aarauerstrasse 73a",
    "sg:city":"Suhr",
    "sg:orig_category":"Physiotherapie",
    "sg:phone":"+41 62 824 62 75",
    "sg:postcode":"5034",
    "sg:province":"Aargau",
    "wof:name":"Ingrid Balen Roth Physiotherapie",
    "wof:placetype":"venue"
},
  "geometry": {"coordinates":[8.0626459122,47.3848648071],"type":"Point"}
}