{
  "type": "Feature",
  "properties": {
    "iso:country":"CH",
    "sg:address":"3991",
    "sg:city":"Betten",
    "sg:orig_category":"Sportvereine Sch\u00fctzen",
    "sg:postcode":"3991",
    "sg:province":"Valais",
    "wof:name":"Sch\u00fctzengesellschaft",
    "wof:placetype":"venue"
},
  "geometry": {"coordinates":[8.0718297958,46.3776016235],"type":"Point"}
}