{
  "type": "Feature",
  "properties": {
    "iso:country":"CH",
    "sg:address":"Beaus\u00e9jour 33",
    "sg:city":"Givisiez",
    "sg:orig_category":"Unclassifiable Establishments",
    "sg:postcode":"1762",
    "sg:province":"Fribourg",
    "wof:name":"Phytinvest Sa",
    "wof:placetype":"venue"
},
  "geometry": {"coordinates":[7.1307110786,46.810634613],"type":"Point"}
}