{
  "type": "Feature",
  "properties": {
    "iso:country":"CH",
    "sg:address":"Adelheid-page-strasse 1",
    "sg:city":"Cham",
    "sg:orig_category":"Maler U Glasergewerbe Malerei",
    "sg:phone":"+41 41 780 25 63",
    "sg:postcode":"6330",
    "sg:province":"Zug",
    "wof:name":"Johan Bloetjes Malergesch\u00e4ft",
    "wof:placetype":"venue"
},
  "geometry": {"coordinates":[8.4653720856,47.1812934875],"type":"Point"}
}