{
  "type": "Feature",
  "properties": {
    "iso:country":"CH",
    "sg:address":"Dorfstrasse 30a",
    "sg:city":"Lommiswil",
    "sg:orig_category":"Sanit\u00e4r, Heizungs U L\u00fcftungsinstallation Sanit\u00e4rinstallation",
    "sg:phone":"+41 32 641 12 01",
    "sg:postcode":"4514",
    "sg:province":"Solothurn",
    "wof:name":"Br\u00fcgger Hans",
    "wof:placetype":"venue"
},
  "geometry": {"coordinates":[7.4731388092,47.2289581299],"type":"Point"}
}