{
  "type": "Feature",
  "properties": {
    "iso:country":"CH",
    "sg:address":"Mythenstrasse 32",
    "sg:city":"Einsiedeln",
    "sg:orig_category":"Kauf U Verkauf von Immobilien auf eigene Rechnung",
    "sg:postcode":"8840",
    "sg:province":"Schwyz",
    "wof:name":"Ochsner Adolf Ag",
    "wof:placetype":"venue"
},
  "geometry": {"coordinates":[8.7409915924,47.1251373291],"type":"Point"}
}