{
  "type": "Feature",
  "properties": {
    "iso:country":"CH",
    "sg:address":"3804",
    "sg:city":"Habkern",
    "sg:orig_category":"Personenbef\u00f6rderung im Linienverkehr zu Land",
    "sg:phone":"+41 33 843 12 15",
    "sg:postcode":"3804",
    "sg:province":"Bern",
    "wof:name":"Skilift Habkern-sattelegg Ag",
    "wof:placetype":"venue"
},
  "geometry": {"coordinates":[7.887360096,46.7530593872],"type":"Point"}
}