{
  "type": "Feature",
  "properties": {
    "iso:country":"CH",
    "sg:address":"Hauptstrasse 60",
    "sg:city":"Cazis",
    "sg:orig_category":"Organisationen des Gesundheitswesen",
    "sg:phone":"+41 81 651 23 63",
    "sg:postcode":"7408",
    "sg:province":"Graubunden",
    "wof:name":"Samariterverein Cazis",
    "wof:placetype":"venue"
},
  "geometry": {"coordinates":[9.4303245544,46.7202911377],"type":"Point"}
}