{
  "type": "Feature",
  "properties": {
    "iso:country":"CH",
    "sg:address":"Weihermattstrasse 58",
    "sg:city":"Aarau",
    "sg:orig_category":"G\u00fcterbef\u00f6rderung im Strassenverkehr",
    "sg:phone":"+41 62 822 30 10",
    "sg:postcode":"5000",
    "sg:province":"Aargau",
    "wof:name":"Alois Sch\u00f6nb\u00e4chler Transporte",
    "wof:placetype":"venue"
},
  "geometry": {"coordinates":[8.0608797073,47.3961372375],"type":"Point"}
}