{
  "type": "Feature",
  "properties": {
    "iso:country":"CH",
    "sg:address":"Turnhalleweg",
    "sg:city":"Sch\u00f6ftland",
    "sg:orig_category":"Vorschulen, Kinderg\u00e4rten",
    "sg:phone":"+41 62 721 48 56",
    "sg:postcode":"5040",
    "sg:province":"Aargau",
    "wof:name":"Kindergarten",
    "wof:placetype":"venue"
},
  "geometry": {"coordinates":[8.0513896942,47.3075447083],"type":"Point"}
}