{
  "type": "Feature",
  "properties": {
    "iso:country":"CH",
    "sg:address":"Hirzenstrasse 4",
    "sg:city":"Niederuzwil",
    "sg:orig_category":"Autogaragen Lastwagen and Nutzfahrzeuge",
    "sg:phone":"+41 71 952 77 11",
    "sg:postcode":"9244",
    "sg:province":"St. Gallen",
    "wof:name":"Volvo Trucks (schweiz) Ag Filiale Niederuzwil",
    "wof:placetype":"venue"
},
  "geometry": {"coordinates":[9.148131,47.443115],"type":"Point"}
}