{
  "type": "Feature",
  "properties": {
    "iso:country":"CH",
    "sg:address":"Mola Via Francesco 3",
    "sg:city":"Chiasso",
    "sg:orig_category":"Herstellung von Teilen U Zubeh\u00f6r f\u00fcr Automobile",
    "sg:postcode":"6830",
    "sg:province":"Ticino",
    "wof:name":"Mec Tuning Di Cerulli Monia",
    "wof:placetype":"venue"
},
  "geometry": {"coordinates":[9.0229969025,45.8335342407],"type":"Point"}
}