{
  "type": "Feature",
  "properties": {
    "iso:country":"CH",
    "sg:address":"Bahnhofstrasse 63",
    "sg:city":"Sevelen",
    "sg:orig_category":"Unclassifiable Establishments",
    "sg:postcode":"9475",
    "sg:province":"St. Gallen",
    "wof:name":"Buono Gmbh",
    "wof:placetype":"venue"
},
  "geometry": {"coordinates":[9.4882631302,47.1221237183],"type":"Point"}
}