{
  "type": "Feature",
  "properties": {
    "iso:country":"CH",
    "sg:address":"Freiestrasse 3",
    "sg:city":"Uster",
    "sg:orig_category":"Herstellung von elektrischen Lampen U Leuchten",
    "sg:phone":"+41 79 941 81 20",
    "sg:postcode":"8610",
    "sg:province":"Z\u00fcrich",
    "wof:name":"Planet Of Dreams Gmbh",
    "wof:placetype":"venue"
},
  "geometry": {"coordinates":[8.7200717926,47.3493537903],"type":"Point"}
}