{
  "type": "Feature",
  "properties": {
    "iso:country":"CH",
    "sg:address":"Schindellegistrasse 27",
    "sg:city":"Wollerau",
    "sg:orig_category":"Grosshandel mit landwirtschaftlichen Maschinen U Ger\u00e4ten Herstellung von sonstigen landwirtschaftlic",
    "sg:phone":"+41 79 412 89 83",
    "sg:postcode":"8832",
    "sg:province":"Schwyz",
    "wof:name":"Eggler Karl",
    "wof:placetype":"venue"
},
  "geometry": {"coordinates":[8.7124032974,47.1873130798],"type":"Point"}
}