{
  "type": "Feature",
  "properties": {
    "iso:country":"CH",
    "sg:address":"Seestrasse 51",
    "sg:city":"Berlingen",
    "sg:classifiers":[
        {
            "category":"Restaurant",
            "type":"Food & Drink"
        }
    ],
    "sg:phone":"+41 52 761 13 06",
    "sg:postcode":"8267",
    "sg:province":"Thurgau",
    "wof:name":"Gasthaus Hirschen",
    "wof:placetype":"venue"
},
  "geometry": {"coordinates":[9.016377449,47.6744117737],"type":"Point"}
}