{
  "type": "Feature",
  "properties": {
    "iso:country":"CH",
    "sg:address":"Route De Lausanne",
    "sg:city":"Epautheyres",
    "sg:orig_category":"Diskotheken, Dancings, Night Clubs",
    "sg:phone":"+41 24 435 11 20",
    "sg:postcode":"1417",
    "sg:province":"Vaud",
    "wof:name":"Dancing Le Rendez-vous",
    "wof:placetype":"venue"
},
  "geometry": {"coordinates":[6.6399388313,46.7164115906],"type":"Point"}
}