{
  "type": "Feature",
  "properties": {
    "iso:country":"CH",
    "sg:address":"Via Sogn Pieder 4 7013 Domat/ems. Postfach 92",
    "sg:city":"Domat/ems",
    "sg:orig_category":"Herstellung von Tanks U Sammelbeh\u00e4ltern aus Metall Reinigungsgewerbe",
    "sg:phone":"+41 81 633 34 44",
    "sg:postcode":"7013",
    "sg:province":"Graubunden",
    "wof:name":"Trido-umweltschutz Ag",
    "wof:placetype":"venue"
},
  "geometry": {"coordinates":[9.450548172,46.8354682922],"type":"Point"}
}