{
  "type": "Feature",
  "properties": {
    "iso:country":"CH",
    "sg:address":"B\u00e4raustrasse 101",
    "sg:city":"B\u00e4rau",
    "sg:orig_category":"Handel mit Automobilen",
    "sg:phone":"+41 34 402 60 60",
    "sg:postcode":"3552",
    "sg:province":"Bern",
    "wof:name":"Frey Auto Ag",
    "wof:placetype":"venue"
},
  "geometry": {"coordinates":[7.8140501976,46.9265899658],"type":"Point"}
}