{
  "type": "Feature",
  "properties": {
    "iso:country":"CH",
    "sg:address":"Stationsstrasse 24",
    "sg:city":"Ennetb\u00fcrgen",
    "sg:orig_category":"Verkehrs- and Tourismusb\u00fcros",
    "sg:phone":"+41 41 620 15 13",
    "sg:postcode":"6373",
    "sg:province":"Nidwalden",
    "wof:name":"Verkehrsverein Ennetb\u00fcrgen Herrn Marcel Wegm\u00fcller",
    "wof:placetype":"venue"
},
  "geometry": {"coordinates":[8.4181671143,46.9870948792],"type":"Point"}
}