{
  "type": "Feature",
  "properties": {
    "iso:country":"CH",
    "sg:address":"Rue Des Rochettes 19",
    "sg:city":"Boudry",
    "sg:orig_category":"Markt U Meinungsforschung",
    "sg:phone":"+41 32 842 15 15",
    "sg:postcode":"2017",
    "sg:province":"Neuch\u00e2tel",
    "wof:name":"Vetterli Marketing & Communication",
    "wof:placetype":"venue"
},
  "geometry": {"coordinates":[6.8347048759,46.9482879639],"type":"Point"}
}