{
  "type": "Feature",
  "properties": {
    "iso:country":"CH",
    "sg:address":"Oberdorfstrasse 39 8820 W\u00e4denswil. Postfach 322",
    "sg:city":"W\u00e4denswil",
    "sg:orig_category":"Druck ohne Zeitungsdruck Offsetdruck",
    "sg:phone":"+41 17803060",
    "sg:postcode":"8820",
    "sg:province":"Z\u00fcrich",
    "wof:name":"Frei Druck",
    "wof:placetype":"venue"
},
  "geometry": {"coordinates":[8.6670417786,47.2296600342],"type":"Point"}
}