{
  "type": "Feature",
  "properties": {
    "iso:country":"CH",
    "sg:address":"Centre Gare R.de L'abbe-monnin",
    "sg:city":"Bassecourt",
    "sg:orig_category":"Detailhandel mit Blumen U Pflanzen",
    "sg:phone":"+41 32 426 75 10",
    "sg:postcode":"2854",
    "sg:province":"Jura",
    "wof:name":"Sylvie Donz\u00e9 Au Fleurs Pour Tous",
    "wof:placetype":"venue"
},
  "geometry": {"coordinates":[7.247902,47.33754],"type":"Point"}
}