{
  "type": "Feature",
  "properties": {
    "iso:country":"CH",
    "sg:address":"Zentralstrasse 36",
    "sg:city":"Volketswil",
    "sg:orig_category":"Grosshandel mit B\u00fcromaschinen Grosshandel mit Datenverarbeitungsger\u00e4ten",
    "sg:postcode":"8604",
    "sg:province":"Z\u00fcrich",
    "wof:name":"Urs Schaller Microlan",
    "wof:placetype":"venue"
},
  "geometry": {"coordinates":[8.6882705688,47.3896942139],"type":"Point"}
}