{
  "type": "Feature",
  "properties": {
    "iso:country":"CH",
    "sg:address":"Dreitannenstrasse 31",
    "sg:city":"Olten",
    "sg:orig_category":"Sonstige Aktivit\u00e4ten der nicht-\u00e4rztlichen Medizinalberufe",
    "sg:phone":"+41 33 654 38 87",
    "sg:postcode":"4600",
    "sg:province":"Solothurn",
    "wof:name":"Gertrud Steffen Atemtherapie",
    "wof:placetype":"venue"
},
  "geometry": {"coordinates":[7.6945428848,46.6608581543],"type":"Point"}
}