{
  "type": "Feature",
  "properties": {
    "iso:country":"CH",
    "sg:address":"Friedackerstrasse 14",
    "sg:city":"Z\u00fcrich",
    "sg:classifiers":[
        {
            "category":"Conference Center",
            "type":"Public Place"
        }
    ],
    "sg:phone":"+41 13172060",
    "sg:postcode":"8050",
    "sg:province":"Z\u00fcrich",
    "sg:tags":[
        "audio",
        "system"
    ],
    "wof:name":"Suprag Ag",
    "wof:placetype":"venue"
},
  "geometry": {"coordinates":[8.553363,47.405552],"type":"Point"}
}