{
  "type": "Feature",
  "properties": {
    "iso:country":"CH",
    "sg:address":"Avenue Beauregard 36",
    "sg:city":"Fribourg",
    "sg:orig_category":"Elektroinstallation",
    "sg:phone":"+41 71 913 99 11",
    "sg:postcode":"1700",
    "sg:province":"Fribourg",
    "wof:name":"Steinlin Und Partner Ag",
    "wof:placetype":"venue"
},
  "geometry": {"coordinates":[9.063586235,47.4639091492],"type":"Point"}
}