{
  "type": "Feature",
  "properties": {
    "iso:country":"CH",
    "sg:address":"Rue Des Bossons 88",
    "sg:city":"Petit-lancy",
    "sg:orig_category":"Fotografische Ateliers Fotografisches Gewerbe U fotografische Laboratorien",
    "sg:phone":"+41 22 793 75 28",
    "sg:postcode":"1213",
    "sg:province":"Gen\u00e8ve",
    "wof:name":"Fabien Cruchon Atelier Photographique",
    "wof:placetype":"venue"
},
  "geometry": {"coordinates":[6.1112799644,46.1893997192],"type":"Point"}
}