{
  "type": "Feature",
  "properties": {
    "iso:country":"CH",
    "sg:address":"Seestrandweg 39",
    "sg:city":"Erlach",
    "sg:orig_category":"Innendekorationsateliers",
    "sg:phone":"+41 32 338 19 15",
    "sg:postcode":"3235",
    "sg:province":"Bern",
    "wof:name":"Heinz Franz Tapezierer-dekorateur",
    "wof:placetype":"venue"
},
  "geometry": {"coordinates":[7.0997591019,47.0440368652],"type":"Point"}
}