{
  "type": "Feature",
  "properties": {
    "iso:country":"CH",
    "sg:address":"Aarauerstrasse 14",
    "sg:city":"Erlinsbach",
    "sg:orig_category":"Detailhandel mit Blumen U Pflanzen Fachdetailhandel in Verkaufsr\u00e4umen",
    "sg:phone":"+41 62 844 49 97",
    "sg:postcode":"5018",
    "sg:province":"Solothurn",
    "wof:name":"Floristica, Wermelinger Sandra",
    "wof:placetype":"venue"
},
  "geometry": {"coordinates":[8.011437,47.397057],"type":"Point"}
}