{
  "type": "Feature",
  "properties": {
    "iso:country":"CH",
    "sg:address":"Grossacher 34a",
    "sg:city":"Krauchthal",
    "sg:orig_category":"K\u00fcnstlerische U schriftstellerische T\u00e4tigkeiten U Darbietungen Orchester, Ch\u00f6re, Musiker",
    "sg:phone":"+41 79 420 48 89",
    "sg:postcode":"3326",
    "sg:province":"Bern",
    "wof:name":"Rubbernecks Country & Rock'n'roll",
    "wof:placetype":"venue"
},
  "geometry": {"coordinates":[8.8566503525,47.1938552856],"type":"Point"}
}