{
  "type": "Feature",
  "properties": {
    "iso:country":"CH",
    "sg:address":"R\u00fctschistrasse 26",
    "sg:city":"Z\u00fcrich",
    "sg:orig_category":"Interessenvertretungen",
    "sg:postcode":"8057",
    "sg:province":"Z\u00fcrich",
    "wof:name":"Schweizerische Tinnitus-liga (stl)",
    "wof:placetype":"venue"
},
  "geometry": {"coordinates":[8.5313186646,47.3940238953],"type":"Point"}
}