{
  "type": "Feature",
  "properties": {
    "iso:country":"CH",
    "sg:address":"Quartier St-maurice",
    "sg:city":"Champagne",
    "sg:orig_category":"Geb\u00e4ude, Wohnungsreinigung Sonstiges Reinigungsgewerbe",
    "sg:phone":"+41 24 436 24 36",
    "sg:postcode":"1424",
    "sg:province":"Vaud",
    "wof:name":"Eric Polo Nettoyage & D\u00e9sinfection",
    "wof:placetype":"venue"
},
  "geometry": {"coordinates":[6.6576800346,46.8356246948],"type":"Point"}
}