{
  "type": "Feature",
  "properties": {
    "iso:country":"CH",
    "sg:address":"Brunnmattstrasse 15",
    "sg:city":"Th\u00f6rishaus",
    "sg:orig_category":"Herstellung von Platten, Folien, Schl\u00e4uchen U Profilen aus Kunststoff",
    "sg:phone":"+41 31 888 28 28",
    "sg:postcode":"3174",
    "sg:province":"Bern",
    "wof:name":"Lichtfolien Technologie Ag",
    "wof:placetype":"venue"
},
  "geometry": {"coordinates":[7.3493680954,46.8907928467],"type":"Point"}
}