{
  "type": "Feature",
  "properties": {
    "iso:country":"CH",
    "sg:address":"Le Ch\u00e2telard",
    "sg:city":"Pailly",
    "sg:orig_category":"Sportvereine Eissport Curling",
    "sg:phone":"+41 21 887 70 43",
    "sg:postcode":"1416",
    "sg:province":"Vaud",
    "wof:name":"M. Federico & D. Andreani Lausanne Cc & Ouchy",
    "wof:placetype":"venue"
},
  "geometry": {"coordinates":[6.6741042137,46.7007598877],"type":"Point"}
}