{
  "type": "Feature",
  "properties": {
    "addr:full":"Muristrasse 8 3000 Bern. Postfach Bern Bern 3005",
    "addr:housenumber":"8",
    "addr:postcode":"3000;postfach;3005",
    "addr:street":"Muristrasse",
    "iso:country":"CH",
    "sg:address":"Muristrasse 8 3000 Bern. Postfach",
    "sg:city":"Bern",
    "sg:orig_category":"Allgemeinbildende weiterf\u00fchrende Schulen",
    "sg:postcode":"3005",
    "sg:province":"Bern",
    "wof:name":"Campus Muristalden Ag",
    "wof:placetype":"venue"
},
  "geometry": {"coordinates":[7.459412,46.944508],"type":"Point"}
}