{
  "type": "Feature",
  "properties": {
    "iso:country":"CH",
    "sg:address":"Sonnenbergstrasse 19",
    "sg:city":"Birsfelden",
    "sg:orig_category":"Primarschulen",
    "sg:phone":"+41 61 312 22 56",
    "sg:postcode":"4127",
    "sg:province":"Basel-Landschaft",
    "wof:name":"Primarschule Sternenfeld",
    "wof:placetype":"venue"
},
  "geometry": {"coordinates":[7.6290268898,47.5561103821],"type":"Point"}
}