{
  "type": "Feature",
  "properties": {
    "iso:country":"CH",
    "sg:address":"Schmittenmattstrasse 14",
    "sg:city":"Schwyz",
    "sg:orig_category":"Primarschulen",
    "sg:phone":"+41 41 811 22 10",
    "sg:postcode":"6430",
    "sg:province":"Schwyz",
    "wof:name":"Primarschule L\u00fccken",
    "wof:placetype":"venue"
},
  "geometry": {"coordinates":[8.6493673325,47.0195426941],"type":"Point"}
}