{
  "type": "Feature",
  "properties": {
    "iso:country":"CH",
    "sg:address":"2943",
    "sg:city":"Vendlincourt",
    "sg:classifiers":[
        {
            "category":"Home & Garden",
            "subcategory":"Furniture",
            "type":"Retail Goods"
        }
    ],
    "sg:phone":"+41 32 474 04 04",
    "sg:postcode":"2943",
    "sg:province":"Jura",
    "sg:tags":[
        "wood"
    ],
    "wof:name":"A. Et C. Corbat Sa Industrie Du Bois",
    "wof:placetype":"venue"
},
  "geometry": {"coordinates":[7.1505169868,47.4510688782],"type":"Point"}
}