{
  "type": "Feature",
  "properties": {
    "iso:country":"CH",
    "sg:address":"G\u00f6tze 7 8197 Rafz. Postfach",
    "sg:city":"Rafz",
    "sg:orig_category":"Verarbeitung von Tee U Kaffee",
    "sg:postcode":"8197",
    "sg:province":"Z\u00fcrich",
    "wof:name":"Creme Cafe Siconolfi Kaffee U. -maschinen; Handel",
    "wof:placetype":"venue"
},
  "geometry": {"coordinates":[8.5416593552,47.6128730774],"type":"Point"}
}