{
  "type": "Feature",
  "properties": {
    "iso:country":"CH",
    "sg:address":"Im Ziel 35 8125 Zollikerberg. Postfach",
    "sg:city":"Forch",
    "sg:orig_category":"Detailhandel mit elektrischen Haushalts-,Radio U Fernsehger\u00e4ten sowie Musikinstrumenten",
    "sg:phone":"+41 71 761 26 27",
    "sg:postcode":"8127",
    "sg:province":"Z\u00fcrich",
    "wof:name":"Radio-tv Hasler",
    "wof:placetype":"venue"
},
  "geometry": {"coordinates":[9.5702228546,47.3238182068],"type":"Point"}
}