{
  "type": "Feature",
  "properties": {
    "iso:country":"CH",
    "sg:address":"Erzgrubenweg 1 5000 Aarau. Postfach",
    "sg:city":"Aarau",
    "sg:orig_category":"Non-Classified Establishments",
    "sg:postcode":"5000",
    "sg:province":"Aargau",
    "wof:name":"Oezl\u00fc Il Mulino Pizza-kurier U. Imbiss-stand",
    "wof:placetype":"venue"
},
  "geometry": {"coordinates":[8.0404176712,47.4009475708],"type":"Point"}
}