{
  "type": "Feature",
  "properties": {
    "iso:country":"CH",
    "sg:address":"Altstalden 129",
    "sg:city":"Unterb\u00f6zberg",
    "sg:orig_category":"G\u00fcterbef\u00f6rderung im Strassenverkehr",
    "sg:postcode":"5224",
    "sg:province":"Aargau",
    "wof:name":"D\u00e4twiler-transporte",
    "wof:placetype":"venue"
},
  "geometry": {"coordinates":[8.1388301849,47.4870567322],"type":"Point"}
}