{
  "type": "Feature",
  "properties": {
    "iso:country":"CH",
    "sg:address":"Rue De La Grenade 8",
    "sg:city":"Aubonne",
    "sg:orig_category":"Handelsvermittlung U Grosshandel Sonstiger Grosshandel",
    "sg:phone":"+41 21 808 57 47",
    "sg:postcode":"1170",
    "sg:province":"Vaud",
    "wof:name":"Gxa China Trading S\u00e0rl",
    "wof:placetype":"venue"
},
  "geometry": {"coordinates":[6.3908119202,46.4961166382],"type":"Point"}
}