{
  "type": "Feature",
  "properties": {
    "iso:country":"CH",
    "sg:address":"Hardgutstrasse 30",
    "sg:city":"Z\u00fcrich",
    "sg:orig_category":"Fahrschulen, Flugschulen",
    "sg:phone":"+41 14911681",
    "sg:postcode":"8048",
    "sg:province":"Z\u00fcrich",
    "wof:name":"Markus W\u00fcrgler Autofahrschule",
    "wof:placetype":"venue"
},
  "geometry": {"coordinates":[8.5016355515,47.383682251],"type":"Point"}
}