{
  "type": "Feature",
  "properties": {
    "iso:country":"CH",
    "sg:address":"Neuhushof 6",
    "sg:city":"Littau",
    "sg:orig_category":"Organisationen des Gesundheitswesen",
    "sg:phone":"+41 55 246 18 21",
    "sg:postcode":"6014",
    "sg:province":"Luzern",
    "wof:name":"Samariterverein",
    "wof:placetype":"venue"
},
  "geometry": {"coordinates":[8.9413003922,47.2884101868],"type":"Point"}
}