{
  "type": "Feature",
  "properties": {
    "iso:country":"CH",
    "sg:address":"Via Tello 6",
    "sg:city":"Domat/ems",
    "sg:orig_category":"Erschliessung von Grundst\u00fccken",
    "sg:postcode":"7013",
    "sg:province":"Graubunden",
    "wof:name":"Baugenossenschaft Calanda Domat/ems",
    "wof:placetype":"venue"
},
  "geometry": {"coordinates":[9.4440736771,46.8354721069],"type":"Point"}
}