{
  "type": "Feature",
  "properties": {
    "iso:country":"CH",
    "sg:address":"Schlatterstrasse",
    "sg:city":"Schlatt",
    "sg:orig_category":"Sportvereine Sch\u00fctzen",
    "sg:postcode":"8418",
    "sg:province":"Z\u00fcrich",
    "wof:name":"Bezirkssch\u00fctzenverband",
    "wof:placetype":"venue"
},
  "geometry": {"coordinates":[8.8312902451,47.6252708435],"type":"Point"}
}