{
  "type": "Feature",
  "properties": {
    "iso:country":"CH",
    "sg:address":"Bahnhofplatz 3",
    "sg:city":"Biel/bienne",
    "sg:orig_category":"Zahnarztpraxen",
    "sg:phone":"+41 32 322 21 54",
    "sg:postcode":"2502",
    "sg:province":"Bern",
    "wof:name":"Dr. Med. Dent. Jean Erler Zahnarzt",
    "wof:placetype":"venue"
},
  "geometry": {"coordinates":[7.2421541214,47.1339607239],"type":"Point"}
}