{
  "type": "Feature",
  "properties": {
    "iso:country":"CH",
    "sg:address":"Schulstrasse 6 9323 Steinach. Postfach",
    "sg:city":"Steinach",
    "sg:orig_category":"Finanzierungsinstitutionen",
    "sg:postcode":"9323",
    "sg:province":"St. Gallen",
    "wof:name":"Stonefinance Ag Investitionen Usw.",
    "wof:placetype":"venue"
},
  "geometry": {"coordinates":[9.441901207,47.5027275085],"type":"Point"}
}