{
  "type": "Feature",
  "properties": {
    "iso:country":"CH",
    "sg:address":"Via Dei Casagrande 49",
    "sg:city":"Breganzona",
    "sg:orig_category":"Allgemeiner Hoch U Tiefbau Strassenbau",
    "sg:postcode":"6932",
    "sg:province":"Ticino",
    "wof:name":"Theiler Rolf",
    "wof:placetype":"venue"
},
  "geometry": {"coordinates":[8.223583,47.131149],"type":"Point"}
}