{
  "type": "Feature",
  "properties": {
    "addr:full":"Storcheng\u00e4sschen 6 3011 Bern. Postfach 6263 Bern Bern 3001",
    "addr:housenumber":"6",
    "addr:postcode":"3011;postfach 6263 bern;3001",
    "addr:street":"Storchengaesschen",
    "iso:country":"CH",
    "sg:address":"Storcheng\u00e4sschen 6 3011 Bern. Postfach 6263",
    "sg:city":"Bern",
    "sg:orig_category":"Advokaturb\u00fcros",
    "sg:phone":"+41 31 312 00 33",
    "sg:postcode":"3001",
    "sg:province":"Bern",
    "wof:name":"Peter W\u00fcthrich Advokaturb\u00fcro",
    "wof:placetype":"venue"
},
  "geometry": {"coordinates":[7.4421,46.947521],"type":"Point"}
}