{
  "type": "Feature",
  "properties": {
    "iso:country":"CH",
    "sg:address":"Tannew\u00e4g 13",
    "sg:city":"Rafz",
    "sg:orig_category":"Dachdeckerei Kaminfeger",
    "sg:phone":"+41 18690288",
    "sg:postcode":"8197",
    "sg:province":"Z\u00fcrich",
    "wof:name":"Thomas Schweizer Dachdecker-& Kaminfegergesch.",
    "wof:placetype":"venue"
},
  "geometry": {"coordinates":[8.539484,47.608215],"type":"Point"}
}