{
  "type": "Feature",
  "properties": {
    "iso:country":"CH",
    "sg:address":"Limmatquai 4",
    "sg:city":"Z\u00fcrich",
    "sg:classifiers":[
        {
            "category":"Banks & Credit Unions",
            "subcategory":"Bank",
            "type":"Services"
        }
    ],
    "sg:phone":"+41 22 704 11 11",
    "sg:postcode":"8024",
    "sg:province":"Z\u00fcrich",
    "wof:name":"Banque Audi (suisse) Sa",
    "wof:placetype":"venue"
},
  "geometry": {"coordinates":[6.13993,46.203819],"type":"Point"}
}