{
  "type": "Feature",
  "properties": {
    "iso:country":"CH",
    "sg:address":"Gartenstrasse 20 2500 Biel/bienne. Postfach",
    "sg:city":"Biel/bienne",
    "sg:orig_category":"Herstellung von konfektionierten Textilwaren ohne Bekleidung",
    "sg:postcode":"2503",
    "sg:province":"Bern",
    "wof:name":"Von Dach H. Haute Couture.",
    "wof:placetype":"venue"
},
  "geometry": {"coordinates":[7.2488012314,47.137336731],"type":"Point"}
}