{
  "type": "Feature",
  "properties": {
    "iso:country":"CH",
    "sg:address":"W\u00fcrenloserstrasse 2 8956 Killwangen. Postfach",
    "sg:city":"Killwangen",
    "sg:orig_category":"Instandhaltung U Reparatur von Automobilen",
    "sg:postcode":"8956",
    "sg:province":"Aargau",
    "wof:name":"Carrosserie Denia Jos\u00e9",
    "wof:placetype":"venue"
},
  "geometry": {"coordinates":[8.3580169678,47.4327926636],"type":"Point"}
}