{
  "type": "Feature",
  "properties": {
    "iso:country":"CH",
    "sg:address":"Avenue C.-f.-ramuz 47",
    "sg:city":"Pully",
    "sg:orig_category":"Rechtsberatung",
    "sg:phone":"+41 21 729 03 57",
    "sg:postcode":"1009",
    "sg:province":"Vaud",
    "wof:name":"Eschle Urs",
    "wof:placetype":"venue"
},
  "geometry": {"coordinates":[6.6491570473,46.5094680786],"type":"Point"}
}