{
  "type": "Feature",
  "properties": {
    "iso:country":"CH",
    "sg:address":"Landshutstrasse 11 3315 B\u00e4tterkinden. Postfach 45",
    "sg:city":"B\u00e4tterkinden",
    "sg:orig_category":"Architekturb\u00fcros",
    "sg:phone":"+41 32 665 30 81",
    "sg:postcode":"3315",
    "sg:province":"Bern",
    "wof:name":"Peter Zaugg Architekturb\u00fcro",
    "wof:placetype":"venue"
},
  "geometry": {"coordinates":[7.541192,47.13097],"type":"Point"}
}