{
  "type": "Feature",
  "properties": {
    "iso:country":"CH",
    "sg:address":"Kasernenstrasse 47 7000 Chur. Postfach",
    "sg:city":"Chur",
    "sg:orig_category":"Herstellung von sonstigen Metallwaren",
    "sg:phone":"+41 79 308 20 51",
    "sg:postcode":"7000",
    "sg:province":"Graubunden",
    "wof:name":"Broder Tech Abdichtungen Von Beton",
    "wof:placetype":"venue"
},
  "geometry": {"coordinates":[9.5233440399,46.8467330933],"type":"Point"}
}