{
  "type": "Feature",
  "properties": {
    "iso:country":"CH",
    "sg:address":"Via Rancate",
    "sg:city":"Ligornetto",
    "sg:orig_category":"Gartenbau",
    "sg:phone":"+41 91 647 09 46",
    "sg:postcode":"6853",
    "sg:province":"Ticino",
    "wof:name":"Mauro Lurati Costruzione & Manut.giardini",
    "wof:placetype":"venue"
},
  "geometry": {"coordinates":[8.9517450333,45.8628311157],"type":"Point"}
}