{
  "type": "Feature",
  "properties": {
    "iso:country":"CH",
    "sg:address":"9622",
    "sg:city":"Krinau",
    "sg:orig_category":"Primarschulen",
    "sg:phone":"+41 71 447 84 12",
    "sg:postcode":"9622",
    "sg:province":"St. Gallen",
    "wof:name":"Primarschule",
    "wof:placetype":"venue"
},
  "geometry": {"coordinates":[9.2270298004,47.1988601685],"type":"Point"}
}