{
  "type": "Feature",
  "properties": {
    "iso:country":"CH",
    "sg:address":"Oberibergerstr. 24",
    "sg:city":"Unteriberg",
    "sg:classifiers":[
        {
            "category":"Banks & Credit Unions",
            "subcategory":"Bank",
            "type":"Services"
        }
    ],
    "sg:phone":"+41 61 851 13 48",
    "sg:postcode":"8842",
    "sg:province":"Schwyz",
    "wof:name":"Raiffeisenbank Zeiningen-zuzgen",
    "wof:placetype":"venue"
},
  "geometry": {"coordinates":[7.87236,47.542671],"type":"Point"}
}