{
  "type": "Feature",
  "properties": {
    "iso:country":"CH",
    "sg:address":"Ronc\u00e0a",
    "sg:city":"Lugaggia",
    "sg:orig_category":"Allgemeiner Gartenbau Blumen U Zierpflanzenbau",
    "sg:phone":"+41 91 943 16 46",
    "sg:postcode":"6953",
    "sg:province":"Ticino",
    "wof:name":"Hans Andreas Hofer Fioricoltura-vivaio",
    "wof:placetype":"venue"
},
  "geometry": {"coordinates":[8.97085,46.055481],"type":"Point"}
}