{
  "type": "Feature",
  "properties": {
    "iso:country":"CH",
    "sg:address":"Rue De Plandodin",
    "sg:city":"Saint-germain",
    "sg:orig_category":"G\u00fcterbef\u00f6rderung im Strassenverkehr",
    "sg:phone":"+41 27 395 10 03",
    "sg:postcode":"1965",
    "sg:province":"Valais",
    "wof:name":"H\u00e9ritier Roland",
    "wof:placetype":"venue"
},
  "geometry": {"coordinates":[7.3511247635,46.2515602112],"type":"Point"}
}