{
  "type": "Feature",
  "properties": {
    "iso:country":"CH",
    "sg:address":"Lindenstrasse 114",
    "sg:city":"Effretikon",
    "sg:orig_category":"Steuerberatung",
    "sg:phone":"+41 32 954 18 74",
    "sg:postcode":"8307",
    "sg:province":"Z\u00fcrich",
    "wof:name":"Rettenmund A. Fidufisc Sa, Succursale Les Breuleux",
    "wof:placetype":"venue"
},
  "geometry": {"coordinates":[7.0058679581,47.2111053467],"type":"Point"}
}