{
  "type": "Feature",
  "properties": {
    "addr:full":"Casa Del Frate Via Losone Ticino 6616",
    "addr:postcode":"6616",
    "addr:street":"Via Losone Ticino",
    "iso:country":"CH",
    "sg:address":"Casa Del Frate Via",
    "sg:city":"Losone",
    "sg:orig_category":"Allgemeiner Hoch U Tiefbau",
    "sg:phone":"+41 91 791 78 92",
    "sg:postcode":"6616",
    "sg:province":"Ticino",
    "wof:name":"Incogest Sa",
    "wof:placetype":"venue"
},
  "geometry": {"coordinates":[8.75584,46.176739],"type":"Point"}
}