{
  "type": "Feature",
  "properties": {
    "iso:country":"CH",
    "sg:address":"Boden",
    "sg:city":"Engelberg",
    "sg:orig_category":"Zimmerei, Dachdeckerei, Bauspenglerei U Abdichtung",
    "sg:postcode":"6390",
    "sg:province":"Obwalden",
    "wof:name":"Spenglerei Geisser M. Gmbh",
    "wof:placetype":"venue"
},
  "geometry": {"coordinates":[8.3862457275,46.823764801],"type":"Point"}
}