{
  "type": "Feature",
  "properties": {
    "iso:country":"CH",
    "sg:address":"Rosenstrasse 1",
    "sg:city":"Winterthur",
    "sg:orig_category":"Maturit\u00e4tsschulen, Lehrerseminarien",
    "sg:phone":"+41 52 260 03 03",
    "sg:postcode":"8400",
    "sg:province":"Z\u00fcrich",
    "wof:name":"Kantonsschule B\u00fcelrain Wirtschaftsgym.& Handelsschule",
    "wof:placetype":"venue"
},
  "geometry": {"coordinates":[8.7307672501,47.4957809448],"type":"Point"}
}