{
  "type": "Feature",
  "properties": {
    "iso:country":"CH",
    "sg:address":"1987",
    "sg:city":"M\u00e2che",
    "sg:orig_category":"S\u00e4ge, Hobel U Holzimpr\u00e4gnierwerke",
    "sg:phone":"+41 27 281 17 69",
    "sg:postcode":"1987",
    "sg:province":"Valais",
    "wof:name":"Les Hoirs De Pralong Camille & Cie",
    "wof:placetype":"venue"
},
  "geometry": {"coordinates":[7.3923749924,46.1570167542],"type":"Point"}
}