{
  "type": "Feature",
  "properties": {
    "iso:country":"CH",
    "sg:address":"4410",
    "sg:city":"Liestal",
    "sg:orig_category":"Sportvereine Hornussen",
    "sg:phone":"+41 61 903 03 19",
    "sg:postcode":"4410",
    "sg:province":"Basel-Landschaft",
    "wof:name":"Hornussergesellschaft",
    "wof:placetype":"venue"
},
  "geometry": {"coordinates":[7.7324171066,47.485458374],"type":"Point"}
}