{
  "type": "Feature",
  "properties": {
    "iso:country":"CH",
    "sg:address":"Avenue Du Ch\u00e2teau 81",
    "sg:city":"Prilly",
    "sg:orig_category":"Sportvereine Ballsport Tischtennis",
    "sg:phone":"+41 21 634 19 31",
    "sg:postcode":"1008",
    "sg:province":"Vaud",
    "wof:name":"Ctt Olympic",
    "wof:placetype":"venue"
},
  "geometry": {"coordinates":[6.6021060944,46.540977478],"type":"Point"}
}