{
  "type": "Feature",
  "properties": {
    "addr:full":"Krebsweg 14 Nidau Bern 2560",
    "addr:housenumber":"14",
    "addr:postcode":"2560",
    "addr:street":"Krebsweg;Bern",
    "iso:country":"CH",
    "sg:address":"Krebsweg 14",
    "sg:city":"Nidau",
    "sg:orig_category":"Datenverarbeitungsdienste Softwareentwicklung U beratung",
    "sg:phone":"+41 32 331 89 80",
    "sg:postcode":"2560",
    "sg:province":"Bern",
    "wof:name":"Kurt Rothenb\u00fchler Datentechnik",
    "wof:placetype":"venue"
},
  "geometry": {"coordinates":[7.246413,47.123001],"type":"Point"}
}