{
  "type": "Feature",
  "properties": {
    "addr:full":"Rue Du Lion D'or 6 Lausanne Vaud 1003",
    "addr:housenumber":"6",
    "addr:postcode":"1003",
    "addr:street":"Rue Du Lion D'Or",
    "iso:country":"CH",
    "sg:address":"Rue Du Lion D'or 6",
    "sg:city":"Lausanne",
    "sg:classifiers":[
        {
            "category":"Banks & Credit Unions",
            "subcategory":"Bank",
            "type":"Services"
        }
    ],
    "sg:phone":"+41 21203311",
    "sg:postcode":"1003",
    "sg:province":"Vaud",
    "wof:name":"Hofstetter, Landolt & Cie Banquiers",
    "wof:placetype":"venue"
},
  "geometry": {"coordinates":[6.63045,46.519989],"type":"Point"}
}