{
  "type": "Feature",
  "properties": {
    "iso:country":"CH",
    "sg:address":"Ecureuils Impasse Des 9b 1763 Granges-paccot. Postfach",
    "sg:city":"Granges-paccot",
    "sg:orig_category":"Interessenvertretungen",
    "sg:phone":"+41 26 466 34 44",
    "sg:postcode":"1763",
    "sg:province":"Fribourg",
    "wof:name":"Fondation Antiglio Marc \u00ables Chemins De Fer Du Kaeserberg\u00bb Cr\u00e9er, Maintenir Une Espace Permanent, Consacr\u00e9 \u00e0 La R\u00e9alisation, La Mise En Valeur De R\u00e9seaux Miniatures, Notamm. En \u00e9cartement Hom Etc",
    "wof:placetype":"venue"
},
  "geometry": {"coordinates":[7.1423649788,46.8250312805],"type":"Point"}
}