{
  "type": "Feature",
  "properties": {
    "iso:country":"CH",
    "sg:address":"Schiblerweg 2",
    "sg:city":"Asp",
    "sg:orig_category":"Innenausbau",
    "sg:phone":"+41 62 822 98 33",
    "sg:postcode":"5025",
    "sg:province":"Aargau",
    "wof:name":"W. & R. Kaufmann Ag Innenausbau & Treppenbau",
    "wof:placetype":"venue"
},
  "geometry": {"coordinates":[8.0493745804,47.4453430176],"type":"Point"}
}