{
  "type": "Feature",
  "properties": {
    "iso:country":"CH",
    "sg:address":"Sagiweg 3",
    "sg:city":"Derendingen",
    "sg:orig_category":"Softwareentwicklung U beratung",
    "sg:phone":"+41 32 682 07 72",
    "sg:postcode":"4552",
    "sg:province":"Solothurn",
    "wof:name":"Qprove Ag",
    "wof:placetype":"venue"
},
  "geometry": {"coordinates":[7.5864200592,47.1895027161],"type":"Point"}
}