{
  "type": "Feature",
  "properties": {
    "iso:country":"CH",
    "sg:address":"Hofackerstrasse 13a 8032 Z\u00fcrich 32 Zust. Postfach 8032 Z\u00fcrich",
    "sg:city":"Zust",
    "sg:orig_category":"Werbung",
    "sg:phone":"+41 13915595",
    "sg:postcode":"32",
    "wof:name":"Simmen Wirth & Partner Ag",
    "wof:placetype":"venue"
},
  "geometry": {"coordinates":[8.5677509308,47.3410224915],"type":"Point"}
}