{
  "type": "Feature",
  "properties": {
    "iso:country":"CH",
    "sg:address":"Place La",
    "sg:city":"Ch\u00e2teau-d'oex",
    "sg:classifiers":[
        {
            "category":"Travel",
            "subcategory":"Hotels & Motels",
            "type":"Entertainment"
        }
    ],
    "sg:postcode":"1837",
    "sg:tags":[
        "hotels",
        "mit",
        "restaurant"
    ],
    "wof:name":"Pittet Julien Et Metral Rapha\u00ebl",
    "wof:placetype":"venue"
},
  "geometry": {"coordinates":[-118.1657333374,34.0966873169],"type":"Point"}
}