{
  "type": "Feature",
  "properties": {
    "iso:country":"CH",
    "sg:address":"Sonnmattstrasse 18",
    "sg:city":"Unteriberg",
    "sg:orig_category":"Allgemeiner Hoch U Tiefbau",
    "sg:postcode":"8842",
    "sg:province":"Schwyz",
    "wof:name":"Bega Berggastst\u00e4tten Ag",
    "wof:placetype":"venue"
},
  "geometry": {"coordinates":[8.803166,47.064293],"type":"Point"}
}