{
  "type": "Feature",
  "properties": {
    "iso:country":"CH",
    "sg:address":"Haberdarre",
    "sg:city":"Grindelwald",
    "sg:orig_category":"RESTAURANTS: TEA-ROOMS",
    "sg:postcode":"3818",
    "sg:province":"Bern",
    "wof:name":"Frau Brigitte Oberstar",
    "wof:placetype":"venue"
},
  "geometry": {"coordinates":[9.0415382385,47.4681472778],"type":"Point"}
}