{
  "type": "Feature",
  "properties": {
    "iso:country":"CH",
    "sg:address":"Sch\u00fctzenstrasse 5c",
    "sg:city":"Steffisburg",
    "sg:orig_category":"Grosshandel mit medizinischen U orthop\u00e4dischen Artikeln",
    "sg:phone":"+41 33 437 81 74",
    "sg:postcode":"3612",
    "sg:province":"Bern",
    "wof:name":"A & K Engineering K.ketterer Med.-techn.einrichtungen",
    "wof:placetype":"venue"
},
  "geometry": {"coordinates":[7.6309762001,46.7880020142],"type":"Point"}
}