{
  "type": "Feature",
  "properties": {
    "iso:country":"CH",
    "sg:address":"Baselstrasse 46",
    "sg:city":"Luzern",
    "sg:orig_category":"Herstellung von sonstigen elektrischen Ausr\u00fcstungen",
    "sg:phone":"+41 41 240 22 08",
    "sg:postcode":"6003",
    "sg:province":"Luzern",
    "wof:name":"Sigrist Charles",
    "wof:placetype":"venue"
},
  "geometry": {"coordinates":[8.2945632935,47.0535087585],"type":"Point"}
}