{
  "type": "Feature",
  "properties": {
    "iso:country":"CH",
    "sg:address":"Meiholzstrasse 3",
    "sg:city":"Ottenbach",
    "sg:orig_category":"Malerei",
    "sg:phone":"+41 71 999 18 55",
    "sg:postcode":"8913",
    "sg:province":"Z\u00fcrich",
    "wof:name":"Notker Koller Malergesch\u00e4ft",
    "wof:placetype":"venue"
},
  "geometry": {"coordinates":[9.2849197388,47.1935844421],"type":"Point"}
}