{
  "type": "Feature",
  "properties": {
    "iso:country":"CH",
    "sg:address":"Scheibenackerstrasse 16",
    "sg:city":"St.gallen",
    "sg:classifiers":[
        {
            "category":"Restaurant",
            "type":"Food & Drink"
        }
    ],
    "sg:phone":"+41 71 245 17 87",
    "sg:postcode":"9000",
    "sg:province":"St. Gallen",
    "wof:name":"Restaurant Chesa Antica",
    "wof:placetype":"venue"
},
  "geometry": {"coordinates":[9.3915939331,47.4294128418],"type":"Point"}
}