{
  "type": "Feature",
  "properties": {
    "addr:full":"Rue Du Temple 2 Ch\u00e2telard-lutry Vaud 1095",
    "addr:housenumber":"2",
    "addr:postcode":"1095",
    "addr:street":"Rue Du Temple",
    "iso:country":"CH",
    "sg:address":"Rue Du Temple 2",
    "sg:city":"Ch\u00e2telard-lutry",
    "sg:orig_category":"Architektur U Ingenieurb\u00fcros Architekturb\u00fcros",
    "sg:phone":"+41 21 791 20 40",
    "sg:postcode":"1095",
    "sg:province":"Vaud",
    "wof:name":"Atelier D'architecture Rickli Demaurex Kissling Sa",
    "wof:placetype":"venue"
},
  "geometry": {"coordinates":[6.686996,46.502487],"type":"Point"}
}