{
  "type": "Feature",
  "properties": {
    "iso:country":"CH",
    "sg:address":"Stadelhoferstrasse 40 8304 Wallisellen. Postfach",
    "sg:city":"Z\u00fcrich",
    "sg:orig_category":"Wirtschaftspr\u00fcfung, Steuerberatung U Treuhand",
    "sg:postcode":"8001",
    "sg:province":"Z\u00fcrich",
    "wof:name":"Jusfidag Treuhand Und Verwaltungs Ag",
    "wof:placetype":"venue"
},
  "geometry": {"coordinates":[8.5934362411,47.4130439758],"type":"Point"}
}