{
  "type": "Feature",
  "properties": {
    "iso:country":"CH",
    "sg:address":"Riedtalstrasse 14",
    "sg:city":"Zofingen",
    "sg:orig_category":"Grosshandel mit Eisenwaren sowie Installationsbedarf f\u00fcr Gas, Wasser U Heizung",
    "sg:phone":"+41 81 330 14 17",
    "sg:postcode":"4800",
    "sg:province":"Aargau",
    "wof:name":"Blue Fan W\u00e4rmetechnik Ag",
    "wof:placetype":"venue"
},
  "geometry": {"coordinates":[9.5032701492,47.011554718],"type":"Point"}
}