{
  "type": "Feature",
  "properties": {
    "iso:country":"CH",
    "sg:address":"Seetalstrasse 9",
    "sg:city":"Seon",
    "sg:orig_category":"Fachdetailhandel in Verkaufsr\u00e4umen",
    "sg:phone":"+41 62 775 11 33",
    "sg:postcode":"5703",
    "sg:province":"Aargau",
    "wof:name":"Walti Spielwaren",
    "wof:placetype":"venue"
},
  "geometry": {"coordinates":[8.1604537964,47.3531494141],"type":"Point"}
}