{
  "type": "Feature",
  "properties": {
    "iso:country":"CH",
    "sg:address":"Sallaz Avenue De La 78 1010 Lausanne. Postfach",
    "sg:city":"Lausanne",
    "sg:orig_category":"RESTAURANTS: TEA-ROOMS",
    "sg:postcode":"1002",
    "sg:province":"Vaud",
    "wof:name":"Hunkar Brasserie La Sallaz",
    "wof:placetype":"venue"
},
  "geometry": {"coordinates":[6.6557598114,46.535900116],"type":"Point"}
}