{
  "type": "Feature",
  "properties": {
    "iso:country":"CH",
    "sg:address":"Zofingerstrasse 20 4665 Oftringen. Postfach",
    "sg:city":"Oftringen",
    "sg:orig_category":"Sonstiger spezialisierter Hoch U Tiefbau",
    "sg:postcode":"4665",
    "sg:province":"Aargau",
    "wof:name":"Gepi Gmbh",
    "wof:placetype":"venue"
},
  "geometry": {"coordinates":[7.9350981712,47.3044509888],"type":"Point"}
}