{
  "type": "Feature",
  "properties": {
    "iso:country":"CH",
    "sg:address":"Gartenstrasse 17",
    "sg:city":"Binningen",
    "sg:orig_category":"Instandhaltung U Reparatur von Automobilen",
    "sg:phone":"+41 61 421 43 27",
    "sg:postcode":"4102",
    "sg:province":"Basel-Landschaft",
    "wof:name":"Garage Mirolo G.parisotto",
    "wof:placetype":"venue"
},
  "geometry": {"coordinates":[7.5741529465,47.5433158875],"type":"Point"}
}