{
  "type": "Feature",
  "properties": {
    "iso:country":"CH",
    "sg:address":"Im Zwinggarten 14",
    "sg:city":"D\u00fcbendorf",
    "sg:orig_category":"Reinigungsgewerbe",
    "sg:phone":"+41 61 711 45 61",
    "sg:postcode":"8600",
    "sg:province":"Z\u00fcrich",
    "wof:name":"Regioservices Gmbh Liegenschaften; Reinigung, Wartung, Unterhalt",
    "wof:placetype":"venue"
},
  "geometry": {"coordinates":[7.6043438911,47.5103492737],"type":"Point"}
}