{
  "type": "Feature",
  "properties": {
    "iso:country":"CH",
    "sg:address":"Kuttelgasse 8 8001 Z\u00fcrich. Postfach",
    "sg:city":"Z\u00fcrich",
    "sg:orig_category":"Sonstiger Detailhandel mit Metallwaren, Anstrichmitteln, Glaswaren, Bau U Heimwerkerbedarf",
    "sg:phone":"+41 71 755 66 60",
    "sg:postcode":"8023",
    "sg:province":"Z\u00fcrich",
    "wof:name":"Basteltruhe",
    "wof:placetype":"venue"
},
  "geometry": {"coordinates":[9.540017128,47.3778800964],"type":"Point"}
}