{
  "type": "Feature",
  "properties": {
    "iso:country":"CH",
    "sg:address":"Bluche",
    "sg:city":"Randogne",
    "sg:classifiers":[
        {
            "category":"Travel",
            "subcategory":"Hotels & Motels",
            "type":"Entertainment"
        }
    ],
    "sg:phone":"+41 27 771 68 44",
    "sg:postcode":"3975",
    "sg:province":"Valais",
    "sg:tags":[
        "hotels",
        "mit",
        "restaurant"
    ],
    "wof:name":"H\u00f4tel Ph\u00e9nix",
    "wof:placetype":"venue"
},
  "geometry": {"coordinates":[7.2220621109,46.0976524353],"type":"Point"}
}