{
  "type": "Feature",
  "properties": {
    "iso:country":"CH",
    "sg:address":"9057",
    "sg:city":"Weissbad",
    "sg:orig_category":"Detailhandel mit Waren verschiedener Art, Hauptrichtung Nahrungsmittel",
    "sg:phone":"+41 71 799 11 64",
    "sg:postcode":"9057",
    "sg:province":"Appenzell Innerhoden",
    "wof:name":"Albert F\u00e4ssler Handlung",
    "wof:placetype":"venue"
},
  "geometry": {"coordinates":[9.4377403259,47.3050384521],"type":"Point"}
}