{
  "type": "Feature",
  "properties": {
    "iso:country":"CH",
    "sg:address":"Glattalstrasse 232 8153 R\u00fcmlang. Postfach",
    "sg:city":"R\u00fcmlang",
    "sg:orig_category":"Werbung",
    "sg:phone":"+41 71 282 41 60",
    "sg:postcode":"8153",
    "sg:province":"Z\u00fcrich",
    "wof:name":"Ipm Impuls Marketing Wild Josef Werbefl\u00e4chen; Verkauf, -mietung. Werbetr\u00e4ger; Vermarktung",
    "wof:placetype":"venue"
},
  "geometry": {"coordinates":[9.4163208008,47.4443435669],"type":"Point"}
}