{
  "type": "Feature",
  "properties": {
    "iso:country":"CH",
    "sg:address":"Bahnhofstrasse 13",
    "sg:city":"Wattwil",
    "sg:orig_category":"Detailhandel mit Uhren U Schmuck Fachdetailhandel in Verkaufsr\u00e4umen",
    "sg:phone":"+41 71 988 10 65",
    "sg:postcode":"9630",
    "sg:province":"St. Gallen",
    "wof:name":"Cemin Uhren-schmuck",
    "wof:placetype":"venue"
},
  "geometry": {"coordinates":[9.0866632462,47.2999954224],"type":"Point"}
}