{
  "type": "Feature",
  "properties": {
    "iso:country":"CH",
    "sg:address":"Mitteldorf 4",
    "sg:city":"Rupperswil",
    "sg:orig_category":"Detailhandel mit Brot, Back U S\u00fcsswaren",
    "sg:postcode":"5102",
    "sg:province":"Aargau",
    "wof:name":"Konditorei-b\u00e4ckerei Beat Tschugmall",
    "wof:placetype":"venue"
},
  "geometry": {"coordinates":[8.51936,47.47646],"type":"Point"}
}