{
  "type": "Feature",
  "properties": {
    "iso:country":"CH",
    "sg:address":"Wanne",
    "sg:city":"Rorschacherberg",
    "sg:classifiers":[
        {
            "category":"Professional",
            "subcategory":"Accounting & Tax Preparation",
            "type":"Services"
        }
    ],
    "sg:phone":"+41 71 855 26 62",
    "sg:postcode":"9404",
    "sg:province":"St. Gallen",
    "sg:tags":[
        "u",
        "yachtbau",
        "boot"
    ],
    "wof:name":"Urs Bl\u00f6chlinger Bootsmotoren-service",
    "wof:placetype":"venue"
},
  "geometry": {"coordinates":[9.513687,47.477146],"type":"Point"}
}