{
  "type": "Feature",
  "properties": {
    "addr:full":"Blauenstrasse 15 Basel Basel-Stadt 4054",
    "addr:housenumber":"15",
    "addr:postcode":"4054",
    "addr:street":"Blauenstrasse",
    "iso:country":"CH",
    "sg:address":"Blauenstrasse 15",
    "sg:city":"Basel",
    "sg:orig_category":"Architekturb\u00fcros",
    "sg:phone":"+41 71 222 33 37",
    "sg:postcode":"4054",
    "sg:province":"Basel-Stadt",
    "wof:name":"Daniel Camenzind Architekturb\u00fcro",
    "wof:placetype":"venue"
},
  "geometry": {"coordinates":[9.388349,47.414291],"type":"Point"}
}