{
  "type": "Feature",
  "properties": {
    "iso:country":"CH",
    "sg:address":"Walchstrasse 6",
    "sg:city":"G\u00fcmligen",
    "sg:orig_category":"Malerei",
    "sg:phone":"+41 31 951 45 68",
    "sg:postcode":"3073",
    "sg:province":"Bern",
    "wof:name":"Karl Gsteiger Malergesch\u00e4ft",
    "wof:placetype":"venue"
},
  "geometry": {"coordinates":[7.5139818192,46.9357032776],"type":"Point"}
}