{
  "type": "Feature",
  "properties": {
    "iso:country":"CH",
    "sg:address":"Levant Chemin Du 47",
    "sg:city":"Lausanne",
    "sg:orig_category":"Sonstiger Grosshandel",
    "sg:postcode":"1005",
    "sg:province":"Vaud",
    "wof:name":"Boschung International Ag",
    "wof:placetype":"venue"
},
  "geometry": {"coordinates":[7.2266697884,46.8414802551],"type":"Point"}
}