{
  "type": "Feature",
  "properties": {
    "iso:country":"CH",
    "sg:address":"Bergstrasse 23",
    "sg:city":"Luzern",
    "sg:orig_category":"Pensionskassen",
    "sg:postcode":"6004",
    "sg:province":"Luzern",
    "wof:name":"Vorsorgestiftung Der Hassler Hans Ag Luzern",
    "wof:placetype":"venue"
},
  "geometry": {"coordinates":[8.3081760406,47.0577354431],"type":"Point"}
}