{
  "type": "Feature",
  "properties": {
    "iso:country":"CH",
    "sg:address":"Arogno",
    "sg:city":"Arogno",
    "sg:classifiers":[
        {
            "category":"Banks & Credit Unions",
            "subcategory":"Bank",
            "type":"Services"
        }
    ],
    "sg:phone":"+41 4191688284",
    "sg:postcode":"6822",
    "sg:province":"Ticino",
    "wof:name":"Cassa Raiffeisen Di Arogno",
    "wof:placetype":"venue"
},
  "geometry": {"coordinates":[8.986733,45.958897],"type":"Point"}
}