{
  "type": "Feature",
  "properties": {
    "iso:country":"CH",
    "sg:address":"Place Du March\u00e9 6b",
    "sg:city":"Montreux",
    "sg:orig_category":"Drogerien Fachdetailhandel mit pharmazeutischen Produkten",
    "sg:phone":"+41 21 965 35 80",
    "sg:postcode":"1820",
    "sg:province":"Vaud",
    "wof:name":"Sun Store Sa",
    "wof:placetype":"venue"
},
  "geometry": {"coordinates":[6.9094290733,46.4319496155],"type":"Point"}
}