{
  "type": "Feature",
  "properties": {
    "iso:country":"CH",
    "sg:address":"Niederhaslistrasse 20",
    "sg:city":"Dielsdorf",
    "sg:orig_category":"Eisbahnen and Eissportpl\u00e4tze Schwimmb\u00e4der",
    "sg:phone":"+41 18533191",
    "sg:postcode":"8157",
    "sg:province":"Z\u00fcrich",
    "wof:name":"Erlen Sport-& Freizeitpark",
    "wof:placetype":"venue"
},
  "geometry": {"coordinates":[8.4719333649,47.4820671082],"type":"Point"}
}