{
  "type": "Feature",
  "properties": {
    "iso:country":"CH",
    "sg:address":"Ergetenstrasse 32 9445 Rebstein. Postfach",
    "sg:city":"Rebstein",
    "sg:orig_category":"Herstellung von Seifen, Wasch U Reinigungsmitteln",
    "sg:postcode":"9445",
    "sg:province":"St. Gallen",
    "wof:name":"Perritaz Mlle B.",
    "wof:placetype":"venue"
},
  "geometry": {"coordinates":[7.0777921677,46.7723312378],"type":"Point"}
}