{
  "type": "Feature",
  "properties": {
    "iso:country":"CH",
    "sg:address":"Via Ai Monti 17 6600 Locarno. Postfach",
    "sg:city":"Locarno",
    "sg:orig_category":"Gesundheitswesen",
    "sg:postcode":"6600",
    "sg:province":"Ticino",
    "wof:name":"Associazione O.a.s.i. - Ora Andiamo Spriritualmente Incontrandoci",
    "wof:placetype":"venue"
},
  "geometry": {"coordinates":[8.7915077209,46.1707000732],"type":"Point"}
}