{
  "type": "Feature",
  "properties": {
    "iso:country":"CH",
    "sg:address":"Neue Bahnhofstrasse 154 4132 Muttenz. Postfach",
    "sg:city":"Muttenz",
    "sg:orig_category":"Herstellung U Veredlung von sonstigem Glas Herstellung von Hohlglas",
    "sg:phone":"+41 61 461 07 77",
    "sg:postcode":"4132",
    "sg:province":"Basel-Landschaft",
    "wof:name":"Werner Rahm Glastechnische Werkst\u00e4tte",
    "wof:placetype":"venue"
},
  "geometry": {"coordinates":[7.6473059654,47.5326843262],"type":"Point"}
}