{
  "type": "Feature",
  "properties": {
    "iso:country":"CH",
    "sg:address":"Chemin De La Perrette 6",
    "sg:city":"Jongny",
    "sg:orig_category":"Vereine Musik/Blasmusik",
    "sg:postcode":"1805",
    "sg:province":"Vaud",
    "wof:name":"Fanfare L'amiti\u00e9",
    "wof:placetype":"venue"
},
  "geometry": {"coordinates":[6.8457651138,46.4854698181],"type":"Point"}
}