{
  "type": "Feature",
  "properties": {
    "iso:country":"CH",
    "sg:address":"L\u00e4delistrasse 12",
    "sg:city":"Luzern",
    "sg:orig_category":"Gartenbau Unternehmensberatung",
    "sg:phone":"+41 41 240 20 23",
    "sg:postcode":"6003",
    "sg:province":"Luzern",
    "wof:name":"Marco Meier & Partner Beratungen F\u00fcr Den Gartenbau",
    "wof:placetype":"venue"
},
  "geometry": {"coordinates":[8.294002533,47.0539321899],"type":"Point"}
}