{
  "type": "Feature",
  "properties": {
    "iso:country":"CH",
    "sg:address":"3937",
    "sg:city":"Baltschieder",
    "sg:orig_category":"Landesverteidigung, Sozialversicherung \u00d6ffentliche Verwaltung",
    "sg:phone":"+41 27 946 38 06",
    "sg:postcode":"3937",
    "sg:province":"Valais",
    "wof:name":"Zivilschutzstelle Baltschieder",
    "wof:placetype":"venue"
},
  "geometry": {"coordinates":[7.8553299904,46.3068313599],"type":"Point"}
}