{
  "type": "Feature",
  "properties": {
    "iso:country":"CH",
    "sg:address":"Bahnhofstrasse 1",
    "sg:city":"Baar",
    "sg:classifiers":[
        {
            "category":"Restaurant",
            "type":"Food & Drink"
        }
    ],
    "sg:phone":"+41 41 761 13 23",
    "sg:postcode":"6340",
    "sg:province":"Zug",
    "wof:name":"Restaurant Hans Waldmann",
    "wof:placetype":"venue"
},
  "geometry": {"coordinates":[8.5253286362,47.1954498291],"type":"Point"}
}