{
  "type": "Feature",
  "properties": {
    "iso:country":"CH",
    "sg:address":"Rheinstrasse 36",
    "sg:city":"Embrach",
    "sg:orig_category":"Herstellung von medizinischen U chirurgischen Ger\u00e4ten sowie orthop\u00e4dischen Vorrichtungen Zahntechnis",
    "sg:phone":"+41 18503838",
    "sg:postcode":"8424",
    "sg:province":"Z\u00fcrich",
    "wof:name":"Dental Dejan Maletaskic",
    "wof:placetype":"venue"
},
  "geometry": {"coordinates":[8.520365715,47.4736099243],"type":"Point"}
}