{
  "type": "Feature",
  "properties": {
    "iso:country":"CH",
    "sg:address":"Kieferstrasse 14",
    "sg:city":"Oftringen",
    "sg:orig_category":"Sportvereine Velo Rad-& Motorfahrer-Bund SRB",
    "sg:phone":"+41 62 797 54 01",
    "sg:postcode":"4665",
    "sg:province":"Aargau",
    "wof:name":"Arb.-touring-bund Oftringen",
    "wof:placetype":"venue"
},
  "geometry": {"coordinates":[7.9383711815,47.2969818115],"type":"Point"}
}