{
  "type": "Feature",
  "properties": {
    "iso:country":"CH",
    "sg:address":"Sonnmatt 20",
    "sg:city":"Rotkreuz",
    "sg:orig_category":"Vermietung von Baumaschinen U ger\u00e4ten mit Bedienungspersonal",
    "sg:postcode":"6343",
    "sg:province":"Zug",
    "wof:name":"Grues Service, Cosandey Patrick",
    "wof:placetype":"venue"
},
  "geometry": {"coordinates":[6.7549271584,46.5529785156],"type":"Point"}
}