{
  "type": "Feature",
  "properties": {
    "iso:country":"CH",
    "sg:address":"6636",
    "sg:city":"Frasco",
    "sg:orig_category":"Landesverteidigung, Sozialversicherung \u00d6ffentliche Verwaltung",
    "sg:phone":"+41 91 746 13 33",
    "sg:postcode":"6636",
    "sg:province":"Ticino",
    "wof:name":"Centro Di Protezione Civile Di Frasco",
    "wof:placetype":"venue"
},
  "geometry": {"coordinates":[8.8020801544,46.3401947021],"type":"Point"}
}