{
  "type": "Feature",
  "properties": {
    "iso:country":"CH",
    "sg:address":"Grand'rue 24",
    "sg:city":"Couvet",
    "sg:orig_category":"Non-Classified Establishments",
    "sg:postcode":"2108",
    "sg:province":"Neuch\u00e2tel",
    "wof:name":"Demirici & Yildirim",
    "wof:placetype":"venue"
},
  "geometry": {"coordinates":[6.6306781769,46.9261779785],"type":"Point"}
}