{
  "type": "Feature",
  "properties": {
    "iso:country":"CH",
    "sg:address":"Waldheimstrasse 41",
    "sg:city":"Bern",
    "sg:orig_category":"W\u00e4scherei U chemische Reinigung",
    "sg:phone":"+41 31 301 88 44",
    "sg:postcode":"3012",
    "sg:province":"Bern",
    "wof:name":"H. Reinhard Chem. Reinigungsanstalt.",
    "wof:placetype":"venue"
},
  "geometry": {"coordinates":[7.4270119667,46.9542388916],"type":"Point"}
}