{
  "type": "Feature",
  "properties": {
    "iso:country":"CH",
    "sg:address":"Moosweg 70",
    "sg:city":"Riehen",
    "sg:orig_category":"Advokaturb\u00fcros",
    "sg:phone":"+41 61 641 00 18",
    "sg:postcode":"4125",
    "sg:province":"Basel-Stadt",
    "wof:name":"Dr.heinrich Ueberwasser Advokaturb\u00fcro",
    "wof:placetype":"venue"
},
  "geometry": {"coordinates":[7.659728,47.581558],"type":"Point"}
}