{
  "type": "Feature",
  "properties": {
    "iso:country":"CH",
    "sg:address":"Habsburgerstrasse 20 6003 Luzern. Postfach 3414",
    "sg:city":"Luzern",
    "sg:orig_category":"Patentanwaltsb\u00fcros, Patentverwertung Rechtsberatung",
    "sg:phone":"+41 41 210 05 65",
    "sg:postcode":"6002",
    "sg:province":"Luzern",
    "wof:name":"Kem\u00e9ny Ag Patentanwaltb\u00fcro",
    "wof:placetype":"venue"
},
  "geometry": {"coordinates":[8.3074474335,47.0471115112],"type":"Point"}
}