{
  "type": "Feature",
  "properties": {
    "iso:country":"CH",
    "sg:address":"Grenzacherweg 81",
    "sg:city":"Riehen",
    "sg:orig_category":"Detailhandel mit Waren verschiedener Art, Hauptrichtung Nahrungsmittel",
    "sg:phone":"+41 61 641 06 11",
    "sg:postcode":"4125",
    "sg:province":"Basel-Stadt",
    "wof:name":"Migros-markt",
    "wof:placetype":"venue"
},
  "geometry": {"coordinates":[7.6466817856,47.5754585266],"type":"Point"}
}