{
  "type": "Feature",
  "properties": {
    "iso:country":"CH",
    "sg:address":"S\u00e4gestrasse 5",
    "sg:city":"Flawil",
    "sg:orig_category":"Unternehmensberatung",
    "sg:phone":"+41 71 393 73 20",
    "sg:postcode":"9230",
    "sg:province":"St. Gallen",
    "wof:name":"Dittmer Business Consulting",
    "wof:placetype":"venue"
},
  "geometry": {"coordinates":[9.179356575,47.4159965515],"type":"Point"}
}