{
  "type": "Feature",
  "properties": {
    "iso:country":"CH",
    "sg:address":"Gotthardstrasse 3",
    "sg:city":"Muri",
    "sg:classifiers":[
        {
            "category":"Communications",
            "subcategory":"Film & Video Production",
            "type":"Services"
        }
    ],
    "sg:phone":"+41 56 675 44 44",
    "sg:postcode":"5630",
    "sg:province":"Aargau",
    "sg:tags":[
        "development",
        "nanotechnology"
    ],
    "wof:name":"Awm Mold Tech Ag",
    "wof:placetype":"venue"
},
  "geometry": {"coordinates":[8.3527173996,47.2628631592],"type":"Point"}
}