{
  "type": "Feature",
  "properties": {
    "iso:country":"CH",
    "sg:address":"Naloz 17",
    "sg:city":"Savognin",
    "sg:orig_category":"Sportvereine Velo Rad-& Motorfahrer-Bund SRB",
    "sg:postcode":"7460",
    "sg:province":"Graubunden",
    "wof:name":"Veloclub Surses Savognin",
    "wof:placetype":"venue"
},
  "geometry": {"coordinates":[9.5964326859,46.59608078],"type":"Point"}
}