{
  "type": "Feature",
  "properties": {
    "iso:country":"CH",
    "sg:address":"Herbartstrasse 5",
    "sg:city":"Z\u00fcrich",
    "sg:orig_category":"Architektur U Ingenieurb\u00fcros",
    "sg:phone":"+41 22 771 08 03",
    "sg:postcode":"8004",
    "sg:province":"Z\u00fcrich",
    "wof:name":"Jos\u00e9 Luis Lopez Bureau D' Ing\u00e9nieur",
    "wof:placetype":"venue"
},
  "geometry": {"coordinates":[6.136228,46.145378],"type":"Point"}
}