{
  "type": "Feature",
  "properties": {
    "iso:country":"CH",
    "sg:address":"Falkenstrasse 26",
    "sg:city":"Z\u00fcrich",
    "sg:orig_category":"Non-Classified Establishments",
    "sg:postcode":"8008",
    "sg:province":"Z\u00fcrich",
    "wof:name":"Katharina Gattiker Kinesiologie",
    "wof:placetype":"venue"
},
  "geometry": {"coordinates":[8.5485172272,47.3655357361],"type":"Point"}
}