{
  "type": "Feature",
  "properties": {
    "iso:country":"CH",
    "sg:address":"Aberenterrasse 7",
    "sg:city":"Baar",
    "sg:orig_category":"Unternehmensberatung",
    "sg:postcode":"6340",
    "sg:province":"Zug",
    "wof:name":"Bedognetti Consulting",
    "wof:placetype":"venue"
},
  "geometry": {"coordinates":[8.52339077,47.204864502],"type":"Point"}
}