{
  "type": "Feature",
  "properties": {
    "iso:country":"CH",
    "sg:address":"R\u00f6mergasse 32",
    "sg:city":"Basel",
    "sg:orig_category":"Werbung",
    "sg:postcode":"4058",
    "sg:province":"Basel-Stadt",
    "wof:name":"Shortcut Media Ag",
    "wof:placetype":"venue"
},
  "geometry": {"coordinates":[7.6001029015,47.5585136414],"type":"Point"}
}