{
  "type": "Feature",
  "properties": {
    "iso:country":"CH",
    "sg:address":"Lido Via Al 9",
    "sg:city":"Viganello",
    "sg:orig_category":"Museen",
    "sg:postcode":"6962",
    "sg:province":"Ticino",
    "wof:name":"Enk Sa",
    "wof:placetype":"venue"
},
  "geometry": {"coordinates":[8.9708967209,46.0149879456],"type":"Point"}
}