{
  "type": "Feature",
  "properties": {
    "iso:country":"CH",
    "sg:address":"Route Cantonale 65",
    "sg:city":"Conthey",
    "sg:orig_category":"Fussboden, Fliesen U Plattenlegerei, Tapeziererei Verlegen von Fliesen U Platten",
    "sg:phone":"+41 27 346 16 23",
    "sg:postcode":"1964",
    "sg:province":"Valais",
    "wof:name":"Duc Michel",
    "wof:placetype":"venue"
},
  "geometry": {"coordinates":[7.3033800125,46.2242584229],"type":"Point"}
}