{
  "type": "Feature",
  "properties": {
    "iso:country":"CH",
    "sg:address":"Rebenweg 3",
    "sg:city":"Dotzigen",
    "sg:orig_category":"Wirtschaftspr\u00fcfung, Steuerberatung U Treuhand",
    "sg:phone":"+41 27 785 25 40",
    "sg:postcode":"3293",
    "sg:province":"Bern",
    "wof:name":"Monnet Cl\u00e9ment",
    "wof:placetype":"venue"
},
  "geometry": {"coordinates":[7.1772699356,46.0913352966],"type":"Point"}
}