{
  "type": "Feature",
  "properties": {
    "iso:country":"CH",
    "sg:address":"Unterdorf",
    "sg:city":"Wauwil",
    "sg:orig_category":"Herstellung von M\u00f6beln verschiedener Art M\u00f6belveredelung U restaurierung",
    "sg:phone":"+41 41 980 02 88",
    "sg:postcode":"6242",
    "sg:province":"Luzern",
    "wof:name":"Barmet Ag",
    "wof:placetype":"venue"
},
  "geometry": {"coordinates":[8.0165548325,47.1848335266],"type":"Point"}
}