{
  "type": "Feature",
  "properties": {
    "iso:country":"CH",
    "sg:address":"Chamerstrasse 22 6300 Zug. Postfach 4356",
    "sg:city":"Zug",
    "sg:orig_category":"Architektur U Ingenieurb\u00fcros Architekturb\u00fcros",
    "sg:phone":"+41 41 710 56 28",
    "sg:postcode":"6304",
    "sg:province":"Zug",
    "wof:name":"Wiederkehr Krummenacher Architekten Ag",
    "wof:placetype":"venue"
},
  "geometry": {"coordinates":[8.510134,47.172462],"type":"Point"}
}