{
  "type": "Feature",
  "properties": {
    "iso:country":"CH",
    "sg:address":"Gurliweg",
    "sg:city":"Plaffeien",
    "sg:orig_category":"RESTAURANTS: TEA-ROOMS",
    "sg:postcode":"1716",
    "sg:province":"Fribourg",
    "wof:name":"Br\u00fcgger Otto.",
    "wof:placetype":"venue"
},
  "geometry": {"coordinates":[7.2832798958,46.711101532],"type":"Point"}
}