{
  "type": "Feature",
  "properties": {
    "iso:country":"CH",
    "sg:address":"Ch\u00fcefergasse 12 8108 D\u00e4llikon. Postfach",
    "sg:city":"D\u00e4llikon",
    "sg:orig_category":"Vermietung U Verpachtung von eigenen Immobilien",
    "sg:postcode":"8108",
    "sg:province":"Z\u00fcrich",
    "wof:name":"Bau Und Boden Anlagen Ag",
    "wof:placetype":"venue"
},
  "geometry": {"coordinates":[8.4349107742,47.4366569519],"type":"Point"}
}