{
  "type": "Feature",
  "properties": {
    "iso:country":"CH",
    "sg:address":"Les Trois Tilleuls",
    "sg:city":"Vulliens",
    "sg:orig_category":"Softwareentwicklung U beratung",
    "sg:phone":"+41 21 905 60 19",
    "sg:postcode":"1085",
    "sg:province":"Vaud",
    "wof:name":"Software Development Studio Jm S\u00e0rl",
    "wof:placetype":"venue"
},
  "geometry": {"coordinates":[6.7915291786,46.6198120117],"type":"Point"}
}