{
  "type": "Feature",
  "properties": {
    "iso:country":"CH",
    "sg:address":"Rain 22 5000 Aarau. Postfach",
    "sg:city":"Aarau",
    "sg:orig_category":"Grosshandel mit Getr\u00e4nken Herstellung von Wein",
    "sg:phone":"+41 62 822 40 92",
    "sg:postcode":"5000",
    "sg:province":"Aargau",
    "wof:name":"U Mmiier Weinhandels Gmbh Wein, Weinerzeugnisse Usw.; Produktion, Handel",
    "wof:placetype":"venue"
},
  "geometry": {"coordinates":[8.0440559387,47.3908462524],"type":"Point"}
}