{
  "type": "Feature",
  "properties": {
    "iso:country":"CH",
    "sg:address":"Avenue De La Gare 1955 Chamoson Case Postale",
    "sg:city":"Chamoson",
    "sg:orig_category":"Grosshandel mit Getr\u00e4nken Rebbau",
    "sg:phone":"+41 71 755 14 09",
    "sg:postcode":"1955",
    "sg:province":"Valais",
    "wof:name":"Haubensak Heini Rebbau Und Weinkellerei",
    "wof:placetype":"venue"
},
  "geometry": {"coordinates":[9.5442667007,47.3792991638],"type":"Point"}
}