{
  "type": "Feature",
  "properties": {
    "iso:country":"CH",
    "sg:address":"Via Peri 16",
    "sg:city":"Lugano",
    "sg:orig_category":"Detailhandel mit Textilien",
    "sg:phone":"+41 91 922 81 29",
    "sg:postcode":"6900",
    "sg:province":"Ticino",
    "wof:name":"Bottega Della Lana Carla & Maria Conti",
    "wof:placetype":"venue"
},
  "geometry": {"coordinates":[8.9508657455,46.0061035156],"type":"Point"}
}