{
  "type": "Feature",
  "properties": {
    "iso:country":"CH",
    "sg:address":"Baarerstrasse 110a 6300 Zug. Postfach 2648",
    "sg:city":"Zug",
    "sg:orig_category":"Softwareentwicklung U beratung",
    "sg:phone":"+41 41 769 77 64",
    "sg:postcode":"6302",
    "sg:province":"Zug",
    "wof:name":"Integrators Ag",
    "wof:placetype":"venue"
},
  "geometry": {"coordinates":[8.5189380646,47.1798820496],"type":"Point"}
}