{
  "type": "Feature",
  "properties": {
    "iso:country":"CH",
    "sg:address":"Strelaweg 7",
    "sg:city":"Chur",
    "sg:orig_category":"Vorschulen, Kinderg\u00e4rten",
    "sg:phone":"+41 81 353 53 47",
    "sg:postcode":"7000",
    "sg:province":"Graubunden",
    "wof:name":"St\u00e4dtischer Kindergarten Strela",
    "wof:placetype":"venue"
},
  "geometry": {"coordinates":[9.5356063843,46.8630027771],"type":"Point"}
}