{
  "type": "Feature",
  "properties": {
    "iso:country":"CH",
    "sg:address":"Rohrerstrasse 107",
    "sg:city":"Aarau",
    "sg:orig_category":"Grosshandel mit B\u00fcromaschinen Grosshandel mit Datenverarbeitungsger\u00e4ten",
    "sg:phone":"+41 62 824 92 82",
    "sg:postcode":"5000",
    "sg:province":"Aargau",
    "wof:name":"Prosoft Aarau Ag",
    "wof:placetype":"venue"
},
  "geometry": {"coordinates":[8.0648765564,47.3956260681],"type":"Point"}
}