{
  "type": "Feature",
  "properties": {
    "iso:country":"CH",
    "sg:address":"Bellot Rue Fran\u00e7ois- 2 1206 Gen\u00e8ve. Postfach",
    "sg:city":"Gen\u00e8ve",
    "sg:orig_category":"Erbringung von Dienstleistungen f\u00fcr Unternehmen",
    "sg:postcode":"1206",
    "sg:province":"Gen\u00e8ve",
    "wof:name":"Capital Events Sa Ev\u00e9nements Culturels, Artistiques, Sportifs, Etc.; Organisation, Production",
    "wof:placetype":"venue"
},
  "geometry": {"coordinates":[6.1515522003,46.1977500916],"type":"Point"}
}