{
  "type": "Feature",
  "properties": {
    "iso:country":"CH",
    "sg:address":"Trogener Strasse 4",
    "sg:city":"Speicher",
    "sg:orig_category":"Arztpraxen",
    "sg:phone":"+41 19327292",
    "sg:postcode":"9042",
    "sg:province":"Appenzell Ausserrhoden",
    "wof:name":"Dr.med.erika Gutte Spezial\u00e4rztin Fmh",
    "wof:placetype":"venue"
},
  "geometry": {"coordinates":[8.795513,47.322052],"type":"Point"}
}