{
  "type": "Feature",
  "properties": {
    "iso:country":"CH",
    "sg:address":"Rue Des D\u00e9lices 31 1200 Gen\u00e8ve. Postfach",
    "sg:city":"Gen\u00e8ve",
    "sg:orig_category":"Wirtschaftspr\u00fcfung, Steuerberatung U Treuhand",
    "sg:phone":"+41 22 345 46 06",
    "sg:postcode":"1203",
    "sg:province":"Gen\u00e8ve",
    "wof:name":"Jmm, Mettan Jeanne Marie",
    "wof:placetype":"venue"
},
  "geometry": {"coordinates":[6.1346278191,46.2081451416],"type":"Point"}
}