{
  "type": "Feature",
  "properties": {
    "iso:country":"CH",
    "sg:address":"Dorfstrasse 13 4717 M\u00fcmliswil. Postfach 114",
    "sg:city":"M\u00fcmliswil",
    "sg:orig_category":"Detailhandel mit Milcherzeugnissen U Eiern Verarbeitung von Milch",
    "sg:phone":"+41 26 912 48 91",
    "sg:postcode":"4717",
    "sg:province":"Solothurn",
    "wof:name":"D\u00e9nervaud Jacques.",
    "wof:placetype":"venue"
},
  "geometry": {"coordinates":[7.0576848984,46.5961875916],"type":"Point"}
}