{
  "type": "Feature",
  "properties": {
    "iso:country":"CH",
    "sg:address":"Ober-m\u00fchle",
    "sg:city":"Vitznau",
    "sg:orig_category":"Autogaragen",
    "sg:phone":"+41 79 208 79 44",
    "sg:postcode":"6354",
    "sg:province":"Luzern",
    "wof:name":"Werner Zimmermann Dorfgarage",
    "wof:placetype":"venue"
},
  "geometry": {"coordinates":[8.485605,47.010155],"type":"Point"}
}