{
  "type": "Feature",
  "properties": {
    "iso:country":"CH",
    "sg:address":"Dorfrain 13",
    "sg:city":"Niederlenz",
    "sg:orig_category":"Veterin\u00e4rwesen",
    "sg:phone":"+41 62 891 51 55",
    "sg:postcode":"5702",
    "sg:province":"Aargau",
    "wof:name":"Tierklinik M\u00fchlebach Barbara Dr.",
    "wof:placetype":"venue"
},
  "geometry": {"coordinates":[8.174448967,47.4016571045],"type":"Point"}
}