{
  "type": "Feature",
  "properties": {
    "iso:country":"CH",
    "sg:address":"Aarauerstrasse 47",
    "sg:city":"Olten",
    "sg:orig_category":"Detailhandel mit Haustieren U zoologischem Bedarf",
    "sg:phone":"+41 62 296 19 88",
    "sg:postcode":"4600",
    "sg:province":"Solothurn",
    "wof:name":"Monica Ravljen Zoo Arakanga",
    "wof:placetype":"venue"
},
  "geometry": {"coordinates":[7.9099431038,47.3486862183],"type":"Point"}
}