{
  "type": "Feature",
  "properties": {
    "iso:country":"CH",
    "sg:address":"Zurlindenstrasse 300",
    "sg:city":"Z\u00fcrich",
    "sg:orig_category":"Detailhandel mit Waren verschiedener Art, Hauptrichtung Nahrungsmittel",
    "sg:phone":"+41 56 441 30 30",
    "sg:postcode":"8003",
    "sg:province":"Z\u00fcrich",
    "wof:name":"Coop Laden",
    "wof:placetype":"venue"
},
  "geometry": {"coordinates":[8.2116804123,47.4871902466],"type":"Point"}
}