{
  "type": "Feature",
  "properties": {
    "iso:country":"CH",
    "sg:address":"Grand-rue 44 1166 Perroy. Postfach",
    "sg:city":"Perroy",
    "sg:orig_category":"Unclassifiable Establishments",
    "sg:postcode":"1166",
    "sg:province":"Vaud",
    "wof:name":"Www.isatis.ch Michon Claude Pages, De Sites Sur Le R\u00e9seau Internet; Conception, R\u00e9alisation, Int\u00e9gration",
    "wof:placetype":"venue"
},
  "geometry": {"coordinates":[6.3654661179,46.4678115845],"type":"Point"}
}