{
  "type": "Feature",
  "properties": {
    "iso:country":"CH",
    "sg:address":"Zurlindenstrasse 231",
    "sg:city":"Z\u00fcrich",
    "sg:orig_category":"RESTAURANTS: TEA-ROOMS",
    "sg:phone":"+41 14511251",
    "sg:postcode":"8003",
    "sg:province":"Z\u00fcrich",
    "wof:name":"Restaurant Zurlinden, Buck Silvia",
    "wof:placetype":"venue"
},
  "geometry": {"coordinates":[8.5132770538,47.3752784729],"type":"Point"}
}