{
  "type": "Feature",
  "properties": {
    "iso:country":"CH",
    "sg:address":"Nespelmattweg 8",
    "sg:city":"Pfeffingen",
    "sg:orig_category":"Grosshandel mit Holz U Baustoffen",
    "sg:phone":"+41 61 751 77 77",
    "sg:postcode":"4148",
    "sg:province":"Basel-Landschaft",
    "wof:name":"Resomur Ag",
    "wof:placetype":"venue"
},
  "geometry": {"coordinates":[7.5956802368,47.4609184265],"type":"Point"}
}