{
  "type": "Feature",
  "properties": {
    "iso:country":"CH",
    "sg:address":"8757",
    "sg:city":"Filzbach",
    "sg:orig_category":"Pensionen mit Restaurant",
    "sg:phone":"+41 55 614 13 34",
    "sg:postcode":"8757",
    "sg:province":"Glarus",
    "wof:name":"Pension Baumgarten",
    "wof:placetype":"venue"
},
  "geometry": {"coordinates":[9.1272640228,47.1211624146],"type":"Point"}
}