{
  "type": "Feature",
  "properties": {
    "iso:country":"CH",
    "sg:address":"Schaffhauserstrasse 1",
    "sg:city":"Kleinandelfingen",
    "sg:classifiers":[
        {
            "category":"Restaurant",
            "type":"Food & Drink"
        }
    ],
    "sg:phone":"+41 52 317 11 44",
    "sg:postcode":"8451",
    "sg:province":"Z\u00fcrich",
    "wof:name":"Restaurant Thurbr\u00fccke",
    "wof:placetype":"venue"
},
  "geometry": {"coordinates":[8.6814632416,47.5974845886],"type":"Point"}
}