{
  "type": "Feature",
  "properties": {
    "iso:country":"CH",
    "sg:address":"8422 Pfungen. Postfach",
    "sg:city":"Pfungen",
    "sg:orig_category":"Herstellung von Ziegeln U sonstiger Baukeramik",
    "sg:postcode":"8422",
    "sg:province":"Z\u00fcrich",
    "wof:name":"Ziegelei Basadingen Ag",
    "wof:placetype":"venue"
},
  "geometry": {"coordinates":[8.64220047,47.5163269043],"type":"Point"}
}