{
  "type": "Feature",
  "properties": {
    "iso:country":"CH",
    "sg:address":"Gehrenweg 2a",
    "sg:city":"Egolzwil",
    "sg:orig_category":"Malerei",
    "sg:phone":"+41 41 980 47 69",
    "sg:postcode":"6243",
    "sg:province":"Luzern",
    "wof:name":"Aebi & Bisang Malergesch\u00e4ft",
    "wof:placetype":"venue"
},
  "geometry": {"coordinates":[8.0072488785,47.1831703186],"type":"Point"}
}