{
  "type": "Feature",
  "properties": {
    "iso:country":"CH",
    "sg:address":"Chemin Champ-vionnet 6",
    "sg:city":"Cossonay-ville",
    "sg:orig_category":"Hardwareberatung Softwareentwicklung U beratung",
    "sg:phone":"+41 21 863 20 50",
    "sg:postcode":"1304",
    "sg:province":"Vaud",
    "wof:name":"Acting S\u00e0rl",
    "wof:placetype":"venue"
},
  "geometry": {"coordinates":[6.4875569344,46.6005821228],"type":"Point"}
}