{
  "type": "Feature",
  "properties": {
    "iso:country":"CH",
    "sg:address":"Route De Gruy\u00e8re 6 1700 Fribourg. Postfach 17",
    "sg:city":"Fribourg",
    "sg:orig_category":"Bau von Strassen, Sportanlagen U Bahnverkehrsstrecken Strassenbau",
    "sg:phone":"+41 26 425 41 26",
    "sg:postcode":"1709",
    "sg:province":"Fribourg",
    "wof:name":"Routes Modernes S.a. Fribourg",
    "wof:placetype":"venue"
},
  "geometry": {"coordinates":[7.143942,46.798496],"type":"Point"}
}