{
  "type": "Feature",
  "properties": {
    "iso:country":"CH",
    "sg:address":"Route Du Ch\u00e2telard 54a",
    "sg:city":"Lausanne",
    "sg:orig_category":"Geb\u00e4ude, Wohnungsreinigung",
    "sg:phone":"+41 79 321 06 35",
    "sg:postcode":"1018",
    "sg:province":"Vaud",
    "wof:name":"Jean-jacques Jordan Entreprise De Nettoyages",
    "wof:placetype":"venue"
},
  "geometry": {"coordinates":[6.6241240501,46.543712616],"type":"Point"}
}