{
  "type": "Feature",
  "properties": {
    "addr:full":"Route De Peney 135 Vernier Gen\u00e8ve 1214",
    "addr:housenumber":"135",
    "addr:postcode":"1214",
    "addr:street":"Route De Peney",
    "iso:country":"CH",
    "sg:address":"Route De Peney 135",
    "sg:city":"Vernier",
    "sg:orig_category":"Bauschreinerei Innenausbau",
    "sg:phone":"+41 33 823 40 60",
    "sg:postcode":"1214",
    "sg:province":"Gen\u00e8ve",
    "wof:name":"Ap Parkett Innenausbau & Fussb\u00f6den",
    "wof:placetype":"venue"
},
  "geometry": {"coordinates":[7.88325,46.698689],"type":"Point"}
}