{
  "type": "Feature",
  "properties": {
    "iso:country":"CH",
    "sg:address":"In Der Euelwies 14",
    "sg:city":"Winterthur",
    "sg:orig_category":"R\u00fcckgewinnung U Vorbereitung f\u00fcr die Wiederverwertung Recycling von nichtmetallischen Altmaterialien",
    "sg:phone":"+41 52 222 48 48",
    "sg:postcode":"8408",
    "sg:province":"Z\u00fcrich",
    "wof:name":"Alpa Handels Ag",
    "wof:placetype":"venue"
},
  "geometry": {"coordinates":[8.678981781,47.5057830811],"type":"Point"}
}