{
  "type": "Feature",
  "properties": {
    "iso:country":"CH",
    "sg:address":"Kriesbachstrasse 5",
    "sg:city":"Wallisellen",
    "sg:orig_category":"Herstellung von Bereifungen",
    "sg:postcode":"8304",
    "sg:province":"Z\u00fcrich",
    "wof:name":"Atd Pneushop S. Zimmermann",
    "wof:placetype":"venue"
},
  "geometry": {"coordinates":[8.1647596359,47.224521637],"type":"Point"}
}