{
  "type": "Feature",
  "properties": {
    "iso:country":"CH",
    "sg:address":"Schafmattweg 78",
    "sg:city":"Binningen",
    "sg:orig_category":"Sonstige pers\u00f6nliche Dienstleistungen",
    "sg:postcode":"4102",
    "sg:province":"Basel-Landschaft",
    "wof:name":"Profit-phone, M. Oes",
    "wof:placetype":"venue"
},
  "geometry": {"coordinates":[7.570291996,47.5310707092],"type":"Point"}
}