{
  "type": "Feature",
  "properties": {
    "iso:country":"CH",
    "sg:address":"Bellerivestrasse 55",
    "sg:city":"Z\u00fcrich",
    "sg:orig_category":"Mit dem Versicherungsgewerbe verbundene T\u00e4tigkeiten",
    "sg:phone":"+41 76 384 49 09",
    "sg:postcode":"8008",
    "sg:province":"Z\u00fcrich",
    "wof:name":"Hebo Beratungs-& Finanzierungs Ag",
    "wof:placetype":"venue"
},
  "geometry": {"coordinates":[9.3690948486,47.4198112488],"type":"Point"}
}