{
  "type": "Feature",
  "properties": {
    "iso:country":"CH",
    "sg:address":"4003 Basel. Postfach",
    "sg:city":"Basel",
    "sg:orig_category":"Sportvereine Turnen",
    "sg:phone":"+41 71 311 17 72",
    "sg:postcode":"4015",
    "sg:province":"Basel-Stadt",
    "wof:name":"Btv Aktivriege",
    "wof:placetype":"venue"
},
  "geometry": {"coordinates":[9.3010997772,47.4011535645],"type":"Point"}
}