{
  "type": "Feature",
  "properties": {
    "iso:country":"CH",
    "sg:address":"Brillancourt Chemin De 4",
    "sg:city":"Lausanne",
    "sg:orig_category":"Werbung",
    "sg:phone":"+41 21 618 61 11",
    "sg:postcode":"1006",
    "sg:province":"Vaud",
    "wof:name":"Orecla Sa",
    "wof:placetype":"venue"
},
  "geometry": {"coordinates":[6.6289801598,46.5103302002],"type":"Point"}
}