{
  "type": "Feature",
  "properties": {
    "iso:country":"CH",
    "sg:address":"B\u00fcelweg 4 8400 Winterthur. Postfach",
    "sg:city":"Winterthur",
    "sg:orig_category":"Detailhandel mit Spielwaren Grosshandel mit sonstigen Gebrauchs U Verbrauchsg\u00fctern",
    "sg:phone":"+41 61 761 71 00",
    "sg:postcode":"8400",
    "sg:province":"Z\u00fcrich",
    "wof:name":"Tewis Ag",
    "wof:placetype":"venue"
},
  "geometry": {"coordinates":[7.5135140419,47.4035758972],"type":"Point"}
}