{
  "type": "Feature",
  "properties": {
    "iso:country":"CH",
    "sg:address":"Rue De La Sagne 21",
    "sg:city":"Ste-croix",
    "sg:orig_category":"Pensionskassen",
    "sg:postcode":"1450",
    "sg:province":"Vaud",
    "wof:name":"Fonds De Pr\u00e9voyance En Faveur Du Personnel De La Fonderie M\u00e9canique De Sainte-croix Sa",
    "wof:placetype":"venue"
},
  "geometry": {"coordinates":[6.5010690689,46.8176193237],"type":"Point"}
}