{
  "type": "Feature",
  "properties": {
    "iso:country":"CH",
    "sg:address":"Gloriastrasse 70",
    "sg:city":"Z\u00fcrich",
    "sg:orig_category":"Arztpraxen",
    "sg:phone":"+41 12529070",
    "sg:postcode":"8044",
    "sg:province":"Z\u00fcrich",
    "wof:name":"Dr.med.ursula Urner Spezial\u00e4rztin Fmh",
    "wof:placetype":"venue"
},
  "geometry": {"coordinates":[8.55675,47.375793],"type":"Point"}
}