{
  "type": "Feature",
  "properties": {
    "iso:country":"CH",
    "sg:address":"Eichholzstrasse 66",
    "sg:city":"Wabern",
    "sg:orig_category":"Chemin\u00e9e- and Ofenbau Hafner",
    "sg:phone":"+41 31 961 58 91",
    "sg:postcode":"3084",
    "sg:province":"Bern",
    "wof:name":"Hans Binggeli Chemin\u00e9ebau & Hafnerei",
    "wof:placetype":"venue"
},
  "geometry": {"coordinates":[7.456176,46.931992],"type":"Point"}
}