{
  "type": "Feature",
  "properties": {
    "iso:country":"CH",
    "sg:address":"Pierre Rue Saint- 18 1700 Fribourg. Postfach",
    "sg:city":"Freiburg",
    "sg:orig_category":"Unternehmensberatung",
    "sg:postcode":"1700",
    "sg:province":"Fribourg",
    "wof:name":"Ibi Trading Et Consulting Sa",
    "wof:placetype":"venue"
},
  "geometry": {"coordinates":[7.1558661461,46.8040313721],"type":"Point"}
}