{
  "type": "Feature",
  "properties": {
    "iso:country":"CH",
    "sg:address":"H\u00f6chistrasse 4a",
    "sg:city":"Uster",
    "sg:orig_category":"Sonstige mit der Informatik verbundene T\u00e4tigkeiten",
    "sg:phone":"+41 55 442 75 80",
    "sg:postcode":"8610",
    "sg:province":"Z\u00fcrich",
    "wof:name":"Darev Engineering Ag",
    "wof:placetype":"venue"
},
  "geometry": {"coordinates":[8.8564291,47.1911964417],"type":"Point"}
}