{
  "type": "Feature",
  "properties": {
    "iso:country":"CH",
    "sg:address":"Chemin Des Bougeries 16",
    "sg:city":"Ch\u00eane-bougeries",
    "sg:orig_category":"Finanzierungsinstitutionen",
    "sg:postcode":"1224",
    "sg:province":"Gen\u00e8ve",
    "wof:name":"Nisoikos Sarl",
    "wof:placetype":"venue"
},
  "geometry": {"coordinates":[6.1897139549,46.1966209412],"type":"Point"}
}