{
  "type": "Feature",
  "properties": {
    "iso:country":"CH",
    "sg:address":"Holzackerstrasse 10b",
    "sg:city":"Belp",
    "sg:orig_category":"Non-Classified Establishments",
    "sg:postcode":"3123",
    "sg:province":"Bern",
    "wof:name":"M\u00fcller H. & Co, Edv-organisation & -programmierung.",
    "wof:placetype":"venue"
},
  "geometry": {"coordinates":[7.5058450699,46.8783111572],"type":"Point"}
}