{
  "type": "Feature",
  "properties": {
    "iso:country":"CH",
    "sg:address":"Aemetstrasse 4",
    "sg:city":"B\u00e4retswil",
    "sg:orig_category":"Herstellung von Anstrichmitteln, Druckfarben U Kitten",
    "sg:phone":"+41 19391329",
    "sg:postcode":"8344",
    "sg:province":"Z\u00fcrich",
    "wof:name":"Jean-claude B\u00e4r Lackfabrik",
    "wof:placetype":"venue"
},
  "geometry": {"coordinates":[8.856669426,47.3358688354],"type":"Point"}
}