{
  "type": "Feature",
  "properties": {
    "iso:country":"CH",
    "sg:address":"Gatternweg 57",
    "sg:city":"Riehen",
    "sg:orig_category":"Handelsvermittlung U Grosshandel Sonstiger Grosshandel",
    "sg:phone":"+41 79 230 69 09",
    "sg:postcode":"4125",
    "sg:province":"Basel-Stadt",
    "wof:name":"Guignard Trading Transport Gtt Sa",
    "wof:placetype":"venue"
},
  "geometry": {"coordinates":[7.0273737907,46.9250793457],"type":"Point"}
}