{
  "type": "Feature",
  "properties": {
    "iso:country":"CH",
    "sg:address":"Marktstrasse 12 6060 Sarnen. Postfach",
    "sg:city":"Sarnen",
    "sg:orig_category":"Druck ohne Zeitungsdruck",
    "sg:postcode":"6060",
    "sg:province":"Obwalden",
    "wof:name":"Pink-point A. Steininger + Co",
    "wof:placetype":"venue"
},
  "geometry": {"coordinates":[8.1540994644,47.2197227478],"type":"Point"}
}