{
  "type": "Feature",
  "properties": {
    "iso:country":"CH",
    "sg:address":"Hauptstrasse 44",
    "sg:city":"Eschenz",
    "sg:orig_category":"Wine Racks, Wine Storage Shelves Made Of Plastic",
    "sg:phone":"+41 52 741 21 38",
    "sg:postcode":"8264",
    "sg:province":"Thurgau",
    "wof:name":"Mirjam Bamert Flaschengestellfabrik",
    "wof:placetype":"venue"
},
  "geometry": {"coordinates":[8.8666791916,47.6497001648],"type":"Point"}
}