{
  "type": "Feature",
  "properties": {
    "addr:full":"Alte Landstrasse 131 Thalwil Z\u00fcrich 8800",
    "addr:housenumber":"131",
    "addr:postcode":"8800",
    "addr:street":"Alte Landstrasse",
    "iso:country":"CH",
    "sg:address":"Alte Landstrasse 131",
    "sg:city":"Thalwil",
    "sg:orig_category":"Detailhandel mit Brillen U anderen Sehhilfen Fachdetailhandel in Verkaufsr\u00e4umen",
    "sg:phone":"+41 17211718",
    "sg:postcode":"8800",
    "sg:province":"Z\u00fcrich",
    "wof:name":"Kusenberg Optik Ag Thalwil",
    "wof:placetype":"venue"
},
  "geometry": {"coordinates":[8.563079,47.29454],"type":"Point"}
}