{
  "type": "Feature",
  "properties": {
    "iso:country":"CH",
    "sg:address":"Rheinweg 4 8200 Schaffhausen. Postfach 1512",
    "sg:city":"Schaffhausen",
    "sg:orig_category":"Herstellung von sonstigen elektrischen Ausr\u00fcstungen",
    "sg:phone":"+41 52 625 25 53",
    "sg:postcode":"8201",
    "sg:province":"Schaffhausen",
    "wof:name":"Testudo Ag Sicherheitstechnik Rhypark",
    "wof:placetype":"venue"
},
  "geometry": {"coordinates":[8.6347980499,47.6939506531],"type":"Point"}
}