{
  "type": "Feature",
  "properties": {
    "addr:full":"Bremgartenstrasse 22 Merenschwand Aargau 5634",
    "addr:housenumber":"22",
    "addr:postcode":"5634",
    "addr:street":"Bremgartenstrasse",
    "iso:country":"CH",
    "sg:address":"Bremgartenstrasse 22",
    "sg:city":"Merenschwand",
    "sg:orig_category":"Bauschreinerei",
    "sg:phone":"+41 56 664 17 93",
    "sg:postcode":"5634",
    "sg:province":"Aargau",
    "wof:name":"Franz Stadelmann Schreinerei",
    "wof:placetype":"venue"
},
  "geometry": {"coordinates":[8.370335,47.263393],"type":"Point"}
}