{
  "type": "Feature",
  "properties": {
    "iso:country":"CH",
    "sg:address":"Sch\u00fctzenstrasse 3315 Kr\u00e4iligen. Postfach",
    "sg:city":"Kr\u00e4iligen",
    "sg:orig_category":"Instandhaltung U Reparatur von Automobilen",
    "sg:phone":"+41 32 665 26 11",
    "sg:postcode":"3315",
    "sg:province":"Bern",
    "wof:name":"H.p. K\u00fcbler",
    "wof:placetype":"venue"
},
  "geometry": {"coordinates":[7.5389471054,47.1312561035],"type":"Point"}
}