{
  "type": "Feature",
  "properties": {
    "iso:country":"CH",
    "sg:address":"Rue Jean-gutenberg 5",
    "sg:city":"Gen\u00e8ve",
    "sg:orig_category":"Datenverarbeitungsdienste",
    "sg:phone":"+41 22 940 04 66",
    "sg:postcode":"1201",
    "sg:province":"Gen\u00e8ve",
    "wof:name":"Ap Informatique",
    "wof:placetype":"venue"
},
  "geometry": {"coordinates":[6.137644,46.208332],"type":"Point"}
}