{
  "type": "Feature",
  "properties": {
    "iso:country":"CH",
    "sg:address":"Obergasse 29",
    "sg:city":"Winterthur",
    "sg:orig_category":"Unclassifiable Establishments",
    "sg:postcode":"8400",
    "sg:province":"Z\u00fcrich",
    "wof:name":"M\u00fcller's Ronald Party-service",
    "wof:placetype":"venue"
},
  "geometry": {"coordinates":[8.4572095871,47.2799339294],"type":"Point"}
}