{
  "type": "Feature",
  "properties": {
    "iso:country":"CH",
    "sg:address":"Neptunstrasse 61",
    "sg:city":"Z\u00fcrich",
    "sg:orig_category":"Public-Relations-Agenturen Werbeagenturen",
    "sg:phone":"+41 13839326",
    "sg:postcode":"8032",
    "sg:province":"Z\u00fcrich",
    "wof:name":"Text Und Mehr Public Relations & Werbung",
    "wof:placetype":"venue"
},
  "geometry": {"coordinates":[8.5574159622,47.3659820557],"type":"Point"}
}