{
  "type": "Feature",
  "properties": {
    "iso:country":"CH",
    "sg:address":"Rue De Lavetan 10",
    "sg:city":"Leytron",
    "sg:orig_category":"Detailhandel mit Getr\u00e4nken",
    "sg:phone":"+41 27 306 25 52",
    "sg:postcode":"1912",
    "sg:province":"Valais",
    "wof:name":"Herv\u00e9 Pierrette Jo\u00eblle Carrupt Vins Grappe Dor\u00e9e",
    "wof:placetype":"venue"
},
  "geometry": {"coordinates":[7.2071352005,46.1879348755],"type":"Point"}
}