{
  "type": "Feature",
  "properties": {
    "iso:country":"CH",
    "sg:address":"Ruggerenstrasse 6",
    "sg:city":"Boppelsen",
    "sg:orig_category":"Architekturb\u00fcros",
    "sg:phone":"+41 18442471",
    "sg:postcode":"8113",
    "sg:province":"Z\u00fcrich",
    "wof:name":"Johannes Schaub Architekturb\u00fcro",
    "wof:placetype":"venue"
},
  "geometry": {"coordinates":[8.401148,47.47234],"type":"Point"}
}