{
  "type": "Feature",
  "properties": {
    "addr:full":"Aarestrasse 10 Zollikofen Bern 3052",
    "addr:housenumber":"10",
    "addr:postcode":"3052",
    "addr:street":"Aarestrasse",
    "iso:country":"CH",
    "sg:address":"Aarestrasse 10",
    "sg:city":"Zollikofen",
    "sg:orig_category":"Arztpraxen",
    "sg:phone":"+41 31 952 79 07",
    "sg:postcode":"3052",
    "sg:province":"Bern",
    "wof:name":"Dr.med.liliana Ilic Spezial\u00e4rztin Fmh",
    "wof:placetype":"venue"
},
  "geometry": {"coordinates":[7.487312,46.932205],"type":"Point"}
}