{
  "type": "Feature",
  "properties": {
    "iso:country":"CH",
    "sg:address":"Feldstrasse 6",
    "sg:city":"Aarburg",
    "sg:orig_category":"Arztpraxen",
    "sg:phone":"+41 62 791 44 88",
    "sg:postcode":"4663",
    "sg:province":"Aargau",
    "wof:name":"Dr.med.louis Clerc Spezialarzt Fmh",
    "wof:placetype":"venue"
},
  "geometry": {"coordinates":[7.901218,47.328899],"type":"Point"}
}