{
  "type": "Feature",
  "properties": {
    "iso:country":"CH",
    "sg:address":"Wilerstrasse 10 9517 Mettlen. Postfach",
    "sg:city":"Mettlen",
    "sg:orig_category":"RESTAURANTS: TEA-ROOMS",
    "sg:postcode":"9517",
    "sg:province":"Thurgau",
    "wof:name":"Krajnjanac Mihajlo",
    "wof:placetype":"venue"
},
  "geometry": {"coordinates":[9.1233243942,47.5289154053],"type":"Point"}
}