{
  "type": "Feature",
  "properties": {
    "iso:country":"CH",
    "sg:address":"Oberneuhofstrasse 8 6340 Baar. Postfach",
    "sg:city":"Baar",
    "sg:orig_category":"Wirtschaftspr\u00fcfung, Steuerberatung U Treuhand",
    "sg:postcode":"6340",
    "sg:province":"Zug",
    "wof:name":"Financial Consultancy & Services Treuhandb\u00fcro Hiebl Susan",
    "wof:placetype":"venue"
},
  "geometry": {"coordinates":[8.5162916183,47.1882781982],"type":"Point"}
}