{
  "type": "Feature",
  "properties": {
    "iso:country":"CH",
    "sg:address":"Seefeldquai 1 6318 Walchwil. Postfach 73",
    "sg:city":"Walchwil",
    "sg:orig_category":"G\u00fcterbef\u00f6rderung im Strassenverkehr",
    "sg:phone":"+41 41 758 12 74",
    "sg:postcode":"6318",
    "sg:province":"Zug",
    "wof:name":"H\u00fcrlimann Anton Ag",
    "wof:placetype":"venue"
},
  "geometry": {"coordinates":[8.5174093246,47.0956802368],"type":"Point"}
}