{
  "type": "Feature",
  "properties": {
    "iso:country":"CH",
    "sg:address":"Avenue Du Casino 42",
    "sg:city":"Montreux",
    "sg:orig_category":"Detailhandel mit B\u00fcchern Detailhandel mit B\u00fcchern, Zeitungen, Schreib U Papeteriewaren",
    "sg:phone":"+41 21 963 06 07",
    "sg:postcode":"1820",
    "sg:province":"Vaud",
    "wof:name":"Payot Sa",
    "wof:placetype":"venue"
},
  "geometry": {"coordinates":[6.911424,46.430653],"type":"Point"}
}