{
  "type": "Feature",
  "properties": {
    "iso:country":"CH",
    "sg:address":"Habsburgstrasse 8",
    "sg:city":"Z\u00fcrich",
    "sg:orig_category":"Detailhandel mit M\u00f6beln U Haushaltsgegenst\u00e4nden",
    "sg:phone":"+41 13617616",
    "sg:postcode":"8037",
    "sg:province":"Z\u00fcrich",
    "wof:name":"Zocca M\u00f6bel & Design",
    "wof:placetype":"venue"
},
  "geometry": {"coordinates":[8.5278253555,47.3917274475],"type":"Point"}
}