{
  "type": "Feature",
  "properties": {
    "iso:country":"CH",
    "sg:address":"Hakab",
    "sg:city":"N\u00fcrensdorf",
    "sg:orig_category":"Grosshandel mit Holz U Bauelementen aus Holz",
    "sg:phone":"+41 18365218",
    "sg:postcode":"8309",
    "sg:province":"Z\u00fcrich",
    "wof:name":"Albert Baltensberger Holzhandel",
    "wof:placetype":"venue"
},
  "geometry": {"coordinates":[8.6539621353,47.4509353638],"type":"Point"}
}