{
  "type": "Feature",
  "properties": {
    "iso:country":"CH",
    "sg:address":"Hohlstrasse 192 8004 Z\u00fcrich. Postfach 7332",
    "sg:city":"Z\u00fcrich",
    "sg:orig_category":"Grosshandel mit pharmazeutischen Erzeugnissen Herstellung von pharmazeutischen Grundstoffen",
    "sg:phone":"+41 12410500",
    "sg:postcode":"8004",
    "sg:province":"Z\u00fcrich",
    "wof:name":"Ecosol Ag",
    "wof:placetype":"venue"
},
  "geometry": {"coordinates":[8.5178842545,47.3813781738],"type":"Point"}
}