{
  "type": "Feature",
  "properties": {
    "iso:country":"CH",
    "sg:address":"Via San Gottardo",
    "sg:city":"Biasca",
    "sg:classifiers":[
        {
            "category":"Travel",
            "subcategory":"Hotels & Motels",
            "type":"Entertainment"
        }
    ],
    "sg:postcode":"6710",
    "sg:province":"Ticino",
    "sg:tags":[
        "hotels",
        "mit",
        "restaurant"
    ],
    "wof:name":"Sola Felice & Co.",
    "wof:placetype":"venue"
},
  "geometry": {"coordinates":[8.9681653976,46.3598899841],"type":"Point"}
}