{
  "type": "Feature",
  "properties": {
    "iso:country":"CH",
    "sg:address":"H\u00e4nggiturm 8755 Ennenda. Postfach",
    "sg:city":"Ennenda",
    "sg:orig_category":"Gesundheitswesen",
    "sg:postcode":"8755",
    "sg:province":"Glarus",
    "wof:name":"Therapiezentrum H\u00e4nggiturm Gmbh",
    "wof:placetype":"venue"
},
  "geometry": {"coordinates":[9.078795433,47.0329093933],"type":"Point"}
}