{
  "type": "Feature",
  "properties": {
    "iso:country":"CH",
    "sg:address":"Weissensteinstrasse 9",
    "sg:city":"Solothurn",
    "sg:orig_category":"Reparatur von Uhren U Schmuck",
    "sg:phone":"+41 32 623 44 23",
    "sg:postcode":"4500",
    "sg:province":"Solothurn",
    "wof:name":"Arthur Flury Uhren-pendulen",
    "wof:placetype":"venue"
},
  "geometry": {"coordinates":[7.5284562111,47.2109565735],"type":"Point"}
}