{
  "type": "Feature",
  "properties": {
    "iso:country":"CH",
    "sg:address":"Route Des Cerisiers 5",
    "sg:city":"Marly",
    "sg:orig_category":"Sonstiger Grosshandel",
    "sg:phone":"+41 26 430 03 00",
    "sg:postcode":"1723",
    "sg:province":"Fribourg",
    "wof:name":"Advanced Products Sa",
    "wof:placetype":"venue"
},
  "geometry": {"coordinates":[7.1630868912,46.7733268738],"type":"Point"}
}