{
  "type": "Feature",
  "properties": {
    "iso:country":"CH",
    "sg:address":"Spiezstrasse 12",
    "sg:city":"Frutigen",
    "sg:orig_category":"RESTAURANTS: TEA-ROOMS",
    "sg:postcode":"3714",
    "sg:province":"Bern",
    "wof:name":"Meyer Susi",
    "wof:placetype":"venue"
},
  "geometry": {"coordinates":[7.6635460854,47.1924057007],"type":"Point"}
}