{
  "type": "Feature",
  "properties": {
    "iso:country":"CH",
    "sg:address":"Ronco Via Al 16",
    "sg:city":"Muzzano",
    "sg:orig_category":"Sonstiger spezialisierter Hoch U Tiefbau",
    "sg:phone":"+41 79 620 75 45",
    "sg:postcode":"6933",
    "sg:province":"Ticino",
    "wof:name":"Mastlo Sagl",
    "wof:placetype":"venue"
},
  "geometry": {"coordinates":[8.9219303131,45.9981193542],"type":"Point"}
}