{
  "type": "Feature",
  "properties": {
    "iso:country":"CH",
    "sg:address":"Jurastrasse 22",
    "sg:city":"Langenthal",
    "sg:orig_category":"Steuer\u00e4mter",
    "sg:phone":"+41 79 332 72 80",
    "sg:postcode":"4900",
    "sg:province":"Bern",
    "wof:name":"Steuerverwaltung",
    "wof:placetype":"venue"
},
  "geometry": {"coordinates":[7.7886781693,47.2143821716],"type":"Point"}
}