{
  "type": "Feature",
  "properties": {
    "iso:country":"CH",
    "sg:address":"Kirchenfeld 469.",
    "sg:city":"Laupersdorf",
    "sg:orig_category":"Zimmerei, Dachdeckerei, Bauspenglerei U Abdichtung",
    "sg:phone":"+41 62 391 38 63",
    "sg:postcode":"4712",
    "sg:province":"Solothurn",
    "wof:name":"Brunner Heinz.",
    "wof:placetype":"venue"
},
  "geometry": {"coordinates":[7.6522831917,47.316570282],"type":"Point"}
}