{
  "type": "Feature",
  "properties": {
    "iso:country":"CH",
    "sg:address":"1922",
    "sg:city":"Salvan",
    "sg:orig_category":"Grosshandel mit Holz U Bauelementen aus Holz",
    "sg:phone":"+41 27 761 15 71",
    "sg:postcode":"1922",
    "sg:province":"Valais",
    "wof:name":"Roger Fournier Commerce De Bois",
    "wof:placetype":"venue"
},
  "geometry": {"coordinates":[7.020275116,46.1201057434],"type":"Point"}
}