{
  "type": "Feature",
  "properties": {
    "iso:country":"CH",
    "sg:address":"Juonweg 11",
    "sg:city":"Brig",
    "sg:orig_category":"Vermietung U Verpachtung von eigenen Immobilien",
    "sg:postcode":"3900",
    "sg:province":"Valais",
    "wof:name":"Alba Ag",
    "wof:placetype":"venue"
},
  "geometry": {"coordinates":[7.997628212,46.3179130554],"type":"Point"}
}