{
  "type": "Feature",
  "properties": {
    "iso:country":"CH",
    "sg:address":"Place Croix-blanche 11",
    "sg:city":"Epalinges",
    "sg:orig_category":"Detailhandel mit Waren verschiedener Art, Hauptrichtung Nahrungsmittel",
    "sg:phone":"+41 21 694 61 11",
    "sg:postcode":"1066",
    "sg:province":"Vaud",
    "wof:name":"Migros",
    "wof:placetype":"venue"
},
  "geometry": {"coordinates":[6.6713080406,46.5485649109],"type":"Point"}
}