{
  "type": "Feature",
  "properties": {
    "iso:country":"CH",
    "sg:address":"Seestrasse 672",
    "sg:city":"Meilen",
    "sg:orig_category":"Unternehmensberatung",
    "sg:phone":"+41 21 641 11 00",
    "sg:postcode":"8706",
    "sg:province":"Z\u00fcrich",
    "wof:name":"Estin & Co S\u00e0rl",
    "wof:placetype":"venue"
},
  "geometry": {"coordinates":[6.6175851822,46.5370407104],"type":"Point"}
}