{
  "type": "Feature",
  "properties": {
    "iso:country":"CH",
    "sg:address":"Kirchenrain 14",
    "sg:city":"Wattwil",
    "sg:orig_category":"Aktivit\u00e4ten der Krankenschwestern U Hebammen, Hauspflege",
    "sg:phone":"+41 17135656",
    "sg:postcode":"9630",
    "sg:province":"St. Gallen",
    "wof:name":"Spitex",
    "wof:placetype":"venue"
},
  "geometry": {"coordinates":[8.539611,47.288658],"type":"Point"}
}