{
  "type": "Feature",
  "properties": {
    "iso:country":"CH",
    "sg:address":"Ruelle Du Fr\u00eane 1",
    "sg:city":"Orbe",
    "sg:orig_category":"Sonstiger Fachdetailhandel mit Nahrungsmitteln, Getr\u00e4nken U Tabak in Verkaufsr\u00e4umen",
    "sg:postcode":"1350",
    "sg:province":"Vaud",
    "wof:name":"T-mipor Ag",
    "wof:placetype":"venue"
},
  "geometry": {"coordinates":[9.1381845474,47.5666694641],"type":"Point"}
}