{
  "type": "Feature",
  "properties": {
    "iso:country":"CH",
    "sg:address":"Avenue De Tivoli 2 1007 Lausanne Case Postale 2232",
    "sg:city":"Lausanne",
    "sg:orig_category":"Architektur U Ingenieurb\u00fcros Architekturb\u00fcros",
    "sg:phone":"+41 21 321 44 66",
    "sg:postcode":"1002",
    "sg:province":"Vaud",
    "wof:name":"Bureau D'architecture Sia E. Catella, E. Hauenstein, H. Ehrensperger Sa",
    "wof:placetype":"venue"
},
  "geometry": {"coordinates":[6.621689,46.520985],"type":"Point"}
}