{
  "type": "Feature",
  "properties": {
    "iso:country":"CH",
    "sg:address":"Via Sasso Carbaro",
    "sg:city":"Bellinzona",
    "sg:classifiers":[
        {
            "category":"Restaurant",
            "type":"Food & Drink"
        }
    ],
    "sg:phone":"+41 91 825 26 20",
    "sg:postcode":"6500",
    "sg:province":"Ticino",
    "wof:name":"Grotto Unterwalden",
    "wof:placetype":"venue"
},
  "geometry": {"coordinates":[9.0294084549,46.1892356873],"type":"Point"}
}