{
  "type": "Feature",
  "properties": {
    "addr:full":"Wirtschaftspark Soor B\u00fctschwil St. Gallen 9606",
    "addr:housenumber":"9606",
    "addr:street":"Wirtschaftspark;Buetschwil",
    "iso:country":"CH",
    "sg:address":"Wirtschaftspark Soor",
    "sg:city":"B\u00fctschwil",
    "sg:orig_category":"Architektur U Ingenieurb\u00fcros Innenausbau",
    "sg:phone":"+41 71 982 82 30",
    "sg:postcode":"9606",
    "sg:province":"St. Gallen",
    "wof:name":"Formateam Ag",
    "wof:placetype":"venue"
},
  "geometry": {"coordinates":[9.07207,47.362431],"type":"Point"}
}