{
  "type": "Feature",
  "properties": {
    "iso:country":"CH",
    "sg:address":"Im Gumprecht",
    "sg:city":"Emmetten",
    "sg:orig_category":"Unternehmensberatung",
    "sg:phone":"+41 41 622 00 12",
    "sg:postcode":"6376",
    "sg:province":"Nidwalden",
    "wof:name":"Triloga Knowledge Ag",
    "wof:placetype":"venue"
},
  "geometry": {"coordinates":[8.5116872787,46.9573783875],"type":"Point"}
}