{
  "type": "Feature",
  "properties": {
    "iso:country":"CH",
    "sg:address":"Rue Saint-georges 42",
    "sg:city":"Yverdon-les-bains",
    "sg:orig_category":"Sonstige mit Sport verbundene T\u00e4tigkeiten",
    "sg:phone":"+41 71 222 36 63",
    "sg:postcode":"1400",
    "sg:province":"Vaud",
    "wof:name":"Sport-schule Nippon Ag St. Gallen.",
    "wof:placetype":"venue"
},
  "geometry": {"coordinates":[9.3718166351,47.4218673706],"type":"Point"}
}