{
  "type": "Feature",
  "properties": {
    "iso:country":"CH",
    "sg:address":"Frauholzstr. 9e Postfach 174",
    "sg:city":"Steinen",
    "sg:classifiers":[
        {
            "category":"Professional",
            "subcategory":"Engineering",
            "type":"Services"
        }
    ],
    "sg:phone":"+41 31 741 15 73",
    "sg:postcode":"6422",
    "sg:province":"Schwyz",
    "sg:tags":[
        "machine",
        "-",
        "mechanical"
    ],
    "wof:name":"Klima- U. Filtertechnik Ag",
    "wof:placetype":"venue"
},
  "geometry": {"coordinates":[7.4012989998,46.9416656494],"type":"Point"}
}