{
  "type": "Feature",
  "properties": {
    "iso:country":"CH",
    "sg:address":"Rue De La Tour 33",
    "sg:city":"Lausanne",
    "sg:orig_category":"Wirtschaftspr\u00fcfung, Steuerberatung U Treuhand",
    "sg:phone":"+41 21 312 69 21",
    "sg:postcode":"1004",
    "sg:province":"Vaud",
    "wof:name":"Fiduciaire Montessuis D. Sa",
    "wof:placetype":"venue"
},
  "geometry": {"coordinates":[6.6281318665,46.5237197876],"type":"Point"}
}