{
  "type": "Feature",
  "properties": {
    "iso:country":"CH",
    "sg:address":"Gerzmattstrasse 16",
    "sg:city":"Wiedlisbach",
    "sg:orig_category":"Sportvereine Turnen Vereine Damen",
    "sg:postcode":"4537",
    "sg:province":"Bern",
    "wof:name":"Damenturnverein Wiedlisbach",
    "wof:placetype":"venue"
},
  "geometry": {"coordinates":[7.649283886,47.2549934387],"type":"Point"}
}