{
  "type": "Feature",
  "properties": {
    "iso:country":"CH",
    "sg:address":"Champs Des Roches 32",
    "sg:city":"Buix",
    "sg:orig_category":"G\u00fcterbef\u00f6rderung im Strassenverkehr",
    "sg:phone":"+41 32 475 53 79",
    "sg:postcode":"2925",
    "sg:province":"Jura",
    "wof:name":"H\u00fcrlimann Paul Transports",
    "wof:placetype":"venue"
},
  "geometry": {"coordinates":[7.0326547623,47.4796180725],"type":"Point"}
}