{
  "type": "Feature",
  "properties": {
    "iso:country":"CH",
    "sg:address":"Via Nova 66",
    "sg:city":"Domat/ems",
    "sg:orig_category":"Detailhandel mit Bekleidung Detailhandel mit Damenbekleidung",
    "sg:phone":"+41 71 222 39 69",
    "sg:postcode":"7013",
    "sg:province":"Graubunden",
    "wof:name":"Seima Mode Ag",
    "wof:placetype":"venue"
},
  "geometry": {"coordinates":[9.046934,47.465443],"type":"Point"}
}