{
  "type": "Feature",
  "properties": {
    "iso:country":"CH",
    "sg:address":"Zelg 560",
    "sg:city":"Wolfhalden",
    "sg:classifiers":[
        {
            "category":"Restaurant",
            "type":"Food & Drink"
        }
    ],
    "sg:phone":"+41 71 888 17 03",
    "sg:postcode":"9427",
    "sg:province":"Appenzell Ausserrhoden",
    "wof:name":"Restaurant Ochsen",
    "wof:placetype":"venue"
},
  "geometry": {"coordinates":[9.5737905502,47.4553031921],"type":"Point"}
}