{
  "type": "Feature",
  "properties": {
    "iso:country":"CH",
    "sg:address":"6912",
    "sg:city":"Pazzallo",
    "sg:orig_category":"Non-Classified Establishments",
    "sg:postcode":"6912",
    "sg:province":"Ticino",
    "wof:name":"Portmann Franz Reparaturwerkstatt Und Pneuservice",
    "wof:placetype":"venue"
},
  "geometry": {"coordinates":[8.0499401093,46.9792098999],"type":"Point"}
}