{
  "type": "Feature",
  "properties": {
    "iso:country":"CH",
    "sg:address":"En Publoz 1070 Puidoux. Postfach",
    "sg:city":"Puidoux",
    "sg:orig_category":"Detailhandel mit Waren verschiedener Art, Hauptrichtung Nahrungsmittel",
    "sg:postcode":"1070",
    "sg:province":"Vaud",
    "wof:name":"Curdy Anita",
    "wof:placetype":"venue"
},
  "geometry": {"coordinates":[6.7696700096,46.4933547974],"type":"Point"}
}