{
  "type": "Feature",
  "properties": {
    "iso:country":"CH",
    "sg:address":"Waldeggstrasse 24 6020 Emmenbr\u00fccke. Postfach",
    "sg:city":"Emmenbr\u00fccke",
    "sg:orig_category":"Grosshandel mit sonstigen Gebrauchs U Verbrauchsg\u00fctern",
    "sg:postcode":"6020",
    "sg:province":"Luzern",
    "wof:name":"Fuog Karl",
    "wof:placetype":"venue"
},
  "geometry": {"coordinates":[8.8589801788,47.6599311829],"type":"Point"}
}