{
  "type": "Feature",
  "properties": {
    "iso:country":"CH",
    "sg:address":"Sonnhaldenweg 18",
    "sg:city":"Sissach",
    "sg:orig_category":"K\u00fcnstlerische Schulen",
    "sg:phone":"+41 61 971 37 42",
    "sg:postcode":"4450",
    "sg:province":"Basel-Landschaft",
    "wof:name":"Jugendmusikschule Pr\u00e4s.frau Dora Mastria",
    "wof:placetype":"venue"
},
  "geometry": {"coordinates":[7.8115887642,47.4708251953],"type":"Point"}
}