{
  "type": "Feature",
  "properties": {
    "iso:country":"CH",
    "sg:address":"Albisriederplatz 1",
    "sg:city":"Z\u00fcrich",
    "sg:orig_category":"Detailhandel mit Fleisch U Fleischwaren",
    "sg:phone":"+41 31 971 04 41",
    "sg:postcode":"8003",
    "sg:province":"Z\u00fcrich",
    "wof:name":"Metzgerei Hort",
    "wof:placetype":"venue"
},
  "geometry": {"coordinates":[7.4140257835,46.9202003479],"type":"Point"}
}