{
  "type": "Feature",
  "properties": {
    "iso:country":"CH",
    "sg:address":"Via Soave 10",
    "sg:city":"Lugano",
    "sg:orig_category":"RESTAURANTS: TEA-ROOMS",
    "sg:phone":"+41 91 922 01 51",
    "sg:postcode":"6900",
    "sg:province":"Ticino",
    "wof:name":"Ristorante Sayonara Sa",
    "wof:placetype":"venue"
},
  "geometry": {"coordinates":[8.9501056671,46.0045623779],"type":"Point"}
}