{
  "type": "Feature",
  "properties": {
    "iso:country":"CH",
    "sg:address":"Sempacherstrasse 19",
    "sg:city":"Luzern",
    "sg:classifiers":[
        {
            "category":"Professional",
            "subcategory":"Employment Agencies",
            "type":"Services"
        }
    ],
    "sg:phone":"+41 41 220 19 19",
    "sg:postcode":"6003",
    "sg:province":"Luzern",
    "sg:tags":[
        "personal",
        "u",
        "stellenvermittlung"
    ],
    "wof:name":"Gst Stellendienst Ag Luzern",
    "wof:placetype":"venue"
},
  "geometry": {"coordinates":[8.3090610504,47.0470848083],"type":"Point"}
}