{
  "type": "Feature",
  "properties": {
    "addr:full":"Klingentalstrasse 58 Basel Basel-Stadt 4057",
    "addr:housenumber":"58",
    "addr:postcode":"4057",
    "addr:street":"Klingentalstrasse",
    "iso:country":"CH",
    "sg:address":"Klingentalstrasse 58",
    "sg:city":"Basel",
    "sg:orig_category":"Arztpraxen",
    "sg:phone":"+41 61 691 33 26",
    "sg:postcode":"4057",
    "sg:province":"Basel-Stadt",
    "wof:name":"Dres Med. Gl\u00e4ttli & Stockmeyer \u00c4rzte F.allgemeine Medizin Fmh",
    "wof:placetype":"venue"
},
  "geometry": {"coordinates":[7.59599,47.564159],"type":"Point"}
}