{
  "type": "Feature",
  "properties": {
    "iso:country":"CH",
    "sg:address":"Sch\u00fctzenmattstrasse 3",
    "sg:city":"W\u00e4denswil",
    "sg:orig_category":"Detailhandel mit M\u00f6beln U Haushaltsgegenst\u00e4nden",
    "sg:postcode":"8820",
    "sg:province":"Z\u00fcrich",
    "wof:name":"Berger Inneneinrichtungen",
    "wof:placetype":"venue"
},
  "geometry": {"coordinates":[8.6669845581,47.2270622253],"type":"Point"}
}