{
  "type": "Feature",
  "properties": {
    "iso:country":"CH",
    "sg:address":"Verena Conzett-strasse 34",
    "sg:city":"Z\u00fcrich",
    "sg:orig_category":"Unternehmensberatung Wirtschaftspr\u00fcfung, Steuerberatung U Treuhand",
    "sg:phone":"+41 12412922",
    "sg:postcode":"8004",
    "sg:province":"Z\u00fcrich",
    "wof:name":"Marquart Treuhand Ag",
    "wof:placetype":"venue"
},
  "geometry": {"coordinates":[8.5254364014,47.3701400757],"type":"Point"}
}