{
  "type": "Feature",
  "properties": {
    "iso:country":"CH",
    "sg:address":"Allenbergstrasse 33",
    "sg:city":"St\u00e4fa",
    "sg:orig_category":"Herstellung U Veredlung von sonstigem Glas",
    "sg:phone":"+41 19268124",
    "sg:postcode":"8712",
    "sg:province":"Z\u00fcrich",
    "wof:name":"Wesa-glasbearbeitung W. K\u00fcng Fenster - Kunstglaserei - Reparaturen - Winterg\u00e4rten",
    "wof:placetype":"venue"
},
  "geometry": {"coordinates":[8.7215709686,47.2494812012],"type":"Point"}
}