{
  "type": "Feature",
  "properties": {
    "iso:country":"CH",
    "sg:address":"A L'en 12",
    "sg:city":"Samedan",
    "sg:orig_category":"Vorschulen, Kinderg\u00e4rten",
    "sg:phone":"+41 81 852 50 41",
    "sg:postcode":"7503",
    "sg:province":"Graubunden",
    "wof:name":"Kindergarten A L'en",
    "wof:placetype":"venue"
},
  "geometry": {"coordinates":[9.8728303909,46.5353507996],"type":"Point"}
}