{
  "type": "Feature",
  "properties": {
    "iso:country":"CH",
    "sg:address":"Vicolo Bena 2",
    "sg:city":"Mendrisio",
    "sg:orig_category":"Unclassifiable Establishments",
    "sg:postcode":"6850",
    "sg:province":"Ticino",
    "wof:name":"Tecnostampi Trading Int. Limitada, Succ. Di Lugano",
    "wof:placetype":"venue"
},
  "geometry": {"coordinates":[8.9917097092,45.8694190979],"type":"Point"}
}