{
  "type": "Feature",
  "properties": {
    "iso:country":"CH",
    "sg:address":"H\u00f6henweg 2",
    "sg:city":"M\u00fcnchenbuchsee",
    "sg:orig_category":"Architektur U Ingenieurb\u00fcros",
    "sg:phone":"+41 31 868 48 48",
    "sg:postcode":"3053",
    "sg:province":"Bern",
    "wof:name":"Ingenieurb\u00fcro Ikp, Iten, Kaltenrieder + Partner Ag",
    "wof:placetype":"venue"
},
  "geometry": {"coordinates":[7.43964,47.023457],"type":"Point"}
}