{
  "type": "Feature",
  "properties": {
    "iso:country":"CH",
    "sg:address":"Dufourstrasse 90",
    "sg:city":"Z\u00fcrich",
    "sg:orig_category":"Unclassifiable Establishments",
    "sg:postcode":"8008",
    "sg:province":"Z\u00fcrich",
    "wof:name":"E-technik Ag",
    "wof:placetype":"venue"
},
  "geometry": {"coordinates":[8.5508108139,47.3596343994],"type":"Point"}
}