{
  "type": "Feature",
  "properties": {
    "iso:country":"CH",
    "sg:address":"Maihofstrasse 83",
    "sg:city":"Luzern",
    "sg:orig_category":"Bauingenieurb\u00fcros",
    "sg:phone":"+41 41 420 85 80",
    "sg:postcode":"6006",
    "sg:province":"Luzern",
    "wof:name":"Ren\u00e9 J. B\u00e4chler Bauleitung",
    "wof:placetype":"venue"
},
  "geometry": {"coordinates":[8.31338,47.066723],"type":"Point"}
}