{
  "type": "Feature",
  "properties": {
    "iso:country":"CH",
    "sg:address":"Seestrasse 157",
    "sg:city":"St\u00e4fa",
    "sg:orig_category":"Handel mit Automobilen Vermietung von Automobilen",
    "sg:phone":"+41 19263240",
    "sg:postcode":"8712",
    "sg:province":"Z\u00fcrich",
    "wof:name":"Autogo Ag Autovermietungen",
    "wof:placetype":"venue"
},
  "geometry": {"coordinates":[8.7342596054,47.2345581055],"type":"Point"}
}