{
  "type": "Feature",
  "properties": {
    "iso:country":"CH",
    "sg:address":"7417",
    "sg:city":"Trans",
    "sg:orig_category":"G\u00fcterbef\u00f6rderung im Strassenverkehr Regelm\u00e4ssige Personenbef\u00f6rderung im Fernverkehr",
    "sg:phone":"+41 81 655 11 24",
    "sg:postcode":"7417",
    "sg:province":"Graubunden",
    "wof:name":"Paul Tscharner Postkurse & Transporte",
    "wof:placetype":"venue"
},
  "geometry": {"coordinates":[9.4602603912,46.7651596069],"type":"Point"}
}