{
  "type": "Feature",
  "properties": {
    "iso:country":"CH",
    "sg:address":"Grand-rue 57",
    "sg:city":"Fribourg",
    "sg:orig_category":"Detailhandel mit Textilien",
    "sg:postcode":"1700",
    "sg:province":"Fribourg",
    "wof:name":"Zi\u00f6rjen Jeanne",
    "wof:placetype":"venue"
},
  "geometry": {"coordinates":[7.1377701759,46.7979011536],"type":"Point"}
}