{
  "type": "Feature",
  "properties": {
    "iso:country":"CH",
    "sg:address":"Finkernstrasse 1",
    "sg:city":"Kreuzlingen",
    "sg:orig_category":"Grosshandel mit Getr\u00e4nken",
    "sg:phone":"+41 71 688 32 46",
    "sg:postcode":"8280",
    "sg:province":"Thurgau",
    "wof:name":"Hangard Andr\u00e9",
    "wof:placetype":"venue"
},
  "geometry": {"coordinates":[9.1684894562,47.6523132324],"type":"Point"}
}