{
  "type": "Feature",
  "properties": {
    "iso:country":"CH",
    "sg:address":"Seidenstrasse 47 8400 Winterthur. Postfach",
    "sg:city":"Winterthur",
    "sg:orig_category":"Mit dem Versicherungsgewerbe verbundene T\u00e4tigkeiten",
    "sg:postcode":"8400",
    "sg:province":"Z\u00fcrich",
    "wof:name":"Ren\u00e9 Gubler",
    "wof:placetype":"venue"
},
  "geometry": {"coordinates":[8.7348003387,47.4991455078],"type":"Point"}
}