{
  "type": "Feature",
  "properties": {
    "iso:country":"CH",
    "sg:address":"Codeborgo Via 17",
    "sg:city":"Bellinzona",
    "sg:orig_category":"RESTAURANTS: TEA-ROOMS",
    "sg:postcode":"6500",
    "sg:province":"Ticino",
    "wof:name":"Seva.chris. S\u00e0rl",
    "wof:placetype":"venue"
},
  "geometry": {"coordinates":[7.094824791,47.062915802],"type":"Point"}
}