{
  "type": "Feature",
  "properties": {
    "iso:country":"CH",
    "sg:address":"Centralbahnplatz 2",
    "sg:city":"Basel",
    "sg:classifiers":[
        {
            "category":"Banks & Credit Unions",
            "subcategory":"Bank",
            "type":"Services"
        }
    ],
    "sg:postcode":"4002",
    "sg:province":"Basel-Stadt",
    "wof:name":"Bank Globo",
    "wof:placetype":"venue"
},
  "geometry": {"coordinates":[8.783489,47.201557],"type":"Point"}
}