{
  "type": "Feature",
  "properties": {
    "iso:country":"CH",
    "sg:address":"Hauptstrasse 28 Guntershausen B. Aadorf 8355 Aadorf. Postfach",
    "sg:city":"Guntershausen",
    "sg:orig_category":"Kauf U Verkauf von Immobilien auf eigene Rechnung",
    "sg:postcode":"8357",
    "sg:province":"Thurgau",
    "wof:name":"Hasler + Kressbach Gmbh",
    "wof:placetype":"venue"
},
  "geometry": {"coordinates":[8.9064102173,47.4980545044],"type":"Point"}
}