{
  "type": "Feature",
  "properties": {
    "iso:country":"CH",
    "sg:address":"Piazza Riforma 9 6900 Lugano. Postfach",
    "sg:city":"Lugano",
    "sg:orig_category":"RESTAURANTS: TEA-ROOMS",
    "sg:phone":"+41 91 922 21 73",
    "sg:postcode":"6901",
    "sg:province":"Ticino",
    "wof:name":"Sa Caff\u00e9 Federale",
    "wof:placetype":"venue"
},
  "geometry": {"coordinates":[8.9511537552,46.0040092468],"type":"Point"}
}