{
  "type": "Feature",
  "properties": {
    "addr:full":"Rue Des Moulins 19 Del\u00e9mont Jura 2800",
    "addr:housenumber":"19",
    "addr:postcode":"2800",
    "addr:street":"Rue Des Moulins;Jura",
    "iso:country":"CH",
    "sg:address":"Rue Des Moulins 19",
    "sg:city":"Del\u00e9mont",
    "sg:orig_category":"Arbeitnehmerverb\u00e4nde",
    "sg:phone":"+41 27 323 51 44",
    "sg:postcode":"2800",
    "sg:province":"Jura",
    "wof:name":"Union Syndicale Valaisanne",
    "wof:placetype":"venue"
},
  "geometry": {"coordinates":[7.359311,46.231594],"type":"Point"}
}