{
  "type": "Feature",
  "properties": {
    "iso:country":"CH",
    "sg:address":"9526",
    "sg:city":"Zuckenriet",
    "sg:orig_category":"Detailhandel mit Textilien Detailhandel mit elektrischen Haushaltsger\u00e4ten",
    "sg:postcode":"9526",
    "sg:province":"St. Gallen",
    "wof:name":"Hans Niedermann Bernina-n\u00e4hmaschinen",
    "wof:placetype":"venue"
},
  "geometry": {"coordinates":[9.1658802032,47.4905204773],"type":"Point"}
}