{
  "type": "Feature",
  "properties": {
    "addr:full":"Zur Kirche M\u00f6rel Valais 3983",
    "addr:postcode":"3983",
    "addr:street":"Zur Kirche Moerel",
    "iso:country":"CH",
    "sg:address":"Zur Kirche",
    "sg:city":"M\u00f6rel",
    "sg:orig_category":"Detailhandel mit Brot, Back U S\u00fcsswaren",
    "sg:phone":"+41 71 744 26 28",
    "sg:postcode":"3983",
    "sg:province":"Valais",
    "wof:name":"B\u00e4ckerei K\u00fcnzler Gmbh",
    "wof:placetype":"venue"
},
  "geometry": {"coordinates":[9.645597,47.450291],"type":"Point"}
}