{
  "type": "Feature",
  "properties": {
    "iso:country":"CH",
    "sg:address":"Rue De Mauborget 23 1510 Moudon Case Postale 279",
    "sg:city":"Moudon",
    "sg:orig_category":"Vereine Musik/Blasmusik",
    "sg:phone":"+41 21 905 23 68",
    "sg:postcode":"1510",
    "sg:province":"Vaud",
    "wof:name":"Union Instrumentale De Moudon",
    "wof:placetype":"venue"
},
  "geometry": {"coordinates":[6.7976078987,46.6673126221],"type":"Point"}
}