{
  "type": "Feature",
  "properties": {
    "addr:full":"Hauptstr. 293 Uerkheim Aargau 4813",
    "addr:housenumber":"293",
    "addr:postcode":"4813",
    "addr:street":"Hauptstr.",
    "iso:country":"CH",
    "sg:address":"Hauptstr. 293",
    "sg:city":"Uerkheim",
    "sg:classifiers":[
        {
            "category":"Banks & Credit Unions",
            "subcategory":"Bank",
            "type":"Services"
        }
    ],
    "sg:phone":"+41 62 721 42 77",
    "sg:postcode":"4813",
    "sg:province":"Aargau",
    "wof:name":"Bank Suhrental, Gesch\u00e4ftsstelle",
    "wof:placetype":"venue"
},
  "geometry": {"coordinates":[8.024054,47.303932],"type":"Point"}
}