{
  "type": "Feature",
  "properties": {
    "iso:country":"CH",
    "sg:address":"Avenue De Rumine 17",
    "sg:city":"Lausanne",
    "sg:orig_category":"Arztpraxen",
    "sg:phone":"+41 21 323 65 34",
    "sg:postcode":"1005",
    "sg:province":"Vaud",
    "wof:name":"Dr M\u00e9d. Andreas Graf M\u00e9decin Sp\u00e9cialiste Fmh",
    "wof:placetype":"venue"
},
  "geometry": {"coordinates":[6.640721,46.517223],"type":"Point"}
}