{
  "type": "Feature",
  "properties": {
    "iso:country":"CH",
    "sg:address":"Bachweg 16",
    "sg:city":"Aarburg",
    "sg:orig_category":"Unternehmensberatung",
    "sg:phone":"+41 55 442 48 30",
    "sg:postcode":"4663",
    "sg:province":"Aargau",
    "wof:name":"Mulfeer Ag",
    "wof:placetype":"venue"
},
  "geometry": {"coordinates":[8.8600683212,47.1943817139],"type":"Point"}
}