{
  "type": "Feature",
  "properties": {
    "iso:country":"CH",
    "sg:address":"Herrengasse 22",
    "sg:city":"Balsthal",
    "sg:orig_category":"Detailhandel mit Uhren U Schmuck",
    "sg:phone":"+41 62 391 46 70",
    "sg:postcode":"4710",
    "sg:province":"Solothurn",
    "wof:name":"Marguerite Meier Goldschmiede",
    "wof:placetype":"venue"
},
  "geometry": {"coordinates":[7.6977248192,47.3161277771],"type":"Point"}
}