{
  "type": "Feature",
  "properties": {
    "iso:country":"CH",
    "sg:address":"Marktstrasse 8 6060 Sarnen. Postfach 10",
    "sg:city":"Sarnen",
    "sg:orig_category":"Versicherungen Generalagenturen",
    "sg:phone":"+41 41 660 67 48",
    "sg:postcode":"6060",
    "sg:province":"Obwalden",
    "wof:name":"Alpina Versicherungen Generalagentur Obwalden",
    "wof:placetype":"venue"
},
  "geometry": {"coordinates":[8.2490301132,46.8971786499],"type":"Point"}
}