{
  "type": "Feature",
  "properties": {
    "addr:full":"Via Ferri 2 Lugano Ticino 6900",
    "addr:housenumber":"2",
    "addr:postcode":"6900",
    "addr:street":"Via Ferri",
    "iso:country":"CH",
    "sg:address":"Via Ferri 2",
    "sg:city":"Lugano",
    "sg:orig_category":"Architektur U Ingenieurb\u00fcros",
    "sg:postcode":"6900",
    "sg:province":"Ticino",
    "wof:name":"Bortoluzzi E Brugnoli.",
    "wof:placetype":"venue"
},
  "geometry": {"coordinates":[8.955469,46.014435],"type":"Point"}
}