{
  "type": "Feature",
  "properties": {
    "iso:country":"CH",
    "sg:address":"Route D'etraz",
    "sg:city":"Mont-sur-rolle",
    "sg:classifiers":[
        {
            "category":"Travel",
            "subcategory":"Hotels & Motels",
            "type":"Entertainment"
        }
    ],
    "sg:phone":"+41 21 825 15 98",
    "sg:postcode":"1185",
    "sg:province":"Vaud",
    "sg:tags":[
        "hotels",
        "mit",
        "restaurant"
    ],
    "wof:name":"H\u00f4tel De La Jeune-suisse",
    "wof:placetype":"venue"
},
  "geometry": {"coordinates":[6.336660862,46.4675788879],"type":"Point"}
}