{
  "type": "Feature",
  "properties": {
    "iso:country":"CH",
    "sg:address":"H\u00fcttenbrunnenstrasse",
    "sg:city":"Weite",
    "sg:orig_category":"G\u00fcterbef\u00f6rderung im Strassenverkehr",
    "sg:phone":"+41 81 783 21 67",
    "sg:postcode":"9476",
    "sg:province":"St. Gallen",
    "wof:name":"Viktor Hanselmann Transporte",
    "wof:placetype":"venue"
},
  "geometry": {"coordinates":[9.4991102219,47.0914001465],"type":"Point"}
}