{
  "type": "Feature",
  "properties": {
    "iso:country":"CH",
    "sg:address":"Fronwagplatz 22 8200 Schaffhausen. Postfach",
    "sg:city":"Schaffhausen",
    "sg:orig_category":"Warenh\u00e4user",
    "sg:phone":"+41 52 625 51 31",
    "sg:postcode":"8201",
    "sg:province":"Schaffhausen",
    "wof:name":"Abm Au Bon March\u00e9",
    "wof:placetype":"venue"
},
  "geometry": {"coordinates":[8.6335859299,47.6971931458],"type":"Point"}
}