{
  "type": "Feature",
  "properties": {
    "iso:country":"CH",
    "sg:address":"B\u00f6hnirainstrasse 12",
    "sg:city":"Thalwil",
    "sg:orig_category":"Detailhandel mit Computern U Software",
    "sg:phone":"+41 17210708",
    "sg:postcode":"8800",
    "sg:province":"Z\u00fcrich",
    "wof:name":"Computer Shop Thalwil",
    "wof:placetype":"venue"
},
  "geometry": {"coordinates":[8.563885,47.284069],"type":"Point"}
}