{
  "type": "Feature",
  "properties": {
    "iso:country":"CH",
    "sg:address":"Bahnhofstrasse",
    "sg:city":"Flums",
    "sg:orig_category":"Interessenvertretungen",
    "sg:postcode":"8890",
    "sg:province":"St. Gallen",
    "wof:name":"Sarganserl\u00e4ndische Stiftung F\u00fcr Die Jugend.",
    "wof:placetype":"venue"
},
  "geometry": {"coordinates":[9.3478298187,47.0957794189],"type":"Point"}
}