{
  "type": "Feature",
  "properties": {
    "iso:country":"CH",
    "sg:address":"Neubr\u00fcckstrasse 93",
    "sg:city":"Bern",
    "sg:orig_category":"Arztpraxen",
    "sg:phone":"+41 31 302 55 11",
    "sg:postcode":"3012",
    "sg:province":"Bern",
    "wof:name":"Dr.med.stephan Steiner Spezialarzt Fmh",
    "wof:placetype":"venue"
},
  "geometry": {"coordinates":[7.436234,46.958263],"type":"Point"}
}