{
  "type": "Feature",
  "properties": {
    "iso:country":"CH",
    "sg:address":"Claisberg",
    "sg:city":"Neftenbach",
    "sg:classifiers":[
        {
            "category":"Professional",
            "subcategory":"Employment Agencies",
            "type":"Services"
        }
    ],
    "sg:postcode":"8413",
    "sg:province":"Z\u00fcrich",
    "sg:tags":[
        "personal",
        "u",
        "stellenvermittlung"
    ],
    "wof:name":"Ris & Solva Svs",
    "wof:placetype":"venue"
},
  "geometry": {"coordinates":[8.6492996216,47.5255355835],"type":"Point"}
}