{
  "type": "Feature",
  "properties": {
    "iso:country":"CH",
    "sg:address":"Vy-de-montorge 1",
    "sg:city":"Mies",
    "sg:classifiers":[
        {
            "category":"Banks & Credit Unions",
            "subcategory":"Bank",
            "type":"Services"
        }
    ],
    "sg:phone":"+41 27 783 13 09",
    "sg:postcode":"1295",
    "sg:province":"Vaud",
    "wof:name":"Banque Raiffeisen Orsieres",
    "wof:placetype":"venue"
},
  "geometry": {"coordinates":[7.14629,46.030689],"type":"Point"}
}