{
  "type": "Feature",
  "properties": {
    "iso:country":"CH",
    "sg:address":"2853",
    "sg:city":"Courfaivre",
    "sg:orig_category":"Vereine Gesang",
    "sg:postcode":"2853",
    "sg:province":"Jura",
    "wof:name":"St\u00e9 De Chant",
    "wof:placetype":"venue"
},
  "geometry": {"coordinates":[7.2807021141,47.3344116211],"type":"Point"}
}