{
  "type": "Feature",
  "properties": {
    "iso:country":"CH",
    "sg:address":"Schulstrasse 72",
    "sg:city":"Schlieren",
    "sg:orig_category":"Herstellung von k\u00e4lte U lufttechnischen Erzeugnissen f\u00fcr gewerbliche Zwecke",
    "sg:postcode":"8952",
    "sg:province":"Z\u00fcrich",
    "wof:name":"Goca-klima L\u00dcftung K\u00c4lte Technik Bajic J.",
    "wof:placetype":"venue"
},
  "geometry": {"coordinates":[8.4609298706,47.3963508606],"type":"Point"}
}