{
  "type": "Feature",
  "properties": {
    "iso:country":"CH",
    "sg:address":"Langfuri",
    "sg:city":"Oberschan",
    "sg:orig_category":"Elektrischer Leitungsbau Handelsvermittlung von Maschinen, technischem Bedarf, Wasser U Luftfahrzeug",
    "sg:phone":"+41 81 740 20 25",
    "sg:postcode":"9479",
    "sg:province":"St. Gallen",
    "wof:name":"Pro-part Ag",
    "wof:placetype":"venue"
},
  "geometry": {"coordinates":[9.4726724625,47.0993728638],"type":"Point"}
}