{
  "type": "Feature",
  "properties": {
    "iso:country":"CH",
    "sg:address":"Rosenb\u00f6hleli 10",
    "sg:city":"Appenzell",
    "sg:orig_category":"Allgemeiner Hoch U Tiefbau Allgemeiner Hochbau",
    "sg:phone":"+41 71 787 36 22",
    "sg:postcode":"9050",
    "sg:province":"Appenzell Innerhoden",
    "wof:name":"H\u00f6rler Emil Ag",
    "wof:placetype":"venue"
},
  "geometry": {"coordinates":[9.429396,47.346081],"type":"Point"}
}