{
  "type": "Feature",
  "properties": {
    "iso:country":"CH",
    "sg:address":"Rue Du Midi 33 2610 St-imier. Postfach",
    "sg:city":"St-imier",
    "sg:orig_category":"Arbeitnehmerverb\u00e4nde",
    "sg:phone":"+41 27 722 85 65",
    "sg:postcode":"2610",
    "sg:province":"Bern",
    "wof:name":"F\u00e9d.chr\u00e9t.des Travailleurs De La Construction De Suisse",
    "wof:placetype":"venue"
},
  "geometry": {"coordinates":[7.076327,46.103317],"type":"Point"}
}