{
  "type": "Feature",
  "properties": {
    "addr:full":"Perry-center Oftringen Aargau 4665",
    "addr:housenumber":"4665",
    "iso:country":"CH",
    "sg:address":"Perry-center",
    "sg:city":"Oftringen",
    "sg:orig_category":"Detailhandel mit Beleuchtungs U Haushaltsgegenst\u00e4nden Detailhandel mit elektrischen Haushalts, Radio",
    "sg:phone":"+41 55 415 66 50",
    "sg:postcode":"4665",
    "sg:province":"Aargau",
    "wof:name":"Fust Ag Elektroapparate",
    "wof:placetype":"venue"
},
  "geometry": {"coordinates":[8.778135,47.201378],"type":"Point"}
}