{
  "type": "Feature",
  "properties": {
    "iso:country":"CH",
    "sg:address":"Widenb\u00fcelstrasse 24",
    "sg:city":"Unterengstringen",
    "sg:orig_category":"Detektivb\u00fcros U \u00dcberwachung",
    "sg:phone":"+41 17503736",
    "sg:postcode":"8103",
    "sg:province":"Z\u00fcrich",
    "wof:name":"Bossotto Sicherheitsberatung Gmbh",
    "wof:placetype":"venue"
},
  "geometry": {"coordinates":[8.4467048645,47.4134101868],"type":"Point"}
}