{
  "type": "Feature",
  "properties": {
    "iso:country":"CH",
    "sg:address":"Stoppa Viale Carlo 10",
    "sg:city":"Chiasso",
    "sg:orig_category":"Hardwareberatung",
    "sg:phone":"+41 32 652 04 03",
    "sg:postcode":"6830",
    "sg:province":"Ticino",
    "wof:name":"Verest Di Awokande Williams",
    "wof:placetype":"venue"
},
  "geometry": {"coordinates":[9.033490181,45.8364524841],"type":"Point"}
}