{
  "type": "Feature",
  "properties": {
    "iso:country":"CH",
    "sg:address":"Buron Rue Du 4",
    "sg:city":"Yverdon-les-bains",
    "sg:orig_category":"Herstellung von k\u00e4lte U lufttechnischen Erzeugnissen f\u00fcr gewerbliche Zwecke",
    "sg:postcode":"1400",
    "sg:province":"Vaud",
    "wof:name":"Schlup Eric",
    "wof:placetype":"venue"
},
  "geometry": {"coordinates":[6.6414198875,46.7786331177],"type":"Point"}
}