{
  "type": "Feature",
  "properties": {
    "addr:full":"Buchholzstrasse 13 Stettlen Bern 3066",
    "addr:housenumber":"13",
    "addr:postcode":"3066",
    "addr:street":"Buchholzstrasse;Bern",
    "iso:country":"CH",
    "sg:address":"Buchholzstrasse 13",
    "sg:city":"Stettlen",
    "sg:orig_category":"Datenverarbeitungsdienste",
    "sg:phone":"+41 31 931 98 39",
    "sg:postcode":"3066",
    "sg:province":"Bern",
    "wof:name":"Ewald Mund Informatik",
    "wof:placetype":"venue"
},
  "geometry": {"coordinates":[7.52417,46.960327],"type":"Point"}
}