{
  "type": "Feature",
  "properties": {
    "iso:country":"CH",
    "sg:address":"In Der Gandstrasse 1",
    "sg:city":"Zumikon",
    "sg:orig_category":"Detailhandel mit Spielwaren Versandhandel",
    "sg:phone":"+41 19182676",
    "sg:postcode":"8126",
    "sg:province":"Z\u00fcrich",
    "wof:name":"Mirawo Modelleisenbahnen",
    "wof:placetype":"venue"
},
  "geometry": {"coordinates":[8.6173124313,47.3359146118],"type":"Point"}
}