{
  "type": "Feature",
  "properties": {
    "iso:country":"CH",
    "sg:address":"Thi\u00e8le 23 F Quai De La",
    "sg:city":"Yverdon-les-bains",
    "sg:orig_category":"Wirtschaftspr\u00fcfung, Steuerberatung U Treuhand",
    "sg:phone":"+41 21 944 26 76",
    "sg:postcode":"1400",
    "sg:province":"Vaud",
    "wof:name":"Pilloud Georges",
    "wof:placetype":"venue"
},
  "geometry": {"coordinates":[6.8612089157,46.4568252563],"type":"Point"}
}