{
  "type": "Feature",
  "properties": {
    "iso:country":"CH",
    "sg:address":"Bahnhofstrasse 35",
    "sg:city":"Schwerzenbach",
    "sg:orig_category":"Unternehmensberatung",
    "sg:postcode":"8603",
    "sg:province":"Z\u00fcrich",
    "wof:name":"Zindel Beratung Revision Treuhand",
    "wof:placetype":"venue"
},
  "geometry": {"coordinates":[8.6621675491,47.3842506409],"type":"Point"}
}