{
  "type": "Feature",
  "properties": {
    "iso:country":"CH",
    "sg:address":"Bahnhofstrasse 180",
    "sg:city":"Uzwil",
    "sg:orig_category":"Kauf U Verkauf von Immobilien auf eigene Rechnung",
    "sg:postcode":"9240",
    "sg:province":"St. Gallen",
    "wof:name":"Immobau-sch\u00f6nau Ag",
    "wof:placetype":"venue"
},
  "geometry": {"coordinates":[9.1519069672,47.4450111389],"type":"Point"}
}