{
  "type": "Feature",
  "properties": {
    "iso:country":"CH",
    "sg:address":"Rue Des Fahys 141",
    "sg:city":"Neuenburg",
    "sg:orig_category":"Reinigungsgewerbe",
    "sg:phone":"+41 32 725 78 67",
    "sg:postcode":"2000",
    "sg:province":"Neuch\u00e2tel",
    "wof:name":"Simon Michel",
    "wof:placetype":"venue"
},
  "geometry": {"coordinates":[6.9455971718,47.0009727478],"type":"Point"}
}