{
  "type": "Feature",
  "properties": {
    "addr:full":"Chemin De La Grassili\u00e8re 8 Cortaillod Neuch\u00e2tel 2016",
    "addr:housenumber":"8",
    "addr:postcode":"2016",
    "addr:street":"Chemin De La Grassilie\u0300Re;Neucha\u0302Tel",
    "iso:country":"CH",
    "sg:address":"Chemin De La Grassili\u00e8re 8",
    "sg:city":"Cortaillod",
    "sg:orig_category":"Autogaragen",
    "sg:phone":"+41 32 841 51 50",
    "sg:postcode":"2016",
    "sg:province":"Neuch\u00e2tel",
    "wof:name":"Olivier Quain Garage",
    "wof:placetype":"venue"
},
  "geometry": {"coordinates":[6.844449,46.945007],"type":"Point"}
}