{
  "type": "Feature",
  "properties": {
    "iso:country":"CH",
    "sg:address":"Sch\u00f6nenbergstrasse 62",
    "sg:city":"W\u00e4denswil",
    "sg:orig_category":"Gesundheitswesen",
    "sg:phone":"+41 17807690",
    "sg:postcode":"8820",
    "sg:province":"Z\u00fcrich",
    "wof:name":"Barbara Florin Walder, Fachstudio F\u00fcr Ern\u00e4hrung",
    "wof:placetype":"venue"
},
  "geometry": {"coordinates":[8.673617363,47.2229576111],"type":"Point"}
}