{
  "type": "Feature",
  "properties": {
    "iso:country":"CH",
    "sg:address":"Melchtalkerns",
    "sg:city":"Kerns",
    "sg:orig_category":"Sportschulen",
    "sg:phone":"+41 41 660 00 69",
    "sg:postcode":"6064",
    "sg:province":"Obwalden",
    "wof:name":"Ski-& Langlaufschule Verkehrsver.melchsee-frutt",
    "wof:placetype":"venue"
},
  "geometry": {"coordinates":[8.2753896713,46.9003486633],"type":"Point"}
}