{
  "type": "Feature",
  "properties": {
    "addr:full":"Gr\u00fcnaustrasse 50 3084 Wabern. Postfach 205 Wabern Bern 3084",
    "addr:housenumber":"50;205",
    "addr:postcode":"3084 wabern.;3084",
    "addr:street":"Gruenaustrasse;Postfach",
    "iso:country":"CH",
    "sg:address":"Gr\u00fcnaustrasse 50 3084 Wabern. Postfach 205",
    "sg:city":"Wabern",
    "sg:orig_category":"Allgemeiner Hochbau D\u00e4mmung gegen K\u00e4lte, W\u00e4rme, Schall U Ersch\u00fctterung",
    "sg:phone":"+41 31 960 24 24",
    "sg:postcode":"3084",
    "sg:province":"Bern",
    "wof:name":"Melliger Malerei & Gipserei Ag",
    "wof:placetype":"venue"
},
  "geometry": {"coordinates":[7.451111,46.926392],"type":"Point"}
}