{
  "type": "Feature",
  "properties": {
    "iso:country":"CH",
    "sg:address":"Neuarlesheimerstrasse 15",
    "sg:city":"Dornach",
    "sg:orig_category":"Softwareentwicklung U beratung",
    "sg:postcode":"4143",
    "sg:province":"Solothurn",
    "wof:name":"Hasselberg Computer",
    "wof:placetype":"venue"
},
  "geometry": {"coordinates":[7.6084499359,47.4890213013],"type":"Point"}
}