{
  "type": "Feature",
  "properties": {
    "iso:country":"CH",
    "sg:address":"Gl\u00e4rnischstrasse 59c",
    "sg:city":"St\u00e4fa",
    "sg:orig_category":"Herstellung von sonstigen elektrischen Ausr\u00fcstungen",
    "sg:postcode":"8712",
    "sg:province":"Z\u00fcrich",
    "wof:name":"Eltec M. Michel",
    "wof:placetype":"venue"
},
  "geometry": {"coordinates":[7.4600148201,47.0012512207],"type":"Point"}
}