{
  "type": "Feature",
  "properties": {
    "iso:country":"CH",
    "sg:address":"Grande Avenue",
    "sg:city":"Chippis",
    "sg:orig_category":"Detailhandel mit Zeitungen U Zeitschriften Kioske",
    "sg:phone":"+41 56 633 62 77",
    "sg:postcode":"3965",
    "sg:province":"Valais",
    "wof:name":"Hallen-& Freibad Isenlauf",
    "wof:placetype":"venue"
},
  "geometry": {"coordinates":[8.3444499969,47.3506698608],"type":"Point"}
}