{
  "type": "Feature",
  "properties": {
    "iso:country":"CH",
    "sg:address":"Bernasconi Largo 5",
    "sg:city":"Mendrisio",
    "sg:orig_category":"Fotografisches Gewerbe U fotografische Laboratorien",
    "sg:phone":"+41 91 646 13 61",
    "sg:postcode":"6850",
    "sg:province":"Ticino",
    "wof:name":"Foto Pedroli",
    "wof:placetype":"venue"
},
  "geometry": {"coordinates":[8.9748888016,45.8637428284],"type":"Point"}
}