{
  "type": "Feature",
  "properties": {
    "iso:country":"CH",
    "sg:address":"Hochstrasse 5 3360 Herzogenbuchsee. Postfach",
    "sg:city":"Herzogenbuchsee",
    "sg:orig_category":"Interessenvertretungen",
    "sg:postcode":"3360",
    "sg:province":"Bern",
    "wof:name":"Outdoor Dreams Gmbh F\u00f6rdert Das Erleben U. Schlafen In Der Natur Durch Kommerzielle Organisation U. Durchf\u00fchrung Von Outdoor-aktivit\u00e4ten Usw",
    "wof:placetype":"venue"
},
  "geometry": {"coordinates":[7.7061929703,47.1857910156],"type":"Point"}
}