{
  "type": "Feature",
  "properties": {
    "addr:full":"Kraftwerkstrasse 6 Pratteln Basel-Landschaft 4133",
    "addr:housenumber":"6",
    "addr:postcode":"4133",
    "addr:street":"Kraftwerkstrasse",
    "iso:country":"CH",
    "sg:address":"Kraftwerkstrasse 6",
    "sg:city":"Pratteln",
    "sg:classifiers":[
        {
            "category":"Structure",
            "subcategory":"Warehouse",
            "type":"Public Place"
        }
    ],
    "sg:phone":"+41 61 826 47 47",
    "sg:postcode":"4133",
    "sg:province":"Basel-Landschaft",
    "sg:tags":[
        "technology",
        "system",
        "clean-room"
    ],
    "wof:name":"Glatt Maschinen- & Apparatebau Ag",
    "wof:placetype":"venue"
},
  "geometry": {"coordinates":[7.694148,47.527199],"type":"Point"}
}