{
  "type": "Feature",
  "properties": {
    "iso:country":"CH",
    "sg:address":"Avenue De Chanel 20 1110 Morges. Postfach",
    "sg:city":"Morges",
    "sg:orig_category":"Sonstiger Grosshandel",
    "sg:postcode":"1110",
    "sg:province":"Vaud",
    "wof:name":"Constall, Franz Baader",
    "wof:placetype":"venue"
},
  "geometry": {"coordinates":[6.4959487915,46.5159950256],"type":"Point"}
}