{
  "type": "Feature",
  "properties": {
    "iso:country":"CH",
    "sg:address":"Fabrikmattenweg 10",
    "sg:city":"Arlesheim",
    "sg:classifiers":[
        {
            "category":"Professional",
            "subcategory":"Advertising",
            "type":"Services"
        }
    ],
    "sg:phone":"+41 43 377 81 11",
    "sg:postcode":"4144",
    "sg:province":"Basel-Landschaft",
    "sg:tags":[
        "postcard"
    ],
    "wof:name":"Ebn\u00f6ther Joos Ag",
    "wof:placetype":"venue"
},
  "geometry": {"coordinates":[8.543217,47.289146],"type":"Point"}
}