{
  "type": "Feature",
  "properties": {
    "iso:country":"CH",
    "sg:address":"Richtung Z\u00fcrich-bern",
    "sg:city":"W\u00fcrenlos",
    "sg:orig_category":"Tankstellen",
    "sg:phone":"+41 56 424 17 76",
    "sg:postcode":"5436",
    "sg:province":"Aargau",
    "wof:name":"Shell Service W\u00fcrenlos Autobahntankstelle N1",
    "wof:placetype":"venue"
},
  "geometry": {"coordinates":[8.3617506027,47.4433746338],"type":"Point"}
}