{
  "type": "Feature",
  "properties": {
    "iso:country":"CH",
    "sg:address":"Pumpwerkstr. 18",
    "sg:city":"Regensdorf",
    "sg:classifiers":[
        {
            "category":"Utilities",
            "subcategory":"Mobile Phone",
            "type":"Services"
        }
    ],
    "sg:phone":"+41 4118404833",
    "sg:postcode":"8105",
    "sg:province":"Z\u00fcrich",
    "sg:tags":[
        "telecommunication",
        "audio-visual"
    ],
    "wof:name":"Uniton Ag",
    "wof:placetype":"venue"
},
  "geometry": {"coordinates":[8.459245,47.44389],"type":"Point"}
}