{
  "type": "Feature",
  "properties": {
    "iso:country":"CH",
    "sg:address":"Erlenstr\u00e4sschen 61",
    "sg:city":"Riehen",
    "sg:orig_category":"Detailhandel mit Geschenkartikeln U Souvenirs",
    "sg:phone":"+41 61 641 45 61",
    "sg:postcode":"4125",
    "sg:province":"Basel-Stadt",
    "wof:name":"Gertraud Oswald Atelier 61",
    "wof:placetype":"venue"
},
  "geometry": {"coordinates":[7.6460051537,47.5850906372],"type":"Point"}
}