{
  "type": "Feature",
  "properties": {
    "iso:country":"CH",
    "sg:address":"Saulcy",
    "sg:city":"Saulcy",
    "sg:classifiers":[
        {
            "category":"Banks & Credit Unions",
            "subcategory":"Bank",
            "type":"Services"
        }
    ],
    "sg:phone":"+41 4166584680",
    "sg:postcode":"2873",
    "sg:province":"Jura",
    "wof:name":"Banque Raiffeisen De Saulcy",
    "wof:placetype":"venue"
},
  "geometry": {"coordinates":[7.153909,47.301781],"type":"Point"}
}