{
  "type": "Feature",
  "properties": {
    "iso:country":"CH",
    "sg:address":"Seengerstrasse 240",
    "sg:city":"Egliswil",
    "sg:orig_category":"Bauschreinerei",
    "sg:phone":"+41 62 775 26 68",
    "sg:postcode":"5704",
    "sg:province":"Aargau",
    "wof:name":"Hans H\u00e4feli Schreinerei",
    "wof:placetype":"venue"
},
  "geometry": {"coordinates":[8.187771,47.346149],"type":"Point"}
}