{
  "type": "Feature",
  "properties": {
    "iso:country":"CH",
    "sg:address":"Kohlestrasse 6",
    "sg:city":"Schlieren",
    "sg:orig_category":"Einzelhandel mit Automobilen",
    "sg:phone":"+41 71 744 32 22",
    "sg:postcode":"8952",
    "sg:province":"Z\u00fcrich",
    "wof:name":"Urs Zoller Autohandel",
    "wof:placetype":"venue"
},
  "geometry": {"coordinates":[9.6344003677,47.4393806458],"type":"Point"}
}