{
  "type": "Feature",
  "properties": {
    "iso:country":"CH",
    "sg:address":"Kleinh\u00fcningeranlage 4057 Basel. Postfach",
    "sg:city":"Basel",
    "sg:orig_category":"Fahrschulen, Flugschulen",
    "sg:postcode":"4019",
    "sg:province":"Basel-Stadt",
    "wof:name":"Verband Der Berufsfahrlehrer Von Basel Und Umgebung",
    "wof:placetype":"venue"
},
  "geometry": {"coordinates":[7.5932002068,47.5815353394],"type":"Point"}
}