{
  "type": "Feature",
  "properties": {
    "iso:country":"CH",
    "sg:address":"H\u00f6henweg 522",
    "sg:city":"Welschenrohr",
    "sg:orig_category":"Grosshandel mit chemischen Erzeugnissen",
    "sg:phone":"+41 79 680 03 08",
    "sg:postcode":"4716",
    "sg:province":"Solothurn",
    "wof:name":"Re Wa Reinigungstechnik",
    "wof:placetype":"venue"
},
  "geometry": {"coordinates":[7.5235099792,47.2829208374],"type":"Point"}
}