{
  "type": "Feature",
  "properties": {
    "iso:country":"CH",
    "sg:address":"T\u00f6ssallmend 2",
    "sg:city":"Neftenbach",
    "sg:orig_category":"Pensionskassen",
    "sg:postcode":"8413",
    "sg:province":"Z\u00fcrich",
    "wof:name":"Baccara Stiftung",
    "wof:placetype":"venue"
},
  "geometry": {"coordinates":[8.6583967209,47.5189704895],"type":"Point"}
}