{
  "type": "Feature",
  "properties": {
    "iso:country":"CH",
    "sg:address":"Frauenfelderstrasse 124",
    "sg:city":"Winterthur",
    "sg:orig_category":"Zahntechnische Laboratorien",
    "sg:phone":"+41 52 242 62 45",
    "sg:postcode":"8404",
    "sg:province":"Z\u00fcrich",
    "wof:name":"Hansj\u00f6rg Projer Zahntechnisches Labor",
    "wof:placetype":"venue"
},
  "geometry": {"coordinates":[8.7482070923,47.5020866394],"type":"Point"}
}