{
  "type": "Feature",
  "properties": {
    "iso:country":"CH",
    "sg:address":"La Grande Fin 33",
    "sg:city":"Courtepin",
    "sg:orig_category":"Technische, physikalische U chemische Untersuchung",
    "sg:phone":"+41 26 684 27 25",
    "sg:postcode":"1784",
    "sg:province":"Fribourg",
    "wof:name":"Qualisan Institut Gmbh",
    "wof:placetype":"venue"
},
  "geometry": {"coordinates":[7.1289792061,46.8619880676],"type":"Point"}
}