{
  "type": "Feature",
  "properties": {
    "iso:country":"CH",
    "sg:address":"Platanenweg 3",
    "sg:city":"Oberentfelden",
    "sg:orig_category":"Sonstiger Grosshandel",
    "sg:phone":"+41 62 724 92 53",
    "sg:postcode":"5036",
    "sg:province":"Aargau",
    "wof:name":"Supracontrol Dr. Urban Meyer",
    "wof:placetype":"venue"
},
  "geometry": {"coordinates":[8.0456771851,47.360824585],"type":"Point"}
}