{
  "type": "Feature",
  "properties": {
    "iso:country":"CH",
    "sg:address":"Wehntalerstrasse 245",
    "sg:city":"Z\u00fcrich",
    "sg:classifiers":[
        {
            "category":"Insurance",
            "subcategory":"Insurance Agent",
            "type":"Services"
        }
    ],
    "sg:phone":"+41 13779077",
    "sg:postcode":"8046",
    "sg:province":"Z\u00fcrich",
    "sg:tags":[
        "versicherungsagenturen",
        "-broker"
    ],
    "wof:name":"Winterthur-versicherungen Agentur Josef Eckl",
    "wof:placetype":"venue"
},
  "geometry": {"coordinates":[8.5283689499,47.4094200134],"type":"Point"}
}