{
  "type": "Feature",
  "properties": {
    "addr:full":"Oberfeldweg 2 6280 Hochdorf. Postfach Hochdorf Luzern 6280",
    "addr:housenumber":"2",
    "addr:postcode":"6280 hochdorf. postfach;6280",
    "addr:street":"Oberfeldweg",
    "iso:country":"CH",
    "sg:address":"Oberfeldweg 2 6280 Hochdorf. Postfach",
    "sg:city":"Hochdorf",
    "sg:orig_category":"Grosshandel mit Holz U Baustoffen",
    "sg:phone":"+41 41 910 10 22",
    "sg:postcode":"6280",
    "sg:province":"Luzern",
    "wof:name":"Sigrist Franz Holzhandel",
    "wof:placetype":"venue"
},
  "geometry": {"coordinates":[8.299458,47.165115],"type":"Point"}
}