{
  "type": "Feature",
  "properties": {
    "iso:country":"CH",
    "sg:address":"Talrain 49",
    "sg:city":"Adligenswil",
    "sg:orig_category":"Grafikateliers, Design",
    "sg:phone":"+41 32 365 30 33",
    "sg:postcode":"6043",
    "sg:province":"Luzern",
    "wof:name":"Marcel Meier Expo Ag",
    "wof:placetype":"venue"
},
  "geometry": {"coordinates":[7.2613368034,47.1201286316],"type":"Point"}
}