{
  "type": "Feature",
  "properties": {
    "iso:country":"CH",
    "sg:address":"Via Cantonale",
    "sg:city":"Magadino",
    "sg:orig_category":"Unclassifiable Establishments",
    "sg:phone":"+41 91 780 41 44",
    "sg:postcode":"6573",
    "sg:province":"Ticino",
    "wof:name":"Esposito Elettricit\u00e0 Sagl",
    "wof:placetype":"venue"
},
  "geometry": {"coordinates":[8.8608789444,46.1484909058],"type":"Point"}
}