{
  "type": "Feature",
  "properties": {
    "iso:country":"CH",
    "sg:address":"Waldst\u00e4tterquai 2 6440 Brunnen. Postfach 345",
    "sg:city":"Brunnen",
    "sg:orig_category":"Architektur U Ingenieurb\u00fcros",
    "sg:phone":"+41 41 820 20 70",
    "sg:postcode":"6440",
    "sg:province":"Schwyz",
    "wof:name":"Inderbitzin Franz Ag",
    "wof:placetype":"venue"
},
  "geometry": {"coordinates":[8.60503,46.993805],"type":"Point"}
}