{
  "type": "Feature",
  "properties": {
    "iso:country":"CH",
    "sg:address":"Bodenmattstrasse 12",
    "sg:city":"Reinach",
    "sg:classifiers":[
        {
            "category":"Organizations",
            "subcategory":"Non-profit Organization",
            "type":"Services"
        }
    ],
    "sg:phone":"+41 61 711 58 00",
    "sg:postcode":"4153",
    "sg:province":"Basel-Landschaft",
    "sg:tags":[
        "alarm",
        "system"
    ],
    "wof:name":"Argus Sicherheitstechnik Ag",
    "wof:placetype":"venue"
},
  "geometry": {"coordinates":[7.594898,47.494133],"type":"Point"}
}