{
  "type": "Feature",
  "properties": {
    "addr:full":"Rue De Gen\u00e8ve 18 Ch\u00eane-bourg Gen\u00e8ve 1225",
    "addr:housenumber":"18",
    "addr:postcode":"1225",
    "addr:street":"Rue De Gene\u0300Ve;Che\u0302Ne-Bourg",
    "iso:country":"CH",
    "sg:address":"Rue De Gen\u00e8ve 18",
    "sg:city":"Ch\u00eane-bourg",
    "sg:orig_category":"Arztpraxen",
    "sg:phone":"+41 22 348 21 21",
    "sg:postcode":"1225",
    "sg:province":"Gen\u00e8ve",
    "wof:name":"Dr M\u00e9d. Jean-luc Desaules M\u00e9decin G\u00e9n\u00e9raliste Fmh",
    "wof:placetype":"venue"
},
  "geometry": {"coordinates":[6.194168,46.19437],"type":"Point"}
}