{
  "type": "Feature",
  "properties": {
    "iso:country":"CH",
    "sg:address":"Kapuzinergasse 8",
    "sg:city":"Rheinfelden",
    "sg:orig_category":"Herstellung von keramischen Haushaltswaren U Ziergegenst\u00e4nden",
    "sg:phone":"+41 61 831 14 35",
    "sg:postcode":"4310",
    "sg:province":"Aargau",
    "wof:name":"Katrin Frey Keramikatelier",
    "wof:placetype":"venue"
},
  "geometry": {"coordinates":[7.7928171158,47.5533981323],"type":"Point"}
}