{
  "type": "Feature",
  "properties": {
    "iso:country":"CH",
    "sg:address":"Bleichemattstrasse 33",
    "sg:city":"Aarau",
    "sg:orig_category":"Installation von Heizungs, L\u00fcftungs U Klimaanlagen",
    "sg:phone":"+41 62 837 62 62",
    "sg:postcode":"5000",
    "sg:province":"Aargau",
    "wof:name":"Therma K\u00e4lte & Klima",
    "wof:placetype":"venue"
},
  "geometry": {"coordinates":[8.0548772812,47.3903999329],"type":"Point"}
}