{
  "type": "Feature",
  "properties": {
    "iso:country":"CH",
    "sg:address":"4856",
    "sg:city":"Glash\u00fctten",
    "sg:classifiers":[
        {
            "category":"Restaurant",
            "type":"Food & Drink"
        }
    ],
    "sg:phone":"+41 62 926 10 89",
    "sg:postcode":"4856",
    "sg:province":"Aargau",
    "wof:name":"Restaurant L\u00f6wen",
    "wof:placetype":"venue"
},
  "geometry": {"coordinates":[7.8451700211,47.2586479187],"type":"Point"}
}