{
  "type": "Feature",
  "properties": {
    "iso:country":"CH",
    "sg:address":"2830",
    "sg:city":"Courrendlin",
    "sg:classifiers":[
        {
            "category":"Restaurant",
            "type":"Food & Drink"
        }
    ],
    "sg:phone":"+41 32 435 52 45",
    "sg:postcode":"2830",
    "sg:province":"Jura",
    "wof:name":"Restaurant Du Violat",
    "wof:placetype":"venue"
},
  "geometry": {"coordinates":[7.3730211258,47.3398246765],"type":"Point"}
}