{
  "type": "Feature",
  "properties": {
    "iso:country":"CH",
    "sg:address":"Schlattweg 323",
    "sg:city":"Egliswil",
    "sg:orig_category":"Pensionskassen",
    "sg:phone":"+41 62 775 22 22",
    "sg:postcode":"5704",
    "sg:province":"Aargau",
    "wof:name":"Ziegler-rollstar-stiftung",
    "wof:placetype":"venue"
},
  "geometry": {"coordinates":[8.1764793396,47.3483428955],"type":"Point"}
}