{
  "type": "Feature",
  "properties": {
    "iso:country":"CH",
    "sg:address":"Ch. Du Tournesol 1",
    "sg:city":"Tolochenaz",
    "sg:orig_category":"Wirtschaftspr\u00fcfung, Steuerberatung U Treuhand",
    "sg:phone":"+41 21 802 23 26",
    "sg:postcode":"1131",
    "sg:province":"Vaud",
    "wof:name":"Reviconseil Consulting Sa Toutes Op\u00e9rations De R\u00e9vision Comptable, Conseils Fiscaux Etc",
    "wof:placetype":"venue"
},
  "geometry": {"coordinates":[6.4747290611,46.5062675476],"type":"Point"}
}