{
  "type": "Feature",
  "properties": {
    "iso:country":"CH",
    "sg:address":"Rishaldenweg",
    "sg:city":"Rothrist",
    "sg:orig_category":"Kosmetikinstitute",
    "sg:phone":"+41 62 785 70 30",
    "sg:postcode":"4852",
    "sg:province":"Aargau",
    "wof:name":"Coiffure & Beaut\u00e9 Rishalden",
    "wof:placetype":"venue"
},
  "geometry": {"coordinates":[7.8927359581,47.3119621277],"type":"Point"}
}