{
  "type": "Feature",
  "properties": {
    "iso:country":"CH",
    "sg:address":"Gopf 9052 Niederteufen. Postfach",
    "sg:city":"Niederteufen",
    "sg:orig_category":"Non-Classified Establishments",
    "sg:postcode":"9052",
    "sg:province":"Appenzell Ausserrhoden",
    "wof:name":"Pictures + Sound B. Roth",
    "wof:placetype":"venue"
},
  "geometry": {"coordinates":[9.3611898422,47.3930282593],"type":"Point"}
}