{
  "type": "Feature",
  "properties": {
    "iso:country":"CH",
    "sg:address":"Sperrstrasse 6",
    "sg:city":"Basel",
    "sg:orig_category":"Autogaragen",
    "sg:phone":"+41 61 681 50 00",
    "sg:postcode":"4057",
    "sg:province":"Basel-Stadt",
    "wof:name":"Ronald M\u00fcller Royal Garage",
    "wof:placetype":"venue"
},
  "geometry": {"coordinates":[7.591744,47.564255],"type":"Point"}
}