{
  "type": "Feature",
  "properties": {
    "iso:country":"CH",
    "sg:address":"Buchenweg 4",
    "sg:city":"Plons",
    "sg:orig_category":"P\u00e9dicure",
    "sg:phone":"+41 79 346 42 78",
    "sg:postcode":"8889",
    "sg:province":"St. Gallen",
    "wof:name":"R\u00f6sly W\u00e4lti",
    "wof:placetype":"venue"
},
  "geometry": {"coordinates":[9.4042415619,47.0559158325],"type":"Point"}
}