{
  "type": "Feature",
  "properties": {
    "iso:country":"CH",
    "sg:address":"Technikumstrasse 10",
    "sg:city":"Winterthur",
    "sg:classifiers":[
        {
            "category":"Bars & Pubs",
            "type":"Food & Drink"
        }
    ],
    "sg:phone":"+41 52 202 21 55",
    "sg:postcode":"8400",
    "sg:province":"Z\u00fcrich",
    "wof:name":"Jack's Bar",
    "wof:placetype":"venue"
},
  "geometry": {"coordinates":[8.730773,47.498001],"type":"Point"}
}