{
  "type": "Feature",
  "properties": {
    "iso:country":"CH",
    "sg:address":"Bielstrasse 134",
    "sg:city":"Grenchen",
    "sg:orig_category":"Architektur U Ingenieurb\u00fcros",
    "sg:postcode":"2540",
    "sg:province":"Solothurn",
    "wof:name":"Kebueg Ag",
    "wof:placetype":"venue"
},
  "geometry": {"coordinates":[7.382826,47.187325],"type":"Point"}
}