{
  "type": "Feature",
  "properties": {
    "iso:country":"CH",
    "sg:address":"Rue De La Borde 64",
    "sg:city":"Lausanne",
    "sg:classifiers":[
        {
            "category":"Home & Garden",
            "subcategory":"Building Materials",
            "type":"Retail Goods"
        }
    ],
    "sg:phone":"+41 22 823 19 25",
    "sg:postcode":"1018",
    "sg:province":"Vaud",
    "sg:tags":[
        "antiglare",
        "blind",
        "roller"
    ],
    "wof:name":"Entreprise G. Brunner",
    "wof:placetype":"venue"
},
  "geometry": {"coordinates":[6.141425,46.183311],"type":"Point"}
}