{
  "type": "Feature",
  "properties": {
    "iso:country":"CH",
    "sg:address":"Hauptstr",
    "sg:city":"Savognin",
    "sg:orig_category":"Grosshandel mit Nahrungsmitteln, Getr\u00e4nken U Tabakwaren ohne ausgepr\u00e4gten Schwerpunkt",
    "sg:postcode":"7460",
    "sg:province":"Graubunden",
    "wof:name":"Pool J\u00fcrg.",
    "wof:placetype":"venue"
},
  "geometry": {"coordinates":[9.5967006683,46.5976028442],"type":"Point"}
}