{
  "type": "Feature",
  "properties": {
    "iso:country":"CH",
    "sg:address":"Route De Cossonay 20",
    "sg:city":"Prilly",
    "sg:orig_category":"Detailhandel mit Radio U Fernsehger\u00e4ten Grosshandel mit sonstigen Gebrauchs U Verbrauchsg\u00fctern",
    "sg:phone":"+41 21 634 03 87",
    "sg:postcode":"1008",
    "sg:province":"Vaud",
    "wof:name":"Intrason Sa",
    "wof:placetype":"venue"
},
  "geometry": {"coordinates":[6.6080031395,46.5335273743],"type":"Point"}
}