{
  "type": "Feature",
  "properties": {
    "iso:country":"CH",
    "sg:address":"Rue Du Closel 12",
    "sg:city":"Marin-centre",
    "sg:orig_category":"Reinigungsgewerbe",
    "sg:postcode":"2074",
    "sg:province":"Neuch\u00e2tel",
    "wof:name":"Ruiz Manuel",
    "wof:placetype":"venue"
},
  "geometry": {"coordinates":[7.0076189041,47.0082855225],"type":"Point"}
}