{
  "type": "Feature",
  "properties": {
    "iso:country":"CH",
    "sg:address":"Moorstrasse 3",
    "sg:city":"Dietlikon",
    "sg:orig_category":"Detailhandel mit M\u00f6beln Detailhandel mit M\u00f6beln U Haushaltsgegenst\u00e4nden",
    "sg:phone":"+41 848 801 100",
    "sg:postcode":"8305",
    "sg:province":"Z\u00fcrich",
    "wof:name":"Ikea Ag, Zweigniederlassung Dietlikon",
    "wof:placetype":"venue"
},
  "geometry": {"coordinates":[8.6221199036,47.4139900208],"type":"Point"}
}