{
  "type": "Feature",
  "properties": {
    "iso:country":"CH",
    "sg:address":"Baarerstrasse 12",
    "sg:city":"Zug",
    "sg:orig_category":"Rechtsberatung",
    "sg:phone":"+41 41 711 01 15",
    "sg:postcode":"6300",
    "sg:province":"Zug",
    "wof:name":"Compaselect Gmbh",
    "wof:placetype":"venue"
},
  "geometry": {"coordinates":[8.5164785385,47.1717300415],"type":"Point"}
}