{
  "type": "Feature",
  "properties": {
    "iso:country":"CH",
    "sg:address":"Route De Malagny 36",
    "sg:city":"Creux-de-genthod",
    "sg:orig_category":"Erwachsenenbildung U Unterricht",
    "sg:postcode":"1294",
    "sg:province":"Gen\u00e8ve",
    "wof:name":"Geneva English School Association",
    "wof:placetype":"venue"
},
  "geometry": {"coordinates":[6.1587381363,46.269985199],"type":"Point"}
}