{
  "type": "Feature",
  "properties": {
    "iso:country":"CH",
    "sg:address":"Viehmarktgasse 29",
    "sg:city":"Laufen",
    "sg:orig_category":"Detailhandel mit elektrischen Haushalts-,Radio U Fernsehger\u00e4ten sowie Musikinstrumenten",
    "sg:phone":"+41 61 761 71 11",
    "sg:postcode":"4242",
    "sg:province":"Basel-Landschaft",
    "wof:name":"Meier Heinz Haushaltservice",
    "wof:placetype":"venue"
},
  "geometry": {"coordinates":[7.4998021126,47.4218254089],"type":"Point"}
}