{
  "type": "Feature",
  "properties": {
    "iso:country":"CH",
    "sg:address":"Saum 45",
    "sg:city":"Herisau",
    "sg:orig_category":"Elektroinstallation Herstellung von Elektromotoren, Generatoren U Transformatoren",
    "sg:phone":"+41 71 350 07 77",
    "sg:postcode":"9100",
    "sg:province":"Appenzell Ausserrhoden",
    "wof:name":"Baumann Electro Ag",
    "wof:placetype":"venue"
},
  "geometry": {"coordinates":[9.3087406158,47.3878097534],"type":"Point"}
}