{
  "type": "Feature",
  "properties": {
    "iso:country":"CH",
    "sg:address":"Petit-cortaillod 23",
    "sg:city":"Cortaillod",
    "sg:orig_category":"Detailhandel mit Sportartikeln",
    "sg:phone":"+41 79 332 01 07",
    "sg:postcode":"2016",
    "sg:province":"Neuch\u00e2tel",
    "wof:name":"Jean-marc De Montmollin Boutique Nautique",
    "wof:placetype":"venue"
},
  "geometry": {"coordinates":[6.8546500206,46.9423217773],"type":"Point"}
}