{
  "type": "Feature",
  "properties": {
    "iso:country":"CH",
    "sg:address":"Steinerstrasse 29",
    "sg:city":"Diessenhofen",
    "sg:orig_category":"Sonstige Aktivit\u00e4ten der nicht-\u00e4rztlichen Medizinalberufe",
    "sg:phone":"+41 52 657 28 01",
    "sg:postcode":"8253",
    "sg:province":"Thurgau",
    "wof:name":"Silvia Sternegg Akupunktur-massage",
    "wof:placetype":"venue"
},
  "geometry": {"coordinates":[8.7569293976,47.6875114441],"type":"Point"}
}