{
  "type": "Feature",
  "properties": {
    "iso:country":"CH",
    "sg:address":"Kurfirstenstrasse 21 8002 Z\u00fcrich. Postfach",
    "sg:city":"Z\u00fcrich",
    "sg:orig_category":"Werbung",
    "sg:postcode":"8027",
    "sg:province":"Z\u00fcrich",
    "wof:name":"De Vita Design Gmbh",
    "wof:placetype":"venue"
},
  "geometry": {"coordinates":[9.1381845474,47.5666694641],"type":"Point"}
}