{
  "type": "Feature",
  "properties": {
    "iso:country":"CH",
    "sg:address":"Schochengasse 6",
    "sg:city":"St.gallen",
    "sg:orig_category":"Vermittlung von Immobilien Verwaltung von Immobilien",
    "sg:phone":"+41 71 499 24 95",
    "sg:postcode":"9000",
    "sg:province":"St. Gallen",
    "wof:name":"Swisscom Immobilien Ag",
    "wof:placetype":"venue"
},
  "geometry": {"coordinates":[9.3721466064,47.420917511],"type":"Point"}
}