{
  "type": "Feature",
  "properties": {
    "iso:country":"CH",
    "sg:address":"1746",
    "sg:city":"Prez-vers-nor\u00e9az",
    "sg:orig_category":"Schmieden",
    "sg:phone":"+41 26 470 12 54",
    "sg:postcode":"1746",
    "sg:province":"Fribourg",
    "wof:name":"Gilbert Grossrieder Ferronnerie D'art",
    "wof:placetype":"venue"
},
  "geometry": {"coordinates":[7.0144600868,46.7842483521],"type":"Point"}
}