{
  "type": "Feature",
  "properties": {
    "iso:country":"CH",
    "sg:address":"Pregny Route De 21",
    "sg:city":"Chamb\u00e9sy",
    "sg:orig_category":"Fachdetailhandel in Verkaufsr\u00e4umen",
    "sg:phone":"+41 27 957 18 22",
    "sg:postcode":"1292",
    "sg:province":"Gen\u00e8ve",
    "wof:name":"Glacier Sport \u00abweissmies\u00bb, Anthamatten Martin",
    "wof:placetype":"venue"
},
  "geometry": {"coordinates":[7.9367241859,46.1232452393],"type":"Point"}
}