{
  "type": "Feature",
  "properties": {
    "iso:country":"CH",
    "sg:address":"Thunstrasse 5",
    "sg:city":"Tafers",
    "sg:orig_category":"Detailhandel mit Schuhen U Lederwaren Detailhandel mit medizinischen U orthop\u00e4dischen Artikeln",
    "sg:phone":"+41 26 494 11 70",
    "sg:postcode":"1712",
    "sg:province":"Fribourg",
    "wof:name":"Jeckelmann Orthopaedie Ag",
    "wof:placetype":"venue"
},
  "geometry": {"coordinates":[7.2171030045,46.8158493042],"type":"Point"}
}