{
  "type": "Feature",
  "properties": {
    "iso:country":"CH",
    "sg:address":"Seeblickstrasse",
    "sg:city":"Untereggen",
    "sg:orig_category":"Politische Parteien CVP",
    "sg:phone":"+41 71 222 33 84",
    "sg:postcode":"9033",
    "sg:province":"St. Gallen",
    "wof:name":"Cvp Ortspartei Untereggen",
    "wof:placetype":"venue"
},
  "geometry": {"coordinates":[9.4470262527,47.4504814148],"type":"Point"}
}