{
  "type": "Feature",
  "properties": {
    "iso:country":"CH",
    "sg:address":"Chrummacherweg 457",
    "sg:city":"Brittnau",
    "sg:orig_category":"Erwachsenenbildung U Unterricht",
    "sg:postcode":"4805",
    "sg:province":"Aargau",
    "wof:name":"Zim Zentrum F\u00fcr Internationales Management Gmbh",
    "wof:placetype":"venue"
},
  "geometry": {"coordinates":[7.9466080666,47.2601356506],"type":"Point"}
}