{
  "type": "Feature",
  "properties": {
    "iso:country":"CH",
    "sg:address":"Route Du Lac 11 1636 Broc Case Postale 41",
    "sg:city":"Broc",
    "sg:orig_category":"Gartenbau Landschaftsplanungsb\u00fcros U Gartenarchitekturb\u00fcros",
    "sg:phone":"+41 26 921 11 33",
    "sg:postcode":"1636",
    "sg:province":"Fribourg",
    "wof:name":"Paysages Et Jardins Jeckelmann Sa",
    "wof:placetype":"venue"
},
  "geometry": {"coordinates":[7.1054139137,46.6098022461],"type":"Point"}
}