{
  "type": "Feature",
  "properties": {
    "iso:country":"CH",
    "sg:address":"M\u00fcrtschenstrasse 8",
    "sg:city":"Schmerikon",
    "sg:orig_category":"Architekturb\u00fcros",
    "sg:phone":"+41 55 282 14 13",
    "sg:postcode":"8716",
    "sg:province":"St. Gallen",
    "wof:name":"Armin Artho Architekturb\u00fcro",
    "wof:placetype":"venue"
},
  "geometry": {"coordinates":[8.955486,47.226002],"type":"Point"}
}