{
  "type": "Feature",
  "properties": {
    "iso:country":"CH",
    "sg:address":"Zugerstrasse 18 6330 Cham. Postfach 57",
    "sg:city":"Cham",
    "sg:orig_category":"Instandhaltung U Reparatur von Automobilen",
    "sg:phone":"+41 41 780 17 23",
    "sg:postcode":"6330",
    "sg:province":"Zug",
    "wof:name":"Garage Arnold J.",
    "wof:placetype":"venue"
},
  "geometry": {"coordinates":[8.4623231888,47.1815032959],"type":"Point"}
}