{
  "type": "Feature",
  "properties": {
    "iso:country":"CH",
    "sg:address":"Hotel R\u00e4tus 7403 Rh\u00e4z\u00fcns. Postfach",
    "sg:city":"Rh\u00e4z\u00fcns",
    "sg:classifiers":[
        {
            "category":"Travel",
            "subcategory":"Hotels & Motels",
            "type":"Entertainment"
        }
    ],
    "sg:postcode":"7403",
    "sg:province":"Graubunden",
    "sg:tags":[
        "hotels",
        "mit",
        "restaurant"
    ],
    "wof:name":"F. B\u00e4chler",
    "wof:placetype":"venue"
},
  "geometry": {"coordinates":[7.4824361801,46.9346160889],"type":"Point"}
}