{
  "type": "Feature",
  "properties": {
    "iso:country":"CH",
    "sg:address":"Basteiplatz 5",
    "sg:city":"Z\u00fcrich",
    "sg:orig_category":"Interessenvertretungen",
    "sg:postcode":"8001",
    "sg:province":"Z\u00fcrich",
    "wof:name":"Genossenschaft Taxi 444 Z\u00fcrich F\u00f6rderung, Sicherung Wirtschaftlicher Interessen Von Taxihaltern Usw",
    "wof:placetype":"venue"
},
  "geometry": {"coordinates":[8.5359420776,47.369594574],"type":"Point"}
}