{
  "type": "Feature",
  "properties": {
    "iso:country":"CH",
    "sg:address":"Glattalstrasse 188",
    "sg:city":"R\u00fcmlang",
    "sg:orig_category":"Detailhandel mit Beleuchtungs U Haushaltsgegenst\u00e4nden Grosshandel mit Eisenwaren sowie Installations",
    "sg:phone":"+41 18170410",
    "sg:postcode":"8153",
    "sg:province":"Z\u00fcrich",
    "wof:name":"G\u00fctlin Eisenwaren Und Haushalt",
    "wof:placetype":"venue"
},
  "geometry": {"coordinates":[8.529302,47.450928],"type":"Point"}
}