{
  "type": "Feature",
  "properties": {
    "iso:country":"CH",
    "sg:address":"Rainstrasse 3",
    "sg:city":"Unter\u00e4geri",
    "sg:orig_category":"Sonstiger Grosshandel",
    "sg:postcode":"6314",
    "sg:province":"Zug",
    "wof:name":"Mineralpor Ag Leichtprodukte Aus Mineralischen Ausgangsmaterialien Usw",
    "wof:placetype":"venue"
},
  "geometry": {"coordinates":[8.2853622437,47.3486633301],"type":"Point"}
}