{
  "type": "Feature",
  "properties": {
    "iso:country":"CH",
    "sg:address":"3415 Hasle-r\u00fcegsau. Postfach 162",
    "sg:city":"Hasle-r\u00fcegsau",
    "sg:orig_category":"Sportvereine Eissport Eishockey",
    "sg:postcode":"3415",
    "sg:province":"Bern",
    "wof:name":"Sc Schafhausen Im Emmental",
    "wof:placetype":"venue"
},
  "geometry": {"coordinates":[7.6564297676,47.0159912109],"type":"Point"}
}