{
  "type": "Feature",
  "properties": {
    "iso:country":"CH",
    "sg:address":"Hasenb\u00fcel 32",
    "sg:city":"Zug",
    "sg:orig_category":"Kauf U Verkauf von Immobilien auf eigene Rechnung",
    "sg:postcode":"6300",
    "sg:province":"Zug",
    "wof:name":"Amorel Ag",
    "wof:placetype":"venue"
},
  "geometry": {"coordinates":[8.5170564651,47.1532363892],"type":"Point"}
}