{
  "type": "Feature",
  "properties": {
    "iso:country":"CH",
    "sg:address":"Collex Route De 20 B 1293 Bellevue. Postfach",
    "sg:city":"Bellevue",
    "sg:orig_category":"Berufsbildende weiterf\u00fchrende Schulen",
    "sg:phone":"+41 22 774 30 47",
    "sg:postcode":"1293",
    "sg:province":"Gen\u00e8ve",
    "wof:name":"Wee-henz Linda, Metacore Services",
    "wof:placetype":"venue"
},
  "geometry": {"coordinates":[6.155174,46.255024],"type":"Point"}
}