{
  "type": "Feature",
  "properties": {
    "iso:country":"CH",
    "sg:address":"Nyon Route De",
    "sg:city":"Gland",
    "sg:orig_category":"Non-Classified Establishments",
    "sg:phone":"+41 22 364 32 44",
    "sg:postcode":"1196",
    "sg:province":"Vaud",
    "wof:name":"Hydrotech, Cosendey Philippe",
    "wof:placetype":"venue"
},
  "geometry": {"coordinates":[6.2614498138,46.4224014282],"type":"Point"}
}