{
  "type": "Feature",
  "properties": {
    "iso:country":"CH",
    "sg:address":"Zugerstrasse 79",
    "sg:city":"Unter\u00e4geri",
    "sg:classifiers":[
        {
            "category":"Professional",
            "subcategory":"Detective & Security Services",
            "type":"Services"
        }
    ],
    "sg:phone":"+41 41 750 05 85",
    "sg:postcode":"6314",
    "sg:province":"Zug",
    "sg:tags":[
        "magnet",
        "chart"
    ],
    "wof:name":"Heil Magnethouse",
    "wof:placetype":"venue"
},
  "geometry": {"coordinates":[8.573009,47.140354],"type":"Point"}
}