{
  "type": "Feature",
  "properties": {
    "iso:country":"CH",
    "sg:address":"Chemin De Champs-fleury 2",
    "sg:city":"Bernex",
    "sg:orig_category":"G\u00fcterbef\u00f6rderung im Strassenverkehr",
    "sg:postcode":"1233",
    "sg:province":"Gen\u00e8ve",
    "wof:name":"Gilbert Favre",
    "wof:placetype":"venue"
},
  "geometry": {"coordinates":[6.0585641861,46.1626701355],"type":"Point"}
}