{
  "type": "Feature",
  "properties": {
    "iso:country":"CH",
    "sg:address":"Schweighof",
    "sg:city":"Kriens",
    "sg:orig_category":"Unclassifiable Establishments",
    "sg:postcode":"6010",
    "sg:province":"Luzern",
    "wof:name":"Drachenstein Ag",
    "wof:placetype":"venue"
},
  "geometry": {"coordinates":[8.2965240479,47.0268096924],"type":"Point"}
}