{
  "type": "Feature",
  "properties": {
    "iso:country":"CH",
    "sg:address":"Fonderie Route De La 2 1700 Fribourg. Postfach",
    "sg:city":"Freiburg",
    "sg:orig_category":"Non-Classified Establishments",
    "sg:phone":"+41 26 460 26 60",
    "sg:postcode":"1700",
    "sg:province":"Fribourg",
    "wof:name":"Parvico Sa",
    "wof:placetype":"venue"
},
  "geometry": {"coordinates":[7.1536831856,46.8037452698],"type":"Point"}
}