{
  "type": "Feature",
  "properties": {
    "iso:country":"CH",
    "sg:address":"Rue De La Gare 17",
    "sg:city":"Morges",
    "sg:orig_category":"Detailhandel mit Damenbekleidung",
    "sg:phone":"+41 21 803 31 32",
    "sg:postcode":"1110",
    "sg:province":"Vaud",
    "wof:name":"Crinoline Robes De Mari\u00e9e Sylvie Jaquet",
    "wof:placetype":"venue"
},
  "geometry": {"coordinates":[6.495286,46.509285],"type":"Point"}
}