{
  "type": "Feature",
  "properties": {
    "iso:country":"CH",
    "sg:address":"Unterdorf 36",
    "sg:city":"Laupersdorf",
    "sg:orig_category":"Detailhandel mit Waren verschiedener Art, Hauptrichtung Nahrungsmittel",
    "sg:phone":"+41 62 391 44 50",
    "sg:postcode":"4712",
    "sg:province":"Solothurn",
    "wof:name":"Coop Oberaargau-thal/g\u00e4u",
    "wof:placetype":"venue"
},
  "geometry": {"coordinates":[7.6515321732,47.3135986328],"type":"Point"}
}