{
  "type": "Feature",
  "properties": {
    "iso:country":"CH",
    "sg:address":"Avenue Des Grandes-communes 27",
    "sg:city":"Onex",
    "sg:orig_category":"Fachdetailhandel mit pharmazeutischen Produkten",
    "sg:phone":"+41 32 968 21 75",
    "sg:postcode":"1213",
    "sg:province":"Gen\u00e8ve",
    "wof:name":"Pharmacie Nicole Bertallo.",
    "wof:placetype":"venue"
},
  "geometry": {"coordinates":[6.8275837898,47.1011428833],"type":"Point"}
}