{
  "type": "Feature",
  "properties": {
    "iso:country":"CH",
    "sg:address":"M\u00fchleweg 4942 Walterswil Be. Postfach",
    "sg:city":"Schmidigen-m\u00fchlew",
    "sg:classifiers":[
        {
            "category":"Travel",
            "subcategory":"Hotels & Motels",
            "type":"Entertainment"
        }
    ],
    "sg:postcode":"3464",
    "sg:province":"Bern",
    "sg:tags":[
        "hotels",
        "mit",
        "restaurant"
    ],
    "wof:name":"Gasthof B\u00e4ren, Walter Hiltbrunner",
    "wof:placetype":"venue"
},
  "geometry": {"coordinates":[7.7537879944,47.095615387],"type":"Point"}
}