{
  "type": "Feature",
  "properties": {
    "iso:country":"CH",
    "sg:address":"Austrasse 15",
    "sg:city":"Chur",
    "sg:orig_category":"Handel mit Motorr\u00e4dern, Teilen U Zubeh\u00f6r Instandhaltung U Reparatur von Motorr\u00e4dern",
    "sg:phone":"+41 81 284 22 88",
    "sg:postcode":"7000",
    "sg:province":"Graubunden",
    "wof:name":"Steffi Velosport, Stefan Brenn",
    "wof:placetype":"venue"
},
  "geometry": {"coordinates":[9.5120916367,46.8613967896],"type":"Point"}
}