{
  "type": "Feature",
  "properties": {
    "iso:country":"CH",
    "sg:address":"Gimenenstrasse 3a",
    "sg:city":"Zug",
    "sg:orig_category":"Herstellung von medizinischen U chirurgischen Ger\u00e4ten sowie orthop\u00e4dischen Vorrichtungen",
    "sg:phone":"+41 21 944 65 13",
    "sg:postcode":"6300",
    "sg:province":"Zug",
    "wof:name":"Isabella Fr\u00e9d\u00e9ric",
    "wof:placetype":"venue"
},
  "geometry": {"coordinates":[6.8596520424,46.4516677856],"type":"Point"}
}