{
  "type": "Feature",
  "properties": {
    "iso:country":"CH",
    "sg:address":"Baslerstrasse 60",
    "sg:city":"Z\u00fcrich",
    "sg:orig_category":"Detailhandel mit Metallwaren, Anstrichmitteln, Glaswaren, Bau U Heimwerkerbedarf",
    "sg:phone":"+41 31 839 01 42",
    "sg:postcode":"8048",
    "sg:province":"Z\u00fcrich",
    "wof:name":"J\u00fcrg Engler Rasen- & Motorger\u00e4te",
    "wof:placetype":"venue"
},
  "geometry": {"coordinates":[7.5574388504,46.9344978333],"type":"Point"}
}