{
  "type": "Feature",
  "properties": {
    "iso:country":"CH",
    "sg:address":"Rheinstrasse 199",
    "sg:city":"Chur",
    "sg:orig_category":"Allgemeiner Hoch U Tiefbau Hoch U Tiefbau",
    "sg:phone":"+41 81 284 87 39",
    "sg:postcode":"7000",
    "sg:province":"Graubunden",
    "wof:name":"Cottiati Ag",
    "wof:placetype":"venue"
},
  "geometry": {"coordinates":[9.513135,46.862583],"type":"Point"}
}