{
  "type": "Feature",
  "properties": {
    "iso:country":"CH",
    "sg:address":"M\u00f6riken",
    "sg:city":"Bronschhofen",
    "sg:orig_category":"Zimmerei, Dachdeckerei, Bauspenglerei U Abdichtung",
    "sg:postcode":"9552",
    "sg:province":"St. Gallen",
    "wof:name":"Stricker H.",
    "wof:placetype":"venue"
},
  "geometry": {"coordinates":[9.0252380371,47.4735527039],"type":"Point"}
}