{
  "type": "Feature",
  "properties": {
    "iso:country":"CH",
    "sg:address":"Hauptstrasse 9",
    "sg:city":"Walkringen",
    "sg:orig_category":"Interessenvertretungen",
    "sg:postcode":"3512",
    "sg:province":"Bern",
    "wof:name":"Sternenzentrum Walkringen",
    "wof:placetype":"venue"
},
  "geometry": {"coordinates":[7.6199641228,46.9464836121],"type":"Point"}
}