{
  "type": "Feature",
  "properties": {
    "iso:country":"CH",
    "sg:address":"St. Jakobstrasse 61",
    "sg:city":"Pratteln",
    "sg:orig_category":"Sonstige Hilfs U Nebent\u00e4tigkeiten f\u00fcr die Schiffahrt",
    "sg:postcode":"4133",
    "sg:province":"Basel-Landschaft",
    "wof:name":"Genossenschaft Boots-winterlager",
    "wof:placetype":"venue"
},
  "geometry": {"coordinates":[7.6841301918,47.5200080872],"type":"Point"}
}