{
  "type": "Feature",
  "properties": {
    "iso:country":"CH",
    "sg:address":"Avenue De Frontenex 5",
    "sg:city":"Gen\u00e8ve",
    "sg:classifiers":[
        {
            "category":"Restaurant",
            "type":"Food & Drink"
        }
    ],
    "sg:phone":"+41 22 736 63 00",
    "sg:postcode":"1207",
    "sg:province":"Gen\u00e8ve",
    "wof:name":"Caf\u00e9 Op\u00e9ra Bouffe",
    "wof:placetype":"venue"
},
  "geometry": {"coordinates":[6.1571707726,46.2018661499],"type":"Point"}
}