{
  "type": "Feature",
  "properties": {
    "iso:country":"CH",
    "sg:address":"Am Bach 75",
    "sg:city":"Leutwil",
    "sg:orig_category":"Markt U Meinungsforschung",
    "sg:phone":"+41 62 777 53 96",
    "sg:postcode":"5725",
    "sg:province":"Aargau",
    "wof:name":"Hid Marketing Gmbh",
    "wof:placetype":"venue"
},
  "geometry": {"coordinates":[8.1739883423,47.3088150024],"type":"Point"}
}