{
  "type": "Feature",
  "properties": {
    "iso:country":"CH",
    "sg:address":"Chemin Du Petit-montfleury 6",
    "sg:city":"Versoix",
    "sg:orig_category":"Handels-H\u00e4user U Gesellschaften",
    "sg:postcode":"1290",
    "sg:province":"Gen\u00e8ve",
    "wof:name":"Safe World Technology, Obielum",
    "wof:placetype":"venue"
},
  "geometry": {"coordinates":[6.1632409096,46.290977478],"type":"Point"}
}