{
  "type": "Feature",
  "properties": {
    "iso:country":"CH",
    "sg:address":"Rudolfstrasse 19",
    "sg:city":"Winterthur",
    "sg:orig_category":"Unternehmensberatung",
    "sg:phone":"+41 52 212 54 40",
    "sg:postcode":"8400",
    "sg:province":"Z\u00fcrich",
    "wof:name":"Sprenger Partner Ag",
    "wof:placetype":"venue"
},
  "geometry": {"coordinates":[8.7232608795,47.5012588501],"type":"Point"}
}