{
  "type": "Feature",
  "properties": {
    "iso:country":"CH",
    "sg:address":"6234",
    "sg:city":"Triengen",
    "sg:orig_category":"Primarschulen",
    "sg:phone":"+41 41 933 14 30",
    "sg:postcode":"6234",
    "sg:province":"Luzern",
    "wof:name":"Primarschule Dorf",
    "wof:placetype":"venue"
},
  "geometry": {"coordinates":[8.0757846832,47.2360610962],"type":"Point"}
}