{
  "type": "Feature",
  "properties": {
    "iso:country":"CH",
    "sg:address":"Winkel 7",
    "sg:city":"Triengen",
    "sg:orig_category":"Grosshandel mit Holz U Baustoffen Herstellung von Teppichen",
    "sg:phone":"+41 41 933 10 86",
    "sg:postcode":"6234",
    "sg:province":"Luzern",
    "wof:name":"Hersche Airtrock",
    "wof:placetype":"venue"
},
  "geometry": {"coordinates":[8.0788593292,47.235710144],"type":"Point"}
}