{
  "type": "Feature",
  "properties": {
    "iso:country":"CH",
    "sg:address":"Langacherstrasse 10",
    "sg:city":"Untersiggenthal",
    "sg:orig_category":"Hoch U Tiefbau",
    "sg:phone":"+41 71 385 17 55",
    "sg:postcode":"5417",
    "sg:province":"Aargau",
    "wof:name":"Johann Stranio Baugesch\u00e4ft",
    "wof:placetype":"venue"
},
  "geometry": {"coordinates":[9.2709121704,47.4137306213],"type":"Point"}
}