{
  "type": "Feature",
  "properties": {
    "addr:full":"Rebenweg 4 Dotzigen Bern 3293",
    "addr:housenumber":"4",
    "addr:postcode":"3293",
    "addr:street":"Rebenweg",
    "iso:country":"CH",
    "sg:address":"Rebenweg 4",
    "sg:city":"Dotzigen",
    "sg:orig_category":"Allgemeiner Hoch U Tiefbau Allgemeiner Hochbau",
    "sg:phone":"+41 79 208 97 71",
    "sg:postcode":"3293",
    "sg:province":"Bern",
    "wof:name":"Schluep + Schori Ag",
    "wof:placetype":"venue"
},
  "geometry": {"coordinates":[7.34452,47.120274],"type":"Point"}
}