{
  "type": "Feature",
  "properties": {
    "iso:country":"CH",
    "sg:address":"Rebenweg 4",
    "sg:city":"Dotzigen",
    "sg:orig_category":"Allgemeiner Hoch U Tiefbau Allgemeiner Hochbau",
    "sg:phone":"+41 79 208 97 71",
    "sg:postcode":"3293",
    "sg:province":"Bern",
    "wof:name":"Schluep + Schori Ag",
    "wof:placetype":"venue"
},
  "geometry": {"coordinates":[7.34452,47.120274],"type":"Point"}
}