{
  "type": "Feature",
  "properties": {
    "addr:full":"Via Ressiga 5 Giubiasco Ticino 6512",
    "addr:housenumber":"5",
    "addr:postcode":"6512",
    "addr:street":"Via Ressiga",
    "iso:country":"CH",
    "sg:address":"Via Ressiga 5",
    "sg:city":"Giubiasco",
    "sg:orig_category":"Arztpraxen",
    "sg:phone":"+41 91 826 10 10",
    "sg:postcode":"6512",
    "sg:province":"Ticino",
    "wof:name":"Dott.med.pier Carlo Nobile Specialista Fmh",
    "wof:placetype":"venue"
},
  "geometry": {"coordinates":[9.004887,46.171028],"type":"Point"}
}