{
  "type": "Feature",
  "properties": {
    "iso:country":"CH",
    "sg:address":"Riesbachstrasse 57",
    "sg:city":"Z\u00fcrich",
    "sg:classifiers":[
        {
            "category":"Structure",
            "subcategory":"Bridge",
            "type":"Public Place"
        }
    ],
    "sg:phone":"+41 13899800",
    "sg:postcode":"8034",
    "sg:province":"Z\u00fcrich",
    "sg:tags":[
        "bearing"
    ],
    "wof:name":"Proceq Sa",
    "wof:placetype":"venue"
},
  "geometry": {"coordinates":[8.555426,47.358334],"type":"Point"}
}