{
  "type": "Feature",
  "properties": {
    "iso:country":"CH",
    "sg:address":"Alte Landstrasse 10",
    "sg:city":"Pf\u00e4ffikon",
    "sg:classifiers":[
        {
            "category":"Shopping Center",
            "type":"Public Place"
        }
    ],
    "sg:phone":"+41 55 410 13 77",
    "sg:postcode":"8808",
    "sg:province":"Schwyz",
    "sg:tags":[
        "aluminium",
        "casting"
    ],
    "wof:name":"Gebr\u00fcder J\u00e4ger",
    "wof:placetype":"venue"
},
  "geometry": {"coordinates":[8.78752,47.202412],"type":"Point"}
}