{
  "type": "Feature",
  "properties": {
    "iso:country":"CH",
    "sg:address":"Teuchelweg 21",
    "sg:city":"Chur",
    "sg:orig_category":"Versicherungen Generalagenturen",
    "sg:phone":"+41 16282828",
    "sg:postcode":"7000",
    "sg:province":"Graubunden",
    "wof:name":"Z\u00fcrich Versicherungen Generaldirektion Schweiz",
    "wof:placetype":"venue"
},
  "geometry": {"coordinates":[8.5612001419,47.4258499146],"type":"Point"}
}