{
  "type": "Feature",
  "properties": {
    "iso:country":"CH",
    "sg:address":"Haldenstrasse 10 8185 Winkel. Postfach",
    "sg:city":"Winkel",
    "sg:orig_category":"Softwareentwicklung U beratung",
    "sg:postcode":"8185",
    "sg:province":"Z\u00fcrich",
    "wof:name":"Top Mac, Verhein B. Pc-systeme; Bewertung, Unterst\u00fctzung, Schulung",
    "wof:placetype":"venue"
},
  "geometry": {"coordinates":[8.5538043976,47.4945411682],"type":"Point"}
}