{
  "type": "Feature",
  "properties": {
    "iso:country":"CH",
    "sg:address":"Artmattstrasse 21",
    "sg:city":"Gerlafingen",
    "sg:orig_category":"Arztpraxen",
    "sg:phone":"+41 62 776 22 36",
    "sg:postcode":"4563",
    "sg:province":"Solothurn",
    "wof:name":"Dr.med.ulrich Widmer Arzt F.allgemeine Medizin Fmh",
    "wof:placetype":"venue"
},
  "geometry": {"coordinates":[8.115115,47.329964],"type":"Point"}
}