{
  "type": "Feature",
  "properties": {
    "iso:country":"CH",
    "sg:address":"Bahnhofstrasse 14",
    "sg:city":"M\u00fcnchenbuchsee",
    "sg:orig_category":"Detailhandel mit Fahrr\u00e4dern",
    "sg:phone":"+41 76 544 13 60",
    "sg:postcode":"3053",
    "sg:province":"Bern",
    "wof:name":"Veloegge",
    "wof:placetype":"venue"
},
  "geometry": {"coordinates":[7.452586174,47.0202713013],"type":"Point"}
}