{
  "type": "Feature",
  "properties": {
    "iso:country":"CH",
    "sg:address":"Seezelgstrasse 22",
    "sg:city":"Altnau",
    "sg:orig_category":"Sportvereine Turnen Vereine Damen",
    "sg:postcode":"8595",
    "sg:province":"Thurgau",
    "wof:name":"Frauenturnverein Stv Ammerswil",
    "wof:placetype":"venue"
},
  "geometry": {"coordinates":[8.2071800232,47.3694801331],"type":"Point"}
}