{
  "type": "Feature",
  "properties": {
    "iso:country":"CH",
    "sg:address":"Hameau Du Ch\u00e2teau",
    "sg:city":"Oron-le-ch\u00e2tel",
    "sg:orig_category":"Verarbeitung von Tee U Kaffee",
    "sg:postcode":"1608",
    "sg:province":"Fribourg",
    "wof:name":"Saveurs D'origine S\u00e0rl",
    "wof:placetype":"venue"
},
  "geometry": {"coordinates":[6.840719223,46.575969696],"type":"Point"}
}