{
  "type": "Feature",
  "properties": {
    "iso:country":"CH",
    "sg:address":"La Rive",
    "sg:city":"Concise",
    "sg:classifiers":[
        {
            "category":"Travel",
            "subcategory":"Hotels & Motels",
            "type":"Entertainment"
        }
    ],
    "sg:phone":"+41 24 434 12 03",
    "sg:postcode":"1426",
    "sg:province":"Vaud",
    "sg:tags":[
        "hotels",
        "mit",
        "restaurant"
    ],
    "wof:name":"H\u00f4tel Des Bateaux",
    "wof:placetype":"venue"
},
  "geometry": {"coordinates":[6.7188878059,46.8491020203],"type":"Point"}
}