{
  "type": "Feature",
  "properties": {
    "iso:country":"CH",
    "sg:address":"Route De Frontenex 62b",
    "sg:city":"Gen\u00e8ve",
    "sg:classifiers":[
        {
            "category":"Restaurant",
            "type":"Food & Drink"
        }
    ],
    "sg:phone":"+41 22 735 13 13",
    "sg:postcode":"1208",
    "sg:province":"Gen\u00e8ve",
    "wof:name":"Restaurant New Modulard",
    "wof:placetype":"venue"
},
  "geometry": {"coordinates":[6.1685490608,46.2036437988],"type":"Point"}
}