{
  "type": "Feature",
  "properties": {
    "addr:full":"Isone Isone Ticino 6810",
    "addr:postcode":"6810",
    "iso:country":"CH",
    "sg:address":"Isone",
    "sg:city":"Isone",
    "sg:classifiers":[
        {
            "category":"Banks & Credit Unions",
            "subcategory":"Bank",
            "type":"Services"
        }
    ],
    "sg:phone":"+41 91 946 28 36",
    "sg:postcode":"6810",
    "sg:province":"Ticino",
    "wof:name":"Raiffeisen Di Isone",
    "wof:placetype":"venue"
},
  "geometry": {"coordinates":[8.987142,46.129604],"type":"Point"}
}