{
  "type": "Feature",
  "properties": {
    "addr:full":"Thunstrasse 12 3770 Zweisimmen. Postfach 430 Zweisimmen Bern 3770",
    "addr:housenumber":"12;430",
    "addr:postcode":"3770;3770",
    "addr:street":"Thunstrasse;Postfach",
    "iso:country":"CH",
    "sg:address":"Thunstrasse 12 3770 Zweisimmen. Postfach 430",
    "sg:city":"Zweisimmen",
    "sg:orig_category":"Bauschreinerei Herstellung von Konstruktionsteilen, Fertigbauteilen U Ausbauelementen aus Holz",
    "sg:phone":"+41 79 215 58 19",
    "sg:postcode":"3770",
    "sg:province":"Bern",
    "wof:name":"Schreinerei Gebr\u00fcder Stalder",
    "wof:placetype":"venue"
},
  "geometry": {"coordinates":[7.37413,46.555756],"type":"Point"}
}