{
  "type": "Feature",
  "properties": {
    "addr:full":"Bruggacherstrasse 8 F\u00e4llanden Z\u00fcrich 8117",
    "addr:housenumber":"8",
    "addr:postcode":"8117",
    "addr:street":"Bruggacherstrasse;Zuerich",
    "iso:country":"CH",
    "sg:address":"Bruggacherstrasse 8",
    "sg:city":"F\u00e4llanden",
    "sg:classifiers":[
        {
            "category":"Health Services",
            "subcategory":"Hospital",
            "type":"Services"
        }
    ],
    "sg:phone":"+41 18068080",
    "sg:postcode":"8117",
    "sg:province":"Z\u00fcrich",
    "sg:tags":[
        "capsule",
        "cap",
        "bottle"
    ],
    "wof:name":"Max Baldinger Ag",
    "wof:placetype":"venue"
},
  "geometry": {"coordinates":[8.632427,47.374283],"type":"Point"}
}