{
  "type": "Feature",
  "properties": {
    "iso:country":"CH",
    "sg:address":"3235",
    "sg:city":"Erlach",
    "sg:orig_category":"Polizei",
    "sg:phone":"+41 32 338 14 44",
    "sg:postcode":"3235",
    "sg:province":"Bern",
    "wof:name":"Kantonale Polizei",
    "wof:placetype":"venue"
},
  "geometry": {"coordinates":[7.0929951668,47.0446243286],"type":"Point"}
}