{
  "type": "Feature",
  "properties": {
    "iso:country":"CH",
    "sg:address":"M\u00fcnzelweg 18",
    "sg:city":"M\u00e4genwil",
    "sg:orig_category":"G\u00fcterbef\u00f6rderung im Strassenverkehr",
    "sg:phone":"+41 62 896 26 76",
    "sg:postcode":"5506",
    "sg:province":"Aargau",
    "wof:name":"Attiger Franz",
    "wof:placetype":"venue"
},
  "geometry": {"coordinates":[8.2407064438,47.4147377014],"type":"Point"}
}