{
  "type": "Feature",
  "properties": {
    "iso:country":"CH",
    "sg:address":"Hauptstrasse 94",
    "sg:city":"B\u00e4ttwil-fl\u00fch",
    "sg:classifiers":[
        {
            "category":"Travel",
            "subcategory":"Hotels & Motels",
            "type":"Entertainment"
        }
    ],
    "sg:postcode":"4112",
    "sg:province":"Solothurn",
    "sg:tags":[
        "hotels",
        "mit",
        "restaurant"
    ],
    "wof:name":"Wernli Georg",
    "wof:placetype":"venue"
},
  "geometry": {"coordinates":[7.2833991051,47.1236839294],"type":"Point"}
}