{
  "type": "Feature",
  "properties": {
    "iso:country":"CH",
    "sg:address":"Singlistrasse 5 8049 Z\u00fcrich. Postfach",
    "sg:city":"Z\u00fcrich",
    "sg:orig_category":"Fernmeldedienste",
    "sg:postcode":"8049",
    "sg:province":"Z\u00fcrich",
    "wof:name":"Hnc Commerce Ag",
    "wof:placetype":"venue"
},
  "geometry": {"coordinates":[8.4953365326,47.403213501],"type":"Point"}
}