{
  "type": "Feature",
  "properties": {
    "iso:country":"CH",
    "sg:address":"Lindenegg 5",
    "sg:city":"Biel/bienne",
    "sg:classifiers":[
        {
            "category":"Travel",
            "subcategory":"Hotels & Motels",
            "type":"Entertainment"
        }
    ],
    "sg:phone":"+41 32 322 94 66",
    "sg:postcode":"2502",
    "sg:province":"Bern",
    "sg:tags":[
        "hotels",
        "mit",
        "restaurant"
    ],
    "wof:name":"Villa Lindenegg Balzli B.",
    "wof:placetype":"venue"
},
  "geometry": {"coordinates":[7.243434906,47.1409072876],"type":"Point"}
}