{
  "type": "Feature",
  "properties": {
    "iso:country":"CH",
    "sg:address":"W\u00e4ssermattstrasse 7",
    "sg:city":"Aarau",
    "sg:orig_category":"Druck ohne Zeitungsdruck",
    "sg:postcode":"5000",
    "sg:province":"Aargau",
    "wof:name":"Mmrt Consulting Gmbh",
    "wof:placetype":"venue"
},
  "geometry": {"coordinates":[8.0673532486,47.3991241455],"type":"Point"}
}