{
  "type": "Feature",
  "properties": {
    "iso:country":"CH",
    "sg:address":"Rue Francillon 25",
    "sg:city":"St-imier",
    "sg:orig_category":"Detailhandel mit elektrischen Haushalts, Radio U Fernsehger\u00e4ten ohne ausgepr\u00e4gten Schwerpunkt Herste",
    "sg:phone":"+41 32 942 41 00",
    "sg:postcode":"2610",
    "sg:province":"Bern",
    "wof:name":"Soci\u00e9t\u00e9 Des Forces Electriques De La Goule",
    "wof:placetype":"venue"
},
  "geometry": {"coordinates":[6.9992218018,47.1530609131],"type":"Point"}
}