{
  "type": "Feature",
  "properties": {
    "iso:country":"CH",
    "sg:address":"Avenue Robert 12 2052 Fontainemelon Case Postale 33",
    "sg:city":"Fontainemelon",
    "sg:orig_category":"HERSTELLUNG VON GER\u00c4TEN DER ELEKTRIZIT\u00c4TSERZEUGUNG, -VERTEILUNG U.\u00c4 Herstellung von sonstigen elektr",
    "sg:phone":"+41 32 854 44 11",
    "sg:postcode":"2052",
    "sg:province":"Neuch\u00e2tel",
    "wof:name":"Meyer Urs Electronic Sa",
    "wof:placetype":"venue"
},
  "geometry": {"coordinates":[6.8929262161,47.0572357178],"type":"Point"}
}