{
  "type": "Feature",
  "properties": {
    "iso:country":"CH",
    "sg:address":"Englischgrusstrasse 48",
    "sg:city":"Glis",
    "sg:orig_category":"Selbst\u00e4ndige bildende K\u00fcnstler",
    "sg:phone":"+41 27 923 37 51",
    "sg:postcode":"3902",
    "sg:province":"Valais",
    "wof:name":"Emil Pfammatter Grabsteingesch\u00e4ft",
    "wof:placetype":"venue"
},
  "geometry": {"coordinates":[7.9828300476,46.3157348633],"type":"Point"}
}