{
  "type": "Feature",
  "properties": {
    "iso:country":"CH",
    "sg:address":"Redingstrasse 2",
    "sg:city":"Kreuzlingen",
    "sg:orig_category":"Sportvereine",
    "sg:phone":"+41 19101466",
    "sg:postcode":"8280",
    "sg:province":"Thurgau",
    "wof:name":"Senioren-verein",
    "wof:placetype":"venue"
},
  "geometry": {"coordinates":[8.5951433182,47.3266181946],"type":"Point"}
}