{
  "type": "Feature",
  "properties": {
    "iso:country":"CH",
    "sg:address":"K\u00fchriedweg 31",
    "sg:city":"Z\u00fcrich",
    "sg:classifiers":[
        {
            "category":"Sports & Exercise",
            "subcategory":"Tennis Court",
            "type":"Entertainment"
        }
    ],
    "sg:phone":"+41 13127270",
    "sg:postcode":"8050",
    "sg:province":"Z\u00fcrich",
    "sg:tags":[
        "squash-centers",
        "hallen",
        "tennis-"
    ],
    "wof:name":"Tennisplatz Riedgraben Sulzer-escher Wyss Ag",
    "wof:placetype":"venue"
},
  "geometry": {"coordinates":[8.5580739975,47.4096107483],"type":"Point"}
}