{
  "type": "Feature",
  "properties": {
    "iso:country":"CH",
    "sg:address":"Haltingerstrasse 104",
    "sg:city":"Basel",
    "sg:classifiers":[
        {
            "category":"Travel",
            "subcategory":"Hotels & Motels",
            "type":"Entertainment"
        }
    ],
    "sg:postcode":"4057",
    "sg:province":"Basel-Stadt",
    "sg:tags":[
        "hotels",
        "mit",
        "restaurant"
    ],
    "wof:name":"Stiftung Micado",
    "wof:placetype":"venue"
},
  "geometry": {"coordinates":[8.5127677917,47.1442947388],"type":"Point"}
}