{
  "type": "Feature",
  "properties": {
    "addr:full":"Via Camana Cadro Ticino 6965",
    "addr:postcode":"6965",
    "addr:street":"Via Camana",
    "iso:country":"CH",
    "sg:address":"Via Camana",
    "sg:city":"Cadro",
    "sg:orig_category":"Betrieb von Sportanlagen",
    "sg:postcode":"6965",
    "sg:province":"Ticino",
    "wof:name":"Bad Alvaneu Ag",
    "wof:placetype":"venue"
},
  "geometry": {"coordinates":[9.649466,46.669079],"type":"Point"}
}