{
  "type": "Feature",
  "properties": {
    "iso:country":"CH",
    "sg:address":"Am Dorfplatz",
    "sg:city":"Lieli",
    "sg:orig_category":"Satzherstellung U Reproduktion",
    "sg:postcode":"6277",
    "sg:province":"Luzern",
    "wof:name":"Kmu-forum Gmbh",
    "wof:placetype":"venue"
},
  "geometry": {"coordinates":[8.2999296188,47.20753479],"type":"Point"}
}