{
  "type": "Feature",
  "properties": {
    "iso:country":"CH",
    "sg:address":"Rain 8",
    "sg:city":"Ennenda",
    "sg:orig_category":"Institutionen f\u00fcr Suchtkranke Institutionen f\u00fcr psychosoziale F\u00e4lle",
    "sg:phone":"+41 55 640 43 46",
    "sg:postcode":"8755",
    "sg:province":"Glarus",
    "wof:name":"Schweiz.rotes Kreuz Durchgangsheim",
    "wof:placetype":"venue"
},
  "geometry": {"coordinates":[9.0788221359,47.0362663269],"type":"Point"}
}