{
  "type": "Feature",
  "properties": {
    "iso:country":"CH",
    "sg:address":"Sigriswilstrasse 209",
    "sg:city":"Gunten",
    "sg:classifiers":[
        {
            "category":"Travel",
            "subcategory":"Hotels & Motels",
            "type":"Entertainment"
        }
    ],
    "sg:phone":"+41 33 243 16 76",
    "sg:postcode":"3654",
    "sg:province":"Bern",
    "sg:tags":[
        "hotels",
        "mit",
        "restaurant"
    ],
    "wof:name":"Hotel Kreuz",
    "wof:placetype":"venue"
},
  "geometry": {"coordinates":[7.6689548492,46.7306976318],"type":"Point"}
}