{
  "type": "Feature",
  "properties": {
    "iso:country":"CH",
    "sg:address":"7138 Surcuolm. Postfach",
    "sg:city":"Surcuolm",
    "sg:orig_category":"RESTAURANTS: TEA-ROOMS",
    "sg:postcode":"7138",
    "sg:province":"Graubunden",
    "wof:name":"Berghaus Foppa Ag",
    "wof:placetype":"venue"
},
  "geometry": {"coordinates":[9.2852306366,46.8366928101],"type":"Point"}
}