{
  "type": "Feature",
  "properties": {
    "iso:country":"CH",
    "sg:address":"Chemin Fr\u00e9d\u00e9ric-ingold 5",
    "sg:city":"Biel/bienne",
    "sg:orig_category":"Military Watches",
    "sg:phone":"+41 32 341 22 13",
    "sg:postcode":"2502",
    "sg:province":"Bern",
    "wof:name":"Glycine Watch Sa",
    "wof:placetype":"venue"
},
  "geometry": {"coordinates":[7.2579159737,47.1461524963],"type":"Point"}
}