{
  "type": "Feature",
  "properties": {
    "iso:country":"CH",
    "sg:address":"Obere Reppischstrasse 39",
    "sg:city":"Dietikon",
    "sg:orig_category":"Grosshandel mit Getr\u00e4nken",
    "sg:phone":"+41 17408027",
    "sg:postcode":"8953",
    "sg:province":"Z\u00fcrich",
    "wof:name":"Getr\u00e4nke Zimmermann Gmbh",
    "wof:placetype":"venue"
},
  "geometry": {"coordinates":[8.3983631134,47.4030380249],"type":"Point"}
}