{
  "type": "Feature",
  "properties": {
    "addr:full":"Wilerstrasse 41 Wattwil St. Gallen 9630",
    "addr:housenumber":"41",
    "addr:postcode":"9630",
    "addr:street":"Wilerstrasse",
    "iso:country":"CH",
    "sg:address":"Wilerstrasse 41",
    "sg:city":"Wattwil",
    "sg:orig_category":"Bestattungswesen Betrieb von Taxis",
    "sg:phone":"+41 61 751 10 03",
    "sg:postcode":"9630",
    "sg:province":"St. Gallen",
    "wof:name":"Heinrich K\u00e4ch Ag",
    "wof:placetype":"venue"
},
  "geometry": {"coordinates":[7.598451,47.466644],"type":"Point"}
}