{
  "type": "Feature",
  "properties": {
    "addr:full":"Avenue De La Grenade 20 Gen\u00e8ve Gen\u00e8ve 1207",
    "addr:housenumber":"20",
    "addr:postcode":"1207",
    "addr:street":"Avenue De La Grenade",
    "iso:country":"CH",
    "sg:address":"Avenue De La Grenade 20",
    "sg:city":"Gen\u00e8ve",
    "sg:orig_category":"Arztpraxen",
    "sg:phone":"+41 22 735 35 55",
    "sg:postcode":"1207",
    "sg:province":"Gen\u00e8ve",
    "wof:name":"Dr M\u00e9d. Evelyne Kolatte M\u00e9decin Sp\u00e9cialiste Fmh",
    "wof:placetype":"venue"
},
  "geometry": {"coordinates":[6.161602,46.20549],"type":"Point"}
}