{
  "type": "Feature",
  "properties": {
    "iso:country":"CH",
    "sg:address":"Wingreis",
    "sg:city":"Twann",
    "sg:orig_category":"Kauf U Verkauf von Immobilien auf eigene Rechnung",
    "sg:phone":"+41 32 315 11 25",
    "sg:postcode":"2513",
    "sg:province":"Bern",
    "wof:name":"Hotel-restaurant Engelberg Ag Twann",
    "wof:placetype":"venue"
},
  "geometry": {"coordinates":[7.1769728661,47.1025657654],"type":"Point"}
}