{
  "type": "Feature",
  "properties": {
    "iso:country":"CH",
    "sg:address":"Le Moulin 1616 Attalens. Postfach",
    "sg:city":"Tatroz",
    "sg:orig_category":"Wirtschaftspr\u00fcfung, Steuerberatung U Treuhand",
    "sg:postcode":"1617",
    "sg:province":"Fribourg",
    "wof:name":"Dv Gestion Dewarrat Val\u00e9rie",
    "wof:placetype":"venue"
},
  "geometry": {"coordinates":[6.8493890762,46.5091896057],"type":"Point"}
}