{
  "type": "Feature",
  "properties": {
    "iso:country":"CH",
    "sg:address":"Baumenrainweg 297",
    "sg:city":"B\u00e4rschwil",
    "sg:classifiers":[
        {
            "category":"Insurance",
            "subcategory":"Insurance Agent",
            "type":"Services"
        }
    ],
    "sg:phone":"+41 56 664 39 50",
    "sg:postcode":"4252",
    "sg:province":"Solothurn",
    "sg:tags":[
        "versicherungsagenturen",
        "-broker"
    ],
    "wof:name":"Alfons St\u00f6ckli Versicherungsb\u00fcro",
    "wof:placetype":"venue"
},
  "geometry": {"coordinates":[8.3174819946,47.2825775146],"type":"Point"}
}