{
  "type": "Feature",
  "properties": {
    "iso:country":"CH",
    "sg:address":"Oberstm\u00fchle 14",
    "sg:city":"Stans",
    "sg:orig_category":"Grosshandel mit Eisenwaren sowie Installationsbedarf f\u00fcr Gas, Wasser U Heizung Herstellung von Werkz",
    "sg:phone":"+41 41 610 99 58",
    "sg:postcode":"6370",
    "sg:province":"Nidwalden",
    "wof:name":"Botech Ag",
    "wof:placetype":"venue"
},
  "geometry": {"coordinates":[8.3549852371,46.968788147],"type":"Point"}
}