{
  "type": "Feature",
  "properties": {
    "iso:country":"CH",
    "sg:address":"Friedentalstrasse 7",
    "sg:city":"Luzern",
    "sg:orig_category":"Detailhandel mit Brennstoffen U Heizmaterial Grosshandel mit festen Brennstoffen U Mineral\u00f6lerzeugni",
    "sg:phone":"+41 21 960 10 27",
    "sg:postcode":"6004",
    "sg:province":"Luzern",
    "wof:name":"Carlo Corsi-regez Sa",
    "wof:placetype":"venue"
},
  "geometry": {"coordinates":[6.926136,46.397156],"type":"Point"}
}