{
  "type": "Feature",
  "properties": {
    "iso:country":"CH",
    "sg:address":"Avenue Des Vergys 13",
    "sg:city":"Ch\u00eane-bourg",
    "sg:classifiers":[
        {
            "category":"Structure",
            "subcategory":"Office Building",
            "type":"Public Place"
        }
    ],
    "sg:phone":"+41 22 797 47 87",
    "sg:postcode":"1225",
    "sg:province":"Gen\u00e8ve",
    "sg:tags":[
        "brick",
        "ceiling",
        "module"
    ],
    "wof:name":"Simon Borga",
    "wof:placetype":"venue"
},
  "geometry": {"coordinates":[6.100012,46.20602],"type":"Point"}
}