{
  "type": "Feature",
  "properties": {
    "iso:country":"CH",
    "sg:address":"Hauptstrasse 163a",
    "sg:city":"Bonaduz",
    "sg:orig_category":"Grosshandel mit B\u00fcromaschinen Grosshandel mit Datenverarbeitungsger\u00e4ten",
    "sg:phone":"+41 81 630 22 50",
    "sg:postcode":"7402",
    "sg:province":"Graubunden",
    "wof:name":"Ragettli Computer Hard-& Software",
    "wof:placetype":"venue"
},
  "geometry": {"coordinates":[9.4022121429,46.8211631775],"type":"Point"}
}