{
  "type": "Feature",
  "properties": {
    "iso:country":"CH",
    "sg:address":"Im Rossfeld 18",
    "sg:city":"Schaan",
    "sg:orig_category":"Non-Classified Establishments",
    "sg:postcode":"9494",
    "wof:name":"Monique Van Geffen Physiotherapie",
    "wof:placetype":"venue"
},
  "geometry": {"coordinates":[9.5136928558,47.1667098999],"type":"Point"}
}