{
  "type": "Feature",
  "properties": {
    "iso:country":"CH",
    "sg:address":"Stegenerstrasse 21",
    "sg:city":"Gachnang",
    "sg:orig_category":"Grosshandel mit Getreide, Saatgut U Futtermitteln Grosshandel mit landwirtschaftlichen Maschinen U G",
    "sg:phone":"+41 52 375 21 60",
    "sg:postcode":"8547",
    "sg:province":"Thurgau",
    "wof:name":"Porlag Ag",
    "wof:placetype":"venue"
},
  "geometry": {"coordinates":[8.8533210754,47.5367660522],"type":"Point"}
}