{
  "type": "Feature",
  "properties": {
    "iso:country":"CH",
    "sg:address":"Luzernerstrasse 144",
    "sg:city":"Littau",
    "sg:orig_category":"Vorschulen, Kinderg\u00e4rten",
    "sg:phone":"+41 41 250 80 15",
    "sg:postcode":"6014",
    "sg:province":"Luzern",
    "wof:name":"Kindergarten",
    "wof:placetype":"venue"
},
  "geometry": {"coordinates":[8.2633876801,47.0496101379],"type":"Point"}
}