{
  "type": "Feature",
  "properties": {
    "iso:country":"CH",
    "sg:address":"Baderg\u00e4ssli 7",
    "sg:city":"Aarau",
    "sg:orig_category":"Haltung von Schafen, Ziegen, Pferden U Eseln Mit Sport verbundene T\u00e4tigkeiten",
    "sg:phone":"+41 62 891 47 77",
    "sg:postcode":"5000",
    "sg:province":"Aargau",
    "wof:name":"Gest\u00fct Staufberg Gmbh",
    "wof:placetype":"venue"
},
  "geometry": {"coordinates":[8.0499897003,47.3918151855],"type":"Point"}
}