{
  "type": "Feature",
  "properties": {
    "iso:country":"CH",
    "sg:address":"Weststrasse 101",
    "sg:city":"Z\u00fcrich",
    "sg:orig_category":"Druckweiterverarbeitung",
    "sg:phone":"+41 19313484",
    "sg:postcode":"8003",
    "sg:province":"Z\u00fcrich",
    "wof:name":"Jonas Westermann Buchbinderei & Einrahmungen",
    "wof:placetype":"venue"
},
  "geometry": {"coordinates":[8.8079767227,47.3251075745],"type":"Point"}
}