{
  "type": "Feature",
  "properties": {
    "iso:country":"CH",
    "sg:address":"Ruessackerstrasse 14",
    "sg:city":"Lampenberg",
    "sg:orig_category":"Softwareentwicklung U beratung",
    "sg:phone":"+41 61 951 20 04",
    "sg:postcode":"4432",
    "sg:province":"Basel-Landschaft",
    "wof:name":"Softwareingenieurb\u00fcro Richner",
    "wof:placetype":"venue"
},
  "geometry": {"coordinates":[7.756307,47.423763],"type":"Point"}
}