{
  "type": "Feature",
  "properties": {
    "iso:country":"CH",
    "sg:address":"Dorfstrasse 31",
    "sg:city":"Alpthal",
    "sg:orig_category":"Grosshandel mit Holz U Baustoffen Hobel U Holzimpr\u00e4gnierwerke",
    "sg:phone":"+41 55 412 22 06",
    "sg:postcode":"8849",
    "sg:province":"Schwyz",
    "wof:name":"Felder Adolf Ag",
    "wof:placetype":"venue"
},
  "geometry": {"coordinates":[8.7148065567,47.0681304932],"type":"Point"}
}