{
  "type": "Feature",
  "properties": {
    "iso:country":"CH",
    "sg:address":"7445",
    "sg:city":"Innerferrera",
    "sg:orig_category":"Forst\u00e4mter",
    "sg:phone":"+41 81 667 12 16",
    "sg:postcode":"7445",
    "sg:province":"Graubunden",
    "wof:name":"Revierforstamt Ferrera-avers",
    "wof:placetype":"venue"
},
  "geometry": {"coordinates":[9.4429302216,46.5210494995],"type":"Point"}
}