{
  "type": "Feature",
  "properties": {
    "iso:country":"CH",
    "sg:address":"Rue Du Rh\u00f4ne 25",
    "sg:city":"Sion",
    "sg:orig_category":"RESTAURANTS: TEA-ROOMS",
    "sg:phone":"+41 27 323 32 31",
    "sg:postcode":"1950",
    "sg:province":"Valais",
    "wof:name":"Moren, Freddy",
    "wof:placetype":"venue"
},
  "geometry": {"coordinates":[7.3615288734,46.2321052551],"type":"Point"}
}