{
  "type": "Feature",
  "properties": {
    "iso:country":"CH",
    "sg:address":"Via Campagne",
    "sg:city":"Tenero",
    "sg:orig_category":"Vermietung U Verpachtung von eigenen Immobilien",
    "sg:postcode":"6598",
    "sg:province":"Ticino",
    "wof:name":"Sa Teco",
    "wof:placetype":"venue"
},
  "geometry": {"coordinates":[8.8504199982,46.1802101135],"type":"Point"}
}