{
  "type": "Feature",
  "properties": {
    "iso:country":"CH",
    "sg:address":"L\u00f6hrenweg 31 2500 Biel/bienne. Postfach",
    "sg:city":"Biel/bienne",
    "sg:orig_category":"Herstellung von Karosserien U Anh\u00e4ngern",
    "sg:phone":"+41 32 342 35 60",
    "sg:postcode":"2504",
    "sg:province":"Bern",
    "wof:name":"Zwahlen Peter Carrosserie Und Fahrzeugbau",
    "wof:placetype":"venue"
},
  "geometry": {"coordinates":[7.2824749947,47.1437950134],"type":"Point"}
}