{
  "type": "Feature",
  "properties": {
    "iso:country":"CH",
    "sg:address":"Ergolzstrasse 29 4410 Liestal. Postfach",
    "sg:city":"Liestal",
    "sg:orig_category":"Unternehmensberatung",
    "sg:postcode":"4410",
    "sg:province":"Basel-Landschaft",
    "wof:name":"Sinzig Carmela",
    "wof:placetype":"venue"
},
  "geometry": {"coordinates":[7.7364420891,47.4879722595],"type":"Point"}
}