{
  "type": "Feature",
  "properties": {
    "iso:country":"CH",
    "sg:address":"Dienerstrasse 29",
    "sg:city":"Z\u00fcrich",
    "sg:orig_category":"Grosshandel mit Getr\u00e4nken Grosshandel mit Wein U Spirituosen",
    "sg:phone":"+41 12404940",
    "sg:postcode":"8004",
    "sg:province":"Z\u00fcrich",
    "wof:name":"Gusto Mondial Gmbh",
    "wof:placetype":"venue"
},
  "geometry": {"coordinates":[8.5274124146,47.3781051636],"type":"Point"}
}