{
  "type": "Feature",
  "properties": {
    "iso:country":"CH",
    "sg:address":"Leinb\u00fctzen",
    "sg:city":"R\u00fcegsau",
    "sg:orig_category":"Verwertung von Milch",
    "sg:phone":"+41 32 652 41 51",
    "sg:postcode":"3417",
    "sg:province":"Bern",
    "wof:name":"K\u00e4sereigenossenschaft Lengnau",
    "wof:placetype":"venue"
},
  "geometry": {"coordinates":[7.366147995,47.1825714111],"type":"Point"}
}