{
  "type": "Feature",
  "properties": {
    "iso:country":"CH",
    "sg:address":"S\u00e4gebachweg 28",
    "sg:city":"Oberwichtrach",
    "sg:orig_category":"Herstellung von sonstigen Metallwaren Stahl U Leichtmetallbau",
    "sg:phone":"+41 41 498 01 30",
    "sg:postcode":"3114",
    "sg:province":"Bern",
    "wof:name":"Mak Metall Und Blechbearbeitung Gmbh Metallwaren; Produktion, Handel Usw",
    "wof:placetype":"venue"
},
  "geometry": {"coordinates":[8.1827249527,47.0368156433],"type":"Point"}
}