{
  "type": "Feature",
  "properties": {
    "iso:country":"CH",
    "sg:address":"R\u00fctiweid 8 6340 Baar. Postfach",
    "sg:city":"Baar",
    "sg:orig_category":"Sonstige mit der Informatik verbundene T\u00e4tigkeiten",
    "sg:postcode":"6340",
    "sg:province":"Zug",
    "wof:name":"Eightcom Gmbh",
    "wof:placetype":"venue"
},
  "geometry": {"coordinates":[8.5306472778,47.1754188538],"type":"Point"}
}