{
  "type": "Feature",
  "properties": {
    "iso:country":"CH",
    "sg:address":"Aarburgerstrasse 88",
    "sg:city":"Olten",
    "sg:orig_category":"Werbegrafikateliers",
    "sg:phone":"+41 62 296 53 80",
    "sg:postcode":"4600",
    "sg:province":"Solothurn",
    "wof:name":"Josef Schelbert Wissenschaftliches Zeichnen",
    "wof:placetype":"venue"
},
  "geometry": {"coordinates":[7.9067759514,47.3453674316],"type":"Point"}
}