{
  "type": "Feature",
  "properties": {
    "iso:country":"CH",
    "sg:address":"Curt Goetz-strasse 21",
    "sg:city":"Binningen",
    "sg:classifiers":[
        {
            "category":"Education",
            "subcategory":"Library",
            "type":"Public Place"
        }
    ],
    "sg:phone":"+41 61 421 40 41",
    "sg:postcode":"4102",
    "sg:province":"Basel-Landschaft",
    "sg:tags":[
        "u",
        "bibliotheken",
        "archive"
    ],
    "wof:name":"Ludothek Familienzentrum",
    "wof:placetype":"venue"
},
  "geometry": {"coordinates":[7.574888,47.54026],"type":"Point"}
}