{
  "type": "Feature",
  "properties": {
    "iso:country":"CH",
    "sg:address":"Bielstrasse 7 4512 Bellach. Postfach",
    "sg:city":"Bellach",
    "sg:orig_category":"Herstellung von Metallerzeugnissen ohne Maschinenbau",
    "sg:phone":"+41 79 209 98 25",
    "sg:postcode":"4512",
    "sg:province":"Solothurn",
    "wof:name":"Hilpertshauser Ag Metallwaren",
    "wof:placetype":"venue"
},
  "geometry": {"coordinates":[9.2117004395,47.4424667358],"type":"Point"}
}