{
  "type": "Feature",
  "properties": {
    "iso:country":"CH",
    "sg:address":"Lungolago Roncaioli",
    "sg:city":"Brusino Arsizio",
    "sg:classifiers":[
        {
            "category":"Banks & Credit Unions",
            "subcategory":"Bank",
            "type":"Services"
        }
    ],
    "sg:phone":"+41 91 996 10 13",
    "sg:postcode":"6827",
    "sg:province":"Ticino",
    "wof:name":"Raiffeisen Di Brusino Arsizio",
    "wof:placetype":"venue"
},
  "geometry": {"coordinates":[8.93759,45.929363],"type":"Point"}
}