{
  "type": "Feature",
  "properties": {
    "iso:country":"CH",
    "sg:address":"Bremgartnerstrasse 87 8953 Dietikon. Postfach 8050 Z\u00fcrich",
    "sg:city":"Zust",
    "sg:orig_category":"Herstellung von Dauerbackwaren",
    "sg:postcode":"50",
    "wof:name":"Meierhofer's Gipfeli-kurier Backwaren, Lebensmittel; Verkauf",
    "wof:placetype":"venue"
},
  "geometry": {"coordinates":[8.3990678787,47.3975219727],"type":"Point"}
}