{
  "type": "Feature",
  "properties": {
    "iso:country":"CH",
    "sg:address":"Oberdorf 24",
    "sg:city":"Beringen",
    "sg:orig_category":"Herstellung von k\u00e4lte U lufttechnischen Erzeugnissen f\u00fcr gewerbliche Zwecke",
    "sg:phone":"+41 52 685 18 26",
    "sg:postcode":"8222",
    "sg:province":"Schaffhausen",
    "wof:name":"Dellenbach Hans",
    "wof:placetype":"venue"
},
  "geometry": {"coordinates":[8.5741949081,47.6992874146],"type":"Point"}
}