{
  "type": "Feature",
  "properties": {
    "iso:country":"CH",
    "sg:address":"Waldeggstrasse 46",
    "sg:city":"Emmenbr\u00fccke",
    "sg:orig_category":"Primarschulen",
    "sg:postcode":"6020",
    "sg:province":"Luzern",
    "wof:name":"Primarschule H\u00fcbeli",
    "wof:placetype":"venue"
},
  "geometry": {"coordinates":[8.2744865417,47.0853118896],"type":"Point"}
}