{
  "type": "Feature",
  "properties": {
    "iso:country":"CH",
    "sg:address":"Floraweg 2 6003 Luzern. Postfach",
    "sg:city":"Luzern",
    "sg:orig_category":"Fernmeldedienste",
    "sg:phone":"+41 32 321 37 37",
    "sg:postcode":"6002",
    "sg:province":"Luzern",
    "wof:name":"Swisscom Directories Ag",
    "wof:placetype":"venue"
},
  "geometry": {"coordinates":[7.2413659096,47.1342658997],"type":"Point"}
}