{
  "type": "Feature",
  "properties": {
    "iso:country":"CH",
    "sg:address":"Thunstrasse 100",
    "sg:city":"Spiez",
    "sg:orig_category":"Blumen U Zierpflanzenbau",
    "sg:phone":"+41 33 654 41 54",
    "sg:postcode":"3700",
    "sg:province":"Bern",
    "wof:name":"Scheidegger Christian, G\u00e4rtnerei Und Blumen-atelier Spiez",
    "wof:placetype":"venue"
},
  "geometry": {"coordinates":[7.664035,46.694183],"type":"Point"}
}