{
  "type": "Feature",
  "properties": {
    "iso:country":"CH",
    "sg:address":"Hertensteinstrasse 12",
    "sg:city":"Hertenstein",
    "sg:orig_category":"Softwareentwicklung U beratung",
    "sg:phone":"+41 41 392 70 80",
    "sg:postcode":"6353",
    "sg:province":"Luzern",
    "wof:name":"Schmedding Software Systeme Gmbh",
    "wof:placetype":"venue"
},
  "geometry": {"coordinates":[8.4075517654,47.030090332],"type":"Point"}
}