{
  "type": "Feature",
  "properties": {
    "iso:country":"CH",
    "sg:address":"Albisblick 43",
    "sg:city":"Allenwinden",
    "sg:orig_category":"Softwareentwicklung U beratung",
    "sg:phone":"+41 41 712 13 65",
    "sg:postcode":"6319",
    "sg:province":"Zug",
    "wof:name":"Emk Topware Software F\u00fcr Kinder",
    "wof:placetype":"venue"
},
  "geometry": {"coordinates":[8.5549783707,47.1635665894],"type":"Point"}
}