{
  "type": "Feature",
  "properties": {
    "iso:country":"CH",
    "sg:address":"Rue Saint-pierre 8",
    "sg:city":"Fribourg",
    "sg:orig_category":"Wohnheime",
    "sg:postcode":"1700",
    "sg:province":"Fribourg",
    "wof:name":"Fondation Pour La Formation Continue Des Personnes Handicap\u00e9es Adultes",
    "wof:placetype":"venue"
},
  "geometry": {"coordinates":[7.1552848816,46.8037796021],"type":"Point"}
}