{
  "type": "Feature",
  "properties": {
    "iso:country":"CH",
    "sg:address":"Bergackerweg 1",
    "sg:city":"Sch\u00fcpfen",
    "sg:orig_category":"Detailhandel mit Fleisch U Fleischwaren",
    "sg:phone":"+41 62 929 11 65",
    "sg:postcode":"3054",
    "sg:province":"Bern",
    "wof:name":"Hans Strahm Metzgerei",
    "wof:placetype":"venue"
},
  "geometry": {"coordinates":[7.8200068474,47.2423782349],"type":"Point"}
}