{
  "type": "Feature",
  "properties": {
    "iso:country":"CH",
    "sg:address":"Route De France 31 1875 Morgins. Postfach",
    "sg:city":"Morgins",
    "sg:orig_category":"Unclassifiable Establishments",
    "sg:phone":"+41 24 477 18 27",
    "sg:postcode":"1875",
    "sg:province":"Valais",
    "wof:name":"Gollut Christophe Et Rudy S\u00e0rl",
    "wof:placetype":"venue"
},
  "geometry": {"coordinates":[6.8524179459,46.2369232178],"type":"Point"}
}