{
  "type": "Feature",
  "properties": {
    "iso:country":"CH",
    "sg:address":"Z\u00fcrichstrasse 148",
    "sg:city":"K\u00fcsnacht",
    "sg:classifiers":[
        {
            "category":"Utilities",
            "subcategory":"Cable",
            "type":"Services"
        }
    ],
    "sg:phone":"+41 19101622",
    "sg:postcode":"8700",
    "sg:province":"Z\u00fcrich",
    "sg:tags":[
        "measuring",
        "defect",
        "devices",
        "detection",
        "unit",
        "locating"
    ],
    "wof:name":"H. Fr\u00f6hlich Ag",
    "wof:placetype":"venue"
},
  "geometry": {"coordinates":[8.580888,47.320309],"type":"Point"}
}