{
  "type": "Feature",
  "properties": {
    "iso:country":"CH",
    "sg:address":"Gurzelngasse 27",
    "sg:city":"Solothurn",
    "sg:orig_category":"Wirtschaftsverb\u00e4nde Industrie, Handel and Gewerbe",
    "sg:phone":"+41 32 623 86 70",
    "sg:postcode":"4500",
    "sg:province":"Solothurn",
    "wof:name":"Schw.verb.d.innendekorat.des M\u00f6belfachhandels & D.sattler",
    "wof:placetype":"venue"
},
  "geometry": {"coordinates":[7.5355148315,47.2078933716],"type":"Point"}
}