{
  "type": "Feature",
  "properties": {
    "iso:country":"CH",
    "sg:address":"Br\u00fcnnenstrasse 66",
    "sg:city":"Bern",
    "sg:orig_category":"Unclassifiable Establishments",
    "sg:postcode":"3018",
    "sg:province":"Bern",
    "wof:name":"Neopost Industrie Ag",
    "wof:placetype":"venue"
},
  "geometry": {"coordinates":[7.3863840103,46.943107605],"type":"Point"}
}