{
  "type": "Feature",
  "properties": {
    "iso:country":"CH",
    "sg:address":"Aarauerstrasse 51",
    "sg:city":"Olten",
    "sg:orig_category":"Spielsalons",
    "sg:phone":"+41 62 771 88 61",
    "sg:postcode":"4600",
    "sg:province":"Solothurn",
    "wof:name":"Spielsalon Tiffany",
    "wof:placetype":"venue"
},
  "geometry": {"coordinates":[8.1859607697,47.249797821],"type":"Point"}
}