{
  "type": "Feature",
  "properties": {
    "iso:country":"CH",
    "sg:address":"Dorfstrasse",
    "sg:city":"Linthal",
    "sg:classifiers":[
        {
            "category":"Travel",
            "subcategory":"Hotels & Motels",
            "type":"Entertainment"
        }
    ],
    "sg:phone":"+41 56 633 13 34",
    "sg:postcode":"8783",
    "sg:province":"Glarus",
    "sg:tags":[
        "hotels",
        "mit",
        "restaurant"
    ],
    "wof:name":"Hotel-restaurant Adler Rolf Bl\u00e4ttler",
    "wof:placetype":"venue"
},
  "geometry": {"coordinates":[8.3403892517,47.3507080078],"type":"Point"}
}