{
  "type": "Feature",
  "properties": {
    "iso:country":"CH",
    "sg:address":"Chemin Du Montillier 3 1009 Pully Case Postale 43",
    "sg:city":"Pully",
    "sg:orig_category":"Verwaltung von Immobilien Wirtschaftspr\u00fcfung, Steuerberatung U Treuhand",
    "sg:phone":"+41 21 728 88 01",
    "sg:postcode":"1009",
    "sg:province":"Vaud",
    "wof:name":"Burkhalter Et Partenaires Sa",
    "wof:placetype":"venue"
},
  "geometry": {"coordinates":[6.6583771706,46.513584137],"type":"Point"}
}