{
  "type": "Feature",
  "properties": {
    "iso:country":"CH",
    "sg:address":"R\u00fctistrasse 2c",
    "sg:city":"Adliswil",
    "sg:orig_category":"Innendekorationsateliers",
    "sg:phone":"+41 17101522",
    "sg:postcode":"8134",
    "sg:province":"Z\u00fcrich",
    "wof:name":"Ren\u00e9 St\u00e4hlin Interior Design",
    "wof:placetype":"venue"
},
  "geometry": {"coordinates":[8.528096199,47.3060493469],"type":"Point"}
}