{
  "type": "Feature",
  "properties": {
    "iso:country":"CH",
    "sg:address":"Hauptstrasse",
    "sg:city":"K\u00fcblis",
    "sg:classifiers":[
        {
            "category":"Travel",
            "subcategory":"Hotels & Motels",
            "type":"Entertainment"
        }
    ],
    "sg:phone":"+41 81 332 12 08",
    "sg:postcode":"7240",
    "sg:province":"Graubunden",
    "sg:tags":[
        "hotels",
        "mit",
        "restaurant"
    ],
    "wof:name":"Reto Barblan",
    "wof:placetype":"venue"
},
  "geometry": {"coordinates":[9.7697753906,46.9135971069],"type":"Point"}
}