{
  "type": "Feature",
  "properties": {
    "iso:country":"CH",
    "sg:address":"Sonnhaldenweg 13",
    "sg:city":"Herisau",
    "sg:orig_category":"Softwareentwicklung U beratung",
    "sg:phone":"+41 71 351 48 72",
    "sg:postcode":"9100",
    "sg:province":"Appenzell Ausserrhoden",
    "wof:name":"Schiess-engineering",
    "wof:placetype":"venue"
},
  "geometry": {"coordinates":[9.2714853287,47.3926010132],"type":"Point"}
}