{
  "type": "Feature",
  "properties": {
    "iso:country":"CH",
    "sg:address":"Rue Des Moulins",
    "sg:city":"Fleurier",
    "sg:orig_category":"Pensionskassen",
    "sg:phone":"+41 32 861 10 34",
    "sg:postcode":"2114",
    "sg:province":"Neuch\u00e2tel",
    "wof:name":"Fonds De Pr\u00e9voyance En Faveur Du Personnel De La Sic Soci\u00e9t\u00e9 Industrielle Du Caoutchouc",
    "wof:placetype":"venue"
},
  "geometry": {"coordinates":[6.5830779076,46.9033546448],"type":"Point"}
}