{
  "type": "Feature",
  "properties": {
    "iso:country":"CH",
    "sg:address":"Obstgartenstrasse 22 8136 Gattikon. Postfach",
    "sg:city":"Gattikon",
    "sg:orig_category":"Architektur U Ingenieurb\u00fcros",
    "sg:phone":"+41 17206444",
    "sg:postcode":"8136",
    "sg:province":"Z\u00fcrich",
    "wof:name":"Stehlin Thierry Dipl. Ing. Ethz Structural Analysis Office",
    "wof:placetype":"venue"
},
  "geometry": {"coordinates":[8.549322,47.283394],"type":"Point"}
}