{
  "type": "Feature",
  "properties": {
    "iso:country":"CH",
    "sg:address":"Althardstrasse 9",
    "sg:city":"Regensdorf",
    "sg:orig_category":"Herstellung von Gummi U Kunststoffwaren Herstellung von Metallerzeugnissen ohne Maschinenbau",
    "sg:phone":"+41 18403626",
    "sg:postcode":"8105",
    "sg:province":"Z\u00fcrich",
    "wof:name":"Compark Ag",
    "wof:placetype":"venue"
},
  "geometry": {"coordinates":[8.4726324081,47.4365844727],"type":"Point"}
}