{
  "type": "Feature",
  "properties": {
    "iso:country":"CH",
    "sg:address":"Schafmattweg 31",
    "sg:city":"Binningen",
    "sg:orig_category":"Sonstige Aktivit\u00e4ten der nicht-\u00e4rztlichen Medizinalberufe",
    "sg:phone":"+41 61 421 94 04",
    "sg:postcode":"4102",
    "sg:province":"Basel-Landschaft",
    "wof:name":"Werner Saladin Kinesiologie & Massage-praxis",
    "wof:placetype":"venue"
},
  "geometry": {"coordinates":[7.5720682144,47.5346488953],"type":"Point"}
}