{
  "type": "Feature",
  "properties": {
    "iso:country":"CH",
    "sg:address":"Rebenweg 50",
    "sg:city":"Gampelen",
    "sg:orig_category":"Architekturb\u00fcros",
    "sg:phone":"+41 32 313 15 92",
    "sg:postcode":"3236",
    "sg:province":"Bern",
    "wof:name":"Paul Gutmann Architekturb\u00fcro",
    "wof:placetype":"venue"
},
  "geometry": {"coordinates":[7.04681,47.018581],"type":"Point"}
}