{
  "type": "Feature",
  "properties": {
    "iso:country":"CH",
    "sg:address":"Baselstrasse 48 4242 Laufen. Postfach",
    "sg:city":"Laufen",
    "sg:orig_category":"Autogaragen Tankstellen",
    "sg:phone":"+41 61 761 13 84",
    "sg:postcode":"4242",
    "sg:province":"Basel-Landschaft",
    "wof:name":"Drive-in Automobile Ag Shell Laufen",
    "wof:placetype":"venue"
},
  "geometry": {"coordinates":[7.504326,47.423615],"type":"Point"}
}