{
  "type": "Feature",
  "properties": {
    "iso:country":"CH",
    "sg:address":"Les Collond\u00e9s 6",
    "sg:city":"L'abbaye",
    "sg:orig_category":"Sportvereine Sch\u00fctzen Bogen",
    "sg:postcode":"1344",
    "sg:province":"Vaud",
    "wof:name":"Les Archers De Joux L'abbaye",
    "wof:placetype":"venue"
},
  "geometry": {"coordinates":[6.3157010078,46.6480026245],"type":"Point"}
}