{
  "type": "Feature",
  "properties": {
    "iso:country":"CH",
    "sg:address":"Trichtenhausenstrasse 39",
    "sg:city":"Z\u00fcrich",
    "sg:orig_category":"Maler U Glasergewerbe",
    "sg:phone":"+41 14220144",
    "sg:postcode":"8053",
    "sg:province":"Z\u00fcrich",
    "wof:name":"Riccardo Berardelli, Z\u00fcrich Malergesch\u00e4ft, Fassadenrenovationen.",
    "wof:placetype":"venue"
},
  "geometry": {"coordinates":[8.5973987579,47.3575286865],"type":"Point"}
}