{
  "type": "Feature",
  "properties": {
    "iso:country":"CH",
    "sg:address":"H\u00fchnerhubelstrasse 62 3123 Belp. Postfach",
    "sg:city":"Belp",
    "sg:orig_category":"Herstellung von Duft U K\u00f6rperpflegemitteln",
    "sg:phone":"+41 31 818 12 28",
    "sg:postcode":"3123",
    "sg:province":"Bern",
    "wof:name":"Apiana Trading, Inhaber Ernst A. Schenk",
    "wof:placetype":"venue"
},
  "geometry": {"coordinates":[7.4954352379,46.9047279358],"type":"Point"}
}