{
  "type": "Feature",
  "properties": {
    "iso:country":"CH",
    "sg:address":"Rathausplatz 3 6370 Stans. Postfach",
    "sg:city":"Stans",
    "sg:orig_category":"Unclassifiable Establishments",
    "sg:postcode":"6370",
    "sg:province":"Nidwalden",
    "wof:name":"Connectpeople24.com Ag Dienstleistungen In Den Bereichen Allg. Kommunikation, Internet, Tele, Satelliten- U. Tv-kommunikation Usw",
    "wof:placetype":"venue"
},
  "geometry": {"coordinates":[8.3666067123,46.9560012817],"type":"Point"}
}