{
  "type": "Feature",
  "properties": {
    "iso:country":"CH",
    "sg:address":"6537 Grono. Postfach",
    "sg:city":"Grono",
    "sg:orig_category":"Unclassifiable Establishments",
    "sg:postcode":"6537",
    "sg:province":"Graubunden",
    "wof:name":"Ord-ix ' Net",
    "wof:placetype":"venue"
},
  "geometry": {"coordinates":[6.4722399712,46.6157417297],"type":"Point"}
}