{
  "type": "Feature",
  "properties": {
    "iso:country":"CH",
    "sg:address":"Unterdorf 9 4203 Grellingen. Postfach",
    "sg:city":"Grellingen",
    "sg:orig_category":"Druckweiterverarbeitung",
    "sg:postcode":"4203",
    "sg:province":"Basel-Landschaft",
    "wof:name":"Spatium 37 Kim Vreni",
    "wof:placetype":"venue"
},
  "geometry": {"coordinates":[7.5884451866,47.4407501221],"type":"Point"}
}