{
  "type": "Feature",
  "properties": {
    "iso:country":"CH",
    "sg:address":"Watterstrasse 81 8105 Regensdorf. Postfach 534",
    "sg:city":"Regensdorf",
    "sg:orig_category":"Vermittlung von Immobilien Verwaltung von Immobilien",
    "sg:phone":"+41 31 952 72 32",
    "sg:postcode":"8105",
    "sg:province":"Z\u00fcrich",
    "wof:name":"Elisabeth Kellenberger Liegenschaftenhandel",
    "wof:placetype":"venue"
},
  "geometry": {"coordinates":[7.4865818024,46.9304733276],"type":"Point"}
}