{
  "type": "Feature",
  "properties": {
    "addr:full":"Spalenring 17 Basel Basel-Stadt 4055",
    "addr:housenumber":"17",
    "addr:postcode":"4055",
    "addr:street":"Spalenring",
    "iso:country":"CH",
    "sg:address":"Spalenring 17",
    "sg:city":"Basel",
    "sg:orig_category":"Arztpraxen",
    "sg:phone":"+41 61 381 43 43",
    "sg:postcode":"4055",
    "sg:province":"Basel-Stadt",
    "wof:name":"Dr.med.peter D\u00e4twyler Spezialarzt",
    "wof:placetype":"venue"
},
  "geometry": {"coordinates":[7.574407,47.560806],"type":"Point"}
}