{
  "type": "Feature",
  "properties": {
    "addr:full":"Dreik\u00f6nigstr. 6 Z\u00fcrich Z\u00fcrich 8022",
    "addr:housenumber":"6",
    "addr:postcode":"8022",
    "addr:street":"Dreikoenigstr.",
    "iso:country":"CH",
    "sg:address":"Dreik\u00f6nigstr. 6",
    "sg:city":"Z\u00fcrich",
    "sg:classifiers":[
        {
            "category":"Banks & Credit Unions",
            "subcategory":"Bank",
            "type":"Services"
        }
    ],
    "sg:postcode":"8022",
    "sg:province":"Z\u00fcrich",
    "wof:name":"Bankers Trust Ag",
    "wof:placetype":"venue"
},
  "geometry": {"coordinates":[8.529911,47.370831],"type":"Point"}
}