{
  "type": "Feature",
  "properties": {
    "iso:country":"CH",
    "sg:address":"Wiesenstrasse 5 8008 Z\u00fcrich. Postfach",
    "sg:city":"Z\u00fcrich",
    "sg:orig_category":"Architektur U Ingenieurb\u00fcros",
    "sg:postcode":"8001",
    "sg:province":"Z\u00fcrich",
    "wof:name":"Anzevui & Deville, Architectes Associ\u00e9s",
    "wof:placetype":"venue"
},
  "geometry": {"coordinates":[6.141425,46.183311],"type":"Point"}
}