{
  "type": "Feature",
  "properties": {
    "addr:full":"Rue Du Bassin 2 Neuenburg Neuch\u00e2tel 2000",
    "addr:housenumber":"2",
    "addr:postcode":"2000",
    "addr:street":"Rue Du Bassin",
    "iso:country":"CH",
    "sg:address":"Rue Du Bassin 2",
    "sg:city":"Neuenburg",
    "sg:orig_category":"Detailhandel mit Bekleidung Detailhandel mit Damenbekleidung",
    "sg:phone":"+41 32 724 08 86",
    "sg:postcode":"2000",
    "sg:province":"Neuch\u00e2tel",
    "wof:name":"Boutique Mary-claire, Mary-claire Verdan",
    "wof:placetype":"venue"
},
  "geometry": {"coordinates":[6.929817,46.991047],"type":"Point"}
}