{
  "type": "Feature",
  "properties": {
    "iso:country":"CH",
    "sg:address":"Schaanerstrasse 114 9494 Schaan. Postfach 563",
    "sg:city":"Schaan",
    "sg:classifiers":[
        {
            "category":"Government",
            "subcategory":"Post Office",
            "type":"Public Place"
        }
    ],
    "sg:phone":"+41 75 232 57 10",
    "sg:postcode":"9494",
    "sg:tags":[
        "caf\u00e9s",
        "tea-rooms"
    ],
    "wof:name":"Caf\u00e9 Forum",
    "wof:placetype":"venue"
},
  "geometry": {"coordinates":[9.506819725,47.1569404602],"type":"Point"}
}