{
  "type": "Feature",
  "properties": {
    "addr:full":"Villars Route De 31 Fribourg Fribourg 1700",
    "addr:housenumber":"31",
    "addr:postcode":"1700",
    "addr:street":"Route De",
    "iso:country":"CH",
    "sg:address":"Villars Route De 31",
    "sg:city":"Fribourg",
    "sg:orig_category":"Betrieb von Taxis",
    "sg:phone":"+41 26 424 31 91",
    "sg:postcode":"1700",
    "sg:province":"Fribourg",
    "wof:name":"Pinto Artur",
    "wof:placetype":"venue"
},
  "geometry": {"coordinates":[7.153683,46.803745],"type":"Point"}
}