{
  "type": "Feature",
  "properties": {
    "iso:country":"CH",
    "sg:address":"Mitteldorfstrasse 88",
    "sg:city":"Ebnat-kappel",
    "sg:orig_category":"Hobel U Holzimpr\u00e4gnierwerke",
    "sg:phone":"+41 33 951 14 80",
    "sg:postcode":"9642",
    "sg:province":"St. Gallen",
    "wof:name":"Hans Anderfuhren Drechslerei",
    "wof:placetype":"venue"
},
  "geometry": {"coordinates":[8.0745048523,46.7537231445],"type":"Point"}
}