{
  "type": "Feature",
  "properties": {
    "iso:country":"CH",
    "sg:address":"5503",
    "sg:city":"Schafisheim",
    "sg:orig_category":"Vereine Vogel-& Naturschutz",
    "sg:postcode":"5503",
    "sg:province":"Aargau",
    "wof:name":"Vogelschutzverein",
    "wof:placetype":"venue"
},
  "geometry": {"coordinates":[8.1427593231,47.3769226074],"type":"Point"}
}