{
  "type": "Feature",
  "properties": {
    "iso:country":"CH",
    "sg:address":"Zielstrasse 50",
    "sg:city":"Appenzell",
    "sg:orig_category":"Autogaragen Instandhaltung U Reparatur von Automobilen",
    "sg:phone":"+41 56 493 40 44",
    "sg:postcode":"9050",
    "sg:province":"Appenzell Innerhoden",
    "wof:name":"Bauer Andreas Automobile Autogarage, Spenglerei, Spritzwerk",
    "wof:placetype":"venue"
},
  "geometry": {"coordinates":[8.293276,47.449108],"type":"Point"}
}