{
  "type": "Feature",
  "properties": {
    "iso:country":"CH",
    "sg:address":"Reinacherstrasse 121-125 4053 Basel. Postfach",
    "sg:city":"Basel",
    "sg:orig_category":"Pensionskassen",
    "sg:postcode":"4053",
    "sg:province":"Basel-Stadt",
    "wof:name":"Jean Keller-st\u00fcnzi Stiftung",
    "wof:placetype":"venue"
},
  "geometry": {"coordinates":[7.6046390533,47.5364646912],"type":"Point"}
}