{
  "type": "Feature",
  "properties": {
    "iso:country":"CH",
    "sg:address":"Hauptstrasse 11",
    "sg:city":"Binningen",
    "sg:orig_category":"Arztpraxen",
    "sg:phone":"+41 61 423 70 00",
    "sg:postcode":"4102",
    "sg:province":"Basel-Landschaft",
    "wof:name":"Pd Dr.med. Daniel \u00e0 Wengen Spezialarzt Fmh",
    "wof:placetype":"venue"
},
  "geometry": {"coordinates":[7.575449,47.543228],"type":"Point"}
}