{
  "type": "Feature",
  "properties": {
    "iso:country":"CH",
    "sg:address":"Z\u00fcrcher Str. 53",
    "sg:city":"Unterengstringen",
    "sg:classifiers":[
        {
            "category":"Shopping",
            "subcategory":"Hobbies, Toys, & Games",
            "type":"Retail Goods"
        }
    ],
    "sg:phone":"+41 4117504644",
    "sg:postcode":"8103",
    "sg:province":"Z\u00fcrich",
    "sg:tags":[
        "product",
        "miscellaneous",
        "entertainment"
    ],
    "wof:name":"Musik G\u00dcnthart Ag",
    "wof:placetype":"venue"
},
  "geometry": {"coordinates":[8.4481935501,47.4137763977],"type":"Point"}
}