{
  "type": "Feature",
  "properties": {
    "iso:country":"CH",
    "sg:address":"Vallone Via 5",
    "sg:city":"Bellinzona",
    "sg:orig_category":"Sanit\u00e4r, Heizungs U L\u00fcftungsinstallation",
    "sg:phone":"+41 79 423 81 20",
    "sg:postcode":"6500",
    "sg:province":"Ticino",
    "wof:name":"Vignola Luigi",
    "wof:placetype":"venue"
},
  "geometry": {"coordinates":[9.0330972672,46.2028961182],"type":"Point"}
}