{
  "type": "Feature",
  "properties": {
    "iso:country":"CH",
    "sg:address":"Diemtigtalstrasse",
    "sg:city":"Oey",
    "sg:orig_category":"Vorschulen, Kinderg\u00e4rten",
    "sg:phone":"+41 71 877 11 30",
    "sg:postcode":"3753",
    "sg:province":"Bern",
    "wof:name":"Kindergarten",
    "wof:placetype":"venue"
},
  "geometry": {"coordinates":[9.4914493561,47.4160804749],"type":"Point"}
}