{
  "type": "Feature",
  "properties": {
    "addr:full":"Hauptstrasse 13 Tecknau Basel-Landschaft 4492",
    "addr:housenumber":"13",
    "addr:postcode":"4492",
    "addr:street":"Hauptstrasse",
    "iso:country":"CH",
    "sg:address":"Hauptstrasse 13",
    "sg:city":"Tecknau",
    "sg:orig_category":"Betrieb von Taxis",
    "sg:phone":"+41 61 981 37 61",
    "sg:postcode":"4492",
    "sg:province":"Basel-Landschaft",
    "wof:name":"Andreas & Samuel Nussbaumer Chauffeurdienste",
    "wof:placetype":"venue"
},
  "geometry": {"coordinates":[7.877479,47.454227],"type":"Point"}
}