{
  "type": "Feature",
  "properties": {
    "iso:country":"CH",
    "sg:address":"Rue De La Fontaine 7",
    "sg:city":"Bevaix",
    "sg:orig_category":"Vereine Camping",
    "sg:postcode":"2022",
    "sg:province":"Neuch\u00e2tel",
    "wof:name":"Camping-club",
    "wof:placetype":"venue"
},
  "geometry": {"coordinates":[6.8158202171,46.9306373596],"type":"Point"}
}