{
  "type": "Feature",
  "properties": {
    "iso:country":"CH",
    "sg:address":"Unterhof 1",
    "sg:city":"Lauerz",
    "sg:orig_category":"Fachdetailhandel in Verkaufsr\u00e4umen",
    "sg:postcode":"6424",
    "sg:province":"Schwyz",
    "wof:name":"Jl Joyce Trading",
    "wof:placetype":"venue"
},
  "geometry": {"coordinates":[8.7781352997,47.2013778687],"type":"Point"}
}