{
  "type": "Feature",
  "properties": {
    "iso:country":"CH",
    "sg:address":"Sonnenberg",
    "sg:city":"Oberembrach",
    "sg:orig_category":"Vereine Vogel-& Naturschutz",
    "sg:phone":"+41 18654150",
    "sg:postcode":"8425",
    "sg:province":"Z\u00fcrich",
    "wof:name":"Vogelschutzverein Oberembrach",
    "wof:placetype":"venue"
},
  "geometry": {"coordinates":[8.6246261597,47.4897193909],"type":"Point"}
}