{
  "type": "Feature",
  "properties": {
    "iso:country":"CH",
    "sg:address":"En Budron A 15",
    "sg:city":"Mont-sur-lausanne",
    "sg:orig_category":"Herstellung von Werkzeugen",
    "sg:phone":"+41 79 212 84 45",
    "sg:postcode":"1052",
    "sg:province":"Vaud",
    "wof:name":"Flora-mat S\u00e0rl",
    "wof:placetype":"venue"
},
  "geometry": {"coordinates":[6.6297330856,46.5709915161],"type":"Point"}
}