{
  "type": "Feature",
  "properties": {
    "iso:country":"CH",
    "sg:address":"Luzernerstrasse 14",
    "sg:city":"Cham",
    "sg:orig_category":"Unclassifiable Establishments",
    "sg:postcode":"6330",
    "sg:province":"Zug",
    "wof:name":"Restaurant Kreuz, Rolf Hartmann",
    "wof:placetype":"venue"
},
  "geometry": {"coordinates":[8.4584341049,47.1802101135],"type":"Point"}
}