{
  "type": "Feature",
  "properties": {
    "iso:country":"CH",
    "sg:address":"Grundstrasse 8",
    "sg:city":"Rotkreuz",
    "sg:orig_category":"Herstellung von Bereifungen",
    "sg:phone":"+41 41 850 00 44",
    "sg:postcode":"6343",
    "sg:province":"Zug",
    "wof:name":"Pronto Pneu Gmbh",
    "wof:placetype":"venue"
},
  "geometry": {"coordinates":[8.4303274155,47.1451263428],"type":"Point"}
}