{
  "type": "Feature",
  "properties": {
    "iso:country":"CH",
    "sg:address":"Unterer Frittenbach.",
    "sg:city":"Lauperswil",
    "sg:orig_category":"G\u00fcterbef\u00f6rderung im Strassenverkehr",
    "sg:postcode":"3438",
    "sg:province":"Bern",
    "wof:name":"Sommer & Co.",
    "wof:placetype":"venue"
},
  "geometry": {"coordinates":[7.763915062,46.9760055542],"type":"Point"}
}