{
  "type": "Feature",
  "properties": {
    "iso:country":"CH",
    "sg:address":"Wehntalerstrasse 113 8105 Regensdorf. Postfach 542",
    "sg:city":"Regensdorf",
    "sg:orig_category":"HERSTELLUNG VON GER\u00c4TEN DER ELEKTRIZIT\u00c4TSERZEUGUNG, -VERTEILUNG U.\u00c4 Herstellung von Kunststoffwaren",
    "sg:phone":"+41 18401128",
    "sg:postcode":"8105",
    "sg:province":"Z\u00fcrich",
    "wof:name":"Werit Kunststoffwerke Schneider H. & Co",
    "wof:placetype":"venue"
},
  "geometry": {"coordinates":[8.4733839035,47.439201355],"type":"Point"}
}