{
  "type": "Feature",
  "properties": {
    "iso:country":"CH",
    "sg:address":"Landhausstrasse 8",
    "sg:city":"St.gallen",
    "sg:orig_category":"Instandhaltung U Reparatur von Automobilen",
    "sg:phone":"+41 71 277 56 11",
    "sg:postcode":"9000",
    "sg:province":"St. Gallen",
    "wof:name":"Harry Heusser",
    "wof:placetype":"venue"
},
  "geometry": {"coordinates":[9.3526334763,47.4130973816],"type":"Point"}
}