{
  "type": "Feature",
  "properties": {
    "addr:full":"Oberdorfstrasse 15 Dietikon Z\u00fcrich 8953",
    "addr:housenumber":"15",
    "addr:postcode":"8953",
    "addr:street":"Oberdorfstrasse",
    "iso:country":"CH",
    "sg:address":"Oberdorfstrasse 15",
    "sg:city":"Dietikon",
    "sg:classifiers":[
        {
            "category":"Social Services",
            "subcategory":"Retirement Home",
            "type":"Services"
        }
    ],
    "sg:phone":"+41 17412443",
    "sg:postcode":"8953",
    "sg:province":"Z\u00fcrich",
    "sg:tags":[
        "pflegeheime",
        "u",
        "alters"
    ],
    "wof:name":"Alters-& Gesundheitszentrum Oberdorf Tagesheim",
    "wof:placetype":"venue"
},
  "geometry": {"coordinates":[8.39966,47.402058],"type":"Point"}
}