{
  "type": "Feature",
  "properties": {
    "iso:country":"CH",
    "sg:address":"Unterm\u00fcli 9",
    "sg:city":"Zug",
    "sg:orig_category":"Detailhandel mit Metallwaren, Anstrichmitteln, Glaswaren, Bau U Heimwerkerbedarf",
    "sg:phone":"+41 79 291 12 04",
    "sg:postcode":"6300",
    "sg:province":"Zug",
    "wof:name":"Ecotes Sa European Commercial And Technical Services",
    "wof:placetype":"venue"
},
  "geometry": {"coordinates":[8.5177631378,47.1804656982],"type":"Point"}
}