{
  "type": "Feature",
  "properties": {
    "iso:country":"CH",
    "sg:address":"Z\u00e4hringerstrasse 32",
    "sg:city":"Z\u00fcrich",
    "sg:orig_category":"Detailhandel mit M\u00f6beln Detailhandel mit M\u00f6beln U Haushaltsgegenst\u00e4nden",
    "sg:phone":"+41 22 343 09 30",
    "sg:postcode":"8001",
    "sg:province":"Z\u00fcrich",
    "wof:name":"Guy Graff Ameublement Style & Rustique",
    "wof:placetype":"venue"
},
  "geometry": {"coordinates":[6.1380448341,46.1761054993],"type":"Point"}
}