{
  "type": "Feature",
  "properties": {
    "iso:country":"CH",
    "sg:address":"Tumigerstrasse 26",
    "sg:city":"Greifensee",
    "sg:orig_category":"Sportvereine Fischerei",
    "sg:phone":"+41 19944075",
    "sg:postcode":"8606",
    "sg:province":"Z\u00fcrich",
    "wof:name":"Freier Fischereiverein Greifensee-schwerzenbach",
    "wof:placetype":"venue"
},
  "geometry": {"coordinates":[8.6804647446,47.3655128479],"type":"Point"}
}