{
  "type": "Feature",
  "properties": {
    "iso:country":"CH",
    "sg:address":"Granges-paccot Av. De 2 1700 Fribourg. Postfach",
    "sg:city":"Fribourg",
    "sg:orig_category":"Sonstige mit der Informatik verbundene T\u00e4tigkeiten",
    "sg:phone":"+41 26 465 13 58",
    "sg:postcode":"1702",
    "sg:province":"Fribourg",
    "wof:name":"Morandi Consultants Conseil En Informatique, S\u00e9curit\u00e9 Informatique Et Organisation",
    "wof:placetype":"venue"
},
  "geometry": {"coordinates":[7.1528320312,46.8124008179],"type":"Point"}
}