{
  "type": "Feature",
  "properties": {
    "iso:country":"CH",
    "sg:address":"Spirenwald",
    "sg:city":"Beatenberg",
    "sg:orig_category":"Bezirks, Sekundar, Realschulen, Oberstufe der Primarschulen",
    "sg:phone":"+41 33 841 12 02",
    "sg:postcode":"3803",
    "sg:province":"Bern",
    "wof:name":"Sekundarschule",
    "wof:placetype":"venue"
},
  "geometry": {"coordinates":[7.798255,46.699974],"type":"Point"}
}