{
  "type": "Feature",
  "properties": {
    "iso:country":"CH",
    "sg:address":"R\u00fctenenstrasse 57",
    "sg:city":"Beckenried",
    "sg:orig_category":"Gewinnung von Kies U Sand",
    "sg:phone":"+41 41 368 11 11",
    "sg:postcode":"6375",
    "sg:province":"Nidwalden",
    "wof:name":"Wabag Kies Ag",
    "wof:placetype":"venue"
},
  "geometry": {"coordinates":[8.4911603928,46.9624137878],"type":"Point"}
}