{
  "type": "Feature",
  "properties": {
    "iso:country":"CH",
    "sg:address":"Chorrichterhuus D\u00f6rfli 11",
    "sg:city":"Alchenstorf",
    "sg:orig_category":"Unclassifiable Establishments",
    "sg:postcode":"3473",
    "sg:province":"Bern",
    "wof:name":"Fatoris R\u00fcedi + Co",
    "wof:placetype":"venue"
},
  "geometry": {"coordinates":[7.6403398514,47.1247901917],"type":"Point"}
}