{
  "type": "Feature",
  "properties": {
    "iso:country":"CH",
    "sg:address":"Unterdorfstrasse 14",
    "sg:city":"Arch",
    "sg:orig_category":"Grosshandel mit Uhren",
    "sg:phone":"+41 32 679 24 42",
    "sg:postcode":"3296",
    "sg:province":"Bern",
    "wof:name":"Isaquartz Verkauf Von Uhrwerken",
    "wof:placetype":"venue"
},
  "geometry": {"coordinates":[7.4267969131,47.1689414978],"type":"Point"}
}