{
  "type": "Feature",
  "properties": {
    "iso:country":"CH",
    "sg:address":"Grand-rue 9",
    "sg:city":"Fleurier",
    "sg:orig_category":"Detailhandel mit S\u00e4uglings U Kinderbekleidung Herstellung von W\u00e4sche",
    "sg:phone":"+41 32 861 21 82",
    "sg:postcode":"2114",
    "sg:province":"Neuch\u00e2tel",
    "wof:name":"Jeunesse Mode, Gis\u00e8le Weissbrodt",
    "wof:placetype":"venue"
},
  "geometry": {"coordinates":[6.5826158524,46.9020576477],"type":"Point"}
}