{
  "type": "Feature",
  "properties": {
    "iso:country":"CH",
    "sg:address":"Z\u00fcrichstrasse 67",
    "sg:city":"Einsiedeln",
    "sg:orig_category":"Grosshandel mit sonstigen Maschinen U Ausr\u00fcstungen f\u00fcr Industrie, Handel U Schiffahrt",
    "sg:postcode":"8840",
    "sg:province":"Schwyz",
    "wof:name":"Landolt A., Einsiedeln",
    "wof:placetype":"venue"
},
  "geometry": {"coordinates":[8.745639801,47.1376113892],"type":"Point"}
}