{
  "type": "Feature",
  "properties": {
    "iso:country":"CH",
    "sg:address":"Hermolingen 25 6023 Rothenburg. Postfach",
    "sg:city":"Emmenbr\u00fccke",
    "sg:orig_category":"Stukkateurgewerbe, Gipserei U Verputzerei",
    "sg:postcode":"6020",
    "sg:province":"Luzern",
    "wof:name":"Spadea Gmbh",
    "wof:placetype":"venue"
},
  "geometry": {"coordinates":[8.2600698471,47.0935668945],"type":"Point"}
}