{
  "type": "Feature",
  "properties": {
    "iso:country":"CH",
    "sg:address":"6692",
    "sg:city":"Brontallo",
    "sg:orig_category":"Schulpflegen",
    "sg:postcode":"6692",
    "sg:province":"Ticino",
    "wof:name":"Delegazione Scolastica Del Comune Di Brontallo",
    "wof:placetype":"venue"
},
  "geometry": {"coordinates":[8.6263399124,46.3551292419],"type":"Point"}
}