{
  "type": "Feature",
  "properties": {
    "iso:country":"CH",
    "sg:address":"Amriswilerstrasse 25",
    "sg:city":"Weinfelden",
    "sg:orig_category":"Elektroinstallation",
    "sg:phone":"+41 55 647 34 34",
    "sg:postcode":"8570",
    "sg:province":"Thurgau",
    "wof:name":"K\u00e4ser Elektroanlagen",
    "wof:placetype":"venue"
},
  "geometry": {"coordinates":[9.0543012619,46.9784011841],"type":"Point"}
}