{
  "type": "Feature",
  "properties": {
    "iso:country":"CH",
    "sg:address":"Sportplatzweg 1",
    "sg:city":"M\u00f6nchaltorf",
    "sg:orig_category":"Non-Classified Establishments",
    "sg:phone":"+41 19481531",
    "sg:postcode":"8617",
    "sg:province":"Z\u00fcrich",
    "wof:name":"Blumen-paradies Gmbh",
    "wof:placetype":"venue"
},
  "geometry": {"coordinates":[8.7283468246,47.3077583313],"type":"Point"}
}