{
  "type": "Feature",
  "properties": {
    "iso:country":"CH",
    "sg:address":"Rheinparkstrasse 5",
    "sg:city":"Birsfelden",
    "sg:orig_category":"RESTAURANTS: TEA-ROOMS",
    "sg:phone":"+41 61 311 93 98",
    "sg:postcode":"4127",
    "sg:province":"Basel-Landschaft",
    "wof:name":"Restaurant Terrasse",
    "wof:placetype":"venue"
},
  "geometry": {"coordinates":[7.624145031,47.5571060181],"type":"Point"}
}