{
  "type": "Feature",
  "properties": {
    "iso:country":"CH",
    "sg:address":"Stitz",
    "sg:city":"Unterwasser",
    "sg:orig_category":"Interessenvertretungen Regionalbanken U Sparkassen",
    "sg:phone":"+41 71 999 12 15",
    "sg:postcode":"9657",
    "sg:province":"St. Gallen",
    "wof:name":"Stiftung Der Ersparnisanstalt Degersheim",
    "wof:placetype":"venue"
},
  "geometry": {"coordinates":[9.305977,47.196972],"type":"Point"}
}