{
  "type": "Feature",
  "properties": {
    "iso:country":"CH",
    "sg:address":"Avenue Du Temple 1",
    "sg:city":"Yvonand",
    "sg:orig_category":"Physiotherapie",
    "sg:phone":"+41 56 442 27 68",
    "sg:postcode":"1462",
    "sg:province":"Vaud",
    "wof:name":"Mechthild Hegener Physiotherapie",
    "wof:placetype":"venue"
},
  "geometry": {"coordinates":[8.2074680328,47.483745575],"type":"Point"}
}