{
  "type": "Feature",
  "properties": {
    "iso:country":"CH",
    "sg:address":"Limmatplatz 3",
    "sg:city":"Z\u00fcrich",
    "sg:orig_category":"RESTAURANTS: TEA-ROOMS",
    "sg:postcode":"8005",
    "sg:province":"Z\u00fcrich",
    "wof:name":"Tramacere Eleonore",
    "wof:placetype":"venue"
},
  "geometry": {"coordinates":[8.720700264,46.1460990906],"type":"Point"}
}