{
  "type": "Feature",
  "properties": {
    "iso:country":"CH",
    "sg:address":"Unterdorfstrasse 37",
    "sg:city":"Birr",
    "sg:orig_category":"Architektur U Ingenieurb\u00fcros",
    "sg:postcode":"5242",
    "sg:province":"Aargau",
    "wof:name":"Baldi O. Giessereitechnik",
    "wof:placetype":"venue"
},
  "geometry": {"coordinates":[8.204175,47.43676],"type":"Point"}
}