{
  "type": "Feature",
  "properties": {
    "iso:country":"CH",
    "sg:address":"Grossholzweg 9",
    "sg:city":"G\u00fcmligen",
    "sg:orig_category":"Wohnheime f\u00fcr Kinder U Jugendliche",
    "sg:phone":"+41 31 951 51 91",
    "sg:postcode":"3073",
    "sg:province":"Bern",
    "wof:name":"Kinderheim Tannhalde",
    "wof:placetype":"venue"
},
  "geometry": {"coordinates":[7.5076799393,46.9374046326],"type":"Point"}
}