{
  "type": "Feature",
  "properties": {
    "iso:country":"CH",
    "sg:address":"Juraweg 13 3053 M\u00fcnchenbuchsee. Postfach",
    "sg:city":"Zollikofen",
    "sg:orig_category":"Architektur U Ingenieurb\u00fcros",
    "sg:phone":"+41 31 869 65 60",
    "sg:postcode":"3052",
    "sg:province":"Bern",
    "wof:name":"Ingenieurb\u00fcro P. Kast",
    "wof:placetype":"venue"
},
  "geometry": {"coordinates":[7.454359,47.024555],"type":"Point"}
}