{
  "type": "Feature",
  "properties": {
    "iso:country":"CH",
    "sg:address":"La Tuili\u00e8re",
    "sg:city":"Vinzel",
    "sg:orig_category":"Rebbau",
    "sg:postcode":"1184",
    "sg:province":"Vaud",
    "wof:name":"Jean Straub Viticulteur",
    "wof:placetype":"venue"
},
  "geometry": {"coordinates":[6.2833271027,46.4478302002],"type":"Point"}
}