{
  "type": "Feature",
  "properties": {
    "iso:country":"CH",
    "sg:address":"Rebgasse 49",
    "sg:city":"Basel",
    "sg:orig_category":"Detailhandel mit Ton U Bildtr\u00e4gern Detailhandel mit elektrischen Haushalts-,Radio U Fernsehger\u00e4ten s",
    "sg:phone":"+41 61 681 92 40",
    "sg:postcode":"4058",
    "sg:province":"Basel-Stadt",
    "wof:name":"Music Paradise Perna N.",
    "wof:placetype":"venue"
},
  "geometry": {"coordinates":[7.5962400436,47.5594596863],"type":"Point"}
}