{
  "type": "Feature",
  "properties": {
    "iso:country":"CH",
    "sg:address":"Steinackerstrasse 38",
    "sg:city":"Urdorf",
    "sg:orig_category":"Innendekorationsateliers",
    "sg:phone":"+41 17343514",
    "sg:postcode":"8902",
    "sg:province":"Z\u00fcrich",
    "wof:name":"Ruth Zaugg Vorhangn\u00e4hservice",
    "wof:placetype":"venue"
},
  "geometry": {"coordinates":[8.424325943,47.3954811096],"type":"Point"}
}