{
  "type": "Feature",
  "properties": {
    "addr:full":"Eichwaldstrasse 5 6074 Giswil. Postfach 11 Giswil Obwalden 6074",
    "addr:housenumber":"5;11",
    "addr:postcode":"6074 giswil.;6074",
    "addr:street":"Eichwaldstrasse;Postfach",
    "iso:country":"CH",
    "sg:address":"Eichwaldstrasse 5 6074 Giswil. Postfach 11",
    "sg:city":"Giswil",
    "sg:orig_category":"Allgemeiner Hoch U Tiefbau Allgemeiner Hochbau",
    "sg:phone":"+41 41 666 30 20",
    "sg:postcode":"6074",
    "sg:province":"Obwalden",
    "wof:name":"Carl Garovi Ag Hoch-& Tiefbau",
    "wof:placetype":"venue"
},
  "geometry": {"coordinates":[8.171353,46.836624],"type":"Point"}
}