{
  "type": "Feature",
  "properties": {
    "iso:country":"CH",
    "sg:address":"Alpenweg 9",
    "sg:city":"Unterentfelden",
    "sg:orig_category":"Herstellung von sonstigen elektrischen Ausr\u00fcstungen",
    "sg:phone":"+41 62 723 76 43",
    "sg:postcode":"5035",
    "sg:province":"Aargau",
    "wof:name":"W. Amsler Engineering",
    "wof:placetype":"venue"
},
  "geometry": {"coordinates":[8.0398769379,47.3723182678],"type":"Point"}
}