{
  "type": "Feature",
  "properties": {
    "addr:full":"Hirschengraben 6 3011 Bern. Postfach Bern Bern 3001",
    "addr:housenumber":"6",
    "addr:postcode":"3011;postfach;3001",
    "addr:street":"Hirschengraben",
    "iso:country":"CH",
    "sg:address":"Hirschengraben 6 3011 Bern. Postfach",
    "sg:city":"Bern",
    "sg:orig_category":"Detailhandel mit B\u00fcchern Detailhandel mit Gebrauchtwaren in Verkaufsr\u00e4umen",
    "sg:phone":"+41 31 381 59 43",
    "sg:postcode":"3001",
    "sg:province":"Bern",
    "wof:name":"Buchantiquariat Iberia Jaime Romagosa Jun. Gebrauchte B\u00fccher U. Graphiken; Handel.",
    "wof:placetype":"venue"
},
  "geometry": {"coordinates":[7.437394,46.946671],"type":"Point"}
}