{
  "type": "Feature",
  "properties": {
    "iso:country":"CH",
    "sg:address":"Rue De La Grenade",
    "sg:city":"Aubonne",
    "sg:orig_category":"Sportvereine Ballsport Tischtennis",
    "sg:phone":"+41 21 808 58 77",
    "sg:postcode":"1170",
    "sg:province":"Vaud",
    "wof:name":"Ctt Bougy",
    "wof:placetype":"venue"
},
  "geometry": {"coordinates":[6.3907351494,46.496181488],"type":"Point"}
}