{
  "type": "Feature",
  "properties": {
    "iso:country":"CH",
    "sg:address":"Moosb\u00fchlstrasse 31",
    "sg:city":"Moosseedorf",
    "sg:orig_category":"Wohnheime",
    "sg:postcode":"3302",
    "sg:province":"Bern",
    "wof:name":"Verein Zur Schaffung Von Wohnm\u00f6glichkeiten F\u00fcr K\u00f6rperlich Behinderte (vswb)",
    "wof:placetype":"venue"
},
  "geometry": {"coordinates":[7.4867630005,47.0155410767],"type":"Point"}
}