{
  "type": "Feature",
  "properties": {
    "iso:country":"CH",
    "sg:address":"Rue Des Echutes 14",
    "sg:city":"Sion",
    "sg:orig_category":"Diskotheken, Dancings, Night Clubs",
    "sg:phone":"+41 27 203 55 98",
    "sg:postcode":"1950",
    "sg:province":"Valais",
    "wof:name":"Bar-disco-dancing Las-vegas",
    "wof:placetype":"venue"
},
  "geometry": {"coordinates":[7.3759450912,46.2362365723],"type":"Point"}
}