{
  "type": "Feature",
  "properties": {
    "iso:country":"CH",
    "sg:address":"B\u00fcelstrasse 3",
    "sg:city":"Baar",
    "sg:orig_category":"Non-Classified Establishments",
    "sg:postcode":"6340",
    "sg:province":"Zug",
    "wof:name":"Vino Ruskova Gmbh",
    "wof:placetype":"venue"
},
  "geometry": {"coordinates":[8.5284414291,47.1968421936],"type":"Point"}
}