{
  "type": "Feature",
  "properties": {
    "iso:country":"CH",
    "sg:address":"Chemin De Riettaz 7",
    "sg:city":"Bussigny-lausanne",
    "sg:orig_category":"Malerei Stukkateurgewerbe, Gipserei U Verputzerei",
    "sg:phone":"+41 21 701 19 64",
    "sg:postcode":"1030",
    "sg:province":"Vaud",
    "wof:name":"Terzi G. & Fils S\u00e0rl",
    "wof:placetype":"venue"
},
  "geometry": {"coordinates":[6.5587759018,46.552406311],"type":"Point"}
}