{
  "type": "Feature",
  "properties": {
    "iso:country":"CH",
    "sg:address":"Birkenweg 6",
    "sg:city":"Nidau",
    "sg:orig_category":"Vorschulen, Kinderg\u00e4rten",
    "sg:phone":"+41 32 331 86 83",
    "sg:postcode":"2560",
    "sg:province":"Bern",
    "wof:name":"Kindergarten Burgerbeunden",
    "wof:placetype":"venue"
},
  "geometry": {"coordinates":[7.2380719185,47.1198577881],"type":"Point"}
}