{
  "type": "Feature",
  "properties": {
    "iso:country":"CH",
    "sg:address":"4665",
    "sg:city":"Oftringen",
    "sg:orig_category":"Herstellung von sonstigen organischen Grundstoffen U Chemikalien",
    "sg:phone":"+41 62 789 29 29",
    "sg:postcode":"4665",
    "sg:province":"Aargau",
    "wof:name":"Tc Pl\u00fcss-staufer Ag Sfs Sektion Tennis",
    "wof:placetype":"venue"
},
  "geometry": {"coordinates":[7.9209251404,47.3165397644],"type":"Point"}
}