{
  "type": "Feature",
  "properties": {
    "iso:country":"CH",
    "sg:address":"Perche Chemin De La 2 2900 Porrentruy. Postfach",
    "sg:city":"Pruntrut",
    "sg:orig_category":"Pensionskassen",
    "sg:phone":"+41 32 466 58 12",
    "sg:postcode":"2900",
    "sg:province":"Jura",
    "wof:name":"Fondation De La Communaut\u00e9 Sociale Interprofessionnelle",
    "wof:placetype":"venue"
},
  "geometry": {"coordinates":[7.0782270432,47.4170303345],"type":"Point"}
}