{
  "type": "Feature",
  "properties": {
    "iso:country":"CH",
    "sg:address":"L\u00fcrlibadstrasse 118",
    "sg:city":"Chur",
    "sg:classifiers":[
        {
            "category":"Education",
            "subcategory":"Library",
            "type":"Public Place"
        }
    ],
    "sg:phone":"+41 62 918 55 55",
    "sg:postcode":"7000",
    "sg:province":"Graubunden",
    "sg:tags":[
        "u",
        "bibliotheken",
        "archive"
    ],
    "wof:name":"Kant.psychiatrische Klinik Bibliothek",
    "wof:placetype":"venue"
},
  "geometry": {"coordinates":[7.84173,47.232971],"type":"Point"}
}