{
  "type": "Feature",
  "properties": {
    "iso:country":"CH",
    "sg:address":"Seefeldstrasse 25 8008 Z\u00fcrich. Postfach 1075",
    "sg:city":"Z\u00fcrich",
    "sg:orig_category":"Wirtschaftsverb\u00e4nde Industrie, Handel and Gewerbe",
    "sg:phone":"+41 12618980",
    "sg:postcode":"8034",
    "sg:province":"Z\u00fcrich",
    "wof:name":"Stahlbau Zentrum Schweiz Szs",
    "wof:placetype":"venue"
},
  "geometry": {"coordinates":[8.549323082,47.3638381958],"type":"Point"}
}