{
  "type": "Feature",
  "properties": {
    "iso:country":"CH",
    "sg:address":"Centralstrasse 3 6410 Goldau. Postfach",
    "sg:city":"Goldau",
    "sg:orig_category":"RESTAURANTS: TEA-ROOMS",
    "sg:phone":"+41 27 923 03 09",
    "sg:postcode":"6410",
    "sg:province":"Schwyz",
    "wof:name":"Geiger C.",
    "wof:placetype":"venue"
},
  "geometry": {"coordinates":[6.9936571121,47.1510772705],"type":"Point"}
}