{
  "type": "Feature",
  "properties": {
    "iso:country":"CH",
    "sg:address":"Hausmattstrasse 6",
    "sg:city":"Sumiswald",
    "sg:orig_category":"Zahnarztpraxen",
    "sg:phone":"+41 34 431 12 05",
    "sg:postcode":"3454",
    "sg:province":"Bern",
    "wof:name":"Dr. Med. Dent. Martin Krebs Zahnarzt",
    "wof:placetype":"venue"
},
  "geometry": {"coordinates":[7.7421388626,47.0271110535],"type":"Point"}
}