{
  "type": "Feature",
  "properties": {
    "iso:country":"CH",
    "sg:address":"Bernstrasse 217 Zollikofen 3053 M\u00fcnchenbuchsee. Postfach",
    "sg:city":"Zollikofen",
    "sg:orig_category":"Architektur U Ingenieurb\u00fcros",
    "sg:postcode":"3052",
    "sg:province":"Bern",
    "wof:name":"Fumatsch Funke Ag",
    "wof:placetype":"venue"
},
  "geometry": {"coordinates":[7.450539,47.021427],"type":"Point"}
}