{
  "type": "Feature",
  "properties": {
    "iso:country":"CH",
    "sg:address":"Rue Des C\u00e8dres 2",
    "sg:city":"Sitten",
    "sg:orig_category":"Detailhandel mit Radio U Fernsehger\u00e4ten Detailhandel mit elektrischen Haushalts-,Radio U Fernsehger\u00e4",
    "sg:phone":"+41 71 911 03 39",
    "sg:postcode":"1950",
    "sg:province":"Valais",
    "wof:name":"Radio-tv Grob",
    "wof:placetype":"venue"
},
  "geometry": {"coordinates":[9.0456190109,47.4625930786],"type":"Point"}
}