{
  "type": "Feature",
  "properties": {
    "iso:country":"CH",
    "sg:address":"Bahnhofstrasse 21",
    "sg:city":"Interlaken",
    "sg:orig_category":"Detailhandel mit Blumen U Pflanzen",
    "sg:phone":"+41 33 822 12 33",
    "sg:postcode":"3800",
    "sg:province":"Bern",
    "wof:name":"Beat Ryffel Blumengesch\u00e4ft",
    "wof:placetype":"venue"
},
  "geometry": {"coordinates":[7.853083,46.684124],"type":"Point"}
}