{
  "type": "Feature",
  "properties": {
    "addr:full":"Schiltstrasse 38 Glarus Glarus 8750",
    "addr:housenumber":"38",
    "addr:postcode":"8750",
    "addr:street":"Schiltstrasse",
    "iso:country":"CH",
    "sg:address":"Schiltstrasse 38",
    "sg:city":"Glarus",
    "sg:orig_category":"Allgemeiner Hoch U Tiefbau",
    "sg:phone":"+41 32 328 88 88",
    "sg:postcode":"8750",
    "sg:province":"Glarus",
    "wof:name":"Bhm Bianchetti Hitzinger Meyer Ingenieure Und Planer Ag",
    "wof:placetype":"venue"
},
  "geometry": {"coordinates":[7.250361,47.143772],"type":"Point"}
}