{
  "type": "Feature",
  "properties": {
    "addr:full":"Spillstatt Grindelwald Bern 3818",
    "addr:postcode":"3818",
    "iso:country":"CH",
    "sg:address":"Spillstatt",
    "sg:city":"Grindelwald",
    "sg:classifiers":[
        {
            "category":"Banks & Credit Unions",
            "subcategory":"Bank",
            "type":"Services"
        }
    ],
    "sg:phone":"+41 36533939",
    "sg:postcode":"3818",
    "sg:province":"Bern",
    "wof:name":"Raiffeisenbank",
    "wof:placetype":"venue"
},
  "geometry": {"coordinates":[8.027288,46.626282],"type":"Point"}
}