{
  "type": "Feature",
  "properties": {
    "iso:country":"CH",
    "sg:address":"Route De Villars 24",
    "sg:city":"Fribourg",
    "sg:orig_category":"Sonstiger spezialisierter Hoch U Tiefbau",
    "sg:postcode":"1700",
    "sg:province":"Fribourg",
    "wof:name":"Castella J.l. Carrelage",
    "wof:placetype":"venue"
},
  "geometry": {"coordinates":[7.1402101517,46.800201416],"type":"Point"}
}