{
  "type": "Feature",
  "properties": {
    "iso:country":"CH",
    "sg:address":"Via Cantonale 78",
    "sg:city":"Riazzino",
    "sg:orig_category":"Instandhaltung U Reparatur von Automobilen R\u00fcckgewinnung U Vorbereitung f\u00fcr die Wiederverwertung Rec",
    "sg:phone":"+41 91 859 11 91",
    "sg:postcode":"6595",
    "sg:province":"Ticino",
    "wof:name":"Giuliani Mauro E Franchino",
    "wof:placetype":"venue"
},
  "geometry": {"coordinates":[8.8985834122,46.174282074],"type":"Point"}
}