{
  "type": "Feature",
  "properties": {
    "iso:country":"CH",
    "sg:address":"Chemin Colladon 24 1200 Gen\u00e8ve. Postfach",
    "sg:city":"Gen\u00e8ve",
    "sg:orig_category":"Unternehmensberatung",
    "sg:postcode":"1209",
    "sg:province":"Gen\u00e8ve",
    "wof:name":"Wallenberg Tsiklis D\u00e9sir\u00e9e",
    "wof:placetype":"venue"
},
  "geometry": {"coordinates":[6.1236867905,46.2233161926],"type":"Point"}
}