{
  "type": "Feature",
  "properties": {
    "iso:country":"CH",
    "sg:address":"Fleur-de-lys Rue De La 26 2074 Marin-centre. Postfach",
    "sg:city":"Epagnier",
    "sg:orig_category":"Fachdetailhandel mit pharmazeutischen Produkten",
    "sg:phone":"+41 26 436 15 66",
    "sg:postcode":"2074",
    "sg:province":"Neuch\u00e2tel",
    "wof:name":"Pharmacie De Marly-centre",
    "wof:placetype":"venue"
},
  "geometry": {"coordinates":[7.1618251801,46.7754707336],"type":"Point"}
}