{
  "type": "Feature",
  "properties": {
    "iso:country":"CH",
    "sg:address":"Route De Collex 199",
    "sg:city":"Collex",
    "sg:orig_category":"Gemeindeverwaltungen",
    "sg:phone":"+41 22 774 19 95",
    "sg:postcode":"1239",
    "sg:province":"Gen\u00e8ve",
    "wof:name":"Administration Communale De Collex-bossy",
    "wof:placetype":"venue"
},
  "geometry": {"coordinates":[6.1251358986,46.2720756531],"type":"Point"}
}