{
  "type": "Feature",
  "properties": {
    "iso:country":"CH",
    "sg:address":"Faucigny Rue P.-a.-de- 5",
    "sg:city":"Fribourg",
    "sg:orig_category":"Reiseb\u00fcros U Reiseveranstalter",
    "sg:phone":"+41 32 936 11 33",
    "sg:postcode":"1700",
    "sg:province":"Fribourg",
    "wof:name":"Protourisa",
    "wof:placetype":"venue"
},
  "geometry": {"coordinates":[6.7034168243,47.0131797791],"type":"Point"}
}