{
  "type": "Feature",
  "properties": {
    "iso:country":"CH",
    "sg:address":"Sch\u00f6nenhofstrasse 19",
    "sg:city":"Frauenfeld",
    "sg:orig_category":"Softwareentwicklung U beratung",
    "sg:phone":"+41 19751717",
    "sg:postcode":"8500",
    "sg:province":"Thurgau",
    "wof:name":"Spenger Christoph + Flor Ic Beratung - Informatik",
    "wof:placetype":"venue"
},
  "geometry": {"coordinates":[8.7688817978,47.3040237427],"type":"Point"}
}