{
  "type": "Feature",
  "properties": {
    "iso:country":"CH",
    "sg:address":"Kirchgasse 3 4144 Arlesheim. Postfach 627",
    "sg:city":"Arlesheim",
    "sg:orig_category":"Polizei",
    "sg:phone":"+41 61 701 13 13",
    "sg:postcode":"4144",
    "sg:province":"Basel-Landschaft",
    "wof:name":"Kantonaler Polizeiposten",
    "wof:placetype":"venue"
},
  "geometry": {"coordinates":[7.6212658882,47.4923324585],"type":"Point"}
}