{
  "type": "Feature",
  "properties": {
    "iso:country":"CH",
    "sg:address":"Baarerstrasse 21",
    "sg:city":"Zug",
    "sg:orig_category":"Unclassifiable Establishments",
    "sg:postcode":"6300",
    "sg:province":"Zug",
    "wof:name":"Aicons",
    "wof:placetype":"venue"
},
  "geometry": {"coordinates":[8.5161685944,47.1722869873],"type":"Point"}
}