{
  "type": "Feature",
  "properties": {
    "addr:full":"Hauptstrasse 23 Pieterlen Bern 2542",
    "addr:housenumber":"23",
    "addr:postcode":"2542",
    "addr:street":"Hauptstrasse",
    "iso:country":"CH",
    "sg:address":"Hauptstrasse 23",
    "sg:city":"Pieterlen",
    "sg:orig_category":"Detailhandel mit Beleuchtungs U Haushaltsgegenst\u00e4nden Detailhandel mit Geschenkartikeln U Souvenirs",
    "sg:phone":"+41 32 377 26 50",
    "sg:postcode":"2542",
    "sg:province":"Bern",
    "wof:name":"Porzellan-bijou Ursula Kirchmann",
    "wof:placetype":"venue"
},
  "geometry": {"coordinates":[7.335418,47.174706],"type":"Point"}
}