{
  "type": "Feature",
  "properties": {
    "iso:country":"CH",
    "sg:address":"R\u00e9sidence Vert-pr\u00e9 1141 S\u00e9very. Postfach",
    "sg:city":"S\u00e9very",
    "sg:orig_category":"Sonstige mit der Informatik verbundene T\u00e4tigkeiten",
    "sg:postcode":"1141",
    "sg:province":"Vaud",
    "wof:name":"Rm Services, Mottier Ren\u00e9",
    "wof:placetype":"venue"
},
  "geometry": {"coordinates":[6.4380950928,46.5761032104],"type":"Point"}
}