{
  "type": "Feature",
  "properties": {
    "iso:country":"CH",
    "sg:address":"Benzenschwilerstrasse 1",
    "sg:city":"Merenschwand",
    "sg:orig_category":"Herstellung von Baubedarfsartikeln aus Kunststoff Zimmerei, Ingenieurholzbau",
    "sg:postcode":"5634",
    "sg:province":"Aargau",
    "wof:name":"Vitus Andermatt",
    "wof:placetype":"venue"
},
  "geometry": {"coordinates":[8.3800115585,47.2461090088],"type":"Point"}
}