{
  "type": "Feature",
  "properties": {
    "iso:country":"CH",
    "sg:address":"9050",
    "sg:city":"Appenzell",
    "sg:orig_category":"Vereine Musik/Blasmusik",
    "sg:phone":"+41 19502646",
    "sg:postcode":"9050",
    "sg:province":"Appenzell Innerhoden",
    "wof:name":"Musikgesellschaft Harmonie",
    "wof:placetype":"venue"
},
  "geometry": {"coordinates":[8.7784910202,47.3743591309],"type":"Point"}
}