{
  "type": "Feature",
  "properties": {
    "iso:country":"CH",
    "sg:address":"Waserstrasse 42",
    "sg:city":"Z\u00fcrich",
    "sg:orig_category":"Sonstiges Textilgewerbe Textilgewerbe",
    "sg:phone":"+41 41 630 00 75",
    "sg:postcode":"8053",
    "sg:province":"Z\u00fcrich",
    "wof:name":"Cassiopeia Trend Ag",
    "wof:placetype":"venue"
},
  "geometry": {"coordinates":[8.3101320267,46.9945487976],"type":"Point"}
}