{
  "type": "Feature",
  "properties": {
    "addr:full":"Aegeristrasse 74 Zug Zug 6300",
    "addr:housenumber":"74",
    "addr:postcode":"6300",
    "addr:street":"Aegeristrasse;Zug",
    "iso:country":"CH",
    "sg:address":"Aegeristrasse 74",
    "sg:city":"Zug",
    "sg:orig_category":"Buchf\u00fchrung Informatikdienste",
    "sg:postcode":"6300",
    "sg:province":"Zug",
    "wof:name":"Edmond Messner E/m/c Consulting",
    "wof:placetype":"venue"
},
  "geometry": {"coordinates":[9.362168,47.386242],"type":"Point"}
}