{
  "type": "Feature",
  "properties": {
    "iso:country":"CH",
    "sg:address":"Bachweg 23 4600 Olten. Postfach",
    "sg:city":"Olten",
    "sg:orig_category":"Physiotherapie",
    "sg:phone":"+41 61 401 29 19",
    "sg:postcode":"4601",
    "sg:province":"Solothurn",
    "wof:name":"Benno Mendelin Physiotherapie",
    "wof:placetype":"venue"
},
  "geometry": {"coordinates":[7.5574917793,47.5145225525],"type":"Point"}
}