{
  "type": "Feature",
  "properties": {
    "iso:country":"CH",
    "sg:address":"Bundkofen",
    "sg:city":"Sch\u00fcpfen",
    "sg:orig_category":"Campingpl\u00e4tze Kioske - nicht eigenst\u00e4ndig",
    "sg:phone":"+41 31 879 15 94",
    "sg:postcode":"3054",
    "sg:province":"Bern",
    "wof:name":"Campingplatz Bundkofen Ag",
    "wof:placetype":"venue"
},
  "geometry": {"coordinates":[7.364904,47.045963],"type":"Point"}
}