{
  "type": "Feature",
  "properties": {
    "iso:country":"CH",
    "sg:address":"Lausanne Route De 8 1400 Yverdon-les-bains. Postfach",
    "sg:city":"Yverdon-les-bains",
    "sg:orig_category":"Herstellung von Teppichen",
    "sg:phone":"+41 24 435 14 32",
    "sg:postcode":"1400",
    "sg:province":"Vaud",
    "wof:name":"Schenker Charles",
    "wof:placetype":"venue"
},
  "geometry": {"coordinates":[6.6513152122,46.767036438],"type":"Point"}
}