{
  "type": "Feature",
  "properties": {
    "iso:country":"CH",
    "sg:address":"Altstetterstrasse 145",
    "sg:city":"Z\u00fcrich",
    "sg:orig_category":"Detailhandel mit Damenbekleidung Detailhandel mit Herrenbekleidung",
    "sg:phone":"+41 14300440",
    "sg:postcode":"8048",
    "sg:province":"Z\u00fcrich",
    "wof:name":"Willy Korn Ag Jeans Shop",
    "wof:placetype":"venue"
},
  "geometry": {"coordinates":[8.4869060516,47.3886413574],"type":"Point"}
}