{
  "type": "Feature",
  "properties": {
    "iso:country":"CH",
    "sg:address":"Herrengasse 7",
    "sg:city":"Chur",
    "sg:orig_category":"Architektur U Ingenieurb\u00fcros Architekturb\u00fcros",
    "sg:phone":"+41 81 253 38 31",
    "sg:postcode":"7000",
    "sg:province":"Graubunden",
    "wof:name":"Horv\u00e1th Pablo",
    "wof:placetype":"venue"
},
  "geometry": {"coordinates":[9.531136,46.848705],"type":"Point"}
}