{
  "type": "Feature",
  "properties": {
    "iso:country":"CH",
    "sg:address":"Arneggerstrasse 38",
    "sg:city":"Waldkirch",
    "sg:orig_category":"Bauschreinerei Herstellung von Konstruktionsteilen, Fertigbauteilen U Ausbauelementen aus Holz",
    "sg:phone":"+41 71 433 11 31",
    "sg:postcode":"9205",
    "sg:province":"St. Gallen",
    "wof:name":"Victor Agosti Schreinerei & Innenausbau",
    "wof:placetype":"venue"
},
  "geometry": {"coordinates":[9.279851,47.465717],"type":"Point"}
}