{
  "type": "Feature",
  "properties": {
    "iso:country":"CH",
    "sg:address":"Ebnetstrasse 2",
    "sg:city":"W\u00e4ngi",
    "sg:orig_category":"Haltung von Schweinen Verwertung von Milch",
    "sg:phone":"+41 71 755 12 89",
    "sg:postcode":"9545",
    "sg:province":"Thurgau",
    "wof:name":"Marti Jakob.",
    "wof:placetype":"venue"
},
  "geometry": {"coordinates":[9.5155897141,47.3734283447],"type":"Point"}
}