{
  "type": "Feature",
  "properties": {
    "iso:country":"CH",
    "sg:address":"Seestrasse 5",
    "sg:city":"Cham",
    "sg:orig_category":"Herstellung von sonstigen elektrischen Ausr\u00fcstungen",
    "sg:phone":"+41 79 413 29 47",
    "sg:postcode":"6330",
    "sg:province":"Zug",
    "wof:name":"Digital Solutions Steiner R.",
    "wof:placetype":"venue"
},
  "geometry": {"coordinates":[8.5404052734,47.2902679443],"type":"Point"}
}