{
  "type": "Feature",
  "properties": {
    "iso:country":"CH",
    "sg:address":"Dorfstrasse 53",
    "sg:city":"Thalwil",
    "sg:orig_category":"RESTAURANTS: TEA-ROOMS",
    "sg:phone":"+41 17803322",
    "sg:postcode":"8800",
    "sg:province":"Z\u00fcrich",
    "wof:name":"Gastrobona Ag",
    "wof:placetype":"venue"
},
  "geometry": {"coordinates":[8.5637607574,47.2879371643],"type":"Point"}
}