{
  "type": "Feature",
  "properties": {
    "iso:country":"CH",
    "sg:address":"Gampelengasse 20",
    "sg:city":"Ins",
    "sg:orig_category":"RESTAURANTS: TEA-ROOMS",
    "sg:postcode":"3232",
    "sg:province":"Bern",
    "wof:name":"Hirschi W.",
    "wof:placetype":"venue"
},
  "geometry": {"coordinates":[7.2388739586,46.9034805298],"type":"Point"}
}