{
  "type": "Feature",
  "properties": {
    "iso:country":"CH",
    "sg:address":"5644",
    "sg:city":"Auw",
    "sg:orig_category":"Politische Parteien CVP",
    "sg:phone":"+41 81 302 27 35",
    "sg:postcode":"5644",
    "sg:province":"Aargau",
    "wof:name":"Cvp Ortspartei Bad Ragaz",
    "wof:placetype":"venue"
},
  "geometry": {"coordinates":[9.5067634583,47.0124168396],"type":"Point"}
}