{
  "type": "Feature",
  "properties": {
    "iso:country":"CH",
    "sg:address":"Chesa M\u00fcstaila Seglias",
    "sg:city":"Pontresina",
    "sg:orig_category":"Bauspenglerei Sanit\u00e4rinstallation",
    "sg:phone":"+41 79 610 48 66",
    "sg:postcode":"7504",
    "sg:province":"Graubunden",
    "wof:name":"Armin Etter Sanit\u00e4re Anlagen & Spenglerei",
    "wof:placetype":"venue"
},
  "geometry": {"coordinates":[9.9075,46.489285],"type":"Point"}
}