{
  "type": "Feature",
  "properties": {
    "iso:country":"CH",
    "sg:address":"Auweg 19",
    "sg:city":"Uttigen",
    "sg:orig_category":"Gartenbau",
    "sg:phone":"+41 33 345 11 77",
    "sg:postcode":"3628",
    "sg:province":"Bern",
    "wof:name":"Margrit Ramseier G\u00e4rtnerei",
    "wof:placetype":"venue"
},
  "geometry": {"coordinates":[7.5772352219,46.7956504822],"type":"Point"}
}