{
  "type": "Feature",
  "properties": {
    "iso:country":"CH",
    "sg:address":"Breitistrasse",
    "sg:city":"Bassersdorf",
    "sg:classifiers":[
        {
            "category":"Social Services",
            "subcategory":"Retirement Home",
            "type":"Services"
        }
    ],
    "sg:phone":"+41 31 302 66 66",
    "sg:postcode":"8303",
    "sg:province":"Z\u00fcrich",
    "sg:tags":[
        "pflegeheime",
        "u",
        "alters"
    ],
    "wof:name":"Altersheim Bremgarten-engehalbinsel",
    "wof:placetype":"venue"
},
  "geometry": {"coordinates":[7.435685,46.976265],"type":"Point"}
}