{
  "type": "Feature",
  "properties": {
    "iso:country":"CH",
    "sg:address":"Zugerstrasse 7",
    "sg:city":"Baar",
    "sg:orig_category":"P\u00e9dicure",
    "sg:phone":"+41 41 761 85 72",
    "sg:postcode":"6340",
    "sg:province":"Zug",
    "wof:name":"Beatrice Huber P\u00e9dicure",
    "wof:placetype":"venue"
},
  "geometry": {"coordinates":[8.5230588913,47.1924819946],"type":"Point"}
}