{
  "type": "Feature",
  "properties": {
    "iso:country":"CH",
    "sg:address":"Zweierstrasse 18",
    "sg:city":"Z\u00fcrich",
    "sg:orig_category":"Finanzierungsinstitutionen Sonstige pers\u00f6nliche Dienstleistungen",
    "sg:phone":"+41 12413717",
    "sg:postcode":"8004",
    "sg:province":"Z\u00fcrich",
    "wof:name":"Cat Finance Ag",
    "wof:placetype":"venue"
},
  "geometry": {"coordinates":[8.5276021957,47.3732681274],"type":"Point"}
}