{
  "type": "Feature",
  "properties": {
    "iso:country":"CH",
    "sg:address":"Feldg\u00fctliweg 2",
    "sg:city":"Z\u00fcrich",
    "sg:classifiers":[
        {
            "category":"Restaurant",
            "type":"Food & Drink"
        }
    ],
    "sg:phone":"+41 12916261",
    "sg:postcode":"8004",
    "sg:province":"Z\u00fcrich",
    "wof:name":"Restaurant Ii Padrino",
    "wof:placetype":"venue"
},
  "geometry": {"coordinates":[8.5241794586,47.3732833862],"type":"Point"}
}