{
  "type": "Feature",
  "properties": {
    "iso:country":"CH",
    "sg:city":"Aumont",
    "sg:classifiers":[
        {
            "category":"Banks & Credit Unions",
            "subcategory":"Bank",
            "type":"Services"
        }
    ],
    "sg:phone":"+41 4137651494",
    "sg:postcode":"1484",
    "sg:province":"Fribourg",
    "wof:name":"Banque Raiffeisen",
    "wof:placetype":"venue"
},
  "geometry": {"coordinates":[6.849645,46.800014],"type":"Point"}
}