{
  "type": "Feature",
  "properties": {
    "iso:country":"CH",
    "sg:address":"Lichtenstrasse 26",
    "sg:city":"Leukerbad",
    "sg:orig_category":"Gymnastik U Fitnesszentren",
    "sg:phone":"+41 27 472 24 04",
    "sg:postcode":"3954",
    "sg:province":"Valais",
    "wof:name":"Fitnessclub Daubenhorn",
    "wof:placetype":"venue"
},
  "geometry": {"coordinates":[7.626581192,46.3807525635],"type":"Point"}
}