{
  "type": "Feature",
  "properties": {
    "addr:full":"Hertenstrasse 41 Frauenfeld Thurgau 8500",
    "addr:housenumber":"41",
    "addr:postcode":"8500",
    "addr:street":"Hertenstrasse",
    "iso:country":"CH",
    "sg:address":"Hertenstrasse 41",
    "sg:city":"Frauenfeld",
    "sg:orig_category":"Botanische U zoologische G\u00e4rten sowie Naturparks Sonstige Kultur U Unterhaltungseinrichtungen",
    "sg:phone":"+41 55 220 72 09",
    "sg:postcode":"8500",
    "sg:province":"Thurgau",
    "wof:name":"Knie Gebr\u00fcder, Schweizer National-circus Ag Rapperswil Schweiz. National-circus Knie Und Kinderzoo",
    "wof:placetype":"venue"
},
  "geometry": {"coordinates":[8.823573,47.229893],"type":"Point"}
}