{
  "type": "Feature",
  "properties": {
    "iso:country":"CH",
    "sg:address":"Lindenstrasse 444",
    "sg:city":"Erstfeld",
    "sg:orig_category":"Organisationen des Gesundheitswesen",
    "sg:phone":"+41 55 282 13 10",
    "sg:postcode":"6472",
    "sg:province":"Uri",
    "wof:name":"Samariterverein Eschebach & Umgebung",
    "wof:placetype":"venue"
},
  "geometry": {"coordinates":[8.9213399887,47.2407302856],"type":"Point"}
}