{
  "type": "Feature",
  "properties": {
    "iso:country":"CH",
    "sg:address":"Route D'yverdon 8",
    "sg:city":"Payerne",
    "sg:orig_category":"Herstellung von Anstrichmitteln, Druckfarben U Kitten Sonstiger Detailhandel mit Metallwaren, Anstri",
    "sg:phone":"+41 26 660 53 19",
    "sg:postcode":"1530",
    "sg:province":"Vaud",
    "wof:name":"Technicolor, Mazzucchi Moreno.",
    "wof:placetype":"venue"
},
  "geometry": {"coordinates":[6.935341835,46.8209648132],"type":"Point"}
}