{
  "type": "Feature",
  "properties": {
    "iso:country":"CH",
    "sg:address":"Lausanne Rue De 91",
    "sg:city":"Fribourg",
    "sg:orig_category":"Architektur U Ingenieurb\u00fcros",
    "sg:phone":"+41 26 322 60 64",
    "sg:postcode":"1700",
    "sg:province":"Fribourg",
    "wof:name":"Poesa Sa",
    "wof:placetype":"venue"
},
  "geometry": {"coordinates":[7.156549,46.805218],"type":"Point"}
}