{
  "type": "Feature",
  "properties": {
    "iso:country":"CH",
    "sg:address":"Gewerbestrasse 13d",
    "sg:city":"Niederhasli",
    "sg:orig_category":"Sanit\u00e4r, Heizungs U L\u00fcftungsinstallation Sanit\u00e4rinstallation",
    "sg:phone":"+41 18501095",
    "sg:postcode":"8155",
    "sg:province":"Z\u00fcrich",
    "wof:name":"B\u00fcnter + Schellenberg Ag Niederhasli",
    "wof:placetype":"venue"
},
  "geometry": {"coordinates":[8.4944782257,47.4799308777],"type":"Point"}
}