{
  "type": "Feature",
  "properties": {
    "iso:country":"CH",
    "sg:address":"Justingerweg 12",
    "sg:city":"Bern",
    "sg:orig_category":"Institutionen des Sozialwesens ohne Beherbergung",
    "sg:phone":"+41 71 912 15 55",
    "sg:postcode":"3005",
    "sg:province":"Bern",
    "wof:name":"Miva Unterst\u00fctzung Von Projekten Der Entwicklungszusammenarbeit U. Der Humanit\u00e4ren Hilfe Durch Beschaffung Von Transport- U. Kommunikationsmittel Usw.",
    "wof:placetype":"venue"
},
  "geometry": {"coordinates":[9.0393066406,47.4613494873],"type":"Point"}
}