{
  "type": "Feature",
  "properties": {
    "iso:country":"CH",
    "sg:address":"G\u00e9n\u00e9ral Jomini Avenue 12",
    "sg:city":"Payerne",
    "sg:orig_category":"Erschliessung von Grundst\u00fccken",
    "sg:postcode":"1530",
    "sg:province":"Vaud",
    "wof:name":"Soci\u00e9t\u00e9 Coop\u00e9rative Du Cheval Blanc",
    "wof:placetype":"venue"
},
  "geometry": {"coordinates":[6.9398331642,46.8227272034],"type":"Point"}
}