{
  "type": "Feature",
  "properties": {
    "iso:country":"CH",
    "sg:address":"Luzernerstrasse 107",
    "sg:city":"Moosleerau",
    "sg:orig_category":"Blumen U Zierpflanzenbau Detailhandel mit Blumen U Pflanzen",
    "sg:phone":"+41 62 726 11 53",
    "sg:postcode":"5054",
    "sg:province":"Aargau",
    "wof:name":"Max L\u00fcscher",
    "wof:placetype":"venue"
},
  "geometry": {"coordinates":[8.064893,47.270691],"type":"Point"}
}