{
  "type": "Feature",
  "properties": {
    "iso:country":"CH",
    "sg:address":"Leimenstrasse 46",
    "sg:city":"Basel",
    "sg:orig_category":"Korrespondenz U Nachrichtenb\u00fcros Korrespondenz U Nachrichtenb\u00fcros, selbst\u00e4ndige Journalisten",
    "sg:phone":"+41 22 361 28 30",
    "sg:postcode":"4051",
    "sg:province":"Basel-Stadt",
    "wof:name":"Ams-diffusion Monsieur Charles-f.p\u00e9coud",
    "wof:placetype":"venue"
},
  "geometry": {"coordinates":[6.2355098724,46.3824462891],"type":"Point"}
}