{
  "type": "Feature",
  "properties": {
    "iso:country":"CH",
    "sg:address":"Unterer Althof",
    "sg:city":"Siebnen",
    "sg:orig_category":"Unclassifiable Establishments",
    "sg:postcode":"8854",
    "sg:province":"Schwyz",
    "wof:name":"Hans Jost Solartechnik, W\u00e4rme & Wasser",
    "wof:placetype":"venue"
},
  "geometry": {"coordinates":[8.9026002884,47.1808357239],"type":"Point"}
}