{
  "type": "Feature",
  "properties": {
    "iso:country":"CH",
    "sg:address":"Stedtli 844",
    "sg:city":"Gr\u00fcningen",
    "sg:orig_category":"Detailhandel mit Damenbekleidung",
    "sg:phone":"+41 19354363",
    "sg:postcode":"8627",
    "sg:province":"Z\u00fcrich",
    "wof:name":"Yvonne Neururer Fancy Second-hand-shop",
    "wof:placetype":"venue"
},
  "geometry": {"coordinates":[8.763625,47.28437],"type":"Point"}
}