{
  "type": "Feature",
  "properties": {
    "iso:country":"CH",
    "sg:address":"Chemin Du Grand-clos 6 1869 Massongex Case Postale 46",
    "sg:city":"Massongex",
    "sg:orig_category":"Bauspenglerei Dachdeckerei",
    "sg:phone":"+41 24 471 34 91",
    "sg:postcode":"1869",
    "sg:province":"Valais",
    "wof:name":"Cristalbox Sa Inst.sanitaires & Ferblanterie",
    "wof:placetype":"venue"
},
  "geometry": {"coordinates":[6.98849,46.243999],"type":"Point"}
}