{
  "type": "Feature",
  "properties": {
    "iso:country":"CH",
    "sg:address":"Staatsstrasse 22",
    "sg:city":"Niederb\u00fcren",
    "sg:orig_category":"Zimmerei, Dachdeckerei, Bauspenglerei U Abdichtung Zimmerei, Ingenieurholzbau",
    "sg:phone":"+41 32 652 45 50",
    "sg:postcode":"9246",
    "sg:province":"St. Gallen",
    "wof:name":"L\u00fcthi Und Co., Holzbau Lengnau",
    "wof:placetype":"venue"
},
  "geometry": {"coordinates":[7.3676300049,47.181312561],"type":"Point"}
}