{
  "type": "Feature",
  "properties": {
    "iso:country":"CH",
    "sg:address":"Termerstrasse 20",
    "sg:city":"Ried-brig",
    "sg:orig_category":"G\u00fcterbef\u00f6rderung im Strassenverkehr",
    "sg:phone":"+41 27 924 13 03",
    "sg:postcode":"3911",
    "sg:province":"Valais",
    "wof:name":"B & B Transporte Gmbh",
    "wof:placetype":"venue"
},
  "geometry": {"coordinates":[8.0171432495,46.3201332092],"type":"Point"}
}