{
  "type": "Feature",
  "properties": {
    "iso:country":"CH",
    "sg:address":"Schulhausstrasse 9",
    "sg:city":"Langendorf",
    "sg:orig_category":"RESTAURANTS: TEA-ROOMS",
    "sg:postcode":"4513",
    "sg:province":"Solothurn",
    "wof:name":"Paradiso, Rindone Giovanni",
    "wof:placetype":"venue"
},
  "geometry": {"coordinates":[9.5604228973,46.9718856812],"type":"Point"}
}