{
  "type": "Feature",
  "properties": {
    "addr:full":"Br\u00fcnigstrasse 25 Luzern Luzern 6005",
    "addr:housenumber":"25",
    "addr:postcode":"6005",
    "addr:street":"Bruenigstrasse",
    "iso:country":"CH",
    "sg:address":"Br\u00fcnigstrasse 25",
    "sg:city":"Luzern",
    "sg:orig_category":"Architektur U Ingenieurb\u00fcros Gartenbau",
    "sg:phone":"+41 41 310 70 80",
    "sg:postcode":"6005",
    "sg:province":"Luzern",
    "wof:name":"Fahrni Christoph Landschaftsarchitekt Htl",
    "wof:placetype":"venue"
},
  "geometry": {"coordinates":[8.31168,47.043091],"type":"Point"}
}