{
  "type": "Feature",
  "properties": {
    "iso:country":"CH",
    "sg:address":"3608 Thun. Postfach 1",
    "sg:city":"Thun",
    "sg:orig_category":"Sportvereine Ballsport Fussball",
    "sg:phone":"+41 41 670 32 36",
    "sg:postcode":"3608",
    "sg:province":"Bern",
    "wof:name":"Fc Alpnach",
    "wof:placetype":"venue"
},
  "geometry": {"coordinates":[8.6473550797,47.5728683472],"type":"Point"}
}