{
  "type": "Feature",
  "properties": {
    "iso:country":"CH",
    "sg:address":"Eidgenossenh\u00e4user 244",
    "sg:city":"Hettenschwil",
    "sg:orig_category":"Mechanische Werkst\u00e4tten",
    "sg:phone":"+41 56 245 38 75",
    "sg:postcode":"5317",
    "sg:province":"Aargau",
    "wof:name":"Werkzeugsch\u00e4rferei Franz Vogel",
    "wof:placetype":"venue"
},
  "geometry": {"coordinates":[8.1988039017,47.5767021179],"type":"Point"}
}