{
  "type": "Feature",
  "properties": {
    "iso:country":"CH",
    "sg:address":"Ch. De La Vallombreuse 79",
    "sg:city":"Prilly",
    "sg:orig_category":"Erbringung von Dienstleistungen f\u00fcr Unternehmen",
    "sg:postcode":"1008",
    "sg:province":"Vaud",
    "wof:name":"Dmd Mat\u00e9riel De D\u00e9coration Deschamps Laurent",
    "wof:placetype":"venue"
},
  "geometry": {"coordinates":[6.6114501953,46.5376777649],"type":"Point"}
}