{
  "type": "Feature",
  "properties": {
    "iso:country":"CH",
    "sg:address":"L\u00e4rchenweg 5 8500 Frauenfeld. Postfach",
    "sg:city":"Frauenfeld",
    "sg:orig_category":"Herstellung von Metallkonstruktionen",
    "sg:phone":"+41 52 720 22 16",
    "sg:postcode":"8500",
    "sg:province":"Thurgau",
    "wof:name":"B\u00e4rlocher Metallbau + Schlosserei Metallbauarbeiten; Herstellung, Montage. Allgemeine Schlosserarbeiten",
    "wof:placetype":"venue"
},
  "geometry": {"coordinates":[8.8775196075,47.552986145],"type":"Point"}
}