{
  "type": "Feature",
  "properties": {
    "iso:country":"CH",
    "sg:address":"Rue Des Cond\u00e9mines 7",
    "sg:city":"Reconvilier",
    "sg:classifiers":[
        {
            "category":"Manufacturing",
            "subcategory":"Metals",
            "type":"Manufacturing & Wholesale Goods"
        }
    ],
    "sg:phone":"+41 32 481 31 56",
    "sg:postcode":"2732",
    "sg:province":"Bern",
    "sg:tags":[
        "metallurgy",
        "metalworking",
        "processing"
    ],
    "wof:name":"Pierval Sa",
    "wof:placetype":"venue"
},
  "geometry": {"coordinates":[7.2194070816,47.2308959961],"type":"Point"}
}