{
  "type": "Feature",
  "properties": {
    "iso:country":"CH",
    "sg:address":"Foralweg 4",
    "sg:city":"Chur",
    "sg:orig_category":"Betrieb von Taxis",
    "sg:phone":"+41 81 252 15 14",
    "sg:postcode":"7000",
    "sg:province":"Graubunden",
    "wof:name":"Abc Taxi Chur Gmbh",
    "wof:placetype":"venue"
},
  "geometry": {"coordinates":[9.517074,46.846432],"type":"Point"}
}