{
  "type": "Feature",
  "properties": {
    "iso:country":"CH",
    "sg:address":"Frohb\u00fchlstrasse 4",
    "sg:city":"Z\u00fcrich",
    "sg:orig_category":"Unternehmensberatung",
    "sg:phone":"+41 55 420 15 18",
    "sg:postcode":"8052",
    "sg:province":"Z\u00fcrich",
    "wof:name":"Polycare Von Burg Maja Unternehmensberatung, Bes. Sitzungs Und Projektkontrolle, Organisation Usw",
    "wof:placetype":"venue"
},
  "geometry": {"coordinates":[8.7847919464,47.1997909546],"type":"Point"}
}