{
  "type": "Feature",
  "properties": {
    "iso:country":"CH",
    "sg:address":"Rue Du Grammont 5",
    "sg:city":"Clarens",
    "sg:orig_category":"Fahrschulen, Flugschulen",
    "sg:phone":"+41 21 964 38 77",
    "sg:postcode":"1815",
    "sg:province":"Vaud",
    "wof:name":"Jean-pierre Maillard Auto-\u00e9cole",
    "wof:placetype":"venue"
},
  "geometry": {"coordinates":[6.8914661407,46.4413375854],"type":"Point"}
}