{
  "type": "Feature",
  "properties": {
    "iso:country":"CH",
    "sg:address":"Holzh\u00e4usernstrasse 1",
    "sg:city":"Rotkreuz",
    "sg:orig_category":"Unternehmensberatung",
    "sg:postcode":"6343",
    "sg:province":"Zug",
    "wof:name":"Powercode Business Consultancy, Britsch-elfring Jos\u00e9",
    "wof:placetype":"venue"
},
  "geometry": {"coordinates":[8.0550851822,46.195930481],"type":"Point"}
}