{
  "type": "Feature",
  "properties": {
    "iso:country":"CH",
    "sg:address":"Alpenqaui 28",
    "sg:city":"Luzern",
    "sg:classifiers":[
        {
            "category":"Professional",
            "subcategory":"Engineering",
            "type":"Services"
        }
    ],
    "sg:phone":"+41 32 931 82 05",
    "sg:postcode":"6002",
    "sg:province":"Luzern",
    "sg:tags":[
        "machine",
        "ceramic",
        "-",
        "mechanical"
    ],
    "wof:name":"Savimec Sa",
    "wof:placetype":"venue"
},
  "geometry": {"coordinates":[6.761765,47.060883],"type":"Point"}
}