{
  "type": "Feature",
  "properties": {
    "iso:country":"CH",
    "sg:address":"Kehlhof 14",
    "sg:city":"Beringen",
    "sg:orig_category":"Bau U Wohngenossenschaften",
    "sg:postcode":"8222",
    "sg:province":"Schaffhausen",
    "wof:name":"Bau-& Wohngen.bienengarten",
    "wof:placetype":"venue"
},
  "geometry": {"coordinates":[8.572448,47.69894],"type":"Point"}
}