{
  "type": "Feature",
  "properties": {
    "iso:country":"CH",
    "sg:address":"Ginevra Via 4 6900 Lugano. Postfach",
    "sg:city":"Lugano",
    "sg:orig_category":"Interessenvertretungen",
    "sg:postcode":"6900",
    "sg:province":"Ticino",
    "wof:name":"Fondazione Grassi Pietro",
    "wof:placetype":"venue"
},
  "geometry": {"coordinates":[8.8408298492,46.0080795288],"type":"Point"}
}