{
  "type": "Feature",
  "properties": {
    "iso:country":"CH",
    "sg:address":"Zwillikerstrasse",
    "sg:city":"Hedingen",
    "sg:orig_category":"Detailhandel mit Waren verschiedener Art, Hauptrichtung Nahrungsmittel",
    "sg:phone":"+41 17617337",
    "sg:postcode":"8908",
    "sg:province":"Z\u00fcrich",
    "wof:name":"Volg Detailhandels Ag",
    "wof:placetype":"venue"
},
  "geometry": {"coordinates":[8.4477291107,47.2981948853],"type":"Point"}
}