{
  "type": "Feature",
  "properties": {
    "iso:country":"CH",
    "sg:address":"L\u00e4tti 201",
    "sg:city":"M\u00fcnchenbuchsee",
    "sg:orig_category":"G\u00fcterbef\u00f6rderung im Strassenverkehr",
    "sg:phone":"+41 31 869 31 21",
    "sg:postcode":"3053",
    "sg:province":"Bern",
    "wof:name":"Heinz Hirschi Transporte & Umz\u00fcge",
    "wof:placetype":"venue"
},
  "geometry": {"coordinates":[7.4505391121,47.0214271545],"type":"Point"}
}