{
  "type": "Feature",
  "properties": {
    "iso:country":"CH",
    "sg:address":"Culmannstrasse 56 8006 Z\u00fcrich. Postfach",
    "sg:city":"Z\u00fcrich",
    "sg:orig_category":"Rechtsberatung",
    "sg:postcode":"8006",
    "sg:province":"Z\u00fcrich",
    "wof:name":"Helbling H. J. Ag",
    "wof:placetype":"venue"
},
  "geometry": {"coordinates":[8.8636655807,47.1902389526],"type":"Point"}
}