{
  "type": "Feature",
  "properties": {
    "iso:country":"CH",
    "sg:address":"Seestrasse 5",
    "sg:city":"Meilen",
    "sg:orig_category":"Grosshandel mit sonstigen Halbwaren",
    "sg:phone":"+41 41 630 37 57",
    "sg:postcode":"8706",
    "sg:province":"Z\u00fcrich",
    "wof:name":"Barano Handels Ag",
    "wof:placetype":"venue"
},
  "geometry": {"coordinates":[8.3137350082,46.9894294739],"type":"Point"}
}