{
  "type": "Feature",
  "properties": {
    "iso:country":"CH",
    "sg:address":"6012",
    "sg:city":"Obernau",
    "sg:orig_category":"Schulpflegen",
    "sg:phone":"+41 41 310 35 61",
    "sg:postcode":"6012",
    "sg:province":"Luzern",
    "wof:name":"Primarschulpflege Der Gemeinde Obernau",
    "wof:placetype":"venue"
},
  "geometry": {"coordinates":[8.2550296783,47.0333786011],"type":"Point"}
}