{
  "type": "Feature",
  "properties": {
    "iso:country":"CH",
    "sg:address":"H\u00e4ringstrasse 17",
    "sg:city":"Z\u00fcrich",
    "sg:orig_category":"Gesundheitswesen",
    "sg:phone":"+41 71 777 23 45",
    "sg:postcode":"8001",
    "sg:province":"Z\u00fcrich",
    "wof:name":"Baroni Aldo Industrievertretungen",
    "wof:placetype":"venue"
},
  "geometry": {"coordinates":[9.5642147064,47.3890647888],"type":"Point"}
}