{
  "type": "Feature",
  "properties": {
    "iso:country":"CH",
    "sg:address":"Quai De La Thi\u00e8le 15",
    "sg:city":"Yverdon-les-bains",
    "sg:orig_category":"Versicherungen Generalagenturen",
    "sg:phone":"+41 24 426 20 20",
    "sg:postcode":"1400",
    "sg:province":"Vaud",
    "wof:name":"Allianz Assurances Agence G\u00e9n\u00e9rale",
    "wof:placetype":"venue"
},
  "geometry": {"coordinates":[6.6364550591,46.7824401855],"type":"Point"}
}