{
  "type": "Feature",
  "properties": {
    "iso:country":"CH",
    "sg:address":"Hagenwilerstrasse 21",
    "sg:city":"Amriswil",
    "sg:orig_category":"Handelsvermittlung U Grosshandel mit Automobilteilen U Zubeh\u00f6r Instandhaltung U Reparatur von Automo",
    "sg:phone":"+41 71 411 28 72",
    "sg:postcode":"8580",
    "sg:province":"Thurgau",
    "wof:name":"Hafner H.p.",
    "wof:placetype":"venue"
},
  "geometry": {"coordinates":[9.2900037766,47.5406112671],"type":"Point"}
}