{
  "type": "Feature",
  "properties": {
    "iso:country":"CH",
    "sg:address":"Bernstrasse 97",
    "sg:city":"M\u00fcnsingen",
    "sg:orig_category":"Handel mit Automobilen",
    "sg:phone":"+41 31 721 79 79",
    "sg:postcode":"3110",
    "sg:province":"Bern",
    "wof:name":"Autohaus M\u00fcnsingen Ag",
    "wof:placetype":"venue"
},
  "geometry": {"coordinates":[7.5543937683,46.8875427246],"type":"Point"}
}