{
  "type": "Feature",
  "properties": {
    "iso:country":"CH",
    "sg:address":"Schocherswilerstrasse 7 8586 Buchackern. Postfach",
    "sg:city":"Buchackern",
    "sg:orig_category":"Mechanik",
    "sg:postcode":"8586",
    "sg:province":"Thurgau",
    "wof:name":"Schlosserei Z\u00e4ch Martin",
    "wof:placetype":"venue"
},
  "geometry": {"coordinates":[9.2337350845,47.5387649536],"type":"Point"}
}