{
  "type": "Feature",
  "properties": {
    "iso:country":"CH",
    "sg:address":"Rue De La Moya 2bis",
    "sg:city":"Martigny",
    "sg:orig_category":"Vermietung U Verpachtung von eigenen Immobilien",
    "sg:postcode":"1920",
    "sg:province":"Valais",
    "wof:name":"Hauri Immobilien Ag Immobiliengesch\u00e4fte. Bauunternehmung",
    "wof:placetype":"venue"
},
  "geometry": {"coordinates":[8.1875915527,47.2501182556],"type":"Point"}
}