{
  "type": "Feature",
  "properties": {
    "iso:country":"CH",
    "sg:address":"Thonon Route De 153 1245 Collonge-bellerive. Postfach",
    "sg:city":"Gen\u00e8ve",
    "sg:orig_category":"Fernmeldedienste",
    "sg:postcode":"1201",
    "sg:province":"Gen\u00e8ve",
    "wof:name":"Radianz Switzerland Sa T\u00e9l\u00e9communication \u00e9lectronique; Promotion, Commercialisation, Services Etc",
    "wof:placetype":"venue"
},
  "geometry": {"coordinates":[6.2042441368,46.2535629272],"type":"Point"}
}