{
  "type": "Feature",
  "properties": {
    "iso:country":"CH",
    "sg:address":"Luzernerstrasse 64",
    "sg:city":"Kriens",
    "sg:orig_category":"Zahnarztpraxen",
    "sg:phone":"+41 41 310 60 60",
    "sg:postcode":"6010",
    "sg:province":"Luzern",
    "wof:name":"Dr.med.dent.davorka Potocnik Zahn\u00e4rztin",
    "wof:placetype":"venue"
},
  "geometry": {"coordinates":[8.2879056931,47.0346069336],"type":"Point"}
}