{
  "type": "Feature",
  "properties": {
    "iso:country":"CH",
    "sg:address":"Stationsstrasse 44",
    "sg:city":"Wettswil",
    "sg:orig_category":"P\u00e9dicure",
    "sg:phone":"+41 17000607",
    "sg:postcode":"8907",
    "sg:province":"Z\u00fcrich",
    "wof:name":"Madelaine Waech P\u00e9dicure",
    "wof:placetype":"venue"
},
  "geometry": {"coordinates":[8.4743099213,47.3332595825],"type":"Point"}
}