{
  "type": "Feature",
  "properties": {
    "iso:country":"CH",
    "sg:address":"Oberneuhofstrasse 13",
    "sg:city":"Baar",
    "sg:orig_category":"Schiffs U Bootsbau",
    "sg:phone":"+41 41 761 71 44",
    "sg:postcode":"6340",
    "sg:province":"Zug",
    "wof:name":"Walter Fedier",
    "wof:placetype":"venue"
},
  "geometry": {"coordinates":[8.5165224075,47.1867828369],"type":"Point"}
}