{
  "type": "Feature",
  "properties": {
    "addr:full":"Ruesserain 121 Moosleerau Aargau 5054",
    "addr:housenumber":"121",
    "addr:postcode":"5054",
    "iso:country":"CH",
    "sg:address":"Ruesserain 121",
    "sg:city":"Moosleerau",
    "sg:orig_category":"Arztpraxen",
    "sg:phone":"+41 34 402 40 04",
    "sg:postcode":"5054",
    "sg:province":"Aargau",
    "wof:name":"Dr.med.hansj\u00f6rg Stauffer Spezialarzt Fmh",
    "wof:placetype":"venue"
},
  "geometry": {"coordinates":[7.75759,46.949127],"type":"Point"}
}