{
  "type": "Feature",
  "properties": {
    "iso:country":"CH",
    "sg:address":"7220",
    "sg:city":"Schiers",
    "sg:classifiers":[
        {
            "category":"Education",
            "subcategory":"Library",
            "type":"Public Place"
        }
    ],
    "sg:phone":"+41 61 835 66 66",
    "sg:postcode":"7220",
    "sg:province":"Graubunden",
    "sg:tags":[
        "u",
        "bibliotheken",
        "archive"
    ],
    "wof:name":"Regionalspital Rheinfelden",
    "wof:placetype":"venue"
},
  "geometry": {"coordinates":[7.806953,47.556274],"type":"Point"}
}