{
  "type": "Feature",
  "properties": {
    "iso:country":"CH",
    "sg:address":"Gondiswil",
    "sg:city":"Gondiswil",
    "sg:classifiers":[
        {
            "category":"Banks & Credit Unions",
            "subcategory":"Bank",
            "type":"Services"
        }
    ],
    "sg:phone":"+41 63781112",
    "sg:postcode":"4955",
    "sg:province":"Bern",
    "wof:name":"Ersparniskasse, Des Amtsbezirkes Aarwangen",
    "wof:placetype":"venue"
},
  "geometry": {"coordinates":[7.872771,47.144112],"type":"Point"}
}