{
  "type": "Feature",
  "properties": {
    "addr:full":"Korbackerweg 21 5502 Hunzenschwil. Postfach 133 Hunzenschwil Aargau 5502",
    "addr:housenumber":"21;133",
    "addr:postcode":"5502 hunzenschwil.;5502",
    "addr:street":"Korbackerweg;Postfach",
    "iso:country":"CH",
    "sg:address":"Korbackerweg 21 5502 Hunzenschwil. Postfach 133",
    "sg:city":"Hunzenschwil",
    "sg:orig_category":"Bau von Strassen, Sportanlagen U Bahnverkehrsstrecken Strassenbau",
    "sg:phone":"+41 62 897 41 81",
    "sg:postcode":"5502",
    "sg:province":"Aargau",
    "wof:name":"Moor Ag Strassen Und Tiefbauunternehmung",
    "wof:placetype":"venue"
},
  "geometry": {"coordinates":[8.131786,47.385933],"type":"Point"}
}