{
  "type": "Feature",
  "properties": {
    "iso:country":"CH",
    "sg:address":"Maison Forte 1287 Laconnex. Postfach",
    "sg:city":"Laconnex",
    "sg:orig_category":"Sanit\u00e4r, Heizungs U L\u00fcftungsinstallation Sanit\u00e4rinstallation",
    "sg:phone":"+41 22 756 06 53",
    "sg:postcode":"1287",
    "sg:province":"Gen\u00e8ve",
    "wof:name":"Sb Sanitaire, Baubonne St\u00e9phane Installations Sanitaires",
    "wof:placetype":"venue"
},
  "geometry": {"coordinates":[6.0366268158,46.1567420959],"type":"Point"}
}