{
  "type": "Feature",
  "properties": {
    "iso:country":"CH",
    "sg:address":"Rue De La Pontaise 2",
    "sg:city":"Lausanne",
    "sg:orig_category":"Druckweiterverarbeitung",
    "sg:phone":"+41 22 342 53 67",
    "sg:postcode":"1018",
    "sg:province":"Vaud",
    "wof:name":"La Boutique Du Relieur, Michel Magnin",
    "wof:placetype":"venue"
},
  "geometry": {"coordinates":[6.1415009499,46.1829872131],"type":"Point"}
}