{
  "type": "Feature",
  "properties": {
    "iso:country":"CH",
    "sg:address":"Rue Du Cudeaux-du-haut",
    "sg:city":"Corcelles",
    "sg:orig_category":"Blanking, Punching, Stamping, Embossing And Drawing Dies, Progressive Dies",
    "sg:phone":"+41 32 730 64 25",
    "sg:postcode":"2035",
    "sg:province":"Neuch\u00e2tel",
    "wof:name":"Mmp Sa",
    "wof:placetype":"venue"
},
  "geometry": {"coordinates":[6.86986,46.98391],"type":"Point"}
}