{
  "type": "Feature",
  "properties": {
    "iso:country":"CH",
    "sg:address":"Kramgasse 3 3506 Grossh\u00f6chstetten. Postfach",
    "sg:city":"Grossh\u00f6chstetten",
    "sg:orig_category":"Elektrizit\u00e4tsversorgung Wasserversorgung",
    "sg:phone":"+41 31 710 21 21",
    "sg:postcode":"3506",
    "sg:province":"Bern",
    "wof:name":"Elektrizit.-& Wasserverwaltung Der Gemeinde Grossh\u00f6chstetten",
    "wof:placetype":"venue"
},
  "geometry": {"coordinates":[7.6390318871,46.9069404602],"type":"Point"}
}