{
  "type": "Feature",
  "properties": {
    "iso:country":"CH",
    "sg:address":"Rue Du Cr\u00eat 7",
    "sg:city":"Lausanne",
    "sg:orig_category":"G\u00fcterbef\u00f6rderung im Strassenverkehr",
    "sg:phone":"+41 27 776 16 33",
    "sg:postcode":"1000",
    "sg:province":"Vaud",
    "wof:name":"Vogel Jos\u00e9",
    "wof:placetype":"venue"
},
  "geometry": {"coordinates":[7.2124481201,46.0804595947],"type":"Point"}
}