{
  "type": "Feature",
  "properties": {
    "iso:country":"CH",
    "sg:address":"Dorf 6156 Luthern. Postfach",
    "sg:city":"Luthern",
    "sg:orig_category":"Sanit\u00e4r, Heizungs U L\u00fcftungsinstallation",
    "sg:postcode":"6156",
    "sg:province":"Luzern",
    "wof:name":"Rolf Bissegger, Heizungen",
    "wof:placetype":"venue"
},
  "geometry": {"coordinates":[8.9839277267,47.4508132935],"type":"Point"}
}