{
  "type": "Feature",
  "properties": {
    "iso:country":"CH",
    "sg:address":"Gaiserau 3",
    "sg:city":"Gais",
    "sg:classifiers":[
        {
            "category":"Restaurant",
            "type":"Food & Drink"
        }
    ],
    "sg:phone":"+41 19361863",
    "sg:postcode":"9056",
    "sg:province":"Appenzell Ausserrhoden",
    "wof:name":"Restaurant L\u00f6wen",
    "wof:placetype":"venue"
},
  "geometry": {"coordinates":[8.7552585602,47.3067550659],"type":"Point"}
}