{
  "type": "Feature",
  "properties": {
    "iso:country":"CH",
    "sg:address":"Muttenzerstrasse 15",
    "sg:city":"Birsfelden",
    "sg:orig_category":"Softwareentwicklung U beratung",
    "sg:phone":"+41 17453020",
    "sg:postcode":"4127",
    "sg:province":"Basel-Landschaft",
    "wof:name":"Hartler Ag",
    "wof:placetype":"venue"
},
  "geometry": {"coordinates":[8.2950334549,47.4472694397],"type":"Point"}
}