{
  "type": "Feature",
  "properties": {
    "iso:country":"CH",
    "sg:address":"Lagerweg 16",
    "sg:city":"Lotzwil",
    "sg:orig_category":"S\u00e4gewerke",
    "sg:phone":"+41 62 922 31 87",
    "sg:postcode":"4932",
    "sg:province":"Bern",
    "wof:name":"Walter Brechb\u00fchler",
    "wof:placetype":"venue"
},
  "geometry": {"coordinates":[7.7854971886,47.1899986267],"type":"Point"}
}