{
  "type": "Feature",
  "properties": {
    "iso:country":"CH",
    "sg:address":"Mitteldorf 19",
    "sg:city":"Zeiningen",
    "sg:orig_category":"Zahnarztpraxen",
    "sg:phone":"+41 61 851 10 20",
    "sg:postcode":"4314",
    "sg:province":"Aargau",
    "wof:name":"Dr. Med. Dent. Remo Loepfe Zahnarzt",
    "wof:placetype":"venue"
},
  "geometry": {"coordinates":[7.8704161644,47.5412712097],"type":"Point"}
}