{
  "type": "Feature",
  "properties": {
    "iso:country":"CH",
    "sg:address":"Reussstrasse",
    "sg:city":"Gisikon",
    "sg:orig_category":"Non-Classified Establishments",
    "sg:phone":"+41 41 450 12 61",
    "sg:postcode":"6038",
    "sg:province":"Luzern",
    "wof:name":"Gasthof Tell",
    "wof:placetype":"venue"
},
  "geometry": {"coordinates":[8.3978347778,47.1261672974],"type":"Point"}
}