{
  "type": "Feature",
  "properties": {
    "iso:country":"CH",
    "sg:address":"6377",
    "sg:city":"Seelisberg",
    "sg:orig_category":"Kantonalbanken",
    "sg:phone":"+41 41 820 15 63",
    "sg:postcode":"6377",
    "sg:province":"Uri",
    "wof:name":"Urner Kantonalbank",
    "wof:placetype":"venue"
},
  "geometry": {"coordinates":[8.5853796005,46.9748535156],"type":"Point"}
}