{
  "type": "Feature",
  "properties": {
    "iso:country":"CH",
    "sg:address":"M\u00f6nthalerstrasse 119",
    "sg:city":"Remigen",
    "sg:orig_category":"Detailhandel mit M\u00f6beln Innenausbau",
    "sg:phone":"+41 79 225 16 15",
    "sg:postcode":"5236",
    "sg:province":"Aargau",
    "wof:name":"Herbert Krebs",
    "wof:placetype":"venue"
},
  "geometry": {"coordinates":[8.1886892319,47.5156555176],"type":"Point"}
}