{
  "type": "Feature",
  "properties": {
    "iso:country":"CH",
    "sg:address":"Froschaugasse 15",
    "sg:city":"Z\u00fcrich",
    "sg:classifiers":[
        {
            "category":"Restaurant",
            "type":"Food & Drink"
        }
    ],
    "sg:phone":"+41 41 811 23 40",
    "sg:postcode":"8001",
    "sg:province":"Z\u00fcrich",
    "wof:name":"Restaurant Magdalena",
    "wof:placetype":"venue"
},
  "geometry": {"coordinates":[8.6655302048,47.017074585],"type":"Point"}
}