{
  "type": "Feature",
  "properties": {
    "iso:country":"CH",
    "sg:address":"Hortensienweg 4",
    "sg:city":"Emmenbr\u00fccke",
    "sg:orig_category":"Autogaragen Autospenglereien",
    "sg:phone":"+41 41 280 53 44",
    "sg:postcode":"6020",
    "sg:province":"Luzern",
    "wof:name":"Guy Clivaz Kapf-garage & Carrosserie",
    "wof:placetype":"venue"
},
  "geometry": {"coordinates":[8.274744,47.091885],"type":"Point"}
}