{
  "type": "Feature",
  "properties": {
    "iso:country":"CH",
    "sg:address":"Spielhof 7",
    "sg:city":"Glarus",
    "sg:orig_category":"G\u00fcterbef\u00f6rderung im Strassenverkehr",
    "sg:phone":"+41 61 461 60 88",
    "sg:postcode":"8750",
    "sg:province":"Glarus",
    "wof:name":"Crosstrans Ag",
    "wof:placetype":"venue"
},
  "geometry": {"coordinates":[9.0662679672,47.0419464111],"type":"Point"}
}