{
  "type": "Feature",
  "properties": {
    "iso:country":"CH",
    "sg:address":"Schulhaus",
    "sg:city":"Bleiken",
    "sg:orig_category":"Vorschulen, Kinderg\u00e4rten",
    "sg:phone":"+41 31 978 26 40",
    "sg:postcode":"3674",
    "sg:province":"Bern",
    "wof:name":"Kindergarten Blindenmoos",
    "wof:placetype":"venue"
},
  "geometry": {"coordinates":[7.4123001099,46.9086112976],"type":"Point"}
}