{
  "type": "Feature",
  "properties": {
    "iso:country":"CH",
    "sg:address":"Bachtelstrasse 26",
    "sg:city":"Hinwil",
    "sg:orig_category":"Herstellung von Konstruktionsteilen, Fertigbauteilen U Ausbauelementen aus Holz Innenausbau",
    "sg:phone":"+41 19771155",
    "sg:postcode":"8340",
    "sg:province":"Z\u00fcrich",
    "wof:name":"H. R. Bischof K\u00fcchen Und Innenausbau Ag",
    "wof:placetype":"venue"
},
  "geometry": {"coordinates":[8.8471212387,47.3003768921],"type":"Point"}
}