{
  "type": "Feature",
  "properties": {
    "iso:country":"CH",
    "sg:address":"Gumpisb\u00fcelstrasse 31",
    "sg:city":"D\u00fcbendorf",
    "sg:orig_category":"Erschliessung von Grundst\u00fccken",
    "sg:postcode":"8600",
    "sg:province":"Z\u00fcrich",
    "wof:name":"Wohnbaugenossenschaft Des Bundespersonals D\u00fcbendorf",
    "wof:placetype":"venue"
},
  "geometry": {"coordinates":[8.6160888672,47.4043273926],"type":"Point"}
}