{
  "type": "Feature",
  "properties": {
    "iso:country":"CH",
    "sg:address":"Dornacherstrasse 145",
    "sg:city":"Basel",
    "sg:orig_category":"Malerei",
    "sg:phone":"+41 61 361 83 62",
    "sg:postcode":"4053",
    "sg:province":"Basel-Stadt",
    "wof:name":"Bernd Gier Malergesch\u00e4ft",
    "wof:placetype":"venue"
},
  "geometry": {"coordinates":[7.5914092064,47.5427284241],"type":"Point"}
}