{
  "type": "Feature",
  "properties": {
    "iso:country":"CH",
    "sg:address":"Grand' Rue",
    "sg:city":"Ch\u00e2teau-d'oex",
    "sg:orig_category":"Detailhandel mit Brot, Back U S\u00fcsswaren",
    "sg:phone":"+41 26 924 57 47",
    "sg:postcode":"1837",
    "wof:name":"P\u00e2tisserie Confiserie Lenoir Jacques",
    "wof:placetype":"venue"
},
  "geometry": {"coordinates":[-75.605957,37.787762],"type":"Point"}
}