{
  "type": "Feature",
  "properties": {
    "iso:country":"CH",
    "sg:address":"Terrassenweg 17",
    "sg:city":"Ober\u00e4geri",
    "sg:orig_category":"Unclassifiable Establishments",
    "sg:postcode":"6315",
    "sg:province":"Zug",
    "wof:name":"Primo Beteiligungs Ag",
    "wof:placetype":"venue"
},
  "geometry": {"coordinates":[8.6243286133,47.1349525452],"type":"Point"}
}