{
  "type": "Feature",
  "properties": {
    "iso:country":"CH",
    "sg:address":"Rotbuchstrasse 83",
    "sg:city":"Z\u00fcrich",
    "sg:orig_category":"Wirtschaftsverb\u00e4nde Detaillisten",
    "sg:phone":"+41 55 210 38 00",
    "sg:postcode":"8037",
    "sg:province":"Z\u00fcrich",
    "wof:name":"Apothekerverein Des Kantons Z\u00fcrich Sekretariat",
    "wof:placetype":"venue"
},
  "geometry": {"coordinates":[8.5307407379,47.3930511475],"type":"Point"}
}