{
  "type": "Feature",
  "properties": {
    "iso:country":"CH",
    "sg:address":"Hochstrasse 54",
    "sg:city":"Basel",
    "sg:orig_category":"Hobel U Holzimpr\u00e4gnierwerke",
    "sg:phone":"+41 61 361 05 60",
    "sg:postcode":"4053",
    "sg:province":"Basel-Stadt",
    "wof:name":"Eduard Jakob Beiz-& Polierwerkst\u00e4tte",
    "wof:placetype":"venue"
},
  "geometry": {"coordinates":[7.594645977,47.5445213318],"type":"Point"}
}