{
  "type": "Feature",
  "properties": {
    "iso:country":"CH",
    "sg:address":"Mattenstrasse 84 2503 Biel/bienne Case Postale 51",
    "sg:city":"Biel/bienne",
    "sg:orig_category":"Grosshandel mit Erzen U Metallen Grosshandel mit sonstigen Maschinen U Ausr\u00fcstungen f\u00fcr Industrie, H",
    "sg:phone":"+41 79 430 44 04",
    "sg:postcode":"2501",
    "sg:province":"Bern",
    "wof:name":"Igv Industrie-g\u00fcter- Vertriebs Ag",
    "wof:placetype":"venue"
},
  "geometry": {"coordinates":[9.1809234619,47.6381607056],"type":"Point"}
}