{
  "type": "Feature",
  "properties": {
    "addr:full":"6595 Riazzino Ticino 6595",
    "addr:housenumber":"6595",
    "addr:postcode":"6595",
    "iso:country":"CH",
    "sg:address":"6595",
    "sg:city":"Riazzino",
    "sg:orig_category":"Betrieb von Taxis",
    "sg:postcode":"6595",
    "sg:province":"Ticino",
    "wof:name":"Umwelt Taxi Schwendimann",
    "wof:placetype":"venue"
},
  "geometry": {"coordinates":[9.041031,47.459126],"type":"Point"}
}