{
  "type": "Feature",
  "properties": {
    "iso:country":"CH",
    "sg:address":"Bernstrasse 93",
    "sg:city":"Sch\u00f6nb\u00fchl-urtenen",
    "sg:orig_category":"Detailhandel mit M\u00f6beln Detailhandel mit M\u00f6beln U Haushaltsgegenst\u00e4nden",
    "sg:phone":"+41 31 859 11 85",
    "sg:postcode":"3322",
    "sg:province":"Bern",
    "wof:name":"Wohnstudio Haller Ag",
    "wof:placetype":"venue"
},
  "geometry": {"coordinates":[7.4995298386,47.0204238892],"type":"Point"}
}