{
  "type": "Feature",
  "properties": {
    "iso:country":"CH",
    "sg:address":"Jurastr. 56",
    "sg:city":"Wettingen",
    "sg:classifiers":[
        {
            "category":"Social Services",
            "subcategory":"Job Training",
            "type":"Services"
        }
    ],
    "sg:phone":"+41 56 437 60 70",
    "sg:postcode":"5430",
    "sg:province":"Aargau",
    "sg:tags":[
        "information",
        "peripheral",
        "-",
        "technology",
        "software"
    ],
    "wof:name":"Cropmark Ag",
    "wof:placetype":"venue"
},
  "geometry": {"coordinates":[8.3324384689,47.4580116272],"type":"Point"}
}