{
  "type": "Feature",
  "properties": {
    "iso:country":"CH",
    "sg:address":"Haldimoos 22",
    "sg:city":"B\u00fctzberg",
    "sg:orig_category":"Allgemeiner Gartenbau Gartenbau",
    "sg:phone":"+41 62 963 11 32",
    "sg:postcode":"4922",
    "sg:province":"Bern",
    "wof:name":"Toni Spreng",
    "wof:placetype":"venue"
},
  "geometry": {"coordinates":[7.753953,47.204174],"type":"Point"}
}