{
  "type": "Feature",
  "properties": {
    "iso:country":"CH",
    "sg:address":"Rainweidstrasse 12 C 6330 Cham. Postfach",
    "sg:city":"Cham",
    "sg:orig_category":"Wirtschaftspr\u00fcfung, Steuerberatung U Treuhand",
    "sg:postcode":"6330",
    "sg:province":"Zug",
    "wof:name":"Act Gmbh Audit Consulting Trust",
    "wof:placetype":"venue"
},
  "geometry": {"coordinates":[8.4445075989,47.175945282],"type":"Point"}
}