{
  "type": "Feature",
  "properties": {
    "iso:country":"CH",
    "sg:address":"Tribschenstrasse 64",
    "sg:city":"Luzern",
    "sg:orig_category":"Fachdetailhandel in Verkaufsr\u00e4umen",
    "sg:postcode":"6005",
    "sg:province":"Luzern",
    "wof:name":"Iten Ag",
    "wof:placetype":"venue"
},
  "geometry": {"coordinates":[8.3174858093,47.0422554016],"type":"Point"}
}