{
  "type": "Feature",
  "properties": {
    "iso:country":"CH",
    "sg:address":"Eugen Huber-strasse 11 8048 Z\u00fcrich. Postfach 1482",
    "sg:city":"Z\u00fcrich",
    "sg:orig_category":"Handelsvermittlung U Grosshandel",
    "sg:phone":"+41 14321830",
    "sg:postcode":"8048",
    "sg:province":"Z\u00fcrich",
    "wof:name":"Varia-travel Management Ag Waren; Handel, Im, Export. Reisearrangements; Vermittlung Usw",
    "wof:placetype":"venue"
},
  "geometry": {"coordinates":[8.4853439331,47.3847732544],"type":"Point"}
}