{
  "type": "Feature",
  "properties": {
    "iso:country":"CH",
    "sg:address":"6417",
    "sg:city":"Sattel",
    "sg:orig_category":"Detailhandel mit Fleisch U Fleischwaren",
    "sg:postcode":"6417",
    "sg:province":"Schwyz",
    "wof:name":"M-m Metzgerei Sijaric Metzgerei Und Lebensmittelhandel",
    "wof:placetype":"venue"
},
  "geometry": {"coordinates":[9.3951673508,47.4995117188],"type":"Point"}
}