{
  "type": "Feature",
  "properties": {
    "iso:country":"CH",
    "sg:address":"Sihlstrasse 33 8001 Z\u00fcrich. Postfach 1278",
    "sg:city":"Z\u00fcrich",
    "sg:orig_category":"Interessenvertretungen U sonstige Vereinigungen",
    "sg:phone":"+41 31 321 60 90",
    "sg:postcode":"8021",
    "sg:province":"Z\u00fcrich",
    "wof:name":"Denkmalpflege Der Stadt Bern",
    "wof:placetype":"venue"
},
  "geometry": {"coordinates":[7.4538078308,46.9475746155],"type":"Point"}
}