{
  "type": "Feature",
  "properties": {
    "iso:country":"CH",
    "sg:address":"Spitzib\u00fchl",
    "sg:city":"Allenwinden",
    "sg:orig_category":"Verlegen von Fliesen U Platten",
    "sg:phone":"+41 41 711 41 75",
    "sg:postcode":"6319",
    "sg:province":"Zug",
    "wof:name":"Josef Arnold Ofenbau & Plattenbel\u00e4ge",
    "wof:placetype":"venue"
},
  "geometry": {"coordinates":[8.556394577,47.164276123],"type":"Point"}
}