{
  "type": "Feature",
  "properties": {
    "iso:country":"CH",
    "sg:address":"Gerbergasse 7",
    "sg:city":"Z\u00fcrich",
    "sg:orig_category":"Detailhandel mit Geschenkartikeln U Souvenirs",
    "sg:phone":"+41 12119916",
    "sg:postcode":"8001",
    "sg:province":"Z\u00fcrich",
    "wof:name":"Cardboutique Olga Donath",
    "wof:placetype":"venue"
},
  "geometry": {"coordinates":[8.536863327,47.3749351501],"type":"Point"}
}