{
  "type": "Feature",
  "properties": {
    "iso:country":"CH",
    "sg:address":"3983",
    "sg:city":"Filet",
    "sg:orig_category":"Grosshandel mit Fleisch U Fleischwaren Grosshandel mit sonstigen Nahrungsmitteln",
    "sg:phone":"+41 27 927 18 13",
    "sg:postcode":"3983",
    "sg:province":"Valais",
    "wof:name":"Baasch Jean Comestibles.",
    "wof:placetype":"venue"
},
  "geometry": {"coordinates":[8.0502500534,46.3586387634],"type":"Point"}
}