{
  "type": "Feature",
  "properties": {
    "iso:country":"CH",
    "sg:address":"Ostermundigenstrasse 34a",
    "sg:city":"Bern",
    "sg:orig_category":"Pensionskassen",
    "sg:postcode":"3006",
    "sg:province":"Bern",
    "wof:name":"Fonds De Pr\u00e9voyance En Faveur Du Personnel De La Soci\u00e9t\u00e9 Anonyme \u00e0 Vevey Et Soci\u00e9t\u00e9s Affili\u00e9es",
    "wof:placetype":"venue"
},
  "geometry": {"coordinates":[5.1808700562,45.8973388672],"type":"Point"}
}