{
  "type": "Feature",
  "properties": {
    "iso:country":"CH",
    "sg:address":"Chemin De La Rueyre 116-118",
    "sg:city":"Renens",
    "sg:classifiers":[
        {
            "category":"Wholesale",
            "subcategory":"Books, Periodicals, & Newspapers",
            "type":"Manufacturing & Wholesale Goods"
        }
    ],
    "sg:phone":"+41 21 632 92 00",
    "sg:postcode":"1020",
    "sg:province":"Vaud",
    "sg:tags":[
        "publisher",
        "journal"
    ],
    "wof:name":"Cb Communication",
    "wof:placetype":"venue"
},
  "geometry": {"coordinates":[6.5893101692,46.544921875],"type":"Point"}
}