{
  "type": "Feature",
  "properties": {
    "iso:country":"CH",
    "sg:address":"Alte Winterthurerstrasse 9",
    "sg:city":"N\u00fcrensdorf",
    "sg:orig_category":"Pensionskassen",
    "sg:postcode":"8309",
    "sg:province":"Z\u00fcrich",
    "wof:name":"Personalf\u00fcrsorgestiftung Der Firma Bosshard S\u00f6hne Ag",
    "wof:placetype":"venue"
},
  "geometry": {"coordinates":[8.6240472794,47.5486221313],"type":"Point"}
}