{
  "type": "Feature",
  "properties": {
    "addr:full":"Le Ch\u00eane Corcelles-payerne Vaud 1562",
    "addr:housenumber":"1562",
    "iso:country":"CH",
    "sg:address":"Le Ch\u00eane",
    "sg:city":"Corcelles-payerne",
    "sg:orig_category":"Bauschreinerei S\u00e4gewerke",
    "sg:phone":"+41 26 660 60 41",
    "sg:postcode":"1562",
    "sg:province":"Vaud",
    "wof:name":"Raymond R\u00fcfenacht Menuiserie & Scierie",
    "wof:placetype":"venue"
},
  "geometry": {"coordinates":[6.965574,46.830643],"type":"Point"}
}