{
  "type": "Feature",
  "properties": {
    "addr:full":"Route D'yverdon 4 Estavayer-le-lac Fribourg 1470",
    "addr:housenumber":"4",
    "addr:postcode":"1470",
    "addr:street":"Route D'Yverdon;Fribourg",
    "iso:country":"CH",
    "sg:address":"Route D'yverdon 4",
    "sg:city":"Estavayer-le-lac",
    "sg:orig_category":"Blumen U Zierpflanzenbau",
    "sg:phone":"+41 26 663 14 54",
    "sg:postcode":"1470",
    "sg:province":"Fribourg",
    "wof:name":"Odilon Borgognon Horticulteur",
    "wof:placetype":"venue"
},
  "geometry": {"coordinates":[6.839558,46.851471],"type":"Point"}
}