{
  "type": "Feature",
  "properties": {
    "iso:country":"CH",
    "sg:address":"Koppigensstrasse 25a",
    "sg:city":"Utzenstorf",
    "sg:orig_category":"Herstellung von Elektromotoren, Generatoren U Transformatoren",
    "sg:postcode":"3427",
    "sg:province":"Bern",
    "wof:name":"Bluenergy Sa Impianti E Apparecchiature Nel Settore Energetico; Studio, Progettaz., Realizzaz., Ecc",
    "wof:placetype":"venue"
},
  "geometry": {"coordinates":[9.128364563,46.2376060486],"type":"Point"}
}