{
  "type": "Feature",
  "properties": {
    "iso:country":"CH",
    "sg:address":"Rue Du Buron 14",
    "sg:city":"Yverdon-les-bains",
    "sg:orig_category":"Bauschreinerei Herstellung von M\u00f6beln verschiedener Art",
    "sg:phone":"+41 24 425 92 44",
    "sg:postcode":"1400",
    "sg:province":"Vaud",
    "wof:name":"Claude Bioley Eb\u00e9nisterie",
    "wof:placetype":"venue"
},
  "geometry": {"coordinates":[6.64565,46.774578],"type":"Point"}
}