{
  "type": "Feature",
  "properties": {
    "iso:country":"CH",
    "sg:address":"Via Motta 4",
    "sg:city":"Chiasso",
    "sg:orig_category":"W\u00e4schereien",
    "sg:phone":"+41 91 858 21 42",
    "sg:postcode":"6830",
    "sg:province":"Ticino",
    "wof:name":"Lavanderia Lavanet",
    "wof:placetype":"venue"
},
  "geometry": {"coordinates":[8.9789562225,46.1534881592],"type":"Point"}
}