{
  "type": "Feature",
  "properties": {
    "iso:country":"CH",
    "sg:address":"Hauptstr. 66 Postfach 100",
    "sg:city":"Wollerau",
    "sg:orig_category":"Miscellaneous Products",
    "sg:phone":"+41 4117874646",
    "sg:postcode":"8832",
    "sg:province":"Schwyz",
    "wof:name":"Meister Co. Ag",
    "wof:placetype":"venue"
},
  "geometry": {"coordinates":[-96.6921539307,30.1632232666],"type":"Point"}
}