{
  "type": "Feature",
  "properties": {
    "iso:country":"CH",
    "sg:address":"Bains Route Des",
    "sg:city":"St-maurice",
    "sg:orig_category":"Herstellung von Automobilen",
    "sg:postcode":"1890",
    "sg:province":"Valais",
    "wof:name":"Transbois S\u00e0rl",
    "wof:placetype":"venue"
},
  "geometry": {"coordinates":[7.0044598579,46.2167739868],"type":"Point"}
}