{
  "type": "Feature",
  "properties": {
    "iso:country":"CH",
    "sg:address":"Alte Passwangstrasse 475",
    "sg:city":"M\u00fcmliswil",
    "sg:orig_category":"Vorschulen, Kinderg\u00e4rten",
    "sg:postcode":"4717",
    "sg:province":"Solothurn",
    "wof:name":"Kindergarten",
    "wof:placetype":"venue"
},
  "geometry": {"coordinates":[7.7012329102,47.3438682556],"type":"Point"}
}