{
  "type": "Feature",
  "properties": {
    "iso:country":"CH",
    "sg:address":"Hauptstrasse 40 4552 Derendingen. Postfach",
    "sg:city":"Derendingen",
    "sg:orig_category":"Handel mit Motorr\u00e4dern, Teilen U Zubeh\u00f6r Instandhaltung U Reparatur von Motorr\u00e4dern",
    "sg:phone":"+41 71 923 48 08",
    "sg:postcode":"4552",
    "sg:province":"Solothurn",
    "wof:name":"2-rad Bossi",
    "wof:placetype":"venue"
},
  "geometry": {"coordinates":[9.0501642227,47.4524116516],"type":"Point"}
}