{
  "type": "Feature",
  "properties": {
    "iso:country":"CH",
    "sg:address":"Oelegasse 87",
    "sg:city":"Kerzers",
    "sg:orig_category":"Detailhandel mit elektrischen Haushalts-,Radio U Fernsehger\u00e4ten sowie Musikinstrumenten",
    "sg:phone":"+41 31516649",
    "sg:postcode":"3210",
    "sg:province":"Fribourg",
    "wof:name":"Schnoutz-records, Eric Merz",
    "wof:placetype":"venue"
},
  "geometry": {"coordinates":[7.2089118958,46.9732818604],"type":"Point"}
}