{
  "type": "Feature",
  "properties": {
    "iso:country":"CH",
    "sg:address":"Oberdorfstrasse 21",
    "sg:city":"Steffisburg",
    "sg:classifiers":[
        {
            "category":"Travel",
            "subcategory":"Hotels & Motels",
            "type":"Entertainment"
        }
    ],
    "sg:postcode":"3612",
    "sg:province":"Bern",
    "sg:tags":[
        "hotels",
        "mit",
        "restaurant"
    ],
    "wof:name":"Hotel Restaurant B\u00e4ren, Hp. Blum",
    "wof:placetype":"venue"
},
  "geometry": {"coordinates":[7.6336789131,46.7800979614],"type":"Point"}
}