{
  "type": "Feature",
  "properties": {
    "iso:country":"CH",
    "sg:address":"Kramgasse 14",
    "sg:city":"Bern",
    "sg:orig_category":"Detailhandel mit Uhren U Schmuck Fachdetailhandel in Verkaufsr\u00e4umen",
    "sg:phone":"+41 31 311 12 60",
    "sg:postcode":"3011",
    "sg:province":"Bern",
    "wof:name":"Skala Franz, Uhren Und Bijouterie",
    "wof:placetype":"venue"
},
  "geometry": {"coordinates":[7.4516010284,46.9481201172],"type":"Point"}
}