{
  "type": "Feature",
  "properties": {
    "iso:country":"CH",
    "sg:address":"General-guisan-strasse 30",
    "sg:city":"Zug",
    "sg:orig_category":"Handelsvermittlung U Grosshandel Sonstiger Grosshandel",
    "sg:phone":"+41 41 710 52 62",
    "sg:postcode":"6300",
    "sg:province":"Zug",
    "wof:name":"Peter Alpha Gmbh",
    "wof:placetype":"venue"
},
  "geometry": {"coordinates":[8.5033836365,47.1801986694],"type":"Point"}
}