{
  "type": "Feature",
  "properties": {
    "addr:full":"Unterleh 13 6300 Zug. Postfach Zug Zug 6301",
    "addr:housenumber":"13",
    "addr:postcode":"6300;postfach;6301",
    "addr:street":"Unterleh;Zug",
    "iso:country":"CH",
    "sg:address":"Unterleh 13 6300 Zug. Postfach",
    "sg:city":"Zug",
    "sg:orig_category":"Architekturb\u00fcros",
    "sg:phone":"+41 41 710 32 62",
    "sg:postcode":"6301",
    "sg:province":"Zug",
    "wof:name":"Christoph Luchsinger Architekturb\u00fcro",
    "wof:placetype":"venue"
},
  "geometry": {"coordinates":[8.522211,47.167046],"type":"Point"}
}