{
  "type": "Feature",
  "properties": {
    "addr:full":"Seestrasse 18 Neuenhof Aargau 5432",
    "addr:housenumber":"18",
    "addr:postcode":"5432",
    "addr:street":"Seestrasse",
    "iso:country":"CH",
    "sg:address":"Seestrasse 18",
    "sg:city":"Neuenhof",
    "sg:orig_category":"Aluminium-Glass Fa\u00e7ades",
    "sg:phone":"+41 56 416 02 00",
    "sg:postcode":"5432",
    "sg:province":"Aargau",
    "wof:name":"Diralsa Ag",
    "wof:placetype":"venue"
},
  "geometry": {"coordinates":[8.327222,47.456207],"type":"Point"}
}