{
  "type": "Feature",
  "properties": {
    "iso:country":"CH",
    "sg:address":"Via Alle Gerre 1 6596 Gordola Casella Postale 149",
    "sg:city":"Gordola",
    "sg:orig_category":"Non-Classified Establishments",
    "sg:postcode":"6596",
    "sg:province":"Ticino",
    "wof:name":"Rege Ag",
    "wof:placetype":"venue"
},
  "geometry": {"coordinates":[8.3115491867,46.9846305847],"type":"Point"}
}