{
  "type": "Feature",
  "properties": {
    "iso:country":"CH",
    "sg:address":"Hans Huber-strasse 8",
    "sg:city":"Z\u00fcrich",
    "sg:orig_category":"Malerei Tapeziererei",
    "sg:phone":"+41 12028231",
    "sg:postcode":"8002",
    "sg:province":"Z\u00fcrich",
    "wof:name":"Werner Attinger Maler-& Tapezierergesch\u00e4ft",
    "wof:placetype":"venue"
},
  "geometry": {"coordinates":[8.5300769806,47.3538856506],"type":"Point"}
}