{
  "type": "Feature",
  "properties": {
    "addr:full":"Ringstrasse 1 4600 Olten. Postfach Olten Solothurn 4600",
    "addr:housenumber":"1",
    "addr:postcode":"4600 olten. postfach;4600",
    "addr:street":"Ringstrasse",
    "iso:country":"CH",
    "sg:address":"Ringstrasse 1 4600 Olten. Postfach",
    "sg:city":"Olten",
    "sg:orig_category":"Bau von Strassen, Sportanlagen U Bahnverkehrsstrecken",
    "sg:postcode":"4600",
    "sg:province":"Solothurn",
    "wof:name":"Albert K\u00f6ppel Ag",
    "wof:placetype":"venue"
},
  "geometry": {"coordinates":[9.199251,47.521545],"type":"Point"}
}