{
  "type": "Feature",
  "properties": {
    "addr:full":"Rue Du Creux Du Van 3 1530 Payerne Case Postale 59 Payerne Vaud 1530",
    "addr:housenumber":"3",
    "addr:postcode":"1530;59;1530",
    "addr:street":"Rue Du Creux Du Van;Postale",
    "iso:country":"CH",
    "sg:address":"Rue Du Creux Du Van 3 1530 Payerne Case Postale 59",
    "sg:city":"Payerne",
    "sg:orig_category":"Allgemeiner Hoch U Tiefbau Allgemeiner Hochbau",
    "sg:phone":"+41 26 660 21 24",
    "sg:postcode":"1530",
    "sg:province":"Vaud",
    "wof:name":"Bianchi Fr\u00e8res Sa",
    "wof:placetype":"venue"
},
  "geometry": {"coordinates":[6.928432,46.819157],"type":"Point"}
}