{
  "type": "Feature",
  "properties": {
    "iso:country":"CH",
    "sg:address":"Viale Franscini 25",
    "sg:city":"Bellinzona",
    "sg:orig_category":"Sprachschulen",
    "sg:phone":"+41 61 751 22 38",
    "sg:postcode":"6500",
    "sg:province":"Ticino",
    "wof:name":"Sprach-& Sportschule Aesch Sekretariat Frau Pia Heilig",
    "wof:placetype":"venue"
},
  "geometry": {"coordinates":[7.5929141045,47.4730491638],"type":"Point"}
}