{
  "type": "Feature",
  "properties": {
    "iso:country":"CH",
    "sg:address":"Obere Hauptgasse 41",
    "sg:city":"Thun",
    "sg:orig_category":"Detailhandel mit elektrischen Haushalts-,Radio U Fernsehger\u00e4ten sowie Musikinstrumenten",
    "sg:postcode":"3600",
    "sg:province":"Bern",
    "wof:name":"Musig-ch\u00e4ller, Stucki Paul",
    "wof:placetype":"venue"
},
  "geometry": {"coordinates":[7.630106926,46.7587203979],"type":"Point"}
}