{
  "type": "Feature",
  "properties": {
    "iso:country":"CH",
    "sg:address":"Hauptstrasse 15 8224 L\u00f6hningen. Postfach",
    "sg:city":"Nebikon",
    "sg:orig_category":"Sanit\u00e4r, Heizungs U L\u00fcftungsinstallation Sanit\u00e4rinstallation",
    "sg:phone":"+41 52 685 24 77",
    "sg:postcode":"6244",
    "sg:province":"Luzern",
    "wof:name":"M\u00fcller Roger, Sanit\u00e4re Anlagen + Heizungen Sanit\u00e4re Anlagen, Heizungen; Planung Ausf\u00fchrung",
    "wof:placetype":"venue"
},
  "geometry": {"coordinates":[8.5550527573,47.7012214661],"type":"Point"}
}