{
  "type": "Feature",
  "properties": {
    "iso:country":"CH",
    "sg:address":"Chalet Erika",
    "sg:city":"Pontresina",
    "sg:orig_category":"Sanit\u00e4r U Heizungsinstallation Sanit\u00e4r, Heizungs U L\u00fcftungsinstallation",
    "sg:phone":"+41 81 842 61 34",
    "sg:postcode":"7504",
    "sg:province":"Graubunden",
    "wof:name":"Horst Knauer Heizungen",
    "wof:placetype":"venue"
},
  "geometry": {"coordinates":[9.9072599411,46.4901542664],"type":"Point"}
}