{
  "type": "Feature",
  "properties": {
    "iso:country":"CH",
    "sg:address":"Rue Du Marterey 7",
    "sg:city":"Lausanne",
    "sg:orig_category":"Physiotherapie",
    "sg:phone":"+41 21 311 04 93",
    "sg:postcode":"1005",
    "sg:province":"Vaud",
    "wof:name":"Carl Fryns Physioth\u00e9rapie",
    "wof:placetype":"venue"
},
  "geometry": {"coordinates":[6.6380591393,46.520526886],"type":"Point"}
}