{
  "type": "Feature",
  "properties": {
    "iso:country":"CH",
    "sg:address":"Effingerstrasse 8 3011 Bern. Postfach 7553",
    "sg:city":"Bern",
    "sg:orig_category":"Handelsvermittlung U Grosshandel Zeitungsverlag",
    "sg:phone":"+41 31 382 34 00",
    "sg:postcode":"3001",
    "sg:province":"Bern",
    "wof:name":"Plattform Ag",
    "wof:placetype":"venue"
},
  "geometry": {"coordinates":[7.4363241196,46.9459381104],"type":"Point"}
}