{
  "type": "Feature",
  "properties": {
    "iso:country":"CH",
    "sg:address":"Kopfgasse 1",
    "sg:city":"B\u00fclach",
    "sg:orig_category":"RESTAURANTS: TEA-ROOMS",
    "sg:phone":"+41 18621820",
    "sg:postcode":"8180",
    "sg:province":"Z\u00fcrich",
    "wof:name":"Restaurant Mr.pickwick",
    "wof:placetype":"venue"
},
  "geometry": {"coordinates":[8.5410556793,47.5188140869],"type":"Point"}
}