{
  "type": "Feature",
  "properties": {
    "iso:country":"CH",
    "sg:address":"Rheintalstrasse 61",
    "sg:city":"Leibstadt",
    "sg:orig_category":"Architekturb\u00fcros",
    "sg:phone":"+41 56 247 13 61",
    "sg:postcode":"5325",
    "sg:province":"Aargau",
    "wof:name":"Holenstein & Jufer Architekturb\u00fcro",
    "wof:placetype":"venue"
},
  "geometry": {"coordinates":[8.174661,47.590141],"type":"Point"}
}