{
  "type": "Feature",
  "properties": {
    "iso:country":"CH",
    "sg:address":"Vorbuchenstrasse 17",
    "sg:city":"Bassersdorf",
    "sg:orig_category":"Grosshandel mit sonstigen Maschinen U Ausr\u00fcstungen f\u00fcr Industrie, Handel U Schiffahrt Nutzfahrzeuge ",
    "sg:postcode":"8303",
    "sg:province":"Z\u00fcrich",
    "wof:name":"Pronet Ag",
    "wof:placetype":"venue"
},
  "geometry": {"coordinates":[9.037191391,47.462146759],"type":"Point"}
}