{
  "type": "Feature",
  "properties": {
    "iso:country":"CH",
    "sg:address":"Winkelstrasse 37 8706 Meilen. Postfach 628",
    "sg:city":"Meilen",
    "sg:orig_category":"Elektroinstallation",
    "sg:phone":"+41 19237070",
    "sg:postcode":"8706",
    "sg:province":"Z\u00fcrich",
    "wof:name":"Hardmeier Ag, Elektro-telecom, Zweigniederlassung Meilen",
    "wof:placetype":"venue"
},
  "geometry": {"coordinates":[8.6402816772,47.2699508667],"type":"Point"}
}