{
  "type": "Feature",
  "properties": {
    "iso:country":"CH",
    "sg:address":"Hohenzornstrasse 9 8500 Frauenfeld. Postfach 1054",
    "sg:city":"Frauenfeld",
    "sg:orig_category":"Informatikdienste Softwareentwicklung U beratung",
    "sg:phone":"+41 52 721 60 10",
    "sg:postcode":"8500",
    "sg:province":"Thurgau",
    "wof:name":"Unique Control Informatik Gmbh Informatik-dienstleistungen Usw",
    "wof:placetype":"venue"
},
  "geometry": {"coordinates":[8.9012203217,47.5588378906],"type":"Point"}
}