{
  "type": "Feature",
  "properties": {
    "iso:country":"CH",
    "sg:address":"Industriestrasse",
    "sg:city":"Inwil",
    "sg:orig_category":"Handelsvermittlung von Maschinen, technischem Bedarf, Wasser U Luftfahrzeugen",
    "sg:phone":"+41 41 449 90 90",
    "sg:postcode":"6034",
    "sg:province":"Luzern",
    "wof:name":"Holz- Her Schweiz Ag Holzbearbeitungsmaschinen",
    "wof:placetype":"venue"
},
  "geometry": {"coordinates":[8.3493375778,47.1181678772],"type":"Point"}
}