{
  "type": "Feature",
  "properties": {
    "iso:country":"CH",
    "sg:address":"Axenstrasse 65",
    "sg:city":"Fl\u00fcelen",
    "sg:orig_category":"Erbringung von Dienstleistungen f\u00fcr Unternehmen",
    "sg:phone":"+41 41 872 05 00",
    "sg:postcode":"6454",
    "sg:province":"Uri",
    "wof:name":"Arnold Patrik Schriftenmalerei Und Reklamen",
    "wof:placetype":"venue"
},
  "geometry": {"coordinates":[8.6225481033,46.9111251831],"type":"Point"}
}