{
  "type": "Feature",
  "properties": {
    "iso:country":"CH",
    "sg:address":"Burgstrasse 30",
    "sg:city":"Glarus",
    "sg:orig_category":"Schulpflegen",
    "sg:postcode":"8750",
    "sg:province":"Glarus",
    "wof:name":"Schulrat Der Gemeinden Glarus-riedern",
    "wof:placetype":"venue"
},
  "geometry": {"coordinates":[9.0684490204,47.0415840149],"type":"Point"}
}