{
  "type": "Feature",
  "properties": {
    "iso:country":"CH",
    "sg:address":"F\u00e4llandenstrasse 14",
    "sg:city":"Maur",
    "sg:orig_category":"Bauschreinerei Innenausbau",
    "sg:phone":"+41 19800665",
    "sg:postcode":"8124",
    "sg:province":"Z\u00fcrich",
    "wof:name":"Vollenweider & Iselin Schreinerei-innenausbau",
    "wof:placetype":"venue"
},
  "geometry": {"coordinates":[8.667716,47.343201],"type":"Point"}
}