{
  "type": "Feature",
  "properties": {
    "addr:full":"Tirolgasse 96 Kaiserstuhl Aargau 5466",
    "addr:housenumber":"96",
    "addr:postcode":"5466",
    "addr:street":"Tirolgasse",
    "iso:country":"CH",
    "sg:address":"Tirolgasse 96",
    "sg:city":"Kaiserstuhl",
    "sg:classifiers":[
        {
            "category":"Education",
            "subcategory":"Special Training",
            "type":"Public Place"
        }
    ],
    "sg:phone":"+41 18582404",
    "sg:postcode":"5466",
    "sg:province":"Aargau",
    "sg:tags":[
        "steel",
        "aluminium",
        "stainless",
        "material",
        "part",
        "cnc",
        "milled"
    ],
    "wof:name":"Toff Drehteile Ag",
    "wof:placetype":"venue"
},
  "geometry": {"coordinates":[8.41814,47.569256],"type":"Point"}
}