{
  "type": "Feature",
  "properties": {
    "addr:full":"Hauptstr. 40 Oensingen Solothurn 4702",
    "addr:housenumber":"40",
    "addr:postcode":"4702",
    "addr:street":"Hauptstr.",
    "iso:country":"CH",
    "sg:address":"Hauptstr. 40",
    "sg:city":"Oensingen",
    "sg:classifiers":[
        {
            "category":"Banks & Credit Unions",
            "subcategory":"Bank",
            "type":"Services"
        }
    ],
    "sg:phone":"+41 62 388 07 88",
    "sg:postcode":"4702",
    "sg:province":"Solothurn",
    "wof:name":"Credit Suisse",
    "wof:placetype":"venue"
},
  "geometry": {"coordinates":[7.719499,47.290085],"type":"Point"}
}