{
  "type": "Feature",
  "properties": {
    "iso:country":"CH",
    "sg:address":"Rellikonstrasse 7",
    "sg:city":"Maur",
    "sg:orig_category":"Arztpraxen",
    "sg:phone":"+41 19803231",
    "sg:postcode":"8124",
    "sg:province":"Z\u00fcrich",
    "wof:name":"Dr.med.peter Cunier Spezialarzt Fmh",
    "wof:placetype":"venue"
},
  "geometry": {"coordinates":[8.670798,47.339668],"type":"Point"}
}