{
  "type": "Feature",
  "properties": {
    "iso:country":"CH",
    "sg:address":"Bodenackerstrasse 5 8304 Wallisellen. Postfach",
    "sg:city":"Wallisellen",
    "sg:orig_category":"Schreib U \u00dcbersetzungsb\u00fcros",
    "sg:phone":"+41 18312062",
    "sg:postcode":"8304",
    "sg:province":"Z\u00fcrich",
    "wof:name":"Kiss Ursula The Outsourcing Office Sekretariatsaufgaben. Schriftverkehr Zwischen Gesch\u00e4ften, Inventar U. Bestellwesen Usw",
    "wof:placetype":"venue"
},
  "geometry": {"coordinates":[8.5864715576,47.4173851013],"type":"Point"}
}