{
  "type": "Feature",
  "properties": {
    "iso:country":"CH",
    "sg:address":"Rue Elie Bertrand 2",
    "sg:city":"Yverdon-les-bains",
    "sg:orig_category":"Verlegen von Fliesen U Platten",
    "sg:phone":"+41 24 425 25 02",
    "sg:postcode":"1400",
    "sg:province":"Vaud",
    "wof:name":"St\u00e9phane B\u00fchler Rev\u00eatements De Sols",
    "wof:placetype":"venue"
},
  "geometry": {"coordinates":[6.6412758827,46.7697982788],"type":"Point"}
}