{
  "type": "Feature",
  "properties": {
    "iso:country":"CH",
    "sg:address":"Rue De La Prairie 17",
    "sg:city":"Gen\u00e8ve",
    "sg:orig_category":"Direktwerbeagenturen Grafikateliers, Design",
    "sg:phone":"+41 22 339 30 30",
    "sg:postcode":"1202",
    "sg:province":"Gen\u00e8ve",
    "wof:name":"Rive Gauche Communication",
    "wof:placetype":"venue"
},
  "geometry": {"coordinates":[6.1348400116,46.2098426819],"type":"Point"}
}