{
  "type": "Feature",
  "properties": {
    "iso:country":"CH",
    "sg:address":"Standweg 7",
    "sg:city":"Grenchen",
    "sg:orig_category":"Detailhandel mit Uhren U Schmuck Fachdetailhandel in Verkaufsr\u00e4umen",
    "sg:phone":"+41 32 652 27 57",
    "sg:postcode":"2540",
    "sg:province":"Solothurn",
    "wof:name":"Kurt Hertner Goldschmied",
    "wof:placetype":"venue"
},
  "geometry": {"coordinates":[7.3936448097,47.2016067505],"type":"Point"}
}