{
  "type": "Feature",
  "properties": {
    "iso:country":"CH",
    "sg:address":"Terbinerstrasse 6 3930 Visp Case Postale 372",
    "sg:city":"Visp",
    "sg:orig_category":"Elektrizit\u00e4tsversorgung",
    "sg:phone":"+41 17373791",
    "sg:postcode":"3930",
    "sg:province":"Valais",
    "wof:name":"Walu Lutz W. Ing. B\u00fcro F\u00fcr Umwelt Und Verfahrenstechnik",
    "wof:placetype":"venue"
},
  "geometry": {"coordinates":[8.4344491959,47.356262207],"type":"Point"}
}