{
  "type": "Feature",
  "properties": {
    "iso:country":"CH",
    "sg:address":"Viale Pereda 2",
    "sg:city":"Balerna",
    "sg:orig_category":"Erbringung von Dienstleistungen f\u00fcr Unternehmen",
    "sg:postcode":"6828",
    "sg:province":"Ticino",
    "wof:name":"Publiccit\u00e0 Di Martignoni G. E Brughera M.",
    "wof:placetype":"venue"
},
  "geometry": {"coordinates":[9.0152378082,45.8410301208],"type":"Point"}
}