{
  "type": "Feature",
  "properties": {
    "iso:country":"CH",
    "sg:address":"M\u00fcrtschenstrasse 5",
    "sg:city":"Goldingen",
    "sg:orig_category":"Sonstiger spezialisierter Hoch U Tiefbau",
    "sg:phone":"+41 55 284 22 91",
    "sg:postcode":"8638",
    "sg:province":"St. Gallen",
    "wof:name":"Schulthess Daniel",
    "wof:placetype":"venue"
},
  "geometry": {"coordinates":[8.9686613083,47.2557983398],"type":"Point"}
}