{
  "type": "Feature",
  "properties": {
    "iso:country":"CH",
    "sg:address":"Walther-hauser-strasse 12",
    "sg:city":"W\u00e4denswil",
    "sg:classifiers":[
        {
            "category":"Insurance",
            "subcategory":"Insurance Agent",
            "type":"Services"
        }
    ],
    "sg:phone":"+41 17805630",
    "sg:postcode":"8820",
    "sg:province":"Z\u00fcrich",
    "sg:tags":[
        "versicherungsagenturen",
        "-broker"
    ],
    "wof:name":"Leo Birrer Agentur Rentenanstalt",
    "wof:placetype":"venue"
},
  "geometry": {"coordinates":[8.6762781143,47.2168083191],"type":"Point"}
}