{
  "type": "Feature",
  "properties": {
    "addr:full":"6003 Luzern. Postfach 3637 Luzern Luzern 6002",
    "addr:postcode":"6003;3637;6002",
    "addr:street":"Postfach",
    "iso:country":"CH",
    "sg:address":"6003 Luzern. Postfach 3637",
    "sg:city":"Luzern",
    "sg:orig_category":"Arbeitnehmerverb\u00e4nde",
    "sg:phone":"+41 41 208 89 02",
    "sg:postcode":"6002",
    "sg:province":"Luzern",
    "wof:name":"Lehrerverein Der Stadt Luzern",
    "wof:placetype":"venue"
},
  "geometry": {"coordinates":[8.29527,47.053661],"type":"Point"}
}