{
  "type": "Feature",
  "properties": {
    "iso:country":"CH",
    "sg:address":"Frutigenstrasse 33",
    "sg:city":"Thun",
    "sg:orig_category":"Arztpraxen",
    "sg:phone":"+41 33 223 27 45",
    "sg:postcode":"3600",
    "sg:province":"Bern",
    "wof:name":"Dr.med.andreas Leuenberger Arzt F\u00fcr Allgemeine Medizin",
    "wof:placetype":"venue"
},
  "geometry": {"coordinates":[7.626657,46.751343],"type":"Point"}
}