{
  "type": "Feature",
  "properties": {
    "iso:country":"CH",
    "sg:address":"Im Grund 5",
    "sg:city":"Wigoltingen",
    "sg:orig_category":"Vereine Geselligkeit",
    "sg:phone":"+41 52 763 21 56",
    "sg:postcode":"8556",
    "sg:province":"Thurgau",
    "wof:name":"Berner-verein Niesen Mittelthurgau",
    "wof:placetype":"venue"
},
  "geometry": {"coordinates":[9.0347070694,47.5993156433],"type":"Point"}
}