{
  "type": "Feature",
  "properties": {
    "iso:country":"CH",
    "sg:address":"Mooosstrasse 3",
    "sg:city":"Sch\u00f6nb\u00fchl-urtenen",
    "sg:orig_category":"Grosshandel mit B\u00fcromaschinen U einrichtungen",
    "sg:phone":"+41 31 850 30 30",
    "sg:postcode":"3322",
    "sg:province":"Bern",
    "wof:name":"Ozalid Ag Toshiba Infotec Kopierer, Fax & Printersysteme",
    "wof:placetype":"venue"
},
  "geometry": {"coordinates":[7.4960050583,47.0172424316],"type":"Point"}
}