{
  "type": "Feature",
  "properties": {
    "iso:country":"CH",
    "sg:address":"Oberauweg 5",
    "sg:city":"Zizers",
    "sg:orig_category":"Bauschreinerei Zimmerei, Ingenieurholzbau",
    "sg:phone":"+41 34 493 35 10",
    "sg:postcode":"7205",
    "sg:province":"Graubunden",
    "wof:name":"Hans Gr\u00fcter Mech.zimmerei & Schreinerei",
    "wof:placetype":"venue"
},
  "geometry": {"coordinates":[7.902688,46.853001],"type":"Point"}
}