{
  "type": "Feature",
  "properties": {
    "iso:country":"CH",
    "sg:address":"Zone Ind. En Reculan",
    "sg:city":"Bussigny-lausanne",
    "sg:orig_category":"Detailhandel Einzelhandel mit Automobilteilen U Zubeh\u00f6r Reparatur von Gebrauchsg\u00fctern",
    "sg:phone":"+41 21 701 45 45",
    "sg:postcode":"1030",
    "sg:province":"Vaud",
    "wof:name":"Adam Touring S\u00e0rl",
    "wof:placetype":"venue"
},
  "geometry": {"coordinates":[6.5548272133,46.5405387878],"type":"Point"}
}