{
  "type": "Feature",
  "properties": {
    "iso:country":"CH",
    "sg:address":"Cuvillard",
    "sg:city":"Aclens",
    "sg:orig_category":"Fachdetailhandel in Verkaufsr\u00e4umen",
    "sg:phone":"+41 21 869 01 01",
    "sg:postcode":"1123",
    "sg:province":"Vaud",
    "wof:name":"Sevymob Sa",
    "wof:placetype":"venue"
},
  "geometry": {"coordinates":[6.5100498199,46.5683288574],"type":"Point"}
}