{
  "type": "Feature",
  "properties": {
    "iso:country":"CH",
    "sg:address":"Roveray 1170 Aubonne Case Postale 5",
    "sg:city":"Aubonne",
    "sg:orig_category":"Instandhaltung U Reparatur von Automobilen",
    "sg:phone":"+41 21 807 39 02",
    "sg:postcode":"1170",
    "sg:province":"Vaud",
    "wof:name":"Garage-carrosserie En Roveray Sa",
    "wof:placetype":"venue"
},
  "geometry": {"coordinates":[6.4023752213,46.4810142517],"type":"Point"}
}