{
  "type": "Feature",
  "properties": {
    "iso:country":"CH",
    "sg:address":"Xxxi-d\u00e9cembre Rue Du 15 1207 Gen\u00e8ve. Postfach",
    "sg:city":"Gen\u00e8ve",
    "sg:orig_category":"Grosshandel mit sonstigen Gebrauchs U Verbrauchsg\u00fctern",
    "sg:postcode":"1207",
    "sg:province":"Gen\u00e8ve",
    "wof:name":"Gonis Happle Gabriele",
    "wof:placetype":"venue"
},
  "geometry": {"coordinates":[8.8623504639,47.6609916687],"type":"Point"}
}