{
  "type": "Feature",
  "properties": {
    "iso:country":"CH",
    "sg:address":"Rue De Bellevue 7 2074 Marin-centre Case Postale 111",
    "sg:city":"Marin-centre",
    "sg:orig_category":"Mechanik Mechanische Werkst\u00e4tten",
    "sg:phone":"+41 32 753 48 65",
    "sg:postcode":"2074",
    "sg:province":"Neuch\u00e2tel",
    "wof:name":"Bepa S\u00e0rl",
    "wof:placetype":"venue"
},
  "geometry": {"coordinates":[7.0054759979,47.0093688965],"type":"Point"}
}