{
  "type": "Feature",
  "properties": {
    "iso:country":"CH",
    "sg:address":"Olsbergerstrasse 6 4310 Rheinfelden. Postfach",
    "sg:city":"Rheinfelden",
    "sg:orig_category":"Herstellung von Metallkonstruktionen",
    "sg:phone":"+41 61 831 28 87",
    "sg:postcode":"4310",
    "sg:province":"Aargau",
    "wof:name":"Signori Metallbau Ag",
    "wof:placetype":"venue"
},
  "geometry": {"coordinates":[7.7968988419,47.5452728271],"type":"Point"}
}