{
  "type": "Feature",
  "properties": {
    "iso:country":"CH",
    "sg:address":"Gewerbestrasse 2",
    "sg:city":"Lausen",
    "sg:orig_category":"Maler U Glasergewerbe Malerei",
    "sg:phone":"+41 61 922 19 22",
    "sg:postcode":"4415",
    "sg:province":"Basel-Landschaft",
    "wof:name":"Oesch Malergesch\u00e4ft",
    "wof:placetype":"venue"
},
  "geometry": {"coordinates":[7.7588481903,47.4719696045],"type":"Point"}
}