{
  "type": "Feature",
  "properties": {
    "iso:country":"CH",
    "sg:address":"Rue De L'ancienne Pointe 24 1920 Martigny Case Postale",
    "sg:city":"Martigny",
    "sg:orig_category":"Architektur U Ingenieurb\u00fcros Herstellung von Elektrizit\u00e4tsverteilungs U schalteinrichtungen",
    "sg:phone":"+41 27 722 93 61",
    "sg:postcode":"1920",
    "sg:province":"Valais",
    "wof:name":"Alro Engineering Sa",
    "wof:placetype":"venue"
},
  "geometry": {"coordinates":[7.094283,46.110382],"type":"Point"}
}