{
  "type": "Feature",
  "properties": {
    "iso:country":"CH",
    "sg:address":"Freiestrasse 30",
    "sg:city":"Uster",
    "sg:orig_category":"Detailhandel mit Fahrr\u00e4dern Handel mit Motorr\u00e4dern, Teilen U Zubeh\u00f6r Instandhaltung U Reparatur von ",
    "sg:phone":"+41 19291172",
    "sg:postcode":"8610",
    "sg:province":"Z\u00fcrich",
    "wof:name":"Hans-rudolf Br\u00fcngger Motorcycles",
    "wof:placetype":"venue"
},
  "geometry": {"coordinates":[8.7217645645,47.269908905],"type":"Point"}
}