{
  "type": "Feature",
  "properties": {
    "iso:country":"CH",
    "sg:address":"Moosholzstrasse 11 9322 Egnach. Postfach",
    "sg:city":"Egnach",
    "sg:orig_category":"Instandhaltung U Reparatur von Automobilen",
    "sg:phone":"+41 33 336 34 05",
    "sg:postcode":"9322",
    "sg:province":"Thurgau",
    "wof:name":"Autospritzwerk Kyburz, Inh. Rud. Jordi",
    "wof:placetype":"venue"
},
  "geometry": {"coordinates":[7.6179609299,46.7301673889],"type":"Point"}
}