{
  "type": "Feature",
  "properties": {
    "iso:country":"CH",
    "sg:address":"Stephan Route Henri 14",
    "sg:city":"Givisiez",
    "sg:orig_category":"Bau von Strassen, Sportanlagen U Bahnverkehrsstrecken",
    "sg:postcode":"1762",
    "sg:province":"Fribourg",
    "wof:name":"Gravisa S.a.",
    "wof:placetype":"venue"
},
  "geometry": {"coordinates":[7.131073,46.813923],"type":"Point"}
}