{
  "type": "Feature",
  "properties": {
    "iso:country":"CH",
    "sg:address":"Sch\u00fcracherstrasse 4",
    "sg:city":"Br\u00fcttisellen",
    "sg:orig_category":"Vorschulen, Kinderg\u00e4rten",
    "sg:phone":"+41 18332312",
    "sg:postcode":"8306",
    "sg:province":"Z\u00fcrich",
    "wof:name":"Kindergarten Dorf",
    "wof:placetype":"venue"
},
  "geometry": {"coordinates":[8.6308231354,47.4228172302],"type":"Point"}
}