{
  "type": "Feature",
  "properties": {
    "addr:full":"Ernastrasse 20 Z\u00fcrich Z\u00fcrich 8004",
    "addr:housenumber":"20",
    "addr:postcode":"8004",
    "addr:street":"Ernastrasse",
    "iso:country":"CH",
    "sg:address":"Ernastrasse 20",
    "sg:city":"Z\u00fcrich",
    "sg:orig_category":"Architektur U Ingenieurb\u00fcros Architekturb\u00fcros",
    "sg:phone":"+41 12810711",
    "sg:postcode":"8004",
    "sg:province":"Z\u00fcrich",
    "wof:name":"Christen Urs Architekt Htl",
    "wof:placetype":"venue"
},
  "geometry": {"coordinates":[8.516987,47.380791],"type":"Point"}
}