{
  "type": "Feature",
  "properties": {
    "iso:country":"CH",
    "sg:address":"Iseliguet 2 8750 Glarus. Postfach",
    "sg:city":"Bilten",
    "sg:orig_category":"Grosshandel mit Nahrungsmitteln, Getr\u00e4nken U Tabakwaren ohne ausgepr\u00e4gten Schwerpunkt",
    "sg:postcode":"8865",
    "sg:province":"Glarus",
    "wof:name":"Lebensmittelgesch\u00e4ft Egli",
    "wof:placetype":"venue"
},
  "geometry": {"coordinates":[9.3592128754,47.417175293],"type":"Point"}
}