{
  "type": "Feature",
  "properties": {
    "iso:country":"CH",
    "sg:address":"Bankgasse 4",
    "sg:city":"Appenzell",
    "sg:orig_category":"Bauschreinerei Detailhandel mit Metallwaren, Anstrichmitteln, Glaswaren, Bau U Heimwerkerbedarf",
    "sg:postcode":"9050",
    "sg:province":"Appenzell Innerhoden",
    "wof:name":"Albin B\u00fcchler",
    "wof:placetype":"venue"
},
  "geometry": {"coordinates":[9.4087,47.32909],"type":"Point"}
}