{
  "type": "Feature",
  "properties": {
    "iso:country":"CH",
    "sg:address":"Luzernerstrasse 33d",
    "sg:city":"Kriens",
    "sg:orig_category":"Instandhaltung U Reparatur von Automobilen",
    "sg:phone":"+41 41 320 00 29",
    "sg:postcode":"6010",
    "sg:province":"Luzern",
    "wof:name":"Dorfgarage Frank & Mihaljevic",
    "wof:placetype":"venue"
},
  "geometry": {"coordinates":[8.2850818634,47.0344352722],"type":"Point"}
}