{
  "type": "Feature",
  "properties": {
    "iso:country":"CH",
    "sg:address":"Viaduktstrasse 33",
    "sg:city":"Basel",
    "sg:orig_category":"Berufliche Weiterbildung, Erwachsenenbildung",
    "sg:phone":"+41 61 288 72 72",
    "sg:postcode":"4052",
    "sg:province":"Basel-Stadt",
    "wof:name":"Ubs Ausbildungs-& Konferenzzentrum",
    "wof:placetype":"venue"
},
  "geometry": {"coordinates":[7.584719,47.549015],"type":"Point"}
}