{
  "type": "Feature",
  "properties": {
    "iso:country":"CH",
    "sg:address":"Seestrasse.",
    "sg:city":"Innerthal",
    "sg:orig_category":"Grosshandel mit sonstigen Nahrungsmitteln",
    "sg:postcode":"8858",
    "sg:province":"Schwyz",
    "wof:name":"Schmid-schuler Heinz.",
    "wof:placetype":"venue"
},
  "geometry": {"coordinates":[8.9311647415,47.0934371948],"type":"Point"}
}