{
  "type": "Feature",
  "properties": {
    "iso:country":"CH",
    "sg:address":"3946",
    "sg:city":"Turtmann",
    "sg:orig_category":"Grosshandel mit Nahrungsmitteln, Getr\u00e4nken U Tabakwaren ohne ausgepr\u00e4gten Schwerpunkt",
    "sg:phone":"+41 27 932 13 05",
    "sg:postcode":"3946",
    "sg:province":"Valais",
    "wof:name":"Konsumgenossenschaft Turtmann",
    "wof:placetype":"venue"
},
  "geometry": {"coordinates":[7.7031202316,46.3017997742],"type":"Point"}
}