{
  "type": "Feature",
  "properties": {
    "iso:country":"CH",
    "sg:address":"Obere Zollgasse 35",
    "sg:city":"Ostermundigen",
    "sg:orig_category":"Detailhandel mit Zeitungen U Zeitschriften Kioske",
    "sg:phone":"+41 31 931 07 94",
    "sg:postcode":"3072",
    "sg:province":"Bern",
    "wof:name":"Anne-marie Winter Kiosk",
    "wof:placetype":"venue"
},
  "geometry": {"coordinates":[7.4856820107,46.954082489],"type":"Point"}
}