{
  "type": "Feature",
  "properties": {
    "addr:full":"Madretschstrasse 33 Biel/bienne Bern 2503",
    "addr:housenumber":"33",
    "addr:postcode":"2503",
    "addr:street":"Madretschstrasse",
    "iso:country":"CH",
    "sg:address":"Madretschstrasse 33",
    "sg:city":"Biel/bienne",
    "sg:classifiers":[
        {
            "category":"Structure",
            "subcategory":"Building",
            "type":"Public Place"
        }
    ],
    "sg:phone":"+41 32 365 82 74",
    "sg:postcode":"2503",
    "sg:province":"Bern",
    "sg:tags":[
        "canopy"
    ],
    "wof:name":"Metallbau Steiner Gmbh",
    "wof:placetype":"venue"
},
  "geometry": {"coordinates":[7.253099,47.132843],"type":"Point"}
}