{
  "type": "Feature",
  "properties": {
    "iso:country":"CH",
    "sg:address":"Lindenhubel 10",
    "sg:city":"Kerzers",
    "sg:orig_category":"Fussboden, Fliesen U Plattenlegerei, Tapeziererei Verlegen von Fliesen U Platten",
    "sg:phone":"+41 31 755 58 24",
    "sg:postcode":"3210",
    "sg:province":"Fribourg",
    "wof:name":"Gurtner Hans",
    "wof:placetype":"venue"
},
  "geometry": {"coordinates":[7.2031440735,46.9786605835],"type":"Point"}
}