{
  "type": "Feature",
  "properties": {
    "iso:country":"CH",
    "sg:address":"Waldblickstrasse 2",
    "sg:city":"Wabern",
    "sg:orig_category":"Chemische Reinigung",
    "sg:phone":"+41 31 961 35 69",
    "sg:postcode":"3084",
    "sg:province":"Bern",
    "wof:name":"Alles Rein Textilreinigung",
    "wof:placetype":"venue"
},
  "geometry": {"coordinates":[7.450314,46.929157],"type":"Point"}
}