{
  "type": "Feature",
  "properties": {
    "iso:country":"CH",
    "sg:address":"Rigacher 1",
    "sg:city":"Lindau",
    "sg:orig_category":"Allgemeiner Hoch U Tiefbau Strassenbau",
    "sg:phone":"+41 52 345 18 94",
    "sg:postcode":"8315",
    "sg:province":"Z\u00fcrich",
    "wof:name":"Brunner Erben Ag Z\u00fcrich Bauunternehmung",
    "wof:placetype":"venue"
},
  "geometry": {"coordinates":[8.68099,47.439144],"type":"Point"}
}