{
  "type": "Feature",
  "properties": {
    "iso:country":"CH",
    "sg:address":"Konstanzerstrasse 46",
    "sg:city":"Kreuzlingen",
    "sg:orig_category":"Non-Classified Establishments",
    "sg:postcode":"8280",
    "sg:province":"Thurgau",
    "wof:name":"Dmg Holdings (iceland) Ehf., Reykjavik, Zweigniederlassung Kreuzlingen",
    "wof:placetype":"venue"
},
  "geometry": {"coordinates":[9.1651687622,47.6510658264],"type":"Point"}
}