{
  "type": "Feature",
  "properties": {
    "iso:country":"CH",
    "sg:address":"Route Du Chili 29",
    "sg:city":"Monthey",
    "sg:classifiers":[
        {
            "category":"Building & Trades",
            "subcategory":"Landscaping Services",
            "type":"Services"
        }
    ],
    "sg:phone":"+41 24 471 21 54",
    "sg:postcode":"1870",
    "sg:province":"Valais",
    "sg:tags":[
        "equipment",
        "beekeeping"
    ],
    "wof:name":"Rithner & Cie",
    "wof:placetype":"venue"
},
  "geometry": {"coordinates":[6.946348,46.248344],"type":"Point"}
}