{
  "type": "Feature",
  "properties": {
    "iso:country":"CH",
    "sg:address":"Trockenloostrasse 37",
    "sg:city":"Regensdorf",
    "sg:orig_category":"Architektur U Ingenieurb\u00fcros",
    "sg:phone":"+41 17481533",
    "sg:postcode":"8105",
    "sg:province":"Z\u00fcrich",
    "wof:name":"Y.p.d. Project Gmbh",
    "wof:placetype":"venue"
},
  "geometry": {"coordinates":[8.474472,47.440632],"type":"Point"}
}