{
  "type": "Feature",
  "properties": {
    "iso:country":"CH",
    "sg:address":"Spitzackerweg 18",
    "sg:city":"Fahrwangen",
    "sg:orig_category":"Kosmetikinstitute",
    "sg:phone":"+41 79 236 07 05",
    "sg:postcode":"5615",
    "sg:province":"Aargau",
    "wof:name":"Burgi Muheim Kosmetikinstitut",
    "wof:placetype":"venue"
},
  "geometry": {"coordinates":[8.2439622879,47.2981948853],"type":"Point"}
}