{
  "type": "Feature",
  "properties": {
    "iso:country":"CH",
    "sg:address":"9058",
    "sg:city":"Br\u00fclisau",
    "sg:orig_category":"Vereine Musik/Blasmusik",
    "sg:phone":"+41 71 744 74 50",
    "sg:postcode":"9058",
    "sg:province":"Appenzell Innerhoden",
    "wof:name":"Musikgesellschaft",
    "wof:placetype":"venue"
},
  "geometry": {"coordinates":[9.3437595367,47.3727684021],"type":"Point"}
}