{
  "type": "Feature",
  "properties": {
    "iso:country":"CH",
    "sg:address":"Schulhausstrasse 6214 Schenkon. Postfach",
    "sg:city":"Schenkon",
    "sg:orig_category":"Gemeindeverwaltungen",
    "sg:phone":"+41 41 921 93 30",
    "sg:postcode":"6214",
    "sg:province":"Luzern",
    "wof:name":"Gemeindeverwaltung Schenkon",
    "wof:placetype":"venue"
},
  "geometry": {"coordinates":[8.1318845749,47.1768760681],"type":"Point"}
}