{
  "type": "Feature",
  "properties": {
    "iso:country":"CH",
    "sg:address":"Vorderhof 173",
    "sg:city":"Untereggen",
    "sg:orig_category":"Verarbeitung von Milch Verwertung von Milch",
    "sg:phone":"+41 71 866 10 32",
    "sg:postcode":"9033",
    "sg:province":"St. Gallen",
    "wof:name":"Benno & Doris Nietlispach K\u00e4serei",
    "wof:placetype":"venue"
},
  "geometry": {"coordinates":[9.4515247345,47.4561843872],"type":"Point"}
}