{
  "type": "Feature",
  "properties": {
    "iso:country":"CH",
    "sg:address":"Summerhaldenstrasse 3",
    "sg:city":"Freienstein",
    "sg:orig_category":"Gem\u00fcsebau",
    "sg:phone":"+41 32 396 12 30",
    "sg:postcode":"8427",
    "sg:province":"Z\u00fcrich",
    "wof:name":"Fritz Winkelmann Gem\u00fcsebau",
    "wof:placetype":"venue"
},
  "geometry": {"coordinates":[7.1900501251,47.0336494446],"type":"Point"}
}