{
  "type": "Feature",
  "properties": {
    "iso:country":"CH",
    "sg:address":"Schmittenweg 10",
    "sg:city":"Worben",
    "sg:orig_category":"Sportvereine Velo Rad-& Motorfahrer-Bund SRB",
    "sg:phone":"+41 32 384 62 85",
    "sg:postcode":"3252",
    "sg:province":"Bern",
    "wof:name":"Atb Vorw\u00e4rts",
    "wof:placetype":"venue"
},
  "geometry": {"coordinates":[7.2935261726,47.1001777649],"type":"Point"}
}