{
  "type": "Feature",
  "properties": {
    "iso:country":"CH",
    "sg:address":"Avenue Louis-ruchonnet 27",
    "sg:city":"Lausanne",
    "sg:orig_category":"Sportvereine Ballsport Tischtennis",
    "sg:postcode":"1003",
    "sg:province":"Vaud",
    "wof:name":"Ctt Zz Lancy",
    "wof:placetype":"venue"
},
  "geometry": {"coordinates":[6.6250009537,46.5188064575],"type":"Point"}
}