{
  "type": "Feature",
  "properties": {
    "iso:country":"CH",
    "sg:address":"7145",
    "sg:city":"Degen",
    "sg:orig_category":"Schulpflegen",
    "sg:postcode":"7145",
    "sg:province":"Graubunden",
    "wof:name":"Schulrat Der Gemeinde Degen",
    "wof:placetype":"venue"
},
  "geometry": {"coordinates":[9.1726398468,46.7045211792],"type":"Point"}
}