{
  "type": "Feature",
  "properties": {
    "iso:country":"CH",
    "sg:address":"Impasse Des Tilleuls 6",
    "sg:city":"Boncourt",
    "sg:orig_category":"Maurerarbeiten",
    "sg:phone":"+41 32 475 52 18",
    "sg:postcode":"2926",
    "sg:province":"Jura",
    "wof:name":"Jean-pierre Bonati Sa Ma\u00e7onnerie",
    "wof:placetype":"venue"
},
  "geometry": {"coordinates":[7.0102710724,47.4885520935],"type":"Point"}
}