{
  "type": "Feature",
  "properties": {
    "iso:country":"CH",
    "sg:address":"Badenerstrasse 21",
    "sg:city":"Dietikon",
    "sg:orig_category":"Detailhandel mit Waren verschiedener Art, Hauptrichtung Nahrungsmittel",
    "sg:phone":"+41 56 450 32 33",
    "sg:postcode":"8953",
    "sg:province":"Z\u00fcrich",
    "wof:name":"Denner Top Superdiscount",
    "wof:placetype":"venue"
},
  "geometry": {"coordinates":[8.2088899612,47.4814033508],"type":"Point"}
}