{
  "type": "Feature",
  "properties": {
    "iso:country":"CH",
    "sg:address":"Route Principale 3",
    "sg:city":"Bo\u00e9court",
    "sg:classifiers":[
        {
            "category":"Restaurant",
            "type":"Food & Drink"
        }
    ],
    "sg:phone":"+41 32 426 55 98",
    "sg:postcode":"2856",
    "sg:province":"Jura",
    "wof:name":"Pizzeria Chez Minet",
    "wof:placetype":"venue"
},
  "geometry": {"coordinates":[7.2141728401,47.3471336365],"type":"Point"}
}