{
  "type": "Feature",
  "properties": {
    "addr:full":"Rosengartenstrasse 5 Z\u00fcrich Z\u00fcrich 8037",
    "addr:housenumber":"5",
    "addr:postcode":"8037",
    "addr:street":"Rosengartenstrasse",
    "iso:country":"CH",
    "sg:address":"Rosengartenstrasse 5",
    "sg:city":"Z\u00fcrich",
    "sg:classifiers":[
        {
            "category":"Shopping",
            "subcategory":"Books",
            "type":"Retail Goods"
        }
    ],
    "sg:phone":"+41 12724744",
    "sg:postcode":"8037",
    "sg:province":"Z\u00fcrich",
    "wof:name":"Wettlin & Co",
    "wof:placetype":"venue"
},
  "geometry": {"coordinates":[8.524673,47.393791],"type":"Point"}
}