{
  "type": "Feature",
  "properties": {
    "iso:country":"CH",
    "sg:address":"Rue De La Tillette",
    "sg:city":"Bi\u00e8re",
    "sg:orig_category":"Herstellung von Reiseartikeln, Leder U Sattlerwaren Sonstige mit Sport verbundene T\u00e4tigkeiten",
    "sg:phone":"+41 41 497 20 75",
    "sg:postcode":"1145",
    "sg:province":"Vaud",
    "wof:name":"R\u00f6\u00f6sli Sattelbau Ag",
    "wof:placetype":"venue"
},
  "geometry": {"coordinates":[8.1451807022,47.0359802246],"type":"Point"}
}