{
  "type": "Feature",
  "properties": {
    "iso:country":"CH",
    "sg:address":"Bahnhofstrasse",
    "sg:city":"Gampel",
    "sg:orig_category":"Grosshandel mit Parf\u00fcmerieartikeln U K\u00f6rperpflegemitteln Sanit\u00e4r, Heizungs U L\u00fcftungsinstallation",
    "sg:phone":"+41 71 929 85 00",
    "sg:postcode":"3945",
    "sg:province":"Valais",
    "wof:name":"Sahag Ag",
    "wof:placetype":"venue"
},
  "geometry": {"coordinates":[9.3773641586,47.4255867004],"type":"Point"}
}