{
  "type": "Feature",
  "properties": {
    "iso:country":"CH",
    "sg:address":"Zugerstrasse 44",
    "sg:city":"Cham",
    "sg:orig_category":"Detailhandel mit Antiquit\u00e4ten Detailhandel mit Antiquit\u00e4ten U Gebrauchtwaren in Verkaufsr\u00e4umen",
    "sg:phone":"+41 41 780 87 15",
    "sg:postcode":"6330",
    "sg:province":"Zug",
    "wof:name":"Gerold Schuler Geri's Antiksch\u00f6pfli",
    "wof:placetype":"venue"
},
  "geometry": {"coordinates":[8.46612,47.181679],"type":"Point"}
}