{
  "type": "Feature",
  "properties": {
    "addr:full":"Rollisb\u00fchl 18 Suberg Bern 3262",
    "addr:housenumber":"18",
    "addr:postcode":"3262",
    "addr:street":"Rollisbuehl",
    "iso:country":"CH",
    "sg:address":"Rollisb\u00fchl 18",
    "sg:city":"Suberg",
    "sg:orig_category":"Datenverarbeitungsdienste Sonstige mit der Informatik verbundene T\u00e4tigkeiten",
    "sg:phone":"+41 32 389 16 16",
    "sg:postcode":"3262",
    "sg:province":"Bern",
    "wof:name":"Csd Computer Solutions Development Ag",
    "wof:placetype":"venue"
},
  "geometry": {"coordinates":[7.341251,47.058487],"type":"Point"}
}