{
  "type": "Feature",
  "properties": {
    "iso:country":"CH",
    "sg:address":"Regensbergstrasse 24",
    "sg:city":"Dielsdorf",
    "sg:orig_category":"Grosshandel mit Obst U Gem\u00fcse",
    "sg:phone":"+41 18530305",
    "sg:postcode":"8157",
    "sg:province":"Z\u00fcrich",
    "wof:name":"Petracca S\u00e0rl",
    "wof:placetype":"venue"
},
  "geometry": {"coordinates":[8.4499902725,47.4817810059],"type":"Point"}
}