{
  "type": "Feature",
  "properties": {
    "iso:country":"CH",
    "sg:address":"Casa Communale",
    "sg:city":"Vira",
    "sg:classifiers":[
        {
            "category":"Banks & Credit Unions",
            "subcategory":"Bank",
            "type":"Services"
        }
    ],
    "sg:phone":"+41 81 681 10 60",
    "sg:postcode":"6574",
    "sg:province":"Ticino",
    "wof:name":"Banca Raiffeisen Albula",
    "wof:placetype":"venue"
},
  "geometry": {"coordinates":[9.51479,46.681145],"type":"Point"}
}