{
  "type": "Feature",
  "properties": {
    "iso:country":"CH",
    "sg:address":"Jungfraustrasse 27",
    "sg:city":"Uetendorf",
    "sg:orig_category":"Herstellung von Werkzeugen Mechanische Werkst\u00e4tten",
    "sg:phone":"+41 33 345 55 77",
    "sg:postcode":"3661",
    "sg:province":"Bern",
    "wof:name":"Romain Bovet Mechanik & Apparatebau",
    "wof:placetype":"venue"
},
  "geometry": {"coordinates":[7.5934472084,46.7788543701],"type":"Point"}
}