{
  "type": "Feature",
  "properties": {
    "iso:country":"CH",
    "sg:address":"L\u00f6wenstrasse 15",
    "sg:city":"Dietikon",
    "sg:orig_category":"Personal U Stellenvermittlung Unternehmensberatung",
    "sg:phone":"+41 17402464",
    "sg:postcode":"8953",
    "sg:province":"Z\u00fcrich",
    "wof:name":"Logjob Ag Personalberatung",
    "wof:placetype":"venue"
},
  "geometry": {"coordinates":[8.4023122787,47.4055175781],"type":"Point"}
}