{
  "type": "Feature",
  "properties": {
    "iso:country":"CH",
    "sg:address":"Chemin Des Ecoliers 5",
    "sg:city":"Belfaux",
    "sg:orig_category":"Vorschulen, Kinderg\u00e4rten",
    "sg:phone":"+41 26 475 19 59",
    "sg:postcode":"1782",
    "sg:province":"Fribourg",
    "wof:name":"Ecole Maternelle",
    "wof:placetype":"venue"
},
  "geometry": {"coordinates":[7.1063699722,46.8199996948],"type":"Point"}
}