{
  "type": "Feature",
  "properties": {
    "iso:country":"CH",
    "sg:address":"Haslirainring 7",
    "sg:city":"Perlen",
    "sg:orig_category":"Werbegrafikateliers",
    "sg:phone":"+41 41 450 41 04",
    "sg:postcode":"6035",
    "sg:province":"Luzern",
    "wof:name":"Beat Galliker Grafisches Atelier",
    "wof:placetype":"venue"
},
  "geometry": {"coordinates":[8.3582515717,47.1055603027],"type":"Point"}
}