{
  "type": "Feature",
  "properties": {
    "iso:country":"CH",
    "sg:address":"Bahnhofstrasse 20",
    "sg:city":"Widnau",
    "sg:orig_category":"RESTAURANTS: TEA-ROOMS",
    "sg:postcode":"9443",
    "sg:province":"St. Gallen",
    "wof:name":"Bel Etage Erlacher Gmbh",
    "wof:placetype":"venue"
},
  "geometry": {"coordinates":[9.6331272125,47.4063301086],"type":"Point"}
}