{
  "type": "Feature",
  "properties": {
    "iso:country":"CH",
    "sg:address":"Seestrasse 45 6353 Weggis. Postfach 43",
    "sg:city":"Weggis",
    "sg:orig_category":"Detailhandel mit Brot, Back U S\u00fcsswaren",
    "sg:phone":"+41 41 390 13 01",
    "sg:postcode":"6353",
    "sg:province":"Luzern",
    "wof:name":"Vreny Dahinden B\u00e4ckerei-confiserie",
    "wof:placetype":"venue"
},
  "geometry": {"coordinates":[8.425808,47.031528],"type":"Point"}
}