{
  "type": "Feature",
  "properties": {
    "iso:country":"CH",
    "sg:address":"Alte Strasse",
    "sg:city":"Sch\u00f6nried",
    "sg:orig_category":"G\u00fcterbef\u00f6rderung im Strassenverkehr Strassenbau",
    "sg:phone":"+41 79 334 41 84",
    "sg:postcode":"3778",
    "sg:province":"Bern",
    "wof:name":"Tsm Von Gr\u00fcnigen Ag",
    "wof:placetype":"venue"
},
  "geometry": {"coordinates":[7.2813868523,46.5020294189],"type":"Point"}
}