{
  "type": "Feature",
  "properties": {
    "iso:country":"CH",
    "sg:address":"Hauserseestrasse 22 8475 Ossingen. Postfach",
    "sg:city":"Ossingen",
    "sg:orig_category":"G\u00fcterbef\u00f6rderung im Strassenverkehr",
    "sg:phone":"+41 56 633 14 55",
    "sg:postcode":"8475",
    "sg:province":"Z\u00fcrich",
    "wof:name":"Rey Transporte Bremgarten",
    "wof:placetype":"venue"
},
  "geometry": {"coordinates":[8.3386716843,47.3468399048],"type":"Point"}
}