{
  "type": "Feature",
  "properties": {
    "iso:country":"CH",
    "sg:address":"Hauptstrasse 109",
    "sg:city":"Leuggern",
    "sg:classifiers":[
        {
            "category":"Restaurant",
            "type":"Food & Drink"
        }
    ],
    "sg:phone":"+41 56 245 12 70",
    "sg:postcode":"5316",
    "sg:province":"Aargau",
    "wof:name":"Restaurant Sternen",
    "wof:placetype":"venue"
},
  "geometry": {"coordinates":[8.2124872208,47.5816764832],"type":"Point"}
}