{
  "type": "Feature",
  "properties": {
    "iso:country":"CH",
    "sg:address":"Mittlere Strasse 17",
    "sg:city":"Basel",
    "sg:orig_category":"Museen",
    "sg:phone":"+41 61 261 52 45",
    "sg:postcode":"4056",
    "sg:province":"Basel-Stadt",
    "wof:name":"Skulpturhalle",
    "wof:placetype":"venue"
},
  "geometry": {"coordinates":[7.5795269012,47.5602531433],"type":"Point"}
}