{
  "type": "Feature",
  "properties": {
    "addr:full":"Rue Marterey 5 Lausanne Vaud 1003",
    "addr:housenumber":"5",
    "addr:postcode":"1003",
    "addr:street":"Rue Marterey",
    "iso:country":"CH",
    "sg:address":"Rue Marterey 5",
    "sg:city":"Lausanne",
    "sg:classifiers":[
        {
            "category":"Banks & Credit Unions",
            "subcategory":"Bank",
            "type":"Services"
        }
    ],
    "sg:phone":"+41 21 340 13 81",
    "sg:postcode":"1003",
    "sg:province":"Vaud",
    "wof:name":"Credit Suisse, Investment Banking",
    "wof:placetype":"venue"
},
  "geometry": {"coordinates":[6.637914,46.520378],"type":"Point"}
}