{
  "type": "Feature",
  "properties": {
    "addr:full":"Flachsacherstrasse 2 Lupfig Aargau 5242",
    "addr:housenumber":"2",
    "addr:postcode":"5242",
    "addr:street":"Flachsacherstrasse",
    "iso:country":"CH",
    "sg:address":"Flachsacherstrasse 2",
    "sg:city":"Lupfig",
    "sg:classifiers":[
        {
            "category":"Social Services",
            "subcategory":"Retirement Home",
            "type":"Services"
        }
    ],
    "sg:phone":"+41 56 464 22 22",
    "sg:postcode":"5242",
    "sg:province":"Aargau",
    "sg:tags":[
        "pflegeheime",
        "u",
        "alters"
    ],
    "wof:name":"Altersheim Eigenamt",
    "wof:placetype":"venue"
},
  "geometry": {"coordinates":[8.205531,47.439621],"type":"Point"}
}