{
  "type": "Feature",
  "properties": {
    "iso:country":"CH",
    "sg:address":"Bahnhofstrasse 22 5400 Baden. Postfach 1259",
    "sg:city":"Baden",
    "sg:orig_category":"Kinos",
    "sg:phone":"+41 56 204 04 00",
    "sg:postcode":"5401",
    "sg:province":"Aargau",
    "wof:name":"Sterk Lichtspieltheater Ag",
    "wof:placetype":"venue"
},
  "geometry": {"coordinates":[8.3074789047,47.4748497009],"type":"Point"}
}