{
  "type": "Feature",
  "properties": {
    "iso:country":"CH",
    "sg:address":"Z\u00fcrcherstrasse 11 4310 Rheinfelden. Postfach",
    "sg:city":"Rheinfelden",
    "sg:orig_category":"Detailhandel mit elektrischen Haushalts-,Radio U Fernsehger\u00e4ten sowie Musikinstrumenten Verlag von b",
    "sg:phone":"+41 61 831 72 72",
    "sg:postcode":"4310",
    "sg:province":"Aargau",
    "wof:name":"Hall Of Sermon Gmbh",
    "wof:placetype":"venue"
},
  "geometry": {"coordinates":[7.7987208366,47.5518112183],"type":"Point"}
}