{
  "type": "Feature",
  "properties": {
    "iso:country":"CH",
    "sg:address":"Landorfstrasse 54",
    "sg:city":"K\u00f6niz",
    "sg:orig_category":"Herstellung von industriellen Prozesssteuerungsanlagen",
    "sg:phone":"+41 31 971 16 71",
    "sg:postcode":"3098",
    "sg:province":"Bern",
    "wof:name":"Hellinge Ingenieurb\u00fcro",
    "wof:placetype":"venue"
},
  "geometry": {"coordinates":[7.4095368385,46.9211387634],"type":"Point"}
}