{
  "type": "Feature",
  "properties": {
    "iso:country":"CH",
    "sg:address":"Kalcheggweg 10",
    "sg:city":"Bern",
    "sg:orig_category":"Konsulate",
    "sg:phone":"+41 31 351 63 85",
    "sg:postcode":"3006",
    "sg:province":"Bern",
    "wof:name":"Ambassade De La R\u00e9publique Populaire De Chine",
    "wof:placetype":"venue"
},
  "geometry": {"coordinates":[7.4657697678,46.939781189],"type":"Point"}
}