{
  "type": "Feature",
  "properties": {
    "iso:country":"CH",
    "sg:address":"Via Maggio 38",
    "sg:city":"Lugano",
    "sg:orig_category":"Unternehmensberatung",
    "sg:phone":"+41 91 971 05 16",
    "sg:postcode":"6900",
    "sg:province":"Ticino",
    "wof:name":"Sofimp Consulting Sa",
    "wof:placetype":"venue"
},
  "geometry": {"coordinates":[8.9661407471,46.0085678101],"type":"Point"}
}