{
  "type": "Feature",
  "properties": {
    "iso:country":"CH",
    "sg:address":"Industriestrasse 52",
    "sg:city":"Otelfingen",
    "sg:orig_category":"Non-Classified Establishments",
    "sg:phone":"+41 18473277",
    "sg:postcode":"8112",
    "sg:province":"Z\u00fcrich",
    "wof:name":"Sulser Logistik Ag",
    "wof:placetype":"venue"
},
  "geometry": {"coordinates":[8.397726059,47.457649231],"type":"Point"}
}