{
  "type": "Feature",
  "properties": {
    "iso:country":"CH",
    "sg:address":"Hauptstrasse 53a",
    "sg:city":"Lommis",
    "sg:orig_category":"Fahrschulen, Flugschulen",
    "sg:phone":"+41 79 632 23 42",
    "sg:postcode":"9506",
    "sg:province":"Thurgau",
    "wof:name":"Peter Imhof Autofahrschule",
    "wof:placetype":"venue"
},
  "geometry": {"coordinates":[7.3728890419,47.1460647583],"type":"Point"}
}