{
  "type": "Feature",
  "properties": {
    "iso:country":"CH",
    "sg:address":"Im Ifang 3",
    "sg:city":"Aarau",
    "sg:orig_category":"Non-Classified Establishments",
    "sg:phone":"+41 62 823 68 42",
    "sg:postcode":"5000",
    "sg:province":"Aargau",
    "wof:name":"Robert Hauri Gmbh",
    "wof:placetype":"venue"
},
  "geometry": {"coordinates":[8.0374479294,47.3870544434],"type":"Point"}
}