{
  "type": "Feature",
  "properties": {
    "iso:country":"CH",
    "sg:address":"Grosswisen 19",
    "sg:city":"Unterehrendingen",
    "sg:orig_category":"Softwareentwicklung U beratung Unternehmensberatung",
    "sg:phone":"+41 56 210 42 16",
    "sg:postcode":"5424",
    "wof:name":"Bachmann Consulting Gmbh",
    "wof:placetype":"venue"
},
  "geometry": {"coordinates":[8.3484258652,47.5037727356],"type":"Point"}
}