{
  "type": "Feature",
  "properties": {
    "iso:country":"CH",
    "sg:address":"M\u00fchlentalstrasse 256",
    "sg:city":"Schaffhausen",
    "sg:orig_category":"Sonstige Kurierdienste",
    "sg:phone":"+41 52 630 12 12",
    "sg:postcode":"8200",
    "sg:province":"Schaffhausen",
    "wof:name":"Dpd Direct Parcel Distribution Ag",
    "wof:placetype":"venue"
},
  "geometry": {"coordinates":[8.6321210861,47.7164268494],"type":"Point"}
}