{
  "type": "Feature",
  "properties": {
    "iso:country":"CH",
    "sg:address":"Gravas",
    "sg:city":"Trun",
    "sg:orig_category":"Grosshandel mit Getr\u00e4nken G\u00fcterbef\u00f6rderung im Strassenverkehr",
    "sg:phone":"+41 81 943 12 78",
    "sg:postcode":"7166",
    "sg:province":"Graubunden",
    "wof:name":"Albin Sa, Transports E Bubrondas",
    "wof:placetype":"venue"
},
  "geometry": {"coordinates":[8.9774999619,46.7402000427],"type":"Point"}
}