{
  "type": "Feature",
  "properties": {
    "iso:country":"CH",
    "sg:address":"Metzgergasse 1",
    "sg:city":"Arbon",
    "sg:classifiers":[
        {
            "category":"Restaurant",
            "type":"Food & Drink"
        }
    ],
    "sg:phone":"+41 71 446 39 51",
    "sg:postcode":"9320",
    "sg:province":"Thurgau",
    "wof:name":"Restaurant Anker",
    "wof:placetype":"venue"
},
  "geometry": {"coordinates":[9.4355459213,47.5157165527],"type":"Point"}
}