{
  "type": "Feature",
  "properties": {
    "iso:country":"CH",
    "sg:address":"Boulevard De Saint-georges 4",
    "sg:city":"Gen\u00e8ve",
    "sg:classifiers":[
        {
            "category":"Government",
            "subcategory":"Post Office",
            "type":"Public Place"
        }
    ],
    "sg:phone":"+41 22 329 37 32",
    "sg:postcode":"1205",
    "sg:province":"Gen\u00e8ve",
    "sg:tags":[
        "caf\u00e9s",
        "tea-rooms"
    ],
    "wof:name":"Bar \u00e0 Caf\u00e9 Habitud",
    "wof:placetype":"venue"
},
  "geometry": {"coordinates":[6.1309227943,46.2011413574],"type":"Point"}
}