{
  "type": "Feature",
  "properties": {
    "iso:country":"CH",
    "sg:address":"Baslerstrasse 50",
    "sg:city":"Z\u00fcrich",
    "sg:orig_category":"Detailhandel mit Damenbekleidung",
    "sg:phone":"+41 14927466",
    "sg:postcode":"8048",
    "sg:province":"Z\u00fcrich",
    "wof:name":"Beldona Ag",
    "wof:placetype":"venue"
},
  "geometry": {"coordinates":[8.498072,47.386131],"type":"Point"}
}