{
  "type": "Feature",
  "properties": {
    "iso:country":"CH",
    "sg:address":"Avenue G\u00e9n\u00e9ral-guisan 46 1009 Pully Case Postale 78",
    "sg:city":"Pully",
    "sg:orig_category":"Unternehmensberatung",
    "sg:phone":"+41 21 729 97 10",
    "sg:postcode":"1009",
    "sg:province":"Vaud",
    "wof:name":"Dp Finance Et Gestion Sa",
    "wof:placetype":"venue"
},
  "geometry": {"coordinates":[6.6483840942,46.5066108704],"type":"Point"}
}