{
  "type": "Feature",
  "properties": {
    "iso:country":"CH",
    "sg:address":"2732",
    "sg:city":"Saicourt",
    "sg:orig_category":"Grosshandel mit lebenden Tieren",
    "sg:phone":"+41 32 481 27 27",
    "sg:postcode":"2732",
    "sg:province":"Bern",
    "wof:name":"Ernest Gerber Commerce De B\u00e9tail",
    "wof:placetype":"venue"
},
  "geometry": {"coordinates":[7.208178997,47.2430877686],"type":"Point"}
}