{
  "type": "Feature",
  "properties": {
    "iso:country":"CH",
    "sg:address":"4204",
    "sg:city":"Himmelried",
    "sg:orig_category":"Landw. Genossenschaften Viehzucht",
    "sg:postcode":"4204",
    "sg:province":"Solothurn",
    "wof:name":"Schwarzfleckviehzucht Genossenschaft Schwarzbubenl.",
    "wof:placetype":"venue"
},
  "geometry": {"coordinates":[7.5978050232,47.42212677],"type":"Point"}
}