{
  "type": "Feature",
  "properties": {
    "iso:country":"CH",
    "sg:address":"Kehr",
    "sg:city":"Z\u00e4ziwil",
    "sg:orig_category":"Vereine Musik/Blasmusik",
    "sg:phone":"+41 31 711 01 09",
    "sg:postcode":"3532",
    "sg:province":"Bern",
    "wof:name":"Posaunenchor Z\u00e4ziwil",
    "wof:placetype":"venue"
},
  "geometry": {"coordinates":[7.6509652138,46.9010810852],"type":"Point"}
}