{
  "type": "Feature",
  "properties": {
    "iso:country":"CH",
    "sg:address":"Unterschlatt",
    "sg:city":"Schlatt",
    "sg:orig_category":"Fahrschulen, Flugschulen",
    "sg:phone":"+41 52 363 17 71",
    "sg:postcode":"8418",
    "sg:province":"Z\u00fcrich",
    "wof:name":"Hans Furrer Autofahrschule",
    "wof:placetype":"venue"
},
  "geometry": {"coordinates":[8.8282804489,47.4700393677],"type":"Point"}
}