{
  "type": "Feature",
  "properties": {
    "iso:country":"CH",
    "sg:address":"Lac Rue Du 119 1815 Clarens. Postfach",
    "sg:city":"Clarens",
    "sg:orig_category":"Betrieb von Taxis",
    "sg:postcode":"1815",
    "sg:province":"Vaud",
    "wof:name":"Taxi Bamby, Balbino Garcia",
    "wof:placetype":"venue"
},
  "geometry": {"coordinates":[6.890805,46.440945],"type":"Point"}
}