{
  "type": "Feature",
  "properties": {
    "iso:country":"CH",
    "sg:address":"Emil Frey-strasse 70",
    "sg:city":"M\u00fcnchenstein",
    "sg:orig_category":"RESTAURANTS: TEA-ROOMS",
    "sg:phone":"+41 61 331 24 45",
    "sg:postcode":"4142",
    "sg:province":"Basel-Landschaft",
    "wof:name":"Rest. Ruchfeld, Stefan Kocsis",
    "wof:placetype":"venue"
},
  "geometry": {"coordinates":[7.610929966,47.5289382935],"type":"Point"}
}