{
  "type": "Feature",
  "properties": {
    "iso:country":"CH",
    "sg:address":"Grubenstr. 12",
    "sg:city":"Ostermundigen",
    "sg:classifiers":[
        {
            "category":"Building & Trades",
            "subcategory":"Construction",
            "type":"Services"
        }
    ],
    "sg:phone":"+41 31 939 31 31",
    "sg:postcode":"3072",
    "sg:province":"Bern",
    "sg:tags":[
        "work",
        "public"
    ],
    "wof:name":"K\u00c4stli Ag Bauunternehmung",
    "wof:placetype":"venue"
},
  "geometry": {"coordinates":[7.490381,46.959751],"type":"Point"}
}