{
  "type": "Feature",
  "properties": {
    "iso:country":"CH",
    "sg:address":"4715",
    "sg:city":"Herbetswil",
    "sg:orig_category":"Landw. Genossenschaften Alpgenossenschaften",
    "sg:postcode":"4715",
    "sg:province":"Solothurn",
    "wof:name":"Alpgenossenschaft Jura",
    "wof:placetype":"venue"
},
  "geometry": {"coordinates":[7.5942831039,47.2935066223],"type":"Point"}
}