{
  "type": "Feature",
  "properties": {
    "iso:country":"CH",
    "sg:address":"Rotfarbstrasse 8",
    "sg:city":"Hauptwil",
    "sg:orig_category":"Herstellung von Schrauben, Nieten, Ketten U Federn",
    "sg:phone":"+41 71 422 54 81",
    "sg:postcode":"9213",
    "sg:province":"Thurgau",
    "wof:name":"Pram D\u00e9colletage Ag",
    "wof:placetype":"venue"
},
  "geometry": {"coordinates":[9.2486057281,47.4797821045],"type":"Point"}
}