{
  "type": "Feature",
  "properties": {
    "iso:country":"CH",
    "sg:address":"Alte Landstrasse 3",
    "sg:city":"Bichelsee",
    "sg:orig_category":"Grosshandel mit Milch, Milcherzeugnissen, Eiern, Speise\u00f6len U Nahrungsfetten",
    "sg:postcode":"8363",
    "sg:province":"Thurgau",
    "wof:name":"Rusch Martin",
    "wof:placetype":"venue"
},
  "geometry": {"coordinates":[8.9225149155,47.4480514526],"type":"Point"}
}