{
  "type": "Feature",
  "properties": {
    "iso:country":"CH",
    "sg:address":"Rathausgasse 8",
    "sg:city":"B\u00fclach",
    "sg:orig_category":"Religi\u00f6se Vereinigungen divers",
    "sg:phone":"+41 18622322",
    "sg:postcode":"8180",
    "sg:province":"Z\u00fcrich",
    "wof:name":"Freie Evang.gemeinde B\u00fclach",
    "wof:placetype":"venue"
},
  "geometry": {"coordinates":[8.5397663116,47.5172424316],"type":"Point"}
}