{
  "type": "Feature",
  "properties": {
    "iso:country":"CH",
    "sg:address":"Klosbachstrasse 103",
    "sg:city":"Z\u00fcrich",
    "sg:orig_category":"Sonstige Aktivit\u00e4ten der nicht-\u00e4rztlichen Medizinalberufe",
    "sg:phone":"+41 12615575",
    "sg:postcode":"8032",
    "sg:province":"Z\u00fcrich",
    "wof:name":"Jacqueline Meyer Kinesiologie",
    "wof:placetype":"venue"
},
  "geometry": {"coordinates":[8.5614690781,47.3684425354],"type":"Point"}
}