{
  "type": "Feature",
  "properties": {
    "iso:country":"CH",
    "sg:address":"6718",
    "sg:city":"Olivone",
    "sg:orig_category":"RESTAURANTS: TEA-ROOMS",
    "sg:postcode":"6718",
    "sg:province":"Ticino",
    "wof:name":"Emch & Canonica",
    "wof:placetype":"venue"
},
  "geometry": {"coordinates":[8.9390602112,46.5288009644],"type":"Point"}
}