{
  "type": "Feature",
  "properties": {
    "iso:country":"CH",
    "sg:address":"Rue De Savoie 59 1950 Sion Case Postale 154",
    "sg:city":"Sion",
    "sg:orig_category":"Instandhaltung U Reparatur von Automobilen Kauf U Verkauf von Immobilien auf eigene Rechnung",
    "sg:phone":"+41 79 220 41 28",
    "sg:postcode":"1951",
    "sg:province":"Valais",
    "wof:name":"Carrosserie Moderne Reynard Hermann Sa",
    "wof:placetype":"venue"
},
  "geometry": {"coordinates":[7.3262519836,46.2252693176],"type":"Point"}
}