{
  "type": "Feature",
  "properties": {
    "iso:country":"CH",
    "sg:address":"Marktplatz 13 4001 Basel. Postfach",
    "sg:city":"Basel",
    "sg:orig_category":"Pensionskassen",
    "sg:phone":"+41 71 282 49 49",
    "sg:postcode":"4001",
    "sg:province":"Basel-Stadt",
    "wof:name":"Pensionskasse Baugesch\u00e4ft B\u00e4rlocher Ag",
    "wof:placetype":"venue"
},
  "geometry": {"coordinates":[9.4188222885,47.4398612976],"type":"Point"}
}