{
  "type": "Feature",
  "properties": {
    "iso:country":"CH",
    "sg:address":"Rue Du M\u00f4le 42bis 1200 Genf. Postfach",
    "sg:city":"Gen\u00e8ve",
    "sg:orig_category":"Instandhaltung U Reparatur von Automobilen",
    "sg:postcode":"1201",
    "sg:province":"Gen\u00e8ve",
    "wof:name":"Garage Royal Sarl",
    "wof:placetype":"venue"
},
  "geometry": {"coordinates":[6.1460990906,46.2135658264],"type":"Point"}
}