{
  "type": "Feature",
  "properties": {
    "iso:country":"CH",
    "sg:address":"Chr\u00fczmatte 6",
    "sg:city":"Sch\u00f6tz",
    "sg:orig_category":"Autolackierereien Autospenglereien",
    "sg:phone":"+41 79 215 77 71",
    "sg:postcode":"6247",
    "sg:province":"Luzern",
    "wof:name":"Carrosserie Willy Borer",
    "wof:placetype":"venue"
},
  "geometry": {"coordinates":[7.437039,47.405071],"type":"Point"}
}