{
  "type": "Feature",
  "properties": {
    "iso:country":"CH",
    "sg:address":"Sch\u00e4renm\u00e4tteliweg 5",
    "sg:city":"Balsthal",
    "sg:orig_category":"Arztpraxen",
    "sg:phone":"+41 79 391 27 26",
    "sg:postcode":"4710",
    "sg:province":"Solothurn",
    "wof:name":"Dr.med.s.nivardo Magarzo Spezialarzt Fmh",
    "wof:placetype":"venue"
},
  "geometry": {"coordinates":[7.689208,47.31208],"type":"Point"}
}