{
  "type": "Feature",
  "properties": {
    "iso:country":"CH",
    "sg:address":"Habsburgstrasse 36",
    "sg:city":"Rudolfstetten",
    "sg:orig_category":"Wirtschaftspr\u00fcfung, Steuerberatung U Treuhand",
    "sg:postcode":"8964",
    "sg:province":"Aargau",
    "wof:name":"Grigia Treuhand Ag",
    "wof:placetype":"venue"
},
  "geometry": {"coordinates":[8.3703508377,47.3627357483],"type":"Point"}
}