{
  "type": "Feature",
  "properties": {
    "iso:country":"CH",
    "sg:address":"Rue Du Geni\u00e8vre 6",
    "sg:city":"Tramelan",
    "sg:classifiers":[
        {
            "category":"Shopping",
            "subcategory":"Discount & Variety Stores",
            "type":"Retail Goods"
        }
    ],
    "sg:phone":"+41 32 487 10 80",
    "sg:postcode":"2720",
    "sg:province":"Bern",
    "sg:tags":[
        "shop",
        "locksmith's"
    ],
    "wof:name":"C.m.t. S.a.",
    "wof:placetype":"venue"
},
  "geometry": {"coordinates":[7.1114039421,47.221824646],"type":"Point"}
}