{
  "type": "Feature",
  "properties": {
    "iso:country":"CH",
    "sg:address":"Wilerstrasse 40",
    "sg:city":"Flawil",
    "sg:orig_category":"Detailhandel mit Fahrr\u00e4dern Handel mit Motorr\u00e4dern, Teilen U Zubeh\u00f6r Instandhaltung U Reparatur von ",
    "sg:phone":"+41 71 393 13 14",
    "sg:postcode":"9230",
    "sg:province":"St. Gallen",
    "wof:name":"Ebneter Guido Velos-motos",
    "wof:placetype":"venue"
},
  "geometry": {"coordinates":[9.1853990555,47.4152145386],"type":"Point"}
}