{
  "type": "Feature",
  "properties": {
    "iso:country":"CH",
    "sg:address":"4922",
    "sg:city":"B\u00fctzberg",
    "sg:orig_category":"Vereine Damen Vereine Gesang",
    "sg:postcode":"4922",
    "sg:province":"Bern",
    "wof:name":"Frauenchor",
    "wof:placetype":"venue"
},
  "geometry": {"coordinates":[7.7463102341,47.2157936096],"type":"Point"}
}