{
  "type": "Feature",
  "properties": {
    "iso:country":"CH",
    "sg:address":"Vevey Rue De 178",
    "sg:city":"Bulle",
    "sg:orig_category":"Herstellung von Hebezeugen U F\u00f6rdermitteln",
    "sg:phone":"+41 27 783 16 16",
    "sg:postcode":"1630",
    "sg:province":"Fribourg",
    "wof:name":"T\u00c9l\u00c9s-vich\u00c8res-liddes Sa",
    "wof:placetype":"venue"
},
  "geometry": {"coordinates":[7.1808519363,46.0040893555],"type":"Point"}
}