{
  "type": "Feature",
  "properties": {
    "iso:country":"CH",
    "sg:address":"Hauptstrasse 302",
    "sg:city":"Rohrbach",
    "sg:orig_category":"Vereine Musik/Blasmusik",
    "sg:postcode":"4938",
    "sg:province":"Bern",
    "wof:name":"Musikverein Langnau-gattikon",
    "wof:placetype":"venue"
},
  "geometry": {"coordinates":[8.5396108627,47.2886581421],"type":"Point"}
}