{
  "type": "Feature",
  "properties": {
    "iso:country":"CH",
    "sg:address":"Lyssstr. 2",
    "sg:city":"Dotzigen",
    "sg:orig_category":"Softwareentwicklung U beratung",
    "sg:postcode":"3293",
    "sg:province":"Bern",
    "wof:name":"Rotec, Schaller R.",
    "wof:placetype":"venue"
},
  "geometry": {"coordinates":[7.341823101,47.1201629639],"type":"Point"}
}