{
  "type": "Feature",
  "properties": {
    "iso:country":"CH",
    "sg:address":"Schweizersholz 9223 Schweizersholz. Postfach",
    "sg:city":"Schweizersholz",
    "sg:orig_category":"Verwertung von Milch",
    "sg:postcode":"9223",
    "sg:province":"Thurgau",
    "wof:name":"W\u00fcthrich K\u00e4serei",
    "wof:placetype":"venue"
},
  "geometry": {"coordinates":[9.1924352646,47.5022506714],"type":"Point"}
}