{
  "type": "Feature",
  "properties": {
    "addr:full":"Lenzb\u00fcel 2 Sirnach Thurgau 8370",
    "addr:housenumber":"2",
    "addr:postcode":"8370",
    "addr:street":"Lenzbueel",
    "iso:country":"CH",
    "sg:address":"Lenzb\u00fcel 2",
    "sg:city":"Sirnach",
    "sg:orig_category":"Datenbanken Softwareentwicklung U beratung",
    "sg:phone":"+41 71 969 60 60",
    "sg:postcode":"8370",
    "sg:province":"Thurgau",
    "wof:name":"Dynatrends Ag",
    "wof:placetype":"venue"
},
  "geometry": {"coordinates":[9.023203,47.462471],"type":"Point"}
}