{
  "type": "Feature",
  "properties": {
    "iso:country":"CH",
    "sg:address":"Jakob-rosius-strasse 6",
    "sg:city":"Biel/bienne",
    "sg:classifiers":[
        {
            "category":"Restaurant",
            "type":"Food & Drink"
        }
    ],
    "sg:phone":"+41 32 322 66 38",
    "sg:postcode":"2502",
    "sg:province":"Bern",
    "wof:name":"Restaurant Egge 6",
    "wof:placetype":"venue"
},
  "geometry": {"coordinates":[7.2447829247,47.140499115],"type":"Point"}
}