{
  "type": "Feature",
  "properties": {
    "iso:country":"CH",
    "sg:address":"Im Feld 298",
    "sg:city":"Leutwil",
    "sg:orig_category":"G\u00fcterbef\u00f6rderung im Strassenverkehr",
    "sg:phone":"+41 62 777 10 00",
    "sg:postcode":"5725",
    "sg:province":"Aargau",
    "wof:name":"L\u00fcscher Dieter",
    "wof:placetype":"venue"
},
  "geometry": {"coordinates":[8.1739883423,47.3088150024],"type":"Point"}
}