{
  "type": "Feature",
  "properties": {
    "iso:country":"CH",
    "sg:address":"Birkenstrasse 9",
    "sg:city":"D\u00e4ttlikon",
    "sg:orig_category":"Elektroinstallation",
    "sg:phone":"+41 52 315 14 40",
    "sg:postcode":"8421",
    "sg:province":"Z\u00fcrich",
    "wof:name":"Stefan M\u00fcller Elektroinstallationsgesch\u00e4ft",
    "wof:placetype":"venue"
},
  "geometry": {"coordinates":[8.62022686,47.526473999],"type":"Point"}
}