{
  "type": "Feature",
  "properties": {
    "iso:country":"CH",
    "sg:address":"Route De Thonon 320",
    "sg:city":"Ani\u00e8res",
    "sg:orig_category":"Grosshandel mit B\u00fcromaschinen Grosshandel mit Datenverarbeitungsger\u00e4ten",
    "sg:phone":"+41 79 633 34 63",
    "sg:postcode":"1247",
    "sg:province":"Gen\u00e8ve",
    "wof:name":"Informatique Tppi Marti",
    "wof:placetype":"venue"
},
  "geometry": {"coordinates":[6.2383499146,46.2671737671],"type":"Point"}
}