{
  "type": "Feature",
  "properties": {
    "iso:country":"CH",
    "sg:address":"Wehntalerstrasse 310 8046 Z\u00fcrich. Postfach",
    "sg:city":"Z\u00fcrich",
    "sg:classifiers":[
        {
            "category":"Restaurant",
            "type":"Food & Drink"
        }
    ],
    "sg:phone":"+41 71 923 11 66",
    "sg:postcode":"8056",
    "wof:name":"Restaurant Hirschen",
    "wof:placetype":"venue"
},
  "geometry": {"coordinates":[9.0706205368,47.4431152344],"type":"Point"}
}