{
  "type": "Feature",
  "properties": {
    "iso:country":"CH",
    "sg:address":"6821",
    "sg:city":"Rovio",
    "sg:orig_category":"Schulpflegen",
    "sg:postcode":"6821",
    "sg:province":"Ticino",
    "wof:name":"Delegazione Scolastica Del Comune Di Rovio",
    "wof:placetype":"venue"
},
  "geometry": {"coordinates":[8.9996595383,45.9354515076],"type":"Point"}
}