{
  "type": "Feature",
  "properties": {
    "iso:country":"CH",
    "sg:address":"Els\u00e4sserstrasse 113 4056 Basel. Postfach",
    "sg:city":"Basel",
    "sg:orig_category":"Werbung",
    "sg:phone":"+41 61 385 97 00",
    "sg:postcode":"4051",
    "sg:province":"Basel-Stadt",
    "wof:name":"Z.b. Zimmermann Basel Werbeatelier Werbeatelier. Dekorationen",
    "wof:placetype":"venue"
},
  "geometry": {"coordinates":[7.5765910149,47.5720443726],"type":"Point"}
}