{
  "type": "Feature",
  "properties": {
    "iso:country":"CH",
    "sg:address":"Riva Caccia 1c",
    "sg:city":"Lugano",
    "sg:orig_category":"Detailhandel mit Sportartikeln",
    "sg:phone":"+41 91 994 73 73",
    "sg:postcode":"6900",
    "sg:province":"Ticino",
    "wof:name":"Horseland Felix B\u00fchler Ag",
    "wof:placetype":"venue"
},
  "geometry": {"coordinates":[8.9475860596,45.9980354309],"type":"Point"}
}