{
  "type": "Feature",
  "properties": {
    "iso:country":"CH",
    "sg:address":"Aegetenstrasse 12",
    "sg:city":"Widnau",
    "sg:orig_category":"Herstellung von Tanks U Sammelbeh\u00e4ltern aus Metall Reinigungsgewerbe",
    "sg:phone":"+41 71 722 41 70",
    "sg:postcode":"9443",
    "sg:province":"St. Gallen",
    "wof:name":"Maichen Tankschutz Widnau Ag",
    "wof:placetype":"venue"
},
  "geometry": {"coordinates":[9.6404972076,47.3967437744],"type":"Point"}
}