{
  "type": "Feature",
  "properties": {
    "iso:country":"CH",
    "sg:address":"Panoramastrasse 11",
    "sg:city":"Ennetb\u00fcrgen",
    "sg:orig_category":"Sportvereine Ballsport Basketball",
    "sg:phone":"+41 41 620 60 28",
    "sg:postcode":"6373",
    "sg:province":"Nidwalden",
    "wof:name":"Bc Ktv Kollegium St.fidelis",
    "wof:placetype":"venue"
},
  "geometry": {"coordinates":[8.41655159,46.9882736206],"type":"Point"}
}