{
  "type": "Feature",
  "properties": {
    "iso:country":"CH",
    "sg:address":"Waldh\u00f6heweg 2",
    "sg:city":"Bern",
    "sg:classifiers":[
        {
            "category":"Travel",
            "subcategory":"Hotels & Motels",
            "type":"Entertainment"
        }
    ],
    "sg:phone":"+41 33 442 21 41",
    "sg:postcode":"3013",
    "sg:province":"Bern",
    "sg:tags":[
        "hotels",
        "mit",
        "restaurant"
    ],
    "wof:name":"Hotel Waldpark",
    "wof:placetype":"venue"
},
  "geometry": {"coordinates":[7.6631250381,46.7628746033],"type":"Point"}
}