{
  "type": "Feature",
  "properties": {
    "iso:country":"CH",
    "sg:address":"Sur La Maille 15",
    "sg:city":"Alle",
    "sg:orig_category":"Fachdetailhandel in Verkaufsr\u00e4umen",
    "sg:phone":"+41 52 363 24 45",
    "sg:postcode":"2942",
    "sg:province":"Jura",
    "wof:name":"Horlogerie Allaine S\u00e0rl",
    "wof:placetype":"venue"
},
  "geometry": {"coordinates":[7.1327328682,47.4302444458],"type":"Point"}
}