{
  "type": "Feature",
  "properties": {
    "iso:country":"CH",
    "sg:address":"Wylerstrasse 83",
    "sg:city":"Bern",
    "sg:orig_category":"Massagestudios",
    "sg:phone":"+41 31 332 51 03",
    "sg:postcode":"3014",
    "sg:province":"Bern",
    "wof:name":"Pia D\u00e4llenbach Medizinische Massagen",
    "wof:placetype":"venue"
},
  "geometry": {"coordinates":[7.446876049,46.9610137939],"type":"Point"}
}