{
  "type": "Feature",
  "properties": {
    "iso:country":"CH",
    "sg:address":"Nadelberg 15 4051 Basel. Postfach",
    "sg:city":"Basel",
    "sg:classifiers":[
        {
            "category":"Communications",
            "subcategory":"Film & Video Production",
            "type":"Services"
        }
    ],
    "sg:phone":"+41 55 410 71 70",
    "sg:postcode":"4003",
    "sg:province":"Basel-Stadt",
    "sg:tags":[
        "videofilmherstellung",
        "u"
    ],
    "wof:name":"Highlight Communications Ag",
    "wof:placetype":"venue"
},
  "geometry": {"coordinates":[8.8029794693,47.2009811401],"type":"Point"}
}