{
  "type": "Feature",
  "properties": {
    "iso:country":"CH",
    "sg:address":"Rue Du Ch\u00e2teau 1",
    "sg:city":"Neuch\u00e2tel",
    "sg:orig_category":"Chemische Reinigung",
    "sg:phone":"+41 21 691 92 92",
    "sg:postcode":"2000",
    "sg:province":"Neuch\u00e2tel",
    "wof:name":"Pressing Trois Etoiles Maria K\u00fcffer",
    "wof:placetype":"venue"
},
  "geometry": {"coordinates":[6.558642,46.510136],"type":"Point"}
}