{
  "type": "Feature",
  "properties": {
    "iso:country":"CH",
    "sg:address":"Baudit Rue 1 1201 Gen\u00e8ve. Postfach",
    "sg:city":"Gen\u00e8ve",
    "sg:orig_category":"Wohnheime",
    "sg:postcode":"1201",
    "sg:province":"Gen\u00e8ve",
    "wof:name":"Fondation Ems (etablissement M\u00e9dico-social) R\u00e9sidence Amiti\u00e9",
    "wof:placetype":"venue"
},
  "geometry": {"coordinates":[6.1387419701,46.2098770142],"type":"Point"}
}