{
  "type": "Feature",
  "properties": {
    "iso:country":"CH",
    "sg:address":"L\u00e4ngackerstrasse 8",
    "sg:city":"Selzach",
    "sg:classifiers":[
        {
            "category":"Autos & Motor Vehicles",
            "subcategory":"Fuel & Gas Station",
            "type":"Retail Goods"
        }
    ],
    "sg:phone":"+41 32 641 25 35",
    "sg:postcode":"2545",
    "sg:province":"Solothurn",
    "sg:tags":[
        "extraction",
        "aggressive",
        "system",
        "vapour"
    ],
    "wof:name":"Enterprise Corporation Ag",
    "wof:placetype":"venue"
},
  "geometry": {"coordinates":[7.4442129135,47.1953926086],"type":"Point"}
}