{
  "type": "Feature",
  "properties": {
    "iso:country":"CH",
    "sg:address":"Buristrasse 14",
    "sg:city":"Bern",
    "sg:orig_category":"Berufsbildende weiterf\u00fchrende Schulen Unternehmensberatung",
    "sg:phone":"+41 31 351 64 51",
    "sg:postcode":"3006",
    "sg:province":"Bern",
    "wof:name":"Imes Institut F\u00fcr Management Und Erwachsenenschulung",
    "wof:placetype":"venue"
},
  "geometry": {"coordinates":[7.47485,46.94495],"type":"Point"}
}