{
  "type": "Feature",
  "properties": {
    "iso:country":"CH",
    "sg:address":"General-dufour-strasse 17",
    "sg:city":"Biel/bienne",
    "sg:orig_category":"Arztpraxen",
    "sg:phone":"+41 27 473 13 06",
    "sg:postcode":"2502",
    "sg:province":"Bern",
    "wof:name":"Dres Kuonen Schnyder Zinsstag \u00c4rzte F\u00fcr Allgemeine Medizin",
    "wof:placetype":"venue"
},
  "geometry": {"coordinates":[7.634661,46.316334],"type":"Point"}
}