{
  "type": "Feature",
  "properties": {
    "iso:country":"CH",
    "sg:address":"Chemin Des Primev\u00e8res 15",
    "sg:city":"Fribourg",
    "sg:orig_category":"Wirtschaftspr\u00fcfung, Steuerberatung U Treuhand",
    "sg:postcode":"1700",
    "sg:province":"Fribourg",
    "wof:name":"Hospes Sa Soci\u00e9t\u00e9 De R\u00e9vision De L'h\u00f4tellerie Et De La Restauration",
    "wof:placetype":"venue"
},
  "geometry": {"coordinates":[7.1421189308,46.8039283752],"type":"Point"}
}