{
  "type": "Feature",
  "properties": {
    "addr:full":"Lausanne Rue De 26 1700 Fribourg. Postfach Fribourg Fribourg 1700",
    "addr:housenumber":"26",
    "addr:postcode":"1700;postfach;1700",
    "addr:street":"Rue De",
    "iso:country":"CH",
    "sg:address":"Lausanne Rue De 26 1700 Fribourg. Postfach",
    "sg:city":"Fribourg",
    "sg:orig_category":"Detailhandel mit Bekleidung",
    "sg:postcode":"1700",
    "sg:province":"Fribourg",
    "wof:name":"Blaser Boutique",
    "wof:placetype":"venue"
},
  "geometry": {"coordinates":[9.822282,46.797943],"type":"Point"}
}