{
  "type": "Feature",
  "properties": {
    "iso:country":"CH",
    "sg:address":"Vieux-canal 29",
    "sg:city":"Sion",
    "sg:orig_category":"Grosshandel mit Getr\u00e4nken",
    "sg:postcode":"1950",
    "sg:province":"Valais",
    "wof:name":"Casa Primavera, Salvado Fernandes",
    "wof:placetype":"venue"
},
  "geometry": {"coordinates":[7.3496460915,46.229385376],"type":"Point"}
}