{
  "type": "Feature",
  "properties": {
    "iso:country":"CH",
    "sg:address":"T\u00e4gerhardstrasse 92 5430 Wettingen. Postfach 83",
    "sg:city":"Wettingen",
    "sg:orig_category":"Bars Diskotheken, Dancings, Night Clubs",
    "sg:phone":"+41 56 426 50 13",
    "sg:postcode":"5430",
    "sg:province":"Aargau",
    "wof:name":"Black Ice Gmbh Black Jack The One For Dance & Fun",
    "wof:placetype":"venue"
},
  "geometry": {"coordinates":[8.330658,47.457108],"type":"Point"}
}