{
  "type": "Feature",
  "properties": {
    "iso:country":"CH",
    "sg:address":"Oberlindach",
    "sg:city":"Kirchlindach",
    "sg:orig_category":"Herstellung von Schneidwaren U Bestecken",
    "sg:phone":"+41 31 829 30 52",
    "sg:postcode":"3038",
    "sg:province":"Bern",
    "wof:name":"Bichsel H. R. Gmbh",
    "wof:placetype":"venue"
},
  "geometry": {"coordinates":[7.4259500504,47.0032691956],"type":"Point"}
}