{
  "type": "Feature",
  "properties": {
    "iso:country":"CH",
    "sg:address":"Surseestrasse 315",
    "sg:city":"Wauwil",
    "sg:orig_category":"Elektroinstallation",
    "sg:postcode":"6242",
    "sg:province":"Luzern",
    "wof:name":"Kaufmann Andreas",
    "wof:placetype":"venue"
},
  "geometry": {"coordinates":[8.0250606537,47.1857528687],"type":"Point"}
}