{
  "type": "Feature",
  "properties": {
    "iso:country":"CH",
    "sg:address":"Baarerstrasse 79",
    "sg:city":"Zug",
    "sg:orig_category":"Detailhandel mit elektrischen Haushalts-,Radio U Fernsehger\u00e4ten sowie Musikinstrumenten",
    "sg:phone":"+41 41 761 85 85",
    "sg:postcode":"6300",
    "sg:province":"Zug",
    "wof:name":"Sl Haushaltwaren Ag",
    "wof:placetype":"venue"
},
  "geometry": {"coordinates":[8.5177192688,47.1772003174],"type":"Point"}
}