{
  "type": "Feature",
  "properties": {
    "iso:country":"CH",
    "sg:address":"Dachslenbergstrasse 43",
    "sg:city":"B\u00fclach",
    "sg:orig_category":"Wirtschaftspr\u00fcfung, Steuerberatung U Treuhand",
    "sg:postcode":"8180",
    "sg:province":"Z\u00fcrich",
    "wof:name":"Bs Treuhand-partner Gmbh",
    "wof:placetype":"venue"
},
  "geometry": {"coordinates":[9.3199663162,47.4219779968],"type":"Point"}
}