{
  "type": "Feature",
  "properties": {
    "iso:country":"CH",
    "sg:address":"Guscha",
    "sg:city":"Sevelen",
    "sg:orig_category":"Herstellung von keramischen Haushaltswaren U Ziergegenst\u00e4nden",
    "sg:postcode":"9475",
    "sg:province":"St. Gallen",
    "wof:name":"Porzellan Boutique D. Sobczak",
    "wof:placetype":"venue"
},
  "geometry": {"coordinates":[8.5396966934,47.3164863586],"type":"Point"}
}