{
  "type": "Feature",
  "properties": {
    "iso:country":"CH",
    "sg:address":"Felsenstrasse 85 9000 St.gallen. Postfach",
    "sg:city":"St.gallen",
    "sg:orig_category":"Detailhandel mit medizinischen U orthop\u00e4dischen Artikeln",
    "sg:phone":"+41 71 223 10 20",
    "sg:postcode":"9000",
    "sg:province":"St. Gallen",
    "wof:name":"Egli Otoplastik",
    "wof:placetype":"venue"
},
  "geometry": {"coordinates":[9.371342659,47.4191017151],"type":"Point"}
}