{
  "type": "Feature",
  "properties": {
    "iso:country":"CH",
    "sg:address":"Hauptstrasse 8",
    "sg:city":"D\u00fcdingen",
    "sg:orig_category":"Detailhandel mit Beleuchtungs U Haushaltsgegenst\u00e4nden Detailhandel mit Spielwaren",
    "sg:phone":"+41 21 866 76 59",
    "sg:postcode":"3186",
    "sg:province":"Fribourg",
    "wof:name":"Jean-jacques Amiguet Quincaillerie Art.m\u00e9nage",
    "wof:placetype":"venue"
},
  "geometry": {"coordinates":[6.514582,46.659245],"type":"Point"}
}