{
  "type": "Feature",
  "properties": {
    "iso:country":"CH",
    "sg:address":"Rue Du Chalet 37",
    "sg:city":"Tramelan",
    "sg:orig_category":"Malerei Stukkateurgewerbe, Gipserei U Verputzerei",
    "sg:phone":"+41 79 407 71 42",
    "sg:postcode":"2720",
    "sg:province":"Bern",
    "wof:name":"Stephane Bichsel Peinture & Pl\u00e2trerie",
    "wof:placetype":"venue"
},
  "geometry": {"coordinates":[7.0958428383,47.2247695923],"type":"Point"}
}