{
  "type": "Feature",
  "properties": {
    "iso:country":"CH",
    "sg:address":"Dorfstrasse 10 7402 Bonaduz. Postfach",
    "sg:city":"Bonaduz",
    "sg:orig_category":"Sanit\u00e4r, Heizungs U L\u00fcftungsinstallation",
    "sg:postcode":"7402",
    "sg:province":"Graubunden",
    "wof:name":"Hofmann Fritz Gmbh",
    "wof:placetype":"venue"
},
  "geometry": {"coordinates":[9.3988895416,46.8118209839],"type":"Point"}
}