{
  "type": "Feature",
  "properties": {
    "iso:country":"CH",
    "sg:address":"Pilatusstrasse 30",
    "sg:city":"Luzern",
    "sg:orig_category":"Arztpraxen",
    "sg:phone":"+41 71 385 88 77",
    "sg:postcode":"6003",
    "sg:province":"Luzern",
    "wof:name":"Dr.med.heidi Martin Spezial\u00e4rztin Fmh",
    "wof:placetype":"venue"
},
  "geometry": {"coordinates":[9.250312,47.416389],"type":"Point"}
}