{
  "type": "Feature",
  "properties": {
    "addr:full":"Gr\u00fcndenstrasse 23 Flurlingen Z\u00fcrich 8247",
    "addr:housenumber":"23",
    "addr:postcode":"8247",
    "addr:street":"Gruendenstrasse",
    "iso:country":"CH",
    "sg:address":"Gr\u00fcndenstrasse 23",
    "sg:city":"Flurlingen",
    "sg:orig_category":"Bauschreinerei Fischzucht, Teichwirtschaft",
    "sg:phone":"+41 52 659 16 44",
    "sg:postcode":"8247",
    "sg:province":"Z\u00fcrich",
    "wof:name":"Adolf Enz Schreinerei & Fischzucht",
    "wof:placetype":"venue"
},
  "geometry": {"coordinates":[8.627327,47.685715],"type":"Point"}
}