{
  "type": "Feature",
  "properties": {
    "iso:country":"CH",
    "sg:address":"Effingerstrasse 39",
    "sg:city":"Bern",
    "sg:orig_category":"Bauschreinerei",
    "sg:phone":"+41 31 385 08 50",
    "sg:postcode":"3008",
    "sg:province":"Bern",
    "wof:name":"Stauffenegger Ag K\u00fcchen-& Innenausbau",
    "wof:placetype":"venue"
},
  "geometry": {"coordinates":[7.42176,46.944649],"type":"Point"}
}