{
  "type": "Feature",
  "properties": {
    "iso:country":"CH",
    "sg:address":"Vex",
    "sg:city":"Vex",
    "sg:classifiers":[
        {
            "category":"Banks & Credit Unions",
            "subcategory":"Bank",
            "type":"Services"
        }
    ],
    "sg:phone":"+41 27272027",
    "sg:postcode":"1981",
    "sg:province":"Valais",
    "wof:name":"Banque Raiffeisen",
    "wof:placetype":"venue"
},
  "geometry": {"coordinates":[7.39541,46.205479],"type":"Point"}
}