{
  "type": "Feature",
  "properties": {
    "iso:country":"CH",
    "sg:address":"Rue Industrielle 30",
    "sg:city":"Montreux",
    "sg:orig_category":"Sanit\u00e4r U Heizungsinstallation Sanit\u00e4rinstallation",
    "sg:phone":"+41 21 963 25 77",
    "sg:postcode":"1820",
    "sg:province":"Vaud",
    "wof:name":"Adolf Hilkersberger Chauffage Sanitaire",
    "wof:placetype":"venue"
},
  "geometry": {"coordinates":[6.9134140015,46.4331817627],"type":"Point"}
}