{
  "type": "Feature",
  "properties": {
    "iso:country":"CH",
    "sg:address":"Fennen 7",
    "sg:city":"Niederurnen",
    "sg:classifiers":[
        {
            "category":"Manufacturing",
            "subcategory":"Metals",
            "type":"Manufacturing & Wholesale Goods"
        }
    ],
    "sg:phone":"+41 4119232323",
    "sg:postcode":"8867",
    "sg:province":"Glarus",
    "sg:tags":[
        "metallurgy",
        "metalworking",
        "processing"
    ],
    "wof:name":"Kaspar Humbel Ag",
    "wof:placetype":"venue"
},
  "geometry": {"coordinates":[9.2822599411,53.6873283386],"type":"Point"}
}