{
  "type": "Feature",
  "properties": {
    "iso:country":"CH",
    "sg:address":"Avenue De La Gare 38 1920 Martigny Case Postale 359",
    "sg:city":"Martigny",
    "sg:orig_category":"Architektur U Ingenieurb\u00fcros Architekturb\u00fcros",
    "sg:phone":"+41 27 722 22 23",
    "sg:postcode":"1920",
    "sg:province":"Valais",
    "wof:name":"Delaloye Architectes Associes",
    "wof:placetype":"venue"
},
  "geometry": {"coordinates":[7.076445,46.103752],"type":"Point"}
}