{
  "type": "Feature",
  "properties": {
    "addr:full":"6487 G\u00f6schenen Uri 6487",
    "addr:housenumber":"6487",
    "addr:postcode":"6487",
    "addr:street":"Goeschenen Uri",
    "iso:country":"CH",
    "sg:address":"6487",
    "sg:city":"G\u00f6schenen",
    "sg:orig_category":"Allgemeiner Hoch U Tiefbau ohne ausgepr\u00e4gten Schwerpunkt",
    "sg:phone":"+41 41 886 81 81",
    "sg:postcode":"6487",
    "sg:province":"Uri",
    "wof:name":"Verkehrspolizei Werkhof",
    "wof:placetype":"venue"
},
  "geometry": {"coordinates":[8.588605,46.667873],"type":"Point"}
}