{
  "type": "Feature",
  "properties": {
    "iso:country":"CH",
    "sg:address":"1687 Vuisternens-romont. Postfach",
    "sg:city":"Vuisternens-romont",
    "sg:orig_category":"Sportvereine Ballsport Fussball",
    "sg:phone":"+41 26 655 14 89",
    "sg:postcode":"1687",
    "sg:province":"Fribourg",
    "wof:name":"Fc Vuisternens/m\u00e9zi\u00e8res",
    "wof:placetype":"venue"
},
  "geometry": {"coordinates":[6.9288749695,46.6564064026],"type":"Point"}
}