{
  "type": "Feature",
  "properties": {
    "iso:country":"CH",
    "sg:address":"Leonhardsstrasse 16",
    "sg:city":"Basel",
    "sg:orig_category":"Psychotherapie",
    "sg:phone":"+41 61 261 00 50",
    "sg:postcode":"4051",
    "sg:province":"Basel-Stadt",
    "wof:name":"Ulrich Baud Psychotherapie",
    "wof:placetype":"venue"
},
  "geometry": {"coordinates":[7.5857858658,47.5542984009],"type":"Point"}
}