{
  "type": "Feature",
  "properties": {
    "iso:country":"CH",
    "sg:address":"Amselweg 2",
    "sg:city":"Riggisberg",
    "sg:orig_category":"Sportvereine Turnen Vereine Damen",
    "sg:phone":"+41 31 809 29 43",
    "sg:postcode":"3132",
    "sg:province":"Bern",
    "wof:name":"Damenriege Stv Riggisberg",
    "wof:placetype":"venue"
},
  "geometry": {"coordinates":[7.4749360085,46.8104095459],"type":"Point"}
}