{
  "type": "Feature",
  "properties": {
    "iso:country":"CH",
    "sg:address":"Aeschi 6410 Goldau. Postfach",
    "sg:city":"Goldau",
    "sg:orig_category":"Verwaltung von Immobilien",
    "sg:phone":"+41 41 855 38 77",
    "sg:postcode":"6410",
    "sg:province":"Schwyz",
    "wof:name":"Aeschi Immobilien Ag",
    "wof:placetype":"venue"
},
  "geometry": {"coordinates":[8.5483999252,47.0499839783],"type":"Point"}
}