{
  "type": "Feature",
  "properties": {
    "iso:country":"CH",
    "sg:address":"Oberrohrdorferstrasse 23",
    "sg:city":"Fislisbach",
    "sg:orig_category":"Architektur U Ingenieurb\u00fcros",
    "sg:phone":"+41 56 493 32 53",
    "sg:postcode":"5442",
    "sg:province":"Aargau",
    "wof:name":"Tbb Technischesb\u00fcro",
    "wof:placetype":"venue"
},
  "geometry": {"coordinates":[8.296859,47.440594],"type":"Point"}
}