{
  "type": "Feature",
  "properties": {
    "iso:country":"CH",
    "sg:address":"Emmentalstrasse 5",
    "sg:city":"Konolfingen",
    "sg:orig_category":"Kaminfeger",
    "sg:phone":"+41 31 791 12 39",
    "sg:postcode":"3510",
    "sg:province":"Bern",
    "wof:name":"Arnold Kocher Kaminfegergesch\u00e4ft",
    "wof:placetype":"venue"
},
  "geometry": {"coordinates":[7.62165308,46.8798713684],"type":"Point"}
}