{
  "type": "Feature",
  "properties": {
    "iso:country":"CH",
    "sg:address":"Tigelbergstrasse 1",
    "sg:city":"Berneck",
    "sg:classifiers":[
        {
            "category":"Health Services",
            "subcategory":"Optometrist",
            "type":"Services"
        }
    ],
    "sg:phone":"+41 71 747 70 70",
    "sg:postcode":"9442",
    "sg:province":"St. Gallen",
    "sg:tags":[
        "curtain",
        "clean-room"
    ],
    "wof:name":"Cr\u00e9ation S. Gmbh",
    "wof:placetype":"venue"
},
  "geometry": {"coordinates":[9.609415,47.430485],"type":"Point"}
}