{
  "type": "Feature",
  "properties": {
    "iso:country":"CH",
    "sg:address":"Chemin De Bellevue 3",
    "sg:city":"Prangins",
    "sg:orig_category":"Mechanische Werkst\u00e4tten Schlossereien",
    "sg:phone":"+41 22 990 33 00",
    "sg:postcode":"1197",
    "sg:province":"Vaud",
    "wof:name":"Bovard & Duperrier Atelier M\u00e9canique",
    "wof:placetype":"venue"
},
  "geometry": {"coordinates":[6.2475910187,46.3885154724],"type":"Point"}
}