{
  "type": "Feature",
  "properties": {
    "iso:country":"CH",
    "sg:address":"Via Vallemaggia 17 6600 Locarno Casella Postale 178",
    "sg:city":"Locarno",
    "sg:orig_category":"K\u00fcnstlerische U schriftstellerische T\u00e4tigkeiten U Darbietungen Selbst\u00e4ndige bildende K\u00fcnstler",
    "sg:postcode":"6600",
    "sg:province":"Ticino",
    "wof:name":"Mosaicon Di De Bernardo Roberto",
    "wof:placetype":"venue"
},
  "geometry": {"coordinates":[8.8003940582,46.1705741882],"type":"Point"}
}