{
  "type": "Feature",
  "properties": {
    "iso:country":"CH",
    "sg:address":"Haus Wehri",
    "sg:city":"Gampel",
    "sg:orig_category":"Softwareentwicklung U beratung",
    "sg:phone":"+41 19291035",
    "sg:postcode":"3945",
    "sg:province":"Valais",
    "wof:name":"Computersysteme Werner Grimm",
    "wof:placetype":"venue"
},
  "geometry": {"coordinates":[8.7167205811,47.2690429688],"type":"Point"}
}