{
  "type": "Feature",
  "properties": {
    "iso:country":"CH",
    "sg:address":"Poststrasse 4",
    "sg:city":"Burgdorf",
    "sg:orig_category":"Instandhaltung U Reparatur von Automobilen Vermietung von Automobilen",
    "sg:phone":"+41 27 721 65 10",
    "sg:postcode":"3400",
    "sg:province":"Bern",
    "wof:name":"Carline Automobiles Boisset Sa",
    "wof:placetype":"venue"
},
  "geometry": {"coordinates":[7.0894680023,46.1012077332],"type":"Point"}
}