{
  "type": "Feature",
  "properties": {
    "iso:country":"CH",
    "sg:address":"Rue De L'h\u00f4tel-de-ville 8",
    "sg:city":"Moutier",
    "sg:orig_category":"Detailhandel mit Waren verschiedener Art, Hauptrichtung Nahrungsmittel",
    "sg:phone":"+41 32 493 17 32",
    "sg:postcode":"2740",
    "sg:province":"Bern",
    "wof:name":"Marino & Gerber",
    "wof:placetype":"venue"
},
  "geometry": {"coordinates":[7.3703918457,47.2791061401],"type":"Point"}
}