{
  "type": "Feature",
  "properties": {
    "iso:country":"CH",
    "sg:address":"Flugplatz Speck",
    "sg:city":"Fehraltorf",
    "sg:orig_category":"Sonstige Hilfs U Nebent\u00e4tigkeiten f\u00fcr die Luftfahrt",
    "sg:phone":"+41 19541253",
    "sg:postcode":"8320",
    "sg:province":"Z\u00fcrich",
    "wof:name":"Flugsportgruppe Z\u00fcrcher Oberland",
    "wof:placetype":"venue"
},
  "geometry": {"coordinates":[8.7620201111,47.3765106201],"type":"Point"}
}