{
  "type": "Feature",
  "properties": {
    "iso:country":"CH",
    "sg:address":"Br\u00fcckenstrasse 11",
    "sg:city":"Bern",
    "sg:orig_category":"Patentanwaltsb\u00fcros, Patentverwertung Rechtsberatung",
    "sg:phone":"+41 31 318 27 67",
    "sg:postcode":"3005",
    "sg:province":"Bern",
    "wof:name":"Semacord Technik Ag",
    "wof:placetype":"venue"
},
  "geometry": {"coordinates":[7.4436688423,46.9445266724],"type":"Point"}
}