{
  "type": "Feature",
  "properties": {
    "iso:country":"CH",
    "sg:address":"Eigerstrasse 38",
    "sg:city":"Bern",
    "sg:orig_category":"Primarschulen",
    "sg:phone":"+41 31 371 05 16",
    "sg:postcode":"3007",
    "sg:province":"Bern",
    "wof:name":"Primarschule Sulgenbach",
    "wof:placetype":"venue"
},
  "geometry": {"coordinates":[7.4341740608,46.9401817322],"type":"Point"}
}