{
  "type": "Feature",
  "properties": {
    "iso:country":"CH",
    "sg:address":"De-bud\u00e9 Avenue 13 1202 Gen\u00e8ve. Postfach",
    "sg:city":"Gen\u00e8ve",
    "sg:orig_category":"Dienstleistungen von Beteiligungsgesellschaften",
    "sg:phone":"+41 22 734 55 50",
    "sg:postcode":"1202",
    "sg:province":"Gen\u00e8ve",
    "wof:name":"Cisa Trust Company (switzerland) Sa",
    "wof:placetype":"venue"
},
  "geometry": {"coordinates":[6.142701149,46.2083587646],"type":"Point"}
}