{
  "type": "Feature",
  "properties": {
    "iso:country":"CH",
    "sg:address":"Churweg 15",
    "sg:city":"Trimmis",
    "sg:orig_category":"Architektur U Ingenieurb\u00fcros Architekturb\u00fcros",
    "sg:phone":"+41 81 353 30 36",
    "sg:postcode":"7203",
    "sg:province":"Graubunden",
    "wof:name":"Architekturb\u00fcro Schmid Beat",
    "wof:placetype":"venue"
},
  "geometry": {"coordinates":[9.558815,46.896],"type":"Point"}
}