{
  "type": "Feature",
  "properties": {
    "iso:country":"CH",
    "sg:address":"Spahau",
    "sg:city":"Littau",
    "sg:classifiers":[
        {
            "category":"Autos & Motor Vehicles",
            "subcategory":"Auto Supplies",
            "type":"Retail Goods"
        }
    ],
    "sg:phone":"+41 81 404 15 73",
    "sg:postcode":"6014",
    "sg:province":"Luzern",
    "sg:tags":[
        "test",
        "automobile",
        "brake",
        "stand"
    ],
    "wof:name":"Julius Durisch Garage",
    "wof:placetype":"venue"
},
  "geometry": {"coordinates":[9.645475,46.668179],"type":"Point"}
}