{
  "type": "Feature",
  "properties": {
    "iso:country":"CH",
    "sg:address":"Poststr. 10. 3414 Oberburg. Postfach",
    "sg:city":"Burgdorf",
    "sg:orig_category":"Detailhandel mit Fleisch U Fleischwaren",
    "sg:phone":"+41 56 633 11 38",
    "sg:postcode":"3400",
    "sg:province":"Bern",
    "wof:name":"Walter Staubli",
    "wof:placetype":"venue"
},
  "geometry": {"coordinates":[8.3448781967,47.3512954712],"type":"Point"}
}