{
  "type": "Feature",
  "properties": {
    "iso:country":"CH",
    "sg:address":"Zugerstrasse 58 E 6330 Cham. Postfach 458",
    "sg:city":"Cham",
    "sg:orig_category":"Wirtschaftspr\u00fcfung, Steuerberatung U Treuhand",
    "sg:phone":"+41 41 850 83 09",
    "sg:postcode":"6330",
    "sg:province":"Zug",
    "wof:name":"Tragatsch Stefan Consulting",
    "wof:placetype":"venue"
},
  "geometry": {"coordinates":[8.4380302429,47.0820579529],"type":"Point"}
}