{
  "type": "Feature",
  "properties": {
    "iso:country":"CH",
    "sg:address":"Florastrasse 5",
    "sg:city":"Goldach",
    "sg:orig_category":"Autogaragen",
    "sg:phone":"+41 71 841 88 61",
    "sg:postcode":"9403",
    "sg:province":"St. Gallen",
    "wof:name":"Erwin Klausberger Autoreparaturen",
    "wof:placetype":"venue"
},
  "geometry": {"coordinates":[9.475454,47.475296],"type":"Point"}
}