{
  "type": "Feature",
  "properties": {
    "iso:country":"CH",
    "sg:address":"Kirchweg 4",
    "sg:city":"Sitterdorf",
    "sg:orig_category":"Erbringung von Dienstleistungen f\u00fcr Unternehmen Grafikateliers, Design",
    "sg:phone":"+41 71 422 11 17",
    "sg:postcode":"8589",
    "sg:province":"Thurgau",
    "wof:name":"Hans-rudolf Bieg Schaufenstergestaltung",
    "wof:placetype":"venue"
},
  "geometry": {"coordinates":[9.2484579086,47.5053634644],"type":"Point"}
}