{
  "type": "Feature",
  "properties": {
    "iso:country":"CH",
    "sg:address":"Buckhalde 17",
    "sg:city":"Koblenz",
    "sg:orig_category":"Sonderschulen Wohnheime f\u00fcr Kinder U Jugendliche",
    "sg:phone":"+41 41 497 25 55",
    "sg:postcode":"5322",
    "sg:province":"Aargau",
    "wof:name":"Stiftung Stadtluzernisches Jugendheim Schachen",
    "wof:placetype":"venue"
},
  "geometry": {"coordinates":[8.1451797485,47.0359802246],"type":"Point"}
}