{
  "type": "Feature",
  "properties": {
    "addr:full":"Oberemattstrasse 33 Pratteln Basel-Landschaft 4133",
    "addr:housenumber":"33",
    "addr:postcode":"4133",
    "addr:street":"Oberemattstrasse",
    "iso:country":"CH",
    "sg:address":"Oberemattstrasse 33",
    "sg:city":"Pratteln",
    "sg:orig_category":"Arztpraxen",
    "sg:phone":"+41 61 821 28 38",
    "sg:postcode":"4133",
    "sg:province":"Basel-Landschaft",
    "wof:name":"Dr.med.remo Bittel Spezialarzt Fmh",
    "wof:placetype":"venue"
},
  "geometry": {"coordinates":[7.697924,47.518883],"type":"Point"}
}