{
  "type": "Feature",
  "properties": {
    "iso:country":"CH",
    "sg:address":"Z\u00fcrcherstrasse 1",
    "sg:city":"Eglisau",
    "sg:orig_category":"Mechanische Werkst\u00e4tten",
    "sg:phone":"+41 18673824",
    "sg:postcode":"8193",
    "sg:province":"Z\u00fcrich",
    "wof:name":"Hans Wirth Mechanische Werkst\u00e4tte",
    "wof:placetype":"venue"
},
  "geometry": {"coordinates":[8.5218896866,47.5743103027],"type":"Point"}
}