{
  "type": "Feature",
  "properties": {
    "iso:country":"CH",
    "sg:address":"Valentin Rue Du 30",
    "sg:city":"Lausanne",
    "sg:orig_category":"Betrieb von Sportanlagen",
    "sg:phone":"+41 71 393 60 70",
    "sg:postcode":"1004",
    "sg:province":"Vaud",
    "wof:name":"Ast Eissport Und Solaranlagenbau Ag",
    "wof:placetype":"venue"
},
  "geometry": {"coordinates":[9.188714,47.414207],"type":"Point"}
}