{
  "type": "Feature",
  "properties": {
    "iso:country":"CH",
    "sg:address":"Bardella 72 A",
    "sg:city":"Maienfeld",
    "sg:orig_category":"Technische, physikalische U chemische Untersuchung",
    "sg:postcode":"7304",
    "sg:province":"Graubunden",
    "wof:name":"Ettinger Christian",
    "wof:placetype":"venue"
},
  "geometry": {"coordinates":[9.5341558456,47.0025901794],"type":"Point"}
}