{
  "type": "Feature",
  "properties": {
    "iso:country":"CH",
    "sg:address":"Nauengasse 18",
    "sg:city":"Rorbas",
    "sg:orig_category":"Arztpraxen",
    "sg:phone":"+41 18653737",
    "sg:postcode":"8427",
    "sg:province":"Z\u00fcrich",
    "wof:name":"Dr.med.alfred F\u00fcllemann Arzt F\u00fcr Allgemeine Medizin",
    "wof:placetype":"venue"
},
  "geometry": {"coordinates":[8.577231,47.533749],"type":"Point"}
}