{
  "type": "Feature",
  "properties": {
    "iso:country":"CH",
    "sg:address":"Steigstrasse 41",
    "sg:city":"Schaffhausen",
    "sg:orig_category":"Herstellung von Elektrizit\u00e4tsverteilungs U schalteinrichtungen Herstellung von sonstigen elektrische",
    "sg:phone":"+41 52 625 68 51",
    "sg:postcode":"8200",
    "sg:province":"Schaffhausen",
    "wof:name":"Graf R. & Co Ag",
    "wof:placetype":"venue"
},
  "geometry": {"coordinates":[8.6289796829,47.6958465576],"type":"Point"}
}