{
  "type": "Feature",
  "properties": {
    "iso:country":"CH",
    "sg:address":"Freiburgstrasse 34",
    "sg:city":"Schwarzenburg",
    "sg:classifiers":[
        {
            "category":"Structure",
            "subcategory":"Office Building",
            "type":"Public Place"
        }
    ],
    "sg:phone":"+41 31 734 41 11",
    "sg:postcode":"3150",
    "sg:province":"Bern",
    "sg:tags":[
        "door",
        "automatic",
        "actuator"
    ],
    "wof:name":"Kaba Gilgen Ag Automatische T\u00fcren Und Tore",
    "wof:placetype":"venue"
},
  "geometry": {"coordinates":[7.335895,46.816765],"type":"Point"}
}