{
  "type": "Feature",
  "properties": {
    "iso:country":"CH",
    "sg:address":"Le Coudray",
    "sg:city":"Basse-nendaz",
    "sg:orig_category":"Druck ohne Zeitungsdruck Offsetdruck",
    "sg:phone":"+41 27 288 15 36",
    "sg:postcode":"1996",
    "sg:province":"Valais",
    "wof:name":"Ign, Imprimerie Des Gentianes Nendaz, Lambiel & Fournier",
    "wof:placetype":"venue"
},
  "geometry": {"coordinates":[7.3086600304,46.1922225952],"type":"Point"}
}