{
  "type": "Feature",
  "properties": {
    "iso:country":"CH",
    "sg:address":"Diebold-schilling-strasse 1",
    "sg:city":"Luzern",
    "sg:orig_category":"Kunsthandel",
    "sg:phone":"+41 41 410 26 74",
    "sg:postcode":"6004",
    "sg:province":"Luzern",
    "wof:name":"Galerie Diebold-schilling",
    "wof:placetype":"venue"
},
  "geometry": {"coordinates":[8.3045711517,47.0554771423],"type":"Point"}
}