{
  "type": "Feature",
  "properties": {
    "addr:full":"Cholplatzweg 22 Trimmis Graubunden 7203",
    "addr:housenumber":"22",
    "addr:postcode":"7203",
    "addr:street":"Cholplatzweg",
    "iso:country":"CH",
    "sg:address":"Cholplatzweg 22",
    "sg:city":"Trimmis",
    "sg:classifiers":[
        {
            "category":"Building & Trades",
            "subcategory":"Construction",
            "type":"Services"
        }
    ],
    "sg:phone":"+41 81 353 88 00",
    "sg:postcode":"7203",
    "sg:province":"Graubunden",
    "sg:tags":[
        "carpenter's",
        "tool"
    ],
    "wof:name":"Rudolf Fitzi",
    "wof:placetype":"venue"
},
  "geometry": {"coordinates":[9.555143,46.902054],"type":"Point"}
}