{
  "type": "Feature",
  "properties": {
    "iso:country":"CH",
    "sg:address":"Risimattli 7 6072 Sachseln. Postfach",
    "sg:city":"Sachseln",
    "sg:orig_category":"Handel mit Automobilen",
    "sg:postcode":"6072",
    "sg:province":"Obwalden",
    "wof:name":"El-hajj Hassan Fahmi Autohandel",
    "wof:placetype":"venue"
},
  "geometry": {"coordinates":[8.2368373871,46.8648490906],"type":"Point"}
}