{
  "type": "Feature",
  "properties": {
    "iso:country":"CH",
    "sg:address":"Sennereigasse",
    "sg:city":"Sevelen",
    "sg:classifiers":[
        {
            "category":"Restaurant",
            "type":"Food & Drink"
        }
    ],
    "sg:phone":"+41 18582203",
    "sg:postcode":"9475",
    "sg:province":"St. Gallen",
    "wof:name":"Restaurant Alte Post",
    "wof:placetype":"venue"
},
  "geometry": {"coordinates":[8.4187402725,47.5677604675],"type":"Point"}
}