{
  "type": "Feature",
  "properties": {
    "iso:country":"CH",
    "sg:address":"Casa Hirundella",
    "sg:city":"Waltensburg/vuorz",
    "sg:orig_category":"Detailhandel mit B\u00fcchern, Zeitungen, Schreib U Papeteriewaren",
    "sg:phone":"+41 71 744 21 23",
    "sg:postcode":"7158",
    "sg:province":"Graubunden",
    "wof:name":"Herby's Kiosk & Shop, Steiger Anna",
    "wof:placetype":"venue"
},
  "geometry": {"coordinates":[9.638302,47.449005],"type":"Point"}
}