{
  "type": "Feature",
  "properties": {
    "iso:country":"CH",
    "sg:address":"Oberdorfstrasse 30",
    "sg:city":"Konolfingen",
    "sg:orig_category":"Primarschulen",
    "sg:phone":"+41 34 402 12 85",
    "sg:postcode":"3510",
    "sg:province":"Bern",
    "wof:name":"Primarschule Dorf",
    "wof:placetype":"venue"
},
  "geometry": {"coordinates":[7.6278781891,46.8885917664],"type":"Point"}
}