{
  "type": "Feature",
  "properties": {
    "iso:country":"CH",
    "sg:address":"Seeblickstrasse 14 8280 Kreuzlingen. Postfach",
    "sg:city":"Kreuzlingen",
    "sg:orig_category":"Herstellung von k\u00e4lte U lufttechnischen Erzeugnissen f\u00fcr gewerbliche Zwecke Installation von Heizung",
    "sg:phone":"+41 17813770",
    "sg:postcode":"8280",
    "sg:province":"Thurgau",
    "wof:name":"Rog-air, M\u00fcller Roger, Klima Und L\u00fcftungsmontagen",
    "wof:placetype":"venue"
},
  "geometry": {"coordinates":[8.630979538,47.246383667],"type":"Point"}
}