{
  "type": "Feature",
  "properties": {
    "iso:country":"CH",
    "sg:address":"1678 Siviriez. Postfach 18",
    "sg:city":"Siviriez",
    "sg:orig_category":"Sportvereine Ballsport Fussball",
    "sg:phone":"+41 21 803 30 16",
    "sg:postcode":"1678",
    "sg:province":"Fribourg",
    "wof:name":"Fc Slavia Ls",
    "wof:placetype":"venue"
},
  "geometry": {"coordinates":[6.579390049,46.5390815735],"type":"Point"}
}