{
  "type": "Feature",
  "properties": {
    "iso:country":"CH",
    "sg:address":"Grandchamp 5",
    "sg:city":"Areuse",
    "sg:orig_category":"Museen",
    "sg:phone":"+41 32 842 30 46",
    "sg:postcode":"2015",
    "sg:province":"Neuch\u00e2tel",
    "wof:name":"Jacques Bovet Mus\u00e9e De L'areuse",
    "wof:placetype":"venue"
},
  "geometry": {"coordinates":[6.8571648598,46.9572257996],"type":"Point"}
}