{
  "type": "Feature",
  "properties": {
    "iso:country":"CH",
    "sg:address":"6775",
    "sg:city":"Ambr\u00ec",
    "sg:orig_category":"Herstellung von Ger\u00e4ten der Elektrizit\u00e4tserzeugung, -verteilung u.\u00e4. -Herstellung von elektronischen",
    "sg:phone":"+41 91 868 12 55",
    "sg:postcode":"6775",
    "sg:province":"Ticino",
    "wof:name":"Juri Adolfo",
    "wof:placetype":"venue"
},
  "geometry": {"coordinates":[8.6938772202,46.5097541809],"type":"Point"}
}