{
  "type": "Feature",
  "properties": {
    "iso:country":"CH",
    "sg:address":"Stationsstrasse 32",
    "sg:city":"Seuzach",
    "sg:orig_category":"Sonstiger Grosshandel",
    "sg:phone":"+41 52 335 40 50",
    "sg:postcode":"8472",
    "sg:province":"Z\u00fcrich",
    "wof:name":"Frank Westrade",
    "wof:placetype":"venue"
},
  "geometry": {"coordinates":[8.7352828979,47.5364646912],"type":"Point"}
}