{
  "type": "Feature",
  "properties": {
    "iso:country":"CH",
    "sg:address":"Dorfstrasse 50 8834 Schindellegi. Postfach",
    "sg:city":"Schindellegi",
    "sg:orig_category":"Unclassifiable Establishments",
    "sg:postcode":"8834",
    "sg:province":"Schwyz",
    "wof:name":"K\u00fchne & Nagel Asia Pacific Holding Ag",
    "wof:placetype":"venue"
},
  "geometry": {"coordinates":[8.7073135376,47.1784858704],"type":"Point"}
}