{
  "type": "Feature",
  "properties": {
    "iso:country":"CH",
    "sg:address":"Dorfplatz 2 6330 Cham. Postfach 376",
    "sg:city":"Cham",
    "sg:orig_category":"Grosshandel mit Nahrungsmitteln, Getr\u00e4nken U Tabakwaren Grosshandel mit chemischen Erzeugnissen",
    "sg:phone":"+41 62 926 01 16",
    "sg:postcode":"6330",
    "sg:province":"Zug",
    "wof:name":"Hippler Ag Handelsfirma",
    "wof:placetype":"venue"
},
  "geometry": {"coordinates":[7.8371567726,47.2683372498],"type":"Point"}
}