{
  "type": "Feature",
  "properties": {
    "iso:country":"CH",
    "sg:address":"Chemin Des Ouches 10",
    "sg:city":"St-blaise",
    "sg:orig_category":"Fachdetailhandel in Verkaufsr\u00e4umen Sonstiger Fachdetailhandel in Verkaufsr\u00e4umen",
    "sg:phone":"+41 32 753 12 54",
    "sg:postcode":"2072",
    "sg:province":"Neuch\u00e2tel",
    "wof:name":"Philat\u00e9lie Cuche Sa",
    "wof:placetype":"venue"
},
  "geometry": {"coordinates":[6.9891338348,47.0156593323],"type":"Point"}
}