{
  "type": "Feature",
  "properties": {
    "iso:country":"CH",
    "sg:address":"Av. Louis-weck-reynold 62",
    "sg:city":"Fribourg",
    "sg:orig_category":"Mechanik",
    "sg:phone":"+41 26 424 70 23",
    "sg:postcode":"1700",
    "sg:province":"Fribourg",
    "wof:name":"Jenny Jean-pierre",
    "wof:placetype":"venue"
},
  "geometry": {"coordinates":[7.1466798782,46.8093490601],"type":"Point"}
}