{
  "type": "Feature",
  "properties": {
    "iso:country":"CH",
    "sg:address":"Hauptstrasse",
    "sg:city":"D\u00e4rstetten",
    "sg:classifiers":[
        {
            "category":"Banks & Credit Unions",
            "subcategory":"Bank",
            "type":"Services"
        }
    ],
    "sg:phone":"+41 33831883",
    "sg:postcode":"3763",
    "sg:province":"Bern",
    "wof:name":"Raiffeisenkasse",
    "wof:placetype":"venue"
},
  "geometry": {"coordinates":[7.4909181595,46.6591072083],"type":"Point"}
}