{
  "type": "Feature",
  "properties": {
    "iso:country":"CH",
    "sg:address":"Alte Steinhauserstrasse 19",
    "sg:city":"Cham",
    "sg:orig_category":"Grosshandel mit B\u00fcromaschinen Grosshandel mit Datenverarbeitungsger\u00e4ten",
    "sg:phone":"+41 41 740 17 77",
    "sg:postcode":"6330",
    "sg:province":"Zug",
    "wof:name":"Sys-x Gmbh Edv-dienstleistungen",
    "wof:placetype":"venue"
},
  "geometry": {"coordinates":[8.4743642807,47.1882553101],"type":"Point"}
}