{
  "type": "Feature",
  "properties": {
    "iso:country":"CH",
    "sg:address":"Belsitostrasse 12 8000 Z\u00fcrich. Postfach",
    "sg:city":"Z\u00fcrich",
    "sg:orig_category":"Wirtschaftspr\u00fcfung, Steuerberatung U Treuhand",
    "sg:postcode":"8044",
    "sg:province":"Z\u00fcrich",
    "wof:name":"Z\u00fcrichberg Treuhand Ag",
    "wof:placetype":"venue"
},
  "geometry": {"coordinates":[8.5620336533,47.3745193481],"type":"Point"}
}