{
  "type": "Feature",
  "properties": {
    "iso:country":"CH",
    "sg:address":"Alemannenweg 5",
    "sg:city":"Obermumpf",
    "sg:orig_category":"Fernmeldedienste Radio U Fernsehanstalten",
    "sg:postcode":"4324",
    "sg:province":"Aargau",
    "wof:name":"Werner Stocker Fernsehgenoss.obermumpf",
    "wof:placetype":"venue"
},
  "geometry": {"coordinates":[7.9367308617,47.5310287476],"type":"Point"}
}