{
  "type": "Feature",
  "properties": {
    "iso:country":"CH",
    "sg:address":"Wegenstettenstrasse 195",
    "sg:city":"Schupfart",
    "sg:orig_category":"Sanit\u00e4r, Heizungs U L\u00fcftungsinstallation Sanit\u00e4rinstallation",
    "sg:phone":"+41 62 216 41 31",
    "sg:postcode":"4325",
    "sg:province":"Aargau",
    "wof:name":"Heck Peter Heizungs Und Sanit\u00e4ranlagen",
    "wof:placetype":"venue"
},
  "geometry": {"coordinates":[7.8470420837,47.323009491],"type":"Point"}
}