{
  "type": "Feature",
  "properties": {
    "iso:country":"CH",
    "sg:address":"Wettingerstrasse 17",
    "sg:city":"Baden",
    "sg:orig_category":"Einzelhandel mit Automobilteilen U Zubeh\u00f6r Handel mit Automobilteilen U Zubeh\u00f6r",
    "sg:phone":"+41 56 222 09 03",
    "sg:postcode":"5400",
    "sg:province":"Aargau",
    "wof:name":"Fm Autozubeh\u00f6r Mancina Francesco",
    "wof:placetype":"venue"
},
  "geometry": {"coordinates":[8.3121376038,47.4721336365],"type":"Point"}
}