{
  "type": "Feature",
  "properties": {
    "iso:country":"CH",
    "sg:address":"Schulgasse 15",
    "sg:city":"Nidau",
    "sg:orig_category":"Markt U Meinungsforschung Unternehmensberatung",
    "sg:phone":"+41 32 331 22 20",
    "sg:postcode":"2560",
    "sg:province":"Bern",
    "wof:name":"William Zahner & Associ\u00e9s Uebersetzung & Unternehmensb.",
    "wof:placetype":"venue"
},
  "geometry": {"coordinates":[7.2401070595,47.1244697571],"type":"Point"}
}