{
  "type": "Feature",
  "properties": {
    "iso:country":"CH",
    "sg:address":"Terrassenweg 12",
    "sg:city":"Bern",
    "sg:orig_category":"Werbegrafikateliers",
    "sg:phone":"+41 61 401 52 20",
    "sg:postcode":"3012",
    "sg:province":"Bern",
    "wof:name":"Roland Scheller Grafisches Atelier Asg",
    "wof:placetype":"venue"
},
  "geometry": {"coordinates":[7.5645670891,47.5161170959],"type":"Point"}
}