{
  "type": "Feature",
  "properties": {
    "iso:country":"CH",
    "sg:address":"Avenue D'echallens 126 1000 Lausanne. Postfach",
    "sg:city":"Lausanne",
    "sg:orig_category":"Grosshandel mit Getr\u00e4nken",
    "sg:phone":"+41 27 306 25 96",
    "sg:postcode":"1003",
    "sg:province":"Vaud",
    "wof:name":"Cave La D\u00f4le Blanche S\u00e0rl",
    "wof:placetype":"venue"
},
  "geometry": {"coordinates":[7.2086448669,46.1864585876],"type":"Point"}
}