{
  "type": "Feature",
  "properties": {
    "addr:full":"Route D'italie Uvrier Valais 1958",
    "addr:postcode":"1958",
    "addr:street":"Route D'Italie",
    "iso:country":"CH",
    "sg:address":"Route D'italie",
    "sg:city":"Uvrier",
    "sg:orig_category":"Detailhandel mit Brot, Back U S\u00fcsswaren",
    "sg:phone":"+41 27 203 10 98",
    "sg:postcode":"1958",
    "sg:province":"Valais",
    "wof:name":"Pellet Alphonse Sa",
    "wof:placetype":"venue"
},
  "geometry": {"coordinates":[7.411451,46.251934],"type":"Point"}
}