{
  "type": "Feature",
  "properties": {
    "iso:country":"CH",
    "sg:address":"Neudorfstrasse 33",
    "sg:city":"Menzingen",
    "sg:orig_category":"Non-Classified Establishments",
    "sg:postcode":"6313",
    "sg:province":"Zug",
    "wof:name":"Nettrade Gmbh",
    "wof:placetype":"venue"
},
  "geometry": {"coordinates":[8.5940113068,47.1765098572],"type":"Point"}
}