{
  "type": "Feature",
  "properties": {
    "iso:country":"CH",
    "sg:address":"L\u00f6wenstrasse 5",
    "sg:city":"Romanshorn",
    "sg:classifiers":[
        {
            "category":"Restaurant",
            "type":"Food & Drink"
        }
    ],
    "sg:phone":"+41 71 463 12 16",
    "sg:postcode":"8590",
    "sg:province":"Thurgau",
    "wof:name":"Restaurant Corallo Blu",
    "wof:placetype":"venue"
},
  "geometry": {"coordinates":[9.3780221939,47.5652694702],"type":"Point"}
}