{
  "type": "Feature",
  "properties": {
    "iso:country":"CH",
    "sg:address":"Hauptstrasse 15",
    "sg:city":"Arbon",
    "sg:orig_category":"RESTAURANTS: TEA-ROOMS",
    "sg:postcode":"9320",
    "sg:province":"Thurgau",
    "wof:name":"Arborum Gastro Gmbh",
    "wof:placetype":"venue"
},
  "geometry": {"coordinates":[9.4354276657,47.5159378052],"type":"Point"}
}