{
  "type": "Feature",
  "properties": {
    "iso:country":"CH",
    "sg:address":"Grand-rue 49 2720 Tramlingen. Postfach",
    "sg:city":"Tramlingen",
    "sg:orig_category":"Allgemeiner Hoch U Tiefbau",
    "sg:postcode":"2720",
    "sg:province":"Bern",
    "wof:name":"Arti Gestion S\u00e0rl Gestion D'entreprises Artisanales Des M\u00e9tiers Du B\u00e2timent Et Des Travaux Publics Etc",
    "wof:placetype":"venue"
},
  "geometry": {"coordinates":[7.113579,47.22316],"type":"Point"}
}