{
  "type": "Feature",
  "properties": {
    "iso:country":"CH",
    "sg:address":"G\u00f6tschihogerweg 1",
    "sg:city":"Aeugstertal",
    "sg:orig_category":"Architekturb\u00fcros",
    "sg:phone":"+41 32 931 37 31",
    "sg:postcode":"8914",
    "sg:province":"Z\u00fcrich",
    "wof:name":"Gtu-ncl Urbanisme & Architecture",
    "wof:placetype":"venue"
},
  "geometry": {"coordinates":[6.751312,47.059868],"type":"Point"}
}