{
  "type": "Feature",
  "properties": {
    "iso:country":"CH",
    "sg:address":"Z\u00fcrcherstrasse 9",
    "sg:city":"Siebnen",
    "sg:orig_category":"Verwertung von Milch",
    "sg:postcode":"8854",
    "sg:province":"Schwyz",
    "wof:name":"Kaufmann H.j. Molkerei.",
    "wof:placetype":"venue"
},
  "geometry": {"coordinates":[8.8954076767,47.1750183105],"type":"Point"}
}