{
  "type": "Feature",
  "properties": {
    "iso:country":"CH",
    "sg:address":"Rosenstrasse 2",
    "sg:city":"Berneck",
    "sg:orig_category":"Detailhandel mit Getr\u00e4nken G\u00fcterbef\u00f6rderung im Strassenverkehr",
    "sg:phone":"+41 71 744 13 53",
    "sg:postcode":"9442",
    "sg:province":"St. Gallen",
    "wof:name":"Ernst Sch\u00fcmperli",
    "wof:placetype":"venue"
},
  "geometry": {"coordinates":[9.6183862686,47.4263954163],"type":"Point"}
}