{
  "type": "Feature",
  "properties": {
    "iso:country":"CH",
    "sg:address":"T\u00fcbacherstrasse 12b",
    "sg:city":"Horn",
    "sg:orig_category":"Unclassifiable Establishments",
    "sg:postcode":"9326",
    "sg:province":"Thurgau",
    "wof:name":"Interpublic Ruckstuhl U.",
    "wof:placetype":"venue"
},
  "geometry": {"coordinates":[9.4615697861,47.4945030212],"type":"Point"}
}