{
  "type": "Feature",
  "properties": {
    "iso:country":"CH",
    "sg:address":"Seminarstrasse 4",
    "sg:city":"Kreuzlingen",
    "sg:orig_category":"Botanische U zoologische G\u00e4rten sowie Naturparks",
    "sg:phone":"+41 71 688 40 34",
    "sg:postcode":"8280",
    "sg:province":"Thurgau",
    "wof:name":"Tierpark Seeburg",
    "wof:placetype":"venue"
},
  "geometry": {"coordinates":[9.181469,47.645367],"type":"Point"}
}