{
  "type": "Feature",
  "properties": {
    "iso:country":"CH",
    "sg:address":"M\u00fchlethalstrasse 53 4800 Zofingen. Postfach",
    "sg:city":"Oftringen",
    "sg:orig_category":"Grosshandel mit Werkzeugmaschinen",
    "sg:postcode":"4665",
    "sg:province":"Aargau",
    "wof:name":"Abanus Gmbh Maschinen, Bes. Werkzeugmaschinen; Handel, Service, Herst.",
    "wof:placetype":"venue"
},
  "geometry": {"coordinates":[7.9514169693,47.2978744507],"type":"Point"}
}