{
  "type": "Feature",
  "properties": {
    "iso:country":"CH",
    "sg:address":"Pilatusstrasse 13",
    "sg:city":"Aarburg",
    "sg:orig_category":"Datenverarbeitungsdienste Unternehmensberatung",
    "sg:phone":"+41 62 787 70 80",
    "sg:postcode":"4663",
    "sg:province":"Aargau",
    "wof:name":"Consultingpool Ag Betriebswirtschaftliche U. Organisatorische Managementberatung Usw",
    "wof:placetype":"venue"
},
  "geometry": {"coordinates":[7.901378,47.319027],"type":"Point"}
}