{
  "type": "Feature",
  "properties": {
    "iso:country":"CH",
    "sg:address":"Gerechtigkeitsgasse 14",
    "sg:city":"Bern",
    "sg:orig_category":"Arztpraxen",
    "sg:phone":"+41 31 312 12 51",
    "sg:postcode":"3011",
    "sg:province":"Bern",
    "wof:name":"Dr.med.werner Stadelmann Spezialarzt Fmh",
    "wof:placetype":"venue"
},
  "geometry": {"coordinates":[7.455505,46.948753],"type":"Point"}
}