{
  "type": "Feature",
  "properties": {
    "iso:country":"CH",
    "sg:address":"Kalberweidliweg 4",
    "sg:city":"Niederg\u00f6sgen",
    "sg:orig_category":"Detailhandel mit Lederwaren U Reiseartikeln",
    "sg:phone":"+41 62 849 52 78",
    "sg:postcode":"5013",
    "sg:province":"Solothurn",
    "wof:name":"Cornelia L\u00fcthy Lederwaren Bl\u00e4ttler",
    "wof:placetype":"venue"
},
  "geometry": {"coordinates":[7.9849801064,47.3739318848],"type":"Point"}
}