{
  "type": "Feature",
  "properties": {
    "iso:country":"CH",
    "sg:address":"Untere Hauptgasse 14",
    "sg:city":"Thun",
    "sg:classifiers":[
        {
            "category":"Government",
            "subcategory":"Post Office",
            "type":"Public Place"
        }
    ],
    "sg:phone":"+41 33 223 43 60",
    "sg:postcode":"3600",
    "sg:province":"Bern",
    "sg:tags":[
        "caf\u00e9s",
        "tea-rooms"
    ],
    "wof:name":"Tea-room Altstadt",
    "wof:placetype":"venue"
},
  "geometry": {"coordinates":[7.6287989616,46.7603187561],"type":"Point"}
}