{
  "type": "Feature",
  "properties": {
    "iso:country":"CH",
    "sg:address":"Schwelle 6003d",
    "sg:city":"Eggiwil",
    "sg:orig_category":"Herstellung von Reiseartikeln, Leder U Sattlerwaren Verlegen von Fussboden",
    "sg:phone":"+41 34 491 23 31",
    "sg:postcode":"3537",
    "sg:province":"Bern",
    "wof:name":"M. & H. Schneeberger Gmbh Sattlerei & Bodenbel\u00e4ge",
    "wof:placetype":"venue"
},
  "geometry": {"coordinates":[7.789935112,46.8806648254],"type":"Point"}
}