{
  "type": "Feature",
  "properties": {
    "iso:country":"CH",
    "sg:address":"Bl\u00e4siring 150 4057 Basel. Postfach",
    "sg:city":"Basel",
    "sg:orig_category":"Fachdetailhandel in Verkaufsr\u00e4umen",
    "sg:phone":"+41 61 692 60 60",
    "sg:postcode":"4051",
    "sg:province":"Basel-Stadt",
    "wof:name":"Velovermietung Velothek G. B\u00f6sch Velo, Veloanh\u00e4nger, Spezialvelo; Vermietung",
    "wof:placetype":"venue"
},
  "geometry": {"coordinates":[7.5951352119,47.5685806274],"type":"Point"}
}