{
  "type": "Feature",
  "properties": {
    "iso:country":"CH",
    "sg:address":"Kasernenstrasse 10",
    "sg:city":"B\u00fclach",
    "sg:orig_category":"Sonstige pers\u00f6nliche Dienstleistungen",
    "sg:postcode":"8180",
    "sg:province":"Z\u00fcrich",
    "wof:name":"Kovacs Lajos, Generalagentur Der Winterthur-leben",
    "wof:placetype":"venue"
},
  "geometry": {"coordinates":[8.5391664505,47.5188102722],"type":"Point"}
}