{
  "type": "Feature",
  "properties": {
    "iso:country":"CH",
    "sg:address":"Brunnweg 11",
    "sg:city":"M\u00fchleberg",
    "sg:orig_category":"Unternehmensberatung",
    "sg:postcode":"3203",
    "sg:province":"Bern",
    "wof:name":"Varnholt Consulting Ag",
    "wof:placetype":"venue"
},
  "geometry": {"coordinates":[9.2849197388,47.1935844421],"type":"Point"}
}