{
  "type": "Feature",
  "properties": {
    "iso:country":"CH",
    "sg:address":"Bahnhofstrasse 16",
    "sg:city":"Niederurnen",
    "sg:orig_category":"Zahnarztpraxen",
    "sg:phone":"+41 55 610 41 21",
    "sg:postcode":"8867",
    "sg:province":"Glarus",
    "wof:name":"Dr. Med. Dent. Thomas Walter Zahnarzt",
    "wof:placetype":"venue"
},
  "geometry": {"coordinates":[9.0576028824,47.1234397888],"type":"Point"}
}