{
  "type": "Feature",
  "properties": {
    "iso:country":"CH",
    "sg:address":"Neuengasse 43a 2502 Biel/bienne. Postfach",
    "sg:city":"Biel/bienne",
    "sg:orig_category":"Detailhandel mit Geschenkartikeln U Souvenirs Herstellung von Oberbekleidung",
    "sg:phone":"+41 32 322 03 02",
    "sg:postcode":"2501",
    "sg:province":"Bern",
    "wof:name":"Bouzaglo J.",
    "wof:placetype":"venue"
},
  "geometry": {"coordinates":[7.2472572327,47.1408882141],"type":"Point"}
}