{
  "type": "Feature",
  "properties": {
    "iso:country":"CH",
    "sg:address":"M\u00fcnchwilerstrasse 40 9554 T\u00e4gerschen. Postfach",
    "sg:city":"T\u00e4gerschen",
    "sg:orig_category":"Herstellung von k\u00e4lte U lufttechnischen Erzeugnissen f\u00fcr gewerbliche Zwecke Sanit\u00e4rinstallation",
    "sg:phone":"+41 81 756 53 25",
    "sg:postcode":"9554",
    "sg:province":"Thurgau",
    "wof:name":"Hsh Installationstechnik Gmbh",
    "wof:placetype":"venue"
},
  "geometry": {"coordinates":[9.4691066742,47.1717185974],"type":"Point"}
}