{
  "type": "Feature",
  "properties": {
    "iso:country":"CH",
    "sg:address":"Route Du Mandement 201",
    "sg:city":"Satigny",
    "sg:orig_category":"Rebbau",
    "sg:phone":"+41 22 753 12 30",
    "sg:postcode":"1242",
    "sg:province":"Gen\u00e8ve",
    "wof:name":"Charles Novelle & Fils Viticulture Le Grand Clos",
    "wof:placetype":"venue"
},
  "geometry": {"coordinates":[6.0304818153,46.2122306824],"type":"Point"}
}