{
  "type": "Feature",
  "properties": {
    "iso:country":"CH",
    "sg:address":"Adlergartenstrasse",
    "sg:city":"Schattdorf",
    "sg:orig_category":"Detailhandel mit Brot, Back U S\u00fcsswaren",
    "sg:postcode":"6467",
    "sg:province":"Uri",
    "wof:name":"Ignaz Schirmer, B\u00e4ckerei-konditorei",
    "wof:placetype":"venue"
},
  "geometry": {"coordinates":[8.65007,46.864613],"type":"Point"}
}