{
  "type": "Feature",
  "properties": {
    "iso:country":"CH",
    "sg:address":"Hauptstrasse 12",
    "sg:city":"Worben",
    "sg:orig_category":"Wasserversorgung",
    "sg:phone":"+41 32 384 04 44",
    "sg:postcode":"3252",
    "sg:province":"Bern",
    "wof:name":"Seel\u00e4ndische Wasserversorgung Swg",
    "wof:placetype":"venue"
},
  "geometry": {"coordinates":[7.2929730415,47.1013526917],"type":"Point"}
}