{
  "type": "Feature",
  "properties": {
    "iso:country":"CH",
    "sg:address":"Bernstrasse 45",
    "sg:city":"M\u00fcnsingen",
    "sg:orig_category":"Elektroinstallation",
    "sg:phone":"+41 31 781 33 30",
    "sg:postcode":"3110",
    "sg:province":"Bern",
    "wof:name":"Elektro M\u00f6ri",
    "wof:placetype":"venue"
},
  "geometry": {"coordinates":[7.5447449684,46.8177452087],"type":"Point"}
}