{
  "type": "Feature",
  "properties": {
    "iso:country":"CH",
    "sg:address":"Avenue De Rochettaz 36",
    "sg:city":"Pully",
    "sg:orig_category":"Allgemeiner Hoch U Tiefbau Architekturb\u00fcros",
    "sg:phone":"+41 81 832 14 75",
    "sg:postcode":"1009",
    "sg:province":"Vaud",
    "wof:name":"Pitsch + Pitsch Ag",
    "wof:placetype":"venue"
},
  "geometry": {"coordinates":[9.819537,46.482731],"type":"Point"}
}