{
  "type": "Feature",
  "properties": {
    "iso:country":"CH",
    "sg:address":"Burgdorfstrasse 33",
    "sg:city":"R\u00fcdtligen",
    "sg:classifiers":[
        {
            "category":"Personal",
            "subcategory":"Sauna",
            "type":"Services"
        }
    ],
    "sg:phone":"+41 34 445 44 82",
    "sg:postcode":"3422",
    "sg:province":"Bern",
    "wof:name":"Hanno Thomann Finn Saunab\u00e4der",
    "wof:placetype":"venue"
},
  "geometry": {"coordinates":[7.5844497681,47.0851898193],"type":"Point"}
}