{
  "type": "Feature",
  "properties": {
    "iso:country":"CH",
    "sg:address":"La Coudre",
    "sg:city":"Mont-la-ville",
    "sg:orig_category":"Tierarztpraxis",
    "sg:phone":"+41 21 864 52 51",
    "sg:postcode":"1328",
    "wof:name":"Dr M\u00e9d. V\u00e9t. Pierre Dumauthioz M\u00e9decin V\u00e9t\u00e9rinaire",
    "wof:placetype":"venue"
},
  "geometry": {"coordinates":[6.4071240425,46.6446990967],"type":"Point"}
}