{
  "type": "Feature",
  "properties": {
    "iso:country":"CH",
    "sg:address":"Bernstrasse 392",
    "sg:city":"Dietikon",
    "sg:orig_category":"Berufliche Weiterbildung, Erwachsenenbildung",
    "sg:phone":"+41 17444747",
    "sg:postcode":"8953",
    "sg:province":"Z\u00fcrich",
    "wof:name":"Netg Gmbh, D\u00fcsseldorf, Zweigniederlassung Dietikon Audio, Video-kassetten, Schriftliches Begleitmaterial Usw.; Herstellung, Vertrieb, Verkauf",
    "wof:placetype":"venue"
},
  "geometry": {"coordinates":[8.395445,47.382839],"type":"Point"}
}