{
  "type": "Feature",
  "properties": {
    "iso:country":"CH",
    "sg:address":"Rautistrasse 106",
    "sg:city":"Z\u00fcrich",
    "sg:orig_category":"Allgemeiner Gartenbau Pensionskassen",
    "sg:phone":"+41 32 686 68 68",
    "sg:postcode":"8048",
    "sg:province":"Z\u00fcrich",
    "wof:name":"Personalstiftung Der Wyss Samen Und Pflanzen Ag.",
    "wof:placetype":"venue"
},
  "geometry": {"coordinates":[8.486406,47.382843],"type":"Point"}
}