{
  "type": "Feature",
  "properties": {
    "iso:country":"CH",
    "sg:address":"Unneri Strass 20 3900 Gamsen. Postfach 139",
    "sg:city":"Glis",
    "sg:orig_category":"Herstellung von Metallkonstruktionen Schlossereien",
    "sg:phone":"+41 27 922 44 31",
    "sg:postcode":"3902",
    "sg:province":"Valais",
    "wof:name":"Metallprofi In-albon Ren\u00e9 Ag",
    "wof:placetype":"venue"
},
  "geometry": {"coordinates":[7.9876461029,46.3158912659],"type":"Point"}
}