{
  "type": "Feature",
  "properties": {
    "iso:country":"CH",
    "sg:address":"Faubourg Du Lac 10",
    "sg:city":"Neuch\u00e2tel",
    "sg:classifiers":[
        {
            "category":"Restaurant",
            "type":"Food & Drink"
        }
    ],
    "sg:phone":"+41 32 721 35 35",
    "sg:postcode":"2000",
    "sg:province":"Neuch\u00e2tel",
    "wof:name":"Brasserie De La Poste",
    "wof:placetype":"venue"
},
  "geometry": {"coordinates":[6.9322090149,46.9915618896],"type":"Point"}
}