{
  "type": "Feature",
  "properties": {
    "iso:country":"CH",
    "sg:address":"Engadinstrasse 30",
    "sg:city":"Chur",
    "sg:classifiers":[
        {
            "category":"Professional",
            "subcategory":"Employment Agencies",
            "type":"Services"
        }
    ],
    "sg:phone":"+41 12186080",
    "sg:postcode":"7000",
    "sg:province":"Graubunden",
    "sg:tags":[
        "personal",
        "u",
        "stellenvermittlung"
    ],
    "wof:name":"Gross Business Ag Lachen",
    "wof:placetype":"venue"
},
  "geometry": {"coordinates":[8.8512620926,47.1924057007],"type":"Point"}
}