{
  "type": "Feature",
  "properties": {
    "iso:country":"CH",
    "sg:address":"Kasinog\u00e4sschen 19",
    "sg:city":"Schaffhausen",
    "sg:orig_category":"Vorschulen, Kinderg\u00e4rten",
    "sg:phone":"+41 52 624 12 03",
    "sg:postcode":"8200",
    "sg:province":"Schaffhausen",
    "wof:name":"Kindergarten Vordersteig",
    "wof:placetype":"venue"
},
  "geometry": {"coordinates":[8.6296253204,47.6966743469],"type":"Point"}
}