{
  "type": "Feature",
  "properties": {
    "iso:country":"CH",
    "sg:address":"T\u00e4gerhardstrasse 118",
    "sg:city":"Wettingen",
    "sg:orig_category":"Allgemeiner Hoch U Tiefbau Allgemeiner Hochbau",
    "sg:phone":"+41 52 765 17 53",
    "sg:postcode":"5430",
    "sg:province":"Aargau",
    "wof:name":"H\u00e4ni Bau Ag, Bauunternehmung Und Elementfabrikation",
    "wof:placetype":"venue"
},
  "geometry": {"coordinates":[8.950717,47.614792],"type":"Point"}
}