{
  "type": "Feature",
  "properties": {
    "iso:country":"CH",
    "sg:address":"S\u00fcdstrasse 45 2500 Biel/bienne. Postfach",
    "sg:city":"Biel/bienne",
    "sg:orig_category":"Oberfl\u00e4chenveredlung U W\u00e4rmebehandlung",
    "sg:phone":"+41 71 288 52 52",
    "sg:postcode":"2504",
    "sg:province":"Bern",
    "wof:name":"Chromwerk Ag",
    "wof:placetype":"venue"
},
  "geometry": {"coordinates":[9.4245443344,47.4425964355],"type":"Point"}
}