{
  "type": "Feature",
  "properties": {
    "iso:country":"CH",
    "sg:address":"Via Santeri 20 7130 Ilanz. Postfach",
    "sg:city":"Ilanz",
    "sg:orig_category":"G\u00fcterbef\u00f6rderung im Strassenverkehr Regelm\u00e4ssige Personenbef\u00f6rderung im Fernverkehr",
    "sg:phone":"+41 81 925 16 56",
    "sg:postcode":"7130",
    "sg:province":"Graubunden",
    "wof:name":"Sol\u00e8r & Fontana.",
    "wof:placetype":"venue"
},
  "geometry": {"coordinates":[9.1971273422,46.7727355957],"type":"Point"}
}