{
  "type": "Feature",
  "properties": {
    "iso:country":"CH",
    "sg:address":"Sarganserstrasse 100 7324 Vilters. Postfach",
    "sg:city":"Vilters",
    "sg:orig_category":"Pensionskassen",
    "sg:postcode":"7324",
    "sg:province":"St. Gallen",
    "wof:name":"Patronale Vorsorgestiftung Elh",
    "wof:placetype":"venue"
},
  "geometry": {"coordinates":[9.4467802048,47.032875061],"type":"Point"}
}