{
  "type": "Feature",
  "properties": {
    "iso:country":"CH",
    "sg:address":"Badenerstrasse 85 8000 Z\u00fcrich. Postfach",
    "sg:city":"Z\u00fcrich",
    "sg:orig_category":"Unclassifiable Establishments",
    "sg:postcode":"8001",
    "sg:province":"Z\u00fcrich",
    "wof:name":"Quick Take Away Kowthaman",
    "wof:placetype":"venue"
},
  "geometry": {"coordinates":[8.5262107849,47.3738479614],"type":"Point"}
}