{
  "type": "Feature",
  "properties": {
    "iso:country":"CH",
    "sg:address":"Dorfstrasse 36",
    "sg:city":"Wittenbach",
    "sg:orig_category":"RESTAURANTS: TEA-ROOMS",
    "sg:postcode":"9303",
    "wof:name":"Restaurant Hirschen Yolanda Stadelmann",
    "wof:placetype":"venue"
},
  "geometry": {"coordinates":[9.3452129364,47.3749771118],"type":"Point"}
}