{
  "type": "Feature",
  "properties": {
    "iso:country":"CH",
    "sg:address":"Zaun 55",
    "sg:city":"Speicher",
    "sg:orig_category":"Hochschulen U h\u00f6here Ausbildung",
    "sg:postcode":"9042",
    "sg:province":"Appenzell Ausserrhoden",
    "wof:name":"Fachhochschule Oekoforum F\u00dcr Den Frieden",
    "wof:placetype":"venue"
},
  "geometry": {"coordinates":[9.4411916733,47.4129180908],"type":"Point"}
}