{
  "type": "Feature",
  "properties": {
    "iso:country":"CH",
    "sg:address":"Dorfplatz 9",
    "sg:city":"Beckenried",
    "sg:orig_category":"Elektrizit\u00e4tsversorgung",
    "sg:phone":"+41 79 350 67 70",
    "sg:postcode":"6375",
    "sg:province":"Nidwalden",
    "wof:name":"Vonlaufen Friedrich Elektro-solar Gmbh",
    "wof:placetype":"venue"
},
  "geometry": {"coordinates":[8.474319458,46.9668540955],"type":"Point"}
}