{
  "type": "Feature",
  "properties": {
    "iso:country":"CH",
    "sg:address":"An Der Keberlistr. 38",
    "sg:city":"Triboltingen",
    "sg:classifiers":[
        {
            "category":"Manufacturing",
            "subcategory":"Tools & Machinery",
            "type":"Manufacturing & Wholesale Goods"
        }
    ],
    "sg:phone":"+41 71 747 10 10",
    "sg:postcode":"8273",
    "sg:province":"Thurgau",
    "sg:tags":[
        "clamping"
    ],
    "wof:name":"Surber Werkzeugmaschinen Ag",
    "wof:placetype":"venue"
},
  "geometry": {"coordinates":[9.10796,47.661896],"type":"Point"}
}