{
  "type": "Feature",
  "properties": {
    "iso:country":"CH",
    "sg:address":"Hauptstrasse 19 5105 Auenstein. Postfach",
    "sg:city":"Auenstein",
    "sg:orig_category":"Herstellung von Elektromotoren, Generatoren U Transformatoren",
    "sg:phone":"+41 79 636 73 70",
    "sg:postcode":"5105",
    "sg:province":"Aargau",
    "wof:name":"Elektro H. Frei Ag",
    "wof:placetype":"venue"
},
  "geometry": {"coordinates":[8.1359357834,47.4165649414],"type":"Point"}
}