{
  "type": "Feature",
  "properties": {
    "iso:country":"CH",
    "sg:address":"Kleinfeldweg 50 4106 Therwil. Postfach",
    "sg:city":"Therwil",
    "sg:orig_category":"Grosshandel mit Fleisch U Fleischwaren Grosshandel mit sonstigen Maschinen U Ausr\u00fcstungen f\u00fcr Indust",
    "sg:phone":"+41 61 723 16 12",
    "sg:postcode":"4106",
    "sg:province":"Basel-Landschaft",
    "wof:name":"Alphons Mittler Industrievertretungen",
    "wof:placetype":"venue"
},
  "geometry": {"coordinates":[7.5645298958,47.500919342],"type":"Point"}
}