{
  "type": "Feature",
  "properties": {
    "addr:full":"Dorfbachweg 4 Steffisburg Bern 3612",
    "addr:housenumber":"4",
    "addr:postcode":"3612",
    "addr:street":"Dorfbachweg;Bern",
    "iso:country":"CH",
    "sg:address":"Dorfbachweg 4",
    "sg:city":"Steffisburg",
    "sg:orig_category":"Arztpraxen",
    "sg:phone":"+41 33 437 70 75",
    "sg:postcode":"3612",
    "sg:province":"Bern",
    "wof:name":"Dr.med.friedrich Huggler Spezialarzt Fmh",
    "wof:placetype":"venue"
},
  "geometry": {"coordinates":[7.635355,46.780102],"type":"Point"}
}