{
  "type": "Feature",
  "properties": {
    "iso:country":"CH",
    "sg:address":"Naasstrasse",
    "sg:city":"Morgarten",
    "sg:orig_category":"Wirtschaftspr\u00fcfung, Steuerberatung U Treuhand",
    "sg:phone":"+41 41 750 25 23",
    "sg:postcode":"6315",
    "sg:province":"Zug",
    "wof:name":"Herms A.",
    "wof:placetype":"venue"
},
  "geometry": {"coordinates":[8.6155376434,47.1342010498],"type":"Point"}
}