{
  "type": "Feature",
  "properties": {
    "iso:country":"CH",
    "sg:address":"Hintere Gasse 2",
    "sg:city":"Wolfwil",
    "sg:classifiers":[
        {
            "category":"Restaurant",
            "type":"Food & Drink"
        }
    ],
    "sg:phone":"+41 62 926 12 05",
    "sg:postcode":"4628",
    "sg:province":"Solothurn",
    "wof:name":"Restaurant Eintracht",
    "wof:placetype":"venue"
},
  "geometry": {"coordinates":[7.7889699936,47.2697525024],"type":"Point"}
}