{
  "type": "Feature",
  "properties": {
    "iso:country":"CH",
    "sg:address":"Bleichemattstrasse 7",
    "sg:city":"Aarau",
    "sg:orig_category":"Dienstleistungen von Beteiligungsgesellschaften Grosshandel mit B\u00fcromaschinen",
    "sg:phone":"+41 17407788",
    "sg:postcode":"5000",
    "sg:province":"Aargau",
    "wof:name":"Graphax Ag",
    "wof:placetype":"venue"
},
  "geometry": {"coordinates":[8.053155899,47.3905715942],"type":"Point"}
}