{
  "type": "Feature",
  "properties": {
    "iso:country":"CH",
    "sg:address":"Heidenburgweg 12b",
    "sg:city":"Lenzburg",
    "sg:orig_category":"Non-Classified Establishments",
    "sg:postcode":"5600",
    "sg:province":"Aargau",
    "wof:name":"Bio Consult Chervet",
    "wof:placetype":"venue"
},
  "geometry": {"coordinates":[8.1773548126,47.3812408447],"type":"Point"}
}