{
  "type": "Feature",
  "properties": {
    "iso:country":"CH",
    "sg:address":"Romanshornerstrasse 10a",
    "sg:city":"Amriswil",
    "sg:orig_category":"Gesundheitswesen Physiotherapie",
    "sg:phone":"+41 71 411 78 76",
    "sg:postcode":"8580",
    "sg:province":"Thurgau",
    "wof:name":"Physio Nijland Vincent",
    "wof:placetype":"venue"
},
  "geometry": {"coordinates":[9.3018932343,47.5462188721],"type":"Point"}
}