{
  "type": "Feature",
  "properties": {
    "addr:full":"Chemin Pr\u00e9-fleuri 1926 Fully. Postfach Fully Valais 1926",
    "addr:postcode":"1926 fully. postfach;1926",
    "addr:street":"Chemin Pre\u0301-Fleuri",
    "iso:country":"CH",
    "sg:address":"Chemin Pr\u00e9-fleuri 1926 Fully. Postfach",
    "sg:city":"Fully",
    "sg:orig_category":"Architektur U Ingenieurb\u00fcros",
    "sg:phone":"+41 27 746 46 10",
    "sg:postcode":"1926",
    "sg:province":"Valais",
    "wof:name":"B\u00fctzberger Engineering Brig Beratende Ingenieure Eth",
    "wof:placetype":"venue"
},
  "geometry": {"coordinates":[7.125165,46.139408],"type":"Point"}
}