{
  "type": "Feature",
  "properties": {
    "iso:country":"CH",
    "sg:address":"Hans-hugi-strasse 7",
    "sg:city":"Biel/bienne",
    "sg:orig_category":"Detailhandel mit Damenbekleidung",
    "sg:phone":"+41 32 322 45 69",
    "sg:postcode":"2502",
    "sg:province":"Bern",
    "wof:name":"Anita Wolf Boutique A Damenmode",
    "wof:placetype":"venue"
},
  "geometry": {"coordinates":[7.245398,47.133743],"type":"Point"}
}