{
  "type": "Feature",
  "properties": {
    "iso:country":"CH",
    "sg:address":"Neuensteinerstrasse 31",
    "sg:city":"Basel",
    "sg:orig_category":"Arztpraxen",
    "sg:phone":"+41 61 331 58 59",
    "sg:postcode":"4053",
    "sg:province":"Basel-Stadt",
    "wof:name":"Dr.med.robert Wenger Spezialarzt",
    "wof:placetype":"venue"
},
  "geometry": {"coordinates":[7.601747,47.540188],"type":"Point"}
}