{
  "type": "Feature",
  "properties": {
    "iso:country":"CH",
    "sg:address":"Grundbielstrasse 13 3902 Glis. Postfach",
    "sg:city":"Glis",
    "sg:orig_category":"Herstellung von sonstigen elektrischen Ausr\u00fcstungen",
    "sg:phone":"+41 27 924 16 80",
    "sg:postcode":"3902",
    "sg:province":"Valais",
    "wof:name":"Jcb Tableaux Electrique, Bejedi Jean-claude",
    "wof:placetype":"venue"
},
  "geometry": {"coordinates":[7.9751858711,46.3111610413],"type":"Point"}
}