{
  "type": "Feature",
  "properties": {
    "addr:full":"Bahnhofstrasse 94 Aarau Aargau 5000",
    "addr:housenumber":"94",
    "addr:postcode":"5000",
    "addr:street":"Bahnhofstrasse",
    "iso:country":"CH",
    "sg:address":"Bahnhofstrasse 94",
    "sg:city":"Aarau",
    "sg:orig_category":"Allgemeiner Hoch U Tiefbau",
    "sg:phone":"+41 17250680",
    "sg:postcode":"5000",
    "sg:province":"Aargau",
    "wof:name":"Daniel Steim Public Relations",
    "wof:placetype":"venue"
},
  "geometry": {"coordinates":[8.59776,47.258091],"type":"Point"}
}