{
  "type": "Feature",
  "properties": {
    "iso:country":"CH",
    "sg:address":"R\u00f6merweg 7",
    "sg:city":"K\u00fcnten",
    "sg:orig_category":"G\u00fcterbef\u00f6rderung im Strassenverkehr Handelsvermittlung U Grosshandel",
    "sg:postcode":"5444",
    "sg:province":"Aargau",
    "wof:name":"Transpex Sa",
    "wof:placetype":"venue"
},
  "geometry": {"coordinates":[6.0722098351,46.2284393311],"type":"Point"}
}