{
  "type": "Feature",
  "properties": {
    "iso:country":"CH",
    "sg:address":"Chemin De Sionnet 65",
    "sg:city":"Jussy",
    "sg:orig_category":"Softwareentwicklung U beratung Sonstige mit der Informatik verbundene T\u00e4tigkeiten",
    "sg:phone":"+41 22 342 47 45",
    "sg:postcode":"1254",
    "sg:province":"Gen\u00e8ve",
    "wof:name":"Baytree Services Sa",
    "wof:placetype":"venue"
},
  "geometry": {"coordinates":[6.2479839325,46.2343559265],"type":"Point"}
}