{
  "type": "Feature",
  "properties": {
    "iso:country":"CH",
    "sg:address":"Seefeldstrasse 159",
    "sg:city":"Z\u00fcrich",
    "sg:classifiers":[
        {
            "category":"Restaurant",
            "type":"Food & Drink"
        }
    ],
    "sg:phone":"+41 14224713",
    "sg:postcode":"8008",
    "sg:province":"Z\u00fcrich",
    "wof:name":"Restaurant Metzg",
    "wof:placetype":"venue"
},
  "geometry": {"coordinates":[8.5564174652,47.3558921814],"type":"Point"}
}