{
  "type": "Feature",
  "properties": {
    "iso:country":"CH",
    "sg:address":"Chemin Du Liaudoz 46",
    "sg:city":"Pully",
    "sg:orig_category":"Architektur U Ingenieurb\u00fcros",
    "sg:phone":"+41 21 728 83 03",
    "sg:postcode":"1009",
    "sg:province":"Vaud",
    "wof:name":"Ingam, Adrian-dor Munteanu",
    "wof:placetype":"venue"
},
  "geometry": {"coordinates":[6.657078,46.51445],"type":"Point"}
}