{
  "type": "Feature",
  "properties": {
    "iso:country":"CH",
    "sg:address":"Avenue Des Mousquines 14",
    "sg:city":"Lausanne",
    "sg:orig_category":"Sanit\u00e4rinstallation",
    "sg:phone":"+41 21 312 75 75",
    "sg:postcode":"1005",
    "sg:province":"Vaud",
    "wof:name":"G\u00e9rard Nicollerat Installations Sanitaires",
    "wof:placetype":"venue"
},
  "geometry": {"coordinates":[6.6452231407,46.517124176],"type":"Point"}
}