{
  "type": "Feature",
  "properties": {
    "iso:country":"CH",
    "sg:address":"Hintere Hauptgasse 9",
    "sg:city":"Zofingen",
    "sg:orig_category":"Handelskammern",
    "sg:phone":"+41 62 752 32 22",
    "sg:postcode":"4800",
    "sg:province":"Aargau",
    "wof:name":"Argentinische Handelskammer In Der Schweiz",
    "wof:placetype":"venue"
},
  "geometry": {"coordinates":[7.9458789825,47.2897796631],"type":"Point"}
}