{
  "type": "Feature",
  "properties": {
    "iso:country":"CH",
    "sg:address":"Oberdorfstrasse 49",
    "sg:city":"Herisau",
    "sg:orig_category":"Herstellung von Holzstoff, Papier, Karton U Pappe Herstellung von Wellpapier U pappe sowie von Verpa",
    "sg:phone":"+41 71 351 18 61",
    "sg:postcode":"9100",
    "sg:province":"Appenzell Ausserrhoden",
    "wof:name":"Josef B\u00f6gle, Cartonage, Buchbinderei",
    "wof:placetype":"venue"
},
  "geometry": {"coordinates":[9.2820529938,47.3854560852],"type":"Point"}
}