{
  "type": "Feature",
  "properties": {
    "iso:country":"CH",
    "sg:address":"Im Chalet",
    "sg:city":"Edlibach",
    "sg:orig_category":"Markt U Meinungsforschung",
    "sg:postcode":"6313",
    "sg:province":"Zug",
    "wof:name":"Ads Training Gmbh",
    "wof:placetype":"venue"
},
  "geometry": {"coordinates":[8.5699119568,47.1834335327],"type":"Point"}
}