{
  "type": "Feature",
  "properties": {
    "iso:country":"CH",
    "sg:address":"Rue De La Servette 32 1200 Genf. Postfach",
    "sg:city":"Tagelswangen",
    "sg:orig_category":"Detailhandel mit Fleisch U Fleischwaren",
    "sg:postcode":"8317",
    "sg:province":"Z\u00fcrich",
    "wof:name":"Test-firma 4711",
    "wof:placetype":"venue"
},
  "geometry": {"coordinates":[6.1359829903,46.2108840942],"type":"Point"}
}