{
  "type": "Feature",
  "properties": {
    "iso:country":"CH",
    "sg:address":"Vicaire-savoyard Rue Du 8 1203 Gen\u00e8ve. Postfach",
    "sg:city":"Gen\u00e8ve",
    "sg:orig_category":"Herstellung von \u00d6fen U Brennern",
    "sg:phone":"+41 22 340 21 24",
    "sg:postcode":"1203",
    "sg:province":"Gen\u00e8ve",
    "wof:name":"Entreprise Gothuey F.",
    "wof:placetype":"venue"
},
  "geometry": {"coordinates":[6.1224608421,46.2041244507],"type":"Point"}
}