{
  "type": "Feature",
  "properties": {
    "addr:full":"Im Seehof 50 Uster Z\u00fcrich 8610",
    "addr:housenumber":"50",
    "addr:postcode":"8610",
    "addr:street":"Im Seehof",
    "iso:country":"CH",
    "sg:address":"Im Seehof 50",
    "sg:city":"Uster",
    "sg:orig_category":"Herstellung sonstiger Textilien Herstellung von Lederwaren U Schuhen",
    "sg:phone":"+41 71 855 13 13",
    "sg:postcode":"8610",
    "sg:province":"Z\u00fcrich",
    "wof:name":"Dipl.ing.werner Graf Ag Treibriemenfabrik",
    "wof:placetype":"venue"
},
  "geometry": {"coordinates":[9.533698,47.479725],"type":"Point"}
}