{
  "type": "Feature",
  "properties": {
    "iso:country":"CH",
    "sg:address":"Gartenstrasse 3d 6331 H\u00fcnenberg. Postfach 24",
    "sg:city":"H\u00fcnenberg",
    "sg:orig_category":"Unternehmensberatung",
    "sg:phone":"+41 41 760 16 30",
    "sg:postcode":"6331",
    "sg:province":"Zug",
    "wof:name":"Peter Blitz Ag Unternehmensberatung",
    "wof:placetype":"venue"
},
  "geometry": {"coordinates":[8.4273967743,47.1789245605],"type":"Point"}
}