{
  "type": "Feature",
  "properties": {
    "iso:country":"CH",
    "sg:address":"Gerbergasse 3",
    "sg:city":"Basel",
    "sg:orig_category":"Detailhandel mit Brot, Back U S\u00fcsswaren",
    "sg:phone":"+41 61 261 69 47",
    "sg:postcode":"4001",
    "sg:province":"Basel-Stadt",
    "wof:name":"Richard Graf Confiserie",
    "wof:placetype":"venue"
},
  "geometry": {"coordinates":[7.588107,47.557598],"type":"Point"}
}