{
  "type": "Feature",
  "properties": {
    "iso:country":"CH",
    "sg:address":"Ring 4 6147 Altb\u00fcron. Postfach",
    "sg:city":"Altb\u00fcron",
    "sg:classifiers":[
        {
            "category":"Restaurant",
            "type":"Food & Drink"
        }
    ],
    "sg:phone":"+41 62 927 11 89",
    "sg:postcode":"6147",
    "sg:province":"Luzern",
    "wof:name":"Restaurant Linde",
    "wof:placetype":"venue"
},
  "geometry": {"coordinates":[7.8841781616,47.1825828552],"type":"Point"}
}