{
  "type": "Feature",
  "properties": {
    "iso:country":"CH",
    "sg:address":"Bammattenweg 21",
    "sg:city":"Naters",
    "sg:orig_category":"Sonstiger spezialisierter Hoch U Tiefbau",
    "sg:phone":"+41 79 435 29 26",
    "sg:postcode":"3904",
    "sg:province":"Valais",
    "wof:name":"Noti Urs, Maurergesch\u00e4ft",
    "wof:placetype":"venue"
},
  "geometry": {"coordinates":[7.9990549088,46.3279762268],"type":"Point"}
}