{
  "type": "Feature",
  "properties": {
    "iso:country":"CH",
    "sg:address":"Finsterseehalde",
    "sg:city":"H\u00fctten",
    "sg:orig_category":"Herstellung von Tanks U Sammelbeh\u00e4ltern aus Metall Kauf U Verkauf von Immobilien auf eigene Rechnung",
    "sg:phone":"+41 17881281",
    "sg:postcode":"8825",
    "sg:province":"Z\u00fcrich",
    "wof:name":"K\u00e4lin Hermann Ag",
    "wof:placetype":"venue"
},
  "geometry": {"coordinates":[8.6380157471,47.1736831665],"type":"Point"}
}