{
  "type": "Feature",
  "properties": {
    "iso:country":"CH",
    "sg:address":"St. Galler-strasse 170 8404 Oberwinterthur. Postfach",
    "sg:city":"Winterthur",
    "sg:orig_category":"Herstellung von Bereifungen",
    "sg:phone":"+41 52 233 23 27",
    "sg:postcode":"8404",
    "sg:province":"Z\u00fcrich",
    "wof:name":"Truck-tyre Handels Ag",
    "wof:placetype":"venue"
},
  "geometry": {"coordinates":[8.7536287308,47.498298645],"type":"Point"}
}