{
  "type": "Feature",
  "properties": {
    "iso:country":"CH",
    "sg:address":"Im Ried 6",
    "sg:city":"Eggersriet",
    "sg:orig_category":"Datenverarbeitungsdienste Sonstige mit der Informatik verbundene T\u00e4tigkeiten",
    "sg:phone":"+41 71 310 02 42",
    "sg:postcode":"9034",
    "sg:province":"St. Gallen",
    "wof:name":"Terracom Informatik Sch\u00e4rer Peter",
    "wof:placetype":"venue"
},
  "geometry": {"coordinates":[9.47229,47.442554],"type":"Point"}
}