{
  "type": "Feature",
  "properties": {
    "iso:country":"CH",
    "sg:address":"Althoossteig 17",
    "sg:city":"Z\u00fcrich",
    "sg:orig_category":"Kosmetikinstitute",
    "sg:phone":"+41 13721538",
    "sg:postcode":"8046",
    "sg:province":"Z\u00fcrich",
    "wof:name":"Jenny Cristina Kosmetikinstitut",
    "wof:placetype":"venue"
},
  "geometry": {"coordinates":[8.524271965,47.4105415344],"type":"Point"}
}