{
  "type": "Feature",
  "properties": {
    "iso:country":"CH",
    "sg:address":"Kantonstrasse",
    "sg:city":"Visp",
    "sg:orig_category":"Instandhaltung U Reparatur von Automobilen",
    "sg:phone":"+41 27 948 87 66",
    "sg:postcode":"3930",
    "sg:province":"Valais",
    "wof:name":"Garage St. Christophe Schnidrig Josef",
    "wof:placetype":"venue"
},
  "geometry": {"coordinates":[7.877933979,46.2925758362],"type":"Point"}
}