{
  "type": "Feature",
  "properties": {
    "iso:country":"CH",
    "sg:address":"Goldbrunnenstrasse 137",
    "sg:city":"Z\u00fcrich",
    "sg:orig_category":"Erbringung von sonstigen Dienstleistungen f\u00fcr Unterhaltung, Erholung U Freizeit",
    "sg:postcode":"8055",
    "sg:province":"Z\u00fcrich",
    "wof:name":"Rosa Kontakt F\u00fcr K\u00fcnstler, Cs\u00f6sz Rozsa K\u00fcnstlervermittlung",
    "wof:placetype":"venue"
},
  "geometry": {"coordinates":[8.511475563,47.371421814],"type":"Point"}
}