{
  "type": "Feature",
  "properties": {
    "iso:country":"CH",
    "sg:address":"Netzibodenstrasse 33 4133 Pratteln. Postfach",
    "sg:city":"Z\u00fcrich",
    "sg:orig_category":"Sonstige mit der Informatik verbundene T\u00e4tigkeiten",
    "sg:phone":"+41 41 918 00 83",
    "sg:postcode":"8001",
    "sg:province":"Z\u00fcrich",
    "wof:name":"Svema Gmbh",
    "wof:placetype":"venue"
},
  "geometry": {"coordinates":[7.5970702171,47.4735298157],"type":"Point"}
}