{
  "type": "Feature",
  "properties": {
    "iso:country":"CH",
    "sg:address":"Bruggli 3",
    "sg:city":"Netstal",
    "sg:orig_category":"Fachdetailhandel in Verkaufsr\u00e4umen",
    "sg:phone":"+41 55 640 71 41",
    "sg:postcode":"8754",
    "sg:province":"Glarus",
    "wof:name":"Regev Elisabeth, Bijouterie En Gros",
    "wof:placetype":"venue"
},
  "geometry": {"coordinates":[9.0575294495,47.060634613],"type":"Point"}
}