{
  "type": "Feature",
  "properties": {
    "iso:country":"CH",
    "sg:address":"Giacomettistrasse 75 7000 Chur. Postfach",
    "sg:city":"Chur",
    "sg:orig_category":"Herstellung von Teppichen",
    "sg:postcode":"7000",
    "sg:province":"Graubunden",
    "wof:name":"Aloise Gmbh",
    "wof:placetype":"venue"
},
  "geometry": {"coordinates":[9.5277118683,46.8635482788],"type":"Point"}
}