{
  "type": "Feature",
  "properties": {
    "iso:country":"CH",
    "sg:address":"Narzissenweg 39 2500 Biel/bienne. Postfach",
    "sg:city":"Biel/bienne",
    "sg:orig_category":"Maler U Glasergewerbe",
    "sg:postcode":"2504",
    "sg:province":"Bern",
    "wof:name":"Romanelli Vinzenzo",
    "wof:placetype":"venue"
},
  "geometry": {"coordinates":[7.2756791115,47.1443328857],"type":"Point"}
}