{
  "type": "Feature",
  "properties": {
    "iso:country":"CH",
    "sg:address":"St\u00fcrlerstrasse 2 3006 Bern. Postfach",
    "sg:city":"Bern",
    "sg:orig_category":"Sonstiger Grosshandel",
    "sg:phone":"+41 31 352 37 36",
    "sg:postcode":"3005",
    "sg:province":"Bern",
    "wof:name":"Pfirter H. Waren; Vertretung. Export, Import U. Handel.",
    "wof:placetype":"venue"
},
  "geometry": {"coordinates":[7.4742760658,46.9360618591],"type":"Point"}
}