{
  "type": "Feature",
  "properties": {
    "iso:country":"CH",
    "sg:address":"Im Trichtisal 29",
    "sg:city":"Z\u00fcrich",
    "sg:orig_category":"Markt U Meinungsforschung Personal U Stellenvermittlung",
    "sg:phone":"+41 14228777",
    "sg:postcode":"8053",
    "sg:province":"Z\u00fcrich",
    "wof:name":"Imvos Sch\u00e4rli Irene D.",
    "wof:placetype":"venue"
},
  "geometry": {"coordinates":[8.60313797,47.3546600342],"type":"Point"}
}