{
  "type": "Feature",
  "properties": {
    "iso:country":"CH",
    "sg:address":"Montmelley 240",
    "sg:city":"Echarlens",
    "sg:orig_category":"G\u00fcterbef\u00f6rderung im Strassenverkehr",
    "sg:phone":"+41 26 915 20 12",
    "sg:postcode":"1646",
    "sg:province":"Fribourg",
    "wof:name":"Daniel Ding Transports",
    "wof:placetype":"venue"
},
  "geometry": {"coordinates":[7.0748100281,46.6435928345],"type":"Point"}
}