{
  "type": "Feature",
  "properties": {
    "iso:country":"CH",
    "sg:address":"Baselstrasse 56",
    "sg:city":"Laufen",
    "sg:orig_category":"RESTAURANTS: TEA-ROOMS",
    "sg:postcode":"4242",
    "sg:province":"Basel-Landschaft",
    "wof:name":"Sylvia's Piano Bar, Locskai S.",
    "wof:placetype":"venue"
},
  "geometry": {"coordinates":[7.5049219131,47.4236373901],"type":"Point"}
}