{
  "type": "Feature",
  "properties": {
    "iso:country":"CH",
    "sg:address":"Allmendstrasse 41",
    "sg:city":"Baden",
    "sg:orig_category":"Fachdetailhandel mit pharmazeutischen Produkten",
    "sg:phone":"+41 56 222 72 22",
    "sg:postcode":"5400",
    "sg:province":"Aargau",
    "wof:name":"Rietsch-fischer Gisela",
    "wof:placetype":"venue"
},
  "geometry": {"coordinates":[8.2918357849,47.4733009338],"type":"Point"}
}