{
  "type": "Feature",
  "properties": {
    "iso:country":"CH",
    "sg:address":"Via Lische 2",
    "sg:city":"Stabio",
    "sg:orig_category":"Grosshandel mit Erzen U Metallen",
    "sg:phone":"+41 91 640 70 30",
    "sg:postcode":"6855",
    "sg:province":"Ticino",
    "wof:name":"Riganti Forging Sa, Lussemburgo, Succursale Di Lugano",
    "wof:placetype":"venue"
},
  "geometry": {"coordinates":[8.9373559952,45.8470497131],"type":"Point"}
}