{
  "type": "Feature",
  "properties": {
    "iso:country":"CH",
    "sg:address":"1610",
    "sg:city":"Oron-la-ville",
    "sg:classifiers":[
        {
            "category":"Education",
            "subcategory":"Vocational School",
            "type":"Public Place"
        }
    ],
    "sg:postcode":"1610",
    "sg:province":"Vaud",
    "sg:tags":[
        "koch-",
        "haushaltschulen"
    ],
    "wof:name":"Ecole M\u00e9nag\u00e8re R\u00e9gionale",
    "wof:placetype":"venue"
},
  "geometry": {"coordinates":[6.8568668365,46.4530258179],"type":"Point"}
}