{
  "type": "Feature",
  "properties": {
    "addr:full":"Route Moulin-roget 16 Avully Gen\u00e8ve 1237",
    "addr:housenumber":"16",
    "addr:postcode":"1237",
    "addr:street":"Route Moulin-Roget",
    "iso:country":"CH",
    "sg:address":"Route Moulin-roget 16",
    "sg:city":"Avully",
    "sg:classifiers":[
        {
            "category":"Banks & Credit Unions",
            "subcategory":"Bank",
            "type":"Services"
        }
    ],
    "sg:phone":"+41 22 756 17 51",
    "sg:postcode":"1237",
    "sg:province":"Gen\u00e8ve",
    "wof:name":"Banque Raiffeisen Avully",
    "wof:placetype":"venue"
},
  "geometry": {"coordinates":[5.998909,46.169022],"type":"Point"}
}