{
  "type": "Feature",
  "properties": {
    "iso:country":"CH",
    "sg:address":"Obereichliweg 31",
    "sg:city":"Immensee",
    "sg:orig_category":"Markt U Meinungsforschung",
    "sg:postcode":"6405",
    "sg:province":"Schwyz",
    "wof:name":"Marcomedia Gmbh",
    "wof:placetype":"venue"
},
  "geometry": {"coordinates":[8.4605522156,47.0910797119],"type":"Point"}
}