{
  "type": "Feature",
  "properties": {
    "iso:country":"CH",
    "sg:address":"Kesselstrasse 9/301",
    "sg:city":"Frauenfeld",
    "sg:orig_category":"P\u00e9dicure",
    "sg:phone":"+41 52 720 41 17",
    "sg:postcode":"8500",
    "sg:province":"Thurgau",
    "wof:name":"Elsy Hanhart P\u00e9dicure",
    "wof:placetype":"venue"
},
  "geometry": {"coordinates":[8.8934268951,47.5533447266],"type":"Point"}
}