{
  "type": "Feature",
  "properties": {
    "iso:country":"CH",
    "sg:address":"Route De Sion 21",
    "sg:city":"Sierre",
    "sg:orig_category":"Wirtschaftspr\u00fcfung, Steuerberatung U Treuhand",
    "sg:phone":"+41 32 757 18 48",
    "sg:postcode":"3960",
    "sg:province":"Valais",
    "wof:name":"Fiduciaire Berthoud Michel",
    "wof:placetype":"venue"
},
  "geometry": {"coordinates":[7.0142259598,47.0359573364],"type":"Point"}
}