{
  "type": "Feature",
  "properties": {
    "iso:country":"CH",
    "sg:address":"Hauptstrasse 68",
    "sg:city":"Salenstein",
    "sg:orig_category":"RESTAURANTS: TEA-ROOMS",
    "sg:postcode":"8268",
    "sg:province":"Thurgau",
    "wof:name":"Funtastic Entertainment Gmbh",
    "wof:placetype":"venue"
},
  "geometry": {"coordinates":[9.8381910324,46.4970664978],"type":"Point"}
}