{
  "type": "Feature",
  "properties": {
    "iso:country":"CH",
    "sg:address":"H\u00f6rnliweg 20",
    "sg:city":"Endingen",
    "sg:orig_category":"Bauschreinerei Herstellung von Konstruktionsteilen, Fertigbauteilen U Ausbauelementen aus Holz",
    "sg:phone":"+41 56 242 16 00",
    "sg:postcode":"5304",
    "sg:province":"Aargau",
    "wof:name":"Keller Konrad, Schreinerei Und Montagen Gmbh",
    "wof:placetype":"venue"
},
  "geometry": {"coordinates":[8.295174,47.539612],"type":"Point"}
}