{
  "type": "Feature",
  "properties": {
    "iso:country":"CH",
    "sg:address":"Langmauerstrasse 65 8006 Z\u00fcrich. Postfach",
    "sg:city":"Z\u00fcrich",
    "sg:orig_category":"Herstellung von Schl\u00f6ssern U Beschl\u00e4gen",
    "sg:phone":"+41 71 282 47 10",
    "sg:postcode":"8001",
    "sg:province":"Z\u00fcrich",
    "wof:name":"Fehr Wilhelm Ag",
    "wof:placetype":"venue"
},
  "geometry": {"coordinates":[9.4159097672,47.4439888],"type":"Point"}
}