{
  "type": "Feature",
  "properties": {
    "iso:country":"CH",
    "sg:address":"Allmendstrasse 28",
    "sg:city":"Port",
    "sg:classifiers":[
        {
            "category":"Manufacturing",
            "subcategory":"Motor Vehicles & Parts",
            "type":"Manufacturing & Wholesale Goods"
        }
    ],
    "sg:phone":"+41 32 331 20 64",
    "sg:postcode":"2562",
    "sg:province":"Bern",
    "sg:tags":[
        "electronic",
        "assembling",
        "component"
    ],
    "wof:name":"Milgray Distribution Gmbh",
    "wof:placetype":"venue"
},
  "geometry": {"coordinates":[7.249467,47.119267],"type":"Point"}
}