{
  "type": "Feature",
  "properties": {
    "iso:country":"CH",
    "sg:address":"Graben 10 5000 Aarau. Postfach",
    "sg:city":"Aarau",
    "sg:orig_category":"Wirtschafts- and Arbeitgeberverb\u00e4nde",
    "sg:phone":"+41 61 821 75 40",
    "sg:postcode":"5001",
    "sg:province":"Aargau",
    "wof:name":"Baumeisterverband Baselland & Umgebung",
    "wof:placetype":"venue"
},
  "geometry": {"coordinates":[7.6915860176,47.5205192566],"type":"Point"}
}