{
  "type": "Feature",
  "properties": {
    "iso:country":"CH",
    "sg:address":"Avenue Du L\u00e9man 36",
    "sg:city":"Lausanne",
    "sg:orig_category":"RESTAURANTS: TEA-ROOMS",
    "sg:phone":"+41 21 728 09 56",
    "sg:postcode":"1005",
    "sg:province":"Vaud",
    "wof:name":"Le Framboisier S\u00e0rl Caf\u00e9-restaurant",
    "wof:placetype":"venue"
},
  "geometry": {"coordinates":[6.6488280296,46.5155677795],"type":"Point"}
}