{
  "type": "Feature",
  "properties": {
    "iso:country":"CH",
    "sg:address":"Schwyzerstrasse 38",
    "sg:city":"Brunnen",
    "sg:orig_category":"Detailhandel mit Bekleidung Grosshandel mit H\u00e4uten, Fellen U Leder",
    "sg:phone":"+41 41 820 25 25",
    "sg:postcode":"6440",
    "sg:province":"Schwyz",
    "wof:name":"Ricky-furs, Rickenbach Rochus & Co, Brunnen",
    "wof:placetype":"venue"
},
  "geometry": {"coordinates":[8.613959,47.000652],"type":"Point"}
}