{
  "type": "Feature",
  "properties": {
    "iso:country":"CH",
    "sg:address":"Gerbestrasse 1",
    "sg:city":"W\u00e4denswil",
    "sg:orig_category":"Fachdetailhandel in Verkaufsr\u00e4umen",
    "sg:phone":"+41 17801424",
    "sg:postcode":"8820",
    "sg:province":"Z\u00fcrich",
    "wof:name":"Augenweide Gmbh",
    "wof:placetype":"venue"
},
  "geometry": {"coordinates":[8.6733407974,47.229183197],"type":"Point"}
}