{
  "type": "Feature",
  "properties": {
    "iso:country":"CH",
    "sg:address":"Dorfstrasse 34",
    "sg:city":"Fl\u00fcelen",
    "sg:orig_category":"RESTAURANTS: TEA-ROOMS",
    "sg:phone":"+41 32 661 11 11",
    "sg:postcode":"6454",
    "sg:province":"Uri",
    "wof:name":"Gasthof Biber",
    "wof:placetype":"venue"
},
  "geometry": {"coordinates":[7.4548568726,47.1454620361],"type":"Point"}
}