{
  "type": "Feature",
  "properties": {
    "iso:country":"CH",
    "sg:address":"Hauptstrasse 16",
    "sg:city":"T\u00e4gerwilen",
    "sg:orig_category":"Instandhaltung U Reparatur von Automobilen",
    "sg:phone":"+41 71 669 17 15",
    "sg:postcode":"8274",
    "sg:province":"Thurgau",
    "wof:name":"Libero Autocenter Gmbh",
    "wof:placetype":"venue"
},
  "geometry": {"coordinates":[9.1245851517,47.6588172913],"type":"Point"}
}