{
  "type": "Feature",
  "properties": {
    "iso:country":"CH",
    "sg:address":"Im Holzerhurd 56",
    "sg:city":"Z\u00fcrich",
    "sg:orig_category":"Pensionskassen",
    "sg:postcode":"8046",
    "sg:province":"Z\u00fcrich",
    "wof:name":"Personalf\u00fcrsorgestiftung Der Gartenbau-genossenschaft Z\u00fcrich",
    "wof:placetype":"venue"
},
  "geometry": {"coordinates":[8.4963035583,47.423625946],"type":"Point"}
}