{
  "type": "Feature",
  "properties": {
    "iso:country":"CH",
    "sg:address":"5224",
    "sg:city":"Linn",
    "sg:orig_category":"Vereine Frauen Vereine Gemeinn\u00fctzige",
    "sg:postcode":"5224",
    "sg:province":"Aargau",
    "wof:name":"Aarg.landfrauenvereinigung",
    "wof:placetype":"venue"
},
  "geometry": {"coordinates":[8.1260786057,47.4697113037],"type":"Point"}
}