{
  "type": "Feature",
  "properties": {
    "iso:country":"CH",
    "sg:address":"Rue Centrale 14 1350 Orbe Case Postale 80",
    "sg:city":"Orbe",
    "sg:orig_category":"Offsetdruck Verlagsgewerbe",
    "sg:phone":"+41 24 441 31 78",
    "sg:postcode":"1350",
    "sg:province":"Vaud",
    "wof:name":"Imprimerie F.a. Orbe Travaux D'impression, D'\u00e9dition Etc",
    "wof:placetype":"venue"
},
  "geometry": {"coordinates":[6.5321779251,46.7232704163],"type":"Point"}
}