{
  "type": "Feature",
  "properties": {
    "iso:country":"CH",
    "sg:address":"Neuend\u00f6rferstrasse 8",
    "sg:city":"H\u00e4rkingen",
    "sg:orig_category":"Unclassifiable Establishments",
    "sg:postcode":"4624",
    "sg:province":"Solothurn",
    "wof:name":"Atelier Ginkgo T. Kamm",
    "wof:placetype":"venue"
},
  "geometry": {"coordinates":[7.8132629395,47.3077430725],"type":"Point"}
}