{
  "type": "Feature",
  "properties": {
    "iso:country":"CH",
    "sg:address":"Dorfstrasse 6 8803 R\u00fcschlikon. Postfach",
    "sg:city":"R\u00fcschlikon",
    "sg:orig_category":"Sonstiger Grosshandel",
    "sg:postcode":"8803",
    "sg:province":"Z\u00fcrich",
    "wof:name":"Pelamag Ag R\u00fcschlikon",
    "wof:placetype":"venue"
},
  "geometry": {"coordinates":[8.5575265884,47.3096466064],"type":"Point"}
}