{
  "type": "Feature",
  "properties": {
    "iso:country":"CH",
    "sg:address":"Hangenmoosstrasse 17",
    "sg:city":"W\u00e4denswil",
    "sg:orig_category":"P\u00e9dicure",
    "sg:phone":"+41 17804818",
    "sg:postcode":"8820",
    "sg:province":"Z\u00fcrich",
    "wof:name":"Marija R\u00fcttimann P\u00e9dicure",
    "wof:placetype":"venue"
},
  "geometry": {"coordinates":[8.6547431946,47.2339019775],"type":"Point"}
}