{
  "type": "Feature",
  "properties": {
    "iso:country":"CH",
    "sg:address":"Tobel 9302 Kronb\u00fchl. Postfach",
    "sg:city":"Kronb\u00fchl",
    "sg:orig_category":"Kalb U Schweine-M\u00e4sterei U Zucht",
    "sg:postcode":"9302",
    "wof:name":"Willi Gebr\u00fcder Ag",
    "wof:placetype":"venue"
},
  "geometry": {"coordinates":[8.1827249527,47.0368156433],"type":"Point"}
}