{
  "type": "Feature",
  "properties": {
    "iso:country":"CH",
    "sg:address":"Schulhaus Kreuzliberg 5400 Baden. Postfach 721",
    "sg:city":"Baden",
    "sg:classifiers":[
        {
            "category":"Education",
            "subcategory":"Library",
            "type":"Public Place"
        }
    ],
    "sg:phone":"+41 55 220 55 99",
    "sg:postcode":"5401",
    "sg:province":"Aargau",
    "sg:tags":[
        "u",
        "bibliotheken",
        "archive"
    ],
    "wof:name":"Bibliothek Des Kaufm\u00e4nnischen Vereins",
    "wof:placetype":"venue"
},
  "geometry": {"coordinates":[8.819773,47.228897],"type":"Point"}
}