{
  "type": "Feature",
  "properties": {
    "iso:country":"CH",
    "sg:address":"Feldwiesenstrasse 50",
    "sg:city":"L\u00fcchingen",
    "sg:orig_category":"Verwaltung von Immobilien",
    "sg:phone":"+41 71 755 46 47",
    "sg:postcode":"9450",
    "sg:province":"St. Gallen",
    "wof:name":"Fischlin Immobilienverwaltung",
    "wof:placetype":"venue"
},
  "geometry": {"coordinates":[9.5548410416,47.3847312927],"type":"Point"}
}