{
  "type": "Feature",
  "properties": {
    "iso:country":"CH",
    "sg:address":"Tabl\u00e0 Nov",
    "sg:city":"Tschierv",
    "sg:orig_category":"Organisationen der Wohlfahrtspflege",
    "sg:phone":"+41 81 851 62 60",
    "sg:postcode":"7532",
    "sg:province":"Graubunden",
    "wof:name":"Pro Juventute Bezirkssekretariat M\u00fcnstertal",
    "wof:placetype":"venue"
},
  "geometry": {"coordinates":[10.3364992142,46.6264190674],"type":"Point"}
}