{
  "type": "Feature",
  "properties": {
    "addr:full":"Quedra 72 Filisur Graubunden 7477",
    "addr:housenumber":"72",
    "addr:postcode":"7477",
    "addr:street":"Quedra;Graubunden",
    "iso:country":"CH",
    "sg:address":"Quedra 72",
    "sg:city":"Filisur",
    "sg:classifiers":[
        {
            "category":"Farming",
            "subcategory":"Farm",
            "type":"Manufacturing & Wholesale Goods"
        }
    ],
    "sg:phone":"+41 81 404 21 21",
    "sg:postcode":"7477",
    "sg:province":"Graubunden",
    "sg:tags":[
        "horticulture",
        "agriculture",
        "livestock"
    ],
    "wof:name":"Schutz Samen + Pflanzen Ag",
    "wof:placetype":"venue"
},
  "geometry": {"coordinates":[9.687248,46.671734],"type":"Point"}
}