{
  "type": "Feature",
  "properties": {
    "iso:country":"CH",
    "sg:address":"1180 Rolle Case Postale 76",
    "sg:city":"Rolle",
    "sg:orig_category":"Grosshandel mit Getr\u00e4nken",
    "sg:phone":"+41 21 822 02 02",
    "sg:postcode":"1180",
    "sg:province":"Vaud",
    "wof:name":"Schenk Sa",
    "wof:placetype":"venue"
},
  "geometry": {"coordinates":[6.3380351067,46.4575614929],"type":"Point"}
}