{
  "type": "Feature",
  "properties": {
    "iso:country":"CH",
    "sg:address":"Leuengasse 2 8952 Schlieren. Postfach",
    "sg:city":"Schlieren",
    "sg:orig_category":"Unternehmensberatung",
    "sg:postcode":"8952",
    "sg:province":"Z\u00fcrich",
    "wof:name":"F & F Consulting Group Ag",
    "wof:placetype":"venue"
},
  "geometry": {"coordinates":[7.089220047,46.9501533508],"type":"Point"}
}