{
  "type": "Feature",
  "properties": {
    "addr:full":"Badenerstrasse 15 Fislisbach Aargau 5442",
    "addr:housenumber":"15",
    "addr:postcode":"5442",
    "addr:street":"Badenerstrasse",
    "iso:country":"CH",
    "sg:address":"Badenerstrasse 15",
    "sg:city":"Fislisbach",
    "sg:orig_category":"Aktivit\u00e4ten der Generalunternehmen im Baugewerbe Kauf U Verkauf von Immobilien auf eigene Rechnung",
    "sg:phone":"+41 56 470 31 10",
    "sg:postcode":"5442",
    "sg:province":"Aargau",
    "wof:name":"Top Heim Ag",
    "wof:placetype":"venue"
},
  "geometry": {"coordinates":[8.29155,47.436901],"type":"Point"}
}