{
  "type": "Feature",
  "properties": {
    "iso:country":"CH",
    "sg:address":"Ocostrasse 20",
    "sg:city":"Zurzach",
    "sg:orig_category":"Hardwareberatung",
    "sg:phone":"+41 56 250 69 00",
    "sg:postcode":"5330",
    "sg:province":"Aargau",
    "wof:name":"Netassist Gmbh",
    "wof:placetype":"venue"
},
  "geometry": {"coordinates":[8.2907733917,47.5918197632],"type":"Point"}
}