{
  "type": "Feature",
  "properties": {
    "iso:country":"CH",
    "sg:address":"Aux Cond\u00e9mines B",
    "sg:city":"Echallens",
    "sg:orig_category":"Reinigungsgewerbe",
    "sg:postcode":"1040",
    "sg:province":"Vaud",
    "wof:name":"Irisnet S\u00e0rl",
    "wof:placetype":"venue"
},
  "geometry": {"coordinates":[6.1426091194,46.186756134],"type":"Point"}
}