{
  "type": "Feature",
  "properties": {
    "iso:country":"CH",
    "sg:address":"Rue Industrie 11",
    "sg:city":"Riaz",
    "sg:classifiers":[
        {
            "category":"Manufacturing",
            "subcategory":"Tools & Machinery",
            "type":"Manufacturing & Wholesale Goods"
        }
    ],
    "sg:phone":"+41 26 919 65 85",
    "sg:postcode":"1632",
    "sg:province":"Fribourg",
    "sg:tags":[
        "machine"
    ],
    "wof:name":"Tyrolit Hydrostress Ag",
    "wof:placetype":"venue"
},
  "geometry": {"coordinates":[7.068374157,46.6437759399],"type":"Point"}
}