{
  "type": "Feature",
  "properties": {
    "iso:country":"CH",
    "sg:address":"Dornacherstrasse 86",
    "sg:city":"Basel",
    "sg:orig_category":"Sportvereine Schach",
    "sg:phone":"+41 61 361 84 04",
    "sg:postcode":"4053",
    "sg:province":"Basel-Stadt",
    "wof:name":"Basler Schachgesellschaft",
    "wof:placetype":"venue"
},
  "geometry": {"coordinates":[7.587553978,47.5438766479],"type":"Point"}
}