{
  "type": "Feature",
  "properties": {
    "iso:country":"CH",
    "sg:address":"Dorfackerstrasse 9",
    "sg:city":"Zuchwil",
    "sg:orig_category":"Grosshandel mit lebenden Tieren",
    "sg:phone":"+41 77312171",
    "sg:postcode":"4528",
    "sg:province":"Solothurn",
    "wof:name":"Georges Brunner Viehhandel",
    "wof:placetype":"venue"
},
  "geometry": {"coordinates":[7.5619778633,47.202960968],"type":"Point"}
}