{
  "type": "Feature",
  "properties": {
    "iso:country":"CH",
    "sg:address":"Burgstrasse 10",
    "sg:city":"W\u00e4denswil",
    "sg:orig_category":"Grosshandel mit B\u00fcromaschinen Sonstige mit der Informatik verbundene T\u00e4tigkeiten",
    "sg:phone":"+41 17250608",
    "sg:postcode":"8820",
    "sg:province":"Z\u00fcrich",
    "wof:name":"Suno Gmbh",
    "wof:placetype":"venue"
},
  "geometry": {"coordinates":[8.6764297485,47.218624115],"type":"Point"}
}