{
  "type": "Feature",
  "properties": {
    "iso:country":"CH",
    "sg:address":"Talstrasse 7",
    "sg:city":"Auenstein",
    "sg:orig_category":"RESTAURANTS: TEA-ROOMS",
    "sg:phone":"+41 56 634 12 06",
    "sg:postcode":"5105",
    "sg:province":"Aargau",
    "wof:name":"Restaurant Burestube Br\u00e4ndli Heinrich",
    "wof:placetype":"venue"
},
  "geometry": {"coordinates":[8.4385242462,47.3228569031],"type":"Point"}
}