{
  "type": "Feature",
  "properties": {
    "iso:country":"CH",
    "sg:address":"Riedtalstrasse 13",
    "sg:city":"Zofingen",
    "sg:orig_category":"Betrieb U technische Hilfsdienste des Kultur U Unterhaltungswesens Detailhandel mit Brillen U andere",
    "sg:phone":"+41 21 802 40 31",
    "sg:postcode":"4800",
    "sg:province":"Aargau",
    "wof:name":"Joachim Knoll Appareils D'acoustique",
    "wof:placetype":"venue"
},
  "geometry": {"coordinates":[6.496952,46.508617],"type":"Point"}
}