{
  "type": "Feature",
  "properties": {
    "iso:country":"CH",
    "sg:address":"Le Vieux-bourg 26",
    "sg:city":"Denges",
    "sg:orig_category":"Architekturb\u00fcros",
    "sg:phone":"+41 31 839 43 47",
    "sg:postcode":"1026",
    "sg:province":"Vaud",
    "wof:name":"Ans Architekten N\u00f6thiger/schlosser",
    "wof:placetype":"venue"
},
  "geometry": {"coordinates":[7.562383,46.929035],"type":"Point"}
}