{
  "type": "Feature",
  "properties": {
    "iso:country":"CH",
    "sg:address":"6655",
    "sg:city":"Verdasio",
    "sg:orig_category":"G\u00fcterbef\u00f6rderung im Strassenverkehr",
    "sg:phone":"+41 79 415 11 45",
    "sg:postcode":"6655",
    "sg:province":"Ticino",
    "wof:name":"Consorzio Trasporti Comino Ctc",
    "wof:placetype":"venue"
},
  "geometry": {"coordinates":[8.6380701065,46.165271759],"type":"Point"}
}