{
  "type": "Feature",
  "properties": {
    "iso:country":"CH",
    "sg:address":"Stucklistrasse 7 6072 Sachseln. Postfach",
    "sg:city":"Sachseln",
    "sg:orig_category":"Fachdetailhandel in Verkaufsr\u00e4umen Kunsthandel",
    "sg:phone":"+41 71 755 19 78",
    "sg:postcode":"6072",
    "sg:province":"Obwalden",
    "wof:name":"Signer Kunsthandel Und Einrahmungen Gmbh",
    "wof:placetype":"venue"
},
  "geometry": {"coordinates":[9.5393238068,47.3780899048],"type":"Point"}
}