{
  "type": "Feature",
  "properties": {
    "iso:country":"CH",
    "sg:address":"Zeughausgasse 10 6300 Zug. Postfach",
    "sg:city":"Zug",
    "sg:orig_category":"Sonstige mit der Informatik verbundene T\u00e4tigkeiten",
    "sg:postcode":"6300",
    "sg:province":"Zug",
    "wof:name":"Ebridge Ag Beratung, Dienstleistungen Im Ber. Edv",
    "wof:placetype":"venue"
},
  "geometry": {"coordinates":[8.5159597397,47.1671104431],"type":"Point"}
}