{
  "type": "Feature",
  "properties": {
    "iso:country":"CH",
    "sg:address":"Kohlschw\u00e4rzistrasse 9",
    "sg:city":"Gretzenbach",
    "sg:orig_category":"Fuhrhaltereien",
    "sg:phone":"+41 62 849 11 81",
    "sg:postcode":"5014",
    "sg:province":"Solothurn",
    "wof:name":"Max Schenker Fuhrhalterei",
    "wof:placetype":"venue"
},
  "geometry": {"coordinates":[7.9987721443,47.3526191711],"type":"Point"}
}