{
  "type": "Feature",
  "properties": {
    "iso:country":"CH",
    "sg:address":"Schupposen 10",
    "sg:city":"Oberburg",
    "sg:orig_category":"Maurerarbeiten Verlegen von Fussboden",
    "sg:phone":"+41 34 422 08 08",
    "sg:postcode":"3414",
    "sg:province":"Bern",
    "wof:name":"Andreas Gasser Allround-resu",
    "wof:placetype":"venue"
},
  "geometry": {"coordinates":[7.6260499954,47.0390052795],"type":"Point"}
}