{
  "type": "Feature",
  "properties": {
    "iso:country":"CH",
    "sg:address":"Br\u00fchlstrasse 43 4415 Lausen. Postfach",
    "sg:city":"Lausen",
    "sg:orig_category":"Schifffahrts\u00e4mter",
    "sg:phone":"+41 61 925 66 90",
    "sg:postcode":"4415",
    "sg:province":"Basel-Landschaft",
    "wof:name":"Verkehrsabt. Kleinschiffahrt Kantonspolizei Baselland",
    "wof:placetype":"venue"
},
  "geometry": {"coordinates":[7.7579741478,47.4733810425],"type":"Point"}
}