{
  "type": "Feature",
  "properties": {
    "iso:country":"CH",
    "sg:address":"Aarburgerstr. 29",
    "sg:city":"Zofingen",
    "sg:classifiers":[
        {
            "category":"Professional",
            "type":"Services"
        }
    ],
    "sg:phone":"+41 21 843 93 00",
    "sg:postcode":"4800",
    "sg:province":"Aargau",
    "sg:tags":[
        "transport",
        "road"
    ],
    "wof:name":"Gondrand Sa",
    "wof:placetype":"venue"
},
  "geometry": {"coordinates":[6.3790950775,46.7119598389],"type":"Point"}
}