{
  "type": "Feature",
  "properties": {
    "iso:country":"CH",
    "sg:address":"Reinacherstrasse 45",
    "sg:city":"M\u00fcnchenstein",
    "sg:orig_category":"Instandhaltung U Reparatur von Automobilen",
    "sg:phone":"+41 61 413 85 40",
    "sg:postcode":"4142",
    "sg:province":"Basel-Landschaft",
    "wof:name":"Shamal-garage G\u00f6tte Gerhard",
    "wof:placetype":"venue"
},
  "geometry": {"coordinates":[7.605700016,47.5296707153],"type":"Point"}
}