{
  "type": "Feature",
  "properties": {
    "iso:country":"CH",
    "sg:address":"Bahnstrasse 23 4932 Lotzwil. Postfach",
    "sg:city":"Lotzwil",
    "sg:orig_category":"Herstellung von Drahtwaren",
    "sg:phone":"+41 71 755 10 73",
    "sg:postcode":"4932",
    "sg:province":"Bern",
    "wof:name":"Drahterosion Tobler & Co",
    "wof:placetype":"venue"
},
  "geometry": {"coordinates":[9.5584745407,47.3671112061],"type":"Point"}
}