{
  "type": "Feature",
  "properties": {
    "iso:country":"CH",
    "sg:address":"Kornplatz 12",
    "sg:city":"Chur",
    "sg:orig_category":"Detailhandel mit Bekleidung",
    "sg:phone":"+41 32 931 81 80",
    "sg:postcode":"7000",
    "sg:province":"Graubunden",
    "wof:name":"Gasser-kaltbrunner Carmen",
    "wof:placetype":"venue"
},
  "geometry": {"coordinates":[6.747378,47.056812],"type":"Point"}
}