{
  "type": "Feature",
  "properties": {
    "iso:country":"CH",
    "sg:address":"Limmattalstrasse 167",
    "sg:city":"Z\u00fcrich",
    "sg:orig_category":"Arztpraxen Physiotherapie",
    "sg:phone":"+41 13413131",
    "sg:postcode":"8049",
    "sg:province":"Z\u00fcrich",
    "wof:name":"Dr.med.j\u00fcrg Ryser Spezialarzt Fmh & Physioth.",
    "wof:placetype":"venue"
},
  "geometry": {"coordinates":[8.500206,47.401642],"type":"Point"}
}