{
  "type": "Feature",
  "properties": {
    "iso:country":"CH",
    "sg:address":"Schachenstrasse 12",
    "sg:city":"Wettswil",
    "sg:orig_category":"Finanzierungsinstitutionen",
    "sg:postcode":"8907",
    "sg:province":"Z\u00fcrich",
    "wof:name":"Werner Maag",
    "wof:placetype":"venue"
},
  "geometry": {"coordinates":[8.473490715,47.3288230896],"type":"Point"}
}