{
  "type": "Feature",
  "properties": {
    "iso:country":"CH",
    "sg:address":"Hofstrasse 7",
    "sg:city":"Zug",
    "sg:orig_category":"Softwareentwicklung U beratung",
    "sg:postcode":"6300",
    "sg:province":"Zug",
    "wof:name":"Softbear Ag",
    "wof:placetype":"venue"
},
  "geometry": {"coordinates":[8.517455101,47.1616477966],"type":"Point"}
}