{
  "type": "Feature",
  "properties": {
    "iso:country":"CH",
    "sg:address":"Via Alla Verbanella 20",
    "sg:city":"Minusio",
    "sg:orig_category":"Detailhandel mit elektrischen Haushalts-,Radio U Fernsehger\u00e4ten sowie Musikinstrumenten Grosshandel ",
    "sg:phone":"+41 91 743 30 01",
    "sg:postcode":"6648",
    "sg:province":"Ticino",
    "wof:name":"Stardomus Sa Articoli Casalinghi",
    "wof:placetype":"venue"
},
  "geometry": {"coordinates":[8.8334665298,46.1813468933],"type":"Point"}
}