{
  "type": "Feature",
  "properties": {
    "iso:country":"CH",
    "sg:address":"Im Dorf 7",
    "sg:city":"N\u00e4fels",
    "sg:orig_category":"Architekturb\u00fcros",
    "sg:phone":"+41 71 999 13 06",
    "sg:postcode":"8752",
    "sg:province":"Glarus",
    "wof:name":"Willi Schweizer Architekturb\u00fcro",
    "wof:placetype":"venue"
},
  "geometry": {"coordinates":[9.28492,47.193584],"type":"Point"}
}