{
  "type": "Feature",
  "properties": {
    "iso:country":"CH",
    "sg:address":"Rathausstrasse 36",
    "sg:city":"Leukerbad",
    "sg:classifiers":[
        {
            "category":"Travel",
            "subcategory":"Hotels & Motels",
            "type":"Entertainment"
        }
    ],
    "sg:phone":"+41 27 472 70 70",
    "sg:postcode":"3954",
    "sg:province":"Valais",
    "sg:tags":[
        "hotels",
        "mit",
        "restaurant"
    ],
    "wof:name":"Hotel Alpenblick",
    "wof:placetype":"venue"
},
  "geometry": {"coordinates":[7.6261219978,46.3769226074],"type":"Point"}
}