{
  "type": "Feature",
  "properties": {
    "iso:country":"CH",
    "sg:address":"Rue Des Sources",
    "sg:city":"Gen\u00e8ve",
    "sg:orig_category":"Vorschulen, Kinderg\u00e4rten",
    "sg:phone":"+41 22 328 77 05",
    "sg:postcode":"1205",
    "sg:province":"Gen\u00e8ve",
    "wof:name":"Jardin D'enfants",
    "wof:placetype":"venue"
},
  "geometry": {"coordinates":[6.1437950134,46.1960449219],"type":"Point"}
}