{
  "type": "Feature",
  "properties": {
    "addr:full":"Affolternstrasse 2 Ottenbach Z\u00fcrich 8913",
    "addr:housenumber":"2",
    "addr:postcode":"8913",
    "addr:street":"Affolternstrasse",
    "iso:country":"CH",
    "sg:address":"Affolternstrasse 2",
    "sg:city":"Ottenbach",
    "sg:orig_category":"Detailhandel mit Blumen U Pflanzen Fachdetailhandel in Verkaufsr\u00e4umen",
    "sg:phone":"+41 17618261",
    "sg:postcode":"8913",
    "sg:province":"Z\u00fcrich",
    "wof:name":"Bluemeh\u00fcsli Artica",
    "wof:placetype":"venue"
},
  "geometry": {"coordinates":[8.403996,47.281078],"type":"Point"}
}