{
  "type": "Feature",
  "properties": {
    "iso:country":"CH",
    "sg:address":"Route De France 21",
    "sg:city":"Morgins",
    "sg:orig_category":"Detailhandel mit Geschenkartikeln U Souvenirs",
    "sg:phone":"+41 24 477 64 22",
    "sg:postcode":"1875",
    "sg:province":"Valais",
    "wof:name":"Boutique L'atelier",
    "wof:placetype":"venue"
},
  "geometry": {"coordinates":[6.8538918495,46.2364425659],"type":"Point"}
}