{
  "type": "Feature",
  "properties": {
    "iso:country":"CH",
    "sg:address":"Zentrum Kelchbach 3904 Naters. Postfach",
    "sg:city":"Naters",
    "sg:orig_category":"RESTAURANTS: TEA-ROOMS",
    "sg:postcode":"3904",
    "sg:province":"Valais",
    "wof:name":"Restaurant Feuerwehr Pub 118, Ritz Marcel",
    "wof:placetype":"venue"
},
  "geometry": {"coordinates":[7.9897751808,46.324420929],"type":"Point"}
}