{
  "type": "Feature",
  "properties": {
    "iso:country":"CH",
    "sg:address":"8200",
    "sg:city":"Schaffhausen",
    "sg:orig_category":"Wirtschafts- and Arbeitgeberverb\u00e4nde",
    "sg:postcode":"8200",
    "sg:province":"Schaffhausen",
    "wof:name":"Milchproduzentengenossenschaft",
    "wof:placetype":"venue"
},
  "geometry": {"coordinates":[8.6247396469,47.7166404724],"type":"Point"}
}