{
  "type": "Feature",
  "properties": {
    "iso:country":"CH",
    "sg:address":"Route De Gl\u00e2ne 107",
    "sg:city":"Villars-sur-gl\u00e2ne",
    "sg:orig_category":"Tierarztpraxis",
    "sg:phone":"+41 26 402 25 44",
    "sg:postcode":"1752",
    "sg:province":"Fribourg",
    "wof:name":"Drs M\u00e9d.v\u00e9t.h.& I. Gauderon M\u00e9decins V\u00e9t\u00e9rinaires",
    "wof:placetype":"venue"
},
  "geometry": {"coordinates":[7.1429300308,46.7916221619],"type":"Point"}
}