{
  "type": "Feature",
  "properties": {
    "iso:country":"CH",
    "sg:address":"Metallstrasse 9a 6300 Zug. Postfach",
    "sg:city":"Zug",
    "sg:orig_category":"Rechtsberatung",
    "sg:phone":"+41 41 726 09 00",
    "sg:postcode":"6300",
    "sg:province":"Zug",
    "wof:name":"Sic Sport Consulting Ag Rechte Usw.; Vermarktung",
    "wof:placetype":"venue"
},
  "geometry": {"coordinates":[8.5183458328,47.1736183167],"type":"Point"}
}