{
  "type": "Feature",
  "properties": {
    "iso:country":"CH",
    "sg:address":"Matzenriedstrasse 56e 3019 Bern. Postfach",
    "sg:city":"Bern",
    "sg:orig_category":"Herstellung von medizinischen U chirurgischen Ger\u00e4ten sowie orthop\u00e4dischen Vorrichtungen",
    "sg:postcode":"3019",
    "sg:province":"Bern",
    "wof:name":"Mastuma Gmbh Gebrauchte Medizin. Apparate, Fahrzeuge, Maschinen Usw; An- U Verkauf",
    "wof:placetype":"venue"
},
  "geometry": {"coordinates":[7.3453640938,46.9333381653],"type":"Point"}
}