{
  "type": "Feature",
  "properties": {
    "iso:country":"CH",
    "sg:address":"Elvezia Corso 14",
    "sg:city":"Lugano",
    "sg:orig_category":"Fachdetailhandel in Verkaufsr\u00e4umen",
    "sg:phone":"+41 91 923 30 51",
    "sg:postcode":"6900",
    "sg:province":"Ticino",
    "wof:name":"Seemar Sa",
    "wof:placetype":"venue"
},
  "geometry": {"coordinates":[8.9558019638,46.0073852539],"type":"Point"}
}