{
  "type": "Feature",
  "properties": {
    "iso:country":"CH",
    "sg:address":"Schulhausstrasse 5",
    "sg:city":"Subingen",
    "sg:orig_category":"Detailhandel Handel mit Motorr\u00e4dern, Teilen U Zubeh\u00f6r Instandhaltung U Reparatur von Motorr\u00e4dern Rep",
    "sg:phone":"+41 32 614 16 31",
    "sg:postcode":"4553",
    "sg:province":"Solothurn",
    "wof:name":"Urs Lehmann Big Bill's Classic Motors",
    "wof:placetype":"venue"
},
  "geometry": {"coordinates":[7.6183338165,47.1975364685],"type":"Point"}
}