{
  "type": "Feature",
  "properties": {
    "addr:full":"Chriesbaumstrasse 2 8604 Volketswil. Postfach Volketswil Z\u00fcrich 8604",
    "addr:housenumber":"2",
    "addr:postcode":"8604;8604",
    "addr:street":"Chriesbaumstrasse;Postfach",
    "iso:country":"CH",
    "sg:address":"Chriesbaumstrasse 2 8604 Volketswil. Postfach",
    "sg:city":"Volketswil",
    "sg:orig_category":"Datenverarbeitungsdienste Softwareentwicklung U beratung",
    "sg:phone":"+41 19085454",
    "sg:postcode":"8604",
    "sg:province":"Z\u00fcrich",
    "wof:name":"Visionbase Stutz",
    "wof:placetype":"venue"
},
  "geometry": {"coordinates":[8.679965,47.381683],"type":"Point"}
}