{
  "type": "Feature",
  "properties": {
    "iso:country":"CH",
    "sg:address":"Chalet Lwk",
    "sg:city":"Kandersteg",
    "sg:orig_category":"Sportvereine Ballsport Tennis",
    "sg:postcode":"3718",
    "sg:province":"Bern",
    "wof:name":"Tc Kandersteg",
    "wof:placetype":"venue"
},
  "geometry": {"coordinates":[7.6733179092,46.498134613],"type":"Point"}
}