{
  "type": "Feature",
  "properties": {
    "iso:country":"CH",
    "sg:address":"M\u00fchle 282",
    "sg:city":"Untervaz",
    "sg:orig_category":"Vereine Musik/Blasmusik",
    "sg:phone":"+41 81 322 18 23",
    "sg:postcode":"7204",
    "sg:province":"Graubunden",
    "wof:name":"Musikgesellschaft",
    "wof:placetype":"venue"
},
  "geometry": {"coordinates":[9.5414838791,46.9396057129],"type":"Point"}
}