{
  "type": "Feature",
  "properties": {
    "iso:country":"CH",
    "sg:address":"Cho D'punt",
    "sg:city":"Samedan",
    "sg:orig_category":"Einzelhandel mit Automobilteilen U Zubeh\u00f6r Instandhaltung U Reparatur von Automobilen",
    "sg:phone":"+41 81 413 37 90",
    "sg:postcode":"7503",
    "sg:province":"Graubunden",
    "wof:name":"Autoservice Sergio Bellicini",
    "wof:placetype":"venue"
},
  "geometry": {"coordinates":[9.831993103,46.7961845398],"type":"Point"}
}