{
  "type": "Feature",
  "properties": {
    "iso:country":"CH",
    "sg:address":"Ch\u00e4rschele 269",
    "sg:city":"Uebeschi",
    "sg:orig_category":"Herstellung von sonstigen keramischen Erzeugnissen",
    "sg:phone":"+41 33 345 58 76",
    "sg:postcode":"3635",
    "sg:province":"Bern",
    "wof:name":"K\u00e4ser",
    "wof:placetype":"venue"
},
  "geometry": {"coordinates":[7.5451669693,46.7499656677],"type":"Point"}
}