{
  "type": "Feature",
  "properties": {
    "iso:country":"CH",
    "sg:address":"Kerzerstrasse 28",
    "sg:city":"M\u00fcntschemier",
    "sg:orig_category":"Benzin, Heiz\u00f6l and Mineral\u00f6lprodukte Grosshandel Tankstellen",
    "sg:phone":"+41 32 313 31 20",
    "sg:postcode":"3225",
    "sg:province":"Bern",
    "wof:name":"Agip (suisse) Sa",
    "wof:placetype":"venue"
},
  "geometry": {"coordinates":[7.1503658295,46.995010376],"type":"Point"}
}