{
  "type": "Feature",
  "properties": {
    "iso:country":"CH",
    "sg:address":"General Wille-strasse 40 8706 Feldmeilen. Postfach 67",
    "sg:city":"Feldmeilen",
    "sg:orig_category":"Unternehmensberatung",
    "sg:phone":"+41 19230051",
    "sg:postcode":"8706",
    "sg:province":"Z\u00fcrich",
    "wof:name":"Bleiker Erich Unternehmensberatung",
    "wof:placetype":"venue"
},
  "geometry": {"coordinates":[8.6128044128,47.28125],"type":"Point"}
}