{
  "type": "Feature",
  "properties": {
    "iso:country":"CH",
    "sg:address":"Nusshaldenstrasse 4",
    "sg:city":"D\u00f6ttingen",
    "sg:orig_category":"Wirtschaftspr\u00fcfung, Steuerberatung U Treuhand",
    "sg:postcode":"5312",
    "sg:province":"Aargau",
    "wof:name":"Zimmermann Treuhand",
    "wof:placetype":"venue"
},
  "geometry": {"coordinates":[8.4558315277,47.3591194153],"type":"Point"}
}