{
  "type": "Feature",
  "properties": {
    "iso:country":"CH",
    "sg:address":"Baumgartenweg 505",
    "sg:city":"Zetzwil",
    "sg:orig_category":"Herstellung von Fahrr\u00e4dern",
    "sg:postcode":"5732",
    "sg:province":"Aargau",
    "wof:name":"2 Und 4 Rad Shop Roth",
    "wof:placetype":"venue"
},
  "geometry": {"coordinates":[8.1494197845,47.2874298096],"type":"Point"}
}