{
  "type": "Feature",
  "properties": {
    "addr:full":"Webergasse 13 8200 Schaffhausen. Postfach Schaffhausen Schaffhausen 8201",
    "addr:housenumber":"13",
    "addr:postcode":"8200 schaffhausen. postfach;8201",
    "addr:street":"Webergasse",
    "iso:country":"CH",
    "sg:address":"Webergasse 13 8200 Schaffhausen. Postfach",
    "sg:city":"Schaffhausen",
    "sg:orig_category":"Detailhandel mit B\u00fcchern Detailhandel mit B\u00fcchern, Zeitungen, Schreib U Papeteriewaren",
    "sg:phone":"+41 52 624 52 33",
    "sg:postcode":"8201",
    "sg:province":"Schaffhausen",
    "wof:name":"B\u00fccher-fass Georg Freivogel Buchhandlung",
    "wof:placetype":"venue"
},
  "geometry": {"coordinates":[8.636268,47.698174],"type":"Point"}
}