{
  "type": "Feature",
  "properties": {
    "iso:country":"CH",
    "sg:address":"Heilbronnerstrasse 25",
    "sg:city":"Solothurn",
    "sg:orig_category":"Markt U Meinungsforschung",
    "sg:phone":"+41 32 665 04 46",
    "sg:postcode":"4500",
    "sg:province":"Solothurn",
    "wof:name":"Meier Peter",
    "wof:placetype":"venue"
},
  "geometry": {"coordinates":[7.5272650719,47.207611084],"type":"Point"}
}