{
  "type": "Feature",
  "properties": {
    "iso:country":"CH",
    "sg:address":"Rue Centrale 8",
    "sg:city":"Bex",
    "sg:classifiers":[
        {
            "category":"Travel",
            "subcategory":"Hotels & Motels",
            "type":"Entertainment"
        }
    ],
    "sg:postcode":"1880",
    "sg:province":"Vaud",
    "sg:tags":[
        "hotels",
        "mit",
        "restaurant"
    ],
    "wof:name":"Montasana, Maschke Winfried Kurse, Seminare, Workshops In Den Bereichen Yoga, Gesundheit Usw",
    "wof:placetype":"venue"
},
  "geometry": {"coordinates":[10.423620224,46.6011390686],"type":"Point"}
}