{
  "type": "Feature",
  "properties": {
    "iso:country":"CH",
    "sg:address":"6710",
    "sg:city":"Biasca",
    "sg:orig_category":"Architektur U Ingenieurb\u00fcros",
    "sg:postcode":"6710",
    "sg:province":"Ticino",
    "wof:name":"Mauro Parini, Studio D'idrogeologia E Geotermia",
    "wof:placetype":"venue"
},
  "geometry": {"coordinates":[8.969845,46.357765],"type":"Point"}
}