{
  "type": "Feature",
  "properties": {
    "iso:country":"CH",
    "sg:address":"Baarerstrasse 79 6300 Zug. Postfach 2718",
    "sg:city":"Zug",
    "sg:orig_category":"Grosshandel mit Nahrungsmitteln, Getr\u00e4nken U Tabakwaren Grosshandel mit Textilien",
    "sg:phone":"+41 41 726 30 76",
    "sg:postcode":"6302",
    "sg:province":"Zug",
    "wof:name":"Wild & Co",
    "wof:placetype":"venue"
},
  "geometry": {"coordinates":[8.5177192688,47.1772003174],"type":"Point"}
}