{
  "type": "Feature",
  "properties": {
    "iso:country":"CH",
    "sg:address":"Solistrasse 15",
    "sg:city":"B\u00fclach",
    "sg:orig_category":"Autogaragen",
    "sg:phone":"+41 79 662 73 60",
    "sg:postcode":"8180",
    "sg:province":"Z\u00fcrich",
    "wof:name":"Hans-ulrich W\u00fcthrich Garage",
    "wof:placetype":"venue"
},
  "geometry": {"coordinates":[8.538294,47.525265],"type":"Point"}
}