{
  "type": "Feature",
  "properties": {
    "iso:country":"CH",
    "sg:address":"Industriezone Reuss 6038 Gisikon. Postfach",
    "sg:city":"Rotkreuz",
    "sg:orig_category":"Herstellung von Fenstern U T\u00fcren aus Holz",
    "sg:phone":"+41 41 450 55 15",
    "sg:postcode":"6343",
    "sg:province":"Zug",
    "wof:name":"Esatto Ag Alles Rund Ums Fenster",
    "wof:placetype":"venue"
},
  "geometry": {"coordinates":[8.4066448212,47.1331596375],"type":"Point"}
}