{
  "type": "Feature",
  "properties": {
    "iso:country":"CH",
    "sg:address":"Biberiststrasse 3 4552 Derendingen. Postfach",
    "sg:city":"Biberist",
    "sg:orig_category":"Sonstige pers\u00f6nliche Dienstleistungen",
    "sg:postcode":"4562",
    "sg:province":"Solothurn",
    "wof:name":"Reinmann Technische Dienstleistungen Gmbh",
    "wof:placetype":"venue"
},
  "geometry": {"coordinates":[7.5822401047,47.1862792969],"type":"Point"}
}