{
  "type": "Feature",
  "properties": {
    "iso:country":"CH",
    "sg:address":"Marktgasse 9",
    "sg:city":"Baar",
    "sg:orig_category":"Detailhandel mit Teppichen Verlegen von Fussboden",
    "sg:phone":"+41 41 761 18 28",
    "sg:postcode":"6340",
    "sg:province":"Zug",
    "wof:name":"Heinrich Innenausstattung",
    "wof:placetype":"venue"
},
  "geometry": {"coordinates":[8.5269708633,47.19581604],"type":"Point"}
}