{
  "type": "Feature",
  "properties": {
    "iso:country":"CH",
    "sg:address":"Rue De Moillebeau 56",
    "sg:city":"Gen\u00e8ve",
    "sg:orig_category":"Konsulate",
    "sg:phone":"+41 22 340 26 21",
    "sg:postcode":"1209",
    "sg:province":"Gen\u00e8ve",
    "wof:name":"Consulat G\u00e9n\u00e9ral Du Ghana",
    "wof:placetype":"venue"
},
  "geometry": {"coordinates":[6.1301689148,46.2225151062],"type":"Point"}
}