{
  "type": "Feature",
  "properties": {
    "addr:full":"Plattenstrasse Oberhittnau Z\u00fcrich 8335",
    "addr:postcode":"8335",
    "addr:street":"Plattenstrasse Oberhittnau Zuerich",
    "iso:country":"CH",
    "sg:address":"Plattenstrasse",
    "sg:city":"Oberhittnau",
    "sg:orig_category":"Allgemeiner Hochbau Strassenbau",
    "sg:phone":"+41 71 288 61 91",
    "sg:postcode":"8335",
    "sg:province":"Z\u00fcrich",
    "wof:name":"Bonaria & Co Ag",
    "wof:placetype":"venue"
},
  "geometry": {"coordinates":[9.402183,47.43729],"type":"Point"}
}