{
  "type": "Feature",
  "properties": {
    "iso:country":"CH",
    "sg:address":"Rue De Neuch\u00e2tel 28",
    "sg:city":"Yverdon-les-bains",
    "sg:orig_category":"Detailhandel mit Teppichen Herstellung von Teppichen",
    "sg:phone":"+41 24 425 21 80",
    "sg:postcode":"1400",
    "sg:province":"Vaud",
    "wof:name":"Porchet Fils Yverdon Sa",
    "wof:placetype":"venue"
},
  "geometry": {"coordinates":[6.6357111931,46.7820205688],"type":"Point"}
}