{
  "type": "Feature",
  "properties": {
    "iso:country":"CH",
    "sg:address":"Avenue De La Gare 52 1003 Lausanne Case Postale 353",
    "sg:city":"Lausanne",
    "sg:orig_category":"Arztpraxen",
    "sg:phone":"+41 21 341 11 60",
    "sg:postcode":"1001",
    "sg:province":"Vaud",
    "wof:name":"Prof. Dr M\u00e9d. Mathieu Cik\u00e8s M\u00e9decin Sp\u00e9cialiste Fmh",
    "wof:placetype":"venue"
},
  "geometry": {"coordinates":[6.630751,46.517345],"type":"Point"}
}