{
  "type": "Feature",
  "properties": {
    "iso:country":"CH",
    "sg:address":"Schulhausstrasse 40 8002 Z\u00fcrich. Postfach 580",
    "sg:city":"Z\u00fcrich",
    "sg:orig_category":"Finanzierungsinstitutionen",
    "sg:phone":"+41 12018373",
    "sg:postcode":"8027",
    "sg:province":"Z\u00fcrich",
    "wof:name":"Taramur Finanz Ag",
    "wof:placetype":"venue"
},
  "geometry": {"coordinates":[8.5275363922,47.3606338501],"type":"Point"}
}