{
  "type": "Feature",
  "properties": {
    "iso:country":"CH",
    "sg:address":"Route Des Pras-longs",
    "sg:city":"Saxon",
    "sg:orig_category":"G\u00fcterbef\u00f6rderung im Strassenverkehr",
    "sg:phone":"+41 27 744 35 14",
    "sg:postcode":"1907",
    "sg:province":"Valais",
    "wof:name":"Maurice Mayencourt Transports",
    "wof:placetype":"venue"
},
  "geometry": {"coordinates":[7.1652197838,46.1457939148],"type":"Point"}
}