{
  "type": "Feature",
  "properties": {
    "iso:country":"CH",
    "sg:address":"Gare Avenue De La 42",
    "sg:city":"Delsberg",
    "sg:orig_category":"Non-Classified Establishments",
    "sg:phone":"+41 32 484 90 91",
    "sg:postcode":"2800",
    "sg:province":"Jura",
    "wof:name":"Montres Edox Et Vista Sa",
    "wof:placetype":"venue"
},
  "geometry": {"coordinates":[7.131289959,47.2574310303],"type":"Point"}
}