{
  "type": "Feature",
  "properties": {
    "iso:country":"CH",
    "sg:address":"Vollandes Rue Des 1 1207 Gen\u00e8ve. Postfach",
    "sg:city":"Gen\u00e8ve",
    "sg:orig_category":"Finanzierungsinstitutionen",
    "sg:postcode":"1201",
    "sg:province":"Gen\u00e8ve",
    "wof:name":"Global Private Invest Group Ag Finanzgesch\u00e4fte. Finanzdienstleistungen, Bes. Im Bereich Der Vermittlung Von Geldanlagen Usw",
    "wof:placetype":"venue"
},
  "geometry": {"coordinates":[8.3148832321,46.9920654297],"type":"Point"}
}