{
  "type": "Feature",
  "properties": {
    "iso:country":"CH",
    "sg:address":"Reusseggstr. 9",
    "sg:city":"Emmenbr\u00fccke",
    "sg:classifiers":[
        {
            "category":"Manufacturing",
            "subcategory":"Printing",
            "type":"Manufacturing & Wholesale Goods"
        }
    ],
    "sg:phone":"+41 41 429 66 66",
    "sg:postcode":"6020",
    "sg:province":"Luzern",
    "sg:tags":[
        "publishing"
    ],
    "wof:name":"Sticher Printing Ag",
    "wof:placetype":"venue"
},
  "geometry": {"coordinates":[8.2827596664,47.0684165955],"type":"Point"}
}