{
  "type": "Feature",
  "properties": {
    "iso:country":"CH",
    "sg:address":"8507",
    "sg:city":"Salen-reutenen",
    "sg:classifiers":[
        {
            "category":"Restaurant",
            "type":"Food & Drink"
        }
    ],
    "sg:phone":"+41 52 761 15 30",
    "sg:postcode":"8507",
    "sg:province":"Thurgau",
    "wof:name":"Restaurant Haidenhaus",
    "wof:placetype":"venue"
},
  "geometry": {"coordinates":[9.0154495239,47.6503105164],"type":"Point"}
}