{
  "type": "Feature",
  "properties": {
    "addr:full":"Aletschstrasse 11 Naters Valais 3904",
    "addr:housenumber":"11",
    "addr:postcode":"3904",
    "addr:street":"Aletschstrasse",
    "iso:country":"CH",
    "sg:address":"Aletschstrasse 11",
    "sg:city":"Naters",
    "sg:orig_category":"Allgemeiner Hochbau Strassenbau",
    "sg:phone":"+41 27 923 81 24",
    "sg:postcode":"3904",
    "sg:province":"Valais",
    "wof:name":"Anton Pfammatter Hoch-& Tiefbau",
    "wof:placetype":"venue"
},
  "geometry": {"coordinates":[7.993878,46.326336],"type":"Point"}
}