{
  "type": "Feature",
  "properties": {
    "iso:country":"CH",
    "sg:address":"Toggenburgerstr. 145",
    "sg:city":"Wil",
    "sg:classifiers":[
        {
            "category":"Shopping",
            "subcategory":"Clothing, Apparel, & Fashions",
            "type":"Retail Goods"
        }
    ],
    "sg:phone":"+41 71 925 32 25",
    "sg:postcode":"9500",
    "sg:province":"St. Gallen",
    "sg:tags":[
        "textile",
        "clothing",
        "clothes"
    ],
    "wof:name":"Danieli Herrenmode-zentrum",
    "wof:placetype":"venue"
},
  "geometry": {"coordinates":[9.049513,47.454227],"type":"Point"}
}