{
  "type": "Feature",
  "properties": {
    "iso:country":"CH",
    "sg:address":"Sternengasse 173",
    "sg:city":"Egerkingen",
    "sg:orig_category":"Detailhandel mit elektrischen Haushalts-,Radio U Fernsehger\u00e4ten sowie Musikinstrumenten",
    "sg:phone":"+41 62 398 00 15",
    "sg:postcode":"4622",
    "sg:province":"Solothurn",
    "wof:name":"Von Rohr Mgs",
    "wof:placetype":"venue"
},
  "geometry": {"coordinates":[7.7939009666,47.3231735229],"type":"Point"}
}