{
  "type": "Feature",
  "properties": {
    "iso:country":"CH",
    "sg:address":"Rte De Chavalon",
    "sg:city":"Villeneuve",
    "sg:classifiers":[
        {
            "category":"Government",
            "subcategory":"Department Of Motor Vehicles",
            "type":"Public Place"
        }
    ],
    "sg:phone":"+41 21 967 21 01",
    "sg:postcode":"1844",
    "sg:province":"Vaud",
    "sg:tags":[
        "equipment",
        "industrial",
        "transport",
        "motor-cars"
    ],
    "wof:name":"Morier Sa",
    "wof:placetype":"venue"
},
  "geometry": {"coordinates":[6.9346351624,46.3913116455],"type":"Point"}
}