{
  "type": "Feature",
  "properties": {
    "iso:country":"CH",
    "sg:address":"Schaffhauserstrasse 340",
    "sg:city":"Z\u00fcrich",
    "sg:orig_category":"Parf\u00fcmerien U sonstiger Detailhandel mit kosmetischen Artikeln U K\u00f6rperpflegemitteln Sonstiger Fachd",
    "sg:phone":"+41 34 402 21 08",
    "sg:postcode":"8050",
    "sg:province":"Z\u00fcrich",
    "wof:name":"K. & M. Blaser",
    "wof:placetype":"venue"
},
  "geometry": {"coordinates":[7.757589817,46.9491271973],"type":"Point"}
}