{
  "type": "Feature",
  "properties": {
    "iso:country":"CH",
    "sg:address":"Rathausgasse 2",
    "sg:city":"Zofingen",
    "sg:orig_category":"Reiseb\u00fcros U Reiseveranstalter",
    "sg:phone":"+41 62 746 20 70",
    "sg:postcode":"4800",
    "sg:province":"Aargau",
    "wof:name":"Hauri Reisen Ag",
    "wof:placetype":"venue"
},
  "geometry": {"coordinates":[7.9461450577,47.2883605957],"type":"Point"}
}