{
  "type": "Feature",
  "properties": {
    "iso:country":"CH",
    "sg:address":"Waffengasse 20 2502 Biel/bienne. Postfach",
    "sg:city":"Dussnang",
    "sg:orig_category":"Herstellung von medizinischen U chirurgischen Ger\u00e4ten sowie orthop\u00e4dischen Vorrichtungen Telecomshop",
    "sg:phone":"+41 32 325 36 56",
    "sg:postcode":"8374",
    "sg:province":"Thurgau",
    "wof:name":"Mobilcenter Von Rotz Gmbh",
    "wof:placetype":"venue"
},
  "geometry": {"coordinates":[7.2450389862,47.1357345581],"type":"Point"}
}