{
  "type": "Feature",
  "properties": {
    "iso:country":"CH",
    "sg:address":"Gr\u00fctstrasse 8843 Oberiberg. Postfach",
    "sg:city":"Oberiberg",
    "sg:classifiers":[
        {
            "category":"Restaurant",
            "type":"Food & Drink"
        }
    ],
    "sg:phone":"+41 55 414 32 12",
    "sg:postcode":"8843",
    "sg:province":"Schwyz",
    "sg:tags":[
        "tea-rooms",
        "restaurants"
    ],
    "wof:name":"Lagler Beny, Restaurant Buoffenalp",
    "wof:placetype":"venue"
},
  "geometry": {"coordinates":[8.7717638016,47.0264434814],"type":"Point"}
}