{
  "type": "Feature",
  "properties": {
    "iso:country":"CH",
    "sg:address":"Burgfelderstrasse 3 4000 Basel. Postfach",
    "sg:city":"Basel",
    "sg:orig_category":"Fachdetailhandel in Verkaufsr\u00e4umen",
    "sg:postcode":"4051",
    "sg:province":"Basel-Stadt",
    "wof:name":"Zoo-tropic Prietzel Esther + Marcel",
    "wof:placetype":"venue"
},
  "geometry": {"coordinates":[7.573307991,47.5619812012],"type":"Point"}
}