{
  "type": "Feature",
  "properties": {
    "iso:country":"CH",
    "sg:address":"Baslerstrasse 44",
    "sg:city":"Z\u00fcrich",
    "sg:orig_category":"Fotografische Ateliers",
    "sg:phone":"+41 13814148",
    "sg:postcode":"8048",
    "sg:province":"Z\u00fcrich",
    "wof:name":"Rainer Tuggener Fotoatelier",
    "wof:placetype":"venue"
},
  "geometry": {"coordinates":[8.5001792908,47.3855056763],"type":"Point"}
}