{
  "type": "Feature",
  "properties": {
    "iso:country":"CH",
    "sg:address":"Tellstrasse 11",
    "sg:city":"Bellach",
    "sg:orig_category":"Handel mit Motorr\u00e4dern, Teilen U Zubeh\u00f6r Instandhaltung U Reparatur von Motorr\u00e4dern",
    "sg:phone":"+41 32 618 10 30",
    "sg:postcode":"4512",
    "sg:province":"Solothurn",
    "wof:name":"Fun-roller-shop Gmbh",
    "wof:placetype":"venue"
},
  "geometry": {"coordinates":[7.5035557747,47.2122573853],"type":"Point"}
}