{
  "type": "Feature",
  "properties": {
    "iso:country":"CH",
    "sg:address":"Industriestrasse 31",
    "sg:city":"Zug",
    "sg:orig_category":"Fachdetailhandel in Verkaufsr\u00e4umen Grosshandel mit Blumen U Pflanzen",
    "sg:phone":"+41 41 710 12 87",
    "sg:postcode":"6300",
    "sg:province":"Zug",
    "wof:name":"Lommerse & Schrama Ag",
    "wof:placetype":"venue"
},
  "geometry": {"coordinates":[8.5194377899,47.1763191223],"type":"Point"}
}