{
  "type": "Feature",
  "properties": {
    "iso:country":"CH",
    "sg:address":"Breitenstrasse 1 5303 W\u00fcrenlingen. Postfach 15",
    "sg:city":"W\u00fcrenlingen",
    "sg:orig_category":"Werbevermittlung Werbung",
    "sg:phone":"+41 22 341 22 88",
    "sg:postcode":"5303",
    "sg:province":"Aargau",
    "wof:name":"Bercher Sa Publicit\u00e9 G\u00e9n\u00e9rale",
    "wof:placetype":"venue"
},
  "geometry": {"coordinates":[6.1536221504,46.195148468],"type":"Point"}
}