{
  "type": "Feature",
  "properties": {
    "iso:country":"CH",
    "sg:address":"1030 Bussigny-lausanne Case Postale 62",
    "sg:city":"Bussigny-lausanne",
    "sg:orig_category":"Sportvereine Ballsport Basketball",
    "sg:phone":"+41 21 701 14 41",
    "sg:postcode":"1030",
    "sg:province":"Vaud",
    "wof:name":"Bussigny Basket Club",
    "wof:placetype":"venue"
},
  "geometry": {"coordinates":[6.5517702103,46.5500411987],"type":"Point"}
}