{
  "type": "Feature",
  "properties": {
    "iso:country":"CH",
    "sg:address":"9428",
    "sg:city":"Walzenhausen",
    "sg:orig_category":"Sportvereine Turnen Vereine Damen",
    "sg:phone":"+41 71 888 13 66",
    "sg:postcode":"9428",
    "sg:province":"Appenzell Ausserrhoden",
    "wof:name":"Frauenturnverein",
    "wof:placetype":"venue"
},
  "geometry": {"coordinates":[9.6042127609,47.4506225586],"type":"Point"}
}