{
  "type": "Feature",
  "properties": {
    "iso:country":"CH",
    "sg:address":"Christoph-schnyder-strasse 46 6210 Sursee. Postfach 3182",
    "sg:city":"Sursee",
    "sg:orig_category":"D\u00e4mmung gegen K\u00e4lte, W\u00e4rme, Schall U Ersch\u00fctterung Stukkateurgewerbe, Gipserei U Verputzerei",
    "sg:phone":"+41 41 921 69 33",
    "sg:postcode":"6210",
    "sg:province":"Luzern",
    "wof:name":"Meier Anton Ag",
    "wof:placetype":"venue"
},
  "geometry": {"coordinates":[8.1054525375,47.1658782959],"type":"Point"}
}