{
  "type": "Feature",
  "properties": {
    "iso:country":"CH",
    "sg:address":"Bovy-lysberg Rue 5 1204 Gen\u00e8ve. Postfach",
    "sg:city":"Gen\u00e8ve",
    "sg:orig_category":"Sonstiger Grosshandel",
    "sg:postcode":"1201",
    "sg:province":"Gen\u00e8ve",
    "wof:name":"Kampur Ag",
    "wof:placetype":"venue"
},
  "geometry": {"coordinates":[8.3142662048,46.9925308228],"type":"Point"}
}