{
  "type": "Feature",
  "properties": {
    "iso:country":"CH",
    "sg:address":"Casa Luise",
    "sg:city":"Quartino",
    "sg:orig_category":"Sonstige Verkehrsvermittlung",
    "sg:postcode":"6572",
    "sg:province":"Ticino",
    "wof:name":"Btl Services S\u00e0rl",
    "wof:placetype":"venue"
},
  "geometry": {"coordinates":[6.126830101,46.2368164062],"type":"Point"}
}