{
  "type": "Feature",
  "properties": {
    "iso:country":"CH",
    "sg:address":"Zamboy",
    "sg:city":"Venth\u00f4ne",
    "sg:orig_category":"Werbung",
    "sg:phone":"+41 27 455 41 47",
    "sg:postcode":"3973",
    "sg:province":"Valais",
    "wof:name":"Gerlach Peter M.",
    "wof:placetype":"venue"
},
  "geometry": {"coordinates":[7.523619175,46.3062667847],"type":"Point"}
}