{
  "type": "Feature",
  "properties": {
    "iso:country":"CH",
    "sg:address":"R\u00e9sidence Le Daguay Appartement 1a",
    "sg:city":"Rougemont",
    "sg:orig_category":"Reiseb\u00fcros U Reiseveranstalter",
    "sg:phone":"+41 26 925 84 18",
    "sg:postcode":"1838",
    "wof:name":"Le Daguay Ag",
    "wof:placetype":"venue"
},
  "geometry": {"coordinates":[-78.9260559082,36.2178535461],"type":"Point"}
}