{
  "type": "Feature",
  "properties": {
    "iso:country":"CH",
    "sg:address":"Burgweg 2",
    "sg:city":"Safnern",
    "sg:orig_category":"Grosshandel mit sonstigen Maschinen U Ausr\u00fcstungen f\u00fcr Industrie, Handel U Schiffahrt",
    "sg:phone":"+41 32 355 32 22",
    "sg:postcode":"2553",
    "sg:province":"Bern",
    "wof:name":"M & B Engineering Ag Industriebedarf",
    "wof:placetype":"venue"
},
  "geometry": {"coordinates":[7.3167099953,47.1587181091],"type":"Point"}
}