{
  "type": "Feature",
  "properties": {
    "addr:full":"Voremberg 11 Schwarzenburg Bern 3150",
    "addr:housenumber":"11",
    "addr:postcode":"3150",
    "addr:street":"Voremberg;Bern",
    "iso:country":"CH",
    "sg:address":"Voremberg 11",
    "sg:city":"Schwarzenburg",
    "sg:orig_category":"Architekturb\u00fcros",
    "sg:phone":"+41 31 731 15 53",
    "sg:postcode":"3150",
    "sg:province":"Bern",
    "wof:name":"Werner Kreuter Architekturb\u00fcro",
    "wof:placetype":"venue"
},
  "geometry": {"coordinates":[7.337574,46.819443],"type":"Point"}
}