{
  "type": "Feature",
  "properties": {
    "iso:country":"CH",
    "sg:address":"8280 Kreuzlingen 1. Postfach",
    "sg:city":"Neuwilen",
    "sg:orig_category":"Sonstiger Grosshandel",
    "sg:postcode":"8566",
    "sg:province":"Thurgau",
    "wof:name":"L\u00f6wen Schwaderloh Ag",
    "wof:placetype":"venue"
},
  "geometry": {"coordinates":[9.173210144,47.641368866],"type":"Point"}
}