{
  "type": "Feature",
  "properties": {
    "iso:country":"CH",
    "sg:address":"Schulhausstrasse 9",
    "sg:city":"Langendorf",
    "sg:orig_category":"RESTAURANTS: TEA-ROOMS",
    "sg:phone":"+41 32 622 20 52",
    "sg:postcode":"4513",
    "sg:province":"Solothurn",
    "wof:name":"Paradiso Vincenzo",
    "wof:placetype":"venue"
},
  "geometry": {"coordinates":[7.5136561394,47.2208442688],"type":"Point"}
}