{
  "type": "Feature",
  "properties": {
    "iso:country":"CH",
    "sg:address":"Landstrasse 124 5430 Wettingen. Postfach 57",
    "sg:city":"Wettingen",
    "sg:orig_category":"Herstellung von Radio U Fernsehger\u00e4ten sowie phono U videotechnischen Ger\u00e4ten",
    "sg:phone":"+41 56 290 10 10",
    "sg:postcode":"5430",
    "sg:province":"Aargau",
    "wof:name":"Radio-tv-service Rohner Ag",
    "wof:placetype":"venue"
},
  "geometry": {"coordinates":[8.2924947739,47.4877624512],"type":"Point"}
}