{
  "type": "Feature",
  "properties": {
    "iso:country":"CH",
    "sg:address":"St\u00e4dtli 21",
    "sg:city":"Werdenberg",
    "sg:orig_category":"Softwareentwicklung U beratung",
    "sg:phone":"+41 81 771 46 66",
    "sg:postcode":"9470",
    "sg:province":"St. Gallen",
    "wof:name":"Gufo J.holstein Softwareberatung & Vertrieb",
    "wof:placetype":"venue"
},
  "geometry": {"coordinates":[9.4625921249,47.1680641174],"type":"Point"}
}