{
  "type": "Feature",
  "properties": {
    "iso:country":"CH",
    "sg:address":"Via Rossago 13 6932 Breganzona. Postfach Caselle Postale 345",
    "sg:city":"Breganzona",
    "sg:orig_category":"Handelsvermittlung U Grosshandel mit Automobilteilen U Zubeh\u00f6r Herstellung von sonstigen Maschinen f",
    "sg:phone":"+41 91 967 48 48",
    "sg:postcode":"6932",
    "sg:province":"Ticino",
    "wof:name":"Spamat Sa",
    "wof:placetype":"venue"
},
  "geometry": {"coordinates":[8.9257364273,46.0066871643],"type":"Point"}
}