{
  "type": "Feature",
  "properties": {
    "iso:country":"CH",
    "sg:address":"Schulhausstrasse 6",
    "sg:city":"Wolfisberg",
    "sg:orig_category":"Gemeindeverwaltungen",
    "sg:phone":"+41 32 631 70 20",
    "sg:postcode":"4704",
    "sg:province":"Bern",
    "wof:name":"Gemeindeverwaltung Wolfisberg",
    "wof:placetype":"venue"
},
  "geometry": {"coordinates":[7.6612110138,47.2713928223],"type":"Point"}
}