{
  "type": "Feature",
  "properties": {
    "iso:country":"CH",
    "sg:address":"6775",
    "sg:city":"Ambr\u00ec",
    "sg:orig_category":"Autogaragen",
    "sg:phone":"+41 79 221 69 22",
    "sg:postcode":"6775",
    "sg:province":"Ticino",
    "wof:name":"Guscetti Car Sa",
    "wof:placetype":"venue"
},
  "geometry": {"coordinates":[8.693877,46.509754],"type":"Point"}
}