{
  "type": "Feature",
  "properties": {
    "iso:country":"CH",
    "sg:address":"Route D'yverdon 8",
    "sg:city":"Pr\u00e9verenges",
    "sg:orig_category":"Architektur U Ingenieurb\u00fcros Architekturb\u00fcros",
    "sg:phone":"+41 31 352 86 86",
    "sg:postcode":"1028",
    "sg:province":"Vaud",
    "wof:name":"Gygax Architekten Ag",
    "wof:placetype":"venue"
},
  "geometry": {"coordinates":[7.456352,46.955315],"type":"Point"}
}