{
  "type": "Feature",
  "properties": {
    "iso:country":"CH",
    "sg:address":"Br\u00fcggliweg 20",
    "sg:city":"G\u00fcmligen",
    "sg:orig_category":"Reiseb\u00fcros",
    "sg:phone":"+41 31 932 27 21",
    "sg:postcode":"3073",
    "sg:province":"Bern",
    "wof:name":"Travel To Ag Reiseveranstalter",
    "wof:placetype":"venue"
},
  "geometry": {"coordinates":[7.5057749748,46.933429718],"type":"Point"}
}