{
  "type": "Feature",
  "properties": {
    "iso:country":"CH",
    "sg:address":"Rebgasse 2",
    "sg:city":"Liestal",
    "sg:orig_category":"Non-Classified Establishments",
    "sg:phone":"+41 61 926 95 90",
    "sg:postcode":"4410",
    "sg:province":"Basel-Landschaft",
    "wof:name":"J\u00dcrg Gysin & Partner Ag F\u00fcr Organisationsentwicklung Und New Public Management",
    "wof:placetype":"venue"
},
  "geometry": {"coordinates":[7.7337670326,47.4856452942],"type":"Point"}
}