{
  "type": "Feature",
  "properties": {
    "iso:country":"CH",
    "sg:address":"Avenue Viollier 1",
    "sg:city":"Nyon",
    "sg:classifiers":[
        {
            "category":"Travel",
            "subcategory":"Hotels & Motels",
            "type":"Entertainment"
        }
    ],
    "sg:phone":"+41 22 361 49 31",
    "sg:postcode":"1260",
    "sg:province":"Vaud",
    "sg:tags":[
        "hotels",
        "mit",
        "restaurant"
    ],
    "wof:name":"H\u00f4tel Des Alpes Et Restaurant Le Perdtemps Sa Nyon",
    "wof:placetype":"venue"
},
  "geometry": {"coordinates":[6.2379398346,46.3840179443],"type":"Point"}
}