{
  "type": "Feature",
  "properties": {
    "iso:country":"CH",
    "sg:address":"M\u00fchlerainstrasse 19",
    "sg:city":"F\u00fcllinsdorf",
    "sg:orig_category":"Sonstiger Fachdetailhandel in Verkaufsr\u00e4umen",
    "sg:phone":"+41 61 902 06 16",
    "sg:postcode":"4414",
    "sg:province":"Basel-Landschaft",
    "wof:name":"Steinschmuck & Mineralien Susanne Caratti",
    "wof:placetype":"venue"
},
  "geometry": {"coordinates":[7.7260351181,47.5022239685],"type":"Point"}
}