{
  "type": "Feature",
  "properties": {
    "addr:full":"Langenthalstrasse 68 Aarwangen Bern 4912",
    "addr:housenumber":"68",
    "addr:postcode":"4912",
    "addr:street":"Langenthalstrasse",
    "iso:country":"CH",
    "sg:address":"Langenthalstrasse 68",
    "sg:city":"Aarwangen",
    "sg:classifiers":[
        {
            "category":"Banks & Credit Unions",
            "subcategory":"Investment Brokerage",
            "type":"Services"
        }
    ],
    "sg:phone":"+41 17634330",
    "sg:postcode":"4912",
    "sg:province":"Bern",
    "sg:tags":[
        "cnc",
        "milling"
    ],
    "wof:name":"Srm Pr\u00e4zisionsmechanik Ag",
    "wof:placetype":"venue"
},
  "geometry": {"coordinates":[8.444438,47.270702],"type":"Point"}
}