{
  "type": "Feature",
  "properties": {
    "iso:country":"CH",
    "sg:address":"T\u00f6pferweg 12",
    "sg:city":"Sarnen",
    "sg:orig_category":"Herstellung von sonstigen Produkten aus nichtmetallischen Mineralien Herstellung von sonstigen keram",
    "sg:phone":"+41 79 660 28 04",
    "sg:postcode":"6060",
    "sg:province":"Obwalden",
    "wof:name":"Dillier Ernst, Kachel- + Baukeramik Ag",
    "wof:placetype":"venue"
},
  "geometry": {"coordinates":[8.2458696365,46.8977012634],"type":"Point"}
}