{
  "type": "Feature",
  "properties": {
    "iso:country":"CH",
    "sg:address":"Le Brocard",
    "sg:city":"Martigny-croix",
    "sg:orig_category":"G\u00fcterbef\u00f6rderung im Strassenverkehr",
    "sg:phone":"+41 17408542",
    "sg:postcode":"1921",
    "sg:province":"Valais",
    "wof:name":"Saxer Oscar",
    "wof:placetype":"venue"
},
  "geometry": {"coordinates":[8.3985261917,47.4041938782],"type":"Point"}
}