{
  "type": "Feature",
  "properties": {
    "iso:country":"CH",
    "sg:address":"L\u00f6wenstrasse 24",
    "sg:city":"Dietikon",
    "sg:orig_category":"Zahntechnische Laboratorien",
    "sg:phone":"+41 17402218",
    "sg:postcode":"8953",
    "sg:province":"Z\u00fcrich",
    "wof:name":"Heinz Keller Zahntechnisches Laboratorium",
    "wof:placetype":"venue"
},
  "geometry": {"coordinates":[8.4019594193,47.4055175781],"type":"Point"}
}