{
  "type": "Feature",
  "properties": {
    "iso:country":"CH",
    "sg:address":"Hofweg 749",
    "sg:city":"Meisterschwanden",
    "sg:orig_category":"Gartenbau",
    "sg:phone":"+41 56 667 33 05",
    "sg:postcode":"5616",
    "sg:province":"Aargau",
    "wof:name":"Fredi Vatter Gartenbau",
    "wof:placetype":"venue"
},
  "geometry": {"coordinates":[8.2277593613,47.2909545898],"type":"Point"}
}