{
  "type": "Feature",
  "properties": {
    "iso:country":"CH",
    "sg:address":"Romanshornerstrasse 58",
    "sg:city":"Kreuzlingen",
    "sg:orig_category":"Instandhaltung U Reparatur von Automobilen Tankstellen",
    "sg:phone":"+41 31 352 49 11",
    "sg:postcode":"8280",
    "sg:province":"Thurgau",
    "wof:name":"Ostring-garage Hans Lack Ag",
    "wof:placetype":"venue"
},
  "geometry": {"coordinates":[7.471432209,46.9457244873],"type":"Point"}
}