{
  "type": "Feature",
  "properties": {
    "iso:country":"CH",
    "sg:address":"Lothringerstrasse 30 4056 Basel. Postfach",
    "sg:city":"Basel",
    "sg:orig_category":"Herstellung von elektrischen Lampen U Leuchten",
    "sg:phone":"+41 61 321 01 20",
    "sg:postcode":"4056",
    "sg:province":"Basel-Stadt",
    "wof:name":"Karl Gysin & Co. Ag Beleuchtungsk\u00f6rper; Fabrik., Handel",
    "wof:placetype":"venue"
},
  "geometry": {"coordinates":[7.579056,47.56694],"type":"Point"}
}