{
  "type": "Feature",
  "properties": {
    "iso:country":"CH",
    "sg:address":"Gr\u00fctstrasse 22",
    "sg:city":"Herrliberg",
    "sg:orig_category":"Unclassifiable Establishments",
    "sg:postcode":"8704",
    "sg:province":"Z\u00fcrich",
    "wof:name":"Marti - Kurier",
    "wof:placetype":"venue"
},
  "geometry": {"coordinates":[8.6096248627,47.2864570618],"type":"Point"}
}