{
  "type": "Feature",
  "properties": {
    "iso:country":"CH",
    "sg:address":"Thunstrasse 102",
    "sg:city":"Rubigen",
    "sg:orig_category":"Maler U Glasergewerbe",
    "sg:postcode":"3113",
    "sg:province":"Bern",
    "wof:name":"Walter Neuenschwander",
    "wof:placetype":"venue"
},
  "geometry": {"coordinates":[7.5485601425,46.8928604126],"type":"Point"}
}