{
  "type": "Feature",
  "properties": {
    "iso:country":"CH",
    "sg:address":"Sternenfeldstrasse 8",
    "sg:city":"Birsfelden",
    "sg:orig_category":"Unclassifiable Establishments",
    "sg:postcode":"4127",
    "sg:province":"Basel-Landschaft",
    "wof:name":"Bwb Engineering Holding Ag",
    "wof:placetype":"venue"
},
  "geometry": {"coordinates":[7.6339030266,47.5510787964],"type":"Point"}
}