{
  "type": "Feature",
  "properties": {
    "iso:country":"CH",
    "sg:address":"Burgstrasse 212",
    "sg:city":"Meilen",
    "sg:orig_category":"Sportvereine Wassersport Segeln",
    "sg:phone":"+41 19237671",
    "sg:postcode":"8706",
    "sg:province":"Z\u00fcrich",
    "wof:name":"Segelclub Rhyspitz Scry",
    "wof:placetype":"venue"
},
  "geometry": {"coordinates":[8.6456327438,47.2758369446],"type":"Point"}
}