{
  "type": "Feature",
  "properties": {
    "iso:country":"CH",
    "sg:address":"L\u00e4nggassstrasse 7",
    "sg:city":"Bern",
    "sg:orig_category":"RESTAURANTS: TEA-ROOMS",
    "sg:phone":"+41 31 301 52 21",
    "sg:postcode":"3012",
    "sg:province":"Bern",
    "wof:name":"Cafe Restaurant Longstreet Stucki Kathrin",
    "wof:placetype":"venue"
},
  "geometry": {"coordinates":[7.4345221519,46.9515609741],"type":"Point"}
}