{
  "type": "Feature",
  "properties": {
    "iso:country":"CH",
    "sg:address":"Talstrasse 38 8200 Schaffhausen. Postfach 594",
    "sg:city":"Schaffhausen",
    "sg:orig_category":"Sonstiger Grosshandel",
    "sg:phone":"+41 52 630 06 90",
    "sg:postcode":"8200",
    "sg:province":"Schaffhausen",
    "wof:name":"Polyprom Ag",
    "wof:placetype":"venue"
},
  "geometry": {"coordinates":[8.6497688293,47.7016563416],"type":"Point"}
}