{
  "type": "Feature",
  "properties": {
    "iso:country":"CH",
    "sg:address":"Effingerstrasse 20",
    "sg:city":"Bern",
    "sg:orig_category":"Detailhandel mit Damenbekleidung",
    "sg:phone":"+41 31 381 48 58",
    "sg:postcode":"3008",
    "sg:province":"Bern",
    "wof:name":"Mode Madame Modehaus Ag",
    "wof:placetype":"venue"
},
  "geometry": {"coordinates":[7.42176,46.944649],"type":"Point"}
}