{
  "type": "Feature",
  "properties": {
    "iso:country":"CH",
    "sg:address":"Route De Divonne 48",
    "sg:city":"Nyon",
    "sg:orig_category":"RESTAURANTS: TEA-ROOMS",
    "sg:phone":"+41 22 362 39 60",
    "sg:postcode":"1260",
    "sg:province":"Vaud",
    "wof:name":"Caf\u00e9 Des M\u00e9tiers, Lutz A.",
    "wof:placetype":"venue"
},
  "geometry": {"coordinates":[6.2227759361,46.3829574585],"type":"Point"}
}