{
  "type": "Feature",
  "properties": {
    "iso:country":"CH",
    "sg:address":"Birchlimatt 1a",
    "sg:city":"Einsiedeln",
    "sg:orig_category":"Sonstiger Grosshandel",
    "sg:phone":"+41 79 200 12 65",
    "sg:postcode":"8840",
    "sg:province":"Schwyz",
    "wof:name":"Gs-rewarding Gmbh",
    "wof:placetype":"venue"
},
  "geometry": {"coordinates":[8.7670927048,47.1309776306],"type":"Point"}
}