{
  "type": "Feature",
  "properties": {
    "iso:country":"CH",
    "sg:address":"Romanshornerstrasse 28",
    "sg:city":"Kreuzlingen",
    "sg:orig_category":"Unclassifiable Establishments",
    "sg:postcode":"8280",
    "sg:province":"Thurgau",
    "wof:name":"Baumgartner D. Transporte",
    "wof:placetype":"venue"
},
  "geometry": {"coordinates":[9.1880779266,47.6421813965],"type":"Point"}
}