{
  "type": "Feature",
  "properties": {
    "iso:country":"CH",
    "sg:address":"Hettlingerstrasse 8",
    "sg:city":"Seuzach",
    "sg:orig_category":"Bauschreinerei Herstellung von Konstruktionsteilen, Fertigbauteilen U Ausbauelementen aus Holz",
    "sg:phone":"+41 52 335 22 56",
    "sg:postcode":"8472",
    "sg:province":"Z\u00fcrich",
    "wof:name":"Schreinerei Eichin",
    "wof:placetype":"venue"
},
  "geometry": {"coordinates":[8.728655,47.537861],"type":"Point"}
}