{
  "type": "Feature",
  "properties": {
    "iso:country":"CH",
    "sg:address":"Chamerstrasse 170",
    "sg:city":"Zug",
    "sg:orig_category":"Sonstige mit der Informatik verbundene T\u00e4tigkeiten",
    "sg:phone":"+41 18691928",
    "sg:postcode":"6300",
    "sg:province":"Zug",
    "wof:name":"Alings Edv-beratung",
    "wof:placetype":"venue"
},
  "geometry": {"coordinates":[8.508061409,47.6049118042],"type":"Point"}
}