{
  "type": "Feature",
  "properties": {
    "iso:country":"CH",
    "sg:address":"Kirchbergstrasse 190 Postfach",
    "sg:city":"Burgdorf",
    "sg:classifiers":[
        {
            "category":"Wholesale",
            "subcategory":"Medical Equipment & Supplies",
            "type":"Manufacturing & Wholesale Goods"
        }
    ],
    "sg:phone":"+41 61 307 90 00",
    "sg:postcode":"3401",
    "sg:province":"Bern",
    "sg:tags":[
        "instrument",
        "health",
        "-",
        "precision"
    ],
    "wof:name":"Eisenhut-vet Ag",
    "wof:placetype":"venue"
},
  "geometry": {"coordinates":[9.487569809,53.921081543],"type":"Point"}
}