{
  "type": "Feature",
  "properties": {
    "iso:country":"CH",
    "sg:address":"1036",
    "sg:city":"Sullens",
    "sg:orig_category":"RESTAURANTS: TEA-ROOMS",
    "sg:postcode":"1036",
    "sg:province":"Vaud",
    "wof:name":"Bocion Fran\u00e7ois.",
    "wof:placetype":"venue"
},
  "geometry": {"coordinates":[6.5671100616,46.5916404724],"type":"Point"}
}