{
  "type": "Feature",
  "properties": {
    "iso:country":"CH",
    "sg:address":"Bahnhofstrasse 2",
    "sg:city":"Elgg",
    "sg:orig_category":"Sonstige mit der Informatik verbundene T\u00e4tigkeiten",
    "sg:phone":"+41 52 364 29 39",
    "sg:postcode":"8353",
    "sg:province":"Z\u00fcrich",
    "wof:name":"Pfister Edv",
    "wof:placetype":"venue"
},
  "geometry": {"coordinates":[8.8642873764,47.4979972839],"type":"Point"}
}