{
  "type": "Feature",
  "properties": {
    "iso:country":"CH",
    "sg:address":"Gerliswilstrasse 27 6020 Emmenbr\u00fccke. Postfach",
    "sg:city":"Emmenbr\u00fccke",
    "sg:orig_category":"Handels-H\u00e4user U Gesellschaften",
    "sg:postcode":"6020",
    "sg:province":"Luzern",
    "wof:name":"Advanced Tachyon Technologies Gmbh",
    "wof:placetype":"venue"
},
  "geometry": {"coordinates":[8.2785749435,47.0724601746],"type":"Point"}
}