{
  "type": "Feature",
  "properties": {
    "iso:country":"CH",
    "sg:address":"Buttenberg 5",
    "sg:city":"Buckten",
    "sg:orig_category":"Organisationen der Wohlfahrtspflege",
    "sg:phone":"+41 62 299 11 10",
    "sg:postcode":"4446",
    "sg:province":"Basel-Landschaft",
    "wof:name":"Paula Greif Pro Senectute Baselland",
    "wof:placetype":"venue"
},
  "geometry": {"coordinates":[7.8424720764,47.4118423462],"type":"Point"}
}