{
  "type": "Feature",
  "properties": {
    "iso:country":"CH",
    "sg:address":"Gewerbestrasse 11",
    "sg:city":"Cham",
    "sg:orig_category":"Informatikschulen Sonstige mit der Informatik verbundene T\u00e4tigkeiten",
    "sg:phone":"+41 17154420",
    "sg:postcode":"6330",
    "sg:province":"Zug",
    "wof:name":"Polypol Ag",
    "wof:placetype":"venue"
},
  "geometry": {"coordinates":[8.5459766388,47.3303375244],"type":"Point"}
}