{
  "type": "Feature",
  "properties": {
    "addr:full":"Rennweg 46 Z\u00fcrich Z\u00fcrich 8001",
    "addr:housenumber":"46",
    "addr:postcode":"8001",
    "addr:street":"Rennweg",
    "iso:country":"CH",
    "sg:address":"Rennweg 46",
    "sg:city":"Z\u00fcrich",
    "sg:orig_category":"Arztpraxen",
    "sg:phone":"+41 12211911",
    "sg:postcode":"8001",
    "sg:province":"Z\u00fcrich",
    "wof:name":"Dr.med.dieter Lohner Spezialarzt Fmh",
    "wof:placetype":"venue"
},
  "geometry": {"coordinates":[8.539293,47.373638],"type":"Point"}
}