{
  "type": "Feature",
  "properties": {
    "addr:full":"Stockerstrasse 24 Horgen Z\u00fcrich 8810",
    "addr:housenumber":"24",
    "addr:postcode":"8810",
    "addr:street":"Stockerstrasse",
    "iso:country":"CH",
    "sg:address":"Stockerstrasse 24",
    "sg:city":"Horgen",
    "sg:orig_category":"Arbeitnehmerverb\u00e4nde",
    "sg:phone":"+41 17254081",
    "sg:postcode":"8810",
    "sg:province":"Z\u00fcrich",
    "wof:name":"Gewerkschaft Industrie,gewerbe & Dienstleistungen Smuv/unia",
    "wof:placetype":"venue"
},
  "geometry": {"coordinates":[8.593244,47.260818],"type":"Point"}
}