{
  "type": "Feature",
  "properties": {
    "iso:country":"CH",
    "sg:address":"Piazza Boffalora 4",
    "sg:city":"Chiasso",
    "sg:orig_category":"Herstellung von pharmazeutischen Grundstoffen",
    "sg:phone":"+41 91 695 42 60",
    "sg:postcode":"6830",
    "sg:province":"Ticino",
    "wof:name":"Recordati Sa Chemical And Pharmaceutical Company, Luxembourg, Succursale Di Chiasso",
    "wof:placetype":"venue"
},
  "geometry": {"coordinates":[9.0214538574,45.8378601074],"type":"Point"}
}