{
  "type": "Feature",
  "properties": {
    "iso:country":"CH",
    "sg:address":"Route Principale 42",
    "sg:city":"Vendlincourt",
    "sg:orig_category":"Sonstige mit der Informatik verbundene T\u00e4tigkeiten",
    "sg:phone":"+41 32 474 51 91",
    "sg:postcode":"2943",
    "sg:province":"Jura",
    "wof:name":"Thierry Cuenat Programmation",
    "wof:placetype":"venue"
},
  "geometry": {"coordinates":[7.1493940353,47.4509124756],"type":"Point"}
}