{
  "type": "Feature",
  "properties": {
    "iso:country":"CH",
    "sg:address":"6714",
    "sg:city":"Semione",
    "sg:orig_category":"Museen",
    "sg:phone":"+41 91 870 12 88",
    "sg:postcode":"6714",
    "sg:province":"Ticino",
    "wof:name":"Museo Fossili & Minerali",
    "wof:placetype":"venue"
},
  "geometry": {"coordinates":[8.9714298248,46.4069595337],"type":"Point"}
}