{
  "type": "Feature",
  "properties": {
    "iso:country":"CH",
    "sg:address":"Grand-rue 19",
    "sg:city":"Payerne",
    "sg:orig_category":"Detailhandel mit Bekleidung Detailhandel mit Herrenbekleidung",
    "sg:phone":"+41 26 660 20 71",
    "sg:postcode":"1530",
    "sg:province":"Vaud",
    "wof:name":"Type Chic, Mode Masculine, Diserens Christiane Et Marlyse",
    "wof:placetype":"venue"
},
  "geometry": {"coordinates":[6.938278,46.821274],"type":"Point"}
}