{
  "type": "Feature",
  "properties": {
    "iso:country":"CH",
    "sg:address":"Hubelweid",
    "sg:city":"Triengen",
    "sg:orig_category":"Softwareentwicklung U beratung Sonstige mit der Informatik verbundene T\u00e4tigkeiten",
    "sg:phone":"+41 41 934 01 11",
    "sg:postcode":"6234",
    "sg:province":"Luzern",
    "wof:name":"Petermann Software Engineering",
    "wof:placetype":"venue"
},
  "geometry": {"coordinates":[8.0902490616,47.2432594299],"type":"Point"}
}