{
  "type": "Feature",
  "properties": {
    "iso:country":"CH",
    "sg:address":"Flughafenstrasse 11",
    "sg:city":"Altenrhein",
    "sg:orig_category":"Luftfahrt",
    "sg:phone":"+41 71 858 27 00",
    "sg:postcode":"9423",
    "sg:province":"St. Gallen",
    "wof:name":"Rheintalflug Vorarlberger Luftfahrt Gmbh",
    "wof:placetype":"venue"
},
  "geometry": {"coordinates":[9.5526638031,47.4885635376],"type":"Point"}
}