{
  "type": "Feature",
  "properties": {
    "iso:country":"CH",
    "sg:address":"Rigistrasse 12 6340 Baar. Postfach",
    "sg:city":"Baar",
    "sg:orig_category":"Betrieb von Taxis",
    "sg:phone":"+41 19108080",
    "sg:postcode":"6340",
    "sg:province":"Zug",
    "wof:name":"Z\u00fcrichsee Und Ch\u00fcsnachter Funk-taxi, Demir & Yumak",
    "wof:placetype":"venue"
},
  "geometry": {"coordinates":[8.580209,47.316051],"type":"Point"}
}