{
  "type": "Feature",
  "properties": {
    "addr:full":"Ausstellungsstrasse 60 8005 Z\u00fcrich. Postfach Z\u00fcrich Z\u00fcrich 8090",
    "addr:housenumber":"60",
    "addr:postcode":"8005 zuerich. postfach;8090",
    "addr:street":"Ausstellungsstrasse",
    "iso:country":"CH",
    "sg:address":"Ausstellungsstrasse 60 8005 Z\u00fcrich. Postfach",
    "sg:city":"Z\u00fcrich",
    "sg:orig_category":"Berufsbildende weiterf\u00fchrende Schulen",
    "sg:phone":"+41 14469710",
    "sg:postcode":"8090",
    "sg:province":"Z\u00fcrich",
    "wof:name":"Allgem.berufsschule Z\u00fcrich",
    "wof:placetype":"venue"
},
  "geometry": {"coordinates":[8.535501,47.382893],"type":"Point"}
}