{
  "type": "Feature",
  "properties": {
    "iso:country":"CH",
    "sg:address":"Chemin Du Raidillon 34",
    "sg:city":"Epalinges",
    "sg:orig_category":"Malerei Stukkateurgewerbe, Gipserei U Verputzerei",
    "sg:phone":"+41 22 732 45 66",
    "sg:postcode":"1066",
    "sg:province":"Vaud",
    "wof:name":"Pierre Kurzen Gypserie & Peinture",
    "wof:placetype":"venue"
},
  "geometry": {"coordinates":[6.1468510628,46.2173805237],"type":"Point"}
}