{
  "type": "Feature",
  "properties": {
    "iso:country":"CH",
    "sg:address":"Austrasse 31 5430 Wettingen. Postfach",
    "sg:city":"Wettingen",
    "sg:orig_category":"Sonstige pers\u00f6nliche Dienstleistungen",
    "sg:postcode":"5430",
    "sg:province":"Aargau",
    "wof:name":"Interconsilium Gmbh",
    "wof:placetype":"venue"
},
  "geometry": {"coordinates":[8.3153820038,47.4678039551],"type":"Point"}
}