{
  "type": "Feature",
  "properties": {
    "iso:country":"CH",
    "sg:address":"Blegi 14",
    "sg:city":"Rotkreuz",
    "sg:orig_category":"Softwareentwicklung U beratung",
    "sg:postcode":"6343",
    "sg:province":"Zug",
    "wof:name":"Weibel Informatik",
    "wof:placetype":"venue"
},
  "geometry": {"coordinates":[9.0463542938,47.4639015198],"type":"Point"}
}