{
  "type": "Feature",
  "properties": {
    "addr:full":"Musardes Chemin Des 2 Corseaux Vaud 1802",
    "addr:postcode":"1802",
    "addr:street":"Chemin Des 2",
    "iso:country":"CH",
    "sg:address":"Musardes Chemin Des 2",
    "sg:city":"Corseaux",
    "sg:orig_category":"Architektur U Ingenieurb\u00fcros",
    "sg:postcode":"1802",
    "sg:province":"Vaud",
    "wof:name":"Bureau Technique Christian Richard",
    "wof:placetype":"venue"
},
  "geometry": {"coordinates":[6.833991,46.471809],"type":"Point"}
}