{
  "type": "Feature",
  "properties": {
    "addr:full":"Baselstrasse 59 Dagmersellen Luzern 6252",
    "addr:housenumber":"59",
    "addr:postcode":"6252",
    "addr:street":"Baselstrasse",
    "iso:country":"CH",
    "sg:address":"Baselstrasse 59",
    "sg:city":"Dagmersellen",
    "sg:classifiers":[
        {
            "category":"Professional",
            "subcategory":"Accounting & Tax Preparation",
            "type":"Services"
        }
    ],
    "sg:phone":"+41 62 748 31 41",
    "sg:postcode":"6252",
    "sg:province":"Luzern",
    "sg:tags":[
        "book-keeping"
    ],
    "wof:name":"Tagmar Ag",
    "wof:placetype":"venue"
},
  "geometry": {"coordinates":[7.982344,47.21954],"type":"Point"}
}