{
  "type": "Feature",
  "properties": {
    "addr:full":"Zentralstrasse 4 8610 Uster. Postfach Uster Z\u00fcrich 8610",
    "addr:housenumber":"4",
    "addr:postcode":"8610;8610",
    "addr:street":"Zentralstrasse;Postfach",
    "iso:country":"CH",
    "sg:address":"Zentralstrasse 4 8610 Uster. Postfach",
    "sg:city":"Uster",
    "sg:orig_category":"Datenverarbeitungsdienste Softwareentwicklung U beratung",
    "sg:phone":"+41 19407555",
    "sg:postcode":"8610",
    "sg:province":"Z\u00fcrich",
    "wof:name":"Unlimited Information Technologies Ag",
    "wof:placetype":"venue"
},
  "geometry": {"coordinates":[8.717874,47.347469],"type":"Point"}
}