{
  "type": "Feature",
  "properties": {
    "iso:country":"CH",
    "sg:address":"B\u00e4derstrasse 23",
    "sg:city":"Baden",
    "sg:orig_category":"Herstellung von Schmuck, Gold U Silberschmiedwaren",
    "sg:phone":"+41 56 221 64 75",
    "sg:postcode":"5400",
    "sg:province":"Aargau",
    "wof:name":"Amh Ag",
    "wof:placetype":"venue"
},
  "geometry": {"coordinates":[8.312869072,47.4801521301],"type":"Point"}
}