{
  "type": "Feature",
  "properties": {
    "iso:country":"CH",
    "sg:address":"Chalet Gschwendli",
    "sg:city":"Matten(st.stephan)",
    "sg:orig_category":"Gartenbau Geb\u00e4ude, Wohnungsreinigung",
    "sg:phone":"+41 91 996 31 07",
    "sg:postcode":"3773",
    "sg:province":"Bern",
    "wof:name":"Racine Service Sagl Manutenz.di Stabili & Giardini",
    "wof:placetype":"venue"
},
  "geometry": {"coordinates":[8.9218196869,45.9306106567],"type":"Point"}
}