{
  "type": "Feature",
  "properties": {
    "iso:country":"CH",
    "sg:address":"Lenkstrasse",
    "sg:city":"Zweisimmen",
    "sg:orig_category":"Interessenvertretungen",
    "sg:postcode":"3770",
    "sg:province":"Bern",
    "wof:name":"Erschliessungsgenossenschaft Ferienhauszone Hintere Wyermatte Ii.",
    "wof:placetype":"venue"
},
  "geometry": {"coordinates":[7.377658844,46.5503005981],"type":"Point"}
}