{
  "type": "Feature",
  "properties": {
    "iso:country":"CH",
    "sg:address":"Chemin Pr\u00e9-cornillons 3 1292 Chamb\u00e9sy Case Postale 85",
    "sg:city":"Chamb\u00e9sy",
    "sg:orig_category":"Buchverlag Verlagsgewerbe",
    "sg:phone":"+41 71 243 03 10",
    "sg:postcode":"1292",
    "sg:province":"Gen\u00e8ve",
    "wof:name":"Act Media Ag",
    "wof:placetype":"venue"
},
  "geometry": {"coordinates":[9.395175,47.431122],"type":"Point"}
}