{
  "type": "Feature",
  "properties": {
    "iso:country":"CH",
    "sg:address":"Girlen 9642 Ebnat. Postfach 11",
    "sg:city":"Ebnat",
    "sg:orig_category":"Sportvereine Ski",
    "sg:phone":"+41 71 993 27 66",
    "sg:postcode":"9642",
    "sg:province":"St. Gallen",
    "wof:name":"Skiclub Speer Ebnat-kappel",
    "wof:placetype":"venue"
},
  "geometry": {"coordinates":[9.1167001724,47.25],"type":"Point"}
}