{
  "type": "Feature",
  "properties": {
    "iso:country":"CH",
    "sg:address":"Hoffnungsstrasse 5",
    "sg:city":"Z\u00fcrich",
    "sg:orig_category":"Grosshandel mit Textilien",
    "sg:phone":"+41 14800442",
    "sg:postcode":"8038",
    "sg:province":"Z\u00fcrich",
    "wof:name":"Blico-seide, Blickenstorfer Emil Ag",
    "wof:placetype":"venue"
},
  "geometry": {"coordinates":[8.5352926254,47.3409881592],"type":"Point"}
}