{
  "type": "Feature",
  "properties": {
    "iso:country":"CH",
    "sg:address":"Gersauerstrasse 12",
    "sg:city":"Brunnen",
    "sg:orig_category":"Detailhandel mit Textilien",
    "sg:phone":"+41 71 223 51 31",
    "sg:postcode":"6440",
    "sg:province":"Schwyz",
    "wof:name":"Ruth Lagler Wolle-egge",
    "wof:placetype":"venue"
},
  "geometry": {"coordinates":[9.3766717911,47.4242591858],"type":"Point"}
}