{
  "type": "Feature",
  "properties": {
    "iso:country":"CH",
    "sg:address":"Mettstrasse 94",
    "sg:city":"Biel/bienne",
    "sg:orig_category":"Herstellung von sonstigen Erzeugnissen",
    "sg:postcode":"2500",
    "sg:province":"Bern",
    "wof:name":"Roth Bertha.",
    "wof:placetype":"venue"
},
  "geometry": {"coordinates":[7.267013073,47.1410255432],"type":"Point"}
}