{
  "type": "Feature",
  "properties": {
    "iso:country":"CH",
    "sg:address":"Via Luganetto 4",
    "sg:city":"Viganello",
    "sg:orig_category":"Arztpraxen",
    "sg:phone":"+41 91 942 41 93",
    "sg:postcode":"6962",
    "sg:province":"Ticino",
    "wof:name":"Dott.med.marc Bischoff Specialista Fmh",
    "wof:placetype":"venue"
},
  "geometry": {"coordinates":[8.960592,46.010921],"type":"Point"}
}