{
  "type": "Feature",
  "properties": {
    "iso:country":"CH",
    "sg:address":"Bois Du P\u00e2quier 9. 2053 Cernier Case Postale",
    "sg:city":"Cernier",
    "sg:orig_category":"Herstellung von Mess U Kontrollinstrumenten U vorrichtungen",
    "sg:postcode":"2053",
    "sg:province":"Neuch\u00e2tel",
    "wof:name":"Bercher Pierre. M\u00e9canique De Pr\u00e9cision, Moules, Injection De Plastique.",
    "wof:placetype":"venue"
},
  "geometry": {"coordinates":[6.8996529579,47.0585479736],"type":"Point"}
}