{
  "type": "Feature",
  "properties": {
    "iso:country":"CH",
    "sg:address":"Weslen 61c",
    "sg:city":"Wynigen",
    "sg:orig_category":"Zimmerei, Dachdeckerei, Bauspenglerei U Abdichtung Zimmerei, Ingenieurholzbau",
    "sg:postcode":"3472",
    "sg:province":"Bern",
    "wof:name":"Hans Rudolf Brechb\u00fchler",
    "wof:placetype":"venue"
},
  "geometry": {"coordinates":[7.667828083,47.1060791016],"type":"Point"}
}