{
  "type": "Feature",
  "properties": {
    "iso:country":"CH",
    "sg:address":"Metzggasse 19",
    "sg:city":"Winterthur",
    "sg:orig_category":"Herstellung von konfektionierten Textilwaren ohne Bekleidung",
    "sg:phone":"+41 52 212 62 05",
    "sg:postcode":"8400",
    "sg:province":"Z\u00fcrich",
    "wof:name":"Weingand Lilly, Couturi\u00e8re",
    "wof:placetype":"venue"
},
  "geometry": {"coordinates":[8.7275896072,47.4989852905],"type":"Point"}
}