{
  "type": "Feature",
  "properties": {
    "iso:country":"CH",
    "sg:address":"Route De La Frasse",
    "sg:city":"Ch\u00e2tel-st-denis",
    "sg:orig_category":"Datenverarbeitungsdienste Softwareentwicklung U beratung",
    "sg:phone":"+41 21 948 60 18",
    "sg:postcode":"1618",
    "sg:province":"Fribourg",
    "wof:name":"Helix J.-p.pichard Informatique",
    "wof:placetype":"venue"
},
  "geometry": {"coordinates":[6.925,46.533211],"type":"Point"}
}