{
  "type": "Feature",
  "properties": {
    "iso:country":"CH",
    "sg:address":"Passage De L'esplanade 1 2610 St-imier. Postfach",
    "sg:city":"St-imier",
    "sg:orig_category":"Verwaltung von Immobilien",
    "sg:postcode":"2610",
    "sg:province":"Bern",
    "wof:name":"Sava 3000 S\u00e0rl",
    "wof:placetype":"venue"
},
  "geometry": {"coordinates":[6.9997291565,47.1534729004],"type":"Point"}
}