{
  "type": "Feature",
  "properties": {
    "iso:country":"CH",
    "sg:address":"Kirchgasse 8",
    "sg:city":"Frenkendorf",
    "sg:orig_category":"Institutionen f\u00fcr Behinderte",
    "sg:phone":"+41 61 901 46 55",
    "sg:postcode":"4402",
    "sg:province":"Basel-Landschaft",
    "wof:name":"Eingliederungsst\u00e4tte & Arbeitszentrum F.behinderte",
    "wof:placetype":"venue"
},
  "geometry": {"coordinates":[7.7134199142,47.5027618408],"type":"Point"}
}