{
  "type": "Feature",
  "properties": {
    "iso:country":"CH",
    "sg:address":"8883",
    "sg:city":"Quarten",
    "sg:orig_category":"Sportvereine Ballsport Tennis",
    "sg:phone":"+41 81 738 14 75",
    "sg:postcode":"8883",
    "sg:province":"St. Gallen",
    "wof:name":"Tc Terza",
    "wof:placetype":"venue"
},
  "geometry": {"coordinates":[9.2411851883,47.1078948975],"type":"Point"}
}