{
  "type": "Feature",
  "properties": {
    "iso:country":"CH",
    "sg:address":"Rue De La Fleur-de-lys 26",
    "sg:city":"Marin-epagnier",
    "sg:orig_category":"Fotografische Laboratorien",
    "sg:phone":"+41 32 753 58 00",
    "sg:postcode":"2074",
    "sg:province":"Neuch\u00e2tel",
    "wof:name":"Minit 1 Sa",
    "wof:placetype":"venue"
},
  "geometry": {"coordinates":[7.0062298775,47.0124397278],"type":"Point"}
}