{
  "type": "Feature",
  "properties": {
    "addr:full":"Rue De Pierre-pertuis 15 Tavannes Bern 2710",
    "addr:housenumber":"15",
    "addr:postcode":"2710",
    "addr:street":"Rue De Pierre-Pertuis",
    "iso:country":"CH",
    "sg:address":"Rue De Pierre-pertuis 15",
    "sg:city":"Tavannes",
    "sg:orig_category":"Arztpraxen",
    "sg:phone":"+41 32 481 33 77",
    "sg:postcode":"2710",
    "sg:province":"Bern",
    "wof:name":"Dr M\u00e9d. Michel Glardon M\u00e9decin G\u00e9n\u00e9raliste",
    "wof:placetype":"venue"
},
  "geometry": {"coordinates":[7.197613,47.21904],"type":"Point"}
}