{
  "type": "Feature",
  "properties": {
    "iso:country":"CH",
    "sg:address":"Guetstrasse 27",
    "sg:city":"Oensingen",
    "sg:orig_category":"Sportvereine Ballsport Tennis",
    "sg:phone":"+41 62 396 16 68",
    "sg:postcode":"4702",
    "sg:province":"Solothurn",
    "wof:name":"Tc Oensingen",
    "wof:placetype":"venue"
},
  "geometry": {"coordinates":[7.7216501236,47.291557312],"type":"Point"}
}