{
  "type": "Feature",
  "properties": {
    "iso:country":"CH",
    "sg:address":"Bahnhofstrasse 5 3800 Interlaken. Postfach 25",
    "sg:city":"Interlaken",
    "sg:orig_category":"Organisationen des Gesundheitswesen",
    "sg:phone":"+41 33 822 91 19",
    "sg:postcode":"3800",
    "sg:province":"Bern",
    "wof:name":"Verein F\u00fcr Langzeitkranke Im Amt Interlaken,beratungsstelle",
    "wof:placetype":"venue"
},
  "geometry": {"coordinates":[7.8539228439,46.6845588684],"type":"Point"}
}