{
  "type": "Feature",
  "properties": {
    "iso:country":"CH",
    "sg:address":"Batlimattweg 3",
    "sg:city":"Oberentfelden",
    "sg:orig_category":"Softwareentwicklung U beratung",
    "sg:phone":"+41 62 723 53 17",
    "sg:postcode":"5036",
    "sg:province":"Aargau",
    "wof:name":"Advance Software, Cavanaugh Charles",
    "wof:placetype":"venue"
},
  "geometry": {"coordinates":[8.0429639816,47.3564300537],"type":"Point"}
}