{
  "type": "Feature",
  "properties": {
    "iso:country":"CH",
    "sg:address":"Route D'epinassey",
    "sg:city":"St-maurice",
    "sg:orig_category":"Bauschreinerei Herstellung von M\u00f6beln verschiedener Art",
    "sg:phone":"+41 24 485 22 11",
    "sg:postcode":"1890",
    "sg:province":"Valais",
    "wof:name":"Menuiserie Des Marais Sa",
    "wof:placetype":"venue"
},
  "geometry": {"coordinates":[7.01291,46.196281],"type":"Point"}
}