{
  "type": "Feature",
  "properties": {
    "iso:country":"CH",
    "sg:address":"Metropol-center",
    "sg:city":"Arbon",
    "sg:orig_category":"Detailhandel mit Schuhen",
    "sg:phone":"+41 71 446 12 80",
    "sg:postcode":"9320",
    "sg:province":"Thurgau",
    "wof:name":"Schuhhaus Walder Ag",
    "wof:placetype":"venue"
},
  "geometry": {"coordinates":[9.4272298813,47.5105209351],"type":"Point"}
}