{
  "type": "Feature",
  "properties": {
    "iso:country":"CH",
    "sg:address":"Chemnin Des Claives 20",
    "sg:city":"Fully",
    "sg:orig_category":"Detailhandel mit Getr\u00e4nken",
    "sg:phone":"+41 79 433 44 90",
    "sg:postcode":"1926",
    "sg:province":"Valais",
    "wof:name":"Andr\u00e9 Roduit & Fils Vins",
    "wof:placetype":"venue"
},
  "geometry": {"coordinates":[7.119784832,46.1373138428],"type":"Point"}
}