{
  "type": "Feature",
  "properties": {
    "iso:country":"CH",
    "sg:address":"Auenstrasse 6",
    "sg:city":"Bichelsee",
    "sg:orig_category":"Gemeindeverwaltungen",
    "sg:phone":"+41 61 721 33 66",
    "sg:postcode":"8363",
    "sg:province":"Thurgau",
    "wof:name":"Gemeindeverwaltung Biel-benken",
    "wof:placetype":"venue"
},
  "geometry": {"coordinates":[7.5185041428,47.5040130615],"type":"Point"}
}