{
  "type": "Feature",
  "properties": {
    "iso:country":"CH",
    "sg:address":"Sch\u00f6nenbergstrasse 50",
    "sg:city":"W\u00e4denswil",
    "sg:orig_category":"Sonstige mit der Informatik verbundene T\u00e4tigkeiten",
    "sg:postcode":"8820",
    "sg:province":"Z\u00fcrich",
    "wof:name":"Informatikb\u00fcro Volery",
    "wof:placetype":"venue"
},
  "geometry": {"coordinates":[8.6728630066,47.2238960266],"type":"Point"}
}