{
  "type": "Feature",
  "properties": {
    "iso:country":"CH",
    "sg:address":"Kettstrasse 8 6374 Buochs. Postfach 431",
    "sg:city":"Buochs",
    "sg:orig_category":"Politische Parteien CVP",
    "sg:postcode":"6374",
    "sg:province":"Nidwalden",
    "wof:name":"Cvp Ortspartei Buochs",
    "wof:placetype":"venue"
},
  "geometry": {"coordinates":[8.4120426178,46.9736442566],"type":"Point"}
}