{
  "type": "Feature",
  "properties": {
    "iso:country":"CH",
    "sg:address":"H\u00fchnerhubelstr. 62",
    "sg:city":"Belp",
    "sg:classifiers":[
        {
            "category":"Building & Trades",
            "subcategory":"Electrical",
            "type":"Services"
        }
    ],
    "sg:phone":"+41 31 818 28 28",
    "sg:postcode":"3123",
    "sg:province":"Bern",
    "sg:tags":[
        "electronic",
        "lighting",
        "equipment"
    ],
    "wof:name":"Siteco Schweiz Ag",
    "wof:placetype":"venue"
},
  "geometry": {"coordinates":[7.4954352379,46.9047279358],"type":"Point"}
}