{
  "type": "Feature",
  "properties": {
    "iso:country":"CH",
    "sg:address":"Rue Marcello 9",
    "sg:city":"Fribourg",
    "sg:orig_category":"Arztpraxen",
    "sg:phone":"+41 26 322 28 33",
    "sg:postcode":"1700",
    "sg:province":"Fribourg",
    "wof:name":"Dr M\u00e9d. Didier Stadler M\u00e9decin G\u00e9n\u00e9raliste Fmh",
    "wof:placetype":"venue"
},
  "geometry": {"coordinates":[7.154223,46.808125],"type":"Point"}
}