{
  "type": "Feature",
  "properties": {
    "iso:country":"CH",
    "sg:address":"Z\u00fcrcherstrasse 120 5432 Neuenhof. Postfach 223",
    "sg:city":"Neuenhof",
    "sg:orig_category":"Handelsvermittlung U Grosshandel mit Automobilteilen U Zubeh\u00f6r Herstellung von Teilen U Zubeh\u00f6r f\u00fcr ",
    "sg:phone":"+41 56 406 17 00",
    "sg:postcode":"5432",
    "sg:province":"Aargau",
    "wof:name":"Josef Rimann Ag",
    "wof:placetype":"venue"
},
  "geometry": {"coordinates":[8.3262195587,47.4501991272],"type":"Point"}
}