{
  "type": "Feature",
  "properties": {
    "iso:country":"CH",
    "sg:address":"Dorf 9657 Unterwasser. Postfach",
    "sg:city":"Unterwasser",
    "sg:classifiers":[
        {
            "category":"Travel",
            "subcategory":"Hotels & Motels",
            "type":"Entertainment"
        }
    ],
    "sg:phone":"+41 79 344 84 03",
    "sg:postcode":"9657",
    "sg:province":"St. Gallen",
    "sg:tags":[
        "hotels",
        "mit",
        "restaurant"
    ],
    "wof:name":"Hotel Reuti",
    "wof:placetype":"venue"
},
  "geometry": {"coordinates":[8.2095499039,46.7326583862],"type":"Point"}
}