{
  "type": "Feature",
  "properties": {
    "iso:country":"CH",
    "sg:address":"Rindermarkt 6",
    "sg:city":"Z\u00fcrich",
    "sg:orig_category":"Detailhandel mit Geschenkartikeln U Souvenirs",
    "sg:phone":"+41 12516969",
    "sg:postcode":"8001",
    "sg:province":"Z\u00fcrich",
    "wof:name":"Schatulle Heidi Stoll-m\u00fcller Boutique. Modeartikel; Handel, Herstellung Usw",
    "wof:placetype":"venue"
},
  "geometry": {"coordinates":[8.5440378189,47.372215271],"type":"Point"}
}