{
  "type": "Feature",
  "properties": {
    "iso:country":"CH",
    "sg:address":"Via Cantonale",
    "sg:city":"Cevio",
    "sg:classifiers":[
        {
            "category":"Mining & Drilling",
            "type":"Manufacturing & Wholesale Goods"
        }
    ],
    "sg:phone":"+41 91 754 13 44",
    "sg:postcode":"6675",
    "sg:province":"Ticino",
    "sg:tags":[
        "quarry"
    ],
    "wof:name":"Graniti Bionda Sa",
    "wof:placetype":"venue"
},
  "geometry": {"coordinates":[8.6104850769,46.3087692261],"type":"Point"}
}