{
  "type": "Feature",
  "properties": {
    "iso:country":"CH",
    "sg:address":"Ussb\u00fchl 8865 Bilten. Postfach 45",
    "sg:city":"Bilten",
    "sg:classifiers":[
        {
            "category":"Restaurant",
            "type":"Food & Drink"
        }
    ],
    "sg:phone":"+41 19324621",
    "sg:postcode":"8865",
    "sg:province":"Glarus",
    "wof:name":"Restaurant Freihof",
    "wof:placetype":"venue"
},
  "geometry": {"coordinates":[8.7871055603,47.329372406],"type":"Point"}
}