{
  "type": "Feature",
  "properties": {
    "addr:full":"Halden 129 Trogen Appenzell Ausserrhoden 9043",
    "addr:housenumber":"129",
    "addr:postcode":"9043",
    "addr:street":"Halden;Ausserrhoden",
    "iso:country":"CH",
    "sg:address":"Halden 129",
    "sg:city":"Trogen",
    "sg:classifiers":[
        {
            "category":"Banks & Credit Unions",
            "subcategory":"Bank",
            "type":"Services"
        }
    ],
    "sg:postcode":"9043",
    "sg:province":"Appenzell Ausserrhoden",
    "wof:name":"Sparkasse Wald",
    "wof:placetype":"venue"
},
  "geometry": {"coordinates":[9.489829,47.415588],"type":"Point"}
}