{
  "type": "Feature",
  "properties": {
    "iso:country":"CH",
    "sg:address":"Oberdorf 228",
    "sg:city":"Wikon",
    "sg:orig_category":"Erbringung von Dienstleistungen f\u00fcr Unternehmen",
    "sg:postcode":"4806",
    "sg:province":"Luzern",
    "wof:name":"Design Und Wohnberatung Felten.",
    "wof:placetype":"venue"
},
  "geometry": {"coordinates":[7.9784460068,47.2615318298],"type":"Point"}
}