{
  "type": "Feature",
  "properties": {
    "iso:country":"CH",
    "sg:address":"Wintersingerstrasse 22",
    "sg:city":"Maisprach",
    "sg:orig_category":"Fahrschulen, Flugschulen",
    "sg:phone":"+41 61 841 14 50",
    "sg:postcode":"4464",
    "sg:province":"Basel-Landschaft",
    "wof:name":"Walter Dettwiler Autofahrschule",
    "wof:placetype":"venue"
},
  "geometry": {"coordinates":[7.8448228836,47.5225334167],"type":"Point"}
}