{
  "type": "Feature",
  "properties": {
    "iso:country":"CH",
    "sg:address":"Hauptstrasse",
    "sg:city":"Pontresina",
    "sg:classifiers":[
        {
            "category":"Travel",
            "subcategory":"Hotels & Motels",
            "type":"Entertainment"
        }
    ],
    "sg:phone":"+41 81 858 51 24",
    "sg:postcode":"7504",
    "sg:province":"Graubunden",
    "sg:tags":[
        "hotels",
        "mit",
        "restaurant"
    ],
    "wof:name":"Hotel Schweizerhof",
    "wof:placetype":"venue"
},
  "geometry": {"coordinates":[10.4197702408,46.6005554199],"type":"Point"}
}