{
  "type": "Feature",
  "properties": {
    "iso:country":"CH",
    "sg:address":"Obere Z\u00e4une 14",
    "sg:city":"Z\u00fcrich",
    "sg:orig_category":"Forschung U Entwicklung im Bereich der Naturwissenschaften",
    "sg:phone":"+41 12543060",
    "sg:postcode":"8001",
    "sg:province":"Z\u00fcrich",
    "wof:name":"Iafob Institut F\u00fcr Arbeitsforschung Und Organisationsberatung Gmbh",
    "wof:placetype":"venue"
},
  "geometry": {"coordinates":[8.5457334518,47.371307373],"type":"Point"}
}