{
  "type": "Feature",
  "properties": {
    "iso:country":"CH",
    "sg:address":"Elvezia Corso 16",
    "sg:city":"Lugano",
    "sg:orig_category":"Non-Classified Establishments",
    "sg:postcode":"6900",
    "sg:province":"Ticino",
    "wof:name":"F & T Holding Ag",
    "wof:placetype":"venue"
},
  "geometry": {"coordinates":[7.48229599,46.9336433411],"type":"Point"}
}