{
  "type": "Feature",
  "properties": {
    "iso:country":"CH",
    "sg:address":"Alte Steinhauserstrasse 19 6330 Cham. Postfach 5347",
    "sg:city":"Cham",
    "sg:orig_category":"Erbringung von Dienstleistungen f\u00fcr Unternehmen Markt U Meinungsforschung",
    "sg:phone":"+41 41 748 78 78",
    "sg:postcode":"6330",
    "sg:province":"Zug",
    "wof:name":"Sysmar Ag F\u00fcr System-marketing",
    "wof:placetype":"venue"
},
  "geometry": {"coordinates":[8.4743642807,47.1882553101],"type":"Point"}
}