{
  "type": "Feature",
  "properties": {
    "iso:country":"CH",
    "sg:address":"Bireggring 4",
    "sg:city":"Luzern",
    "sg:orig_category":"Gymnastik U Fitnesszentren Tanzschulen, Tanzlehrer",
    "sg:phone":"+41 41 340 03 30",
    "sg:postcode":"6005",
    "sg:province":"Luzern",
    "wof:name":"Jazzercise",
    "wof:placetype":"venue"
},
  "geometry": {"coordinates":[8.3335599899,47.0247917175],"type":"Point"}
}