{
  "type": "Feature",
  "properties": {
    "iso:country":"CH",
    "sg:address":"Rue De L'horloge 8",
    "sg:city":"Lutry",
    "sg:orig_category":"Detailhandel mit M\u00f6beln Kunsthandel",
    "sg:phone":"+41 21 791 56 77",
    "sg:postcode":"1095",
    "sg:province":"Vaud",
    "wof:name":"Galerie Tango Liliane Zimmermann",
    "wof:placetype":"venue"
},
  "geometry": {"coordinates":[6.6853680611,46.5026626587],"type":"Point"}
}