{
  "type": "Feature",
  "properties": {
    "iso:country":"CH",
    "sg:address":"Chemin Des Fontenailles",
    "sg:city":"Gland",
    "sg:orig_category":"Grosshandel mit Blumen U Pflanzen Grosshandel mit Obst U Gem\u00fcse",
    "sg:phone":"+41 22 999 99 99",
    "sg:postcode":"1196",
    "sg:province":"Vaud",
    "wof:name":"Georges Helfer Sa Primeurs D'outre-mer",
    "wof:placetype":"venue"
},
  "geometry": {"coordinates":[6.2725510597,46.4137229919],"type":"Point"}
}