{
  "type": "Feature",
  "properties": {
    "iso:country":"CH",
    "sg:address":"Bergstrasse 27",
    "sg:city":"Z\u00fcrich",
    "sg:orig_category":"Kinderkrippen U horte",
    "sg:phone":"+41 12522449",
    "sg:postcode":"8044",
    "sg:province":"Z\u00fcrich",
    "wof:name":"Kindervilla Alibaba",
    "wof:placetype":"venue"
},
  "geometry": {"coordinates":[8.561463356,47.373966217],"type":"Point"}
}