{
  "type": "Feature",
  "properties": {
    "iso:country":"CH",
    "sg:address":"Vordergasse 1274 8610 Uster. Postfach",
    "sg:city":"Wermatswil",
    "sg:orig_category":"Grosshandel mit Getr\u00e4nken",
    "sg:postcode":"8615",
    "sg:province":"Z\u00fcrich",
    "wof:name":"Oswald-mathiuet Verena, Weinhandlung",
    "wof:placetype":"venue"
},
  "geometry": {"coordinates":[8.7151899338,47.3495101929],"type":"Point"}
}