{
  "type": "Feature",
  "properties": {
    "iso:country":"CH",
    "sg:address":"Tannwaldstr. 68 4600 Olten. Postfach",
    "sg:city":"Olten",
    "sg:orig_category":"Detailhandel mit elektrischen Haushalts-,Radio U Fernsehger\u00e4ten sowie Musikinstrumenten",
    "sg:postcode":"4601",
    "sg:province":"Solothurn",
    "wof:name":"Kuhn Willy Music- & Showbusiness",
    "wof:placetype":"venue"
},
  "geometry": {"coordinates":[7.9088201523,47.3530464172],"type":"Point"}
}