{
  "type": "Feature",
  "properties": {
    "iso:country":"CH",
    "sg:address":"Florastrasse 18",
    "sg:city":"Uster",
    "sg:orig_category":"Versicherungen Generalagenturen",
    "sg:phone":"+41 19059311",
    "sg:postcode":"8610",
    "sg:province":"Z\u00fcrich",
    "wof:name":"Helvetia Patria Versicherungen Agentur",
    "wof:placetype":"venue"
},
  "geometry": {"coordinates":[8.7205734253,47.3474349976],"type":"Point"}
}