{
  "type": "Feature",
  "properties": {
    "iso:country":"CH",
    "sg:address":"Am Schanzengraben 23 8002 Z\u00fcrich. Postfach",
    "sg:city":"Z\u00fcrich",
    "sg:orig_category":"Reiseb\u00fcros U Reiseveranstalter",
    "sg:phone":"+41 79 449 19 88",
    "sg:postcode":"8001",
    "sg:province":"Z\u00fcrich",
    "wof:name":"Omnia Travel & Trade Sa",
    "wof:placetype":"venue"
},
  "geometry": {"coordinates":[6.0825028419,46.2376327515],"type":"Point"}
}