{
  "type": "Feature",
  "properties": {
    "addr:full":"Ruelle Des Barri\u00e8res 2 1907 Mayens-de-saxon Case Postale 44 Mayens-de-saxon Valais 1907",
    "addr:housenumber":"2;44;1907",
    "addr:postcode":"1907",
    "addr:street":"Ruelle Des Barrie\u0300Res;Case Postale",
    "iso:country":"CH",
    "sg:address":"Ruelle Des Barri\u00e8res 2 1907 Mayens-de-saxon Case Postale 44",
    "sg:city":"Mayens-de-saxon",
    "sg:orig_category":"Architekturb\u00fcros",
    "sg:phone":"+41 27 744 28 48",
    "sg:postcode":"1907",
    "sg:province":"Valais",
    "wof:name":"Dominique Favre Bureau D'architecture",
    "wof:placetype":"venue"
},
  "geometry": {"coordinates":[-90.413383,46.493099],"type":"Point"}
}