{
  "type": "Feature",
  "properties": {
    "iso:country":"CH",
    "sg:address":"Schlundstrasse",
    "sg:city":"Kriens",
    "sg:orig_category":"Primarschulen",
    "sg:phone":"+41 71 455 14 43",
    "sg:postcode":"6010",
    "sg:province":"Luzern",
    "wof:name":"Primarschule Roggwil",
    "wof:placetype":"venue"
},
  "geometry": {"coordinates":[9.3965301514,47.5006713867],"type":"Point"}
}