{
  "type": "Feature",
  "properties": {
    "iso:country":"CH",
    "sg:address":"Bahnhofstrasse 1",
    "sg:city":"Sachseln",
    "sg:orig_category":"Wasserversorgung",
    "sg:phone":"+41 41 660 50 55",
    "sg:postcode":"6072",
    "sg:province":"Obwalden",
    "wof:name":"Wasserversorgung",
    "wof:placetype":"venue"
},
  "geometry": {"coordinates":[8.2391090393,46.8693313599],"type":"Point"}
}