{
  "type": "Feature",
  "properties": {
    "iso:country":"CH",
    "sg:address":"Erlenstr. 15",
    "sg:city":"Basel",
    "sg:classifiers":[
        {
            "category":"Professional",
            "type":"Services"
        }
    ],
    "sg:phone":"+41 26 494 15 66",
    "sg:postcode":"4021",
    "sg:tags":[
        "transport",
        "road"
    ],
    "wof:name":"Aeby Transporte",
    "wof:placetype":"venue"
},
  "geometry": {"coordinates":[7.2228989601,46.7874031067],"type":"Point"}
}