{
  "type": "Feature",
  "properties": {
    "iso:country":"CH",
    "sg:address":"Holeestrasse 117 4054 Basel. Postfach",
    "sg:city":"Basel",
    "sg:orig_category":"Wohnheime f\u00fcr Kinder U Jugendliche",
    "sg:phone":"+41 61 302 78 73",
    "sg:postcode":"4015",
    "sg:province":"Basel-Stadt",
    "wof:name":"Foyer Neubad",
    "wof:placetype":"venue"
},
  "geometry": {"coordinates":[7.5680837631,47.5455284119],"type":"Point"}
}