{
  "type": "Feature",
  "properties": {
    "iso:country":"CH",
    "sg:address":"Zugerstrasse 31",
    "sg:city":"W\u00e4denswil",
    "sg:orig_category":"Detailhandel mit Getr\u00e4nken Grosshandel mit festen Brennstoffen U Mineral\u00f6lerzeugnissen",
    "sg:phone":"+41 17803166",
    "sg:postcode":"8820",
    "sg:province":"Z\u00fcrich",
    "wof:name":"Langendorf H.j. Ag",
    "wof:placetype":"venue"
},
  "geometry": {"coordinates":[8.6684627533,47.2297592163],"type":"Point"}
}