{
  "type": "Feature",
  "properties": {
    "iso:country":"CH",
    "sg:address":"Rue Liotard 75",
    "sg:city":"Gen\u00e8ve",
    "sg:classifiers":[
        {
            "category":"Restaurant",
            "type":"Food & Drink"
        }
    ],
    "sg:phone":"+41 22 345 57 35",
    "sg:postcode":"1203",
    "sg:province":"Gen\u00e8ve",
    "wof:name":"Restaurant Jardin De Villars",
    "wof:placetype":"venue"
},
  "geometry": {"coordinates":[6.1293997765,46.2116012573],"type":"Point"}
}