{
  "type": "Feature",
  "properties": {
    "iso:country":"CH",
    "sg:address":"Route De C\u00e9ligny 5",
    "sg:city":"Crans-pr\u00e8s-c\u00e9ligny",
    "sg:orig_category":"Innendekorationsateliers",
    "sg:phone":"+41 22 776 90 35",
    "sg:postcode":"1299",
    "sg:province":"Vaud",
    "wof:name":"G. Spicher & C. Fekrane D\u00e9coration D'int\u00e9rieur",
    "wof:placetype":"venue"
},
  "geometry": {"coordinates":[6.203289032,46.3566932678],"type":"Point"}
}