{
  "type": "Feature",
  "properties": {
    "addr:full":"8594 G\u00fcttingen Thurgau 8594",
    "addr:housenumber":"8594",
    "addr:postcode":"8594",
    "addr:street":"Guettingen Thurgau",
    "iso:country":"CH",
    "sg:address":"8594",
    "sg:city":"G\u00fcttingen",
    "sg:classifiers":[
        {
            "category":"Education",
            "subcategory":"Library",
            "type":"Public Place"
        }
    ],
    "sg:postcode":"8594",
    "sg:province":"Thurgau",
    "sg:tags":[
        "u",
        "bibliotheken",
        "archive"
    ],
    "wof:name":"Jugendbibliothek Des Katholischen Pfarramtes",
    "wof:placetype":"venue"
},
  "geometry": {"coordinates":[9.288002,47.603771],"type":"Point"}
}