{
  "type": "Feature",
  "properties": {
    "iso:country":"CH",
    "sg:address":"Paradiesstrasse 28",
    "sg:city":"Rorschacherberg",
    "sg:classifiers":[
        {
            "category":"Restaurant",
            "type":"Food & Drink"
        }
    ],
    "sg:phone":"+41 71 755 13 64",
    "sg:postcode":"9404",
    "sg:province":"St. Gallen",
    "wof:name":"Restaurant Paradies",
    "wof:placetype":"venue"
},
  "geometry": {"coordinates":[9.5440635681,47.3791313171],"type":"Point"}
}