{
  "type": "Feature",
  "properties": {
    "iso:country":"CH",
    "sg:address":"Rue De L'ancienne-poste 4",
    "sg:city":"Yverdon-les-bains",
    "sg:orig_category":"Zahnkliniken",
    "sg:phone":"+41 24 423 64 00",
    "sg:postcode":"1400",
    "sg:province":"Vaud",
    "wof:name":"Clinique Dentaire Scolaire",
    "wof:placetype":"venue"
},
  "geometry": {"coordinates":[6.6390161514,46.7801094055],"type":"Point"}
}