{
  "type": "Feature",
  "properties": {
    "iso:country":"CH",
    "sg:address":"Sagi 6 3324 Hindelbank. Postfach 4",
    "sg:city":"Hindelbank",
    "sg:orig_category":"Handelsvermittlung U Grosshandel Sonstiger Grosshandel",
    "sg:phone":"+41 34 411 44 44",
    "sg:postcode":"3324",
    "sg:province":"Bern",
    "wof:name":"Pelisago Gmbh",
    "wof:placetype":"venue"
},
  "geometry": {"coordinates":[7.5496468544,47.036239624],"type":"Point"}
}