{
  "type": "Feature",
  "properties": {
    "iso:country":"CH",
    "sg:address":"Klybeckstrasse 79",
    "sg:city":"Basel",
    "sg:orig_category":"Detailhandel mit fotografischen Artikeln Fotografische Ateliers",
    "sg:phone":"+41 61 693 04 00",
    "sg:postcode":"4057",
    "sg:province":"Basel-Stadt",
    "wof:name":"Foto Dilek",
    "wof:placetype":"venue"
},
  "geometry": {"coordinates":[7.5902628899,47.5682449341],"type":"Point"}
}