{
  "type": "Feature",
  "properties": {
    "iso:country":"CH",
    "sg:address":"Couvaloup Rue De 19",
    "sg:city":"St-prex",
    "sg:orig_category":"Stukkateurgewerbe, Gipserei U Verputzerei",
    "sg:phone":"+41 21 806 28 97",
    "sg:postcode":"1162",
    "sg:province":"Vaud",
    "wof:name":"Sauteur Daniel",
    "wof:placetype":"venue"
},
  "geometry": {"coordinates":[6.4583158493,46.479095459],"type":"Point"}
}