{
  "type": "Feature",
  "properties": {
    "iso:country":"CH",
    "sg:address":"Schiffm\u00fchle 4",
    "sg:city":"Untersiggenthal",
    "sg:orig_category":"Zimmerei, Dachdeckerei, Bauspenglerei U Abdichtung",
    "sg:phone":"+41 56 223 23 51",
    "sg:postcode":"5417",
    "sg:province":"Aargau",
    "wof:name":"K\u00fcng + Partner Ag",
    "wof:placetype":"venue"
},
  "geometry": {"coordinates":[8.2642412186,47.4898414612],"type":"Point"}
}