{
  "type": "Feature",
  "properties": {
    "iso:country":"CH",
    "sg:address":"Forchstrasse 317",
    "sg:city":"Z\u00fcrich",
    "sg:orig_category":"Non-Classified Establishments",
    "sg:postcode":"8008",
    "sg:province":"Z\u00fcrich",
    "wof:name":"Movie World Videothek, Maccio",
    "wof:placetype":"venue"
},
  "geometry": {"coordinates":[8.2710981369,47.3501052856],"type":"Point"}
}