{
  "type": "Feature",
  "properties": {
    "addr:full":"Elfenauweg 51 - Bern Bern 3006",
    "addr:housenumber":"51",
    "addr:postcode":"3006",
    "addr:street":"Elfenauweg",
    "iso:country":"CH",
    "sg:address":"Elfenauweg 51 -",
    "sg:city":"Bern",
    "sg:classifiers":[
        {
            "category":"Professional",
            "subcategory":"Art Services",
            "type":"Services"
        }
    ],
    "sg:phone":"+41 31 352 09 83",
    "sg:postcode":"3006",
    "sg:province":"Bern",
    "sg:tags":[
        "export-import"
    ],
    "wof:name":"Indonesia Embassy",
    "wof:placetype":"venue"
},
  "geometry": {"coordinates":[7.465679,46.936882],"type":"Point"}
}