{
  "type": "Feature",
  "properties": {
    "iso:country":"CH",
    "sg:address":"Fontaines Route De 3",
    "sg:city":"Boudevilliers",
    "sg:classifiers":[
        {
            "category":"Travel",
            "subcategory":"Hotels & Motels",
            "type":"Entertainment"
        }
    ],
    "sg:phone":"+41 32 857 24 62",
    "sg:postcode":"2043",
    "sg:province":"Neuch\u00e2tel",
    "sg:tags":[
        "hotels",
        "mit",
        "restaurant"
    ],
    "wof:name":"Jost, S\u00e9jours Et Loisirs",
    "wof:placetype":"venue"
},
  "geometry": {"coordinates":[6.8900518417,47.0297737122],"type":"Point"}
}