{
  "type": "Feature",
  "properties": {
    "addr:full":"Rue De Saint-jean 58 Gen\u00e8ve Gen\u00e8ve 1203",
    "addr:housenumber":"58",
    "addr:postcode":"1203",
    "addr:street":"Rue De Saint-Jean",
    "iso:country":"CH",
    "sg:address":"Rue De Saint-jean 58",
    "sg:city":"Gen\u00e8ve",
    "sg:classifiers":[
        {
            "category":"Bars & Pubs",
            "type":"Food & Drink"
        }
    ],
    "sg:phone":"+41 22 340 44 60",
    "sg:postcode":"1203",
    "sg:province":"Gen\u00e8ve",
    "wof:name":"Jasper Bar",
    "wof:placetype":"venue"
},
  "geometry": {"coordinates":[6.132445,46.205273],"type":"Point"}
}