{
  "type": "Feature",
  "properties": {
    "iso:country":"CH",
    "sg:address":"Rundbuckstrasse 6",
    "sg:city":"Neuhausen",
    "sg:orig_category":"Sonstiger Grosshandel",
    "sg:phone":"+41 52 675 59 27",
    "sg:postcode":"8212",
    "sg:province":"Schaffhausen",
    "wof:name":"Bothli-trade Ag",
    "wof:placetype":"venue"
},
  "geometry": {"coordinates":[8.6040248871,47.6752586365],"type":"Point"}
}