{
  "type": "Feature",
  "properties": {
    "iso:country":"CH",
    "sg:address":"Alte Lyss-strasse 12 3270 Aarberg. Postfach",
    "sg:city":"Aarberg",
    "sg:orig_category":"Handel mit Motorr\u00e4dern, Teilen U Zubeh\u00f6r Instandhaltung U Reparatur von Motorr\u00e4dern",
    "sg:phone":"+41 32 373 11 71",
    "sg:postcode":"3270",
    "sg:province":"Bern",
    "wof:name":"M\u00f6schler Franz",
    "wof:placetype":"venue"
},
  "geometry": {"coordinates":[7.2803530693,47.1241836548],"type":"Point"}
}