{
  "type": "Feature",
  "properties": {
    "iso:country":"CH",
    "sg:address":"Kornhausplatz 19",
    "sg:city":"Bern",
    "sg:classifiers":[
        {
            "category":"Restaurant",
            "type":"Food & Drink"
        }
    ],
    "sg:phone":"+41 31 311 25 40",
    "sg:postcode":"3011",
    "sg:province":"Bern",
    "wof:name":"Restaurant Ringgenberg",
    "wof:placetype":"venue"
},
  "geometry": {"coordinates":[7.447783947,46.9487838745],"type":"Point"}
}