{
  "type": "Feature",
  "properties": {
    "iso:country":"CH",
    "sg:address":"Rengglochstrasse 38 6012 Obernau. Postfach 3059",
    "sg:city":"Luzern",
    "sg:orig_category":"Chemische Industrie Herstellung von sonstigen Maschinen f\u00fcr unspezifische Verwendung",
    "sg:phone":"+41 32 910 03 03",
    "sg:postcode":"6006",
    "sg:province":"Luzern",
    "wof:name":"C.m.t. Rickenbach Sa",
    "wof:placetype":"venue"
},
  "geometry": {"coordinates":[6.835043,47.094803],"type":"Point"}
}