{
  "type": "Feature",
  "properties": {
    "iso:country":"CH",
    "sg:address":"Hauptstrasse 8",
    "sg:city":"Lommiswil",
    "sg:orig_category":"Mechanische Werkst\u00e4tten",
    "sg:phone":"+41 32 641 18 73",
    "sg:postcode":"4514",
    "sg:province":"Solothurn",
    "wof:name":"Hermann Schaue Mechanische Werkstatt",
    "wof:placetype":"venue"
},
  "geometry": {"coordinates":[7.4713439941,47.2224082947],"type":"Point"}
}