{
  "type": "Feature",
  "properties": {
    "iso:country":"CH",
    "sg:address":"Via Stazione 5",
    "sg:city":"Muralto",
    "sg:orig_category":"Sportvereine Wassersport Rudern",
    "sg:postcode":"6600",
    "sg:province":"Ticino",
    "wof:name":"Societ\u00e0 Canottieri Locarno",
    "wof:placetype":"venue"
},
  "geometry": {"coordinates":[8.8009414673,46.1722640991],"type":"Point"}
}