{
  "type": "Feature",
  "properties": {
    "iso:country":"CH",
    "sg:address":"Rennweg 26",
    "sg:city":"Mettmenstetten",
    "sg:orig_category":"Markt U Meinungsforschung",
    "sg:phone":"+41 17682011",
    "sg:postcode":"8932",
    "sg:province":"Z\u00fcrich",
    "wof:name":"Pmv Ag Pressemedien Verkaufsf\u00f6rderung",
    "wof:placetype":"venue"
},
  "geometry": {"coordinates":[8.4666671753,47.2472724915],"type":"Point"}
}