{
  "type": "Feature",
  "properties": {
    "iso:country":"CH",
    "sg:address":"Hauptstrasse 38",
    "sg:city":"Flaach",
    "sg:classifiers":[
        {
            "category":"Insurance",
            "subcategory":"Insurance Agent",
            "type":"Services"
        }
    ],
    "sg:phone":"+41 52 318 10 20",
    "sg:postcode":"8416",
    "sg:province":"Z\u00fcrich",
    "sg:tags":[
        "versicherungsagenturen",
        "-broker"
    ],
    "wof:name":"Winterthur-versicherungen Agentur",
    "wof:placetype":"venue"
},
  "geometry": {"coordinates":[8.6040353775,47.5747108459],"type":"Point"}
}