{
  "type": "Feature",
  "properties": {
    "iso:country":"CH",
    "sg:address":"Gfennstrasse 11 B",
    "sg:city":"D\u00fcbendorf",
    "sg:orig_category":"Sonstiger spezialisierter Hoch U Tiefbau",
    "sg:postcode":"8600",
    "sg:province":"Z\u00fcrich",
    "wof:name":"Societ\u00e0 Cooperativa D'irrigazione Trembellina",
    "wof:placetype":"venue"
},
  "geometry": {"coordinates":[8.8010902405,46.3217811584],"type":"Point"}
}