{
  "type": "Feature",
  "properties": {
    "iso:country":"CH",
    "sg:address":"Routedmoncor 10",
    "sg:city":"Bellach",
    "sg:classifiers":[
        {
            "category":"Professional",
            "subcategory":"Employment Agencies",
            "type":"Services"
        }
    ],
    "sg:phone":"+41 31 990 88 00",
    "sg:postcode":"4512",
    "sg:province":"Solothurn",
    "sg:tags":[
        "drug",
        "cabinet"
    ],
    "wof:name":"Democal Ag",
    "wof:placetype":"venue"
},
  "geometry": {"coordinates":[7.4991607666,47.2127151489],"type":"Point"}
}