{
  "type": "Feature",
  "properties": {
    "iso:country":"CH",
    "sg:address":"Thungschneitweg 51 3627 Heimberg. Postfach",
    "sg:city":"Heimberg",
    "sg:orig_category":"G\u00fcterbef\u00f6rderung im Strassenverkehr",
    "sg:phone":"+41 33 437 56 12",
    "sg:postcode":"3627",
    "sg:province":"Bern",
    "wof:name":"Reber Beat Transporte",
    "wof:placetype":"venue"
},
  "geometry": {"coordinates":[7.5897908211,46.7963867188],"type":"Point"}
}