{
  "type": "Feature",
  "properties": {
    "iso:country":"CH",
    "sg:address":"Terrassenweg 3818 Grindelwald. Postfach 32",
    "sg:city":"Grindelwald",
    "sg:classifiers":[
        {
            "category":"Travel",
            "subcategory":"Hotels & Motels",
            "type":"Entertainment"
        }
    ],
    "sg:phone":"+41 33 853 12 20",
    "sg:postcode":"3818",
    "sg:province":"Bern",
    "sg:tags":[
        "hotels",
        "mit",
        "restaurant"
    ],
    "wof:name":"Hotel-restaurant Bodmi, Kaufmann Elisabeth",
    "wof:placetype":"venue"
},
  "geometry": {"coordinates":[8.0461292267,46.6298942566],"type":"Point"}
}