{
  "type": "Feature",
  "properties": {
    "iso:country":"CH",
    "sg:address":"Gh\u00fcrststrasse",
    "sg:city":"Oberuzwil",
    "sg:orig_category":"Schwimmb\u00e4der",
    "sg:phone":"+41 71 951 67 57",
    "sg:postcode":"9242",
    "sg:province":"St. Gallen",
    "wof:name":"Schwimmbad Oberuzwil",
    "wof:placetype":"venue"
},
  "geometry": {"coordinates":[9.1222352982,47.4292449951],"type":"Point"}
}