{
  "type": "Feature",
  "properties": {
    "iso:country":"CH",
    "sg:address":"Hauptstrasse 41 9400 Rorschach. Postfach 344",
    "sg:city":"Rorschach",
    "sg:orig_category":"Elektroinstallation Herstellung von Radio U Fernsehger\u00e4ten sowie phono U videotechnischen Ger\u00e4ten",
    "sg:phone":"+41 71 841 32 15",
    "sg:postcode":"9401",
    "sg:province":"St. Gallen",
    "wof:name":"Eisenring-unterhaltungselektronik Ag",
    "wof:placetype":"venue"
},
  "geometry": {"coordinates":[9.4941062927,47.478061676],"type":"Point"}
}