{
  "type": "Feature",
  "properties": {
    "iso:country":"CH",
    "sg:address":"Zelg",
    "sg:city":"Mamishaus",
    "sg:orig_category":"Zimmerei, Dachdeckerei, Bauspenglerei U Abdichtung",
    "sg:phone":"+41 31 731 31 11",
    "sg:postcode":"3152",
    "sg:province":"Bern",
    "wof:name":"Gh Holzbau Ag",
    "wof:placetype":"venue"
},
  "geometry": {"coordinates":[7.3641462326,46.8205718994],"type":"Point"}
}