{
  "type": "Feature",
  "properties": {
    "iso:country":"CH",
    "sg:address":"Grenzweg 903",
    "sg:city":"Gontenschwil",
    "sg:orig_category":"Maler U Glasergewerbe Malerei",
    "sg:phone":"+41 62 773 16 83",
    "sg:postcode":"5728",
    "sg:province":"Aargau",
    "wof:name":"Rudolf Maurer Ag Gontenschwil",
    "wof:placetype":"venue"
},
  "geometry": {"coordinates":[8.1455516815,47.2747306824],"type":"Point"}
}