{
  "type": "Feature",
  "properties": {
    "iso:country":"CH",
    "sg:address":"1261",
    "sg:city":"Burtigny",
    "sg:orig_category":"Herstellung von Schl\u00f6ssern U Beschl\u00e4gen",
    "sg:phone":"+41 56 493 08 00",
    "sg:postcode":"1261",
    "sg:province":"Vaud",
    "wof:name":"Alltop Enzo Pilla T\u00fcrschloss Service",
    "wof:placetype":"venue"
},
  "geometry": {"coordinates":[8.2878856659,47.4522247314],"type":"Point"}
}