{
  "type": "Feature",
  "properties": {
    "iso:country":"CH",
    "sg:address":"Chemin Des Croix-rouges 18",
    "sg:city":"Lausanne",
    "sg:orig_category":"Wirtschaftspr\u00fcfung, Steuerberatung U Treuhand",
    "sg:phone":"+41 55 240 44 22",
    "sg:postcode":"1007",
    "sg:province":"Vaud",
    "wof:name":"P\u00fcnter & Berndt Treuhand Ag",
    "wof:placetype":"venue"
},
  "geometry": {"coordinates":[8.8521413803,47.2596893311],"type":"Point"}
}