{
  "type": "Feature",
  "properties": {
    "iso:country":"CH",
    "sg:address":"Chez Les Mellets",
    "sg:city":"Montpreveyres",
    "sg:orig_category":"Detektivb\u00fcros U \u00dcberwachung Sicherheitsdienste",
    "sg:phone":"+41 21 903 06 06",
    "sg:postcode":"1081",
    "sg:province":"Vaud",
    "wof:name":"Lynx Securite Sa",
    "wof:placetype":"venue"
},
  "geometry": {"coordinates":[6.7422800064,46.5822410583],"type":"Point"}
}