{
  "type": "Feature",
  "properties": {
    "iso:country":"CH",
    "sg:address":"Chemin De Tourelle 2",
    "sg:city":"Gen\u00e8ve",
    "sg:orig_category":"Kosmetikinstitute",
    "sg:phone":"+41 22 798 44 41",
    "sg:postcode":"1209",
    "sg:province":"Gen\u00e8ve",
    "wof:name":"Dominic Mantesch Coiffure & Beaut\u00e9 Dim",
    "wof:placetype":"venue"
},
  "geometry": {"coordinates":[6.1261291504,46.2242355347],"type":"Point"}
}