{
  "type": "Feature",
  "properties": {
    "iso:country":"CH",
    "sg:address":"Lido Via 49",
    "sg:city":"Ascona",
    "sg:orig_category":"Grosshandel mit sonstigen Gebrauchs U Verbrauchsg\u00fctern",
    "sg:phone":"+41 14636680",
    "sg:postcode":"6612",
    "sg:province":"Ticino",
    "wof:name":"Pubblisystem Di Matozzo",
    "wof:placetype":"venue"
},
  "geometry": {"coordinates":[8.7698612213,46.1564369202],"type":"Point"}
}