{
  "type": "Feature",
  "properties": {
    "iso:country":"CH",
    "sg:address":"Schulstrasse 54",
    "sg:city":"Landquart",
    "sg:orig_category":"Detailhandel mit Milcherzeugnissen U Eiern Grosshandel mit Nahrungsmitteln, Getr\u00e4nken U Tabakwaren o",
    "sg:phone":"+41 81 322 22 80",
    "sg:postcode":"7302",
    "sg:province":"Graubunden",
    "wof:name":"Jakob Ryser Ch\u00e4s-harfe Ried",
    "wof:placetype":"venue"
},
  "geometry": {"coordinates":[9.5600748062,46.9613952637],"type":"Point"}
}