{
  "type": "Feature",
  "properties": {
    "iso:country":"CH",
    "sg:address":"Neum\u00fchlequai 10",
    "sg:city":"Z\u00fcrich",
    "sg:orig_category":"Verwaltung der Volkswirtschaft",
    "sg:phone":"+41 12591111",
    "sg:postcode":"8090",
    "sg:province":"Z\u00fcrich",
    "wof:name":"Direktion Der Volkswirtschaft Des Kantons Z\u00fcrich",
    "wof:placetype":"venue"
},
  "geometry": {"coordinates":[8.5429525375,47.3783302307],"type":"Point"}
}