{
  "type": "Feature",
  "properties": {
    "addr:full":"Rietlirain 43 8713 Uerikon. Postfach Uerikon Z\u00fcrich 8713",
    "addr:housenumber":"43",
    "addr:postcode":"8713;postfach;8713",
    "addr:street":"Rietlirain",
    "iso:country":"CH",
    "sg:address":"Rietlirain 43 8713 Uerikon. Postfach",
    "sg:city":"Uerikon",
    "sg:orig_category":"Allgemeiner Hoch U Tiefbau Bauingenieurb\u00fcros Hochbau",
    "sg:phone":"+41 19264703",
    "sg:postcode":"8713",
    "sg:province":"Z\u00fcrich",
    "wof:name":"Bergmann Heinz Gmbh Tiefbau; Bauleitungen. Strassen, Kanalisationen Usw.; Verwaltung, Unterhalt",
    "wof:placetype":"venue"
},
  "geometry": {"coordinates":[8.748362,47.235439],"type":"Point"}
}