{
  "type": "Feature",
  "properties": {
    "iso:country":"CH",
    "sg:address":"Bahnhofstrasse 14-16",
    "sg:city":"Glarus",
    "sg:orig_category":"Sonstiges Versicherungsgewerbe",
    "sg:phone":"+41 55 640 44 42",
    "sg:postcode":"8750",
    "sg:province":"Glarus",
    "wof:name":"Jakob Tr\u00fcmpi",
    "wof:placetype":"venue"
},
  "geometry": {"coordinates":[9.0689096451,47.0398597717],"type":"Point"}
}