{
  "type": "Feature",
  "properties": {
    "iso:country":"CH",
    "sg:address":"Furrenstrasse 15",
    "sg:city":"Unter\u00e4geri",
    "sg:orig_category":"Sonstige mit der Informatik verbundene T\u00e4tigkeiten",
    "sg:phone":"+41 41 750 39 60",
    "sg:postcode":"6314",
    "sg:province":"Zug",
    "wof:name":"Impa Consulting Gmbh",
    "wof:placetype":"venue"
},
  "geometry": {"coordinates":[8.5705966949,47.139125824],"type":"Point"}
}