{
  "type": "Feature",
  "properties": {
    "iso:country":"CH",
    "sg:address":"Vignettes Chemin Des 16",
    "sg:city":"Crans-pr\u00e8s-c\u00e9ligny",
    "sg:orig_category":"Technische, physikalische U chemische Untersuchung",
    "sg:phone":"+41 22 776 55 17",
    "sg:postcode":"1299",
    "sg:province":"Vaud",
    "wof:name":"Ageox Consultants, Dasen Erwin",
    "wof:placetype":"venue"
},
  "geometry": {"coordinates":[6.2061100006,46.3593864441],"type":"Point"}
}