{
  "type": "Feature",
  "properties": {
    "iso:country":"CH",
    "sg:address":"Kreuzstrasse 54",
    "sg:city":"Z\u00fcrich",
    "sg:orig_category":"Handels-H\u00e4user U Gesellschaften",
    "sg:postcode":"8008",
    "sg:province":"Z\u00fcrich",
    "wof:name":"Coes Vertriebs Ag",
    "wof:placetype":"venue"
},
  "geometry": {"coordinates":[8.5520362854,47.3641777039],"type":"Point"}
}