{
  "type": "Feature",
  "properties": {
    "iso:country":"CH",
    "sg:address":"Via San Gottardo 37",
    "sg:city":"Lugano",
    "sg:orig_category":"Architektur U Ingenieurb\u00fcros",
    "sg:postcode":"6900",
    "sg:province":"Ticino",
    "wof:name":"U.c.t. Ufficio Consulenze Tecniche Sa",
    "wof:placetype":"venue"
},
  "geometry": {"coordinates":[8.946473,46.008308],"type":"Point"}
}