{
  "type": "Feature",
  "properties": {
    "iso:country":"CH",
    "sg:address":"Blancherie Rue De La 35",
    "sg:city":"Sion",
    "sg:orig_category":"Vermietung U Verpachtung von eigenen Immobilien",
    "sg:phone":"+41 27 322 50 92",
    "sg:postcode":"1950",
    "sg:province":"Valais",
    "wof:name":"Archi Concept Sa",
    "wof:placetype":"venue"
},
  "geometry": {"coordinates":[7.3551220894,46.2261581421],"type":"Point"}
}