{
  "type": "Feature",
  "properties": {
    "iso:country":"CH",
    "sg:address":"Th\u00e9\u00e2tre Rue Du 3",
    "sg:city":"Montreux",
    "sg:orig_category":"Non-Classified Establishments",
    "sg:postcode":"1820",
    "sg:province":"Vaud",
    "wof:name":"Si M\u00e9zi\u00e8res Transports Sa",
    "wof:placetype":"venue"
},
  "geometry": {"coordinates":[6.7640500069,46.5876998901],"type":"Point"}
}