{
  "type": "Feature",
  "properties": {
    "iso:country":"CH",
    "sg:address":"Ferdinand Hodler-strasse 8",
    "sg:city":"Z\u00fcrich",
    "sg:orig_category":"Erwachsenenbildung U Unterricht",
    "sg:phone":"+41 13411166",
    "sg:postcode":"8049",
    "sg:province":"Z\u00fcrich",
    "wof:name":"Telegenia Ag",
    "wof:placetype":"venue"
},
  "geometry": {"coordinates":[8.501955986,47.4037513733],"type":"Point"}
}