{
  "type": "Feature",
  "properties": {
    "iso:country":"CH",
    "sg:address":"Rue De La Gare 7",
    "sg:city":"Bevaix",
    "sg:orig_category":"Geb\u00e4ude, Wohnungsreinigung Reinigungsgewerbe",
    "sg:phone":"+41 32 846 10 11",
    "sg:postcode":"2022",
    "sg:province":"Neuch\u00e2tel",
    "wof:name":"Nikel, Pereira Fontes",
    "wof:placetype":"venue"
},
  "geometry": {"coordinates":[6.8141469955,46.9300842285],"type":"Point"}
}