{
  "type": "Feature",
  "properties": {
    "iso:country":"CH",
    "sg:address":"Rue De La Gare 6",
    "sg:city":"Morges",
    "sg:orig_category":"Kunsthandel Museen",
    "sg:phone":"+41 21 801 67 31",
    "sg:postcode":"1110",
    "sg:province":"Vaud",
    "wof:name":"Galerie Pro-arte I. Kaspar",
    "wof:placetype":"venue"
},
  "geometry": {"coordinates":[6.4964442253,46.5083961487],"type":"Point"}
}