{
  "type": "Feature",
  "properties": {
    "iso:country":"CH",
    "sg:address":"Luzernerstrasse 40",
    "sg:city":"Oftringen",
    "sg:orig_category":"Instandhaltung U Reparatur von Automobilen",
    "sg:phone":"+41 62 797 20 20",
    "sg:postcode":"4665",
    "sg:province":"Aargau",
    "wof:name":"Gerhard Staub",
    "wof:placetype":"venue"
},
  "geometry": {"coordinates":[7.9239058495,47.310092926],"type":"Point"}
}