{
  "type": "Feature",
  "properties": {
    "iso:country":"CH",
    "sg:address":"6015 Reussb\u00fchl. Postfach 915",
    "sg:city":"Reussb\u00fchl",
    "sg:orig_category":"Sportvereine Ballsport Basketball Vereine Damen",
    "sg:phone":"+41 79 428 91 91",
    "sg:postcode":"6015",
    "sg:province":"Luzern",
    "wof:name":"Femina Basket Reussb\u00fchl",
    "wof:placetype":"venue"
},
  "geometry": {"coordinates":[8.2813596725,47.0650215149],"type":"Point"}
}