{
  "type": "Feature",
  "properties": {
    "iso:country":"CH",
    "sg:address":"Grand-rue 6",
    "sg:city":"Reconvilier",
    "sg:orig_category":"Leichtmetallgiesserei",
    "sg:phone":"+41 32 481 13 31",
    "sg:postcode":"2732",
    "sg:province":"Bern",
    "wof:name":"Swissmetal - Ums Usines M\u00e9tallurgiques Suisses Sa",
    "wof:placetype":"venue"
},
  "geometry": {"coordinates":[7.2228932381,47.2338562012],"type":"Point"}
}