{
  "type": "Feature",
  "properties": {
    "iso:country":"CH",
    "sg:address":"Dorfstrasse",
    "sg:city":"Adelboden",
    "sg:orig_category":"Herstellung von sonstigen elektrischen Ausr\u00fcstungen",
    "sg:postcode":"3715",
    "sg:province":"Bern",
    "wof:name":"Stucki Ag",
    "wof:placetype":"venue"
},
  "geometry": {"coordinates":[7.5596499443,46.4931602478],"type":"Point"}
}