{
  "type": "Feature",
  "properties": {
    "iso:country":"CH",
    "sg:address":"Lerzenstrasse 16",
    "sg:city":"Dietikon",
    "sg:orig_category":"Herstellung von optischen Instrumenten Optische Ger\u00e4te Grosshandel",
    "sg:postcode":"8953",
    "sg:province":"Z\u00fcrich",
    "wof:name":"Prose Messtechnik Gmbh",
    "wof:placetype":"venue"
},
  "geometry": {"coordinates":[8.2664804459,47.3609809875],"type":"Point"}
}