{
  "type": "Feature",
  "properties": {
    "iso:country":"CH",
    "sg:address":"Liebr\u00fctistrasse 39",
    "sg:city":"Kaiseraugst",
    "sg:orig_category":"Detailhandel mit Waren verschiedener Art, Hauptrichtung Nahrungsmittel",
    "sg:phone":"+41 61 811 28 28",
    "sg:postcode":"4303",
    "sg:province":"Aargau",
    "wof:name":"Migros-markt",
    "wof:placetype":"venue"
},
  "geometry": {"coordinates":[7.7305221558,47.53515625],"type":"Point"}
}