{
  "type": "Feature",
  "properties": {
    "iso:country":"CH",
    "sg:address":"Hauptstrasse 33",
    "sg:city":"Brunegg",
    "sg:orig_category":"Mit Sport verbundene T\u00e4tigkeiten",
    "sg:phone":"+41 62 896 25 40",
    "sg:postcode":"5505",
    "sg:province":"Aargau",
    "wof:name":"Willy Bosshart Reit-& Ausbildungsstall",
    "wof:placetype":"venue"
},
  "geometry": {"coordinates":[8.2172641754,47.4193763733],"type":"Point"}
}