{
  "type": "Feature",
  "properties": {
    "iso:country":"CH",
    "sg:address":"Hinterdorfstrasse 29",
    "sg:city":"Winterthur",
    "sg:orig_category":"Allgemeiner Hochbau Strassenbau",
    "sg:phone":"+41 52 232 27 69",
    "sg:postcode":"8405",
    "sg:province":"Z\u00fcrich",
    "wof:name":"Jakob Frei Hoch-& Tiefbau",
    "wof:placetype":"venue"
},
  "geometry": {"coordinates":[8.761874,47.485882],"type":"Point"}
}