{
  "type": "Feature",
  "properties": {
    "iso:country":"CH",
    "sg:address":"Winzerstrasse 11",
    "sg:city":"Z\u00fcrich",
    "sg:orig_category":"Instandhaltung U Reparatur von Automobilen",
    "sg:phone":"+41 13420204",
    "sg:postcode":"8049",
    "sg:province":"Z\u00fcrich",
    "wof:name":"Garage Matthys Lastwagen, Baumaschinen Usw; Reparatur. Waren, Treibstoffhandel",
    "wof:placetype":"venue"
},
  "geometry": {"coordinates":[8.4934005737,47.400302887],"type":"Point"}
}