{
  "type": "Feature",
  "properties": {
    "iso:country":"CH",
    "sg:address":"Simplon Rue Du 150",
    "sg:city":"Martigny",
    "sg:orig_category":"Tankstellen",
    "sg:postcode":"1920",
    "sg:province":"Valais",
    "wof:name":"Ancay A. S\u00e0rl",
    "wof:placetype":"venue"
},
  "geometry": {"coordinates":[7.0902328491,46.108543396],"type":"Point"}
}