{
  "type": "Feature",
  "properties": {
    "iso:country":"CH",
    "sg:address":"Via Peri 2a",
    "sg:city":"Lugano",
    "sg:orig_category":"Detailhandel mit Parf\u00fcmerieartikeln U K\u00f6rperpflegemitteln Parf\u00fcmerien U sonstiger Detailhandel mit k",
    "sg:phone":"+41 91 922 04 53",
    "sg:postcode":"6900",
    "sg:province":"Ticino",
    "wof:name":"Profumeria Kyphi Angela Fusi",
    "wof:placetype":"venue"
},
  "geometry": {"coordinates":[8.9508810043,46.0053215027],"type":"Point"}
}