{
  "type": "Feature",
  "properties": {
    "iso:country":"CH",
    "sg:address":"Kirchweg 683",
    "sg:city":"Volketswil",
    "sg:orig_category":"Non-Classified Establishments",
    "sg:postcode":"8604",
    "sg:province":"Z\u00fcrich",
    "wof:name":"Eggi Design Ag",
    "wof:placetype":"venue"
},
  "geometry": {"coordinates":[8.6909046173,47.3876953125],"type":"Point"}
}