{
  "type": "Feature",
  "properties": {
    "iso:country":"CH",
    "sg:address":"Gundeldingerstrasse 432",
    "sg:city":"Basel",
    "sg:orig_category":"Softwareentwicklung U beratung",
    "sg:phone":"+41 61 337 46 11",
    "sg:postcode":"4053",
    "sg:province":"Basel-Stadt",
    "wof:name":"F\u00f6ry Consulting Ag",
    "wof:placetype":"venue"
},
  "geometry": {"coordinates":[7.6000418663,47.5378723145],"type":"Point"}
}