{
  "type": "Feature",
  "properties": {
    "iso:country":"CH",
    "sg:address":"Zofingerstrasse 30",
    "sg:city":"Strengelbach",
    "sg:orig_category":"Handel mit Automobilen Tankstellen",
    "sg:phone":"+41 62 745 30 10",
    "sg:postcode":"4802",
    "sg:province":"Aargau",
    "wof:name":"Auto Meier Ag Strengelbach",
    "wof:placetype":"venue"
},
  "geometry": {"coordinates":[7.9340901375,47.281036377],"type":"Point"}
}