{
  "type": "Feature",
  "properties": {
    "iso:country":"CH",
    "sg:address":"Alpenstrasse 4",
    "sg:city":"Zug",
    "sg:orig_category":"Hochschulen U h\u00f6here Ausbildung",
    "sg:phone":"+41 41 710 13 11",
    "sg:postcode":"6300",
    "sg:province":"Zug",
    "wof:name":"Iwag Institut F\u00fcr Aus-& Weiterbildung Zug Ag",
    "wof:placetype":"venue"
},
  "geometry": {"coordinates":[8.5139045715,47.1710357666],"type":"Point"}
}