{
  "type": "Feature",
  "properties": {
    "iso:country":"CH",
    "sg:address":"Hochschorenstrasse 6",
    "sg:city":"Herisau",
    "sg:orig_category":"Abwasserreinigung, Abfallbeseitigung U sonstige Entsorgung",
    "sg:postcode":"9100",
    "sg:province":"Appenzell Ausserrhoden",
    "wof:name":"Kanal-frisch Kanalreinigung, Frischknecht O.",
    "wof:placetype":"venue"
},
  "geometry": {"coordinates":[9.27817,47.385101],"type":"Point"}
}