{
  "type": "Feature",
  "properties": {
    "iso:country":"CH",
    "sg:address":"Tannholzstrasse 20",
    "sg:city":"Watt",
    "sg:orig_category":"Non-Classified Establishments",
    "sg:postcode":"8105",
    "sg:province":"Z\u00fcrich",
    "wof:name":"Oekoplan Architekten Gmbh",
    "wof:placetype":"venue"
},
  "geometry": {"coordinates":[8.4794960022,47.4392318726],"type":"Point"}
}