{
  "type": "Feature",
  "properties": {
    "iso:country":"CH",
    "sg:address":"Martin Disteli-strasse 26 4600 Olten. Postfach",
    "sg:city":"Olten",
    "sg:orig_category":"Grosshandel mit Obst U Gem\u00fcse",
    "sg:phone":"+41 62 296 61 26",
    "sg:postcode":"4601",
    "sg:province":"Solothurn",
    "wof:name":"Nieder\u00f6st-ringold & Sohn Getreide & Landesprodukte",
    "wof:placetype":"venue"
},
  "geometry": {"coordinates":[7.9102468491,47.3510475159],"type":"Point"}
}