{
  "type": "Feature",
  "properties": {
    "iso:country":"CH",
    "sg:address":"Sihlmatten 14",
    "sg:city":"Adliswil",
    "sg:orig_category":"G\u00fcterbef\u00f6rderung im Strassenverkehr",
    "sg:phone":"+41 17101320",
    "sg:postcode":"8134",
    "sg:province":"Z\u00fcrich",
    "wof:name":"Johann Ettl Transporte",
    "wof:placetype":"venue"
},
  "geometry": {"coordinates":[8.5301561356,47.301574707],"type":"Point"}
}