{
  "type": "Feature",
  "properties": {
    "iso:country":"CH",
    "sg:address":"Corso San Gottardo 52",
    "sg:city":"Chiasso",
    "sg:orig_category":"Wirtschaftspr\u00fcfung, Steuerberatung U Treuhand",
    "sg:phone":"+41 91 682 08 62",
    "sg:postcode":"6830",
    "sg:province":"Ticino",
    "wof:name":"Ten Consulting Sa",
    "wof:placetype":"venue"
},
  "geometry": {"coordinates":[9.0286865234,45.8349075317],"type":"Point"}
}