{
  "type": "Feature",
  "properties": {
    "iso:country":"CH",
    "sg:address":"Spitalstrasse 25",
    "sg:city":"Schlieren",
    "sg:orig_category":"Non-Classified Establishments",
    "sg:phone":"+41 17304460",
    "sg:postcode":"8952",
    "sg:province":"Z\u00fcrich",
    "wof:name":"Da Rocha U., Fliegende Pfanne",
    "wof:placetype":"venue"
},
  "geometry": {"coordinates":[8.4286117554,47.3925247192],"type":"Point"}
}