{
  "type": "Feature",
  "properties": {
    "iso:country":"CH",
    "sg:address":"Eisenbahnstrasse 2",
    "sg:city":"Einsiedeln",
    "sg:orig_category":"Reparatur von Schuhen U Lederwaren",
    "sg:phone":"+41 55 412 83 93",
    "sg:postcode":"8840",
    "sg:province":"Schwyz",
    "wof:name":"Schuhe & Schl\u00fcsselservice Acat Gebro",
    "wof:placetype":"venue"
},
  "geometry": {"coordinates":[8.7455530167,47.1289024353],"type":"Point"}
}