{
  "type": "Feature",
  "properties": {
    "iso:country":"CH",
    "sg:address":"Dorfstrasse 913 3506 Grossh\u00f6chstetten. Postfach",
    "sg:city":"Grossh\u00f6chstetten",
    "sg:orig_category":"Erzeugung U Erstbearbeitung von Aluminium",
    "sg:phone":"+41 31 711 18 31",
    "sg:postcode":"3506",
    "sg:province":"Bern",
    "wof:name":"Aloxyd Sa Zweigniederlassung Grossh\u00f6chstetten",
    "wof:placetype":"venue"
},
  "geometry": {"coordinates":[7.6437897682,46.9045715332],"type":"Point"}
}