{
  "type": "Feature",
  "properties": {
    "addr:full":"Birmensdorferstrasse 122 Urdorf Z\u00fcrich 8902",
    "addr:housenumber":"122",
    "addr:postcode":"8902",
    "addr:street":"Birmensdorferstrasse",
    "iso:country":"CH",
    "sg:address":"Birmensdorferstrasse 122",
    "sg:city":"Urdorf",
    "sg:orig_category":"Autogaragen",
    "sg:phone":"+41 17343260",
    "sg:postcode":"8902",
    "sg:province":"Z\u00fcrich",
    "wof:name":"Bruno Doll Garage",
    "wof:placetype":"venue"
},
  "geometry": {"coordinates":[8.422695,47.381145],"type":"Point"}
}