{
  "type": "Feature",
  "properties": {
    "iso:country":"CH",
    "sg:address":"Gewerbehaus Dreispitz",
    "sg:city":"Erlen",
    "sg:orig_category":"Werbung",
    "sg:phone":"+41 17147711",
    "sg:postcode":"8586",
    "sg:province":"Thurgau",
    "wof:name":"As Werbung Ag",
    "wof:placetype":"venue"
},
  "geometry": {"coordinates":[8.5360240936,47.2945404053],"type":"Point"}
}