{
  "type": "Feature",
  "properties": {
    "iso:country":"CH",
    "sg:address":"Dorfstrasse 27",
    "sg:city":"Wangenried",
    "sg:orig_category":"Gemeindeverwaltungen",
    "sg:phone":"+41 32 631 14 92",
    "sg:postcode":"3374",
    "sg:province":"Bern",
    "wof:name":"Gemeindeverwaltung Wangenried",
    "wof:placetype":"venue"
},
  "geometry": {"coordinates":[7.6588168144,47.2178878784],"type":"Point"}
}