{
  "type": "Feature",
  "properties": {
    "iso:country":"CH",
    "sg:address":"B\u00e4ckerstrasse 35",
    "sg:city":"Z\u00fcrich",
    "sg:orig_category":"Grosshandel mit sonstigen Gebrauchs U Verbrauchsg\u00fctern",
    "sg:postcode":"8004",
    "sg:province":"Z\u00fcrich",
    "wof:name":"Arms Import-licences, P. H. Kuhn",
    "wof:placetype":"venue"
},
  "geometry": {"coordinates":[8.4616298676,47.4535255432],"type":"Point"}
}