{
  "type": "Feature",
  "properties": {
    "iso:country":"CH",
    "sg:address":"Chemin Champ-du-gour 2",
    "sg:city":"Moudon",
    "sg:orig_category":"Instandhaltung U Reparatur von Automobilen",
    "sg:postcode":"1510",
    "sg:province":"Vaud",
    "wof:name":"Le Car, Ambrosino Roland",
    "wof:placetype":"venue"
},
  "geometry": {"coordinates":[6.7965540886,46.6673927307],"type":"Point"}
}