{
  "type": "Feature",
  "properties": {
    "iso:country":"CH",
    "sg:address":"Viale Papio 5",
    "sg:city":"Ascona",
    "sg:orig_category":"Grosshandel mit Maschinen U Ausr\u00fcstungen Herstellung von sonstigen Maschinen f\u00fcr unspezifische Verwe",
    "sg:phone":"+41 32 342 28 28",
    "sg:postcode":"6612",
    "sg:province":"Ticino",
    "wof:name":"Unirock Sa",
    "wof:placetype":"venue"
},
  "geometry": {"coordinates":[7.2635669708,47.1482048035],"type":"Point"}
}