{
  "type": "Feature",
  "properties": {
    "iso:country":"CH",
    "sg:address":"Beau-s\u00e9jour Rue 15",
    "sg:city":"Lausanne",
    "sg:orig_category":"Finanzierungsinstitutionen",
    "sg:postcode":"1003",
    "sg:province":"Vaud",
    "wof:name":"Fondation Du Denantou",
    "wof:placetype":"venue"
},
  "geometry": {"coordinates":[6.635887146,46.5178909302],"type":"Point"}
}