{
  "type": "Feature",
  "properties": {
    "iso:country":"CH",
    "sg:address":"Kanzleistrasse 9",
    "sg:city":"N\u00fcrensdorf",
    "sg:orig_category":"Bauschreinerei D\u00e4mmung gegen K\u00e4lte, W\u00e4rme, Schall U Ersch\u00fctterung",
    "sg:phone":"+41 18365863",
    "sg:postcode":"8309",
    "sg:province":"Z\u00fcrich",
    "wof:name":"Gebr. Ruoss Mech.schreinerei Isolierungen",
    "wof:placetype":"venue"
},
  "geometry": {"coordinates":[8.647748,47.447994],"type":"Point"}
}