{
  "type": "Feature",
  "properties": {
    "iso:country":"CH",
    "sg:address":"Haus Sunnihubil",
    "sg:city":"Leukerbad",
    "sg:orig_category":"Zimmerei, Dachdeckerei, Bauspenglerei U Abdichtung",
    "sg:postcode":"3954",
    "sg:province":"Valais",
    "wof:name":"Dachdecker-spenglerei, Roten Kurt",
    "wof:placetype":"venue"
},
  "geometry": {"coordinates":[7.6253261566,46.3759307861],"type":"Point"}
}