{
  "type": "Feature",
  "properties": {
    "iso:country":"CH",
    "sg:address":"F\u00e4hrweg 10",
    "sg:city":"Olten",
    "sg:orig_category":"Non-Classified Establishments",
    "sg:phone":"+41 31 309 95 95",
    "sg:postcode":"4600",
    "sg:province":"Solothurn",
    "wof:name":"Dres Med. K. Saurer & C. Ott Spezial\u00e4rztinnen Fmh",
    "wof:placetype":"venue"
},
  "geometry": {"coordinates":[7.4359350204,46.9595756531],"type":"Point"}
}