{
  "type": "Feature",
  "properties": {
    "addr:full":"Via Pioda 12 Casella Postale 2217 Lugano Ticino 6901",
    "addr:housenumber":"12",
    "addr:postcode":"2217;6901",
    "addr:street":"Via Pioda;Postale",
    "iso:country":"CH",
    "sg:address":"Via Pioda 12 Casella Postale 2217",
    "sg:city":"Lugano",
    "sg:classifiers":[
        {
            "category":"Health Services",
            "subcategory":"Medical Lab",
            "type":"Services"
        }
    ],
    "sg:phone":"+41 91 923 98 68",
    "sg:postcode":"6901",
    "sg:province":"Ticino",
    "sg:tags":[
        "chemical",
        "pharmaceutical",
        "pharmacy"
    ],
    "wof:name":"Pds Pharma Development Services Sa",
    "wof:placetype":"venue"
},
  "geometry": {"coordinates":[8.951305,46.002975],"type":"Point"}
}