{
  "type": "Feature",
  "properties": {
    "iso:country":"CH",
    "sg:address":"H\u00f4tel De Ville Place De L'",
    "sg:city":"Cudrefin",
    "sg:orig_category":"Herstellung von konfektionierten Textilwaren ohne Bekleidung",
    "sg:postcode":"1588",
    "sg:province":"Vaud",
    "wof:name":"Boutique Bambou Bo\u00eete \u00e0 Ouvrages S\u00e0rl",
    "wof:placetype":"venue"
},
  "geometry": {"coordinates":[7.0185198784,46.9558601379],"type":"Point"}
}