{
  "type": "Feature",
  "properties": {
    "iso:country":"CH",
    "sg:address":"Scierie Rue De La 14",
    "sg:city":"Martigny",
    "sg:orig_category":"Herstellung von Heizk\u00f6rpern U kesseln f\u00fcr die Zentralheizung",
    "sg:phone":"+41 79 341 03 02",
    "sg:postcode":"1920",
    "sg:province":"Valais",
    "wof:name":"Br\u00fcgger Gebr.",
    "wof:placetype":"venue"
},
  "geometry": {"coordinates":[7.6635460854,47.1924057007],"type":"Point"}
}