{
  "type": "Feature",
  "properties": {
    "iso:country":"CH",
    "sg:address":"Hauptstrasse 35 8750 Glarus. Postfach",
    "sg:city":"Glarus",
    "sg:orig_category":"Allgemeinbildende weiterf\u00fchrende Schulen Unterrichtswesen",
    "sg:phone":"+41 19142050",
    "sg:postcode":"8750",
    "sg:province":"Glarus",
    "wof:name":"Stiftung Zweisprachige Tagesschule Z\u00fcrichsee",
    "wof:placetype":"venue"
},
  "geometry": {"coordinates":[8.572417,47.331352],"type":"Point"}
}