{
  "type": "Feature",
  "properties": {
    "iso:country":"CH",
    "sg:address":"Wiesentalstrasse 135 7000 Chur. Postfach 27",
    "sg:city":"Chur",
    "sg:orig_category":"Detailhandel mit Spielwaren Handel mit Motorr\u00e4dern, Teilen U Zubeh\u00f6r Instandhaltung U Reparatur von ",
    "sg:phone":"+41 81 285 13 85",
    "sg:postcode":"7006",
    "sg:province":"Graubunden",
    "wof:name":"Fritz Imholz Ag Moto-center & Babyland",
    "wof:placetype":"venue"
},
  "geometry": {"coordinates":[9.5303850174,46.8638725281],"type":"Point"}
}