{
  "type": "Feature",
  "properties": {
    "iso:country":"CH",
    "sg:address":"Achenbergweg 3",
    "sg:city":"Klingnau",
    "sg:orig_category":"Detailhandel mit Fahrr\u00e4dern Handel mit Motorr\u00e4dern, Teilen U Zubeh\u00f6r Instandhaltung U Reparatur von ",
    "sg:phone":"+41 56 245 47 82",
    "sg:postcode":"5313",
    "sg:province":"Aargau",
    "wof:name":"Thomas Lerf Velos-motos",
    "wof:placetype":"venue"
},
  "geometry": {"coordinates":[8.2550458908,47.5792808533],"type":"Point"}
}