{
  "type": "Feature",
  "properties": {
    "iso:country":"CH",
    "sg:address":"1329",
    "sg:city":"Bretonni\u00e8res",
    "sg:orig_category":"Sportvereine Sch\u00fctzen",
    "sg:postcode":"1329",
    "sg:province":"Vaud",
    "wof:name":"St\u00e9 De Tir Armes De Guerre",
    "wof:placetype":"venue"
},
  "geometry": {"coordinates":[6.3145170212,46.6668548584],"type":"Point"}
}