{
  "type": "Feature",
  "properties": {
    "iso:country":"CH",
    "sg:address":"Rebenweg 11",
    "sg:city":"Russikon",
    "sg:orig_category":"Detailhandel Handel mit Motorr\u00e4dern, Teilen U Zubeh\u00f6r Instandhaltung U Reparatur von Motorr\u00e4dern Rep",
    "sg:phone":"+41 19550858",
    "sg:postcode":"8332",
    "sg:province":"Z\u00fcrich",
    "wof:name":"S.t.a.d-motos R\u00f6thlin",
    "wof:placetype":"venue"
},
  "geometry": {"coordinates":[8.7773189545,47.3931388855],"type":"Point"}
}