{
  "type": "Feature",
  "properties": {
    "iso:country":"CH",
    "sg:address":"Zentralstrasse 87",
    "sg:city":"Neuhausen",
    "sg:orig_category":"Arztpraxen",
    "sg:phone":"+41 52 625 59 13",
    "sg:postcode":"8212",
    "sg:province":"Schaffhausen",
    "wof:name":"Dres Med. Bolt & Daeniker Spezial\u00e4rzte Fmh",
    "wof:placetype":"venue"
},
  "geometry": {"coordinates":[8.621154,47.683395],"type":"Point"}
}