{
  "type": "Feature",
  "properties": {
    "iso:country":"CH",
    "sg:address":"B\u00fchl 53",
    "sg:city":"Staffelbach",
    "sg:orig_category":"Gem\u00fcsebau",
    "sg:phone":"+41 62 721 30 83",
    "sg:postcode":"5053",
    "sg:province":"Aargau",
    "wof:name":"Ulrich Stalder Gem\u00fcsebau",
    "wof:placetype":"venue"
},
  "geometry": {"coordinates":[8.0431699753,47.280544281],"type":"Point"}
}