{
  "type": "Feature",
  "properties": {
    "iso:country":"CH",
    "sg:address":"Eyboden 2",
    "sg:city":"Niederscherli",
    "sg:orig_category":"Verwaltung von Immobilien Wirtschaftspr\u00fcfung, Steuerberatung U Treuhand",
    "sg:phone":"+41 31 312 24 05",
    "sg:postcode":"3145",
    "sg:province":"Bern",
    "wof:name":"Ctr Treuhand & Revisions Ag",
    "wof:placetype":"venue"
},
  "geometry": {"coordinates":[7.3898391724,46.8862686157],"type":"Point"}
}