{
  "type": "Feature",
  "properties": {
    "iso:country":"CH",
    "sg:address":"Schulhausstrasse 21",
    "sg:city":"Ebikon",
    "sg:orig_category":"Maler U Glasergewerbe",
    "sg:phone":"+41 41 440 70 51",
    "sg:postcode":"6030",
    "sg:province":"Luzern",
    "wof:name":"Monica Glauco Dipl. Malermeister",
    "wof:placetype":"venue"
},
  "geometry": {"coordinates":[8.3407402039,47.0805397034],"type":"Point"}
}