{
  "type": "Feature",
  "properties": {
    "iso:country":"CH",
    "sg:address":"Meisterswil 6331 H\u00fcnenberg. Postfach 925",
    "sg:city":"H\u00fcnenberg",
    "sg:orig_category":"Parkettleger",
    "sg:phone":"+41 32 841 23 27",
    "sg:postcode":"6331",
    "sg:province":"Zug",
    "wof:name":"Baroni Terrassements Sa",
    "wof:placetype":"venue"
},
  "geometry": {"coordinates":[6.8587169647,46.968585968],"type":"Point"}
}