{
  "type": "Feature",
  "properties": {
    "iso:country":"CH",
    "sg:address":"Quellenweg 10",
    "sg:city":"Rorschacherberg",
    "sg:orig_category":"Sonstiges Versicherungsgewerbe",
    "sg:phone":"+41 71 855 82 62",
    "sg:postcode":"9404",
    "sg:province":"St. Gallen",
    "wof:name":"Garanta (schweiz) Versicherungs Ag",
    "wof:placetype":"venue"
},
  "geometry": {"coordinates":[9.5136871338,47.4771461487],"type":"Point"}
}