{
  "type": "Feature",
  "properties": {
    "iso:country":"CH",
    "sg:address":"Hotzstrasse 52 8006 Z\u00fcrich. Postfach",
    "sg:city":"Z\u00fcrich",
    "sg:orig_category":"Gesundheitswesen",
    "sg:phone":"+41 13642904",
    "sg:postcode":"8001",
    "sg:province":"Z\u00fcrich",
    "wof:name":"Fit & Well Baroni Ivana B\u00fcro F\u00fcr Gesundheitsberatung",
    "wof:placetype":"venue"
},
  "geometry": {"coordinates":[8.5399560928,47.3917274475],"type":"Point"}
}