{
  "type": "Feature",
  "properties": {
    "iso:country":"CH",
    "sg:address":"Albisriederstrasse 381 8047 Z\u00fcrich. Postfach",
    "sg:city":"Z\u00fcrich",
    "sg:orig_category":"Detailhandel mit Fahrr\u00e4dern Handel mit Motorr\u00e4dern, Teilen U Zubeh\u00f6r Instandhaltung U Reparatur von ",
    "sg:phone":"+41 61 711 30 09",
    "sg:postcode":"8047",
    "sg:province":"Z\u00fcrich",
    "wof:name":"Harder Velo",
    "wof:placetype":"venue"
},
  "geometry": {"coordinates":[7.5922689438,47.4932136536],"type":"Point"}
}