{
  "type": "Feature",
  "properties": {
    "iso:country":"CH",
    "sg:address":"Zeughausgasse 9 3011 Bern. Postfach",
    "sg:city":"Bern",
    "sg:classifiers":[
        {
            "category":"Travel",
            "subcategory":"Hotels & Motels",
            "type":"Entertainment"
        }
    ],
    "sg:phone":"+41 31 312 10 21",
    "sg:postcode":"3005",
    "sg:province":"Bern",
    "sg:tags":[
        "hotels",
        "mit",
        "restaurant"
    ],
    "wof:name":"Volkshaus Ag Bern Hotel M Restaurant U S\u00e4len Usw",
    "wof:placetype":"venue"
},
  "geometry": {"coordinates":[7.4464859962,46.9486465454],"type":"Point"}
}