{
  "type": "Feature",
  "properties": {
    "iso:country":"CH",
    "sg:address":"7747 Viano. Postfach",
    "sg:city":"Viano",
    "sg:orig_category":"Allgemeiner Hoch U Tiefbau",
    "sg:phone":"+41 81 846 56 09",
    "sg:postcode":"7747",
    "sg:province":"Graubunden",
    "wof:name":"Marco Merlo Impresa Costruzioni",
    "wof:placetype":"venue"
},
  "geometry": {"coordinates":[10.138196,46.254452],"type":"Point"}
}