{
  "type": "Feature",
  "properties": {
    "iso:country":"CH",
    "sg:address":"Bois-genoud Route Du 1a",
    "sg:city":"Crissier",
    "sg:orig_category":"Sonstiger Detailhandel nicht in Verkaufsr\u00e4umen",
    "sg:postcode":"1023",
    "sg:province":"Vaud",
    "wof:name":"Distrinvest Sa",
    "wof:placetype":"venue"
},
  "geometry": {"coordinates":[6.5846700668,46.5471343994],"type":"Point"}
}