{
  "type": "Feature",
  "properties": {
    "iso:country":"CH",
    "sg:address":"Riet",
    "sg:city":"Wildhaus",
    "sg:orig_category":"Maler U Glasergewerbe Malerei",
    "sg:phone":"+41 71 999 13 15",
    "sg:postcode":"9658",
    "sg:province":"St. Gallen",
    "wof:name":"G\u00fcntert Malerwerkst\u00e4tte Ag",
    "wof:placetype":"venue"
},
  "geometry": {"coordinates":[9.3261852264,47.2003326416],"type":"Point"}
}