{
  "type": "Feature",
  "properties": {
    "iso:country":"CH",
    "sg:address":"Kronengasse 2",
    "sg:city":"Brig",
    "sg:orig_category":"Detailhandel mit Fleisch U Fleischwaren",
    "sg:postcode":"3900",
    "sg:province":"Valais",
    "wof:name":"Meat Promo Ag",
    "wof:placetype":"venue"
},
  "geometry": {"coordinates":[7.988866806,46.3170204163],"type":"Point"}
}