{
  "type": "Feature",
  "properties": {
    "iso:country":"CH",
    "sg:address":"Avenue Du Grand-st-bernard 1",
    "sg:city":"Martigny",
    "sg:classifiers":[
        {
            "category":"Restaurant",
            "type":"Food & Drink"
        }
    ],
    "sg:phone":"+41 27 722 21 30",
    "sg:postcode":"1920",
    "sg:province":"Valais",
    "wof:name":"Caf\u00e9 Lion D'or",
    "wof:placetype":"venue"
},
  "geometry": {"coordinates":[7.0721149445,46.1005706787],"type":"Point"}
}