{
  "type": "Feature",
  "properties": {
    "iso:country":"CH",
    "sg:address":"Sporrengasse 7",
    "sg:city":"Schaffhausen",
    "sg:orig_category":"Museen",
    "sg:phone":"+41 52 625 88 46",
    "sg:postcode":"8200",
    "sg:province":"Schaffhausen",
    "wof:name":"Museum Stemmler",
    "wof:placetype":"venue"
},
  "geometry": {"coordinates":[8.6344614029,47.6966781616],"type":"Point"}
}