{
  "type": "Feature",
  "properties": {
    "iso:country":"CH",
    "sg:address":"Niesenweg 3",
    "sg:city":"Nieder\u00f6nz",
    "sg:orig_category":"Sportschulen Fern\u00f6stliche Kampfsportarten Sportvereine Judo and Karate",
    "sg:phone":"+41 62 961 45 51",
    "sg:postcode":"3362",
    "sg:province":"Bern",
    "wof:name":"Judo Schule Nieder\u00f6nz",
    "wof:placetype":"venue"
},
  "geometry": {"coordinates":[7.6930961609,47.1879501343],"type":"Point"}
}