{
  "type": "Feature",
  "properties": {
    "iso:country":"CH",
    "sg:address":"3533",
    "sg:city":"Bowil",
    "sg:orig_category":"RESTAURANTS: TEA-ROOMS",
    "sg:postcode":"3533",
    "sg:province":"Bern",
    "wof:name":"Fankhauser U.",
    "wof:placetype":"venue"
},
  "geometry": {"coordinates":[7.1893959045,47.0321159363],"type":"Point"}
}