{
  "type": "Feature",
  "properties": {
    "iso:country":"CH",
    "sg:address":"L'auberge 178e",
    "sg:city":"Bellelay",
    "sg:orig_category":"Kaminfeger",
    "sg:phone":"+41 32 484 99 34",
    "sg:postcode":"2713",
    "sg:province":"Bern",
    "wof:name":"Charles & Davy Vermeille Ramonage",
    "wof:placetype":"venue"
},
  "geometry": {"coordinates":[7.1673998833,47.2626800537],"type":"Point"}
}