{
  "type": "Feature",
  "properties": {
    "iso:country":"CH",
    "sg:address":"Hammerstrasse 114",
    "sg:city":"Basel",
    "sg:orig_category":"Detailhandel mit Waren verschiedener Art, Hauptrichtung Nahrungsmittel Fachdetailhandel mit Nahrungs",
    "sg:phone":"+41 31 332 62 11",
    "sg:postcode":"4057",
    "sg:province":"Basel-Stadt",
    "wof:name":"La Maison Du Canard Rozoy Kunz",
    "wof:placetype":"venue"
},
  "geometry": {"coordinates":[7.451169014,46.9533805847],"type":"Point"}
}