{
  "type": "Feature",
  "properties": {
    "iso:country":"CH",
    "sg:address":"F\u00f6hrenweg 9 4856 Glash\u00fctten. Postfach",
    "sg:city":"Glash\u00fctten",
    "sg:orig_category":"Unclassifiable Establishments",
    "sg:phone":"+41 62 926 35 54",
    "sg:postcode":"4856",
    "sg:province":"Aargau",
    "wof:name":"J. B. Ruf Etiketten Service",
    "wof:placetype":"venue"
},
  "geometry": {"coordinates":[7.8309078217,47.2614784241],"type":"Point"}
}