{
  "type": "Feature",
  "properties": {
    "iso:country":"CH",
    "sg:address":"Rue Des B\u00e2ts 12",
    "sg:city":"Del\u00e9mont",
    "sg:orig_category":"Herstellung von K\u00fcchenm\u00f6beln Herstellung von Metallerzeugnissen ohne Maschinenbau",
    "sg:phone":"+41 32 422 17 17",
    "sg:postcode":"2800",
    "sg:province":"Jura",
    "wof:name":"Gelso-piquerez Jean-paul, Arteco",
    "wof:placetype":"venue"
},
  "geometry": {"coordinates":[7.3461427689,47.364692688],"type":"Point"}
}