{
  "type": "Feature",
  "properties": {
    "iso:country":"CH",
    "sg:address":"Av. Pictet-de-rochemont 5",
    "sg:city":"Genf",
    "sg:orig_category":"Fachdetailhandel in Verkaufsr\u00e4umen Kunsthandel",
    "sg:postcode":"1200",
    "sg:province":"Gen\u00e8ve",
    "wof:name":"Castellino Michel",
    "wof:placetype":"venue"
},
  "geometry": {"coordinates":[6.1572909355,46.2025146484],"type":"Point"}
}