{
  "type": "Feature",
  "properties": {
    "iso:country":"CH",
    "sg:address":"Juchstrasse 25",
    "sg:city":"Frauenfeld",
    "sg:classifiers":[
        {
            "category":"Manufacturing",
            "subcategory":"Wood Products",
            "type":"Manufacturing & Wholesale Goods"
        }
    ],
    "sg:phone":"+41 52 722 49 49",
    "sg:postcode":"8500",
    "sg:province":"Thurgau",
    "sg:tags":[
        "lumber"
    ],
    "wof:name":"Ef Confirma Ag",
    "wof:placetype":"venue"
},
  "geometry": {"coordinates":[8.9087629318,47.5693969727],"type":"Point"}
}