{
  "type": "Feature",
  "properties": {
    "iso:country":"CH",
    "sg:address":"Chrischonastrasse 2",
    "sg:city":"Birsfelden",
    "sg:orig_category":"Detailhandel mit Waren verschiedener Art, Hauptrichtung Nahrungsmittel",
    "sg:phone":"+41 61 312 31 07",
    "sg:postcode":"4127",
    "sg:province":"Basel-Landschaft",
    "wof:name":"Migros-genossenschaft",
    "wof:placetype":"venue"
},
  "geometry": {"coordinates":[7.6241459846,47.5556678772],"type":"Point"}
}