{
  "type": "Feature",
  "properties": {
    "iso:country":"CH",
    "sg:address":"Avenue Des Tilleuls 15",
    "sg:city":"Gen\u00e8ve",
    "sg:orig_category":"Detailhandel mit Brot, Back U S\u00fcsswaren RESTAURANTS: TEA-ROOMS",
    "sg:phone":"+41 22 340 61 87",
    "sg:postcode":"1203",
    "sg:province":"Gen\u00e8ve",
    "wof:name":"Les Forsythias Sarl",
    "wof:placetype":"venue"
},
  "geometry": {"coordinates":[6.13026,46.205669],"type":"Point"}
}