{
  "type": "Feature",
  "properties": {
    "iso:country":"CH",
    "sg:address":"Dorfgasse 8",
    "sg:city":"Twann",
    "sg:classifiers":[
        {
            "category":"Restaurant",
            "type":"Food & Drink"
        }
    ],
    "sg:phone":"+41 32 351 11 51",
    "sg:postcode":"2513",
    "sg:province":"Bern",
    "wof:name":"Restaurant Traube",
    "wof:placetype":"venue"
},
  "geometry": {"coordinates":[7.3629250526,47.1085662842],"type":"Point"}
}