{
  "type": "Feature",
  "properties": {
    "iso:country":"CH",
    "sg:address":"Bachtelstrasse 10",
    "sg:city":"Hinwil",
    "sg:orig_category":"Detailhandel mit Spielwaren",
    "sg:phone":"+41 19381161",
    "sg:postcode":"8340",
    "sg:province":"Z\u00fcrich",
    "wof:name":"Spielhaus Ruth Bolleter",
    "wof:placetype":"venue"
},
  "geometry": {"coordinates":[8.8433771133,47.3004837036],"type":"Point"}
}