{
  "type": "Feature",
  "properties": {
    "iso:country":"CH",
    "sg:address":"Feierabendstr. 25 4000 Basel. Postfach 146",
    "sg:city":"Basel",
    "sg:orig_category":"Herstellung von sonstigen chemischen Erzeugnissen",
    "sg:phone":"+41 61 271 88 89",
    "sg:postcode":"4051",
    "sg:province":"Basel-Stadt",
    "wof:name":"Jokol Ag",
    "wof:placetype":"venue"
},
  "geometry": {"coordinates":[7.5816440582,47.5519332886],"type":"Point"}
}