{
  "type": "Feature",
  "properties": {
    "iso:country":"CH",
    "sg:address":"Baarerstrasse 10",
    "sg:city":"Zug",
    "sg:orig_category":"Fachdetailhandel in Verkaufsr\u00e4umen Grosshandel mit Foto U Kinoger\u00e4ten, feinmechanischen U optischen ",
    "sg:phone":"+41 41 711 03 47",
    "sg:postcode":"6300",
    "sg:province":"Zug",
    "wof:name":"Interphot Recycling Ag",
    "wof:placetype":"venue"
},
  "geometry": {"coordinates":[8.5164327621,47.1715621948],"type":"Point"}
}