{
  "type": "Feature",
  "properties": {
    "iso:country":"CH",
    "sg:address":"Bellerivematte 10 6006 Luzern. Postfach",
    "sg:city":"Luzern",
    "sg:orig_category":"Non-Classified Establishments",
    "sg:phone":"+41 41 370 40 50",
    "sg:postcode":"6003",
    "sg:province":"Luzern",
    "wof:name":"G\u00fcbelin Daniela Kommunikationsberatung Unternehmensberatung, Bes. Kommunikation U. Pr",
    "wof:placetype":"venue"
},
  "geometry": {"coordinates":[8.3315563202,47.0556716919],"type":"Point"}
}