{
  "type": "Feature",
  "properties": {
    "iso:country":"CH",
    "sg:address":"Pflugg\u00e4sslein 8",
    "sg:city":"Basel",
    "sg:orig_category":"Detailhandel mit Geschenkartikeln U Souvenirs",
    "sg:phone":"+41 61 261 03 60",
    "sg:postcode":"4001",
    "sg:province":"Basel-Stadt",
    "wof:name":"Anti-flirt Boutique",
    "wof:placetype":"venue"
},
  "geometry": {"coordinates":[7.5893740654,47.5560798645],"type":"Point"}
}