{
  "type": "Feature",
  "properties": {
    "iso:country":"CH",
    "sg:address":"Culmannstrasse 19 8006 Z\u00fcrich. Postfach",
    "sg:city":"Z\u00fcrich",
    "sg:orig_category":"RESTAURANTS: TEA-ROOMS",
    "sg:phone":"+41 55 211 13 45",
    "sg:postcode":"8001",
    "sg:province":"Z\u00fcrich",
    "wof:name":"Rest. Bar R\u00f6ssli, Delli Colli Rocco",
    "wof:placetype":"venue"
},
  "geometry": {"coordinates":[8.8163261414,47.2267608643],"type":"Point"}
}