{
  "type": "Feature",
  "properties": {
    "iso:country":"CH",
    "sg:address":"St. Karli-strasse 65",
    "sg:city":"Luzern",
    "sg:orig_category":"Geb\u00e4ude, Wohnungsreinigung Reinigungsgewerbe",
    "sg:phone":"+41 32 652 70 15",
    "sg:postcode":"6004",
    "sg:province":"Luzern",
    "wof:name":"L\u00fcko Geb\u00e4ude-reinigungen",
    "wof:placetype":"venue"
},
  "geometry": {"coordinates":[7.3792061806,47.1856498718],"type":"Point"}
}