{
  "type": "Feature",
  "properties": {
    "iso:country":"CH",
    "sg:address":"Grafenauweg 8",
    "sg:city":"Zug",
    "sg:classifiers":[
        {
            "category":"Manufacturing",
            "subcategory":"Petroleum Products",
            "type":"Manufacturing & Wholesale Goods"
        }
    ],
    "sg:phone":"+41 41 710 88 28",
    "sg:postcode":"6300",
    "sg:province":"Zug",
    "sg:tags":[
        "crude",
        "oil"
    ],
    "wof:name":"Wintershall Oil Ag",
    "wof:placetype":"venue"
},
  "geometry": {"coordinates":[8.512555,47.174221],"type":"Point"}
}