{
  "type": "Feature",
  "properties": {
    "iso:country":"CH",
    "sg:address":"Baumacker 4",
    "sg:city":"Altnau",
    "sg:orig_category":"Allgemeiner Hoch U Tiefbau Grosshandel mit chemischen Erzeugnissen",
    "sg:phone":"+41 22 342 36 88",
    "sg:postcode":"8595",
    "sg:province":"Thurgau",
    "wof:name":"Anhy Sa",
    "wof:placetype":"venue"
},
  "geometry": {"coordinates":[6.137989,46.181461],"type":"Point"}
}