{
  "type": "Feature",
  "properties": {
    "iso:country":"CH",
    "sg:address":"Neumattstrasse 39",
    "sg:city":"Urdorf",
    "sg:orig_category":"Massagestudios P\u00e9dicure",
    "sg:phone":"+41 17345883",
    "sg:postcode":"8902",
    "sg:province":"Z\u00fcrich",
    "wof:name":"Lina Wernli",
    "wof:placetype":"venue"
},
  "geometry": {"coordinates":[8.4225816727,47.3877105713],"type":"Point"}
}