{
  "type": "Feature",
  "properties": {
    "iso:country":"CH",
    "sg:address":"Winkelriedstrasse 37",
    "sg:city":"Luzern",
    "sg:orig_category":"Detailhandel mit B\u00fcchern, Zeitungen, Schreib U Papeteriewaren",
    "sg:phone":"+41 41 210 07 57",
    "sg:postcode":"6003",
    "sg:province":"Luzern",
    "wof:name":"Papeterie Linsi, Inhaberin Zust Ruth",
    "wof:placetype":"venue"
},
  "geometry": {"coordinates":[8.306934,47.047119],"type":"Point"}
}