{
  "type": "Feature",
  "properties": {
    "iso:country":"CH",
    "sg:address":"Brauerstrasse 9",
    "sg:city":"Z\u00fcrich",
    "sg:orig_category":"Detailhandel mit Waren verschiedener Art, Hauptrichtung Nahrungsmittel Fischerei",
    "sg:phone":"+41 41 460 12 22",
    "sg:postcode":"8004",
    "sg:province":"Z\u00fcrich",
    "wof:name":"Zwimpfer Seefischerei Fischhandel",
    "wof:placetype":"venue"
},
  "geometry": {"coordinates":[8.2235832214,47.131149292],"type":"Point"}
}