{
  "type": "Feature",
  "properties": {
    "iso:country":"CH",
    "sg:address":"Ludretikonerstrasse 40-42",
    "sg:city":"Thalwil",
    "sg:orig_category":"Instandhaltung U Reparatur von Automobilen",
    "sg:phone":"+41 17203040",
    "sg:postcode":"8800",
    "sg:province":"Z\u00fcrich",
    "wof:name":"Kronen-garage Ag",
    "wof:placetype":"venue"
},
  "geometry": {"coordinates":[8.5617628098,47.2992134094],"type":"Point"}
}