{
  "type": "Feature",
  "properties": {
    "iso:country":"CH",
    "sg:address":"Farnern 88",
    "sg:city":"Heimiswil",
    "sg:orig_category":"Gartenbau",
    "sg:phone":"+41 34 422 49 35",
    "sg:postcode":"3412",
    "sg:province":"Bern",
    "wof:name":"Hans M\u00e4usli Baumpfplege",
    "wof:placetype":"venue"
},
  "geometry": {"coordinates":[7.6611199379,47.0585021973],"type":"Point"}
}