{
  "type": "Feature",
  "properties": {
    "iso:country":"CH",
    "sg:address":"Landstrasse 93",
    "sg:city":"Schaan",
    "sg:orig_category":"Malerei",
    "sg:phone":"+423 232 17 40",
    "sg:postcode":"9494",
    "wof:name":"Stefan Wachter Ag Malergesch\u00e4ft",
    "wof:placetype":"venue"
},
  "geometry": {"coordinates":[9.5089092255,47.1615066528],"type":"Point"}
}