{
  "type": "Feature",
  "properties": {
    "iso:country":"CH",
    "sg:address":"Route De Moudon 25",
    "sg:city":"Oron-la-ville",
    "sg:orig_category":"Sonstiger spezialisierter Hoch U Tiefbau",
    "sg:phone":"+41 21 907 92 73",
    "sg:postcode":"1610",
    "sg:province":"Vaud",
    "wof:name":"Edmond-yvan Riesen",
    "wof:placetype":"venue"
},
  "geometry": {"coordinates":[6.8225069046,46.5748405457],"type":"Point"}
}