{
  "type": "Feature",
  "properties": {
    "iso:country":"CH",
    "sg:address":"Niklaus-konrad-strasse 16",
    "sg:city":"Solothurn",
    "sg:orig_category":"Detailhandel mit Radio U Fernsehger\u00e4ten Herstellung von Radio U Fernsehger\u00e4ten sowie phono U videote",
    "sg:phone":"+41 32 622 79 82",
    "sg:postcode":"4500",
    "sg:province":"Solothurn",
    "wof:name":"Reber Radio-tv.",
    "wof:placetype":"venue"
},
  "geometry": {"coordinates":[7.5411581993,47.2047157288],"type":"Point"}
}