{
  "type": "Feature",
  "properties": {
    "iso:country":"CH",
    "sg:address":"Kesselweg 34",
    "sg:city":"Liestal",
    "sg:orig_category":"Vorschulen, Kinderg\u00e4rten",
    "sg:phone":"+41 61 721 73 03",
    "sg:postcode":"4410",
    "sg:province":"Basel-Landschaft",
    "wof:name":"Kindergarten Fraumatten",
    "wof:placetype":"venue"
},
  "geometry": {"coordinates":[7.5254898071,47.5062713623],"type":"Point"}
}