{
  "type": "Feature",
  "properties": {
    "iso:country":"CH",
    "sg:address":"Kasernenstrasse 110",
    "sg:city":"B\u00fclach",
    "sg:orig_category":"Herstellung von Fenstern U T\u00fcren aus Holz Herstellung von Metallkonstruktionen",
    "sg:phone":"+41 91 966 04 28",
    "sg:postcode":"8180",
    "sg:province":"Z\u00fcrich",
    "wof:name":"Wigra Winterg\u00e4rten Graf Werner",
    "wof:placetype":"venue"
},
  "geometry": {"coordinates":[8.5262842178,47.5134277344],"type":"Point"}
}