{
  "type": "Feature",
  "properties": {
    "iso:country":"CH",
    "sg:address":"Margencel Rue 29",
    "sg:city":"Aigle",
    "sg:orig_category":"Wirtschaftspr\u00fcfung, Steuerberatung U Treuhand",
    "sg:phone":"+41 24 466 41 41",
    "sg:postcode":"1860",
    "sg:province":"Vaud",
    "wof:name":"Fiducial Sa",
    "wof:placetype":"venue"
},
  "geometry": {"coordinates":[6.9649510384,46.3181343079],"type":"Point"}
}