{
  "type": "Feature",
  "properties": {
    "iso:country":"CH",
    "sg:address":"Wien-strasse 26 4000 Basel. Postfach",
    "sg:city":"Basel",
    "sg:orig_category":"Herstellung von Mess U Kontrollinstrumenten U vorrichtungen",
    "sg:postcode":"4000",
    "sg:province":"Basel-Stadt",
    "wof:name":"Rudjic Stjepan, Pr\u00e4zisionsmechanik",
    "wof:placetype":"venue"
},
  "geometry": {"coordinates":[7.6070227623,47.5326576233],"type":"Point"}
}