{
  "type": "Feature",
  "properties": {
    "iso:country":"CH",
    "sg:address":"Neue Badstrasse 7",
    "sg:city":"Lostorf",
    "sg:orig_category":"Betrieb von Sportanlagen",
    "sg:phone":"+41 55 410 22 17",
    "sg:postcode":"4654",
    "sg:province":"Solothurn",
    "wof:name":"Bad Seedamm Ag",
    "wof:placetype":"venue"
},
  "geometry": {"coordinates":[8.787952,47.20192],"type":"Point"}
}