{
  "type": "Feature",
  "properties": {
    "iso:country":"CH",
    "sg:address":"Rue Pierre-p\u00e9quignat 10",
    "sg:city":"Del\u00e9mont",
    "sg:orig_category":"Fachdetailhandel mit pharmazeutischen Produkten",
    "sg:phone":"+41 32 422 11 12",
    "sg:postcode":"2800",
    "sg:province":"Jura",
    "wof:name":"Pharmacie Ville",
    "wof:placetype":"venue"
},
  "geometry": {"coordinates":[7.3443250656,47.365398407],"type":"Point"}
}