{
  "type": "Feature",
  "properties": {
    "iso:country":"CH",
    "sg:address":"Murtenstrasse 11",
    "sg:city":"Bern",
    "sg:orig_category":"Gesundheitswesen",
    "sg:postcode":"3008",
    "sg:province":"Bern",
    "wof:name":"Sgri Service Gestion, Thomas R\u00e4ss",
    "wof:placetype":"venue"
},
  "geometry": {"coordinates":[6.8637962341,46.462600708],"type":"Point"}
}