{
  "type": "Feature",
  "properties": {
    "iso:country":"CH",
    "sg:address":"Goumoensstrasse 48",
    "sg:city":"Bern",
    "sg:orig_category":"Vorschulen, Kinderg\u00e4rten",
    "sg:phone":"+41 31 371 13 11",
    "sg:postcode":"3007",
    "sg:province":"Bern",
    "wof:name":"Kindergarten Steinh\u00f6lzli Ii",
    "wof:placetype":"venue"
},
  "geometry": {"coordinates":[7.4310731888,46.934715271],"type":"Point"}
}