{
  "type": "Feature",
  "properties": {
    "iso:country":"CH",
    "sg:address":"Chemin Des Rochettes 29",
    "sg:city":"Auvernier",
    "sg:orig_category":"Detailhandel mit elektrischen Haushalts-,Radio U Fernsehger\u00e4ten sowie Musikinstrumenten Elektroinsta",
    "sg:phone":"+41 33 755 15 64",
    "sg:postcode":"2012",
    "sg:province":"Neuch\u00e2tel",
    "wof:name":"Elektrohuus Von Allmen Ag",
    "wof:placetype":"venue"
},
  "geometry": {"coordinates":[7.2673168182,46.3836975098],"type":"Point"}
}