{
  "type": "Feature",
  "properties": {
    "iso:country":"CH",
    "sg:address":"Rue Du Temple 38 2024 St-aubin-sauges Case Postale 120",
    "sg:city":"St-aubin-sauges",
    "sg:orig_category":"Sportvereine Sch\u00fctzen Pistolen-& Gewehr",
    "sg:postcode":"2024",
    "sg:province":"Neuch\u00e2tel",
    "wof:name":"St\u00e9 Tir Pistolet La Tour-de-p.",
    "wof:placetype":"venue"
},
  "geometry": {"coordinates":[6.8635802269,46.4562797546],"type":"Point"}
}