{
  "type": "Feature",
  "properties": {
    "iso:country":"CH",
    "sg:address":"Poststrasse 22",
    "sg:city":"Zug",
    "sg:orig_category":"Unclassifiable Establishments",
    "sg:postcode":"6300",
    "sg:province":"Zug",
    "wof:name":"Alk-holding Ag",
    "wof:placetype":"venue"
},
  "geometry": {"coordinates":[8.5168733597,47.1707458496],"type":"Point"}
}