{
  "type": "Feature",
  "properties": {
    "iso:country":"CH",
    "sg:address":"Lindenstrasse 34",
    "sg:city":"Sch\u00f6nholzerswilen",
    "sg:orig_category":"Bauspenglerei Zimmerei, Dachdeckerei, Bauspenglerei U Abdichtung",
    "sg:phone":"+41 71 633 25 91",
    "sg:postcode":"8577",
    "sg:province":"Thurgau",
    "wof:name":"Str\u00e4ssle Spenglerei & Solartechnik",
    "wof:placetype":"venue"
},
  "geometry": {"coordinates":[9.139118,47.516682],"type":"Point"}
}