{
  "type": "Feature",
  "properties": {
    "iso:country":"CH",
    "sg:address":"Marktgasse 18",
    "sg:city":"Bern",
    "sg:orig_category":"Detailhandel mit Lederwaren U Reiseartikeln",
    "sg:phone":"+41 31 311 20 66",
    "sg:postcode":"3011",
    "sg:province":"Bern",
    "wof:name":"Hummel Lederwaren Ag Lederwaren, Reiseartikel Usw; Fabr., Handel.",
    "wof:placetype":"venue"
},
  "geometry": {"coordinates":[7.4465332031,46.9480628967],"type":"Point"}
}