{
  "type": "Feature",
  "properties": {
    "iso:country":"CH",
    "sg:address":"H\u00fcnigenstrasse 15",
    "sg:city":"Konolfingen",
    "sg:orig_category":"Wasserversorgung",
    "sg:postcode":"3510",
    "sg:province":"Bern",
    "wof:name":"Wasserverbund Kiesental Ag",
    "wof:placetype":"venue"
},
  "geometry": {"coordinates":[7.6241979599,46.8786468506],"type":"Point"}
}