{
  "type": "Feature",
  "properties": {
    "iso:country":"CH",
    "sg:address":"Doggilochstrasse Haus Sunnama",
    "sg:city":"Klosters",
    "sg:orig_category":"Unternehmensberatung",
    "sg:phone":"+41 79 445 70 66",
    "sg:postcode":"7250",
    "sg:province":"Graubunden",
    "wof:name":"Schilt Consult.",
    "wof:placetype":"venue"
},
  "geometry": {"coordinates":[9.8801698685,46.8800468445],"type":"Point"}
}