{
  "type": "Feature",
  "properties": {
    "iso:country":"CH",
    "sg:address":"3920 Zermatt. Postfach 37",
    "sg:city":"Zermatt",
    "sg:classifiers":[
        {
            "category":"Education",
            "subcategory":"Vocational School",
            "type":"Public Place"
        }
    ],
    "sg:postcode":"3920",
    "sg:province":"Valais",
    "sg:tags":[
        "koch-",
        "haushaltschulen"
    ],
    "wof:name":"Haushaltungsschule",
    "wof:placetype":"venue"
},
  "geometry": {"coordinates":[7.7484002113,46.024143219],"type":"Point"}
}