{
  "type": "Feature",
  "properties": {
    "iso:country":"CH",
    "sg:address":"Castelrotto 6980 Castelrotto. Postfach",
    "sg:city":"Castelrotto",
    "sg:orig_category":"RESTAURANTS: TEA-ROOMS",
    "sg:phone":"+41 91 608 23 11",
    "sg:postcode":"6980",
    "sg:province":"Ticino",
    "wof:name":"Grotto Rossi Sagl",
    "wof:placetype":"venue"
},
  "geometry": {"coordinates":[8.8387699127,45.9946212769],"type":"Point"}
}