{
  "type": "Feature",
  "properties": {
    "iso:country":"CH",
    "sg:address":"Kehlhofstrasse 50",
    "sg:city":"Egnach",
    "sg:orig_category":"Sportvereine Sch\u00fctzen Armbrust",
    "sg:phone":"+41 71 965 26 34",
    "sg:postcode":"9322",
    "sg:province":"Thurgau",
    "wof:name":"Armbrustsch\u00fctzen.neukirch-eg.",
    "wof:placetype":"venue"
},
  "geometry": {"coordinates":[9.3760671616,47.5499763489],"type":"Point"}
}