{
  "type": "Feature",
  "properties": {
    "addr:full":"Salstrasse 39 Winterthur Z\u00fcrich 8400",
    "addr:housenumber":"39",
    "addr:postcode":"8400",
    "addr:street":"Salstrasse",
    "iso:country":"CH",
    "sg:address":"Salstrasse 39",
    "sg:city":"Winterthur",
    "sg:classifiers":[
        {
            "category":"Landmark",
            "subcategory":"Unesco World Heritage Site",
            "type":"Public Place"
        }
    ],
    "sg:phone":"+41 52 223 01 35",
    "sg:postcode":"8400",
    "sg:province":"Z\u00fcrich",
    "sg:tags":[
        "programming",
        "database"
    ],
    "wof:name":"Thomas Grosserode",
    "wof:placetype":"venue"
},
  "geometry": {"coordinates":[8.717056,47.503933],"type":"Point"}
}