{
  "type": "Feature",
  "properties": {
    "iso:country":"CH",
    "sg:address":"Holenackerstrasse 35/b6",
    "sg:city":"Bern",
    "sg:orig_category":"Unternehmensberatung",
    "sg:phone":"+41 31 994 21 20",
    "sg:postcode":"3027",
    "sg:province":"Bern",
    "wof:name":"Jalalian Unternehmensberatung",
    "wof:placetype":"venue"
},
  "geometry": {"coordinates":[7.3663301468,46.9502563477],"type":"Point"}
}