{
  "type": "Feature",
  "properties": {
    "iso:country":"CH",
    "sg:address":"Rue Du Midi 15",
    "sg:city":"Gland",
    "sg:orig_category":"Grosshandel mit Getr\u00e4nken Grosshandel mit Wein U Spirituosen",
    "sg:phone":"+41 22 364 41 23",
    "sg:postcode":"1196",
    "sg:province":"Vaud",
    "wof:name":"La Grappe D'or Marc Brauchli",
    "wof:placetype":"venue"
},
  "geometry": {"coordinates":[6.2724618912,46.4186286926],"type":"Point"}
}