{
  "type": "Feature",
  "properties": {
    "iso:country":"CH",
    "sg:address":"Rue Des Usines 17",
    "sg:city":"Neuch\u00e2tel",
    "sg:orig_category":"Herstellung von Ger\u00e4ten der Elektrizit\u00e4tserzeugung, -verteilung u.\u00e4. -Herstellung von elektronischen",
    "sg:phone":"+41 32 730 50 70",
    "sg:postcode":"2000",
    "sg:province":"Neuch\u00e2tel",
    "wof:name":"Unidynamic S\u00e0rl",
    "wof:placetype":"venue"
},
  "geometry": {"coordinates":[6.9032769203,46.9824714661],"type":"Point"}
}