{
  "type": "Feature",
  "properties": {
    "iso:country":"CH",
    "sg:address":"Hauptstrasse 42 6280 Hochdorf. Postfach",
    "sg:city":"Hochdorf",
    "sg:orig_category":"Pensionskassen",
    "sg:phone":"+41 41 914 09 14",
    "sg:postcode":"6280",
    "sg:province":"Luzern",
    "wof:name":"Stiftung Personalf\u00fcrsorge Der Buchdruckerei Hochdorf Ag",
    "wof:placetype":"venue"
},
  "geometry": {"coordinates":[8.2886552811,47.1679878235],"type":"Point"}
}