{
  "type": "Feature",
  "properties": {
    "addr:full":"Obersaxen Obersaxen Graubunden 7134",
    "addr:housenumber":"7134",
    "iso:country":"CH",
    "sg:address":"Obersaxen",
    "sg:city":"Obersaxen",
    "sg:classifiers":[
        {
            "category":"Banks & Credit Unions",
            "subcategory":"Bank",
            "type":"Services"
        }
    ],
    "sg:phone":"+41 81 933 18 80",
    "sg:postcode":"7134",
    "sg:province":"Graubunden",
    "wof:name":"Raiffeisenbank, Obersaxen-meierhof",
    "wof:placetype":"venue"
},
  "geometry": {"coordinates":[9.103146,46.751328],"type":"Point"}
}