{
  "type": "Feature",
  "properties": {
    "iso:country":"CH",
    "sg:address":"Rieterstrasse 60 8002 Z\u00fcrich. Postfach",
    "sg:city":"Z\u00fcrich",
    "sg:orig_category":"Gesundheitswesen",
    "sg:postcode":"8001",
    "sg:province":"Z\u00fcrich",
    "wof:name":"Orthocare Gmbh",
    "wof:placetype":"venue"
},
  "geometry": {"coordinates":[8.5059127808,47.1442489624],"type":"Point"}
}