{
  "type": "Feature",
  "properties": {
    "iso:country":"CH",
    "sg:address":"Gartensiedlung 322",
    "sg:city":"M\u00e4genwil",
    "sg:orig_category":"G\u00fcterbef\u00f6rderung im Strassenverkehr",
    "sg:phone":"+41 55 220 83 00",
    "sg:postcode":"5506",
    "sg:province":"Aargau",
    "wof:name":"B.t.c. Bulk Transport Corporation",
    "wof:placetype":"venue"
},
  "geometry": {"coordinates":[8.817661,47.226372],"type":"Point"}
}