{
  "type": "Feature",
  "properties": {
    "iso:country":"CH",
    "sg:address":"St\u00e4deliweg 7",
    "sg:city":"Bischofszell",
    "sg:classifiers":[
        {
            "category":"Building & Trades",
            "subcategory":"Construction",
            "type":"Services"
        }
    ],
    "sg:phone":"+41 71 422 14 74",
    "sg:postcode":"9220",
    "sg:province":"Thurgau",
    "sg:tags":[
        "jig",
        "fixture"
    ],
    "wof:name":"Paul Bosshardt's Erben",
    "wof:placetype":"venue"
},
  "geometry": {"coordinates":[9.2438554764,47.4965515137],"type":"Point"}
}