{
  "type": "Feature",
  "properties": {
    "iso:country":"CH",
    "sg:address":"Breitenrain 1b",
    "sg:city":"Orpund",
    "sg:orig_category":"Bauschreinerei Innenausbau",
    "sg:phone":"+41 32 355 10 92",
    "sg:postcode":"2552",
    "sg:province":"Bern",
    "wof:name":"Kurt L\u00f6ffel Ag K\u00fcchen-& Chemin\u00e9ebau",
    "wof:placetype":"venue"
},
  "geometry": {"coordinates":[7.304344,47.139786],"type":"Point"}
}