{
  "type": "Feature",
  "properties": {
    "iso:country":"CH",
    "sg:address":"Dorf",
    "sg:city":"Liebistorf",
    "sg:orig_category":"Autogaragen",
    "sg:phone":"+41 26 674 11 01",
    "sg:postcode":"3213",
    "sg:province":"Fribourg",
    "wof:name":"Max Meyer Garage",
    "wof:placetype":"venue"
},
  "geometry": {"coordinates":[7.193875,46.908951],"type":"Point"}
}