{
  "type": "Feature",
  "properties": {
    "iso:country":"CH",
    "sg:address":"Marktgasse 43",
    "sg:city":"Olten",
    "sg:orig_category":"Offsetdruck Satzherstellung U Reproduktion",
    "sg:phone":"+41 55 260 22 22",
    "sg:postcode":"4600",
    "sg:province":"Solothurn",
    "wof:name":"Patrick Egli Computer-allround",
    "wof:placetype":"venue"
},
  "geometry": {"coordinates":[8.844909668,47.2565765381],"type":"Point"}
}