{
  "type": "Feature",
  "properties": {
    "iso:country":"CH",
    "sg:address":"Dornacherstrasse 1 4600 Olten. Postfach",
    "sg:city":"Olten",
    "sg:orig_category":"Finanz\u00e4mter Steuer\u00e4mter",
    "sg:phone":"+41 62 206 11 11",
    "sg:postcode":"4603",
    "sg:province":"Solothurn",
    "wof:name":"Finanzdirektion & Steuerver- Waltung Der Stadt Olten",
    "wof:placetype":"venue"
},
  "geometry": {"coordinates":[7.9011821747,47.3508720398],"type":"Point"}
}