{
  "type": "Feature",
  "properties": {
    "iso:country":"CH",
    "sg:address":"Lindenplatz 3",
    "sg:city":"Gr\u00e4nichen",
    "sg:orig_category":"Kosmetikinstitute",
    "sg:phone":"+41 62 842 04 50",
    "sg:postcode":"5722",
    "sg:province":"Aargau",
    "wof:name":"Claudia Noser Kosmetikinstitut",
    "wof:placetype":"venue"
},
  "geometry": {"coordinates":[8.0978336334,47.3597145081],"type":"Point"}
}