{
  "type": "Feature",
  "properties": {
    "iso:country":"CH",
    "sg:address":"Strahlholz",
    "sg:city":"Gais",
    "sg:orig_category":"Herstellung von Ger\u00e4ten der Elektrizit\u00e4tserzeugung, -verteilung u.\u00e4. -Herstellung von elektronischen",
    "sg:phone":"+41 71 793 30 30",
    "sg:postcode":"9056",
    "sg:province":"Appenzell Ausserrhoden",
    "wof:name":"Optimatik Ag",
    "wof:placetype":"venue"
},
  "geometry": {"coordinates":[9.4317789078,47.3668365479],"type":"Point"}
}