{
  "type": "Feature",
  "properties": {
    "iso:country":"CH",
    "sg:address":"Rte Du Simplon 112",
    "sg:city":"Martigny",
    "sg:orig_category":"Maler U Glasergewerbe",
    "sg:phone":"+41 27 722 26 55",
    "sg:postcode":"1920",
    "sg:province":"Valais",
    "wof:name":"Peinture Industrielle - Granges Alain",
    "wof:placetype":"venue"
},
  "geometry": {"coordinates":[7.0862421989,46.106590271],"type":"Point"}
}