{
  "type": "Feature",
  "properties": {
    "iso:country":"CH",
    "sg:address":"Rue Th\u00e9odore-de-b\u00e8ze 2-4",
    "sg:city":"Gen\u00e8ve",
    "sg:orig_category":"Bezirks, Sekundar, Realschulen, Oberstufe der Primarschulen",
    "sg:phone":"+41 22 318 03 20",
    "sg:postcode":"1204",
    "sg:province":"Gen\u00e8ve",
    "wof:name":"Ecole Secondaire Calvin",
    "wof:placetype":"venue"
},
  "geometry": {"coordinates":[6.151984,46.200428],"type":"Point"}
}