{
  "type": "Feature",
  "properties": {
    "iso:country":"CH",
    "sg:address":"Weissental",
    "sg:city":"Kollbrunn",
    "sg:classifiers":[
        {
            "category":"Shopping",
            "subcategory":"Beauty & Cosmetics",
            "type":"Retail Goods"
        }
    ],
    "sg:phone":"+41 52 394 04 04",
    "sg:postcode":"8483",
    "sg:province":"Z\u00fcrich",
    "sg:tags":[
        "farm",
        "equipment",
        "care",
        "institute",
        "wellness"
    ],
    "wof:name":"Hydrozei",
    "wof:placetype":"venue"
},
  "geometry": {"coordinates":[8.785002,47.456364],"type":"Point"}
}