{
  "type": "Feature",
  "properties": {
    "iso:country":"CH",
    "sg:address":"Industriestrasse 8",
    "sg:city":"Dietlikon",
    "sg:classifiers":[
        {
            "category":"Government",
            "subcategory":"Fire Station",
            "type":"Public Place"
        }
    ],
    "sg:phone":"+41 22 342 36 50",
    "sg:postcode":"8305",
    "sg:province":"Z\u00fcrich",
    "sg:tags":[
        "filter",
        "air"
    ],
    "wof:name":"Elbaron Sa",
    "wof:placetype":"venue"
},
  "geometry": {"coordinates":[6.141425,46.183311],"type":"Point"}
}