{
  "type": "Feature",
  "properties": {
    "iso:country":"CH",
    "sg:address":"Pestalozzi Place 9 1400 Yverdon-les-bains. Postfach",
    "sg:city":"Cheseaux-nor\u00e9az",
    "sg:orig_category":"Fotografisches Gewerbe U fotografische Laboratorien",
    "sg:phone":"+41 24 425 71 85",
    "sg:postcode":"1400",
    "sg:province":"Vaud",
    "wof:name":"L'atelier Photographique, Porchet Thierry Atelier De Photographie, D\u00e9veloppement De Photos De Presse Etc",
    "wof:placetype":"venue"
},
  "geometry": {"coordinates":[6.6411590576,46.7787094116],"type":"Point"}
}