{
  "type": "Feature",
  "properties": {
    "iso:country":"CH",
    "sg:address":"Zone Industrielle",
    "sg:city":"Grolley",
    "sg:orig_category":"Grosshandel mit Eisenwaren sowie Installationsbedarf f\u00fcr Gas, Wasser U Heizung",
    "sg:phone":"+41 71 923 63 63",
    "sg:postcode":"1772",
    "sg:province":"Fribourg",
    "wof:name":"Lehmann Urs.",
    "wof:placetype":"venue"
},
  "geometry": {"coordinates":[9.0443258286,47.4591636658],"type":"Point"}
}