{
  "type": "Feature",
  "properties": {
    "iso:country":"CH",
    "sg:address":"Steinacherstrasse 18",
    "sg:city":"Illnau",
    "sg:orig_category":"Religi\u00f6se Vereinigungen divers",
    "sg:phone":"+41 52 346 19 27",
    "sg:postcode":"8308",
    "sg:province":"Z\u00fcrich",
    "wof:name":"Oekum.bazarverein Illnau",
    "wof:placetype":"venue"
},
  "geometry": {"coordinates":[8.7127466202,47.4114112854],"type":"Point"}
}