{
  "type": "Feature",
  "properties": {
    "iso:country":"CH",
    "sg:address":"Neustadt 57",
    "sg:city":"Schaffhausen",
    "sg:orig_category":"Informatikdienste Sonstige mit der Informatik verbundene T\u00e4tigkeiten",
    "sg:phone":"+41 52 625 24 20",
    "sg:postcode":"8200",
    "sg:province":"Schaffhausen",
    "wof:name":"The Brain Company Gmbh",
    "wof:placetype":"venue"
},
  "geometry": {"coordinates":[8.6320848465,47.6954803467],"type":"Point"}
}