{
  "type": "Feature",
  "properties": {
    "iso:country":"CH",
    "sg:address":"Avenue De Collonge 29",
    "sg:city":"Montreux",
    "sg:orig_category":"Detailhandel mit elektrischen Haushalts-,Radio U Fernsehger\u00e4ten sowie Musikinstrumenten",
    "sg:postcode":"1820",
    "sg:province":"Vaud",
    "wof:name":"Sadiam, Gafner L.",
    "wof:placetype":"venue"
},
  "geometry": {"coordinates":[6.9256329536,46.424697876],"type":"Point"}
}