{
  "type": "Feature",
  "properties": {
    "iso:country":"CH",
    "sg:address":"S\u00e4ntisstrasse 13",
    "sg:city":"Wallisellen",
    "sg:orig_category":"Stukkateurgewerbe, Gipserei U Verputzerei",
    "sg:postcode":"8304",
    "sg:province":"Z\u00fcrich",
    "wof:name":"Cafazzo-manhart G.",
    "wof:placetype":"venue"
},
  "geometry": {"coordinates":[8.595416069,47.4140892029],"type":"Point"}
}