{
  "type": "Feature",
  "properties": {
    "iso:country":"CH",
    "sg:address":"Bofeld 6340 Baar. Postfach 2459",
    "sg:city":"Baar",
    "sg:orig_category":"Non-Classified Establishments",
    "sg:postcode":"6340",
    "sg:province":"Zug",
    "wof:name":"Herby's Kiosk Beatrice Vogler",
    "wof:placetype":"venue"
},
  "geometry": {"coordinates":[9.6383018494,47.449005127],"type":"Point"}
}