{
  "type": "Feature",
  "properties": {
    "iso:country":"CH",
    "sg:address":"1041",
    "sg:city":"Boulens",
    "sg:orig_category":"Herstellung von Metallkonstruktionen",
    "sg:phone":"+41 21 905 36 92",
    "sg:postcode":"1041",
    "sg:province":"Vaud",
    "wof:name":"Clot Jacques-henri",
    "wof:placetype":"venue"
},
  "geometry": {"coordinates":[6.7201547623,46.6814537048],"type":"Point"}
}