{
  "type": "Feature",
  "properties": {
    "iso:country":"CH",
    "sg:address":"Via Industria",
    "sg:city":"Lamone",
    "sg:orig_category":"Herstellung von Damen U M\u00e4dchenoberbekleidung Herstellung von Herren U Knabenoberbekleidung",
    "sg:phone":"+41 91 605 22 27",
    "sg:postcode":"6814",
    "sg:province":"Ticino",
    "wof:name":"Swisstex Logistics Ag",
    "wof:placetype":"venue"
},
  "geometry": {"coordinates":[8.9248304367,46.0384063721],"type":"Point"}
}