{
  "type": "Feature",
  "properties": {
    "iso:country":"CH",
    "sg:address":"Rue Des Vernes 3",
    "sg:city":"Meyrin",
    "sg:orig_category":"Sonstige Kultur U Unterhaltungseinrichtungen",
    "sg:phone":"+41 22 782 67 85",
    "sg:postcode":"1217",
    "sg:province":"Gen\u00e8ve",
    "wof:name":"Jardin Robinson De Meyrin",
    "wof:placetype":"venue"
},
  "geometry": {"coordinates":[6.0747652054,46.233581543],"type":"Point"}
}