{
  "type": "Feature",
  "properties": {
    "iso:country":"CH",
    "sg:address":"Moulins Rue Des 51 2000 Neuenburg Case Postale",
    "sg:city":"Neuenburg",
    "sg:orig_category":"Wirtschaftspr\u00fcfung, Steuerberatung U Treuhand",
    "sg:phone":"+41 32 729 00 50",
    "sg:postcode":"2000",
    "sg:province":"Neuch\u00e2tel",
    "wof:name":"Ernst & Young Sa",
    "wof:placetype":"venue"
},
  "geometry": {"coordinates":[6.927230835,46.9932136536],"type":"Point"}
}