{
  "type": "Feature",
  "properties": {
    "iso:country":"CH",
    "sg:address":"Appartementhaus Rothorn",
    "sg:city":"Melchsee-frutt",
    "sg:classifiers":[
        {
            "category":"Travel",
            "subcategory":"Hotels & Motels",
            "type":"Entertainment"
        }
    ],
    "sg:postcode":"6068",
    "sg:province":"Obwalden",
    "sg:tags":[
        "hotels",
        "mit",
        "restaurant"
    ],
    "wof:name":"Hotel Reinhard Ag",
    "wof:placetype":"venue"
},
  "geometry": {"coordinates":[8.2701473236,46.7734031677],"type":"Point"}
}