{
  "type": "Feature",
  "properties": {
    "addr:full":"Compognastrasse Thusis Graubunden 7430",
    "addr:postcode":"7430",
    "addr:street":"Compognastrasse;Graubunden",
    "iso:country":"CH",
    "sg:address":"Compognastrasse",
    "sg:city":"Thusis",
    "sg:orig_category":"Dachdeckerei Zimmerei, Dachdeckerei, Bauspenglerei U Abdichtung",
    "sg:phone":"+41 19501518",
    "sg:postcode":"7430",
    "sg:province":"Graubunden",
    "wof:name":"Wintsch Bedachungen",
    "wof:placetype":"venue"
},
  "geometry": {"coordinates":[8.794641,47.364002],"type":"Point"}
}