{
  "type": "Feature",
  "properties": {
    "iso:country":"CH",
    "sg:address":"Schosshaldenstrasse 37",
    "sg:city":"Bern",
    "sg:classifiers":[
        {
            "category":"Education",
            "subcategory":"Library",
            "type":"Public Place"
        }
    ],
    "sg:phone":"+41 31 352 21 64",
    "sg:postcode":"3006",
    "sg:province":"Bern",
    "sg:tags":[
        "u",
        "bibliotheken",
        "archive"
    ],
    "wof:name":"Regionalbibliothek Bern Zweigstelle Laubegg",
    "wof:placetype":"venue"
},
  "geometry": {"coordinates":[7.465715,46.947323],"type":"Point"}
}