{
  "type": "Feature",
  "properties": {
    "iso:country":"CH",
    "sg:address":"Bahnhofstrasse 3",
    "sg:city":"Amriswil",
    "sg:orig_category":"Mechanik",
    "sg:postcode":"8580",
    "sg:province":"Thurgau",
    "wof:name":"Schori Ernst",
    "wof:placetype":"venue"
},
  "geometry": {"coordinates":[9.2996606827,47.5459365845],"type":"Point"}
}