{
  "type": "Feature",
  "properties": {
    "iso:country":"CH",
    "sg:address":"Sundgauerstrasse 18",
    "sg:city":"Basel",
    "sg:orig_category":"Druckweiterverarbeitung Siebdruck",
    "sg:phone":"+41 61 321 78 65",
    "sg:postcode":"4055",
    "sg:province":"Basel-Stadt",
    "wof:name":"Reinhard Spinnler Buchbinderei & Pr\u00e4gedruck",
    "wof:placetype":"venue"
},
  "geometry": {"coordinates":[7.5629549026,47.5653953552],"type":"Point"}
}