{
  "type": "Feature",
  "properties": {
    "iso:country":"CH",
    "sg:address":"Route Principale 3",
    "sg:city":"Corban",
    "sg:orig_category":"Kosmetikinstitute",
    "sg:phone":"+41 32 438 86 36",
    "sg:postcode":"2826",
    "sg:province":"Jura",
    "wof:name":"Claudine Bron Institut De Beaut\u00e9",
    "wof:placetype":"venue"
},
  "geometry": {"coordinates":[7.4743528366,47.3474121094],"type":"Point"}
}