{
  "type": "Feature",
  "properties": {
    "iso:country":"CH",
    "sg:address":"Badstubenstrasse 11 8880 Walenstadt. Postfach 92",
    "sg:city":"Walenstadt",
    "sg:orig_category":"Grosshandel mit Erzen U Metallen Sonstiger Detailhandel mit Metallwaren, Anstrichmitteln, Glaswaren,",
    "sg:phone":"+41 71 755 15 10",
    "sg:postcode":"8880",
    "sg:province":"St. Gallen",
    "wof:name":"Sfs Stadler Heerbrugg Ag Eisenwaren & Baumaterialien",
    "wof:placetype":"venue"
},
  "geometry": {"coordinates":[9.5404472351,47.3787269592],"type":"Point"}
}