{
  "type": "Feature",
  "properties": {
    "iso:country":"CH",
    "sg:address":"Dorfstrasse 2",
    "sg:city":"Trubschachen",
    "sg:orig_category":"Wohnheime",
    "sg:phone":"+41 34 495 61 96",
    "sg:postcode":"3555",
    "sg:province":"Bern",
    "wof:name":"Asylanten-unterkunft",
    "wof:placetype":"venue"
},
  "geometry": {"coordinates":[7.8461389542,46.9226303101],"type":"Point"}
}