{
  "type": "Feature",
  "properties": {
    "addr:full":"Avenue Des Boveresses 54 Lausanne Vaud 1010",
    "addr:housenumber":"54",
    "addr:postcode":"1010",
    "addr:street":"Avenue Des Boveresses",
    "iso:country":"CH",
    "sg:address":"Avenue Des Boveresses 54",
    "sg:city":"Lausanne",
    "sg:orig_category":"Architektur U Ingenieurb\u00fcros",
    "sg:phone":"+41 21 652 14 63",
    "sg:postcode":"1010",
    "sg:province":"Vaud",
    "wof:name":"Geberit Conseils Techniques Sa",
    "wof:placetype":"venue"
},
  "geometry": {"coordinates":[6.66772,46.535473],"type":"Point"}
}