{
  "type": "Feature",
  "properties": {
    "iso:country":"CH",
    "sg:address":"Berg",
    "sg:city":"Weissbad",
    "sg:orig_category":"Bauschreinerei Innenausbau",
    "sg:phone":"+41 26 674 31 55",
    "sg:postcode":"9057",
    "sg:province":"Appenzell Innerhoden",
    "wof:name":"Arno B\u00fcrgy Antikschreinerei",
    "wof:placetype":"venue"
},
  "geometry": {"coordinates":[7.14476,46.898251],"type":"Point"}
}