{
  "type": "Feature",
  "properties": {
    "iso:country":"CH",
    "sg:address":"Grenzstrasse 7",
    "sg:city":"Winterthur",
    "sg:classifiers":[
        {
            "category":"Restaurant",
            "type":"Food & Drink"
        }
    ],
    "sg:phone":"+41 52 202 20 54",
    "sg:postcode":"8406",
    "sg:province":"Z\u00fcrich",
    "wof:name":"Restaurant Grenzhof",
    "wof:placetype":"venue"
},
  "geometry": {"coordinates":[8.7124834061,47.4908027649],"type":"Point"}
}