{
  "type": "Feature",
  "properties": {
    "iso:country":"CH",
    "sg:address":"Via Molino",
    "sg:city":"Ascona",
    "sg:orig_category":"Blumen U Zierpflanzenbau",
    "sg:phone":"+41 91 791 00 40",
    "sg:postcode":"6612",
    "sg:province":"Ticino",
    "wof:name":"Zanoli & Brun",
    "wof:placetype":"venue"
},
  "geometry": {"coordinates":[8.77754,46.162159],"type":"Point"}
}