{
  "type": "Feature",
  "properties": {
    "iso:country":"CH",
    "sg:address":"Rue De Graman 97",
    "sg:city":"Puplinge",
    "sg:orig_category":"Detailhandel mit B\u00fcchern, Zeitungen, Schreib U Papeteriewaren",
    "sg:phone":"+41 32 365 13 14",
    "sg:postcode":"1241",
    "sg:province":"Gen\u00e8ve",
    "wof:name":"Afa-organisation Ag",
    "wof:placetype":"venue"
},
  "geometry": {"coordinates":[7.259232,47.121204],"type":"Point"}
}