{
  "type": "Feature",
  "properties": {
    "iso:country":"CH",
    "sg:address":"Bahnhofstrasse 1",
    "sg:city":"B\u00fclach",
    "sg:orig_category":"Detailhandel mit Schuhen Detailhandel mit Schuhen U Lederwaren",
    "sg:phone":"+41 18620760",
    "sg:postcode":"8180",
    "sg:province":"Z\u00fcrich",
    "wof:name":"G & C Shoes Keller Corinne",
    "wof:placetype":"venue"
},
  "geometry": {"coordinates":[8.5400123596,47.5193023682],"type":"Point"}
}