{
  "type": "Feature",
  "properties": {
    "iso:country":"CH",
    "sg:address":"Aarbergstrasse 29",
    "sg:city":"Biel/bienne",
    "sg:orig_category":"Unclassifiable Establishments",
    "sg:postcode":"2503",
    "sg:province":"Bern",
    "wof:name":"Yfo E. Beer",
    "wof:placetype":"venue"
},
  "geometry": {"coordinates":[7.2395300865,47.1306343079],"type":"Point"}
}