{
  "type": "Feature",
  "properties": {
    "addr:full":"Schwertstrasse 4 8200 Schaffhausen. Postfach 1025 Schaffhausen Schaffhausen 8201",
    "addr:housenumber":"4",
    "addr:postcode":"8200 schaffhausen.;1025;8201",
    "addr:street":"Schwertstrasse;Postfach",
    "iso:country":"CH",
    "sg:address":"Schwertstrasse 4 8200 Schaffhausen. Postfach 1025",
    "sg:city":"Schaffhausen",
    "sg:orig_category":"Architekturb\u00fcros",
    "sg:phone":"+41 52 625 39 85",
    "sg:postcode":"8201",
    "sg:province":"Schaffhausen",
    "wof:name":"Stefan M\u00fcller Architekten & Planer",
    "wof:placetype":"venue"
},
  "geometry": {"coordinates":[8.633067,47.697304],"type":"Point"}
}