{
  "type": "Feature",
  "properties": {
    "iso:country":"CH",
    "sg:address":"Obere Rotenwies 19",
    "sg:city":"Gais",
    "sg:orig_category":"Pensionen mit Restaurant",
    "sg:phone":"+41 71 793 14 41",
    "sg:postcode":"9056",
    "sg:province":"Appenzell Ausserrhoden",
    "wof:name":"Pension Alpenr\u00f6sli",
    "wof:placetype":"venue"
},
  "geometry": {"coordinates":[9.4632720947,47.3676261902],"type":"Point"}
}