{
  "type": "Feature",
  "properties": {
    "iso:country":"CH",
    "sg:address":"Waffenplatzstrasse 15",
    "sg:city":"Solothurn",
    "sg:orig_category":"Herstellung von Uhren",
    "sg:postcode":"4500",
    "sg:province":"Solothurn",
    "wof:name":"Walliser, Georges",
    "wof:placetype":"venue"
},
  "geometry": {"coordinates":[7.543680191,47.2048721313],"type":"Point"}
}