{
  "type": "Feature",
  "properties": {
    "iso:country":"CH",
    "sg:address":"Schreinerstrasse 1",
    "sg:city":"St.gallen",
    "sg:orig_category":"Berufliche Weiterbildung, Erwachsenenbildung Informatikschulen",
    "sg:phone":"+41 71 222 27 68",
    "sg:postcode":"9000",
    "sg:province":"St. Gallen",
    "wof:name":"Ausbildungszentrum Credit Suisse",
    "wof:placetype":"venue"
},
  "geometry": {"coordinates":[9.373128,47.422569],"type":"Point"}
}