{
  "type": "Feature",
  "properties": {
    "iso:country":"CH",
    "sg:address":"Gamschol 1841.",
    "sg:city":"Gams",
    "sg:orig_category":"D\u00e4mmung gegen K\u00e4lte, W\u00e4rme, Schall U Ersch\u00fctterung",
    "sg:phone":"+41 81 771 18 15",
    "sg:postcode":"9473",
    "sg:province":"St. Gallen",
    "wof:name":"Schneider Isolierungen.",
    "wof:placetype":"venue"
},
  "geometry": {"coordinates":[9.4479351044,47.2134361267],"type":"Point"}
}