{
  "type": "Feature",
  "properties": {
    "iso:country":"CH",
    "sg:address":"Sch\u00f6nblickstrasse 3",
    "sg:city":"Meggen",
    "sg:orig_category":"Herstellung von sonstigen Erzeugnissen",
    "sg:phone":"+41 21 792 16 42",
    "sg:postcode":"6045",
    "sg:province":"Luzern",
    "wof:name":"Nit Network International Trading S\u00e0rl Comm. De Plantes Artificielles",
    "wof:placetype":"venue"
},
  "geometry": {"coordinates":[6.7025499344,46.5161094666],"type":"Point"}
}