{
  "type": "Feature",
  "properties": {
    "iso:country":"CH",
    "sg:address":"Chemin De Bas-de-plan 11",
    "sg:city":"Bussigny-lausanne",
    "sg:orig_category":"Immobilienwesen Vermietung U Verpachtung von eigenen Immobilien",
    "sg:phone":"+41 21 701 15 29",
    "sg:postcode":"1030",
    "sg:province":"Vaud",
    "wof:name":"Palica Immobili\u00e8re Sa",
    "wof:placetype":"venue"
},
  "geometry": {"coordinates":[6.5607690811,46.545337677],"type":"Point"}
}