{
  "type": "Feature",
  "properties": {
    "addr:full":"Dufourstrasse 17 Biel/bienne Bern 2502",
    "addr:housenumber":"17",
    "addr:postcode":"2502",
    "addr:street":"Dufourstrasse",
    "iso:country":"CH",
    "sg:address":"Dufourstrasse 17",
    "sg:city":"Biel/bienne",
    "sg:orig_category":"Arztpraxen",
    "sg:phone":"+41 32 323 17 23",
    "sg:postcode":"2502",
    "sg:province":"Bern",
    "wof:name":"Dres Med. Taddei & B\u00f6siger Spezial\u00e4rztinnen Fmh",
    "wof:placetype":"venue"
},
  "geometry": {"coordinates":[7.247434,47.139885],"type":"Point"}
}