{
  "type": "Feature",
  "properties": {
    "iso:country":"CH",
    "sg:address":"Schulstrasse 75",
    "sg:city":"Schlieren",
    "sg:orig_category":"Unclassifiable Establishments",
    "sg:postcode":"8952",
    "sg:province":"Z\u00fcrich",
    "wof:name":"Money-bras Reisen Und Service, Nunes",
    "wof:placetype":"venue"
},
  "geometry": {"coordinates":[8.4615373611,47.3964996338],"type":"Point"}
}