{
  "type": "Feature",
  "properties": {
    "iso:country":"CH",
    "sg:address":"Bahnhofstrasse 36 8560 M\u00e4rstetten. Postfach 141",
    "sg:city":"M\u00e4rstetten",
    "sg:orig_category":"Baugewerbe Dachdeckerei",
    "sg:phone":"+41 71 657 14 11",
    "sg:postcode":"8560",
    "sg:province":"Thurgau",
    "wof:name":"Walker Dach + Wand",
    "wof:placetype":"venue"
},
  "geometry": {"coordinates":[9.065798,47.591473],"type":"Point"}
}