{
  "type": "Feature",
  "properties": {
    "addr:full":"Rotbachweg 8 Hellb\u00fchl Luzern 6016",
    "addr:housenumber":"8",
    "addr:postcode":"6016",
    "addr:street":"Rotbachweg",
    "iso:country":"CH",
    "sg:address":"Rotbachweg 8",
    "sg:city":"Hellb\u00fchl",
    "sg:orig_category":"Allgemeiner Hochbau Strassenbau",
    "sg:phone":"+41 41 467 13 67",
    "sg:postcode":"6016",
    "sg:province":"Luzern",
    "wof:name":"Franz Krummenacher Baugesch\u00e4ft & Ger\u00fcstbau",
    "wof:placetype":"venue"
},
  "geometry": {"coordinates":[8.201575,47.070953],"type":"Point"}
}