{
  "type": "Feature",
  "properties": {
    "iso:country":"CH",
    "sg:address":"B\u00fcchsweg 10",
    "sg:city":"Olten",
    "sg:orig_category":"Elektrizit\u00e4tsversorgung",
    "sg:phone":"+41 62 295 18 18",
    "sg:postcode":"4600",
    "sg:province":"Solothurn",
    "wof:name":"Remac Umwelttechnik Mark R.",
    "wof:placetype":"venue"
},
  "geometry": {"coordinates":[7.9195170403,47.3491172791],"type":"Point"}
}