{
  "type": "Feature",
  "properties": {
    "iso:country":"CH",
    "sg:address":"Bahnhofstrasse 23",
    "sg:city":"Bettlach",
    "sg:orig_category":"RESTAURANTS: TEA-ROOMS",
    "sg:phone":"+41 65551832",
    "sg:postcode":"2544",
    "sg:province":"Solothurn",
    "wof:name":"Zbinden Mara",
    "wof:placetype":"venue"
},
  "geometry": {"coordinates":[7.4272961617,47.1956672668],"type":"Point"}
}