{
  "type": "Feature",
  "properties": {
    "iso:country":"CH",
    "sg:address":"M\u00fclistrasse 3",
    "sg:city":"Altendorf",
    "sg:classifiers":[
        {
            "category":"Restaurant",
            "type":"Food & Drink"
        }
    ],
    "sg:phone":"+41 55 442 26 66",
    "sg:postcode":"8852",
    "sg:province":"Schwyz",
    "wof:name":"Restaurant Samarkand",
    "wof:placetype":"venue"
},
  "geometry": {"coordinates":[8.8486881256,47.1845397949],"type":"Point"}
}