{
  "type": "Feature",
  "properties": {
    "iso:country":"CH",
    "sg:address":"Muzy Rue 7",
    "sg:city":"Gen\u00e8ve",
    "sg:orig_category":"Unclassifiable Establishments",
    "sg:postcode":"1207",
    "sg:province":"Gen\u00e8ve",
    "wof:name":"L\u00e9man Services S\u00e0rl",
    "wof:placetype":"venue"
},
  "geometry": {"coordinates":[6.1563649178,46.2038650513],"type":"Point"}
}