{
  "type": "Feature",
  "properties": {
    "iso:country":"CH",
    "sg:address":"Bettlachstrasse 3",
    "sg:city":"Grenchen",
    "sg:orig_category":"Herstellung von Schmuck, Gold U Silberschmiedwaren",
    "sg:phone":"+41 41 410 21 12",
    "sg:postcode":"2540",
    "sg:province":"Solothurn",
    "wof:name":"Liefert Ren\u00e9, Goldschmied",
    "wof:placetype":"venue"
},
  "geometry": {"coordinates":[8.3063211441,47.0527420044],"type":"Point"}
}