{
  "type": "Feature",
  "properties": {
    "iso:country":"CH",
    "sg:address":"Dorfstrasse 52 4057 Basel. Postfach",
    "sg:city":"Basel",
    "sg:orig_category":"Instandhaltung U Reparatur von Automobilen",
    "sg:phone":"+41 61 631 03 58",
    "sg:postcode":"4051",
    "sg:province":"Basel-Stadt",
    "wof:name":"Steinbacher Import, Sigg Gebhard Fahrzeuge; Import",
    "wof:placetype":"venue"
},
  "geometry": {"coordinates":[7.5929188728,47.5844497681],"type":"Point"}
}