{
  "type": "Feature",
  "properties": {
    "iso:country":"CH",
    "sg:address":"D\u00fcbendorfstrasse",
    "sg:city":"F\u00e4llanden",
    "sg:orig_category":"Gesundheitswesen",
    "sg:phone":"+41 18254147",
    "sg:postcode":"8117",
    "sg:province":"Z\u00fcrich",
    "wof:name":"Ergotherapiezentrum F\u00e4llanden, Inge Saur",
    "wof:placetype":"venue"
},
  "geometry": {"coordinates":[8.6332302094,47.3746032715],"type":"Point"}
}