{
  "type": "Feature",
  "properties": {
    "iso:country":"CH",
    "sg:address":"P\u00fcntstrasse 4",
    "sg:city":"Niederhasli",
    "sg:orig_category":"Grosshandel mit sonstigen Getr\u00e4nken",
    "sg:phone":"+41 18852266",
    "sg:postcode":"8155",
    "sg:province":"Z\u00fcrich",
    "wof:name":"Fruitag Ag",
    "wof:placetype":"venue"
},
  "geometry": {"coordinates":[8.4897632599,47.4811325073],"type":"Point"}
}