{
  "type": "Feature",
  "properties": {
    "iso:country":"CH",
    "sg:address":"Sur La Combe Bruquelin 25",
    "sg:city":"Porrentruy",
    "sg:orig_category":"Grosshandel mit Getr\u00e4nken Grosshandel mit Wein U Spirituosen",
    "sg:phone":"+41 79 251 16 74",
    "sg:postcode":"2900",
    "sg:province":"Jura",
    "wof:name":"Valmi Sa",
    "wof:placetype":"venue"
},
  "geometry": {"coordinates":[7.0901741982,47.427986145],"type":"Point"}
}