{
  "type": "Feature",
  "properties": {
    "iso:country":"CH",
    "sg:address":"Englischgrusstrasse 14",
    "sg:city":"Glis",
    "sg:orig_category":"Instandhaltung U Reparatur von Automobilen",
    "sg:phone":"+41 32 953 11 87",
    "sg:postcode":"3902",
    "sg:province":"Valais",
    "wof:name":"Garage Salzmann",
    "wof:placetype":"venue"
},
  "geometry": {"coordinates":[6.9572901726,47.2244682312],"type":"Point"}
}