{
  "type": "Feature",
  "properties": {
    "addr:full":"Grundstrasse 10a 8712 St\u00e4fa. Postfach St\u00e4fa Z\u00fcrich 8712",
    "addr:housenumber":"10a",
    "addr:postcode":"8712;8712",
    "addr:street":"Grundstrasse;Postfach Staefa Zuerich",
    "iso:country":"CH",
    "sg:address":"Grundstrasse 10a 8712 St\u00e4fa. Postfach",
    "sg:city":"St\u00e4fa",
    "sg:orig_category":"Detailhandel mit Bekleidung",
    "sg:phone":"+41 17962324",
    "sg:postcode":"8712",
    "sg:province":"Z\u00fcrich",
    "wof:name":"Henggeler Catherine Gmbh Entwicklung, Produktion U. Handel Von Artikel Im Bereich Mode, Bekleidung, Innenausstattung",
    "wof:placetype":"venue"
},
  "geometry": {"coordinates":[8.726304,47.241116],"type":"Point"}
}