{
  "type": "Feature",
  "properties": {
    "iso:country":"CH",
    "sg:address":"Holbeinstrasse 68",
    "sg:city":"Basel",
    "sg:orig_category":"Unternehmensberatung",
    "sg:phone":"+41 61 228 99 09",
    "sg:postcode":"4051",
    "sg:province":"Basel-Stadt",
    "wof:name":"Kresta, Schnider & Partners, Management Consultants",
    "wof:placetype":"venue"
},
  "geometry": {"coordinates":[7.5831971169,47.551525116],"type":"Point"}
}