{
  "type": "Feature",
  "properties": {
    "iso:country":"CH",
    "sg:address":"Bahnhofstrasse 16",
    "sg:city":"Zug",
    "sg:classifiers":[
        {
            "category":"Professional",
            "subcategory":"Employment Agencies",
            "type":"Services"
        }
    ],
    "sg:postcode":"6300",
    "sg:province":"Zug",
    "sg:tags":[
        "personal",
        "u",
        "stellenvermittlung"
    ],
    "wof:name":"Vip Consulting Kretz Markus Beratung Von Firmen U. Personen In Sach, Personal- U. Finanzfragen Usw",
    "wof:placetype":"venue"
},
  "geometry": {"coordinates":[8.4703445435,47.3574867249],"type":"Point"}
}