{
  "type": "Feature",
  "properties": {
    "iso:country":"CH",
    "sg:address":"5014 Gretzenbach. Postfach 2",
    "sg:city":"Gretzenbach",
    "sg:orig_category":"Sportvereine Ballsport Fussball",
    "sg:phone":"+41 62 849 74 27",
    "sg:postcode":"5014",
    "sg:province":"Solothurn",
    "wof:name":"Fc Gretzenbach",
    "wof:placetype":"venue"
},
  "geometry": {"coordinates":[7.9965882301,47.3613014221],"type":"Point"}
}