{
  "type": "Feature",
  "properties": {
    "addr:full":"Bahnhofstrasse 24 Z\u00fcrich Z\u00fcrich 8001",
    "addr:housenumber":"24",
    "addr:postcode":"8001",
    "addr:street":"Bahnhofstrasse",
    "iso:country":"CH",
    "sg:address":"Bahnhofstrasse 24",
    "sg:city":"Z\u00fcrich",
    "sg:orig_category":"Advokaturb\u00fcros",
    "sg:phone":"+41 31 352 11 88",
    "sg:postcode":"8001",
    "sg:province":"Z\u00fcrich",
    "wof:name":"Hodler & Emmenegger",
    "wof:placetype":"venue"
},
  "geometry": {"coordinates":[7.462605,46.938995],"type":"Point"}
}