{
  "type": "Feature",
  "properties": {
    "iso:country":"CH",
    "sg:address":"Chemin Du Jura 14",
    "sg:city":"Crans-pr\u00e8s-c\u00e9ligny",
    "sg:orig_category":"Unclassifiable Establishments",
    "sg:phone":"+41 31 889 05 82",
    "sg:postcode":"1299",
    "sg:province":"Vaud",
    "wof:name":"Burrens Burehofm\u00e4rit Beeren & Gem\u00fcse",
    "wof:placetype":"venue"
},
  "geometry": {"coordinates":[7.3602480888,46.9157333374],"type":"Point"}
}