{
  "type": "Feature",
  "properties": {
    "iso:country":"CH",
    "sg:address":"Avenue Juste-olivier 16 1006 Lausanne Case Postale 1436",
    "sg:city":"Lausanne",
    "sg:orig_category":"Herstellung von medizinischen U chirurgischen Ger\u00e4ten sowie orthop\u00e4dischen Vorrichtungen Zahntechnis",
    "sg:phone":"+41 61 711 34 38",
    "sg:postcode":"1001",
    "sg:province":"Vaud",
    "wof:name":"Teuber Christoph, Zahntechn. Labor",
    "wof:placetype":"venue"
},
  "geometry": {"coordinates":[7.6002430916,47.5062522888],"type":"Point"}
}