{
  "type": "Feature",
  "properties": {
    "iso:country":"CH",
    "sg:address":"Rue Du Jura 19 1030 Bussigny-lausanne Case Postale 300",
    "sg:city":"Bussigny-lausanne",
    "sg:orig_category":"Allgemeiner Hochbau Herstellung von Hebezeugen U F\u00f6rdermitteln",
    "sg:phone":"+41 21 701 35 21",
    "sg:postcode":"1030",
    "sg:province":"Vaud",
    "wof:name":"Maltech-baudrocco Sa",
    "wof:placetype":"venue"
},
  "geometry": {"coordinates":[6.549573,46.554722],"type":"Point"}
}