{
  "type": "Feature",
  "properties": {
    "iso:country":"CH",
    "sg:address":"Grederstrasse 28",
    "sg:city":"Bellach",
    "sg:classifiers":[
        {
            "category":"Communications",
            "subcategory":"Film & Video Production",
            "type":"Services"
        }
    ],
    "sg:phone":"+41 32 618 39 86",
    "sg:postcode":"4512",
    "sg:province":"Solothurn",
    "sg:tags":[
        "videofilmherstellung",
        "u"
    ],
    "wof:name":"Video Studio Gasser",
    "wof:placetype":"venue"
},
  "geometry": {"coordinates":[7.5093431473,47.2106399536],"type":"Point"}
}