{
  "type": "Feature",
  "properties": {
    "iso:country":"CH",
    "sg:address":"Rue De La Poste 16",
    "sg:city":"Martigny",
    "sg:orig_category":"Advokaturb\u00fcros Notariate",
    "sg:phone":"+41 27 722 18 80",
    "sg:postcode":"1920",
    "sg:province":"Valais",
    "wof:name":"Jean-louis Bruchez Etude D'avocat & Notaire",
    "wof:placetype":"venue"
},
  "geometry": {"coordinates":[7.076966,46.102543],"type":"Point"}
}