{
  "type": "Feature",
  "properties": {
    "iso:country":"CH",
    "sg:address":"Village",
    "sg:city":"Vaulruz",
    "sg:orig_category":"Sanit\u00e4r U Heizungsinstallation Sanit\u00e4rinstallation",
    "sg:phone":"+41 26 912 61 10",
    "sg:postcode":"1627",
    "sg:province":"Fribourg",
    "wof:name":"Ars\u00e8ne Progin Sanitaires & Chauffages",
    "wof:placetype":"venue"
},
  "geometry": {"coordinates":[6.9883079529,46.6200714111],"type":"Point"}
}