{
  "type": "Feature",
  "properties": {
    "addr:full":"Junkholz Amlikon Thurgau 8514",
    "addr:postcode":"8514",
    "iso:country":"CH",
    "sg:address":"Junkholz",
    "sg:city":"Amlikon",
    "sg:orig_category":"Detailhandel mit Brot, Back U S\u00fcsswaren",
    "sg:phone":"+41 71 651 14 33",
    "sg:postcode":"8514",
    "sg:province":"Thurgau",
    "wof:name":"Bartholdi M.",
    "wof:placetype":"venue"
},
  "geometry": {"coordinates":[9.05828,47.570133],"type":"Point"}
}