{
  "type": "Feature",
  "properties": {
    "iso:country":"CH",
    "sg:address":"Unterdorf",
    "sg:city":"Saanen",
    "sg:orig_category":"Detailhandel mit Bekleidung",
    "sg:phone":"+41 33 744 41 65",
    "sg:postcode":"3792",
    "sg:province":"Bern",
    "wof:name":"Erwin Hofer Textilien",
    "wof:placetype":"venue"
},
  "geometry": {"coordinates":[7.258111,46.489372],"type":"Point"}
}