{
  "type": "Feature",
  "properties": {
    "iso:country":"CH",
    "sg:address":"Freiestrasse 12",
    "sg:city":"Uster",
    "sg:orig_category":"Detailhandel mit Sportartikeln Fachdetailhandel in Verkaufsr\u00e4umen",
    "sg:phone":"+41 19404947",
    "sg:postcode":"8610",
    "sg:province":"Z\u00fcrich",
    "wof:name":"Fischli's Sport Shop",
    "wof:placetype":"venue"
},
  "geometry": {"coordinates":[8.7210464478,47.3486442566],"type":"Point"}
}