{
  "type": "Feature",
  "properties": {
    "iso:country":"CH",
    "sg:address":"Seewenstrasse 18",
    "sg:city":"Duggingen",
    "sg:classifiers":[
        {
            "category":"Autos & Motor Vehicles",
            "subcategory":"Auto Supplies",
            "type":"Retail Goods"
        }
    ],
    "sg:phone":"+41 61 741 21 20",
    "sg:postcode":"4202",
    "sg:province":"Basel-Landschaft",
    "sg:tags":[
        "part",
        "spare",
        "motorcycle",
        "accessory"
    ],
    "wof:name":"Dirt-bike Factory",
    "wof:placetype":"venue"
},
  "geometry": {"coordinates":[7.6097798347,47.4363250732],"type":"Point"}
}