{
  "type": "Feature",
  "properties": {
    "iso:country":"CH",
    "sg:address":"Alfred Schindlerstrasse 46",
    "sg:city":"Ebikon",
    "sg:orig_category":"Kauf U Verkauf von Immobilien auf eigene Rechnung Vermietung U Verpachtung von eigenen Immobilien",
    "sg:phone":"+41 41 440 37 65",
    "sg:postcode":"6030",
    "sg:province":"Luzern",
    "wof:name":"Abcr Immobilien Ag",
    "wof:placetype":"venue"
},
  "geometry": {"coordinates":[8.3535518646,47.0883102417],"type":"Point"}
}