{
  "type": "Feature",
  "properties": {
    "iso:country":"CH",
    "sg:address":"1123",
    "sg:city":"Aclens",
    "sg:orig_category":"Pensionskassen",
    "sg:phone":"+41 21 691 91 70",
    "sg:postcode":"1123",
    "sg:province":"Vaud",
    "wof:name":"Fondation De Pr\u00e9voyance En Faveur Du Personnel Des Soci\u00e9t\u00e9s Du Groupe Sun'store (bvg)",
    "wof:placetype":"venue"
},
  "geometry": {"coordinates":[6.5580701828,46.5100784302],"type":"Point"}
}