{
  "type": "Feature",
  "properties": {
    "iso:country":"CH",
    "sg:address":"Bundesplatz 14",
    "sg:city":"Zug",
    "sg:orig_category":"Non-Classified Establishments",
    "sg:phone":"+41 62 771 03 30",
    "sg:postcode":"6300",
    "sg:province":"Zug",
    "wof:name":"Wochen-post Verlag Ag Reinach",
    "wof:placetype":"venue"
},
  "geometry": {"coordinates":[8.1875534058,47.2637329102],"type":"Point"}
}