{
  "type": "Feature",
  "properties": {
    "iso:country":"CH",
    "sg:address":"Rue De La Gare 38",
    "sg:city":"Marin-epagnier",
    "sg:classifiers":[
        {
            "category":"Restaurant",
            "type":"Food & Drink"
        }
    ],
    "sg:phone":"+41 21 799 26 86",
    "sg:postcode":"2074",
    "sg:province":"Neuch\u00e2tel",
    "wof:name":"Restaurant De La Gare",
    "wof:placetype":"venue"
},
  "geometry": {"coordinates":[0.1336299926,47.041431427],"type":"Point"}
}