{
  "type": "Feature",
  "properties": {
    "iso:country":"CH",
    "sg:address":"Herzentalstrasse 5",
    "sg:city":"Dornach",
    "sg:orig_category":"Herstellung von sonstigen Maschinen f\u00fcr bestimmte Verwendung",
    "sg:phone":"+41 878753",
    "sg:postcode":"4143",
    "sg:province":"Solothurn",
    "wof:name":"Loipe Goms",
    "wof:placetype":"venue"
},
  "geometry": {"coordinates":[8.2618379593,46.4867591858],"type":"Point"}
}