{
  "type": "Feature",
  "properties": {
    "iso:country":"CH",
    "sg:address":"Brent Route De 30 1817 Brent. Postfach",
    "sg:city":"Brent",
    "sg:orig_category":"Sonstige mit der Informatik verbundene T\u00e4tigkeiten",
    "sg:postcode":"1817",
    "sg:province":"Vaud",
    "wof:name":"Easy Computing, Eracle Martine Informatique; Cours Et Conseils",
    "wof:placetype":"venue"
},
  "geometry": {"coordinates":[6.9011001587,46.4577255249],"type":"Point"}
}