{
  "type": "Feature",
  "properties": {
    "iso:country":"CH",
    "sg:address":"Kirchenfeld -",
    "sg:city":"Bern",
    "sg:classifiers":[
        {
            "category":"Professional",
            "subcategory":"Art Services",
            "type":"Services"
        }
    ],
    "sg:phone":"+41 22 755 11 94",
    "sg:postcode":"3000",
    "sg:province":"Bern",
    "sg:tags":[
        "export-import"
    ],
    "wof:name":"Guainea Bissau Consulate",
    "wof:placetype":"venue"
},
  "geometry": {"coordinates":[6.16715,46.280289],"type":"Point"}
}