{
  "type": "Feature",
  "properties": {
    "iso:country":"CH",
    "sg:address":"Gewerbeweg 143",
    "sg:city":"Schaanwald",
    "sg:orig_category":"Herstellung von Medikamenten U sonstigen pharmazeutischen Erzeugnissen Herstellung von pharmazeutisc",
    "sg:phone":"+41 55 451 00 00",
    "sg:postcode":"9486",
    "wof:name":"Pharma Base Sa",
    "wof:placetype":"venue"
},
  "geometry": {"coordinates":[8.8020591736,47.2011299133],"type":"Point"}
}