{
  "type": "Feature",
  "properties": {
    "iso:country":"CH",
    "sg:address":"H\u00fcndlerstrasse 67a 8406 Winterthur. Postfach",
    "sg:city":"Winterthur",
    "sg:orig_category":"Softwareentwicklung U beratung",
    "sg:postcode":"8406",
    "sg:province":"Z\u00fcrich",
    "wof:name":"Mwin Werffeli & Co, Informatik Informatik-dienstleistungen",
    "wof:placetype":"venue"
},
  "geometry": {"coordinates":[8.436756134,47.4220352173],"type":"Point"}
}