{
  "type": "Feature",
  "properties": {
    "iso:country":"CH",
    "sg:address":"Via Prati Grandi 1b",
    "sg:city":"Cadenazzo",
    "sg:orig_category":"Non-Classified Establishments",
    "sg:postcode":"6593",
    "sg:province":"Ticino",
    "wof:name":"Rosita Madoglio-kaehr Terapia Lotus",
    "wof:placetype":"venue"
},
  "geometry": {"coordinates":[8.9429588318,46.1508255005],"type":"Point"}
}