{
  "type": "Feature",
  "properties": {
    "iso:country":"CH",
    "sg:address":"Chemin De La Tuilerie 2350 Saignel\u00e9gier. Postfach",
    "sg:city":"Saignel\u00e9gier",
    "sg:orig_category":"Diskotheken, Dancings, Night Clubs",
    "sg:phone":"+41 32 951 23 16",
    "sg:postcode":"2350",
    "sg:province":"Jura",
    "wof:name":"Bar-dancing La Tuillerie Sa",
    "wof:placetype":"venue"
},
  "geometry": {"coordinates":[7.0038361549,47.252784729],"type":"Point"}
}