{
  "type": "Feature",
  "properties": {
    "iso:country":"CH",
    "sg:address":"Melchr\u00fctistrasse 2 8304 Wallisellen. Postfach",
    "sg:city":"Wallisellen",
    "sg:orig_category":"Vermittlung von Immobilien Verwaltung von Immobilien",
    "sg:phone":"+41 18311616",
    "sg:postcode":"8304",
    "sg:province":"Z\u00fcrich",
    "wof:name":"Keller Immobilien Treuhand Ag",
    "wof:placetype":"venue"
},
  "geometry": {"coordinates":[8.5806941986,47.4171676636],"type":"Point"}
}