{
  "type": "Feature",
  "properties": {
    "iso:country":"CH",
    "sg:address":"Spitalgasse 37",
    "sg:city":"Bern",
    "sg:orig_category":"Architektur U Ingenieurb\u00fcros",
    "sg:phone":"+41 19504984",
    "sg:postcode":"3011",
    "sg:province":"Bern",
    "wof:name":"Thommen & Brunner, Architekten",
    "wof:placetype":"venue"
},
  "geometry": {"coordinates":[8.805202,47.379517],"type":"Point"}
}