{
  "type": "Feature",
  "properties": {
    "iso:country":"CH",
    "sg:address":"Route De La Heitera 3 1700 Fribourg Case Postale",
    "sg:city":"Fribourg",
    "sg:orig_category":"Nationale Postdienste",
    "sg:phone":"+41 26 481 13 33",
    "sg:postcode":"1707",
    "sg:province":"Fribourg",
    "wof:name":"La Poste Suisse Fribourg 7 Sch\u00f6nberg",
    "wof:placetype":"venue"
},
  "geometry": {"coordinates":[7.1728310585,46.8106155396],"type":"Point"}
}