{
  "type": "Feature",
  "properties": {
    "iso:country":"CH",
    "sg:address":"Zentralstrasse 133",
    "sg:city":"Wettingen",
    "sg:orig_category":"Tankstellen",
    "sg:phone":"+41 56 426 35 45",
    "sg:postcode":"5430",
    "sg:province":"Aargau",
    "wof:name":"Reinle Ag",
    "wof:placetype":"venue"
},
  "geometry": {"coordinates":[8.3282117844,47.4623985291],"type":"Point"}
}