{
  "type": "Feature",
  "properties": {
    "iso:country":"CH",
    "sg:address":"Flurweg 1",
    "sg:city":"Zuchwil",
    "sg:orig_category":"Erschliessung von Grundst\u00fccken",
    "sg:postcode":"4528",
    "sg:province":"Solothurn",
    "wof:name":"Wohnbau-gen.zuchwil-dorf",
    "wof:placetype":"venue"
},
  "geometry": {"coordinates":[7.5595197678,47.2034339905],"type":"Point"}
}