{
  "type": "Feature",
  "properties": {
    "iso:country":"CH",
    "sg:address":"8953",
    "sg:city":"Dietikon",
    "sg:orig_category":"Betrieb von Sportanlagen",
    "sg:phone":"+41 17401166",
    "sg:postcode":"8953",
    "sg:province":"Z\u00fcrich",
    "wof:name":"Junior Tennis Academy Lerzen C/o Tenniscenter",
    "wof:placetype":"venue"
},
  "geometry": {"coordinates":[8.4037,47.403889],"type":"Point"}
}