{
  "type": "Feature",
  "properties": {
    "iso:country":"CH",
    "sg:address":"Haltenriedstrasse 19 6045 Meggen. Postfach",
    "sg:city":"Meggen",
    "sg:orig_category":"Vermietung U Verpachtung von eigenen Immobilien",
    "sg:phone":"+41 41 378 06 66",
    "sg:postcode":"6045",
    "sg:province":"Luzern",
    "wof:name":"Limo Ag",
    "wof:placetype":"venue"
},
  "geometry": {"coordinates":[8.3770503998,47.0513648987],"type":"Point"}
}