{
  "type": "Feature",
  "properties": {
    "iso:country":"CH",
    "sg:address":"Rennweg 43",
    "sg:city":"Z\u00fcrich",
    "sg:orig_category":"Personal U Stellenvermittlung Unternehmensberatung",
    "sg:phone":"+41 12181444",
    "sg:postcode":"8001",
    "sg:province":"Z\u00fcrich",
    "wof:name":"Inspi Consulting Ag Dienstleistungsunternehmen Im Bereich D. Personalberatung Usw.",
    "wof:placetype":"venue"
},
  "geometry": {"coordinates":[8.5389966965,47.3734436035],"type":"Point"}
}