{
  "type": "Feature",
  "properties": {
    "iso:country":"CH",
    "sg:address":"Chemin Jonchets 19",
    "sg:city":"Presinge",
    "sg:classifiers":[
        {
            "category":"Social Services",
            "subcategory":"Retirement Home",
            "type":"Services"
        }
    ],
    "sg:phone":"+41 22 759 21 19",
    "sg:postcode":"1243",
    "sg:province":"Gen\u00e8ve",
    "sg:tags":[
        "pflegeheime",
        "u",
        "alters"
    ],
    "wof:name":"Pension Belle-epoque Pour Personnes \u00e2g\u00e9es",
    "wof:placetype":"venue"
},
  "geometry": {"coordinates":[6.277673,46.220589],"type":"Point"}
}