{
  "type": "Feature",
  "properties": {
    "iso:country":"CH",
    "sg:address":"Zinkereistrasse 2",
    "sg:city":"Wolfhausen",
    "sg:orig_category":"Herstellung von Ger\u00e4ten der Elektrizit\u00e4tserzeugung, -verteilung u.\u00e4. -Herstellung von Mess U Kontrol",
    "sg:phone":"+41 79 420 63 87",
    "sg:postcode":"8633",
    "sg:province":"Z\u00fcrich",
    "wof:name":"Metag Mess-technik & Automations Ag",
    "wof:placetype":"venue"
},
  "geometry": {"coordinates":[8.2771577835,47.3622322083],"type":"Point"}
}