{
  "type": "Feature",
  "properties": {
    "iso:country":"CH",
    "sg:address":"Bergstrasse 34",
    "sg:city":"Oberrohrdorf",
    "sg:orig_category":"Schulpflegen",
    "sg:phone":"+41 56 496 01 19",
    "sg:postcode":"5452",
    "sg:province":"Aargau",
    "wof:name":"Schulpflege Oberrohrdorf Herrn F.renfer",
    "wof:placetype":"venue"
},
  "geometry": {"coordinates":[8.3209629059,47.4210700989],"type":"Point"}
}