{
  "type": "Feature",
  "properties": {
    "iso:country":"CH",
    "sg:address":"Hauptstrasse 36",
    "sg:city":"Felben",
    "sg:orig_category":"Detailhandel mit Waren verschiedener Art, Hauptrichtung Nahrungsmittel",
    "sg:phone":"+41 52 765 11 29",
    "sg:postcode":"8552",
    "sg:province":"Thurgau",
    "wof:name":"Landi Thurtal",
    "wof:placetype":"venue"
},
  "geometry": {"coordinates":[8.9415187836,47.5787963867],"type":"Point"}
}