{
  "type": "Feature",
  "properties": {
    "iso:country":"CH",
    "sg:address":"Tanniweg",
    "sg:city":"Sulzbach",
    "sg:orig_category":"Vereine Frauen",
    "sg:postcode":"8614",
    "sg:province":"Z\u00fcrich",
    "wof:name":"Frauenverein Sulzbach",
    "wof:placetype":"venue"
},
  "geometry": {"coordinates":[8.7467346191,47.3284301758],"type":"Point"}
}