{
  "type": "Feature",
  "properties": {
    "iso:country":"CH",
    "sg:address":"Rue De Moillebeau 33",
    "sg:city":"Gen\u00e8ve",
    "sg:orig_category":"Arztpraxen",
    "sg:phone":"+41 22 733 44 03",
    "sg:postcode":"1209",
    "sg:province":"Gen\u00e8ve",
    "wof:name":"Dr M\u00e9d. Michel Ribordy M\u00e9decin Sp\u00e9cialiste Fmh",
    "wof:placetype":"venue"
},
  "geometry": {"coordinates":[6.12832,46.22134],"type":"Point"}
}