{
  "type": "Feature",
  "properties": {
    "iso:country":"CH",
    "sg:address":"Gare Place De La 15",
    "sg:city":"Fribourg",
    "sg:orig_category":"Sonstiger spezialisierter Hoch U Tiefbau",
    "sg:postcode":"1700",
    "sg:province":"Fribourg",
    "wof:name":"Z\u00fcger Marcel Gmbh",
    "wof:placetype":"venue"
},
  "geometry": {"coordinates":[8.9527902603,47.1751785278],"type":"Point"}
}