{
  "type": "Feature",
  "properties": {
    "iso:country":"CH",
    "sg:address":"Kanzleistrasse 76",
    "sg:city":"Z\u00fcrich",
    "sg:orig_category":"Non-Classified Establishments",
    "sg:postcode":"8004",
    "sg:province":"Z\u00fcrich",
    "wof:name":"Sportbar Gmbh",
    "wof:placetype":"venue"
},
  "geometry": {"coordinates":[8.5245113373,47.3756713867],"type":"Point"}
}