{
  "type": "Feature",
  "properties": {
    "iso:country":"CH",
    "sg:address":"Chesslergasse 5",
    "sg:city":"Rafz",
    "sg:orig_category":"Schulpflegen",
    "sg:phone":"+41 18690166",
    "sg:postcode":"8197",
    "sg:province":"Z\u00fcrich",
    "wof:name":"Schulpflege Rafz",
    "wof:placetype":"venue"
},
  "geometry": {"coordinates":[8.5371322632,47.6132698059],"type":"Point"}
}