{
  "type": "Feature",
  "properties": {
    "iso:country":"CH",
    "sg:address":"Frauenfelderstrasse 68 8404 Oberwinterthur. Postfach",
    "sg:city":"Oberwinterthur",
    "sg:orig_category":"Erbringung von sonstigen Dienstleistungen f\u00fcr Unterhaltung, Erholung U Freizeit",
    "sg:postcode":"8404",
    "sg:province":"Z\u00fcrich",
    "wof:name":"Live Music Production, Domenico Albanese",
    "wof:placetype":"venue"
},
  "geometry": {"coordinates":[8.7544660568,47.5046615601],"type":"Point"}
}