{
  "type": "Feature",
  "properties": {
    "iso:country":"CH",
    "sg:address":"Place Du Nord",
    "sg:city":"Chexbres",
    "sg:orig_category":"Autogaragen Instandhaltung U Reparatur von Automobilen",
    "sg:phone":"+41 21 946 11 56",
    "sg:postcode":"1071",
    "sg:province":"Vaud",
    "wof:name":"Garage De La Corniche Sa",
    "wof:placetype":"venue"
},
  "geometry": {"coordinates":[6.77624,46.482113],"type":"Point"}
}