{
  "type": "Feature",
  "properties": {
    "iso:country":"CH",
    "sg:address":"Roosstrasse 10b",
    "sg:city":"Wollerau",
    "sg:orig_category":"Bau U Wohngenossenschaften",
    "sg:phone":"+41 56 622 33 59",
    "sg:postcode":"8832",
    "sg:province":"Schwyz",
    "wof:name":"Gen.alterswohungen Niederwil",
    "wof:placetype":"venue"
},
  "geometry": {"coordinates":[8.292252,47.376003],"type":"Point"}
}