{
  "type": "Feature",
  "properties": {
    "iso:country":"CH",
    "sg:address":"Bahnhofstrasse 8",
    "sg:city":"Murten",
    "sg:orig_category":"Elektroinstallation",
    "sg:phone":"+41 26 670 34 26",
    "sg:postcode":"3280",
    "sg:province":"Fribourg",
    "wof:name":"Fischer Beat, Elektrische Installationen",
    "wof:placetype":"venue"
},
  "geometry": {"coordinates":[7.1159272194,46.9260139465],"type":"Point"}
}