{
  "type": "Feature",
  "properties": {
    "iso:country":"CH",
    "sg:address":"Melchnaustrasse 11",
    "sg:city":"Madiswil",
    "sg:orig_category":"Detailhandel mit Milcherzeugnissen U Eiern Verarbeitung von Milch",
    "sg:phone":"+41 62 965 15 65",
    "sg:postcode":"4934",
    "sg:province":"Bern",
    "wof:name":"K\u00e4serei Dorf Fritz Rentsch",
    "wof:placetype":"venue"
},
  "geometry": {"coordinates":[7.7999181747,47.1660957336],"type":"Point"}
}