{
  "type": "Feature",
  "properties": {
    "iso:country":"CH",
    "sg:address":"Sch\u00fctzenstrasse 33 8902 Urdorf. Postfach 102",
    "sg:city":"Urdorf",
    "sg:orig_category":"Non-Classified Establishments",
    "sg:phone":"+41 17352424",
    "sg:postcode":"8902",
    "sg:province":"Z\u00fcrich",
    "wof:name":"Lku Leuenberger Klimager\u00e4te Vertriebs Gmbh",
    "wof:placetype":"venue"
},
  "geometry": {"coordinates":[8.4243869781,47.3720703125],"type":"Point"}
}