{
  "type": "Feature",
  "properties": {
    "iso:country":"CH",
    "sg:address":"Oberdorf 9105 Sch\u00f6nengrund. Postfach",
    "sg:city":"Sch\u00f6nengrund",
    "sg:orig_category":"RESTAURANTS: TEA-ROOMS",
    "sg:postcode":"9105",
    "sg:province":"Appenzell Ausserrhoden",
    "wof:name":"Sturzenegger Margrith",
    "wof:placetype":"venue"
},
  "geometry": {"coordinates":[9.3031291962,47.4047927856],"type":"Point"}
}