{
  "type": "Feature",
  "properties": {
    "iso:country":"CH",
    "sg:address":"Grundstrasse 2 8590 Romanshorn. Postfach",
    "sg:city":"Romanshorn",
    "sg:orig_category":"Architektur U Ingenieurb\u00fcros Architekturb\u00fcros",
    "sg:phone":"+41 71 461 20 50",
    "sg:postcode":"8590",
    "sg:province":"Thurgau",
    "wof:name":"L\u00fctschg Und Partner Ag Architektur Und Planung",
    "wof:placetype":"venue"
},
  "geometry": {"coordinates":[9.365458,47.566303],"type":"Point"}
}