{
  "type": "Feature",
  "properties": {
    "iso:country":"CH",
    "sg:address":"Im Moos 8",
    "sg:city":"L\u00fcchingen",
    "sg:classifiers":[
        {
            "category":"Professional",
            "subcategory":"Advertising",
            "type":"Services"
        }
    ],
    "sg:phone":"+41 71 755 34 84",
    "sg:postcode":"9450",
    "sg:province":"St. Gallen",
    "sg:tags":[
        "balloon",
        "child"
    ],
    "wof:name":"Texco Swiss",
    "wof:placetype":"venue"
},
  "geometry": {"coordinates":[9.557142,47.384502],"type":"Point"}
}