{
  "type": "Feature",
  "properties": {
    "iso:country":"CH",
    "sg:address":"Le Raffort",
    "sg:city":"Ch\u00e2tonnaye",
    "sg:orig_category":"Interessenvertretungen U sonstige Vereinigungen",
    "sg:phone":"+41 27 458 19 65",
    "sg:postcode":"1553",
    "sg:province":"Fribourg",
    "wof:name":"Fssh F\u00e9d.cantonale",
    "wof:placetype":"venue"
},
  "geometry": {"coordinates":[7.4636449814,46.2584381104],"type":"Point"}
}