{
  "type": "Feature",
  "properties": {
    "iso:country":"CH",
    "sg:address":"Seebahnstrasse 85 8003 Z\u00fcrich. Postfach 8702",
    "sg:city":"Z\u00fcrich",
    "sg:orig_category":"Advokaturb\u00fcros",
    "sg:phone":"+41 14622250",
    "sg:postcode":"8036",
    "sg:province":"Z\u00fcrich",
    "wof:name":"Jean Plancherel Advokaturb\u00fcro",
    "wof:placetype":"venue"
},
  "geometry": {"coordinates":[8.522876,47.371174],"type":"Point"}
}