{
  "type": "Feature",
  "properties": {
    "iso:country":"CH",
    "sg:address":"Burgunderstrasse 7",
    "sg:city":"Witterswil",
    "sg:orig_category":"Architekturb\u00fcros",
    "sg:phone":"+41 79 645 60 02",
    "sg:postcode":"4108",
    "sg:province":"Solothurn",
    "wof:name":"Josef Stebler Architekturb\u00fcro",
    "wof:placetype":"venue"
},
  "geometry": {"coordinates":[7.526806,47.485733],"type":"Point"}
}