{
  "type": "Feature",
  "properties": {
    "iso:country":"CH",
    "sg:address":"Sch\u00f6nhaldenstrasse 15",
    "sg:city":"M\u00e4nnedorf",
    "sg:orig_category":"Erschliessung von Grundst\u00fccken",
    "sg:postcode":"8708",
    "sg:province":"Z\u00fcrich",
    "wof:name":"Baugenossenschaft Hasenacker M\u00e4nnedorf",
    "wof:placetype":"venue"
},
  "geometry": {"coordinates":[8.6886138916,47.2605209351],"type":"Point"}
}