{
  "type": "Feature",
  "properties": {
    "iso:country":"CH",
    "sg:address":"4533 Riedholz. Postfach 112",
    "sg:city":"Riedholz",
    "sg:orig_category":"Sportvereine Ballsport Fussball",
    "sg:phone":"+41 62 929 36 98",
    "sg:postcode":"4533",
    "sg:province":"Solothurn",
    "wof:name":"Fc Roggwil",
    "wof:placetype":"venue"
},
  "geometry": {"coordinates":[7.8228058815,47.2411155701],"type":"Point"}
}