{
  "type": "Feature",
  "properties": {
    "iso:country":"CH",
    "sg:address":"Chemin Du Belv\u00e9d\u00e8re 11",
    "sg:city":"Ste-croix",
    "sg:classifiers":[
        {
            "category":"Restaurant",
            "type":"Food & Drink"
        }
    ],
    "sg:phone":"+41 24 454 16 95",
    "sg:postcode":"1450",
    "sg:province":"Vaud",
    "wof:name":"Restaurant Les Petites-roches",
    "wof:placetype":"venue"
},
  "geometry": {"coordinates":[6.5284042358,46.8261871338],"type":"Point"}
}