{
  "type": "Feature",
  "properties": {
    "iso:country":"CH",
    "sg:address":"6760",
    "sg:city":"Faido",
    "sg:orig_category":"Sportvereine Sch\u00fctzen",
    "sg:phone":"+41 91 866 17 77",
    "sg:postcode":"6760",
    "sg:province":"Ticino",
    "wof:name":"Societ\u00e0 Di Tiro Carabinieri Faidesi",
    "wof:placetype":"venue"
},
  "geometry": {"coordinates":[8.8208904266,46.4896316528],"type":"Point"}
}