{
  "type": "Feature",
  "properties": {
    "addr:full":"Rue De Ch\u00eatre 1 2800 Del\u00e9mont Case Postale 2144 Delsberg Jura 2800",
    "addr:housenumber":"1",
    "addr:postcode":"2800;2144;2800",
    "addr:street":"Rue De Che\u0302Tre;Postale;Jura",
    "iso:country":"CH",
    "sg:address":"Rue De Ch\u00eatre 1 2800 Del\u00e9mont Case Postale 2144",
    "sg:city":"Delsberg",
    "sg:orig_category":"Datenverarbeitungsdienste Softwareentwicklung U beratung",
    "sg:phone":"+41 32 422 39 51",
    "sg:postcode":"2800",
    "sg:province":"Jura",
    "wof:name":"Kr\u00e4uchi Informatique Sa",
    "wof:placetype":"venue"
},
  "geometry": {"coordinates":[7.343303,47.366447],"type":"Point"}
}