{
  "type": "Feature",
  "properties": {
    "iso:country":"CH",
    "sg:address":"Unterdorf 15",
    "sg:city":"Oberhallau",
    "sg:orig_category":"Sanit\u00e4r, Heizungs U L\u00fcftungsinstallation",
    "sg:postcode":"8216",
    "sg:province":"Schaffhausen",
    "wof:name":"Graf P. + Management Sanit\u00e4r Heizungen Sanit\u00e4re Installationen U. Heizungen; Reparatur",
    "wof:placetype":"venue"
},
  "geometry": {"coordinates":[7.2406539917,46.9019241333],"type":"Point"}
}