{
  "type": "Feature",
  "properties": {
    "iso:country":"CH",
    "sg:address":"Aeulestrasse 74",
    "sg:city":"Vaduz",
    "sg:orig_category":"Wirtschaftspr\u00fcfung, Steuerberatung U Treuhand",
    "sg:phone":"+423 236 04 87",
    "sg:postcode":"9490",
    "wof:name":"Interfiducia Trust Reg. Treuhandb\u00fcro",
    "wof:placetype":"venue"
},
  "geometry": {"coordinates":[9.5217914581,47.1374282837],"type":"Point"}
}