{
  "type": "Feature",
  "properties": {
    "iso:country":"CH",
    "sg:address":"Via Motto 4",
    "sg:city":"Cureglia",
    "sg:orig_category":"Unclassifiable Establishments",
    "sg:postcode":"6944",
    "sg:province":"Ticino",
    "wof:name":"Friendly Switzerland Di Tiziano Matteo De Gasperi",
    "wof:placetype":"venue"
},
  "geometry": {"coordinates":[8.9421958923,46.0332870483],"type":"Point"}
}