{
  "type": "Feature",
  "properties": {
    "iso:country":"CH",
    "sg:address":"Burgau",
    "sg:city":"Flawil",
    "sg:orig_category":"Verwertung von Milch",
    "sg:phone":"+41 71 393 11 55",
    "sg:postcode":"9230",
    "sg:province":"St. Gallen",
    "wof:name":"Isenegger Max",
    "wof:placetype":"venue"
},
  "geometry": {"coordinates":[9.2097196579,47.4052391052],"type":"Point"}
}