{
  "type": "Feature",
  "properties": {
    "iso:country":"CH",
    "sg:address":"Allschwilerstrasse 118 4055 Basel. Postfach",
    "sg:city":"Basel",
    "sg:orig_category":"Flachsaufbereitung U spinnerei",
    "sg:phone":"+41 61 261 93 48",
    "sg:postcode":"4051",
    "sg:province":"Basel-Stadt",
    "wof:name":"Sibannac Gmbh Hanfprodukte, Waren Aller Art; Handel",
    "wof:placetype":"venue"
},
  "geometry": {"coordinates":[7.5654058456,47.55727005],"type":"Point"}
}