{
  "type": "Feature",
  "properties": {
    "iso:country":"CH",
    "sg:address":"Unterstrasse 1",
    "sg:city":"Kronb\u00fchl",
    "sg:orig_category":"Malerei Tapeziererei",
    "sg:phone":"+41 19327093",
    "sg:postcode":"9302",
    "wof:name":"Josef Mikusi Maler-& Tapezierergesch\u00e4ft",
    "wof:placetype":"venue"
},
  "geometry": {"coordinates":[8.7895402908,47.3252906799],"type":"Point"}
}