{
  "type": "Feature",
  "properties": {
    "iso:country":"CH",
    "sg:address":"Sevogelstrasse 1",
    "sg:city":"Bubendorf",
    "sg:orig_category":"Detailhandel mit Geschenkartikeln U Souvenirs Sonstige k\u00fcnstlerische U schriftstellerische T\u00e4tigkeit",
    "sg:phone":"+41 61 931 26 34",
    "sg:postcode":"4416",
    "sg:province":"Basel-Landschaft",
    "wof:name":"Felix & Edith Gysin",
    "wof:placetype":"venue"
},
  "geometry": {"coordinates":[7.7395310402,47.4443473816],"type":"Point"}
}