{
  "type": "Feature",
  "properties": {
    "iso:country":"CH",
    "sg:address":"9057",
    "sg:city":"Schwende",
    "sg:orig_category":"Vorschulen, Kinderg\u00e4rten",
    "sg:phone":"+41 71 799 16 33",
    "sg:postcode":"9057",
    "sg:province":"Appenzell Innerhoden",
    "wof:name":"Kindergarten",
    "wof:placetype":"venue"
},
  "geometry": {"coordinates":[9.4352722168,47.3014221191],"type":"Point"}
}