{
  "type": "Feature",
  "properties": {
    "iso:country":"CH",
    "sg:address":"Binzstrasse 15",
    "sg:city":"Z\u00fcrich",
    "sg:orig_category":"Softwareentwicklung U beratung",
    "sg:postcode":"8045",
    "sg:province":"Z\u00fcrich",
    "wof:name":"Inactsoft Gmbh",
    "wof:placetype":"venue"
},
  "geometry": {"coordinates":[8.5157432556,47.3626327515],"type":"Point"}
}