{
  "type": "Feature",
  "properties": {
    "iso:country":"CH",
    "sg:address":"1143",
    "sg:city":"Apples",
    "sg:classifiers":[
        {
            "category":"Travel",
            "subcategory":"Hotels & Motels",
            "type":"Entertainment"
        }
    ],
    "sg:phone":"+41 21 800 32 34",
    "sg:postcode":"1143",
    "sg:province":"Vaud",
    "sg:tags":[
        "hotels",
        "mit",
        "restaurant"
    ],
    "wof:name":"H\u00f4tel De Commune",
    "wof:placetype":"venue"
},
  "geometry": {"coordinates":[6.4290990829,46.5518035889],"type":"Point"}
}