{
  "type": "Feature",
  "properties": {
    "iso:country":"CH",
    "sg:address":"Route De La Croix-blanche 33",
    "sg:city":"Epalinges",
    "sg:orig_category":"Detailhandel mit Spielwaren Detailhandel mit S\u00e4uglings U Kinderbekleidung",
    "sg:phone":"+41 21 784 40 04",
    "sg:postcode":"1066",
    "sg:province":"Vaud",
    "wof:name":"V. Renaud & M.-th. Pittet Boutique Pomme & Arthur",
    "wof:placetype":"venue"
},
  "geometry": {"coordinates":[6.6733498573,46.5483512878],"type":"Point"}
}