{
  "type": "Feature",
  "properties": {
    "iso:country":"CH",
    "sg:address":"Wiesriedtweg 10",
    "sg:city":"R\u00fcti",
    "sg:classifiers":[
        {
            "category":"Home & Garden",
            "subcategory":"Hardware",
            "type":"Retail Goods"
        }
    ],
    "sg:phone":"+41 55 240 50 55",
    "sg:postcode":"8630",
    "sg:province":"Z\u00fcrich",
    "sg:tags":[
        "component",
        "electronic"
    ],
    "wof:name":"Datec Electronic Ag",
    "wof:placetype":"venue"
},
  "geometry": {"coordinates":[8.8424520493,47.2564697266],"type":"Point"}
}