{
  "type": "Feature",
  "properties": {
    "iso:country":"CH",
    "sg:address":"Jakobstrasse 2",
    "sg:city":"Wettingen",
    "sg:orig_category":"Wirtschaftspr\u00fcfung, Steuerberatung U Treuhand",
    "sg:postcode":"5430",
    "sg:province":"Aargau",
    "wof:name":"Ronco Treuhand Gmbh",
    "wof:placetype":"venue"
},
  "geometry": {"coordinates":[8.317111969,47.4698219299],"type":"Point"}
}