{
  "type": "Feature",
  "properties": {
    "iso:country":"CH",
    "sg:address":"Bucheggstrasse 4",
    "sg:city":"Grenchen",
    "sg:orig_category":"Grosshandel mit Datenverarbeitungsger\u00e4ten Softwareentwicklung U beratung",
    "sg:phone":"+41 32 653 87 45",
    "sg:postcode":"2540",
    "sg:province":"Solothurn",
    "wof:name":"Ipc Consulting Gmbh",
    "wof:placetype":"venue"
},
  "geometry": {"coordinates":[7.3970007896,47.1870956421],"type":"Point"}
}