{
  "type": "Feature",
  "properties": {
    "iso:country":"CH",
    "sg:address":"Route De Formangueires",
    "sg:city":"Belfaux",
    "sg:orig_category":"Grosshandel mit Holz U Baustoffen",
    "sg:phone":"+41 26 475 36 45",
    "sg:postcode":"1782",
    "sg:province":"Fribourg",
    "wof:name":"Kerastone Sa Granit-marbre-pierre Naturelle",
    "wof:placetype":"venue"
},
  "geometry": {"coordinates":[7.1152839661,46.8261642456],"type":"Point"}
}