{
  "type": "Feature",
  "properties": {
    "iso:country":"CH",
    "sg:address":"6865",
    "sg:city":"Tremona",
    "sg:classifiers":[
        {
            "category":"Restaurant",
            "type":"Food & Drink"
        }
    ],
    "sg:phone":"+41 79 353 94 04",
    "sg:postcode":"6865",
    "sg:province":"Ticino",
    "wof:name":"Grotto Grassi",
    "wof:placetype":"venue"
},
  "geometry": {"coordinates":[8.9583797455,45.8813705444],"type":"Point"}
}