{
  "type": "Feature",
  "properties": {
    "iso:country":"CH",
    "sg:address":"Via Sonvico 3a",
    "sg:city":"Canobbio",
    "sg:orig_category":"Einzelhandel mit Automobilen Instandhaltung U Reparatur von Automobilen",
    "sg:phone":"+41 91 942 01 55",
    "sg:postcode":"6952",
    "sg:province":"Ticino",
    "wof:name":"Autoresega Sagl",
    "wof:placetype":"venue"
},
  "geometry": {"coordinates":[8.9669380188,46.0280990601],"type":"Point"}
}