{
  "type": "Feature",
  "properties": {
    "iso:country":"CH",
    "sg:address":"Industriestrasse 8",
    "sg:city":"Neuheim",
    "sg:orig_category":"Hoch U Tiefbau",
    "sg:phone":"+41 41 712 06 93",
    "sg:postcode":"6345",
    "sg:province":"Zug",
    "wof:name":"Franz Kummer Bauunternehmung",
    "wof:placetype":"venue"
},
  "geometry": {"coordinates":[8.5775184631,47.2023544312],"type":"Point"}
}