{
  "type": "Feature",
  "properties": {
    "iso:country":"CH",
    "sg:address":"Rue De Bernex 248",
    "sg:city":"Bernex",
    "sg:orig_category":"Kunststoff-Produkte",
    "sg:phone":"+41 91 646 37 76",
    "sg:postcode":"1233",
    "sg:province":"Gen\u00e8ve",
    "wof:name":"Ginella Jos\u00e9",
    "wof:placetype":"venue"
},
  "geometry": {"coordinates":[8.9810810089,45.8568572998],"type":"Point"}
}