{
  "type": "Feature",
  "properties": {
    "iso:country":"CH",
    "sg:address":"Brittnauerstrasse 8",
    "sg:city":"Zofingen",
    "sg:orig_category":"Technische, physikalische U chemische Untersuchung",
    "sg:postcode":"4800",
    "sg:province":"Aargau",
    "wof:name":"Kyburz A., \u00d6ko Produkte",
    "wof:placetype":"venue"
},
  "geometry": {"coordinates":[7.9469599724,47.2798805237],"type":"Point"}
}