{
  "type": "Feature",
  "properties": {
    "iso:country":"CH",
    "sg:address":"Schulg\u00e4ssli 17",
    "sg:city":"Heimberg",
    "sg:orig_category":"Zimmerei, Dachdeckerei, Bauspenglerei U Abdichtung Zimmerei, Ingenieurholzbau",
    "sg:phone":"+41 71 351 24 66",
    "sg:postcode":"3627",
    "sg:province":"Bern",
    "wof:name":"Hugo Scherle Zimmerei",
    "wof:placetype":"venue"
},
  "geometry": {"coordinates":[9.2377490997,47.3829078674],"type":"Point"}
}