{
  "type": "Feature",
  "properties": {
    "addr:full":"Neuhausweg 7 3506 Grossh\u00f6chstetten. Postfach Grossh\u00f6chstetten Bern 3506",
    "addr:housenumber":"7",
    "addr:postcode":"3506;3506",
    "addr:street":"Neuhausweg;Postfach",
    "iso:country":"CH",
    "sg:address":"Neuhausweg 7 3506 Grossh\u00f6chstetten. Postfach",
    "sg:city":"Grossh\u00f6chstetten",
    "sg:orig_category":"Arztpraxen",
    "sg:phone":"+41 31 839 94 30",
    "sg:postcode":"3506",
    "sg:province":"Bern",
    "wof:name":"Dr.med.beatrice Galliker Spezial\u00e4rztin Fmh",
    "wof:placetype":"venue"
},
  "geometry": {"coordinates":[7.635117,46.91061],"type":"Point"}
}