{
  "type": "Feature",
  "properties": {
    "iso:country":"CH",
    "sg:address":"Tretteliweg 7",
    "sg:city":"Dietlikon",
    "sg:orig_category":"P\u00e9dicure",
    "sg:phone":"+41 71 222 50 19",
    "sg:postcode":"8305",
    "sg:province":"Z\u00fcrich",
    "wof:name":"Daniela De Martin P\u00e9dicure",
    "wof:placetype":"venue"
},
  "geometry": {"coordinates":[9.3748855591,47.4273605347],"type":"Point"}
}