{
  "type": "Feature",
  "properties": {
    "iso:country":"CH",
    "sg:address":"Klosternhalde 3",
    "sg:city":"Steffisburg",
    "sg:orig_category":"Softwareentwicklung U beratung",
    "sg:postcode":"3612",
    "sg:province":"Bern",
    "wof:name":"Meyes Franziska Informatik",
    "wof:placetype":"venue"
},
  "geometry": {"coordinates":[7.6369519234,46.7821159363],"type":"Point"}
}