{
  "type": "Feature",
  "properties": {
    "iso:country":"CH",
    "sg:address":"Rohrerstrasse 89",
    "sg:city":"Aarau",
    "sg:orig_category":"Reinigungsgewerbe",
    "sg:phone":"+41 62 822 44 12",
    "sg:postcode":"5000",
    "sg:province":"Aargau",
    "wof:name":"Tankrevisionen Roppel Ag",
    "wof:placetype":"venue"
},
  "geometry": {"coordinates":[8.0631437302,47.3954391479],"type":"Point"}
}