{
  "type": "Feature",
  "properties": {
    "iso:country":"CH",
    "sg:address":"Zugerstrasse 2",
    "sg:city":"W\u00e4denswil",
    "sg:orig_category":"Detailhandel mit B\u00fcchern Detailhandel mit Ton U Bildtr\u00e4gern",
    "sg:phone":"+41 17802230",
    "sg:postcode":"8820",
    "sg:province":"Z\u00fcrich",
    "wof:name":"Ex Libris Ag",
    "wof:placetype":"venue"
},
  "geometry": {"coordinates":[8.673353,47.2299],"type":"Point"}
}