{
  "type": "Feature",
  "properties": {
    "iso:country":"CH",
    "sg:address":"M\u00e9sanges Chemin Des 7 1012 Lausanne. Postfach",
    "sg:city":"Lausanne",
    "sg:orig_category":"Herstellung von Konstruktionsteilen, Fertigbauteilen U Ausbauelementen aus Holz",
    "sg:postcode":"1012",
    "sg:province":"Vaud",
    "wof:name":"Entreprise Henriques Manuel Et Cie Chapes-isolations Et Carrelages",
    "wof:placetype":"venue"
},
  "geometry": {"coordinates":[6.6568899155,46.526309967],"type":"Point"}
}