{
  "type": "Feature",
  "properties": {
    "iso:country":"CH",
    "sg:address":"Einsiedlerstrasse",
    "sg:city":"W\u00e4denswil",
    "sg:orig_category":"Instandhaltung U Reparatur von Automobilen",
    "sg:phone":"+41 17808546",
    "sg:postcode":"8820",
    "sg:province":"Z\u00fcrich",
    "wof:name":"Reidholz Garage Ag",
    "wof:placetype":"venue"
},
  "geometry": {"coordinates":[8.6795768738,47.2250137329],"type":"Point"}
}