{
  "type": "Feature",
  "properties": {
    "iso:country":"CH",
    "sg:address":"Grand'rue 11",
    "sg:city":"Lucens",
    "sg:orig_category":"Kosmetikinstitute",
    "sg:phone":"+41 24 499 22 01",
    "sg:postcode":"1522",
    "sg:province":"Vaud",
    "wof:name":"Martine Sauge Institut De Beaut\u00e9 Or & Noir",
    "wof:placetype":"venue"
},
  "geometry": {"coordinates":[6.9906110764,46.2946739197],"type":"Point"}
}