{
  "type": "Feature",
  "properties": {
    "iso:country":"CH",
    "sg:address":"Burgstrasse 28",
    "sg:city":"Glarus",
    "sg:orig_category":"Herstellung von Maschinen f\u00fcr die Textil, Bekleidungsherstellung U die Lederverarbeitung",
    "sg:phone":"+41 55 640 46 22",
    "sg:postcode":"8750",
    "sg:province":"Glarus",
    "wof:name":"Graf Verkaufsgesellschaft Ag",
    "wof:placetype":"venue"
},
  "geometry": {"coordinates":[9.0686101913,47.041179657],"type":"Point"}
}