{
  "type": "Feature",
  "properties": {
    "iso:country":"CH",
    "sg:address":"Fabrikstrasse 50",
    "sg:city":"Z\u00fcrich",
    "sg:orig_category":"Finanzierungsinstitutionen",
    "sg:phone":"+41 26 350 23 23",
    "sg:postcode":"8005",
    "sg:province":"Z\u00fcrich",
    "wof:name":"Multinvest Ag",
    "wof:placetype":"venue"
},
  "geometry": {"coordinates":[8.525604248,47.3845787048],"type":"Point"}
}