{
  "type": "Feature",
  "properties": {
    "addr:full":"Rue De Gottefrey Saxon Valais 1907",
    "addr:postcode":"1907",
    "addr:street":"Rue De Gottefrey",
    "iso:country":"CH",
    "sg:address":"Rue De Gottefrey",
    "sg:city":"Saxon",
    "sg:classifiers":[
        {
            "category":"Banks & Credit Unions",
            "subcategory":"Bank",
            "type":"Services"
        }
    ],
    "sg:phone":"+41 27 744 24 67",
    "sg:postcode":"1907",
    "sg:province":"Valais",
    "wof:name":"Raiffeisen",
    "wof:placetype":"venue"
},
  "geometry": {"coordinates":[7.175865,46.14996],"type":"Point"}
}