{
  "type": "Feature",
  "properties": {
    "iso:country":"CH",
    "sg:address":"Chemin De L'ancien-stand 3",
    "sg:city":"Blonay",
    "sg:orig_category":"Detailhandel mit Waren verschiedener Art, Hauptrichtung Nahrungsmittel",
    "sg:phone":"+41 26 322 16 62",
    "sg:postcode":"1807",
    "sg:province":"Vaud",
    "wof:name":"The Irish Shop Jean-louis Larigaldie",
    "wof:placetype":"venue"
},
  "geometry": {"coordinates":[7.1598849297,46.8060302734],"type":"Point"}
}