{
  "type": "Feature",
  "properties": {
    "iso:country":"CH",
    "sg:address":"Glarnerstrasse 22",
    "sg:city":"Siebnen",
    "sg:orig_category":"Detailhandel mit Brot, Back U S\u00fcsswaren",
    "sg:postcode":"8854",
    "sg:province":"Schwyz",
    "wof:name":"Wepfer Franz, B\u00e4ckerei & Konditorei",
    "wof:placetype":"venue"
},
  "geometry": {"coordinates":[8.79848,47.32452],"type":"Point"}
}