{
  "type": "Feature",
  "properties": {
    "iso:country":"CH",
    "sg:address":"Rue Du Stade (savi\u00e8se)",
    "sg:city":"Saint-germain",
    "sg:classifiers":[
        {
            "category":"Government",
            "subcategory":"Post Office",
            "type":"Public Place"
        }
    ],
    "sg:phone":"+41 27 395 22 44",
    "sg:postcode":"1965",
    "sg:province":"Valais",
    "sg:tags":[
        "caf\u00e9s",
        "tea-rooms"
    ],
    "wof:name":"Tea-room Gourmandine",
    "wof:placetype":"venue"
},
  "geometry": {"coordinates":[7.3524518013,46.2501907349],"type":"Point"}
}