{
  "type": "Feature",
  "properties": {
    "iso:country":"CH",
    "sg:address":"Stadtbachstrasse 42 3012 Bern. Postfach 8920",
    "sg:city":"Bern",
    "sg:orig_category":"Interessenvertretungen",
    "sg:phone":"+41 31 305 30 60",
    "sg:postcode":"3012",
    "sg:province":"Bern",
    "wof:name":"Youth For Understanding (yfu) (schweiz)",
    "wof:placetype":"venue"
},
  "geometry": {"coordinates":[7.4317212105,46.948928833],"type":"Point"}
}