{
  "type": "Feature",
  "properties": {
    "iso:country":"CH",
    "sg:address":"Route De Glion 16 1820 Territet-veytaux. Postfach",
    "sg:city":"Lausanne",
    "sg:orig_category":"Hardwareberatung",
    "sg:phone":"+41 21 311 68 83",
    "sg:postcode":"1003",
    "sg:province":"Vaud",
    "wof:name":"Switch Technology Sa Outils Et Composants Informatiques Et \u00e9lectroniques Etc.; Import.",
    "wof:placetype":"venue"
},
  "geometry": {"coordinates":[6.9105057716,46.4316940308],"type":"Point"}
}