{
  "type": "Feature",
  "properties": {
    "iso:country":"CH",
    "sg:address":"4458",
    "sg:city":"Eptingen",
    "sg:orig_category":"Vereine Spar",
    "sg:postcode":"4458",
    "sg:province":"Basel-Landschaft",
    "wof:name":"Sparverein",
    "wof:placetype":"venue"
},
  "geometry": {"coordinates":[7.2517299652,46.7967414856],"type":"Point"}
}