{
  "type": "Feature",
  "properties": {
    "iso:country":"CH",
    "sg:address":"Via Alberto Giacometti 1",
    "sg:city":"Lugano",
    "sg:orig_category":"Herstellung von Maschinen f\u00fcr die Metallerzeugung",
    "sg:phone":"+41 32 631 29 56",
    "sg:postcode":"6900",
    "sg:province":"Ticino",
    "wof:name":"Grorymab Ag",
    "wof:placetype":"venue"
},
  "geometry": {"coordinates":[7.6575760841,47.231048584],"type":"Point"}
}