{
  "type": "Feature",
  "properties": {
    "iso:country":"CH",
    "sg:address":"Burgunderstrasse 15 4512 Bellach. Postfach",
    "sg:city":"Bellach",
    "sg:orig_category":"Softwareentwicklung U beratung",
    "sg:postcode":"4512",
    "sg:province":"Solothurn",
    "wof:name":"Pebsol Gmbh Hard Und Software Im Bereich Der Industrieelektronik, Bes. Von Gesamtl\u00f6sungen Usw.; Entwicklung",
    "wof:placetype":"venue"
},
  "geometry": {"coordinates":[7.5072669983,47.2136611938],"type":"Point"}
}