{
  "type": "Feature",
  "properties": {
    "iso:country":"CH",
    "sg:address":"B\u00f6hlerstrasse 3",
    "sg:city":"Unterkulm",
    "sg:orig_category":"P\u00e9dicure",
    "sg:phone":"+41 62 776 12 57",
    "sg:postcode":"5726",
    "sg:province":"Aargau",
    "wof:name":"Romy B\u00fchler P\u00e9dicure",
    "wof:placetype":"venue"
},
  "geometry": {"coordinates":[8.1132936478,47.3101615906],"type":"Point"}
}