{
  "type": "Feature",
  "properties": {
    "iso:country":"CH",
    "sg:address":"Kirchrain 1",
    "sg:city":"H\u00e4gendorf",
    "sg:orig_category":"Erschliessung von Grundst\u00fccken Restaurants",
    "sg:phone":"+41 62 216 11 19",
    "sg:postcode":"4614",
    "sg:province":"Solothurn",
    "wof:name":"Baugenossenschaft Teufelsschlucht H\u00e4gendodrf",
    "wof:placetype":"venue"
},
  "geometry": {"coordinates":[7.8427448273,47.3341789246],"type":"Point"}
}