{
  "type": "Feature",
  "properties": {
    "iso:country":"CH",
    "sg:address":"Eigentalstrasse 7",
    "sg:city":"Oberembrach",
    "sg:orig_category":"Schreibb\u00fcros",
    "sg:phone":"+41 18655030",
    "sg:postcode":"8425",
    "sg:province":"Z\u00fcrich",
    "wof:name":"Brigitte Marzohl Brima-schreibdienst",
    "wof:placetype":"venue"
},
  "geometry": {"coordinates":[8.6190948486,47.4870223999],"type":"Point"}
}