{
  "type": "Feature",
  "properties": {
    "iso:country":"CH",
    "sg:address":"Chapelle Chemin De La 32 1964 Conthey. Postfach",
    "sg:city":"Conthey",
    "sg:orig_category":"R\u00fcckgewinnung U Vorbereitung f\u00fcr die Wiederverwertung Recycling von nichtmetallischen Altmaterialien",
    "sg:postcode":"1964",
    "sg:province":"Valais",
    "wof:name":"R\u00e9no-grenaillage S\u00e0rl",
    "wof:placetype":"venue"
},
  "geometry": {"coordinates":[7.2982797623,46.224319458],"type":"Point"}
}