{
  "type": "Feature",
  "properties": {
    "iso:country":"CH",
    "sg:address":"1462",
    "sg:city":"Yvonand",
    "sg:orig_category":"Abwasserreinigung Wasserversorgung",
    "sg:phone":"+41 24 430 12 56",
    "sg:postcode":"1462",
    "sg:province":"Vaud",
    "wof:name":"Service Des Eaux De La Commune D'yvonand",
    "wof:placetype":"venue"
},
  "geometry": {"coordinates":[6.745075,46.799728],"type":"Point"}
}