{
  "type": "Feature",
  "properties": {
    "iso:country":"CH",
    "sg:address":"Kleinwilstrasse 1a",
    "sg:city":"Horw",
    "sg:orig_category":"Sanit\u00e4r U Heizungsinstallation Sanit\u00e4r, Heizungs U L\u00fcftungsinstallation",
    "sg:phone":"+41 21 691 59 42",
    "sg:postcode":"6048",
    "sg:province":"Luzern",
    "wof:name":"Masson J. Sa",
    "wof:placetype":"venue"
},
  "geometry": {"coordinates":[6.5636148453,46.5251121521],"type":"Point"}
}