{
  "type": "Feature",
  "properties": {
    "iso:country":"CH",
    "sg:address":"Holdenstrasse 186",
    "sg:city":"Egliswil",
    "sg:orig_category":"Sportvereine Motorrad",
    "sg:phone":"+41 62 775 10 14",
    "sg:postcode":"5704",
    "sg:province":"Aargau",
    "wof:name":"Moto-club Seon",
    "wof:placetype":"venue"
},
  "geometry": {"coordinates":[8.1888313293,47.3519058228],"type":"Point"}
}