{
  "type": "Feature",
  "properties": {
    "iso:country":"CH",
    "sg:address":"Rue De La Chomaz 8",
    "sg:city":"Gimel",
    "sg:orig_category":"Darlehenskassen U Raiffeisenbanken",
    "sg:phone":"+41 32 954 11 47",
    "sg:postcode":"1188",
    "sg:province":"Vaud",
    "wof:name":"Banque Raiffeisen",
    "wof:placetype":"venue"
},
  "geometry": {"coordinates":[7.005208,47.210239],"type":"Point"}
}