{
  "type": "Feature",
  "properties": {
    "addr:full":"Rebli 87 B\u00fcchslen Fribourg 3215",
    "addr:housenumber":"87",
    "addr:postcode":"3215",
    "addr:street":"Rebli;Fribourg",
    "iso:country":"CH",
    "sg:address":"Rebli 87",
    "sg:city":"B\u00fcchslen",
    "sg:orig_category":"Abbruch U Sprenggewerbe, Erdbewegungsarbeiten Erdbewegungsarbeiten",
    "sg:phone":"+41 31 751 18 51",
    "sg:postcode":"3215",
    "sg:province":"Fribourg",
    "wof:name":"Zmoos Sa G\u00e9nie Civil",
    "wof:placetype":"venue"
},
  "geometry": {"coordinates":[7.17242,46.928894],"type":"Point"}
}