{
  "type": "Feature",
  "properties": {
    "iso:country":"CH",
    "sg:address":"St. Alban-vorstadt 96",
    "sg:city":"Basel",
    "sg:orig_category":"Mit dem Versicherungsgewerbe verbundene T\u00e4tigkeiten",
    "sg:phone":"+41 61 271 80 85",
    "sg:postcode":"4052",
    "sg:province":"Basel-Stadt",
    "wof:name":"Hippenmeyer Asset Management",
    "wof:placetype":"venue"
},
  "geometry": {"coordinates":[7.6018080711,47.5534324646],"type":"Point"}
}