{
  "type": "Feature",
  "properties": {
    "addr:full":"Kolbi Pohlern Bern 3638",
    "addr:postcode":"3638",
    "iso:country":"CH",
    "sg:address":"Kolbi",
    "sg:city":"Pohlern",
    "sg:classifiers":[
        {
            "category":"Government",
            "subcategory":"Fire Station",
            "type":"Public Place"
        }
    ],
    "sg:phone":"+41 33 356 15 33",
    "sg:postcode":"3638",
    "sg:province":"Bern",
    "sg:tags":[
        "alloy",
        "light",
        "aluminium",
        "processing"
    ],
    "wof:name":"Metallbau Rufener Ag",
    "wof:placetype":"venue"
},
  "geometry": {"coordinates":[7.527208,46.731525],"type":"Point"}
}