{
  "type": "Feature",
  "properties": {
    "iso:country":"CH",
    "sg:address":"Ochsenweid",
    "sg:city":"R\u00fceggisberg",
    "sg:orig_category":"Sportvereine Sch\u00fctzen",
    "sg:phone":"+41 31 809 20 08",
    "sg:postcode":"3088",
    "sg:province":"Bern",
    "wof:name":"Sch\u00fctzengesellschaft",
    "wof:placetype":"venue"
},
  "geometry": {"coordinates":[9.16294384,47.5812110901],"type":"Point"}
}