{
  "type": "Feature",
  "properties": {
    "iso:country":"CH",
    "sg:address":"Altenbergstrasse 32a",
    "sg:city":"Bern",
    "sg:orig_category":"Architekturb\u00fcros",
    "sg:phone":"+41 31 332 52 01",
    "sg:postcode":"3013",
    "sg:province":"Bern",
    "wof:name":"Uli Huber Architekturb\u00fcro",
    "wof:placetype":"venue"
},
  "geometry": {"coordinates":[7.457534,46.950623],"type":"Point"}
}