{
  "type": "Feature",
  "properties": {
    "iso:country":"CH",
    "sg:address":"Haslenstrasse",
    "sg:city":"Appenzell",
    "sg:classifiers":[
        {
            "category":"Restaurant",
            "type":"Food & Drink"
        }
    ],
    "sg:phone":"+41 71 787 11 58",
    "sg:postcode":"9050",
    "sg:province":"Appenzell Innerhoden",
    "wof:name":"Restaurant R\u00f6ssli Lank",
    "wof:placetype":"venue"
},
  "geometry": {"coordinates":[9.4011535645,47.3401794434],"type":"Point"}
}