{
  "type": "Feature",
  "properties": {
    "iso:country":"CH",
    "sg:address":"Bolligenstrasse 92",
    "sg:city":"Bolligen",
    "sg:orig_category":"Detailhandel mit Waren verschiedener Art, Hauptrichtung Nahrungsmittel",
    "sg:phone":"+41 31 925 92 92",
    "sg:postcode":"3065",
    "sg:province":"Bern",
    "wof:name":"Landi Bolligen Und Umgebung",
    "wof:placetype":"venue"
},
  "geometry": {"coordinates":[7.4968042374,46.9705581665],"type":"Point"}
}