{
  "type": "Feature",
  "properties": {
    "iso:country":"CH",
    "sg:address":"Austrasse 15 9490 Vaduz. Postfach 1117",
    "sg:city":"Vaduz",
    "sg:orig_category":"Versicherungen Hauptagenturen",
    "sg:phone":"+423 237 12 20",
    "sg:postcode":"9490",
    "wof:name":"Rentenanstalt/swiss Life Hauptagentur",
    "wof:placetype":"venue"
},
  "geometry": {"coordinates":[9.5226926804,47.1311950684],"type":"Point"}
}