{
  "type": "Feature",
  "properties": {
    "iso:country":"CH",
    "sg:address":"Schaffhauserstrasse 94",
    "sg:city":"Glattbrugg",
    "sg:orig_category":"Versicherungen Hauptagenturen",
    "sg:phone":"+41 18102737",
    "sg:postcode":"8152",
    "sg:province":"Z\u00fcrich",
    "wof:name":"Winterthur Versicherungen Hauptagentur",
    "wof:placetype":"venue"
},
  "geometry": {"coordinates":[8.5646257401,47.4325904846],"type":"Point"}
}