{
  "type": "Feature",
  "properties": {
    "iso:country":"CH",
    "sg:address":"6944 Cureglia. Postfach",
    "sg:city":"Cureglia",
    "sg:orig_category":"Arbeitnehmerverb\u00e4nde",
    "sg:phone":"+41 91 967 49 22",
    "sg:postcode":"6944",
    "sg:province":"Ticino",
    "wof:name":"Fed.svizz.ispettori D.assicur. Ticino,sig.gianni Pagnamenta",
    "wof:placetype":"venue"
},
  "geometry": {"coordinates":[8.94409,46.03701],"type":"Point"}
}