{
  "type": "Feature",
  "properties": {
    "iso:country":"CH",
    "sg:address":"Josefstrasse 119",
    "sg:city":"Z\u00fcrich",
    "sg:orig_category":"Non-Classified Establishments",
    "sg:postcode":"8005",
    "sg:province":"Z\u00fcrich",
    "wof:name":"Carelia Holding Ag",
    "wof:placetype":"venue"
},
  "geometry": {"coordinates":[8.4728374481,47.359539032],"type":"Point"}
}