{
  "type": "Feature",
  "properties": {
    "iso:country":"CH",
    "sg:address":"Avenue Des Boveresse 58",
    "sg:city":"Lausanne",
    "sg:orig_category":"Detailhandel mit Musikinstrumenten Detailhandel mit elektrischen Haushalts-,Radio U Fernsehger\u00e4ten s",
    "sg:phone":"+41 21 657 67 77",
    "sg:postcode":"1010",
    "sg:province":"Vaud",
    "wof:name":"Sticks Musique, Lionel Blanc",
    "wof:placetype":"venue"
},
  "geometry": {"coordinates":[6.6695828438,46.5352210999],"type":"Point"}
}