{
  "type": "Feature",
  "properties": {
    "iso:country":"CH",
    "sg:address":"Wilerstrasse 2",
    "sg:city":"Erstfeld",
    "sg:orig_category":"Detailhandel mit Waren verschiedener Art, Hauptrichtung Nahrungsmittel Grosshandel mit Nahrungsmitte",
    "sg:phone":"+41 41 880 13 54",
    "sg:postcode":"6472",
    "sg:province":"Uri",
    "wof:name":"P\u00fcntener-imhof A. Lebensmittel",
    "wof:placetype":"venue"
},
  "geometry": {"coordinates":[8.6456604004,46.8167190552],"type":"Point"}
}