{
  "type": "Feature",
  "properties": {
    "iso:country":"CH",
    "sg:address":"Richemont Rue De 10 1202 Gen\u00e8ve. Postfach",
    "sg:city":"Gen\u00e8ve",
    "sg:orig_category":"Unclassifiable Establishments",
    "sg:postcode":"1202",
    "sg:province":"Gen\u00e8ve",
    "wof:name":"Dauth Landmaschinen Ag",
    "wof:placetype":"venue"
},
  "geometry": {"coordinates":[9.351398468,47.3750267029],"type":"Point"}
}