{
  "type": "Feature",
  "properties": {
    "iso:country":"CH",
    "sg:address":"Kreuzb\u00fchlstrasse 1",
    "sg:city":"Z\u00fcrich",
    "sg:orig_category":"Detailhandel mit Bekleidung",
    "sg:postcode":"8008",
    "sg:province":"Z\u00fcrich",
    "wof:name":"Carol's Second Hand Mode, Schellenberg N. & R.",
    "wof:placetype":"venue"
},
  "geometry": {"coordinates":[8.551668,47.365765],"type":"Point"}
}