{
  "type": "Feature",
  "properties": {
    "iso:country":"CH",
    "sg:address":"Lect Rue 29 1217 Meyrin. Postfach",
    "sg:city":"Meyrin",
    "sg:orig_category":"Reinigungsgewerbe",
    "sg:phone":"+41 22 989 80 00",
    "sg:postcode":"1217",
    "sg:province":"Gen\u00e8ve",
    "wof:name":"Iss Commultiservice Sa Services Dans Le Secteur De L'entretien Et De L'exploitation De B\u00e2timents Etc",
    "wof:placetype":"venue"
},
  "geometry": {"coordinates":[6.0815730095,46.2250823975],"type":"Point"}
}