{
  "type": "Feature",
  "properties": {
    "iso:country":"CH",
    "sg:address":"1568 Portalban. Postfach 1",
    "sg:city":"Portalban",
    "sg:orig_category":"Sportvereine Ballsport Fussball",
    "sg:phone":"+41 26 677 22 82",
    "sg:postcode":"1568",
    "sg:province":"Fribourg",
    "wof:name":"Fc Portalban-gletterens",
    "wof:placetype":"venue"
},
  "geometry": {"coordinates":[6.9551901817,46.9181594849],"type":"Point"}
}