{
  "type": "Feature",
  "properties": {
    "iso:country":"CH",
    "sg:address":"Seestrasse 87",
    "sg:city":"Oberrieden",
    "sg:orig_category":"Schifffahrts\u00e4mter",
    "sg:phone":"+41 17208333",
    "sg:postcode":"8942",
    "sg:province":"Z\u00fcrich",
    "wof:name":"Schiffahrtskontrolle Des Kantons Z\u00fcrich",
    "wof:placetype":"venue"
},
  "geometry": {"coordinates":[8.5857181549,47.2706604004],"type":"Point"}
}