{
  "type": "Feature",
  "properties": {
    "iso:country":"CH",
    "sg:address":"L\u00fctis\u00e4metstrasse 95",
    "sg:city":"Meilen",
    "sg:orig_category":"Betrieb von Taxis",
    "sg:phone":"+41 19234351",
    "sg:postcode":"8706",
    "sg:province":"Z\u00fcrich",
    "wof:name":"Hermes Limousine Service Pafis",
    "wof:placetype":"venue"
},
  "geometry": {"coordinates":[8.665626,47.267403],"type":"Point"}
}