{
  "type": "Feature",
  "properties": {
    "iso:country":"CH",
    "sg:address":"Rietstrasse 41",
    "sg:city":"Zollikon",
    "sg:orig_category":"Personal U Stellenvermittlung Unternehmensberatung",
    "sg:phone":"+41 22 365 44 44",
    "sg:postcode":"8702",
    "sg:province":"Z\u00fcrich",
    "wof:name":"Mercuri Urval Sa, Succursale De Nyon Succursale De Nyon",
    "wof:placetype":"venue"
},
  "geometry": {"coordinates":[6.2193551064,46.3856620789],"type":"Point"}
}