{
  "type": "Feature",
  "properties": {
    "iso:country":"CH",
    "sg:address":"Arneggerstrasse 22a",
    "sg:city":"Waldkirch",
    "sg:orig_category":"Zimmerei, Dachdeckerei, Bauspenglerei U Abdichtung",
    "sg:phone":"+41 71 433 20 70",
    "sg:postcode":"9205",
    "sg:province":"St. Gallen",
    "wof:name":"Schildknecht & H\u00e4ttenschwiler Ag Holzbau",
    "wof:placetype":"venue"
},
  "geometry": {"coordinates":[9.2815246582,47.4668006897],"type":"Point"}
}