{
  "type": "Feature",
  "properties": {
    "iso:country":"CH",
    "sg:address":"Eichwaldstrasse 15",
    "sg:city":"Zug",
    "sg:orig_category":"Sportvereine Turnen Vereine Damen",
    "sg:phone":"+41 32 392 43 04",
    "sg:postcode":"6300",
    "sg:province":"Zug",
    "wof:name":"Damenriege Stv Aarberg",
    "wof:placetype":"venue"
},
  "geometry": {"coordinates":[7.2608218193,47.0364952087],"type":"Point"}
}