{
  "type": "Feature",
  "properties": {
    "addr:full":"Chemin Du Foron 43 Th\u00f4nex Gen\u00e8ve 1226",
    "addr:housenumber":"43",
    "addr:postcode":"1226",
    "addr:street":"Chemin Du Foron",
    "iso:country":"CH",
    "sg:address":"Chemin Du Foron 43",
    "sg:city":"Th\u00f4nex",
    "sg:orig_category":"Bezirks, Sekundar, Realschulen, Oberstufe der Primarschulen",
    "sg:phone":"+41 22 348 24 77",
    "sg:postcode":"1226",
    "sg:province":"Gen\u00e8ve",
    "wof:name":"Ecole Secondaire Coll\u00e8ge Du Foron",
    "wof:placetype":"venue"
},
  "geometry": {"coordinates":[6.211201,46.196449],"type":"Point"}
}