{
  "type": "Feature",
  "properties": {
    "iso:country":"CH",
    "sg:address":"Hauptstr. 147",
    "sg:city":"Bubendorf",
    "sg:classifiers":[
        {
            "category":"Professional",
            "subcategory":"Engineering",
            "type":"Services"
        }
    ],
    "sg:phone":"+41 61 935 17 10",
    "sg:postcode":"4416",
    "sg:province":"Basel-Landschaft",
    "sg:tags":[
        "-",
        "household",
        "appliance",
        "machine",
        "equipment",
        "electrical",
        "mechanical",
        "electronic"
    ],
    "wof:name":"Tiba Ag",
    "wof:placetype":"venue"
},
  "geometry": {"coordinates":[7.7329978943,47.4433174133],"type":"Point"}
}