{
  "type": "Feature",
  "properties": {
    "iso:country":"CH",
    "sg:address":"M\u00fchlegasse 4",
    "sg:city":"Fraubrunnen",
    "sg:orig_category":"Sanit\u00e4r U Heizungsinstallation Sanit\u00e4rinstallation",
    "sg:phone":"+41 31 767 75 20",
    "sg:postcode":"3312",
    "sg:province":"Bern",
    "wof:name":"J\u00fcrg Reinmann Sanit\u00e4re Anlagen & Heizungen",
    "wof:placetype":"venue"
},
  "geometry": {"coordinates":[7.5275030136,47.0856933594],"type":"Point"}
}