{
  "type": "Feature",
  "properties": {
    "iso:country":"CH",
    "sg:address":"Hirschmattstrasse 13 6003 Luzern. Postfach",
    "sg:city":"Luzern",
    "sg:orig_category":"Fachdetailhandel in Verkaufsr\u00e4umen",
    "sg:phone":"+41 41 630 18 26",
    "sg:postcode":"6003",
    "sg:province":"Luzern",
    "wof:name":"Hofstetter & Berney Ag",
    "wof:placetype":"venue"
},
  "geometry": {"coordinates":[8.3038454056,46.9916534424],"type":"Point"}
}