{
  "type": "Feature",
  "properties": {
    "iso:country":"CH",
    "sg:address":"Zwillikerstrasse",
    "sg:city":"Hedingen",
    "sg:orig_category":"Detailhandel mit Waren verschiedener Art, Hauptrichtung Nahrungsmittel",
    "sg:phone":"+41 56 241 16 15",
    "sg:postcode":"8908",
    "sg:province":"Z\u00fcrich",
    "wof:name":"Volg Detailhandels Ag",
    "wof:placetype":"venue"
},
  "geometry": {"coordinates":[8.3297224045,47.52085495],"type":"Point"}
}