{
  "type": "Feature",
  "properties": {
    "addr:full":"M\u00fchlestr. 4 Belp Bern 3123",
    "addr:housenumber":"4",
    "addr:postcode":"3123",
    "addr:street":"Muehlestr.",
    "iso:country":"CH",
    "sg:address":"M\u00fchlestr. 4",
    "sg:city":"Belp",
    "sg:classifiers":[
        {
            "category":"Manufacturing",
            "subcategory":"Chemicals & Compounds",
            "type":"Manufacturing & Wholesale Goods"
        }
    ],
    "sg:phone":"+41 22 342 16 16",
    "sg:postcode":"3123",
    "sg:province":"Bern",
    "sg:tags":[
        "pharmaceutical",
        "chemistry",
        "-",
        "by-product"
    ],
    "wof:name":"Louis Tempia Sa",
    "wof:placetype":"venue"
},
  "geometry": {"coordinates":[6.144114,46.181835],"type":"Point"}
}