{
  "type": "Feature",
  "properties": {
    "iso:country":"CH",
    "sg:address":"H\u00f6henweg 17",
    "sg:city":"Pratteln",
    "sg:orig_category":"Verlegen von Fliesen U Platten Verlegen von Fussboden",
    "sg:phone":"+41 61 821 40 63",
    "sg:postcode":"4133",
    "sg:province":"Basel-Landschaft",
    "wof:name":"Fritz Koch Mosaik-keramik-& Industriebel\u00e4ge Ag",
    "wof:placetype":"venue"
},
  "geometry": {"coordinates":[7.6957907677,47.514793396],"type":"Point"}
}