{
  "type": "Feature",
  "properties": {
    "iso:country":"CH",
    "sg:address":"Ottikerstrasse 40 8006 Z\u00fcrich. Postfach 13",
    "sg:city":"Z\u00fcrich",
    "sg:orig_category":"Pensionskassen",
    "sg:phone":"+41 13228550",
    "sg:postcode":"8006",
    "sg:province":"Z\u00fcrich",
    "wof:name":"Personalf\u00fcrsorgestiftung Der Firma Hetzel Gmbh",
    "wof:placetype":"venue"
},
  "geometry": {"coordinates":[8.5464916229,47.385723114],"type":"Point"}
}