{
  "type": "Feature",
  "properties": {
    "iso:country":"CH",
    "sg:address":"Place De La Croix-blanche 9 1066 Epalinges Case Postale 4",
    "sg:city":"Epalinges",
    "sg:orig_category":"Detailhandel mit Fleisch U Fleischwaren Sonstiger Fachdetailhandel mit Nahrungsmitteln, Getr\u00e4nken U ",
    "sg:phone":"+41 21 784 19 39",
    "sg:postcode":"1066",
    "sg:province":"Vaud",
    "wof:name":"Boucherie De La Croix-blanche S\u00e0rl",
    "wof:placetype":"venue"
},
  "geometry": {"coordinates":[6.6714820862,46.5484886169],"type":"Point"}
}