{
  "type": "Feature",
  "properties": {
    "iso:country":"CH",
    "sg:address":"Schanzm\u00e4ttelistrasse 32",
    "sg:city":"Aarau",
    "sg:classifiers":[
        {
            "category":"Education",
            "subcategory":"Library",
            "type":"Public Place"
        }
    ],
    "sg:phone":"+41 79 418 98 61",
    "sg:postcode":"5000",
    "sg:province":"Aargau",
    "sg:tags":[
        "u",
        "bibliotheken",
        "archive"
    ],
    "wof:name":"Neue Kantonsschule Bibliothek",
    "wof:placetype":"venue"
},
  "geometry": {"coordinates":[8.045002,47.386101],"type":"Point"}
}