{
  "type": "Feature",
  "properties": {
    "iso:country":"CH",
    "sg:address":"Bodmeli",
    "sg:city":"Grindelwald",
    "sg:orig_category":"Sanit\u00e4r U Heizungsinstallation",
    "sg:phone":"+41 33 853 36 40",
    "sg:postcode":"3818",
    "sg:province":"Bern",
    "wof:name":"Hans Schmocker Heizungen",
    "wof:placetype":"venue"
},
  "geometry": {"coordinates":[8.041806221,46.6263923645],"type":"Point"}
}