{
  "type": "Feature",
  "properties": {
    "iso:country":"CH",
    "sg:address":"Dorfgasse 170",
    "sg:city":"Twann",
    "sg:orig_category":"Dauerkulturbau Rebbau",
    "sg:phone":"+41 32 315 11 06",
    "sg:postcode":"2513",
    "sg:province":"Bern",
    "wof:name":"Martin Hubacher Johanniterkeller",
    "wof:placetype":"venue"
},
  "geometry": {"coordinates":[7.160811,47.095161],"type":"Point"}
}