{
  "type": "Feature",
  "properties": {
    "iso:country":"CH",
    "sg:address":"Spino",
    "sg:city":"Promontogno",
    "sg:orig_category":"Malerei",
    "sg:phone":"+41 81 822 13 33",
    "sg:postcode":"7606",
    "sg:province":"Graubunden",
    "wof:name":"Roberto Vetsch Impresa Di Pittura",
    "wof:placetype":"venue"
},
  "geometry": {"coordinates":[9.5540342331,46.3356285095],"type":"Point"}
}