{
  "type": "Feature",
  "properties": {
    "iso:country":"CH",
    "sg:address":"Chamerstrasse 12a 6300 Zug. Postfach",
    "sg:city":"Zug",
    "sg:orig_category":"Herstellung von sonstigen Maschinen f\u00fcr unspezifische Verwendung",
    "sg:postcode":"6300",
    "sg:province":"Zug",
    "wof:name":"Aps Automatic Packaging Systems Ag Maschinen, Industrieerzeugnisse, Bes. Produkte F\u00fcr Die Verpackungsindustrie; Handel",
    "wof:placetype":"venue"
},
  "geometry": {"coordinates":[8.5116653442,47.1717948914],"type":"Point"}
}