{
  "type": "Feature",
  "properties": {
    "iso:country":"CH",
    "sg:address":"Holbeinstrasse 22",
    "sg:city":"Basel",
    "sg:orig_category":"Herstellung von Musikinstrumenten",
    "sg:phone":"+41 61 271 15 81",
    "sg:postcode":"4051",
    "sg:province":"Basel-Stadt",
    "wof:name":"Felix Hefti Atelier F\u00fcr Geigenbau",
    "wof:placetype":"venue"
},
  "geometry": {"coordinates":[7.5842709541,47.5537643433],"type":"Point"}
}