{
  "type": "Feature",
  "properties": {
    "iso:country":"CH",
    "sg:address":"Rue Achille-merguin 19",
    "sg:city":"Porrentruy",
    "sg:orig_category":"Herstellung von medizinischen U chirurgischen Ger\u00e4ten sowie orthop\u00e4dischen Vorrichtungen Zahntechnis",
    "sg:phone":"+41 71 223 17 90",
    "sg:postcode":"2900",
    "sg:province":"Jura",
    "wof:name":"B\u00fcttner & Abderhalden Zahntechnik",
    "wof:placetype":"venue"
},
  "geometry": {"coordinates":[9.3705272675,47.4222297668],"type":"Point"}
}