{
  "type": "Feature",
  "properties": {
    "iso:country":"CH",
    "sg:address":"Rue Du Clos-de-bulle 7",
    "sg:city":"Lausanne",
    "sg:classifiers":[
        {
            "category":"Bars & Pubs",
            "type":"Food & Drink"
        }
    ],
    "sg:phone":"+41 21 320 77 37",
    "sg:postcode":"1004",
    "sg:province":"Vaud",
    "sg:tags":[
        "restaurant"
    ],
    "wof:name":"Restaurant & Bar Le Miro",
    "wof:placetype":"venue"
},
  "geometry": {"coordinates":[6.630439,46.524345],"type":"Point"}
}