{
  "type": "Feature",
  "properties": {
    "iso:country":"CH",
    "sg:address":"W\u00e4ssermattstrasse 12 5004 Aarau. Postfach 631",
    "sg:city":"Aarau",
    "sg:orig_category":"Ger\u00fcstbau Herstellung von Bergwerks U Baumaschinen",
    "sg:phone":"+41 56 496 21 41",
    "sg:postcode":"5000",
    "sg:province":"Aargau",
    "wof:name":"Rogeba Inter Sa",
    "wof:placetype":"venue"
},
  "geometry": {"coordinates":[8.2826576233,47.452545166],"type":"Point"}
}