{
  "type": "Feature",
  "properties": {
    "iso:country":"CH",
    "sg:address":"Avenue De-choiseul 21 1290 Versoix. Postfach",
    "sg:city":"Versoix",
    "sg:orig_category":"Fernmeldedienste",
    "sg:phone":"+41 56 470 05 05",
    "sg:postcode":"1290",
    "sg:province":"Gen\u00e8ve",
    "wof:name":"Highcom Gmbh",
    "wof:placetype":"venue"
},
  "geometry": {"coordinates":[8.2811307907,47.4542007446],"type":"Point"}
}