{
  "type": "Feature",
  "properties": {
    "iso:country":"CH",
    "sg:address":"Porclis",
    "sg:city":"Trin",
    "sg:orig_category":"Sportvereine Ballsport Tennis",
    "sg:phone":"+41 81 635 12 62",
    "sg:postcode":"7014",
    "sg:province":"Graubunden",
    "wof:name":"Tc Trin",
    "wof:placetype":"venue"
},
  "geometry": {"coordinates":[9.3524084091,46.8270225525],"type":"Point"}
}