{
  "type": "Feature",
  "properties": {
    "iso:country":"CH",
    "sg:address":"Schaffhauserstrasse 56a",
    "sg:city":"Winterthur",
    "sg:orig_category":"W\u00e4scherei U chemische Reinigung",
    "sg:postcode":"8400",
    "sg:province":"Z\u00fcrich",
    "wof:name":"Estrela Teppichreinigung Und Pflege, A. Courvoisier",
    "wof:placetype":"venue"
},
  "geometry": {"coordinates":[8.7216320038,47.5118751526],"type":"Point"}
}