{
  "type": "Feature",
  "properties": {
    "iso:country":"CH",
    "sg:address":"Hotel Schl\u00f6ssli",
    "sg:city":"Sax",
    "sg:orig_category":"Wirtschafts- and Arbeitgeberverb\u00e4nde",
    "sg:postcode":"9468",
    "sg:province":"St. Gallen",
    "wof:name":"Wirteverein Werdenberg",
    "wof:placetype":"venue"
},
  "geometry": {"coordinates":[9.4527215958,47.2272453308],"type":"Point"}
}