{
  "type": "Feature",
  "properties": {
    "iso:country":"CH",
    "sg:address":"Industriestrasse 3",
    "sg:city":"Kleind\u00f6ttingen",
    "sg:orig_category":"Herstellung von Metallerzeugnissen ohne Maschinenbau Herstellung von sonstigen Maschinen f\u00fcr unspezi",
    "sg:phone":"+41 56 245 46 86",
    "sg:postcode":"5314",
    "sg:province":"Aargau",
    "wof:name":"Robo-mat Ag",
    "wof:placetype":"venue"
},
  "geometry": {"coordinates":[8.237695694,47.575969696],"type":"Point"}
}