{
  "type": "Feature",
  "properties": {
    "iso:country":"CH",
    "sg:address":"Rue De La Vernie 6",
    "sg:city":"Crissier",
    "sg:orig_category":"Detailhandel mit Waren verschiedener Art, Hauptrichtung Nahrungsmittel Grosshandel mit Nahrungsmitte",
    "sg:phone":"+41 56 493 09 20",
    "sg:postcode":"1023",
    "sg:province":"Vaud",
    "wof:name":"Comarsa Commercio Alimentari Sa",
    "wof:placetype":"venue"
},
  "geometry": {"coordinates":[8.2947158813,47.4468193054],"type":"Point"}
}