{
  "type": "Feature",
  "properties": {
    "iso:country":"CH",
    "sg:address":"Obergrundstrasse 7",
    "sg:city":"Luzern",
    "sg:classifiers":[
        {
            "category":"Restaurant",
            "type":"Food & Drink"
        }
    ],
    "sg:phone":"+41 41 240 76 64",
    "sg:postcode":"6003",
    "sg:province":"Luzern",
    "wof:name":"Restaurant Pilatus",
    "wof:placetype":"venue"
},
  "geometry": {"coordinates":[8.3041296005,47.0474433899],"type":"Point"}
}