{
  "type": "Feature",
  "properties": {
    "iso:country":"CH",
    "sg:address":"B\u00fcelstrasse 21a",
    "sg:city":"Baar",
    "sg:orig_category":"Markt U Meinungsforschung",
    "sg:postcode":"6340",
    "sg:province":"Zug",
    "wof:name":"Outsourcing Ag",
    "wof:placetype":"venue"
},
  "geometry": {"coordinates":[8.528673172,47.1980628967],"type":"Point"}
}