{
  "type": "Feature",
  "properties": {
    "addr:full":"Tscharnerstrasse 13 Bern Bern 3007",
    "addr:housenumber":"13",
    "addr:postcode":"3007",
    "addr:street":"Tscharnerstrasse",
    "iso:country":"CH",
    "sg:address":"Tscharnerstrasse 13",
    "sg:city":"Bern",
    "sg:orig_category":"Architektur U Ingenieurb\u00fcros",
    "sg:phone":"+41 31 371 10 11",
    "sg:postcode":"3007",
    "sg:province":"Bern",
    "wof:name":"Pareth Dipl. Ingenieure Eth/sia Ag Bern",
    "wof:placetype":"venue"
},
  "geometry": {"coordinates":[7.429598,46.94149],"type":"Point"}
}