{
  "type": "Feature",
  "properties": {
    "iso:country":"CH",
    "sg:address":"Landstrasse 52",
    "sg:city":"Gipf-oberfrick",
    "sg:orig_category":"Herstellung von Tanks U Sammelbeh\u00e4ltern aus Metall Sanit\u00e4r U Heizungsinstallation",
    "sg:phone":"+41 56 441 55 85",
    "sg:postcode":"5073",
    "sg:province":"Aargau",
    "wof:name":"Voegtlin-meyer Ag",
    "wof:placetype":"venue"
},
  "geometry": {"coordinates":[8.2120265961,47.4823951721],"type":"Point"}
}