{
  "type": "Feature",
  "properties": {
    "iso:country":"CH",
    "sg:address":"Lottenweg 22 5037 Muhen. Postfach 43",
    "sg:city":"Muhen",
    "sg:orig_category":"Druckweiterverarbeitung Handelsvermittlung U Grosshandel",
    "sg:phone":"+41 62 737 20 40",
    "sg:postcode":"5037",
    "sg:province":"Aargau",
    "wof:name":"Tr\u00fcmpy Ag Schildertechnik",
    "wof:placetype":"venue"
},
  "geometry": {"coordinates":[8.061076,47.338985],"type":"Point"}
}