{
  "type": "Feature",
  "properties": {
    "iso:country":"CH",
    "sg:address":"Boden.",
    "sg:city":"Adelboden",
    "sg:orig_category":"Zimmerei, Dachdeckerei, Bauspenglerei U Abdichtung",
    "sg:postcode":"3715",
    "sg:province":"Bern",
    "wof:name":"Schmid Ueli.",
    "wof:placetype":"venue"
},
  "geometry": {"coordinates":[7.5584602356,46.4810714722],"type":"Point"}
}