{
  "type": "Feature",
  "properties": {
    "iso:country":"CH",
    "sg:address":"Trevano Via 2",
    "sg:city":"Lugano",
    "sg:orig_category":"Vermietung U Verpachtung von eigenen Immobilien",
    "sg:postcode":"6900",
    "sg:province":"Ticino",
    "wof:name":"Immobiliare Bellacosta A",
    "wof:placetype":"venue"
},
  "geometry": {"coordinates":[8.9551677704,46.0127220154],"type":"Point"}
}