{
  "type": "Feature",
  "properties": {
    "iso:country":"CH",
    "sg:address":"Binzstrasse 18",
    "sg:city":"Z\u00fcrich",
    "sg:orig_category":"Grosshandel mit Software Softwareentwicklung U beratung",
    "sg:postcode":"8045",
    "sg:province":"Z\u00fcrich",
    "wof:name":"Meditext Ag Knowledge Engineering",
    "wof:placetype":"venue"
},
  "geometry": {"coordinates":[8.5150213242,47.3627510071],"type":"Point"}
}