{
  "type": "Feature",
  "properties": {
    "iso:country":"CH",
    "sg:address":"Loestrasse 79a",
    "sg:city":"Chur",
    "sg:orig_category":"Wirtschaftspr\u00fcfung, Steuerberatung U Treuhand",
    "sg:phone":"+41 81 353 38 23",
    "sg:postcode":"7000",
    "sg:province":"Graubunden",
    "wof:name":"Caviezel Gitta, Eidg. Dipl. Buchhalterin, Treuhandb\u00fcro",
    "wof:placetype":"venue"
},
  "geometry": {"coordinates":[9.5373935699,46.8592414856],"type":"Point"}
}