{
  "type": "Feature",
  "properties": {
    "iso:country":"CH",
    "sg:address":"1464",
    "sg:city":"Chavannes-le-ch\u00eane",
    "sg:orig_category":"Vereine Gesang",
    "sg:postcode":"1464",
    "sg:province":"Vaud",
    "wof:name":"St\u00e9 De Chant",
    "wof:placetype":"venue"
},
  "geometry": {"coordinates":[6.7790598869,46.7747802734],"type":"Point"}
}