{
  "type": "Feature",
  "properties": {
    "iso:country":"CH",
    "sg:address":"Burgweg 28 8000 Z\u00fcrich. Postfach",
    "sg:city":"Z\u00fcrich",
    "sg:orig_category":"Unternehmensberatung",
    "sg:postcode":"8008",
    "sg:province":"Z\u00fcrich",
    "wof:name":"Albatros Consulting Ag",
    "wof:placetype":"venue"
},
  "geometry": {"coordinates":[8.5591192245,47.3592796326],"type":"Point"}
}