{
  "type": "Feature",
  "properties": {
    "addr:full":"Wilstrasse 53 D\u00fcbendorf Z\u00fcrich 8600",
    "addr:housenumber":"53",
    "addr:postcode":"8600",
    "addr:street":"Wilstrasse;Zuerich",
    "iso:country":"CH",
    "sg:address":"Wilstrasse 53",
    "sg:city":"D\u00fcbendorf",
    "sg:orig_category":"Detailhandel mit Blumen U Pflanzen Fachdetailhandel in Verkaufsr\u00e4umen",
    "sg:phone":"+41 18215251",
    "sg:postcode":"8600",
    "sg:province":"Z\u00fcrich",
    "wof:name":"Verena Heigl Blumengesch\u00e4ft",
    "wof:placetype":"venue"
},
  "geometry": {"coordinates":[8.617572,47.393463],"type":"Point"}
}