{
  "type": "Feature",
  "properties": {
    "iso:country":"CH",
    "sg:address":"Chilchacherstrasse 24",
    "sg:city":"Koppigen",
    "sg:orig_category":"Wasserversorgung",
    "sg:phone":"+41 79 343 23 40",
    "sg:postcode":"3425",
    "sg:province":"Bern",
    "wof:name":"Fl\u00dcko, Fl\u00dcckiger Ueli",
    "wof:placetype":"venue"
},
  "geometry": {"coordinates":[7.6028208733,47.1359024048],"type":"Point"}
}