{
  "type": "Feature",
  "properties": {
    "addr:full":"Z\u00fcrichholzstrasse 7 Z\u00fcrich Z\u00fcrich 8057",
    "addr:housenumber":"7",
    "addr:postcode":"8057",
    "addr:street":"Zuerichholzstrasse",
    "iso:country":"CH",
    "sg:address":"Z\u00fcrichholzstrasse 7",
    "sg:city":"Z\u00fcrich",
    "sg:orig_category":"Architektur U Ingenieurb\u00fcros",
    "sg:phone":"+41 55 214 27 41",
    "sg:postcode":"8057",
    "sg:province":"Z\u00fcrich",
    "wof:name":"Dr.j. Stoffel Elektro-ingenieurb\u00fcro",
    "wof:placetype":"venue"
},
  "geometry": {"coordinates":[8.829574,47.231796],"type":"Point"}
}