{
  "type": "Feature",
  "properties": {
    "iso:country":"CH",
    "sg:address":"L\u00e4rchenstrasse 24 4142 M\u00fcnchenstein. Postfach",
    "sg:city":"M\u00fcnchenstein",
    "sg:orig_category":"Herstellung von Kakao, Schokoladeerzeugnissen U Zuckerwaren",
    "sg:phone":"+41 61 411 95 69",
    "sg:postcode":"4142",
    "sg:province":"Basel-Landschaft",
    "wof:name":"Gebr\u00fcder Jud Ag",
    "wof:placetype":"venue"
},
  "geometry": {"coordinates":[7.6122307777,47.5216598511],"type":"Point"}
}