{
  "type": "Feature",
  "properties": {
    "addr:full":"Bahnhofstrasse 32 8880 Walenstadt. Postfach 96 Walenstadt St. Gallen 8880",
    "addr:housenumber":"32;96",
    "addr:postcode":"8880 walenstadt.;8880",
    "addr:street":"Bahnhofstrasse;Postfach",
    "iso:country":"CH",
    "sg:address":"Bahnhofstrasse 32 8880 Walenstadt. Postfach 96",
    "sg:city":"Walenstadt",
    "sg:orig_category":"Detailhandel mit Beleuchtungs U Haushaltsgegenst\u00e4nden Grosshandel mit Textilien",
    "sg:phone":"+41 81 735 11 30",
    "sg:postcode":"8880",
    "sg:province":"St. Gallen",
    "wof:name":"Rido-laden Imhof S. + P.",
    "wof:placetype":"venue"
},
  "geometry": {"coordinates":[9.313007,47.121632],"type":"Point"}
}