{
  "type": "Feature",
  "properties": {
    "iso:country":"CH",
    "sg:address":"Schulstrasse 12",
    "sg:city":"Basadingen",
    "sg:orig_category":"K\u00fcnstlerische Schulen",
    "sg:phone":"+41 52 654 18 15",
    "sg:postcode":"8254",
    "sg:province":"Thurgau",
    "wof:name":"Musikschule Andelfingen & Umgebung",
    "wof:placetype":"venue"
},
  "geometry": {"coordinates":[8.7454977036,47.6691856384],"type":"Point"}
}