{
  "type": "Feature",
  "properties": {
    "iso:country":"CH",
    "sg:address":"Rottes Route Des 18 A",
    "sg:city":"Conthey",
    "sg:orig_category":"Unclassifiable Establishments",
    "sg:postcode":"1964",
    "sg:province":"Valais",
    "wof:name":"Abel Joaquim 'eismann'",
    "wof:placetype":"venue"
},
  "geometry": {"coordinates":[7.2982797623,46.224319458],"type":"Point"}
}