{
  "type": "Feature",
  "properties": {
    "iso:country":"CH",
    "sg:address":"Gewerbestrasse 37",
    "sg:city":"Nottwil",
    "sg:orig_category":"Instandhaltung U Reparatur von Automobilen",
    "sg:phone":"+41 41 937 15 15",
    "sg:postcode":"6207",
    "sg:province":"Luzern",
    "wof:name":"Garage Frey Nottwil Gmbh",
    "wof:placetype":"venue"
},
  "geometry": {"coordinates":[8.1325321198,47.1378631592],"type":"Point"}
}