{
  "type": "Feature",
  "properties": {
    "iso:country":"CH",
    "sg:address":"Karpfenstrasse 5",
    "sg:city":"Oberrieden",
    "sg:orig_category":"Unternehmensberatung",
    "sg:phone":"+41 17221033",
    "sg:postcode":"8942",
    "sg:province":"Z\u00fcrich",
    "wof:name":"Dubach Marcel Consulting",
    "wof:placetype":"venue"
},
  "geometry": {"coordinates":[8.578748703,47.2811508179],"type":"Point"}
}