{
  "type": "Feature",
  "properties": {
    "iso:country":"CH",
    "sg:address":"Br\u00fc\u00f6l 11",
    "sg:city":"Schwyz",
    "sg:orig_category":"Unclassifiable Establishments",
    "sg:postcode":"6430",
    "sg:province":"Schwyz",
    "wof:name":"Dr.med.mathias Oechslin Spezialarzt Fmh",
    "wof:placetype":"venue"
},
  "geometry": {"coordinates":[8.6544418335,47.0197296143],"type":"Point"}
}