{
  "type": "Feature",
  "properties": {
    "iso:country":"CH",
    "sg:address":"Randenstrasse 36",
    "sg:city":"Schleitheim",
    "sg:orig_category":"Grosshandel mit Getreide, Saatgut U Futtermitteln Handelsvermittlung U Grosshandel",
    "sg:phone":"+41 79 602 59 85",
    "sg:postcode":"8226",
    "sg:province":"Schaffhausen",
    "wof:name":"The Nuance Group Ag",
    "wof:placetype":"venue"
},
  "geometry": {"coordinates":[9.3504571915,47.4141807556],"type":"Point"}
}