{
  "type": "Feature",
  "properties": {
    "iso:country":"CH",
    "sg:address":"Allmendstrasse 15a",
    "sg:city":"Liestal",
    "sg:orig_category":"Druckweiterverarbeitung Herstellung von Wellpapier U pappe sowie von Verpackungsmitteln aus Papier, ",
    "sg:phone":"+41 61 921 94 09",
    "sg:postcode":"4410",
    "sg:province":"Basel-Landschaft",
    "wof:name":"Kurt Tschudin Muster & Verpackungen",
    "wof:placetype":"venue"
},
  "geometry": {"coordinates":[7.7400579453,47.4821510315],"type":"Point"}
}