{
  "type": "Feature",
  "properties": {
    "addr:full":"Limmattalstrasse 177 Z\u00fcrich Z\u00fcrich 8049",
    "addr:housenumber":"177",
    "addr:postcode":"8049",
    "addr:street":"Limmattalstrasse",
    "iso:country":"CH",
    "sg:address":"Limmattalstrasse 177",
    "sg:city":"Z\u00fcrich",
    "sg:orig_category":"Architektur U Ingenieurb\u00fcros",
    "sg:phone":"+41 13424333",
    "sg:postcode":"8049",
    "sg:province":"Z\u00fcrich",
    "wof:name":"Rauch, Bau-promotion",
    "wof:placetype":"venue"
},
  "geometry": {"coordinates":[8.499398,47.401814],"type":"Point"}
}