{
  "type": "Feature",
  "properties": {
    "iso:country":"CH",
    "sg:address":"6702",
    "sg:city":"Claro",
    "sg:classifiers":[
        {
            "category":"Restaurant",
            "type":"Food & Drink"
        }
    ],
    "sg:phone":"+41 91 683 11 79",
    "sg:postcode":"6702",
    "sg:province":"Ticino",
    "wof:name":"Osteria-ristorante Del Sole",
    "wof:placetype":"venue"
},
  "geometry": {"coordinates":[9.0503702164,45.870098114],"type":"Point"}
}