{
  "type": "Feature",
  "properties": {
    "iso:country":"CH",
    "sg:address":"Hauptstrasse 46",
    "sg:city":"Islikon",
    "sg:classifiers":[
        {
            "category":"Banks & Credit Unions",
            "subcategory":"Bank",
            "type":"Services"
        }
    ],
    "sg:phone":"+41 4154551126",
    "sg:postcode":"8546",
    "sg:province":"Thurgau",
    "wof:name":"Thurg. Kantonalbank",
    "wof:placetype":"venue"
},
  "geometry": {"coordinates":[8.844075,47.546684],"type":"Point"}
}