{
  "type": "Feature",
  "properties": {
    "iso:country":"CH",
    "sg:address":"Steinbrunnengasse 9",
    "sg:city":"Seengen",
    "sg:orig_category":"Detailhandel mit Fleisch U Fleischwaren HOTELS: MIT RESTAURANT",
    "sg:phone":"+41 62 777 11 20",
    "sg:postcode":"5707",
    "sg:province":"Aargau",
    "wof:name":"Gasthaus Und Metzgerei Zum Roten Haus Hs. B\u00fchlmann",
    "wof:placetype":"venue"
},
  "geometry": {"coordinates":[8.2064876556,47.3229637146],"type":"Point"}
}