{
  "type": "Feature",
  "properties": {
    "iso:country":"CH",
    "sg:address":"Kronenplatz 5",
    "sg:city":"Dietikon",
    "sg:orig_category":"Herstellung von Fahrr\u00e4dern Herstellung von Metallerzeugnissen ohne Maschinenbau",
    "sg:phone":"+41 17403824",
    "sg:postcode":"8953",
    "sg:province":"Z\u00fcrich",
    "wof:name":"Walter Hedinger",
    "wof:placetype":"venue"
},
  "geometry": {"coordinates":[8.4010009766,47.4056358337],"type":"Point"}
}