{
  "type": "Feature",
  "properties": {
    "iso:country":"CH",
    "sg:address":"8862 Sch\u00fcbelbach. Postfach",
    "sg:city":"Siebnen",
    "sg:orig_category":"Haltung von Rindern",
    "sg:postcode":"8854",
    "sg:province":"Schwyz",
    "wof:name":"Viehzuchtgenossenschaft Sch\u00fcbelbach",
    "wof:placetype":"venue"
},
  "geometry": {"coordinates":[8.9299297333,47.1765098572],"type":"Point"}
}