{
  "type": "Feature",
  "properties": {
    "iso:country":"CH",
    "sg:address":"Bahnhofplatz 4",
    "sg:city":"Biel/bienne",
    "sg:orig_category":"Bahnhofbuffets",
    "sg:phone":"+41 32 322 33 11",
    "sg:postcode":"2502",
    "sg:province":"Bern",
    "wof:name":"Bahnhofbuffet Poissonni\u00e8re",
    "wof:placetype":"venue"
},
  "geometry": {"coordinates":[7.243405,47.132797],"type":"Point"}
}