{
  "type": "Feature",
  "properties": {
    "iso:country":"CH",
    "sg:address":"Grand-rue",
    "sg:city":"Bulle",
    "sg:orig_category":"Detailhandel mit Fleisch U Fleischwaren",
    "sg:phone":"+41 26 912 78 88",
    "sg:postcode":"1630",
    "sg:province":"Fribourg",
    "wof:name":"Soci\u00e9t\u00e9 De Ma\u00eetres-bouchers Et Charcutiers De La Ville De Bulle Et Des Environs",
    "wof:placetype":"venue"
},
  "geometry": {"coordinates":[7.0580048561,46.6206245422],"type":"Point"}
}