{
  "type": "Feature",
  "properties": {
    "iso:country":"CH",
    "sg:address":"Urn\u00e4schstrasse 6 9014 St. Gallen",
    "sg:city":"Zust",
    "sg:orig_category":"Architektur U Ingenieurb\u00fcros",
    "sg:postcode":"14",
    "wof:name":"Architekturb\u00fcro Kutter Ag",
    "wof:placetype":"venue"
},
  "geometry": {"coordinates":[9.33633,47.40992],"type":"Point"}
}