{
  "type": "Feature",
  "properties": {
    "iso:country":"CH",
    "sg:address":"Grabenstrasse 26",
    "sg:city":"Diessenhofen",
    "sg:classifiers":[
        {
            "category":"Communications",
            "subcategory":"Radio Station",
            "type":"Services"
        }
    ],
    "sg:phone":"+41 52 657 38 90",
    "sg:postcode":"8253",
    "sg:province":"Thurgau",
    "sg:tags":[
        "fernsehanstalten",
        "u"
    ],
    "wof:name":"Lokalfernsehen Diessenhofen",
    "wof:placetype":"venue"
},
  "geometry": {"coordinates":[8.7535171509,47.6880531311],"type":"Point"}
}