{
  "type": "Feature",
  "properties": {
    "iso:country":"CH",
    "sg:address":"Kleinwangenstrasse 12 6280 Hochdorf. Postfach 846",
    "sg:city":"Hochdorf",
    "sg:orig_category":"Detailhandel mit Waren verschiedener Art, Hauptrichtung Nahrungsmittel Fachdetailhandel mit Nahrungs",
    "sg:phone":"+41 41 910 28 28",
    "sg:postcode":"6281",
    "sg:province":"Luzern",
    "wof:name":"Spar Supermarkt",
    "wof:placetype":"venue"
},
  "geometry": {"coordinates":[8.291387558,47.1672859192],"type":"Point"}
}