{
  "type": "Feature",
  "properties": {
    "iso:country":"CH",
    "sg:address":"Plein-centre",
    "sg:city":"Verbier",
    "sg:orig_category":"Elektroinstallation Herstellung von sonstigen elektrischen Ausr\u00fcstungen",
    "sg:phone":"+41 27 775 38 38",
    "sg:postcode":"1936",
    "sg:province":"Valais",
    "wof:name":"Baillod Sa",
    "wof:placetype":"venue"
},
  "geometry": {"coordinates":[7.2229619026,46.0967292786],"type":"Point"}
}