{
  "type": "Feature",
  "properties": {
    "iso:country":"CH",
    "sg:address":"Landbergstrasse 86",
    "sg:city":"Flawil",
    "sg:classifiers":[
        {
            "category":"Personal",
            "subcategory":"Sauna",
            "type":"Services"
        }
    ],
    "sg:phone":"+41 52 365 42 43",
    "sg:postcode":"9230",
    "sg:province":"St. Gallen",
    "wof:name":"Hugo Weber Sauna",
    "wof:placetype":"venue"
},
  "geometry": {"coordinates":[8.9052438736,47.4805603027],"type":"Point"}
}