{
  "type": "Feature",
  "properties": {
    "iso:country":"CH",
    "sg:address":"Glattalstrasse 501",
    "sg:city":"R\u00fcmlang",
    "sg:classifiers":[
        {
            "category":"Professional",
            "subcategory":"Computer Services",
            "type":"Services"
        }
    ],
    "sg:phone":"+41 71 274 20 50",
    "sg:postcode":"8153",
    "sg:province":"Z\u00fcrich",
    "sg:tags":[
        "administration",
        "software"
    ],
    "wof:name":"Cmsys Ag",
    "wof:placetype":"venue"
},
  "geometry": {"coordinates":[9.334637,47.401894],"type":"Point"}
}