{
  "type": "Feature",
  "properties": {
    "iso:country":"CH",
    "sg:address":"Birch 103",
    "sg:city":"Unterb\u00f6zberg",
    "sg:orig_category":"Bauschreinerei Herstellung von Konstruktionsteilen, Fertigbauteilen U Ausbauelementen aus Holz",
    "sg:phone":"+41 56 441 39 68",
    "sg:postcode":"5224",
    "sg:province":"Aargau",
    "wof:name":"Schreinerei-zimmerei Kurt Br\u00e4ndli",
    "wof:placetype":"venue"
},
  "geometry": {"coordinates":[8.145706,47.485912],"type":"Point"}
}