{
  "type": "Feature",
  "properties": {
    "iso:country":"CH",
    "sg:address":"Freiestrasse 221 8032 Z\u00fcrich. Postfach",
    "sg:city":"Z\u00fcrich",
    "sg:orig_category":"Vereine Quartier",
    "sg:postcode":"8029",
    "wof:name":"Quartierverein Hirslanden",
    "wof:placetype":"venue"
},
  "geometry": {"coordinates":[8.5668554306,47.3604240417],"type":"Point"}
}