{
  "type": "Feature",
  "properties": {
    "iso:country":"CH",
    "sg:address":"Br\u00fchlstrasse 49 2503 Biel/bienne. Postfach",
    "sg:city":"Biel/bienne",
    "sg:orig_category":"Schreib U \u00dcbersetzungsb\u00fcros",
    "sg:phone":"+41 71 891 57 71",
    "sg:postcode":"2503",
    "sg:province":"Bern",
    "wof:name":"Ed-service, Deppeler Erich",
    "wof:placetype":"venue"
},
  "geometry": {"coordinates":[9.5062351227,47.4447250366],"type":"Point"}
}