{
  "type": "Feature",
  "properties": {
    "iso:country":"CH",
    "sg:address":"Stichermattstrasse 11",
    "sg:city":"Emmen",
    "sg:orig_category":"Herstellung von Metallkonstruktionen Stahl U Leichtmetallbau",
    "sg:phone":"+41 41 260 22 88",
    "sg:postcode":"6032",
    "sg:province":"Luzern",
    "wof:name":"Kempf Metallbau, Inhaber Bucher & Kleeb, Emmen",
    "wof:placetype":"venue"
},
  "geometry": {"coordinates":[8.2997789383,47.0770301819],"type":"Point"}
}