{
  "type": "Feature",
  "properties": {
    "iso:country":"CH",
    "sg:address":"Reutistrasse 1",
    "sg:city":"Kreuzlingen",
    "sg:orig_category":"Architekturb\u00fcros",
    "sg:phone":"+41 71 688 45 32",
    "sg:postcode":"8280",
    "sg:province":"Thurgau",
    "wof:name":"Heinz Willi Dipl. Architekt Fh",
    "wof:placetype":"venue"
},
  "geometry": {"coordinates":[9.197611,47.639587],"type":"Point"}
}