{
  "type": "Feature",
  "properties": {
    "iso:country":"CH",
    "sg:address":"L\u00e4ttenstrasse 19 8185 Winkel. Postfach",
    "sg:city":"Winkel",
    "sg:orig_category":"Detailhandel mit Metallwaren, Anstrichmitteln, Glaswaren, Bau U Heimwerkerbedarf",
    "sg:postcode":"8185",
    "sg:province":"Z\u00fcrich",
    "wof:name":"Bmg Gas + Industrietechnologie Gmbh",
    "wof:placetype":"venue"
},
  "geometry": {"coordinates":[8.5603599548,47.4923858643],"type":"Point"}
}