{
  "type": "Feature",
  "properties": {
    "iso:country":"CH",
    "sg:address":"Via Maroggia 7",
    "sg:city":"Bissone",
    "sg:orig_category":"Herstellung von Metallkonstruktionen",
    "sg:phone":"+41 91 649 68 20",
    "sg:postcode":"6816",
    "sg:province":"Ticino",
    "wof:name":"Costruzioni Metalliche Di Comizzoli Erna",
    "wof:placetype":"venue"
},
  "geometry": {"coordinates":[8.9660110474,45.9494247437],"type":"Point"}
}