{
  "type": "Feature",
  "properties": {
    "iso:country":"CH",
    "sg:address":"Konstanzerstrasse 9",
    "sg:city":"Kreuzlingen",
    "sg:orig_category":"Detailhandel mit Waren verschiedener Art, Hauptrichtung Nahrungsmittel",
    "sg:phone":"+41 71 672 18 18",
    "sg:postcode":"8280",
    "sg:province":"Thurgau",
    "wof:name":"Migros-markt",
    "wof:placetype":"venue"
},
  "geometry": {"coordinates":[9.1684331894,47.6545524597],"type":"Point"}
}