{
  "type": "Feature",
  "properties": {
    "addr:full":"Hauptstrasse Pf\u00e4fers St. Gallen 7312",
    "addr:housenumber":"7312",
    "addr:street":"Hauptstrasse",
    "iso:country":"CH",
    "sg:address":"Hauptstrasse",
    "sg:city":"Pf\u00e4fers",
    "sg:classifiers":[
        {
            "category":"Banks & Credit Unions",
            "subcategory":"Bank",
            "type":"Services"
        }
    ],
    "sg:phone":"+41 81 302 48 48",
    "sg:postcode":"7312",
    "sg:province":"St. Gallen",
    "wof:name":"Raiffeisenbank",
    "wof:placetype":"venue"
},
  "geometry": {"coordinates":[9.500452,46.988842],"type":"Point"}
}