{
  "type": "Feature",
  "properties": {
    "iso:country":"CH",
    "sg:address":"Viktoriaplatz 2",
    "sg:city":"Bern 25",
    "sg:orig_category":"Industrie, Metallindustrie",
    "sg:postcode":"3000",
    "sg:province":"Bern",
    "wof:name":"Juvent Sa",
    "wof:placetype":"venue"
},
  "geometry": {"coordinates":[7.450888,46.955032],"type":"Point"}
}