{
  "type": "Feature",
  "properties": {
    "addr:full":"Viktoriaplatz 2 Bern 25 Bern 3000",
    "addr:housenumber":"2;25",
    "addr:postcode":"3000",
    "addr:street":"Viktoriaplatz;Bern;Bern",
    "iso:country":"CH",
    "sg:address":"Viktoriaplatz 2",
    "sg:city":"Bern 25",
    "sg:orig_category":"Industrie, Metallindustrie",
    "sg:postcode":"3000",
    "sg:province":"Bern",
    "wof:name":"Juvent Sa",
    "wof:placetype":"venue"
},
  "geometry": {"coordinates":[7.450888,46.955032],"type":"Point"}
}