{
  "type": "Feature",
  "properties": {
    "iso:country":"CH",
    "sg:address":"St. Wolfgang",
    "sg:city":"H\u00fcnenberg",
    "sg:orig_category":"G\u00fcterbef\u00f6rderung im Strassenverkehr",
    "sg:postcode":"6331",
    "sg:province":"Zug",
    "wof:name":"Stocker Transport Ag",
    "wof:placetype":"venue"
},
  "geometry": {"coordinates":[8.4245271683,47.1830596924],"type":"Point"}
}