{
  "type": "Feature",
  "properties": {
    "iso:country":"CH",
    "sg:address":"Rue De Montchoisy 50",
    "sg:city":"Gen\u00e8ve",
    "sg:orig_category":"Detailhandel mit Blumen U Pflanzen",
    "sg:phone":"+41 22 736 98 41",
    "sg:postcode":"1207",
    "sg:province":"Gen\u00e8ve",
    "wof:name":"Heidi Heer D\u00e9corations Florales",
    "wof:placetype":"venue"
},
  "geometry": {"coordinates":[6.16242,46.204258],"type":"Point"}
}