{
  "type": "Feature",
  "properties": {
    "iso:country":"CH",
    "sg:address":"G\u00fcterstrasse 276",
    "sg:city":"Basel",
    "sg:orig_category":"Unclassifiable Establishments",
    "sg:postcode":"4053",
    "sg:province":"Basel-Stadt",
    "wof:name":"Haci Kocahal",
    "wof:placetype":"venue"
},
  "geometry": {"coordinates":[7.5992288589,47.5413208008],"type":"Point"}
}