{
  "type": "Feature",
  "properties": {
    "iso:country":"CH",
    "sg:address":"La Bichette",
    "sg:city":"Vich",
    "sg:orig_category":"G\u00fcterbef\u00f6rderung im Strassenverkehr",
    "sg:phone":"+41 22 364 35 06",
    "sg:postcode":"1267",
    "sg:province":"Vaud",
    "wof:name":"Zika Transports, Jovanovic Zika",
    "wof:placetype":"venue"
},
  "geometry": {"coordinates":[6.2545890808,46.4256706238],"type":"Point"}
}