{
  "type": "Feature",
  "properties": {
    "iso:country":"CH",
    "sg:address":"Via Cantonale 34a",
    "sg:city":"Manno",
    "sg:orig_category":"Non-Classified Establishments",
    "sg:postcode":"6928",
    "sg:province":"Ticino",
    "wof:name":"Ms Multy Solutions Sagl",
    "wof:placetype":"venue"
},
  "geometry": {"coordinates":[8.9234104156,46.0330581665],"type":"Point"}
}