{
  "type": "Feature",
  "properties": {
    "addr:full":"Route De Veyrier 272 Veyrier Gen\u00e8ve 1255",
    "addr:housenumber":"272",
    "addr:postcode":"1255",
    "addr:street":"Route De Veyrier",
    "iso:country":"CH",
    "sg:address":"Route De Veyrier 272",
    "sg:city":"Veyrier",
    "sg:classifiers":[
        {
            "category":"Banks & Credit Unions",
            "subcategory":"Bank",
            "type":"Services"
        }
    ],
    "sg:phone":"+41 26 785 18 14",
    "sg:postcode":"1255",
    "sg:province":"Gen\u00e8ve",
    "wof:name":"Banque Raiffeisen Voll\u00ebges",
    "wof:placetype":"venue"
},
  "geometry": {"coordinates":[7.16049,46.095032],"type":"Point"}
}