{
  "type": "Feature",
  "properties": {
    "iso:country":"CH",
    "sg:address":"Avenue Des Planches 25",
    "sg:city":"Montreux",
    "sg:orig_category":"Vorschulen, Kinderg\u00e4rten",
    "sg:phone":"+41 21 963 59 35",
    "sg:postcode":"1820",
    "sg:province":"Vaud",
    "wof:name":"Ecole Enfantine Catholique",
    "wof:placetype":"venue"
},
  "geometry": {"coordinates":[6.9130430222,46.4308166504],"type":"Point"}
}