{
  "type": "Feature",
  "properties": {
    "iso:country":"CH",
    "sg:address":"Neugass 13",
    "sg:city":"Berneck",
    "sg:orig_category":"Detailhandel mit Radio U Fernsehger\u00e4ten Detailhandel mit elektrischen Haushalts-,Radio U Fernsehger\u00e4",
    "sg:phone":"+41 71 744 68 80",
    "sg:postcode":"9442",
    "sg:province":"St. Gallen",
    "wof:name":"Mario Bordasch Radio-tv-hifi-service",
    "wof:placetype":"venue"
},
  "geometry": {"coordinates":[9.6118154526,47.4255104065],"type":"Point"}
}