{
  "type": "Feature",
  "properties": {
    "iso:country":"CH",
    "sg:address":"Bahnhofstrasse 2",
    "sg:city":"Visp",
    "sg:orig_category":"Non-Classified Establishments",
    "sg:phone":"+41 56 633 11 60",
    "sg:postcode":"3930",
    "sg:province":"Valais",
    "wof:name":"Hotel Waage",
    "wof:placetype":"venue"
},
  "geometry": {"coordinates":[8.3395528793,47.3492012024],"type":"Point"}
}