{
  "type": "Feature",
  "properties": {
    "iso:country":"CH",
    "sg:address":"8048",
    "sg:city":"Z\u00fcrich",
    "sg:orig_category":"Sonstiger Grosshandel",
    "sg:phone":"+41 62 216 45 25",
    "sg:postcode":"8048",
    "sg:province":"Z\u00fcrich",
    "wof:name":"Vivell & Co Ag Schwimmbadtechnik",
    "wof:placetype":"venue"
},
  "geometry": {"coordinates":[7.8424930573,47.3260231018],"type":"Point"}
}