{
  "type": "Feature",
  "properties": {
    "iso:country":"CH",
    "sg:address":"Erlachstrasse 23",
    "sg:city":"Bern",
    "sg:orig_category":"Detailhandel mit Radio U Fernsehger\u00e4ten Detailhandel mit elektrischen Haushalts-,Radio U Fernsehger\u00e4",
    "sg:phone":"+41 31 302 67 87",
    "sg:postcode":"3012",
    "sg:province":"Bern",
    "wof:name":"B\u00f6hlen R. Inhaber Kilcher Bruno",
    "wof:placetype":"venue"
},
  "geometry": {"coordinates":[7.4313941002,46.9518356323],"type":"Point"}
}