{
  "type": "Feature",
  "properties": {
    "addr:full":"Via Nassa 66 Lugano Ticino 6900",
    "addr:housenumber":"66",
    "addr:postcode":"6900",
    "addr:street":"Via Nassa",
    "iso:country":"CH",
    "sg:address":"Via Nassa 66",
    "sg:city":"Lugano",
    "sg:orig_category":"Detailhandel mit Bekleidung",
    "sg:phone":"+41 91 923 79 22",
    "sg:postcode":"6900",
    "sg:province":"Ticino",
    "wof:name":"Modaseta Sa",
    "wof:placetype":"venue"
},
  "geometry": {"coordinates":[8.949176,46.000641],"type":"Point"}
}