{
  "type": "Feature",
  "properties": {
    "addr:full":"Bellevoie 8 Delsberg Jura 2800",
    "addr:housenumber":"8",
    "addr:postcode":"2800",
    "addr:street":"Bellevoie;Jura",
    "iso:country":"CH",
    "sg:address":"Bellevoie 8",
    "sg:city":"Delsberg",
    "sg:orig_category":"Architektur U Ingenieurb\u00fcros Geometerb\u00fcros",
    "sg:phone":"+41 27 398 54 51",
    "sg:postcode":"2800",
    "sg:province":"Jura",
    "wof:name":"Bureau D'ing\u00e9nieurs & G\u00e9om\u00e8tres Jollien & Rey Sa",
    "wof:placetype":"venue"
},
  "geometry": {"coordinates":[7.406825,46.276783],"type":"Point"}
}