{
  "type": "Feature",
  "properties": {
    "iso:country":"CH",
    "sg:address":"1429",
    "sg:city":"Giez",
    "sg:orig_category":"RESTAURANTS: TEA-ROOMS",
    "sg:postcode":"1429",
    "sg:province":"Vaud",
    "wof:name":"Wenger Alfred.",
    "wof:placetype":"venue"
},
  "geometry": {"coordinates":[6.6160497665,46.813659668],"type":"Point"}
}