{
  "type": "Feature",
  "properties": {
    "iso:country":"CH",
    "sg:address":"Hans Huber-strasse 41 4500 Solothurn. Postfach",
    "sg:city":"Solothurn",
    "sg:orig_category":"Gesundheitswesen",
    "sg:phone":"+41 32 622 17 37",
    "sg:postcode":"4500",
    "sg:province":"Solothurn",
    "wof:name":"Therapie Leasing L\u00fcdi Ag",
    "wof:placetype":"venue"
},
  "geometry": {"coordinates":[7.5283122063,47.2009010315],"type":"Point"}
}