{
  "type": "Feature",
  "properties": {
    "iso:country":"CH",
    "sg:address":"Dorfstrasse 82",
    "sg:city":"Buchberg",
    "sg:orig_category":"Gemeindeverwaltungen",
    "sg:phone":"+41 18671311",
    "sg:postcode":"8454",
    "sg:province":"Schaffhausen",
    "wof:name":"Gemeindeverwaltung Buchberg",
    "wof:placetype":"venue"
},
  "geometry": {"coordinates":[8.5584802628,47.5724182129],"type":"Point"}
}