{
  "type": "Feature",
  "properties": {
    "iso:country":"CH",
    "sg:address":"1899",
    "sg:city":"Torgon",
    "sg:orig_category":"Sportvereine Sch\u00fctzen",
    "sg:postcode":"1899",
    "sg:province":"Valais",
    "wof:name":"St\u00e9 De Tir La Montagnarde Revereulaz",
    "wof:placetype":"venue"
},
  "geometry": {"coordinates":[6.8765802383,46.3203010559],"type":"Point"}
}