{
  "type": "Feature",
  "properties": {
    "iso:country":"CH",
    "sg:address":"Cour Avenue De 67",
    "sg:city":"Lausanne",
    "sg:classifiers":[
        {
            "category":"Bars & Pubs",
            "type":"Food & Drink"
        }
    ],
    "sg:postcode":"1007",
    "sg:province":"Vaud",
    "wof:name":"Recordon Pierre-alain Et Michel",
    "wof:placetype":"venue"
},
  "geometry": {"coordinates":[6.632335,46.519596],"type":"Point"}
}