{
  "type": "Feature",
  "properties": {
    "iso:country":"CH",
    "sg:address":"Limmattalstrasse 65",
    "sg:city":"Geroldswil",
    "sg:orig_category":"Instandhaltung U Reparatur von Automobilen",
    "sg:phone":"+41 17470033",
    "sg:postcode":"8954",
    "sg:province":"Z\u00fcrich",
    "wof:name":"Bernhard Schweizer, Carrosseriewerkst\u00e4tte",
    "wof:placetype":"venue"
},
  "geometry": {"coordinates":[8.4072628021,47.4216766357],"type":"Point"}
}