{
  "type": "Feature",
  "properties": {
    "iso:country":"CH",
    "sg:address":"Jungfraustrasse 25",
    "sg:city":"Uetendorf",
    "sg:orig_category":"Kaminfeger",
    "sg:phone":"+41 19303636",
    "sg:postcode":"3661",
    "sg:province":"Bern",
    "wof:name":"Peter Waser Kaminfegergesch\u00e4ft",
    "wof:placetype":"venue"
},
  "geometry": {"coordinates":[8.7983121872,47.3326835632],"type":"Point"}
}