{
  "type": "Feature",
  "properties": {
    "iso:country":"CH",
    "sg:address":"Taubenhausstrasse 24",
    "sg:city":"Luzern",
    "sg:orig_category":"Psychotherapie",
    "sg:phone":"+41 41 310 84 92",
    "sg:postcode":"6005",
    "sg:province":"Luzern",
    "wof:name":"J. Bendel & C. Bolay Psychotherapie",
    "wof:placetype":"venue"
},
  "geometry": {"coordinates":[8.3019561768,47.0423698425],"type":"Point"}
}