{
  "type": "Feature",
  "properties": {
    "iso:country":"CH",
    "sg:address":"L\u00f6berenstrasse 49",
    "sg:city":"Zug",
    "sg:orig_category":"Gesundheitswesen",
    "sg:phone":"+41 41 711 62 82",
    "sg:postcode":"6300",
    "sg:province":"Zug",
    "wof:name":"Buck J\u00fcrg, Beratung-seminare, Werkstatt F\u00fcr Wohlbefinden",
    "wof:placetype":"venue"
},
  "geometry": {"coordinates":[8.5231637955,47.1717033386],"type":"Point"}
}