{
  "type": "Feature",
  "properties": {
    "iso:country":"CH",
    "sg:address":"Gottardo Via San 78",
    "sg:city":"Balerna",
    "sg:classifiers":[
        {
            "category":"Travel",
            "subcategory":"Hotels & Motels",
            "type":"Entertainment"
        }
    ],
    "sg:postcode":"6828",
    "sg:province":"Ticino",
    "sg:tags":[
        "hotels",
        "mit",
        "restaurant"
    ],
    "wof:name":"Albergo Garage Carrozzeria Bellavista Sa",
    "wof:placetype":"venue"
},
  "geometry": {"coordinates":[9.0070486069,45.8459281921],"type":"Point"}
}