{
  "type": "Feature",
  "properties": {
    "iso:country":"CH",
    "sg:address":"Binzikerstrasse 10",
    "sg:city":"Gr\u00fcningen",
    "sg:orig_category":"Arztpraxen",
    "sg:phone":"+41 19353993",
    "sg:postcode":"8627",
    "sg:province":"Z\u00fcrich",
    "wof:name":"Dr.med.robert Minder Spezialarzt Fmh",
    "wof:placetype":"venue"
},
  "geometry": {"coordinates":[8.759852,47.280548],"type":"Point"}
}