{
  "type": "Feature",
  "properties": {
    "iso:country":"CH",
    "sg:address":"Gewerbestrasse 17a",
    "sg:city":"Unter\u00e4geri",
    "sg:orig_category":"Mechanische Werkst\u00e4tten",
    "sg:phone":"+41 41 750 26 71",
    "sg:postcode":"6314",
    "sg:province":"Zug",
    "wof:name":"Fridolin Meier Werkzeugschleiferei",
    "wof:placetype":"venue"
},
  "geometry": {"coordinates":[8.5733003616,47.1336669922],"type":"Point"}
}