{
  "type": "Feature",
  "properties": {
    "iso:country":"CH",
    "sg:address":"Plazzet 14",
    "sg:city":"Samedan",
    "sg:orig_category":"Detailhandel mit Schuhen Detailhandel mit medizinischen U orthop\u00e4dischen Artikeln",
    "sg:phone":"+41 81 852 11 38",
    "sg:postcode":"7503",
    "sg:province":"Graubunden",
    "wof:name":"Orlando Rada",
    "wof:placetype":"venue"
},
  "geometry": {"coordinates":[9.8717031479,46.5347557068],"type":"Point"}
}