{
  "type": "Feature",
  "properties": {
    "iso:country":"CH",
    "sg:address":"Schwyzerstrasse 21c",
    "sg:city":"Brunnen",
    "sg:orig_category":"Unclassifiable Establishments",
    "sg:postcode":"6440",
    "sg:province":"Schwyz",
    "wof:name":"Tsch\u00fcmperlin & Co Schuhe & Sport",
    "wof:placetype":"venue"
},
  "geometry": {"coordinates":[8.6139593124,47.0006523132],"type":"Point"}
}