{
  "type": "Feature",
  "properties": {
    "iso:country":"CH",
    "sg:address":"Baarerstrasse 73 6300 Zug. Postfach",
    "sg:city":"Zug",
    "sg:orig_category":"Unclassifiable Establishments",
    "sg:postcode":"6300",
    "sg:province":"Zug",
    "wof:name":"Syntec Holding Ag",
    "wof:placetype":"venue"
},
  "geometry": {"coordinates":[8.3031778336,47.396697998],"type":"Point"}
}