{
  "type": "Feature",
  "properties": {
    "iso:country":"CH",
    "sg:address":"Av. Daniel-jeanrichard 2 1",
    "sg:city":"Fleurier",
    "sg:classifiers":[
        {
            "category":"Science Facility",
            "type":"Public Place"
        }
    ],
    "sg:phone":"+41 32 926 46 85",
    "sg:postcode":"2114",
    "sg:province":"Neuch\u00e2tel",
    "sg:tags":[
        "dial",
        "gauge"
    ],
    "wof:name":"Montres Dolmy S.a.",
    "wof:placetype":"venue"
},
  "geometry": {"coordinates":[6.8219380379,47.094127655],"type":"Point"}
}