{
  "type": "Feature",
  "properties": {
    "iso:country":"CH",
    "sg:address":"Avenue Du Ch\u00e2teau 33",
    "sg:city":"Prilly",
    "sg:orig_category":"Innendekorationsateliers Maler U Glasergewerbe",
    "sg:phone":"+41 21 634 88 17",
    "sg:postcode":"1008",
    "sg:province":"Vaud",
    "wof:name":"Furlan C.",
    "wof:placetype":"venue"
},
  "geometry": {"coordinates":[6.6041908264,46.5378684998],"type":"Point"}
}