{
  "type": "Feature",
  "properties": {
    "iso:country":"CH",
    "sg:address":"Bahnstrasse 43 5012 Sch\u00f6nenwerd. Postfach",
    "sg:city":"Sch\u00f6nenwerd",
    "sg:orig_category":"Herstellung von Lederwaren U Schuhen Stickerei",
    "sg:phone":"+41 34 435 13 43",
    "sg:postcode":"5012",
    "sg:province":"Solothurn",
    "wof:name":"Martin Eggimann Glockenriemenstickerei",
    "wof:placetype":"venue"
},
  "geometry": {"coordinates":[7.7483658791,47.061416626],"type":"Point"}
}