{
  "type": "Feature",
  "properties": {
    "iso:country":"CH",
    "sg:address":"Neufeldstrasse 128",
    "sg:city":"Bern",
    "sg:orig_category":"Arztpraxen",
    "sg:phone":"+41 31 301 68 16",
    "sg:postcode":"3012",
    "sg:province":"Bern",
    "wof:name":"Dr.med.hans Gerber Spezialarzt Fmh",
    "wof:placetype":"venue"
},
  "geometry": {"coordinates":[7.43493,46.958202],"type":"Point"}
}