{
  "type": "Feature",
  "properties": {
    "iso:country":"CH",
    "sg:address":"Coquelicots Chemin Des 16",
    "sg:city":"Vernier",
    "sg:orig_category":"Herstellung von medizinischen U chirurgischen Ger\u00e4ten sowie orthop\u00e4dischen Vorrichtungen",
    "sg:phone":"+41 22 306 04 01",
    "sg:postcode":"1214",
    "sg:province":"Gen\u00e8ve",
    "wof:name":"Eli Lilly Vostok Sa",
    "wof:placetype":"venue"
},
  "geometry": {"coordinates":[6.0947341919,46.2219467163],"type":"Point"}
}