{
  "type": "Feature",
  "properties": {
    "iso:country":"CH",
    "sg:address":"Niederhardstrasse 18",
    "sg:city":"D\u00e4niken",
    "sg:classifiers":[
        {
            "category":"Professional",
            "subcategory":"Computer Services",
            "type":"Services"
        }
    ],
    "sg:phone":"+41 62 291 42 16",
    "sg:postcode":"4658",
    "sg:province":"Solothurn",
    "sg:tags":[
        "development",
        "software"
    ],
    "wof:name":"Argon Software Ag",
    "wof:placetype":"venue"
},
  "geometry": {"coordinates":[7.9757680893,47.3568458557],"type":"Point"}
}