{
  "type": "Feature",
  "properties": {
    "iso:country":"CH",
    "sg:address":"Hottingerstrasse 14",
    "sg:city":"Z\u00fcrich",
    "sg:orig_category":"Erschliessung von Grundst\u00fccken",
    "sg:postcode":"8021",
    "sg:province":"Z\u00fcrich",
    "wof:name":"Gfw Genossenschaft Zur F\u00f6rderung Des Wohnungsbaues, Gossau Sg",
    "wof:placetype":"venue"
},
  "geometry": {"coordinates":[9.2679262161,47.4167251587],"type":"Point"}
}