{
  "type": "Feature",
  "properties": {
    "iso:country":"CH",
    "sg:address":"Luzernerstrasse 34",
    "sg:city":"Kriens",
    "sg:orig_category":"Detailhandel mit M\u00f6beln U Haushaltsgegenst\u00e4nden Verlegen von Fussboden",
    "sg:phone":"+41 55 462 36 40",
    "sg:postcode":"6010",
    "sg:province":"Luzern",
    "wof:name":"Tepmat Ag Teppiche, Teppichresten; Verarbeitung, Handel",
    "wof:placetype":"venue"
},
  "geometry": {"coordinates":[8.8658399582,47.1920814514],"type":"Point"}
}