{
  "type": "Feature",
  "properties": {
    "iso:country":"CH",
    "sg:address":"Hauptstrasse 50 3186 D\u00fcdingen. Postfach",
    "sg:city":"D\u00fcdingen",
    "sg:orig_category":"Architektur U Ingenieurb\u00fcros",
    "sg:postcode":"3186",
    "sg:province":"Fribourg",
    "wof:name":"Ass - Evolvere Ag",
    "wof:placetype":"venue"
},
  "geometry": {"coordinates":[7.192016,46.851524],"type":"Point"}
}