{
  "type": "Feature",
  "properties": {
    "iso:country":"CH",
    "sg:address":"1272",
    "sg:city":"Genolier",
    "sg:orig_category":"Fachdetailhandel in Verkaufsr\u00e4umen",
    "sg:postcode":"1272",
    "sg:province":"Vaud",
    "wof:name":"Le Kiosque, Fleurs Et Vid\u00e9o, Antignani & Cie",
    "wof:placetype":"venue"
},
  "geometry": {"coordinates":[6.2200398445,46.4343109131],"type":"Point"}
}