{
  "type": "Feature",
  "properties": {
    "addr:full":"Konstanzer Strasse 29b Kreuzlingen Thurgau 8280",
    "addr:housenumber":"29b",
    "addr:postcode":"8280",
    "addr:street":"Konstanzer Strasse",
    "iso:country":"CH",
    "sg:address":"Konstanzer Strasse 29b",
    "sg:city":"Kreuzlingen",
    "sg:orig_category":"Bau U Wohngenossenschaften",
    "sg:phone":"+41 71 672 96 60",
    "sg:postcode":"8280",
    "sg:province":"Thurgau",
    "wof:name":"Logis Suisse (ostschweiz) Sa",
    "wof:placetype":"venue"
},
  "geometry": {"coordinates":[9.166035,47.651569],"type":"Point"}
}