{
  "type": "Feature",
  "properties": {
    "iso:country":"CH",
    "sg:address":"Route Du P\u00e9age 10",
    "sg:city":"Sugiez",
    "sg:orig_category":"Unclassifiable Establishments",
    "sg:postcode":"1786",
    "sg:province":"Fribourg",
    "wof:name":"Maco Inneneinrichtungen Gmbh",
    "wof:placetype":"venue"
},
  "geometry": {"coordinates":[7.1174750328,46.9645385742],"type":"Point"}
}