{
  "type": "Feature",
  "properties": {
    "iso:country":"CH",
    "sg:address":"Pertuis-du-sault Ch. Du 42 2000 Neuch\u00e2tel. Postfach",
    "sg:city":"Neuch\u00e2tel",
    "sg:orig_category":"Ackerbau",
    "sg:phone":"+41 32 721 45 19",
    "sg:postcode":"2000",
    "sg:province":"Neuch\u00e2tel",
    "wof:name":"Fischer Claude Bureau De Biologie De Terrain",
    "wof:placetype":"venue"
},
  "geometry": {"coordinates":[6.934281,46.999985],"type":"Point"}
}