{
  "type": "Feature",
  "properties": {
    "iso:country":"CH",
    "sg:address":"Schulhausstrasse 64 8704 Herrliberg. Postfach",
    "sg:city":"Herrliberg",
    "sg:orig_category":"Grosshandel mit Nahrungsmitteln, Getr\u00e4nken U Tabakwaren ohne ausgepr\u00e4gten Schwerpunkt",
    "sg:postcode":"8704",
    "sg:province":"Z\u00fcrich",
    "wof:name":"Import & Handel, R\u00e4schle Urs",
    "wof:placetype":"venue"
},
  "geometry": {"coordinates":[8.6108922958,47.2894973755],"type":"Point"}
}