{
  "type": "Feature",
  "properties": {
    "iso:country":"CH",
    "sg:address":"R\u00f6merstrasse 14 2555 Br\u00fcgg Be. Postfach",
    "sg:city":"Biel/bienne",
    "sg:orig_category":"Allgemeiner Hochbau Strassenbau",
    "sg:phone":"+41 41 660 42 46",
    "sg:postcode":"2503",
    "sg:province":"Bern",
    "wof:name":"B\u00fcrgi Ag Alpnach Bauunternehmung",
    "wof:placetype":"venue"
},
  "geometry": {"coordinates":[8.24486,46.893364],"type":"Point"}
}