{
  "type": "Feature",
  "properties": {
    "iso:country":"CH",
    "sg:address":"Bleicherweg 15a",
    "sg:city":"Z\u00fcrich",
    "sg:orig_category":"Detailhandel mit Uhren U Schmuck",
    "sg:phone":"+41 12015112",
    "sg:postcode":"8002",
    "sg:province":"Z\u00fcrich",
    "wof:name":"Gh Goldhaus Ag Bijouterie",
    "wof:placetype":"venue"
},
  "geometry": {"coordinates":[8.5361948013,47.3679771423],"type":"Point"}
}