{
  "type": "Feature",
  "properties": {
    "iso:country":"CH",
    "sg:address":"L\u00e4ttichstrasse 6",
    "sg:city":"Baar",
    "sg:orig_category":"Detailhandel mit M\u00f6beln U Haushaltsgegenst\u00e4nden",
    "sg:postcode":"6340",
    "sg:province":"Zug",
    "wof:name":"Mds M\u00f6bel & Design Ag",
    "wof:placetype":"venue"
},
  "geometry": {"coordinates":[9.0449714661,47.4638404846],"type":"Point"}
}