{
  "type": "Feature",
  "properties": {
    "addr:full":"Ch. Du Fief-de-chapitre 1 Petit-lancy Grand-lancy Gen\u00e8ve 1212",
    "addr:housenumber":"1",
    "addr:postcode":"1212",
    "addr:street":"Ch. Du Fief-De-Chapitre;Grand-Lancy",
    "iso:country":"CH",
    "sg:address":"Ch. Du Fief-de-chapitre 1 Petit-lancy",
    "sg:city":"Grand-lancy",
    "sg:orig_category":"Architektur U Ingenieurb\u00fcros",
    "sg:postcode":"1212",
    "sg:province":"Gen\u00e8ve",
    "wof:name":"Architecture Studio, Sanchez Jos\u00e9",
    "wof:placetype":"venue"
},
  "geometry": {"coordinates":[6.1205,46.182808],"type":"Point"}
}