{
  "type": "Feature",
  "properties": {
    "iso:country":"CH",
    "sg:address":"Luzernerstrasse 181",
    "sg:city":"Moosleerau",
    "sg:orig_category":"Sanit\u00e4r, Heizungs U L\u00fcftungsinstallation Sanit\u00e4rinstallation",
    "sg:postcode":"5054",
    "sg:province":"Aargau",
    "wof:name":"Graber Otto",
    "wof:placetype":"venue"
},
  "geometry": {"coordinates":[8.0646591187,47.2699241638],"type":"Point"}
}