{
  "type": "Feature",
  "properties": {
    "iso:country":"CH",
    "sg:address":"L\u00e4ttenwiesenstrasse 34",
    "sg:city":"Glattbrugg",
    "sg:orig_category":"Grosshandel mit sonstigen Gebrauchs U Verbrauchsg\u00fctern",
    "sg:postcode":"8152",
    "sg:province":"Z\u00fcrich",
    "wof:name":"Moritz Esther, Werbeartikel",
    "wof:placetype":"venue"
},
  "geometry": {"coordinates":[8.5623903275,47.4267082214],"type":"Point"}
}