{
  "type": "Feature",
  "properties": {
    "iso:country":"CH",
    "sg:address":"Neudorfstrasse 30",
    "sg:city":"Horgen",
    "sg:orig_category":"Architektur U Ingenieurb\u00fcros Architekturb\u00fcros",
    "sg:phone":"+41 17257343",
    "sg:postcode":"8810",
    "sg:province":"Z\u00fcrich",
    "wof:name":"Archenuovo Martin Wieser Architekturb\u00fcro",
    "wof:placetype":"venue"
},
  "geometry": {"coordinates":[8.601577,47.258194],"type":"Point"}
}