{
  "type": "Feature",
  "properties": {
    "iso:country":"CH",
    "sg:address":"Industriestrasse 49 3052 Zollikofen. Postfach 580",
    "sg:city":"Zollikofen",
    "sg:orig_category":"Herstellung von Metallerzeugnissen ohne Maschinenbau Herstellung von landwirtschaftlichen Maschinen",
    "sg:phone":"+41 31 911 40 24",
    "sg:postcode":"3052",
    "sg:province":"Bern",
    "wof:name":"Ott Landmaschinen Ag",
    "wof:placetype":"venue"
},
  "geometry": {"coordinates":[7.4666061401,47.0069046021],"type":"Point"}
}