{
  "type": "Feature",
  "properties": {
    "iso:country":"CH",
    "sg:address":"Buriet",
    "sg:city":"Thal",
    "sg:orig_category":"Herstellung von Metallkonstruktionen",
    "sg:phone":"+41 71 888 26 27",
    "sg:postcode":"9425",
    "sg:province":"St. Gallen",
    "wof:name":"Pl\u00fcss E.",
    "wof:placetype":"venue"
},
  "geometry": {"coordinates":[9.5775098801,47.475818634],"type":"Point"}
}