{
  "type": "Feature",
  "properties": {
    "iso:country":"CH",
    "sg:address":"Avenue De La Gare 42",
    "sg:city":"Del\u00e9mont",
    "sg:orig_category":"Detailhandel mit Uhren U Schmuck Reparatur von Uhren U Schmuck",
    "sg:phone":"+41 32 422 47 50",
    "sg:postcode":"2800",
    "sg:province":"Jura",
    "wof:name":"Alain Kottelat Horlogerie-bijouterie",
    "wof:placetype":"venue"
},
  "geometry": {"coordinates":[7.3492779732,47.3639602661],"type":"Point"}
}