{
  "type": "Feature",
  "properties": {
    "iso:country":"CH",
    "sg:address":"M\u00fchle 1 9127 Peterzell. Postfach",
    "sg:city":"Peterzell",
    "sg:orig_category":"Zimmerei, Ingenieurholzbau",
    "sg:phone":"+41 71 377 20 40",
    "sg:postcode":"9127",
    "sg:province":"St. Gallen",
    "wof:name":"Jbex Ag Holzbau",
    "wof:placetype":"venue"
},
  "geometry": {"coordinates":[8.3682727814,48.1414604187],"type":"Point"}
}