{
  "type": "Feature",
  "properties": {
    "iso:country":"CH",
    "sg:address":"Kleinfeldstrasse 6",
    "sg:city":"Ipsach",
    "sg:orig_category":"Architektur U Ingenieurb\u00fcros",
    "sg:phone":"+41 32 331 31 41",
    "sg:postcode":"2563",
    "sg:province":"Bern",
    "wof:name":"M\u00fcller's B. Architekten Ag",
    "wof:placetype":"venue"
},
  "geometry": {"coordinates":[7.230381,47.111855],"type":"Point"}
}