{
  "type": "Feature",
  "properties": {
    "addr:full":"Josef-m\u00fcller-weg 1 Sursee Luzern 6210",
    "addr:housenumber":"1",
    "addr:postcode":"6210",
    "addr:street":"Josef-Mueller-Weg",
    "iso:country":"CH",
    "sg:address":"Josef-m\u00fcller-weg 1",
    "sg:city":"Sursee",
    "sg:orig_category":"Arztpraxen",
    "sg:phone":"+41 41 921 52 44",
    "sg:postcode":"6210",
    "sg:province":"Luzern",
    "wof:name":"Dres Med. B. Franz & H. Peters Spezial\u00e4rzte Fmh",
    "wof:placetype":"venue"
},
  "geometry": {"coordinates":[8.108226,47.172733],"type":"Point"}
}