{
  "type": "Feature",
  "properties": {
    "addr:full":"Avenue De La Gare 1950 Sion Case Postale 679 Sion Valais 1951",
    "addr:housenumber":"679",
    "addr:postcode":"1950;1951",
    "addr:street":"Avenue De La Gare;Postale",
    "iso:country":"CH",
    "sg:address":"Avenue De La Gare 1950 Sion Case Postale 679",
    "sg:city":"Sion",
    "sg:orig_category":"Detailhandel mit B\u00fcchern Grosshandel mit sonstigen Gebrauchs U Verbrauchsg\u00fctern",
    "sg:phone":"+41 27 322 26 10",
    "sg:postcode":"1951",
    "sg:province":"Valais",
    "wof:name":"Au Nain Bleu Sa",
    "wof:placetype":"venue"
},
  "geometry": {"coordinates":[7.3567,46.233364],"type":"Point"}
}