{
  "type": "Feature",
  "properties": {
    "iso:country":"CH",
    "sg:address":"Via Iragna",
    "sg:city":"Biasca",
    "sg:orig_category":"Bauingenieurb\u00fcros allgemein",
    "sg:phone":"+41 91 862 09 00",
    "sg:postcode":"6710",
    "sg:province":"Ticino",
    "wof:name":"G. Balmelli & A. Filippini Studio D'ingegneria",
    "wof:placetype":"venue"
},
  "geometry": {"coordinates":[8.969525,46.354912],"type":"Point"}
}