{
  "type": "Feature",
  "properties": {
    "iso:country":"CH",
    "sg:address":"Rosentalstrasse 55",
    "sg:city":"Winterthur",
    "sg:orig_category":"Verwaltung von Immobilien Wirtschaftspr\u00fcfung, Steuerberatung U Treuhand",
    "sg:phone":"+41 52 202 66 06",
    "sg:postcode":"8400",
    "sg:province":"Z\u00fcrich",
    "wof:name":"Holenstein Treuhand",
    "wof:placetype":"venue"
},
  "geometry": {"coordinates":[8.721783638,47.5103416443],"type":"Point"}
}