{
  "type": "Feature",
  "properties": {
    "addr:full":"Flughafen Kloten Terminal A 8058 Z\u00fcrich. Postfach Z\u00fcrich Z\u00fcrich 8001",
    "addr:postcode":"8058 zuerich. postfach;8001",
    "addr:street":"A",
    "iso:country":"CH",
    "sg:address":"Flughafen Kloten Terminal A 8058 Z\u00fcrich. Postfach",
    "sg:city":"Z\u00fcrich",
    "sg:orig_category":"Betrieb von Taxis",
    "sg:postcode":"8001",
    "sg:province":"Z\u00fcrich",
    "wof:name":"Alternative Parking Ag",
    "wof:placetype":"venue"
},
  "geometry": {"coordinates":[8.53801,47.369091],"type":"Point"}
}