{
  "type": "Feature",
  "properties": {
    "addr:full":"Missionsstrasse 2 Basel Basel-Stadt 4055",
    "addr:housenumber":"2",
    "addr:postcode":"4055",
    "addr:street":"Missionsstrasse",
    "iso:country":"CH",
    "sg:address":"Missionsstrasse 2",
    "sg:city":"Basel",
    "sg:orig_category":"Detailhandel mit Antiquit\u00e4ten",
    "sg:phone":"+41 61 281 60 30",
    "sg:postcode":"4055",
    "sg:province":"Basel-Stadt",
    "wof:name":"Peter Herzog Antiquit\u00e4ten",
    "wof:placetype":"venue"
},
  "geometry": {"coordinates":[7.58073,47.558475],"type":"Point"}
}