{
  "type": "Feature",
  "properties": {
    "addr:full":"Via Dangio 6949 Comano. Postfach Comano Ticino 6949",
    "addr:postcode":"6949 comano. postfach;6949",
    "addr:street":"Via Dangio",
    "iso:country":"CH",
    "sg:address":"Via Dangio 6949 Comano. Postfach",
    "sg:city":"Comano",
    "sg:orig_category":"Detailhandel mit B\u00fcchern, Zeitungen, Schreib U Papeteriewaren",
    "sg:phone":"+41 91 940 12 12",
    "sg:postcode":"6949",
    "sg:province":"Ticino",
    "wof:name":"M\u00f6we Ag",
    "wof:placetype":"venue"
},
  "geometry": {"coordinates":[8.951669,46.041435],"type":"Point"}
}