{
  "type": "Feature",
  "properties": {
    "addr:full":"Weststrasse 8 Chur Graubunden 7000",
    "addr:housenumber":"8",
    "addr:postcode":"7000",
    "addr:street":"Weststrasse",
    "iso:country":"CH",
    "sg:address":"Weststrasse 8",
    "sg:city":"Chur",
    "sg:orig_category":"Bauschreinerei Herstellung von Konstruktionsteilen, Fertigbauteilen U Ausbauelementen aus Holz",
    "sg:phone":"+41 81 252 33 81",
    "sg:postcode":"7000",
    "sg:province":"Graubunden",
    "wof:name":"J\u00f6rimann Toni",
    "wof:placetype":"venue"
},
  "geometry": {"coordinates":[9.524216,46.846451],"type":"Point"}
}