{
  "type": "Feature",
  "properties": {
    "iso:country":"CH",
    "sg:address":"Hauptgasse 19",
    "sg:city":"Willisau",
    "sg:orig_category":"Detailhandel mit Brot, Back U S\u00fcsswaren",
    "sg:phone":"+41 34 445 33 55",
    "sg:postcode":"6130",
    "sg:province":"Luzern",
    "wof:name":"Fritz Nyffenegger Aemme-beck",
    "wof:placetype":"venue"
},
  "geometry": {"coordinates":[7.58305,47.08551],"type":"Point"}
}