{
  "type": "Feature",
  "properties": {
    "iso:country":"CH",
    "sg:address":"Place De L'h\u00f4tel De Ville 8",
    "sg:city":"Echallens",
    "sg:orig_category":"Unternehmensberatung",
    "sg:phone":"+41 32 724 78 74",
    "sg:postcode":"1040",
    "sg:province":"Vaud",
    "wof:name":"Fran\u00e7ois Girardet, Consultant Horloger",
    "wof:placetype":"venue"
},
  "geometry": {"coordinates":[6.9310851097,46.9903335571],"type":"Point"}
}