{
  "type": "Feature",
  "properties": {
    "iso:country":"CH",
    "sg:address":"En S\u00e9cheron 1123 Aclens. Postfach",
    "sg:city":"Aclens",
    "sg:orig_category":"Gartenbau",
    "sg:postcode":"1123",
    "sg:province":"Vaud",
    "wof:name":"Tschanz Alain Sa",
    "wof:placetype":"venue"
},
  "geometry": {"coordinates":[6.5100498199,46.5683288574],"type":"Point"}
}