{
  "type": "Feature",
  "properties": {
    "iso:country":"CH",
    "sg:address":"Lagerstrasse 14 8600 D\u00fcbendorf. Postfach",
    "sg:city":"D\u00fcbendorf",
    "sg:orig_category":"Herstellung von Bereifungen",
    "sg:postcode":"8600",
    "sg:province":"Z\u00fcrich",
    "wof:name":"Pneu-handel D\u00fcbendorf Schmitz Ag Pneus, Auspuffanlagen; Handel. Liegenschaften Usw",
    "wof:placetype":"venue"
},
  "geometry": {"coordinates":[8.6035528183,47.4002456665],"type":"Point"}
}