{
  "type": "Feature",
  "properties": {
    "iso:country":"CH",
    "sg:address":"Hauptstrasse 41",
    "sg:city":"Fruthwilen",
    "sg:orig_category":"Markt U Meinungsforschung",
    "sg:postcode":"8559",
    "wof:name":"Britta Consulting Service Ag",
    "wof:placetype":"venue"
},
  "geometry": {"coordinates":[9.4814300537,47.1677818298],"type":"Point"}
}