{
  "type": "Feature",
  "properties": {
    "iso:country":"CH",
    "sg:address":"Ibelweg 18a 6300 Zug. Postfach",
    "sg:city":"Zug",
    "sg:orig_category":"Non-Classified Establishments",
    "sg:postcode":"6300",
    "sg:province":"Zug",
    "wof:name":"Hl Investments Inc.",
    "wof:placetype":"venue"
},
  "geometry": {"coordinates":[8.5249156952,47.1819992065],"type":"Point"}
}