{
  "type": "Feature",
  "properties": {
    "addr:full":"Alpenstrasse 9 Ostermundigen Bern 3072",
    "addr:housenumber":"9",
    "addr:postcode":"3072",
    "addr:street":"Alpenstrasse",
    "iso:country":"CH",
    "sg:address":"Alpenstrasse 9",
    "sg:city":"Ostermundigen",
    "sg:classifiers":[
        {
            "category":"Banks & Credit Unions",
            "subcategory":"Bank",
            "type":"Services"
        }
    ],
    "sg:phone":"+41 31 931 75 15",
    "sg:postcode":"3072",
    "sg:province":"Bern",
    "wof:name":"Schweiz. Mobiliar",
    "wof:placetype":"venue"
},
  "geometry": {"coordinates":[7.48576,46.956264],"type":"Point"}
}