{
  "type": "Feature",
  "properties": {
    "iso:country":"CH",
    "sg:address":"Pfeffingerweg 1 4144 Arlesheim. Postfach",
    "sg:city":"Arlesheim",
    "sg:orig_category":"Herstellung von Medikamenten U sonstigen pharmazeutischen Erzeugnissen",
    "sg:postcode":"4144",
    "sg:province":"Basel-Landschaft",
    "wof:name":"Laboratorio Cora Sagl",
    "wof:placetype":"venue"
},
  "geometry": {"coordinates":[7.6147489548,47.4937400818],"type":"Point"}
}