{
  "type": "Feature",
  "properties": {
    "iso:country":"CH",
    "sg:address":"Quai Maria-belgia 8",
    "sg:city":"Vevey",
    "sg:orig_category":"Vermittlung von Immobilien",
    "sg:phone":"+41 21 921 41 12",
    "sg:postcode":"1800",
    "sg:province":"Vaud",
    "wof:name":"La Fiaz Sa Agence Immobili\u00e8re",
    "wof:placetype":"venue"
},
  "geometry": {"coordinates":[6.837665081,46.4601287842],"type":"Point"}
}