{
  "type": "Feature",
  "properties": {
    "iso:country":"CH",
    "sg:address":"Louis Giroud-strasse 26 4600 Olten. Postfach",
    "sg:city":"Olten",
    "sg:orig_category":"Pulvermetallurgie Schmieden, Pressen, Stanzen U Profilwalzen von Metallen Stahl U Leichtmetallbau",
    "sg:phone":"+41 62 287 78 78",
    "sg:postcode":"4601",
    "sg:province":"Solothurn",
    "wof:name":"Stiftung F\u00fcr Wohlfahrtszwecke Der Giroud-olma Ag",
    "wof:placetype":"venue"
},
  "geometry": {"coordinates":[7.9093251228,47.3450584412],"type":"Point"}
}