{
  "type": "Feature",
  "properties": {
    "iso:country":"CH",
    "sg:address":"Moorberg Nassenwil",
    "sg:city":"Niederhasli",
    "sg:orig_category":"Landwirtschaft, Jagd U damit verbundene Dienstleistungen",
    "sg:phone":"+41 79 666 65 11",
    "sg:postcode":"8155",
    "sg:province":"Z\u00fcrich",
    "wof:name":"Hansruedi Schmid Gutsbetrieb",
    "wof:placetype":"venue"
},
  "geometry": {"coordinates":[8.4839477539,47.4812355042],"type":"Point"}
}