{
  "type": "Feature",
  "properties": {
    "iso:country":"CH",
    "sg:address":"Quai Du Seujet 10",
    "sg:city":"Gen\u00e8ve",
    "sg:classifiers":[
        {
            "category":"Professional",
            "subcategory":"Advertising",
            "type":"Services"
        }
    ],
    "sg:phone":"+41 22 906 49 49",
    "sg:postcode":"1201",
    "sg:province":"Gen\u00e8ve",
    "sg:tags":[
        "agency"
    ],
    "wof:name":"Grey Worldwide",
    "wof:placetype":"venue"
},
  "geometry": {"coordinates":[6.137059,46.205723],"type":"Point"}
}