{
  "type": "Feature",
  "properties": {
    "iso:country":"CH",
    "sg:address":"Tulpenstrasse 1",
    "sg:city":"Z\u00fcrich",
    "sg:orig_category":"Wirtschaftsverb\u00e4nde Gewerbeverb\u00e4nde/-vereine",
    "sg:phone":"+41 13226729",
    "sg:postcode":"8051",
    "sg:province":"Z\u00fcrich",
    "wof:name":"Gewerbeverein Schwamendingen C/o H\u00e4nni Carrosseriewerk",
    "wof:placetype":"venue"
},
  "geometry": {"coordinates":[8.5640449524,47.4055137634],"type":"Point"}
}