{
  "type": "Feature",
  "properties": {
    "iso:country":"CH",
    "sg:address":"Industrie Birren 10",
    "sg:city":"Seon",
    "sg:orig_category":"Herstellung von sonstigen chemischen Erzeugnissen",
    "sg:phone":"+41 62 769 66 44",
    "sg:postcode":"5703",
    "sg:province":"Aargau",
    "wof:name":"Soda Fresh Ag",
    "wof:placetype":"venue"
},
  "geometry": {"coordinates":[8.1603841782,47.3467407227],"type":"Point"}
}