{
  "type": "Feature",
  "properties": {
    "iso:country":"CH",
    "sg:address":"Badenerstrasse 811",
    "sg:city":"Z\u00fcrich",
    "sg:orig_category":"G\u00fcterbef\u00f6rderung im Strassenverkehr Sonstige Kurierdienste",
    "sg:phone":"+41 79 421 33 82",
    "sg:postcode":"8048",
    "sg:province":"Z\u00fcrich",
    "wof:name":"Kurier & Kleintransporte Otto Gubser",
    "wof:placetype":"venue"
},
  "geometry": {"coordinates":[8.4744358063,47.3928527832],"type":"Point"}
}