{
  "type": "Feature",
  "properties": {
    "iso:country":"CH",
    "sg:address":"Seeweg A 199",
    "sg:city":"Berlingen",
    "sg:orig_category":"Architektur U Ingenieurb\u00fcros",
    "sg:phone":"+41 18400670",
    "sg:postcode":"8267",
    "sg:province":"Thurgau",
    "wof:name":"Sunset Dienstleistungs Gmbh",
    "wof:placetype":"venue"
},
  "geometry": {"coordinates":[8.468116,47.446152],"type":"Point"}
}