{
  "type": "Feature",
  "properties": {
    "iso:country":"CH",
    "sg:address":"Hauptstrasse 1",
    "sg:city":"Arbon",
    "sg:orig_category":"Hardwareberatung",
    "sg:postcode":"9320",
    "sg:province":"Thurgau",
    "wof:name":"Yellow-com-arbon Schnarr",
    "wof:placetype":"venue"
},
  "geometry": {"coordinates":[9.4362039566,47.5155601501],"type":"Point"}
}