{
  "type": "Feature",
  "properties": {
    "iso:country":"CH",
    "sg:address":"Landstrasse 89",
    "sg:city":"Gebenstorf",
    "sg:classifiers":[
        {
            "category":"Social Services",
            "subcategory":"Child Care",
            "type":"Services"
        }
    ],
    "sg:phone":"+41 79 413 29 90",
    "sg:postcode":"5412",
    "sg:province":"Aargau",
    "sg:tags":[
        "broaching"
    ],
    "wof:name":"Horus R\u00e4umungszentrale",
    "wof:placetype":"venue"
},
  "geometry": {"coordinates":[8.236555,47.480461],"type":"Point"}
}