{
  "type": "Feature",
  "properties": {
    "addr:full":"Sonnenweg 8 N\u00e4fels Glarus 8752",
    "addr:housenumber":"8",
    "addr:postcode":"8752",
    "addr:street":"Sonnenweg;Naefels Glarus",
    "iso:country":"CH",
    "sg:address":"Sonnenweg 8",
    "sg:city":"N\u00e4fels",
    "sg:orig_category":"Allgemeiner Hoch U Tiefbau",
    "sg:postcode":"8752",
    "sg:province":"Glarus",
    "wof:name":"Schwitter-fischli Franz",
    "wof:placetype":"venue"
},
  "geometry": {"coordinates":[9.063508,47.093323],"type":"Point"}
}