{
  "type": "Feature",
  "properties": {
    "iso:country":"CH",
    "sg:address":"Rue Des Eaux-vives 8",
    "sg:city":"Gen\u00e8ve",
    "sg:orig_category":"Reiseb\u00fcros U Reiseveranstalter",
    "sg:phone":"+41 22 735 43 95",
    "sg:postcode":"1207",
    "sg:province":"Gen\u00e8ve",
    "wof:name":"Evasion Voyages Sa",
    "wof:placetype":"venue"
},
  "geometry": {"coordinates":[6.1574640274,46.2031669617],"type":"Point"}
}