{
  "type": "Feature",
  "properties": {
    "iso:country":"CH",
    "sg:address":"Alte Surbtalstrasse 29",
    "sg:city":"Unterendingen",
    "sg:orig_category":"Dachdeckerei Zimmerei, Dachdeckerei, Bauspenglerei U Abdichtung",
    "sg:phone":"+41 56 242 18 39",
    "sg:postcode":"5305",
    "sg:province":"Aargau",
    "wof:name":"Martin Riedener Bedachungen Ag Spenglerei Und Flachdachbau",
    "wof:placetype":"venue"
},
  "geometry": {"coordinates":[8.290519,47.548191],"type":"Point"}
}