{
  "type": "Feature",
  "properties": {
    "iso:country":"CH",
    "sg:address":"Konkordiastrasse 11 8032 Z\u00fcrich. Postfach",
    "sg:city":"Z\u00fcrich",
    "sg:orig_category":"Sanit\u00e4r, Heizungs U L\u00fcftungsinstallation Sanit\u00e4rinstallation",
    "sg:postcode":"8030",
    "wof:name":"Isr Installations Sanitaires Rapides, Perrotin Michel",
    "wof:placetype":"venue"
},
  "geometry": {"coordinates":[6.1343698502,46.1879043579],"type":"Point"}
}