{
  "type": "Feature",
  "properties": {
    "iso:country":"CH",
    "sg:address":"Aeschstrasse 1 8127 Forch. Postfach",
    "sg:city":"Forch",
    "sg:orig_category":"Architektur U Ingenieurb\u00fcros Architekturb\u00fcros",
    "sg:phone":"+41 19822200",
    "sg:postcode":"8127",
    "sg:province":"Z\u00fcrich",
    "wof:name":"Ettlin + Grando Gmbh",
    "wof:placetype":"venue"
},
  "geometry": {"coordinates":[8.655075,47.328751],"type":"Point"}
}