{
  "type": "Feature",
  "properties": {
    "iso:country":"CH",
    "sg:address":"R\u00fctiweg 9",
    "sg:city":"Pratteln",
    "sg:orig_category":"Gymnastik U Fitnesszentren Saunas, Solarien, Fitnesszentren U \u00e4hnliches",
    "sg:phone":"+41 61 821 90 90",
    "sg:postcode":"4133",
    "sg:province":"Basel-Landschaft",
    "wof:name":"Dynamic Sports-center, Kisling Oliver",
    "wof:placetype":"venue"
},
  "geometry": {"coordinates":[7.707862854,47.5242462158],"type":"Point"}
}