{
  "type": "Feature",
  "properties": {
    "iso:country":"CH",
    "sg:address":"Morgartenstrasse 24",
    "sg:city":"Z\u00fcrich",
    "sg:orig_category":"Architekturb\u00fcros",
    "sg:phone":"+41 12422538",
    "sg:postcode":"8004",
    "sg:province":"Z\u00fcrich",
    "wof:name":"Richard Stengele Architekturb\u00fcro",
    "wof:placetype":"venue"
},
  "geometry": {"coordinates":[8.528193,47.37146],"type":"Point"}
}