{
  "type": "Feature",
  "properties": {
    "iso:country":"CH",
    "sg:address":"Dittingerstrasse 6",
    "sg:city":"Basel",
    "sg:orig_category":"Softwareentwicklung U beratung",
    "sg:phone":"+41 61 361 46 26",
    "sg:postcode":"4053",
    "sg:province":"Basel-Stadt",
    "wof:name":"Dachs Computing & Biosciences Gmbh",
    "wof:placetype":"venue"
},
  "geometry": {"coordinates":[7.5894198418,47.5408287048],"type":"Point"}
}