{
  "type": "Feature",
  "properties": {
    "iso:country":"CH",
    "sg:address":"Hausmatt 10",
    "sg:city":"Seftigen",
    "sg:orig_category":"Allgemeiner Hoch U Tiefbau",
    "sg:phone":"+41 79 356 49 65",
    "sg:postcode":"3662",
    "sg:province":"Bern",
    "wof:name":"Messerli Bau Ag",
    "wof:placetype":"venue"
},
  "geometry": {"coordinates":[7.543812,46.78722],"type":"Point"}
}