{
  "type": "Feature",
  "properties": {
    "iso:country":"CH",
    "sg:address":"M\u00fchlemattstrasse 15",
    "sg:city":"Luzern",
    "sg:orig_category":"Architektur U Ingenieurb\u00fcros",
    "sg:phone":"+41 41 361 02 63",
    "sg:postcode":"6004",
    "sg:province":"Luzern",
    "wof:name":"Sivag Luzern A. Meier",
    "wof:placetype":"venue"
},
  "geometry": {"coordinates":[8.301436,47.056183],"type":"Point"}
}