{
  "type": "Feature",
  "properties": {
    "iso:country":"CH",
    "sg:address":"Stadthausstrasse 81",
    "sg:city":"Winterthur",
    "sg:orig_category":"Pensionskassen",
    "sg:phone":"+41 52 213 82 52",
    "sg:postcode":"8400",
    "sg:province":"Z\u00fcrich",
    "wof:name":"F\u00fcrsorgekasse Der Societ\u00e0 Cooperativa In Winterthur",
    "wof:placetype":"venue"
},
  "geometry": {"coordinates":[8.7288913727,47.5000724792],"type":"Point"}
}