{
  "type": "Feature",
  "properties": {
    "iso:country":"CH",
    "sg:address":"Rue Des Ronzades 9 1200 Gen\u00e8ve. Postfach",
    "sg:city":"Gen\u00e8ve",
    "sg:orig_category":"Detailhandel mit Brot, Back U S\u00fcsswaren",
    "sg:phone":"+41 22 300 30 90",
    "sg:postcode":"1200",
    "sg:province":"Gen\u00e8ve",
    "wof:name":"Correia Mesquita Da Silva Silvia Da Conceicao Boulangerie, P\u00e2tisserie, Tea-room",
    "wof:placetype":"venue"
},
  "geometry": {"coordinates":[6.136975,46.190678],"type":"Point"}
}