{
  "type": "Feature",
  "properties": {
    "iso:country":"CH",
    "sg:address":"Avenue Europe 21",
    "sg:city":"Monthey",
    "sg:orig_category":"Betrieb von Taxis",
    "sg:phone":"+41 24 471 41 41",
    "sg:postcode":"1870",
    "sg:province":"Valais",
    "wof:name":"Taxis De Monthey Association",
    "wof:placetype":"venue"
},
  "geometry": {"coordinates":[6.946892,46.261143],"type":"Point"}
}