{
  "type": "Feature",
  "properties": {
    "iso:country":"CH",
    "sg:address":"Sch\u00f6nenbuchstrasse 15",
    "sg:city":"Allschwil",
    "sg:orig_category":"Zahnarztpraxen",
    "sg:phone":"+41 61 481 14 14",
    "sg:postcode":"4123",
    "sg:province":"Basel-Landschaft",
    "wof:name":"Dr. Med. Dent. Laurent Meier Zahnarzt",
    "wof:placetype":"venue"
},
  "geometry": {"coordinates":[7.534722805,47.5513343811],"type":"Point"}
}