{
  "type": "Feature",
  "properties": {
    "iso:country":"CH",
    "sg:address":"W. Kutter-weg 31",
    "sg:city":"Biel/bienne",
    "sg:orig_category":"Sportvereine Velo Rad-& Motorfahrer-Bund SRB",
    "sg:phone":"+41 32 365 89 30",
    "sg:postcode":"2503",
    "sg:province":"Bern",
    "wof:name":"Radrennclub Magglingen",
    "wof:placetype":"venue"
},
  "geometry": {"coordinates":[7.2565498352,47.1257705688],"type":"Point"}
}