{
  "type": "Feature",
  "properties": {
    "iso:country":"CH",
    "sg:address":"Hohw\u00fcrz",
    "sg:city":"Eggiwil",
    "sg:orig_category":"Landw. Genossenschaften Viehzucht",
    "sg:phone":"+41 34 491 13 13",
    "sg:postcode":"3537",
    "sg:province":"Bern",
    "wof:name":"Viehzuchtgenossenschaft Trubschachen Hans Thomi",
    "wof:placetype":"venue"
},
  "geometry": {"coordinates":[7.832321167,46.883480072],"type":"Point"}
}