{
  "type": "Feature",
  "properties": {
    "iso:country":"CH",
    "sg:address":"Burgdorfstrasse 5",
    "sg:city":"Th\u00f6rigen",
    "sg:orig_category":"Geb\u00e4ude, Wohnungsreinigung Reinigungsgewerbe",
    "sg:phone":"+41 62 961 59 55",
    "sg:postcode":"3367",
    "sg:province":"Bern",
    "wof:name":"Buri Peter, Reinigungsgesch\u00e4ft",
    "wof:placetype":"venue"
},
  "geometry": {"coordinates":[7.7269420624,47.1726341248],"type":"Point"}
}