{
  "type": "Feature",
  "properties": {
    "iso:country":"CH",
    "sg:address":"Schaffhauserstrasse 139",
    "sg:city":"Kloten",
    "sg:orig_category":"Detailhandel mit Uhren U Schmuck Reparatur von Uhren U Schmuck",
    "sg:phone":"+41 18137423",
    "sg:postcode":"8302",
    "sg:province":"Z\u00fcrich",
    "wof:name":"Kurt Z\u00fcrcher Uhren Bijouterie",
    "wof:placetype":"venue"
},
  "geometry": {"coordinates":[8.5804872513,47.4521141052],"type":"Point"}
}