{
  "type": "Feature",
  "properties": {
    "iso:country":"CH",
    "sg:address":"Ober Wiesechen 20",
    "sg:city":"Diegten",
    "sg:orig_category":"Sonstige pers\u00f6nliche Dienstleistungen",
    "sg:phone":"+41 61 973 92 15",
    "sg:postcode":"4457",
    "sg:province":"Basel-Landschaft",
    "wof:name":"Agro-zeller Gmbh",
    "wof:placetype":"venue"
},
  "geometry": {"coordinates":[7.7917847633,47.4187355042],"type":"Point"}
}