{
  "type": "Feature",
  "properties": {
    "iso:country":"CH",
    "sg:address":"2610",
    "sg:city":"St-imier",
    "sg:orig_category":"Alters U Pflegeheime Wohnheime",
    "sg:phone":"+41 32 941 47 17",
    "sg:postcode":"2610",
    "sg:province":"Bern",
    "wof:name":"Home Les Lauriers Sa",
    "wof:placetype":"venue"
},
  "geometry": {"coordinates":[6.995817,47.152042],"type":"Point"}
}