{
  "type": "Feature",
  "properties": {
    "addr:full":"Schloss Klingelburg 9424 Rheineck. Postfach Rheineck St. Gallen 9424",
    "addr:postcode":"9424;9424",
    "addr:street":"Rheineck. Postfach",
    "iso:country":"CH",
    "sg:address":"Schloss Klingelburg 9424 Rheineck. Postfach",
    "sg:city":"Rheineck",
    "sg:orig_category":"Architektur U Ingenieurb\u00fcros",
    "sg:postcode":"9424",
    "sg:province":"St. Gallen",
    "wof:name":"Keller & Hirschi, Architekten Htl",
    "wof:placetype":"venue"
},
  "geometry": {"coordinates":[8.261838,46.486759],"type":"Point"}
}