{
  "type": "Feature",
  "properties": {
    "iso:country":"CH",
    "sg:address":"Augustinergasse 48 8001 Z\u00fcrich. Postfach",
    "sg:city":"Z\u00fcrich",
    "sg:orig_category":"Detailhandel mit Uhren U Schmuck",
    "sg:phone":"+41 32 724 52 94",
    "sg:postcode":"8023",
    "sg:province":"Z\u00fcrich",
    "wof:name":"Bernard M\u00fcller Bijouterie",
    "wof:placetype":"venue"
},
  "geometry": {"coordinates":[6.9319930077,46.9925498962],"type":"Point"}
}