{
  "type": "Feature",
  "properties": {
    "iso:country":"CH",
    "sg:address":"M\u00fcrgstrasse 20 6370 Stans. Postfach 1148",
    "sg:city":"Stans",
    "sg:orig_category":"Jugendorganisationen",
    "sg:phone":"+41 41 618 74 66",
    "sg:postcode":"6371",
    "sg:province":"Nidwalden",
    "wof:name":"Turnsektion Jugendkraft Kollegium St.fidelis",
    "wof:placetype":"venue"
},
  "geometry": {"coordinates":[8.3707847595,46.9547538757],"type":"Point"}
}