{
  "type": "Feature",
  "properties": {
    "iso:country":"CH",
    "sg:address":"Ringstrasse 14",
    "sg:city":"Chur",
    "sg:orig_category":"Unternehmensberatung Wirtschaftspr\u00fcfung, Steuerberatung U Treuhand",
    "sg:phone":"+41 81 250 68 50",
    "sg:postcode":"7000",
    "sg:province":"Graubunden",
    "wof:name":"Uli Lippuner Bautreuhand Und Beratung",
    "wof:placetype":"venue"
},
  "geometry": {"coordinates":[9.5139331818,46.8502388],"type":"Point"}
}