{
  "type": "Feature",
  "properties": {
    "iso:country":"CH",
    "sg:address":"Rue Du Stand 38",
    "sg:city":"Gen\u00e8ve",
    "sg:orig_category":"RESTAURANTS: TEA-ROOMS",
    "sg:phone":"+41 22 320 13 22",
    "sg:postcode":"1204",
    "sg:province":"Gen\u00e8ve",
    "wof:name":"River Kwa\u00ef S\u00e0rl",
    "wof:placetype":"venue"
},
  "geometry": {"coordinates":[6.1378550529,46.2032623291],"type":"Point"}
}