{
  "type": "Feature",
  "properties": {
    "iso:country":"CH",
    "sg:address":"Einschlagweg 67 3400 Burgdorf. Postfach Postfach",
    "sg:city":"Burgdorf",
    "sg:orig_category":"Allgemeiner Hoch U Tiefbau Hoch U Tiefbau",
    "sg:phone":"+41 41 630 00 20",
    "sg:postcode":"3401",
    "sg:province":"Bern",
    "wof:name":"B\u00fcrki Hansj\u00fcrg Bauarbeiten Ag",
    "wof:placetype":"venue"
},
  "geometry": {"coordinates":[8.310492,46.997456],"type":"Point"}
}