{
  "type": "Feature",
  "properties": {
    "iso:country":"CH",
    "sg:address":"Zentweg 17",
    "sg:city":"Bern",
    "sg:orig_category":"Non-Classified Establishments",
    "sg:postcode":"3006",
    "sg:province":"Bern",
    "wof:name":"Cr-design Gmbh",
    "wof:placetype":"venue"
},
  "geometry": {"coordinates":[7.474219799,46.9566879272],"type":"Point"}
}