{
  "type": "Feature",
  "properties": {
    "iso:country":"CH",
    "sg:address":"Platz 8",
    "sg:city":"Mels",
    "sg:orig_category":"RESTAURANTS: TEA-ROOMS",
    "sg:postcode":"8887",
    "sg:province":"St. Gallen",
    "wof:name":"Margaretha Hidber-kalberer",
    "wof:placetype":"venue"
},
  "geometry": {"coordinates":[9.4195241928,47.0470428467],"type":"Point"}
}