{
  "type": "Feature",
  "properties": {
    "iso:country":"CH",
    "sg:address":"Bahnhofstrasse 37 8001 Z\u00fcrich. Postfach 6128",
    "sg:city":"Z\u00fcrich",
    "sg:orig_category":"Advokaturb\u00fcros",
    "sg:phone":"+41 12212920",
    "sg:postcode":"8023",
    "sg:province":"Z\u00fcrich",
    "wof:name":"Stierli & Partner Advokaturb\u00fcro",
    "wof:placetype":"venue"
},
  "geometry": {"coordinates":[8.538503,47.371311],"type":"Point"}
}