{
  "type": "Feature",
  "properties": {
    "iso:country":"CH",
    "sg:address":"Staubstrasse 3 8038 Z\u00fcrich. Postfach",
    "sg:city":"Z\u00fcrich",
    "sg:orig_category":"Handels-H\u00e4user U Gesellschaften",
    "sg:phone":"+41 14812466",
    "sg:postcode":"8038",
    "sg:province":"Z\u00fcrich",
    "wof:name":"Mellow Gmbh",
    "wof:placetype":"venue"
},
  "geometry": {"coordinates":[8.5321731567,47.3471183777],"type":"Point"}
}