{
  "type": "Feature",
  "properties": {
    "iso:country":"CH",
    "sg:address":"Predigergasse 8",
    "sg:city":"Z\u00fcrich",
    "sg:orig_category":"Herstellung von Metallkonstruktionen Schlossereien",
    "sg:phone":"+41 12519435",
    "sg:postcode":"8001",
    "sg:province":"Z\u00fcrich",
    "wof:name":"Hans Gautschi Metallbau & Kunstschmiede",
    "wof:placetype":"venue"
},
  "geometry": {"coordinates":[8.5464076996,47.3732147217],"type":"Point"}
}