{
  "type": "Feature",
  "properties": {
    "addr:full":"Avenue De La Gare 5 Conthey Valais 1964",
    "addr:housenumber":"5",
    "addr:postcode":"1964",
    "addr:street":"Avenue De La Gare",
    "iso:country":"CH",
    "sg:address":"Avenue De La Gare 5",
    "sg:city":"Conthey",
    "sg:orig_category":"Bahnhofbuffets Restaurants",
    "sg:phone":"+41 27 346 14 78",
    "sg:postcode":"1964",
    "sg:province":"Valais",
    "wof:name":"Restaurant Auberge Buffet",
    "wof:placetype":"venue"
},
  "geometry": {"coordinates":[7.304007,46.216724],"type":"Point"}
}