{
  "type": "Feature",
  "properties": {
    "iso:country":"CH",
    "sg:address":"Hauptstrasse 62",
    "sg:city":"Sch\u00fcpfheim",
    "sg:orig_category":"Grosshandel mit Eisenwaren sowie Installationsbedarf f\u00fcr Gas, Wasser U Heizung Herstellung von Heizk",
    "sg:phone":"+41 33 437 30 37",
    "sg:postcode":"6170",
    "sg:province":"Luzern",
    "wof:name":"Prosysteme Heizungs Und Sanit\u00e4rbedarf Gmbh",
    "wof:placetype":"venue"
},
  "geometry": {"coordinates":[8.0070590973,46.943862915],"type":"Point"}
}