{
  "type": "Feature",
  "properties": {
    "iso:country":"CH",
    "sg:address":"Gr\u00fczefeldstrasse 51 8404 Oberwinterthur. Postfach",
    "sg:city":"Oberwinterthur",
    "sg:orig_category":"Kauf U Verkauf von Immobilien auf eigene Rechnung",
    "sg:postcode":"8404",
    "sg:province":"Z\u00fcrich",
    "wof:name":"Lengwiler Immobilien Ag",
    "wof:placetype":"venue"
},
  "geometry": {"coordinates":[8.7567844391,47.4929428101],"type":"Point"}
}