{
  "type": "Feature",
  "properties": {
    "iso:country":"CH",
    "sg:address":"Via Giuseppe Motta 78a",
    "sg:city":"Massagno",
    "sg:orig_category":"Herstellung von medizinischen U chirurgischen Ger\u00e4ten sowie orthop\u00e4dischen Vorrichtungen Zahntechnis",
    "sg:phone":"+41 91 966 69 69",
    "sg:postcode":"6900",
    "sg:province":"Ticino",
    "wof:name":"Alberto Cassinelli Laboratorio D'odontotecnico",
    "wof:placetype":"venue"
},
  "geometry": {"coordinates":[8.9425897598,46.0129508972],"type":"Point"}
}