{
  "type": "Feature",
  "properties": {
    "iso:country":"CH",
    "sg:address":"Im Oberen Boden 150",
    "sg:city":"Z\u00fcrich",
    "sg:orig_category":"Herstellung von sonstigen chemischen Erzeugnissen",
    "sg:postcode":"8049",
    "sg:province":"Z\u00fcrich",
    "wof:name":"Secur Ag Oberfl\u00e4chenschutz Chemisch-technische Produkte; Herstellung U. Handel.",
    "wof:placetype":"venue"
},
  "geometry": {"coordinates":[8.4760160446,47.4159393311],"type":"Point"}
}