{
  "type": "Feature",
  "properties": {
    "addr:full":"Juch 10 Waltenschwil Aargau 5622",
    "addr:housenumber":"10",
    "addr:postcode":"5622",
    "addr:street":"Juch",
    "iso:country":"CH",
    "sg:address":"Juch 10",
    "sg:city":"Waltenschwil",
    "sg:orig_category":"Cad/Cam Programming",
    "sg:phone":"+41 56 621 88 66",
    "sg:postcode":"5622",
    "sg:province":"Aargau",
    "wof:name":"Ncp Nc-technik Ag",
    "wof:placetype":"venue"
},
  "geometry": {"coordinates":[8.295215,47.330624],"type":"Point"}
}