{
  "type": "Feature",
  "properties": {
    "iso:country":"CH",
    "sg:address":"Neue Kirchstrasse",
    "sg:city":"Thusis",
    "sg:orig_category":"Berufsberatungen",
    "sg:phone":"+41 81 651 18 62",
    "sg:postcode":"7430",
    "sg:province":"Graubunden",
    "wof:name":"Berufsberatung F\u00fcr Jugendliche & Erwachsene",
    "wof:placetype":"venue"
},
  "geometry": {"coordinates":[9.438735,46.69833],"type":"Point"}
}