{
  "type": "Feature",
  "properties": {
    "iso:country":"CH",
    "sg:address":"Stauffacherstrasse 16",
    "sg:city":"Bern",
    "sg:orig_category":"Coiffeursalons Detailhandel mit Damenbekleidung",
    "sg:phone":"+41 31 331 11 15",
    "sg:postcode":"3014",
    "sg:province":"Bern",
    "wof:name":"Atelier Haarscharf",
    "wof:placetype":"venue"
},
  "geometry": {"coordinates":[7.454807,46.960972],"type":"Point"}
}