{
  "type": "Feature",
  "properties": {
    "iso:country":"CH",
    "sg:address":"Riedtlistrasse 74",
    "sg:city":"Z\u00fcrich",
    "sg:orig_category":"Vereine Geselligkeit",
    "sg:phone":"+41 71 245 78 66",
    "sg:postcode":"8006",
    "sg:province":"Z\u00fcrich",
    "wof:name":"Oesterreicher-club",
    "wof:placetype":"venue"
},
  "geometry": {"coordinates":[9.4056873322,47.4254798889],"type":"Point"}
}