{
  "type": "Feature",
  "properties": {
    "iso:country":"CH",
    "sg:address":"Florastrasse 49",
    "sg:city":"Z\u00fcrich",
    "sg:orig_category":"Architektur U Ingenieurb\u00fcros",
    "sg:phone":"+41 14226040",
    "sg:postcode":"8008",
    "sg:province":"Z\u00fcrich",
    "wof:name":"Buchhofer Barbe Ag Umwelt Und Bauingenieure",
    "wof:placetype":"venue"
},
  "geometry": {"coordinates":[8.552895,47.361965],"type":"Point"}
}