{
  "type": "Feature",
  "properties": {
    "iso:country":"CH",
    "sg:address":"Sch\u00fcrmattstrasse 2",
    "sg:city":"Villigen",
    "sg:orig_category":"Fahrschulen, Flugschulen",
    "sg:phone":"+41 56 284 16 07",
    "sg:postcode":"5234",
    "sg:province":"Aargau",
    "wof:name":"Gino Fedrizzi Autofahrschule",
    "wof:placetype":"venue"
},
  "geometry": {"coordinates":[8.2175750732,47.5265388489],"type":"Point"}
}