{
  "type": "Feature",
  "properties": {
    "iso:country":"CH",
    "sg:address":"Battoirs Rue Des 7 1205 Gen\u00e8ve. Postfach",
    "sg:city":"Gen\u00e8ve",
    "sg:orig_category":"Forschung U Entwicklung im Bereich der Naturwissenschaften",
    "sg:phone":"+41 22 342 16 21",
    "sg:postcode":"1205",
    "sg:province":"Gen\u00e8ve",
    "wof:name":"Institut Creas, Christine Leckie",
    "wof:placetype":"venue"
},
  "geometry": {"coordinates":[6.1405248642,46.1867446899],"type":"Point"}
}