{
  "type": "Feature",
  "properties": {
    "iso:country":"CH",
    "sg:address":"Im Aecherli 7",
    "sg:city":"Russikon",
    "sg:orig_category":"Politische Parteien Evangelische Volkspartei",
    "sg:phone":"+41 55 240 44 16",
    "sg:postcode":"8332",
    "sg:province":"Z\u00fcrich",
    "wof:name":"Evp Ortspartei R\u00fcti",
    "wof:placetype":"venue"
},
  "geometry": {"coordinates":[8.8537464142,47.2499923706],"type":"Point"}
}