{
  "type": "Feature",
  "properties": {
    "iso:country":"CH",
    "sg:address":"Dorf",
    "sg:city":"Linthal",
    "sg:orig_category":"Bauschreinerei",
    "sg:phone":"+41 55 643 32 30",
    "sg:postcode":"8783",
    "sg:province":"Glarus",
    "wof:name":"Rudolf Stutz Schreinerei",
    "wof:placetype":"venue"
},
  "geometry": {"coordinates":[8.996278,46.9175],"type":"Point"}
}