{
  "type": "Feature",
  "properties": {
    "iso:country":"CH",
    "sg:address":"St. Gallerstrasse 1",
    "sg:city":"Goldach",
    "sg:orig_category":"Solarien",
    "sg:phone":"+41 71 841 88 36",
    "sg:postcode":"9403",
    "sg:province":"St. Gallen",
    "wof:name":"Lubomier Lenz Florida Sonnenstudio",
    "wof:placetype":"venue"
},
  "geometry": {"coordinates":[9.4803657532,47.4783706665],"type":"Point"}
}