{
  "type": "Feature",
  "properties": {
    "iso:country":"CH",
    "sg:address":"Aegerten",
    "sg:city":"Wilderswil",
    "sg:orig_category":"Non-Classified Establishments",
    "sg:postcode":"3812",
    "sg:province":"Bern",
    "wof:name":"Luma-motors Gmbh Garage",
    "wof:placetype":"venue"
},
  "geometry": {"coordinates":[-105.89307403559999,39.3157958984],"type":"Point"}
}