{
  "type": "Feature",
  "properties": {
    "iso:country":"CH",
    "sg:address":"Rombachstrasse 20",
    "sg:city":"Rombach",
    "sg:orig_category":"Einbau von Schreinerwaren",
    "sg:phone":"+41 62 827 34 20",
    "sg:postcode":"5022",
    "sg:province":"Aargau",
    "wof:name":"Veriset K\u00fcchen Ag K\u00fcchen & Schr\u00e4nke",
    "wof:placetype":"venue"
},
  "geometry": {"coordinates":[8.0444154739,47.4009857178],"type":"Point"}
}