{
  "type": "Feature",
  "properties": {
    "iso:country":"CH",
    "sg:address":"Seedammstrasse 83",
    "sg:city":"Freienbach",
    "sg:orig_category":"Wirtschaftspr\u00fcfung, Steuerberatung U Treuhand",
    "sg:phone":"+41 55 420 22 92",
    "sg:postcode":"8807",
    "sg:province":"Schwyz",
    "wof:name":"R\u00e4ber Treuhand",
    "wof:placetype":"venue"
},
  "geometry": {"coordinates":[8.8082752228,47.2194900513],"type":"Point"}
}