{
  "type": "Feature",
  "properties": {
    "iso:country":"CH",
    "sg:address":"H\u00fcttenrain 3",
    "sg:city":"Pfaffnau",
    "sg:orig_category":"Mit dem Versicherungsgewerbe verbundene T\u00e4tigkeiten",
    "sg:phone":"+41 62 754 10 92",
    "sg:postcode":"6264",
    "sg:province":"Luzern",
    "wof:name":"Hp Consulting Gmbh",
    "wof:placetype":"venue"
},
  "geometry": {"coordinates":[7.8999018669,47.2277336121],"type":"Point"}
}