{
  "type": "Feature",
  "properties": {
    "iso:country":"CH",
    "sg:address":"Sandrainstrasse 4",
    "sg:city":"Bern",
    "sg:orig_category":"Hardwareberatung",
    "sg:postcode":"3007",
    "sg:province":"Bern",
    "wof:name":"L\u00e1szl\u00f3 Computer-steuerungen Und Anlagen",
    "wof:placetype":"venue"
},
  "geometry": {"coordinates":[7.4413661957,46.940410614],"type":"Point"}
}