{
  "type": "Feature",
  "properties": {
    "iso:country":"CH",
    "sg:address":"Rue Saint-laurent 3 1200 Genf. Postfach",
    "sg:city":"Gen\u00e8ve",
    "sg:orig_category":"Detailhandel mit Bekleidung",
    "sg:postcode":"1204",
    "sg:province":"Gen\u00e8ve",
    "wof:name":"Version B Int\u00e9rieur Et Architecture Sa",
    "wof:placetype":"venue"
},
  "geometry": {"coordinates":[6.156241,46.200565],"type":"Point"}
}