{
  "type": "Feature",
  "properties": {
    "iso:country":"CH",
    "sg:address":"Chemin Du Vigny 12",
    "sg:city":"Riex",
    "sg:orig_category":"Rebbau",
    "sg:phone":"+41 79 436 59 41",
    "sg:postcode":"1097",
    "sg:province":"Vaud",
    "wof:name":"Jean Duboux Vigneron P\u00e9pini\u00e9riste",
    "wof:placetype":"venue"
},
  "geometry": {"coordinates":[6.7357549667,46.4933700562],"type":"Point"}
}