{
  "type": "Feature",
  "properties": {
    "iso:country":"CH",
    "sg:address":"M\u00fchletalstrasse 24",
    "sg:city":"M\u00fcnsingen",
    "sg:orig_category":"Herstellung von Futtermitteln f\u00fcr Nutztiere Mahl U Sch\u00e4lm\u00fchlen",
    "sg:phone":"+41 31 721 10 12",
    "sg:postcode":"3110",
    "sg:province":"Bern",
    "wof:name":"Strahm M\u00fchle Ag",
    "wof:placetype":"venue"
},
  "geometry": {"coordinates":[7.5735602379,46.8777999878],"type":"Point"}
}