{
  "type": "Feature",
  "properties": {
    "iso:country":"CH",
    "sg:address":"Badenerstrasse 338",
    "sg:city":"Z\u00fcrich",
    "sg:orig_category":"Autotransporte M\u00f6bel Lagerh\u00e4user",
    "sg:phone":"+41 14014860",
    "sg:postcode":"8004",
    "sg:province":"Z\u00fcrich",
    "wof:name":"W. Wiedmer Ag Transporte Umz\u00fcge Lagerhaus",
    "wof:placetype":"venue"
},
  "geometry": {"coordinates":[8.511191,47.378113],"type":"Point"}
}