{
  "type": "Feature",
  "properties": {
    "iso:country":"CH",
    "sg:address":"Alte B\u00e4ckerei",
    "sg:city":"Faulensee",
    "sg:orig_category":"Reiseb\u00fcros",
    "sg:phone":"+41 33 654 54 68",
    "sg:postcode":"3705",
    "sg:province":"Bern",
    "wof:name":"Maluco Gastro Gmbh",
    "wof:placetype":"venue"
},
  "geometry": {"coordinates":[7.700553894,46.6758499146],"type":"Point"}
}