{
  "type": "Feature",
  "properties": {
    "iso:country":"CH",
    "sg:address":"Bahnhofstrasse 4 9630 Wattwil. Postfach",
    "sg:city":"Wattwil",
    "sg:orig_category":"Detailhandel mit Computern U Software Sonstige mit der Informatik verbundene T\u00e4tigkeiten",
    "sg:phone":"+41 71 988 17 17",
    "sg:postcode":"9630",
    "sg:province":"St. Gallen",
    "wof:name":"Weboption Gmbh Dienstleistungen Im Bereich Des Hosting Von Webseiten. Hard- U. Software; Verkauf Via Internet Usw.",
    "wof:placetype":"venue"
},
  "geometry": {"coordinates":[9.085963,47.30146],"type":"Point"}
}