{
  "type": "Feature",
  "properties": {
    "iso:country":"CH",
    "sg:address":"Villastrasse 26",
    "sg:city":"Ennenda",
    "sg:orig_category":"K\u00fcnstlerische U schriftstellerische T\u00e4tigkeiten U Darbietungen Selbst\u00e4ndige bildende K\u00fcnstler",
    "sg:phone":"+41 55 640 14 77",
    "sg:postcode":"8755",
    "sg:province":"Glarus",
    "wof:name":"Oertli & Ledergerber Bildhaueratelier",
    "wof:placetype":"venue"
},
  "geometry": {"coordinates":[9.0741043091,47.0352745056],"type":"Point"}
}