{
  "type": "Feature",
  "properties": {
    "iso:country":"CH",
    "sg:address":"Hirschmattstrasse 15",
    "sg:city":"Luzern",
    "sg:orig_category":"Non-Classified Establishments",
    "sg:postcode":"6003",
    "sg:province":"Luzern",
    "wof:name":"Nightboat Ag",
    "wof:placetype":"venue"
},
  "geometry": {"coordinates":[8.3066654205,47.048625946],"type":"Point"}
}