{
  "type": "Feature",
  "properties": {
    "iso:country":"CH",
    "sg:address":"Bahnhofstrasse 17",
    "sg:city":"Z\u00fcrich",
    "sg:classifiers":[
        {
            "category":"Social Services",
            "subcategory":"Child Care",
            "type":"Services"
        }
    ],
    "sg:phone":"+41 12112030",
    "sg:postcode":"8001",
    "sg:province":"Z\u00fcrich",
    "sg:tags":[
        "baby",
        "product"
    ],
    "wof:name":"Parfa Parf\u00fcmerie Und Kosmetik Ag",
    "wof:placetype":"venue"
},
  "geometry": {"coordinates":[8.539434,47.369205],"type":"Point"}
}