{
  "type": "Feature",
  "properties": {
    "iso:country":"CH",
    "sg:address":"Rue Du Lac 17",
    "sg:city":"Yverdon-les-bains",
    "sg:orig_category":"Detailhandel mit Fleisch U Fleischwaren",
    "sg:phone":"+41 24 425 24 42",
    "sg:postcode":"1400",
    "sg:province":"Vaud",
    "wof:name":"Elisabeth Robellaz Boucherie-charcuterie",
    "wof:placetype":"venue"
},
  "geometry": {"coordinates":[6.6397771835,46.7791442871],"type":"Point"}
}