{
  "type": "Feature",
  "properties": {
    "iso:country":"CH",
    "sg:address":"Zelglistrasse 64",
    "sg:city":"Maur",
    "sg:orig_category":"Sonstiger Grosshandel",
    "sg:postcode":"8124",
    "sg:province":"Z\u00fcrich",
    "wof:name":"Wh Gmbh",
    "wof:placetype":"venue"
},
  "geometry": {"coordinates":[8.6241769791,47.3571243286],"type":"Point"}
}