{
  "type": "Feature",
  "properties": {
    "iso:country":"CH",
    "sg:address":"Buobenmatt 1 6003 Luzern. Postfach 3439",
    "sg:city":"Luzern",
    "sg:orig_category":"Steuer\u00e4mter",
    "sg:phone":"+41 41 228 51 11",
    "sg:postcode":"6002",
    "sg:province":"Luzern",
    "wof:name":"Kantonale Steuerverwaltung",
    "wof:placetype":"venue"
},
  "geometry": {"coordinates":[8.3062324524,47.0502433777],"type":"Point"}
}