{
  "type": "Feature",
  "properties": {
    "iso:country":"CH",
    "sg:address":"Tour Rue De La 3 B 1870 Monthey Case Postale 1066",
    "sg:city":"Monthey",
    "sg:orig_category":"Vermietung U Verpachtung von eigenen Immobilien",
    "sg:phone":"+41 24 471 97 77",
    "sg:postcode":"1870",
    "sg:province":"Valais",
    "wof:name":"Cec Udry Sa, Cabinet Immobilier",
    "wof:placetype":"venue"
},
  "geometry": {"coordinates":[6.9471468925,46.2516288757],"type":"Point"}
}