{
  "type": "Feature",
  "properties": {
    "iso:country":"CH",
    "sg:address":"Rte Principale 18",
    "sg:city":"Courtema\u00eeche",
    "sg:orig_category":"Herstellung von Konstruktionsteilen, Fertigbauteilen U Ausbauelementen aus Holz",
    "sg:phone":"+41 32 466 60 17",
    "sg:postcode":"2923",
    "sg:province":"Jura",
    "wof:name":"Li\u00e8vre Tony",
    "wof:placetype":"venue"
},
  "geometry": {"coordinates":[7.0479102135,47.4646186829],"type":"Point"}
}