{
  "type": "Feature",
  "properties": {
    "iso:country":"CH",
    "sg:address":"2536",
    "sg:city":"Plagne",
    "sg:orig_category":"Sportvereine Sch\u00fctzen",
    "sg:postcode":"2536",
    "sg:province":"Bern",
    "wof:name":"St\u00e9 De Tir De Campagne",
    "wof:placetype":"venue"
},
  "geometry": {"coordinates":[7.3273501396,47.1881484985],"type":"Point"}
}