{
  "type": "Feature",
  "properties": {
    "iso:country":"CH",
    "sg:address":"L\u00e4ttenstrasse 31 8952 Schlieren. Postfach",
    "sg:city":"Schlieren",
    "sg:orig_category":"Grosshandel mit keramischen Erzeugnissen, Glaswaren U Reinigungsmitteln Grosshandel mit keramischen ",
    "sg:phone":"+41 17304343",
    "sg:postcode":"8952",
    "sg:province":"Z\u00fcrich",
    "wof:name":"Glas-m\u00fcller Ag",
    "wof:placetype":"venue"
},
  "geometry": {"coordinates":[8.4427404404,47.4028015137],"type":"Point"}
}