{
  "type": "Feature",
  "properties": {
    "iso:country":"CH",
    "sg:address":"Z\u00fcrichstrasse 110b",
    "sg:city":"Adliswil",
    "sg:orig_category":"Erbringung von Dienstleistungen f\u00fcr Unternehmen",
    "sg:phone":"+41 17001696",
    "sg:postcode":"8134",
    "sg:province":"Z\u00fcrich",
    "wof:name":"Kgt Quaiser",
    "wof:placetype":"venue"
},
  "geometry": {"coordinates":[8.5299043655,47.3269309998],"type":"Point"}
}