{
  "type": "Feature",
  "properties": {
    "iso:country":"CH",
    "sg:address":"Willisauerstr. 37",
    "sg:city":"Menznau",
    "sg:classifiers":[
        {
            "category":"Home & Garden",
            "subcategory":"Furniture",
            "type":"Retail Goods"
        }
    ],
    "sg:phone":"+41 41 494 94 94",
    "sg:postcode":"6122",
    "sg:province":"Luzern",
    "sg:tags":[
        "wood"
    ],
    "wof:name":"Kronospan Ag",
    "wof:placetype":"venue"
},
  "geometry": {"coordinates":[8.0300273895,47.0883102417],"type":"Point"}
}