{
  "type": "Feature",
  "properties": {
    "iso:country":"CH",
    "sg:address":"Chlupfstrasse 7",
    "sg:city":"Sch\u00f6fflisdorf",
    "sg:orig_category":"Bauspenglerei Sanit\u00e4r, Heizungs U L\u00fcftungsinstallation",
    "sg:phone":"+41 18561383",
    "sg:postcode":"8165",
    "sg:province":"Z\u00fcrich",
    "wof:name":"Walder W. Ag",
    "wof:placetype":"venue"
},
  "geometry": {"coordinates":[8.412366,47.498749],"type":"Point"}
}