{
  "type": "Feature",
  "properties": {
    "iso:country":"CH",
    "sg:address":"Gm\u00fcndstrasse 8",
    "sg:city":"Heerbrugg",
    "sg:orig_category":"Hoch U Tiefbau",
    "sg:phone":"+41 91 857 42 48",
    "sg:postcode":"9435",
    "sg:province":"St. Gallen",
    "wof:name":"Andrea Rossi Impresa Costruzioni",
    "wof:placetype":"venue"
},
  "geometry": {"coordinates":[8.9903097153,46.1537704468],"type":"Point"}
}