{
  "type": "Feature",
  "properties": {
    "addr:full":"Solothurnstrasse 81 Oensingen Solothurn 4702",
    "addr:housenumber":"81",
    "addr:postcode":"4702",
    "addr:street":"Solothurnstrasse",
    "iso:country":"CH",
    "sg:address":"Solothurnstrasse 81",
    "sg:city":"Oensingen",
    "sg:classifiers":[
        {
            "category":"Banks & Credit Unions",
            "subcategory":"Bank",
            "type":"Services"
        }
    ],
    "sg:phone":"+41 4162784848",
    "sg:postcode":"4702",
    "sg:province":"Solothurn",
    "wof:name":"Solothurner Kantonalbank",
    "wof:placetype":"venue"
},
  "geometry": {"coordinates":[7.715685,47.290291],"type":"Point"}
}