{
  "type": "Feature",
  "properties": {
    "iso:country":"CH",
    "sg:address":"Rotbuchstrasse 43",
    "sg:city":"Z\u00fcrich",
    "sg:orig_category":"Non-Classified Establishments",
    "sg:postcode":"8037",
    "sg:province":"Z\u00fcrich",
    "wof:name":"Mtf E-solutions Center Ag Mebs",
    "wof:placetype":"venue"
},
  "geometry": {"coordinates":[136.9690246582,37.0364608765],"type":"Point"}
}