{
  "type": "Feature",
  "properties": {
    "iso:country":"CH",
    "sg:address":"Terrassenweg 3818 Grindelwald. Postfach 32",
    "sg:city":"Grindelwald",
    "sg:classifiers":[
        {
            "category":"Travel",
            "subcategory":"Hotels & Motels",
            "type":"Entertainment"
        }
    ],
    "sg:postcode":"3818",
    "sg:province":"Bern",
    "sg:tags":[
        "hotels",
        "mit",
        "restaurant"
    ],
    "wof:name":"Hotel-restaurant B\u00e4ren, Wahl M.-l. + E.",
    "wof:placetype":"venue"
},
  "geometry": {"coordinates":[8.1754245758,46.7503967285],"type":"Point"}
}