{
  "type": "Feature",
  "properties": {
    "iso:country":"CH",
    "sg:address":"H\u00fcbelreben 467",
    "sg:city":"Birrwil",
    "sg:orig_category":"Sonstige Hilfs U Nebent\u00e4tigkeiten f\u00fcr die Schiffahrt",
    "sg:postcode":"5708",
    "sg:province":"Aargau",
    "wof:name":"Bootssteggenossenschaft Birrwil",
    "wof:placetype":"venue"
},
  "geometry": {"coordinates":[8.1987791061,47.2997512817],"type":"Point"}
}