{
  "type": "Feature",
  "properties": {
    "iso:country":"CH",
    "sg:address":"Hauptstrasse 37",
    "sg:city":"F\u00fcrstenaubruck",
    "sg:orig_category":"Autospenglereien",
    "sg:phone":"+41 81 651 52 25",
    "sg:postcode":"7413",
    "sg:province":"Graubunden",
    "wof:name":"Raphael Casutt Carrosserie",
    "wof:placetype":"venue"
},
  "geometry": {"coordinates":[9.450235,46.714005],"type":"Point"}
}