{
  "type": "Feature",
  "properties": {
    "iso:country":"CH",
    "sg:address":"Voreimatt 99 4492 Tecknau. Postfach",
    "sg:city":"Tecknau",
    "sg:orig_category":"Instandhaltung U Reparatur von Automobilen",
    "sg:phone":"+41 52 745 21 76",
    "sg:postcode":"4492",
    "sg:province":"Basel-Landschaft",
    "wof:name":"Garage Bussinger",
    "wof:placetype":"venue"
},
  "geometry": {"coordinates":[8.8177452087,47.6094284058],"type":"Point"}
}