{
  "type": "Feature",
  "properties": {
    "iso:country":"CH",
    "sg:address":"Hauptstrasse 96 9052 Niederteufen. Postfach",
    "sg:city":"Niederteufen",
    "sg:orig_category":"Naturheil\u00e4rzte and Heilpraktiker",
    "sg:phone":"+41 71 333 16 10",
    "sg:postcode":"9052",
    "sg:province":"Appenzell Ausserrhoden",
    "wof:name":"Josef Ruckstuhl Magnetopath",
    "wof:placetype":"venue"
},
  "geometry": {"coordinates":[9.3681726456,47.3921051025],"type":"Point"}
}