{
  "type": "Feature",
  "properties": {
    "iso:country":"CH",
    "sg:address":"Ristenb\u00fchl",
    "sg:city":"Matzingen",
    "sg:orig_category":"Detailhandel mit Bekleidung",
    "sg:phone":"+41 52 366 34 91",
    "sg:postcode":"9548",
    "sg:province":"Thurgau",
    "wof:name":"Tyros Gmbh",
    "wof:placetype":"venue"
},
  "geometry": {"coordinates":[8.9113,47.524456],"type":"Point"}
}