{
  "type": "Feature",
  "properties": {
    "iso:country":"CH",
    "sg:address":"Alisbachweg 6",
    "sg:city":"Ober\u00e4geri",
    "sg:classifiers":[
        {
            "category":"Professional",
            "subcategory":"Printing & Photocopies",
            "type":"Services"
        }
    ],
    "sg:phone":"+41 41 750 36 14",
    "sg:postcode":"6315",
    "sg:province":"Zug",
    "sg:tags":[
        "menu",
        "folder"
    ],
    "wof:name":"Glen Ag",
    "wof:placetype":"venue"
},
  "geometry": {"coordinates":[8.6260108948,47.1337928772],"type":"Point"}
}