{
  "type": "Feature",
  "properties": {
    "iso:country":"CH",
    "sg:address":"Via San Gottardo 123",
    "sg:city":"Arbedo",
    "sg:orig_category":"Grosshandel mit Getr\u00e4nken Rebbau",
    "sg:phone":"+41 91 829 10 44",
    "sg:postcode":"6517",
    "sg:province":"Ticino",
    "wof:name":"Carlevaro Vinicola Sa",
    "wof:placetype":"venue"
},
  "geometry": {"coordinates":[9.0421924591,46.2133598328],"type":"Point"}
}