{
  "type": "Feature",
  "properties": {
    "iso:country":"CH",
    "sg:address":"Seevorstadt 19 2500 Biel/bienne. Postfach",
    "sg:city":"Biel/bienne",
    "sg:orig_category":"K\u00fcnstlerische U schriftstellerische T\u00e4tigkeiten U Darbietungen",
    "sg:postcode":"2502",
    "sg:province":"Bern",
    "wof:name":"Boulanger Georges Gesellschaft",
    "wof:placetype":"venue"
},
  "geometry": {"coordinates":[7.2354669571,47.1360359192],"type":"Point"}
}