{
  "type": "Feature",
  "properties": {
    "iso:country":"CH",
    "sg:address":"Bahnhofstrasse 1 9220 Bischofszell. Postfach 341",
    "sg:city":"Bischofszell",
    "sg:orig_category":"Druck ohne Zeitungsdruck Verlagsgewerbe",
    "sg:phone":"+41 71 422 15 20",
    "sg:postcode":"9220",
    "sg:province":"Thurgau",
    "wof:name":"Artis Druck Ag",
    "wof:placetype":"venue"
},
  "geometry": {"coordinates":[9.2412805557,47.4925765991],"type":"Point"}
}