{
  "type": "Feature",
  "properties": {
    "iso:country":"CH",
    "sg:address":"Viale Carlo Cattaneo 11",
    "sg:city":"Lugano",
    "sg:orig_category":"Grosshandel mit Nahrungsmitteln, Getr\u00e4nken U Tabakwaren ohne ausgepr\u00e4gten Schwerpunkt",
    "sg:postcode":"6900",
    "sg:province":"Ticino",
    "wof:name":"Necap Sa",
    "wof:placetype":"venue"
},
  "geometry": {"coordinates":[8.9577865601,46.0058555603],"type":"Point"}
}