{
  "type": "Feature",
  "properties": {
    "iso:country":"CH",
    "sg:address":"Lindenstr. 7",
    "sg:city":"Neuhausen",
    "sg:orig_category":"RESTAURANTS: TEA-ROOMS",
    "sg:postcode":"8212",
    "sg:province":"Schaffhausen",
    "wof:name":"B\u00fcrgin Eduard.",
    "wof:placetype":"venue"
},
  "geometry": {"coordinates":[8.6191339493,47.6796607971],"type":"Point"}
}