{
  "type": "Feature",
  "properties": {
    "iso:country":"CH",
    "sg:address":"Wyde 19",
    "sg:city":"Birr",
    "sg:orig_category":"Technische B\u00fcros",
    "sg:phone":"+41 56 444 83 54",
    "sg:postcode":"5242",
    "sg:province":"Aargau",
    "wof:name":"Peter Vonwiller Technische Dokumentation",
    "wof:placetype":"venue"
},
  "geometry": {"coordinates":[8.2115058899,47.4398345947],"type":"Point"}
}