{
  "type": "Feature",
  "properties": {
    "iso:country":"CH",
    "sg:address":"Via Pessina 20",
    "sg:city":"Lugano",
    "sg:orig_category":"Reparatur von Uhren U Schmuck Sonstiger Grosshandel",
    "sg:phone":"+41 91 923 64 56",
    "sg:postcode":"6900",
    "sg:province":"Ticino",
    "wof:name":"Taleda Sa",
    "wof:placetype":"venue"
},
  "geometry": {"coordinates":[8.9508810043,46.0047149658],"type":"Point"}
}