{
  "type": "Feature",
  "properties": {
    "addr:full":"Piazza Verscio Ticino 6653",
    "addr:postcode":"6653",
    "addr:street":"Piazza Verscio Ticino",
    "iso:country":"CH",
    "sg:address":"Piazza",
    "sg:city":"Verscio",
    "sg:classifiers":[
        {
            "category":"Bars & Pubs",
            "type":"Food & Drink"
        }
    ],
    "sg:phone":"+41 81 756 73 73",
    "sg:postcode":"6653",
    "sg:province":"Ticino",
    "sg:tags":[
        "restaurant"
    ],
    "wof:name":"Pizzeria & Bar Rondo",
    "wof:placetype":"venue"
},
  "geometry": {"coordinates":[9.476657,47.159798],"type":"Point"}
}