{
  "type": "Feature",
  "properties": {
    "iso:country":"CH",
    "sg:address":"S\u00e4lischl\u00f6ssli",
    "sg:city":"Olten",
    "sg:classifiers":[
        {
            "category":"Restaurant",
            "type":"Food & Drink"
        }
    ],
    "sg:phone":"+41 62 295 71 71",
    "sg:postcode":"4600",
    "sg:province":"Solothurn",
    "wof:name":"Restaurant Ch\u00e2teau Mosimann Sa",
    "wof:placetype":"venue"
},
  "geometry": {"coordinates":[7.9040288925,47.3521194458],"type":"Point"}
}