{
  "type": "Feature",
  "properties": {
    "iso:country":"CH",
    "sg:address":"Rue Du Grand-ch\u00eane 8",
    "sg:city":"Lausanne",
    "sg:orig_category":"Arztpraxen",
    "sg:phone":"+41 21 323 90 81",
    "sg:postcode":"1003",
    "sg:province":"Vaud",
    "wof:name":"Dr M\u00e9d. Andr\u00e9 Veya M\u00e9decin Sp\u00e9cialiste Fmh",
    "wof:placetype":"venue"
},
  "geometry": {"coordinates":[6.630392,46.519855],"type":"Point"}
}