{
  "type": "Feature",
  "properties": {
    "iso:country":"CH",
    "sg:address":"Kanderstegstrasse 29 3714 Frutigen. Postfach 114",
    "sg:city":"Frutigen",
    "sg:orig_category":"Detailhandel mit Beleuchtungs U Haushaltsgegenst\u00e4nden",
    "sg:phone":"+41 33 671 14 15",
    "sg:postcode":"3714",
    "sg:province":"Bern",
    "wof:name":"Adolf Wandfluh Eisenwaren Haushaltartikel",
    "wof:placetype":"venue"
},
  "geometry": {"coordinates":[7.64797,46.585876],"type":"Point"}
}