{
  "type": "Feature",
  "properties": {
    "iso:country":"CH",
    "sg:address":"Bahnhofstrasse 85",
    "sg:city":"Steffisburg",
    "sg:orig_category":"Detailhandel mit Waren verschiedener Art, Hauptrichtung Nahrungsmittel Detailhandel mit Zeitungen U ",
    "sg:phone":"+41 33 336 25 02",
    "sg:postcode":"3613",
    "sg:province":"Bern",
    "wof:name":"Alfred Schopfer Lebensmittel & Kiosk",
    "wof:placetype":"venue"
},
  "geometry": {"coordinates":[7.6271619797,46.7287979126],"type":"Point"}
}