{
  "type": "Feature",
  "properties": {
    "iso:country":"CH",
    "sg:address":"L\u00e4ndtestrasse 40 2503 Biel/bienne. Postfach",
    "sg:city":"Biel/bienne",
    "sg:orig_category":"Sportvereine",
    "sg:postcode":"2501",
    "sg:province":"Bern",
    "wof:name":"Panathlon-club Biel/bienne",
    "wof:placetype":"venue"
},
  "geometry": {"coordinates":[7.2391219139,47.131072998],"type":"Point"}
}