{
  "type": "Feature",
  "properties": {
    "iso:country":"CH",
    "sg:address":"7112",
    "sg:city":"Duvin",
    "sg:orig_category":"Primarschulen",
    "sg:phone":"+41 81 931 10 04",
    "sg:postcode":"7112",
    "sg:province":"Graubunden",
    "wof:name":"Primarschule",
    "wof:placetype":"venue"
},
  "geometry": {"coordinates":[9.2431201935,46.6927108765],"type":"Point"}
}