{
  "type": "Feature",
  "properties": {
    "iso:country":"CH",
    "sg:address":"Bahnhofstrasse 42",
    "sg:city":"Eschenz",
    "sg:orig_category":"Sonstige mit der Informatik verbundene T\u00e4tigkeiten",
    "sg:postcode":"8264",
    "sg:province":"Thurgau",
    "wof:name":"G\u00fcttinger Max.",
    "wof:placetype":"venue"
},
  "geometry": {"coordinates":[8.877702713,47.6429481506],"type":"Point"}
}