{
  "type": "Feature",
  "properties": {
    "iso:country":"CH",
    "sg:address":"Allschwilerstrasse 27",
    "sg:city":"Basel",
    "sg:orig_category":"Detailhandel mit Geschenkartikeln U Souvenirs Fachdetailhandel in Verkaufsr\u00e4umen",
    "sg:phone":"+41 61 301 18 60",
    "sg:postcode":"4055",
    "sg:province":"Basel-Stadt",
    "wof:name":"Atelier S, Winiger M\u00fcnster Sandra",
    "wof:placetype":"venue"
},
  "geometry": {"coordinates":[7.573633194,47.5559272766],"type":"Point"}
}