{
  "type": "Feature",
  "properties": {
    "iso:country":"CH",
    "sg:address":"Route Du Ch\u00e2teau-du-crest 4",
    "sg:city":"Meinier",
    "sg:orig_category":"Gartenbau Landschaftsplanungsb\u00fcros U Gartenarchitekturb\u00fcros",
    "sg:phone":"+41 22 759 15 39",
    "sg:postcode":"1252",
    "sg:province":"Gen\u00e8ve",
    "wof:name":"Jean Ruepp",
    "wof:placetype":"venue"
},
  "geometry": {"coordinates":[6.2468152046,46.2393035889],"type":"Point"}
}