{
  "type": "Feature",
  "properties": {
    "iso:country":"CH",
    "sg:address":"Rue De La Poste 3",
    "sg:city":"Boudry",
    "sg:orig_category":"RESTAURANTS: TEA-ROOMS",
    "sg:postcode":"2017",
    "sg:province":"Neuch\u00e2tel",
    "wof:name":"Ignoto R.",
    "wof:placetype":"venue"
},
  "geometry": {"coordinates":[6.8380651474,46.9499816895],"type":"Point"}
}