{
  "type": "Feature",
  "properties": {
    "iso:country":"CH",
    "sg:address":"Via Vallone 29",
    "sg:city":"Bellinzona",
    "sg:orig_category":"Kaufm\u00e4nnische Berufsschulen",
    "sg:phone":"+41 91 821 60 30",
    "sg:postcode":"6500",
    "sg:province":"Ticino",
    "wof:name":"Scuola Professionale Commerciale Della Ssic",
    "wof:placetype":"venue"
},
  "geometry": {"coordinates":[9.0266046524,46.2052650452],"type":"Point"}
}