{
  "type": "Feature",
  "properties": {
    "iso:country":"CH",
    "sg:address":"Kieswerkstrasse",
    "sg:city":"Untervaz",
    "sg:orig_category":"R\u00fcckgewinnung U Vorbereitung f\u00fcr die Wiederverwertung Recycling von nichtmetallischen Altmaterialien",
    "sg:phone":"+41 17610838",
    "sg:postcode":"7204",
    "sg:province":"Graubunden",
    "wof:name":"Schaffner + Huldi Ag",
    "wof:placetype":"venue"
},
  "geometry": {"coordinates":[8.4446649551,47.2715187073],"type":"Point"}
}