{
  "type": "Feature",
  "properties": {
    "iso:country":"CH",
    "sg:address":"Via G. Camponovo 4",
    "sg:city":"Chiasso",
    "sg:orig_category":"Institutionen f\u00fcr Behinderte Tagesheime f\u00fcr Behinderte, gesch\u00fctzte Werkst\u00e4tten",
    "sg:phone":"+41 91 682 70 18",
    "sg:postcode":"6830",
    "sg:province":"Ticino",
    "wof:name":"Fondazione Diamante Laboratorio Le Fornaci",
    "wof:placetype":"venue"
},
  "geometry": {"coordinates":[9.0322170258,45.8368530273],"type":"Point"}
}