{
  "type": "Feature",
  "properties": {
    "iso:country":"CH",
    "sg:address":"Hauptstrasse",
    "sg:city":"Quarten",
    "sg:orig_category":"Tankstellen",
    "sg:phone":"+41 81 723 52 52",
    "sg:postcode":"8883",
    "sg:province":"St. Gallen",
    "wof:name":"Hans Walser Ag, Unterterzen",
    "wof:placetype":"venue"
},
  "geometry": {"coordinates":[9.2709827423,47.113910675],"type":"Point"}
}