{
  "type": "Feature",
  "properties": {
    "iso:country":"CH",
    "sg:address":"Webereistrasse 56 8134 Adliswil. Postfach",
    "sg:city":"Adliswil",
    "sg:orig_category":"Zimmerei, Dachdeckerei, Bauspenglerei U Abdichtung",
    "sg:phone":"+41 17108818",
    "sg:postcode":"8134",
    "sg:province":"Z\u00fcrich",
    "wof:name":"Studer & Thomann Spenglerei Ag",
    "wof:placetype":"venue"
},
  "geometry": {"coordinates":[8.5247211456,47.3057785034],"type":"Point"}
}