{
  "type": "Feature",
  "properties": {
    "addr:full":"Thiersteinerrain 9 4053 Basel. Postfach Basel Basel-Stadt 4008",
    "addr:housenumber":"9",
    "addr:postcode":"4053;4008",
    "addr:street":"Thiersteinerrain;Postfach",
    "iso:country":"CH",
    "sg:address":"Thiersteinerrain 9 4053 Basel. Postfach",
    "sg:city":"Basel",
    "sg:orig_category":"Datenverarbeitungsdienste",
    "sg:phone":"+41 61 332 11 33",
    "sg:postcode":"4008",
    "sg:province":"Basel-Stadt",
    "wof:name":"Eibit Ag Edv; Dienstleistungen Wie Unternehmensberatung, Betriebsorganisation, Planung V. Gesamtkonzepten, Ausbildung, Personalvermitlung",
    "wof:placetype":"venue"
},
  "geometry": {"coordinates":[7.595893,47.538528],"type":"Point"}
}