{
  "type": "Feature",
  "properties": {
    "iso:country":"CH",
    "sg:address":"Seestrasse 102",
    "sg:city":"Steckborn",
    "sg:classifiers":[
        {
            "category":"Travel",
            "subcategory":"Hotels & Motels",
            "type":"Entertainment"
        }
    ],
    "sg:phone":"+41 52 761 11 14",
    "sg:postcode":"8266",
    "sg:province":"Thurgau",
    "sg:tags":[
        "hotels",
        "mit",
        "restaurant"
    ],
    "wof:name":"Hotel L\u00f6wen",
    "wof:placetype":"venue"
},
  "geometry": {"coordinates":[8.9821624756,47.6680641174],"type":"Point"}
}