{
  "type": "Feature",
  "properties": {
    "iso:country":"CH",
    "sg:address":"Meisenweg 1",
    "sg:city":"Luzern",
    "sg:orig_category":"Sonstige mit Sport verbundene T\u00e4tigkeiten",
    "sg:postcode":"6006",
    "sg:province":"Luzern",
    "wof:name":"Stiftung Landhockey Luzern",
    "wof:placetype":"venue"
},
  "geometry": {"coordinates":[8.3367395401,47.0547332764],"type":"Point"}
}