{
  "type": "Feature",
  "properties": {
    "iso:country":"CH",
    "sg:address":"Route De L'aurore 1",
    "sg:city":"Cernier",
    "sg:orig_category":"Landwirtschafts\u00e4mter",
    "sg:phone":"+41 32 854 05 70",
    "sg:postcode":"2053",
    "sg:province":"Neuch\u00e2tel",
    "wof:name":"Service De L'\u00e9conomie Agricole",
    "wof:placetype":"venue"
},
  "geometry": {"coordinates":[6.9081759453,47.0589675903],"type":"Point"}
}