{
  "type": "Feature",
  "properties": {
    "iso:country":"CH",
    "sg:address":"Oberdorfstrasse 8",
    "sg:city":"R\u00fcmlang",
    "sg:orig_category":"Unclassifiable Establishments",
    "sg:postcode":"8153",
    "sg:province":"Z\u00fcrich",
    "wof:name":"Fishingstar Starcevic & Antic",
    "wof:placetype":"venue"
},
  "geometry": {"coordinates":[8.5301351547,47.451839447],"type":"Point"}
}