{
  "type": "Feature",
  "properties": {
    "iso:country":"CH",
    "sg:address":"2855",
    "sg:city":"Glovelier",
    "sg:orig_category":"Sportvereine Sch\u00fctzen",
    "sg:phone":"+41 32 426 67 94",
    "sg:postcode":"2855",
    "sg:province":"Jura",
    "wof:name":"St\u00e9 De Tir De Campagne",
    "wof:placetype":"venue"
},
  "geometry": {"coordinates":[7.1992797852,47.3326377869],"type":"Point"}
}