{
  "type": "Feature",
  "properties": {
    "iso:country":"CH",
    "sg:address":"Terrassenweg 40",
    "sg:city":"M\u00fcnsingen",
    "sg:orig_category":"Architektur U Ingenieurb\u00fcros",
    "sg:phone":"+41 33 828 13 63",
    "sg:postcode":"3110",
    "sg:province":"Bern",
    "wof:name":"Toneatti Engineering Ag",
    "wof:placetype":"venue"
},
  "geometry": {"coordinates":[7.857148,46.670734],"type":"Point"}
}