{
  "type": "Feature",
  "properties": {
    "iso:country":"CH",
    "sg:address":"Dorfstrasse 176",
    "sg:city":"Kirchleerau",
    "sg:orig_category":"Gemeindeverwaltungen",
    "sg:phone":"+41 62 726 28 60",
    "sg:postcode":"5054",
    "sg:province":"Aargau",
    "wof:name":"Gemeindeverwaltung Kirchleerau",
    "wof:placetype":"venue"
},
  "geometry": {"coordinates":[8.0652418137,47.276058197],"type":"Point"}
}