{
  "type": "Feature",
  "properties": {
    "iso:country":"CH",
    "sg:address":"Schulstrasse 18",
    "sg:city":"Niederg\u00f6sgen",
    "sg:orig_category":"Gewinnung von Kies U Sand Herstellung von Betonerzeugnissen f\u00fcr den Bau",
    "sg:phone":"+41 62 844 10 15",
    "sg:postcode":"5013",
    "sg:province":"Solothurn",
    "wof:name":"Belser Ag, Niederg\u00f6sgen, Zweigniederlasung Erlinsbach Ag",
    "wof:placetype":"venue"
},
  "geometry": {"coordinates":[8.0190753937,47.3967552185],"type":"Point"}
}