{
  "type": "Feature",
  "properties": {
    "iso:country":"CH",
    "sg:address":"Waldhofstrasse 2",
    "sg:city":"Dottikon",
    "sg:orig_category":"Maler U Glasergewerbe Malerei",
    "sg:phone":"+41 56 624 10 11",
    "sg:postcode":"5605",
    "sg:province":"Aargau",
    "wof:name":"F. Carlino & Sohn Malergesch\u00e4ft",
    "wof:placetype":"venue"
},
  "geometry": {"coordinates":[8.2484483719,47.3810424805],"type":"Point"}
}