{
  "type": "Feature",
  "properties": {
    "iso:country":"CH",
    "sg:address":"Champs-montants 16b",
    "sg:city":"Marin-centre",
    "sg:orig_category":"Herstellung von Mess U Kontrollinstrumenten U vorrichtungen Herstellung von Uhren",
    "sg:phone":"+41 32 723 07 00",
    "sg:postcode":"2074",
    "sg:province":"Neuch\u00e2tel",
    "wof:name":"Bertolucci Distribution Sa",
    "wof:placetype":"venue"
},
  "geometry": {"coordinates":[6.9998049736,47.0116462708],"type":"Point"}
}