{
  "type": "Feature",
  "properties": {
    "iso:country":"CH",
    "sg:address":"4710 Balsthal. Postfach 205",
    "sg:city":"Balsthal",
    "sg:orig_category":"Sportvereine Ballsport Fussball",
    "sg:phone":"+41 41 921 58 26",
    "sg:postcode":"4710",
    "sg:province":"Solothurn",
    "wof:name":"Fc Knutwil",
    "wof:placetype":"venue"
},
  "geometry": {"coordinates":[8.0722904205,47.2124214172],"type":"Point"}
}