{
  "type": "Feature",
  "properties": {
    "iso:country":"CH",
    "sg:address":"B\u00e4raustrasse 27",
    "sg:city":"B\u00e4rau",
    "sg:orig_category":"Herstellung von sonstigen Metallwaren",
    "sg:phone":"+41 34 402 54 89",
    "sg:postcode":"3552",
    "sg:province":"Bern",
    "wof:name":"Kathrin Megert Gravier-service",
    "wof:placetype":"venue"
},
  "geometry": {"coordinates":[7.8094091415,46.9339485168],"type":"Point"}
}