{
  "type": "Feature",
  "properties": {
    "iso:country":"CH",
    "sg:address":"Werkstr. 5",
    "sg:city":"Malters",
    "sg:classifiers":[
        {
            "category":"Manufacturing",
            "subcategory":"Metals",
            "type":"Manufacturing & Wholesale Goods"
        }
    ],
    "sg:phone":"+41 41 499 92 00",
    "sg:postcode":"6102",
    "sg:province":"Luzern",
    "sg:tags":[
        "metallurgy",
        "metalworking",
        "processing"
    ],
    "wof:name":"Blaser Ag Malters",
    "wof:placetype":"venue"
},
  "geometry": {"coordinates":[8.177903,47.041786],"type":"Point"}
}