{
  "type": "Feature",
  "properties": {
    "iso:country":"CH",
    "sg:address":"Schlossstrasse 1 6005 Luzern. Postfach 2602",
    "sg:city":"Luzern",
    "sg:orig_category":"Datenverarbeitungsdienste Softwareentwicklung U beratung",
    "sg:phone":"+41 41 319 92 95",
    "sg:postcode":"6002",
    "sg:province":"Luzern",
    "wof:name":"Dacor Ag",
    "wof:placetype":"venue"
},
  "geometry": {"coordinates":[8.302566,47.042465],"type":"Point"}
}