{
  "type": "Feature",
  "properties": {
    "iso:country":"CH",
    "sg:address":"Seefeldstrasse 152",
    "sg:city":"Z\u00fcrich",
    "sg:orig_category":"Architektur U Ingenieurb\u00fcros Architekturb\u00fcros",
    "sg:phone":"+41 13814848",
    "sg:postcode":"8008",
    "sg:province":"Z\u00fcrich",
    "wof:name":"Albers S\u00e0rl",
    "wof:placetype":"venue"
},
  "geometry": {"coordinates":[8.555116,47.356873],"type":"Point"}
}