{
  "type": "Feature",
  "properties": {
    "addr:full":"Hofstrasse 21 H\u00f6ri Z\u00fcrich 8181",
    "addr:housenumber":"21",
    "addr:postcode":"8181",
    "addr:street":"Hofstrasse;Zuerich",
    "iso:country":"CH",
    "sg:address":"Hofstrasse 21",
    "sg:city":"H\u00f6ri",
    "sg:orig_category":"Bauschreinerei Innenausbau",
    "sg:phone":"+41 18604983",
    "sg:postcode":"8181",
    "sg:province":"Z\u00fcrich",
    "wof:name":"Kipfer Innenausbau Ag",
    "wof:placetype":"venue"
},
  "geometry": {"coordinates":[8.518913,47.512386],"type":"Point"}
}