{
  "type": "Feature",
  "properties": {
    "iso:country":"CH",
    "sg:address":"6370",
    "sg:city":"Stans",
    "sg:orig_category":"RESTAURANTS: TEA-ROOMS",
    "sg:postcode":"6370",
    "sg:province":"Nidwalden",
    "wof:name":"Amstutz, Irmgard.",
    "wof:placetype":"venue"
},
  "geometry": {"coordinates":[8.4357471466,47.3549613953],"type":"Point"}
}