{
  "type": "Feature",
  "properties": {
    "iso:country":"CH",
    "sg:address":"Homburgerstr.4",
    "sg:city":"Muttenz",
    "sg:orig_category":"Forstwirtschaft",
    "sg:phone":"+41 61 461 09 11",
    "sg:postcode":"4132",
    "sg:province":"Basel-Landschaft",
    "wof:name":"Stocker Brennholz",
    "wof:placetype":"venue"
},
  "geometry": {"coordinates":[7.6511301994,47.5300140381],"type":"Point"}
}