{
  "type": "Feature",
  "properties": {
    "iso:country":"CH",
    "sg:address":"Grand P\u00e2quier",
    "sg:city":"Chavornay",
    "sg:orig_category":"Non-Classified Establishments",
    "sg:postcode":"1373",
    "sg:province":"Vaud",
    "wof:name":"Ichthys S\u00e0rl",
    "wof:placetype":"venue"
},
  "geometry": {"coordinates":[6.5474948883,46.7036361694],"type":"Point"}
}