{
  "type": "Feature",
  "properties": {
    "iso:country":"CH",
    "sg:address":"St. Margrethenstrasse 17a 7000 Chur. Postfach",
    "sg:city":"Chur",
    "sg:orig_category":"Herstellung von K\u00fcchenm\u00f6beln Herstellung von Metallerzeugnissen ohne Maschinenbau",
    "sg:phone":"+41 81 252 90 09",
    "sg:postcode":"7007",
    "sg:province":"Graubunden",
    "wof:name":"Alig Grossk\u00fcchen",
    "wof:placetype":"venue"
},
  "geometry": {"coordinates":[9.5274295807,46.8472633362],"type":"Point"}
}