{
  "type": "Feature",
  "properties": {
    "iso:country":"CH",
    "sg:address":"Seestrasse 110",
    "sg:city":"Richterswil",
    "sg:orig_category":"Mit dem Versicherungsgewerbe verbundene T\u00e4tigkeiten",
    "sg:postcode":"8805",
    "sg:province":"Z\u00fcrich",
    "wof:name":"Office-business Versicherungen + Finanzen Ag",
    "wof:placetype":"venue"
},
  "geometry": {"coordinates":[8.6953849792,47.218120575],"type":"Point"}
}