{
  "type": "Feature",
  "properties": {
    "iso:country":"CH",
    "sg:address":"Neugutstrasse 3",
    "sg:city":"Obfelden",
    "sg:orig_category":"Sportvereine Billard",
    "sg:phone":"+41 17600108",
    "sg:postcode":"8912",
    "sg:province":"Z\u00fcrich",
    "wof:name":"Billard-club H\u00e4d\u00e4-h\u00e4d\u00e4",
    "wof:placetype":"venue"
},
  "geometry": {"coordinates":[8.4303350449,47.2635536194],"type":"Point"}
}