{
  "type": "Feature",
  "properties": {
    "iso:country":"CH",
    "sg:address":"1666",
    "sg:city":"Grandvillard",
    "sg:orig_category":"Non-Classified Establishments",
    "sg:phone":"+41 26 928 11 35",
    "sg:postcode":"1666",
    "sg:province":"Fribourg",
    "wof:name":"Sainte-anne Energie Sa",
    "wof:placetype":"venue"
},
  "geometry": {"coordinates":[7.0855789185,46.5394859314],"type":"Point"}
}