{
  "type": "Feature",
  "properties": {
    "iso:country":"CH",
    "sg:address":"Rue De La Vernie 9 1023 Crissier. Postfach",
    "sg:city":"Crissier",
    "sg:orig_category":"Instandhaltung U Reparatur von Automobilen",
    "sg:phone":"+41 79 235 18 17",
    "sg:postcode":"1023",
    "sg:province":"Vaud",
    "wof:name":"Garage Du Simplon Martigny Sa",
    "wof:placetype":"venue"
},
  "geometry": {"coordinates":[7.0862421989,46.106590271],"type":"Point"}
}