{
  "type": "Feature",
  "properties": {
    "iso:country":"CH",
    "sg:address":"Sch\u00f6nbrunnen",
    "sg:city":"M\u00fcnchenbuchsee",
    "sg:classifiers":[
        {
            "category":"Travel",
            "subcategory":"Hotels & Motels",
            "type":"Entertainment"
        }
    ],
    "sg:phone":"+41 31 869 01 99",
    "sg:postcode":"3053",
    "sg:province":"Bern",
    "sg:tags":[
        "mit",
        "restaurant"
    ],
    "wof:name":"Motel Bern-biel",
    "wof:placetype":"venue"
},
  "geometry": {"coordinates":[7.4505391121,47.0214271545],"type":"Point"}
}