{
  "type": "Feature",
  "properties": {
    "iso:country":"CH",
    "sg:address":"Avenue De Miremont 1 1200 Genf. Postfach",
    "sg:city":"Gen\u00e8ve",
    "sg:orig_category":"Fernmeldedienste",
    "sg:postcode":"1201",
    "sg:province":"Gen\u00e8ve",
    "wof:name":"Liebermann Charles",
    "wof:placetype":"venue"
},
  "geometry": {"coordinates":[6.153439045,46.1917266846],"type":"Point"}
}