{
  "type": "Feature",
  "properties": {
    "iso:country":"CH",
    "sg:address":"Chalet Central Gstaad 3792 Saanen. Postfach",
    "sg:city":"Gstaad",
    "sg:orig_category":"Detailhandel mit Bekleidung",
    "sg:postcode":"3780",
    "sg:province":"Bern",
    "wof:name":"Herrmann Maya",
    "wof:placetype":"venue"
},
  "geometry": {"coordinates":[7.259921,46.489792],"type":"Point"}
}