{
  "type": "Feature",
  "properties": {
    "iso:country":"CH",
    "sg:address":"Delfterstrasse 30",
    "sg:city":"Aarau",
    "sg:orig_category":"Detailhandel mit M\u00f6beln Herstellung von Reiseartikeln, Leder U Sattlerwaren",
    "sg:phone":"+41 62 822 08 52",
    "sg:postcode":"5004",
    "sg:province":"Aargau",
    "wof:name":"Mato Crnkovic Polsterm\u00f6bel-service",
    "wof:placetype":"venue"
},
  "geometry": {"coordinates":[8.0610237122,47.4009552002],"type":"Point"}
}