{
  "type": "Feature",
  "properties": {
    "iso:country":"CH",
    "sg:address":"Rte De La Croix-blanche 44",
    "sg:city":"Epalinges",
    "sg:orig_category":"Nahrungsmittel-Industrie: Rohstoffe",
    "sg:phone":"+41 21 784 19 83",
    "sg:postcode":"1066",
    "sg:province":"Vaud",
    "wof:name":"Cantinho Do Ceu, De Oliveira",
    "wof:placetype":"venue"
},
  "geometry": {"coordinates":[6.6739830971,46.548248291],"type":"Point"}
}