{
  "type": "Feature",
  "properties": {
    "iso:country":"CH",
    "sg:address":"Chemin Des Vendanges 8",
    "sg:city":"Sierre",
    "sg:classifiers":[
        {
            "category":"Insurance",
            "subcategory":"Insurance Agent",
            "type":"Services"
        }
    ],
    "sg:phone":"+41 27 455 05 01",
    "sg:postcode":"3960",
    "sg:province":"Valais",
    "sg:tags":[
        "versicherungsagenturen",
        "-broker"
    ],
    "wof:name":"Lucien Posse Assurances",
    "wof:placetype":"venue"
},
  "geometry": {"coordinates":[7.520075798,46.2888031006],"type":"Point"}
}