{
  "type": "Feature",
  "properties": {
    "iso:country":"CH",
    "sg:address":"1986",
    "sg:city":"Arolla",
    "sg:orig_category":"Detailhandel mit Waren verschiedener Art, Hauptrichtung Nahrungsmittel",
    "sg:phone":"+41 27 283 11 65",
    "sg:postcode":"1986",
    "sg:province":"Valais",
    "wof:name":"Denis & Fran\u00e7oise Anz\u00e9vui Alimentation La Source",
    "wof:placetype":"venue"
},
  "geometry": {"coordinates":[7.4876799583,46.0387115479],"type":"Point"}
}