{
  "type": "Feature",
  "properties": {
    "iso:country":"CH",
    "sg:address":"5644",
    "sg:city":"Auw",
    "sg:orig_category":"Politische Parteien FDP",
    "sg:postcode":"5644",
    "sg:province":"Aargau",
    "wof:name":"Fdp Ortspartei R\u00fcti",
    "wof:placetype":"venue"
},
  "geometry": {"coordinates":[8.8560152054,47.2494735718],"type":"Point"}
}