{
  "type": "Feature",
  "properties": {
    "iso:country":"CH",
    "sg:address":"L\u00e4nggasse 26",
    "sg:city":"Thun",
    "sg:orig_category":"Kinderkrippen U horte",
    "sg:phone":"+41 33 222 71 45",
    "sg:postcode":"3600",
    "sg:province":"Bern",
    "wof:name":"Kinderhort Tagesheim Thun",
    "wof:placetype":"venue"
},
  "geometry": {"coordinates":[7.6238350868,46.7530670166],"type":"Point"}
}