{
  "type": "Feature",
  "properties": {
    "iso:country":"CH",
    "sg:address":"Rigistrasse 10",
    "sg:city":"Lostorf",
    "sg:orig_category":"Grosshandel mit B\u00fcromaschinen Grosshandel mit Datenverarbeitungsger\u00e4ten",
    "sg:phone":"+41 62 298 30 60",
    "sg:postcode":"4654",
    "sg:province":"Solothurn",
    "wof:name":"Ato Eng",
    "wof:placetype":"venue"
},
  "geometry": {"coordinates":[7.9519500732,47.3835716248],"type":"Point"}
}