{
  "type": "Feature",
  "properties": {
    "iso:country":"CH",
    "sg:address":"Grand-rue 16",
    "sg:city":"Payerne",
    "sg:orig_category":"Sonstiger Fachdetailhandel mit Nahrungsmitteln, Getr\u00e4nken U Tabak in Verkaufsr\u00e4umen",
    "sg:phone":"+41 26 660 26 82",
    "sg:postcode":"1530",
    "sg:province":"Vaud",
    "wof:name":"Righetti Philippe",
    "wof:placetype":"venue"
},
  "geometry": {"coordinates":[6.9390130043,46.8217010498],"type":"Point"}
}