{
  "type": "Feature",
  "properties": {
    "iso:country":"CH",
    "sg:address":"Hardstrasse 51 5432 Neuenhof. Postfach",
    "sg:city":"Neuenhof",
    "sg:orig_category":"Fussboden, Fliesen U Plattenlegerei, Tapeziererei",
    "sg:postcode":"5432",
    "sg:province":"Aargau",
    "wof:name":"Mehmeti B. Naturstein Und Plattenbel\u00e4ge Natursteine, Wand Und Bodenbel\u00e4ge",
    "wof:placetype":"venue"
},
  "geometry": {"coordinates":[9.4086799622,47.4363822937],"type":"Point"}
}