{
  "type": "Feature",
  "properties": {
    "iso:country":"CH",
    "sg:address":"Alpenstrasse 83",
    "sg:city":"Grenchen",
    "sg:orig_category":"Tanzschulen, Tanzlehrer",
    "sg:phone":"+41 32 652 17 84",
    "sg:postcode":"2540",
    "sg:province":"Solothurn",
    "wof:name":"Ursula Fankhauser Gymnastikstudio Schmiedehof",
    "wof:placetype":"venue"
},
  "geometry": {"coordinates":[7.40122509,47.2011032104],"type":"Point"}
}