{
  "type": "Feature",
  "properties": {
    "iso:country":"CH",
    "sg:address":"Im Gsteig 37 8713 Uerikon. Postfach",
    "sg:city":"Uerikon",
    "sg:orig_category":"Grosshandel mit pharmazeutischen Erzeugnissen, medizinischen U orthop\u00e4dischen Artikeln",
    "sg:phone":"+41 17962198",
    "sg:postcode":"8713",
    "sg:province":"Z\u00fcrich",
    "wof:name":"Care Medical Gmbh",
    "wof:placetype":"venue"
},
  "geometry": {"coordinates":[8.7620182037,47.2384338379],"type":"Point"}
}