{
  "type": "Feature",
  "properties": {
    "iso:country":"CH",
    "sg:address":"6558",
    "sg:city":"Lostallo",
    "sg:classifiers":[
        {
            "category":"Building & Trades",
            "subcategory":"Construction",
            "type":"Services"
        }
    ],
    "sg:phone":"+41 91 830 13 37",
    "sg:postcode":"6558",
    "sg:province":"Graubunden",
    "sg:tags":[
        "industrial",
        "timber"
    ],
    "wof:name":"Segheria Tam\u00f2",
    "wof:placetype":"venue"
},
  "geometry": {"coordinates":[9.1959848404,46.3131256104],"type":"Point"}
}