{
  "type": "Feature",
  "properties": {
    "iso:country":"CH",
    "sg:address":"Liestalerstrasse 4",
    "sg:city":"Seltisberg",
    "sg:orig_category":"Landesverteidigung, Sozialversicherung \u00d6ffentliche Verwaltung",
    "sg:phone":"+41 61 911 99 11",
    "sg:postcode":"4411",
    "sg:province":"Basel-Landschaft",
    "wof:name":"Zivilschutzstelle Seltisberg",
    "wof:placetype":"venue"
},
  "geometry": {"coordinates":[7.721162796,47.4629898071],"type":"Point"}
}