{
  "type": "Feature",
  "properties": {
    "iso:country":"CH",
    "sg:address":"Trogenerstrasse 34 9450 Altst\u00e4tten Sg. Postfach",
    "sg:city":"L\u00fcchingen",
    "sg:orig_category":"Detailhandel mit Radio U Fernsehger\u00e4ten Sonstiger Fachdetailhandel in Verkaufsr\u00e4umen",
    "sg:phone":"+41 71 755 60 10",
    "sg:postcode":"9450",
    "sg:province":"St. Gallen",
    "wof:name":"Video & Schmuckothek Evelyn & Gert Bruderer",
    "wof:placetype":"venue"
},
  "geometry": {"coordinates":[9.5390777588,47.378868103],"type":"Point"}
}