{
  "type": "Feature",
  "properties": {
    "iso:country":"CH",
    "sg:address":"Terrassenweg 17 6315 Ober\u00e4geri. Postfach",
    "sg:city":"Ober\u00e4geri",
    "sg:orig_category":"Kauf U Verkauf von Immobilien auf eigene Rechnung",
    "sg:postcode":"6315",
    "sg:province":"Zug",
    "wof:name":"Nataka Ag Vermittlung Und Beratung Auf Dem Gebiet Von Liegenschaften Usw",
    "wof:placetype":"venue"
},
  "geometry": {"coordinates":[8.6243286133,47.1349525452],"type":"Point"}
}