{
  "type": "Feature",
  "properties": {
    "iso:country":"CH",
    "sg:address":"Gotthardstrasse 100",
    "sg:city":"Erstfeld",
    "sg:orig_category":"Drogerien Fachdetailhandel mit pharmazeutischen Produkten",
    "sg:phone":"+41 41 880 22 44",
    "sg:postcode":"6472",
    "sg:province":"Uri",
    "wof:name":"Bahnhofapotheke H.p. Birchler",
    "wof:placetype":"venue"
},
  "geometry": {"coordinates":[8.6504936218,46.8209228516],"type":"Point"}
}