{
  "type": "Feature",
  "properties": {
    "iso:country":"CH",
    "sg:address":"Avenue Menthon 19",
    "sg:city":"Lausanne",
    "sg:orig_category":"Reiseb\u00fcros U Reiseveranstalter",
    "sg:phone":"+41 21 311 20 22",
    "sg:postcode":"1005",
    "sg:province":"Vaud",
    "wof:name":"Panorama Voyages, Aguiar T. & F.",
    "wof:placetype":"venue"
},
  "geometry": {"coordinates":[6.6366319656,46.5237808228],"type":"Point"}
}