{
  "type": "Feature",
  "properties": {
    "iso:country":"CH",
    "sg:address":"Rotzbergstrasse 19",
    "sg:city":"Stansstad",
    "sg:orig_category":"Markt U Meinungsforschung",
    "sg:phone":"+41 41 610 56 47",
    "sg:postcode":"6362",
    "sg:province":"Nidwalden",
    "wof:name":"Harve Handels Und Publikations Gmbh",
    "wof:placetype":"venue"
},
  "geometry": {"coordinates":[8.3389501572,46.9702796936],"type":"Point"}
}