{
  "type": "Feature",
  "properties": {
    "addr:full":"Sierenzerstrasse 9 Basel Basel-Stadt 4055",
    "addr:housenumber":"9",
    "addr:postcode":"4055",
    "addr:street":"Sierenzerstrasse",
    "iso:country":"CH",
    "sg:address":"Sierenzerstrasse 9",
    "sg:city":"Basel",
    "sg:orig_category":"Allgemeiner Hoch U Tiefbau",
    "sg:phone":"+41 61 382 80 86",
    "sg:postcode":"4055",
    "sg:province":"Basel-Stadt",
    "wof:name":"Pus Consult Gmbh",
    "wof:placetype":"venue"
},
  "geometry": {"coordinates":[7.570324,47.56049],"type":"Point"}
}