{
  "type": "Feature",
  "properties": {
    "iso:country":"CH",
    "sg:address":"1376",
    "sg:city":"Goumoens-la-ville",
    "sg:orig_category":"Landesverteidigung, Sozialversicherung \u00d6ffentliche Verwaltung",
    "sg:phone":"+41 21 881 38 50",
    "sg:postcode":"1376",
    "sg:province":"Vaud",
    "wof:name":"Centre De Protection Civile",
    "wof:placetype":"venue"
},
  "geometry": {"coordinates":[6.6045541763,46.6579742432],"type":"Point"}
}