{
  "type": "Feature",
  "properties": {
    "iso:country":"CH",
    "sg:address":"Weidhof",
    "sg:city":"Oberweningen",
    "sg:orig_category":"Fachdetailhandel in Verkaufsr\u00e4umen Herstellung von Sport U Freizeitbekleidung",
    "sg:phone":"+41 55 210 26 72",
    "sg:postcode":"8165",
    "sg:province":"Z\u00fcrich",
    "wof:name":"Moser Mode Ag",
    "wof:placetype":"venue"
},
  "geometry": {"coordinates":[8.8288106918,47.2260017395],"type":"Point"}
}