{
  "type": "Feature",
  "properties": {
    "iso:country":"CH",
    "sg:address":"Esserts Route Des 48",
    "sg:city":"Bogis-bossey",
    "sg:orig_category":"Pensionskassen",
    "sg:postcode":"1279",
    "sg:province":"Vaud",
    "wof:name":"Association Pour La Protection Des Patrons Ind\u00e9pendants (appi)",
    "wof:placetype":"venue"
},
  "geometry": {"coordinates":[6.1625461578,46.3447494507],"type":"Point"}
}