{
  "type": "Feature",
  "properties": {
    "iso:country":"CH",
    "sg:address":"Bernstrasse 81",
    "sg:city":"Toffen",
    "sg:orig_category":"D\u00e4mmung gegen K\u00e4lte, W\u00e4rme, Schall U Ersch\u00fctterung",
    "sg:phone":"+41 31 819 19 78",
    "sg:postcode":"3125",
    "sg:province":"Bern",
    "wof:name":"Hans Hartmann Isolierungen",
    "wof:placetype":"venue"
},
  "geometry": {"coordinates":[7.4926428795,46.8753509521],"type":"Point"}
}