{
  "type": "Feature",
  "properties": {
    "iso:country":"CH",
    "sg:address":"Ifangstrasse 101 8153 R\u00fcmlang. Postfach 237",
    "sg:city":"R\u00fcmlang",
    "sg:orig_category":"Grosshandel mit Getr\u00e4nken Grosshandel mit Wein U Spirituosen",
    "sg:phone":"+41 18171876",
    "sg:postcode":"8153",
    "sg:province":"Z\u00fcrich",
    "wof:name":"Franvin Sa Weinhandlung",
    "wof:placetype":"venue"
},
  "geometry": {"coordinates":[8.5386648178,47.4462661743],"type":"Point"}
}