{
  "type": "Feature",
  "properties": {
    "iso:country":"CH",
    "sg:address":"Arnold Isler-strasse 2",
    "sg:city":"D\u00fcbendorf",
    "sg:orig_category":"Vereine Geselligkeit",
    "sg:phone":"+41 18219348",
    "sg:postcode":"8600",
    "sg:province":"Z\u00fcrich",
    "wof:name":"Flaachtalverein Z\u00fcrich",
    "wof:placetype":"venue"
},
  "geometry": {"coordinates":[8.6279449463,47.4010047913],"type":"Point"}
}