{
  "type": "Feature",
  "properties": {
    "iso:country":"CH",
    "sg:address":"Rigistr. 2",
    "sg:city":"Merenschwand",
    "sg:orig_category":"Herstellung von Metallerzeugnissen ohne Maschinenbau",
    "sg:phone":"+41 56 664 18 94",
    "sg:postcode":"5634",
    "sg:province":"Aargau",
    "wof:name":"Schwegler Erich Ag",
    "wof:placetype":"venue"
},
  "geometry": {"coordinates":[8.3877973557,47.2604866028],"type":"Point"}
}