{
  "type": "Feature",
  "properties": {
    "iso:country":"CH",
    "sg:address":"Cr\u00eat-taconnet Rue Du 48",
    "sg:city":"Neuch\u00e2tel",
    "sg:orig_category":"Stukkateurgewerbe, Gipserei U Verputzerei",
    "sg:postcode":"2000",
    "sg:province":"Neuch\u00e2tel",
    "wof:name":"Pl\u00e2trerie-peinture, P.-a. Stauffer",
    "wof:placetype":"venue"
},
  "geometry": {"coordinates":[6.9310851097,46.9903335571],"type":"Point"}
}