{
  "type": "Feature",
  "properties": {
    "iso:country":"CH",
    "sg:address":"Hohlstrasse 560 8048 Z\u00fcrich. Postfach",
    "sg:city":"Z\u00fcrich",
    "sg:orig_category":"Aktivit\u00e4ten der Generalunternehmen im Baugewerbe Vermittlung von Immobilien",
    "sg:phone":"+41 14358080",
    "sg:postcode":"8048",
    "sg:province":"Z\u00fcrich",
    "wof:name":"Mobag Ag Finanzen + Controlling",
    "wof:placetype":"venue"
},
  "geometry": {"coordinates":[8.489227,47.390865],"type":"Point"}
}