{
  "type": "Feature",
  "properties": {
    "iso:country":"CH",
    "sg:address":"Drosselstrasse 21",
    "sg:city":"Therwil",
    "sg:orig_category":"Gartenbau",
    "sg:phone":"+41 61 721 37 88",
    "sg:postcode":"4106",
    "sg:province":"Basel-Landschaft",
    "wof:name":"Gutzwiller Walter Gartenbau Gmbh",
    "wof:placetype":"venue"
},
  "geometry": {"coordinates":[7.5507807732,47.4944343567],"type":"Point"}
}