{
  "type": "Feature",
  "properties": {
    "iso:country":"CH",
    "sg:address":"Moosgasse 3",
    "sg:city":"Sursee",
    "sg:classifiers":[
        {
            "category":"Restaurant",
            "type":"Food & Drink"
        }
    ],
    "sg:phone":"+41 81 415 36 36",
    "sg:postcode":"6210",
    "sg:province":"Luzern",
    "wof:name":"Restaurant Time-out - Eisbahn",
    "wof:placetype":"venue"
},
  "geometry": {"coordinates":[9.8269090652,46.7977981567],"type":"Point"}
}