{
  "type": "Feature",
  "properties": {
    "iso:country":"CH",
    "sg:address":"Bahnhofstrasse 12",
    "sg:city":"Zug",
    "sg:classifiers":[
        {
            "category":"Restaurant",
            "type":"Food & Drink"
        }
    ],
    "sg:phone":"+41 41 711 18 72",
    "sg:postcode":"6300",
    "sg:province":"Zug",
    "wof:name":"Restaurant M\u00f6venpick",
    "wof:placetype":"venue"
},
  "geometry": {"coordinates":[8.5159311295,47.1688079834],"type":"Point"}
}