{
  "type": "Feature",
  "properties": {
    "iso:country":"CH",
    "sg:address":"Carl-spitteler-strasse 2",
    "sg:city":"Romanshorn",
    "sg:orig_category":"Versicherungen Generalagenturen",
    "sg:phone":"+41 71 411 75 73",
    "sg:postcode":"8590",
    "sg:province":"Thurgau",
    "wof:name":"Rentenanstalt/swiss Life Generalagentur",
    "wof:placetype":"venue"
},
  "geometry": {"coordinates":[9.3671216965,47.5708694458],"type":"Point"}
}