{
  "type": "Feature",
  "properties": {
    "iso:country":"CH",
    "sg:address":"Unterdorf 9",
    "sg:city":"Rechthalten",
    "sg:classifiers":[
        {
            "category":"Retail",
            "subcategory":"Repair Shop",
            "type":"Services"
        }
    ],
    "sg:phone":"+41 26 418 21 01",
    "sg:postcode":"1718",
    "sg:province":"Fribourg",
    "sg:tags":[
        "agricultural",
        "machinery"
    ],
    "wof:name":"Peter Baechler Landmaschinen",
    "wof:placetype":"venue"
},
  "geometry": {"coordinates":[7.240399,46.767632],"type":"Point"}
}