{
  "type": "Feature",
  "properties": {
    "iso:country":"CH",
    "sg:address":"Via Chiasso 30",
    "sg:city":"Biasca",
    "sg:orig_category":"Herstellung von Karosserien U Anh\u00e4ngern",
    "sg:phone":"+41 79 685 57 37",
    "sg:postcode":"6710",
    "sg:province":"Ticino",
    "wof:name":"Carrozzeria M\u00fcller & Maggetti Sa",
    "wof:placetype":"venue"
},
  "geometry": {"coordinates":[8.9764661789,46.3404846191],"type":"Point"}
}