{
  "type": "Feature",
  "properties": {
    "iso:country":"CH",
    "sg:address":"Rue Centrale 30",
    "sg:city":"Chavannes-renens",
    "sg:orig_category":"Arztpraxen",
    "sg:phone":"+41 32 931 89 78",
    "sg:postcode":"1022",
    "sg:province":"Vaud",
    "wof:name":"Dr M\u00e9d. Reda Bekechi M\u00e9decin Sp\u00e9cialiste Fmh",
    "wof:placetype":"venue"
},
  "geometry": {"coordinates":[6.749143,47.056316],"type":"Point"}
}