{
  "type": "Feature",
  "properties": {
    "iso:country":"CH",
    "sg:address":"Rue Des Vollandes 21",
    "sg:city":"Gen\u00e8ve",
    "sg:orig_category":"Kosmetikinstitute",
    "sg:phone":"+41 71 222 58 21",
    "sg:postcode":"1207",
    "sg:province":"Gen\u00e8ve",
    "wof:name":"All-cosmetic Susanna Z\u00fcblin",
    "wof:placetype":"venue"
},
  "geometry": {"coordinates":[9.3775186539,47.4257049561],"type":"Point"}
}