{
  "type": "Feature",
  "properties": {
    "addr:full":"Kastanienbaumstr. 57 Horw Luzern 6048",
    "addr:housenumber":"57",
    "addr:postcode":"6048",
    "addr:street":"Kastanienbaumstr.",
    "iso:country":"CH",
    "sg:address":"Kastanienbaumstr. 57",
    "sg:city":"Horw",
    "sg:classifiers":[
        {
            "category":"Farming",
            "subcategory":"Farm & Veterinary Services",
            "type":"Manufacturing & Wholesale Goods"
        }
    ],
    "sg:phone":"+41 41 340 30 32",
    "sg:postcode":"6048",
    "sg:province":"Luzern",
    "sg:tags":[
        "advice",
        "agriculture",
        "livestock",
        "business"
    ],
    "wof:name":"Gebr. Burri Gartenbau Ag",
    "wof:placetype":"venue"
},
  "geometry": {"coordinates":[8.30954,47.023514],"type":"Point"}
}