{
  "type": "Feature",
  "properties": {
    "iso:country":"CH",
    "sg:address":"Geren 8",
    "sg:city":"Tagelswangen",
    "sg:orig_category":"Fachdetailhandel in Verkaufsr\u00e4umen Grosshandel mit Sportartikeln",
    "sg:phone":"+41 52 765 28 28",
    "sg:postcode":"8317",
    "sg:province":"Z\u00fcrich",
    "wof:name":"J\u00fcrg Schawalder Ism Sportmarketing",
    "wof:placetype":"venue"
},
  "geometry": {"coordinates":[8.6666793823,47.4323577881],"type":"Point"}
}