{
  "type": "Feature",
  "properties": {
    "iso:country":"CH",
    "sg:address":"Kornmattgasse 12",
    "sg:city":"Spiez",
    "sg:orig_category":"Arbeitnehmerverb\u00e4nde",
    "sg:phone":"+41 33 654 27 57",
    "sg:postcode":"3700",
    "sg:province":"Bern",
    "wof:name":"Kaufm\u00e4nnischer Verein Spiez",
    "wof:placetype":"venue"
},
  "geometry": {"coordinates":[7.675288,46.687031],"type":"Point"}
}