{
  "type": "Feature",
  "properties": {
    "iso:country":"CH",
    "sg:address":"Industriestrasse",
    "sg:city":"Sarnen",
    "sg:orig_category":"Rechtsberatung",
    "sg:phone":"+41 41 666 99 66",
    "sg:postcode":"6060",
    "sg:province":"Obwalden",
    "wof:name":"Sarna Patent Und Lizenz Ag",
    "wof:placetype":"venue"
},
  "geometry": {"coordinates":[8.2517948151,46.9028129578],"type":"Point"}
}