{
  "type": "Feature",
  "properties": {
    "addr:full":"Rotacker Krattigen Bern 3704",
    "addr:postcode":"3704",
    "iso:country":"CH",
    "sg:address":"Rotacker",
    "sg:city":"Krattigen",
    "sg:classifiers":[
        {
            "category":"Banks & Credit Unions",
            "subcategory":"Bank",
            "type":"Services"
        }
    ],
    "sg:phone":"+41 33543453",
    "sg:postcode":"3704",
    "sg:province":"Bern",
    "wof:name":"Schweiz. Mobiliar",
    "wof:placetype":"venue"
},
  "geometry": {"coordinates":[7.727885,46.661083],"type":"Point"}
}