{
  "type": "Feature",
  "properties": {
    "iso:country":"CH",
    "sg:address":"Neudorf.",
    "sg:city":"Sennwald",
    "sg:orig_category":"Detailhandel mit Fleisch U Fleischwaren",
    "sg:phone":"+41 81 302 13 22",
    "sg:postcode":"9466",
    "sg:province":"St. Gallen",
    "wof:name":"Metzgerei Kellenberger",
    "wof:placetype":"venue"
},
  "geometry": {"coordinates":[9.5017824173,47.0033226013],"type":"Point"}
}