{
  "type": "Feature",
  "properties": {
    "addr:full":"Postplatz 4 Kerns Obwalden 6064",
    "addr:housenumber":"4",
    "addr:postcode":"6064",
    "addr:street":"Postplatz",
    "iso:country":"CH",
    "sg:address":"Postplatz 4",
    "sg:city":"Kerns",
    "sg:orig_category":"Detailhandel mit B\u00fcchern, Zeitungen, Schreib U Papeteriewaren Detailhandel mit Schreib U Papeteriewa",
    "sg:phone":"+41 41 660 89 71",
    "sg:postcode":"6064",
    "sg:province":"Obwalden",
    "wof:name":"Papeterie Durrer Gmbh",
    "wof:placetype":"venue"
},
  "geometry": {"coordinates":[8.274907,46.900772],"type":"Point"}
}