{
  "type": "Feature",
  "properties": {
    "addr:full":"Dorfplatz 2 Altendorf Schwyz 8852",
    "addr:housenumber":"2",
    "addr:postcode":"8852",
    "addr:street":"Dorfplatz",
    "iso:country":"CH",
    "sg:address":"Dorfplatz 2",
    "sg:city":"Altendorf",
    "sg:orig_category":"Arztpraxen",
    "sg:phone":"+41 55 462 33 33",
    "sg:postcode":"8852",
    "sg:province":"Schwyz",
    "wof:name":"Dres Med. Bolliger & Steiner Spezial\u00e4rzte Fmh",
    "wof:placetype":"venue"
},
  "geometry": {"coordinates":[8.829836,47.191944],"type":"Point"}
}