{
  "type": "Feature",
  "properties": {
    "iso:country":"CH",
    "sg:address":"Baselstrasse 35",
    "sg:city":"Sch\u00f6nenbuch",
    "sg:orig_category":"Malerei",
    "sg:phone":"+41 61 481 42 05",
    "sg:postcode":"4124",
    "sg:province":"Basel-Landschaft",
    "wof:name":"Marcel Colin Malergesch\u00e4ft",
    "wof:placetype":"venue"
},
  "geometry": {"coordinates":[7.5065307617,47.5398330688],"type":"Point"}
}