{
  "type": "Feature",
  "properties": {
    "addr:full":"Bachstrasse 8 5417 Untersiggenthal. Postfach Untersiggenthal Aargau 5417",
    "addr:housenumber":"8",
    "addr:postcode":"5417;5417",
    "addr:street":"Bachstrasse",
    "iso:country":"CH",
    "sg:address":"Bachstrasse 8 5417 Untersiggenthal. Postfach",
    "sg:city":"Untersiggenthal",
    "sg:orig_category":"Architektur U Ingenieurb\u00fcros",
    "sg:phone":"+41 56 288 39 76",
    "sg:postcode":"5417",
    "sg:province":"Aargau",
    "wof:name":"L. Ruf Architekturb\u00fcro Ag",
    "wof:placetype":"venue"
},
  "geometry": {"coordinates":[8.262558,47.496899],"type":"Point"}
}