{
  "type": "Feature",
  "properties": {
    "iso:country":"CH",
    "sg:address":"Lausanne Route De 207",
    "sg:city":"Cully",
    "sg:orig_category":"Dienstleistungen von Beteiligungsgesellschaften",
    "sg:postcode":"1096",
    "sg:province":"Vaud",
    "wof:name":"H.a.s. Assist, H\u00e9l\u00e8ne-antoinette Savioz",
    "wof:placetype":"venue"
},
  "geometry": {"coordinates":[6.7303199768,46.4881858826],"type":"Point"}
}