{
  "type": "Feature",
  "properties": {
    "iso:country":"CH",
    "sg:address":"1564",
    "sg:city":"Domdidier",
    "sg:orig_category":"Druck ohne Zeitungsdruck",
    "sg:phone":"+41 21 921 74 12",
    "sg:postcode":"1564",
    "sg:province":"Fribourg",
    "wof:name":"Imprimerie Friedli",
    "wof:placetype":"venue"
},
  "geometry": {"coordinates":[5.1808700562,45.8973388672],"type":"Point"}
}