{
  "type": "Feature",
  "properties": {
    "iso:country":"CH",
    "sg:address":"Ormalingerstrasse 36",
    "sg:city":"Gelterkinden",
    "sg:orig_category":"Bauspenglerei Dachdeckerei",
    "sg:phone":"+41 61 981 42 32",
    "sg:postcode":"4460",
    "sg:province":"Basel-Landschaft",
    "wof:name":"Fetda E.furrer & E.thommen Bedachungen & Spenglerei",
    "wof:placetype":"venue"
},
  "geometry": {"coordinates":[7.86211,47.46862],"type":"Point"}
}