{
  "type": "Feature",
  "properties": {
    "iso:country":"CH",
    "sg:address":"B\u00f6hl 303",
    "sg:city":"Waldstatt",
    "sg:orig_category":"Herstellung von sonstigen chemischen Erzeugnissen Herstellung von sonstigen organischen Grundstoffen",
    "sg:phone":"+41 71 350 11 11",
    "sg:postcode":"9104",
    "sg:province":"Appenzell Ausserrhoden",
    "wof:name":"Arcolor Ag",
    "wof:placetype":"venue"
},
  "geometry": {"coordinates":[9.2850294113,47.3537940979],"type":"Point"}
}