{
  "type": "Feature",
  "properties": {
    "addr:full":"Wangenstrasse 22 Deitingen Solothurn 4543",
    "addr:housenumber":"22",
    "addr:postcode":"4543",
    "addr:street":"Wangenstrasse",
    "iso:country":"CH",
    "sg:address":"Wangenstrasse 22",
    "sg:city":"Deitingen",
    "sg:classifiers":[
        {
            "category":"Manufacturing",
            "subcategory":"Tools & Machinery",
            "type":"Manufacturing & Wholesale Goods"
        }
    ],
    "sg:phone":"+41 32 614 32 33",
    "sg:postcode":"4543",
    "sg:province":"Solothurn",
    "sg:tags":[
        "machining",
        "cnc"
    ],
    "wof:name":"Rsd Mechanik Rothermann / Schreier",
    "wof:placetype":"venue"
},
  "geometry": {"coordinates":[7.622414,47.214394],"type":"Point"}
}