{
  "type": "Feature",
  "properties": {
    "iso:country":"CH",
    "sg:address":"Neuenburgerstrasse 2",
    "sg:city":"Aarau",
    "sg:orig_category":"Patentverwertung",
    "sg:phone":"+41 62 823 63 29",
    "sg:postcode":"5004",
    "sg:province":"Aargau",
    "wof:name":"Abatron-patentb\u00fcro Ag Filiale Aarau",
    "wof:placetype":"venue"
},
  "geometry": {"coordinates":[8.0619907379,47.3992156982],"type":"Point"}
}