{
  "type": "Feature",
  "properties": {
    "iso:country":"CH",
    "sg:address":"Hofstrasse 3",
    "sg:city":"Glattfelden",
    "sg:orig_category":"Verlagsgewerbe Zeitungsverlag",
    "sg:phone":"+41 18672300",
    "sg:postcode":"8192",
    "sg:province":"Z\u00fcrich",
    "wof:name":"Schweizerische Weinzeitung Verlag Ag",
    "wof:placetype":"venue"
},
  "geometry": {"coordinates":[8.5025978088,47.5582275391],"type":"Point"}
}