{
  "type": "Feature",
  "properties": {
    "iso:country":"CH",
    "sg:address":"Route De Fermens",
    "sg:city":"Apples",
    "sg:orig_category":"Bauschreinerei Herstellung von Konstruktionsteilen, Fertigbauteilen U Ausbauelementen aus Holz",
    "sg:phone":"+41 21 800 40 26",
    "sg:postcode":"1143",
    "sg:province":"Vaud",
    "wof:name":"Michel Devenoge Entreprise De Menuiserie",
    "wof:placetype":"venue"
},
  "geometry": {"coordinates":[6.399418,46.573017],"type":"Point"}
}