{
  "type": "Feature",
  "properties": {
    "iso:country":"CH",
    "sg:address":"7438 Hinterrhein. Postfach",
    "sg:city":"Hinterrhein",
    "sg:orig_category":"Interessenvertretungen",
    "sg:postcode":"7438",
    "sg:province":"Graubunden",
    "wof:name":"Meuli-stiftung, Prof. Dr. Martin",
    "wof:placetype":"venue"
},
  "geometry": {"coordinates":[9.1967449188,46.530380249],"type":"Point"}
}