{
  "type": "Feature",
  "properties": {
    "iso:country":"CH",
    "sg:address":"Kamorstrasse 8 9400 Rorschach. Postfach",
    "sg:city":"Rorschach",
    "sg:orig_category":"Sanit\u00e4r U Heizungsinstallation Sanit\u00e4r, Heizungs U L\u00fcftungsinstallation",
    "sg:phone":"+41 71 844 19 20",
    "sg:postcode":"9401",
    "sg:province":"St. Gallen",
    "wof:name":"Hagmann Ag",
    "wof:placetype":"venue"
},
  "geometry": {"coordinates":[9.4825878143,47.4767227173],"type":"Point"}
}