{
  "type": "Feature",
  "properties": {
    "iso:country":"CH",
    "sg:address":"Rickenstrasse 10 9630 Wattwil. Postfach 336",
    "sg:city":"Wattwil",
    "sg:orig_category":"Detailhandel mit Brot, Back U S\u00fcsswaren Erschliessung von Grundst\u00fccken",
    "sg:phone":"+41 71 988 10 08",
    "sg:postcode":"9630",
    "sg:province":"St. Gallen",
    "wof:name":"B\u00e4ckerei-konditorei Eisenegger M.",
    "wof:placetype":"venue"
},
  "geometry": {"coordinates":[9.084265,47.30069],"type":"Point"}
}