{
  "type": "Feature",
  "properties": {
    "iso:country":"CH",
    "sg:address":"Nordstrasse 24/26",
    "sg:city":"Z\u00fcrich",
    "sg:orig_category":"Herstellung von Metallkonstruktionen Stahl U Leichtmetallbau",
    "sg:phone":"+41 32 373 11 21",
    "sg:postcode":"8006",
    "sg:province":"Z\u00fcrich",
    "wof:name":"Baik Gmbh",
    "wof:placetype":"venue"
},
  "geometry": {"coordinates":[7.2705478668,47.1204490662],"type":"Point"}
}