{
  "type": "Feature",
  "properties": {
    "iso:country":"CH",
    "sg:address":"Blumenaustrasse 3",
    "sg:city":"Heiden",
    "sg:orig_category":"Museen",
    "sg:phone":"+41 81 302 57 14",
    "sg:postcode":"9410",
    "sg:province":"Appenzell Ausserrhoden",
    "wof:name":"Artiservicium Zellweger Sandra",
    "wof:placetype":"venue"
},
  "geometry": {"coordinates":[9.5315122604,47.4447937012],"type":"Point"}
}