{
  "type": "Feature",
  "properties": {
    "iso:country":"CH",
    "sg:address":"Ouest Rue De L' 12 2740 Montagne-moutier. Postfach",
    "sg:city":"Montagne-moutier",
    "sg:orig_category":"Wirtschaftspr\u00fcfung, Steuerberatung U Treuhand",
    "sg:postcode":"2740",
    "sg:province":"Bern",
    "wof:name":"Fiduciaire De La Pr\u00e9v\u00f4te S\u00e0rl Bureau Fiduciaire, Etc",
    "wof:placetype":"venue"
},
  "geometry": {"coordinates":[7.382581234,47.2798233032],"type":"Point"}
}