{
  "type": "Feature",
  "properties": {
    "iso:country":"CH",
    "sg:address":"Fabrikstrasse 4",
    "sg:city":"Siebnen",
    "sg:orig_category":"Sonstiger Grosshandel",
    "sg:phone":"+41 55 440 63 31",
    "sg:postcode":"8854",
    "sg:province":"Schwyz",
    "wof:name":"W. Schwendeler Import & Handel",
    "wof:placetype":"venue"
},
  "geometry": {"coordinates":[8.8965892792,47.1753578186],"type":"Point"}
}