{
  "type": "Feature",
  "properties": {
    "iso:country":"CH",
    "sg:address":"Alberenberg 9402 M\u00f6rschwil. Postfach 124",
    "sg:city":"M\u00f6rschwil",
    "sg:orig_category":"Kauf U Verkauf von Immobilien auf eigene Rechnung Vermittlung von Immobilien",
    "sg:phone":"+41 61 402 00 70",
    "sg:postcode":"9402",
    "sg:province":"St. Gallen",
    "wof:name":"Stephan Walter Senn Immobilien-treuhand",
    "wof:placetype":"venue"
},
  "geometry": {"coordinates":[7.5566082001,47.5195083618],"type":"Point"}
}