{
  "type": "Feature",
  "properties": {
    "iso:country":"CH",
    "sg:address":"Lerchenrain 8",
    "sg:city":"Z\u00fcrich",
    "sg:classifiers":[
        {
            "category":"Professional",
            "subcategory":"Employment Agencies",
            "type":"Services"
        }
    ],
    "sg:phone":"+41 13719435",
    "sg:postcode":"8046",
    "sg:province":"Z\u00fcrich",
    "sg:tags":[
        "personal",
        "u",
        "stellenvermittlung"
    ],
    "wof:name":"Maurer + Partner Personalberatung",
    "wof:placetype":"venue"
},
  "geometry": {"coordinates":[8.5087108612,47.4141807556],"type":"Point"}
}