{
  "type": "Feature",
  "properties": {
    "iso:country":"CH",
    "sg:address":"Schulstrasse",
    "sg:city":"Friltschen",
    "sg:orig_category":"Tierheime",
    "sg:phone":"+41 71 655 13 30",
    "sg:postcode":"9504",
    "sg:province":"Thurgau",
    "wof:name":"Yvonne Christen Katzenferienheim",
    "wof:placetype":"venue"
},
  "geometry": {"coordinates":[9.0853796005,47.5387649536],"type":"Point"}
}