{
  "type": "Feature",
  "properties": {
    "iso:country":"CH",
    "sg:address":"Eierbrechtstrasse 47 8000 Z\u00fcrich. Postfach",
    "sg:city":"Z\u00fcrich",
    "sg:orig_category":"Gesundheitswesen",
    "sg:postcode":"8053",
    "sg:province":"Z\u00fcrich",
    "wof:name":"Pharma Progress Gmbh",
    "wof:placetype":"venue"
},
  "geometry": {"coordinates":[8.5783042908,47.3577804565],"type":"Point"}
}