{
  "type": "Feature",
  "properties": {
    "iso:country":"CH",
    "sg:address":"1874",
    "sg:city":"Champ\u00e9ry",
    "sg:orig_category":"Reiseb\u00fcros U Reiseveranstalter",
    "sg:phone":"+41 24 479 14 27",
    "sg:postcode":"1874",
    "sg:province":"Valais",
    "wof:name":"Soci\u00e9t\u00e9 De Promotion De Planachaux Sa (spp)",
    "wof:placetype":"venue"
},
  "geometry": {"coordinates":[6.8706860542,46.1794052124],"type":"Point"}
}