{
  "type": "Feature",
  "properties": {
    "iso:country":"CH",
    "sg:address":"M\u00fchlemattweg 24",
    "sg:city":"Magden",
    "sg:orig_category":"Kosmetikinstitute",
    "sg:phone":"+41 61 841 16 89",
    "sg:postcode":"4312",
    "sg:province":"Aargau",
    "wof:name":"Silvia Breitenmoser Kosmetikinstitut",
    "wof:placetype":"venue"
},
  "geometry": {"coordinates":[7.8152618408,47.5200462341],"type":"Point"}
}