{
  "type": "Feature",
  "properties": {
    "iso:country":"CH",
    "sg:address":"2942",
    "sg:city":"Alle",
    "sg:orig_category":"Maler U Glasergewerbe Stukkateurgewerbe, Gipserei U Verputzerei",
    "sg:phone":"+41 32 471 13 26",
    "sg:postcode":"2942",
    "sg:province":"Jura",
    "wof:name":"Burgerey Sa",
    "wof:placetype":"venue"
},
  "geometry": {"coordinates":[7.1273069382,47.4245681763],"type":"Point"}
}