{
  "type": "Feature",
  "properties": {
    "iso:country":"CH",
    "sg:address":"Molliserstrasse 41",
    "sg:city":"Netstal",
    "sg:orig_category":"Detailhandel mit Waren verschiedener Art, Hauptrichtung Nahrungsmittel",
    "sg:phone":"+41 55 640 86 86",
    "sg:postcode":"8754",
    "sg:province":"Glarus",
    "wof:name":"Coop Super Center Wiggispark",
    "wof:placetype":"venue"
},
  "geometry": {"coordinates":[9.0588922501,47.0662612915],"type":"Point"}
}