{
  "type": "Feature",
  "properties": {
    "iso:country":"CH",
    "sg:address":"Route Du Nant-d'avril 107",
    "sg:city":"Meyrin",
    "sg:orig_category":"Ledererzeugung",
    "sg:phone":"+41 22 782 27 77",
    "sg:postcode":"1217",
    "sg:province":"Gen\u00e8ve",
    "wof:name":"Cuiraneuf Sa",
    "wof:placetype":"venue"
},
  "geometry": {"coordinates":[6.0722098351,46.2284393311],"type":"Point"}
}