{
  "type": "Feature",
  "properties": {
    "iso:country":"CH",
    "sg:address":"Rue Jordils 23bis",
    "sg:city":"Yverdon-les-bains",
    "sg:orig_category":"Herstellung von Tanks U Sammelbeh\u00e4ltern aus Metall Sanit\u00e4r, Heizungs U L\u00fcftungsinstallation",
    "sg:phone":"+41 24 425 95 65",
    "sg:postcode":"1400",
    "sg:province":"Vaud",
    "wof:name":"Philippe Randin Br\u00fbleur Service",
    "wof:placetype":"venue"
},
  "geometry": {"coordinates":[6.6400361061,46.7761497498],"type":"Point"}
}