{
  "type": "Feature",
  "properties": {
    "iso:country":"CH",
    "sg:address":"Furkastrasse 42",
    "sg:city":"Naters",
    "sg:classifiers":[
        {
            "category":"Manufacturing",
            "subcategory":"Glass & Minerals",
            "type":"Manufacturing & Wholesale Goods"
        }
    ],
    "sg:phone":"+41 27 923 92 17",
    "sg:postcode":"3904",
    "sg:province":"Valais",
    "sg:tags":[
        "flat"
    ],
    "wof:name":"Eggel Gmbh",
    "wof:placetype":"venue"
},
  "geometry": {"coordinates":[7.993078,46.324173],"type":"Point"}
}