{
  "type": "Feature",
  "properties": {
    "iso:country":"CH",
    "sg:address":"B\u00fcntstrasse 17",
    "sg:city":"Grabs",
    "sg:orig_category":"Sonstige pers\u00f6nliche Dienstleistungen",
    "sg:postcode":"9472",
    "sg:province":"St. Gallen",
    "wof:name":"D\u00fcsel H\u00f6henarbeit",
    "wof:placetype":"venue"
},
  "geometry": {"coordinates":[9.4412431717,47.1838378906],"type":"Point"}
}