{
  "type": "Feature",
  "properties": {
    "iso:country":"CH",
    "sg:address":"Fliederstrasse 15",
    "sg:city":"Wettingen",
    "sg:orig_category":"P\u00e9dicure",
    "sg:phone":"+41 56 426 28 52",
    "sg:postcode":"5430",
    "sg:province":"Aargau",
    "wof:name":"Irene Antonopoulo Kosmetikinstitut Adena",
    "wof:placetype":"venue"
},
  "geometry": {"coordinates":[8.3213396072,47.4661026001],"type":"Point"}
}