{
  "type": "Feature",
  "properties": {
    "iso:country":"CH",
    "sg:address":"Clos Rue Du 61 J",
    "sg:city":"Soulce",
    "sg:orig_category":"Sanit\u00e4r, Heizungs U L\u00fcftungsinstallation",
    "sg:phone":"+41 26 921 22 41",
    "sg:postcode":"2864",
    "sg:province":"Jura",
    "wof:name":"Aebh Maintenance Hostettler E.",
    "wof:placetype":"venue"
},
  "geometry": {"coordinates":[7.1626710892,46.6232261658],"type":"Point"}
}