{
  "type": "Feature",
  "properties": {
    "iso:country":"CH",
    "sg:address":"Niklaus Wengistrasse 40 2540 Grenchen. Postfach 977",
    "sg:city":"Grenchen",
    "sg:orig_category":"Giessereiindustrie Herstellung von Metallerzeugnissen ohne Maschinenbau",
    "sg:phone":"+41 32 652 10 38",
    "sg:postcode":"2540",
    "sg:province":"Solothurn",
    "wof:name":"Giesserei Und Metallwarenfabrik Rieger Josef Ag",
    "wof:placetype":"venue"
},
  "geometry": {"coordinates":[7.4047012329,47.1879806519],"type":"Point"}
}