{
  "type": "Feature",
  "properties": {
    "iso:country":"CH",
    "sg:address":"Im Kapf",
    "sg:city":"Morschach",
    "sg:orig_category":"Erbringung von Dienstleistungen f\u00fcr Unternehmen",
    "sg:postcode":"6443",
    "sg:province":"Schwyz",
    "wof:name":"Zenh\u00e4usern Lorenz, Boden Und Wandbel\u00e4ge",
    "wof:placetype":"venue"
},
  "geometry": {"coordinates":[7.8033881187,46.2830123901],"type":"Point"}
}