{
  "type": "Feature",
  "properties": {
    "addr:full":"Rue Maurice-braillard 18 Gen\u00e8ve Gen\u00e8ve 1202",
    "addr:housenumber":"18",
    "addr:postcode":"1202",
    "addr:street":"Rue Maurice-Braillard",
    "iso:country":"CH",
    "sg:address":"Rue Maurice-braillard 18",
    "sg:city":"Gen\u00e8ve",
    "sg:orig_category":"Arztpraxen",
    "sg:phone":"+41 22 734 22 50",
    "sg:postcode":"1202",
    "sg:province":"Gen\u00e8ve",
    "wof:name":"Dr M\u00e9d.antonella Valiton-crusi M\u00e9decin Sp\u00e9cialiste Fmh",
    "wof:placetype":"venue"
},
  "geometry": {"coordinates":[6.131732,46.220268],"type":"Point"}
}