{
  "type": "Feature",
  "properties": {
    "iso:country":"CH",
    "sg:address":"R\u00fctiweg 7 8200 Schaffhausen. Postfach",
    "sg:city":"Schaffhausen",
    "sg:orig_category":"Sonstiger Grosshandel",
    "sg:postcode":"8203",
    "sg:province":"Schaffhausen",
    "wof:name":"Brooklyn-vertrieb Wabel & Hug",
    "wof:placetype":"venue"
},
  "geometry": {"coordinates":[8.654501915,47.6983299255],"type":"Point"}
}