{
  "type": "Feature",
  "properties": {
    "iso:country":"CH",
    "sg:address":"Seetalstrasse 85",
    "sg:city":"Hallwil",
    "sg:orig_category":"Landw. Genossenschaften Dresch",
    "sg:phone":"+41 62 777 14 25",
    "sg:postcode":"5705",
    "sg:province":"Aargau",
    "wof:name":"Rudolf Urech M\u00e4hdrescherei",
    "wof:placetype":"venue"
},
  "geometry": {"coordinates":[8.1724014282,47.3320999146],"type":"Point"}
}