{
  "type": "Feature",
  "properties": {
    "iso:country":"CH",
    "sg:address":"Brunnadernstrase 27",
    "sg:city":"Leuzigen",
    "sg:orig_category":"Reparatur von Uhren U Schmuck",
    "sg:phone":"+41 32 679 36 94",
    "sg:postcode":"3297",
    "sg:province":"Bern",
    "wof:name":"Ren\u00e9 Isler Uhrenmacher",
    "wof:placetype":"venue"
},
  "geometry": {"coordinates":[7.4656100273,47.1730194092],"type":"Point"}
}