{
  "type": "Feature",
  "properties": {
    "iso:country":"CH",
    "sg:address":"Kirchstrasse 4",
    "sg:city":"Wallisellen",
    "sg:orig_category":"Kosmetikinstitute",
    "sg:phone":"+41 71 222 38 16",
    "sg:postcode":"8304",
    "sg:province":"Z\u00fcrich",
    "wof:name":"Maria Wyss Kosmetikinstitut B\u00fcrgi",
    "wof:placetype":"venue"
},
  "geometry": {"coordinates":[9.3756361008,47.4241714478],"type":"Point"}
}