{
  "type": "Feature",
  "properties": {
    "iso:country":"CH",
    "sg:address":"2735",
    "sg:city":"B\u00e9vilard",
    "sg:orig_category":"Architektur U Ingenieurb\u00fcros",
    "sg:phone":"+41 32 492 27 27",
    "sg:postcode":"2735",
    "sg:province":"Bern",
    "wof:name":"Fn Sa",
    "wof:placetype":"venue"
},
  "geometry": {"coordinates":[7.282712,47.236618],"type":"Point"}
}