{
  "type": "Feature",
  "properties": {
    "iso:country":"CH",
    "sg:address":"Rive Rue De 4 1204 Gen\u00e8ve. Postfach",
    "sg:city":"Gen\u00e8ve",
    "sg:orig_category":"RESTAURANTS: TEA-ROOMS",
    "sg:postcode":"1204",
    "sg:province":"Gen\u00e8ve",
    "wof:name":"Gross Ulrich.",
    "wof:placetype":"venue"
},
  "geometry": {"coordinates":[9.5397453308,47.3774223328],"type":"Point"}
}