{
  "type": "Feature",
  "properties": {
    "iso:country":"CH",
    "sg:address":"Kasernenstrasse 117",
    "sg:city":"Chur",
    "sg:orig_category":"Detailhandel mit M\u00f6beln U Haushaltsgegenst\u00e4nden",
    "sg:postcode":"7000",
    "sg:province":"Graubunden",
    "wof:name":"Alfred Pally, Gastro + Restaurationsberatung",
    "wof:placetype":"venue"
},
  "geometry": {"coordinates":[9.5169839859,46.8466148376],"type":"Point"}
}