{
  "type": "Feature",
  "properties": {
    "iso:country":"CH",
    "sg:address":"Margencel Rue 13",
    "sg:city":"Aigle",
    "sg:orig_category":"Non-Classified Establishments",
    "sg:postcode":"1860",
    "sg:province":"Vaud",
    "wof:name":"Fondation Calcutta-espoir",
    "wof:placetype":"venue"
},
  "geometry": {"coordinates":[6.9651651382,46.3173866272],"type":"Point"}
}