{
  "type": "Feature",
  "properties": {
    "iso:country":"CH",
    "sg:address":"S\u00e4ntisstrasse 5",
    "sg:city":"Wolfhausen",
    "sg:orig_category":"Grosshandel mit B\u00fcromaschinen Softwareentwicklung U beratung",
    "sg:phone":"+41 55 243 36 50",
    "sg:postcode":"8633",
    "sg:province":"Z\u00fcrich",
    "wof:name":"Jordi Informatik",
    "wof:placetype":"venue"
},
  "geometry": {"coordinates":[8.79920578,47.2601394653],"type":"Point"}
}