{
  "type": "Feature",
  "properties": {
    "iso:country":"CH",
    "sg:address":"Grindelstrasse 43",
    "sg:city":"Volketswil",
    "sg:orig_category":"Softwareentwicklung U beratung",
    "sg:phone":"+41 19450175",
    "sg:postcode":"8604",
    "sg:province":"Z\u00fcrich",
    "wof:name":"Rms It-consulting Gmbh",
    "wof:placetype":"venue"
},
  "geometry": {"coordinates":[8.665561676,47.3869514465],"type":"Point"}
}