{
  "type": "Feature",
  "properties": {
    "iso:country":"CH",
    "sg:address":"Sonnenbergstrasse 50 8032 Z\u00fcrich 32 Zust. Postfach 8032 Z\u00fcrich",
    "sg:city":"Zust",
    "sg:orig_category":"Fachdetailhandel in Verkaufsr\u00e4umen",
    "sg:postcode":"32",
    "wof:name":"Elgeba Elsener Geschenk- U. Bastelartikel; Vertrieb",
    "wof:placetype":"venue"
},
  "geometry": {"coordinates":[9.3019227982,47.4013366699],"type":"Point"}
}