{
  "type": "Feature",
  "properties": {
    "addr:full":"B\u00fcren 2 Gansingen Aargau 5272",
    "addr:housenumber":"2",
    "addr:postcode":"5272",
    "addr:street":"Bueren",
    "iso:country":"CH",
    "sg:address":"B\u00fcren 2",
    "sg:city":"Gansingen",
    "sg:orig_category":"Dachdeckerei Zimmerei, Dachdeckerei, Bauspenglerei U Abdichtung",
    "sg:phone":"+41 62 875 27 49",
    "sg:postcode":"5272",
    "sg:province":"Aargau",
    "wof:name":"Kr\u00e4henb\u00fchl Urs Spenglerei",
    "wof:placetype":"venue"
},
  "geometry": {"coordinates":[8.138472,47.532642],"type":"Point"}
}