{
  "type": "Feature",
  "properties": {
    "iso:country":"CH",
    "sg:address":"Via Vedreggio 1",
    "sg:city":"Pregassona",
    "sg:orig_category":"Nationale Postdienste",
    "sg:phone":"+41 91 941 45 19",
    "sg:postcode":"6963",
    "sg:province":"Ticino",
    "wof:name":"La Posta Svizzera",
    "wof:placetype":"venue"
},
  "geometry": {"coordinates":[8.9708824158,46.0203056335],"type":"Point"}
}