{
  "type": "Feature",
  "properties": {
    "addr:full":"Unterdorfstrasse 10 Geuensee Luzern 6232",
    "addr:housenumber":"10",
    "addr:postcode":"6232",
    "addr:street":"Unterdorfstrasse",
    "iso:country":"CH",
    "sg:address":"Unterdorfstrasse 10",
    "sg:city":"Geuensee",
    "sg:orig_category":"Blumen U Zierpflanzenbau Detailhandel mit Blumen U Pflanzen",
    "sg:phone":"+41 34 437 15 13",
    "sg:postcode":"6232",
    "sg:province":"Luzern",
    "wof:name":"Hansrudolf Leuenberger",
    "wof:placetype":"venue"
},
  "geometry": {"coordinates":[7.797445,47.042538],"type":"Point"}
}