{
  "type": "Feature",
  "properties": {
    "iso:country":"CH",
    "sg:address":"Saummattli 4",
    "sg:city":"Engelberg",
    "sg:orig_category":"Selbst\u00e4ndige bildende K\u00fcnstler",
    "sg:phone":"+41 41 637 24 57",
    "sg:postcode":"6390",
    "sg:province":"Obwalden",
    "wof:name":"Franz Dillier Holzbildhauer Werkstatt",
    "wof:placetype":"venue"
},
  "geometry": {"coordinates":[8.387178421,46.8202857971],"type":"Point"}
}