{
  "type": "Feature",
  "properties": {
    "iso:country":"CH",
    "sg:address":"Bankstrasse 21",
    "sg:city":"Glarus",
    "sg:orig_category":"Non-Classified Establishments",
    "sg:postcode":"8750",
    "sg:province":"Glarus",
    "wof:name":"Beteiligungsgesellschaft Zur F\u00f6rderung Von Studien In Handel Und Industrie, Sopadec",
    "wof:placetype":"venue"
},
  "geometry": {"coordinates":[9.0687503815,47.0403785706],"type":"Point"}
}