{
  "type": "Feature",
  "properties": {
    "iso:country":"CH",
    "sg:address":"Laubgasse 43",
    "sg:city":"Frauenfeld",
    "sg:orig_category":"Unclassifiable Establishments",
    "sg:phone":"+41 19290100",
    "sg:postcode":"8500",
    "sg:province":"Thurgau",
    "wof:name":"A. Lohm\u00fcller Restaurant Storchenst\u00fcbli",
    "wof:placetype":"venue"
},
  "geometry": {"coordinates":[8.7302980423,47.272693634],"type":"Point"}
}