{
  "type": "Feature",
  "properties": {
    "iso:country":"CH",
    "sg:address":"1820",
    "sg:city":"Territet-veytaux",
    "sg:orig_category":"Landesverteidigung, Sozialversicherung \u00d6ffentliche Verwaltung",
    "sg:phone":"+41 21 963 83 21",
    "sg:postcode":"1820",
    "sg:province":"Vaud",
    "wof:name":"Centre De Protection Civile",
    "wof:placetype":"venue"
},
  "geometry": {"coordinates":[6.9246101379,46.4245414734],"type":"Point"}
}