{
  "type": "Feature",
  "properties": {
    "iso:country":"CH",
    "sg:address":"Bahnhofstrasse 1 2542 Pieterlen. Postfach 287",
    "sg:city":"Pieterlen",
    "sg:classifiers":[
        {
            "category":"Travel",
            "subcategory":"Hotels & Motels",
            "type":"Entertainment"
        }
    ],
    "sg:phone":"+41 32 377 33 33",
    "sg:postcode":"2542",
    "sg:province":"Bern",
    "sg:tags":[
        "hotels",
        "mit",
        "restaurant"
    ],
    "wof:name":"Hotel Kl\u00f6sterli",
    "wof:placetype":"venue"
},
  "geometry": {"coordinates":[7.3384261131,47.174823761],"type":"Point"}
}