{
  "type": "Feature",
  "properties": {
    "iso:country":"CH",
    "sg:address":"4522",
    "sg:city":"R\u00fcttenen",
    "sg:orig_category":"Schwimmb\u00e4der",
    "sg:phone":"+41 18440640",
    "sg:postcode":"4522",
    "sg:province":"Solothurn",
    "wof:name":"Schulhaus Zihl Betriebsleitung Hallenbad",
    "wof:placetype":"venue"
},
  "geometry": {"coordinates":[8.4326639175,47.4601325989],"type":"Point"}
}