{
  "type": "Feature",
  "properties": {
    "iso:country":"CH",
    "sg:address":"Oberstadt 2",
    "sg:city":"Sursee",
    "sg:orig_category":"Grosshandel mit sonstigen Nahrungsmitteln",
    "sg:postcode":"6210",
    "sg:province":"Luzern",
    "wof:name":"B\u00fchler Fischhandlung",
    "wof:placetype":"venue"
},
  "geometry": {"coordinates":[8.1101074219,47.1723861694],"type":"Point"}
}