{
  "type": "Feature",
  "properties": {
    "iso:country":"CH",
    "sg:address":"Via Serodine 4",
    "sg:city":"Lugano",
    "sg:orig_category":"Kauf U Verkauf von Immobilien auf eigene Rechnung Vermittlung von Immobilien",
    "sg:phone":"+41 91 966 32 52",
    "sg:postcode":"6900",
    "sg:province":"Ticino",
    "wof:name":"B\u00f6rner-albertini Manfred",
    "wof:placetype":"venue"
},
  "geometry": {"coordinates":[8.9399261475,46.0086593628],"type":"Point"}
}