{
  "type": "Feature",
  "properties": {
    "iso:country":"CH",
    "sg:address":"Ch. De Praz-lau 3 Vern",
    "sg:city":"Lausanne",
    "sg:orig_category":"Mechanik",
    "sg:phone":"+41 19373930",
    "sg:postcode":"1000",
    "sg:province":"Vaud",
    "wof:name":"Prewetool Ag",
    "wof:placetype":"venue"
},
  "geometry": {"coordinates":[8.8433103561,47.3144493103],"type":"Point"}
}