{
  "type": "Feature",
  "properties": {
    "iso:country":"CH",
    "sg:address":"Lautengartenstrasse 7",
    "sg:city":"Basel",
    "sg:orig_category":"Advokaturb\u00fcros Notariate",
    "sg:phone":"+41 61 272 81 70",
    "sg:postcode":"4052",
    "sg:province":"Basel-Stadt",
    "wof:name":"Haab Haab M\u00fcller B\u00fcrgin & Schmutz",
    "wof:placetype":"venue"
},
  "geometry": {"coordinates":[7.595579,47.553337],"type":"Point"}
}