{
  "type": "Feature",
  "properties": {
    "iso:country":"CH",
    "sg:address":"Wehntalerstrasse 58",
    "sg:city":"Z\u00fcrich",
    "sg:orig_category":"Film U Videofilmherstellung Korrespondenz U Nachrichtenb\u00fcros, selbst\u00e4ndige Journalisten",
    "sg:phone":"+41 79 321 24 46",
    "sg:postcode":"8057",
    "sg:province":"Z\u00fcrich",
    "wof:name":"Positv Medienproduktion, Tschudin M.",
    "wof:placetype":"venue"
},
  "geometry": {"coordinates":[8.5378828049,47.4002571106],"type":"Point"}
}