{
  "type": "Feature",
  "properties": {
    "iso:country":"CH",
    "sg:address":"Industriestrasse 12 6300 Zug. Postfach",
    "sg:city":"Zug",
    "sg:orig_category":"Vermietung U Verpachtung von eigenen Immobilien Vermittlung von Immobilien",
    "sg:phone":"+41 41 729 10 10",
    "sg:postcode":"6304",
    "sg:province":"Zug",
    "wof:name":"Mz-immobilien Ag",
    "wof:placetype":"venue"
},
  "geometry": {"coordinates":[8.5185194016,47.1720466614],"type":"Point"}
}