{
  "type": "Feature",
  "properties": {
    "iso:country":"CH",
    "sg:address":"Z\u00fcrcherstrasse 14 8400 Winterthur. Postfach 414",
    "sg:city":"Winterthur",
    "sg:orig_category":"Unternehmensberatung",
    "sg:phone":"+41 52 262 11 22",
    "sg:postcode":"8400",
    "sg:province":"Z\u00fcrich",
    "wof:name":"Sulzer Management Ag",
    "wof:placetype":"venue"
},
  "geometry": {"coordinates":[8.717959404,47.4983100891],"type":"Point"}
}