{
  "type": "Feature",
  "properties": {
    "iso:country":"CH",
    "sg:address":"Unter-frittenbach",
    "sg:city":"Zollbr\u00fcck",
    "sg:orig_category":"Instandhaltung U Reparatur von Automobilen",
    "sg:phone":"+41 34 496 79 88",
    "sg:postcode":"3436",
    "sg:province":"Bern",
    "wof:name":"Garage Hertig",
    "wof:placetype":"venue"
},
  "geometry": {"coordinates":[7.7483658791,46.9748382568],"type":"Point"}
}