{
  "type": "Feature",
  "properties": {
    "iso:country":"CH",
    "sg:address":"Rue De La Couronne 5",
    "sg:city":"St-aubin-sauges",
    "sg:orig_category":"Herstellung von Hebezeugen U F\u00f6rdermitteln Herstellung von Schrauben, Nieten, Ketten U Federn",
    "sg:phone":"+41 32 838 10 85",
    "sg:postcode":"2024",
    "sg:province":"Neuch\u00e2tel",
    "wof:name":"Tendon Christian Cames",
    "wof:placetype":"venue"
},
  "geometry": {"coordinates":[6.7751350403,46.895324707],"type":"Point"}
}