{
  "type": "Feature",
  "properties": {
    "addr:full":"Moosgasse 17 Kerzers Fribourg 3210",
    "addr:housenumber":"17",
    "addr:postcode":"3210",
    "addr:street":"Moosgasse",
    "iso:country":"CH",
    "sg:address":"Moosgasse 17",
    "sg:city":"Kerzers",
    "sg:orig_category":"Detailhandel mit Brennstoffen U Heizmaterial G\u00fcterbef\u00f6rderung im Strassenverkehr",
    "sg:postcode":"3210",
    "sg:province":"Fribourg",
    "wof:name":"Tschachtli Uli",
    "wof:placetype":"venue"
},
  "geometry": {"coordinates":[7.193841,46.976357],"type":"Point"}
}