{
  "type": "Feature",
  "properties": {
    "iso:country":"CH",
    "sg:address":"Martinet Chemin Du 28",
    "sg:city":"Lausanne",
    "sg:orig_category":"Sonstiger Grosshandel",
    "sg:postcode":"1007",
    "sg:province":"Vaud",
    "wof:name":"Asco/joucomatic Sarl",
    "wof:placetype":"venue"
},
  "geometry": {"coordinates":[7.3060708046,47.1093521118],"type":"Point"}
}