{
  "type": "Feature",
  "properties": {
    "iso:country":"CH",
    "sg:address":"Dorfstrasse 11",
    "sg:city":"Engelberg",
    "sg:orig_category":"Non-Classified Establishments",
    "sg:postcode":"6390",
    "sg:province":"Obwalden",
    "wof:name":"Swiss Beam Ag Elektronenstrahl Schweisstechnik Ein Unternehmen Der Schlatter-gruppe",
    "wof:placetype":"venue"
},
  "geometry": {"coordinates":[-85.56592559809999,38.1064949036],"type":"Point"}
}