{
  "type": "Feature",
  "properties": {
    "iso:country":"CH",
    "sg:address":"Rainackerweg 68",
    "sg:city":"Gampelen",
    "sg:orig_category":"Sportvereine Turnen Vereine Damen",
    "sg:phone":"+41 32 313 40 28",
    "sg:postcode":"3236",
    "sg:province":"Bern",
    "wof:name":"Damenriege Stv Gampelen",
    "wof:placetype":"venue"
},
  "geometry": {"coordinates":[7.0546097755,47.0162086487],"type":"Point"}
}