{
  "type": "Feature",
  "properties": {
    "iso:country":"CH",
    "sg:address":"Hofackerstrasse 33 8953 Dietikon. Postfach",
    "sg:city":"Dietikon",
    "sg:orig_category":"Instandhaltung U Reparatur von Automobilen",
    "sg:phone":"+41 17410815",
    "sg:postcode":"8953",
    "sg:province":"Z\u00fcrich",
    "wof:name":"Auto - Pet\u00f6 Motorfahrzeug-handel",
    "wof:placetype":"venue"
},
  "geometry": {"coordinates":[8.4149799347,47.395652771],"type":"Point"}
}