{
  "type": "Feature",
  "properties": {
    "iso:country":"CH",
    "sg:address":"Via Giovan Battist Pioda 12",
    "sg:city":"Lugano",
    "sg:orig_category":"Unclassifiable Establishments",
    "sg:phone":"+41 91 911 70 20",
    "sg:postcode":"6900",
    "sg:province":"Ticino",
    "wof:name":"Mewica Holding Sa",
    "wof:placetype":"venue"
},
  "geometry": {"coordinates":[8.9544038773,46.0073471069],"type":"Point"}
}