{
  "type": "Feature",
  "properties": {
    "iso:country":"CH",
    "sg:address":"Rankweg 9",
    "sg:city":"Frenkendorf",
    "sg:orig_category":"Fotografische Ateliers Werbung",
    "sg:phone":"+41 61 901 31 00",
    "sg:postcode":"4402",
    "sg:province":"Basel-Landschaft",
    "wof:name":"Zimmer's Creativteam Werbeagentur",
    "wof:placetype":"venue"
},
  "geometry": {"coordinates":[7.7196850777,47.5043182373],"type":"Point"}
}