{
  "type": "Feature",
  "properties": {
    "iso:country":"CH",
    "sg:address":"Marienstrasse 15 3005 Bern. Postfach",
    "sg:city":"Bern",
    "sg:orig_category":"Sonstige Kultur U Unterhaltungseinrichtungen",
    "sg:postcode":"3005",
    "sg:province":"Bern",
    "wof:name":"Dance Passion Pauli Rathbone Rita & Rathbone Brad",
    "wof:placetype":"venue"
},
  "geometry": {"coordinates":[7.4518017769,46.9439506531],"type":"Point"}
}