{
  "type": "Feature",
  "properties": {
    "iso:country":"CH",
    "sg:address":"Oberbiel 38",
    "sg:city":"Reigoldswil",
    "sg:orig_category":"Non-Classified Establishments",
    "sg:postcode":"4418",
    "sg:province":"Basel-Landschaft",
    "wof:name":"Briggen-b\u00e4chler Ulrich",
    "wof:placetype":"venue"
},
  "geometry": {"coordinates":[7.6947999001,47.3924102783],"type":"Point"}
}