{
  "type": "Feature",
  "properties": {
    "iso:country":"CH",
    "sg:address":"Obere Hauptgasse 78 3600 Thun. Postfach 1246",
    "sg:city":"Thun",
    "sg:orig_category":"Kinos",
    "sg:postcode":"3601",
    "sg:province":"Bern",
    "wof:name":"Le Cin\u00e9ma Feuerwehrmagazin No 1 Kino, F\u00f6rderung Des Filmwesens Usw",
    "wof:placetype":"venue"
},
  "geometry": {"coordinates":[7.1084527969,46.9252319336],"type":"Point"}
}