{
  "type": "Feature",
  "properties": {
    "iso:country":"CH",
    "sg:address":"Murtenstrasse 342",
    "sg:city":"Bern",
    "sg:orig_category":"Instandhaltung U Reparatur von Automobilen",
    "sg:phone":"+41 31 991 36 24",
    "sg:postcode":"3027",
    "sg:province":"Bern",
    "wof:name":"Garage Daniel Rebmann Ag, Bern",
    "wof:placetype":"venue"
},
  "geometry": {"coordinates":[7.3845567703,46.9497871399],"type":"Point"}
}