{
  "type": "Feature",
  "properties": {
    "iso:country":"CH",
    "sg:address":"Neubergstr. 3",
    "sg:city":"Rothenhausen",
    "sg:classifiers":[
        {
            "category":"Manufacturing",
            "subcategory":"Tools & Machinery",
            "type":"Manufacturing & Wholesale Goods"
        }
    ],
    "sg:phone":"+41 71 622 33 40",
    "sg:postcode":"9565",
    "sg:province":"Thurgau",
    "sg:tags":[
        "metallurgy",
        "metalworking"
    ],
    "wof:name":"Innotool Ag",
    "wof:placetype":"venue"
},
  "geometry": {"coordinates":[9.1028413773,47.5484428406],"type":"Point"}
}