{
  "type": "Feature",
  "properties": {
    "iso:country":"CH",
    "sg:address":"Weiherweg 86 4054 Basel. Postfach 166",
    "sg:city":"Basel",
    "sg:orig_category":"Werbevermittlung Werbung",
    "sg:phone":"+41 18582179",
    "sg:postcode":"4011",
    "sg:province":"Basel-Stadt",
    "wof:name":"Hans Zesiger Werbeberatung",
    "wof:placetype":"venue"
},
  "geometry": {"coordinates":[8.4181509018,47.5681190491],"type":"Point"}
}