{
  "type": "Feature",
  "properties": {
    "iso:country":"CH",
    "sg:address":"Fineta",
    "sg:city":"Cordast",
    "sg:orig_category":"Hoch U Tiefbau",
    "sg:phone":"+41 26 684 19 61",
    "sg:postcode":"1792",
    "sg:province":"Fribourg",
    "wof:name":"Erwin Schmutz Bauunternehmung",
    "wof:placetype":"venue"
},
  "geometry": {"coordinates":[7.1526999474,46.8708152771],"type":"Point"}
}