{
  "type": "Feature",
  "properties": {
    "iso:country":"CH",
    "sg:address":"Simplon Rue Du 9",
    "sg:city":"Lausanne",
    "sg:classifiers":[
        {
            "category":"Professional",
            "subcategory":"Employment Agencies",
            "type":"Services"
        }
    ],
    "sg:phone":"+41 21 613 13 80",
    "sg:postcode":"1006",
    "sg:province":"Vaud",
    "sg:tags":[
        "personal",
        "u",
        "stellenvermittlung"
    ],
    "wof:name":"Pro-informatique & Quick Job Personnel S\u00e0rl",
    "wof:placetype":"venue"
},
  "geometry": {"coordinates":[6.6306900978,46.5156135559],"type":"Point"}
}