{
  "type": "Feature",
  "properties": {
    "iso:country":"CH",
    "sg:address":"Via Ai Ronchi",
    "sg:city":"Lumino",
    "sg:orig_category":"Allgemeiner Hoch U Tiefbau Strassenbau",
    "sg:phone":"+41 91 829 35 70",
    "sg:postcode":"6533",
    "sg:province":"Ticino",
    "wof:name":"Greuter Fondazioni Sa",
    "wof:placetype":"venue"
},
  "geometry": {"coordinates":[9.067508,46.233391],"type":"Point"}
}