{
  "type": "Feature",
  "properties": {
    "iso:country":"CH",
    "sg:address":"Schmiedenstrasse 13 8840 Einsiedeln. Postfach",
    "sg:city":"Einsiedeln",
    "sg:orig_category":"Erbringung von Dienstleistungen f\u00fcr Unternehmen",
    "sg:postcode":"8840",
    "sg:province":"Schwyz",
    "wof:name":"Limacher Innendekoration Ag",
    "wof:placetype":"venue"
},
  "geometry": {"coordinates":[8.7469625473,47.1277809143],"type":"Point"}
}