{
  "type": "Feature",
  "properties": {
    "iso:country":"CH",
    "sg:address":"Schulstrasse 2 7130 Ilanz. Postfach",
    "sg:city":"Ilanz",
    "sg:orig_category":"Elektroinstallation Vorbereitende Baustellenarbeiten",
    "sg:phone":"+41 91 690 16 91",
    "sg:postcode":"7130",
    "sg:province":"Graubunden",
    "wof:name":"Manuel Sagl Manutenzione Elettromeccanica",
    "wof:placetype":"venue"
},
  "geometry": {"coordinates":[9.0161905289,45.8540382385],"type":"Point"}
}