{
  "type": "Feature",
  "properties": {
    "iso:country":"CH",
    "sg:address":"Hauptstrasse 79",
    "sg:city":"Degersheim",
    "sg:orig_category":"Softwareentwicklung U beratung",
    "sg:postcode":"9113",
    "sg:province":"St. Gallen",
    "wof:name":"Gis Degersheim Ag",
    "wof:placetype":"venue"
},
  "geometry": {"coordinates":[9.1966772079,47.3726959229],"type":"Point"}
}