{
  "type": "Feature",
  "properties": {
    "iso:country":"CH",
    "sg:address":"Coppet-sur-conthey",
    "sg:city":"Conthey",
    "sg:classifiers":[
        {
            "category":"Restaurant",
            "type":"Food & Drink"
        }
    ],
    "sg:phone":"+41 27 346 19 03",
    "sg:postcode":"1964",
    "sg:province":"Valais",
    "wof:name":"Caf\u00e9 Beau-site",
    "wof:placetype":"venue"
},
  "geometry": {"coordinates":[7.2982797623,46.224319458],"type":"Point"}
}