{
  "type": "Feature",
  "properties": {
    "iso:country":"CH",
    "sg:address":"R\u00fcdel 6122 Menznau. Postfach",
    "sg:city":"Menznau",
    "sg:orig_category":"Herstellung von Metallkonstruktionen",
    "sg:phone":"+41 41 610 15 94",
    "sg:postcode":"6122",
    "sg:province":"Luzern",
    "wof:name":"Helfenstein Metallbau Ag",
    "wof:placetype":"venue"
},
  "geometry": {"coordinates":[8.365904808,46.9572486877],"type":"Point"}
}