{
  "type": "Feature",
  "properties": {
    "iso:country":"CH",
    "sg:address":"M\u00fchledorfstrasse 1/62 3018 Bern. Postfach",
    "sg:city":"Bern",
    "sg:orig_category":"Architektur U Ingenieurb\u00fcros",
    "sg:phone":"+41 21 943 64 16",
    "sg:postcode":"3018",
    "sg:province":"Bern",
    "wof:name":"Meldem Christian",
    "wof:placetype":"venue"
},
  "geometry": {"coordinates":[6.88343,46.470474],"type":"Point"}
}