{
  "type": "Feature",
  "properties": {
    "iso:country":"CH",
    "sg:address":"Dufourstrasse 131",
    "sg:city":"Z\u00fcrich",
    "sg:orig_category":"Non-Classified Establishments",
    "sg:postcode":"8008",
    "sg:province":"Z\u00fcrich",
    "wof:name":"Functionaldesign, Volker Marwik",
    "wof:placetype":"venue"
},
  "geometry": {"coordinates":[8.795167923,47.3651351929],"type":"Point"}
}