{
  "type": "Feature",
  "properties": {
    "addr:full":"Chemin Du Closel 18 Renens Vaud 1020",
    "addr:housenumber":"18",
    "addr:postcode":"1020",
    "addr:street":"Chemin Du Closel",
    "iso:country":"CH",
    "sg:address":"Chemin Du Closel 18",
    "sg:city":"Renens",
    "sg:classifiers":[
        {
            "category":"Banks & Credit Unions",
            "subcategory":"Bureau De Change",
            "type":"Services"
        }
    ],
    "sg:phone":"+41 22 797 55 77",
    "sg:postcode":"1020",
    "sg:province":"Vaud",
    "sg:tags":[
        "demolition"
    ],
    "wof:name":"Dmb Sa",
    "wof:placetype":"venue"
},
  "geometry": {"coordinates":[6.100399,46.205147],"type":"Point"}
}