{
  "type": "Feature",
  "properties": {
    "iso:country":"CH",
    "sg:address":"Engadinstrasse 2",
    "sg:city":"Chur",
    "sg:orig_category":"Non-Classified Establishments",
    "sg:postcode":"7000",
    "sg:province":"Graubunden",
    "wof:name":"Cb Holding Ag",
    "wof:placetype":"venue"
},
  "geometry": {"coordinates":[9.5286464691,46.8523788452],"type":"Point"}
}