{
  "type": "Feature",
  "properties": {
    "iso:country":"CH",
    "sg:address":"Im Hasen 73",
    "sg:city":"Lauerz",
    "sg:orig_category":"Softwareentwicklung U beratung",
    "sg:phone":"+41 26 668 17 12",
    "sg:postcode":"6424",
    "sg:province":"Schwyz",
    "wof:name":"Mce Services La Bioleyre, C. Mattern",
    "wof:placetype":"venue"
},
  "geometry": {"coordinates":[6.898774147,46.7189559937],"type":"Point"}
}