{
  "type": "Feature",
  "properties": {
    "iso:country":"CH",
    "sg:address":"Route Cantonale 266",
    "sg:city":"V\u00e9troz",
    "sg:orig_category":"Erdbewegungsarbeiten",
    "sg:phone":"+41 27 346 16 14",
    "sg:postcode":"1963",
    "sg:province":"Valais",
    "wof:name":"Lucien Gros Entreprise De Terrassement",
    "wof:placetype":"venue"
},
  "geometry": {"coordinates":[7.2615089417,46.2177810669],"type":"Point"}
}