{
  "type": "Feature",
  "properties": {
    "iso:country":"CH",
    "sg:address":"Sch\u00fctzenhalde 1070",
    "sg:city":"Wolfhalden",
    "sg:orig_category":"Wohnheime",
    "sg:phone":"+41 52 763 29 62",
    "sg:postcode":"9427",
    "sg:province":"Appenzell Ausserrhoden",
    "wof:name":"Genossenschaft Alterssiedlung M\u00fcllheim",
    "wof:placetype":"venue"
},
  "geometry": {"coordinates":[9.0002679825,47.6032028198],"type":"Point"}
}