{
  "type": "Feature",
  "properties": {
    "addr:full":"Winkelstrasse 6 9534 G\u00e4hwil. Postfach G\u00e4hwil St. Gallen 9534",
    "addr:housenumber":"6",
    "addr:postcode":"9534;9534",
    "addr:street":"Winkelstrasse;Postfach Gaehwil",
    "iso:country":"CH",
    "sg:address":"Winkelstrasse 6 9534 G\u00e4hwil. Postfach",
    "sg:city":"G\u00e4hwil",
    "sg:orig_category":"Bau von Strassen, Sportanlagen U Bahnverkehrsstrecken",
    "sg:postcode":"9534",
    "sg:province":"St. Gallen",
    "wof:name":"Strassenerhalt Brem",
    "wof:placetype":"venue"
},
  "geometry": {"coordinates":[9.001864,47.399231],"type":"Point"}
}