{
  "type": "Feature",
  "properties": {
    "iso:country":"CH",
    "sg:address":"Quadratscha 36",
    "sg:city":"Samedan",
    "sg:classifiers":[
        {
            "category":"Utilities",
            "subcategory":"Electric",
            "type":"Services"
        }
    ],
    "sg:phone":"+41 81 839 75 00",
    "sg:postcode":"7503",
    "sg:province":"Graubunden",
    "sg:tags":[
        "electricity",
        "electronic",
        "electrical",
        "equipment"
    ],
    "wof:name":"R\u00c4tia Energie Klosters Ag",
    "wof:placetype":"venue"
},
  "geometry": {"coordinates":[9.8766927719,46.5380592346],"type":"Point"}
}