{
  "type": "Feature",
  "properties": {
    "iso:country":"CH",
    "sg:address":"Eichgutweg 8",
    "sg:city":"M\u00fcnchenbuchsee",
    "sg:orig_category":"Unternehmensberatung",
    "sg:phone":"+41 31 869 67 10",
    "sg:postcode":"3053",
    "sg:province":"Bern",
    "wof:name":"Hascon Hasler Consulting",
    "wof:placetype":"venue"
},
  "geometry": {"coordinates":[7.4580340385,47.0110206604],"type":"Point"}
}