{
  "type": "Feature",
  "properties": {
    "iso:country":"CH",
    "sg:address":"Hochstrasse 68",
    "sg:city":"Basel",
    "sg:orig_category":"Geb\u00e4ude, Wohnungsreinigung Reinigungsgewerbe",
    "sg:phone":"+41 79 214 55 33",
    "sg:postcode":"4053",
    "sg:province":"Basel-Stadt",
    "wof:name":"First Cleaning Service Zigic & Ifrid Yagci",
    "wof:placetype":"venue"
},
  "geometry": {"coordinates":[7.5956788063,47.5442123413],"type":"Point"}
}