{
  "type": "Feature",
  "properties": {
    "iso:country":"CH",
    "sg:address":"Trischlistrasse 15",
    "sg:city":"Rorschach",
    "sg:orig_category":"Sonstiger Grosshandel",
    "sg:phone":"+41 71 841 25 25",
    "sg:postcode":"9400",
    "sg:province":"St. Gallen",
    "wof:name":"Hbt-technik Beutler Hans",
    "wof:placetype":"venue"
},
  "geometry": {"coordinates":[9.4889574051,47.4778518677],"type":"Point"}
}