{
  "type": "Feature",
  "properties": {
    "iso:country":"CH",
    "sg:address":"Aegertenweg 3",
    "sg:city":"Rickenbach-attikon",
    "sg:orig_category":"Herstellung von sonstigen Metallwaren Ingenieurb\u00fcros Maschinenbau",
    "sg:phone":"+41 52 338 23 60",
    "sg:postcode":"8544",
    "sg:province":"Z\u00fcrich",
    "wof:name":"Ridex Swiss Ag Maschinen U. Apparate F\u00fcr Die Verpackungs- U. Produktionsindustrie; Entwicklung, Produktion, Vertrieb Usw",
    "wof:placetype":"venue"
},
  "geometry": {"coordinates":[8.797454834,47.5358734131],"type":"Point"}
}