{
  "type": "Feature",
  "properties": {
    "iso:country":"CH",
    "sg:address":"Alpenstrasse 8",
    "sg:city":"Zug",
    "sg:orig_category":"Non-Classified Establishments",
    "sg:phone":"+41 41 710 23 92",
    "sg:postcode":"6300",
    "sg:province":"Zug",
    "wof:name":"Morgane Holding Ag",
    "wof:placetype":"venue"
},
  "geometry": {"coordinates":[8.5143871307,47.1716270447],"type":"Point"}
}