{
  "type": "Feature",
  "properties": {
    "iso:country":"CH",
    "sg:address":"Arosastrasse 8",
    "sg:city":"Z\u00fcrich",
    "sg:orig_category":"Betrieb U technische Hilfsdienste des Kultur U Unterhaltungswesens",
    "sg:phone":"+41 13820805",
    "sg:postcode":"8008",
    "sg:province":"Z\u00fcrich",
    "wof:name":"Fink About It",
    "wof:placetype":"venue"
},
  "geometry": {"coordinates":[8.560241,47.353783],"type":"Point"}
}