{
  "type": "Feature",
  "properties": {
    "iso:country":"CH",
    "sg:address":"Hardstrasse 41",
    "sg:city":"Wettingen",
    "sg:orig_category":"G\u00fcterbef\u00f6rderung im Strassenverkehr",
    "sg:postcode":"5430",
    "sg:province":"Aargau",
    "wof:name":"Kiva Atelier, Import & Export, Robellaz",
    "wof:placetype":"venue"
},
  "geometry": {"coordinates":[6.8607091904,46.4585838318],"type":"Point"}
}