{
  "type": "Feature",
  "properties": {
    "iso:country":"CH",
    "sg:address":"Rue Peillonnex 39 1225 Ch\u00eane-bourg Case Postale 138",
    "sg:city":"Ch\u00eane-bourg",
    "sg:orig_category":"Herstellung der Ausstattung von Uhren Herstellung von Reiseartikeln, Leder U Sattlerwaren",
    "sg:phone":"+41 22 348 44 66",
    "sg:postcode":"1225",
    "sg:province":"Gen\u00e8ve",
    "wof:name":"Bracelets Protexo Sa",
    "wof:placetype":"venue"
},
  "geometry": {"coordinates":[6.198813,46.195393],"type":"Point"}
}