{
  "type": "Feature",
  "properties": {
    "iso:country":"CH",
    "sg:address":"Birchstrasse 150",
    "sg:city":"Oberhasli",
    "sg:orig_category":"Nationale Postdienste",
    "sg:phone":"+41 18502340",
    "sg:postcode":"8156",
    "sg:province":"Z\u00fcrich",
    "wof:name":"Die Schweizerische Post",
    "wof:placetype":"venue"
},
  "geometry": {"coordinates":[8.4991941452,47.4673843384],"type":"Point"}
}