{
  "type": "Feature",
  "properties": {
    "iso:country":"CH",
    "sg:address":"Marktgasse 20",
    "sg:city":"Rheinfelden",
    "sg:orig_category":"Fotografische Ateliers Fotografisches Gewerbe U fotografische Laboratorien",
    "sg:phone":"+41 61 831 54 16",
    "sg:postcode":"4310",
    "sg:province":"Aargau",
    "wof:name":"Fotostudio Zimmermann",
    "wof:placetype":"venue"
},
  "geometry": {"coordinates":[7.7930188179,47.5553894043],"type":"Point"}
}