{
  "type": "Feature",
  "properties": {
    "iso:country":"CH",
    "sg:address":"Galeries Benjamin-constant 1 1000 Lausanne Case Postale",
    "sg:city":"Lausanne",
    "sg:orig_category":"Wirtschaftspr\u00fcfung, Steuerberatung U Treuhand",
    "sg:postcode":"1000",
    "sg:province":"Vaud",
    "wof:name":"Tyrena Sa Etudes Juridiques, Fiscales Et Financi\u00e8res",
    "wof:placetype":"venue"
},
  "geometry": {"coordinates":[6.6947751045,46.5545883179],"type":"Point"}
}