{
  "type": "Feature",
  "properties": {
    "iso:country":"CH",
    "sg:address":"Scheideggweg 17",
    "sg:city":"W\u00fcrenlingen",
    "sg:orig_category":"Unclassifiable Establishments",
    "sg:postcode":"5303",
    "sg:province":"Aargau",
    "wof:name":"Helix Business Soft Ag",
    "wof:placetype":"venue"
},
  "geometry": {"coordinates":[8.2500658035,47.5278701782],"type":"Point"}
}