{
  "type": "Feature",
  "properties": {
    "iso:country":"CH",
    "sg:address":"Arabienstrasse 5",
    "sg:city":"Basel",
    "sg:orig_category":"Technische, physikalische U chemische Untersuchung",
    "sg:phone":"+41 61 361 11 61",
    "sg:postcode":"4059",
    "sg:province":"Basel-Stadt",
    "wof:name":"Stiftung Wald-klima-umwelt",
    "wof:placetype":"venue"
},
  "geometry": {"coordinates":[7.5880942345,47.5323791504],"type":"Point"}
}