{
  "type": "Feature",
  "properties": {
    "iso:country":"CH",
    "sg:address":"Bellevuestrasse 21 3052 Zollikofen. Postfach",
    "sg:city":"Zollikofen",
    "sg:orig_category":"Softwareentwicklung U beratung",
    "sg:phone":"+41 31 910 40 40",
    "sg:postcode":"3052",
    "sg:province":"Bern",
    "wof:name":"Kagemaro Gmbh",
    "wof:placetype":"venue"
},
  "geometry": {"coordinates":[7.4534392357,46.991558075],"type":"Point"}
}