{
  "type": "Feature",
  "properties": {
    "iso:country":"CH",
    "sg:address":"Allmendstrasse 4 4512 Bellach. Postfach",
    "sg:city":"Bellach",
    "sg:orig_category":"Herstellung von Mess U Kontrollinstrumenten U vorrichtungen Mechanische Werkst\u00e4tten",
    "sg:phone":"+41 19361414",
    "sg:postcode":"4512",
    "sg:province":"Solothurn",
    "wof:name":"Kofag Josef Schmucki",
    "wof:placetype":"venue"
},
  "geometry": {"coordinates":[8.7589416504,47.3045120239],"type":"Point"}
}