{
  "type": "Feature",
  "properties": {
    "iso:country":"CH",
    "sg:address":"Im Glockenacker 53",
    "sg:city":"Z\u00fcrich",
    "sg:orig_category":"Elektroinstallation",
    "sg:phone":"+41 13819988",
    "sg:postcode":"8053",
    "sg:province":"Z\u00fcrich",
    "wof:name":"Heeb & Enzler Ag Alternativenergie",
    "wof:placetype":"venue"
},
  "geometry": {"coordinates":[8.6007499695,47.3603858948],"type":"Point"}
}