{
  "type": "Feature",
  "properties": {
    "addr:full":"Therwilerstrasse 40 4054 Basel. Postfach Basel Basel-Stadt 4051",
    "addr:housenumber":"40",
    "addr:postcode":"4054;4051",
    "addr:street":"Therwilerstrasse;Postfach",
    "iso:country":"CH",
    "sg:address":"Therwilerstrasse 40 4054 Basel. Postfach",
    "sg:city":"Basel",
    "sg:orig_category":"Architektur U Ingenieurb\u00fcros",
    "sg:phone":"+41 61 283 13 72",
    "sg:postcode":"4051",
    "sg:province":"Basel-Stadt",
    "wof:name":"Sim-x Ag",
    "wof:placetype":"venue"
},
  "geometry": {"coordinates":[7.576106,47.549557],"type":"Point"}
}