{
  "type": "Feature",
  "properties": {
    "iso:country":"CH",
    "sg:address":"Brunnmattstrasse 9",
    "sg:city":"Th\u00f6rishaus",
    "sg:orig_category":"Illumination Systems For Image Processing",
    "sg:phone":"+41 31 888 88 00",
    "sg:postcode":"3174",
    "sg:province":"Bern",
    "wof:name":"Qualimatest Sa",
    "wof:placetype":"venue"
},
  "geometry": {"coordinates":[7.348968029,46.8909988403],"type":"Point"}
}