{
  "type": "Feature",
  "properties": {
    "iso:country":"CH",
    "sg:address":"Sonnenbergstrasse 4",
    "sg:city":"Ennetbaden",
    "sg:classifiers":[
        {
            "category":"Shopping",
            "subcategory":"Clothing, Apparel, & Fashions",
            "type":"Retail Goods"
        }
    ],
    "sg:phone":"+41 56 221 33 10",
    "sg:postcode":"5408",
    "sg:province":"Aargau",
    "sg:tags":[
        "protective",
        "clothing"
    ],
    "wof:name":"Workware-factory Gmbh",
    "wof:placetype":"venue"
},
  "geometry": {"coordinates":[8.313782692,47.4790802002],"type":"Point"}
}