{
  "type": "Feature",
  "properties": {
    "iso:country":"CH",
    "sg:address":"Via Soldino 28",
    "sg:city":"Lugano",
    "sg:orig_category":"Architektur U Ingenieurb\u00fcros Unternehmensberatung",
    "sg:phone":"+41 91 967 52 25",
    "sg:postcode":"6900",
    "sg:province":"Ticino",
    "wof:name":"Tecno-tre, Consulenze Tecnico-commerciali Di Lic. Oec. Tresoldi Guido",
    "wof:placetype":"venue"
},
  "geometry": {"coordinates":[8.938683,46.007393],"type":"Point"}
}