{
  "type": "Feature",
  "properties": {
    "iso:country":"CH",
    "sg:address":"Luzernerstr. 8",
    "sg:city":"Meggen",
    "sg:classifiers":[
        {
            "category":"Banks & Credit Unions",
            "subcategory":"Bank",
            "type":"Services"
        }
    ],
    "sg:phone":"+41 41 377 44 88",
    "sg:postcode":"6045",
    "sg:province":"Luzern",
    "wof:name":"Luzerner Regiobank Ag",
    "wof:placetype":"venue"
},
  "geometry": {"coordinates":[8.37126,47.045692],"type":"Point"}
}