{
  "type": "Feature",
  "properties": {
    "iso:country":"CH",
    "sg:address":"Rue Centrale 7",
    "sg:city":"Avenches",
    "sg:classifiers":[
        {
            "category":"Insurance",
            "subcategory":"Insurance Agent",
            "type":"Services"
        }
    ],
    "sg:phone":"+41 26 675 32 86",
    "sg:postcode":"1580",
    "sg:province":"Vaud",
    "sg:tags":[
        "versicherungsagenturen",
        "-broker"
    ],
    "wof:name":"Winterthur Assurances Agence",
    "wof:placetype":"venue"
},
  "geometry": {"coordinates":[7.0416798592,46.8803596497],"type":"Point"}
}