{
  "type": "Feature",
  "properties": {
    "iso:country":"CH",
    "sg:address":"Industriestrasse 13",
    "sg:city":"Etziken",
    "sg:orig_category":"Zahntechnische Laboratorien",
    "sg:phone":"+41 32 682 24 27",
    "sg:postcode":"4554",
    "sg:province":"Solothurn",
    "wof:name":"Jindrich Kocnar Zahntechnisches Labor",
    "wof:placetype":"venue"
},
  "geometry": {"coordinates":[7.6371102333,47.1889610291],"type":"Point"}
}