{
  "type": "Feature",
  "properties": {
    "iso:country":"CH",
    "sg:address":"5056",
    "sg:city":"Attelwil",
    "sg:orig_category":"Primarschulen",
    "sg:postcode":"5056",
    "sg:province":"Aargau",
    "wof:name":"Primarschule",
    "wof:placetype":"venue"
},
  "geometry": {"coordinates":[8.0388698578,47.2628898621],"type":"Point"}
}