{
  "type": "Feature",
  "properties": {
    "iso:country":"CH",
    "sg:address":"Wildeggerstrasse 5",
    "sg:city":"Niederlenz",
    "sg:orig_category":"Herstellung von sonstigen elektrischen Ausr\u00fcstungen",
    "sg:phone":"+41 62 891 54 11",
    "sg:postcode":"5702",
    "sg:province":"Aargau",
    "wof:name":"W\u00fcrgler Handel Ag",
    "wof:placetype":"venue"
},
  "geometry": {"coordinates":[8.1732664108,47.405380249],"type":"Point"}
}