{
  "type": "Feature",
  "properties": {
    "iso:country":"CH",
    "sg:address":"Badenerstrasse 658",
    "sg:city":"Z\u00fcrich",
    "sg:orig_category":"Detailhandel mit elektrischen Haushalts-,Radio U Fernsehger\u00e4ten sowie Musikinstrumenten Elektroinsta",
    "sg:phone":"+41 61 811 60 61",
    "sg:postcode":"8048",
    "sg:province":"Z\u00fcrich",
    "wof:name":"Bt Boutique F\u00fcr Bild Und Ton Ag",
    "wof:placetype":"venue"
},
  "geometry": {"coordinates":[7.7198209763,47.5365142822],"type":"Point"}
}