{
  "type": "Feature",
  "properties": {
    "iso:country":"CH",
    "sg:address":"8301 Glattzentrum. Postfach 1441",
    "sg:city":"Glattzentrum",
    "sg:orig_category":"Wirtschaftspr\u00fcfung, Steuerberatung U Treuhand",
    "sg:phone":"+41 13214045",
    "sg:postcode":"8301",
    "sg:province":"Z\u00fcrich",
    "wof:name":"Hefina Treuhand Ag",
    "wof:placetype":"venue"
},
  "geometry": {"coordinates":[8.5951404572,47.4236717224],"type":"Point"}
}