{
  "type": "Feature",
  "properties": {
    "iso:country":"CH",
    "sg:address":"Via Balestra 4",
    "sg:city":"Lugano",
    "sg:orig_category":"Detailhandel mit Waren verschiedener Art, Hauptrichtung Nahrungsmittel Fleischverarbeitung",
    "sg:phone":"+41 71 245 90 05",
    "sg:postcode":"6900",
    "sg:province":"Ticino",
    "wof:name":"Wietlisbach Bruno, Salami-versand Ag",
    "wof:placetype":"venue"
},
  "geometry": {"coordinates":[9.401804924,47.4299125671],"type":"Point"}
}