{
  "type": "Feature",
  "properties": {
    "iso:country":"CH",
    "sg:address":"Pumpwerkstrasse 35",
    "sg:city":"M\u00fcnchenstein",
    "sg:orig_category":"Mechanische Werkst\u00e4tten Stahl U Leichtmetallbau",
    "sg:phone":"+41 61 411 11 16",
    "sg:postcode":"4142",
    "sg:province":"Basel-Landschaft",
    "wof:name":"Kueny Maschinenbau Ag",
    "wof:placetype":"venue"
},
  "geometry": {"coordinates":[7.6132998466,47.5146217346],"type":"Point"}
}