{
  "type": "Feature",
  "properties": {
    "iso:country":"CH",
    "sg:address":"Alpenrosenstrasse 5",
    "sg:city":"Kreuzlingen",
    "sg:orig_category":"Landschaftsplanungsb\u00fcros U Gartenarchitekturb\u00fcros",
    "sg:phone":"+41 71 672 65 55",
    "sg:postcode":"8280",
    "sg:province":"Thurgau",
    "wof:name":"Mwg Gartenarchitektur Walter Merk Ag",
    "wof:placetype":"venue"
},
  "geometry": {"coordinates":[9.168047905,47.6489181519],"type":"Point"}
}