{
  "type": "Feature",
  "properties": {
    "iso:country":"CH",
    "sg:address":"Gartenstrasse 1",
    "sg:city":"Bern",
    "sg:orig_category":"Pensionskassen",
    "sg:phone":"+41 31 382 19 00",
    "sg:postcode":"3007",
    "sg:province":"Bern",
    "wof:name":"Kadervorsorgestiftung Uiag",
    "wof:placetype":"venue"
},
  "geometry": {"coordinates":[7.4293007851,46.9450836182],"type":"Point"}
}