{
  "type": "Feature",
  "properties": {
    "iso:country":"CH",
    "sg:address":"Kasernenstrasse 83",
    "sg:city":"Chur",
    "sg:orig_category":"Detailhandel mit Brot, Back U S\u00fcsswaren",
    "sg:postcode":"7000",
    "sg:province":"Graubunden",
    "wof:name":"Stoffel Ph.",
    "wof:placetype":"venue"
},
  "geometry": {"coordinates":[9.520578,46.846962],"type":"Point"}
}