{
  "type": "Feature",
  "properties": {
    "iso:country":"CH",
    "sg:address":"Rheinstrasse 4 7320 Sargans. Postfach 240",
    "sg:city":"Sargans",
    "sg:orig_category":"Feuerl\u00f6schapparate Herstellung Feuerwehr",
    "sg:phone":"+41 79611401862835",
    "sg:postcode":"7320",
    "sg:province":"St. Gallen",
    "wof:name":"Zentex Brandschutz Ag, Sargans L\u00f6schanlagen",
    "wof:placetype":"venue"
},
  "geometry": {"coordinates":[9.4411220551,47.0481681824],"type":"Point"}
}