{
  "type": "Feature",
  "properties": {
    "iso:country":"CH",
    "sg:address":"Bernstrasse 3",
    "sg:city":"Thun",
    "sg:orig_category":"Detailhandel mit Waren verschiedener Art in Verkaufsr\u00e4umen Fachdetailhandel mit Nahrungsmitteln, Get",
    "sg:phone":"+41 33 222 01 23",
    "sg:postcode":"3600",
    "sg:province":"Bern",
    "wof:name":"Otto's Ag",
    "wof:placetype":"venue"
},
  "geometry": {"coordinates":[7.6284790039,46.7622261047],"type":"Point"}
}