{
  "type": "Feature",
  "properties": {
    "iso:country":"CH",
    "sg:address":"Feithieren",
    "sg:city":"Susten",
    "sg:orig_category":"Sportvereine Turnen",
    "sg:phone":"+41 27 473 27 64",
    "sg:postcode":"3952",
    "sg:province":"Valais",
    "wof:name":"Turnverein Stv Leuk-susten",
    "wof:placetype":"venue"
},
  "geometry": {"coordinates":[7.6449799538,46.3076095581],"type":"Point"}
}