{
  "type": "Feature",
  "properties": {
    "iso:country":"CH",
    "sg:address":"Friesencham 3",
    "sg:city":"Cham",
    "sg:orig_category":"Verwertung von Milch",
    "sg:postcode":"6330",
    "sg:province":"Zug",
    "wof:name":"K\u00e4sereigenossenschaft Cham",
    "wof:placetype":"venue"
},
  "geometry": {"coordinates":[8.4483699799,47.1966094971],"type":"Point"}
}