{
  "type": "Feature",
  "properties": {
    "iso:country":"CH",
    "sg:address":"Hauptstrasse 1151",
    "sg:city":"Unterwasser",
    "sg:orig_category":"Bauspenglerei Sanit\u00e4rinstallation",
    "sg:phone":"+41 79 445 55 20",
    "sg:postcode":"9657",
    "sg:province":"St. Gallen",
    "wof:name":"Urs Lindenlaub Sanit\u00e4re Anlagen & Spenglerei",
    "wof:placetype":"venue"
},
  "geometry": {"coordinates":[9.305977,47.196972],"type":"Point"}
}