{
  "type": "Feature",
  "properties": {
    "iso:country":"CH",
    "sg:address":"Hubenstrasse 14",
    "sg:city":"Z\u00fcrich",
    "sg:orig_category":"Reinigungsgewerbe",
    "sg:phone":"+41 13210612",
    "sg:postcode":"8057",
    "sg:province":"Z\u00fcrich",
    "wof:name":"F\u00e4h-garcia Gladys",
    "wof:placetype":"venue"
},
  "geometry": {"coordinates":[8.5584030151,47.40366745],"type":"Point"}
}