{
  "type": "Feature",
  "properties": {
    "iso:country":"CH",
    "sg:address":"Ueberlandstrasse 193",
    "sg:city":"D\u00fcbendorf",
    "sg:orig_category":"Instandhaltung U Reparatur von Automobilen",
    "sg:phone":"+41 18216363",
    "sg:postcode":"8600",
    "sg:province":"Z\u00fcrich",
    "wof:name":"Tresch Automobile Ag",
    "wof:placetype":"venue"
},
  "geometry": {"coordinates":[8.6204500198,47.4011917114],"type":"Point"}
}