{
  "type": "Feature",
  "properties": {
    "iso:country":"CH",
    "sg:address":"Mythenquai 26 8002 Z\u00fcrich. Postfach",
    "sg:city":"Z\u00fcrich",
    "sg:orig_category":"Fachdetailhandel in Verkaufsr\u00e4umen",
    "sg:postcode":"8001",
    "sg:province":"Z\u00fcrich",
    "wof:name":"Vecovit Ag Veterin\u00e4rprodukte, Pharmazeut Pr\u00e4parate Usw; Vertrieb, Verkauf",
    "wof:placetype":"venue"
},
  "geometry": {"coordinates":[8.53515625,47.360622406],"type":"Point"}
}