{
  "type": "Feature",
  "properties": {
    "iso:country":"CH",
    "sg:address":"Feldh\u00fcsli",
    "sg:city":"Trub",
    "sg:orig_category":"Allgemeiner Hochbau Strassenbau",
    "sg:phone":"+41 34 495 53 73",
    "sg:postcode":"3556",
    "sg:province":"Bern",
    "wof:name":"Schwitter Bau Ag Trub",
    "wof:placetype":"venue"
},
  "geometry": {"coordinates":[7.876793,46.940765],"type":"Point"}
}