{
  "type": "Feature",
  "properties": {
    "iso:country":"CH",
    "sg:address":"Bahnhofstrasse 9 2540 Grenchen. Postfach 3536",
    "sg:city":"Grenchen",
    "sg:orig_category":"Herstellung von Uhren",
    "sg:phone":"+41 32 913 65 32",
    "sg:postcode":"2540",
    "sg:province":"Solothurn",
    "wof:name":"Chronolyre S\u00e0rl",
    "wof:placetype":"venue"
},
  "geometry": {"coordinates":[6.8190631866,47.0987548828],"type":"Point"}
}