{
  "type": "Feature",
  "properties": {
    "iso:country":"CH",
    "sg:address":"Rathausstrasse",
    "sg:city":"Leukerbad",
    "sg:orig_category":"Grosshandel mit Getr\u00e4nken",
    "sg:phone":"+41 27 470 10 29",
    "sg:postcode":"3954",
    "sg:province":"Valais",
    "wof:name":"Badner Keller Ag",
    "wof:placetype":"venue"
},
  "geometry": {"coordinates":[7.6267747879,46.379108429],"type":"Point"}
}