{
  "type": "Feature",
  "properties": {
    "iso:country":"CH",
    "sg:address":"Haus Pick",
    "sg:city":"Wengen",
    "sg:orig_category":"Erbringung von Dienstleistungen f\u00fcr Unternehmen",
    "sg:phone":"+41 79 697 46 07",
    "sg:postcode":"3823",
    "sg:province":"Bern",
    "wof:name":"Jaggi Dekorationen",
    "wof:placetype":"venue"
},
  "geometry": {"coordinates":[7.921599865,46.6051940918],"type":"Point"}
}