{
  "type": "Feature",
  "properties": {
    "iso:country":"CH",
    "sg:address":"Pr\u00e9-grassey",
    "sg:city":"Oron-la-ville",
    "sg:orig_category":"Tierarztpraxis",
    "sg:phone":"+41 21 907 86 31",
    "sg:postcode":"1610",
    "sg:province":"Vaud",
    "wof:name":"Dr M\u00e9d. V\u00e9t. Jacques Gloor M\u00e9decin V\u00e9t\u00e9rinaire",
    "wof:placetype":"venue"
},
  "geometry": {"coordinates":[6.8285551071,46.5676307678],"type":"Point"}
}