{
  "type": "Feature",
  "properties": {
    "iso:country":"CH",
    "sg:address":"Widum 97",
    "sg:city":"Schellenberg",
    "sg:orig_category":"Mechanische Werkst\u00e4tten",
    "sg:phone":"+423 373 19 38",
    "sg:postcode":"9488",
    "wof:name":"Batliner Ag Werkzeugsch\u00e4rferei",
    "wof:placetype":"venue"
},
  "geometry": {"coordinates":[9.5375099182,47.2286186218],"type":"Point"}
}