{
  "type": "Feature",
  "properties": {
    "iso:country":"CH",
    "sg:address":"Maulbeerstrasse 31",
    "sg:city":"Basel",
    "sg:orig_category":"Detailhandel mit Waren verschiedener Art, Hauptrichtung Nahrungsmittel",
    "sg:phone":"+41 61 691 80 40",
    "sg:postcode":"4058",
    "sg:province":"Basel-Stadt",
    "wof:name":"Coop Basel Mattenstrasse",
    "wof:placetype":"venue"
},
  "geometry": {"coordinates":[7.6011548042,47.5673332214],"type":"Point"}
}