{
  "type": "Feature",
  "properties": {
    "iso:country":"CH",
    "sg:address":"Moosstrasse 2",
    "sg:city":"Hochdorf",
    "sg:orig_category":"Sonstige mit der Informatik verbundene T\u00e4tigkeiten",
    "sg:phone":"+41 41 910 51 15",
    "sg:postcode":"6280",
    "sg:province":"Luzern",
    "wof:name":"Ctw Computer Technologies Werder",
    "wof:placetype":"venue"
},
  "geometry": {"coordinates":[8.2915487289,47.1700019836],"type":"Point"}
}