{
  "type": "Feature",
  "properties": {
    "iso:country":"CH",
    "sg:address":"Dorfstrasse 41",
    "sg:city":"Buchrain",
    "sg:orig_category":"Abwasserreinigung, Abfallbeseitigung U sonstige Entsorgung",
    "sg:postcode":"6033",
    "sg:province":"Luzern",
    "wof:name":"M. L\u00fcchinger Ag",
    "wof:placetype":"venue"
},
  "geometry": {"coordinates":[8.349758,47.104305],"type":"Point"}
}