{
  "type": "Feature",
  "properties": {
    "iso:country":"CH",
    "sg:address":"Schulgasse 249",
    "sg:city":"Zetzwil",
    "sg:orig_category":"Herstellung von Radio U Fernsehger\u00e4ten sowie phono U videotechnischen Ger\u00e4ten",
    "sg:phone":"+41 62 773 81 55",
    "sg:postcode":"5732",
    "sg:province":"Aargau",
    "wof:name":"Com-tech",
    "wof:placetype":"venue"
},
  "geometry": {"coordinates":[8.1518468857,47.2852935791],"type":"Point"}
}