{
  "type": "Feature",
  "properties": {
    "addr:full":"Rue Hoffmann 11 Gen\u00e8ve Gen\u00e8ve 1202",
    "addr:housenumber":"11",
    "addr:postcode":"1202",
    "addr:street":"Rue Hoffmann",
    "iso:country":"CH",
    "sg:address":"Rue Hoffmann 11",
    "sg:city":"Gen\u00e8ve",
    "sg:orig_category":"Detailhandel mit Beleuchtungs U Haushaltsgegenst\u00e4nden Herstellung von K\u00fcchenm\u00f6beln",
    "sg:phone":"+41 22 733 21 23",
    "sg:postcode":"1202",
    "sg:province":"Gen\u00e8ve",
    "wof:name":"Simonin Electro-menagers Sa",
    "wof:placetype":"venue"
},
  "geometry": {"coordinates":[6.130237,46.215359],"type":"Point"}
}