{
  "type": "Feature",
  "properties": {
    "iso:country":"CH",
    "sg:address":"H\u00f4tel Du Connelier",
    "sg:city":"Bulle",
    "sg:orig_category":"Sonstiges Versicherungsgewerbe",
    "sg:postcode":"1630",
    "sg:province":"Fribourg",
    "wof:name":"Soci\u00e9t\u00e9 De Secours Mutuels De La Gruy\u00e8re",
    "wof:placetype":"venue"
},
  "geometry": {"coordinates":[7.0573811531,46.6186027527],"type":"Point"}
}