{
  "type": "Feature",
  "properties": {
    "iso:country":"CH",
    "sg:address":"Kauffmannweg 8",
    "sg:city":"Luzern",
    "sg:orig_category":"Unclassifiable Establishments",
    "sg:postcode":"6003",
    "sg:province":"Luzern",
    "wof:name":"Interior Luzern Ag",
    "wof:placetype":"venue"
},
  "geometry": {"coordinates":[8.305521965,47.0473823547],"type":"Point"}
}