{
  "type": "Feature",
  "properties": {
    "iso:country":"CH",
    "sg:address":"2613",
    "sg:city":"Villeret",
    "sg:orig_category":"Schulpflegen",
    "sg:phone":"+41 32 941 43 81",
    "sg:postcode":"2613",
    "sg:province":"Bern",
    "wof:name":"Commission Scolaire De L'ecole Primaire",
    "wof:placetype":"venue"
},
  "geometry": {"coordinates":[7.0182671547,47.1577110291],"type":"Point"}
}