{
  "type": "Feature",
  "properties": {
    "iso:country":"CH",
    "sg:address":"Schmiedenstrasse 6",
    "sg:city":"Einsiedeln",
    "sg:classifiers":[
        {
            "category":"Restaurant",
            "type":"Food & Drink"
        }
    ],
    "sg:phone":"+41 55 412 26 51",
    "sg:postcode":"8840",
    "sg:province":"Schwyz",
    "wof:name":"Restaurant Hofstatt",
    "wof:placetype":"venue"
},
  "geometry": {"coordinates":[8.7465419769,47.1277732849],"type":"Point"}
}