{
  "type": "Feature",
  "properties": {
    "iso:country":"CH",
    "sg:address":"Postgasshalde 41",
    "sg:city":"Bern",
    "sg:orig_category":"Unternehmensberatung",
    "sg:postcode":"3011",
    "sg:province":"Bern",
    "wof:name":"Rytz Und Partner Gmbh",
    "wof:placetype":"venue"
},
  "geometry": {"coordinates":[7.453163147,46.9488983154],"type":"Point"}
}