{
  "type": "Feature",
  "properties": {
    "iso:country":"CH",
    "sg:address":"Weingarten 309",
    "sg:city":"G\u00fcnsberg",
    "sg:orig_category":"Elektroinstallation",
    "sg:phone":"+41 32 637 21 13",
    "sg:postcode":"4524",
    "sg:province":"Solothurn",
    "wof:name":"Ryf Rudolf",
    "wof:placetype":"venue"
},
  "geometry": {"coordinates":[7.5812458992,47.2536888123],"type":"Point"}
}