{
  "type": "Feature",
  "properties": {
    "iso:country":"CH",
    "sg:address":"Rosenstrasse 3 3800 Interlaken. Postfach 291",
    "sg:city":"Interlaken",
    "sg:orig_category":"Allgemeiner Hoch U Tiefbau",
    "sg:phone":"+41 33 822 88 44",
    "sg:postcode":"3800",
    "sg:province":"Bern",
    "wof:name":"Realplan Generalbauunternehmungs Ag",
    "wof:placetype":"venue"
},
  "geometry": {"coordinates":[7.85512,46.684254],"type":"Point"}
}