{
  "type": "Feature",
  "properties": {
    "iso:country":"CH",
    "sg:address":"Reichsgasse 61",
    "sg:city":"Chur",
    "sg:orig_category":"Grosshandel mit B\u00fcromaschinen Grosshandel mit Datenverarbeitungsger\u00e4ten",
    "sg:phone":"+41 22 343 41 88",
    "sg:postcode":"7000",
    "sg:province":"Graubunden",
    "wof:name":"Sicam Sa",
    "wof:placetype":"venue"
},
  "geometry": {"coordinates":[6.1286759377,46.1855392456],"type":"Point"}
}