{
  "type": "Feature",
  "properties": {
    "iso:country":"CH",
    "sg:address":"Kalabinth 29",
    "sg:city":"Speicher",
    "sg:orig_category":"Bauspenglerei Sanit\u00e4rinstallation",
    "sg:phone":"+41 71 344 16 84",
    "sg:postcode":"9042",
    "sg:province":"Appenzell Ausserrhoden",
    "wof:name":"Wild Sanit\u00e4r/spenglerei Ag",
    "wof:placetype":"venue"
},
  "geometry": {"coordinates":[9.44095,47.415272],"type":"Point"}
}