{
  "type": "Feature",
  "properties": {
    "iso:country":"CH",
    "sg:address":"Im Stieg 12",
    "sg:city":"Adliswil",
    "sg:orig_category":"Unclassifiable Establishments",
    "sg:postcode":"8134",
    "sg:province":"Z\u00fcrich",
    "wof:name":"Ruf Identity Consulting",
    "wof:placetype":"venue"
},
  "geometry": {"coordinates":[8.5182914734,47.3076286316],"type":"Point"}
}