{
  "type": "Feature",
  "properties": {
    "iso:country":"CH",
    "sg:address":"Bahnhofstrasse 16",
    "sg:city":"Interlaken",
    "sg:orig_category":"RESTAURANTS: TEA-ROOMS",
    "sg:phone":"+41 33 822 31 31",
    "sg:postcode":"3800",
    "sg:province":"Bern",
    "wof:name":"Restaurant Bernerhof Gmbh",
    "wof:placetype":"venue"
},
  "geometry": {"coordinates":[7.8523201942,46.6839942932],"type":"Point"}
}