{
  "type": "Feature",
  "properties": {
    "iso:country":"CH",
    "sg:address":"Rest. Grappe D'or 1880 Bex. Postfach",
    "sg:city":"Bex",
    "sg:classifiers":[
        {
            "category":"Travel",
            "subcategory":"Hotels & Motels",
            "type":"Entertainment"
        }
    ],
    "sg:postcode":"1880",
    "sg:province":"Vaud",
    "sg:tags":[
        "hotels",
        "mit",
        "restaurant"
    ],
    "wof:name":"Ghaber Amar",
    "wof:placetype":"venue"
},
  "geometry": {"coordinates":[7.0156798363,46.2502593994],"type":"Point"}
}