{
  "type": "Feature",
  "properties": {
    "iso:country":"CH",
    "sg:address":"Bahnhofstrasse 32",
    "sg:city":"N\u00e4fels",
    "sg:orig_category":"R\u00fcckgewinnung U Vorbereitung f\u00fcr die Wiederverwertung Recycling von nichtmetallischen Altmaterialien",
    "sg:postcode":"8752",
    "sg:province":"Glarus",
    "wof:name":"M\u00fcller Sonja - Recontra",
    "wof:placetype":"venue"
},
  "geometry": {"coordinates":[8.8698387146,47.6595687866],"type":"Point"}
}