{
  "type": "Feature",
  "properties": {
    "iso:country":"CH",
    "sg:address":"Thomas Bornhauserstrasse 14 8570 Weinfelden. Postfach 322",
    "sg:city":"Weinfelden",
    "sg:orig_category":"Wirtschaftsverb\u00e4nde Gewerbeverb\u00e4nde/-vereine",
    "sg:phone":"+41 32 722 15 30",
    "sg:postcode":"8570",
    "sg:province":"Thurgau",
    "wof:name":"Union Cant.neuch\u00e2teloise Des Arts & M\u00e9tiers",
    "wof:placetype":"venue"
},
  "geometry": {"coordinates":[6.9331688881,46.9946403503],"type":"Point"}
}