{
  "type": "Feature",
  "properties": {
    "iso:country":"CH",
    "sg:address":"3771",
    "sg:city":"Blankenburg",
    "sg:orig_category":"Detailhandel mit Milcherzeugnissen U Eiern Verarbeitung von Milch",
    "sg:postcode":"3771",
    "sg:province":"Bern",
    "wof:name":"Milchverwertungsgenossenschaft Zweisimmen Walter Schl\u00e4ppi",
    "wof:placetype":"venue"
},
  "geometry": {"coordinates":[7.3881897926,46.5409088135],"type":"Point"}
}