{
  "type": "Feature",
  "properties": {
    "iso:country":"CH",
    "sg:address":"Sonnenhof 13 8117 F\u00e4llanden. Postfach",
    "sg:city":"Benglen",
    "sg:orig_category":"Grosshandel mit Erzen U Metallen",
    "sg:postcode":"8121",
    "sg:province":"Z\u00fcrich",
    "wof:name":"Aurum Edelmetallverwertungsgesellschaft Gelewski W. & Classen M.",
    "wof:placetype":"venue"
},
  "geometry": {"coordinates":[8.6370296478,47.3588447571],"type":"Point"}
}