{
  "type": "Feature",
  "properties": {
    "iso:country":"CH",
    "sg:address":"Rue Du R\u00e9servoir 2a",
    "sg:city":"Peseux",
    "sg:orig_category":"Spindles For Machine And Apparatus Construction",
    "sg:phone":"+41 32 731 19 57",
    "sg:postcode":"2034",
    "sg:province":"Neuch\u00e2tel",
    "wof:name":"Baudin Fr\u00e8res",
    "wof:placetype":"venue"
},
  "geometry": {"coordinates":[6.8888912201,46.9902915955],"type":"Point"}
}