{
  "type": "Feature",
  "properties": {
    "iso:country":"CH",
    "sg:address":"Via Angelo Maspoli 12",
    "sg:city":"Mendrisio",
    "sg:orig_category":"Verarbeitung von Tee U Kaffee",
    "sg:phone":"+41 91 646 39 06",
    "sg:postcode":"6850",
    "sg:province":"Ticino",
    "wof:name":"Sacca Societ\u00e0 Anonima Caff\u00e9 Coloniali & Alimentari",
    "wof:placetype":"venue"
},
  "geometry": {"coordinates":[8.9787416458,45.8741607666],"type":"Point"}
}