{
  "type": "Feature",
  "properties": {
    "iso:country":"CH",
    "sg:address":"Via Delle Scuole",
    "sg:city":"Tenero",
    "sg:orig_category":"Handelsvermittlung U Grosshandel R\u00fcckgewinnung U Vorbereitung f\u00fcr die Wiederverwertung Recycling",
    "sg:phone":"+41 32 751 38 33",
    "sg:postcode":"6598",
    "sg:province":"Ticino",
    "wof:name":"Martin Roten",
    "wof:placetype":"venue"
},
  "geometry": {"coordinates":[7.1012649536,47.0693397522],"type":"Point"}
}