{
  "type": "Feature",
  "properties": {
    "iso:country":"CH",
    "sg:address":"Graub\u00fchlstrasse 9",
    "sg:city":"Mumpf",
    "sg:orig_category":"G\u00fcterbef\u00f6rderung im Strassenverkehr",
    "sg:phone":"+41 62 873 33 02",
    "sg:postcode":"4322",
    "sg:province":"Aargau",
    "wof:name":"Leo Dietz Transporte",
    "wof:placetype":"venue"
},
  "geometry": {"coordinates":[7.9193201065,47.5448112488],"type":"Point"}
}