{
  "type": "Feature",
  "properties": {
    "iso:country":"CH",
    "sg:address":"Hauptstrasse 8",
    "sg:city":"Rottenschwil",
    "sg:orig_category":"Interessenvertretungen",
    "sg:phone":"+41 56 634 21 41",
    "sg:postcode":"8919",
    "sg:province":"Aargau",
    "wof:name":"Stiftung Reusstal",
    "wof:placetype":"venue"
},
  "geometry": {"coordinates":[8.3680858612,47.317199707],"type":"Point"}
}