{
  "type": "Feature",
  "properties": {
    "iso:country":"CH",
    "sg:address":"Obertilistrasse 23",
    "sg:city":"Adliswil",
    "sg:orig_category":"Vorschulen, Kinderg\u00e4rten",
    "sg:phone":"+41 17109619",
    "sg:postcode":"8134",
    "sg:province":"Z\u00fcrich",
    "wof:name":"Kindergarten Neugut",
    "wof:placetype":"venue"
},
  "geometry": {"coordinates":[8.5296697617,47.3070144653],"type":"Point"}
}