{
  "type": "Feature",
  "properties": {
    "iso:country":"CH",
    "sg:address":"Via Bonzanigo 6 6500 Bellinzona. Postfach Caselle Postale 1570",
    "sg:city":"Bellinzona",
    "sg:orig_category":"Verlagsgewerbe Zeitungsverlag",
    "sg:phone":"+41 91 825 12 45",
    "sg:postcode":"6501",
    "sg:province":"Ticino",
    "wof:name":"Popolo & Libert\u00e0 Edizioni Sa",
    "wof:placetype":"venue"
},
  "geometry": {"coordinates":[9.0215072632,46.1908340454],"type":"Point"}
}