{
  "type": "Feature",
  "properties": {
    "iso:country":"CH",
    "sg:address":"Drossa 6809 Medeglia. Postfach",
    "sg:city":"Medeglia",
    "sg:orig_category":"Maler U Glasergewerbe",
    "sg:postcode":"6809",
    "sg:province":"Ticino",
    "wof:name":"Zucchetti Alain",
    "wof:placetype":"venue"
},
  "geometry": {"coordinates":[8.9636383057,46.1168937683],"type":"Point"}
}