{
  "type": "Feature",
  "properties": {
    "iso:country":"CH",
    "sg:address":"Optingenstrasse 54 3013 Bern. Postfach 7635",
    "sg:city":"Bern",
    "sg:orig_category":"Fotografische Ateliers Korrespondenz U Nachrichtenb\u00fcros, selbst\u00e4ndige Journalisten",
    "sg:phone":"+41 31 333 50 33",
    "sg:postcode":"3001",
    "sg:province":"Bern",
    "wof:name":"Puncto Presseb\u00fcro, Sch\u00e4ublin, Haller + Co. Inhaberin Sch\u00e4ublin Elisabeth",
    "wof:placetype":"venue"
},
  "geometry": {"coordinates":[7.4509019852,46.95677948],"type":"Point"}
}