{
  "type": "Feature",
  "properties": {
    "iso:country":"CH",
    "sg:address":"Schwertgasse 11",
    "sg:city":"Zurzach",
    "sg:orig_category":"Detailhandel mit elektrischen Haushaltsger\u00e4ten Filmverleih U Videoprogrammanbieter",
    "sg:phone":"+41 56 249 26 66",
    "sg:postcode":"5330",
    "sg:province":"Aargau",
    "wof:name":"Fischer Arnold Gmbh",
    "wof:placetype":"venue"
},
  "geometry": {"coordinates":[8.2947473526,47.5871810913],"type":"Point"}
}