{
  "type": "Feature",
  "properties": {
    "addr:full":"Lingwurmstrasse 35 Brig Valais 3900",
    "addr:housenumber":"35",
    "addr:postcode":"3900",
    "addr:street":"Lingwurmstrasse",
    "iso:country":"CH",
    "sg:address":"Lingwurmstrasse 35",
    "sg:city":"Brig",
    "sg:orig_category":"Architektur U Ingenieurb\u00fcros",
    "sg:phone":"+41 27 924 20 10",
    "sg:postcode":"3900",
    "sg:province":"Valais",
    "wof:name":"Renato Demostene Ingenieurb\u00fcro",
    "wof:placetype":"venue"
},
  "geometry": {"coordinates":[8.002429,46.310562],"type":"Point"}
}