{
  "type": "Feature",
  "properties": {
    "iso:country":"CH",
    "sg:address":"Route De Crissier 6",
    "sg:city":"Bussigny-lausanne",
    "sg:orig_category":"Tankstellen",
    "sg:phone":"+41 21 701 14 41",
    "sg:postcode":"1030",
    "sg:province":"Vaud",
    "wof:name":"Bp (switzerland)",
    "wof:placetype":"venue"
},
  "geometry": {"coordinates":[6.5638928413,46.5493965149],"type":"Point"}
}