{
  "type": "Feature",
  "properties": {
    "iso:country":"CH",
    "sg:address":"Felsenaustrasse 2 8704 Herrliberg. Postfach",
    "sg:city":"Herrliberg",
    "sg:orig_category":"Herstellung von Schmuck, Gold U Silberschmiedwaren",
    "sg:phone":"+41 19150242",
    "sg:postcode":"8704",
    "sg:province":"Z\u00fcrich",
    "wof:name":"Gold Und Silberschmiedeatelier Robert Und Imelda Steinlin",
    "wof:placetype":"venue"
},
  "geometry": {"coordinates":[8.6076068878,47.2891082764],"type":"Point"}
}