{
  "type": "Feature",
  "properties": {
    "iso:country":"CH",
    "sg:address":"Dorfplatz 9056 Gais. Postfach",
    "sg:city":"Gais",
    "sg:classifiers":[
        {
            "category":"Travel",
            "subcategory":"Hotels & Motels",
            "type":"Entertainment"
        }
    ],
    "sg:phone":"+41 71 793 12 26",
    "sg:postcode":"9056",
    "sg:province":"Appenzell Ausserrhoden",
    "sg:tags":[
        "hotels",
        "mit",
        "restaurant"
    ],
    "wof:name":"Colette Kreckelbergh-portner",
    "wof:placetype":"venue"
},
  "geometry": {"coordinates":[9.4541692734,47.3623886108],"type":"Point"}
}