{
  "type": "Feature",
  "properties": {
    "addr:full":"Bahnhofstrasse 3 Hitzkirch Luzern 6285",
    "addr:housenumber":"3",
    "addr:postcode":"6285",
    "addr:street":"Bahnhofstrasse",
    "iso:country":"CH",
    "sg:address":"Bahnhofstrasse 3",
    "sg:city":"Hitzkirch",
    "sg:orig_category":"Arztpraxen",
    "sg:phone":"+41 41 917 12 27",
    "sg:postcode":"6285",
    "sg:province":"Luzern",
    "wof:name":"Dr.med.j\u00f6rg Jans Arzt F.allgemeine Medizin Fmh",
    "wof:placetype":"venue"
},
  "geometry": {"coordinates":[8.262396,47.224689],"type":"Point"}
}