{
  "type": "Feature",
  "properties": {
    "iso:country":"CH",
    "sg:address":"Elisabethenstrasse 22 4051 Basel. Postfach",
    "sg:city":"Basel",
    "sg:orig_category":"Arbeitnehmerverb\u00e4nde",
    "sg:phone":"+41 61 205 93 40",
    "sg:postcode":"4010",
    "sg:province":"Basel-Stadt",
    "wof:name":"Gewerkschaft Industrie,gewerbe & Dienstleist.smuv,sekt.basel",
    "wof:placetype":"venue"
},
  "geometry": {"coordinates":[7.590897,47.551479],"type":"Point"}
}