{
  "type": "Feature",
  "properties": {
    "iso:country":"CH",
    "sg:address":"Bahnhofstrasse 1 3000 Bern. Postfach",
    "sg:city":"Bern",
    "sg:orig_category":"Herstellung von Radio U Fernsehger\u00e4ten sowie phono U videotechnischen Ger\u00e4ten",
    "sg:postcode":"3000",
    "sg:province":"Bern",
    "wof:name":"Correctton Gmbh H\u00f6rger\u00e4teakustik, Audiometrische Technik; Dienstl., Handel",
    "wof:placetype":"venue"
},
  "geometry": {"coordinates":[7.4411821365,46.9479370117],"type":"Point"}
}