{
  "type": "Feature",
  "properties": {
    "iso:country":"CH",
    "sg:address":"R\u00e9sidence Le Yacht",
    "sg:city":"Soyhi\u00e8res",
    "sg:orig_category":"Detailhandel mit Waren verschiedener Art, Hauptrichtung Nahrungsmittel",
    "sg:postcode":"2805",
    "sg:province":"Jura",
    "wof:name":"Philippe Sangsue",
    "wof:placetype":"venue"
},
  "geometry": {"coordinates":[7.369204998,47.3905067444],"type":"Point"}
}