{
  "type": "Feature",
  "properties": {
    "iso:country":"CH",
    "sg:address":"Via San Gottardo 56",
    "sg:city":"Minusio",
    "sg:orig_category":"Arztpraxen",
    "sg:phone":"+41 91 743 12 72",
    "sg:postcode":"6648",
    "sg:province":"Ticino",
    "wof:name":"Dott.med.paul Peyer Specialista Fmh",
    "wof:placetype":"venue"
},
  "geometry": {"coordinates":[8.811046,46.175396],"type":"Point"}
}