{
  "type": "Feature",
  "properties": {
    "iso:country":"CH",
    "sg:address":"1958",
    "sg:city":"St-l\u00e9onard",
    "sg:orig_category":"Elektrischer Leitungsbau Elektrizit\u00e4tsversorgung",
    "sg:phone":"+41 27 203 17 14",
    "sg:postcode":"1958",
    "sg:province":"Valais",
    "wof:name":"L'energie De Sion-r\u00e9gion Sa",
    "wof:placetype":"venue"
},
  "geometry": {"coordinates":[7.4179301262,46.2533912659],"type":"Point"}
}