{
  "type": "Feature",
  "properties": {
    "iso:country":"CH",
    "sg:address":"Via Vedeggio 5",
    "sg:city":"Manno",
    "sg:orig_category":"Einzelhandel mit Automobilen Herstellung von Karosserien U Anh\u00e4ngern",
    "sg:phone":"+41 91 605 27 61",
    "sg:postcode":"6928",
    "sg:province":"Ticino",
    "wof:name":"Caravan Bralla Di Bralla Elio",
    "wof:placetype":"venue"
},
  "geometry": {"coordinates":[8.9257183075,46.0372467041],"type":"Point"}
}