{
  "type": "Feature",
  "properties": {
    "iso:country":"CH",
    "sg:address":"Z\u00fcrcherstrasse 5",
    "sg:city":"Stadel",
    "sg:orig_category":"Detailhandel mit Waren verschiedener Art, Hauptrichtung Nahrungsmittel Tankstellen",
    "sg:phone":"+41 18582133",
    "sg:postcode":"8174",
    "sg:province":"Z\u00fcrich",
    "wof:name":"Landwirtschaftliche Konsumgenossenschaft Stadel-neerach-bachs",
    "wof:placetype":"venue"
},
  "geometry": {"coordinates":[8.4664039612,47.5282974243],"type":"Point"}
}