{
  "type": "Feature",
  "properties": {
    "iso:country":"CH",
    "sg:address":"Bahnhofstrasse 106",
    "sg:city":"Z\u00fcrich",
    "sg:orig_category":"Gesundheitswesen",
    "sg:postcode":"8001",
    "sg:province":"Z\u00fcrich",
    "wof:name":"Stiftung F\u00fcr Privatbetreuungs Und Pflegedienste",
    "wof:placetype":"venue"
},
  "geometry": {"coordinates":[8.5398216248,47.376499176],"type":"Point"}
}