{
  "type": "Feature",
  "properties": {
    "iso:country":"CH",
    "sg:address":"Johann-verresius-strasse 13",
    "sg:city":"Biel/bienne",
    "sg:orig_category":"Verwaltung von Immobilien Wirtschaftspr\u00fcfung, Steuerberatung U Treuhand",
    "sg:phone":"+41 32 325 26 66",
    "sg:postcode":"2502",
    "sg:province":"Bern",
    "wof:name":"Beat Feurer Steuerexperten",
    "wof:placetype":"venue"
},
  "geometry": {"coordinates":[7.2457561493,47.1327476501],"type":"Point"}
}