{
  "type": "Feature",
  "properties": {
    "iso:country":"CH",
    "sg:address":"St. Annastrasse 13",
    "sg:city":"Ebikon",
    "sg:orig_category":"Grosshandel mit Milch, Milcherzeugnissen, Eiern, Speise\u00f6len U Nahrungsfetten",
    "sg:phone":"+41 41 440 96 87",
    "sg:postcode":"6030",
    "sg:province":"Luzern",
    "wof:name":"Weilenmann Marcel",
    "wof:placetype":"venue"
},
  "geometry": {"coordinates":[8.3420782089,47.0807991028],"type":"Point"}
}