{
  "type": "Feature",
  "properties": {
    "iso:country":"CH",
    "sg:address":"Greyerzerstrasse 57",
    "sg:city":"Bern",
    "sg:orig_category":"Detailhandel mit B\u00fcchern",
    "sg:phone":"+41 31 333 37 11",
    "sg:postcode":"3013",
    "sg:province":"Bern",
    "wof:name":"Kinderbuchladen Mulwurf Buss J. + Saner P.",
    "wof:placetype":"venue"
},
  "geometry": {"coordinates":[7.44936,46.956848],"type":"Point"}
}