{
  "type": "Feature",
  "properties": {
    "iso:country":"CH",
    "sg:address":"Via E. Bossi 50",
    "sg:city":"Chiasso",
    "sg:orig_category":"Vermietung U Verpachtung von eigenen Immobilien",
    "sg:postcode":"6830",
    "sg:province":"Ticino",
    "wof:name":"Pyramus Gmbh",
    "wof:placetype":"venue"
},
  "geometry": {"coordinates":[7.5999908447,47.4788513184],"type":"Point"}
}