{
  "type": "Feature",
  "properties": {
    "addr:full":"1038 Bercher Vaud 1038",
    "addr:housenumber":"1038",
    "addr:postcode":"1038",
    "addr:street":"Bercher",
    "iso:country":"CH",
    "sg:address":"1038",
    "sg:city":"Bercher",
    "sg:orig_category":"Abwasserreinigung",
    "sg:phone":"+41 21 903 10 21",
    "sg:postcode":"1038",
    "sg:province":"Vaud",
    "wof:name":"Station D'\u00e9puration Des Eaux",
    "wof:placetype":"venue"
},
  "geometry": {"coordinates":[6.75595,46.576881],"type":"Point"}
}