{
  "type": "Feature",
  "properties": {
    "iso:country":"CH",
    "sg:address":"Octodure Rue D' 17",
    "sg:city":"Martigny",
    "sg:orig_category":"RESTAURANTS: TEA-ROOMS",
    "sg:postcode":"1920",
    "sg:province":"Valais",
    "wof:name":"Michellod Janine",
    "wof:placetype":"venue"
},
  "geometry": {"coordinates":[6.9743900299,46.082359314],"type":"Point"}
}