{
  "type": "Feature",
  "properties": {
    "iso:country":"CH",
    "sg:address":"Route De Courgenay 37 2942 Alle Case Postale 58",
    "sg:city":"Alle",
    "sg:orig_category":"Herstellung U Zusammensetzung von Uhren Herstellung der Ausstattung von Uhren",
    "sg:phone":"+41 32 751 61 51",
    "sg:postcode":"2942",
    "sg:province":"Jura",
    "wof:name":"Nth Nouvelles Techniques Horlog\u00e8res Sa",
    "wof:placetype":"venue"
},
  "geometry": {"coordinates":[7.0607051849,47.0561332703],"type":"Point"}
}