{
  "type": "Feature",
  "properties": {
    "iso:country":"CH",
    "sg:address":"Rumlikerstrasse 9",
    "sg:city":"Fehraltorf",
    "sg:orig_category":"Grosshandel mit sonstigen Getr\u00e4nken",
    "sg:phone":"+41 19541651",
    "sg:postcode":"8320",
    "sg:province":"Z\u00fcrich",
    "wof:name":"Alfred Wallimann Valser-depot",
    "wof:placetype":"venue"
},
  "geometry": {"coordinates":[8.7521600723,47.3890419006],"type":"Point"}
}