{
  "type": "Feature",
  "properties": {
    "iso:country":"CH",
    "sg:address":"Rigistrasse 9",
    "sg:city":"Dierikon",
    "sg:orig_category":"Sanit\u00e4r, Heizungs U L\u00fcftungsinstallation Sanit\u00e4rinstallation",
    "sg:phone":"+41 41 450 15 59",
    "sg:postcode":"6036",
    "sg:province":"Luzern",
    "wof:name":"Herzog Franz",
    "wof:placetype":"venue"
},
  "geometry": {"coordinates":[8.3680667877,47.0971069336],"type":"Point"}
}