{
  "type": "Feature",
  "properties": {
    "iso:country":"CH",
    "sg:address":"Kunkels",
    "sg:city":"Tamins",
    "sg:classifiers":[
        {
            "category":"Restaurant",
            "type":"Food & Drink"
        }
    ],
    "sg:phone":"+41 81 641 11 62",
    "sg:postcode":"7015",
    "sg:province":"Graubunden",
    "wof:name":"Restaurant Passh\u00f6he Ueberuf",
    "wof:placetype":"venue"
},
  "geometry": {"coordinates":[9.4104299545,46.8694992065],"type":"Point"}
}