{
  "type": "Feature",
  "properties": {
    "iso:country":"CH",
    "sg:address":"Route De Gen\u00e8ve",
    "sg:city":"Cheseaux-lausanne",
    "sg:orig_category":"D\u00e4mmung gegen K\u00e4lte, W\u00e4rme, Schall U Ersch\u00fctterung",
    "sg:phone":"+41 21 731 21 86",
    "sg:postcode":"1033",
    "sg:province":"Vaud",
    "wof:name":"Balzan & Immer Sa Etanch\u00e9it\u00e9-sols Industriels",
    "wof:placetype":"venue"
},
  "geometry": {"coordinates":[6.5904297829,46.5771217346],"type":"Point"}
}