{
  "type": "Feature",
  "properties": {
    "iso:country":"CH",
    "sg:address":"Oberwilerstrasse 36 B",
    "sg:city":"Berikon",
    "sg:orig_category":"Finanzierungsinstitutionen",
    "sg:phone":"+41 56 631 66 81",
    "sg:postcode":"8965",
    "sg:province":"Aargau",
    "wof:name":"Dkz Forex Ag",
    "wof:placetype":"venue"
},
  "geometry": {"coordinates":[8.3757781982,47.3479766846],"type":"Point"}
}