{
  "type": "Feature",
  "properties": {
    "iso:country":"CH",
    "sg:address":"1651",
    "sg:city":"Villarvolard",
    "sg:orig_category":"Herstellung von Konstruktionsteilen, Fertigbauteilen U Ausbauelementen aus Holz",
    "sg:phone":"+41 26 915 19 78",
    "sg:postcode":"1651",
    "sg:province":"Fribourg",
    "wof:name":"Drompt Bernard",
    "wof:placetype":"venue"
},
  "geometry": {"coordinates":[7.1070871353,46.6457557678],"type":"Point"}
}