{
  "type": "Feature",
  "properties": {
    "iso:country":"CH",
    "sg:address":"Via Da Martin",
    "sg:city":"Poschiavo",
    "sg:orig_category":"Sanit\u00e4r, Heizungs U L\u00fcftungsinstallation",
    "sg:phone":"+41 62 291 11 83",
    "sg:postcode":"7742",
    "sg:province":"Graubunden",
    "wof:name":"Bondt Konrad Sanit\u00e4re Anlagen",
    "wof:placetype":"venue"
},
  "geometry": {"coordinates":[7.9883761406,47.3536720276],"type":"Point"}
}