{
  "type": "Feature",
  "properties": {
    "iso:country":"CH",
    "sg:address":"Rue De L'avenir 17",
    "sg:city":"Avenches",
    "sg:orig_category":"Massagestudios",
    "sg:phone":"+41 26 675 14 04",
    "sg:postcode":"1580",
    "sg:province":"Vaud",
    "wof:name":"Elie Delacour Massages",
    "wof:placetype":"venue"
},
  "geometry": {"coordinates":[7.037364006,46.8808631897],"type":"Point"}
}