{
  "type": "Feature",
  "properties": {
    "iso:country":"CH",
    "sg:address":"Rue De L'industrie 8",
    "sg:city":"Monthey",
    "sg:orig_category":"Korrespondenz U Nachrichtenb\u00fcros, selbst\u00e4ndige Journalisten",
    "sg:phone":"+41 24 472 15 72",
    "sg:postcode":"1870",
    "sg:province":"Valais",
    "wof:name":"Zuber Jean-jacques",
    "wof:placetype":"venue"
},
  "geometry": {"coordinates":[6.9496221542,46.2519378662],"type":"Point"}
}