{
  "type": "Feature",
  "properties": {
    "iso:country":"CH",
    "sg:address":"Bahnhofstr. 16",
    "sg:city":"Root",
    "sg:classifiers":[
        {
            "category":"Banks & Credit Unions",
            "subcategory":"Bank",
            "type":"Services"
        }
    ],
    "sg:phone":"+41 4141913644",
    "sg:postcode":"6037",
    "sg:province":"Luzern",
    "wof:name":"Luzerner Kantonalbank",
    "wof:placetype":"venue"
},
  "geometry": {"coordinates":[8.392033,47.117359],"type":"Point"}
}