{
  "type": "Feature",
  "properties": {
    "iso:country":"CH",
    "sg:address":"Gysulastrasse 70",
    "sg:city":"Rombach",
    "sg:orig_category":"Sonstige Aktivit\u00e4ten der nicht-\u00e4rztlichen Medizinalberufe",
    "sg:phone":"+41 62 824 69 34",
    "sg:postcode":"5022",
    "sg:province":"Aargau",
    "wof:name":"Ars\u00e8ne Soder Fussreflexzonen",
    "wof:placetype":"venue"
},
  "geometry": {"coordinates":[8.049744606,47.4077110291],"type":"Point"}
}