{
  "type": "Feature",
  "properties": {
    "iso:country":"CH",
    "sg:address":"Avenue D'ouchy 30",
    "sg:city":"Lausanne",
    "sg:orig_category":"Parf\u00fcmerien U sonstiger Detailhandel mit kosmetischen Artikeln U K\u00f6rperpflegemitteln",
    "sg:phone":"+41 71 688 68 15",
    "sg:postcode":"1006",
    "sg:province":"Vaud",
    "wof:name":"Hans-j\u00f6rg Edelmann",
    "wof:placetype":"venue"
},
  "geometry": {"coordinates":[9.1936950684,47.6357307434],"type":"Point"}
}