{
  "type": "Feature",
  "properties": {
    "iso:country":"CH",
    "sg:address":"Zollhausstrasse 39",
    "sg:city":"Glarus",
    "sg:orig_category":"Kauf U Verkauf von Immobilien auf eigene Rechnung",
    "sg:postcode":"8750",
    "sg:province":"Glarus",
    "wof:name":"Sola Ag",
    "wof:placetype":"venue"
},
  "geometry": {"coordinates":[9.0634899139,47.0433692932],"type":"Point"}
}