{
  "type": "Feature",
  "properties": {
    "iso:country":"CH",
    "sg:address":"Bahnhofstr. 14",
    "sg:city":"Au",
    "sg:classifiers":[
        {
            "category":"Banks & Credit Unions",
            "subcategory":"Bank",
            "type":"Services"
        }
    ],
    "sg:phone":"+41 61 826 73 73",
    "sg:postcode":"9434",
    "sg:province":"St. Gallen",
    "wof:name":"Swiss Bank Corp.",
    "wof:placetype":"venue"
},
  "geometry": {"coordinates":[7.691951,47.520874],"type":"Point"}
}