{
  "type": "Feature",
  "properties": {
    "iso:country":"CH",
    "sg:address":"Bettlistrasse 28 8600 D\u00fcbendorf. Postfach 274",
    "sg:city":"D\u00fcbendorf",
    "sg:orig_category":"Unternehmensberatung Wirtschaftspr\u00fcfung, Steuerberatung U Treuhand",
    "sg:phone":"+41 18215930",
    "sg:postcode":"8600",
    "sg:province":"Z\u00fcrich",
    "wof:name":"Revor Ag, Treuhand- & Revisionsgesellschaft",
    "wof:placetype":"venue"
},
  "geometry": {"coordinates":[8.6247911453,47.3977203369],"type":"Point"}
}