{
  "type": "Feature",
  "properties": {
    "iso:country":"CH",
    "sg:address":"Gr\u00fcttstrasse 5",
    "sg:city":"Obergerlafingen",
    "sg:orig_category":"Maurerarbeiten",
    "sg:phone":"+41 81 416 42 64",
    "sg:postcode":"4564",
    "sg:province":"Bern",
    "wof:name":"Robert Schmidhauser Maurergesch\u00e4ft",
    "wof:placetype":"venue"
},
  "geometry": {"coordinates":[9.8481521606,46.8039512634],"type":"Point"}
}