{
  "type": "Feature",
  "properties": {
    "iso:country":"CH",
    "sg:address":"Schanzeneckstrasse 9",
    "sg:city":"Bern",
    "sg:orig_category":"Softwareentwicklung U beratung",
    "sg:phone":"+41 878 878 171",
    "sg:postcode":"3012",
    "sg:province":"Bern",
    "wof:name":"Franz Fankhauser Edv-beratung",
    "wof:placetype":"venue"
},
  "geometry": {"coordinates":[7.4349169731,46.9501228333],"type":"Point"}
}