{
  "type": "Feature",
  "properties": {
    "iso:country":"CH",
    "sg:address":"Hohe Winde-strasse 120 4059 Basel. Postfach",
    "sg:city":"Basel",
    "sg:orig_category":"Werbung",
    "sg:phone":"+41 61 361 14 04",
    "sg:postcode":"4002",
    "sg:province":"Basel-Stadt",
    "wof:name":"Hkw Hersperger Kundenwerbung",
    "wof:placetype":"venue"
},
  "geometry": {"coordinates":[7.5937161446,47.5332107544],"type":"Point"}
}