{
  "type": "Feature",
  "properties": {
    "iso:country":"CH",
    "sg:address":"Zentrumstrasse 4 5443 Niederrohrdorf. Postfach 29",
    "sg:city":"Niederrohrdorf",
    "sg:orig_category":"Ger\u00fcstbau Sonstiger spezialisierter Hoch U Tiefbau",
    "sg:phone":"+41 79 420 69 92",
    "sg:postcode":"5443",
    "sg:province":"Aargau",
    "wof:name":"Rex Ger\u00fcst-bau Gmbh",
    "wof:placetype":"venue"
},
  "geometry": {"coordinates":[8.30555439,47.4233436584],"type":"Point"}
}