{
  "type": "Feature",
  "properties": {
    "iso:country":"CH",
    "sg:address":"Dorfstrasse 12",
    "sg:city":"Russikon",
    "sg:orig_category":"Markt U Meinungsforschung",
    "sg:postcode":"8332",
    "sg:province":"Z\u00fcrich",
    "wof:name":"Werbeagentur Speidel Promotion",
    "wof:placetype":"venue"
},
  "geometry": {"coordinates":[8.7757062912,47.393913269],"type":"Point"}
}