{
  "type": "Feature",
  "properties": {
    "iso:country":"CH",
    "sg:address":"Suststrasse 4",
    "sg:city":"Brunnen",
    "sg:classifiers":[
        {
            "category":"Insurance",
            "subcategory":"Insurance Agent",
            "type":"Services"
        }
    ],
    "sg:phone":"+41 41 820 46 33",
    "sg:postcode":"6440",
    "sg:province":"Schwyz",
    "sg:tags":[
        "versicherungsagenturen",
        "-broker"
    ],
    "wof:name":"Franz Betschart Agentur Winterthur-versicher.",
    "wof:placetype":"venue"
},
  "geometry": {"coordinates":[8.6070318222,46.9953041077],"type":"Point"}
}