{
  "type": "Feature",
  "properties": {
    "iso:country":"CH",
    "sg:address":"Martin Disteli-strasse 9",
    "sg:city":"Olten",
    "sg:classifiers":[
        {
            "category":"Banks & Credit Unions",
            "subcategory":"Investment Brokerage",
            "type":"Services"
        }
    ],
    "sg:phone":"+41 62 296 88 88",
    "sg:postcode":"4600",
    "sg:province":"Solothurn",
    "sg:tags":[
        "development",
        "electronics"
    ],
    "wof:name":"Kehr Engineering",
    "wof:placetype":"venue"
},
  "geometry": {"coordinates":[7.9091210365,47.3513183594],"type":"Point"}
}