{
  "type": "Feature",
  "properties": {
    "iso:country":"CH",
    "sg:address":"Vordere Hauptgasse 32",
    "sg:city":"Zofingen",
    "sg:orig_category":"Drogerien",
    "sg:phone":"+41 62 751 12 33",
    "sg:postcode":"4800",
    "sg:province":"Aargau",
    "wof:name":"Drogerie Unterstadt, Sager Monika",
    "wof:placetype":"venue"
},
  "geometry": {"coordinates":[7.9442720413,47.2895774841],"type":"Point"}
}