{
  "type": "Feature",
  "properties": {
    "iso:country":"CH",
    "sg:address":"25",
    "sg:city":"Lausanne",
    "sg:classifiers":[
        {
            "category":"Banks & Credit Unions",
            "subcategory":"Bank",
            "type":"Services"
        }
    ],
    "sg:phone":"+41 21 617 46 81",
    "sg:postcode":"1001",
    "sg:province":"Vaud",
    "wof:name":"Domus Bank",
    "wof:placetype":"venue"
},
  "geometry": {"coordinates":[6.629411,46.515976],"type":"Point"}
}