{
  "type": "Feature",
  "properties": {
    "iso:country":"CH",
    "sg:address":"Alte Landstrasse 45",
    "sg:city":"Tenniken",
    "sg:orig_category":"Herstellung von sonstigen Metallwaren",
    "sg:phone":"+41 61 971 36 54",
    "sg:postcode":"4456",
    "sg:province":"Basel-Landschaft",
    "wof:name":"Suter Willy",
    "wof:placetype":"venue"
},
  "geometry": {"coordinates":[7.8112049103,47.4349708557],"type":"Point"}
}