{
  "type": "Feature",
  "properties": {
    "iso:country":"CH",
    "sg:address":"2944",
    "sg:city":"Bonfol",
    "sg:orig_category":"Primarschulen",
    "sg:phone":"+41 32 474 43 42",
    "sg:postcode":"2944",
    "sg:province":"Jura",
    "wof:name":"Ecole Primaire",
    "wof:placetype":"venue"
},
  "geometry": {"coordinates":[7.1496939659,47.4781341553],"type":"Point"}
}