{
  "type": "Feature",
  "properties": {
    "iso:country":"CH",
    "sg:address":"Dorfstrasse 33b",
    "sg:city":"Wattenwil",
    "sg:orig_category":"Zimmerei, Dachdeckerei, Bauspenglerei U Abdichtung",
    "sg:phone":"+41 33 359 35 35",
    "sg:postcode":"3665",
    "sg:province":"Bern",
    "wof:name":"Zumbrag Holzbau & Bedachung Ag",
    "wof:placetype":"venue"
},
  "geometry": {"coordinates":[7.5093970299,46.7700538635],"type":"Point"}
}