{
  "type": "Feature",
  "properties": {
    "iso:country":"CH",
    "sg:address":"Milit\u00e4rstrasse 91",
    "sg:city":"Z\u00fcrich",
    "sg:orig_category":"Arztpraxen",
    "sg:phone":"+41 12411550",
    "sg:postcode":"8004",
    "sg:province":"Z\u00fcrich",
    "wof:name":"Dr.med.walter W. Bossart Arzt F\u00fcr Allgemeine Medizin",
    "wof:placetype":"venue"
},
  "geometry": {"coordinates":[8.529418,47.37896],"type":"Point"}
}