{
  "type": "Feature",
  "properties": {
    "addr:full":"Rautistrasse 19 Z\u00fcrich Z\u00fcrich 8047",
    "addr:housenumber":"19",
    "addr:postcode":"8047",
    "addr:street":"Rautistrasse",
    "iso:country":"CH",
    "sg:address":"Rautistrasse 19",
    "sg:city":"Z\u00fcrich",
    "sg:classifiers":[
        {
            "category":"Utilities",
            "subcategory":"Natural Gas",
            "type":"Services"
        }
    ],
    "sg:phone":"+41 14068011",
    "sg:postcode":"8047",
    "sg:province":"Z\u00fcrich",
    "sg:tags":[
        "barrel",
        "pump"
    ],
    "wof:name":"Ernst Hausammann & Co Ag",
    "wof:placetype":"venue"
},
  "geometry": {"coordinates":[8.493858,47.380051],"type":"Point"}
}