{
  "type": "Feature",
  "properties": {
    "iso:country":"CH",
    "sg:address":"Rue De Neuch\u00e2tel 26",
    "sg:city":"Yverdon-les-bains",
    "sg:orig_category":"Fotografisches Gewerbe U fotografische Laboratorien",
    "sg:postcode":"1400",
    "sg:province":"Vaud",
    "wof:name":"Photo-marketing, H. Scheinpflug",
    "wof:placetype":"venue"
},
  "geometry": {"coordinates":[6.635766983,46.7819633484],"type":"Point"}
}