{
  "type": "Feature",
  "properties": {
    "iso:country":"CH",
    "sg:address":"Hegistrasse 10",
    "sg:city":"Winterthur",
    "sg:orig_category":"Sonstige Institutionen des Sozialwesens ohne Beherbergung",
    "sg:phone":"+41 52 242 32 48",
    "sg:postcode":"8404",
    "sg:province":"Z\u00fcrich",
    "wof:name":"Invaliden-verein Winterthur",
    "wof:placetype":"venue"
},
  "geometry": {"coordinates":[8.7469749451,47.5006217957],"type":"Point"}
}