{
  "type": "Feature",
  "properties": {
    "iso:country":"CH",
    "sg:address":"Via Borromini 7",
    "sg:city":"Lugano",
    "sg:orig_category":"Vermietung U Verpachtung von eigenen Immobilien Vermittlung von Immobilien",
    "sg:phone":"+41 41 630 31 31",
    "sg:postcode":"6900",
    "sg:province":"Ticino",
    "wof:name":"Marbet Immobilien-treuhand Und Marketing",
    "wof:placetype":"venue"
},
  "geometry": {"coordinates":[8.3032217026,47.0448646545],"type":"Point"}
}