{
  "type": "Feature",
  "properties": {
    "iso:country":"CH",
    "sg:address":"Via Vincenzo D'alberti 4",
    "sg:city":"Bellinzona",
    "sg:classifiers":[
        {
            "category":"Manufacturing",
            "subcategory":"Building Materials",
            "type":"Manufacturing & Wholesale Goods"
        }
    ],
    "sg:phone":"+41 91 648 30 81",
    "sg:postcode":"6500",
    "sg:province":"Ticino",
    "sg:tags":[
        "biological"
    ],
    "wof:name":"Min8 Sa",
    "wof:placetype":"venue"
},
  "geometry": {"coordinates":[9.020085,46.194145],"type":"Point"}
}