{
  "type": "Feature",
  "properties": {
    "iso:country":"CH",
    "sg:address":"Gerbestrasse 4",
    "sg:city":"Appenzell",
    "sg:orig_category":"Organisationen des Gesundheitswesen",
    "sg:phone":"+41 71 966 26 85",
    "sg:postcode":"9050",
    "sg:province":"Appenzell Innerhoden",
    "wof:name":"Spitex-krankenpflegeverein M\u00fcnchwilen-eschlikon",
    "wof:placetype":"venue"
},
  "geometry": {"coordinates":[8.9933509827,47.4789543152],"type":"Point"}
}