{
  "type": "Feature",
  "properties": {
    "iso:country":"CH",
    "sg:address":"Grotzenm\u00fchlestrasse 26",
    "sg:city":"Einsiedeln",
    "sg:orig_category":"Non-Classified Establishments",
    "sg:postcode":"8840",
    "sg:province":"Schwyz",
    "wof:name":"Siebdruck Inderfurth Gmbh",
    "wof:placetype":"venue"
},
  "geometry": {"coordinates":[8.7382068634,47.1257705688],"type":"Point"}
}