{
  "type": "Feature",
  "properties": {
    "iso:country":"CH",
    "sg:address":"De-candolle Rue 8 1205 Gen\u00e8ve. Postfach",
    "sg:city":"Gen\u00e8ve",
    "sg:orig_category":"Unternehmensberatung",
    "sg:phone":"+41 52 337 28 26",
    "sg:postcode":"1205",
    "sg:province":"Gen\u00e8ve",
    "wof:name":"M\u00f6rgeli Alfred, Unternehmensberatung",
    "wof:placetype":"venue"
},
  "geometry": {"coordinates":[8.7959194183,47.5517463684],"type":"Point"}
}