{
  "type": "Feature",
  "properties": {
    "iso:country":"CH",
    "sg:address":"Im Werd 6",
    "sg:city":"Unterengstringen",
    "sg:orig_category":"Unclassifiable Establishments",
    "sg:postcode":"8103",
    "sg:province":"Z\u00fcrich",
    "wof:name":"Dal Fara & Sangiorgio Technische Dienste",
    "wof:placetype":"venue"
},
  "geometry": {"coordinates":[8.42719841,47.4021987915],"type":"Point"}
}