{
  "type": "Feature",
  "properties": {
    "iso:country":"CH",
    "sg:address":"Zimmerlistrasse 21",
    "sg:city":"Aarburg",
    "sg:orig_category":"Detailhandel mit Metallwaren, Anstrichmitteln, Glaswaren, Bau U Heimwerkerbedarf Grosshandel mit Wer",
    "sg:phone":"+41 32 492 27 78",
    "sg:postcode":"4663",
    "sg:province":"Aargau",
    "wof:name":"Cenom Trading Ltd",
    "wof:placetype":"venue"
},
  "geometry": {"coordinates":[7.1003022194,47.2231445312],"type":"Point"}
}