{
  "type": "Feature",
  "properties": {
    "iso:country":"CH",
    "sg:address":"Schwandelstrasse 34 8800 Thalwil. Postfach 1114",
    "sg:city":"Thalwil",
    "sg:orig_category":"Detailhandel mit Musikinstrumenten Herstellung von Musikinstrumenten",
    "sg:phone":"+41 17205397",
    "sg:postcode":"8800",
    "sg:province":"Z\u00fcrich",
    "wof:name":"Pianohaus Schoekle Ag",
    "wof:placetype":"venue"
},
  "geometry": {"coordinates":[8.5603132248,47.2920913696],"type":"Point"}
}