{
  "type": "Feature",
  "properties": {
    "iso:country":"CH",
    "sg:address":"Staubstrasse 1",
    "sg:city":"Z\u00fcrich",
    "sg:orig_category":"Wirtschaftspr\u00fcfung, Steuerberatung U Treuhand",
    "sg:phone":"+41 12028525",
    "sg:postcode":"8038",
    "sg:province":"Z\u00fcrich",
    "wof:name":"Rebmann W. & Co",
    "wof:placetype":"venue"
},
  "geometry": {"coordinates":[8.532576561,47.3471755981],"type":"Point"}
}