{
  "type": "Feature",
  "properties": {
    "iso:country":"CH",
    "sg:address":"Avenue De B\u00e9thusy 31",
    "sg:city":"Lausanne",
    "sg:orig_category":"Grosshandel mit Nahrungsmitteln, Getr\u00e4nken U Tabakwaren",
    "sg:phone":"+41 21 312 52 32",
    "sg:postcode":"1012",
    "sg:province":"Vaud",
    "wof:name":"Arvensis Produits Naturels",
    "wof:placetype":"venue"
},
  "geometry": {"coordinates":[6.6471748352,46.5221710205],"type":"Point"}
}