{
  "type": "Feature",
  "properties": {
    "iso:country":"CH",
    "sg:address":"Hinterbergstrasse 36",
    "sg:city":"Cham",
    "sg:orig_category":"G\u00fcterbef\u00f6rderung im Strassenverkehr",
    "sg:phone":"+41 41 740 26 26",
    "sg:postcode":"6330",
    "sg:province":"Zug",
    "wof:name":"Galliker Transport Ag",
    "wof:placetype":"venue"
},
  "geometry": {"coordinates":[8.4762506485,47.1866188049],"type":"Point"}
}