{
  "type": "Feature",
  "properties": {
    "iso:country":"CH",
    "sg:address":"Place Du Temple 4",
    "sg:city":"Cossonay-ville",
    "sg:orig_category":"Bestattungswesen",
    "sg:phone":"+41 21 861 30 45",
    "sg:postcode":"1304",
    "sg:province":"Vaud",
    "wof:name":"Philippe & Evelyne Wiesmann Pompes Fun\u00e8bres Alpha",
    "wof:placetype":"venue"
},
  "geometry": {"coordinates":[6.487557,46.600582],"type":"Point"}
}