{
  "type": "Feature",
  "properties": {
    "iso:country":"CH",
    "sg:address":"R. Des Caves 2 Case Postale 16",
    "sg:city":"Riddes",
    "sg:classifiers":[
        {
            "category":"Food Court",
            "type":"Food & Drink"
        }
    ],
    "sg:phone":"+41 27 305 15 00",
    "sg:postcode":"1908",
    "sg:province":"Valais",
    "sg:tags":[
        "product",
        "related"
    ],
    "wof:name":"Maye Les Fils Sa",
    "wof:placetype":"venue"
},
  "geometry": {"coordinates":[-7.8974699974,41.5094985962],"type":"Point"}
}