{
  "type": "Feature",
  "properties": {
    "iso:country":"CH",
    "sg:address":"Rue Du Vieux-village Bramois",
    "sg:city":"Bramois",
    "sg:orig_category":"Unclassifiable Establishments",
    "sg:postcode":"1967",
    "sg:province":"Valais",
    "wof:name":"Caf\u00e9-restaurant Le Bramoisien, Hasler Ilse Ria",
    "wof:placetype":"venue"
},
  "geometry": {"coordinates":[7.4049649239,46.2329978943],"type":"Point"}
}