{
  "type": "Feature",
  "properties": {
    "iso:country":"CH",
    "sg:address":"Gotthardstrasse 42 - Golda",
    "sg:city":"Arth",
    "sg:orig_category":"Verwertung von Milch",
    "sg:postcode":"6415",
    "sg:province":"Schwyz",
    "wof:name":"Jmlig, K\u00e4serei Und Lebensmittel.",
    "wof:placetype":"venue"
},
  "geometry": {"coordinates":[8.5223703384,47.0628089905],"type":"Point"}
}