{
  "type": "Feature",
  "properties": {
    "iso:country":"CH",
    "sg:address":"Maunoir Rue 42",
    "sg:city":"Gen\u00e8ve",
    "sg:orig_category":"Reinigungsgewerbe",
    "sg:postcode":"1207",
    "sg:province":"Gen\u00e8ve",
    "wof:name":"Guerra Maria De Lourdes",
    "wof:placetype":"venue"
},
  "geometry": {"coordinates":[6.1616830826,46.2022361755],"type":"Point"}
}