{
  "type": "Feature",
  "properties": {
    "iso:country":"CH",
    "sg:address":"Rennweg 62 2504 Biel/bienne Case Postale 3546",
    "sg:city":"Biel/bienne",
    "sg:orig_category":"Ingenieurb\u00fcros Elektro",
    "sg:phone":"+41 32 344 06 15",
    "sg:postcode":"2502",
    "sg:province":"Bern",
    "wof:name":"Ben-engineering",
    "wof:placetype":"venue"
},
  "geometry": {"coordinates":[7.266201973,47.1440238953],"type":"Point"}
}