{
  "type": "Feature",
  "properties": {
    "iso:country":"CH",
    "sg:address":"Paracelsusweg 1",
    "sg:city":"Stans",
    "sg:orig_category":"Fahrschulen, Flugschulen",
    "sg:phone":"+41 79 204 93 33",
    "sg:postcode":"6370",
    "sg:province":"Nidwalden",
    "wof:name":"Paul Eberli Fahrschule",
    "wof:placetype":"venue"
},
  "geometry": {"coordinates":[8.355178833,46.9608078003],"type":"Point"}
}