{
  "type": "Feature",
  "properties": {
    "iso:country":"CH",
    "sg:address":"Chemin Des Aulx 18",
    "sg:city":"Plan-les-ouates",
    "sg:orig_category":"HERSTELLUNG VON GER\u00c4TEN DER ELEKTRIZIT\u00c4TSERZEUGUNG, -VERTEILUNG U.\u00c4",
    "sg:phone":"+41 56 496 15 26",
    "sg:postcode":"1228",
    "sg:province":"Gen\u00e8ve",
    "wof:name":"Control & Monitoring Systems Gmbh",
    "wof:placetype":"venue"
},
  "geometry": {"coordinates":[8.313249588,47.4063491821],"type":"Point"}
}