{
  "type": "Feature",
  "properties": {
    "iso:country":"CH",
    "sg:address":"Frauenfelderstrasse 84",
    "sg:city":"Weinfelden",
    "sg:orig_category":"Detailhandel mit Getr\u00e4nken Grosshandel mit Getr\u00e4nken",
    "sg:phone":"+41 71 622 44 33",
    "sg:postcode":"8570",
    "sg:province":"Thurgau",
    "wof:name":"B\u00e4rlocher's Trankstelle Ag",
    "wof:placetype":"venue"
},
  "geometry": {"coordinates":[9.1004781723,47.5708885193],"type":"Point"}
}