{
  "type": "Feature",
  "properties": {
    "iso:country":"CH",
    "sg:address":"Stadelhoferstrasse 18",
    "sg:city":"Z\u00fcrich",
    "sg:classifiers":[
        {
            "category":"Bars & Pubs",
            "type":"Food & Drink"
        }
    ],
    "sg:phone":"+41 12521575",
    "sg:postcode":"8001",
    "sg:province":"Z\u00fcrich",
    "sg:tags":[
        "restaurant"
    ],
    "wof:name":"Restaurant Outback Lodge & Australian Bar",
    "wof:placetype":"venue"
},
  "geometry": {"coordinates":[8.547481,47.366722],"type":"Point"}
}