{
  "type": "Feature",
  "properties": {
    "addr:full":"Chemin Du Saux 17 1131 Tolochenaz Case Postale Tolochenaz Vaud 1131",
    "addr:housenumber":"17",
    "addr:postcode":"1131;postale tolochenaz;1131",
    "addr:street":"Chemin Du Saux",
    "iso:country":"CH",
    "sg:address":"Chemin Du Saux 17 1131 Tolochenaz Case Postale",
    "sg:city":"Tolochenaz",
    "sg:orig_category":"Bauingenieurb\u00fcros Zimmerei, Dachdeckerei, Bauspenglerei U Abdichtung",
    "sg:phone":"+41 21 802 40 45",
    "sg:postcode":"1131",
    "sg:province":"Vaud",
    "wof:name":"Toiture-concept S\u00e0rl Toitures Et Fa\u00e7ades L\u00e9g\u00e8res Ventil\u00e9es; \u00e9tude De Conception",
    "wof:placetype":"venue"
},
  "geometry": {"coordinates":[6.480485,46.501919],"type":"Point"}
}