{
  "type": "Feature",
  "properties": {
    "iso:country":"CH",
    "sg:address":"Stauffacherstrasse 130g",
    "sg:city":"Bern",
    "sg:orig_category":"K\u00fcnstlerische U schriftstellerische T\u00e4tigkeiten U Darbietungen",
    "sg:postcode":"3014",
    "sg:province":"Bern",
    "wof:name":"Bruchon V\u00e9ronique, Boutique D'art",
    "wof:placetype":"venue"
},
  "geometry": {"coordinates":[6.7483859062,47.0565185547],"type":"Point"}
}