{
  "type": "Feature",
  "properties": {
    "iso:country":"CH",
    "sg:address":"Auwiesstrasse 25 8127 Forch. Postfach",
    "sg:city":"Forch",
    "sg:orig_category":"Unternehmensberatung",
    "sg:phone":"+41 79 340 64 00",
    "sg:postcode":"8127",
    "sg:province":"Z\u00fcrich",
    "wof:name":"Hcc-hockey-consulting-company",
    "wof:placetype":"venue"
},
  "geometry": {"coordinates":[7.5760140419,46.9278182983],"type":"Point"}
}