{
  "type": "Feature",
  "properties": {
    "iso:country":"CH",
    "sg:address":"Laufenburgerstrasse 6",
    "sg:city":"Eiken",
    "sg:orig_category":"Detailhandel mit Waren verschiedener Art, Hauptrichtung Nahrungsmittel",
    "sg:phone":"+41 61 855 95 95",
    "sg:postcode":"5074",
    "sg:province":"Aargau",
    "wof:name":"Landi Frila",
    "wof:placetype":"venue"
},
  "geometry": {"coordinates":[7.9876561165,47.5335769653],"type":"Point"}
}