{
  "type": "Feature",
  "properties": {
    "iso:country":"CH",
    "sg:address":"7243",
    "sg:city":"Pany",
    "sg:orig_category":"Personenbef\u00f6rderung im Linienverkehr zu Land",
    "sg:phone":"+41 81 332 27 36",
    "sg:postcode":"7243",
    "sg:province":"Graubunden",
    "wof:name":"Skilift Pany Ag",
    "wof:placetype":"venue"
},
  "geometry": {"coordinates":[9.770409584,46.9283485413],"type":"Point"}
}