{
  "type": "Feature",
  "properties": {
    "iso:country":"CH",
    "sg:address":"Hauptstrasse 5 5312 D\u00f6ttingen. Postfach",
    "sg:city":"D\u00f6ttingen",
    "sg:orig_category":"M\u00f6belschreinereien",
    "sg:postcode":"5312",
    "sg:province":"Aargau",
    "wof:name":"T\u00fctsch Ag",
    "wof:placetype":"venue"
},
  "geometry": {"coordinates":[8.2554883957,47.5769195557],"type":"Point"}
}