{
  "type": "Feature",
  "properties": {
    "iso:country":"CH",
    "sg:address":"Schallenbergacker 278",
    "sg:city":"Liebistorf",
    "sg:orig_category":"Herstellung von sonstigen elektrischen Ausr\u00fcstungen",
    "sg:phone":"+41 26 674 22 01",
    "sg:postcode":"3213",
    "sg:province":"Fribourg",
    "wof:name":"Bruwe Engineering Wenger Bruno",
    "wof:placetype":"venue"
},
  "geometry": {"coordinates":[7.1885299683,46.9060592651],"type":"Point"}
}