{
  "type": "Feature",
  "properties": {
    "iso:country":"CH",
    "sg:address":"Albisstrasse 27",
    "sg:city":"Adliswil",
    "sg:orig_category":"Massagestudios",
    "sg:phone":"+41 17091180",
    "sg:postcode":"8134",
    "sg:province":"Z\u00fcrich",
    "wof:name":"Rita Eggenberger Massagen",
    "wof:placetype":"venue"
},
  "geometry": {"coordinates":[8.5257453918,47.3096504211],"type":"Point"}
}