{
  "type": "Feature",
  "properties": {
    "iso:country":"CH",
    "sg:address":"Corso Pestalozzi 12",
    "sg:city":"Lugano",
    "sg:orig_category":"Detailhandel mit B\u00fcchern",
    "sg:phone":"+41 91 923 42 09",
    "sg:postcode":"6900",
    "sg:province":"Ticino",
    "wof:name":"Libreria S. Paolo",
    "wof:placetype":"venue"
},
  "geometry": {"coordinates":[8.954492,46.005543],"type":"Point"}
}