{
  "type": "Feature",
  "properties": {
    "addr:full":"Hauptg. 21 Olten Solothurn 4601",
    "addr:housenumber":"21",
    "addr:postcode":"4601",
    "addr:street":"Hauptg.",
    "iso:country":"CH",
    "sg:address":"Hauptg. 21",
    "sg:city":"Olten",
    "sg:classifiers":[
        {
            "category":"Shopping",
            "subcategory":"Clothing, Apparel, & Fashions",
            "type":"Retail Goods"
        }
    ],
    "sg:phone":"+41 62 207 07 30",
    "sg:postcode":"4601",
    "sg:province":"Solothurn",
    "sg:tags":[
        "textile",
        "clothing",
        "clothes"
    ],
    "wof:name":"Bernheim & Co Ag",
    "wof:placetype":"venue"
},
  "geometry": {"coordinates":[7.904029,47.352119],"type":"Point"}
}