{
  "type": "Feature",
  "properties": {
    "iso:country":"CH",
    "sg:address":"Gutenbergstrasse 4",
    "sg:city":"Kreuzlingen",
    "sg:orig_category":"Gesundheitswesen",
    "sg:phone":"+41 21 960 44 45",
    "sg:postcode":"8280",
    "sg:province":"Thurgau",
    "wof:name":"Bioth\u00e9rapie L'eau-vive Sa",
    "wof:placetype":"venue"
},
  "geometry": {"coordinates":[6.9257059097,46.3936080933],"type":"Point"}
}