{
  "type": "Feature",
  "properties": {
    "iso:country":"CH",
    "sg:address":"Jolimontweg 5",
    "sg:city":"Lyss",
    "sg:orig_category":"Detailhandel mit Damenbekleidung",
    "sg:phone":"+41 32 384 22 91",
    "sg:postcode":"3250",
    "sg:province":"Bern",
    "wof:name":"Margrit F\u00e4ssler Couture-atelier",
    "wof:placetype":"venue"
},
  "geometry": {"coordinates":[7.316127,47.077309],"type":"Point"}
}