{
  "type": "Feature",
  "properties": {
    "iso:country":"CH",
    "sg:address":"Coll\u00e8gegasse 9",
    "sg:city":"Biel/bienne",
    "sg:orig_category":"Detailhandel mit Radio U Fernsehger\u00e4ten",
    "sg:phone":"+41 800 800 800",
    "sg:postcode":"2502",
    "sg:province":"Bern",
    "wof:name":"Swisscom-shop",
    "wof:placetype":"venue"
},
  "geometry": {"coordinates":[6.8282628059,47.1023788452],"type":"Point"}
}