{
  "type": "Feature",
  "properties": {
    "iso:country":"CH",
    "sg:address":"Juin Rue Du Vingt-trois 32",
    "sg:city":"Del\u00e9mont",
    "sg:classifiers":[
        {
            "category":"Travel",
            "subcategory":"Hotels & Motels",
            "type":"Entertainment"
        }
    ],
    "sg:postcode":"2800",
    "sg:province":"Jura",
    "sg:tags":[
        "hotels",
        "mit",
        "restaurant"
    ],
    "wof:name":"H\u00f4tel-restaurant La Bonne Auberge Gelso Gabrielle Et Gelso Gregory",
    "wof:placetype":"venue"
},
  "geometry": {"coordinates":[7.3429079056,47.3650093079],"type":"Point"}
}