{
  "type": "Feature",
  "properties": {
    "iso:country":"CH",
    "sg:address":"Bergschule Brunnersberg",
    "sg:city":"M\u00fcmliswil",
    "sg:orig_category":"Vereine Vogel-& Naturschutz",
    "sg:phone":"+41 62 929 14 81",
    "sg:postcode":"4717",
    "sg:province":"Solothurn",
    "wof:name":"Ornithologischer Verein Roggwil & Umgebung",
    "wof:placetype":"venue"
},
  "geometry": {"coordinates":[7.8228001595,47.2411117554],"type":"Point"}
}