{
  "type": "Feature",
  "properties": {
    "addr:full":"Route De Yens Apples Vaud 1143",
    "addr:postcode":"1143",
    "addr:street":"Route De Yens",
    "iso:country":"CH",
    "sg:address":"Route De Yens",
    "sg:city":"Apples",
    "sg:orig_category":"Arztpraxen",
    "sg:phone":"+41 21 800 36 80",
    "sg:postcode":"1143",
    "sg:province":"Vaud",
    "wof:name":"Drs M\u00e9d.j-o.& E. Dupraz M\u00e9decins G\u00e9n\u00e9ralistes",
    "wof:placetype":"venue"
},
  "geometry": {"coordinates":[6.426054,46.550682],"type":"Point"}
}