{
  "type": "Feature",
  "properties": {
    "iso:country":"CH",
    "sg:address":"Obstgartenstrasse 17",
    "sg:city":"Kloten",
    "sg:orig_category":"Kinderkrippen U horte",
    "sg:phone":"+41 18030870",
    "sg:postcode":"8302",
    "sg:province":"Z\u00fcrich",
    "wof:name":"Chinderhuus Oepfelbaum Frau Jutta Hauser",
    "wof:placetype":"venue"
},
  "geometry": {"coordinates":[8.5788869858,47.450378418],"type":"Point"}
}