{
  "type": "Feature",
  "properties": {
    "iso:country":"CH",
    "sg:address":"Neugutstrasse 16 8304 Wallisellen. Postfach",
    "sg:city":"Wallisellen",
    "sg:orig_category":"Softwareentwicklung U beratung",
    "sg:phone":"+41 71 380 00 53",
    "sg:postcode":"8304",
    "sg:province":"Z\u00fcrich",
    "wof:name":"Symtec Ag",
    "wof:placetype":"venue"
},
  "geometry": {"coordinates":[9.2492933273,47.4204864502],"type":"Point"}
}