{
  "type": "Feature",
  "properties": {
    "iso:country":"CH",
    "sg:address":"Wehntalerstrasse 366 8046 Z\u00fcrich. Postfach",
    "sg:city":"Wettingen",
    "sg:orig_category":"Grosshandel mit festen Brennstoffen U Mineral\u00f6lerzeugnissen",
    "sg:postcode":"5430",
    "sg:province":"Aargau",
    "wof:name":"Bucher-k\u00fcttel Klara Brennstoffe; Handel. Transporte",
    "wof:placetype":"venue"
},
  "geometry": {"coordinates":[8.3117341995,46.9878578186],"type":"Point"}
}