{
  "type": "Feature",
  "properties": {
    "iso:country":"CH",
    "sg:address":"2830",
    "sg:city":"Courrendlin",
    "sg:orig_category":"Schulpflegen",
    "sg:postcode":"2830",
    "sg:province":"Jura",
    "wof:name":"Commission Scolaire De L'\u00e9cole Secondaire",
    "wof:placetype":"venue"
},
  "geometry": {"coordinates":[7.463640213,46.2584381104],"type":"Point"}
}