{
  "type": "Feature",
  "properties": {
    "iso:country":"CH",
    "sg:address":"Route Suisse 36",
    "sg:city":"Mies",
    "sg:orig_category":"Tankstellen",
    "sg:phone":"+41 22 755 50 65",
    "sg:postcode":"1295",
    "sg:province":"Vaud",
    "wof:name":"Moscatello Andrea",
    "wof:placetype":"venue"
},
  "geometry": {"coordinates":[6.1747832298,46.3007507324],"type":"Point"}
}