{
  "type": "Feature",
  "properties": {
    "iso:country":"CH",
    "sg:address":"1274 Signy. Postfach",
    "sg:city":"Signy",
    "sg:orig_category":"Instandhaltung U Reparatur von Automobilen",
    "sg:phone":"+41 19321775",
    "sg:postcode":"1274",
    "sg:province":"Vaud",
    "wof:name":"Mathis J\u00fcrg Automobile",
    "wof:placetype":"venue"
},
  "geometry": {"coordinates":[8.7937774658,47.3199729919],"type":"Point"}
}