{
  "type": "Feature",
  "properties": {
    "iso:country":"CH",
    "sg:address":"Orellistrasse 21",
    "sg:city":"Z\u00fcrich",
    "sg:orig_category":"HOTELS: MIT RESTAURANT Kongress- and Tagungshotels mit Restaurant",
    "sg:phone":"+41 12683535",
    "sg:postcode":"8044",
    "sg:province":"Z\u00fcrich",
    "wof:name":"Hotel Z\u00fcrichberg",
    "wof:placetype":"venue"
},
  "geometry": {"coordinates":[8.568107605,47.3821525574],"type":"Point"}
}