{
  "type": "Feature",
  "properties": {
    "iso:country":"CH",
    "sg:address":"Schangnau",
    "sg:city":"Schangnau",
    "sg:classifiers":[
        {
            "category":"Banks & Credit Unions",
            "subcategory":"Bank",
            "type":"Services"
        }
    ],
    "sg:phone":"+41 3563103",
    "sg:postcode":"6197",
    "sg:province":"Bern",
    "wof:name":"Bank In Langnau",
    "wof:placetype":"venue"
},
  "geometry": {"coordinates":[7.860563,46.827526],"type":"Point"}
}