{
  "type": "Feature",
  "properties": {
    "iso:country":"CH",
    "sg:address":"Alpsteinstrasse 35 A 9100 Herisau. Postfach",
    "sg:city":"Herisau",
    "sg:orig_category":"Instandhaltung U Reparatur von Automobilen",
    "sg:phone":"+41 79 353 56 81",
    "sg:postcode":"9100",
    "sg:province":"Appenzell Ausserrhoden",
    "wof:name":"Auto M\u00fcller Herisau Ag",
    "wof:placetype":"venue"
},
  "geometry": {"coordinates":[9.2790699005,47.3781700134],"type":"Point"}
}