{
  "type": "Feature",
  "properties": {
    "iso:country":"CH",
    "sg:address":"Im Str\u00e4ler 38",
    "sg:city":"Z\u00fcrich",
    "sg:orig_category":"Herstellung von medizinischen U chirurgischen Ger\u00e4ten sowie orthop\u00e4dischen Vorrichtungen",
    "sg:postcode":"8047",
    "sg:province":"Z\u00fcrich",
    "wof:name":"Hanns Treichler & Co., Dentalwaren, Inhaberin Patricia Treichler",
    "wof:placetype":"venue"
},
  "geometry": {"coordinates":[8.4986381531,47.3706741333],"type":"Point"}
}