{
  "type": "Feature",
  "properties": {
    "iso:country":"CH",
    "sg:address":"Avenue De Valmont 18",
    "sg:city":"Lausanne",
    "sg:orig_category":"Maschinen and Apparate divers Grosshandel",
    "sg:phone":"+41 21 652 92 51",
    "sg:postcode":"1010",
    "sg:province":"Vaud",
    "wof:name":"Georges Usberti Appareils Autom.\u00e0 Musique",
    "wof:placetype":"venue"
},
  "geometry": {"coordinates":[6.6571931839,46.5374679565],"type":"Point"}
}