{
  "type": "Feature",
  "properties": {
    "iso:country":"CH",
    "sg:address":"Route Des Ch\u00eanes 2",
    "sg:city":"Fribourg",
    "sg:orig_category":"Pensionskassen",
    "sg:phone":"+41 26 674 19 45",
    "sg:postcode":"1700",
    "sg:province":"Fribourg",
    "wof:name":"Fonds De Pr\u00e9voyance En Faveur Du Personnel De Filotrico Sa",
    "wof:placetype":"venue"
},
  "geometry": {"coordinates":[7.177382946,46.8107833862],"type":"Point"}
}