{
  "type": "Feature",
  "properties": {
    "iso:country":"CH",
    "sg:address":"6218",
    "sg:city":"Ettiswil",
    "sg:orig_category":"Sportvereine Ski",
    "sg:phone":"+41 79 421 35 57",
    "sg:postcode":"6218",
    "sg:province":"Luzern",
    "wof:name":"Skiclub Etzel Pf\u00e4ffikon",
    "wof:placetype":"venue"
},
  "geometry": {"coordinates":[8.7638702393,47.3056373596],"type":"Point"}
}