{
  "type": "Feature",
  "properties": {
    "iso:country":"CH",
    "sg:address":"4553",
    "sg:city":"Subingen",
    "sg:orig_category":"Schwimmb\u00e4der",
    "sg:phone":"+41 18501393",
    "sg:postcode":"4553",
    "sg:province":"Solothurn",
    "wof:name":"Primarschulhaus Jungwingert Betriebsleitung Hallenbad",
    "wof:placetype":"venue"
},
  "geometry": {"coordinates":[8.517457962,47.4772148132],"type":"Point"}
}