{
  "type": "Feature",
  "properties": {
    "addr:full":"Thalerstrasse 1 Heiden Appenzell Ausserrhoden 9410",
    "addr:housenumber":"1",
    "addr:postcode":"9410",
    "addr:street":"Thalerstrasse;Ausserrhoden",
    "iso:country":"CH",
    "sg:address":"Thalerstrasse 1",
    "sg:city":"Heiden",
    "sg:orig_category":"Densimeters",
    "sg:phone":"+41 71 898 01 01",
    "sg:postcode":"9410",
    "sg:province":"Appenzell Ausserrhoden",
    "wof:name":"Grossauer Elektro-handels Ag",
    "wof:placetype":"venue"
},
  "geometry": {"coordinates":[9.535781,47.447514],"type":"Point"}
}