{
  "type": "Feature",
  "properties": {
    "iso:country":"CH",
    "sg:address":"Hermolingen 25 6023 Rothenburg. Postfach",
    "sg:city":"Emmenbr\u00fccke",
    "sg:orig_category":"Stukkateurgewerbe, Gipserei U Verputzerei",
    "sg:postcode":"6020",
    "sg:province":"Luzern",
    "wof:name":"Specchia + Weber, Gipsergesch\u00e4ft",
    "wof:placetype":"venue"
},
  "geometry": {"coordinates":[9.058848381,47.4691696167],"type":"Point"}
}