{
  "type": "Feature",
  "properties": {
    "iso:country":"CH",
    "sg:address":"8053 Z\u00fcrich. Postfach 58",
    "sg:city":"Z\u00fcrich",
    "sg:orig_category":"Sportvereine Ballsport Tennis",
    "sg:phone":"+41 13834972",
    "sg:postcode":"8053",
    "sg:province":"Z\u00fcrich",
    "wof:name":"Tennisclub Im Hau Witikon",
    "wof:placetype":"venue"
},
  "geometry": {"coordinates":[8.5992002487,47.3622283936],"type":"Point"}
}