{
  "type": "Feature",
  "properties": {
    "iso:country":"CH",
    "sg:address":"Giacomettistrasse 100",
    "sg:city":"Chur",
    "sg:orig_category":"Unclassifiable Establishments",
    "sg:postcode":"7000",
    "sg:province":"Graubunden",
    "wof:name":"Vitamoc Gmbh",
    "wof:placetype":"venue"
},
  "geometry": {"coordinates":[9.5240402222,46.8625717163],"type":"Point"}
}