{
  "type": "Feature",
  "properties": {
    "iso:country":"CH",
    "sg:address":"Tschannhof",
    "sg:city":"Buchrain",
    "sg:orig_category":"B\u00e4ckereien Konditoreien",
    "sg:phone":"+41 41 440 00 88",
    "sg:postcode":"6033",
    "sg:province":"Luzern",
    "wof:name":"Joseph Brunner B\u00e4ckerei Zur M\u00fchle",
    "wof:placetype":"venue"
},
  "geometry": {"coordinates":[8.346935,47.095493],"type":"Point"}
}