{
  "type": "Feature",
  "properties": {
    "iso:country":"CH",
    "sg:address":"Grand-places 14",
    "sg:city":"Fribourg",
    "sg:orig_category":"Finanzierungsinstitutionen",
    "sg:postcode":"1700",
    "sg:province":"Fribourg",
    "wof:name":"Q-seven Systems, Inc., Salt Lake City (utah/usa), Zweigniederlassung Buchs",
    "wof:placetype":"venue"
},
  "geometry": {"coordinates":[9.4626941681,47.169380188],"type":"Point"}
}