{
  "type": "Feature",
  "properties": {
    "iso:country":"CH",
    "sg:address":"Albisriederstrasse 352",
    "sg:city":"Z\u00fcrich",
    "sg:orig_category":"Herstellung von konfektionierten Textilwaren ohne Bekleidung",
    "sg:phone":"+41 14015060",
    "sg:postcode":"8047",
    "sg:province":"Z\u00fcrich",
    "wof:name":"Atelier B\u00f6pp, Guler-vogel R.",
    "wof:placetype":"venue"
},
  "geometry": {"coordinates":[8.4862184525,47.3755989075],"type":"Point"}
}