{
  "type": "Feature",
  "properties": {
    "addr:full":"Bosco Via Al 42 6974 Aldesago. Postfach Aldesago Ticino 6974",
    "addr:housenumber":"42",
    "addr:postcode":"6974;6974",
    "addr:street":"Via Al;Postfach;Ticino",
    "iso:country":"CH",
    "sg:address":"Bosco Via Al 42 6974 Aldesago. Postfach",
    "sg:city":"Aldesago",
    "sg:orig_category":"Architektur U Ingenieurb\u00fcros",
    "sg:postcode":"6974",
    "sg:province":"Ticino",
    "wof:name":"U.c.c. Ufficio Di Consulenza Carcano",
    "wof:placetype":"venue"
},
  "geometry": {"coordinates":[8.978525,46.007977],"type":"Point"}
}