{
  "type": "Feature",
  "properties": {
    "iso:country":"CH",
    "sg:address":"Chemin De Renens 56",
    "sg:city":"Lausanne",
    "sg:orig_category":"Detailhandel mit Fleisch U Fleischwaren",
    "sg:phone":"+41 71 911 25 11",
    "sg:postcode":"1004",
    "sg:province":"Vaud",
    "wof:name":"Marc Siegfried Metzgerei-wursterei",
    "wof:placetype":"venue"
},
  "geometry": {"coordinates":[9.0457754135,47.4629592896],"type":"Point"}
}