{
  "type": "Feature",
  "properties": {
    "iso:country":"CH",
    "sg:address":"B\u00f6zingenstrasse 39",
    "sg:city":"Biel/bienne",
    "sg:orig_category":"Jeans Rivets And Buttons",
    "sg:phone":"+41 32 344 20 07",
    "sg:postcode":"2502",
    "sg:province":"Bern",
    "wof:name":"Brero Ag",
    "wof:placetype":"venue"
},
  "geometry": {"coordinates":[7.2561421394,47.1473846436],"type":"Point"}
}