{
  "type": "Feature",
  "properties": {
    "iso:country":"CH",
    "sg:address":"Hirsackerstrasse 32",
    "sg:city":"Horgen",
    "sg:orig_category":"Forschung U Entwicklung im Bereich der Naturwissenschaften",
    "sg:postcode":"8810",
    "sg:province":"Z\u00fcrich",
    "wof:name":"R + D Consulting Gmbh",
    "wof:placetype":"venue"
},
  "geometry": {"coordinates":[8.6079759598,47.2577400208],"type":"Point"}
}