{
  "type": "Feature",
  "properties": {
    "addr:full":"Chatelat Chatelat 2711",
    "addr:housenumber":"2711",
    "iso:country":"CH",
    "sg:address":"Chatelat",
    "sg:city":"Chatelat",
    "sg:classifiers":[
        {
            "category":"Banks & Credit Unions",
            "subcategory":"Bank",
            "type":"Services"
        }
    ],
    "sg:phone":"+41 32919546",
    "sg:postcode":"2711",
    "wof:name":"Raiffeisenkasse",
    "wof:placetype":"venue"
},
  "geometry": {"coordinates":[6.138082,49.634319],"type":"Point"}
}