{
  "type": "Feature",
  "properties": {
    "iso:country":"CH",
    "sg:address":"Gr\u00fczenstrasse 34",
    "sg:city":"D\u00fcbendorf",
    "sg:orig_category":"Fussboden, Fliesen U Plattenlegerei, Tapeziererei",
    "sg:phone":"+41 79 620 33 06",
    "sg:postcode":"8600",
    "sg:province":"Z\u00fcrich",
    "wof:name":"Arena Posaceramic Sagl",
    "wof:placetype":"venue"
},
  "geometry": {"coordinates":[8.9738349915,45.8963050842],"type":"Point"}
}