{
  "type": "Feature",
  "properties": {
    "iso:country":"CH",
    "sg:address":"Parkstrasse 36 4102 Binningen. Postfach",
    "sg:city":"Binningen",
    "sg:orig_category":"Hardwareberatung",
    "sg:phone":"+41 61 422 03 39",
    "sg:postcode":"4102",
    "sg:province":"Basel-Landschaft",
    "wof:name":"Remac Pc & Network Solution Remo Schweiger",
    "wof:placetype":"venue"
},
  "geometry": {"coordinates":[7.5724391937,47.5342063904],"type":"Point"}
}