{
  "type": "Feature",
  "properties": {
    "iso:country":"CH",
    "sg:address":"Route De Vevey 47",
    "sg:city":"Cully",
    "sg:orig_category":"Rebbau",
    "sg:phone":"+41 21 799 16 30",
    "sg:postcode":"1096",
    "sg:province":"Vaud",
    "wof:name":"Georges-louis Fonjallaz Propri\u00e9taire Vigneron",
    "wof:placetype":"venue"
},
  "geometry": {"coordinates":[6.7365279198,46.4897613525],"type":"Point"}
}