{
  "type": "Feature",
  "properties": {
    "iso:country":"CH",
    "sg:address":"Via Dragoni 8",
    "sg:city":"Gravesano",
    "sg:orig_category":"Grosshandel mit Werkzeugmaschinen",
    "sg:postcode":"6929",
    "sg:province":"Ticino",
    "wof:name":"Girschweiler A.",
    "wof:placetype":"venue"
},
  "geometry": {"coordinates":[6.5906581879,46.5457077026],"type":"Point"}
}