{
  "type": "Feature",
  "properties": {
    "iso:country":"CH",
    "sg:address":"Dolderstrasse 30",
    "sg:city":"Z\u00fcrich",
    "sg:orig_category":"Arztpraxen",
    "sg:phone":"+41 12515229",
    "sg:postcode":"8032",
    "sg:province":"Z\u00fcrich",
    "wof:name":"Dr.med.claudia Sigg Spezial\u00e4rztin Fmh",
    "wof:placetype":"venue"
},
  "geometry": {"coordinates":[8.559236,47.370625],"type":"Point"}
}