{
  "type": "Feature",
  "properties": {
    "addr:full":"1077 Servion Vaud 1077",
    "addr:housenumber":"1077",
    "addr:postcode":"1077",
    "addr:street":"Servion",
    "iso:country":"CH",
    "sg:address":"1077",
    "sg:city":"Servion",
    "sg:orig_category":"Detailhandel mit Brot, Back U S\u00fcsswaren Detailhandel mit Waren verschiedener Art, Hauptrichtung Nahr",
    "sg:phone":"+41 21 903 12 41",
    "sg:postcode":"1077",
    "sg:province":"Vaud",
    "wof:name":"Max D\u00e9nervaud",
    "wof:placetype":"venue"
},
  "geometry": {"coordinates":[6.77983,46.573509],"type":"Point"}
}