{
  "type": "Feature",
  "properties": {
    "iso:country":"CH",
    "sg:address":"Rue Du Coll\u00e8ge 38",
    "sg:city":"Sonceboz-sombeval",
    "sg:classifiers":[
        {
            "category":"Insurance",
            "subcategory":"Insurance Agent",
            "type":"Services"
        }
    ],
    "sg:phone":"+41 32 489 18 61",
    "sg:postcode":"2605",
    "sg:province":"Bern",
    "sg:tags":[
        "versicherungsagenturen",
        "-broker"
    ],
    "wof:name":"Winterthur-vie Agence",
    "wof:placetype":"venue"
},
  "geometry": {"coordinates":[7.1667318344,47.1985969543],"type":"Point"}
}