{
  "type": "Feature",
  "properties": {
    "iso:country":"CH",
    "sg:address":"Seestrasse 78",
    "sg:city":"Berlingen",
    "sg:orig_category":"Unternehmensberatung",
    "sg:phone":"+41 52 762 51 51",
    "sg:postcode":"8267",
    "sg:province":"Thurgau",
    "wof:name":"Tertianum Optisysteme Ag",
    "wof:placetype":"venue"
},
  "geometry": {"coordinates":[9.0188808441,47.6746520996],"type":"Point"}
}