{
  "type": "Feature",
  "properties": {
    "iso:country":"CH",
    "sg:address":"Landriani Via 3",
    "sg:city":"Lugano",
    "sg:orig_category":"Unternehmensberatung",
    "sg:postcode":"6900",
    "sg:province":"Ticino",
    "wof:name":"Value Partners Llc, Maryland (usa), Lugano Branch",
    "wof:placetype":"venue"
},
  "geometry": {"coordinates":[8.9589481354,46.006149292],"type":"Point"}
}