{
  "type": "Feature",
  "properties": {
    "iso:country":"CH",
    "sg:address":"Chemin Des Murdines 8",
    "sg:city":"Bevaix",
    "sg:orig_category":"Sanit\u00e4r, Heizungs U L\u00fcftungsinstallation",
    "sg:postcode":"2022",
    "sg:province":"Neuch\u00e2tel",
    "wof:name":"Sanitaire Service Thomas A.",
    "wof:placetype":"venue"
},
  "geometry": {"coordinates":[6.8175039291,46.9317398071],"type":"Point"}
}