{
  "type": "Feature",
  "properties": {
    "iso:country":"CH",
    "sg:address":"Obere Kirchgasse 2",
    "sg:city":"Winterthur",
    "sg:orig_category":"Grosshandel mit Sportartikeln Herstellung von Reiseartikeln, Leder U Sattlerwaren",
    "sg:phone":"+41 52 213 61 30",
    "sg:postcode":"8400",
    "sg:province":"Z\u00fcrich",
    "wof:name":"Sunset, Hintermeister O.",
    "wof:placetype":"venue"
},
  "geometry": {"coordinates":[8.7294044495,47.4984016418],"type":"Point"}
}