{
  "type": "Feature",
  "properties": {
    "addr:full":"Industriestrasse 8 Altst\u00e4tten St. Gallen 9450",
    "addr:housenumber":"8;st.",
    "addr:postcode":"9450",
    "addr:street":"Industriestrasse",
    "iso:country":"CH",
    "sg:address":"Industriestrasse 8",
    "sg:city":"Altst\u00e4tten",
    "sg:classifiers":[
        {
            "category":"Banks & Credit Unions",
            "subcategory":"Investment Brokerage",
            "type":"Services"
        }
    ],
    "sg:phone":"+41 71 757 81 00",
    "sg:postcode":"9450",
    "sg:province":"St. Gallen",
    "sg:tags":[
        "plotter",
        "character",
        "cutter"
    ],
    "wof:name":"Z\u00fcnd Systemtechnik Ag",
    "wof:placetype":"venue"
},
  "geometry": {"coordinates":[9.557456,47.377987],"type":"Point"}
}