{
  "type": "Feature",
  "properties": {
    "iso:country":"CH",
    "sg:address":"Hauptstr. 70",
    "sg:city":"Lommis",
    "sg:orig_category":"Architektur U Ingenieurb\u00fcros",
    "sg:postcode":"9506",
    "sg:province":"Thurgau",
    "wof:name":"Steiner Peter, Dipl. Ing. Eth/sia",
    "wof:placetype":"venue"
},
  "geometry": {"coordinates":[7.493035,46.927734],"type":"Point"}
}