{
  "type": "Feature",
  "properties": {
    "iso:country":"CH",
    "sg:address":"Hornstrasse 2",
    "sg:city":"Gebenstorf",
    "sg:orig_category":"Allgemeiner Hoch U Tiefbau Allgemeiner Hochbau",
    "sg:phone":"+41 56 223 14 20",
    "sg:postcode":"5412",
    "sg:province":"Aargau",
    "wof:name":"Heinrich Pabst Bauunternehmung",
    "wof:placetype":"venue"
},
  "geometry": {"coordinates":[8.245907,47.481293],"type":"Point"}
}