{
  "type": "Feature",
  "properties": {
    "iso:country":"CH",
    "sg:address":"Hauptstrasse 41",
    "sg:city":"Herznach",
    "sg:orig_category":"Wirtschaftspr\u00fcfung, Steuerberatung U Treuhand",
    "sg:phone":"+41 62 878 19 45",
    "sg:postcode":"5027",
    "sg:province":"Aargau",
    "wof:name":"Km Treuhand Gmbh",
    "wof:placetype":"venue"
},
  "geometry": {"coordinates":[8.0511388779,47.4738960266],"type":"Point"}
}