{
  "type": "Feature",
  "properties": {
    "iso:country":"CH",
    "sg:address":"Rue De Morat 54",
    "sg:city":"Fribourg",
    "sg:classifiers":[
        {
            "category":"Restaurant",
            "type":"Food & Drink"
        }
    ],
    "sg:phone":"+41 22 342 07 98",
    "sg:postcode":"1700",
    "sg:province":"Fribourg",
    "wof:name":"Caf\u00e9-restaurant Stade",
    "wof:placetype":"venue"
},
  "geometry": {"coordinates":[6.1477608681,46.1848220825],"type":"Point"}
}