{
  "type": "Feature",
  "properties": {
    "iso:country":"CH",
    "sg:address":"Place Centrale 4",
    "sg:city":"Monthey",
    "sg:orig_category":"Arbeitnehmerverb\u00e4nde",
    "sg:phone":"+41 22 738 03 66",
    "sg:postcode":"1870",
    "sg:province":"Valais",
    "wof:name":"Sib Syndicat Industrie & B\u00e2timent",
    "wof:placetype":"venue"
},
  "geometry": {"coordinates":[6.14125,46.208096],"type":"Point"}
}