{
  "type": "Feature",
  "properties": {
    "iso:country":"CH",
    "sg:address":"Kreuzkapellenweg 2",
    "sg:city":"Wettingen",
    "sg:orig_category":"Innenarchitekturb\u00fcros",
    "sg:phone":"+41 56 426 36 26",
    "sg:postcode":"5430",
    "sg:province":"Aargau",
    "wof:name":"Toni Scherrer Innenarchitekturb\u00fcro",
    "wof:placetype":"venue"
},
  "geometry": {"coordinates":[8.3404970169,47.4604187012],"type":"Point"}
}