{
  "type": "Feature",
  "properties": {
    "iso:country":"CH",
    "sg:address":"Zielstrasse 38",
    "sg:city":"Appenzell",
    "sg:orig_category":"Fachdetailhandel in Verkaufsr\u00e4umen",
    "sg:postcode":"9050",
    "sg:province":"Appenzell Innerhoden",
    "wof:name":"The Fairway Store Ag",
    "wof:placetype":"venue"
},
  "geometry": {"coordinates":[9.4077110291,47.3339538574],"type":"Point"}
}