{
  "type": "Feature",
  "properties": {
    "iso:country":"CH",
    "sg:address":"St\u00e4dtli 9",
    "sg:city":"Wiedlisbach",
    "sg:orig_category":"Architekturb\u00fcros",
    "sg:phone":"+41 32 636 00 80",
    "sg:postcode":"4537",
    "sg:province":"Bern",
    "wof:name":"Daniel M\u00fcller Architekturb\u00fcro",
    "wof:placetype":"venue"
},
  "geometry": {"coordinates":[7.647372,47.252041],"type":"Point"}
}