{
  "type": "Feature",
  "properties": {
    "iso:country":"CH",
    "sg:address":"Blankweg 53",
    "sg:city":"Ostermundigen",
    "sg:orig_category":"Grosshandel mit Maschinen U Ausr\u00fcstungen Grosshandel mit sonstigen Maschinen U Ausr\u00fcstungen f\u00fcr Indu",
    "sg:phone":"+41 79 653 72 21",
    "sg:postcode":"3072",
    "sg:province":"Bern",
    "wof:name":"Kisslig Reinigungssysteme",
    "wof:placetype":"venue"
},
  "geometry": {"coordinates":[7.4923062325,46.9556083679],"type":"Point"}
}