{
  "type": "Feature",
  "properties": {
    "iso:country":"CH",
    "sg:address":"Chemin De La Rottaz",
    "sg:city":"Chailly-montreux",
    "sg:orig_category":"Grosshandel mit sonstigen Nahrungsmitteln",
    "sg:phone":"+41 21 964 41 40",
    "sg:postcode":"1816",
    "sg:province":"Vaud",
    "wof:name":"Fumoir De Chailly, Fopp Hans-martin",
    "wof:placetype":"venue"
},
  "geometry": {"coordinates":[6.899254,46.452003],"type":"Point"}
}