{
  "type": "Feature",
  "properties": {
    "iso:country":"CH",
    "sg:address":"Langr\u00fctistr. 3",
    "sg:city":"Thalwil",
    "sg:orig_category":"Freizeit, Sonstige Freizeitangebote",
    "sg:phone":"+41 17206140",
    "sg:postcode":"8800",
    "sg:province":"Z\u00fcrich",
    "wof:name":"Jungwacht & Blauring Thalwl",
    "wof:placetype":"venue"
},
  "geometry": {"coordinates":[8.559204,47.299942],"type":"Point"}
}