{
  "type": "Feature",
  "properties": {
    "iso:country":"CH",
    "sg:address":"Rosswiesstrasse 27",
    "sg:city":"Bubikon",
    "sg:orig_category":"Herstellung von Elektrizit\u00e4tsverteilungs U schalteinrichtungen",
    "sg:phone":"+41 61 722 06 04",
    "sg:postcode":"8608",
    "sg:province":"Z\u00fcrich",
    "wof:name":"Mezger Hugo, Dipl. Ing (fh), C2e Controls Consulting + Engineering",
    "wof:placetype":"venue"
},
  "geometry": {"coordinates":[7.5358901024,47.5069046021],"type":"Point"}
}