{
  "type": "Feature",
  "properties": {
    "iso:country":"CH",
    "sg:address":"Schmiedhof",
    "sg:city":"Reichenburg",
    "sg:orig_category":"RESTAURANTS: TEA-ROOMS",
    "sg:postcode":"8864",
    "sg:province":"Schwyz",
    "wof:name":"Remo's Gastro Impex Ag",
    "wof:placetype":"venue"
},
  "geometry": {"coordinates":[8.9886751175,47.1683540344],"type":"Point"}
}