{
  "type": "Feature",
  "properties": {
    "iso:country":"CH",
    "sg:address":"Hiterdorfstrasse 8",
    "sg:city":"Koblenz",
    "sg:orig_category":"Herstellung von Konstruktionsteilen, Fertigbauteilen U Ausbauelementen aus Holz",
    "sg:phone":"+41 56 246 12 30",
    "sg:postcode":"5322",
    "sg:province":"Aargau",
    "wof:name":"Carlin Lorenz Vorm. Schmid Frid",
    "wof:placetype":"venue"
},
  "geometry": {"coordinates":[8.2379341125,47.6092605591],"type":"Point"}
}