{
  "type": "Feature",
  "properties": {
    "iso:country":"CH",
    "sg:address":"Bleick 8",
    "sg:city":"Edlibach",
    "sg:orig_category":"Fernmeldedienste",
    "sg:postcode":"6313",
    "sg:province":"Zug",
    "wof:name":"Tele Consult Frank St\u00e4ubli, Telecommunications Consulting",
    "wof:placetype":"venue"
},
  "geometry": {"coordinates":[8.5687170029,47.1807785034],"type":"Point"}
}