{
  "type": "Feature",
  "properties": {
    "iso:country":"CH",
    "sg:address":"Bubenbergstrasse 22",
    "sg:city":"Thun",
    "sg:orig_category":"Stukkateurgewerbe, Gipserei U Verputzerei",
    "sg:phone":"+41 33 336 06 50",
    "sg:postcode":"3600",
    "sg:province":"Bern",
    "wof:name":"Burri Peter, Eidg. Dipl. Gipsermeister",
    "wof:placetype":"venue"
},
  "geometry": {"coordinates":[7.6163568497,46.7350387573],"type":"Point"}
}