{
  "type": "Feature",
  "properties": {
    "iso:country":"CH",
    "sg:address":"Aux Ch\u00eanes",
    "sg:city":"Oron-la-ville",
    "sg:orig_category":"Architektur U Ingenieurb\u00fcros",
    "sg:phone":"+41 21 907 79 54",
    "sg:postcode":"1610",
    "sg:province":"Vaud",
    "wof:name":"Butor Engineering, Eric Brand",
    "wof:placetype":"venue"
},
  "geometry": {"coordinates":[6.826364,46.569866],"type":"Point"}
}