{
  "type": "Feature",
  "properties": {
    "iso:country":"CH",
    "sg:address":"Kramgasse 71",
    "sg:city":"Bern",
    "sg:orig_category":"Detailhandel mit Schuhen",
    "sg:phone":"+41 31 311 05 52",
    "sg:postcode":"3011",
    "sg:province":"Bern",
    "wof:name":"Schuhhaus B\u00fcchler, Inhaber A. Hagen Schuhwaren Usw; Handel",
    "wof:placetype":"venue"
},
  "geometry": {"coordinates":[7.4487509727,46.9478378296],"type":"Point"}
}