{
  "type": "Feature",
  "properties": {
    "iso:country":"CH",
    "sg:address":"Hoftrog",
    "sg:city":"Muotathal",
    "sg:orig_category":"Detailhandel mit Getr\u00e4nken Einzelhandel mit Automobilteilen U Zubeh\u00f6r",
    "sg:phone":"+41 41 830 18 43",
    "sg:postcode":"6436",
    "sg:province":"Schwyz",
    "wof:name":"Josef Betschart Getr\u00e4nke Pneu Festmobiliar",
    "wof:placetype":"venue"
},
  "geometry": {"coordinates":[8.766834259,46.9762420654],"type":"Point"}
}