{
  "type": "Feature",
  "properties": {
    "iso:country":"CH",
    "sg:address":"Friloweg 504",
    "sg:city":"Huttwil",
    "sg:orig_category":"Elektroinstallation Selbst\u00e4ndige bildende K\u00fcnstler",
    "sg:phone":"+41 62 962 37 55",
    "sg:postcode":"4950",
    "sg:province":"Bern",
    "wof:name":"Von Arx Urs Gmbh",
    "wof:placetype":"venue"
},
  "geometry": {"coordinates":[7.8365359306,47.1164207458],"type":"Point"}
}