{
  "type": "Feature",
  "properties": {
    "iso:country":"CH",
    "sg:address":"Schaffhauserstrasse 175 8400 Winterthur. Postfach",
    "sg:city":"Winterthur",
    "sg:orig_category":"Verwaltung von Immobilien",
    "sg:phone":"+41 52 213 13 65",
    "sg:postcode":"8400",
    "sg:province":"Z\u00fcrich",
    "wof:name":"Zum Schneeberg Ernst C. Ag",
    "wof:placetype":"venue"
},
  "geometry": {"coordinates":[8.7223596573,47.5101699829],"type":"Point"}
}