{
  "type": "Feature",
  "properties": {
    "iso:country":"CH",
    "sg:address":"Achereggstrasse 2",
    "sg:city":"Stansstad",
    "sg:orig_category":"Mit dem Versicherungsgewerbe verbundene T\u00e4tigkeiten",
    "sg:phone":"+41 17133378",
    "sg:postcode":"6362",
    "sg:province":"Nidwalden",
    "wof:name":"Guntli & Partner",
    "wof:placetype":"venue"
},
  "geometry": {"coordinates":[8.5245666504,47.2923812866],"type":"Point"}
}