{
  "type": "Feature",
  "properties": {
    "iso:country":"CH",
    "sg:address":"Sch\u00f6nb\u00fchlweg 10",
    "sg:city":"Meggen",
    "sg:orig_category":"Vermietung U Verpachtung von eigenen Immobilien Vermittlung von Immobilien",
    "sg:phone":"+41 41 249 30 70",
    "sg:postcode":"6045",
    "sg:province":"Luzern",
    "wof:name":"Teamag Immobilien Ag",
    "wof:placetype":"venue"
},
  "geometry": {"coordinates":[8.3587493896,47.0420684814],"type":"Point"}
}