{
  "type": "Feature",
  "properties": {
    "iso:country":"CH",
    "sg:address":"Primelweg 13",
    "sg:city":"Bern",
    "sg:orig_category":"Bauschreinerei Herstellung von M\u00f6beln verschiedener Art",
    "sg:phone":"+41 31 302 55 22",
    "sg:postcode":"3004",
    "sg:province":"Bern",
    "wof:name":"Hawker M.",
    "wof:placetype":"venue"
},
  "geometry": {"coordinates":[7.443787,46.971855],"type":"Point"}
}