{
  "type": "Feature",
  "properties": {
    "iso:country":"CH",
    "sg:address":"Chamerstrasse 63",
    "sg:city":"Zug",
    "sg:orig_category":"Non-Classified Establishments",
    "sg:postcode":"6300",
    "sg:province":"Zug",
    "wof:name":"Golden Games Peter Schorno",
    "wof:placetype":"venue"
},
  "geometry": {"coordinates":[8.8604326248,47.2015228271],"type":"Point"}
}