{
  "type": "Feature",
  "properties": {
    "iso:country":"CH",
    "sg:address":"B\u00fcrenstrasse 62",
    "sg:city":"Leuzigen",
    "sg:orig_category":"Herstellung von Schrauben, Nieten, Ketten U Federn Herstellung von Zahnr\u00e4dern U Antriebselementen",
    "sg:phone":"+41 32 679 30 21",
    "sg:postcode":"3297",
    "sg:province":"Bern",
    "wof:name":"Aare Fahrzeug Ag",
    "wof:placetype":"venue"
},
  "geometry": {"coordinates":[7.4461340904,47.1745796204],"type":"Point"}
}