{
  "type": "Feature",
  "properties": {
    "iso:country":"CH",
    "sg:address":"Sch\u00f6nenbuchstrasse 49a",
    "sg:city":"Allschwil",
    "sg:orig_category":"Autogaragen Handelsvermittlung U Grosshandel mit Automobilteilen U Zubeh\u00f6r",
    "sg:phone":"+41 61 481 71 65",
    "sg:postcode":"4123",
    "sg:province":"Basel-Landschaft",
    "wof:name":"Mad\u00f6rin & Pellmont Ag Gotthelf-garage & Tankstelle",
    "wof:placetype":"venue"
},
  "geometry": {"coordinates":[7.531243,47.550766],"type":"Point"}
}