{
  "type": "Feature",
  "properties": {
    "iso:country":"CH",
    "sg:address":"Artherstrasse 44",
    "sg:city":"Immensee",
    "sg:orig_category":"Allgemeiner Hoch U Tiefbau Hoch U Tiefbau",
    "sg:phone":"+41 41 850 46 46",
    "sg:postcode":"6405",
    "sg:province":"Schwyz",
    "wof:name":"Vanoli C. Ag Bauunternehmung",
    "wof:placetype":"venue"
},
  "geometry": {"coordinates":[8.4588,47.09325],"type":"Point"}
}