{
  "type": "Feature",
  "properties": {
    "iso:country":"CH",
    "sg:address":"Grotzenm\u00fchlestrasse 32",
    "sg:city":"Einsiedeln",
    "sg:orig_category":"Sonstige mit der Informatik verbundene T\u00e4tigkeiten",
    "sg:phone":"+41 17716533",
    "sg:postcode":"8840",
    "sg:province":"Schwyz",
    "wof:name":"Rolf A. Staub",
    "wof:placetype":"venue"
},
  "geometry": {"coordinates":[8.5402507782,47.3279838562],"type":"Point"}
}