{
  "type": "Feature",
  "properties": {
    "addr:full":"Witzbergstrasse 25 Pf\u00e4ffikon Z\u00fcrich 8330",
    "addr:housenumber":"25",
    "addr:postcode":"8330",
    "addr:street":"Witzbergstrasse",
    "iso:country":"CH",
    "sg:address":"Witzbergstrasse 25",
    "sg:city":"Pf\u00e4ffikon",
    "sg:classifiers":[
        {
            "category":"Professional",
            "subcategory":"Testing Lab",
            "type":"Services"
        }
    ],
    "sg:phone":"+41 19521070",
    "sg:postcode":"8330",
    "sg:province":"Z\u00fcrich",
    "sg:tags":[
        "analytical",
        "laboratory",
        "balance"
    ],
    "wof:name":"Pesa Waagen Ag",
    "wof:placetype":"venue"
},
  "geometry": {"coordinates":[8.770265,47.368923],"type":"Point"}
}