{
  "type": "Feature",
  "properties": {
    "iso:country":"CH",
    "sg:address":"Neugasse 52 8005 Z\u00fcrich. Postfach 3165",
    "sg:city":"Z\u00fcrich",
    "sg:orig_category":"Herstellung von Tanks U Sammelbeh\u00e4ltern aus Metall",
    "sg:phone":"+41 12726343",
    "sg:postcode":"8031",
    "sg:province":"Z\u00fcrich",
    "wof:name":"Kayser Ag Tankrevisionen & -anlagen",
    "wof:placetype":"venue"
},
  "geometry": {"coordinates":[8.5296411514,47.3827972412],"type":"Point"}
}