{
  "type": "Feature",
  "properties": {
    "iso:country":"CH",
    "sg:address":"Holzstrasse 88",
    "sg:city":"Safenwil",
    "sg:orig_category":"Vereine Abstinenten",
    "sg:phone":"+41 62 797 12 88",
    "sg:postcode":"5745",
    "sg:province":"Aargau",
    "wof:name":"Guttemplerloge Froher Mut",
    "wof:placetype":"venue"
},
  "geometry": {"coordinates":[8.0042819977,47.3277664185],"type":"Point"}
}