{
  "type": "Feature",
  "properties": {
    "iso:country":"CH",
    "sg:address":"Hauptstrasse",
    "sg:city":"Algetshausen",
    "sg:orig_category":"Sonstige Institutionen des Sozialwesens ohne Beherbergung",
    "sg:phone":"+41 41 497 44 87",
    "sg:postcode":"9249",
    "sg:province":"St. Gallen",
    "wof:name":"La Leche Liga Stillberatung",
    "wof:placetype":"venue"
},
  "geometry": {"coordinates":[8.1827249527,47.0368156433],"type":"Point"}
}