{
  "type": "Feature",
  "properties": {
    "iso:country":"CH",
    "sg:address":"Stampfenbachstrasse 125",
    "sg:city":"Z\u00fcrich",
    "sg:orig_category":"Non-Classified Establishments",
    "sg:postcode":"8006",
    "sg:province":"Z\u00fcrich",
    "wof:name":"Dr.regula Dickenmann B\u00fcro F.angewandte Oekologie",
    "wof:placetype":"venue"
},
  "geometry": {"coordinates":[8.5397262573,47.3849449158],"type":"Point"}
}