{
  "type": "Feature",
  "properties": {
    "iso:country":"CH",
    "sg:address":"Industriestrasse 16",
    "sg:city":"Gunzgen",
    "sg:orig_category":"Autotransporte Fl\u00fcssigkeit Autotransporte international",
    "sg:phone":"+41 62 216 43 33",
    "sg:postcode":"4617",
    "sg:province":"Solothurn",
    "wof:name":"Fritz Heller Fl\u00fcssigtransporte",
    "wof:placetype":"venue"
},
  "geometry": {"coordinates":[7.829297,47.323418],"type":"Point"}
}