{
  "type": "Feature",
  "properties": {
    "iso:country":"CH",
    "sg:address":"Heimweg 4",
    "sg:city":"Oberkulm",
    "sg:orig_category":"Herstellung von Tanks U Sammelbeh\u00e4ltern aus Metall Reinigungsgewerbe",
    "sg:phone":"+41 62 776 27 27",
    "sg:postcode":"5727",
    "sg:province":"Aargau",
    "wof:name":"E. Hunziker Ag Tankrevisionen",
    "wof:placetype":"venue"
},
  "geometry": {"coordinates":[8.1156291962,47.3026313782],"type":"Point"}
}