{
  "type": "Feature",
  "properties": {
    "iso:country":"CH",
    "sg:address":"Avenue G\u00e9n.-guisan",
    "sg:city":"Sierre",
    "sg:orig_category":"Non-Classified Establishments",
    "sg:postcode":"3960",
    "sg:province":"Valais",
    "wof:name":"Tube Clean Gmbh",
    "wof:placetype":"venue"
},
  "geometry": {"coordinates":[8.8368453979,47.3006668091],"type":"Point"}
}