{
  "type": "Feature",
  "properties": {
    "iso:country":"CH",
    "sg:address":"Chemin De La Montagne 136",
    "sg:city":"Ch\u00eane-bougeries",
    "sg:orig_category":"Detailhandel mit Waren verschiedener Art, Hauptrichtung Nahrungsmittel",
    "sg:phone":"+41 22 348 39 41",
    "sg:postcode":"1224",
    "sg:province":"Gen\u00e8ve",
    "wof:name":"Coop Montagne",
    "wof:placetype":"venue"
},
  "geometry": {"coordinates":[6.2000060081,46.2046966553],"type":"Point"}
}