{
  "type": "Feature",
  "properties": {
    "iso:country":"CH",
    "sg:address":"Rue Du Pr\u00e9 10",
    "sg:city":"Yverdon-les-bains",
    "sg:orig_category":"RESTAURANTS: TEA-ROOMS",
    "sg:phone":"+41 24 425 42 82",
    "sg:postcode":"1400",
    "sg:province":"Vaud",
    "wof:name":"Pizzeria Don Camillo",
    "wof:placetype":"venue"
},
  "geometry": {"coordinates":[6.6384310722,46.779460907],"type":"Point"}
}