{
  "type": "Feature",
  "properties": {
    "iso:country":"CH",
    "sg:address":"Route Petite-corniche 15",
    "sg:city":"Lutry",
    "sg:orig_category":"Detailhandel mit Teppichen Verlegen von Fussboden",
    "sg:phone":"+41 21 791 20 14",
    "sg:postcode":"1095",
    "sg:province":"Vaud",
    "wof:name":"Anne-lise Clairet Tapis & Rideaux",
    "wof:placetype":"venue"
},
  "geometry": {"coordinates":[6.6958699226,46.5013961792],"type":"Point"}
}