{
  "type": "Feature",
  "properties": {
    "iso:country":"CH",
    "sg:address":"Aarestrasse 29",
    "sg:city":"Rupperswil",
    "sg:orig_category":"Datenverarbeitungsdienste Sonstige mit der Informatik verbundene T\u00e4tigkeiten",
    "sg:phone":"+41 62 897 52 76",
    "sg:postcode":"5102",
    "sg:province":"Aargau",
    "wof:name":"Swisswin Gmbh It - L\u00f6sungen, Webservices",
    "wof:placetype":"venue"
},
  "geometry": {"coordinates":[8.124108,47.407509],"type":"Point"}
}