{
  "type": "Feature",
  "properties": {
    "iso:country":"CH",
    "sg:address":"Via Al Mulino 26 6926 Montagnola. Postfach",
    "sg:city":"Pambio-noranco",
    "sg:orig_category":"G\u00fcterbef\u00f6rderung im Strassenverkehr",
    "sg:phone":"+41 91 994 71 53",
    "sg:postcode":"6915",
    "sg:province":"Ticino",
    "wof:name":"Giudici Daniele",
    "wof:placetype":"venue"
},
  "geometry": {"coordinates":[8.9169063568,45.981918335],"type":"Point"}
}