{
  "type": "Feature",
  "properties": {
    "iso:country":"CH",
    "sg:address":"1358",
    "sg:city":"Valeyres-rances",
    "sg:orig_category":"Lagerung",
    "sg:postcode":"1358",
    "sg:province":"Vaud",
    "wof:name":"Centre Collecteur Des C\u00e9r\u00e9ales De Valeyres-sous-rances Et Environs.",
    "wof:placetype":"venue"
},
  "geometry": {"coordinates":[6.5307450294,46.7602310181],"type":"Point"}
}