{
  "type": "Feature",
  "properties": {
    "iso:country":"CH",
    "sg:address":"Poststrasse",
    "sg:city":"Arosa",
    "sg:orig_category":"RESTAURANTS: TEA-ROOMS",
    "sg:postcode":"7050",
    "sg:province":"Graubunden",
    "wof:name":"Oreiller Martial.",
    "wof:placetype":"venue"
},
  "geometry": {"coordinates":[7.2124481201,46.0804595947],"type":"Point"}
}