{
  "type": "Feature",
  "properties": {
    "iso:country":"CH",
    "sg:address":"Ifangstrasse 76",
    "sg:city":"R\u00fcmlang",
    "sg:orig_category":"Sanit\u00e4r, Heizungs U L\u00fcftungsinstallation",
    "sg:phone":"+41 18180443",
    "sg:postcode":"8153",
    "sg:province":"Z\u00fcrich",
    "wof:name":"Reinli Kurt",
    "wof:placetype":"venue"
},
  "geometry": {"coordinates":[8.5360689163,47.4489974976],"type":"Point"}
}