{
  "type": "Feature",
  "properties": {
    "iso:country":"CH",
    "sg:address":"Neuengasse 24 3011 Bern. Postfach",
    "sg:city":"Bern",
    "sg:orig_category":"Fachdetailhandel in Verkaufsr\u00e4umen",
    "sg:postcode":"3005",
    "sg:province":"Bern",
    "wof:name":"Hans Omar Schneiter Schmuck, Edelsteine; Handel",
    "wof:placetype":"venue"
},
  "geometry": {"coordinates":[7.4423241615,46.9490394592],"type":"Point"}
}