{
  "type": "Feature",
  "properties": {
    "iso:country":"CH",
    "sg:address":"St-christophe",
    "sg:city":"Vich",
    "sg:orig_category":"Architekturb\u00fcros",
    "sg:phone":"+41 22 366 11 18",
    "sg:postcode":"1267",
    "sg:province":"Vaud",
    "wof:name":"Gabriel Poncet Bureau D'architecture Epfl Sia",
    "wof:placetype":"venue"
},
  "geometry": {"coordinates":[6.242109,46.433376],"type":"Point"}
}