{
  "type": "Feature",
  "properties": {
    "iso:country":"CH",
    "sg:address":"Rue De La Pontaise 31",
    "sg:city":"Lausanne",
    "sg:classifiers":[
        {
            "category":"Government",
            "subcategory":"Post Office",
            "type":"Public Place"
        }
    ],
    "sg:phone":"+41 21 646 81 46",
    "sg:postcode":"1018",
    "sg:province":"Vaud",
    "sg:tags":[
        "caf\u00e9s",
        "tea-rooms"
    ],
    "wof:name":"Bar \u00e0 Caf\u00e9 Le P\u00e9nalty",
    "wof:placetype":"venue"
},
  "geometry": {"coordinates":[6.6296281815,46.5302429199],"type":"Point"}
}