{
  "type": "Feature",
  "properties": {
    "addr:full":"Enzenb\u00fchlstrasse 91 Flawil St. Gallen 9230",
    "addr:housenumber":"91",
    "addr:postcode":"9230",
    "addr:street":"Enzenbuehlstrasse",
    "iso:country":"CH",
    "sg:address":"Enzenb\u00fchlstrasse 91",
    "sg:city":"Flawil",
    "sg:orig_category":"Buchf\u00fchrung Wirtschaftspr\u00fcfung, Steuerberatung U Treuhand",
    "sg:phone":"+41 71 393 83 61",
    "sg:postcode":"9230",
    "sg:province":"St. Gallen",
    "wof:name":"Metzger Elmar, Buchhaltungen",
    "wof:placetype":"venue"
},
  "geometry": {"coordinates":[9.17715,47.417168],"type":"Point"}
}