{
  "type": "Feature",
  "properties": {
    "iso:country":"CH",
    "sg:address":"Moserstrasse 15",
    "sg:city":"Bern",
    "sg:orig_category":"Arztpraxen",
    "sg:phone":"+41 71 385 95 85",
    "sg:postcode":"3014",
    "sg:province":"Bern",
    "wof:name":"Dr.med.angelika Stahlkopf Spezial\u00e4rztin Fmh",
    "wof:placetype":"venue"
},
  "geometry": {"coordinates":[9.268142,47.415264],"type":"Point"}
}