{
  "type": "Feature",
  "properties": {
    "iso:country":"CH",
    "sg:address":"Luthernmatte 6",
    "sg:city":"Nebikon",
    "sg:orig_category":"Detailhandel mit Musikinstrumenten Musikschulen and Konservatorien",
    "sg:phone":"+41 62 756 03 92",
    "sg:postcode":"6244",
    "sg:province":"Luzern",
    "wof:name":"Antonio Maiorano Musikfachgesch\u00e4ft Irpinia",
    "wof:placetype":"venue"
},
  "geometry": {"coordinates":[7.9740209579,47.1905403137],"type":"Point"}
}