{
  "type": "Feature",
  "properties": {
    "iso:country":"CH",
    "sg:address":"Harderstr. 35",
    "sg:city":"Interlaken",
    "sg:orig_category":"Non-Classified Establishments",
    "sg:postcode":"3800",
    "sg:province":"Bern",
    "wof:name":"Gartenbau K\u00fcnzli Ag",
    "wof:placetype":"venue"
},
  "geometry": {"coordinates":[7.8555989265,46.6881713867],"type":"Point"}
}