{
  "type": "Feature",
  "properties": {
    "iso:country":"CH",
    "sg:address":"Oberdorfstrasse 89",
    "sg:city":"D\u00fcbendorf",
    "sg:orig_category":"Sanit\u00e4r, Heizungs U L\u00fcftungsinstallation Sanit\u00e4rinstallation",
    "sg:phone":"+41 18210095",
    "sg:postcode":"8600",
    "sg:province":"Z\u00fcrich",
    "wof:name":"Sanit\u00e4r Ag, D\u00fcbendorf",
    "wof:placetype":"venue"
},
  "geometry": {"coordinates":[8.6217412949,47.3888969421],"type":"Point"}
}