{
  "type": "Feature",
  "properties": {
    "iso:country":"CH",
    "sg:address":"Vorstadt 4 8200 Schaffhausen. Postfach",
    "sg:city":"Schaffhausen",
    "sg:orig_category":"Reiseb\u00fcros U Reiseveranstalter",
    "sg:phone":"+41 12778111",
    "sg:postcode":"8201",
    "sg:province":"Schaffhausen",
    "wof:name":"Hotelplan Internationale Reiseorganisation Ag",
    "wof:placetype":"venue"
},
  "geometry": {"coordinates":[8.075630188,47.3880691528],"type":"Point"}
}