{
  "type": "Feature",
  "properties": {
    "iso:country":"CH",
    "sg:address":"Boulevard De P\u00e9rolles 38 1700 Fribourg. Postfach",
    "sg:city":"Fribourg",
    "sg:classifiers":[
        {
            "category":"Education",
            "subcategory":"Library",
            "type":"Public Place"
        }
    ],
    "sg:phone":"+41 26 426 42 22",
    "sg:postcode":"1705",
    "sg:province":"Fribourg",
    "sg:tags":[
        "u",
        "bibliotheken",
        "archive"
    ],
    "wof:name":"Biblioth\u00e8que St-paul",
    "wof:placetype":"venue"
},
  "geometry": {"coordinates":[7.15441,46.797398],"type":"Point"}
}