{
  "type": "Feature",
  "properties": {
    "iso:country":"CH",
    "sg:address":"Chemin De La Montagne 85",
    "sg:city":"Ch\u00eane-bougeries",
    "sg:orig_category":"Arztpraxen",
    "sg:phone":"+41 22 348 39 39",
    "sg:postcode":"1224",
    "sg:province":"Gen\u00e8ve",
    "wof:name":"Dr M\u00e9d. Claude Aubert M\u00e9decin Sp\u00e9cialiste Fmh",
    "wof:placetype":"venue"
},
  "geometry": {"coordinates":[6.200441,46.207043],"type":"Point"}
}