{
  "type": "Feature",
  "properties": {
    "iso:country":"CH",
    "sg:address":"H\u00fcnenbergstrasse 2",
    "sg:city":"Luzern",
    "sg:orig_category":"Detailhandel mit Radio U Fernsehger\u00e4ten",
    "sg:phone":"+41 41 420 02 51",
    "sg:postcode":"6006",
    "sg:province":"Luzern",
    "wof:name":"Ineichen Radio-tv-hifi-video. Radio, Fernseh, Hi-fi- U. Videoger\u00e4te; Handel U. Reparatur.",
    "wof:placetype":"venue"
},
  "geometry": {"coordinates":[8.3094968796,47.0620117188],"type":"Point"}
}