{
  "type": "Feature",
  "properties": {
    "iso:country":"CH",
    "sg:address":"Kasernenstrasse 2",
    "sg:city":"Herisau",
    "sg:classifiers":[
        {
            "category":"Professional",
            "subcategory":"Employment Agencies",
            "type":"Services"
        }
    ],
    "sg:phone":"+41 71 353 63 60",
    "sg:postcode":"9100",
    "sg:province":"Appenzell Ausserrhoden",
    "sg:tags":[
        "personal",
        "u",
        "stellenvermittlung"
    ],
    "wof:name":"Rav Regionales Arbeitsvermittlungszentrum",
    "wof:placetype":"venue"
},
  "geometry": {"coordinates":[9.2805452347,47.3856468201],"type":"Point"}
}