{
  "type": "Feature",
  "properties": {
    "iso:country":"CH",
    "sg:address":"Obergasse 3",
    "sg:city":"B\u00fclach",
    "sg:orig_category":"Vermietung U Verpachtung von eigenen Immobilien",
    "sg:postcode":"8180",
    "sg:province":"Z\u00fcrich",
    "wof:name":"Fran\u00e7ois Gabriele",
    "wof:placetype":"venue"
},
  "geometry": {"coordinates":[8.5417079926,47.5183372498],"type":"Point"}
}