{
  "type": "Feature",
  "properties": {
    "iso:country":"CH",
    "sg:address":"3954",
    "sg:city":"Leukerbad",
    "sg:orig_category":"Elektroinstallation Herstellung von Elektromotoren, Generatoren U Transformatoren",
    "sg:phone":"+41 79 310 49 33",
    "sg:postcode":"3954",
    "sg:province":"Valais",
    "wof:name":"Elektroh\u00fcs Ag",
    "wof:placetype":"venue"
},
  "geometry": {"coordinates":[7.7464680672,46.3153152466],"type":"Point"}
}