{
  "type": "Feature",
  "properties": {
    "iso:country":"CH",
    "sg:address":"Binzenmatt 7 6314 Unter\u00e4geri. Postfach 456",
    "sg:city":"Unter\u00e4geri",
    "sg:orig_category":"Rolladen- and Storenmontage",
    "sg:phone":"+41 41 750 58 18",
    "sg:postcode":"6314",
    "sg:province":"Zug",
    "wof:name":"Bruno Riedmann Storenbau",
    "wof:placetype":"venue"
},
  "geometry": {"coordinates":[8.57949543,47.1366615295],"type":"Point"}
}