{
  "type": "Feature",
  "properties": {
    "iso:country":"CH",
    "sg:address":"Chrummb\u00fcel",
    "sg:city":"Br\u00fctten",
    "sg:orig_category":"Grosshandel mit landwirtschaftlichen Maschinen U Ger\u00e4ten Herstellung von sonstigen landwirtschaftlic",
    "sg:phone":"+41 52 345 20 16",
    "sg:postcode":"8311",
    "sg:province":"Z\u00fcrich",
    "wof:name":"Baltensperger Farmtechnik Ag",
    "wof:placetype":"venue"
},
  "geometry": {"coordinates":[8.6632099152,47.4766082764],"type":"Point"}
}