{
  "type": "Feature",
  "properties": {
    "iso:country":"CH",
    "sg:address":"Vazerolgasse 2",
    "sg:city":"Chur",
    "sg:orig_category":"Architektur U Ingenieurb\u00fcros",
    "sg:postcode":"7000",
    "sg:province":"Graubunden",
    "wof:name":"Mercadi Ag",
    "wof:placetype":"venue"
},
  "geometry": {"coordinates":[9.532909,46.85059],"type":"Point"}
}