{
  "type": "Feature",
  "properties": {
    "iso:country":"CH",
    "sg:address":"Winkelriedstrasse 53",
    "sg:city":"Luzern",
    "sg:orig_category":"Softwareentwicklung U beratung",
    "sg:phone":"+41 41 210 53 10",
    "sg:postcode":"6003",
    "sg:province":"Luzern",
    "wof:name":"M2 Murray Mccreadie",
    "wof:placetype":"venue"
},
  "geometry": {"coordinates":[8.3075799942,47.046333313],"type":"Point"}
}