{
  "type": "Feature",
  "properties": {
    "iso:country":"CH",
    "sg:address":"Avenue Des P\u00e2quis 11",
    "sg:city":"Morges",
    "sg:orig_category":"Detailhandel mit Getr\u00e4nken",
    "sg:phone":"+41 21 803 26 30",
    "sg:postcode":"1110",
    "sg:province":"Vaud",
    "wof:name":"Isabelle Luparia La Cave Du Village",
    "wof:placetype":"venue"
},
  "geometry": {"coordinates":[6.4990878105,46.512336731],"type":"Point"}
}