{
  "type": "Feature",
  "properties": {
    "iso:country":"CH",
    "sg:address":"Viale Portone 5",
    "sg:city":"Bellinzona",
    "sg:orig_category":"Vermittlung von Immobilien Wirtschaftspr\u00fcfung, Steuerberatung U Treuhand",
    "sg:phone":"+41 22 791 08 50",
    "sg:postcode":"6500",
    "sg:province":"Ticino",
    "wof:name":"Michel Pasquier Bureau Fiduciaire",
    "wof:placetype":"venue"
},
  "geometry": {"coordinates":[6.1229338646,46.2303581238],"type":"Point"}
}