{
  "type": "Feature",
  "properties": {
    "iso:country":"CH",
    "sg:address":"Haus Dryas",
    "sg:city":"Arosa",
    "sg:classifiers":[
        {
            "category":"Education",
            "subcategory":"Library",
            "type":"Public Place"
        }
    ],
    "sg:phone":"+41 81 377 23 48",
    "sg:postcode":"7050",
    "sg:province":"Graubunden",
    "sg:tags":[
        "u",
        "bibliotheken",
        "archive"
    ],
    "wof:name":"Ludothek Arosa Herr U. Schurtenberger",
    "wof:placetype":"venue"
},
  "geometry": {"coordinates":[9.676552,46.777863],"type":"Point"}
}