{
  "type": "Feature",
  "properties": {
    "iso:country":"CH",
    "sg:address":"Hardaustrasse 5",
    "sg:city":"Z\u00fcrich",
    "sg:orig_category":"Detailhandel mit Tabakwaren Tabakverarbeitung",
    "sg:phone":"+41 12419036",
    "sg:postcode":"8003",
    "sg:province":"Z\u00fcrich",
    "wof:name":"Naegeli Zum Tabakfass Ag",
    "wof:placetype":"venue"
},
  "geometry": {"coordinates":[8.5095796585,47.377620697],"type":"Point"}
}