{
  "type": "Feature",
  "properties": {
    "iso:country":"CH",
    "sg:address":"Graben 31",
    "sg:city":"Aarau",
    "sg:orig_category":"Herstellung von Kakao, Schokoladeerzeugnissen U Zuckerwaren",
    "sg:phone":"+41 79 429 12 42",
    "sg:postcode":"5000",
    "sg:province":"Aargau",
    "wof:name":"Waldmeier Confiserie Tea-room Inh. Hofmann Rolf",
    "wof:placetype":"venue"
},
  "geometry": {"coordinates":[8.0450344086,47.3918914795],"type":"Point"}
}