{
  "type": "Feature",
  "properties": {
    "iso:country":"CH",
    "sg:address":"Hertensteinstrasse 62",
    "sg:city":"Luzern",
    "sg:orig_category":"Herstellung von Medikamenten U sonstigen pharmazeutischen Erzeugnissen Parf\u00fcmerien U sonstiger Detai",
    "sg:phone":"+41 41 410 96 48",
    "sg:postcode":"6004",
    "sg:province":"Luzern",
    "wof:name":"Alrodo Ag",
    "wof:placetype":"venue"
},
  "geometry": {"coordinates":[8.3069171906,47.0537834167],"type":"Point"}
}