{
  "type": "Feature",
  "properties": {
    "iso:country":"CH",
    "sg:address":"Au Mont",
    "sg:city":"Hermenches",
    "sg:orig_category":"Fahrschulen, Flugschulen",
    "sg:phone":"+41 79 310 10 44",
    "sg:postcode":"1513",
    "sg:province":"Vaud",
    "wof:name":"Raymond Porchet Auto-\u00e9cole",
    "wof:placetype":"venue"
},
  "geometry": {"coordinates":[6.7485427856,46.6343231201],"type":"Point"}
}