{
  "type": "Feature",
  "properties": {
    "iso:country":"CH",
    "sg:address":"Sattlaweg 9",
    "sg:city":"Frutigen",
    "sg:orig_category":"Herstellung von Hebezeugen U F\u00f6rdermitteln S\u00e4ge, Hobel U Holzimpr\u00e4gnierwerke",
    "sg:phone":"+41 34 409 02 01",
    "sg:postcode":"3714",
    "sg:province":"Bern",
    "wof:name":"Balz Holz Ag",
    "wof:placetype":"venue"
},
  "geometry": {"coordinates":[7.757589817,46.9491271973],"type":"Point"}
}