{
  "type": "Feature",
  "properties": {
    "iso:country":"CH",
    "sg:address":"Rue Du Puits-godet 8a",
    "sg:city":"Neuch\u00e2tel",
    "sg:orig_category":"Herstellung von Arbeits U Berufsbekleidung",
    "sg:phone":"+41 32 724 62 42",
    "sg:postcode":"2000",
    "sg:province":"Neuch\u00e2tel",
    "wof:name":"Ecw Network S\u00e0rl V\u00eatements Professionnels",
    "wof:placetype":"venue"
},
  "geometry": {"coordinates":[6.9140100479,46.9987220764],"type":"Point"}
}