{
  "type": "Feature",
  "properties": {
    "iso:country":"CH",
    "sg:address":"Maulbeerstrasse 12",
    "sg:city":"Basel",
    "sg:orig_category":"Fussboden, Fliesen U Plattenlegerei, Tapeziererei",
    "sg:postcode":"4058",
    "sg:province":"Basel-Stadt",
    "wof:name":"Rado Parkett Teppich, Djukic",
    "wof:placetype":"venue"
},
  "geometry": {"coordinates":[8.5419559479,47.2861709595],"type":"Point"}
}