{
  "type": "Feature",
  "properties": {
    "iso:country":"CH",
    "sg:address":"Kassenplatz",
    "sg:city":"Wiedlisbach",
    "sg:orig_category":"Kantonalbanken",
    "sg:phone":"+41 32 636 10 70",
    "sg:postcode":"4537",
    "sg:province":"Bern",
    "wof:name":"Berner Kantonalbank Bekb/bcbe",
    "wof:placetype":"venue"
},
  "geometry": {"coordinates":[7.646127224,47.2515182495],"type":"Point"}
}