{
  "type": "Feature",
  "properties": {
    "iso:country":"CH",
    "sg:address":"Route De Coppoz 5",
    "sg:city":"Mont-sur-lausanne",
    "sg:orig_category":"Architektur U Ingenieurb\u00fcros",
    "sg:phone":"+41 21 960 20 04",
    "sg:postcode":"1052",
    "sg:province":"Vaud",
    "wof:name":"Andr\u00e9 Fattebert Bureau Technique",
    "wof:placetype":"venue"
},
  "geometry": {"coordinates":[6.9262,46.397743],"type":"Point"}
}