{
  "type": "Feature",
  "properties": {
    "addr:full":"7157 Siat Graubunden 7157",
    "addr:housenumber":"7157",
    "addr:postcode":"7157",
    "addr:street":"Siat Graubunden",
    "iso:country":"CH",
    "sg:address":"7157",
    "sg:city":"Siat",
    "sg:orig_category":"Darlehenskassen U Raiffeisenbanken",
    "sg:phone":"+41 81 925 17 05",
    "sg:postcode":"7157",
    "sg:province":"Graubunden",
    "wof:name":"Raiffeisenbank",
    "wof:placetype":"venue"
},
  "geometry": {"coordinates":[9.162077,46.789879],"type":"Point"}
}