{
  "type": "Feature",
  "properties": {
    "iso:country":"CH",
    "sg:address":"Gigering 27",
    "sg:city":"Neunkirch",
    "sg:orig_category":"Non-Classified Establishments",
    "sg:phone":"+41 52 687 06 87",
    "sg:postcode":"8213",
    "sg:province":"Schaffhausen",
    "wof:name":"Hidrostal Holding Ag",
    "wof:placetype":"venue"
},
  "geometry": {"coordinates":[8.4911718369,47.6879692078],"type":"Point"}
}