{
  "type": "Feature",
  "properties": {
    "iso:country":"CH",
    "sg:address":"Granges Route De 2 3978 Flanthey. Postfach",
    "sg:city":"Flanthey",
    "sg:orig_category":"Unclassifiable Establishments",
    "sg:postcode":"3978",
    "sg:province":"Valais",
    "wof:name":"Web Wizards, Christen And Co",
    "wof:placetype":"venue"
},
  "geometry": {"coordinates":[7.4497947693,46.2690734863],"type":"Point"}
}