{
  "type": "Feature",
  "properties": {
    "iso:country":"CH",
    "sg:address":"Freiestrasse 2",
    "sg:city":"Grenchen",
    "sg:orig_category":"Interessenvertretungen",
    "sg:phone":"+41 32 652 50 22",
    "sg:postcode":"2540",
    "sg:province":"Solothurn",
    "wof:name":"Stiftung Grenchner Kunsthaus",
    "wof:placetype":"venue"
},
  "geometry": {"coordinates":[7.3983712196,47.1896514893],"type":"Point"}
}