{
  "type": "Feature",
  "properties": {
    "iso:country":"CH",
    "sg:address":"Schulhausstrasse 18 8706 Meilen. Postfach 732",
    "sg:city":"Meilen",
    "sg:orig_category":"Non-Classified Establishments",
    "sg:phone":"+41 19252033",
    "sg:postcode":"8706",
    "sg:province":"Z\u00fcrich",
    "wof:name":"Elektrizit\u00e4tswerke Des Kantons Z\u00fcrich (ekz) Eltop",
    "wof:placetype":"venue"
},
  "geometry": {"coordinates":[8.6416540146,47.2684555054],"type":"Point"}
}