{
  "type": "Feature",
  "properties": {
    "iso:country":"CH",
    "sg:address":"Rue Du Vingt-trois-juin 6",
    "sg:city":"Porrentruy",
    "sg:orig_category":"Offsetdruck Verlagsgewerbe",
    "sg:phone":"+41 32 466 10 84",
    "sg:postcode":"2900",
    "sg:province":"Jura",
    "wof:name":"Publicitas Sa",
    "wof:placetype":"venue"
},
  "geometry": {"coordinates":[7.0758628845,47.4170074463],"type":"Point"}
}