{
  "type": "Feature",
  "properties": {
    "iso:country":"CH",
    "sg:address":"Chemin De La Vuach\u00e8re 23",
    "sg:city":"Lausanne",
    "sg:orig_category":"Stukkateurgewerbe, Gipserei U Verputzerei",
    "sg:phone":"+41 21 729 42 44",
    "sg:postcode":"1012",
    "sg:province":"Vaud",
    "wof:name":"Willy Tonacini S\u00e0rl Pl\u00e2trerie & Peinture",
    "wof:placetype":"venue"
},
  "geometry": {"coordinates":[6.6541481018,46.5196151733],"type":"Point"}
}