{
  "type": "Feature",
  "properties": {
    "iso:country":"CH",
    "sg:address":"Untergasse 2",
    "sg:city":"Eglisau",
    "sg:orig_category":"RESTAURANTS: TEA-ROOMS",
    "sg:postcode":"8193",
    "sg:province":"Z\u00fcrich",
    "wof:name":"Julietta Restaurationsbetrieb Gmbh",
    "wof:placetype":"venue"
},
  "geometry": {"coordinates":[8.523979187,47.5757141113],"type":"Point"}
}