{
  "type": "Feature",
  "properties": {
    "iso:country":"CH",
    "sg:address":"Hauptstrasse",
    "sg:city":"Niederried Interl",
    "sg:classifiers":[
        {
            "category":"Banks & Credit Unions",
            "subcategory":"Bank",
            "type":"Services"
        }
    ],
    "sg:phone":"+41 61 795 96 96",
    "sg:postcode":"3853",
    "sg:province":"Bern",
    "wof:name":"Raiffeisenbank Nunningen-himmelried",
    "wof:placetype":"venue"
},
  "geometry": {"coordinates":[7.536927,47.210541],"type":"Point"}
}