{
  "type": "Feature",
  "properties": {
    "iso:country":"CH",
    "sg:address":"Grand-rue 44",
    "sg:city":"Lutry",
    "sg:orig_category":"Herstellung von Metallkonstruktionen Mechanik",
    "sg:phone":"+41 21 791 10 95",
    "sg:postcode":"1095",
    "sg:province":"Vaud",
    "wof:name":"Serrurerie Du Bourg Gasser Et Mauroux S\u00e0rl",
    "wof:placetype":"venue"
},
  "geometry": {"coordinates":[6.6860938072,46.5020523071],"type":"Point"}
}