{
  "type": "Feature",
  "properties": {
    "iso:country":"CH",
    "sg:address":"Magdenauer Strasse 2",
    "sg:city":"Flawil",
    "sg:orig_category":"Reiseb\u00fcros Reiseb\u00fcros U Reiseveranstalter",
    "sg:phone":"+41 22 820 32 47",
    "sg:postcode":"9230",
    "sg:province":"St. Gallen",
    "wof:name":"Antilles Evasions, Bischofberger Et Brunet",
    "wof:placetype":"venue"
},
  "geometry": {"coordinates":[6.1419038773,46.1851921082],"type":"Point"}
}