{
  "type": "Feature",
  "properties": {
    "iso:country":"CH",
    "sg:address":"Balmbergstrasse 39",
    "sg:city":"G\u00fcnsberg",
    "sg:orig_category":"Detailhandel mit Milcherzeugnissen U Eiern Verarbeitung von Milch",
    "sg:phone":"+41 32 637 15 22",
    "sg:postcode":"4524",
    "sg:province":"Solothurn",
    "wof:name":"Peter Michel K\u00e4serei",
    "wof:placetype":"venue"
},
  "geometry": {"coordinates":[7.5702300072,47.2578582764],"type":"Point"}
}