{
  "type": "Feature",
  "properties": {
    "iso:country":"CH",
    "sg:address":"7560",
    "sg:city":"Martina",
    "sg:orig_category":"Zoll- and Grenzb\u00fcros",
    "sg:phone":"+41 81 866 34 06",
    "sg:postcode":"7560",
    "sg:province":"Graubunden",
    "wof:name":"Eidg. Zollverwaltung",
    "wof:placetype":"venue"
},
  "geometry": {"coordinates":[10.4631204605,46.8840103149],"type":"Point"}
}