{
  "type": "Feature",
  "properties": {
    "iso:country":"CH",
    "sg:address":"Vogelneststrasse 13 8834 Schindellegi. Postfach",
    "sg:city":"Schindellegi",
    "sg:orig_category":"Detailhandel mit Teppichen Verlegen von Fussboden",
    "sg:phone":"+41 17847852",
    "sg:postcode":"8834",
    "sg:province":"Schwyz",
    "wof:name":"Indecor Ag",
    "wof:placetype":"venue"
},
  "geometry": {"coordinates":[8.7051134109,47.1790771484],"type":"Point"}
}