{
  "type": "Feature",
  "properties": {
    "iso:country":"CH",
    "sg:address":"Romanshornerstrasse 58",
    "sg:city":"Arbon",
    "sg:orig_category":"Kauf U Verkauf von Immobilien auf eigene Rechnung",
    "sg:phone":"+41 71 446 46 10",
    "sg:postcode":"9320",
    "sg:province":"Thurgau",
    "wof:name":"Eg Immobilien Ag",
    "wof:placetype":"venue"
},
  "geometry": {"coordinates":[9.4244642258,47.5192451477],"type":"Point"}
}