{
  "type": "Feature",
  "properties": {
    "iso:country":"CH",
    "sg:address":"Hofstrasse 7",
    "sg:city":"Zug",
    "sg:orig_category":"Softwareentwicklung U beratung",
    "sg:postcode":"6300",
    "sg:province":"Zug",
    "wof:name":"Softbee Gmbh Dienstleistungen Im Informatikbereich, Bes. Beratung U. Schulung",
    "wof:placetype":"venue"
},
  "geometry": {"coordinates":[7.2183871269,46.7895698547],"type":"Point"}
}