{
  "type": "Feature",
  "properties": {
    "iso:country":"CH",
    "sg:address":"Hauptstrasse 47 8840 Einsiedeln. Postfach 456",
    "sg:city":"Einsiedeln",
    "sg:orig_category":"Detailhandel mit B\u00fcchern, Zeitungen, Schreib U Papeteriewaren",
    "sg:postcode":"8840",
    "sg:province":"Schwyz",
    "wof:name":"Schnydrig Pierre, Kiosk-bazar",
    "wof:placetype":"venue"
},
  "geometry": {"coordinates":[7.791824,46.139481],"type":"Point"}
}