{
  "type": "Feature",
  "properties": {
    "iso:country":"CH",
    "sg:address":"Freiestrasse 96",
    "sg:city":"Z\u00fcrich",
    "sg:orig_category":"Chemische Reinigung W\u00e4schereien",
    "sg:phone":"+41 62 771 36 33",
    "sg:postcode":"8032",
    "sg:province":"Z\u00fcrich",
    "wof:name":"Kurt Wirz Textilreinigung & W\u00e4scherei",
    "wof:placetype":"venue"
},
  "geometry": {"coordinates":[8.189716,47.256718],"type":"Point"}
}