{
  "type": "Feature",
  "properties": {
    "iso:country":"CH",
    "sg:address":"Zugerstrasse 34",
    "sg:city":"Zufikon",
    "sg:orig_category":"G\u00fcterbef\u00f6rderung im Strassenverkehr",
    "sg:phone":"+41 56331476",
    "sg:postcode":"5621",
    "sg:province":"Aargau",
    "wof:name":"Stutz Ag",
    "wof:placetype":"venue"
},
  "geometry": {"coordinates":[8.356467247,47.3390274048],"type":"Point"}
}