{
  "type": "Feature",
  "properties": {
    "iso:country":"CH",
    "sg:address":"Via Baraggie 4",
    "sg:city":"Ascona",
    "sg:orig_category":"Zahnarztpraxen",
    "sg:phone":"+41 91 791 81 38",
    "sg:postcode":"6612",
    "sg:province":"Ticino",
    "wof:name":"Dottori Med.dent. K\u00f6lla Dentisti",
    "wof:placetype":"venue"
},
  "geometry": {"coordinates":[8.7714271545,46.1565284729],"type":"Point"}
}