{
  "type": "Feature",
  "properties": {
    "iso:country":"CH",
    "sg:address":"Marktpassage 7",
    "sg:city":"Grenchen",
    "sg:classifiers":[
        {
            "category":"Travel",
            "subcategory":"Hotels & Motels",
            "type":"Entertainment"
        }
    ],
    "sg:phone":"+41 32 654 20 10",
    "sg:postcode":"2540",
    "sg:province":"Solothurn",
    "sg:tags":[
        "hotels",
        "mit",
        "restaurant"
    ],
    "wof:name":"Stauffer Martin, Hotel Restaurant Passage",
    "wof:placetype":"venue"
},
  "geometry": {"coordinates":[7.3974871635,47.1938018799],"type":"Point"}
}