{
  "type": "Feature",
  "properties": {
    "iso:country":"CH",
    "sg:address":"Hofen",
    "sg:city":"Oeschenbach",
    "sg:orig_category":"Organisationen des Gesundheitswesen",
    "sg:phone":"+41 62 965 15 46",
    "sg:postcode":"4943",
    "sg:province":"Bern",
    "wof:name":"Samariterver.ursenbach & Umg.",
    "wof:placetype":"venue"
},
  "geometry": {"coordinates":[7.7549300194,47.1199493408],"type":"Point"}
}