{
  "type": "Feature",
  "properties": {
    "iso:country":"CH",
    "sg:address":"Oltnerstrasse 44",
    "sg:city":"Sch\u00f6nenwerd",
    "sg:orig_category":"Reiseb\u00fcros U Reiseveranstalter",
    "sg:phone":"+41 62 849 55 42",
    "sg:postcode":"5012",
    "sg:province":"Solothurn",
    "wof:name":"Thomi Travels",
    "wof:placetype":"venue"
},
  "geometry": {"coordinates":[8.001581192,47.3700485229],"type":"Point"}
}