{
  "type": "Feature",
  "properties": {
    "iso:country":"CH",
    "sg:address":"Kantonsstrasse 19",
    "sg:city":"Reichenburg",
    "sg:classifiers":[
        {
            "category":"Travel",
            "subcategory":"Hotels & Motels",
            "type":"Entertainment"
        }
    ],
    "sg:phone":"+41 55 444 13 50",
    "sg:postcode":"8864",
    "sg:province":"Schwyz",
    "sg:tags":[
        "hotels",
        "mit",
        "restaurant"
    ],
    "wof:name":"Hotel Hirschen",
    "wof:placetype":"venue"
},
  "geometry": {"coordinates":[8.9742975235,47.170753479],"type":"Point"}
}