{
  "type": "Feature",
  "properties": {
    "iso:country":"CH",
    "sg:address":"Aargauerstrasse 1 6215 Berom\u00fcnster. Postfach 70",
    "sg:city":"Berom\u00fcnster",
    "sg:orig_category":"Detailhandel mit Damenbekleidung Grosshandel mit Textilien",
    "sg:phone":"+41 41 930 13 25",
    "sg:postcode":"6215",
    "sg:province":"Luzern",
    "wof:name":"Modehaus Wicky Ag",
    "wof:placetype":"venue"
},
  "geometry": {"coordinates":[8.191283226,47.2070770264],"type":"Point"}
}