{
  "type": "Feature",
  "properties": {
    "iso:country":"CH",
    "sg:address":"Neuve-du-molard Rue 16 1204 Gen\u00e8ve. Postfach",
    "sg:city":"Gen\u00e8ve",
    "sg:orig_category":"Maler U Glasergewerbe",
    "sg:phone":"+41 22 342 00 77",
    "sg:postcode":"1204",
    "sg:province":"Gen\u00e8ve",
    "wof:name":"Entreprise Ajeti D\u00e9coration Entreprise De Peinture, Gypserie Et D\u00e9coration",
    "wof:placetype":"venue"
},
  "geometry": {"coordinates":[6.1449508667,46.1852264404],"type":"Point"}
}