{
  "type": "Feature",
  "properties": {
    "iso:country":"CH",
    "sg:address":"Spitelstrasse 2",
    "sg:city":"Weesen",
    "sg:classifiers":[
        {
            "category":"Restaurant",
            "type":"Food & Drink"
        }
    ],
    "sg:phone":"+41 55 616 12 43",
    "sg:postcode":"8872",
    "sg:province":"St. Gallen",
    "wof:name":"Restaurant Freieck",
    "wof:placetype":"venue"
},
  "geometry": {"coordinates":[9.0949010849,47.1344451904],"type":"Point"}
}