{
  "type": "Feature",
  "properties": {
    "addr:full":"Via Del Carmagnola 9 Arbedo Ticino 6517",
    "addr:housenumber":"9",
    "addr:postcode":"6517",
    "addr:street":"Via Del Carmagnola",
    "iso:country":"CH",
    "sg:address":"Via Del Carmagnola 9",
    "sg:city":"Arbedo",
    "sg:orig_category":"Autogaragen",
    "sg:phone":"+41 91 829 10 89",
    "sg:postcode":"6517",
    "sg:province":"Ticino",
    "wof:name":"Proteo Sa Garage",
    "wof:placetype":"venue"
},
  "geometry": {"coordinates":[9.048267,46.217056],"type":"Point"}
}