{
  "type": "Feature",
  "properties": {
    "iso:country":"CH",
    "sg:address":"Muristrasse 26",
    "sg:city":"Ottenbach",
    "sg:orig_category":"Detailhandel mit Fleisch U Fleischwaren",
    "sg:phone":"+41 17612105",
    "sg:postcode":"8913",
    "sg:province":"Z\u00fcrich",
    "wof:name":"Aregger Metzgerei",
    "wof:placetype":"venue"
},
  "geometry": {"coordinates":[8.400179863,47.2812576294],"type":"Point"}
}