{
  "type": "Feature",
  "properties": {
    "iso:country":"CH",
    "sg:address":"Luisenstrasse 46",
    "sg:city":"Bern",
    "sg:orig_category":"Vermittlung von Immobilien Verwaltung von Immobilien",
    "sg:phone":"+41 31 352 86 86",
    "sg:postcode":"3005",
    "sg:province":"Bern",
    "wof:name":"Peppino Vicini Dipl. Architekt Eth Sia",
    "wof:placetype":"venue"
},
  "geometry": {"coordinates":[7.4530391693,46.9404335022],"type":"Point"}
}