{
  "type": "Feature",
  "properties": {
    "addr:full":"Talstrasse 40 Schaffhausen Schaffhausen 8200",
    "addr:housenumber":"40",
    "addr:postcode":"8200",
    "addr:street":"Talstrasse",
    "iso:country":"CH",
    "sg:address":"Talstrasse 40",
    "sg:city":"Schaffhausen",
    "sg:orig_category":"Bauschreinerei Herstellung von Konstruktionsteilen, Fertigbauteilen U Ausbauelementen aus Holz",
    "sg:phone":"+41 79 636 91 35",
    "sg:postcode":"8200",
    "sg:province":"Schaffhausen",
    "wof:name":"Andrea Fliri",
    "wof:placetype":"venue"
},
  "geometry": {"coordinates":[10.408041,46.609097],"type":"Point"}
}