{
  "type": "Feature",
  "properties": {
    "iso:country":"CH",
    "sg:address":"Route A\u00e9roport 31",
    "sg:city":"Gen\u00e8ve",
    "sg:classifiers":[
        {
            "category":"Banks & Credit Unions",
            "subcategory":"Bank",
            "type":"Services"
        }
    ],
    "sg:phone":"+41 22 798 56 72",
    "sg:postcode":"1215",
    "sg:province":"Gen\u00e8ve",
    "wof:name":"Union Bank Of Switzerland",
    "wof:placetype":"venue"
},
  "geometry": {"coordinates":[6.11052,46.235802],"type":"Point"}
}