{
  "type": "Feature",
  "properties": {
    "iso:country":"CH",
    "sg:address":"Hardstrasse 32",
    "sg:city":"Pratteln",
    "sg:orig_category":"Grosshandel mit Holz U Baustoffen",
    "sg:phone":"+41 21 841 10 43",
    "sg:postcode":"4133",
    "sg:province":"Basel-Landschaft",
    "wof:name":"Rochat Olivier",
    "wof:placetype":"venue"
},
  "geometry": {"coordinates":[6.2822909355,46.6275558472],"type":"Point"}
}