{
  "type": "Feature",
  "properties": {
    "iso:country":"CH",
    "sg:address":"Hauptstrasse 7",
    "sg:city":"Utzenstorf",
    "sg:orig_category":"Bauschreinerei Herstellung von M\u00f6beln verschiedener Art",
    "sg:phone":"+41 71 311 35 79",
    "sg:postcode":"3427",
    "sg:province":"Bern",
    "wof:name":"Sennhauser Ren\u00e9",
    "wof:placetype":"venue"
},
  "geometry": {"coordinates":[9.322078,47.416367],"type":"Point"}
}