{
  "type": "Feature",
  "properties": {
    "iso:country":"CH",
    "sg:address":"Pl. Du Tilleul 9 1630 Bulle. Postfach",
    "sg:city":"Bulle",
    "sg:orig_category":"Pensionskassen",
    "sg:phone":"+41 26 912 81 91",
    "sg:postcode":"1630",
    "sg:province":"Fribourg",
    "wof:name":"Fonds Patronal En Faveur Du Personnel De Salami S.a.",
    "wof:placetype":"venue"
},
  "geometry": {"coordinates":[7.0663948059,46.6079711914],"type":"Point"}
}