{
  "type": "Feature",
  "properties": {
    "iso:country":"CH",
    "sg:address":"Kreuzzelgstrasse 9",
    "sg:city":"Mellingen",
    "sg:orig_category":"Non-Classified Establishments",
    "sg:postcode":"5507",
    "sg:province":"Aargau",
    "wof:name":"Gregori Water Technologies Wassernachbehandlungstechnik; Beratung, Projektierung Und Verkauf Usw",
    "wof:placetype":"venue"
},
  "geometry": {"coordinates":[8.2730369568,47.4135284424],"type":"Point"}
}