{
  "type": "Feature",
  "properties": {
    "iso:country":"CH",
    "sg:address":"Bahnhofstrasse 118",
    "sg:city":"M\u00f6hlin",
    "sg:orig_category":"Kauf U Verkauf von Immobilien auf eigene Rechnung",
    "sg:postcode":"4313",
    "sg:province":"Aargau",
    "wof:name":"Provica Immobilien Ag",
    "wof:placetype":"venue"
},
  "geometry": {"coordinates":[7.847219944,47.5546684265],"type":"Point"}
}