{
  "type": "Feature",
  "properties": {
    "iso:country":"CH",
    "sg:address":"Avenue De Morges 157 1000 Lausanne. Postfach",
    "sg:city":"Lausanne",
    "sg:orig_category":"Erbringung von Dienstleistungen f\u00fcr Unternehmen",
    "sg:postcode":"1003",
    "sg:province":"Vaud",
    "wof:name":"F\u00eate Des Jeux Menthonnex B.",
    "wof:placetype":"venue"
},
  "geometry": {"coordinates":[6.610970974,46.5262184143],"type":"Point"}
}