{
  "type": "Feature",
  "properties": {
    "iso:country":"CH",
    "sg:address":"Chilehalde 23",
    "sg:city":"Rain",
    "sg:orig_category":"Sportvereine Sch\u00fctzen Pistolen-& Gewehr",
    "sg:postcode":"6026",
    "sg:province":"Luzern",
    "wof:name":"Pistolensekt.d.feldsch\u00fctzeng.",
    "wof:placetype":"venue"
},
  "geometry": {"coordinates":[8.2557401657,47.1290283203],"type":"Point"}
}