{
  "type": "Feature",
  "properties": {
    "iso:country":"CH",
    "sg:address":"Gewerbestrasse 2",
    "sg:city":"Stadel(winterthur)",
    "sg:orig_category":"Unclassifiable Establishments",
    "sg:postcode":"8404",
    "sg:province":"Z\u00fcrich",
    "wof:name":"J. Kremser Services",
    "wof:placetype":"venue"
},
  "geometry": {"coordinates":[8.4592990875,47.4532356262],"type":"Point"}
}