{
  "type": "Feature",
  "properties": {
    "iso:country":"CH",
    "sg:address":"Rue Fleury 5",
    "sg:city":"Neuch\u00e2tel",
    "sg:orig_category":"Detailhandel mit Uhren U Schmuck Fachdetailhandel in Verkaufsr\u00e4umen",
    "sg:phone":"+41 32 724 14 21",
    "sg:postcode":"2000",
    "sg:province":"Neuch\u00e2tel",
    "wof:name":"Poget Pierre & Cie",
    "wof:placetype":"venue"
},
  "geometry": {"coordinates":[6.9283919334,46.9915161133],"type":"Point"}
}