{
  "type": "Feature",
  "properties": {
    "addr:full":"Rue Pr\u00e9-du-march\u00e9 23 Lausanne Vaud 1004",
    "addr:housenumber":"23",
    "addr:postcode":"1004",
    "addr:street":"Rue Pre\u0301-Du-Marche\u0301",
    "iso:country":"CH",
    "sg:address":"Rue Pr\u00e9-du-march\u00e9 23",
    "sg:city":"Lausanne",
    "sg:orig_category":"Softwareentwicklung U beratung",
    "sg:phone":"+41 71 274 20 50",
    "sg:postcode":"1004",
    "sg:province":"Vaud",
    "wof:name":"Cmsys Ag, St. Gallen Computer-programm-erstellung Usw",
    "wof:placetype":"venue"
},
  "geometry": {"coordinates":[9.334637,47.401894],"type":"Point"}
}