{
  "type": "Feature",
  "properties": {
    "addr:full":"Avenue Max Huber 10 3960 Sierre. Postfach Sierre Valais 3960",
    "addr:housenumber":"10",
    "addr:postcode":"3960 sierre. postfach;3960",
    "addr:street":"Avenue Max Huber",
    "iso:country":"CH",
    "sg:address":"Avenue Max Huber 10 3960 Sierre. Postfach",
    "sg:city":"Sierre",
    "sg:orig_category":"Architekturb\u00fcros",
    "sg:phone":"+41 27 455 17 58",
    "sg:postcode":"3960",
    "sg:province":"Valais",
    "wof:name":"Andr\u00e9 Zufferey Bureau D'architecture",
    "wof:placetype":"venue"
},
  "geometry": {"coordinates":[7.535605,46.293888],"type":"Point"}
}