{
  "type": "Feature",
  "properties": {
    "iso:country":"CH",
    "sg:address":"Malerweg 4",
    "sg:city":"Thun",
    "sg:orig_category":"Architektur U Ingenieurb\u00fcros",
    "sg:phone":"+41 79 414 29 73",
    "sg:postcode":"3600",
    "sg:province":"Bern",
    "wof:name":"Gut Bozzola + Partner Ag",
    "wof:placetype":"venue"
},
  "geometry": {"coordinates":[8.44671,47.277473],"type":"Point"}
}