{
  "type": "Feature",
  "properties": {
    "addr:full":"Zwidellen 2 Frick Aargau 5070",
    "addr:housenumber":"2",
    "addr:postcode":"5070",
    "addr:street":"Zwidellen",
    "iso:country":"CH",
    "sg:address":"Zwidellen 2",
    "sg:city":"Frick",
    "sg:orig_category":"Arztpraxen",
    "sg:phone":"+41 62 871 85 00",
    "sg:postcode":"5070",
    "sg:province":"Aargau",
    "wof:name":"Dr.med.felix Zumsteg Arzt F.allgemeine Medizin Fmh",
    "wof:placetype":"venue"
},
  "geometry": {"coordinates":[8.019861,47.50753],"type":"Point"}
}