{
  "type": "Feature",
  "properties": {
    "iso:country":"CH",
    "sg:address":"Am Schilt",
    "sg:city":"Wengen",
    "sg:orig_category":"Sanit\u00e4r U Heizungsinstallation Sanit\u00e4r, Heizungs U L\u00fcftungsinstallation",
    "sg:phone":"+41 33 855 14 55",
    "sg:postcode":"3823",
    "sg:province":"Bern",
    "wof:name":"Kurt K\u00fcbli Ag Sanit\u00e4re Anlagen Zentralheizungen \u00d6lf\u00fchrungen Reparaturservice",
    "wof:placetype":"venue"
},
  "geometry": {"coordinates":[7.9220399857,46.6074905396],"type":"Point"}
}