{
  "type": "Feature",
  "properties": {
    "iso:country":"CH",
    "sg:address":"Konsumweg 3",
    "sg:city":"Oberburg",
    "sg:orig_category":"Verarbeitung U Konservierung von Kartoffeln",
    "sg:phone":"+41 34 420 53 57",
    "sg:postcode":"3414",
    "sg:province":"Bern",
    "wof:name":"Fripo Sa Liegenschaften & Verwaltung",
    "wof:placetype":"venue"
},
  "geometry": {"coordinates":[7.6272878647,47.0391464233],"type":"Point"}
}