{
  "type": "Feature",
  "properties": {
    "iso:country":"CH",
    "sg:address":"Feldstrasse 9215 Sch\u00f6nenberg Tg. Postfach 32",
    "sg:city":"Kradolf",
    "sg:orig_category":"Sonstige Weberei Textilgewerbe",
    "sg:phone":"+41 71 642 45 30",
    "sg:postcode":"9214",
    "sg:province":"Thurgau",
    "wof:name":"Badertscher P. Ag",
    "wof:placetype":"venue"
},
  "geometry": {"coordinates":[9.1996498108,47.5189666748],"type":"Point"}
}