{
  "type": "Feature",
  "properties": {
    "iso:country":"CH",
    "sg:address":"9427",
    "sg:city":"Wolfhalden",
    "sg:orig_category":"Sportvereine Sch\u00fctzen",
    "sg:postcode":"9427",
    "sg:province":"Appenzell Ausserrhoden",
    "wof:name":"Standsch\u00fctzengesellschaft",
    "wof:placetype":"venue"
},
  "geometry": {"coordinates":[9.5497522354,47.453414917],"type":"Point"}
}