{
  "type": "Feature",
  "properties": {
    "iso:country":"CH",
    "sg:address":"Route Des Ronquoz 120",
    "sg:city":"Sion",
    "sg:orig_category":"Instandhaltung U Reparatur von Automobilen",
    "sg:phone":"+41 27 322 24 55",
    "sg:postcode":"1950",
    "sg:province":"Valais",
    "wof:name":"Garage De La Plaine, Bisolfati Fr\u00e8res",
    "wof:placetype":"venue"
},
  "geometry": {"coordinates":[7.3519630432,46.2221260071],"type":"Point"}
}