{
  "type": "Feature",
  "properties": {
    "iso:country":"CH",
    "sg:address":"6276",
    "sg:city":"Hohenrain",
    "sg:orig_category":"Verarbeitung von Milch Verwertung von Milch",
    "sg:postcode":"6276",
    "sg:province":"Luzern",
    "wof:name":"K\u00e4sereigenossenschaft Unterebersol",
    "wof:placetype":"venue"
},
  "geometry": {"coordinates":[8.3156652451,47.1791915894],"type":"Point"}
}