{
  "type": "Feature",
  "properties": {
    "iso:country":"CH",
    "sg:address":"2732",
    "sg:city":"Reconvilier",
    "sg:orig_category":"RESTAURANTS: TEA-ROOMS",
    "sg:phone":"+41 32 866 12 65",
    "sg:postcode":"2732",
    "sg:province":"Bern",
    "wof:name":"Rey P.-e",
    "wof:placetype":"venue"
},
  "geometry": {"coordinates":[6.4590067863,46.9147453308],"type":"Point"}
}