{
  "type": "Feature",
  "properties": {
    "iso:country":"CH",
    "sg:address":"Via Sturetscha Surlej 7513 Silvaplana. Postfach",
    "sg:city":"Silvaplana",
    "sg:orig_category":"Unternehmensberatung",
    "sg:phone":"+41 81 834 32 92",
    "sg:postcode":"7513",
    "sg:province":"Graubunden",
    "wof:name":"Tommasini Piero Consulting Unternehmensberatung Usw",
    "wof:placetype":"venue"
},
  "geometry": {"coordinates":[9.8395700455,46.4299850464],"type":"Point"}
}