{
  "type": "Feature",
  "properties": {
    "iso:country":"CH",
    "sg:address":"Hauptstrasse 1050",
    "sg:city":"Wolfhalden",
    "sg:orig_category":"Sportvereine Sch\u00fctzen Pistolen-& Gewehr",
    "sg:phone":"+41 71 891 45 88",
    "sg:postcode":"9427",
    "sg:province":"Appenzell Ausserrhoden",
    "wof:name":"Pistolenschiessverein Heiden",
    "wof:placetype":"venue"
},
  "geometry": {"coordinates":[9.5497522354,47.453414917],"type":"Point"}
}