{
  "type": "Feature",
  "properties": {
    "iso:country":"CH",
    "sg:address":"Herdernstrasse 56",
    "sg:city":"Z\u00fcrich",
    "sg:orig_category":"RESTAURANTS: TEA-ROOMS",
    "sg:postcode":"8001",
    "sg:province":"Z\u00fcrich",
    "wof:name":"Bbs Gastro Ag",
    "wof:placetype":"venue"
},
  "geometry": {"coordinates":[8.5059690475,47.3829498291],"type":"Point"}
}