{
  "type": "Feature",
  "properties": {
    "iso:country":"CH",
    "sg:address":"Cassarinetta Via 21",
    "sg:city":"Lugano",
    "sg:orig_category":"Herstellung von Maschinen f\u00fcr die Textil, Bekleidungsherstellung U die Lederverarbeitung",
    "sg:postcode":"6900",
    "sg:province":"Ticino",
    "wof:name":"Officina Desmo Salati E.",
    "wof:placetype":"venue"
},
  "geometry": {"coordinates":[8.9411287308,45.9913139343],"type":"Point"}
}