{
  "type": "Feature",
  "properties": {
    "iso:country":"CH",
    "sg:address":"Olmishausen",
    "sg:city":"Steinebrunn",
    "sg:orig_category":"Unclassifiable Establishments",
    "sg:postcode":"9314",
    "sg:province":"Thurgau",
    "wof:name":"Oepfelfarm Gmbh",
    "wof:placetype":"venue"
},
  "geometry": {"coordinates":[9.3482151031,47.5336685181],"type":"Point"}
}