{
  "type": "Feature",
  "properties": {
    "iso:country":"CH",
    "sg:address":"Samstagernstrasse 18",
    "sg:city":"Wollerau",
    "sg:orig_category":"Zimmerei, Dachdeckerei, Bauspenglerei U Abdichtung Zimmerei, Ingenieurholzbau",
    "sg:phone":"+41 17861563",
    "sg:postcode":"8832",
    "sg:province":"Schwyz",
    "wof:name":"Ott Holzbau",
    "wof:placetype":"venue"
},
  "geometry": {"coordinates":[8.7111196518,47.1903915405],"type":"Point"}
}