{
  "type": "Feature",
  "properties": {
    "iso:country":"CH",
    "sg:address":"Birmensdorferstrasse 16a",
    "sg:city":"Urdorf",
    "sg:orig_category":"Geb\u00e4ude, Wohnungsreinigung",
    "sg:phone":"+41 22 342 53 85",
    "sg:postcode":"8902",
    "sg:province":"Z\u00fcrich",
    "wof:name":"A. Andr\u00e9 Entreprise De Nettoyage",
    "wof:placetype":"venue"
},
  "geometry": {"coordinates":[6.1321501732,46.1877593994],"type":"Point"}
}