{
  "type": "Feature",
  "properties": {
    "iso:country":"CH",
    "sg:address":"Wiesentalstrasse 12",
    "sg:city":"Oberuzwil",
    "sg:orig_category":"Bauspenglerei Sanit\u00e4rinstallation",
    "sg:phone":"+41 71 951 54 64",
    "sg:postcode":"9242",
    "sg:province":"St. Gallen",
    "wof:name":"Bruno Wirth San.installationen,spenglerei",
    "wof:placetype":"venue"
},
  "geometry": {"coordinates":[9.12508,47.430134],"type":"Point"}
}