{
  "type": "Feature",
  "properties": {
    "iso:country":"CH",
    "sg:address":"Via Pioda 27",
    "sg:city":"Locarno",
    "sg:orig_category":"Religi\u00f6se Vereinigungen",
    "sg:phone":"+41 91 751 34 37",
    "sg:postcode":"6600",
    "sg:province":"Ticino",
    "wof:name":"Fondazione Chiesa Sacra Famiglia, Locarno",
    "wof:placetype":"venue"
},
  "geometry": {"coordinates":[8.8003940582,46.1705741882],"type":"Point"}
}