{
  "type": "Feature",
  "properties": {
    "iso:country":"CH",
    "sg:address":"Rue Louis-duchosal 6 1200 Gen\u00e8ve. Postfach",
    "sg:city":"Gen\u00e8ve",
    "sg:orig_category":"Herstellung von W\u00e4sche",
    "sg:phone":"+41 22 736 93 43",
    "sg:postcode":"1207",
    "sg:province":"Gen\u00e8ve",
    "wof:name":"Ottomani Claudia Et Raymond",
    "wof:placetype":"venue"
},
  "geometry": {"coordinates":[6.1555609703,46.2016868591],"type":"Point"}
}