{
  "type": "Feature",
  "properties": {
    "iso:country":"CH",
    "sg:address":"Sihlbruggstrasse 6345 Neuheim. Postfach 75",
    "sg:city":"Neuheim",
    "sg:orig_category":"Gewinnung von Kies U Sand Herstellung von Transportbeton",
    "sg:phone":"+41 52 315 19 13",
    "sg:postcode":"6345",
    "sg:province":"Zug",
    "wof:name":"Schneider Beton Ag",
    "wof:placetype":"venue"
},
  "geometry": {"coordinates":[8.6812343597,47.5417976379],"type":"Point"}
}