{
  "type": "Feature",
  "properties": {
    "iso:country":"CH",
    "sg:address":"Rue De La Cit\u00e9 10",
    "sg:city":"Chavornay",
    "sg:orig_category":"Malerei Stukkateurgewerbe, Gipserei U Verputzerei",
    "sg:phone":"+41 21 691 21 03",
    "sg:postcode":"1373",
    "sg:province":"Vaud",
    "wof:name":"Luigi De Cagna Pl\u00e2trerie & Peinture",
    "wof:placetype":"venue"
},
  "geometry": {"coordinates":[6.5646429062,46.5298881531],"type":"Point"}
}