{
  "type": "Feature",
  "properties": {
    "iso:country":"CH",
    "sg:address":"Br\u00fcggstrasse 1",
    "sg:city":"Biel/bienne",
    "sg:orig_category":"Zahnarztpraxen",
    "sg:phone":"+41 32 365 92 72",
    "sg:postcode":"2503",
    "sg:province":"Bern",
    "wof:name":"Dr. Med. Dent. Erwin Hess Zahnarzt",
    "wof:placetype":"venue"
},
  "geometry": {"coordinates":[7.2522349358,47.1322097778],"type":"Point"}
}