{
  "type": "Feature",
  "properties": {
    "iso:country":"CH",
    "sg:address":"Lauetstrasse 37",
    "sg:city":"Otelfingen",
    "sg:orig_category":"Unclassifiable Establishments",
    "sg:postcode":"8112",
    "sg:province":"Z\u00fcrich",
    "wof:name":"Pizza Kurier Pinocchio, \u00d6devci Mendufa",
    "wof:placetype":"venue"
},
  "geometry": {"coordinates":[8.4081096649,47.4569396973],"type":"Point"}
}