{
  "type": "Feature",
  "properties": {
    "iso:country":"CH",
    "sg:address":"Egliswilerstrasse 1",
    "sg:city":"Seon",
    "sg:orig_category":"Lichtpause U Reprografiebetriebe Schnelldruck U Kopierservice",
    "sg:phone":"+41 62 775 31 81",
    "sg:postcode":"5703",
    "sg:province":"Aargau",
    "wof:name":"S2 Druckweiterverarbeitung Gmbh",
    "wof:placetype":"venue"
},
  "geometry": {"coordinates":[8.162686348,47.3482818604],"type":"Point"}
}