{
  "type": "Feature",
  "properties": {
    "iso:country":"CH",
    "sg:address":"Weinbergstrasse 30 8280 Kreuzlingen. Postfach",
    "sg:city":"Kreuzlingen",
    "sg:orig_category":"Non-Classified Establishments",
    "sg:postcode":"8280",
    "sg:province":"Thurgau",
    "wof:name":"Cc-top Eventmarketing Cotting Jubil\u00e4ums Und Festaktivit\u00e4ten; Planung, Organisation",
    "wof:placetype":"venue"
},
  "geometry": {"coordinates":[9.1802883148,47.6408882141],"type":"Point"}
}