{
  "type": "Feature",
  "properties": {
    "iso:country":"CH",
    "sg:address":"4934",
    "sg:city":"Madiswil",
    "sg:orig_category":"Vereine Vogel-& Naturschutz",
    "sg:postcode":"4934",
    "sg:province":"Bern",
    "wof:name":"Ornithologischer Verein",
    "wof:placetype":"venue"
},
  "geometry": {"coordinates":[8.0869503021,47.4043197632],"type":"Point"}
}