{
  "type": "Feature",
  "properties": {
    "iso:country":"CH",
    "sg:address":"Siggenthalerstrasse 427",
    "sg:city":"W\u00fcrenlingen",
    "sg:orig_category":"Grosshandel mit Nahrungsmitteln, Getr\u00e4nken U Tabakwaren ohne ausgepr\u00e4gten Schwerpunkt",
    "sg:postcode":"5303",
    "sg:province":"Aargau",
    "wof:name":"Schneider Silvan Ag",
    "wof:placetype":"venue"
},
  "geometry": {"coordinates":[8.2484102249,47.5265159607],"type":"Point"}
}