{
  "type": "Feature",
  "properties": {
    "iso:country":"CH",
    "sg:address":"Escht\u00fcrlistrasse",
    "sg:city":"Horgenberg",
    "sg:orig_category":"Herstellung von Schrauben, Nieten, Ketten U Federn",
    "sg:phone":"+41 17250453",
    "sg:postcode":"8815",
    "sg:province":"Z\u00fcrich",
    "wof:name":"Peter Blaser Schraubenfabrikation",
    "wof:placetype":"venue"
},
  "geometry": {"coordinates":[8.5887145996,47.2466964722],"type":"Point"}
}