{
  "type": "Feature",
  "properties": {
    "iso:country":"CH",
    "sg:address":"Hauptgasse 20",
    "sg:city":"Olten",
    "sg:orig_category":"Herstellung von Schmuck, Gold U Silberschmiedwaren",
    "sg:postcode":"4600",
    "sg:province":"Solothurn",
    "wof:name":"Brunner J\u00fcrg Schmuckdesign Und Uhren",
    "wof:placetype":"venue"
},
  "geometry": {"coordinates":[7.903813839,47.3499717712],"type":"Point"}
}