{
  "type": "Feature",
  "properties": {
    "addr:full":"Chemin Gr\u00e9ly Sion Valais 1950",
    "addr:postcode":"1950",
    "addr:street":"Chemin Gre\u0301Ly",
    "iso:country":"CH",
    "sg:address":"Chemin Gr\u00e9ly",
    "sg:city":"Sion",
    "sg:orig_category":"Autogaragen Lastwagen and Nutzfahrzeuge",
    "sg:phone":"+41 27 323 78 79",
    "sg:postcode":"1950",
    "sg:province":"Valais",
    "wof:name":"Charly Troillet Garage",
    "wof:placetype":"venue"
},
  "geometry": {"coordinates":[7.341575,46.218529],"type":"Point"}
}