{
  "type": "Feature",
  "properties": {
    "iso:country":"CH",
    "sg:address":"1636",
    "sg:city":"Broc",
    "sg:orig_category":"Sportvereine Sch\u00fctzen",
    "sg:phone":"+41 26 921 20 40",
    "sg:postcode":"1636",
    "sg:province":"Fribourg",
    "wof:name":"St\u00e9 Des Carabiniers",
    "wof:placetype":"venue"
},
  "geometry": {"coordinates":[7.1003518105,46.6031494141],"type":"Point"}
}