{
  "type": "Feature",
  "properties": {
    "iso:country":"CH",
    "sg:address":"Kasernenstrasse 97",
    "sg:city":"Z\u00fcrich",
    "sg:orig_category":"Unclassifiable Establishments",
    "sg:postcode":"8004",
    "sg:province":"Z\u00fcrich",
    "wof:name":"Kleiner Konditorei-b\u00e4ckerei Ag",
    "wof:placetype":"venue"
},
  "geometry": {"coordinates":[8.5349578857,47.3768806458],"type":"Point"}
}