{
  "type": "Feature",
  "properties": {
    "iso:country":"CH",
    "sg:address":"Via Daro 6a",
    "sg:city":"Bellinzona",
    "sg:orig_category":"Herstellung von Tanks U Sammelbeh\u00e4ltern aus Metall Sanit\u00e4rinstallation",
    "sg:phone":"+41 91 825 13 40",
    "sg:postcode":"6500",
    "sg:province":"Ticino",
    "wof:name":"Tankrevisa Bulloni & Co Sa",
    "wof:placetype":"venue"
},
  "geometry": {"coordinates":[9.0300159454,46.1939697266],"type":"Point"}
}