{
  "type": "Feature",
  "properties": {
    "iso:country":"CH",
    "sg:address":"Maderno Via 9",
    "sg:city":"Lugano",
    "sg:orig_category":"Finanzierungsinstitutionen",
    "sg:postcode":"6900",
    "sg:province":"Ticino",
    "wof:name":"Trefin Ag, Succursale Di Lugano",
    "wof:placetype":"venue"
},
  "geometry": {"coordinates":[8.9549045563,46.0097045898],"type":"Point"}
}