{
  "type": "Feature",
  "properties": {
    "iso:country":"CH",
    "sg:address":"Stationsstrasse 98 6023 Rothenburg. Postfach 7",
    "sg:city":"Rothenburg",
    "sg:orig_category":"Bauschreinerei Herstellung von Konstruktionsteilen, Fertigbauteilen U Ausbauelementen aus Holz",
    "sg:phone":"+41 41 280 12 51",
    "sg:postcode":"6023",
    "sg:province":"Luzern",
    "wof:name":"Sch\u00e4r Gebr\u00fcder",
    "wof:placetype":"venue"
},
  "geometry": {"coordinates":[8.252466,47.091412],"type":"Point"}
}