{
  "type": "Feature",
  "properties": {
    "addr:full":"Seidenstrasse 27 Winterthur Z\u00fcrich 8400",
    "addr:housenumber":"27",
    "addr:postcode":"8400",
    "addr:street":"Seidenstrasse",
    "iso:country":"CH",
    "sg:address":"Seidenstrasse 27",
    "sg:city":"Winterthur",
    "sg:orig_category":"Architekturb\u00fcros",
    "sg:phone":"+41 52 243 03 03",
    "sg:postcode":"8400",
    "sg:province":"Z\u00fcrich",
    "wof:name":"Peter Stutz & Markus Bolt Architekturb\u00fcro",
    "wof:placetype":"venue"
},
  "geometry": {"coordinates":[8.738753,47.499367],"type":"Point"}
}