{
  "type": "Feature",
  "properties": {
    "iso:country":"CH",
    "sg:address":"Z\u00fcrcherstrasse 68",
    "sg:city":"Schlieren",
    "sg:orig_category":"Detailhandel mit elektrischen Haushalts, Radio U Fernsehger\u00e4ten ohne ausgepr\u00e4gten Schwerpunkt Elektr",
    "sg:phone":"+41 17302250",
    "sg:postcode":"8952",
    "sg:province":"Z\u00fcrich",
    "wof:name":"Elektro Weber Ag",
    "wof:placetype":"venue"
},
  "geometry": {"coordinates":[8.4568719864,47.3981819153],"type":"Point"}
}