{
  "type": "Feature",
  "properties": {
    "iso:country":"CH",
    "sg:address":"6661",
    "sg:city":"Loco",
    "sg:orig_category":"Non-Classified Establishments",
    "sg:postcode":"6661",
    "sg:province":"Ticino",
    "wof:name":"Ristorante Onsernone Di Fi\u00e9vet Bernard",
    "wof:placetype":"venue"
},
  "geometry": {"coordinates":[8.6732797623,46.2026901245],"type":"Point"}
}