{
  "type": "Feature",
  "properties": {
    "iso:country":"CH",
    "sg:address":"Aeschistrasse 48",
    "sg:city":"Bolken",
    "sg:orig_category":"Elektroinstallation",
    "sg:phone":"+41 62 961 88 87",
    "sg:postcode":"4556",
    "sg:province":"Solothurn",
    "wof:name":"Aerni Elektro Anlagen",
    "wof:placetype":"venue"
},
  "geometry": {"coordinates":[7.6634969711,47.1859970093],"type":"Point"}
}