{
  "type": "Feature",
  "properties": {
    "iso:country":"CH",
    "sg:address":"Hochdorferstrasse 2",
    "sg:city":"Hildisrieden",
    "sg:orig_category":"Grosshandel mit sonstigen Nahrungsmitteln",
    "sg:postcode":"6024",
    "sg:province":"Luzern",
    "wof:name":"Tiefk\u00fchlservice Haas Adrian",
    "wof:placetype":"venue"
},
  "geometry": {"coordinates":[8.2306680679,47.1511726379],"type":"Point"}
}