{
  "type": "Feature",
  "properties": {
    "iso:country":"CH",
    "sg:address":"Hauptstrasse 16",
    "sg:city":"Bichelsee",
    "sg:orig_category":"Fotografische Ateliers",
    "sg:phone":"+41 77966949",
    "sg:postcode":"8363",
    "sg:province":"Thurgau",
    "wof:name":"Daniel Germann Fotografisches Studio",
    "wof:placetype":"venue"
},
  "geometry": {"coordinates":[8.9243125916,47.4481925964],"type":"Point"}
}