{
  "type": "Feature",
  "properties": {
    "iso:country":"CH",
    "sg:address":"Route De Riant-val",
    "sg:city":"Leysin",
    "sg:orig_category":"Maurerarbeiten Sonstiger spezialisierter Hoch U Tiefbau",
    "sg:phone":"+41 24 494 24 66",
    "sg:postcode":"1854",
    "sg:province":"Vaud",
    "wof:name":"Borghi Jean-fran\u00e7ois",
    "wof:placetype":"venue"
},
  "geometry": {"coordinates":[7.0130829811,46.3435630798],"type":"Point"}
}