{
  "type": "Feature",
  "properties": {
    "iso:country":"CH",
    "sg:address":"St.galler Strasse 1",
    "sg:city":"Sitterdorf",
    "sg:orig_category":"Einzelhandel mit Automobilteilen U Zubeh\u00f6r Herstellung von Bereifungen",
    "sg:phone":"+41 41 870 75 34",
    "sg:postcode":"8589",
    "sg:province":"Thurgau",
    "wof:name":"Indergand Werner",
    "wof:placetype":"venue"
},
  "geometry": {"coordinates":[8.6314592361,46.8779144287],"type":"Point"}
}