{
  "type": "Feature",
  "properties": {
    "iso:country":"CH",
    "sg:address":"Gewerbestrasse 25 4123 Allschwil. Postfach",
    "sg:city":"Allschwil",
    "sg:orig_category":"Grosshandel mit medizinischen U orthop\u00e4dischen Artikeln Grosshandel mit pharmazeutischen Erzeugnisse",
    "sg:phone":"+41 848 811 822",
    "sg:postcode":"4123",
    "sg:province":"Basel-Landschaft",
    "wof:name":"Fango Gmbh",
    "wof:placetype":"venue"
},
  "geometry": {"coordinates":[8.8160018921,47.2251815796],"type":"Point"}
}