{
  "type": "Feature",
  "properties": {
    "iso:country":"CH",
    "sg:address":"Route De Taillepied 91",
    "sg:city":"Ch\u00e2telard-lutry",
    "sg:orig_category":"Sonstige mit der Informatik verbundene T\u00e4tigkeiten",
    "sg:phone":"+41 21 791 26 47",
    "sg:postcode":"1095",
    "sg:province":"Vaud",
    "wof:name":"Ili Informatique Schlaefli Edouard",
    "wof:placetype":"venue"
},
  "geometry": {"coordinates":[6.681707859,46.5053253174],"type":"Point"}
}