{
  "type": "Feature",
  "properties": {
    "iso:country":"CH",
    "sg:address":"Usserfeld 7214 Gr\u00fcsch. Postfach",
    "sg:city":"Gr\u00fcsch",
    "sg:orig_category":"Unternehmensberatung",
    "sg:postcode":"7214",
    "sg:province":"Graubunden",
    "wof:name":"Customer World Ag Customer Relationship Management Strategien, It-systeme; Entwicklung, F\u00f6rderung, Umsetzung Usw",
    "wof:placetype":"venue"
},
  "geometry": {"coordinates":[9.6414651871,46.9769134521],"type":"Point"}
}