{
  "type": "Feature",
  "properties": {
    "iso:country":"CH",
    "sg:address":"Rigistrasse 20",
    "sg:city":"Zufikon",
    "sg:orig_category":"Wohnheime",
    "sg:postcode":"5621",
    "sg:province":"Aargau",
    "wof:name":"Thut-luise-stiftung Aargauer Hospiz",
    "wof:placetype":"venue"
},
  "geometry": {"coordinates":[8.3570995331,47.3559417725],"type":"Point"}
}