{
  "type": "Feature",
  "properties": {
    "iso:country":"CH",
    "sg:address":"Chemin Du Chasseron 3",
    "sg:city":"Lausanne",
    "sg:orig_category":"Detailhandel mit Radio U Fernsehger\u00e4ten Herstellung von Radio U Fernsehger\u00e4ten sowie phono U videote",
    "sg:phone":"+41 21 625 78 55",
    "sg:postcode":"1004",
    "sg:province":"Vaud",
    "wof:name":"Videocolor Diolosa V. S\u00e0rl",
    "wof:placetype":"venue"
},
  "geometry": {"coordinates":[6.6134281158,46.5314292908],"type":"Point"}
}