{
  "type": "Feature",
  "properties": {
    "iso:country":"CH",
    "sg:address":"Avenue De Tourbillon 72",
    "sg:city":"Sion",
    "sg:orig_category":"Grosshandel mit Tabakwaren",
    "sg:phone":"+41 27 322 48 64",
    "sg:postcode":"1950",
    "sg:province":"Valais",
    "wof:name":"Nelson Maia",
    "wof:placetype":"venue"
},
  "geometry": {"coordinates":[7.3679418564,46.2308921814],"type":"Point"}
}