{
  "type": "Feature",
  "properties": {
    "iso:country":"CH",
    "sg:address":"Langackerweg 2",
    "sg:city":"Arlesheim",
    "sg:orig_category":"Unclassifiable Establishments",
    "sg:postcode":"4144",
    "sg:province":"Basel-Landschaft",
    "wof:name":"B\u00e4renland Schweiz Ag",
    "wof:placetype":"venue"
},
  "geometry": {"coordinates":[7.6153049469,47.4925804138],"type":"Point"}
}