{
  "type": "Feature",
  "properties": {
    "iso:country":"CH",
    "sg:address":"Schutz 624",
    "sg:city":"Walzenhausen",
    "sg:orig_category":"Tierheime",
    "sg:phone":"+41 61 811 35 83",
    "sg:postcode":"9428",
    "sg:province":"Appenzell Ausserrhoden",
    "wof:name":"Tierheim Zum Schn\u00fcffel Stiftung Sos F\u00fcr Tiere",
    "wof:placetype":"venue"
},
  "geometry": {"coordinates":[7.7212600708,47.5278816223],"type":"Point"}
}