{
  "type": "Feature",
  "properties": {
    "iso:country":"CH",
    "sg:address":"Bruggerstrasse 44 5400 Baden. Postfach",
    "sg:city":"Baden",
    "sg:orig_category":"Sonstige mit der Informatik verbundene T\u00e4tigkeiten",
    "sg:postcode":"5400",
    "sg:province":"Aargau",
    "wof:name":"Widmer Informatik",
    "wof:placetype":"venue"
},
  "geometry": {"coordinates":[8.4397602081,47.4589004517],"type":"Point"}
}