{
  "type": "Feature",
  "properties": {
    "iso:country":"CH",
    "sg:address":"D\u00e4ndlikerweg 15",
    "sg:city":"Bern",
    "sg:orig_category":"Fussreflexzonenmassage",
    "sg:phone":"+41 71 891 45 19",
    "sg:postcode":"3014",
    "sg:province":"Bern",
    "wof:name":"Frieda Weiler Fussreflexmassage",
    "wof:placetype":"venue"
},
  "geometry": {"coordinates":[9.5611085892,47.4241752625],"type":"Point"}
}