{
  "type": "Feature",
  "properties": {
    "iso:country":"CH",
    "sg:address":"S\u00e4geweg 10",
    "sg:city":"Innerberg",
    "sg:orig_category":"Sportschulen Gleitschirm-& Deltaflugschulen",
    "sg:phone":"+41 79 357 20 50",
    "sg:postcode":"3044",
    "sg:province":"Bern",
    "wof:name":"Hans Guler Flugschule Davos",
    "wof:placetype":"venue"
},
  "geometry": {"coordinates":[9.8209104538,46.7938690186],"type":"Point"}
}