{
  "type": "Feature",
  "properties": {
    "iso:country":"CH",
    "sg:address":"Dietlistrasse 74a",
    "sg:city":"St.gallen",
    "sg:orig_category":"Grosshandel mit sonstigen Maschinen U Ausr\u00fcstungen f\u00fcr Industrie, Handel U Schiffahrt",
    "sg:phone":"+41 71 222 44 40",
    "sg:postcode":"9000",
    "sg:province":"St. Gallen",
    "wof:name":"Coro Corazza R.",
    "wof:placetype":"venue"
},
  "geometry": {"coordinates":[9.3662481308,47.4275817871],"type":"Point"}
}