{
  "type": "Feature",
  "properties": {
    "iso:country":"CH",
    "sg:address":"Lindenbachstrasse 1/408",
    "sg:city":"Z\u00fcrich",
    "sg:orig_category":"P\u00e9dicure",
    "sg:phone":"+41 13611560",
    "sg:postcode":"8006",
    "sg:province":"Z\u00fcrich",
    "wof:name":"Emma Hefti P\u00e9dicure",
    "wof:placetype":"venue"
},
  "geometry": {"coordinates":[8.5391979218,47.3869514465],"type":"Point"}
}