{
  "type": "Feature",
  "properties": {
    "iso:country":"CH",
    "sg:address":"Sardonastrasse 5",
    "sg:city":"Chur",
    "sg:orig_category":"Sportvereine Ski",
    "sg:phone":"+41 81 286 70 53",
    "sg:postcode":"7000",
    "sg:province":"Graubunden",
    "wof:name":"Skiclub R\u00e4tia Chur",
    "wof:placetype":"venue"
},
  "geometry": {"coordinates":[9.5164775848,46.8617134094],"type":"Point"}
}