{
  "type": "Feature",
  "properties": {
    "iso:country":"CH",
    "sg:address":"7458",
    "sg:city":"Mon",
    "sg:orig_category":"Wirtschaftspr\u00fcfung, Steuerberatung U Treuhand",
    "sg:postcode":"7458",
    "sg:province":"Graubunden",
    "wof:name":"Treuhand Augustin Marius, Lic. Oec. Hsg",
    "wof:placetype":"venue"
},
  "geometry": {"coordinates":[9.5644903183,46.6498832703],"type":"Point"}
}