{
  "type": "Feature",
  "properties": {
    "iso:country":"CH",
    "sg:address":"Kantonsstrasse 74",
    "sg:city":"Reichenburg",
    "sg:orig_category":"Bau von Strassen, Sportanlagen U Bahnverkehrsstrecken",
    "sg:phone":"+41 55 640 74 16",
    "sg:postcode":"8864",
    "sg:province":"Schwyz",
    "wof:name":"H\u00f6sli Walter Strassenbau Ag Zweigniederlassung Reichenburg",
    "wof:placetype":"venue"
},
  "geometry": {"coordinates":[8.981675,47.167286],"type":"Point"}
}