{
  "type": "Feature",
  "properties": {
    "iso:country":"CH",
    "sg:address":"Blegistrasse",
    "sg:city":"Rotkreuz",
    "sg:orig_category":"Grosshandel mit Erzen U Metallen",
    "sg:phone":"+41 41 790 52 32",
    "sg:postcode":"6343",
    "sg:province":"Zug",
    "wof:name":"Metaltrade Ag",
    "wof:placetype":"venue"
},
  "geometry": {"coordinates":[8.4356946945,47.1475868225],"type":"Point"}
}