{
  "type": "Feature",
  "properties": {
    "addr:full":"Zollikerstrasse 44 Zollikon Z\u00fcrich 8702",
    "addr:housenumber":"44",
    "addr:postcode":"8702",
    "addr:street":"Zollikerstrasse",
    "iso:country":"CH",
    "sg:address":"Zollikerstrasse 44",
    "sg:city":"Zollikon",
    "sg:orig_category":"Datenverarbeitungsdienste Softwareentwicklung U beratung",
    "sg:phone":"+41 13919563",
    "sg:postcode":"8702",
    "sg:province":"Z\u00fcrich",
    "wof:name":"Valebit Ag",
    "wof:placetype":"venue"
},
  "geometry": {"coordinates":[8.570758,47.343132],"type":"Point"}
}