{
  "type": "Feature",
  "properties": {
    "iso:country":"CH",
    "sg:address":"Rue De Neuch\u00e2tel 14",
    "sg:city":"Yverdon-les-bains",
    "sg:classifiers":[
        {
            "category":"Government",
            "subcategory":"Post Office",
            "type":"Public Place"
        }
    ],
    "sg:phone":"+41 24 425 93 91",
    "sg:postcode":"1400",
    "sg:province":"Vaud",
    "sg:tags":[
        "caf\u00e9s",
        "tea-rooms"
    ],
    "wof:name":"Bar \u00e0 Caf\u00e9 La Diligence",
    "wof:placetype":"venue"
},
  "geometry": {"coordinates":[6.6362371445,46.7815284729],"type":"Point"}
}