{
  "type": "Feature",
  "properties": {
    "iso:country":"CH",
    "sg:address":"Im Breitacher 34",
    "sg:city":"R\u00fctihof",
    "sg:classifiers":[
        {
            "category":"Professional",
            "subcategory":"Art Services",
            "type":"Services"
        }
    ],
    "sg:phone":"+41 56 470 04 77",
    "sg:postcode":"5406",
    "sg:province":"Aargau",
    "sg:tags":[
        "homepage",
        "designing"
    ],
    "wof:name":"Petignat Edv-beratung",
    "wof:placetype":"venue"
},
  "geometry": {"coordinates":[8.2654905319,47.438533783],"type":"Point"}
}