{
  "type": "Feature",
  "properties": {
    "iso:country":"CH",
    "sg:address":"Hirschenplatz 1 6215 Berom\u00fcnster. Postfach",
    "sg:city":"Berom\u00fcnster",
    "sg:classifiers":[
        {
            "category":"Travel",
            "subcategory":"Hotels & Motels",
            "type":"Entertainment"
        }
    ],
    "sg:phone":"+41 41 410 51 50",
    "sg:postcode":"6215",
    "sg:province":"Luzern",
    "sg:tags":[
        "hotels",
        "mit",
        "restaurant"
    ],
    "wof:name":"Hotel Hirschen",
    "wof:placetype":"venue"
},
  "geometry": {"coordinates":[8.3052511215,47.0523490906],"type":"Point"}
}