{
  "type": "Feature",
  "properties": {
    "iso:country":"CH",
    "sg:address":"La Berzin",
    "sg:city":"Is\u00e9rables",
    "sg:orig_category":"Grosshandel mit lebenden Tieren",
    "sg:phone":"+41 27 306 33 32",
    "sg:postcode":"1914",
    "sg:province":"Valais",
    "wof:name":"Th\u00e9odule Fort Commerce De B\u00e9tail",
    "wof:placetype":"venue"
},
  "geometry": {"coordinates":[7.24518013,46.1604385376],"type":"Point"}
}