{
  "type": "Feature",
  "properties": {
    "iso:country":"CH",
    "sg:address":"Avenue De La Gare 5a",
    "sg:city":"Fleurier",
    "sg:orig_category":"Detailhandel mit Schuhen Detailhandel mit Schuhen U Lederwaren",
    "sg:phone":"+41 32 861 11 40",
    "sg:postcode":"2114",
    "sg:province":"Neuch\u00e2tel",
    "wof:name":"Au Sabot D'argent Chaussures",
    "wof:placetype":"venue"
},
  "geometry": {"coordinates":[6.5814571381,46.9029121399],"type":"Point"}
}