{
  "type": "Feature",
  "properties": {
    "iso:country":"CH",
    "sg:address":"Dufourstrasse 153",
    "sg:city":"Z\u00fcrich",
    "sg:orig_category":"Architektur U Ingenieurb\u00fcros",
    "sg:phone":"+41 21 634 36 14",
    "sg:postcode":"8008",
    "sg:province":"Z\u00fcrich",
    "wof:name":"Ecm Engineering Consulting Management Sa",
    "wof:placetype":"venue"
},
  "geometry": {"coordinates":[6.582137,46.530254],"type":"Point"}
}