{
  "type": "Feature",
  "properties": {
    "iso:country":"CH",
    "sg:address":"Am Wasser 161",
    "sg:city":"Z\u00fcrich",
    "sg:orig_category":"Gartenbau",
    "sg:postcode":"8049",
    "sg:province":"Z\u00fcrich",
    "wof:name":"Ernst Bigler",
    "wof:placetype":"venue"
},
  "geometry": {"coordinates":[7.5633797646,46.9297447205],"type":"Point"}
}