{
  "type": "Feature",
  "properties": {
    "iso:country":"CH",
    "sg:address":"Baselstrasse 68",
    "sg:city":"Solothurn",
    "sg:orig_category":"Detailhandel mit Fleisch U Fleischwaren",
    "sg:phone":"+41 71 911 25 11",
    "sg:postcode":"4500",
    "sg:province":"Solothurn",
    "wof:name":"Metzgerei Siegfried",
    "wof:placetype":"venue"
},
  "geometry": {"coordinates":[9.0457754135,47.4629592896],"type":"Point"}
}