{
  "type": "Feature",
  "properties": {
    "iso:country":"CH",
    "sg:address":"Welsikon",
    "sg:city":"Dinhard",
    "sg:classifiers":[
        {
            "category":"Restaurant",
            "type":"Food & Drink"
        }
    ],
    "sg:phone":"+41 52 336 11 81",
    "sg:postcode":"8474",
    "sg:province":"Z\u00fcrich",
    "wof:name":"Restaurant Bahnhof",
    "wof:placetype":"venue"
},
  "geometry": {"coordinates":[8.7494802475,47.5545082092],"type":"Point"}
}