{
  "type": "Feature",
  "properties": {
    "iso:country":"CH",
    "sg:address":"2565",
    "sg:city":"Jens",
    "sg:orig_category":"Schulpflegen",
    "sg:phone":"+41 32 831 12 62",
    "sg:postcode":"2565",
    "sg:province":"Bern",
    "wof:name":"Primarschulkommission Der Gemeinde Jens",
    "wof:placetype":"venue"
},
  "geometry": {"coordinates":[7.2709598541,47.0965995789],"type":"Point"}
}