{
  "type": "Feature",
  "properties": {
    "iso:country":"CH",
    "sg:address":"8766",
    "sg:city":"Matt",
    "sg:orig_category":"Sportvereine Turnen",
    "sg:phone":"+41 79 870 53 95",
    "sg:postcode":"8766",
    "sg:province":"Glarus",
    "wof:name":"Turnverein Matt",
    "wof:placetype":"venue"
},
  "geometry": {"coordinates":[9.1705522537,46.9643096924],"type":"Point"}
}