{
  "type": "Feature",
  "properties": {
    "iso:country":"CH",
    "sg:address":"Luisenstrasse 39",
    "sg:city":"Z\u00fcrich",
    "sg:orig_category":"Unternehmensberatung",
    "sg:phone":"+41 21 691 49 29",
    "sg:postcode":"8005",
    "sg:province":"Z\u00fcrich",
    "wof:name":"Salzmann Fr\u00e9d\u00e9ric",
    "wof:placetype":"venue"
},
  "geometry": {"coordinates":[6.5640521049,46.5120544434],"type":"Point"}
}