{
  "type": "Feature",
  "properties": {
    "iso:country":"CH",
    "sg:address":"Via Bascira 2",
    "sg:city":"Agno",
    "sg:orig_category":"Kosmetikinstitute",
    "sg:phone":"+41 91 605 17 78",
    "sg:postcode":"6982",
    "sg:province":"Ticino",
    "wof:name":"La Rosa Estetica Sagl",
    "wof:placetype":"venue"
},
  "geometry": {"coordinates":[8.9003448486,45.9971580505],"type":"Point"}
}