{
  "type": "Feature",
  "properties": {
    "iso:country":"CH",
    "sg:address":"Via Bartolomeo Papio",
    "sg:city":"Ascona",
    "sg:orig_category":"Herstellung von keramischen Haushaltswaren U Ziergegenst\u00e4nden Herstellung von sonstigen keramischen ",
    "sg:phone":"+41 91 791 53 88",
    "sg:postcode":"6612",
    "sg:province":"Ticino",
    "wof:name":"Marco Roggero Ceramiche Macroc",
    "wof:placetype":"venue"
},
  "geometry": {"coordinates":[8.7708053589,46.15574646],"type":"Point"}
}