{
  "type": "Feature",
  "properties": {
    "iso:country":"CH",
    "sg:address":"Aeulistrasse 23",
    "sg:city":"Vilters",
    "sg:orig_category":"Unclassifiable Establishments",
    "sg:postcode":"7324",
    "sg:province":"St. Gallen",
    "wof:name":"Fillmann Ag",
    "wof:placetype":"venue"
},
  "geometry": {"coordinates":[8.7771053314,47.2004928589],"type":"Point"}
}