{
  "type": "Feature",
  "properties": {
    "addr:full":"Rue Du Perron 62 Gland Vaud 1196",
    "addr:housenumber":"62",
    "addr:postcode":"1196",
    "addr:street":"Rue Du Perron",
    "iso:country":"CH",
    "sg:address":"Rue Du Perron 62",
    "sg:city":"Gland",
    "sg:orig_category":"Bauschreinerei",
    "sg:phone":"+41 71 385 94 42",
    "sg:postcode":"1196",
    "sg:province":"Vaud",
    "wof:name":"Michael Eisenring Mesi Schreinermontagen",
    "wof:placetype":"venue"
},
  "geometry": {"coordinates":[9.25015,47.423649],"type":"Point"}
}