{
  "type": "Feature",
  "properties": {
    "addr:full":"Ried M\u00f6rel Valais 3986",
    "addr:postcode":"3986",
    "addr:street":"Ried Moerel",
    "iso:country":"CH",
    "sg:city":"Ried M\u00f6rel",
    "sg:classifiers":[
        {
            "category":"Banks & Credit Unions",
            "subcategory":"Bank",
            "type":"Services"
        }
    ],
    "sg:phone":"+41 27 927 31 77",
    "sg:postcode":"3986",
    "sg:province":"Valais",
    "wof:name":"Raiffeisenbank",
    "wof:placetype":"venue"
},
  "geometry": {"coordinates":[8.032008,46.357342],"type":"Point"}
}