{
  "type": "Feature",
  "properties": {
    "iso:country":"CH",
    "sg:address":"3705",
    "sg:city":"Faulensee",
    "sg:classifiers":[
        {
            "category":"Government",
            "subcategory":"Post Office",
            "type":"Public Place"
        }
    ],
    "sg:phone":"+41 33 654 22 04",
    "sg:postcode":"3705",
    "sg:province":"Bern",
    "sg:tags":[
        "die",
        "poststellen"
    ],
    "wof:name":"Die Post",
    "wof:placetype":"venue"
},
  "geometry": {"coordinates":[7.7005500793,46.6758384705],"type":"Point"}
}