{
  "type": "Feature",
  "properties": {
    "iso:country":"CH",
    "sg:address":"Luzernerstrasse 27",
    "sg:city":"Oftringen",
    "sg:orig_category":"Detailhandel mit Uhren U Schmuck Reparatur von Uhren U Schmuck",
    "sg:phone":"+41 62 797 27 26",
    "sg:postcode":"4665",
    "sg:province":"Aargau",
    "wof:name":"Paul Imboden Uhren & Bijouterie",
    "wof:placetype":"venue"
},
  "geometry": {"coordinates":[7.9248971939,47.3097801208],"type":"Point"}
}