{
  "type": "Feature",
  "properties": {
    "iso:country":"CH",
    "sg:address":"Delsbergerallee 38 4000 Basel. Postfach",
    "sg:city":"Basel",
    "sg:orig_category":"Gesundheitswesen",
    "sg:postcode":"4051",
    "sg:province":"Basel-Stadt",
    "wof:name":"Cardiocard Ag",
    "wof:placetype":"venue"
},
  "geometry": {"coordinates":[7.5999631882,47.540977478],"type":"Point"}
}