{
  "type": "Feature",
  "properties": {
    "addr:full":"Kapellstrasse 26 Grenchen Solothurn 2540",
    "addr:housenumber":"26",
    "addr:postcode":"2540",
    "addr:street":"Kapellstrasse",
    "iso:country":"CH",
    "sg:address":"Kapellstrasse 26",
    "sg:city":"Grenchen",
    "sg:classifiers":[
        {
            "category":"Manufacturing",
            "subcategory":"Metals",
            "type":"Manufacturing & Wholesale Goods"
        }
    ],
    "sg:phone":"+41 32 653 10 10",
    "sg:postcode":"2540",
    "sg:province":"Solothurn",
    "sg:tags":[
        "automatic",
        "used",
        "lathe",
        "working"
    ],
    "wof:name":"M\u00fclchi Decolletage",
    "wof:placetype":"venue"
},
  "geometry": {"coordinates":[7.396957,47.195614],"type":"Point"}
}