{
  "type": "Feature",
  "properties": {
    "addr:full":"Quadergasse 6 Untervaz Graubunden 7204",
    "addr:housenumber":"6;7204",
    "addr:street":"Quadergasse",
    "iso:country":"CH",
    "sg:address":"Quadergasse 6",
    "sg:city":"Untervaz",
    "sg:orig_category":"Aktivit\u00e4ten der Krankenschwestern U Hebammen, Hauspflege Organisationen des Gesundheitswesen",
    "sg:phone":"+41 71 222 77 55",
    "sg:postcode":"7204",
    "sg:province":"Graubunden",
    "wof:name":"Spitex Centrum",
    "wof:placetype":"venue"
},
  "geometry": {"coordinates":[9.366394,47.422787],"type":"Point"}
}