{
  "type": "Feature",
  "properties": {
    "iso:country":"CH",
    "sg:address":"Tunnel Rue Du 1 1005 Lausanne. Postfach",
    "sg:city":"Lausanne",
    "sg:orig_category":"RESTAURANTS: TEA-ROOMS",
    "sg:phone":"+41 61 401 14 03",
    "sg:postcode":"1003",
    "sg:province":"Vaud",
    "wof:name":"Buttons Pubs Ag",
    "wof:placetype":"venue"
},
  "geometry": {"coordinates":[7.5549287796,47.5092124939],"type":"Point"}
}