{
  "type": "Feature",
  "properties": {
    "iso:country":"CH",
    "sg:address":"Viale Verbano 13",
    "sg:city":"Muralto",
    "sg:orig_category":"Detailhandel mit Herrenbekleidung",
    "sg:phone":"+41 91 743 13 13",
    "sg:postcode":"6600",
    "sg:province":"Ticino",
    "wof:name":"Severi Moda Sagl Negozio Di Vestiti Per Uomo",
    "wof:placetype":"venue"
},
  "geometry": {"coordinates":[8.8024082184,46.171710968],"type":"Point"}
}