{
  "type": "Feature",
  "properties": {
    "iso:country":"CH",
    "sg:address":"Gempenstrasse 42a",
    "sg:city":"Dornach",
    "sg:orig_category":"Textilveredlung",
    "sg:phone":"+41 61 701 88 00",
    "sg:postcode":"4143",
    "sg:province":"Solothurn",
    "wof:name":"Pflanzenf\u00e4rberei Ernst Bollhalder",
    "wof:placetype":"venue"
},
  "geometry": {"coordinates":[7.6211709976,47.4752960205],"type":"Point"}
}