{
  "type": "Feature",
  "properties": {
    "iso:country":"CH",
    "sg:address":"M\u00fchlegasse 8",
    "sg:city":"Pfyn",
    "sg:orig_category":"Grosshandel mit Baumaschinen Grosshandel mit Holz U Baustoffen",
    "sg:phone":"+41 52 765 25 55",
    "sg:postcode":"8505",
    "sg:province":"Thurgau",
    "wof:name":"Maxit Ag Moderne Baustofftechnik",
    "wof:placetype":"venue"
},
  "geometry": {"coordinates":[8.9586400986,47.5959091187],"type":"Point"}
}