{
  "type": "Feature",
  "properties": {
    "iso:country":"CH",
    "sg:address":"Route Du Pas-de-l'echelle 120",
    "sg:city":"Veyrier",
    "sg:orig_category":"Bauschreinerei Zimmerei, Dachdeckerei, Bauspenglerei U Abdichtung",
    "sg:phone":"+41 22 784 16 32",
    "sg:postcode":"1255",
    "sg:province":"Gen\u00e8ve",
    "wof:name":"Reymond Charly, Bonaldi Christian Succ.",
    "wof:placetype":"venue"
},
  "geometry": {"coordinates":[6.096983,49.614574],"type":"Point"}
}