{
  "type": "Feature",
  "properties": {
    "iso:country":"CH",
    "sg:address":"Rue Des Sablons 47",
    "sg:city":"Neuch\u00e2tel",
    "sg:orig_category":"Autolackierereien Autospenglereien",
    "sg:phone":"+41 32 725 85 19",
    "sg:postcode":"2000",
    "sg:province":"Neuch\u00e2tel",
    "wof:name":"Alves Rui Pedro Ribeiro Carrosserie Des Sablons",
    "wof:placetype":"venue"
},
  "geometry": {"coordinates":[6.931754,46.996155],"type":"Point"}
}