{
  "type": "Feature",
  "properties": {
    "iso:country":"CH",
    "sg:address":"Niederglatterstrasse 2 8155 Niederhasli. Postfach 173",
    "sg:city":"Niederhasli",
    "sg:orig_category":"Bauspenglerei Zimmerei, Dachdeckerei, Bauspenglerei U Abdichtung",
    "sg:phone":"+41 18503657",
    "sg:postcode":"8155",
    "sg:province":"Z\u00fcrich",
    "wof:name":"Suter-d\u00f6rig Bruno, Bauspenglerei Und Sanit\u00e4re Anlagen",
    "wof:placetype":"venue"
},
  "geometry": {"coordinates":[8.484151,47.481354],"type":"Point"}
}