{
  "type": "Feature",
  "properties": {
    "addr:full":"Via Zurigo 46 Lugano Ticino 6900",
    "addr:housenumber":"46",
    "addr:postcode":"6900",
    "addr:street":"Via Zurigo",
    "iso:country":"CH",
    "sg:address":"Via Zurigo 46",
    "sg:city":"Lugano",
    "sg:classifiers":[
        {
            "category":"Banks & Credit Unions",
            "subcategory":"Bank",
            "type":"Services"
        }
    ],
    "sg:phone":"+41 91 922 02 03",
    "sg:postcode":"6900",
    "sg:province":"Ticino",
    "wof:name":"R\u00fcegg Bank Ag",
    "wof:placetype":"venue"
},
  "geometry": {"coordinates":[8.950382,46.010155],"type":"Point"}
}