{
  "type": "Feature",
  "properties": {
    "iso:country":"CH",
    "sg:address":"Hohr\u00fctistrasse 4 Forch 8700 K\u00fcsnacht Zh. Postfach",
    "sg:city":"Forch",
    "sg:orig_category":"Unclassifiable Establishments",
    "sg:postcode":"8127",
    "sg:province":"Z\u00fcrich",
    "wof:name":"Weber Christian Gartenbau & Unterhalt Gmbh",
    "wof:placetype":"venue"
},
  "geometry": {"coordinates":[8.5801410675,47.3188972473],"type":"Point"}
}