{
  "type": "Feature",
  "properties": {
    "iso:country":"CH",
    "sg:address":"Oberneuhofstrasse 3",
    "sg:city":"Baar",
    "sg:orig_category":"Sonstiges Textilgewerbe",
    "sg:postcode":"6340",
    "sg:province":"Zug",
    "wof:name":"Bachmann Ag",
    "wof:placetype":"venue"
},
  "geometry": {"coordinates":[8.8529987335,47.2574234009],"type":"Point"}
}