{
  "type": "Feature",
  "properties": {
    "iso:country":"CH",
    "sg:address":"Rickenstr. 17",
    "sg:city":"Wattwil",
    "sg:classifiers":[
        {
            "category":"Professional",
            "subcategory":"Engineering",
            "type":"Services"
        }
    ],
    "sg:phone":"+41 71 988 33 30",
    "sg:postcode":"9630",
    "sg:province":"St. Gallen",
    "sg:tags":[
        "machine",
        "-",
        "mechanical"
    ],
    "wof:name":"R Seiz Ag",
    "wof:placetype":"venue"
},
  "geometry": {"coordinates":[9.0851430893,47.3001861572],"type":"Point"}
}