{
  "type": "Feature",
  "properties": {
    "iso:country":"CH",
    "sg:address":"4445",
    "sg:city":"H\u00e4felfingen",
    "sg:orig_category":"Vorschulen, Kinderg\u00e4rten",
    "sg:phone":"+41 62 299 00 49",
    "sg:postcode":"4445",
    "sg:province":"Basel-Landschaft",
    "wof:name":"Kindergarten",
    "wof:placetype":"venue"
},
  "geometry": {"coordinates":[7.8694601059,47.4138717651],"type":"Point"}
}