{
  "type": "Feature",
  "properties": {
    "iso:country":"CH",
    "sg:address":"Route D'oron 2 1010 Lausanne Case Postale 44",
    "sg:city":"Lausanne",
    "sg:orig_category":"Grosshandel mit sonstigen Konsumg\u00fctern",
    "sg:phone":"+41 21 651 20 50",
    "sg:postcode":"1010",
    "sg:province":"Vaud",
    "wof:name":"Combaro Sa",
    "wof:placetype":"venue"
},
  "geometry": {"coordinates":[6.6660060883,46.5069389343],"type":"Point"}
}