{
  "type": "Feature",
  "properties": {
    "iso:country":"CH",
    "sg:address":"Goldhaldenstrasse 62 8702 Zollikon. Postfach",
    "sg:city":"Zollikon",
    "sg:orig_category":"Wohnheime",
    "sg:postcode":"8702",
    "sg:province":"Z\u00fcrich",
    "wof:name":"Reimann-b\u00e4chtold-stiftung Alterswohnheim F. Geistig Oder K\u00f6rperlich Behinderte Menschen",
    "wof:placetype":"venue"
},
  "geometry": {"coordinates":[8.5764741898,47.3337860107],"type":"Point"}
}