{
  "type": "Feature",
  "properties": {
    "iso:country":"CH",
    "sg:address":"Rue Du Bourg 11",
    "sg:city":"Aigle",
    "sg:orig_category":"Detailhandel mit Fleisch U Fleischwaren",
    "sg:phone":"+41 24 466 20 68",
    "sg:postcode":"1860",
    "sg:province":"Vaud",
    "wof:name":"Roland Besan\u00e7on Boucherie-charcuterie",
    "wof:placetype":"venue"
},
  "geometry": {"coordinates":[6.9684839249,46.3184814453],"type":"Point"}
}