{
  "type": "Feature",
  "properties": {
    "iso:country":"CH",
    "sg:address":"Rue De Bourg 10 1003 Lausanne Case Postale 2545",
    "sg:city":"Lausanne",
    "sg:orig_category":"Reiseb\u00fcros U Reiseveranstalter",
    "sg:phone":"+41 21 311 88 12",
    "sg:postcode":"1002",
    "sg:province":"Vaud",
    "wof:name":"Voyages Et Culture Cvc Sa",
    "wof:placetype":"venue"
},
  "geometry": {"coordinates":[6.6353340149,46.5198936462],"type":"Point"}
}