{
  "type": "Feature",
  "properties": {
    "iso:country":"CH",
    "sg:address":"Morgenacherstrasse 2f",
    "sg:city":"Oberrohrdorf",
    "sg:orig_category":"Rechtsberatung",
    "sg:postcode":"5452",
    "sg:province":"Aargau",
    "wof:name":"Fucellco Ag",
    "wof:placetype":"venue"
},
  "geometry": {"coordinates":[8.3186130524,47.417301178],"type":"Point"}
}