{
  "type": "Feature",
  "properties": {
    "iso:country":"CH",
    "sg:address":"Tafersstrasse 2 1700 Fribourg Case Postale 74",
    "sg:city":"Fribourg",
    "sg:orig_category":"Kantonalbanken",
    "sg:phone":"+41 26 484 84 80",
    "sg:postcode":"1707",
    "sg:province":"Fribourg",
    "wof:name":"Banque Cantonale De Fribourg Succursale Du Schoenberg",
    "wof:placetype":"venue"
},
  "geometry": {"coordinates":[7.1536831856,46.8037452698],"type":"Point"}
}