{
  "type": "Feature",
  "properties": {
    "iso:country":"CH",
    "sg:address":"Obere Hauptgasse 8",
    "sg:city":"Thun",
    "sg:orig_category":"Herstellung von sonstigen Holzwaren",
    "sg:postcode":"3600",
    "sg:province":"Bern",
    "wof:name":"Ludowa, Untern\u00e4hrer Walter P.",
    "wof:placetype":"venue"
},
  "geometry": {"coordinates":[7.6288571358,46.7591743469],"type":"Point"}
}