{
  "type": "Feature",
  "properties": {
    "iso:country":"CH",
    "sg:address":"Steigbach",
    "sg:city":"B\u00fchler",
    "sg:orig_category":"RESTAURANTS: TEA-ROOMS",
    "sg:phone":"+41 71 793 17 45",
    "sg:postcode":"9055",
    "sg:province":"Appenzell Ausserrhoden",
    "wof:name":"Restaurant Rose B\u00fchler Gmbh",
    "wof:placetype":"venue"
},
  "geometry": {"coordinates":[9.4029035568,47.3776359558],"type":"Point"}
}