{
  "type": "Feature",
  "properties": {
    "addr:full":"Boulevard De P\u00e9rolles 68 1700 Fribourg. Postfach Fribourg Fribourg 1705",
    "addr:housenumber":"68",
    "addr:postcode":"1700;postfach;1705",
    "addr:street":"Boulevard De Pe\u0301Rolles",
    "iso:country":"CH",
    "sg:address":"Boulevard De P\u00e9rolles 68 1700 Fribourg. Postfach",
    "sg:city":"Fribourg",
    "sg:orig_category":"Bezirks, Sekundar, Realschulen, Oberstufe der Primarschulen Primarschulen",
    "sg:phone":"+41 26 424 55 88",
    "sg:postcode":"1705",
    "sg:province":"Fribourg",
    "wof:name":"Cycle D'orientation De P\u00e9rolles",
    "wof:placetype":"venue"
},
  "geometry": {"coordinates":[7.157507,46.794769],"type":"Point"}
}