{
  "type": "Feature",
  "properties": {
    "iso:country":"CH",
    "sg:address":"Route De La Fonderie 8c",
    "sg:city":"Fribourg",
    "sg:orig_category":"Non-Classified Establishments",
    "sg:postcode":"1700",
    "sg:province":"Fribourg",
    "wof:name":"Cin\u00e9magination S\u00e0rl Films & Images",
    "wof:placetype":"venue"
},
  "geometry": {"coordinates":[7.152867794,46.7945594788],"type":"Point"}
}