{
  "type": "Feature",
  "properties": {
    "iso:country":"CH",
    "sg:address":"St.gallerstrasse 29",
    "sg:city":"Herisau",
    "sg:classifiers":[
        {
            "category":"Restaurant",
            "type":"Food & Drink"
        }
    ],
    "sg:phone":"+41 71 351 20 76",
    "sg:postcode":"9100",
    "sg:province":"Appenzell Ausserrhoden",
    "wof:name":"Restaurant Talhof",
    "wof:placetype":"venue"
},
  "geometry": {"coordinates":[9.2779359818,47.3918571472],"type":"Point"}
}