{
  "type": "Feature",
  "properties": {
    "addr:full":"Les Communs S\u00e2les Fribourg 1625",
    "addr:postcode":"sa\u0302les;1625",
    "iso:country":"CH",
    "sg:address":"Les Communs",
    "sg:city":"S\u00e2les",
    "sg:classifiers":[
        {
            "category":"Transit Center",
            "subcategory":"Freight",
            "type":"Transportation"
        }
    ],
    "sg:phone":"+41 26 917 84 01",
    "sg:postcode":"1625",
    "sg:province":"Fribourg",
    "sg:tags":[
        "milling",
        "cnc"
    ],
    "wof:name":"Bumotec Sa Machines-outils",
    "wof:placetype":"venue"
},
  "geometry": {"coordinates":[6.97125,46.63237],"type":"Point"}
}