{
  "type": "Feature",
  "properties": {
    "iso:country":"CH",
    "sg:address":"Alte Landstrasse 26 9445 Rebstein. Postfach",
    "sg:city":"Rebstein",
    "sg:orig_category":"RESTAURANTS: TEA-ROOMS",
    "sg:postcode":"9445",
    "sg:province":"St. Gallen",
    "wof:name":"K\u00f6ppel Manuela Restaurationsbetrieb",
    "wof:placetype":"venue"
},
  "geometry": {"coordinates":[9.585559845,47.3997459412],"type":"Point"}
}