{
  "type": "Feature",
  "properties": {
    "iso:country":"CH",
    "sg:address":"Graben",
    "sg:city":"Siblingen",
    "sg:orig_category":"P\u00e9dicure",
    "sg:phone":"+41 62 822 85 36",
    "sg:postcode":"8225",
    "sg:province":"Schaffhausen",
    "wof:name":"Margrit Tellenbach P\u00e9dicure",
    "wof:placetype":"venue"
},
  "geometry": {"coordinates":[8.082365036,47.3999710083],"type":"Point"}
}