{
  "type": "Feature",
  "properties": {
    "iso:country":"CH",
    "sg:address":"Luzernerstrasse 19",
    "sg:city":"Wikon",
    "sg:orig_category":"Verwertung von Milch",
    "sg:postcode":"4806",
    "sg:province":"Luzern",
    "wof:name":"K\u00e4serei-genossenschaft Wikon-adelboden",
    "wof:placetype":"venue"
},
  "geometry": {"coordinates":[7.9635257721,47.2663650513],"type":"Point"}
}