{
  "type": "Feature",
  "properties": {
    "iso:country":"CH",
    "sg:address":"Biberbrugg",
    "sg:city":"Bennau",
    "sg:classifiers":[
        {
            "category":"Travel",
            "subcategory":"Hotels & Motels",
            "type":"Entertainment"
        }
    ],
    "sg:phone":"+41 81 861 92 00",
    "sg:postcode":"8836",
    "sg:province":"Schwyz",
    "sg:tags":[
        "hotels",
        "mit",
        "restaurant"
    ],
    "wof:name":"Hotel Post",
    "wof:placetype":"venue"
},
  "geometry": {"coordinates":[10.3607826233,46.9438514709],"type":"Point"}
}