{
  "type": "Feature",
  "properties": {
    "iso:country":"CH",
    "sg:address":"St\u00fcsslingerstrasse 6",
    "sg:city":"Niedererlinsbach",
    "sg:orig_category":"Reinigungsgewerbe",
    "sg:phone":"+41 79 330 26 41",
    "sg:postcode":"5015",
    "sg:province":"Solothurn",
    "wof:name":"Franco's Work M.t.g. Gmbh",
    "wof:placetype":"venue"
},
  "geometry": {"coordinates":[8.0074653625,47.3984985352],"type":"Point"}
}