{
  "type": "Feature",
  "properties": {
    "iso:country":"CH",
    "sg:address":"Passage Malbuisson 17-18bis 1200 Genf. Postfach",
    "sg:city":"Gen\u00e8ve",
    "sg:orig_category":"Fachdetailhandel in Verkaufsr\u00e4umen",
    "sg:postcode":"1200",
    "sg:province":"Gen\u00e8ve",
    "wof:name":"Le Portique Malbuisson Sa",
    "wof:placetype":"venue"
},
  "geometry": {"coordinates":[6.1465239525,46.2037239075],"type":"Point"}
}