{
  "type": "Feature",
  "properties": {
    "iso:country":"CH",
    "sg:address":"Via Sindacatori 4 6900 Massagno. Postfach",
    "sg:city":"Massagno",
    "sg:orig_category":"RESTAURANTS: TEA-ROOMS",
    "sg:postcode":"6900",
    "sg:province":"Ticino",
    "wof:name":"Zelop Sa",
    "wof:placetype":"venue"
},
  "geometry": {"coordinates":[8.9436264038,46.0111732483],"type":"Point"}
}