{
  "type": "Feature",
  "properties": {
    "iso:country":"CH",
    "sg:address":"Landstrasse 47",
    "sg:city":"Gipf-oberfrick",
    "sg:orig_category":"Detailhandel mit Schuhen U Lederwaren",
    "sg:postcode":"5073",
    "sg:province":"Aargau",
    "wof:name":"Schuhaus Ursprung U. Orthop\u00e4d. Werkst\u00e4tte",
    "wof:placetype":"venue"
},
  "geometry": {"coordinates":[8.0020599365,47.4969711304],"type":"Point"}
}