{
  "type": "Feature",
  "properties": {
    "iso:country":"CH",
    "sg:address":"Pr\u00e9 Chemin Du 5",
    "sg:city":"St-prex",
    "sg:orig_category":"Sonstiges Versicherungsgewerbe",
    "sg:phone":"+41 22 818 55 30",
    "sg:postcode":"1162",
    "sg:province":"Vaud",
    "wof:name":"Asc Assurances Et Courtages Sa",
    "wof:placetype":"venue"
},
  "geometry": {"coordinates":[6.1611471176,46.1972312927],"type":"Point"}
}