{
  "type": "Feature",
  "properties": {
    "iso:country":"CH",
    "sg:address":"Rue De L'ecluse 49",
    "sg:city":"Neuch\u00e2tel",
    "sg:orig_category":"Sportvereine Ballsport Fussball",
    "sg:phone":"+41 32 724 41 10",
    "sg:postcode":"2000",
    "sg:province":"Neuch\u00e2tel",
    "wof:name":"Fc Salento C/o Fam.leccese",
    "wof:placetype":"venue"
},
  "geometry": {"coordinates":[6.9229187965,46.9921531677],"type":"Point"}
}