{
  "type": "Feature",
  "properties": {
    "iso:country":"CH",
    "sg:address":"Geerenstrasse 6 8157 Dielsdorf. Postfach 210",
    "sg:city":"Dielsdorf",
    "sg:orig_category":"Architektur U Ingenieurb\u00fcros",
    "sg:phone":"+41 31 839 09 11",
    "sg:postcode":"8157",
    "sg:province":"Z\u00fcrich",
    "wof:name":"Will + Partner Architekten Ag",
    "wof:placetype":"venue"
},
  "geometry": {"coordinates":[7.56353,46.930168],"type":"Point"}
}