{
  "type": "Feature",
  "properties": {
    "iso:country":"CH",
    "sg:address":"1773",
    "sg:city":"Chandon",
    "sg:orig_category":"Elektroinstallation",
    "sg:postcode":"1773",
    "sg:province":"Fribourg",
    "wof:name":"Paul Sautaux Et Fils Sa",
    "wof:placetype":"venue"
},
  "geometry": {"coordinates":[7.0473098755,46.8386802673],"type":"Point"}
}