{
  "type": "Feature",
  "properties": {
    "iso:country":"CH",
    "sg:address":"Steinwiesstrasse 34",
    "sg:city":"Z\u00fcrich",
    "sg:orig_category":"Vereine Gesang",
    "sg:phone":"+41 12516035",
    "sg:postcode":"8032",
    "sg:province":"Z\u00fcrich",
    "wof:name":"Gemischter Chor Der Baptistengemeinde",
    "wof:placetype":"venue"
},
  "geometry": {"coordinates":[8.5536050797,47.3703536987],"type":"Point"}
}