{
  "type": "Feature",
  "properties": {
    "iso:country":"CH",
    "sg:address":"Spechtenstrasse 52",
    "sg:city":"Dierikon",
    "sg:orig_category":"Herstellung von K\u00fcchenm\u00f6beln Innenausbau",
    "sg:phone":"+41 79 218 50 51",
    "sg:postcode":"6036",
    "sg:province":"Luzern",
    "wof:name":"Pl\u00fcss Sigi",
    "wof:placetype":"venue"
},
  "geometry": {"coordinates":[8.3678092957,47.0931930542],"type":"Point"}
}