{
  "type": "Feature",
  "properties": {
    "iso:country":"CH",
    "sg:address":"Br\u00fcnigstrasse 82",
    "sg:city":"Sachseln",
    "sg:orig_category":"Herstellung von W\u00e4sche",
    "sg:phone":"+41 41 660 05 22",
    "sg:postcode":"6072",
    "sg:province":"Obwalden",
    "wof:name":"Karussell Tornusciolo A.",
    "wof:placetype":"venue"
},
  "geometry": {"coordinates":[8.2409572601,46.870426178],"type":"Point"}
}