{
  "type": "Feature",
  "properties": {
    "addr:full":"Seefeldstrasse 197 Z\u00fcrich Z\u00fcrich 8008",
    "addr:housenumber":"197",
    "addr:postcode":"8008",
    "addr:street":"Seefeldstrasse",
    "iso:country":"CH",
    "sg:address":"Seefeldstrasse 197",
    "sg:city":"Z\u00fcrich",
    "sg:orig_category":"Detailhandel mit Bekleidung",
    "sg:phone":"+41 13831206",
    "sg:postcode":"8008",
    "sg:province":"Z\u00fcrich",
    "wof:name":"Atelier Sch\u00e4rer Claire, Inh. Wiederkehr-sch\u00e4rer U.",
    "wof:placetype":"venue"
},
  "geometry": {"coordinates":[8.558724,47.353455],"type":"Point"}
}