{
  "type": "Feature",
  "properties": {
    "iso:country":"CH",
    "sg:address":"Bellariastrasse 23",
    "sg:city":"Z\u00fcrich",
    "sg:orig_category":"Non-Classified Establishments",
    "sg:phone":"+41 12048000",
    "sg:postcode":"8002",
    "sg:province":"Z\u00fcrich",
    "wof:name":"Swissfirst Bank Ag",
    "wof:placetype":"venue"
},
  "geometry": {"coordinates":[8.5308265686,47.3532943726],"type":"Point"}
}