{
  "type": "Feature",
  "properties": {
    "iso:country":"CH",
    "sg:address":"Imm.ramona",
    "sg:city":"Montana-vermala",
    "sg:orig_category":"Detailhandel mit Uhren U Schmuck Sonstiger Fachdetailhandel in Verkaufsr\u00e4umen",
    "sg:phone":"+41 27 481 51 61",
    "sg:postcode":"3962",
    "wof:name":"Fun & Fashion Heidi Zurfluh Montre Bijoux Fantaisie",
    "wof:placetype":"venue"
},
  "geometry": {"coordinates":[7.4924340248,46.3144187927],"type":"Point"}
}