{
  "type": "Feature",
  "properties": {
    "iso:country":"CH",
    "sg:address":"Z\u00fcrcherstrasse 102",
    "sg:city":"Altendorf",
    "sg:orig_category":"Grosshandel mit B\u00fcromaschinen Grosshandel mit Datenverarbeitungsger\u00e4ten",
    "sg:phone":"+41 71 313 96 90",
    "sg:postcode":"8852",
    "sg:province":"Schwyz",
    "wof:name":"Datadesign Office Ag",
    "wof:placetype":"venue"
},
  "geometry": {"coordinates":[9.3128166199,47.4085845947],"type":"Point"}
}