{
  "type": "Feature",
  "properties": {
    "iso:country":"CH",
    "sg:address":"Bachweg 1d",
    "sg:city":"Ober\u00e4geri",
    "sg:orig_category":"Non-Classified Establishments",
    "sg:phone":"+41 41 763 64 47",
    "sg:postcode":"6315",
    "sg:province":"Zug",
    "wof:name":"Vocalis Telecom Holding Ag",
    "wof:placetype":"venue"
},
  "geometry": {"coordinates":[8.6125745773,47.1349945068],"type":"Point"}
}