{
  "type": "Feature",
  "properties": {
    "iso:country":"CH",
    "sg:address":"Pestalozzistrasse 69b",
    "sg:city":"Thun",
    "sg:orig_category":"Unclassifiable Establishments",
    "sg:postcode":"3600",
    "sg:province":"Bern",
    "wof:name":"Mgs-videoproduktionen, Nikolic M.",
    "wof:placetype":"venue"
},
  "geometry": {"coordinates":[7.6141247749,46.7509727478],"type":"Point"}
}