{
  "type": "Feature",
  "properties": {
    "iso:country":"CH",
    "sg:address":"Manessestrasse 10",
    "sg:city":"Z\u00fcrich",
    "sg:orig_category":"Advokaturb\u00fcros",
    "sg:phone":"+41 12024727",
    "sg:postcode":"8003",
    "sg:province":"Z\u00fcrich",
    "wof:name":"Dani Rothschild Advokaturb\u00fcro",
    "wof:placetype":"venue"
},
  "geometry": {"coordinates":[8.526767,47.369473],"type":"Point"}
}