{
  "type": "Feature",
  "properties": {
    "iso:country":"CH",
    "sg:address":"Maraini Via 27 6942 Savosa. Postfach",
    "sg:city":"Savosa",
    "sg:orig_category":"Fachdetailhandel in Verkaufsr\u00e4umen",
    "sg:phone":"+41 91 972 51 70",
    "sg:postcode":"6942",
    "sg:province":"Ticino",
    "wof:name":"Ludex Sa",
    "wof:placetype":"venue"
},
  "geometry": {"coordinates":[8.9505434036,46.0234375],"type":"Point"}
}