{
  "type": "Feature",
  "properties": {
    "iso:country":"CH",
    "sg:address":"Susenbergstrasse 31",
    "sg:city":"Z\u00fcrich",
    "sg:orig_category":"Advokaturb\u00fcros",
    "sg:phone":"+41 12527717",
    "sg:postcode":"8044",
    "sg:province":"Z\u00fcrich",
    "wof:name":"Hanspeter Buchschacher Advokaturb\u00fcro",
    "wof:placetype":"venue"
},
  "geometry": {"coordinates":[8.56715,47.378441],"type":"Point"}
}