{
  "type": "Feature",
  "properties": {
    "iso:country":"CH",
    "sg:address":"Rest. Tanne 3536 Aeschau. Postfach",
    "sg:city":"Aeschau",
    "sg:orig_category":"RESTAURANTS: TEA-ROOMS",
    "sg:postcode":"3536",
    "sg:province":"Bern",
    "wof:name":"Moser Therese",
    "wof:placetype":"venue"
},
  "geometry": {"coordinates":[7.7624411583,46.9091949463],"type":"Point"}
}