{
  "type": "Feature",
  "properties": {
    "iso:country":"CH",
    "sg:address":"Hauptstrasse 8754 Netstal. Postfach",
    "sg:city":"Netstal",
    "sg:orig_category":"RESTAURANTS: TEA-ROOMS",
    "sg:phone":"+41 62 824 28 82",
    "sg:postcode":"8754",
    "sg:province":"Glarus",
    "wof:name":"Caf\u00e9 Zentrum Huser K.",
    "wof:placetype":"venue"
},
  "geometry": {"coordinates":[8.0734796524,47.3886985779],"type":"Point"}
}