{
  "type": "Feature",
  "properties": {
    "iso:country":"CH",
    "sg:address":"Cossonay Route De",
    "sg:city":"Echallens",
    "sg:orig_category":"Herstellung von Mess U Kontrollinstrumenten U vorrichtungen",
    "sg:phone":"+41 21 886 30 30",
    "sg:postcode":"1040",
    "sg:province":"Vaud",
    "wof:name":"Amg Henchoz Patrick Sa",
    "wof:placetype":"venue"
},
  "geometry": {"coordinates":[6.634363,46.640865],"type":"Point"}
}