{
  "type": "Feature",
  "properties": {
    "iso:country":"CH",
    "sg:address":"4537",
    "sg:city":"Wiedlisbach",
    "sg:orig_category":"Schulpflegen",
    "sg:postcode":"4537",
    "sg:province":"Bern",
    "wof:name":"Primarschulkommission Der Gemeinde Wilen Bei Wil",
    "wof:placetype":"venue"
},
  "geometry": {"coordinates":[9.0343503952,47.4465484619],"type":"Point"}
}