{
  "type": "Feature",
  "properties": {
    "iso:country":"CH",
    "sg:address":"Rue De L'eglise",
    "sg:city":"Fully",
    "sg:orig_category":"Elektrizit\u00e4tsversorgung Wasserversorgung",
    "sg:phone":"+41 27 747 11 70",
    "sg:postcode":"1926",
    "sg:province":"Valais",
    "wof:name":"Administration Communale Services Industriels",
    "wof:placetype":"venue"
},
  "geometry": {"coordinates":[7.1151638031,46.1387557983],"type":"Point"}
}