{
  "type": "Feature",
  "properties": {
    "iso:country":"CH",
    "sg:address":"Gfeld 153",
    "sg:city":"Trogen",
    "sg:classifiers":[
        {
            "category":"Restaurant",
            "type":"Food & Drink"
        }
    ],
    "sg:phone":"+41 71 344 14 09",
    "sg:postcode":"9043",
    "sg:province":"Appenzell Ausserrhoden",
    "wof:name":"Restaurant Sonne",
    "wof:placetype":"venue"
},
  "geometry": {"coordinates":[9.4572687149,47.4059486389],"type":"Point"}
}