{
  "type": "Feature",
  "properties": {
    "iso:country":"CH",
    "sg:address":"Via Rongia 3",
    "sg:city":"Losone",
    "sg:classifiers":[
        {
            "category":"Train Station",
            "subcategory":"Light Rail",
            "type":"Transportation"
        }
    ],
    "sg:phone":"+41 91 791 85 55",
    "sg:postcode":"6616",
    "sg:province":"Ticino",
    "sg:tags":[
        "cartridge",
        "seal"
    ],
    "wof:name":"Gommec Guarnizioni Meccaniche S.a.",
    "wof:placetype":"venue"
},
  "geometry": {"coordinates":[8.738091,46.178253],"type":"Point"}
}