{
  "type": "Feature",
  "properties": {
    "addr:full":"Dorfstrasse 115 Effingen Aargau 5078",
    "addr:housenumber":"115",
    "addr:postcode":"5078",
    "addr:street":"Dorfstrasse",
    "iso:country":"CH",
    "sg:address":"Dorfstrasse 115",
    "sg:city":"Effingen",
    "sg:orig_category":"Darlehenskassen U Raiffeisenbanken",
    "sg:phone":"+41 62 867 40 60",
    "sg:postcode":"5078",
    "sg:province":"Aargau",
    "wof:name":"Raiffeisenbank B\u00f6zberg West",
    "wof:placetype":"venue"
},
  "geometry": {"coordinates":[8.104475,47.48933],"type":"Point"}
}