{
  "type": "Feature",
  "properties": {
    "iso:country":"CH",
    "sg:address":"Allmend",
    "sg:city":"Wengen",
    "sg:classifiers":[
        {
            "category":"Restaurant",
            "type":"Food & Drink"
        }
    ],
    "sg:phone":"+41 33 855 58 00",
    "sg:postcode":"3823",
    "sg:province":"Bern",
    "wof:name":"Restaurant Allmend",
    "wof:placetype":"venue"
},
  "geometry": {"coordinates":[7.921599865,46.6051940918],"type":"Point"}
}