{
  "type": "Feature",
  "properties": {
    "iso:country":"CH",
    "sg:address":"Rue Des Granges 24",
    "sg:city":"Payerne",
    "sg:orig_category":"Vermittlung von Immobilien Verwaltung von Immobilien",
    "sg:phone":"+41 79 358 38 64",
    "sg:postcode":"1530",
    "sg:province":"Vaud",
    "wof:name":"Neo Villa S\u00e0rl",
    "wof:placetype":"venue"
},
  "geometry": {"coordinates":[6.9388728142,46.8197555542],"type":"Point"}
}