{
  "type": "Feature",
  "properties": {
    "iso:country":"CH",
    "sg:address":"Herrengasse 3",
    "sg:city":"Schwyz",
    "sg:orig_category":"Architektur U Ingenieurb\u00fcros",
    "sg:phone":"+41 41 811 68 21",
    "sg:postcode":"6431",
    "sg:province":"Schwyz",
    "wof:name":"G\u00fcrber A. Ag",
    "wof:placetype":"venue"
},
  "geometry": {"coordinates":[8.6529598236,47.0214691162],"type":"Point"}
}