{
  "type": "Feature",
  "properties": {
    "iso:country":"CH",
    "sg:address":"Avenue Des Cavaliers 11",
    "sg:city":"Ch\u00eane-bougeries",
    "sg:orig_category":"Kauf U Verkauf von Immobilien auf eigene Rechnung",
    "sg:phone":"+41 79 607 64 71",
    "sg:postcode":"1224",
    "sg:province":"Gen\u00e8ve",
    "wof:name":"Bartel Immobilier",
    "wof:placetype":"venue"
},
  "geometry": {"coordinates":[6.1836748123,46.2022438049],"type":"Point"}
}