{
  "type": "Feature",
  "properties": {
    "iso:country":"CH",
    "sg:address":"Industria Via 2 6963 Pregassona. Postfach",
    "sg:city":"Pregassona",
    "sg:orig_category":"Non-Classified Establishments",
    "sg:postcode":"6963",
    "sg:province":"Ticino",
    "wof:name":"Terzic Jozo Sports Management Manager Sportivo Spec. Intermediazione Di Contratti Per Calciatori Ecc",
    "wof:placetype":"venue"
},
  "geometry": {"coordinates":[8.9659729004,46.0219612122],"type":"Point"}
}