{
  "type": "Feature",
  "properties": {
    "iso:country":"CH",
    "sg:address":"Heitersberg 837",
    "sg:city":"Wolfhalden",
    "sg:orig_category":"Herstellung von Elektrizit\u00e4tsverteilungs U schalteinrichtungen Herstellung von elektronischen Bauele",
    "sg:phone":"+41 71 888 66 11",
    "sg:postcode":"9427",
    "sg:province":"Appenzell Ausserrhoden",
    "wof:name":"Abb Cmc Systeme Ag",
    "wof:placetype":"venue"
},
  "geometry": {"coordinates":[9.5709581375,47.4534912109],"type":"Point"}
}