{
  "type": "Feature",
  "properties": {
    "iso:country":"CH",
    "sg:address":"Bohler 334",
    "sg:city":"Gontenschwil",
    "sg:orig_category":"Grosshandel mit Baumaterialien",
    "sg:phone":"+41 62 773 25 89",
    "sg:postcode":"5728",
    "sg:province":"Aargau",
    "wof:name":"Sebastian M\u00fcller Ag Betonwaren",
    "wof:placetype":"venue"
},
  "geometry": {"coordinates":[8.1328325272,47.2463111877],"type":"Point"}
}