{
  "type": "Feature",
  "properties": {
    "iso:country":"CH",
    "sg:address":"Rue Du March\u00e9 7 1522 Lucens. Postfach",
    "sg:city":"Lucens",
    "sg:orig_category":"Detailhandel mit Fleisch U Fleischwaren",
    "sg:phone":"+41 41 850 13 39",
    "sg:postcode":"1522",
    "sg:province":"Vaud",
    "wof:name":"Armin Sidler Metzgerei",
    "wof:placetype":"venue"
},
  "geometry": {"coordinates":[8.4395217896,47.0818634033],"type":"Point"}
}