{
  "type": "Feature",
  "properties": {
    "iso:country":"CH",
    "sg:address":"Laupenstrasse 22",
    "sg:city":"Bern",
    "sg:orig_category":"Vermietung von Automobilen",
    "sg:phone":"+41 31 381 75 55",
    "sg:postcode":"3008",
    "sg:province":"Bern",
    "wof:name":"Europcar Autovermietung",
    "wof:placetype":"venue"
},
  "geometry": {"coordinates":[7.4339089394,46.9475097656],"type":"Point"}
}