{
  "type": "Feature",
  "properties": {
    "iso:country":"CH",
    "sg:address":"Oristalstr. 87a",
    "sg:city":"Liestal",
    "sg:orig_category":"Miscellaneous Products",
    "sg:phone":"+41 61 926 87 00",
    "sg:postcode":"4410",
    "sg:province":"Basel-Landschaft",
    "wof:name":"Niclas Ag",
    "wof:placetype":"venue"
},
  "geometry": {"coordinates":[7.7247920036,47.4765586853],"type":"Point"}
}