{
  "type": "Feature",
  "properties": {
    "iso:country":"CH",
    "sg:address":"Sch\u00fctzenweg 3",
    "sg:city":"Balsthal",
    "sg:orig_category":"Instandhaltung U Reparatur von Automobilen",
    "sg:phone":"+41 62 391 50 40",
    "sg:postcode":"4710",
    "sg:province":"Solothurn",
    "wof:name":"J\u00e4ggin Ruedi",
    "wof:placetype":"venue"
},
  "geometry": {"coordinates":[7.6964788437,47.3133239746],"type":"Point"}
}