{
  "type": "Feature",
  "properties": {
    "iso:country":"CH",
    "sg:address":"Gotthardstrasse 26",
    "sg:city":"Arth",
    "sg:classifiers":[
        {
            "category":"Museum",
            "subcategory":"Art Museum",
            "type":"Entertainment"
        }
    ],
    "sg:phone":"+41 41 855 14 10",
    "sg:postcode":"6415",
    "sg:province":"Schwyz",
    "sg:tags":[
        "artwork"
    ],
    "wof:name":"Druckerei Rauchenstein",
    "wof:placetype":"venue"
},
  "geometry": {"coordinates":[8.522834,47.062183],"type":"Point"}
}