{
  "type": "Feature",
  "properties": {
    "iso:country":"CH",
    "sg:address":"Alpenstrasse 8",
    "sg:city":"Heimberg",
    "sg:orig_category":"Grosshandel mit Datenverarbeitungsger\u00e4ten Softwareentwicklung U beratung",
    "sg:phone":"+41 33 437 38 45",
    "sg:postcode":"3627",
    "sg:province":"Bern",
    "wof:name":"Garatec Gmbh",
    "wof:placetype":"venue"
},
  "geometry": {"coordinates":[7.6018381119,46.7914466858],"type":"Point"}
}