{
  "type": "Feature",
  "properties": {
    "iso:country":"CH",
    "sg:address":"3989",
    "sg:city":"Ritzingen",
    "sg:orig_category":"Malerei",
    "sg:phone":"+41 27 973 13 60",
    "sg:postcode":"3989",
    "sg:province":"Valais",
    "wof:name":"Maria Salzmann Malergesch\u00e4ft",
    "wof:placetype":"venue"
},
  "geometry": {"coordinates":[8.2226200104,46.4570388794],"type":"Point"}
}