{
  "type": "Feature",
  "properties": {
    "iso:country":"CH",
    "sg:address":"Reinacherstrasse 43",
    "sg:city":"M\u00fcnchenstein",
    "sg:orig_category":"Reparatur von Schuhen U Lederwaren",
    "sg:phone":"+41 61 411 56 92",
    "sg:postcode":"4142",
    "sg:province":"Basel-Landschaft",
    "wof:name":"Stefano Maruccia Schuh-& Schl\u00fcsselservice",
    "wof:placetype":"venue"
},
  "geometry": {"coordinates":[7.605700016,47.5296707153],"type":"Point"}
}