{
  "type": "Feature",
  "properties": {
    "iso:country":"CH",
    "sg:address":"Ueberlandstrasse 9 3900 Brig. Postfach 256",
    "sg:city":"Brig",
    "sg:orig_category":"Personenbef\u00f6rderung im Linienverkehr zu Land Personenbef\u00f6rderung im Nahverkehr",
    "sg:phone":"+41 27 922 81 11",
    "sg:postcode":"3900",
    "sg:province":"Valais",
    "wof:name":"Furka-oberalp-bahn",
    "wof:placetype":"venue"
},
  "geometry": {"coordinates":[7.9846119881,46.3180198669],"type":"Point"}
}