{
  "type": "Feature",
  "properties": {
    "iso:country":"CH",
    "sg:address":"Sonnenbergstrasse 5",
    "sg:city":"D\u00fcrnten",
    "sg:orig_category":"Reiseb\u00fcros U Reiseveranstalter",
    "sg:postcode":"8635",
    "sg:province":"Z\u00fcrich",
    "wof:name":"Express Reisen, Degirmenler Kadri",
    "wof:placetype":"venue"
},
  "geometry": {"coordinates":[8.8527851105,47.2657051086],"type":"Point"}
}