{
  "type": "Feature",
  "properties": {
    "iso:country":"CH",
    "sg:address":"Gr\u00fcnenstrasse 25 3455 Gr\u00fcnen. Postfach",
    "sg:city":"Gr\u00fcnen",
    "sg:orig_category":"Elektroinstallation",
    "sg:phone":"+41 34 431 15 66",
    "sg:postcode":"3455",
    "sg:province":"Bern",
    "wof:name":"Elektro Reist Ag",
    "wof:placetype":"venue"
},
  "geometry": {"coordinates":[7.7388429642,47.0245323181],"type":"Point"}
}