{
  "type": "Feature",
  "properties": {
    "iso:country":"CH",
    "sg:address":"Langensandstrasse 25",
    "sg:city":"Luzern",
    "sg:orig_category":"Architekturb\u00fcros",
    "sg:phone":"+41 41 362 11 95",
    "sg:postcode":"6005",
    "sg:province":"Luzern",
    "wof:name":"Werner Hunziker Architekturb\u00fcro",
    "wof:placetype":"venue"
},
  "geometry": {"coordinates":[8.328139,47.036884],"type":"Point"}
}