{
  "type": "Feature",
  "properties": {
    "iso:country":"CH",
    "sg:address":"Baselstrasse 50 6003 Luzern. Postfach",
    "sg:city":"Luzern",
    "sg:orig_category":"Detailhandel mit Bekleidung",
    "sg:postcode":"6003",
    "sg:province":"Luzern",
    "wof:name":"Boutique Ciao Mammarella Textilien; Verkauf",
    "wof:placetype":"venue"
},
  "geometry": {"coordinates":[8.294352,47.053558],"type":"Point"}
}