{
  "type": "Feature",
  "properties": {
    "iso:country":"CH",
    "sg:address":"Fontanella Via 16 6932 Breganzona. Postfach",
    "sg:city":"Breganzona",
    "sg:orig_category":"Unclassifiable Establishments",
    "sg:postcode":"6932",
    "sg:province":"Ticino",
    "wof:name":"Art & Giardini Sagl Lavori Di Giardinaggio Ecc.; Progettazione, Consulenza E Realizzazione",
    "wof:placetype":"venue"
},
  "geometry": {"coordinates":[8.9248876572,46.0064048767],"type":"Point"}
}