{
  "type": "Feature",
  "properties": {
    "iso:country":"CH",
    "sg:address":"Thorenbergstrasse 45",
    "sg:city":"Littau",
    "sg:orig_category":"Gartenbau",
    "sg:phone":"+41 41 250 75 50",
    "sg:postcode":"6014",
    "sg:province":"Luzern",
    "wof:name":"Felix Hodel & Partner Gartenpflege",
    "wof:placetype":"venue"
},
  "geometry": {"coordinates":[8.2567996979,47.0558586121],"type":"Point"}
}