{
  "type": "Feature",
  "properties": {
    "iso:country":"CH",
    "sg:address":"Sch\u00f6nbeinstrasse 20",
    "sg:city":"Basel",
    "sg:orig_category":"Forschung U Entwicklung im Bereich der Naturwissenschaften",
    "sg:phone":"+41 22 827 27 27",
    "sg:postcode":"4056",
    "sg:province":"Basel-Stadt",
    "wof:name":"Battelle Memorial Institute, At Columbus (ohio, Usa), Geneva Research Centres, Carouge (geneva)",
    "wof:placetype":"venue"
},
  "geometry": {"coordinates":[6.1383857727,46.1757926941],"type":"Point"}
}