{
  "type": "Feature",
  "properties": {
    "iso:country":"CH",
    "sg:address":"Route De Fribourg",
    "sg:city":"Pensier",
    "sg:orig_category":"Bauingenieurb\u00fcros Heizung L\u00fcftung Klima Bauingenieurb\u00fcros allgemein",
    "sg:phone":"+41 26 684 00 40",
    "sg:postcode":"1783",
    "sg:province":"Fribourg",
    "wof:name":"Im Bureau D'ingenieurs Maggia Sa",
    "wof:placetype":"venue"
},
  "geometry": {"coordinates":[7.159655,46.857666],"type":"Point"}
}