{
  "type": "Feature",
  "properties": {
    "iso:country":"CH",
    "sg:address":"Bitzi",
    "sg:city":"Obstalden",
    "sg:orig_category":"Bauschreinerei Herstellung von Konstruktionsteilen, Fertigbauteilen U Ausbauelementen aus Holz",
    "sg:phone":"+41 33 822 39 66",
    "sg:postcode":"8758",
    "sg:province":"Glarus",
    "wof:name":"Ed. Kuhn Ag",
    "wof:placetype":"venue"
},
  "geometry": {"coordinates":[7.86665,46.67712],"type":"Point"}
}