{
  "type": "Feature",
  "properties": {
    "iso:country":"CH",
    "sg:address":"Oberdorf",
    "sg:city":"Bettwil",
    "sg:orig_category":"Primarschulen",
    "sg:phone":"+41 56 667 25 38",
    "sg:postcode":"5618",
    "sg:province":"Aargau",
    "wof:name":"Primarschule",
    "wof:placetype":"venue"
},
  "geometry": {"coordinates":[8.2651901245,47.2903289795],"type":"Point"}
}