{
  "type": "Feature",
  "properties": {
    "iso:country":"CH",
    "sg:address":"Bergstrasse 8",
    "sg:city":"Embrach",
    "sg:orig_category":"G\u00fcterbef\u00f6rderung im Strassenverkehr",
    "sg:postcode":"8424",
    "sg:province":"Z\u00fcrich",
    "wof:name":"Waldmeier Hans",
    "wof:placetype":"venue"
},
  "geometry": {"coordinates":[8.5990867615,47.501373291],"type":"Point"}
}