{
  "type": "Feature",
  "properties": {
    "iso:country":"CH",
    "sg:address":"6390 Engelberg. Postfach 324",
    "sg:city":"Engelberg",
    "sg:orig_category":"Interessenvertretungen U sonstige Vereinigungen",
    "sg:postcode":"6391",
    "sg:province":"Obwalden",
    "wof:name":"Verb.schw.tapetenfachh\u00e4ndler C/o Schwager Tapeten",
    "wof:placetype":"venue"
},
  "geometry": {"coordinates":[9.0666770935,47.4648742676],"type":"Point"}
}