{
  "type": "Feature",
  "properties": {
    "iso:country":"CH",
    "sg:address":"Kirchhofplatz 19",
    "sg:city":"Schaffhausen",
    "sg:classifiers":[
        {
            "category":"Education",
            "subcategory":"Vocational School",
            "type":"Public Place"
        }
    ],
    "sg:phone":"+41 52 624 16 97",
    "sg:postcode":"8200",
    "sg:province":"Schaffhausen",
    "sg:tags":[
        "koch-",
        "haushaltschulen"
    ],
    "wof:name":"Schule F.haushalt & Praktische Lebensgestaltung Shpl",
    "wof:placetype":"venue"
},
  "geometry": {"coordinates":[8.6363048553,47.6967811584],"type":"Point"}
}