{
  "type": "Feature",
  "properties": {
    "iso:country":"CH",
    "sg:address":"Gutenbergstrasse 40b",
    "sg:city":"Bern",
    "sg:orig_category":"Grosshandel mit Eisenwaren sowie Installationsbedarf f\u00fcr Gas, Wasser U Heizung Herstellung von k\u00e4lte",
    "sg:phone":"+41 31 382 24 26",
    "sg:postcode":"3011",
    "sg:province":"Bern",
    "wof:name":"Gr\u00fctt-air Ag",
    "wof:placetype":"venue"
},
  "geometry": {"coordinates":[7.4335579872,46.9433822632],"type":"Point"}
}