{
  "type": "Feature",
  "properties": {
    "addr:full":"Avenue De Rumine 31 Lausanne Vaud 1005",
    "addr:housenumber":"31",
    "addr:postcode":"1005",
    "addr:street":"Avenue De Rumine",
    "iso:country":"CH",
    "sg:address":"Avenue De Rumine 31",
    "sg:city":"Lausanne",
    "sg:orig_category":"Arztpraxen",
    "sg:phone":"+41 21 312 01 12",
    "sg:postcode":"1005",
    "sg:province":"Vaud",
    "wof:name":"Dr M\u00e9d. Florence Depeursinge M\u00e9decin Sp\u00e9cialiste Fmh",
    "wof:placetype":"venue"
},
  "geometry": {"coordinates":[6.64162,46.516533],"type":"Point"}
}