{
  "type": "Feature",
  "properties": {
    "iso:country":"CH",
    "sg:address":"Bifang 56",
    "sg:city":"Grindel",
    "sg:orig_category":"Politische Parteien FDP",
    "sg:phone":"+41 61 761 69 76",
    "sg:postcode":"4247",
    "sg:province":"Solothurn",
    "wof:name":"Fdp Ortspartei Grindel",
    "wof:placetype":"venue"
},
  "geometry": {"coordinates":[7.5032730103,47.3797187805],"type":"Point"}
}