{
  "type": "Feature",
  "properties": {
    "iso:country":"CH",
    "sg:address":"Alter Z\u00fcrichweg 21 8952 Schlieren. Postfach",
    "sg:city":"Schlieren",
    "sg:orig_category":"Sonstiger Grosshandel",
    "sg:postcode":"8952",
    "sg:province":"Z\u00fcrich",
    "wof:name":"Schurtenberger E.",
    "wof:placetype":"venue"
},
  "geometry": {"coordinates":[8.4513721466,47.3948745728],"type":"Point"}
}