{
  "type": "Feature",
  "properties": {
    "iso:country":"CH",
    "sg:address":"Place De La Tillette",
    "sg:city":"Bassins",
    "sg:orig_category":"Architekturb\u00fcros",
    "sg:phone":"+41 21 366 30 65",
    "sg:postcode":"1269",
    "sg:province":"Vaud",
    "wof:name":"G. Dup\u00e9rier & J. Meichtry Bureau D'architecture",
    "wof:placetype":"venue"
},
  "geometry": {"coordinates":[6.231705,46.46376],"type":"Point"}
}