{
  "type": "Feature",
  "properties": {
    "iso:country":"CH",
    "sg:address":"Obere Gletscherstrasse",
    "sg:city":"Grindelwald",
    "sg:orig_category":"Bauschreinerei Bestattungswesen",
    "sg:phone":"+41 34 435 12 82",
    "sg:postcode":"3818",
    "sg:province":"Bern",
    "wof:name":"Hansueli Stalder Schreinerei & Bestattungen",
    "wof:placetype":"venue"
},
  "geometry": {"coordinates":[7.741273,47.062836],"type":"Point"}
}