{
  "type": "Feature",
  "properties": {
    "iso:country":"CH",
    "sg:address":"Alte Schmiede 111",
    "sg:city":"Eriswil",
    "sg:orig_category":"Herstellung von Metallkonstruktionen",
    "sg:phone":"+41 62 966 12 68",
    "sg:postcode":"4952",
    "sg:province":"Bern",
    "wof:name":"Rutschmann Metallbautechnik",
    "wof:placetype":"venue"
},
  "geometry": {"coordinates":[7.8506450653,47.0790901184],"type":"Point"}
}