{
  "type": "Feature",
  "properties": {
    "iso:country":"CH",
    "sg:address":"Kellerhofstrasse 11 8353 Elgg. Postfach 171",
    "sg:city":"Elgg",
    "sg:orig_category":"Vermietung U Verpachtung von eigenen Immobilien Vermittlung von Immobilien",
    "sg:phone":"+41 52 364 16 67",
    "sg:postcode":"8353",
    "sg:province":"Z\u00fcrich",
    "wof:name":"Immotreu Immobilien- & Treuhand Ag",
    "wof:placetype":"venue"
},
  "geometry": {"coordinates":[8.874168396,47.4864349365],"type":"Point"}
}