{
  "type": "Feature",
  "properties": {
    "iso:country":"CH",
    "sg:address":"Route Des Ronquoz 17 1950 Sion Case Postale 669",
    "sg:city":"Sion",
    "sg:orig_category":"Herstellung von Baubedarfsartikeln aus Kunststoff",
    "sg:phone":"+41 27 327 43 43",
    "sg:postcode":"1951",
    "sg:province":"Valais",
    "wof:name":"Michel Sa Fabrique De Stores Storen Fabrik",
    "wof:placetype":"venue"
},
  "geometry": {"coordinates":[7.364906,46.226078],"type":"Point"}
}