{
  "type": "Feature",
  "properties": {
    "iso:country":"CH",
    "sg:address":"Rue Du Valentin 14/16",
    "sg:city":"Lausanne",
    "sg:orig_category":"Detailhandel mit Damenbekleidung",
    "sg:phone":"+41 21 323 17 91",
    "sg:postcode":"1004",
    "sg:province":"Vaud",
    "wof:name":"V\u00e9rio Coradazzi Boutique V\u00e9rio",
    "wof:placetype":"venue"
},
  "geometry": {"coordinates":[6.631845,46.524387],"type":"Point"}
}