{
  "type": "Feature",
  "properties": {
    "iso:country":"CH",
    "sg:address":"Z\u00fcrcherstrasse 138a",
    "sg:city":"Frauenfeld",
    "sg:orig_category":"Verm\u00f6gensverwaltung",
    "sg:phone":"+41 52 721 34 30",
    "sg:postcode":"8500",
    "sg:province":"Thurgau",
    "wof:name":"Bfw Verm\u00f6gensverwaltung Ag",
    "wof:placetype":"venue"
},
  "geometry": {"coordinates":[8.8955030441,47.5543823242],"type":"Point"}
}