{
  "type": "Feature",
  "properties": {
    "iso:country":"CH",
    "sg:address":"Riedernstrasse 13h",
    "sg:city":"Frauenkappelen",
    "sg:orig_category":"Herstellung von Werkzeugen Mechanische Werkst\u00e4tten",
    "sg:phone":"+41 31 926 12 69",
    "sg:postcode":"3202",
    "sg:province":"Bern",
    "wof:name":"Wewag Ag",
    "wof:placetype":"venue"
},
  "geometry": {"coordinates":[7.3542141914,46.9519386292],"type":"Point"}
}