{
  "type": "Feature",
  "properties": {
    "iso:country":"CH",
    "sg:address":"Bruchstrasse 2",
    "sg:city":"Luzern",
    "sg:orig_category":"Betrieb von Taxis",
    "sg:phone":"+41 41 242 00 00",
    "sg:postcode":"6003",
    "sg:province":"Luzern",
    "wof:name":"City-taxi Wicki S.",
    "wof:placetype":"venue"
},
  "geometry": {"coordinates":[8.298729,47.051586],"type":"Point"}
}