{
  "type": "Feature",
  "properties": {
    "iso:country":"CH",
    "sg:address":"Rue Du Cropt 11 1880 Bex Case Postale 202",
    "sg:city":"Bex",
    "sg:orig_category":"Wirtschaftspr\u00fcfung, Steuerberatung U Treuhand",
    "sg:phone":"+41 24 463 25 81",
    "sg:postcode":"1880",
    "sg:province":"Vaud",
    "wof:name":"Fiduciaire J.-m.kohli Sa",
    "wof:placetype":"venue"
},
  "geometry": {"coordinates":[7.0151081085,46.250328064],"type":"Point"}
}