{
  "type": "Feature",
  "properties": {
    "iso:country":"CH",
    "sg:address":"Karpfenstrasse 5",
    "sg:city":"Oberrieden",
    "sg:orig_category":"Herstellung von B\u00fcromaschinen",
    "sg:phone":"+41 79 401 67 67",
    "sg:postcode":"8942",
    "sg:province":"Z\u00fcrich",
    "wof:name":"Bema Etikettiertechnik, Berlanda Romano",
    "wof:placetype":"venue"
},
  "geometry": {"coordinates":[8.578748703,47.2811508179],"type":"Point"}
}