{
  "type": "Feature",
  "properties": {
    "iso:country":"CH",
    "sg:address":"8157",
    "sg:city":"Dielsdorf",
    "sg:orig_category":"Bezirks, Sekundar, Realschulen, Oberstufe der Primarschulen",
    "sg:phone":"+41 18442542",
    "sg:postcode":"8157",
    "sg:province":"Z\u00fcrich",
    "wof:name":"Oberstufenschule Petermoos",
    "wof:placetype":"venue"
},
  "geometry": {"coordinates":[8.43976,47.4589],"type":"Point"}
}