{
  "type": "Feature",
  "properties": {
    "iso:country":"CH",
    "sg:address":"Rheinstrasse 81",
    "sg:city":"Pratteln",
    "sg:orig_category":"Herstellung von Ger\u00e4ten der Elektrizit\u00e4tserzeugung, -verteilung u.\u00e4. -Herstellung von sonstigen elek",
    "sg:phone":"+41 61 811 24 25",
    "sg:postcode":"4133",
    "sg:province":"Basel-Landschaft",
    "wof:name":"Sst Sensing Systems Technics Ag",
    "wof:placetype":"venue"
},
  "geometry": {"coordinates":[7.710791111,47.5346908569],"type":"Point"}
}