{
  "type": "Feature",
  "properties": {
    "iso:country":"CH",
    "sg:address":"Zaunplatz 20",
    "sg:city":"Glarus",
    "sg:orig_category":"Unclassifiable Establishments",
    "sg:postcode":"8750",
    "sg:province":"Glarus",
    "wof:name":"Unseld Ladenbau Handels Gmbh",
    "wof:placetype":"venue"
},
  "geometry": {"coordinates":[8.2651767731,47.3616256714],"type":"Point"}
}