{
  "type": "Feature",
  "properties": {
    "iso:country":"CH",
    "sg:address":"Kirchenrainstrasse 5 8632 Tann. Postfach",
    "sg:city":"F\u00e4gswil",
    "sg:orig_category":"Reinigungsgewerbe",
    "sg:postcode":"8630",
    "sg:province":"Z\u00fcrich",
    "wof:name":"A Plus Reinigungen Gmbh",
    "wof:placetype":"venue"
},
  "geometry": {"coordinates":[8.8507585526,47.262588501],"type":"Point"}
}