{
  "type": "Feature",
  "properties": {
    "iso:country":"CH",
    "sg:address":"Niederschongau",
    "sg:city":"Schongau",
    "sg:orig_category":"Wasserversorgung",
    "sg:postcode":"6288",
    "sg:province":"Luzern",
    "wof:name":"Wasserversorgungsgenossenschaft Niederwil.",
    "wof:placetype":"venue"
},
  "geometry": {"coordinates":[8.1647596359,47.224521637],"type":"Point"}
}