{
  "type": "Feature",
  "properties": {
    "iso:country":"CH",
    "sg:address":"Nassi 6",
    "sg:city":"Burgdorf",
    "sg:orig_category":"Sanit\u00e4r U Heizungsinstallation",
    "sg:phone":"+41 402860",
    "sg:postcode":"3400",
    "sg:province":"Bern",
    "wof:name":"Karl Petrig Heizungen",
    "wof:placetype":"venue"
},
  "geometry": {"coordinates":[8.8005161285,47.363117218],"type":"Point"}
}