{
  "type": "Feature",
  "properties": {
    "iso:country":"CH",
    "sg:address":"Mellingerstrasse 12",
    "sg:city":"Niederrohrdorf",
    "sg:orig_category":"Herstellung von sonstigen elektrischen Ausr\u00fcstungen Softwareentwicklung U beratung",
    "sg:phone":"+41 56 485 91 91",
    "sg:postcode":"5443",
    "sg:province":"Aargau",
    "wof:name":"Logmatic Ag",
    "wof:placetype":"venue"
},
  "geometry": {"coordinates":[8.300028801,47.424949646],"type":"Point"}
}