{
  "type": "Feature",
  "properties": {
    "iso:country":"CH",
    "sg:address":"Rue De La Borde 75",
    "sg:city":"Lausanne",
    "sg:classifiers":[
        {
            "category":"Professional",
            "subcategory":"Engineering",
            "type":"Services"
        }
    ],
    "sg:phone":"+41 21 646 83 23",
    "sg:postcode":"1018",
    "sg:province":"Vaud",
    "sg:tags":[
        "machine",
        "-",
        "mechanical"
    ],
    "wof:name":"Beboux Sa",
    "wof:placetype":"venue"
},
  "geometry": {"coordinates":[6.6297287941,46.5330924988],"type":"Point"}
}