{
  "type": "Feature",
  "properties": {
    "iso:country":"CH",
    "sg:address":"Bernstrasse 142",
    "sg:city":"Ostermundigen",
    "sg:orig_category":"Detailhandel mit Waren verschiedener Art, Hauptrichtung Nahrungsmittel",
    "sg:phone":"+41 31 931 00 19",
    "sg:postcode":"3072",
    "sg:province":"Bern",
    "wof:name":"Coop Center R\u00fctiweg/steingr\u00fcbli",
    "wof:placetype":"venue"
},
  "geometry": {"coordinates":[7.5002479553,46.9593811035],"type":"Point"}
}