{
  "type": "Feature",
  "properties": {
    "iso:country":"CH",
    "sg:address":"Postweg 4",
    "sg:city":"Birrhard",
    "sg:orig_category":"Naturheil\u00e4rzte and Heilpraktiker",
    "sg:phone":"+41 56 225 25 01",
    "sg:postcode":"5244",
    "sg:province":"Aargau",
    "wof:name":"Alice Lanz Praxis F\u00fcr Bioresonanz",
    "wof:placetype":"venue"
},
  "geometry": {"coordinates":[8.2435884476,47.4316482544],"type":"Point"}
}