{
  "type": "Feature",
  "properties": {
    "iso:country":"CH",
    "sg:address":"Via San Giorgio 16",
    "sg:city":"Castagnola",
    "sg:orig_category":"Unternehmensberatung",
    "sg:postcode":"6976",
    "sg:province":"Ticino",
    "wof:name":"H. Steinegger Unternehmensberatung",
    "wof:placetype":"venue"
},
  "geometry": {"coordinates":[8.2141523361,47.4660987854],"type":"Point"}
}