{
  "type": "Feature",
  "properties": {
    "iso:country":"CH",
    "sg:address":"Schaffhauserstrasse 134",
    "sg:city":"Kloten",
    "sg:orig_category":"Detailhandel mit Lederwaren U Reiseartikeln Verlegen von Fussboden",
    "sg:phone":"+41 18137245",
    "sg:postcode":"8302",
    "sg:province":"Z\u00fcrich",
    "wof:name":"Adolf Berlinger Lederwaren Teppiche",
    "wof:placetype":"venue"
},
  "geometry": {"coordinates":[8.5808753967,47.4521713257],"type":"Point"}
}