{
  "type": "Feature",
  "properties": {
    "iso:country":"CH",
    "sg:address":"Campingplatz Waldruh 8374 Dussnang. Postfach",
    "sg:city":"Dussnang",
    "sg:orig_category":"Campingpl\u00e4tze",
    "sg:postcode":"8374",
    "sg:province":"Thurgau",
    "wof:name":"Residenz Waldruh Ag",
    "wof:placetype":"venue"
},
  "geometry": {"coordinates":[8.961124,47.430317],"type":"Point"}
}