{
  "type": "Feature",
  "properties": {
    "iso:country":"CH",
    "sg:address":"M\u00e4rwiler Strasse 26",
    "sg:city":"Affeltrangen",
    "sg:orig_category":"Politische Parteien FDP",
    "sg:postcode":"9556",
    "sg:province":"Thurgau",
    "wof:name":"Fdp Bezirkspartei Lauchetal",
    "wof:placetype":"venue"
},
  "geometry": {"coordinates":[9.0338821411,47.5257606506],"type":"Point"}
}