{
  "type": "Feature",
  "properties": {
    "iso:country":"CH",
    "sg:address":"Windwurfstrasse 15",
    "sg:city":"Unter\u00e4geri",
    "sg:orig_category":"Wirtschaftspr\u00fcfung, Steuerberatung U Treuhand",
    "sg:phone":"+41 41 763 03 20",
    "sg:postcode":"6314",
    "sg:province":"Zug",
    "wof:name":"Mb Trust & Corporate Services Ag",
    "wof:placetype":"venue"
},
  "geometry": {"coordinates":[8.576215744,47.1333351135],"type":"Point"}
}