{
  "type": "Feature",
  "properties": {
    "iso:country":"CH",
    "sg:address":"Austrasse 95 4051 Basel. Postfach",
    "sg:city":"Basel",
    "sg:orig_category":"Vermittlung von Immobilien Verwaltung von Immobilien",
    "sg:phone":"+41 71 228 01 80",
    "sg:postcode":"4003",
    "sg:province":"Basel-Stadt",
    "wof:name":"Schaeppi Grundst\u00fccke Kollektivgesellschaft",
    "wof:placetype":"venue"
},
  "geometry": {"coordinates":[9.3745412827,47.4256896973],"type":"Point"}
}