{
  "type": "Feature",
  "properties": {
    "iso:country":"CH",
    "sg:address":"R\u00fcmelinbachweg 18",
    "sg:city":"Basel",
    "sg:orig_category":"Personal U Stellenvermittlung Unternehmensberatung",
    "sg:phone":"+41 61 281 04 07",
    "sg:postcode":"4054",
    "sg:province":"Basel-Stadt",
    "wof:name":"H\u00e4fliger Dr. & Partner Unternehmensberatung",
    "wof:placetype":"venue"
},
  "geometry": {"coordinates":[7.5832982063,47.5510444641],"type":"Point"}
}