{
  "type": "Feature",
  "properties": {
    "iso:country":"CH",
    "sg:address":"B\u00f6nlerstrasse 21 8626 Ottikon. Postfach",
    "sg:city":"Ottikon",
    "sg:orig_category":"RESTAURANTS: TEA-ROOMS",
    "sg:phone":"+41 79 437 12 86",
    "sg:postcode":"8626",
    "sg:province":"Z\u00fcrich",
    "wof:name":"Traube Ottikon - Boesch Patrick",
    "wof:placetype":"venue"
},
  "geometry": {"coordinates":[8.7871351242,47.2954750061],"type":"Point"}
}