{
  "type": "Feature",
  "properties": {
    "iso:country":"CH",
    "sg:address":"Z.i.en Communet Moulin-du-choc",
    "sg:city":"Romanel-sur-morges",
    "sg:orig_category":"Elektroinstallation",
    "sg:phone":"+41 21 869 83 00",
    "sg:postcode":"1122",
    "sg:province":"Vaud",
    "wof:name":"Grossenbacher Electricit\u00e9",
    "wof:placetype":"venue"
},
  "geometry": {"coordinates":[6.5107097626,46.5554008484],"type":"Point"}
}