{
  "type": "Feature",
  "properties": {
    "iso:country":"CH",
    "sg:address":"Sternenweg",
    "sg:city":"Baar",
    "sg:orig_category":"Vorschulen, Kinderg\u00e4rten",
    "sg:phone":"+41 61 711 40 58",
    "sg:postcode":"6340",
    "sg:province":"Zug",
    "wof:name":"Kindergarten",
    "wof:placetype":"venue"
},
  "geometry": {"coordinates":[7.5821390152,47.4928474426],"type":"Point"}
}