{
  "type": "Feature",
  "properties": {
    "iso:country":"CH",
    "sg:address":"Lagerstrasse 33",
    "sg:city":"Z\u00fcrich",
    "sg:orig_category":"Unternehmensberatung",
    "sg:phone":"+41 17881653",
    "sg:postcode":"8004",
    "sg:province":"Z\u00fcrich",
    "wof:name":"Dms Dr.max Schnopp & Partner Ag",
    "wof:placetype":"venue"
},
  "geometry": {"coordinates":[8.6427469254,47.1967353821],"type":"Point"}
}