{
  "type": "Feature",
  "properties": {
    "iso:country":"CH",
    "sg:address":"1423",
    "sg:city":"Villars-burquin",
    "sg:orig_category":"Gemeindeverwaltungen",
    "sg:phone":"+41 24 436 15 56",
    "sg:postcode":"1423",
    "sg:province":"Vaud",
    "wof:name":"Administration Communale De Villars-burquin",
    "wof:placetype":"venue"
},
  "geometry": {"coordinates":[6.6263198853,46.8477592468],"type":"Point"}
}