{
  "type": "Feature",
  "properties": {
    "addr:full":"Baumackerstrasse 15 Z\u00fcrich Z\u00fcrich 8050",
    "addr:housenumber":"15",
    "addr:postcode":"8050",
    "addr:street":"Baumackerstrasse",
    "iso:country":"CH",
    "sg:address":"Baumackerstrasse 15",
    "sg:city":"Z\u00fcrich",
    "sg:orig_category":"Bezirks, Sekundar, Realschulen, Oberstufe der Primarschulen Primarschulen",
    "sg:phone":"+41 13126060",
    "sg:postcode":"8050",
    "sg:province":"Z\u00fcrich",
    "wof:name":"Evangelische Schule Baumacker",
    "wof:placetype":"venue"
},
  "geometry": {"coordinates":[8.545456,47.408218],"type":"Point"}
}