{
  "type": "Feature",
  "properties": {
    "iso:country":"CH",
    "sg:address":"1696",
    "sg:city":"Vuisternens-ogoz",
    "sg:classifiers":[
        {
            "category":"Travel",
            "subcategory":"Hotels & Motels",
            "type":"Entertainment"
        }
    ],
    "sg:phone":"+41 26 411 41 40",
    "sg:postcode":"1696",
    "sg:province":"Fribourg",
    "sg:tags":[
        "hotels",
        "mit",
        "restaurant"
    ],
    "wof:name":"Ducret Ren\u00e9",
    "wof:placetype":"venue"
},
  "geometry": {"coordinates":[7.0502500534,46.7054786682],"type":"Point"}
}