{
  "type": "Feature",
  "properties": {
    "iso:country":"CH",
    "sg:address":"Br\u00fcgglistrasse 11",
    "sg:city":"Altendorf",
    "sg:orig_category":"Detailhandel mit Getr\u00e4nken Grosshandel mit Getr\u00e4nken",
    "sg:phone":"+41 55 451 11 11",
    "sg:postcode":"8852",
    "sg:province":"Schwyz",
    "wof:name":"Ruoss Getr\u00e4nke & Transporte Ag Getr\u00e4nkehandel U. Transporte",
    "wof:placetype":"venue"
},
  "geometry": {"coordinates":[8.8393888474,47.1893501282],"type":"Point"}
}