{
  "type": "Feature",
  "properties": {
    "iso:country":"CH",
    "sg:address":"Bahnhofstrasse 3",
    "sg:city":"Berikon",
    "sg:orig_category":"Reparatur von Schuhen U Lederwaren",
    "sg:phone":"+41 19501331",
    "sg:postcode":"8965",
    "sg:province":"Aargau",
    "wof:name":"Schuh-& Schl\u00fcssel Pit Stop Carmine De Lorenzo",
    "wof:placetype":"venue"
},
  "geometry": {"coordinates":[8.7827320099,47.3678398132],"type":"Point"}
}