{
  "type": "Feature",
  "properties": {
    "iso:country":"CH",
    "sg:address":"Via Francesco Catenazzi 23",
    "sg:city":"Mendrisio",
    "sg:classifiers":[
        {
            "category":"Health Services",
            "subcategory":"Hospital",
            "type":"Services"
        }
    ],
    "sg:phone":"+41 71 314 62 62",
    "sg:postcode":"6850",
    "sg:province":"Ticino",
    "sg:tags":[
        "hip",
        "prosthesis"
    ],
    "wof:name":"Ulrich Ag",
    "wof:placetype":"venue"
},
  "geometry": {"coordinates":[9.3108139038,47.4034805298],"type":"Point"}
}