{
  "type": "Feature",
  "properties": {
    "iso:country":"CH",
    "sg:address":"Bergstrasse 10",
    "sg:city":"Herisau",
    "sg:orig_category":"Baugewerbe Mechanik",
    "sg:phone":"+41 71 351 11 78",
    "sg:postcode":"9100",
    "sg:province":"Appenzell Ausserrhoden",
    "wof:name":"Metas-montagen Ag",
    "wof:placetype":"venue"
},
  "geometry": {"coordinates":[9.279739,47.383942],"type":"Point"}
}