{
  "type": "Feature",
  "properties": {
    "iso:country":"CH",
    "sg:address":"Avenue De Tivoli 19",
    "sg:city":"Lausanne",
    "sg:orig_category":"Betrieb von Taxis",
    "sg:phone":"+41 21 625 74 88",
    "sg:postcode":"1007",
    "sg:province":"Vaud",
    "wof:name":"Mohamed Doudouhi Limousines Services",
    "wof:placetype":"venue"
},
  "geometry": {"coordinates":[6.615235,46.520794],"type":"Point"}
}