{
  "type": "Feature",
  "properties": {
    "iso:country":"CH",
    "sg:address":"Shopping Center",
    "sg:city":"Spreitenbach",
    "sg:orig_category":"Reiseb\u00fcros",
    "sg:phone":"+41 56 401 31 77",
    "sg:postcode":"8957",
    "sg:province":"Aargau",
    "wof:name":"Plus Reisen City Ag",
    "wof:placetype":"venue"
},
  "geometry": {"coordinates":[8.3702945709,47.4206886292],"type":"Point"}
}