{
  "type": "Feature",
  "properties": {
    "iso:country":"CH",
    "sg:address":"Gr\u00fcnaustrasse 10",
    "sg:city":"Diepoldsau",
    "sg:orig_category":"Elektroinstallation",
    "sg:phone":"+41 71 733 40 30",
    "sg:postcode":"9444",
    "sg:province":"St. Gallen",
    "wof:name":"Elektro Federer.",
    "wof:placetype":"venue"
},
  "geometry": {"coordinates":[9.6618461609,47.3814125061],"type":"Point"}
}