{
  "type": "Feature",
  "properties": {
    "iso:country":"CH",
    "sg:address":"Eggstrasse 93",
    "sg:city":"R\u00fcschlikon",
    "sg:orig_category":"Elektroinstallation",
    "sg:postcode":"8803",
    "sg:province":"Z\u00fcrich",
    "wof:name":"Robinson Nugent S.a.",
    "wof:placetype":"venue"
},
  "geometry": {"coordinates":[8.5459413528,47.3018112183],"type":"Point"}
}