{
  "type": "Feature",
  "properties": {
    "iso:country":"CH",
    "sg:address":"Rosengasse 68",
    "sg:city":"Olten",
    "sg:orig_category":"Sportvereine Velo Rad-& Motorfahrer-Bund SRB",
    "sg:postcode":"4600",
    "sg:province":"Solothurn",
    "wof:name":"Mtb-club Jura-mounties Olten",
    "wof:placetype":"venue"
},
  "geometry": {"coordinates":[7.9136610031,47.349697113],"type":"Point"}
}