{
  "type": "Feature",
  "properties": {
    "iso:country":"CH",
    "sg:address":"Neuhauserstrasse 66a",
    "sg:city":"Frauenfeld",
    "sg:orig_category":"Unclassifiable Establishments",
    "sg:phone":"+41 52 721 51 18",
    "sg:postcode":"8500",
    "sg:province":"Thurgau",
    "wof:name":"Be Happy Gmbh",
    "wof:placetype":"venue"
},
  "geometry": {"coordinates":[8.9108762741,47.5537338257],"type":"Point"}
}