{
  "type": "Feature",
  "properties": {
    "iso:country":"CH",
    "sg:address":"Gr\u00fcnaustrasse 50",
    "sg:city":"Wabern",
    "sg:orig_category":"Grosshandel mit sonstigen Halbwaren Grosshandel mit sonstigen Konsumg\u00fctern",
    "sg:phone":"+41 800 800 809",
    "sg:postcode":"3084",
    "sg:province":"Bern",
    "wof:name":"Tupperware (suisse) Sa",
    "wof:placetype":"venue"
},
  "geometry": {"coordinates":[6.2294120789,46.3862342834],"type":"Point"}
}