{
  "type": "Feature",
  "properties": {
    "iso:country":"CH",
    "sg:address":"Gartenstrasse 3",
    "sg:city":"Derendingen",
    "sg:orig_category":"Sonstige mit der Informatik verbundene T\u00e4tigkeiten",
    "sg:phone":"+41 32 682 31 32",
    "sg:postcode":"4552",
    "sg:province":"Solothurn",
    "wof:name":"Sims Ag",
    "wof:placetype":"venue"
},
  "geometry": {"coordinates":[7.583668232,47.1985855103],"type":"Point"}
}