{
  "type": "Feature",
  "properties": {
    "iso:country":"CH",
    "sg:address":"Chemin Du Tr\u00e9si 6b",
    "sg:city":"Pr\u00e9verenges",
    "sg:orig_category":"Grosshandel mit Eisenwaren sowie Installationsbedarf f\u00fcr Gas, Wasser U Heizung Sanit\u00e4r, Heizungs U L",
    "sg:phone":"+41 21 801 92 23",
    "sg:postcode":"1028",
    "sg:province":"Vaud",
    "wof:name":"Hyprom Sa",
    "wof:placetype":"venue"
},
  "geometry": {"coordinates":[6.5308151245,46.5229797363],"type":"Point"}
}