{
  "type": "Feature",
  "properties": {
    "iso:country":"CH",
    "sg:address":"Falkenstr. 1",
    "sg:city":"Z\u00fcrich",
    "sg:classifiers":[
        {
            "category":"Sports & Exercise",
            "subcategory":"Sports Center",
            "type":"Entertainment"
        }
    ],
    "sg:phone":"+41 32 926 67 77",
    "sg:postcode":"8008",
    "sg:province":"Z\u00fcrich",
    "sg:tags":[
        "game"
    ],
    "wof:name":"Physic Club Christian Matthey Sa",
    "wof:placetype":"venue"
},
  "geometry": {"coordinates":[6.8044881821,47.0877761841],"type":"Point"}
}