{
  "type": "Feature",
  "properties": {
    "iso:country":"CH",
    "sg:address":"Hintermatt 24",
    "sg:city":"Ziefen",
    "sg:orig_category":"Non-Classified Establishments",
    "sg:phone":"+41 61 933 05 50",
    "sg:postcode":"4417",
    "sg:province":"Basel-Landschaft",
    "wof:name":"Ger\u00fcste Bobst",
    "wof:placetype":"venue"
},
  "geometry": {"coordinates":[7.7022361755,47.431552887],"type":"Point"}
}