{
  "type": "Feature",
  "properties": {
    "iso:country":"CH",
    "sg:address":"Seilergasse 6",
    "sg:city":"Solothurn",
    "sg:orig_category":"Wirtschafts- and Arbeitgeberverb\u00e4nde",
    "sg:postcode":"4500",
    "sg:province":"Solothurn",
    "wof:name":"Buchbindermeister-verband Solothurn,herrn Rolf Christ",
    "wof:placetype":"venue"
},
  "geometry": {"coordinates":[7.5393462181,47.2077331543],"type":"Point"}
}