{
  "type": "Feature",
  "properties": {
    "iso:country":"CH",
    "sg:address":"Marktgasse 1",
    "sg:city":"Interlaken",
    "sg:orig_category":"Arztpraxen",
    "sg:phone":"+41 33 822 02 02",
    "sg:postcode":"3800",
    "sg:province":"Bern",
    "wof:name":"Dres Med. A. & I. Baumgartner Spezial\u00e4rzte Fmh",
    "wof:placetype":"venue"
},
  "geometry": {"coordinates":[7.85389,46.685188],"type":"Point"}
}