{
  "type": "Feature",
  "properties": {
    "iso:country":"CH",
    "sg:address":"Eschenweg 6",
    "sg:city":"Plons",
    "sg:orig_category":"Interessenvertretungen U sonstige Vereinigungen",
    "sg:phone":"+41 81 723 17 54",
    "sg:postcode":"8889",
    "sg:province":"St. Gallen",
    "wof:name":"Eidgen\u00f6ssischer Schwingerverband Esv",
    "wof:placetype":"venue"
},
  "geometry": {"coordinates":[9.4048776627,47.0557861328],"type":"Point"}
}