{
  "type": "Feature",
  "properties": {
    "iso:country":"CH",
    "sg:address":"La Forge",
    "sg:city":"Goumoens-la-ville",
    "sg:orig_category":"M\u00f6belschreinereien",
    "sg:phone":"+41 21 881 27 62",
    "sg:postcode":"1376",
    "sg:province":"Vaud",
    "wof:name":"Monnier Laurent",
    "wof:placetype":"venue"
},
  "geometry": {"coordinates":[6.6041049957,46.6581611633],"type":"Point"}
}