{
  "type": "Feature",
  "properties": {
    "iso:country":"CH",
    "sg:address":"Wiesenstrasse 21",
    "sg:city":"Dietikon",
    "sg:orig_category":"Softwareentwicklung U beratung",
    "sg:phone":"+41 17745900",
    "sg:postcode":"8953",
    "sg:province":"Z\u00fcrich",
    "wof:name":"Weiss Projekte",
    "wof:placetype":"venue"
},
  "geometry": {"coordinates":[8.4214963913,47.3960533142],"type":"Point"}
}