{
  "type": "Feature",
  "properties": {
    "iso:country":"CH",
    "sg:address":"Thorenbergstrasse 8 6014 Littau. Postfach",
    "sg:city":"Littau",
    "sg:orig_category":"Grosshandel mit sonstigen Maschinen U Ausr\u00fcstungen f\u00fcr Industrie, Handel U Schiffahrt Handelsvermitt",
    "sg:phone":"+41 41 250 57 72",
    "sg:postcode":"6014",
    "sg:province":"Luzern",
    "wof:name":"Poly-romy Gmbh Maschinen, Schlossereiprodukte; Handel",
    "wof:placetype":"venue"
},
  "geometry": {"coordinates":[8.2486543655,47.0520019531],"type":"Point"}
}