{
  "type": "Feature",
  "properties": {
    "iso:country":"CH",
    "sg:address":"6153",
    "sg:city":"Ufhusen",
    "sg:orig_category":"Vereine Musik/Blasmusik",
    "sg:postcode":"6153",
    "sg:province":"Luzern",
    "wof:name":"Musikgesellschaft",
    "wof:placetype":"venue"
},
  "geometry": {"coordinates":[7.8967909813,47.1169509888],"type":"Point"}
}