{
  "type": "Feature",
  "properties": {
    "iso:country":"CH",
    "sg:address":"Vallombreuse Av. De La 100",
    "sg:city":"Prilly",
    "sg:orig_category":"Pensionskassen",
    "sg:phone":"+41 21 644 61 11",
    "sg:postcode":"1008",
    "sg:province":"Vaud",
    "wof:name":"Fondation De Pr\u00e9voyance Professionnelle Unicible",
    "wof:placetype":"venue"
},
  "geometry": {"coordinates":[6.6094288826,46.5408096313],"type":"Point"}
}