{
  "type": "Feature",
  "properties": {
    "iso:country":"CH",
    "sg:address":"Loorenstrasse 74",
    "sg:city":"Z\u00fcrich",
    "sg:orig_category":"Wohnheime f\u00fcr Kinder U Jugendliche",
    "sg:phone":"+41 13812600",
    "sg:postcode":"8053",
    "sg:province":"Z\u00fcrich",
    "wof:name":"Studentenheim Des Justinus-verein",
    "wof:placetype":"venue"
},
  "geometry": {"coordinates":[8.5926551819,47.3636054993],"type":"Point"}
}