{
  "type": "Feature",
  "properties": {
    "iso:country":"CH",
    "sg:address":"Gewerbestrasse 6 4553 Subingen. Postfach",
    "sg:city":"Subingen",
    "sg:orig_category":"Herstellung von Bereifungen Pneus Grosshandel",
    "sg:phone":"+41 32 614 08 84",
    "sg:postcode":"4553",
    "sg:province":"Solothurn",
    "wof:name":"Profi Pneu Ag",
    "wof:placetype":"venue"
},
  "geometry": {"coordinates":[7.6082630157,47.1955528259],"type":"Point"}
}