{
  "type": "Feature",
  "properties": {
    "iso:country":"CH",
    "sg:address":"Place Du Ch\u00e2teau 2",
    "sg:city":"Grandson",
    "sg:orig_category":"Konkurs- and Betreibungs\u00e4mter",
    "sg:phone":"+41 24 447 47 20",
    "sg:postcode":"1422",
    "sg:province":"Vaud",
    "wof:name":"Office Des Poursuites & Faillites",
    "wof:placetype":"venue"
},
  "geometry": {"coordinates":[6.6459121704,46.8091926575],"type":"Point"}
}