{
  "type": "Feature",
  "properties": {
    "iso:country":"CH",
    "sg:address":"Tiermatti Schwenden 3754 Diemtigen. Postfach",
    "sg:city":"Schwenden",
    "sg:orig_category":"Verwertung von Milch",
    "sg:postcode":"3757",
    "sg:province":"Bern",
    "wof:name":"Milchgenossenschaft Schwenden",
    "wof:placetype":"venue"
},
  "geometry": {"coordinates":[7.4914069176,46.5693664551],"type":"Point"}
}