{
  "type": "Feature",
  "properties": {
    "iso:country":"CH",
    "sg:address":"Allmendstr. 1",
    "sg:city":"Sachseln",
    "sg:classifiers":[
        {
            "category":"Home & Garden",
            "subcategory":"Furniture",
            "type":"Retail Goods"
        }
    ],
    "sg:phone":"+41 41 666 26 66",
    "sg:postcode":"6072",
    "sg:province":"Obwalden",
    "sg:tags":[
        "household",
        "wood"
    ],
    "wof:name":"Reinhard Holzwarenfabrik Ag",
    "wof:placetype":"venue"
},
  "geometry": {"coordinates":[8.2425699234,46.8713874817],"type":"Point"}
}