{
  "type": "Feature",
  "properties": {
    "iso:country":"CH",
    "sg:address":"Chamerstrasse 106",
    "sg:city":"Zug",
    "sg:orig_category":"Herstellung von Betonerzeugnissen f\u00fcr den Bau Herstellung von sonstigen Produkten aus nichtmetallisc",
    "sg:phone":"+41 41 741 32 32",
    "sg:postcode":"6300",
    "sg:province":"Zug",
    "wof:name":"Breitenstein Christian Ag",
    "wof:placetype":"venue"
},
  "geometry": {"coordinates":[8.4950017929,47.1784629822],"type":"Point"}
}