{
  "type": "Feature",
  "properties": {
    "iso:country":"CH",
    "sg:address":"R\u00fctenenweg 32",
    "sg:city":"Ennetbaden",
    "sg:orig_category":"Non-Classified Establishments",
    "sg:postcode":"5408",
    "sg:province":"Aargau",
    "wof:name":"Alfred J\u00c4ckle Consulting",
    "wof:placetype":"venue"
},
  "geometry": {"coordinates":[8.320555687,47.4782562256],"type":"Point"}
}