{
  "type": "Feature",
  "properties": {
    "iso:country":"CH",
    "sg:address":"Dornacherstrasse 250 4053 Basel. Postfach",
    "sg:city":"Basel",
    "sg:orig_category":"Grosshandel mit Holz U Baustoffen",
    "sg:phone":"+41 61 272 51 90",
    "sg:postcode":"4018",
    "sg:province":"Basel-Stadt",
    "wof:name":"Ck-bloc- Ag Bausysteme & Betonelemente",
    "wof:placetype":"venue"
},
  "geometry": {"coordinates":[7.5969071388,47.5406227112],"type":"Point"}
}