{
  "type": "Feature",
  "properties": {
    "iso:country":"CH",
    "sg:address":"Weihermattstrasse 739",
    "sg:city":"M\u00fcmliswil",
    "sg:orig_category":"Herstellung von keramischen Wand U Bodenfliesen U platten",
    "sg:phone":"+41 62 391 25 32",
    "sg:postcode":"4717",
    "sg:province":"Solothurn",
    "wof:name":"Brunner Andr\u00e9",
    "wof:placetype":"venue"
},
  "geometry": {"coordinates":[7.7093749046,47.3416595459],"type":"Point"}
}