{
  "type": "Feature",
  "properties": {
    "iso:country":"CH",
    "sg:address":"Mettlenstrasse 7 8488 Turbenthal. Postfach",
    "sg:city":"Turbenthal",
    "sg:orig_category":"Instandhaltung U Reparatur von Automobilen",
    "sg:postcode":"8488",
    "sg:province":"Z\u00fcrich",
    "wof:name":"Garage L\u00e4derach & Co",
    "wof:placetype":"venue"
},
  "geometry": {"coordinates":[8.8602685928,47.4344596863],"type":"Point"}
}