{
  "type": "Feature",
  "properties": {
    "addr:full":"Martinsbergstrasse 40 5400 Baden. Postfach Baden Aargau 5400",
    "addr:housenumber":"40",
    "addr:postcode":"5400;5400",
    "addr:street":"Martinsbergstrasse;Postfach",
    "iso:country":"CH",
    "sg:address":"Martinsbergstrasse 40 5400 Baden. Postfach",
    "sg:city":"Baden",
    "sg:orig_category":"Architektur U Ingenieurb\u00fcros",
    "sg:postcode":"5400",
    "sg:province":"Aargau",
    "wof:name":"Burkard, Meyer. Architekten Bsa Ag",
    "wof:placetype":"venue"
},
  "geometry": {"coordinates":[8.301013,47.476631],"type":"Point"}
}