{
  "type": "Feature",
  "properties": {
    "iso:country":"CH",
    "sg:address":"Via Monte Boglia 3",
    "sg:city":"Lugano",
    "sg:orig_category":"Mechanische Werkst\u00e4tten",
    "sg:phone":"+41 91 971 94 34",
    "sg:postcode":"6900",
    "sg:province":"Ticino",
    "wof:name":"Adelino Pin Garage Molino Nuovo",
    "wof:placetype":"venue"
},
  "geometry": {"coordinates":[8.9578790665,46.0182685852],"type":"Point"}
}