{
  "type": "Feature",
  "properties": {
    "iso:country":"CH",
    "sg:address":"Furrengasse 6",
    "sg:city":"Luzern",
    "sg:orig_category":"Detailhandel mit Schuhen U Lederwaren",
    "sg:postcode":"6004",
    "sg:province":"Luzern",
    "wof:name":"Offermann Gmbh & Co. Kg In Bergisch Gladbach, Zweigniederlassung Luzern",
    "wof:placetype":"venue"
},
  "geometry": {"coordinates":[8.3073368073,47.0524291992],"type":"Point"}
}