{
  "type": "Feature",
  "properties": {
    "iso:country":"CH",
    "sg:address":"Binderstrasse 60 8702 Zollikon. Postfach",
    "sg:city":"Zollikon",
    "sg:orig_category":"Erbringung von Dienstleistungen f\u00fcr Unternehmen",
    "sg:postcode":"8702",
    "sg:province":"Z\u00fcrich",
    "wof:name":"Sfb-k\u00fcnstlermanagement Gmbh",
    "wof:placetype":"venue"
},
  "geometry": {"coordinates":[8.5706653595,47.3399238586],"type":"Point"}
}