{
  "type": "Feature",
  "properties": {
    "iso:country":"CH",
    "sg:address":"M\u00fcnsterhof 10",
    "sg:city":"Z\u00fcrich",
    "sg:orig_category":"Detailhandel mit Schuhen Detailhandel mit Schuhen U Lederwaren",
    "sg:phone":"+41 12221700",
    "sg:postcode":"8001",
    "sg:province":"Z\u00fcrich",
    "wof:name":"Schuh-caf\u00e9 Marco Bloch",
    "wof:placetype":"venue"
},
  "geometry": {"coordinates":[8.5405712128,47.3703651428],"type":"Point"}
}