{
  "type": "Feature",
  "properties": {
    "iso:country":"CH",
    "sg:address":"Chemin Des Bosquets",
    "sg:city":"Yverdon-les-bains",
    "sg:orig_category":"RESTAURANTS: TEA-ROOMS",
    "sg:phone":"+41 24 425 82 32",
    "sg:postcode":"1400",
    "sg:province":"Vaud",
    "wof:name":"Le Ranch, Raymondaz Denise Et Esteves Heidi",
    "wof:placetype":"venue"
},
  "geometry": {"coordinates":[6.6421499252,46.7873916626],"type":"Point"}
}