{
  "type": "Feature",
  "properties": {
    "addr:full":"Ruesserain 121 Moosleerau Aargau 5054",
    "addr:housenumber":"121",
    "addr:postcode":"5054",
    "iso:country":"CH",
    "sg:address":"Ruesserain 121",
    "sg:city":"Moosleerau",
    "sg:orig_category":"Detailhandel mit Brot, Back U S\u00fcsswaren",
    "sg:postcode":"5054",
    "sg:province":"Aargau",
    "wof:name":"Stalder Mme.",
    "wof:placetype":"venue"
},
  "geometry": {"coordinates":[6.590139,46.529259],"type":"Point"}
}