{
  "type": "Feature",
  "properties": {
    "iso:country":"CH",
    "sg:address":"Avenue De France 90",
    "sg:city":"Lausanne",
    "sg:orig_category":"Immobilienwesen Wirtschaftspr\u00fcfung, Steuerberatung U Treuhand",
    "sg:phone":"+41 21 646 17 45",
    "sg:postcode":"1004",
    "sg:province":"Vaud",
    "wof:name":"Evolution 4 Op\u00e9rations Immob. Et Activit\u00e9s Fiduciaires",
    "wof:placetype":"venue"
},
  "geometry": {"coordinates":[6.6154470444,46.5318565369],"type":"Point"}
}