{
  "type": "Feature",
  "properties": {
    "iso:country":"CH",
    "sg:address":"Via Borgo",
    "sg:city":"Ascona",
    "sg:orig_category":"Detailhandel mit Damenbekleidung Detailhandel mit Herrenbekleidung",
    "sg:phone":"+41 91 791 39 19",
    "sg:postcode":"6612",
    "sg:province":"Ticino",
    "wof:name":"Romolo Di Filippo Boutique King Calzature",
    "wof:placetype":"venue"
},
  "geometry": {"coordinates":[8.7669448853,46.1553840637],"type":"Point"}
}