{
  "type": "Feature",
  "properties": {
    "iso:country":"CH",
    "sg:address":"Herrengasse 23",
    "sg:city":"Schwyz",
    "sg:orig_category":"RESTAURANTS: TEA-ROOMS",
    "sg:postcode":"6430",
    "sg:province":"Schwyz",
    "wof:name":"L\u00fctenegger-ineichen R.",
    "wof:placetype":"venue"
},
  "geometry": {"coordinates":[8.6509561539,47.0220069885],"type":"Point"}
}