{
  "type": "Feature",
  "properties": {
    "iso:country":"CH",
    "sg:address":"Bremgarterstrasse 31",
    "sg:city":"Widen",
    "sg:orig_category":"Reinigungsgewerbe",
    "sg:phone":"+41 56 641 09 00",
    "sg:postcode":"8967",
    "sg:province":"Aargau",
    "wof:name":"Reinigungsservice Jasari",
    "wof:placetype":"venue"
},
  "geometry": {"coordinates":[8.360502243,47.3660964966],"type":"Point"}
}