{
  "type": "Feature",
  "properties": {
    "iso:country":"CH",
    "sg:address":"Gartenstrasse 10 3125 Toffen. Postfach",
    "sg:city":"Burgistein",
    "sg:orig_category":"Gem\u00fcsebau Herstellung von Nahrungsmitteln undGetr\u00e4nken",
    "sg:phone":"+41 31 819 05 46",
    "sg:postcode":"3664",
    "sg:province":"Bern",
    "wof:name":"Hans-ulrich Gerber Champignonkulturen",
    "wof:placetype":"venue"
},
  "geometry": {"coordinates":[7.4904518127,46.8684768677],"type":"Point"}
}