{
  "type": "Feature",
  "properties": {
    "iso:country":"CH",
    "sg:address":"Avenue De Bellevue 29",
    "sg:city":"Moutier",
    "sg:orig_category":"Architekturb\u00fcros",
    "sg:phone":"+41 32 493 23 27",
    "sg:postcode":"2740",
    "sg:province":"Bern",
    "wof:name":"Jean-philippe Kessi Bureau D'architecture",
    "wof:placetype":"venue"
},
  "geometry": {"coordinates":[7.363699,47.277885],"type":"Point"}
}