{
  "type": "Feature",
  "properties": {
    "iso:country":"CH",
    "sg:address":"Au Cras 104",
    "sg:city":"Courtema\u00eeche",
    "sg:orig_category":"Maurerarbeiten Strassenbau",
    "sg:phone":"+41 32 466 40 69",
    "sg:postcode":"2923",
    "sg:province":"Jura",
    "wof:name":"Claude G\u00fcttly Ma\u00e7onnerie Et G\u00e9nie Civil",
    "wof:placetype":"venue"
},
  "geometry": {"coordinates":[7.0439558029,47.4576530457],"type":"Point"}
}