{
  "type": "Feature",
  "properties": {
    "iso:country":"CH",
    "sg:address":"Chemin Du Chablais 3",
    "sg:city":"Th\u00f4nex",
    "sg:orig_category":"W\u00e4scherei U chemische Reinigung",
    "sg:postcode":"1226",
    "sg:province":"Gen\u00e8ve",
    "wof:name":"Pascalor Sa",
    "wof:placetype":"venue"
},
  "geometry": {"coordinates":[6.2007751465,46.1955413818],"type":"Point"}
}