{
  "type": "Feature",
  "properties": {
    "iso:country":"CH",
    "sg:address":"7527",
    "sg:city":"Brail",
    "sg:orig_category":"Wohnheime",
    "sg:phone":"+41 81 854 18 12",
    "sg:postcode":"7527",
    "sg:province":"Graubunden",
    "wof:name":"Ferienhaus Piz D'esan Der Gemeinde Rothrist",
    "wof:placetype":"venue"
},
  "geometry": {"coordinates":[10.0346298218,46.6555480957],"type":"Point"}
}