{
  "type": "Feature",
  "properties": {
    "iso:country":"CH",
    "sg:address":"H\u00f6chistrasse 7 + 9",
    "sg:city":"Kaltbrunn",
    "sg:orig_category":"Mechanik",
    "sg:phone":"+41 55 283 23 65",
    "sg:postcode":"8722",
    "sg:province":"St. Gallen",
    "wof:name":"F\u00e4h Peter",
    "wof:placetype":"venue"
},
  "geometry": {"coordinates":[9.0130844116,47.216999054],"type":"Point"}
}