{
  "type": "Feature",
  "properties": {
    "iso:country":"CH",
    "sg:address":"Schlattstrasse 18",
    "sg:city":"Endingen",
    "sg:orig_category":"Innendekorationsateliers",
    "sg:phone":"+41 56 406 17 01",
    "sg:postcode":"5304",
    "sg:province":"Aargau",
    "wof:name":"Don Verlag",
    "wof:placetype":"venue"
},
  "geometry": {"coordinates":[8.2863855362,47.5387268066],"type":"Point"}
}