{
  "type": "Feature",
  "properties": {
    "addr:full":"Oberdorfstrasse 8 8001 Z\u00fcrich. Postfach Z\u00fcrich Z\u00fcrich 8024",
    "addr:housenumber":"8",
    "addr:postcode":"8001 zuerich. postfach;8024",
    "addr:street":"Oberdorfstrasse",
    "iso:country":"CH",
    "sg:address":"Oberdorfstrasse 8 8001 Z\u00fcrich. Postfach",
    "sg:city":"Z\u00fcrich",
    "sg:orig_category":"Advokaturb\u00fcros",
    "sg:phone":"+41 12622800",
    "sg:postcode":"8024",
    "sg:province":"Z\u00fcrich",
    "wof:name":"Dr.rolf Fischer Advokaturb\u00fcro",
    "wof:placetype":"venue"
},
  "geometry": {"coordinates":[8.545829,47.36842],"type":"Point"}
}