{
  "type": "Feature",
  "properties": {
    "iso:country":"CH",
    "sg:address":"Frickenstrasse 22",
    "sg:city":"D\u00fcbendorf",
    "sg:orig_category":"Fahrschulen, Flugschulen",
    "sg:phone":"+41 18217112",
    "sg:postcode":"8600",
    "sg:province":"Z\u00fcrich",
    "wof:name":"Eugen F\u00fcllemann Autofahrschule",
    "wof:placetype":"venue"
},
  "geometry": {"coordinates":[8.6302499771,47.3923797607],"type":"Point"}
}