{
  "type": "Feature",
  "properties": {
    "iso:country":"CH",
    "sg:address":"Via Vorame 122",
    "sg:city":"Ascona",
    "sg:orig_category":"Malerei",
    "sg:phone":"+41 79 444 01 49",
    "sg:postcode":"6612",
    "sg:province":"Ticino",
    "wof:name":"Giancarlo Rizzi Impresa Di Pittura",
    "wof:placetype":"venue"
},
  "geometry": {"coordinates":[8.7796535492,46.1599273682],"type":"Point"}
}