{
  "type": "Feature",
  "properties": {
    "iso:country":"CH",
    "sg:address":"Chemin Des Fourches",
    "sg:city":"Penthalaz",
    "sg:orig_category":"Grosshandel mit keramischen Erzeugnissen,Glaswaren U Tapeten Herstellung von Anstrichmitteln, Druckf",
    "sg:phone":"+41 21 861 23 87",
    "sg:postcode":"1305",
    "sg:province":"Vaud",
    "wof:name":"Osaka Distribution, Charrotton J.",
    "wof:placetype":"venue"
},
  "geometry": {"coordinates":[6.526409,46.603401],"type":"Point"}
}