{
  "type": "Feature",
  "properties": {
    "iso:country":"CH",
    "sg:address":"Laupenstrasse 2 3178 B\u00f6singen. Postfach",
    "sg:city":"B\u00f6singen",
    "sg:orig_category":"Gemeindeverwaltungen",
    "sg:phone":"+41 31 747 72 42",
    "sg:postcode":"3178",
    "sg:province":"Fribourg",
    "wof:name":"Gemeindeverwaltung B\u00f6singen",
    "wof:placetype":"venue"
},
  "geometry": {"coordinates":[7.2298297882,46.8936347961],"type":"Point"}
}