{
  "type": "Feature",
  "properties": {
    "iso:country":"CH",
    "sg:address":"Tschuggenstrasse 17",
    "sg:city":"Chur",
    "sg:orig_category":"Fahrschulen, Flugschulen",
    "sg:phone":"+41 81 356 60 48",
    "sg:postcode":"7000",
    "sg:province":"Graubunden",
    "wof:name":"Flugschule Montalin, Schlegel Andi",
    "wof:placetype":"venue"
},
  "geometry": {"coordinates":[9.5352106094,46.8707008362],"type":"Point"}
}