{
  "type": "Feature",
  "properties": {
    "iso:country":"CH",
    "sg:address":"Im Luchli 1 3110 M\u00fcnsingen. Postfach 1375",
    "sg:city":"M\u00fcnsingen",
    "sg:orig_category":"Datenverarbeitungsdienste",
    "sg:phone":"+41 22 344 89 77",
    "sg:postcode":"3110",
    "sg:province":"Bern",
    "wof:name":"Bwz Informatique Sa Bureau D'architecture",
    "wof:placetype":"venue"
},
  "geometry": {"coordinates":[6.138045,46.176105],"type":"Point"}
}