{
  "type": "Feature",
  "properties": {
    "iso:country":"CH",
    "sg:address":"Bahnhofstrasse 22 8580 Amriswil. Postfach",
    "sg:city":"Amriswil",
    "sg:orig_category":"RESTAURANTS: TEA-ROOMS",
    "sg:postcode":"8580",
    "sg:province":"Thurgau",
    "wof:name":"Kulturbistro Amriswil Gmbh",
    "wof:placetype":"venue"
},
  "geometry": {"coordinates":[9.3024625778,47.5480499268],"type":"Point"}
}