{
  "type": "Feature",
  "properties": {
    "iso:country":"CH",
    "sg:address":"Spalenring 40",
    "sg:city":"Basel",
    "sg:orig_category":"Physiotherapie",
    "sg:phone":"+41 56 621 98 30",
    "sg:postcode":"4055",
    "sg:province":"Basel-Stadt",
    "wof:name":"Derk & Tilly Welmers Physiotherapie",
    "wof:placetype":"venue"
},
  "geometry": {"coordinates":[8.2731761932,47.3501815796],"type":"Point"}
}