{
  "type": "Feature",
  "properties": {
    "iso:country":"CH",
    "sg:address":"General-guisanstrasse 27a",
    "sg:city":"Interlaken",
    "sg:orig_category":"Fachdetailhandel in Verkaufsr\u00e4umen",
    "sg:postcode":"3800",
    "sg:province":"Bern",
    "wof:name":"Laku Ag",
    "wof:placetype":"venue"
},
  "geometry": {"coordinates":[7.8546462059,46.6820831299],"type":"Point"}
}