{
  "type": "Feature",
  "properties": {
    "addr:full":"Schwarzenbergstrasse 27 Malters Luzern 6102",
    "addr:housenumber":"27",
    "addr:postcode":"6102",
    "addr:street":"Schwarzenbergstrasse",
    "iso:country":"CH",
    "sg:address":"Schwarzenbergstrasse 27",
    "sg:city":"Malters",
    "sg:orig_category":"Allgemeiner Gartenbau",
    "sg:phone":"+41 41 497 22 93",
    "sg:postcode":"6102",
    "sg:province":"Luzern",
    "wof:name":"Uebelmann-lampugnani J., Gartengestaltung",
    "wof:placetype":"venue"
},
  "geometry": {"coordinates":[8.176455,47.03315],"type":"Point"}
}