{
  "type": "Feature",
  "properties": {
    "iso:country":"CH",
    "sg:address":"Oberriedweg 1",
    "sg:city":"Belp",
    "sg:orig_category":"Sanit\u00e4r, Heizungs U L\u00fcftungsinstallation Sanit\u00e4rinstallation",
    "sg:phone":"+41 31 819 14 41",
    "sg:postcode":"3123",
    "sg:province":"Bern",
    "wof:name":"Oester Installationen",
    "wof:placetype":"venue"
},
  "geometry": {"coordinates":[7.496049881,46.8917350769],"type":"Point"}
}