{
  "type": "Feature",
  "properties": {
    "iso:country":"CH",
    "sg:address":"Postgasse 8",
    "sg:city":"M\u00e4nnedorf",
    "sg:orig_category":"Non-Classified Establishments",
    "sg:phone":"+41 17903442",
    "sg:postcode":"8708",
    "sg:province":"Z\u00fcrich",
    "wof:name":"Sukar Praxis F\u00fcr Biologische Haarentfernung, Horvath-tschirren U.",
    "wof:placetype":"venue"
},
  "geometry": {"coordinates":[8.690700531,47.2531013489],"type":"Point"}
}