{
  "type": "Feature",
  "properties": {
    "iso:country":"CH",
    "sg:address":"Hofmattstrasse 3",
    "sg:city":"Zermatt",
    "sg:orig_category":"Grosshandel mit sonstigen Getr\u00e4nken G\u00fcterbef\u00f6rderung im Strassenverkehr",
    "sg:phone":"+41 27 967 23 16",
    "sg:postcode":"3920",
    "sg:province":"Valais",
    "wof:name":"Viktor Graven",
    "wof:placetype":"venue"
},
  "geometry": {"coordinates":[7.7475538254,46.0222663879],"type":"Point"}
}