{
  "type": "Feature",
  "properties": {
    "iso:country":"CH",
    "sg:address":"Chemin De Pinchat 25",
    "sg:city":"Vessy",
    "sg:orig_category":"Kunsthandel",
    "sg:phone":"+41 22 784 01 43",
    "sg:postcode":"1234",
    "sg:province":"Gen\u00e8ve",
    "wof:name":"Galerie Calimala",
    "wof:placetype":"venue"
},
  "geometry": {"coordinates":[6.1575222015,46.172996521],"type":"Point"}
}