{
  "type": "Feature",
  "properties": {
    "iso:country":"CH",
    "sg:address":"Anwandstrasse 7",
    "sg:city":"Z\u00fcrich",
    "sg:orig_category":"Non-Classified Establishments",
    "sg:postcode":"8004",
    "sg:province":"Z\u00fcrich",
    "wof:name":"Ssi Service System Ag",
    "wof:placetype":"venue"
},
  "geometry": {"coordinates":[8.524769783,47.3759346008],"type":"Point"}
}