{
  "type": "Feature",
  "properties": {
    "iso:country":"CH",
    "sg:address":"Unter-kapf 9",
    "sg:city":"Emmenbr\u00fccke",
    "sg:orig_category":"Grosshandel mit B\u00fcromaschinen Grosshandel mit Datenverarbeitungsger\u00e4ten",
    "sg:phone":"+41 41 282 06 50",
    "sg:postcode":"6020",
    "sg:province":"Luzern",
    "wof:name":"Multi Graphic Bruno Bieri",
    "wof:placetype":"venue"
},
  "geometry": {"coordinates":[8.2778244019,47.091091156],"type":"Point"}
}