{
  "type": "Feature",
  "properties": {
    "iso:country":"CH",
    "sg:address":"6512",
    "sg:city":"Giubiasco",
    "sg:orig_category":"Herstellung von Metallkonstruktionen Stahl U Leichtmetallbau",
    "sg:phone":"+41 91 857 31 31",
    "sg:postcode":"6512",
    "sg:province":"Ticino",
    "wof:name":"Ferriere Cattaneo Sa",
    "wof:placetype":"venue"
},
  "geometry": {"coordinates":[9.0060901642,46.1762809753],"type":"Point"}
}