{
  "type": "Feature",
  "properties": {
    "iso:country":"CH",
    "sg:address":"Wiedenhubstrasse 15",
    "sg:city":"Liestal",
    "sg:orig_category":"Detailhandel mit Getr\u00e4nken Grosshandel mit Getr\u00e4nken",
    "sg:phone":"+41 61 922 13 10",
    "sg:postcode":"4410",
    "sg:province":"Basel-Landschaft",
    "wof:name":"Klar Weine",
    "wof:placetype":"venue"
},
  "geometry": {"coordinates":[7.7280430794,47.4861488342],"type":"Point"}
}