{
  "type": "Feature",
  "properties": {
    "iso:country":"CH",
    "sg:address":"Bahnh\u00f6flistrasse 4",
    "sg:city":"Ermensee",
    "sg:orig_category":"G\u00fcterbef\u00f6rderung im Strassenverkehr",
    "sg:phone":"+41 41 917 12 75",
    "sg:postcode":"6294",
    "sg:province":"Luzern",
    "wof:name":"Urs M\u00fcller Transporte",
    "wof:placetype":"venue"
},
  "geometry": {"coordinates":[8.2419118881,47.2294311523],"type":"Point"}
}