{
  "type": "Feature",
  "properties": {
    "iso:country":"CH",
    "sg:address":"Schulstrasse 2a",
    "sg:city":"Romanshorn",
    "sg:orig_category":"Arztpraxen",
    "sg:phone":"+41 71 463 10 84",
    "sg:postcode":"8590",
    "sg:province":"Thurgau",
    "wof:name":"Dr.med.markus Zeller Spezialarzt Fmh",
    "wof:placetype":"venue"
},
  "geometry": {"coordinates":[9.373982,47.564754],"type":"Point"}
}