{
  "type": "Feature",
  "properties": {
    "iso:country":"CH",
    "sg:address":"Neumarktstrasse 64 2503 Biel/bienne Case Postale 943",
    "sg:city":"Biel/bienne",
    "sg:orig_category":"Kauf U Verkauf von Immobilien auf eigene Rechnung Vermittlung von Immobilien",
    "sg:phone":"+41 32 323 11 57",
    "sg:postcode":"2501",
    "sg:province":"Bern",
    "wof:name":"Roma Immobilien Ag",
    "wof:placetype":"venue"
},
  "geometry": {"coordinates":[7.2515420914,47.1367225647],"type":"Point"}
}