{
  "type": "Feature",
  "properties": {
    "iso:country":"CH",
    "sg:address":"Im Wuhrenberg 4",
    "sg:city":"Magden",
    "sg:orig_category":"Herstellung von sonstigen Maschinen f\u00fcr unspezifische Verwendung",
    "sg:postcode":"4312",
    "sg:province":"Aargau",
    "wof:name":"Perel-dfs Gmbh",
    "wof:placetype":"venue"
},
  "geometry": {"coordinates":[7.8102068901,47.5324935913],"type":"Point"}
}