{
  "type": "Feature",
  "properties": {
    "iso:country":"CH",
    "sg:address":"Tramstrasse 55",
    "sg:city":"M\u00fcnchenstein",
    "sg:orig_category":"Advokaturb\u00fcros",
    "sg:phone":"+41 61 411 47 63",
    "sg:postcode":"4142",
    "sg:province":"Basel-Landschaft",
    "wof:name":"Heidi Hindermann Fluri Advokaturb\u00fcro",
    "wof:placetype":"venue"
},
  "geometry": {"coordinates":[7.61819,47.50985],"type":"Point"}
}