{
  "type": "Feature",
  "properties": {
    "iso:country":"CH",
    "sg:address":"Route Des Ateliers 12",
    "sg:city":"V\u00e9troz",
    "sg:orig_category":"Massagestudios",
    "sg:phone":"+41 27 346 36 54",
    "sg:postcode":"1963",
    "sg:province":"Valais",
    "wof:name":"Harmony Massage Institute",
    "wof:placetype":"venue"
},
  "geometry": {"coordinates":[7.2737011909,46.2165641785],"type":"Point"}
}