{
  "type": "Feature",
  "properties": {
    "iso:country":"CH",
    "sg:address":"Litternaring 12 3930 Visp Case Postale 33",
    "sg:city":"Visp",
    "sg:orig_category":"Gewinnung von Natursteinen f\u00fcr den Bau Herstellung von sonstigen Produkten aus nichtmetallischen Min",
    "sg:phone":"+41 27 946 20 63",
    "sg:postcode":"3930",
    "sg:province":"Valais",
    "wof:name":"Leo Imboden Quarzitsteinbr\u00fcche Ag",
    "wof:placetype":"venue"
},
  "geometry": {"coordinates":[7.8864741325,46.2923355103],"type":"Point"}
}