{
  "type": "Feature",
  "properties": {
    "iso:country":"CH",
    "sg:address":"Blegistrasse 15",
    "sg:city":"Baar",
    "sg:orig_category":"Berufliche Weiterbildung, Erwachsenenbildung Informatikschulen",
    "sg:phone":"+41 41 767 71 60",
    "sg:postcode":"6340",
    "sg:province":"Zug",
    "wof:name":"Ernst Witzig Ag Itc Informatik Training Center",
    "wof:placetype":"venue"
},
  "geometry": {"coordinates":[8.568669,47.215614],"type":"Point"}
}