{
  "type": "Feature",
  "properties": {
    "iso:country":"CH",
    "sg:address":"Hofmattstrasse 22",
    "sg:city":"Waltenschwil",
    "sg:orig_category":"Informatikdienste Unternehmensberatung",
    "sg:phone":"+41 32 843 49 60",
    "sg:postcode":"5622",
    "sg:province":"Aargau",
    "wof:name":"Fibatech Sa, Conseil D'entreprise Et Fiduciaire Conseil Aux Pme Et Aux Organisations Etc",
    "wof:placetype":"venue"
},
  "geometry": {"coordinates":[6.8647432327,46.9613037109],"type":"Point"}
}