{
  "type": "Feature",
  "properties": {
    "iso:country":"CH",
    "sg:address":"G\u00e4demji",
    "sg:city":"Fideris",
    "sg:orig_category":"Zimmerei, Dachdeckerei, Bauspenglerei U Abdichtung",
    "sg:phone":"+41 71 923 25 11",
    "sg:postcode":"7235",
    "sg:province":"Graubunden",
    "wof:name":"Georg Egli Holzbau Ag",
    "wof:placetype":"venue"
},
  "geometry": {"coordinates":[9.0534296036,47.4628791809],"type":"Point"}
}