{
  "type": "Feature",
  "properties": {
    "iso:country":"CH",
    "sg:address":"Avenue G\u00e9n\u00e9ral-guisan 18",
    "sg:city":"Sierre",
    "sg:orig_category":"Detailhandel mit B\u00fcchern Detailhandel mit B\u00fcchern, Zeitungen, Schreib U Papeteriewaren",
    "sg:phone":"+41 27 455 88 68",
    "sg:postcode":"3960",
    "sg:province":"Valais",
    "wof:name":"Librairie Papeterie Amacker",
    "wof:placetype":"venue"
},
  "geometry": {"coordinates":[7.530849,46.292538],"type":"Point"}
}