{
  "type": "Feature",
  "properties": {
    "iso:country":"CH",
    "sg:address":"Rue Pr\u00e9-fleuri 5",
    "sg:city":"Sion",
    "sg:orig_category":"Architektur U Ingenieurb\u00fcros Architekturb\u00fcros",
    "sg:phone":"+41 27 323 61 60",
    "sg:postcode":"1950",
    "sg:province":"Valais",
    "wof:name":"Berclaz R. & Torrent J.-l. S\u00e0rl",
    "wof:placetype":"venue"
},
  "geometry": {"coordinates":[7.356769,46.228737],"type":"Point"}
}