{
  "type": "Feature",
  "properties": {
    "iso:country":"CH",
    "sg:address":"Schmiedstrasse 6",
    "sg:city":"Cham",
    "sg:orig_category":"Allgemeiner Hoch U Tiefbau",
    "sg:postcode":"6330",
    "sg:province":"Zug",
    "wof:name":"Gerschwiler & Co, Baugesch\u00e4ft.",
    "wof:placetype":"venue"
},
  "geometry": {"coordinates":[9.04929,47.457172],"type":"Point"}
}