{
  "type": "Feature",
  "properties": {
    "iso:country":"CH",
    "sg:address":"8267",
    "sg:city":"Berlingen",
    "sg:orig_category":"Jugendorganisationen",
    "sg:phone":"+41 81 635 12 15",
    "sg:postcode":"8267",
    "sg:province":"Thurgau",
    "wof:name":"T\u00f6chterturnverein Trin",
    "wof:placetype":"venue"
},
  "geometry": {"coordinates":[9.3398199081,46.8325424194],"type":"Point"}
}