{
  "type": "Feature",
  "properties": {
    "iso:country":"CH",
    "sg:address":"Piazza Alighieri Dante 8",
    "sg:city":"Lugano",
    "sg:classifiers":[
        {
            "category":"Travel",
            "subcategory":"Hotels & Motels",
            "type":"Entertainment"
        }
    ],
    "sg:postcode":"6900",
    "sg:province":"Ticino",
    "sg:tags":[
        "hotels",
        "mit",
        "restaurant"
    ],
    "wof:name":"Exobar Sagl",
    "wof:placetype":"venue"
},
  "geometry": {"coordinates":[8.951086998,46.0051116943],"type":"Point"}
}