{
  "type": "Feature",
  "properties": {
    "iso:country":"CH",
    "sg:address":"Weing\u00e4rtli 4",
    "sg:city":"Fl\u00fcelen",
    "sg:orig_category":"Fahrschulen, Flugschulen",
    "sg:phone":"+41 41 870 68 37",
    "sg:postcode":"6454",
    "sg:province":"Uri",
    "wof:name":"Roger Garrisi Autofahrschule",
    "wof:placetype":"venue"
},
  "geometry": {"coordinates":[8.62479496,46.9115142822],"type":"Point"}
}