{
  "type": "Feature",
  "properties": {
    "iso:country":"CH",
    "sg:address":"Avenue Haldimand 24a",
    "sg:city":"Yverdon-les-bains",
    "sg:classifiers":[
        {
            "category":"Government",
            "subcategory":"Post Office",
            "type":"Public Place"
        }
    ],
    "sg:phone":"+41 24 426 33 63",
    "sg:postcode":"1400",
    "sg:province":"Vaud",
    "sg:tags":[
        "caf\u00e9s",
        "tea-rooms"
    ],
    "wof:name":"Tea-room Don Quichotte",
    "wof:placetype":"venue"
},
  "geometry": {"coordinates":[6.6449809074,46.7792015076],"type":"Point"}
}