{
  "type": "Feature",
  "properties": {
    "iso:country":"CH",
    "sg:address":"Heidenlochstrasse 84",
    "sg:city":"Liestal",
    "sg:orig_category":"Sportvereine Sch\u00fctzen",
    "sg:phone":"+41 6119014451",
    "sg:postcode":"4410",
    "sg:province":"Basel-Landschaft",
    "wof:name":"Sch\u00fctzenklub Liestal",
    "wof:placetype":"venue"
},
  "geometry": {"coordinates":[7.7494158745,47.4811973572],"type":"Point"}
}