{
  "type": "Feature",
  "properties": {
    "iso:country":"CH",
    "sg:address":"Bahnhofstrasse 42",
    "sg:city":"Baden",
    "sg:orig_category":"Sonstiges Versicherungsgewerbe",
    "sg:phone":"+41 56 222 44 42",
    "sg:postcode":"5400",
    "sg:province":"Aargau",
    "wof:name":"Schweizerische Mobiliar Versicherungsgesellschaft, Generalagentur P\u00e9rillard Marc, Baden",
    "wof:placetype":"venue"
},
  "geometry": {"coordinates":[8.3088083267,47.4775505066],"type":"Point"}
}