{
  "type": "Feature",
  "properties": {
    "iso:country":"CH",
    "sg:address":"7472",
    "sg:city":"Surava",
    "sg:orig_category":"Zivilschutz",
    "sg:phone":"+41 81 681 18 59",
    "sg:postcode":"7472",
    "sg:province":"Graubunden",
    "wof:name":"Amt F\u00fcr Zivilschutz",
    "wof:placetype":"venue"
},
  "geometry": {"coordinates":[9.6153678894,46.6665725708],"type":"Point"}
}