{
  "type": "Feature",
  "properties": {
    "iso:country":"CH",
    "sg:address":"Rue De La Maison Rouge 11",
    "sg:city":"Yverdon-les-bains",
    "sg:orig_category":"Detailhandel mit M\u00f6beln U Haushaltsgegenst\u00e4nden",
    "sg:postcode":"1400",
    "sg:province":"Vaud",
    "wof:name":"Schwab Albert",
    "wof:placetype":"venue"
},
  "geometry": {"coordinates":[6.6425337791,46.7786979675],"type":"Point"}
}