{
  "type": "Feature",
  "properties": {
    "iso:country":"CH",
    "sg:address":"Falkensteinerstrasse 4",
    "sg:city":"Muttenz",
    "sg:classifiers":[
        {
            "category":"Manufacturing",
            "subcategory":"Rubber & Plastics",
            "type":"Manufacturing & Wholesale Goods"
        }
    ],
    "sg:phone":"+41 61 467 93 93",
    "sg:postcode":"4132",
    "sg:province":"Basel-Landschaft",
    "sg:tags":[
        "barrel"
    ],
    "wof:name":"Plastomatic Ag",
    "wof:placetype":"venue"
},
  "geometry": {"coordinates":[7.655832,47.528019],"type":"Point"}
}