{
  "type": "Feature",
  "properties": {
    "iso:country":"CH",
    "sg:address":"Chemin De La Reraise 24",
    "sg:city":"Attalens",
    "sg:orig_category":"Malerei Tapeziererei",
    "sg:phone":"+41 21 947 46 11",
    "sg:postcode":"1616",
    "sg:province":"Fribourg",
    "wof:name":"Pergher Peintures S\u00e0rl Pl\u00e2trerie-peinture",
    "wof:placetype":"venue"
},
  "geometry": {"coordinates":[6.8513731956,46.5021095276],"type":"Point"}
}