{
  "type": "Feature",
  "properties": {
    "iso:country":"CH",
    "sg:address":"Lavasson Chemin Du 41",
    "sg:city":"Gland",
    "sg:orig_category":"Sonstiges Versicherungsgewerbe",
    "sg:postcode":"1196",
    "sg:province":"Vaud",
    "wof:name":"Assurjet, Abb\u00fchl Jean-pierre",
    "wof:placetype":"venue"
},
  "geometry": {"coordinates":[6.2614498138,46.4224014282],"type":"Point"}
}