{
  "type": "Feature",
  "properties": {
    "iso:country":"CH",
    "sg:address":"Oetwil 2944",
    "sg:city":"G\u00e4hwil",
    "sg:orig_category":"Hoch U Tiefbau",
    "sg:phone":"+41 71 931 39 60",
    "sg:postcode":"9534",
    "sg:province":"St. Gallen",
    "wof:name":"Guido Allenspach Baugesch\u00e4ft",
    "wof:placetype":"venue"
},
  "geometry": {"coordinates":[9.001206398,47.3997383118],"type":"Point"}
}