{
  "type": "Feature",
  "properties": {
    "iso:country":"CH",
    "sg:address":"Wyerweg 9",
    "sg:city":"Rothenthurm",
    "sg:orig_category":"Sportvereine Automobil",
    "sg:phone":"+41 24 471 67 93",
    "sg:postcode":"6418",
    "sg:province":"Schwyz",
    "wof:name":"Auto-moto-club Monthey",
    "wof:placetype":"venue"
},
  "geometry": {"coordinates":[6.9508309364,46.2431144714],"type":"Point"}
}