{
  "type": "Feature",
  "properties": {
    "iso:country":"CH",
    "sg:address":"Neustrasse 2",
    "sg:city":"Romanshorn",
    "sg:orig_category":"Detailhandel Reparatur von Gebrauchsg\u00fctern Vermietung von Gebrauchsg\u00fctern",
    "sg:phone":"+41 71 461 28 29",
    "sg:postcode":"8590",
    "sg:province":"Thurgau",
    "wof:name":"Benito Coradazzi Kino & Videothek Modern",
    "wof:placetype":"venue"
},
  "geometry": {"coordinates":[9.3789319992,47.5650062561],"type":"Point"}
}