{
  "type": "Feature",
  "properties": {
    "iso:country":"CH",
    "sg:address":"Flughafenstrasse",
    "sg:city":"Basel",
    "sg:classifiers":[
        {
            "category":"Airport",
            "type":"Transportation"
        }
    ],
    "sg:phone":"+41 800 558 833",
    "sg:postcode":"4056",
    "sg:province":"Basel-Stadt",
    "sg:tags":[
        "air-freight",
        "forwarders"
    ],
    "wof:name":"United Parcel Service (schweiz)",
    "wof:placetype":"venue"
},
  "geometry": {"coordinates":[7.569275,47.570553],"type":"Point"}
}