{
  "type": "Feature",
  "properties": {
    "iso:country":"CH",
    "sg:address":"Leberngasse 9",
    "sg:city":"Olten",
    "sg:orig_category":"Unclassifiable Establishments",
    "sg:phone":"+41 62 206 06 06",
    "sg:postcode":"4600",
    "sg:province":"Solothurn",
    "wof:name":"Bernhof Holding Ag",
    "wof:placetype":"venue"
},
  "geometry": {"coordinates":[7.900706768,47.3489761353],"type":"Point"}
}