{
  "type": "Feature",
  "properties": {
    "iso:country":"CH",
    "sg:address":"Pfannenstiel 12",
    "sg:city":"H\u00e4rkingen",
    "sg:classifiers":[
        {
            "category":"Utilities",
            "subcategory":"Refuse",
            "type":"Services"
        }
    ],
    "sg:phone":"+41 62 389 00 89",
    "sg:postcode":"4624",
    "sg:province":"Solothurn",
    "sg:tags":[
        "ironing",
        "board"
    ],
    "wof:name":"Brabantia Ag",
    "wof:placetype":"venue"
},
  "geometry": {"coordinates":[7.8111581802,47.3150253296],"type":"Point"}
}