{
  "type": "Feature",
  "properties": {
    "iso:country":"CH",
    "sg:address":"Grand-rue 37",
    "sg:city":"Morges",
    "sg:orig_category":"Religi\u00f6se Vereinigungen",
    "sg:postcode":"1110",
    "sg:province":"Vaud",
    "wof:name":"Fondation Bouddhiste L\u00e9manique",
    "wof:placetype":"venue"
},
  "geometry": {"coordinates":[6.4990329742,46.5096931458],"type":"Point"}
}