{
  "type": "Feature",
  "properties": {
    "iso:country":"CH",
    "sg:address":"La Faye",
    "sg:city":"Moudon",
    "sg:orig_category":"G\u00fcterbef\u00f6rderung im Strassenverkehr",
    "sg:phone":"+41 79 436 99 56",
    "sg:postcode":"1510",
    "sg:province":"Vaud",
    "wof:name":"Jean Maillard Transports",
    "wof:placetype":"venue"
},
  "geometry": {"coordinates":[6.8003668785,46.6674957275],"type":"Point"}
}