{
  "type": "Feature",
  "properties": {
    "iso:country":"CH",
    "sg:address":"Dorfstrasse 1",
    "sg:city":"Winkel",
    "sg:orig_category":"Architektur U Ingenieurb\u00fcros Architekturb\u00fcros",
    "sg:phone":"+41 19330505",
    "sg:postcode":"8185",
    "sg:province":"Z\u00fcrich",
    "wof:name":"Meierpartner Architekten Eth Sia Ag Architekturb\u00fcro, Bes. Planung U. Ausf\u00fchrung Von Bauten Usw",
    "wof:placetype":"venue"
},
  "geometry": {"coordinates":[8.795828,47.318485],"type":"Point"}
}