{
  "type": "Feature",
  "properties": {
    "iso:country":"CH",
    "sg:address":"Schlossallee 17",
    "sg:city":"Greng",
    "sg:orig_category":"Gartenbau Landschaftsplanungsb\u00fcros U Gartenarchitekturb\u00fcros",
    "sg:phone":"+41 21 634 52 38",
    "sg:postcode":"3280",
    "sg:province":"Fribourg",
    "wof:name":"Monod Louis",
    "wof:placetype":"venue"
},
  "geometry": {"coordinates":[6.5849099159,46.5432701111],"type":"Point"}
}