{
  "type": "Feature",
  "properties": {
    "addr:full":"Place Du Midi 46 1950 Sion Case Postale Sion Valais 1951",
    "addr:housenumber":"46",
    "addr:postcode":"1950;postale;1951",
    "addr:street":"Place Du Midi",
    "iso:country":"CH",
    "sg:address":"Place Du Midi 46 1950 Sion Case Postale",
    "sg:city":"Sion",
    "sg:orig_category":"Aktivit\u00e4t der Bankinstitute",
    "sg:phone":"+41 27 327 44 20",
    "sg:postcode":"1951",
    "sg:province":"Valais",
    "wof:name":"Banque Coop Succursale Sion",
    "wof:placetype":"venue"
},
  "geometry": {"coordinates":[7.362155,46.231895],"type":"Point"}
}