{
  "type": "Feature",
  "properties": {
    "iso:country":"CH",
    "sg:address":"4571",
    "sg:city":"L\u00fcterkofen-ichert",
    "sg:orig_category":"Landesverteidigung, Sozialversicherung \u00d6ffentliche Verwaltung",
    "sg:phone":"+41 32 677 16 56",
    "sg:postcode":"4571",
    "sg:province":"Solothurn",
    "wof:name":"Zivilschutzstelle L\u00fcterkofen-ichertswil",
    "wof:placetype":"venue"
},
  "geometry": {"coordinates":[7.5095710754,47.1624641418],"type":"Point"}
}