{
  "type": "Feature",
  "properties": {
    "addr:full":"Grienbachstrasse 33 Zug Zug 6300",
    "addr:housenumber":"33",
    "addr:postcode":"6300",
    "addr:street":"Grienbachstrasse;Zug",
    "iso:country":"CH",
    "sg:address":"Grienbachstrasse 33",
    "sg:city":"Zug",
    "sg:orig_category":"Bauschreinerei Herstellung von Konstruktionsteilen, Fertigbauteilen U Ausbauelementen aus Holz",
    "sg:phone":"+41 41 760 30 03",
    "sg:postcode":"6300",
    "sg:province":"Zug",
    "wof:name":"Br\u00e4ndle Ag, Schreinerei - Innenausbau",
    "wof:placetype":"venue"
},
  "geometry": {"coordinates":[8.525962,47.182434],"type":"Point"}
}