{
  "type": "Feature",
  "properties": {
    "iso:country":"CH",
    "sg:address":"Lochr\u00fctistrasse 6",
    "sg:city":"Wolfhausen",
    "sg:orig_category":"Bauspenglerei Dachdeckerei",
    "sg:phone":"+41 55 263 20 30",
    "sg:postcode":"8633",
    "sg:province":"Z\u00fcrich",
    "wof:name":"Mf Spenglerei Gmbh Bauspenglerei & Flachd\u00e4cher",
    "wof:placetype":"venue"
},
  "geometry": {"coordinates":[8.801215,47.257175],"type":"Point"}
}