{
  "type": "Feature",
  "properties": {
    "iso:country":"CH",
    "sg:address":"Place De La Riponne 3 1000 Lausanne. Postfach",
    "sg:city":"Lausanne",
    "sg:orig_category":"Reiseb\u00fcros U Reiseveranstalter",
    "sg:postcode":"1003",
    "sg:province":"Vaud",
    "wof:name":"Histoire & Voyages S\u00e0rl",
    "wof:placetype":"venue"
},
  "geometry": {"coordinates":[6.6318302155,46.5234375],"type":"Point"}
}