{
  "type": "Feature",
  "properties": {
    "iso:country":"CH",
    "sg:address":"Bernstrasse 171",
    "sg:city":"Rothrist",
    "sg:orig_category":"Detailhandel mit Lederwaren U Reiseartikeln Innendekorationsateliers",
    "sg:phone":"+41 62 794 41 00",
    "sg:postcode":"4852",
    "sg:province":"Aargau",
    "wof:name":"Alfred Friedli Innendekoration & Lederwaren",
    "wof:placetype":"venue"
},
  "geometry": {"coordinates":[7.8804922104,47.3049926758],"type":"Point"}
}