{
  "type": "Feature",
  "properties": {
    "iso:country":"CH",
    "sg:address":"Dorfstrasse 21",
    "sg:city":"Bellach",
    "sg:orig_category":"Fernmeldedienste",
    "sg:postcode":"4512",
    "sg:province":"Solothurn",
    "wof:name":"Smartelcom Gmbh, Engineering & Management",
    "wof:placetype":"venue"
},
  "geometry": {"coordinates":[7.4953999519,47.2127113342],"type":"Point"}
}