{
  "type": "Feature",
  "properties": {
    "addr:full":"Sonnenberg 9055 B\u00fchler. Postfach 14 B\u00fchler Appenzell Ausserrhoden 9055",
    "addr:housenumber":"9055;14",
    "addr:postcode":"buehler.;9055",
    "addr:street":"Sonnenberg;Postfach;Ausserrhoden",
    "iso:country":"CH",
    "sg:address":"Sonnenberg 9055 B\u00fchler. Postfach 14",
    "sg:city":"B\u00fchler",
    "sg:orig_category":"Betrieb von Sportanlagen",
    "sg:postcode":"9055",
    "sg:province":"Appenzell Ausserrhoden",
    "wof:name":"Genossenschaft Pro B\u00fchler",
    "wof:placetype":"venue"
},
  "geometry": {"coordinates":[9.42232,47.375389],"type":"Point"}
}