{
  "type": "Feature",
  "properties": {
    "iso:country":"CH",
    "sg:address":"Pian Lorenzo Via 12 6500 Bellinzona Casella Postale 1235",
    "sg:city":"Bellinzona",
    "sg:orig_category":"Detailhandel mit Metallwaren, Anstrichmitteln, Glaswaren, Bau U Heimwerkerbedarf",
    "sg:phone":"+41 91 840 20 30",
    "sg:postcode":"6500",
    "sg:province":"Ticino",
    "wof:name":"Tecnomedia Sa",
    "wof:placetype":"venue"
},
  "geometry": {"coordinates":[9.0241193771,46.1944618225],"type":"Point"}
}