{
  "type": "Feature",
  "properties": {
    "iso:country":"CH",
    "sg:address":"Via Cantonale",
    "sg:city":"Genestrerio",
    "sg:orig_category":"Einzelhandel mit Automobilteilen U Zubeh\u00f6r Herstellung von Bereifungen",
    "sg:phone":"+41 91 647 25 15",
    "sg:postcode":"6852",
    "sg:province":"Ticino",
    "wof:name":"Nicola Mazzei",
    "wof:placetype":"venue"
},
  "geometry": {"coordinates":[8.9605751038,45.8548202515],"type":"Point"}
}