{
  "type": "Feature",
  "properties": {
    "iso:country":"CH",
    "sg:address":"Zugerstrasse",
    "sg:city":"Hirzel",
    "sg:orig_category":"Non-Classified Establishments",
    "sg:postcode":"8816",
    "sg:province":"Z\u00fcrich",
    "wof:name":"Autohandel Vilaj",
    "wof:placetype":"venue"
},
  "geometry": {"coordinates":[8.6120376587,47.2191238403],"type":"Point"}
}