{
  "type": "Feature",
  "properties": {
    "iso:country":"CH",
    "sg:address":"Rue Des Anciens-bains 4 1180 Rolle. Postfach",
    "sg:city":"Rolle",
    "sg:orig_category":"Vermietung U Verpachtung von eigenen Immobilien Vermittlung von Immobilien",
    "sg:phone":"+41 21 601 56 03",
    "sg:postcode":"1180",
    "sg:province":"Vaud",
    "wof:name":"Immoproject Sa Immeubles Etc",
    "wof:placetype":"venue"
},
  "geometry": {"coordinates":[6.3401618004,46.4601783752],"type":"Point"}
}