{
  "type": "Feature",
  "properties": {
    "iso:country":"CH",
    "sg:address":"Furkastrasse 12",
    "sg:city":"Basel",
    "sg:orig_category":"Religi\u00f6se Vereinigungen divers Vereine Damen",
    "sg:phone":"+41 61 301 77 79",
    "sg:postcode":"4054",
    "sg:province":"Basel-Stadt",
    "wof:name":"M\u00e4dchenjungschar Stephanus C/o Gemeindehaus Stephanus",
    "wof:placetype":"venue"
},
  "geometry": {"coordinates":[7.562265873,47.5471305847],"type":"Point"}
}