{
  "type": "Feature",
  "properties": {
    "iso:country":"CH",
    "sg:address":"Seeblick 1",
    "sg:city":"Cham",
    "sg:orig_category":"Hardwareberatung Sonstige mit der Informatik verbundene T\u00e4tigkeiten",
    "sg:postcode":"6330",
    "sg:province":"Zug",
    "wof:name":"Infortis Ag Sap-beratung &- Entwicklung",
    "wof:placetype":"venue"
},
  "geometry": {"coordinates":[9.2388324738,47.4182128906],"type":"Point"}
}