{
  "type": "Feature",
  "properties": {
    "iso:country":"CH",
    "sg:address":"Via Municipio 2",
    "sg:city":"Savosa",
    "sg:orig_category":"Detailhandel mit Antiquit\u00e4ten U Gebrauchtwaren in Verkaufsr\u00e4umen",
    "sg:postcode":"6942",
    "sg:province":"Ticino",
    "wof:name":"Rinnovatec Sagl",
    "wof:placetype":"venue"
},
  "geometry": {"coordinates":[8.939106,46.018536],"type":"Point"}
}