{
  "type": "Feature",
  "properties": {
    "iso:country":"CH",
    "sg:address":"Salensteinerstrasse 27",
    "sg:city":"Ermatingen",
    "sg:orig_category":"Finanzierungsinstitutionen Grosshandel mit pharmazeutischen Erzeugnissen",
    "sg:phone":"+41 71 664 28 34",
    "sg:postcode":"8272",
    "sg:province":"Thurgau",
    "wof:name":"Altherr Import/export Inhaberin Knecht-altherr Liliane",
    "wof:placetype":"venue"
},
  "geometry": {"coordinates":[9.0710496902,47.6669044495],"type":"Point"}
}