{
  "type": "Feature",
  "properties": {
    "iso:country":"CH",
    "sg:address":"Ohne Domizil",
    "sg:city":"Bern",
    "sg:orig_category":"Detailhandel mit M\u00f6beln U Haushaltsgegenst\u00e4nden",
    "sg:phone":"+41 31 382 02 60",
    "sg:postcode":"3000",
    "sg:province":"Bern",
    "wof:name":"Soltani Ag",
    "wof:placetype":"venue"
},
  "geometry": {"coordinates":[7.4482097626,46.9480209351],"type":"Point"}
}