{
  "type": "Feature",
  "properties": {
    "iso:country":"CH",
    "sg:address":"Rue Du G\u00e9n\u00e9ral Comman 25 2950 Courgenay Case Postale",
    "sg:city":"Courgenay",
    "sg:orig_category":"Herstellung von Uhren",
    "sg:phone":"+41 32 427 04 40",
    "sg:postcode":"2950",
    "sg:province":"Jura",
    "wof:name":"Valentini Sa Manufacture De Bo\u00eetes De Montres",
    "wof:placetype":"venue"
},
  "geometry": {"coordinates":[7.1206359863,47.4053230286],"type":"Point"}
}