{
  "type": "Feature",
  "properties": {
    "iso:country":"CH",
    "sg:address":"Hinterm\u00e4ttlistrasse 9 5506 M\u00e4genwil. Postfach",
    "sg:city":"M\u00e4genwil",
    "sg:orig_category":"Hardwareberatung",
    "sg:postcode":"5506",
    "sg:province":"Aargau",
    "wof:name":"Coss Computertechnik Und System-service Gmbh",
    "wof:placetype":"venue"
},
  "geometry": {"coordinates":[8.2246875763,47.4111557007],"type":"Point"}
}