{
  "type": "Feature",
  "properties": {
    "iso:country":"CH",
    "sg:address":"Industriestrasse 31",
    "sg:city":"Dietlikon",
    "sg:classifiers":[
        {
            "category":"Home & Garden",
            "subcategory":"Carpets & Floor Coverings",
            "type":"Retail Goods"
        }
    ],
    "sg:phone":"+41 18352288",
    "sg:postcode":"8305",
    "sg:province":"Z\u00fcrich",
    "sg:tags":[
        "caoutchouc"
    ],
    "wof:name":"Freudenberg Vertriebsb\u00fcro Schweiz",
    "wof:placetype":"venue"
},
  "geometry": {"coordinates":[8.618557,47.412266],"type":"Point"}
}