{
  "type": "Feature",
  "properties": {
    "addr:full":"Schl\u00fcsselacher 2 Willisau Luzern 6130",
    "addr:housenumber":"2",
    "addr:postcode":"6130",
    "addr:street":"Schluesselacher",
    "iso:country":"CH",
    "sg:address":"Schl\u00fcsselacher 2",
    "sg:city":"Willisau",
    "sg:orig_category":"Dachdeckerei",
    "sg:phone":"+41 41 970 26 36",
    "sg:postcode":"6130",
    "sg:province":"Luzern",
    "wof:name":"Werner Schmidiger Bedachungsgesch\u00e4ft",
    "wof:placetype":"venue"
},
  "geometry": {"coordinates":[7.983464,47.119694],"type":"Point"}
}