{
  "type": "Feature",
  "properties": {
    "iso:country":"CH",
    "sg:address":"Pestalozzistrasse 24 8032 Z\u00fcrich. Postfach 132",
    "sg:city":"Z\u00fcrich",
    "sg:orig_category":"Advokaturb\u00fcros",
    "sg:phone":"+41 12623344",
    "sg:postcode":"8028",
    "wof:name":"Suhr & W\u00fcrgler & Maag & Bisang Advokaturb\u00fcro",
    "wof:placetype":"venue"
},
  "geometry": {"coordinates":[8.554558,47.373558],"type":"Point"}
}