{
  "type": "Feature",
  "properties": {
    "iso:country":"CH",
    "sg:address":"9038 Rehetobel. Postfach 42",
    "sg:city":"Rehetobel",
    "sg:orig_category":"Sessellifte and Skilifte",
    "sg:phone":"+41 79 658 25 91",
    "sg:postcode":"9038",
    "sg:province":"Appenzell Ausserrhoden",
    "wof:name":"Hanspeter Anhorn Skilift Scheidweg",
    "wof:placetype":"venue"
},
  "geometry": {"coordinates":[9.4833850861,47.4260749817],"type":"Point"}
}