{
  "type": "Feature",
  "properties": {
    "addr:full":"Rigistrasse 3 6330 Cham. Postfach 584 Cham Zug 6330",
    "addr:housenumber":"3;584",
    "addr:postcode":"6330;6330",
    "addr:street":"Rigistrasse;Postfach;Zug",
    "iso:country":"CH",
    "sg:address":"Rigistrasse 3 6330 Cham. Postfach 584",
    "sg:city":"Cham",
    "sg:classifiers":[
        {
            "category":"Social Services",
            "subcategory":"Retirement Home",
            "type":"Services"
        }
    ],
    "sg:phone":"+41 41 784 08 08",
    "sg:postcode":"6330",
    "sg:province":"Zug",
    "sg:tags":[
        "pflegeheime",
        "u",
        "alters"
    ],
    "wof:name":"Altersheim B\u00fcel",
    "wof:placetype":"venue"
},
  "geometry": {"coordinates":[8.45568,47.181786],"type":"Point"}
}