{
  "type": "Feature",
  "properties": {
    "iso:country":"CH",
    "sg:address":"Panzella",
    "sg:city":"Novazzano",
    "sg:orig_category":"RESTAURANTS: TEA-ROOMS",
    "sg:phone":"+41 91 647 24 21",
    "sg:postcode":"6883",
    "sg:province":"Ticino",
    "wof:name":"Robbiani Giorgio.",
    "wof:placetype":"venue"
},
  "geometry": {"coordinates":[8.9822053909,45.8426856995],"type":"Point"}
}