{
  "type": "Feature",
  "properties": {
    "iso:country":"CH",
    "sg:address":"Niedermattstrasse 25 4538 Oberbipp. Postfach",
    "sg:city":"Oberbipp",
    "sg:orig_category":"Handel mit Automobilen",
    "sg:phone":"+41 32 636 41 41",
    "sg:postcode":"4538",
    "sg:province":"Bern",
    "wof:name":"Bb Auto Und Carrosserie Ag, 4538 Oberbipp",
    "wof:placetype":"venue"
},
  "geometry": {"coordinates":[7.6674489975,47.2614021301],"type":"Point"}
}