{
  "type": "Feature",
  "properties": {
    "iso:country":"CH",
    "sg:address":"Farnsbergstrasse 28",
    "sg:city":"Herzogenbuchsee",
    "sg:orig_category":"Architektur U Ingenieurb\u00fcros",
    "sg:phone":"+41 81 410 15 20",
    "sg:postcode":"3360",
    "sg:province":"Bern",
    "wof:name":"Diag Davoser Ingenieure Ag",
    "wof:placetype":"venue"
},
  "geometry": {"coordinates":[9.813053,46.787067],"type":"Point"}
}