{
  "type": "Feature",
  "properties": {
    "addr:full":"Chemin Du Vallon 18 1030 Bussigny-lausanne Case Postale 217 Bussigny-lausanne Vaud 1030",
    "addr:housenumber":"18;217",
    "addr:postcode":"1030;1030",
    "addr:street":"Chemin Du Vallon;Case Postale",
    "iso:country":"CH",
    "sg:address":"Chemin Du Vallon 18 1030 Bussigny-lausanne Case Postale 217",
    "sg:city":"Bussigny-lausanne",
    "sg:orig_category":"Autogaragen",
    "sg:phone":"+41 21 701 10 91",
    "sg:postcode":"1030",
    "sg:province":"Vaud",
    "wof:name":"Jean-claude Keller Garage",
    "wof:placetype":"venue"
},
  "geometry": {"coordinates":[6.551758,46.544758],"type":"Point"}
}