{
  "type": "Feature",
  "properties": {
    "iso:country":"CH",
    "sg:address":"Sch\u00f6nenb\u00fchlstrasse 58",
    "sg:city":"Wettingen",
    "sg:orig_category":"Herstellung von Elektromotoren, Generatoren U Transformatoren",
    "sg:postcode":"5430",
    "sg:province":"Aargau",
    "wof:name":"Vk Consult Gmbh",
    "wof:placetype":"venue"
},
  "geometry": {"coordinates":[8.3306903839,47.4696922302],"type":"Point"}
}