{
  "type": "Feature",
  "properties": {
    "iso:country":"CH",
    "sg:address":"Buonaserstrasse 28b",
    "sg:city":"Rotkreuz",
    "sg:orig_category":"Herstellung von Musikinstrumenten Herstellung von sonstigen elektrischen Ausr\u00fcstungen",
    "sg:phone":"+41 41 790 65 60",
    "sg:postcode":"6343",
    "sg:province":"Zug",
    "wof:name":"Rm Drums, De Silva",
    "wof:placetype":"venue"
},
  "geometry": {"coordinates":[8.4349117279,47.1406936646],"type":"Point"}
}