{
  "type": "Feature",
  "properties": {
    "iso:country":"CH",
    "sg:address":"Moosstrasse 7",
    "sg:city":"Luzern",
    "sg:orig_category":"Verwaltung von Immobilien Wirtschaftspr\u00fcfung, Steuerberatung U Treuhand",
    "sg:phone":"+41 41 210 44 44",
    "sg:postcode":"6003",
    "sg:province":"Luzern",
    "wof:name":"Alpina Treuhand Luzern",
    "wof:placetype":"venue"
},
  "geometry": {"coordinates":[8.3049650192,47.0458602905],"type":"Point"}
}