{
  "type": "Feature",
  "properties": {
    "iso:country":"CH",
    "sg:address":"Oberdorfstrasse 51",
    "sg:city":"Dietikon",
    "sg:orig_category":"Herstellung von keramischen Wand U Bodenfliesen U platten Verlegen von Fliesen U Platten",
    "sg:phone":"+41 79 610 23 47",
    "sg:postcode":"8953",
    "sg:province":"Z\u00fcrich",
    "wof:name":"Posch Rolf",
    "wof:placetype":"venue"
},
  "geometry": {"coordinates":[9.487947464,47.1498565674],"type":"Point"}
}