{
  "type": "Feature",
  "properties": {
    "iso:country":"CH",
    "sg:address":"Fabrikstrasse 11 4614 H\u00e4gendorf. Postfach",
    "sg:city":"H\u00e4gendorf",
    "sg:orig_category":"Grosshandel mit Blumen U Pflanzen",
    "sg:phone":"+41 62 216 53 83",
    "sg:postcode":"4614",
    "sg:province":"Solothurn",
    "wof:name":"Blumen-grossmarkt G\u00e4u Hein Georg Blumen, Pflanzen; Handel",
    "wof:placetype":"venue"
},
  "geometry": {"coordinates":[7.839029789,47.3294181824],"type":"Point"}
}