{
  "type": "Feature",
  "properties": {
    "addr:full":"Dorfstrasse 10 Sch\u00f6ftland Aargau 5040",
    "addr:housenumber":"10",
    "addr:postcode":"5040",
    "addr:street":"Dorfstrasse",
    "iso:country":"CH",
    "sg:address":"Dorfstrasse 10",
    "sg:city":"Sch\u00f6ftland",
    "sg:orig_category":"Detailhandel mit Brot, Back U S\u00fcsswaren",
    "sg:phone":"+41 62 721 12 57",
    "sg:postcode":"5040",
    "sg:province":"Aargau",
    "wof:name":"Hans Herzog B\u00e4ckerei-konditorei",
    "wof:placetype":"venue"
},
  "geometry": {"coordinates":[8.051454,47.305229],"type":"Point"}
}