{
  "type": "Feature",
  "properties": {
    "iso:country":"CH",
    "sg:address":"Weinbergstrasse 56/58 8006 Z\u00fcrich. Postfach",
    "sg:city":"Z\u00fcrich",
    "sg:orig_category":"Unclassifiable Establishments",
    "sg:postcode":"8006",
    "sg:province":"Z\u00fcrich",
    "wof:name":"Cottonwick Holding Ag",
    "wof:placetype":"venue"
},
  "geometry": {"coordinates":[8.5440120697,47.3814582825],"type":"Point"}
}