{
  "type": "Feature",
  "properties": {
    "iso:country":"CH",
    "sg:address":"Farbweg 11",
    "sg:city":"Burgdorf",
    "sg:orig_category":"Sonstige Institutionen des Sozialwesens ohne Beherbergung",
    "sg:phone":"+41 34 423 40 02",
    "sg:postcode":"3400",
    "sg:province":"Bern",
    "wof:name":"Brigitta Jeker M\u00fctter- & V\u00e4terberatung",
    "wof:placetype":"venue"
},
  "geometry": {"coordinates":[7.6239981651,47.059841156],"type":"Point"}
}