{
  "type": "Feature",
  "properties": {
    "iso:country":"CH",
    "sg:address":"Sch\u00f6nb\u00fcelstrasse 7",
    "sg:city":"Wallisellen",
    "sg:orig_category":"Grosshandel mit Spielwaren Grosshandel mit sonstigen Gebrauchs U Verbrauchsg\u00fctern",
    "sg:phone":"+41 18133849",
    "sg:postcode":"8304",
    "sg:province":"Z\u00fcrich",
    "wof:name":"The Mousehouse Company Gmbh Handel & Vertrieb V.spielzeug",
    "wof:placetype":"venue"
},
  "geometry": {"coordinates":[8.6083803177,47.4121704102],"type":"Point"}
}