{
  "type": "Feature",
  "properties": {
    "iso:country":"CH",
    "sg:address":"Albisstrasse 12",
    "sg:city":"Adliswil",
    "sg:orig_category":"Detailhandel mit Waren verschiedener Art, Hauptrichtung Nahrungsmittel",
    "sg:phone":"+41 17100553",
    "sg:postcode":"8134",
    "sg:province":"Z\u00fcrich",
    "wof:name":"Migros-markt",
    "wof:placetype":"venue"
},
  "geometry": {"coordinates":[8.5253143311,47.3110847473],"type":"Point"}
}