{
  "type": "Feature",
  "properties": {
    "iso:country":"CH",
    "sg:address":"Route D'evian",
    "sg:city":"Aigle",
    "sg:orig_category":"Blumen U Zierpflanzenbau",
    "sg:phone":"+41 91 825 10 94",
    "sg:postcode":"1860",
    "sg:province":"Vaud",
    "wof:name":"Remo Rossini Orticoltore",
    "wof:placetype":"venue"
},
  "geometry": {"coordinates":[8.995528,46.187714],"type":"Point"}
}