{
  "type": "Feature",
  "properties": {
    "iso:country":"CH",
    "sg:address":"Z\u00fcrichstrasse 9",
    "sg:city":"Herzogenbuchsee",
    "sg:orig_category":"Unclassifiable Establishments",
    "sg:postcode":"3360",
    "sg:province":"Bern",
    "wof:name":"Montageunternehmungen Ism Group Ag",
    "wof:placetype":"venue"
},
  "geometry": {"coordinates":[7.7065420151,47.1886367798],"type":"Point"}
}