{
  "type": "Feature",
  "properties": {
    "iso:country":"CH",
    "sg:address":"Schulweg 2",
    "sg:city":"Hitzkirch",
    "sg:orig_category":"Sportvereine Motorrad",
    "sg:phone":"+41 41 917 17 01",
    "sg:postcode":"6285",
    "sg:province":"Luzern",
    "wof:name":"Motoclub Schongau",
    "wof:placetype":"venue"
},
  "geometry": {"coordinates":[8.2599687576,47.2253456116],"type":"Point"}
}