{
  "type": "Feature",
  "properties": {
    "iso:country":"CH",
    "sg:address":"H\u00fcnenbergerstrasse 3",
    "sg:city":"Cham",
    "sg:orig_category":"Sonstiger Fachdetailhandel mit Nahrungsmitteln, Getr\u00e4nken U Tabak in Verkaufsr\u00e4umen",
    "sg:phone":"+41 41 780 13 40",
    "sg:postcode":"6330",
    "sg:province":"Zug",
    "wof:name":"Ch\u00e4s-m\u00e4rt Ruckli",
    "wof:placetype":"venue"
},
  "geometry": {"coordinates":[8.4572095871,47.1795883179],"type":"Point"}
}