{
  "type": "Feature",
  "properties": {
    "iso:country":"CH",
    "sg:address":"Baumgartenweg 20",
    "sg:city":"Muttenz",
    "sg:orig_category":"Sonstige mit der Informatik verbundene T\u00e4tigkeiten",
    "sg:postcode":"4132",
    "sg:province":"Basel-Landschaft",
    "wof:name":"Softwave Pinck",
    "wof:placetype":"venue"
},
  "geometry": {"coordinates":[7.6393609047,47.5239372253],"type":"Point"}
}