{
  "type": "Feature",
  "properties": {
    "iso:country":"CH",
    "sg:address":"Heimisbach",
    "sg:city":"Trachselwald",
    "sg:orig_category":"Haltung von Rindern",
    "sg:postcode":"3456",
    "sg:province":"Bern",
    "wof:name":"Viehzuchtgenossenschaft Heimisbach",
    "wof:placetype":"venue"
},
  "geometry": {"coordinates":[7.741109848,47.0142211914],"type":"Point"}
}