{
  "type": "Feature",
  "properties": {
    "iso:country":"CH",
    "sg:address":"Frank Buchserstrasse 9",
    "sg:city":"Feldbrunnen",
    "sg:orig_category":"Public-Relations-Agenturen",
    "sg:phone":"+41 32 623 82 80",
    "sg:postcode":"4532",
    "sg:province":"Solothurn",
    "wof:name":"Vigier Public Relations",
    "wof:placetype":"venue"
},
  "geometry": {"coordinates":[7.5553750992,47.2194824219],"type":"Point"}
}