{
  "type": "Feature",
  "properties": {
    "iso:country":"CH",
    "sg:address":"Unterdorfstrasse 19 4415 Lausen. Postfach",
    "sg:city":"Lausen",
    "sg:orig_category":"Drogerien",
    "sg:phone":"+41 61 921 02 00",
    "sg:postcode":"4415",
    "sg:province":"Basel-Landschaft",
    "wof:name":"Ergolz-drogerie Ag",
    "wof:placetype":"venue"
},
  "geometry": {"coordinates":[7.7602472305,47.4726448059],"type":"Point"}
}