{
  "type": "Feature",
  "properties": {
    "iso:country":"CH",
    "sg:address":"Grossmatte-ost 8",
    "sg:city":"Littau",
    "sg:orig_category":"Detailhandel mit Musikinstrumenten Detailhandel mit Ton U Bildtr\u00e4gern",
    "sg:phone":"+41 41 240 44 24",
    "sg:postcode":"6014",
    "sg:province":"Luzern",
    "wof:name":"Soundhouse Musicservice Ag",
    "wof:placetype":"venue"
},
  "geometry": {"coordinates":[8.2677707672,47.0489311218],"type":"Point"}
}