{
  "type": "Feature",
  "properties": {
    "iso:country":"CH",
    "sg:address":"Wydenmatt",
    "sg:city":"Willisau",
    "sg:orig_category":"Non-Classified Establishments",
    "sg:phone":"+41 17881963",
    "sg:postcode":"6130",
    "sg:province":"Luzern",
    "wof:name":"Black Arrow Gmbh",
    "wof:placetype":"venue"
},
  "geometry": {"coordinates":[8.6433610916,47.1966247559],"type":"Point"}
}