{
  "type": "Feature",
  "properties": {
    "iso:country":"CH",
    "sg:address":"H\u00f4pital Rue De L' 7 1700 Freiburg. Postfach",
    "sg:city":"Freiburg",
    "sg:orig_category":"Fachdetailhandel in Verkaufsr\u00e4umen",
    "sg:phone":"+41 26 322 13 69",
    "sg:postcode":"1700",
    "sg:province":"Fribourg",
    "wof:name":"Codourey Opticien Sa",
    "wof:placetype":"venue"
},
  "geometry": {"coordinates":[7.1746201515,46.8062400818],"type":"Point"}
}