{
  "type": "Feature",
  "properties": {
    "iso:country":"CH",
    "sg:address":"Rainweg 2",
    "sg:city":"Brittnau",
    "sg:orig_category":"Maschinen-Fabrikation",
    "sg:phone":"+41 62 797 76 86",
    "sg:postcode":"4805",
    "sg:province":"Aargau",
    "wof:name":"Aubeko Ag",
    "wof:placetype":"venue"
},
  "geometry": {"coordinates":[7.9472351074,47.2549362183],"type":"Point"}
}