{
  "type": "Feature",
  "properties": {
    "iso:country":"CH",
    "sg:address":"Gempenring 34",
    "sg:city":"Dornach",
    "sg:orig_category":"Primarschulen",
    "sg:phone":"+41 61 701 62 52",
    "sg:postcode":"4143",
    "sg:province":"Solothurn",
    "wof:name":"Primarschule Br\u00fchl",
    "wof:placetype":"venue"
},
  "geometry": {"coordinates":[7.6126279831,47.4809532166],"type":"Point"}
}