{
  "type": "Feature",
  "properties": {
    "iso:country":"CH",
    "sg:address":"Melchenb\u00fchlweg 4",
    "sg:city":"Bern",
    "sg:orig_category":"Herstellung von Drahtwaren",
    "sg:phone":"+41 31 931 16 29",
    "sg:postcode":"3006",
    "sg:province":"Bern",
    "wof:name":"Umbehr Ag Verschl\u00fcsse, Massenartikel In Metall, Draht Usw; Fabr., Handel",
    "wof:placetype":"venue"
},
  "geometry": {"coordinates":[7.4758749008,46.9509162903],"type":"Point"}
}