{
  "type": "Feature",
  "properties": {
    "iso:country":"CH",
    "sg:address":"B\u00e4renplatz 5 3920 Zermatt. Postfach",
    "sg:city":"Bern",
    "sg:classifiers":[
        {
            "category":"Restaurant",
            "type":"Food & Drink"
        }
    ],
    "sg:phone":"+41 27 966 06 06",
    "sg:postcode":"3005",
    "sg:province":"Bern",
    "sg:tags":[
        "tea-rooms",
        "restaurants"
    ],
    "wof:name":"L\u00f6ffel Erich Restaurant Le Mazot",
    "wof:placetype":"venue"
},
  "geometry": {"coordinates":[7.7484002113,46.024143219],"type":"Point"}
}