{
  "type": "Feature",
  "properties": {
    "iso:country":"CH",
    "sg:address":"Dorfbachstrasse 40 3098 K\u00f6niz. Postfach",
    "sg:city":"K\u00f6niz",
    "sg:orig_category":"Detailhandel mit elektrischen Haushalts-,Radio U Fernsehger\u00e4ten sowie Musikinstrumenten Werbeagentur",
    "sg:phone":"+41 41 630 00 78",
    "sg:postcode":"3098",
    "sg:province":"Bern",
    "wof:name":"Comsense Gmbh Ger\u00e4te Auf Dem Gebiet Der Visuellen Kommunikation; Handel, Vermietung",
    "wof:placetype":"venue"
},
  "geometry": {"coordinates":[8.3071937561,46.9907646179],"type":"Point"}
}