{
  "type": "Feature",
  "properties": {
    "iso:country":"CH",
    "sg:address":"Gschwaderstrasse 1",
    "sg:city":"Uster",
    "sg:orig_category":"Fachdetailhandel in Verkaufsr\u00e4umen",
    "sg:postcode":"8610",
    "sg:province":"Z\u00fcrich",
    "wof:name":"Br\u00f6nnimann's Roadhouse + Co",
    "wof:placetype":"venue"
},
  "geometry": {"coordinates":[8.7080287933,47.3540344238],"type":"Point"}
}