{
  "type": "Feature",
  "properties": {
    "addr:full":"Hafenstrasse 58 Romanshorn Thurgau 8590",
    "addr:housenumber":"58",
    "addr:postcode":"8590",
    "addr:street":"Hafenstrasse",
    "iso:country":"CH",
    "sg:address":"Hafenstrasse 58",
    "sg:city":"Romanshorn",
    "sg:orig_category":"Boots U Yachtbau Instandhaltung U Reparatur von Automobilen",
    "sg:phone":"+41 71 463 70 30",
    "sg:postcode":"8590",
    "sg:province":"Thurgau",
    "wof:name":"Seegarage Tibor Potzar",
    "wof:placetype":"venue"
},
  "geometry": {"coordinates":[9.381954,47.567829],"type":"Point"}
}