{
  "type": "Feature",
  "properties": {
    "iso:country":"CH",
    "sg:address":"Schmiedgasse 86",
    "sg:city":"Ibach",
    "sg:orig_category":"Herstellung von Werkzeugmaschinen",
    "sg:phone":"+41 41 760 35 04",
    "sg:postcode":"6438",
    "sg:province":"Schwyz",
    "wof:name":"Tipton Gmbh",
    "wof:placetype":"venue"
},
  "geometry": {"coordinates":[8.6482696533,47.015914917],"type":"Point"}
}