{
  "type": "Feature",
  "properties": {
    "iso:country":"CH",
    "sg:address":"Kesslerstrasse 7",
    "sg:city":"Schlieren",
    "sg:orig_category":"P\u00e9dicure",
    "sg:phone":"+41 17306183",
    "sg:postcode":"8952",
    "sg:province":"Z\u00fcrich",
    "wof:name":"Marianne Bernet P\u00e9dicure",
    "wof:placetype":"venue"
},
  "geometry": {"coordinates":[8.4386386871,47.3959388733],"type":"Point"}
}