{
  "type": "Feature",
  "properties": {
    "iso:country":"CH",
    "sg:address":"Bernstrasse 72",
    "sg:city":"Stettlen",
    "sg:orig_category":"Architekturb\u00fcros",
    "sg:phone":"+41 31 931 32 14",
    "sg:postcode":"3066",
    "sg:province":"Bern",
    "wof:name":"Hansj\u00f6rg Utiger Architekturb\u00fcro",
    "wof:placetype":"venue"
},
  "geometry": {"coordinates":[7.521365,46.958664],"type":"Point"}
}