{
  "type": "Feature",
  "properties": {
    "iso:country":"CH",
    "sg:address":"1115",
    "sg:city":"Vullierens",
    "sg:orig_category":"Landesverteidigung, Sozialversicherung \u00d6ffentliche Verwaltung",
    "sg:phone":"+41 21 800 31 10",
    "sg:postcode":"1115",
    "sg:province":"Vaud",
    "wof:name":"Centre De Protection Civile",
    "wof:placetype":"venue"
},
  "geometry": {"coordinates":[6.4529600143,46.5753707886],"type":"Point"}
}