{
  "type": "Feature",
  "properties": {
    "iso:country":"CH",
    "sg:address":"Untere Weidstrasse 17",
    "sg:city":"W\u00e4denswil",
    "sg:orig_category":"Detailhandel mit B\u00fcromaschinen U einrichtungen",
    "sg:phone":"+41 71 223 30 23",
    "sg:postcode":"8820",
    "sg:province":"Z\u00fcrich",
    "wof:name":"Zangerl B\u00fcromaschinen",
    "wof:placetype":"venue"
},
  "geometry": {"coordinates":[9.368898,47.423889],"type":"Point"}
}