{
  "type": "Feature",
  "properties": {
    "iso:country":"CH",
    "sg:address":"Perdonnet Quai 5 1800 Hauteville (vevey). Postfach",
    "sg:city":"Lausanne",
    "sg:orig_category":"Pensionskassen",
    "sg:postcode":"1018",
    "sg:province":"Vaud",
    "wof:name":"Aaa Fondation De Pr\u00e9voyance",
    "wof:placetype":"venue"
},
  "geometry": {"coordinates":[5.1808700562,45.8973388672],"type":"Point"}
}