{
  "type": "Feature",
  "properties": {
    "addr:full":"Grande-rue 9 Cossonay Vaud 1304",
    "addr:housenumber":"9",
    "addr:postcode":"1304",
    "addr:street":"Grande-Rue",
    "iso:country":"CH",
    "sg:address":"Grande-rue 9",
    "sg:city":"Cossonay",
    "sg:classifiers":[
        {
            "category":"Banks & Credit Unions",
            "subcategory":"Bank",
            "type":"Services"
        }
    ],
    "sg:phone":"+41 21 861 15 41",
    "sg:postcode":"1304",
    "sg:province":"Vaud",
    "wof:name":"Banque Cr\u00e9dit Foncier Vaudois",
    "wof:placetype":"venue"
},
  "geometry": {"coordinates":[6.51941,46.606098],"type":"Point"}
}