{
  "type": "Feature",
  "properties": {
    "iso:country":"CH",
    "sg:address":"Z\u00e4hringerstrasse 16 4057 Basel. Postfach 217",
    "sg:city":"Basel",
    "sg:orig_category":"Interessenvertretungen",
    "sg:postcode":"4051",
    "sg:province":"Basel-Stadt",
    "wof:name":"Fatima-weltapostolat Der Deutsch-schweiz",
    "wof:placetype":"venue"
},
  "geometry": {"coordinates":[7.5881328583,47.5698661804],"type":"Point"}
}