{
  "type": "Feature",
  "properties": {
    "iso:country":"CH",
    "sg:address":"Brandschenkestrasse 6",
    "sg:city":"Z\u00fcrich",
    "sg:orig_category":"Unternehmensberatung",
    "sg:postcode":"8002",
    "sg:province":"Z\u00fcrich",
    "wof:name":"Stiftung Zur F\u00f6rderung Der Internationalen Darshan-schulen",
    "wof:placetype":"venue"
},
  "geometry": {"coordinates":[8.533706665,47.3698692322],"type":"Point"}
}