{
  "type": "Feature",
  "properties": {
    "iso:country":"CH",
    "sg:address":"Luzernerstrasse 34",
    "sg:city":"Root",
    "sg:orig_category":"Herstellung von Konstruktionsteilen, Fertigbauteilen U Ausbauelementen aus Holz",
    "sg:phone":"+41 41 450 11 45",
    "sg:postcode":"6037",
    "sg:province":"Luzern",
    "wof:name":"Schreinerei J. Kretz Ag",
    "wof:placetype":"venue"
},
  "geometry": {"coordinates":[8.3867893219,47.1120147705],"type":"Point"}
}