{
  "type": "Feature",
  "properties": {
    "iso:country":"CH",
    "sg:address":"Sonnhalde 1",
    "sg:city":"Sarmenstorf",
    "sg:orig_category":"Politische Parteien SVP",
    "sg:phone":"+41 56 667 15 82",
    "sg:postcode":"5614",
    "sg:province":"Aargau",
    "wof:name":"Svp Ortspartei Sarmenstorf",
    "wof:placetype":"venue"
},
  "geometry": {"coordinates":[8.2549848557,47.3090629578],"type":"Point"}
}