{
  "type": "Feature",
  "properties": {
    "iso:country":"CH",
    "sg:address":"Seestrasse 247",
    "sg:city":"Z\u00fcrich",
    "sg:orig_category":"Unclassifiable Establishments",
    "sg:phone":"+41 71 244 75 53",
    "sg:postcode":"8038",
    "sg:province":"Z\u00fcrich",
    "wof:name":"Go+life Ag",
    "wof:placetype":"venue"
},
  "geometry": {"coordinates":[9.3142166138,47.4091873169],"type":"Point"}
}