{
  "type": "Feature",
  "properties": {
    "iso:country":"CH",
    "sg:address":"Ch\u00e4ppelistrasse 10",
    "sg:city":"Jonen",
    "sg:orig_category":"Herstellung von industriellen Prozesssteuerungsanlagen",
    "sg:phone":"+41 56 640 12 44",
    "sg:postcode":"8916",
    "sg:province":"Aargau",
    "wof:name":"Icon Industrial Controls Gmbh",
    "wof:placetype":"venue"
},
  "geometry": {"coordinates":[8.3939771652,47.3013420105],"type":"Point"}
}