{
  "type": "Feature",
  "properties": {
    "iso:country":"CH",
    "sg:address":"De-ternier Ch. G\u00e9rard- 14 1213 Petit-lancy. Postfach",
    "sg:city":"Lancy",
    "sg:orig_category":"Herstellung von sonstigen elektrischen Ausr\u00fcstungen",
    "sg:postcode":"1213",
    "sg:province":"Gen\u00e8ve",
    "wof:name":"Finelec Sa, Succursale De Lancy (gen\u00e8ve) Vente De Mat\u00e9riel \u00e9lectrique Etc",
    "wof:placetype":"venue"
},
  "geometry": {"coordinates":[6.1087851524,46.1953239441],"type":"Point"}
}