{
  "type": "Feature",
  "properties": {
    "iso:country":"CH",
    "sg:address":"Chalet Verzache 3962 Montana. Postfach",
    "sg:city":"Montana",
    "sg:orig_category":"Fachdetailhandel in Verkaufsr\u00e4umen",
    "sg:phone":"+41 19501389",
    "sg:postcode":"3962",
    "wof:name":"Rybi Rybike",
    "wof:placetype":"venue"
},
  "geometry": {"coordinates":[8.7757968903,47.3678207397],"type":"Point"}
}