{
  "type": "Feature",
  "properties": {
    "iso:country":"CH",
    "sg:address":"Florimont Avenue De 1",
    "sg:city":"Montreux",
    "sg:orig_category":"Herstellung von Duft U K\u00f6rperpflegemitteln",
    "sg:phone":"+41 21 966 15 15",
    "sg:postcode":"1820",
    "sg:province":"Vaud",
    "wof:name":"La Colline Cellular Research Laboratories Sa",
    "wof:placetype":"venue"
},
  "geometry": {"coordinates":[6.9191050529,46.4302482605],"type":"Point"}
}