{
  "type": "Feature",
  "properties": {
    "iso:country":"CH",
    "sg:address":"3984",
    "sg:city":"Fiesch",
    "sg:classifiers":[
        {
            "category":"Education",
            "subcategory":"Library",
            "type":"Public Place"
        }
    ],
    "sg:postcode":"3984",
    "sg:province":"Valais",
    "sg:tags":[
        "u",
        "bibliotheken",
        "archive"
    ],
    "wof:name":"Volksbibliothek",
    "wof:placetype":"venue"
},
  "geometry": {"coordinates":[8.06109,46.477242],"type":"Point"}
}