{
  "type": "Feature",
  "properties": {
    "iso:country":"CH",
    "sg:address":"Bolgengasse 3770 Zweisimmen. Postfach 250",
    "sg:city":"Zweisimmen",
    "sg:orig_category":"Vermittlung von Immobilien Verwaltung von Immobilien",
    "sg:phone":"+41 22 704 19 00",
    "sg:postcode":"3770",
    "sg:province":"Bern",
    "wof:name":"Simonin Jean Sa",
    "wof:placetype":"venue"
},
  "geometry": {"coordinates":[6.1681427956,46.194152832],"type":"Point"}
}