{
  "type": "Feature",
  "properties": {
    "iso:country":"CH",
    "sg:address":"8552",
    "sg:city":"Felben-wellhausen",
    "sg:orig_category":"Schulpflegen",
    "sg:phone":"+41 52 765 23 01",
    "sg:postcode":"8552",
    "sg:province":"Thurgau",
    "wof:name":"Schulkommission Der Gemeinde Felben",
    "wof:placetype":"venue"
},
  "geometry": {"coordinates":[8.9425401688,47.5796318054],"type":"Point"}
}