{
  "type": "Feature",
  "properties": {
    "iso:country":"CH",
    "sg:address":"Seeackerstrasse 14",
    "sg:city":"Horn",
    "sg:orig_category":"Herstellung von konfektionierten Textilwaren ohne Bekleidung",
    "sg:phone":"+41 71 845 21 63",
    "sg:postcode":"9326",
    "sg:province":"Thurgau",
    "wof:name":"Huwiler Hans",
    "wof:placetype":"venue"
},
  "geometry": {"coordinates":[9.4580955505,47.4961738586],"type":"Point"}
}