{
  "type": "Feature",
  "properties": {
    "addr:full":"Dorf 16 Uffikon Luzern 6253",
    "addr:housenumber":"16",
    "addr:postcode":"6253",
    "addr:street":"Dorf",
    "iso:country":"CH",
    "sg:address":"Dorf 16",
    "sg:city":"Uffikon",
    "sg:orig_category":"Ausbaugewerbe Verlegen von Fliesen U Platten",
    "sg:phone":"+41 62 756 35 15",
    "sg:postcode":"6253",
    "sg:province":"Luzern",
    "wof:name":"G\u00e4hwiler Thomas Chemin\u00e9ebau + Umbauten",
    "wof:placetype":"venue"
},
  "geometry": {"coordinates":[8.01805,47.212547],"type":"Point"}
}