{
  "type": "Feature",
  "properties": {
    "iso:country":"CH",
    "sg:address":"Stationsstr. 59",
    "sg:city":"N\u00e4nikon",
    "sg:classifiers":[
        {
            "category":"Bakery",
            "type":"Food & Drink"
        }
    ],
    "sg:phone":"+41 4119405397",
    "sg:postcode":"8606",
    "sg:province":"Z\u00fcrich",
    "sg:tags":[
        "cake",
        "product",
        "related",
        "bread"
    ],
    "wof:name":"Pan Gusto Ag",
    "wof:placetype":"venue"
},
  "geometry": {"coordinates":[8.685938,47.368752],"type":"Point"}
}