{
  "type": "Feature",
  "properties": {
    "iso:country":"CH",
    "sg:address":"Bahnhofstrasse 16",
    "sg:city":"Littau",
    "sg:orig_category":"Laboratory Measuring Instruments",
    "sg:phone":"+41 41 250 88 88",
    "sg:postcode":"6014",
    "sg:province":"Luzern",
    "wof:name":"Megatec Ag",
    "wof:placetype":"venue"
},
  "geometry": {"coordinates":[8.2578678131,47.0528793335],"type":"Point"}
}