{
  "type": "Feature",
  "properties": {
    "iso:country":"CH",
    "sg:address":"Wilerstrasse 8",
    "sg:city":"Rorbas",
    "sg:orig_category":"Schnelldruck U Kopierservice",
    "sg:phone":"+41 18652021",
    "sg:postcode":"8427",
    "sg:province":"Z\u00fcrich",
    "wof:name":"Wilhelm Weingast Kopierservice",
    "wof:placetype":"venue"
},
  "geometry": {"coordinates":[8.5705041885,47.5336112976],"type":"Point"}
}