{
  "type": "Feature",
  "properties": {
    "iso:country":"CH",
    "sg:address":"Huebwiesenstrasse 27",
    "sg:city":"Geroldswil",
    "sg:orig_category":"Drogerien",
    "sg:phone":"+41 17481005",
    "sg:postcode":"8954",
    "sg:province":"Z\u00fcrich",
    "wof:name":"Markus Locher Drogerie",
    "wof:placetype":"venue"
},
  "geometry": {"coordinates":[8.4088430405,47.4220428467],"type":"Point"}
}