{
  "type": "Feature",
  "properties": {
    "iso:country":"CH",
    "sg:address":"M\u00fchlehofstrasse 4",
    "sg:city":"Ebikon",
    "sg:orig_category":"Grosshandel mit Milch, Milcherzeugnissen, Eiern, Speise\u00f6len U Nahrungsfetten",
    "sg:phone":"+41 41 440 70 77",
    "sg:postcode":"6030",
    "sg:province":"Luzern",
    "wof:name":"Eier Kandi Gmbh",
    "wof:placetype":"venue"
},
  "geometry": {"coordinates":[8.3374099731,47.0732383728],"type":"Point"}
}