{
  "type": "Feature",
  "properties": {
    "iso:country":"CH",
    "sg:address":"Geissfluhweg 3",
    "sg:city":"Grellingen",
    "sg:orig_category":"Sanit\u00e4r, Heizungs U L\u00fcftungsinstallation",
    "sg:postcode":"4203",
    "sg:province":"Basel-Landschaft",
    "wof:name":"Heizungsinstallationen Markus Bigler",
    "wof:placetype":"venue"
},
  "geometry": {"coordinates":[7.3758120537,47.1797943115],"type":"Point"}
}