{
  "type": "Feature",
  "properties": {
    "iso:country":"CH",
    "sg:address":"Auf Weinbergli 17",
    "sg:city":"Luzern",
    "sg:orig_category":"Arztpraxen",
    "sg:phone":"+41 41 360 31 55",
    "sg:postcode":"6005",
    "sg:province":"Luzern",
    "wof:name":"Dr.med.markus St\u00f6ckli Spezialarzt Fmh",
    "wof:placetype":"venue"
},
  "geometry": {"coordinates":[8.318965,47.039322],"type":"Point"}
}