{
  "type": "Feature",
  "properties": {
    "addr:full":"H\u00e4berlinstrasse 17 Frauenfeld Thurgau 8500",
    "addr:housenumber":"17",
    "addr:postcode":"8500",
    "addr:street":"Haeberlinstrasse",
    "iso:country":"CH",
    "sg:address":"H\u00e4berlinstrasse 17",
    "sg:city":"Frauenfeld",
    "sg:orig_category":"Detailhandel mit Bekleidung",
    "sg:phone":"+41 52 720 31 66",
    "sg:postcode":"8500",
    "sg:province":"Thurgau",
    "wof:name":"Meierhofer Rosa-maria.",
    "wof:placetype":"venue"
},
  "geometry": {"coordinates":[8.884307,47.554466],"type":"Point"}
}