{
  "type": "Feature",
  "properties": {
    "iso:country":"CH",
    "sg:address":"Hauptstrasse 92 9400 Rorschach. Postfach 206",
    "sg:city":"Rorschach",
    "sg:classifiers":[
        {
            "category":"Travel",
            "subcategory":"Hotels & Motels",
            "type":"Entertainment"
        }
    ],
    "sg:postcode":"9401",
    "sg:province":"St. Gallen",
    "sg:tags":[
        "hotels",
        "mit",
        "restaurant"
    ],
    "wof:name":"Walter Quirin",
    "wof:placetype":"venue"
},
  "geometry": {"coordinates":[9.099445343,46.7489891052],"type":"Point"}
}