{
  "type": "Feature",
  "properties": {
    "iso:country":"CH",
    "sg:address":"Hirschengraben 10",
    "sg:city":"Bern",
    "sg:orig_category":"Arztpraxen",
    "sg:phone":"+41 71 223 52 55",
    "sg:postcode":"3011",
    "sg:province":"Bern",
    "wof:name":"Dr.med.hans-georg F\u00fcllemann Spezialarzt Fmh",
    "wof:placetype":"venue"
},
  "geometry": {"coordinates":[9.373674,47.421867],"type":"Point"}
}