{
  "type": "Feature",
  "properties": {
    "iso:country":"CH",
    "sg:address":"Widenmatt 3",
    "sg:city":"Malters",
    "sg:orig_category":"Fahrschulen, Flugschulen",
    "sg:phone":"+41 41 497 20 52",
    "sg:postcode":"6102",
    "sg:province":"Luzern",
    "wof:name":"Ferdy Bucher Autofahrschule",
    "wof:placetype":"venue"
},
  "geometry": {"coordinates":[8.1776571274,47.0343818665],"type":"Point"}
}