{
  "type": "Feature",
  "properties": {
    "iso:country":"CH",
    "sg:address":"Fluhstrasse 30",
    "sg:city":"Jona",
    "sg:orig_category":"Grosshandel mit Baumaterialien Grosshandel mit Holz U Baustoffen",
    "sg:phone":"+41 55 210 09 64",
    "sg:postcode":"8645",
    "sg:province":"St. Gallen",
    "wof:name":"Protap (schweiz) Gmbh",
    "wof:placetype":"venue"
},
  "geometry": {"coordinates":[8.8180732727,47.2379302979],"type":"Point"}
}