{
  "type": "Feature",
  "properties": {
    "iso:country":"CH",
    "sg:address":"Sonnengruss",
    "sg:city":"Entlebuch",
    "sg:orig_category":"Mineralwasser Detailhandel Wein Detailhandel",
    "sg:postcode":"6162",
    "sg:province":"Luzern",
    "wof:name":"M. & St. Monnier & Co Getr\u00e4nkehandel",
    "wof:placetype":"venue"
},
  "geometry": {"coordinates":[7.3063697815,47.1114425659],"type":"Point"}
}