{
  "type": "Feature",
  "properties": {
    "iso:country":"CH",
    "sg:address":"Haldenstrasse 10",
    "sg:city":"Wangs",
    "sg:orig_category":"Elektroinstallation",
    "sg:phone":"+41 79 611 44 00",
    "sg:postcode":"7323",
    "sg:province":"St. Gallen",
    "wof:name":"Fritz Ackermann Elektro-,tv-& Telefoninstall.",
    "wof:placetype":"venue"
},
  "geometry": {"coordinates":[9.4304962158,47.0338516235],"type":"Point"}
}