{
  "type": "Feature",
  "properties": {
    "iso:country":"CH",
    "sg:address":"Stadthausquai 1",
    "sg:city":"Z\u00fcrich",
    "sg:orig_category":"Advokaturb\u00fcros",
    "sg:phone":"+41 61 361 35 84",
    "sg:postcode":"8001",
    "sg:province":"Z\u00fcrich",
    "wof:name":"Von Blarer Vest & Wirz Advokaturb\u00fcro",
    "wof:placetype":"venue"
},
  "geometry": {"coordinates":[7.600915,47.466358],"type":"Point"}
}