{
  "type": "Feature",
  "properties": {
    "iso:country":"CH",
    "sg:address":"Bahnhofstrasse 42",
    "sg:city":"Horw",
    "sg:orig_category":"Arbeitnehmerverb\u00e4nde",
    "sg:phone":"+41 41 348 02 00",
    "sg:postcode":"6048",
    "sg:province":"Luzern",
    "wof:name":"Schweiz.faktoren-verband Sekt.luzern Herrn Heinz Eicher",
    "wof:placetype":"venue"
},
  "geometry": {"coordinates":[8.307373,47.017857],"type":"Point"}
}