{
  "type": "Feature",
  "properties": {
    "iso:country":"CH",
    "sg:address":"Rickenbacherstrasse 17",
    "sg:city":"Ottenbach",
    "sg:orig_category":"Elektroinstallation Herstellung von sonstigen elektrischen Ausr\u00fcstungen",
    "sg:phone":"+41 17626141",
    "sg:postcode":"8913",
    "sg:province":"Z\u00fcrich",
    "wof:name":"Elektro Ackermann Gmbh, Ottenbach",
    "wof:placetype":"venue"
},
  "geometry": {"coordinates":[8.4054956436,47.2770767212],"type":"Point"}
}