{
  "type": "Feature",
  "properties": {
    "iso:country":"CH",
    "sg:address":"1544",
    "sg:city":"Gletterens",
    "sg:classifiers":[
        {
            "category":"Travel",
            "subcategory":"Hotels & Motels",
            "type":"Entertainment"
        }
    ],
    "sg:postcode":"1544",
    "sg:province":"Fribourg",
    "sg:tags":[
        "hotels",
        "mit",
        "restaurant"
    ],
    "wof:name":"Duc Monique.",
    "wof:placetype":"venue"
},
  "geometry": {"coordinates":[6.93708992,46.8953018188],"type":"Point"}
}