{
  "type": "Feature",
  "properties": {
    "iso:country":"CH",
    "sg:address":"Kloosfeldstrasse 10",
    "sg:city":"Rheinfelden",
    "sg:orig_category":"Maler U Glasergewerbe",
    "sg:postcode":"4310",
    "sg:province":"Aargau",
    "wof:name":"K\u00e4ser Armin",
    "wof:placetype":"venue"
},
  "geometry": {"coordinates":[7.7819638252,47.5500526428],"type":"Point"}
}