{
  "type": "Feature",
  "properties": {
    "iso:country":"CH",
    "sg:address":"Z\u00fcrichstrasse 116",
    "sg:city":"Ebmatingen",
    "sg:orig_category":"Fernmeldedienste",
    "sg:phone":"+41 31 839 53 33",
    "sg:postcode":"8123",
    "sg:province":"Z\u00fcrich",
    "wof:name":"Ggaw Antennen Worb Ag",
    "wof:placetype":"venue"
},
  "geometry": {"coordinates":[7.5622019768,46.9284286499],"type":"Point"}
}