{
  "type": "Feature",
  "properties": {
    "iso:country":"CH",
    "sg:address":"Oberdorfstrasse 27-31",
    "sg:city":"W\u00e4denswil",
    "sg:orig_category":"Detailhandel mit Waren verschiedener Art, Hauptrichtung Nahrungsmittel",
    "sg:phone":"+41 71 913 91 20",
    "sg:postcode":"8820",
    "sg:province":"Z\u00fcrich",
    "wof:name":"Migros-markt",
    "wof:placetype":"venue"
},
  "geometry": {"coordinates":[9.0424432755,47.4629745483],"type":"Point"}
}