{
  "type": "Feature",
  "properties": {
    "iso:country":"CH",
    "sg:address":"Albisriederplatz 3 8003 Z\u00fcrich. Postfach",
    "sg:city":"Z\u00fcrich",
    "sg:orig_category":"Drogerien",
    "sg:phone":"+41 14966030",
    "sg:postcode":"8040",
    "sg:province":"Z\u00fcrich",
    "wof:name":"Drogerie Albisriederplatz Ag",
    "wof:placetype":"venue"
},
  "geometry": {"coordinates":[8.5100393295,47.378074646],"type":"Point"}
}