{
  "type": "Feature",
  "properties": {
    "iso:country":"CH",
    "sg:address":"Steinweg 9 4144 Arlesheim. Postfach 542",
    "sg:city":"Arlesheim",
    "sg:orig_category":"Allgemeiner Hoch U Tiefbau Verwaltung von Immobilien",
    "sg:phone":"+41 61 701 10 20",
    "sg:postcode":"4144",
    "sg:province":"Basel-Landschaft",
    "wof:name":"Meury Bau Ag",
    "wof:placetype":"venue"
},
  "geometry": {"coordinates":[7.610079,47.490479],"type":"Point"}
}