{
  "type": "Feature",
  "properties": {
    "iso:country":"CH",
    "sg:address":"Gehrenstrasse 19",
    "sg:city":"Flawil",
    "sg:orig_category":"G\u00fcterbef\u00f6rderung im Strassenverkehr",
    "sg:phone":"+41 71 393 33 24",
    "sg:postcode":"9230",
    "sg:province":"St. Gallen",
    "wof:name":"Sch\u00f6n Transporte",
    "wof:placetype":"venue"
},
  "geometry": {"coordinates":[9.1844921112,47.4089508057],"type":"Point"}
}