{
  "type": "Feature",
  "properties": {
    "iso:country":"CH",
    "sg:address":"Hinterb\u00e4chlistrasse 11 5452 Oberrohrdorf. Postfach",
    "sg:city":"Oberrohrdorf",
    "sg:orig_category":"Sportvereine Sch\u00fctzen",
    "sg:phone":"+41 56 496 19 91",
    "sg:postcode":"5452",
    "sg:province":"Aargau",
    "wof:name":"Feldsch\u00fctzen Oberrohrdorf",
    "wof:placetype":"venue"
},
  "geometry": {"coordinates":[8.31528759,47.4236564636],"type":"Point"}
}