{
  "type": "Feature",
  "properties": {
    "iso:country":"CH",
    "sg:address":"Utoquai 47",
    "sg:city":"Z\u00fcrich",
    "sg:classifiers":[
        {
            "category":"Travel",
            "subcategory":"Hotels & Motels",
            "type":"Entertainment"
        }
    ],
    "sg:phone":"+41 4112544000",
    "sg:postcode":"8008",
    "sg:province":"Z\u00fcrich",
    "sg:tags":[
        "hotels",
        "business",
        "restaurant"
    ],
    "wof:name":"Steigenberger Hotels",
    "wof:placetype":"venue"
},
  "geometry": {"coordinates":[8.547655,47.362278],"type":"Point"}
}