{
  "type": "Feature",
  "properties": {
    "iso:country":"CH",
    "sg:address":"Bahnhofstrasse 75 8001 Z\u00fcrich. Postfach",
    "sg:city":"Z\u00fcrich",
    "sg:orig_category":"Warenh\u00e4user",
    "sg:phone":"+41 12295111",
    "sg:postcode":"8021",
    "sg:province":"Z\u00fcrich",
    "wof:name":"Manor",
    "wof:placetype":"venue"
},
  "geometry": {"coordinates":[8.5385637283,47.3748054504],"type":"Point"}
}