{
  "type": "Feature",
  "properties": {
    "iso:country":"CH",
    "sg:address":"Promenadenstrasse 74 9400 Rorschach. Postfach",
    "sg:city":"Rorschach",
    "sg:orig_category":"Elektrizit\u00e4tsversorgung Wasserversorgung",
    "sg:phone":"+41 71 929 70 46",
    "sg:postcode":"9401",
    "sg:province":"St. Gallen",
    "wof:name":"Technische Betriebe",
    "wof:placetype":"venue"
},
  "geometry": {"coordinates":[-75.5082855225,44.0607643127],"type":"Point"}
}