{
  "type": "Feature",
  "properties": {
    "iso:country":"CH",
    "sg:address":"N\u00e4ppisuelistrasse 12",
    "sg:city":"Wattwil",
    "sg:orig_category":"Detailhandel mit Musikinstrumenten",
    "sg:phone":"+41 71 988 14 46",
    "sg:postcode":"9630",
    "sg:province":"St. Gallen",
    "wof:name":"Helene Waespe Musikhaus",
    "wof:placetype":"venue"
},
  "geometry": {"coordinates":[9.0875654221,47.3008155823],"type":"Point"}
}