{
  "type": "Feature",
  "properties": {
    "iso:country":"CH",
    "sg:address":"Im Schloss",
    "sg:city":"Arbon",
    "sg:orig_category":"Museen",
    "sg:phone":"+41 71 446 10 58",
    "sg:postcode":"9320",
    "sg:province":"Thurgau",
    "wof:name":"Historisches Museum",
    "wof:placetype":"venue"
},
  "geometry": {"coordinates":[9.4365100861,47.5159072876],"type":"Point"}
}