{
  "type": "Feature",
  "properties": {
    "iso:country":"CH",
    "sg:address":"Hinterdorf 7311 Vas\u00f6n",
    "sg:city":"Pf\u00e4fers",
    "sg:orig_category":"Grosshandel mit lebenden Tieren",
    "sg:postcode":"7312",
    "sg:province":"St. Gallen",
    "wof:name":"Viehhandlung Bonifaz K\u00fchne",
    "wof:placetype":"venue"
},
  "geometry": {"coordinates":[9.5004520416,46.9888420105],"type":"Point"}
}