{
  "type": "Feature",
  "properties": {
    "iso:country":"CH",
    "sg:address":"Rue Du Carro 27",
    "sg:city":"St-maurice",
    "sg:orig_category":"Herstellung von Betonerzeugnissen f\u00fcr den Bau",
    "sg:postcode":"1890",
    "sg:province":"Valais",
    "wof:name":"Mds Mahmoud Djafer Sa",
    "wof:placetype":"venue"
},
  "geometry": {"coordinates":[7.0042901039,46.2184410095],"type":"Point"}
}