{
  "type": "Feature",
  "properties": {
    "iso:country":"CH",
    "sg:address":"Egliswilerstrasse 50",
    "sg:city":"Seengen",
    "sg:orig_category":"Malerei Tapeziererei",
    "sg:phone":"+41 62 777 24 00",
    "sg:postcode":"5707",
    "sg:province":"Aargau",
    "wof:name":"Franz Roth Maler-& Tapezierergesch\u00e4ft",
    "wof:placetype":"venue"
},
  "geometry": {"coordinates":[8.2007713318,47.3306770325],"type":"Point"}
}