{
  "type": "Feature",
  "properties": {
    "iso:country":"CH",
    "sg:address":"Br\u00fcggstrasse 40 2500 Biel/bienne. Postfach",
    "sg:city":"Biel/bienne",
    "sg:orig_category":"Instandhaltung U Reparatur von Automobilen",
    "sg:postcode":"2503",
    "sg:province":"Bern",
    "wof:name":"Madretsch Garage Eichenberger Rolf",
    "wof:placetype":"venue"
},
  "geometry": {"coordinates":[7.2531719208,47.1305656433],"type":"Point"}
}