{
  "type": "Feature",
  "properties": {
    "iso:country":"CH",
    "sg:address":"Salmsacherstr. 9",
    "sg:city":"Romanshorn",
    "sg:classifiers":[
        {
            "category":"Utilities",
            "subcategory":"Electric",
            "type":"Services"
        }
    ],
    "sg:phone":"+41 71 466 81 11",
    "sg:postcode":"8590",
    "sg:province":"Thurgau",
    "sg:tags":[
        "electricity",
        "electronic",
        "electrical",
        "equipment"
    ],
    "wof:name":"Fatzer Ag Drahtseilfabrik",
    "wof:placetype":"venue"
},
  "geometry": {"coordinates":[9.3734836578,47.5640640259],"type":"Point"}
}