{
  "type": "Feature",
  "properties": {
    "iso:country":"CH",
    "sg:address":"Lehenmattstrasse 144 4052 Basel. Postfach",
    "sg:city":"Basel",
    "sg:orig_category":"Maler U Glasergewerbe",
    "sg:postcode":"4052",
    "sg:province":"Basel-Stadt",
    "wof:name":"Jan Posva",
    "wof:placetype":"venue"
},
  "geometry": {"coordinates":[7.6198248863,47.5512275696],"type":"Point"}
}