{
  "type": "Feature",
  "properties": {
    "iso:country":"CH",
    "sg:address":"Rue Du Liseron 9",
    "sg:city":"Lausanne",
    "sg:orig_category":"Mechanische Werkst\u00e4tten",
    "sg:phone":"+41 21 616 07 51",
    "sg:postcode":"1006",
    "sg:province":"Vaud",
    "wof:name":"Gilbert Tinembart Atelier M\u00e9canique",
    "wof:placetype":"venue"
},
  "geometry": {"coordinates":[6.6260461807,46.5083618164],"type":"Point"}
}