{
  "type": "Feature",
  "properties": {
    "iso:country":"CH",
    "sg:address":"Tesserete Via 42",
    "sg:city":"Lugano",
    "sg:orig_category":"Vermietung U Verpachtung von eigenen Immobilien",
    "sg:postcode":"6900",
    "sg:province":"Ticino",
    "wof:name":"Antinea Sa",
    "wof:placetype":"venue"
},
  "geometry": {"coordinates":[8.9510536194,46.0152320862],"type":"Point"}
}