{
  "type": "Feature",
  "properties": {
    "iso:country":"CH",
    "sg:address":"Chemin De La Venoge 7",
    "sg:city":"St-sulpice",
    "sg:classifiers":[
        {
            "category":"Building & Trades",
            "subcategory":"Equipment Rental",
            "type":"Services"
        }
    ],
    "sg:phone":"+41 21 694 11 11",
    "sg:postcode":"1025",
    "sg:province":"Vaud",
    "sg:tags":[
        "brazing"
    ],
    "wof:name":"Castolin Eutectic International S.a",
    "wof:placetype":"venue"
},
  "geometry": {"coordinates":[6.54302,46.51239],"type":"Point"}
}