{
  "type": "Feature",
  "properties": {
    "iso:country":"CH",
    "sg:address":"G\u00fcmligentalstr. 83a",
    "sg:city":"Ostermundigen",
    "sg:orig_category":"Herstellung von Konstruktionsteilen, Fertigbauteilen U Ausbauelementen aus Holz",
    "sg:phone":"+41 31 931 37 51",
    "sg:postcode":"3072",
    "sg:province":"Bern",
    "wof:name":"Hartmann Holzbau Ag",
    "wof:placetype":"venue"
},
  "geometry": {"coordinates":[7.5109839439,46.9534759521],"type":"Point"}
}