{
  "type": "Feature",
  "properties": {
    "iso:country":"CH",
    "sg:address":"Rue Des Pervenches 2",
    "sg:city":"Del\u00e9mont",
    "sg:orig_category":"Detailhandel mit Zeitungen U Zeitschriften Kioske",
    "sg:phone":"+41 32 422 58 03",
    "sg:postcode":"2800",
    "sg:province":"Jura",
    "wof:name":"Kiosque Du Righi Beuret St\u00e9phanie",
    "wof:placetype":"venue"
},
  "geometry": {"coordinates":[7.3567399979,47.3635292053],"type":"Point"}
}