{
  "type": "Feature",
  "properties": {
    "iso:country":"CH",
    "sg:address":"Oberstrasse 149",
    "sg:city":"St.gallen",
    "sg:orig_category":"Architektur U Ingenieurb\u00fcros",
    "sg:phone":"+41 71 274 00 20",
    "sg:postcode":"9000",
    "sg:province":"St. Gallen",
    "wof:name":"B\u00e4nziger + K\u00f6ppel + Partner Ingenieure + Planer Sia Usic Diplomingenieure Eth",
    "wof:placetype":"venue"
},
  "geometry": {"coordinates":[9.35662,47.414032],"type":"Point"}
}