{
  "type": "Feature",
  "properties": {
    "iso:country":"CH",
    "sg:address":"Place Dufour 1 1110 Morges. Postfach",
    "sg:city":"Morges",
    "sg:orig_category":"Interessenvertretungen",
    "sg:phone":"+41 31 931 11 66",
    "sg:postcode":"1110",
    "sg:province":"Vaud",
    "wof:name":"Privat-stiftung Sp\u00e4th-berger G. Und H.",
    "wof:placetype":"venue"
},
  "geometry": {"coordinates":[7.515226841,46.9583206177],"type":"Point"}
}