{
  "type": "Feature",
  "properties": {
    "iso:country":"CH",
    "sg:address":"Kehlstrasse 39",
    "sg:city":"Baden",
    "sg:orig_category":"Fussboden, Fliesen U Plattenlegerei, Tapeziererei Verlegen von Fliesen U Platten",
    "sg:phone":"+41 56 222 60 47",
    "sg:postcode":"5400",
    "sg:province":"Aargau",
    "wof:name":"Zehnder & Poletti Ag, Wand Und Bodenbel\u00e4ge",
    "wof:placetype":"venue"
},
  "geometry": {"coordinates":[8.2890443802,47.465713501],"type":"Point"}
}