{
  "type": "Feature",
  "properties": {
    "iso:country":"CH",
    "sg:address":"R\u00fcmlangstrasse 73",
    "sg:city":"Z\u00fcrich",
    "sg:orig_category":"Instandhaltung U Reparatur von Automobilen",
    "sg:phone":"+41 13021314",
    "sg:postcode":"8052",
    "sg:province":"Z\u00fcrich",
    "wof:name":"Garage Horvat",
    "wof:placetype":"venue"
},
  "geometry": {"coordinates":[8.5407810211,47.4299621582],"type":"Point"}
}