{
  "type": "Feature",
  "properties": {
    "iso:country":"CH",
    "sg:address":"St. Galler Strasse 68",
    "sg:city":"Bernhardzell",
    "sg:orig_category":"Autospenglereien",
    "sg:phone":"+41 81 404 14 49",
    "sg:postcode":"9304",
    "sg:province":"St. Gallen",
    "wof:name":"Ren\u00e9 Gruber Autospenglerei & Carrosserie",
    "wof:placetype":"venue"
},
  "geometry": {"coordinates":[9.672824,46.687962],"type":"Point"}
}