{
  "type": "Feature",
  "properties": {
    "iso:country":"CH",
    "sg:address":"Forchstrasse 167 8132 Hinteregg. Postfach",
    "sg:city":"Hinteregg",
    "sg:orig_category":"Herstellung von Kunststoffwaren",
    "sg:phone":"+41 17617951",
    "sg:postcode":"8132",
    "sg:province":"Z\u00fcrich",
    "wof:name":"Printoplast Ag",
    "wof:placetype":"venue"
},
  "geometry": {"coordinates":[8.445941925,47.2697944641],"type":"Point"}
}