{
  "type": "Feature",
  "properties": {
    "iso:country":"CH",
    "sg:address":"Josefstrasse 25 8005 Z\u00fcrich. Postfach",
    "sg:city":"Z\u00fcrich",
    "sg:orig_category":"RESTAURANTS: TEA-ROOMS",
    "sg:postcode":"8001",
    "sg:province":"Z\u00fcrich",
    "wof:name":"Pussycat Bar Club, H. Flesch",
    "wof:placetype":"venue"
},
  "geometry": {"coordinates":[8.5335054398,47.3809394836],"type":"Point"}
}