{
  "type": "Feature",
  "properties": {
    "iso:country":"CH",
    "sg:address":"G\u00fcterstrasse 93 4053 Basel. Postfach",
    "sg:city":"Basel",
    "sg:orig_category":"Einzelhandel mit Automobilen Herstellung von Bereifungen",
    "sg:phone":"+41 61 283 82 08",
    "sg:postcode":"4053",
    "sg:province":"Basel-Stadt",
    "wof:name":"Kmh Pneudiscount Gmbh Pneus, Autos, Zubeh\u00f6r; Handel Usw",
    "wof:placetype":"venue"
},
  "geometry": {"coordinates":[7.5857901573,47.5463294983],"type":"Point"}
}