{
  "type": "Feature",
  "properties": {
    "iso:country":"CH",
    "sg:address":"Vordere Vorstadt 19",
    "sg:city":"Aarau",
    "sg:classifiers":[
        {
            "category":"Professional",
            "subcategory":"Employment Agencies",
            "type":"Services"
        }
    ],
    "sg:phone":"+41 62 824 92 00",
    "sg:postcode":"5000",
    "sg:province":"Aargau",
    "sg:tags":[
        "personal",
        "u",
        "stellenvermittlung"
    ],
    "wof:name":"K & W Ag F\u00fcr Tempor\u00e4r-& Dauerstellen",
    "wof:placetype":"venue"
},
  "geometry": {"coordinates":[8.0451335907,47.3909683228],"type":"Point"}
}