{
  "type": "Feature",
  "properties": {
    "addr:full":"Aarm\u00fchlestrasse 29 Interlaken Bern 3800",
    "addr:housenumber":"29",
    "addr:postcode":"3800",
    "addr:street":"Aarmuehlestrasse",
    "iso:country":"CH",
    "sg:address":"Aarm\u00fchlestrasse 29",
    "sg:city":"Interlaken",
    "sg:orig_category":"Arztpraxen",
    "sg:phone":"+41 33 822 26 77",
    "sg:postcode":"3800",
    "sg:province":"Bern",
    "wof:name":"Dr.med.manfred Harder Spezialarzt Fmh",
    "wof:placetype":"venue"
},
  "geometry": {"coordinates":[7.85259,46.683067],"type":"Point"}
}