{
  "type": "Feature",
  "properties": {
    "iso:country":"CH",
    "sg:address":"Rue Charles-sch\u00e4ublin 2",
    "sg:city":"Malleray-b\u00e9vilard",
    "sg:classifiers":[
        {
            "category":"Utilities",
            "subcategory":"Water",
            "type":"Services"
        }
    ],
    "sg:phone":"+41 32 491 65 30",
    "sg:postcode":"2735",
    "sg:province":"Bern",
    "sg:tags":[
        "industrial",
        "computer"
    ],
    "wof:name":"Mw Programmation S.a.",
    "wof:placetype":"venue"
},
  "geometry": {"coordinates":[7.2982158661,47.2552528381],"type":"Point"}
}