{
  "type": "Feature",
  "properties": {
    "iso:country":"CH",
    "sg:address":"Chemin Rieu 6",
    "sg:city":"Gen\u00e8ve",
    "sg:orig_category":"Grosshandel mit Eisenwaren sowie Installationsbedarf f\u00fcr Gas, Wasser U Heizung Grosshandel mit sonst",
    "sg:phone":"+41 19436010",
    "sg:postcode":"1208",
    "sg:province":"Gen\u00e8ve",
    "wof:name":"Bettosini, Uster",
    "wof:placetype":"venue"
},
  "geometry": {"coordinates":[8.7256355286,47.3461036682],"type":"Point"}
}