{
  "type": "Feature",
  "properties": {
    "iso:country":"CH",
    "sg:address":"R\u00f6sslimatt 4",
    "sg:city":"Neuenkirch",
    "sg:orig_category":"Fachdetailhandel in Verkaufsr\u00e4umen",
    "sg:postcode":"6206",
    "sg:province":"Luzern",
    "wof:name":"Pos Systems Consulting A. Michel",
    "wof:placetype":"venue"
},
  "geometry": {"coordinates":[8.1969347,47.10597229],"type":"Point"}
}