{
  "type": "Feature",
  "properties": {
    "iso:country":"CH",
    "sg:address":"Felseggweg 3b 9247 Henau. Postfach",
    "sg:city":"Henau",
    "sg:orig_category":"G\u00fcterbef\u00f6rderung im Strassenverkehr",
    "sg:phone":"+41 71 952 66 88",
    "sg:postcode":"9247",
    "sg:province":"St. Gallen",
    "wof:name":"Brunner Robert Transporte",
    "wof:placetype":"venue"
},
  "geometry": {"coordinates":[9.1197834015,47.4610061646],"type":"Point"}
}