{
  "type": "Feature",
  "properties": {
    "iso:country":"CH",
    "sg:address":"Hasenbergstrasse 54a",
    "sg:city":"Bellikon",
    "sg:orig_category":"Grosshandel mit Sportartikeln",
    "sg:phone":"+41 19333040",
    "sg:postcode":"5454",
    "sg:province":"Aargau",
    "wof:name":"Ffs Fitness Ag Sport, Freizeit, Tourismus, Vertretungen",
    "wof:placetype":"venue"
},
  "geometry": {"coordinates":[8.7938747406,47.3109474182],"type":"Point"}
}