{
  "type": "Feature",
  "properties": {
    "iso:country":"CH",
    "sg:address":"Route Du Rawyl 5b",
    "sg:city":"Sierre",
    "sg:orig_category":"Detailhandel mit Radio U Fernsehger\u00e4ten Detailhandel mit elektrischen Haushalts-,Radio U Fernsehger\u00e4",
    "sg:phone":"+41 27 455 22 48",
    "sg:postcode":"3960",
    "sg:province":"Valais",
    "wof:name":"Beysard Jean.",
    "wof:placetype":"venue"
},
  "geometry": {"coordinates":[7.5328240395,46.2959899902],"type":"Point"}
}