{
  "type": "Feature",
  "properties": {
    "iso:country":"CH",
    "sg:address":"B\u00f6schachstrasse 45",
    "sg:city":"Widnau",
    "sg:orig_category":"Sportvereine Turnen",
    "sg:phone":"+41 71 722 40 85",
    "sg:postcode":"9443",
    "sg:province":"St. Gallen",
    "wof:name":"Turnverein Etv Widnau",
    "wof:placetype":"venue"
},
  "geometry": {"coordinates":[9.6469335556,47.4044265747],"type":"Point"}
}