{
  "type": "Feature",
  "properties": {
    "iso:country":"CH",
    "sg:address":"Steinenbr\u00fccke",
    "sg:city":"Kaltbrunn",
    "sg:orig_category":"Verwertung von Milch",
    "sg:postcode":"8722",
    "sg:province":"St. Gallen",
    "wof:name":"K\u00e4sereigenossenschaft Steinenbr\u00fccke",
    "wof:placetype":"venue"
},
  "geometry": {"coordinates":[9.0297966003,47.2046508789],"type":"Point"}
}