{
  "type": "Feature",
  "properties": {
    "iso:country":"CH",
    "sg:address":"Zuchwilstrasse 16",
    "sg:city":"Luterbach",
    "sg:orig_category":"Datenverarbeitungsdienste Softwareentwicklung U beratung",
    "sg:phone":"+41 32 682 44 31",
    "sg:postcode":"4542",
    "sg:province":"Solothurn",
    "wof:name":"Zoph Engineering Zoller",
    "wof:placetype":"venue"
},
  "geometry": {"coordinates":[7.578539,47.215843],"type":"Point"}
}