{
  "type": "Feature",
  "properties": {
    "iso:country":"CH",
    "sg:address":"Effingerstrasse 6a 3011 Bern. Postfach",
    "sg:city":"Bern",
    "sg:orig_category":"Erwachsenenbildung U Unterricht",
    "sg:postcode":"3005",
    "sg:province":"Bern",
    "wof:name":"The English Language Sandwich, Novak Eva. Englischkurse, Unterricht In Anderen Sprachen.",
    "wof:placetype":"venue"
},
  "geometry": {"coordinates":[7.4365501404,46.9459457397],"type":"Point"}
}