{
  "type": "Feature",
  "properties": {
    "iso:country":"CH",
    "sg:address":"Hauptstr. 28.",
    "sg:city":"R\u00fcttenen",
    "sg:orig_category":"Herstellung von Elektromotoren, Generatoren U Transformatoren",
    "sg:phone":"+41 32 623 38 78",
    "sg:postcode":"4522",
    "sg:province":"Solothurn",
    "wof:name":"Zaugg Theodor.",
    "wof:placetype":"venue"
},
  "geometry": {"coordinates":[7.5293579102,47.2297515869],"type":"Point"}
}