{
  "type": "Feature",
  "properties": {
    "iso:country":"CH",
    "sg:address":"Becklimattweg 6",
    "sg:city":"Strengelbach",
    "sg:orig_category":"Hardwareberatung",
    "sg:phone":"+41 62 751 41 67",
    "sg:postcode":"4802",
    "sg:province":"Aargau",
    "wof:name":"Solutions Jardim Idalina",
    "wof:placetype":"venue"
},
  "geometry": {"coordinates":[7.9261989594,47.2855377197],"type":"Point"}
}