{
  "type": "Feature",
  "properties": {
    "iso:country":"CH",
    "sg:address":"Contrada Maggiore 6",
    "sg:city":"Ascona",
    "sg:classifiers":[
        {
            "category":"Restaurant",
            "type":"Food & Drink"
        }
    ],
    "sg:phone":"+41 91 791 38 96",
    "sg:postcode":"6612",
    "sg:province":"Ticino",
    "wof:name":"Hosteria S.pietro",
    "wof:placetype":"venue"
},
  "geometry": {"coordinates":[8.7675008774,46.1553840637],"type":"Point"}
}