{
  "type": "Feature",
  "properties": {
    "iso:country":"CH",
    "sg:address":"Rue De La Plaine 12 1400 Yverdon-les-bains. Postfach",
    "sg:city":"Yverdon",
    "sg:orig_category":"Versicherungen Generalagenturen",
    "sg:phone":"+41 79 206 40 37",
    "sg:postcode":"1401",
    "sg:province":"Vaud",
    "wof:name":"St\u00e9 D'assur. Mobili\u00e8re Suisse Agence G\u00e9n\u00e9rale",
    "wof:placetype":"venue"
},
  "geometry": {"coordinates":[6.6429262161,46.7774848938],"type":"Point"}
}