{
  "type": "Feature",
  "properties": {
    "iso:country":"CH",
    "sg:address":"Steinentorstrasse 13 4051 Basel. Postfach",
    "sg:city":"Basel",
    "sg:classifiers":[
        {
            "category":"Communications",
            "subcategory":"Radio Station",
            "type":"Services"
        }
    ],
    "sg:phone":"+41 61 467 85 55",
    "sg:postcode":"4051",
    "sg:province":"Basel-Stadt",
    "sg:tags":[
        "fernsehanstalten",
        "u"
    ],
    "wof:name":"Emh Editores Medicorum Helveticorum Ag Fmh/schwabe",
    "wof:placetype":"venue"
},
  "geometry": {"coordinates":[7.5895547867,47.5516624451],"type":"Point"}
}