{
  "type": "Feature",
  "properties": {
    "iso:country":"CH",
    "sg:address":"Dorfgasse 37",
    "sg:city":"M\u00e4nnedorf",
    "sg:orig_category":"Sonstige Institutionen des Sozialwesens ohne Beherbergung",
    "sg:phone":"+41 19215912",
    "sg:postcode":"8708",
    "sg:province":"Z\u00fcrich",
    "wof:name":"M\u00fctterberatung St\u00e4fa Uerikon Hombrechtikon Feldbach Oetwil",
    "wof:placetype":"venue"
},
  "geometry": {"coordinates":[8.6903858185,47.2532196045],"type":"Point"}
}