{
  "type": "Feature",
  "properties": {
    "iso:country":"CH",
    "sg:address":"Grabenstrasse 2",
    "sg:city":"Neunkirch",
    "sg:orig_category":"Detailhandel mit Waren verschiedener Art, Hauptrichtung Nahrungsmittel",
    "sg:phone":"+41 52 681 39 87",
    "sg:postcode":"8213",
    "sg:province":"Schaffhausen",
    "wof:name":"Landw. Genossenschaft Neunkirch",
    "wof:placetype":"venue"
},
  "geometry": {"coordinates":[8.4996910095,47.689540863],"type":"Point"}
}