{
  "type": "Feature",
  "properties": {
    "iso:country":"CH",
    "sg:address":"Carl Spitteler-strasse 2",
    "sg:city":"Z\u00fcrich",
    "sg:orig_category":"Detailhandel mit Radio U Fernsehger\u00e4ten",
    "sg:phone":"+41 81 911 33 77",
    "sg:postcode":"8053",
    "sg:province":"Z\u00fcrich",
    "wof:name":"Schneider & Capaul Ag Audio-telecom-video",
    "wof:placetype":"venue"
},
  "geometry": {"coordinates":[9.2883176804,46.8262405396],"type":"Point"}
}