{
  "type": "Feature",
  "properties": {
    "iso:country":"CH",
    "sg:address":"1287 Laconnex Case Postale 2",
    "sg:city":"Laconnex",
    "sg:orig_category":"Sportvereine Ballsport Fussball",
    "sg:phone":"+41 22 757 29 84",
    "sg:postcode":"1287",
    "sg:province":"Gen\u00e8ve",
    "wof:name":"Fc Etolie-laconnex",
    "wof:placetype":"venue"
},
  "geometry": {"coordinates":[6.034840107,46.1592712402],"type":"Point"}
}