{
  "type": "Feature",
  "properties": {
    "iso:country":"CH",
    "sg:address":"Oey 3792 Saanen. Postfach",
    "sg:city":"Saanen",
    "sg:orig_category":"Chemische Reinigung W\u00e4schereien",
    "sg:phone":"+41 33 744 37 54",
    "sg:postcode":"3792",
    "sg:province":"Bern",
    "wof:name":"Renate Mayor Chem.reinigung Waschsalon",
    "wof:placetype":"venue"
},
  "geometry": {"coordinates":[7.25744,46.489464],"type":"Point"}
}