{
  "type": "Feature",
  "properties": {
    "iso:country":"CH",
    "sg:address":"Waserstrasse 53",
    "sg:city":"Z\u00fcrich",
    "sg:orig_category":"Interessenvertretungen",
    "sg:postcode":"8053",
    "sg:province":"Z\u00fcrich",
    "wof:name":"Von Hevesy-stiftung Georg F\u00fcr Nuklearmedizin Nuklearmedizin Usw; Erfahrungsaustausch",
    "wof:placetype":"venue"
},
  "geometry": {"coordinates":[8.5782270432,47.3585968018],"type":"Point"}
}