{
  "type": "Feature",
  "properties": {
    "addr:full":"Avenue Du Casino 36 Montreux Vaud 1820",
    "addr:housenumber":"36",
    "addr:postcode":"1820",
    "addr:street":"Avenue Du Casino",
    "iso:country":"CH",
    "sg:address":"Avenue Du Casino 36",
    "sg:city":"Montreux",
    "sg:orig_category":"Arztpraxen",
    "sg:phone":"+41 21 963 32 23",
    "sg:postcode":"1820",
    "sg:province":"Vaud",
    "wof:name":"Dr M\u00e9d. Robert Cougn M\u00e9decin G\u00e9n\u00e9raliste Fmh",
    "wof:placetype":"venue"
},
  "geometry": {"coordinates":[6.911692,46.430565],"type":"Point"}
}