{
  "type": "Feature",
  "properties": {
    "iso:country":"CH",
    "sg:address":"Avry-centre",
    "sg:city":"Avry-sur-matran",
    "sg:orig_category":"Detailhandel mit Beleuchtungs U Haushaltsgegenst\u00e4nden Detailhandel mit Geschenkartikeln U Souvenirs",
    "sg:phone":"+41 26 470 15 76",
    "sg:postcode":"1754",
    "sg:province":"Fribourg",
    "wof:name":"Bregger Sa Porcelaine Boutique Cadeaux",
    "wof:placetype":"venue"
},
  "geometry": {"coordinates":[7.072196,46.788326],"type":"Point"}
}