{
  "type": "Feature",
  "properties": {
    "iso:country":"CH",
    "sg:address":"Kirchstrasse 3",
    "sg:city":"Duggingen",
    "sg:orig_category":"Bauschreinerei Herstellung von Konstruktionsteilen, Fertigbauteilen U Ausbauelementen aus Holz",
    "sg:phone":"+41 61 751 20 30",
    "sg:postcode":"4202",
    "sg:province":"Basel-Landschaft",
    "wof:name":"Hofner Ag Bau-& M\u00f6belschreinerei",
    "wof:placetype":"venue"
},
  "geometry": {"coordinates":[7.605563,47.45274],"type":"Point"}
}