{
  "type": "Feature",
  "properties": {
    "iso:country":"CH",
    "sg:address":"Via Sasselli",
    "sg:city":"Agno",
    "sg:orig_category":"Bauschreinerei",
    "sg:phone":"+41 91 605 11 40",
    "sg:postcode":"6982",
    "sg:province":"Ticino",
    "wof:name":"Erwin Trippel Falegnameria",
    "wof:placetype":"venue"
},
  "geometry": {"coordinates":[8.898687,45.997013],"type":"Point"}
}