{
  "type": "Feature",
  "properties": {
    "iso:country":"CH",
    "sg:address":"Bernstrasse 27",
    "sg:city":"Moosseedorf",
    "sg:orig_category":"Berufliche Weiterbildung, Erwachsenenbildung",
    "sg:phone":"+41 31 859 51 06",
    "sg:postcode":"3302",
    "sg:province":"Bern",
    "wof:name":"Marianne Frauchiger Maschinenschreibschule",
    "wof:placetype":"venue"
},
  "geometry": {"coordinates":[7.478493,47.01503],"type":"Point"}
}