{
  "type": "Feature",
  "properties": {
    "iso:country":"CH",
    "sg:address":"Pfandersmatt",
    "sg:city":"Burgistein",
    "sg:orig_category":"Detailhandel mit Getr\u00e4nken Detailhandel mit Waren verschiedener Art, Hauptrichtung Nahrungsmittel",
    "sg:phone":"+41 33 356 12 08",
    "sg:postcode":"3664",
    "sg:province":"Bern",
    "wof:name":"Hans Probst Lebensmittel & Getr\u00e4nke",
    "wof:placetype":"venue"
},
  "geometry": {"coordinates":[7.5205559731,46.7881660461],"type":"Point"}
}