{
  "type": "Feature",
  "properties": {
    "iso:country":"CH",
    "sg:address":"Altgraben 21",
    "sg:city":"H\u00e4rkingen",
    "sg:orig_category":"Herstellung von Automobilen",
    "sg:phone":"+41 62 398 46 40",
    "sg:postcode":"4624",
    "sg:province":"Solothurn",
    "wof:name":"M\u00fcller Nutzfahrzeuge Ag",
    "wof:placetype":"venue"
},
  "geometry": {"coordinates":[7.8119931221,47.3162574768],"type":"Point"}
}