{
  "type": "Feature",
  "properties": {
    "iso:country":"CH",
    "sg:address":"Parkstrasse 18",
    "sg:city":"Schaffhausen",
    "sg:orig_category":"Vermietung U Verpachtung von eigenen Immobilien",
    "sg:phone":"+41 33 736 33 33",
    "sg:postcode":"8200",
    "sg:province":"Schaffhausen",
    "wof:name":"Schl\u00e4ppi Hansueli Ag",
    "wof:placetype":"venue"
},
  "geometry": {"coordinates":[9.0765180588,47.4424552917],"type":"Point"}
}