{
  "type": "Feature",
  "properties": {
    "iso:country":"CH",
    "sg:address":"S\u00fcristrasse 22",
    "sg:city":"Neuenegg",
    "sg:classifiers":[
        {
            "category":"Restaurant",
            "type":"Food & Drink"
        }
    ],
    "sg:phone":"+41 31 741 01 61",
    "sg:postcode":"3176",
    "sg:province":"Bern",
    "wof:name":"Restaurant Z. Denkmal",
    "wof:placetype":"venue"
},
  "geometry": {"coordinates":[7.2806200981,46.909538269],"type":"Point"}
}