{
  "type": "Feature",
  "properties": {
    "addr:full":"R\u00f6telstrasse 122 Z\u00fcrich Z\u00fcrich 8057",
    "addr:housenumber":"122",
    "addr:postcode":"8057",
    "addr:street":"Roetelstrasse",
    "iso:country":"CH",
    "sg:address":"R\u00f6telstrasse 122",
    "sg:city":"Z\u00fcrich",
    "sg:orig_category":"Detailhandel mit Computern U Software Softwareentwicklung U beratung",
    "sg:phone":"+41 13611205",
    "sg:postcode":"8057",
    "sg:province":"Z\u00fcrich",
    "wof:name":"Computer - Support Surina Roberto",
    "wof:placetype":"venue"
},
  "geometry": {"coordinates":[8.532278,47.398888],"type":"Point"}
}