{
  "type": "Feature",
  "properties": {
    "iso:country":"CH",
    "sg:address":"Viale Bartolomeo Papio 8",
    "sg:city":"Ascona",
    "sg:orig_category":"Capacitors For Measurement Technique And Control Engineering",
    "sg:phone":"+41 91 785 11 50",
    "sg:postcode":"6612",
    "sg:province":"Ticino",
    "wof:name":"Camatec Ag",
    "wof:placetype":"venue"
},
  "geometry": {"coordinates":[8.770425,46.155872],"type":"Point"}
}