{
  "type": "Feature",
  "properties": {
    "iso:country":"CH",
    "sg:address":"Boulevard Carl-vogt 102",
    "sg:city":"Gen\u00e8ve",
    "sg:classifiers":[
        {
            "category":"Education",
            "subcategory":"Library",
            "type":"Public Place"
        }
    ],
    "sg:phone":"+41 22 705 96 36",
    "sg:postcode":"1205",
    "sg:province":"Gen\u00e8ve",
    "sg:tags":[
        "u",
        "bibliotheken",
        "archive"
    ],
    "wof:name":"Facult\u00e9 De Psychol.& Sciences De L'education,biblioth\u00e8que",
    "wof:placetype":"venue"
},
  "geometry": {"coordinates":[6.138386,46.175793],"type":"Point"}
}