{
  "type": "Feature",
  "properties": {
    "iso:country":"CH",
    "sg:address":"Levant Chemin Du",
    "sg:city":"Froideville",
    "sg:orig_category":"Saunas, Solarien, Fitnesszentren U \u00e4hnliches",
    "sg:phone":"+41 21 881 38 71",
    "sg:postcode":"1055",
    "sg:province":"Vaud",
    "wof:name":"Self-solarium Yvonne K\u00f6nig Sa",
    "wof:placetype":"venue"
},
  "geometry": {"coordinates":[6.6880102158,46.5993614197],"type":"Point"}
}