{
  "type": "Feature",
  "properties": {
    "iso:country":"CH",
    "sg:address":"Bahnhofstrasse 11 Feldbach 8634 Hombrechtikon. Postfach",
    "sg:city":"Feldbach",
    "sg:orig_category":"Herstellung von sonstigen landwirtschaftlichen Maschinen",
    "sg:postcode":"8714",
    "sg:province":"Z\u00fcrich",
    "wof:name":"Bh-agra-tech Heiniger B.",
    "wof:placetype":"venue"
},
  "geometry": {"coordinates":[8.7669401169,47.2505340576],"type":"Point"}
}