{
  "type": "Feature",
  "properties": {
    "iso:country":"CH",
    "sg:address":"Dorfstrasse",
    "sg:city":"Grabs",
    "sg:orig_category":"Grosshandel mit Nahrungsmitteln, Getr\u00e4nken U Tabakwaren ohne ausgepr\u00e4gten Schwerpunkt",
    "sg:phone":"+41 79 659 06 42",
    "sg:postcode":"9472",
    "sg:province":"St. Gallen",
    "wof:name":"Vetsch Kaspar.",
    "wof:placetype":"venue"
},
  "geometry": {"coordinates":[9.4409151077,47.1816482544],"type":"Point"}
}