{
  "type": "Feature",
  "properties": {
    "iso:country":"CH",
    "sg:address":"Place De La Croix-blanche 1",
    "sg:city":"Bercher",
    "sg:classifiers":[
        {
            "category":"Restaurant",
            "type":"Food & Drink"
        }
    ],
    "sg:phone":"+41 21 887 71 51",
    "sg:postcode":"1038",
    "sg:province":"Vaud",
    "wof:name":"Caf\u00e9 De La Croix-blanche",
    "wof:placetype":"venue"
},
  "geometry": {"coordinates":[6.7115278244,46.6920204163],"type":"Point"}
}