{
  "type": "Feature",
  "properties": {
    "iso:country":"CH",
    "sg:address":"Landstrasse 148",
    "sg:city":"Klosters",
    "sg:orig_category":"Detailhandel mit Brot, Back U S\u00fcsswaren",
    "sg:phone":"+41 81 413 11 96",
    "sg:postcode":"7250",
    "sg:province":"Graubunden",
    "wof:name":"Charly's B\u00e4ckerei-conditorei Ag",
    "wof:placetype":"venue"
},
  "geometry": {"coordinates":[9.81855,46.79068],"type":"Point"}
}