{
  "type": "Feature",
  "properties": {
    "iso:country":"CH",
    "sg:address":"Stampfenbachstrasse 42",
    "sg:city":"Z\u00fcrich",
    "sg:orig_category":"Advokaturb\u00fcros",
    "sg:phone":"+41 13505690",
    "sg:postcode":"8006",
    "sg:province":"Z\u00fcrich",
    "wof:name":"Ren\u00e9 W. Schleifer Rechtsanwalt",
    "wof:placetype":"venue"
},
  "geometry": {"coordinates":[8.542995,47.380371],"type":"Point"}
}