{
  "type": "Feature",
  "properties": {
    "iso:country":"CH",
    "sg:address":"Rue Centrale 1",
    "sg:city":"Morges",
    "sg:orig_category":"Detailhandel mit Zeitungen U Zeitschriften Kioske",
    "sg:phone":"+41 21 801 71 03",
    "sg:postcode":"1110",
    "sg:province":"Vaud",
    "wof:name":"Paquier & Cie Kiosque",
    "wof:placetype":"venue"
},
  "geometry": {"coordinates":[6.4987897873,46.5092048645],"type":"Point"}
}