{
  "type": "Feature",
  "properties": {
    "iso:country":"CH",
    "sg:address":"Dorfstrasse 7",
    "sg:city":"Linden",
    "sg:orig_category":"Bauschreinerei Herstellung von Konstruktionsteilen, Fertigbauteilen U Ausbauelementen aus Holz",
    "sg:phone":"+41 31 771 19 41",
    "sg:postcode":"3673",
    "sg:province":"Bern",
    "wof:name":"Hansj\u00f6rg Nafzger M\u00f6belschreinerei Innenausbau",
    "wof:placetype":"venue"
},
  "geometry": {"coordinates":[7.675775,46.845699],"type":"Point"}
}