{
  "type": "Feature",
  "properties": {
    "iso:country":"CH",
    "sg:address":"Holzegg",
    "sg:city":"Alpthal",
    "sg:orig_category":"Detailhandel mit Sportartikeln",
    "sg:phone":"+41 41 811 12 34",
    "sg:postcode":"8849",
    "sg:province":"Schwyz",
    "wof:name":"Fritsche-sport",
    "wof:placetype":"venue"
},
  "geometry": {"coordinates":[8.6981563568,47.0287742615],"type":"Point"}
}