{
  "type": "Feature",
  "properties": {
    "iso:country":"CH",
    "sg:address":"In Grosswiesen 23 8044 Gockhausen. Postfach",
    "sg:city":"Z\u00fcrich",
    "sg:orig_category":"Verlagsgewerbe Zeitungsverlag",
    "sg:phone":"+41 14627166",
    "sg:postcode":"8044",
    "sg:province":"Z\u00fcrich",
    "wof:name":"Segert A. Publikationen",
    "wof:placetype":"venue"
},
  "geometry": {"coordinates":[8.5958862305,47.3836174011],"type":"Point"}
}