{
  "type": "Feature",
  "properties": {
    "iso:country":"CH",
    "sg:address":"Rietwiesstrasse 101",
    "sg:city":"Horgen",
    "sg:orig_category":"Unclassifiable Establishments",
    "sg:phone":"+41 17701141",
    "sg:postcode":"8810",
    "sg:province":"Z\u00fcrich",
    "wof:name":"Helmut Reincke, Hr Kommunikation",
    "wof:placetype":"venue"
},
  "geometry": {"coordinates":[8.6179704666,47.2511901855],"type":"Point"}
}