{
  "type": "Feature",
  "properties": {
    "iso:country":"CH",
    "sg:address":"Zielackerstrasse 26 8304 Wallisellen. Postfach",
    "sg:city":"Wallisellen",
    "sg:orig_category":"Minigolfpl\u00e4tze",
    "sg:phone":"+41 41 850 58 55",
    "sg:postcode":"8304",
    "sg:province":"Z\u00fcrich",
    "wof:name":"Minigolf-anlage Verkehrsverein",
    "wof:placetype":"venue"
},
  "geometry": {"coordinates":[8.4394292831,47.0804252625],"type":"Point"}
}