{
  "type": "Feature",
  "properties": {
    "iso:country":"CH",
    "sg:address":"Burggasse",
    "sg:city":"Altendorf",
    "sg:classifiers":[
        {
            "category":"Government",
            "subcategory":"Post Office",
            "type":"Public Place"
        }
    ],
    "sg:phone":"+41 24 491 21 37",
    "sg:postcode":"8852",
    "sg:province":"Schwyz",
    "sg:tags":[
        "caf\u00e9s",
        "tea-rooms"
    ],
    "wof:name":"Caf\u00e9 Buvette De L'arsaz",
    "wof:placetype":"venue"
},
  "geometry": {"coordinates":[7.1021499634,46.3953399658],"type":"Point"}
}