{
  "type": "Feature",
  "properties": {
    "iso:country":"CH",
    "sg:address":"Carri\u00e8re Rue De La 2",
    "sg:city":"Fribourg",
    "sg:orig_category":"Handel mit Automobilen",
    "sg:phone":"+41 26 424 69 31",
    "sg:postcode":"1700",
    "sg:province":"Fribourg",
    "wof:name":"Guri Shemsedin",
    "wof:placetype":"venue"
},
  "geometry": {"coordinates":[7.1536831856,46.8037452698],"type":"Point"}
}