{
  "type": "Feature",
  "properties": {
    "iso:country":"CH",
    "sg:address":"Untergasse 23",
    "sg:city":"Biel/bienne",
    "sg:orig_category":"Grafikateliers, Design Webdesign",
    "sg:phone":"+41 32 325 44 44",
    "sg:postcode":"2502",
    "sg:province":"Bern",
    "wof:name":"Moxi Ltd Grafik & Design",
    "wof:placetype":"venue"
},
  "geometry": {"coordinates":[7.2472162247,47.1419258118],"type":"Point"}
}