{
  "type": "Feature",
  "properties": {
    "iso:country":"CH",
    "sg:address":"1950",
    "sg:city":"Sitten",
    "sg:orig_category":"Reiseb\u00fcros U Reiseveranstalter",
    "sg:phone":"+41 27 322 53 63",
    "sg:postcode":"1950",
    "sg:province":"Valais",
    "wof:name":"Elys\u00e9e Voyages Biaggi Sa",
    "wof:placetype":"venue"
},
  "geometry": {"coordinates":[7.3633999825,46.2366981506],"type":"Point"}
}