{
  "type": "Feature",
  "properties": {
    "iso:country":"CH",
    "sg:address":"Poststr. 24 8226 Schleitheim. Postfach",
    "sg:city":"Bern",
    "sg:orig_category":"Detailhandel mit Beleuchtungs U Haushaltsgegenst\u00e4nden Elektroinstallation",
    "sg:phone":"+41 22 345 11 11",
    "sg:postcode":"3013",
    "sg:province":"Bern",
    "wof:name":"Willy Ledermann Electrom\u00e9nager",
    "wof:placetype":"venue"
},
  "geometry": {"coordinates":[6.126174,46.212811],"type":"Point"}
}