{
  "type": "Feature",
  "properties": {
    "addr:full":"6563 Mesocco Graubunden 6563",
    "addr:housenumber":"6563",
    "addr:postcode":"6563",
    "addr:street":"Mesocco Graubunden",
    "iso:country":"CH",
    "sg:address":"6563",
    "sg:city":"Mesocco",
    "sg:orig_category":"Allgemeiner Hochbau Strassenbau",
    "sg:phone":"+41 91 831 11 44",
    "sg:postcode":"6563",
    "sg:province":"Graubunden",
    "wof:name":"Alberto Cereghetti Sa Impresa Costruzioni",
    "wof:placetype":"venue"
},
  "geometry": {"coordinates":[9.2329,46.391632],"type":"Point"}
}