{
  "type": "Feature",
  "properties": {
    "iso:country":"CH",
    "sg:address":"Ceresio Via 8 6963 Pregassona. Postfach",
    "sg:city":"Pregassona",
    "sg:orig_category":"Sanit\u00e4r, Heizungs U L\u00fcftungsinstallation",
    "sg:postcode":"6963",
    "sg:province":"Ticino",
    "wof:name":"Casalini Sagl Impianti Sanitari E Riscaldamenti; Posa, Vendita",
    "wof:placetype":"venue"
},
  "geometry": {"coordinates":[8.9647417068,46.0169181824],"type":"Point"}
}