{
  "type": "Feature",
  "properties": {
    "iso:country":"CH",
    "sg:address":"Bahnhofstrasse 110",
    "sg:city":"M\u00f6hlin",
    "sg:orig_category":"Wirtschaftspr\u00fcfung, Steuerberatung U Treuhand",
    "sg:phone":"+41 61 855 97 97",
    "sg:postcode":"4313",
    "sg:province":"Aargau",
    "wof:name":"Holzer Und L\u00fcthi Ag",
    "wof:placetype":"venue"
},
  "geometry": {"coordinates":[7.832159996,47.5613517761],"type":"Point"}
}