{
  "type": "Feature",
  "properties": {
    "iso:country":"CH",
    "sg:address":"Burgweg 2 4512 Bellach. Postfach 348",
    "sg:city":"Bellach",
    "sg:orig_category":"Herstellung von Metallkonstruktionen Stahl U Leichtmetallbau",
    "sg:phone":"+41 79 222 47 22",
    "sg:postcode":"4512",
    "sg:province":"Solothurn",
    "wof:name":"Kaeser Stahlbau Ag",
    "wof:placetype":"venue"
},
  "geometry": {"coordinates":[7.5075778961,47.2095222473],"type":"Point"}
}