{
  "type": "Feature",
  "properties": {
    "iso:country":"CH",
    "sg:address":"Rue De Chamblon 43",
    "sg:city":"Yverdon-les-bains",
    "sg:classifiers":[
        {
            "category":"Government",
            "subcategory":"Post Office",
            "type":"Public Place"
        }
    ],
    "sg:phone":"+41 24 426 02 95",
    "sg:postcode":"1400",
    "sg:province":"Vaud",
    "sg:tags":[
        "caf\u00e9s",
        "tea-rooms"
    ],
    "wof:name":"Caf\u00e9 Le Mandarin",
    "wof:placetype":"venue"
},
  "geometry": {"coordinates":[6.6282839775,46.7790565491],"type":"Point"}
}