{
  "type": "Feature",
  "properties": {
    "iso:country":"CH",
    "sg:address":"Via Ai Crotti 4",
    "sg:city":"Chiasso",
    "sg:orig_category":"Interessenvertretungen",
    "sg:postcode":"6830",
    "sg:province":"Ticino",
    "wof:name":"Fondazione Sorelle Nespoli Fu Emilio",
    "wof:placetype":"venue"
},
  "geometry": {"coordinates":[9.0255565643,45.832775116],"type":"Point"}
}