{
  "type": "Feature",
  "properties": {
    "iso:country":"CH",
    "sg:address":"M\u00fchlestrasse 66",
    "sg:city":"Belp",
    "sg:orig_category":"Sportvereine J and S Fachleiter Sportvereine Orientierungslauf",
    "sg:phone":"+41 31 819 28 04",
    "sg:postcode":"3123",
    "sg:province":"Bern",
    "wof:name":"J & S Fachleiter",
    "wof:placetype":"venue"
},
  "geometry": {"coordinates":[7.5049118996,46.8838996887],"type":"Point"}
}