{
  "type": "Feature",
  "properties": {
    "iso:country":"CH",
    "sg:address":"Bodenackerstrasse 20",
    "sg:city":"Otelfingen",
    "sg:orig_category":"Maurerarbeiten Verlegen von Fussboden",
    "sg:postcode":"8112",
    "sg:province":"Z\u00fcrich",
    "wof:name":"Daniel Treichler Maurer, Boden- & Wandbel\u00e4ge",
    "wof:placetype":"venue"
},
  "geometry": {"coordinates":[8.3915090561,47.4603385925],"type":"Point"}
}