{
  "type": "Feature",
  "properties": {
    "iso:country":"CH",
    "sg:address":"Rue De La Blancherie 29 1022 Chavannes-renens Case Postale",
    "sg:city":"Chavannes-renens",
    "sg:orig_category":"Fachdetailhandel in Verkaufsr\u00e4umen Herstellung von Sportger\u00e4ten",
    "sg:phone":"+41 22 707 44 60",
    "sg:postcode":"1022",
    "sg:province":"Vaud",
    "wof:name":"Sporloisirs Sa",
    "wof:placetype":"venue"
},
  "geometry": {"coordinates":[6.155687809,46.2039985657],"type":"Point"}
}