{
  "type": "Feature",
  "properties": {
    "iso:country":"CH",
    "sg:address":"Stampfistrasse 1",
    "sg:city":"Knonau",
    "sg:orig_category":"Landesverteidigung, Sozialversicherung \u00d6ffentliche Verwaltung",
    "sg:phone":"+41 55 442 49 22",
    "sg:postcode":"8934",
    "sg:province":"Z\u00fcrich",
    "wof:name":"Zivilschutzstelle Knonau",
    "wof:placetype":"venue"
},
  "geometry": {"coordinates":[8.4612693787,47.2235107422],"type":"Point"}
}