{
  "type": "Feature",
  "properties": {
    "iso:country":"CH",
    "sg:address":"Via Della Salina 5",
    "sg:city":"Muralto",
    "sg:orig_category":"Architekturb\u00fcros",
    "sg:phone":"+41 91 743 21 22",
    "sg:postcode":"6600",
    "sg:province":"Ticino",
    "wof:name":"Raffaele Cavadini Studio D'architettura",
    "wof:placetype":"venue"
},
  "geometry": {"coordinates":[8.80119,46.171597],"type":"Point"}
}