{
  "type": "Feature",
  "properties": {
    "iso:country":"CH",
    "sg:address":"Hostatt",
    "sg:city":"Ennetmoos",
    "sg:orig_category":"Verwertung von Milch",
    "sg:postcode":"6372",
    "sg:province":"Nidwalden",
    "wof:name":"Odermatt-gander Josef",
    "wof:placetype":"venue"
},
  "geometry": {"coordinates":[8.3147687912,46.9308929443],"type":"Point"}
}