{
  "type": "Feature",
  "properties": {
    "iso:country":"CH",
    "sg:address":"Via Cantonale 6594 Contone Casella Postale 137",
    "sg:city":"Contone",
    "sg:orig_category":"Einbau von Schreinerwaren Herstellung von K\u00fcchenm\u00f6beln",
    "sg:phone":"+41 91 858 27 27",
    "sg:postcode":"6594",
    "sg:province":"Ticino",
    "wof:name":"Cucine Piatti Sa",
    "wof:placetype":"venue"
},
  "geometry": {"coordinates":[8.9260749817,46.148525238],"type":"Point"}
}