{
  "type": "Feature",
  "properties": {
    "iso:country":"CH",
    "sg:address":"Ruswilstrasse 1 6016 Hellb\u00fchl. Postfach",
    "sg:city":"Hellb\u00fchl",
    "sg:orig_category":"Nationale Postdienste",
    "sg:phone":"+41 55 282 11 05",
    "sg:postcode":"6016",
    "sg:province":"Luzern",
    "wof:name":"Die Schweizerische Post",
    "wof:placetype":"venue"
},
  "geometry": {"coordinates":[8.9213428497,47.2407341003],"type":"Point"}
}