{
  "type": "Feature",
  "properties": {
    "iso:country":"CH",
    "sg:address":"6647",
    "sg:city":"Mergoscia",
    "sg:orig_category":"Detailhandel mit Waren verschiedener Art, Hauptrichtung Nahrungsmittel",
    "sg:phone":"+41 41 930 12 20",
    "sg:postcode":"6647",
    "sg:province":"Ticino",
    "wof:name":"Anna Schmid Handlung",
    "wof:placetype":"venue"
},
  "geometry": {"coordinates":[8.1532936096,47.2194252014],"type":"Point"}
}