{
  "type": "Feature",
  "properties": {
    "iso:country":"CH",
    "sg:address":"Dorfstrasse 87",
    "sg:city":"Geroldswil",
    "sg:orig_category":"Hochschulen U h\u00f6here Ausbildung",
    "sg:postcode":"8954",
    "sg:province":"Z\u00fcrich",
    "wof:name":"Marlier Didier - The 5th Dimension Partnership",
    "wof:placetype":"venue"
},
  "geometry": {"coordinates":[6.9953799248,46.2966117859],"type":"Point"}
}