{
  "type": "Feature",
  "properties": {
    "iso:country":"CH",
    "sg:address":"M\u00fchlegasse 3 8902 Urdorf. Postfach",
    "sg:city":"Urdorf",
    "sg:orig_category":"Herstellung von sonstigen Erzeugnissen",
    "sg:phone":"+41 17352054",
    "sg:postcode":"8902",
    "sg:province":"Z\u00fcrich",
    "wof:name":"Fega-service Gmbh Festmaterial, Fl\u00fcssiggas; Verkauf, Vermietung, Handel",
    "wof:placetype":"venue"
},
  "geometry": {"coordinates":[8.4240083694,47.3803443909],"type":"Point"}
}