{
  "type": "Feature",
  "properties": {
    "iso:country":"CH",
    "sg:address":"Standbachstrasse 19",
    "sg:city":"Sirnach",
    "sg:orig_category":"Sonstiger Fachdetailhandel mit Nahrungsmitteln, Getr\u00e4nken U Tabak in Verkaufsr\u00e4umen",
    "sg:postcode":"8370",
    "sg:province":"Thurgau",
    "wof:name":"Lattmann & Co. Ag",
    "wof:placetype":"venue"
},
  "geometry": {"coordinates":[8.9937467575,47.4604568481],"type":"Point"}
}