{
  "type": "Feature",
  "properties": {
    "iso:country":"CH",
    "sg:address":"Bahnhofstrasse 13",
    "sg:city":"Sulgen",
    "sg:orig_category":"Architektur U Ingenieurb\u00fcros",
    "sg:phone":"+41 71 642 31 22",
    "sg:postcode":"8583",
    "sg:province":"Thurgau",
    "wof:name":"J\u00fcrg Widmer Ingenieur-& Planungsb\u00fcro",
    "wof:placetype":"venue"
},
  "geometry": {"coordinates":[9.183602,47.540787],"type":"Point"}
}