{
  "type": "Feature",
  "properties": {
    "iso:country":"CH",
    "sg:address":"Grossalbis 10",
    "sg:city":"Z\u00fcrich",
    "sg:orig_category":"Kunsthandel",
    "sg:phone":"+41 14636240",
    "sg:postcode":"8045",
    "sg:province":"Z\u00fcrich",
    "wof:name":"Laura Van Deurzen Kunsthandel Dena",
    "wof:placetype":"venue"
},
  "geometry": {"coordinates":[8.509062767,47.3566436768],"type":"Point"}
}