{
  "type": "Feature",
  "properties": {
    "iso:country":"CH",
    "sg:address":"S.bartolomeo",
    "sg:city":"Vogorno",
    "sg:classifiers":[
        {
            "category":"Travel",
            "subcategory":"Hotels & Motels",
            "type":"Entertainment"
        }
    ],
    "sg:phone":"+41 91 745 15 97",
    "sg:postcode":"6632",
    "sg:province":"Ticino",
    "sg:tags":[
        "hotels",
        "mit",
        "restaurant"
    ],
    "wof:name":"Albergo Osteria Verzasca",
    "wof:placetype":"venue"
},
  "geometry": {"coordinates":[8.8464813232,46.2327575684],"type":"Point"}
}