{
  "type": "Feature",
  "properties": {
    "iso:country":"CH",
    "sg:address":"Rennweg 61 2502 Biel/bienne. Postfach",
    "sg:city":"Biel/bienne",
    "sg:orig_category":"Reiseb\u00fcros U Reiseveranstalter",
    "sg:phone":"+41 79 667 31 49",
    "sg:postcode":"2502",
    "sg:province":"Bern",
    "wof:name":"Nan's Tours, Tadic Svetlana",
    "wof:placetype":"venue"
},
  "geometry": {"coordinates":[7.2695221901,47.1451225281],"type":"Point"}
}