{
  "type": "Feature",
  "properties": {
    "iso:country":"CH",
    "sg:address":"Tannenstrasse 98 8424 Embrach. Postfach",
    "sg:city":"Embrach",
    "sg:orig_category":"Pensionskassen",
    "sg:phone":"+41 18652450",
    "sg:postcode":"8424",
    "sg:province":"Z\u00fcrich",
    "wof:name":"Wohlfahrtsfonds Der Spirella Ag, Embrach",
    "wof:placetype":"venue"
},
  "geometry": {"coordinates":[8.5909910202,47.5077133179],"type":"Point"}
}