{
  "type": "Feature",
  "properties": {
    "iso:country":"CH",
    "sg:address":"Chemin Saint-martin 5",
    "sg:city":"Marly",
    "sg:orig_category":"Wirtschaftspr\u00fcfung, Steuerberatung U Treuhand",
    "sg:postcode":"1723",
    "sg:province":"Fribourg",
    "wof:name":"Ficoges Marly S\u00e0rl",
    "wof:placetype":"venue"
},
  "geometry": {"coordinates":[7.1428442001,46.7791175842],"type":"Point"}
}