{
  "type": "Feature",
  "properties": {
    "iso:country":"CH",
    "sg:address":"Cit\u00e9 Vieusseux 12",
    "sg:city":"Gen\u00e8ve",
    "sg:orig_category":"Physiotherapie",
    "sg:phone":"+41 21 635 31 77",
    "sg:postcode":"1203",
    "sg:province":"Gen\u00e8ve",
    "wof:name":"J.-m. Monseux & J.-m. Sengelen Physioth\u00e9rapie",
    "wof:placetype":"venue"
},
  "geometry": {"coordinates":[6.5799598694,46.5360984802],"type":"Point"}
}