{
  "type": "Feature",
  "properties": {
    "iso:country":"CH",
    "sg:address":"7504",
    "sg:city":"Pontresina",
    "sg:orig_category":"Sportschulen Ski-& Snowboardschulen",
    "sg:phone":"+41 81 833 62 33",
    "sg:postcode":"7504",
    "sg:province":"Graubunden",
    "wof:name":"Langlauf-& Skiwanderschule",
    "wof:placetype":"venue"
},
  "geometry": {"coordinates":[9.8325080872,46.4820976257],"type":"Point"}
}