{
  "type": "Feature",
  "properties": {
    "iso:country":"CH",
    "sg:address":"Bahnhofstrasse 28 7302 Landquart. Postfach",
    "sg:city":"Landquart",
    "sg:orig_category":"Allgemeiner Hoch U Tiefbau",
    "sg:postcode":"7302",
    "sg:province":"Graubunden",
    "wof:name":"Schneider Otto Wohnbau & Cie",
    "wof:placetype":"venue"
},
  "geometry": {"coordinates":[9.558322,46.967747],"type":"Point"}
}