{
  "type": "Feature",
  "properties": {
    "iso:country":"CH",
    "sg:address":"Haldenstrasse 5",
    "sg:city":"Baar",
    "sg:orig_category":"Unclassifiable Establishments",
    "sg:postcode":"6340",
    "sg:province":"Zug",
    "wof:name":"Bemi Reinigungsdienst, D. Misturelli",
    "wof:placetype":"venue"
},
  "geometry": {"coordinates":[8.7813358307,47.3710365295],"type":"Point"}
}