{
  "type": "Feature",
  "properties": {
    "iso:country":"CH",
    "sg:address":"Fehrenweg 9478 Azmoos. Postfach",
    "sg:city":"Azmoos",
    "sg:orig_category":"Innenausbau Sanit\u00e4r, Heizungs U L\u00fcftungsinstallation",
    "sg:phone":"+41 81 783 34 34",
    "sg:postcode":"9478",
    "sg:province":"St. Gallen",
    "wof:name":"Rudolf Riederer Ag Innenausbau & K\u00fcchen",
    "wof:placetype":"venue"
},
  "geometry": {"coordinates":[9.476269722,47.0777015686],"type":"Point"}
}