{
  "type": "Feature",
  "properties": {
    "iso:country":"CH",
    "sg:address":"Wilenstrasse 12",
    "sg:city":"Rorschach",
    "sg:orig_category":"Aktivit\u00e4ten der Generalunternehmen im Baugewerbe Herstellung von Konstruktionsteilen, Fertigbauteile",
    "sg:phone":"+41 71 855 57 12",
    "sg:postcode":"9400",
    "sg:province":"St. Gallen",
    "wof:name":"Hans Peter Lemmenmeier Generalunternehmnung",
    "wof:placetype":"venue"
},
  "geometry": {"coordinates":[9.4952,47.47794],"type":"Point"}
}