{
  "type": "Feature",
  "properties": {
    "iso:country":"CH",
    "sg:address":"Gottfried-keller-strasse 4 8590 Romanshorn. Postfach",
    "sg:city":"Romanshorn",
    "sg:orig_category":"Pensionskassen",
    "sg:phone":"+41 71 463 11 71",
    "sg:postcode":"8590",
    "sg:province":"Thurgau",
    "wof:name":"Patronalen Wohlfahrtsfond Der Firma Daniel Ag",
    "wof:placetype":"venue"
},
  "geometry": {"coordinates":[9.3740282059,47.5665245056],"type":"Point"}
}