{
  "type": "Feature",
  "properties": {
    "iso:country":"CH",
    "sg:address":"Im Staubeweidli 19 8820 W\u00e4denswil. Postfach",
    "sg:city":"W\u00e4denswil",
    "sg:orig_category":"Architektur U Ingenieurb\u00fcros",
    "sg:postcode":"8820",
    "sg:province":"Z\u00fcrich",
    "wof:name":"Ema Elektro Mechanische Antriebstechnik Gmbh",
    "wof:placetype":"venue"
},
  "geometry": {"coordinates":[8.687173,47.221085],"type":"Point"}
}