{
  "type": "Feature",
  "properties": {
    "iso:country":"CH",
    "sg:address":"Nova Via 89",
    "sg:city":"Domat/ems",
    "sg:orig_category":"Elektroinstallation",
    "sg:postcode":"7013",
    "sg:province":"Graubunden",
    "wof:name":"Schumacher Elektro Ag",
    "wof:placetype":"venue"
},
  "geometry": {"coordinates":[8.1827249527,47.0368156433],"type":"Point"}
}