{
  "type": "Feature",
  "properties": {
    "iso:country":"CH",
    "sg:address":"Kirchb\u00fcntstrasse 15",
    "sg:city":"Grabs",
    "sg:orig_category":"Chemin\u00e9e- and Ofenbau Hafner",
    "sg:phone":"+41 81 771 67 27",
    "sg:postcode":"9472",
    "sg:province":"St. Gallen",
    "wof:name":"Alain Schulthess Ofenbau & Hafnerarbeiten",
    "wof:placetype":"venue"
},
  "geometry": {"coordinates":[9.445754,47.178429],"type":"Point"}
}