{
  "type": "Feature",
  "properties": {
    "iso:country":"CH",
    "sg:address":"Mattstrasse 18",
    "sg:city":"Netstal",
    "sg:orig_category":"Elektro- and elektronische Maschinen Grosshandel Herstellung von elektronischen Bauelementen",
    "sg:phone":"+41 56 483 34 00",
    "sg:postcode":"8754",
    "sg:province":"Glarus",
    "wof:name":"Mpi-xp Power Ag Elektronische Komponenten U. Systeme; Handel, Vertrieb",
    "wof:placetype":"venue"
},
  "geometry": {"coordinates":[8.2939882278,47.4476890564],"type":"Point"}
}