{
  "type": "Feature",
  "properties": {
    "iso:country":"CH",
    "sg:address":"Belpbergstrasse 14",
    "sg:city":"Belp",
    "sg:orig_category":"Detailhandel mit Fleisch U Fleischwaren Grosshandel mit Fleisch U Fleischwaren",
    "sg:phone":"+41 79 214 09 19",
    "sg:postcode":"3123",
    "sg:province":"Bern",
    "wof:name":"Bio Carna & Comestibles",
    "wof:placetype":"venue"
},
  "geometry": {"coordinates":[7.933672905,46.1117172241],"type":"Point"}
}