{
  "type": "Feature",
  "properties": {
    "iso:country":"CH",
    "sg:address":"Bahnhofstrase 86 5000 Aarau. Postfach",
    "sg:city":"Aarau",
    "sg:orig_category":"Reiseb\u00fcros",
    "sg:phone":"+41 62 837 08 88",
    "sg:postcode":"5001",
    "sg:province":"Aargau",
    "wof:name":"Bti Kuoni Switzerland Kuoni Reisen Ag",
    "wof:placetype":"venue"
},
  "geometry": {"coordinates":[8.0526533127,47.3923988342],"type":"Point"}
}