{
  "type": "Feature",
  "properties": {
    "iso:country":"CH",
    "sg:address":"Oberschrot",
    "sg:city":"Plaffeien",
    "sg:orig_category":"Detailhandel mit Fleisch U Fleischwaren",
    "sg:phone":"+41 26 419 11 33",
    "sg:postcode":"1716",
    "sg:province":"Fribourg",
    "wof:name":"Rudolf Klaus Metzgerei B\u00fchl",
    "wof:placetype":"venue"
},
  "geometry": {"coordinates":[7.2859301567,46.7442512512],"type":"Point"}
}