{
  "type": "Feature",
  "properties": {
    "iso:country":"CH",
    "sg:address":"Route Du Simplon",
    "sg:city":"Saxon",
    "sg:orig_category":"Herstellung von Metallerzeugnissen ohne Maschinenbau Maschinenbau",
    "sg:phone":"+41 27 744 31 21",
    "sg:postcode":"1907",
    "sg:province":"Valais",
    "wof:name":"Guy Rubellin Machines Pour L'alimentation",
    "wof:placetype":"venue"
},
  "geometry": {"coordinates":[7.1886501312,46.1560516357],"type":"Point"}
}