{
  "type": "Feature",
  "properties": {
    "iso:country":"CH",
    "sg:address":"Tellistrasse 67",
    "sg:city":"Aarau",
    "sg:orig_category":"Nationale Postdienste",
    "sg:phone":"+41 41 761 26 13",
    "sg:postcode":"5004",
    "sg:province":"Aargau",
    "wof:name":"Die Schweizerische Post Baar 1",
    "wof:placetype":"venue"
},
  "geometry": {"coordinates":[8.5248403549,47.1942100525],"type":"Point"}
}