{
  "type": "Feature",
  "properties": {
    "iso:country":"CH",
    "sg:address":"Grand-rue 32",
    "sg:city":"Gland",
    "sg:orig_category":"Bauschreinerei Herstellung von M\u00f6beln verschiedener Art",
    "sg:phone":"+41 22 364 11 68",
    "sg:postcode":"1196",
    "sg:province":"Vaud",
    "wof:name":"Peneveyre Fran\u00e7ois",
    "wof:placetype":"venue"
},
  "geometry": {"coordinates":[6.264087,46.423069],"type":"Point"}
}