{
  "type": "Feature",
  "properties": {
    "iso:country":"CH",
    "sg:address":"Im Sch\u00e4chli",
    "sg:city":"Bowil",
    "sg:orig_category":"K\u00fcnstlerische U schriftstellerische T\u00e4tigkeiten U Darbietungen Sonstige k\u00fcnstlerische U schriftstell",
    "sg:phone":"+41 31 711 15 95",
    "sg:postcode":"3533",
    "sg:province":"Bern",
    "wof:name":"Samuel Thierstein Bauernmalerei",
    "wof:placetype":"venue"
},
  "geometry": {"coordinates":[7.7017951012,46.8957443237],"type":"Point"}
}