{
  "type": "Feature",
  "properties": {
    "iso:country":"CH",
    "sg:address":"Lenggstrasse 60",
    "sg:city":"Z\u00fcrich",
    "sg:orig_category":"Institutionen f\u00fcr Behinderte Sonderschulen",
    "sg:phone":"+41 13821030",
    "sg:postcode":"8008",
    "sg:province":"Z\u00fcrich",
    "wof:name":"Escher Mathilde-stiftung",
    "wof:placetype":"venue"
},
  "geometry": {"coordinates":[8.5733175278,47.35338974],"type":"Point"}
}