{
  "type": "Feature",
  "properties": {
    "iso:country":"CH",
    "sg:address":"Lindauerstrasse 25",
    "sg:city":"Tagelswangen",
    "sg:orig_category":"Kunststoff-Produkte",
    "sg:phone":"+41 52 343 95 15",
    "sg:postcode":"8317",
    "sg:province":"Z\u00fcrich",
    "wof:name":"Tennisclub Duralon",
    "wof:placetype":"venue"
},
  "geometry": {"coordinates":[8.6727581024,47.4349441528],"type":"Point"}
}