{
  "type": "Feature",
  "properties": {
    "iso:country":"CH",
    "sg:address":"Mattackerstrasse 17",
    "sg:city":"Seebach",
    "sg:orig_category":"Herstellung von Fahrr\u00e4dern",
    "sg:phone":"+41 13026612",
    "sg:postcode":"8052",
    "sg:province":"Z\u00fcrich",
    "wof:name":"Faber Rudolf Fapar Fabrikation V. Und Handel Mit Fahrrad-parkierst\u00e4ndern Und Haltern",
    "wof:placetype":"venue"
},
  "geometry": {"coordinates":[8.5402402878,47.4224815369],"type":"Point"}
}