{
  "type": "Feature",
  "properties": {
    "iso:country":"CH",
    "sg:address":"Eichstrasse 54",
    "sg:city":"Cham",
    "sg:orig_category":"Unclassifiable Establishments",
    "sg:postcode":"6330",
    "sg:province":"Zug",
    "wof:name":"Cig Cham Intermediaries Group Ag",
    "wof:placetype":"venue"
},
  "geometry": {"coordinates":[8.4726114273,47.184513092],"type":"Point"}
}