{
  "type": "Feature",
  "properties": {
    "iso:country":"CH",
    "sg:address":"8401 Winterthur. Postfach 1190",
    "sg:city":"Winterthur",
    "sg:orig_category":"Sportvereine Flug Delta",
    "sg:postcode":"8401",
    "sg:province":"Z\u00fcrich",
    "wof:name":"Dc Bora Winterthur",
    "wof:placetype":"venue"
},
  "geometry": {"coordinates":[8.7261600494,47.4998817444],"type":"Point"}
}