{
  "type": "Feature",
  "properties": {
    "iso:country":"CH",
    "sg:address":"Lindenstrasse 21",
    "sg:city":"Wildegg",
    "sg:orig_category":"Herstellung von Teppichen",
    "sg:postcode":"5103",
    "sg:province":"Aargau",
    "wof:name":"D\u00fcbendorfer O.",
    "wof:placetype":"venue"
},
  "geometry": {"coordinates":[8.1625461578,47.4135284424],"type":"Point"}
}