{
  "type": "Feature",
  "properties": {
    "iso:country":"CH",
    "sg:address":"Kantonsstrasse",
    "sg:city":"Susten",
    "sg:orig_category":"Tankstellen",
    "sg:phone":"+41 71 744 07 88",
    "sg:postcode":"3952",
    "sg:province":"Valais",
    "wof:name":"Migrol Tankstelle",
    "wof:placetype":"venue"
},
  "geometry": {"coordinates":[9.6348695755,47.4514694214],"type":"Point"}
}