{
  "type": "Feature",
  "properties": {
    "iso:country":"CH",
    "sg:address":"Route Des Pr\u00e9alpes 8",
    "sg:city":"Matran",
    "sg:orig_category":"G\u00fcterbef\u00f6rderung im Strassenverkehr",
    "sg:phone":"+41 26 402 71 18",
    "sg:postcode":"1753",
    "sg:province":"Fribourg",
    "wof:name":"Jean-martin Hayoz Transports",
    "wof:placetype":"venue"
},
  "geometry": {"coordinates":[7.0995030403,46.7883911133],"type":"Point"}
}