{
  "type": "Feature",
  "properties": {
    "iso:country":"CH",
    "sg:address":"1145",
    "sg:city":"Bi\u00e8re",
    "sg:orig_category":"Vereine Gesang",
    "sg:postcode":"1145",
    "sg:province":"Vaud",
    "wof:name":"St\u00e9 De Chant L'esp\u00e9rance",
    "wof:placetype":"venue"
},
  "geometry": {"coordinates":[6.3328051567,46.5380134583],"type":"Point"}
}