{
  "type": "Feature",
  "properties": {
    "addr:full":"Riedmattstrasse 14 Sattel Schwyz 6417",
    "addr:housenumber":"14",
    "addr:postcode":"6417",
    "addr:street":"Riedmattstrasse;Schwyz",
    "iso:country":"CH",
    "sg:address":"Riedmattstrasse 14",
    "sg:city":"Sattel",
    "sg:orig_category":"Autogaragen",
    "sg:phone":"+41 41 835 13 70",
    "sg:postcode":"6417",
    "sg:province":"Schwyz",
    "wof:name":"Paul Mathis Autoreparaturwerkst\u00e4tte",
    "wof:placetype":"venue"
},
  "geometry": {"coordinates":[8.62588,47.08358],"type":"Point"}
}