{
  "type": "Feature",
  "properties": {
    "iso:country":"CH",
    "sg:address":"Route Des Ateliers 8",
    "sg:city":"Sion",
    "sg:orig_category":"Mechanische Werkst\u00e4tten Schlossereien",
    "sg:phone":"+41 27 203 47 47",
    "sg:postcode":"1950",
    "sg:province":"Valais",
    "wof:name":"Arepa-racing Sa",
    "wof:placetype":"venue"
},
  "geometry": {"coordinates":[7.3690319061,46.2268409729],"type":"Point"}
}