{
  "type": "Feature",
  "properties": {
    "iso:country":"CH",
    "sg:address":"Zihlschlacht",
    "sg:city":"Zihlschlacht",
    "sg:orig_category":"Unclassifiable Establishments",
    "sg:phone":"+41 71 422 26 74",
    "sg:postcode":"8588",
    "sg:province":"Thurgau",
    "wof:name":"Keller Otto",
    "wof:placetype":"venue"
},
  "geometry": {"coordinates":[9.2475366592,47.5086860657],"type":"Point"}
}