{
  "type": "Feature",
  "properties": {
    "iso:country":"CH",
    "sg:address":"Ruppisbergweid 3512 Walkringen. Postfach",
    "sg:city":"Walkringen",
    "sg:orig_category":"Softwareentwicklung U beratung",
    "sg:phone":"+41 31 702 00 11",
    "sg:postcode":"3512",
    "sg:province":"Bern",
    "wof:name":"Heimetli Software Ag",
    "wof:placetype":"venue"
},
  "geometry": {"coordinates":[7.6357030869,46.9597473145],"type":"Point"}
}