{
  "type": "Feature",
  "properties": {
    "iso:country":"CH",
    "sg:address":"Bahnhofstrasse 37 8854 Siebnen. Postfach 244",
    "sg:city":"Siebnen",
    "sg:orig_category":"Maler U Glasergewerbe Tapeziererei",
    "sg:phone":"+41 55 440 12 72",
    "sg:postcode":"8854",
    "sg:province":"Schwyz",
    "wof:name":"Z\u00fcger Ag",
    "wof:placetype":"venue"
},
  "geometry": {"coordinates":[8.8976774216,47.1786422729],"type":"Point"}
}