{
  "type": "Feature",
  "properties": {
    "iso:country":"CH",
    "sg:address":"Stationsstrasse 5",
    "sg:city":"Z\u00fcrich",
    "sg:orig_category":"Handel mit Motorr\u00e4dern, Teilen U Zubeh\u00f6r Instandhaltung U Reparatur von Motorr\u00e4dern",
    "sg:phone":"+41 14638111",
    "sg:postcode":"8003",
    "sg:province":"Z\u00fcrich",
    "wof:name":"Velogarage Gmbh",
    "wof:placetype":"venue"
},
  "geometry": {"coordinates":[8.5200242996,47.3727760315],"type":"Point"}
}