{
  "type": "Feature",
  "properties": {
    "iso:country":"CH",
    "sg:address":"Tramstrasse 10",
    "sg:city":"Z\u00fcrich",
    "sg:orig_category":"Werbung",
    "sg:postcode":"8050",
    "sg:province":"Z\u00fcrich",
    "wof:name":"Direct Data Ag",
    "wof:placetype":"venue"
},
  "geometry": {"coordinates":[8.8636655807,47.1902389526],"type":"Point"}
}