{
  "type": "Feature",
  "properties": {
    "iso:country":"CH",
    "sg:address":"7562",
    "sg:city":"Samnaun-compatsch",
    "sg:orig_category":"Gemeindeverwaltungen",
    "sg:phone":"+41 81 858 57 22",
    "sg:postcode":"7562",
    "sg:province":"Graubunden",
    "wof:name":"Gemeindeverwaltung Santa Maria Im M\u00fcnstertal",
    "wof:placetype":"venue"
},
  "geometry": {"coordinates":[10.4217195511,46.6009635925],"type":"Point"}
}