{
  "type": "Feature",
  "properties": {
    "iso:country":"CH",
    "sg:address":"Pl\u00e4nkestrasse 1",
    "sg:city":"Biel/bienne",
    "sg:orig_category":"Detailhandel mit M\u00f6beln U Haushaltsgegenst\u00e4nden Innendekorationsateliers",
    "sg:phone":"+41 32 323 41 52",
    "sg:postcode":"2502",
    "sg:province":"Bern",
    "wof:name":"Heim Decor, Zimmermann Rolf",
    "wof:placetype":"venue"
},
  "geometry": {"coordinates":[7.2426447868,47.1364746094],"type":"Point"}
}