{
  "type": "Feature",
  "properties": {
    "addr:full":"Lisighaus Wildhaus St. Gallen 9658",
    "addr:postcode":"9658",
    "addr:street":"Lisighaus Wildhaus",
    "iso:country":"CH",
    "sg:address":"Lisighaus",
    "sg:city":"Wildhaus",
    "sg:orig_category":"Bezirks, Sekundar, Realschulen, Oberstufe der Primarschulen",
    "sg:phone":"+41 71 999 26 44",
    "sg:postcode":"9658",
    "sg:province":"St. Gallen",
    "wof:name":"Sekundarschule Wildhaus Alt St.johann",
    "wof:placetype":"venue"
},
  "geometry": {"coordinates":[9.341564,47.201797],"type":"Point"}
}