{
  "type": "Feature",
  "properties": {
    "iso:country":"CH",
    "sg:address":"Rietpark 6",
    "sg:city":"Greifensee",
    "sg:orig_category":"Wirtschaftspr\u00fcfung, Steuerberatung U Treuhand",
    "sg:phone":"+41 19944553",
    "sg:postcode":"8606",
    "sg:province":"Z\u00fcrich",
    "wof:name":"Stettler Treuhand",
    "wof:placetype":"venue"
},
  "geometry": {"coordinates":[8.6822500229,47.366317749],"type":"Point"}
}