{
  "type": "Feature",
  "properties": {
    "addr:full":"Burnand Avenue Eug\u00e8ne 5 1510 Moudon. Postfach Moudon Vaud 1510",
    "addr:housenumber":"5",
    "addr:postcode":"1510 moudon. postfach;1510",
    "addr:street":"Burnand Avenue Euge\u0300Ne",
    "iso:country":"CH",
    "sg:address":"Burnand Avenue Eug\u00e8ne 5 1510 Moudon. Postfach",
    "sg:city":"Moudon",
    "sg:orig_category":"Allgemeiner Hoch U Tiefbau",
    "sg:postcode":"1510",
    "sg:province":"Vaud",
    "wof:name":"Artek-os S\u00e0rl Entreprise G\u00e9n\u00e9rale De Construction, Notamm. Travaux De Charpenterie, De Menuiserie Etc",
    "wof:placetype":"venue"
},
  "geometry": {"coordinates":[6.796972,46.663788],"type":"Point"}
}