{
  "type": "Feature",
  "properties": {
    "iso:country":"CH",
    "sg:address":"Niedermatt 249",
    "sg:city":"Hellikon",
    "sg:orig_category":"Herstellung von Konstruktionsteilen, Fertigbauteilen U Ausbauelementen aus Holz",
    "sg:phone":"+41 61 871 08 90",
    "sg:postcode":"4316",
    "sg:province":"Aargau",
    "wof:name":"Rita Schlienger Damen-& Herrensalon Rita",
    "wof:placetype":"venue"
},
  "geometry": {"coordinates":[7.9217648506,47.5103759766],"type":"Point"}
}