{
  "type": "Feature",
  "properties": {
    "iso:country":"CH",
    "sg:address":"Blockweg 7 6410 Goldau. Postfach 344",
    "sg:city":"Goldau",
    "sg:orig_category":"Verwaltung von Immobilien Wirtschaftspr\u00fcfung, Steuerberatung U Treuhand",
    "sg:phone":"+41 14920113",
    "sg:postcode":"6410",
    "sg:province":"Schwyz",
    "wof:name":"Baumann Treuhand",
    "wof:placetype":"venue"
},
  "geometry": {"coordinates":[8.4385242462,47.3228569031],"type":"Point"}
}