{
  "type": "Feature",
  "properties": {
    "iso:country":"CH",
    "sg:address":"Hauptstrasse 36",
    "sg:city":"Muttenz",
    "sg:orig_category":"Non-Classified Establishments",
    "sg:phone":"+41 61 461 52 55",
    "sg:postcode":"4132",
    "sg:province":"Basel-Landschaft",
    "wof:name":"Beteiligungsgesellschaft Zum Wartenberg",
    "wof:placetype":"venue"
},
  "geometry": {"coordinates":[7.6463990211,47.5245475769],"type":"Point"}
}