{
  "type": "Feature",
  "properties": {
    "iso:country":"CH",
    "sg:address":"Emmersbergstrasse 46",
    "sg:city":"Schaffhausen",
    "sg:orig_category":"Werbeagenturen Werbegrafikateliers",
    "sg:phone":"+41 52 625 17 17",
    "sg:postcode":"8200",
    "sg:province":"Schaffhausen",
    "wof:name":"Markus H\u00fcbscher Werbung & Grafik",
    "wof:placetype":"venue"
},
  "geometry": {"coordinates":[8.639787674,47.7012290955],"type":"Point"}
}