{
  "type": "Feature",
  "properties": {
    "iso:country":"CH",
    "sg:address":"Schaffhauserstrasse 18",
    "sg:city":"Frauenfeld",
    "sg:orig_category":"Werbung",
    "sg:phone":"+41 52 720 88 80",
    "sg:postcode":"8500",
    "sg:province":"Thurgau",
    "wof:name":"Bb Werbungs Und Verlags Ag",
    "wof:placetype":"venue"
},
  "geometry": {"coordinates":[8.8873023987,47.5615234375],"type":"Point"}
}