{
  "type": "Feature",
  "properties": {
    "iso:country":"CH",
    "sg:address":"Winterthurerstrasse 539",
    "sg:city":"Z\u00fcrich",
    "sg:orig_category":"Reparatur von elektrischen Haushaltsger\u00e4ten",
    "sg:phone":"+41 13212323",
    "sg:postcode":"8051",
    "sg:province":"Z\u00fcrich",
    "wof:name":"Bless Elektro",
    "wof:placetype":"venue"
},
  "geometry": {"coordinates":[8.5739555359,47.4042892456],"type":"Point"}
}