{
  "type": "Feature",
  "properties": {
    "iso:country":"CH",
    "sg:address":"Rue De La Porte-neuve 14",
    "sg:city":"Sitten",
    "sg:orig_category":"Detailhandel mit Geschenkartikeln U Souvenirs Fachdetailhandel in Verkaufsr\u00e4umen",
    "sg:phone":"+41 27 322 80 90",
    "sg:postcode":"1950",
    "sg:province":"Valais",
    "wof:name":"Petit Cadeau, Gill Claudia",
    "wof:placetype":"venue"
},
  "geometry": {"coordinates":[7.360309124,46.232219696],"type":"Point"}
}