{
  "type": "Feature",
  "properties": {
    "iso:country":"CH",
    "sg:address":"Strassacker 3",
    "sg:city":"Bolligen",
    "sg:orig_category":"Sonstige mit der Informatik verbundene T\u00e4tigkeiten",
    "sg:postcode":"3065",
    "sg:province":"Bern",
    "wof:name":"Sturm Consulting",
    "wof:placetype":"venue"
},
  "geometry": {"coordinates":[7.5023541451,46.9785041809],"type":"Point"}
}