{
  "type": "Feature",
  "properties": {
    "iso:country":"CH",
    "sg:address":"Rue Du Midi 15",
    "sg:city":"Aigle",
    "sg:orig_category":"Detailhandel mit Uhren U Schmuck Herstellung von Schmuck, Gold U Silberschmiedwaren",
    "sg:phone":"+41 24 466 65 88",
    "sg:postcode":"1860",
    "sg:province":"Vaud",
    "wof:name":"Krebs Fran\u00e7ois",
    "wof:placetype":"venue"
},
  "geometry": {"coordinates":[6.9681739807,46.3169670105],"type":"Point"}
}