{
  "type": "Feature",
  "properties": {
    "iso:country":"CH",
    "sg:address":"Via Vigno 3",
    "sg:city":"Mendrisio",
    "sg:orig_category":"Grosshandel mit Getr\u00e4nken Grosshandel mit Wein U Spirituosen",
    "sg:phone":"+41 91 646 40 21",
    "sg:postcode":"6850",
    "sg:province":"Ticino",
    "wof:name":"Casa Vinicola Gialdi Sa",
    "wof:placetype":"venue"
},
  "geometry": {"coordinates":[8.9825620651,45.8847732544],"type":"Point"}
}