{
  "type": "Feature",
  "properties": {
    "iso:country":"CH",
    "sg:address":"Zelgstrasse 79",
    "sg:city":"Uetendorf",
    "sg:orig_category":"Fleischverarbeitung",
    "sg:postcode":"3661",
    "sg:province":"Bern",
    "wof:name":"Lienhard P. Charcuterie.",
    "wof:placetype":"venue"
},
  "geometry": {"coordinates":[6.6853518486,46.5566101074],"type":"Point"}
}