{
  "type": "Feature",
  "properties": {
    "iso:country":"CH",
    "sg:address":"Ch. De La Muraille 11",
    "sg:city":"Vernier",
    "sg:orig_category":"Sonstiger Grosshandel",
    "sg:phone":"+41 22 906 40 80",
    "sg:postcode":"1214",
    "sg:province":"Gen\u00e8ve",
    "wof:name":"Distrimed S\u00e0rl",
    "wof:placetype":"venue"
},
  "geometry": {"coordinates":[6.1446180344,46.209022522],"type":"Point"}
}