{
  "type": "Feature",
  "properties": {
    "iso:country":"CH",
    "sg:address":"Pappelweg 5 3612 Steffisburg. Postfach 48",
    "sg:city":"Steffisburg",
    "sg:orig_category":"Sportvereine Landhockey",
    "sg:phone":"+41 33 437 48 38",
    "sg:postcode":"3612",
    "sg:province":"Bern",
    "wof:name":"Hc Steffisburg Hcst",
    "wof:placetype":"venue"
},
  "geometry": {"coordinates":[7.6409440041,46.7791061401],"type":"Point"}
}