{
  "type": "Feature",
  "properties": {
    "iso:country":"CH",
    "sg:address":"Baslerstrasse 70",
    "sg:city":"Rheinfelden",
    "sg:orig_category":"Fachdetailhandel in Verkaufsr\u00e4umen",
    "sg:postcode":"4310",
    "sg:province":"Aargau",
    "wof:name":"Schmuck Atelier Boissevain",
    "wof:placetype":"venue"
},
  "geometry": {"coordinates":[7.7763080597,47.5507583618],"type":"Point"}
}