{
  "type": "Feature",
  "properties": {
    "iso:country":"CH",
    "sg:address":"Aehrenweg 6",
    "sg:city":"Hombrechtikon",
    "sg:orig_category":"Architektur U Ingenieurb\u00fcros",
    "sg:phone":"+41 55 264 21 75",
    "sg:postcode":"8634",
    "sg:province":"Z\u00fcrich",
    "wof:name":"M\u00e4rki Informatik",
    "wof:placetype":"venue"
},
  "geometry": {"coordinates":[8.770348,47.249844],"type":"Point"}
}