{
  "type": "Feature",
  "properties": {
    "iso:country":"CH",
    "sg:address":"Belpstrasse 51 3007 Bern. Postfach",
    "sg:city":"Bern",
    "sg:orig_category":"RESTAURANTS: TEA-ROOMS",
    "sg:postcode":"3005",
    "sg:province":"Bern",
    "wof:name":"Andreas Kobel Rest. Frohegg",
    "wof:placetype":"venue"
},
  "geometry": {"coordinates":[7.431581974,46.9423713684],"type":"Point"}
}