{
  "type": "Feature",
  "properties": {
    "iso:country":"CH",
    "sg:address":"Servette Rue De La 81 1202 Gen\u00e8ve. Postfach",
    "sg:city":"Gen\u00e8ve",
    "sg:orig_category":"Fachdetailhandel in Verkaufsr\u00e4umen",
    "sg:phone":"+41 33 823 88 90",
    "sg:postcode":"1202",
    "sg:province":"Gen\u00e8ve",
    "wof:name":"Cosmos Sportswear Gmbh",
    "wof:placetype":"venue"
},
  "geometry": {"coordinates":[7.862033844,46.6795272827],"type":"Point"}
}