{
  "type": "Feature",
  "properties": {
    "iso:country":"CH",
    "sg:address":"Gemeindehaus Dorf 7 9127 Peterzell. Postfach",
    "sg:city":"Peterzell",
    "sg:orig_category":"Landesverteidigung, Sozialversicherung \u00d6ffentliche Verwaltung",
    "sg:phone":"+41 26 418 10 70",
    "sg:postcode":"9127",
    "sg:province":"St. Gallen",
    "wof:name":"Zivilschutzstelle St.silvester",
    "wof:placetype":"venue"
},
  "geometry": {"coordinates":[7.2211098671,46.7417182922],"type":"Point"}
}