{
  "type": "Feature",
  "properties": {
    "iso:country":"CH",
    "sg:address":"Chemin De La Motte 1",
    "sg:city":"Lausanne",
    "sg:orig_category":"Fachdetailhandel mit pharmazeutischen Produkten",
    "sg:phone":"+41 21 647 21 21",
    "sg:postcode":"1018",
    "sg:province":"Vaud",
    "wof:name":"Pharmacie De Bellevaux S\u00e0rl",
    "wof:placetype":"venue"
},
  "geometry": {"coordinates":[6.633728981,46.5331993103],"type":"Point"}
}