{
  "type": "Feature",
  "properties": {
    "iso:country":"CH",
    "sg:address":"Hauptstrasse 11",
    "sg:city":"M\u00e4rwil",
    "sg:classifiers":[
        {
            "category":"Wholesale",
            "subcategory":"Meat",
            "type":"Manufacturing & Wholesale Goods"
        }
    ],
    "sg:phone":"+41 71 654 65 10",
    "sg:postcode":"9562",
    "sg:province":"Thurgau",
    "sg:tags":[
        "chicken"
    ],
    "wof:name":"Sofri Gefl\u00fcgel Ag",
    "wof:placetype":"venue"
},
  "geometry": {"coordinates":[9.068138,47.532925],"type":"Point"}
}