{
  "type": "Feature",
  "properties": {
    "iso:country":"CH",
    "sg:address":"L\u00e4ngg\u00e4ssli 1",
    "sg:city":"Thun",
    "sg:orig_category":"Datenverarbeitungsdienste Finanzierungsinstitutionen",
    "sg:phone":"+41 33 336 62 54",
    "sg:postcode":"3604",
    "sg:province":"Bern",
    "wof:name":"Bkt Creative Ag",
    "wof:placetype":"venue"
},
  "geometry": {"coordinates":[7.612788,46.733021],"type":"Point"}
}