{
  "type": "Feature",
  "properties": {
    "iso:country":"CH",
    "sg:address":"Bahnhofstr.",
    "sg:city":"Raron",
    "sg:orig_category":"RESTAURANTS: TEA-ROOMS",
    "sg:phone":"+41 27 934 14 51",
    "sg:postcode":"3942",
    "sg:province":"Valais",
    "wof:name":"Zurbriggen-salzgeber, Restaurant Burg.",
    "wof:placetype":"venue"
},
  "geometry": {"coordinates":[7.8003549576,46.307308197],"type":"Point"}
}