{
  "type": "Feature",
  "properties": {
    "iso:country":"CH",
    "sg:address":"3803",
    "sg:city":"Beatenberg",
    "sg:orig_category":"Sportvereine Sch\u00fctzen",
    "sg:phone":"+41 33 841 18 76",
    "sg:postcode":"3803",
    "sg:province":"Bern",
    "wof:name":"Feldsch\u00fctzenges.beatenberg",
    "wof:placetype":"venue"
},
  "geometry": {"coordinates":[7.7930397987,46.6966781616],"type":"Point"}
}