{
  "type": "Feature",
  "properties": {
    "iso:country":"CH",
    "sg:address":"Schwab Rue Dr- 2",
    "sg:city":"St-imier",
    "sg:orig_category":"Unclassifiable Establishments",
    "sg:postcode":"2610",
    "sg:province":"Bern",
    "wof:name":"Mehowa Finanz, Beteiligungs Und Verwaltungs-ag",
    "wof:placetype":"venue"
},
  "geometry": {"coordinates":[9.1381845474,47.5666694641],"type":"Point"}
}