{
  "type": "Feature",
  "properties": {
    "iso:country":"CH",
    "sg:address":"Steinibachweg 3",
    "sg:city":"Zollikofen",
    "sg:orig_category":"Effektenvermittlung Broker Finanzierungsinstitutionen",
    "sg:phone":"+41 31 911 19 89",
    "sg:postcode":"3052",
    "sg:province":"Bern",
    "wof:name":"Sampex Capital Inc",
    "wof:placetype":"venue"
},
  "geometry": {"coordinates":[7.4583277702,46.9834480286],"type":"Point"}
}