{
  "type": "Feature",
  "properties": {
    "iso:country":"CH",
    "sg:address":"Thunstrasse 7",
    "sg:city":"Steffisburg",
    "sg:orig_category":"Reparatur von Schuhen U Lederwaren",
    "sg:phone":"+41 33 437 61 69",
    "sg:postcode":"3612",
    "sg:province":"Bern",
    "wof:name":"Paul Burri Schuhmacherei",
    "wof:placetype":"venue"
},
  "geometry": {"coordinates":[7.6317439079,46.7713928223],"type":"Point"}
}