{
  "type": "Feature",
  "properties": {
    "iso:country":"CH",
    "sg:address":"Oberfeldstrasse 111",
    "sg:city":"Winterthur",
    "sg:orig_category":"Unternehmensberatung",
    "sg:phone":"+41 81 302 81 44",
    "sg:postcode":"8408",
    "sg:province":"Z\u00fcrich",
    "wof:name":"Unternehmensberatung Partel",
    "wof:placetype":"venue"
},
  "geometry": {"coordinates":[9.5030212402,47.0102729797],"type":"Point"}
}