{
  "type": "Feature",
  "properties": {
    "iso:country":"CH",
    "sg:address":"Jurastrasse 22",
    "sg:city":"Biel/bienne",
    "sg:orig_category":"Detailhandel mit Fleisch U Fleischwaren",
    "sg:phone":"+41 32 342 45 76",
    "sg:postcode":"2502",
    "sg:province":"Bern",
    "wof:name":"Caterino Dipietro Metzgerei",
    "wof:placetype":"venue"
},
  "geometry": {"coordinates":[7.2488808632,47.1419372559],"type":"Point"}
}