{
  "type": "Feature",
  "properties": {
    "iso:country":"CH",
    "sg:address":"Oberschiltstr. 7",
    "sg:city":"Stansstad",
    "sg:orig_category":"Handels-H\u00e4user U Gesellschaften",
    "sg:postcode":"6362",
    "sg:province":"Nidwalden",
    "wof:name":"Kisa Sa",
    "wof:placetype":"venue"
},
  "geometry": {"coordinates":[8.3547210693,46.9845619202],"type":"Point"}
}