{
  "type": "Feature",
  "properties": {
    "iso:country":"CH",
    "sg:address":"S\u00e4gestrasse 35",
    "sg:city":"Dielsdorf",
    "sg:orig_category":"Non-Classified Establishments",
    "sg:postcode":"8157",
    "sg:province":"Z\u00fcrich",
    "wof:name":"Setsound - Reinert",
    "wof:placetype":"venue"
},
  "geometry": {"coordinates":[8.4492073059,47.4825668335],"type":"Point"}
}