{
  "type": "Feature",
  "properties": {
    "iso:country":"CH",
    "sg:address":"H\u00f6heweg 60 3626 H\u00fcnibach. Postfach",
    "sg:city":"H\u00fcnibach",
    "sg:orig_category":"Gesundheitswesen",
    "sg:phone":"+41 71 243 00 30",
    "sg:postcode":"3626",
    "sg:province":"Bern",
    "wof:name":"Radiologie Im Silberturm",
    "wof:placetype":"venue"
},
  "geometry": {"coordinates":[9.3951749802,47.4311218262],"type":"Point"}
}