{
  "type": "Feature",
  "properties": {
    "iso:country":"CH",
    "sg:address":"Aube Chemin De L'",
    "sg:city":"Albeuve",
    "sg:orig_category":"Sonstiger spezialisierter Hoch U Tiefbau",
    "sg:phone":"+41 26 928 27 24",
    "sg:postcode":"1669",
    "sg:province":"Fribourg",
    "wof:name":"Beaud Meinrad",
    "wof:placetype":"venue"
},
  "geometry": {"coordinates":[7.0558800697,46.5188217163],"type":"Point"}
}