{
  "type": "Feature",
  "properties": {
    "addr:full":"Worblentalstrasse 87 Ittigen Bern 3063",
    "addr:housenumber":"87",
    "addr:postcode":"3063",
    "addr:street":"Worblentalstrasse",
    "iso:country":"CH",
    "sg:address":"Worblentalstrasse 87",
    "sg:city":"Ittigen",
    "sg:orig_category":"Detailhandel mit Blumen U Pflanzen Fachdetailhandel in Verkaufsr\u00e4umen",
    "sg:phone":"+41 61 712 55 66",
    "sg:postcode":"3063",
    "sg:province":"Bern",
    "wof:name":"Blumenatelier Bl\u00fcten Und Bl\u00e4tter Gmbh",
    "wof:placetype":"venue"
},
  "geometry": {"coordinates":[7.594253,47.493484],"type":"Point"}
}