{
  "type": "Feature",
  "properties": {
    "iso:country":"CH",
    "sg:address":"Mythenstrasse 6 6003 Luzern. Postfach 3144",
    "sg:city":"Luzern",
    "sg:orig_category":"Vermittlung von Immobilien Wirtschaftspr\u00fcfung, Steuerberatung U Treuhand",
    "sg:phone":"+41 19373066",
    "sg:postcode":"6002",
    "sg:province":"Luzern",
    "wof:name":"L\u00e4tsch Treuhand Ag",
    "wof:placetype":"venue"
},
  "geometry": {"coordinates":[8.8461303711,47.3007392883],"type":"Point"}
}