{
  "type": "Feature",
  "properties": {
    "iso:country":"CH",
    "sg:address":"Jostenstrasse 2",
    "sg:city":"Galgenen",
    "sg:classifiers":[
        {
            "category":"Travel",
            "subcategory":"Hotels & Motels",
            "type":"Entertainment"
        }
    ],
    "sg:phone":"+41 79 440 82 91",
    "sg:postcode":"8854",
    "sg:province":"Schwyz",
    "sg:tags":[
        "hotels",
        "mit",
        "restaurant"
    ],
    "wof:name":"Gasthaus Blume, Ronner German",
    "wof:placetype":"venue"
},
  "geometry": {"coordinates":[8.8748416901,47.1807174683],"type":"Point"}
}