{
  "type": "Feature",
  "properties": {
    "iso:country":"CH",
    "sg:address":"Route Du Grand-mont 16",
    "sg:city":"Mont-sur-lausanne",
    "sg:orig_category":"Drogerien",
    "sg:phone":"+41 21 652 83 48",
    "sg:postcode":"1052",
    "sg:province":"Vaud",
    "wof:name":"Herv\u00e9 Burgener Pharmacie Du Mont",
    "wof:placetype":"venue"
},
  "geometry": {"coordinates":[6.6324248314,46.562461853],"type":"Point"}
}