{
  "type": "Feature",
  "properties": {
    "iso:country":"CH",
    "sg:address":"Route De La Conversion 155 1095 Ch\u00e2telard-lutry Case Postale 249",
    "sg:city":"Ch\u00e2telard-lutry",
    "sg:orig_category":"Unternehmensberatung Vermittlung von Immobilien",
    "sg:phone":"+41 21 791 15 46",
    "sg:postcode":"1095",
    "sg:province":"Vaud",
    "wof:name":"Alfred-h. Engel Cons.d'entreprises & Immob.",
    "wof:placetype":"venue"
},
  "geometry": {"coordinates":[6.6826019287,46.5088806152],"type":"Point"}
}