{
  "type": "Feature",
  "properties": {
    "iso:country":"CH",
    "sg:address":"Voie-romaine 3",
    "sg:city":"Cormondr\u00e8che",
    "sg:classifiers":[
        {
            "category":"Professional",
            "subcategory":"Employment Agencies",
            "type":"Services"
        }
    ],
    "sg:phone":"+41 32 730 10 06",
    "sg:postcode":"2036",
    "sg:province":"Neuch\u00e2tel",
    "sg:tags":[
        "personal",
        "u",
        "stellenvermittlung"
    ],
    "wof:name":"Kulczyki-wolczko & Cie Advise Network Knowledge",
    "wof:placetype":"venue"
},
  "geometry": {"coordinates":[6.8674039841,46.9828262329],"type":"Point"}
}