{
  "type": "Feature",
  "properties": {
    "iso:country":"CH",
    "sg:address":"Sornthalstr. 3 9213 Hauptwil. Postfach",
    "sg:city":"Hauptwil",
    "sg:orig_category":"Detailhandel mit Brot, Back U S\u00fcsswaren",
    "sg:phone":"+41 71 422 13 59",
    "sg:postcode":"9213",
    "sg:province":"Thurgau",
    "wof:name":"Schmid Franz",
    "wof:placetype":"venue"
},
  "geometry": {"coordinates":[9.250124,47.479214],"type":"Point"}
}