{
  "type": "Feature",
  "properties": {
    "iso:country":"CH",
    "sg:address":"Seestrasse 86",
    "sg:city":"Spiez",
    "sg:orig_category":"Architektur U Ingenieurb\u00fcros",
    "sg:phone":"+41 33546174",
    "sg:postcode":"3700",
    "sg:province":"Bern",
    "wof:name":"Neue Stadt 2000 Ag",
    "wof:placetype":"venue"
},
  "geometry": {"coordinates":[7.68736,46.688862],"type":"Point"}
}