{
  "type": "Feature",
  "properties": {
    "iso:country":"CH",
    "sg:address":"Wiesental",
    "sg:city":"Goldach",
    "sg:orig_category":"Sportvereine Ballsport Tennis",
    "sg:phone":"+41 24 445 11 96",
    "sg:postcode":"9403",
    "sg:province":"St. Gallen",
    "wof:name":"Tennisclub Grandson Courts",
    "wof:placetype":"venue"
},
  "geometry": {"coordinates":[6.6352858543,46.8035621643],"type":"Point"}
}