{
  "type": "Feature",
  "properties": {
    "iso:country":"CH",
    "sg:address":"Juchstrasse 43",
    "sg:city":"Matzingen",
    "sg:orig_category":"G\u00fcterbef\u00f6rderung im Strassenverkehr",
    "sg:phone":"+41 52 376 17 20",
    "sg:postcode":"9548",
    "sg:province":"Thurgau",
    "wof:name":"Improsa Ag",
    "wof:placetype":"venue"
},
  "geometry": {"coordinates":[8.9288043976,47.5233421326],"type":"Point"}
}