{
  "type": "Feature",
  "properties": {
    "iso:country":"CH",
    "sg:address":"Braunaustr. 161 8104 Weiningen Zh. Postfach",
    "sg:city":"Fahrweid",
    "sg:orig_category":"Herstellung von Fahrr\u00e4dern",
    "sg:postcode":"8951",
    "sg:province":"Z\u00fcrich",
    "wof:name":"Franz Laternser, Ersatzteile + Zubeh\u00f6r F\u00fcr Fahrr\u00e4der",
    "wof:placetype":"venue"
},
  "geometry": {"coordinates":[8.4348077774,47.4201469421],"type":"Point"}
}