{
  "type": "Feature",
  "properties": {
    "iso:country":"CH",
    "sg:address":"Mont-goulin Avenue De 27",
    "sg:city":"Prilly",
    "sg:orig_category":"Instandhaltung U Reparatur von Automobilen",
    "sg:phone":"+41 21 925 36 66",
    "sg:postcode":"1008",
    "sg:province":"Vaud",
    "wof:name":"Garage De La Veveyse Sa",
    "wof:placetype":"venue"
},
  "geometry": {"coordinates":[6.8626499176,46.4653282166],"type":"Point"}
}