{
  "type": "Feature",
  "properties": {
    "iso:country":"CH",
    "sg:address":"Dorfstrasse 87",
    "sg:city":"Geroldswil",
    "sg:orig_category":"Hochschulen U h\u00f6here Ausbildung",
    "sg:phone":"+41 55 266 16 16",
    "sg:postcode":"8954",
    "sg:province":"Z\u00fcrich",
    "wof:name":"Martin Muheim, Dtp & Ebv, Beratung, Schulung, Support",
    "wof:placetype":"venue"
},
  "geometry": {"coordinates":[8.9413003922,47.2884101868],"type":"Point"}
}