{
  "type": "Feature",
  "properties": {
    "iso:country":"CH",
    "sg:address":"Gasometerstrasse 20",
    "sg:city":"Z\u00fcrich",
    "sg:classifiers":[
        {
            "category":"Restaurant",
            "type":"Food & Drink"
        }
    ],
    "sg:phone":"+41 12713990",
    "sg:postcode":"8005",
    "sg:province":"Z\u00fcrich",
    "wof:name":"Restaurant Eisenhof",
    "wof:placetype":"venue"
},
  "geometry": {"coordinates":[8.5287122726,47.3835830688],"type":"Point"}
}