{
  "type": "Feature",
  "properties": {
    "addr:full":"St\u00e4dtchenstrasse 87 Sargans St. Gallen 7320",
    "addr:housenumber":"87",
    "addr:postcode":"7320",
    "addr:street":"Staedtchenstrasse",
    "iso:country":"CH",
    "sg:address":"St\u00e4dtchenstrasse 87",
    "sg:city":"Sargans",
    "sg:orig_category":"Bauschreinerei",
    "sg:phone":"+41 81 723 19 26",
    "sg:postcode":"7320",
    "sg:province":"St. Gallen",
    "wof:name":"Kassian Locher Mechanische Schreinerei",
    "wof:placetype":"venue"
},
  "geometry": {"coordinates":[9.433176,47.0509],"type":"Point"}
}