{
  "type": "Feature",
  "properties": {
    "iso:country":"CH",
    "sg:address":"Rue Des Moulins 4",
    "sg:city":"Travers",
    "sg:orig_category":"Handel mit Automobilteilen U Zubeh\u00f6r",
    "sg:phone":"+41 32 863 16 16",
    "sg:postcode":"2105",
    "sg:province":"Neuch\u00e2tel",
    "wof:name":"Ernesto Piccirilli Garage Ep Automobile",
    "wof:placetype":"venue"
},
  "geometry": {"coordinates":[6.6718392372,46.9386291504],"type":"Point"}
}