{
  "type": "Feature",
  "properties": {
    "iso:country":"CH",
    "sg:address":"6487",
    "sg:city":"G\u00f6schenen",
    "sg:orig_category":"Elektrizit\u00e4tsversorgung",
    "sg:phone":"+41 41 885 14 54",
    "sg:postcode":"6487",
    "sg:province":"Uri",
    "wof:name":"Kraftwerk G\u00f6schenen Ag",
    "wof:placetype":"venue"
},
  "geometry": {"coordinates":[8.5886049271,46.6678733826],"type":"Point"}
}