{
  "type": "Feature",
  "properties": {
    "iso:country":"CH",
    "sg:address":"Mettstrasse 6",
    "sg:city":"Biel/bienne",
    "sg:orig_category":"Sportvereine Ballsport Handball",
    "sg:phone":"+41 81 725 30 30",
    "sg:postcode":"2503",
    "sg:province":"Bern",
    "wof:name":"Hc Mels",
    "wof:placetype":"venue"
},
  "geometry": {"coordinates":[9.4134464264,47.0568504333],"type":"Point"}
}