{
  "type": "Feature",
  "properties": {
    "iso:country":"CH",
    "sg:address":"Hauptstrasse 57",
    "sg:city":"Magden",
    "sg:orig_category":"Detailhandel mit Fleisch U Fleischwaren",
    "sg:phone":"+41 32 484 01 08",
    "sg:postcode":"4312",
    "sg:province":"Aargau",
    "wof:name":"Tschanz Robert, Boucherie-charcuterie Sa",
    "wof:placetype":"venue"
},
  "geometry": {"coordinates":[7.1378297806,47.2788200378],"type":"Point"}
}