{
  "type": "Feature",
  "properties": {
    "addr:full":"Rorschacher Strasse 38 L\u00fcchingen St. Gallen 9450",
    "addr:housenumber":"38;st.",
    "addr:postcode":"9450",
    "addr:street":"Rorschacher Strasse",
    "iso:country":"CH",
    "sg:address":"Rorschacher Strasse 38",
    "sg:city":"L\u00fcchingen",
    "sg:orig_category":"Aktivit\u00e4ten der Generalunternehmen im Baugewerbe Vermittlung von Immobilien",
    "sg:postcode":"9450",
    "sg:province":"St. Gallen",
    "wof:name":"S & L Architektur Ag",
    "wof:placetype":"venue"
},
  "geometry": {"coordinates":[9.547372,47.381935],"type":"Point"}
}