{
  "type": "Feature",
  "properties": {
    "addr:full":"Ruhbergstrasse 57a St.gallen St. Gallen 9000",
    "addr:housenumber":"57a",
    "addr:postcode":"9000",
    "addr:street":"Ruhbergstrasse",
    "iso:country":"CH",
    "sg:address":"Ruhbergstrasse 57a",
    "sg:city":"St.gallen",
    "sg:orig_category":"Bauschreinerei Herstellung von Konstruktionsteilen, Fertigbauteilen U Ausbauelementen aus Holz",
    "sg:phone":"+41 71 277 80 20",
    "sg:postcode":"9000",
    "sg:province":"St. Gallen",
    "wof:name":"Spiess Ernst",
    "wof:placetype":"venue"
},
  "geometry": {"coordinates":[9.364442,47.415447],"type":"Point"}
}