{
  "type": "Feature",
  "properties": {
    "iso:country":"CH",
    "sg:address":"Rue Du Valentin 30",
    "sg:city":"Lausanne",
    "sg:orig_category":"Tanzschulen, Tanzlehrer",
    "sg:phone":"+41 21 323 49 29",
    "sg:postcode":"1004",
    "sg:province":"Vaud",
    "wof:name":"Gilbert Martin Ballroom Dancing Club Of Ls",
    "wof:placetype":"venue"
},
  "geometry": {"coordinates":[6.6318998337,46.5241012573],"type":"Point"}
}