{
  "type": "Feature",
  "properties": {
    "iso:country":"CH",
    "sg:address":"Rue Rochette 12",
    "sg:city":"Estavayer-le-lac",
    "sg:orig_category":"Offsetdruck",
    "sg:phone":"+41 26 663 15 07",
    "sg:postcode":"1470",
    "sg:province":"Fribourg",
    "wof:name":"Goumaz - Calley Sa Imprimerie",
    "wof:placetype":"venue"
},
  "geometry": {"coordinates":[6.8454589844,46.8501052856],"type":"Point"}
}