{
  "type": "Feature",
  "properties": {
    "iso:country":"CH",
    "sg:address":"Bellevuestrasse 10",
    "sg:city":"Wettingen",
    "sg:orig_category":"Window Renovation",
    "sg:phone":"+41 56 427 27 72",
    "sg:postcode":"5430",
    "sg:province":"Aargau",
    "wof:name":"Peter Jetzer",
    "wof:placetype":"venue"
},
  "geometry": {"coordinates":[8.3398418427,47.4622001648],"type":"Point"}
}