{
  "type": "Feature",
  "properties": {
    "iso:country":"CH",
    "sg:address":"Theaterstrasse 4 4051 Basel. Postfach",
    "sg:city":"Basel",
    "sg:orig_category":"Vermittlung von Immobilien Wirtschaftspr\u00fcfung, Steuerberatung U Treuhand",
    "sg:phone":"+41 21 311 32 00",
    "sg:postcode":"4051",
    "sg:province":"Basel-Stadt",
    "wof:name":"Cofiducia Sa",
    "wof:placetype":"venue"
},
  "geometry": {"coordinates":[6.6318440437,46.522857666],"type":"Point"}
}