{
  "type": "Feature",
  "properties": {
    "addr:full":"Emmenholzweg 33 Zuchwil Solothurn 4528",
    "addr:housenumber":"33",
    "addr:postcode":"4528",
    "addr:street":"Emmenholzweg",
    "iso:country":"CH",
    "sg:address":"Emmenholzweg 33",
    "sg:city":"Zuchwil",
    "sg:orig_category":"Arztpraxen",
    "sg:phone":"+41 32 685 23 53",
    "sg:postcode":"4528",
    "sg:province":"Solothurn",
    "wof:name":"Dr.med.stephan Von Arx Arzt F.allgemeine Medizin Fmh",
    "wof:placetype":"venue"
},
  "geometry": {"coordinates":[7.559986,47.213139],"type":"Point"}
}