{
  "type": "Feature",
  "properties": {
    "iso:country":"CH",
    "sg:address":"Dorfstrasse 65 8805 Richterswil. Postfach",
    "sg:city":"Richterswil",
    "sg:orig_category":"Grosshandel mit Textilien",
    "sg:phone":"+41 17844166",
    "sg:postcode":"8805",
    "sg:province":"Z\u00fcrich",
    "wof:name":"Ag Mietlich, Richterswil",
    "wof:placetype":"venue"
},
  "geometry": {"coordinates":[8.7040624619,47.2090530396],"type":"Point"}
}