{
  "type": "Feature",
  "properties": {
    "iso:country":"CH",
    "sg:address":"Kirchweg 2",
    "sg:city":"Tafers",
    "sg:orig_category":"Museen",
    "sg:phone":"+41 26 494 25 31",
    "sg:postcode":"1712",
    "sg:province":"Fribourg",
    "wof:name":"Heimatmuseum Des Sensebezirks",
    "wof:placetype":"venue"
},
  "geometry": {"coordinates":[7.2167987823,46.8151245117],"type":"Point"}
}