{
  "type": "Feature",
  "properties": {
    "iso:country":"CH",
    "sg:address":"Caznerwiesen",
    "sg:city":"Thusis",
    "sg:orig_category":"Instandhaltung U Reparatur von Automobilen",
    "sg:phone":"+41 81 651 32 64",
    "sg:postcode":"7430",
    "sg:province":"Graubunden",
    "wof:name":"Sibilia G.",
    "wof:placetype":"venue"
},
  "geometry": {"coordinates":[9.4392318726,46.7119674683],"type":"Point"}
}