{
  "type": "Feature",
  "properties": {
    "iso:country":"CH",
    "sg:address":"Gewerbestrasse 1",
    "sg:city":"Lyssach",
    "sg:orig_category":"Herstellung von Medikamenten U sonstigen pharmazeutischen Erzeugnissen",
    "sg:phone":"+41 34 445 40 66",
    "sg:postcode":"3421",
    "sg:province":"Bern",
    "wof:name":"Provet Ag",
    "wof:placetype":"venue"
},
  "geometry": {"coordinates":[7.5825080872,47.0797729492],"type":"Point"}
}