{
  "type": "Feature",
  "properties": {
    "iso:country":"CH",
    "sg:address":"Av. Des Boveresses 50",
    "sg:city":"Lausanne",
    "sg:classifiers":[
        {
            "category":"Utilities",
            "subcategory":"Telephone",
            "type":"Services"
        }
    ],
    "sg:phone":"+41 4117506688",
    "sg:postcode":"1010",
    "sg:province":"Vaud",
    "sg:tags":[
        "telecommunication"
    ],
    "wof:name":"Media Engineering M Stocker",
    "wof:placetype":"venue"
},
  "geometry": {"coordinates":[8.4269008636,47.4182319641],"type":"Point"}
}