{
  "type": "Feature",
  "properties": {
    "iso:country":"CH",
    "sg:address":"Reverdil Avenue 4",
    "sg:city":"Nyon",
    "sg:orig_category":"Softwareentwicklung U beratung",
    "sg:phone":"+41 21 683 25 54",
    "sg:postcode":"1260",
    "sg:province":"Vaud",
    "wof:name":"Azicom S.\u00e0 R.l.",
    "wof:placetype":"venue"
},
  "geometry": {"coordinates":[6.2339959145,46.382358551],"type":"Point"}
}