{
  "type": "Feature",
  "properties": {
    "iso:country":"CH",
    "sg:address":"4412",
    "sg:city":"Nuglar",
    "sg:orig_category":"Vereine Musik/Blasmusik",
    "sg:postcode":"4412",
    "sg:province":"Solothurn",
    "wof:name":"Musikgesellschaft",
    "wof:placetype":"venue"
},
  "geometry": {"coordinates":[7.6901831627,47.4607582092],"type":"Point"}
}