{
  "type": "Feature",
  "properties": {
    "iso:country":"CH",
    "sg:address":"Avenue De Lavaux 24",
    "sg:city":"Pully",
    "sg:orig_category":"Herstellung von konfektionierten Textilwaren ohne Bekleidung",
    "sg:phone":"+41 21 729 69 81",
    "sg:postcode":"1009",
    "sg:province":"Vaud",
    "wof:name":"Atelier Du V\u00eatement Magnani A.",
    "wof:placetype":"venue"
},
  "geometry": {"coordinates":[6.6560502052,46.5123405457],"type":"Point"}
}