{
  "type": "Feature",
  "properties": {
    "iso:country":"CH",
    "sg:address":"Steinstrasse 35 8003 Z\u00fcrich. Postfach",
    "sg:city":"Z\u00fcrich",
    "sg:orig_category":"Grosshandel mit Software Softwareentwicklung U beratung",
    "sg:phone":"+41 14511662",
    "sg:postcode":"8003",
    "sg:province":"Z\u00fcrich",
    "wof:name":"Immopac Ag Waren, Bes. Softwareprodukte; Handel. Produkteentwicklung, Dienstleistungen Im Informatikbereich",
    "wof:placetype":"venue"
},
  "geometry": {"coordinates":[8.520318985,47.3669395447],"type":"Point"}
}