{
  "type": "Feature",
  "properties": {
    "addr:full":"Lauriedstrasse 7 6300 Zug. Postfach 329 Zug Zug 6301",
    "addr:housenumber":"7;329",
    "addr:postcode":"6300;6301",
    "addr:street":"Lauriedstrasse;Postfach;Zug",
    "iso:country":"CH",
    "sg:address":"Lauriedstrasse 7 6300 Zug. Postfach 329",
    "sg:city":"Zug",
    "sg:orig_category":"Architektur U Ingenieurb\u00fcros",
    "sg:postcode":"6301",
    "sg:province":"Zug",
    "wof:name":"Plano Architekturb\u00fcro M\u00fcntener W.",
    "wof:placetype":"venue"
},
  "geometry": {"coordinates":[9.487285,47.149467],"type":"Point"}
}