{
  "type": "Feature",
  "properties": {
    "iso:country":"CH",
    "sg:address":"Poststrasse 6",
    "sg:city":"Wigoltingen",
    "sg:orig_category":"Kantonalbanken",
    "sg:phone":"+41 52 763 20 21",
    "sg:postcode":"8556",
    "sg:province":"Thurgau",
    "wof:name":"Thurgauer Kantonalbank",
    "wof:placetype":"venue"
},
  "geometry": {"coordinates":[9.0312337875,47.598274231],"type":"Point"}
}