{
  "type": "Feature",
  "properties": {
    "iso:country":"CH",
    "sg:address":"Hauptstrasse",
    "sg:city":"Gr\u00fcnenmatt",
    "sg:classifiers":[
        {
            "category":"Restaurant",
            "type":"Food & Drink"
        }
    ],
    "sg:phone":"+41 34 431 14 55",
    "sg:postcode":"3452",
    "sg:province":"Bern",
    "wof:name":"Restaurant L\u00f6wen",
    "wof:placetype":"venue"
},
  "geometry": {"coordinates":[7.7228679657,47.0094337463],"type":"Point"}
}