{
  "type": "Feature",
  "properties": {
    "iso:country":"CH",
    "sg:address":"Kasernenstrasse 95",
    "sg:city":"Chur",
    "sg:orig_category":"Pensionskassen",
    "sg:phone":"+41 81 257 00 20",
    "sg:postcode":"7000",
    "sg:province":"Graubunden",
    "wof:name":"Hilfsfonds Der Firma Br\u00fcniger & Co., Ingenieurb\u00fcro",
    "wof:placetype":"venue"
},
  "geometry": {"coordinates":[9.519949913,46.8467330933],"type":"Point"}
}