{
  "type": "Feature",
  "properties": {
    "iso:country":"CH",
    "sg:address":"Via Povr\u00f2 16",
    "sg:city":"Massagno",
    "sg:orig_category":"Fa\u00e7ade Glazing",
    "sg:phone":"+41 91 966 90 32",
    "sg:postcode":"6900",
    "sg:province":"Ticino",
    "wof:name":"Mescoli Sagl",
    "wof:placetype":"venue"
},
  "geometry": {"coordinates":[8.9391403198,46.0149002075],"type":"Point"}
}