{
  "type": "Feature",
  "properties": {
    "iso:country":"CH",
    "sg:address":"Pl\u00e4nkestrasse 6",
    "sg:city":"Biel/bienne",
    "sg:orig_category":"Finanzierungsinstitutionen Wirtschaftspr\u00fcfung, Steuerberatung U Treuhand",
    "sg:phone":"+41 32 322 12 11",
    "sg:postcode":"2502",
    "sg:province":"Bern",
    "wof:name":"Young 4 Young Masson Gmbh",
    "wof:placetype":"venue"
},
  "geometry": {"coordinates":[7.2430071831,47.1363372803],"type":"Point"}
}