{
  "type": "Feature",
  "properties": {
    "addr:full":"Zumhofweg 2 Kriens Luzern 6010",
    "addr:housenumber":"2",
    "addr:postcode":"6010",
    "addr:street":"Zumhofweg",
    "iso:country":"CH",
    "sg:address":"Zumhofweg 2",
    "sg:city":"Kriens",
    "sg:orig_category":"Allgemeiner Hoch U Tiefbau Hoch U Tiefbau",
    "sg:phone":"+41 91 945 22 60",
    "sg:postcode":"6010",
    "sg:province":"Luzern",
    "wof:name":"Edilbau Sa",
    "wof:placetype":"venue"
},
  "geometry": {"coordinates":[8.950507,46.060902],"type":"Point"}
}