{
  "type": "Feature",
  "properties": {
    "iso:country":"CH",
    "sg:address":"Oberseeburg 48 6006 Luzern. Postfach",
    "sg:city":"Luzern",
    "sg:orig_category":"Sonstiger Grosshandel",
    "sg:postcode":"6003",
    "sg:province":"Luzern",
    "wof:name":"Wallace Global Trading Warenhandel",
    "wof:placetype":"venue"
},
  "geometry": {"coordinates":[8.3486013412,47.0508232117],"type":"Point"}
}