{
  "type": "Feature",
  "properties": {
    "iso:country":"CH",
    "sg:address":"Schulhausweg 10 5442 Fislisbach. Postfach 85",
    "sg:city":"Fislisbach",
    "sg:orig_category":"Wirtschaftspr\u00fcfung, Steuerberatung U Treuhand",
    "sg:postcode":"5442",
    "sg:province":"Aargau",
    "wof:name":"Fga - Fiduciaire De Gestion Et D'audit, Andr\u00e9 Cattin",
    "wof:placetype":"venue"
},
  "geometry": {"coordinates":[7.0049629211,47.2118835449],"type":"Point"}
}