{
  "type": "Feature",
  "properties": {
    "iso:country":"CH",
    "sg:address":"Puits-godet Rue Du 8",
    "sg:city":"Neuch\u00e2tel",
    "sg:orig_category":"Einbau von Schreinerwaren",
    "sg:postcode":"2000",
    "sg:province":"Neuch\u00e2tel",
    "wof:name":"Cappuccino Ag",
    "wof:placetype":"venue"
},
  "geometry": {"coordinates":[6.9140100479,46.9987220764],"type":"Point"}
}