{
  "type": "Feature",
  "properties": {
    "iso:country":"CH",
    "sg:address":"Austrasse 2",
    "sg:city":"Vaduz",
    "sg:classifiers":[
        {
            "category":"Restaurant",
            "type":"Food & Drink"
        }
    ],
    "sg:postcode":"9490",
    "wof:name":"Restaurant Au",
    "wof:placetype":"venue"
},
  "geometry": {"coordinates":[9.5220327377,47.1323013306],"type":"Point"}
}