{
  "type": "Feature",
  "properties": {
    "iso:country":"CH",
    "sg:address":"Grand-rue 23 Bis",
    "sg:city":"Peseux",
    "sg:orig_category":"Unclassifiable Establishments",
    "sg:phone":"+41 32 730 35 11",
    "sg:postcode":"2034",
    "sg:province":"Neuch\u00e2tel",
    "wof:name":"Pro'fusion Ducommun Yannick",
    "wof:placetype":"venue"
},
  "geometry": {"coordinates":[6.8893518448,46.987575531],"type":"Point"}
}