{
  "type": "Feature",
  "properties": {
    "iso:country":"CH",
    "sg:address":"Avenue De France 6 1950 Sion. Postfach 148",
    "sg:city":"Sion",
    "sg:orig_category":"Zahnarztpraxen",
    "sg:phone":"+41 27 322 64 55",
    "sg:postcode":"1951",
    "sg:province":"Valais",
    "wof:name":"Drs M\u00e9d.dent. Barras & Muresan M\u00e9decins-dentistes",
    "wof:placetype":"venue"
},
  "geometry": {"coordinates":[7.358235836,46.228187561],"type":"Point"}
}