{
  "type": "Feature",
  "properties": {
    "iso:country":"CH",
    "sg:address":"Schlossstrasse 115b",
    "sg:city":"Bern",
    "sg:orig_category":"Detailhandel mit Waren verschiedener Art, Hauptrichtung Nahrungsmittel",
    "sg:phone":"+41 31 381 87 76",
    "sg:postcode":"3008",
    "sg:province":"Bern",
    "wof:name":"Coop Center Holligen",
    "wof:placetype":"venue"
},
  "geometry": {"coordinates":[7.4123430252,46.9438781738],"type":"Point"}
}