{
  "type": "Feature",
  "properties": {
    "iso:country":"CH",
    "sg:address":"Chemin De Chantemerle",
    "sg:city":"Neuch\u00e2tel",
    "sg:orig_category":"Detailhandel mit Zeitungen U Zeitschriften Kioske",
    "sg:phone":"+41 32 724 65 41",
    "sg:postcode":"2000",
    "sg:province":"Neuch\u00e2tel",
    "wof:name":"Annette Mermoud Kiosque Du Pont-du-mail",
    "wof:placetype":"venue"
},
  "geometry": {"coordinates":[6.9467320442,46.9996566772],"type":"Point"}
}