{
  "type": "Feature",
  "properties": {
    "iso:country":"CH",
    "sg:address":"Willisauerstrasse 16",
    "sg:city":"Menznau",
    "sg:orig_category":"Autogaragen",
    "sg:phone":"+41 79 342 01 41",
    "sg:postcode":"6122",
    "sg:province":"Luzern",
    "wof:name":"Stirnimann Ag Garage",
    "wof:placetype":"venue"
},
  "geometry": {"coordinates":[8.037557,47.085945],"type":"Point"}
}