{
  "type": "Feature",
  "properties": {
    "iso:country":"CH",
    "sg:address":"Aschoren 6454 Fl\u00fcelen. Postfach",
    "sg:city":"Fl\u00fcelen",
    "sg:orig_category":"G\u00fcterbef\u00f6rderung im Strassenverkehr",
    "sg:phone":"+41 41 870 24 50",
    "sg:postcode":"6454",
    "sg:province":"Uri",
    "wof:name":"Wipfli Ag",
    "wof:placetype":"venue"
},
  "geometry": {"coordinates":[8.6228246689,46.8975715637],"type":"Point"}
}