{
  "type": "Feature",
  "properties": {
    "iso:country":"CH",
    "sg:address":"Ringstrasse 16",
    "sg:city":"Frauenfeld",
    "sg:orig_category":"Kultur\u00e4mter",
    "sg:phone":"+41 52 721 45 61",
    "sg:postcode":"8500",
    "sg:province":"Thurgau",
    "wof:name":"Denkmalpflege Thurgau",
    "wof:placetype":"venue"
},
  "geometry": {"coordinates":[8.9027318954,47.5558166504],"type":"Point"}
}