{
  "type": "Feature",
  "properties": {
    "iso:country":"CH",
    "sg:address":"Sornard",
    "sg:city":"Haute-nendaz",
    "sg:orig_category":"Malerei",
    "sg:phone":"+41 27 288 26 87",
    "sg:postcode":"1997",
    "sg:province":"Valais",
    "wof:name":"Pierre Fournier Entreprise De Peinture",
    "wof:placetype":"venue"
},
  "geometry": {"coordinates":[7.298746109,46.1898498535],"type":"Point"}
}