{
  "type": "Feature",
  "properties": {
    "iso:country":"CH",
    "sg:address":"Rehweg 4 3097 Liebefeld. Postfach",
    "sg:city":"Liebefeld",
    "sg:orig_category":"Architektur U Ingenieurb\u00fcros",
    "sg:postcode":"3097",
    "sg:province":"Bern",
    "wof:name":"Casa Cadplanung Gmbh Cadpl\u00e4ne; Herstellung. Architektur-arbeiten Usw.",
    "wof:placetype":"venue"
},
  "geometry": {"coordinates":[7.424407,46.932842],"type":"Point"}
}