{
  "type": "Feature",
  "properties": {
    "iso:country":"CH",
    "sg:address":"M\u00fclibachstrasse 34",
    "sg:city":"Richterswil",
    "sg:orig_category":"Malerei Tapeziererei",
    "sg:phone":"+41 79 691 31 33",
    "sg:postcode":"8805",
    "sg:province":"Z\u00fcrich",
    "wof:name":"Fernando Corradini Maler-& Tapezierergesch\u00e4ft",
    "wof:placetype":"venue"
},
  "geometry": {"coordinates":[8.7006759644,47.2041893005],"type":"Point"}
}