{
  "type": "Feature",
  "properties": {
    "iso:country":"CH",
    "sg:address":"Via Gaggini Da Bissone 14 6900 Lugano. Postfach Caselle Postale 2699",
    "sg:city":"Lugano",
    "sg:orig_category":"Sportvereine Landhockey",
    "sg:phone":"+41 91 994 43 07",
    "sg:postcode":"6901",
    "sg:province":"Ticino",
    "wof:name":"Hockey Club Lugano Sa Gestione Sportiva, Finanziaria Ecc",
    "wof:placetype":"venue"
},
  "geometry": {"coordinates":[8.9447889328,45.9959754944],"type":"Point"}
}