{
  "type": "Feature",
  "properties": {
    "iso:country":"CH",
    "sg:address":"4314 Zeiningen. Postfach",
    "sg:city":"Zeiningen",
    "sg:orig_category":"Sportvereine Ballsport Fussball",
    "sg:phone":"+41 61 851 19 08",
    "sg:postcode":"4314",
    "sg:province":"Aargau",
    "wof:name":"Fc Zeiningen",
    "wof:placetype":"venue"
},
  "geometry": {"coordinates":[7.8723649979,47.542678833],"type":"Point"}
}