{
  "type": "Feature",
  "properties": {
    "iso:country":"CH",
    "sg:address":"Via Santeri 11 7130 Ilanz. Postfach",
    "sg:city":"Ilanz",
    "sg:orig_category":"Gartenbau",
    "sg:phone":"+41 79 218 29 09",
    "sg:postcode":"7130",
    "sg:province":"Graubunden",
    "wof:name":"Cultira Sa",
    "wof:placetype":"venue"
},
  "geometry": {"coordinates":[9.1999263763,46.7730560303],"type":"Point"}
}