{
  "type": "Feature",
  "properties": {
    "iso:country":"CH",
    "sg:address":"Haus Engelfrid",
    "sg:city":"Regensberg",
    "sg:orig_category":"Interessenvertretungen",
    "sg:phone":"+41 18531366",
    "sg:postcode":"8158",
    "sg:province":"Z\u00fcrich",
    "wof:name":"Stiftung G\u00fcnthart-maag Lotte Und Willi",
    "wof:placetype":"venue"
},
  "geometry": {"coordinates":[8.4363718033,47.4825248718],"type":"Point"}
}