{
  "type": "Feature",
  "properties": {
    "iso:country":"CH",
    "sg:address":"Badstrasse 4",
    "sg:city":"Baden",
    "sg:orig_category":"Kosmetikinstitute",
    "sg:phone":"+41 56 493 47 84",
    "sg:postcode":"5400",
    "sg:province":"Aargau",
    "wof:name":"Stephanie Aebischer Kosmetikinstitut",
    "wof:placetype":"venue"
},
  "geometry": {"coordinates":[8.2878103256,47.4519195557],"type":"Point"}
}