{
  "type": "Feature",
  "properties": {
    "iso:country":"CH",
    "sg:address":"Im Oberfeld 4",
    "sg:city":"Amlikon",
    "sg:orig_category":"Herstellung von elektronischen Bauelementen",
    "sg:phone":"+41 32 913 76 14",
    "sg:postcode":"8514",
    "sg:province":"Thurgau",
    "wof:name":"Swisstouch S\u00e0rl",
    "wof:placetype":"venue"
},
  "geometry": {"coordinates":[6.8174991608,47.1012077332],"type":"Point"}
}