{
  "type": "Feature",
  "properties": {
    "iso:country":"CH",
    "sg:address":"Gottstattstrasse 24",
    "sg:city":"Biel/bienne",
    "sg:orig_category":"Unternehmensberatung",
    "sg:phone":"+41 41 630 44 70",
    "sg:postcode":"2504",
    "sg:province":"Bern",
    "wof:name":"Logitron Ag",
    "wof:placetype":"venue"
},
  "geometry": {"coordinates":[8.3073587418,46.9956970215],"type":"Point"}
}