{
  "type": "Feature",
  "properties": {
    "addr:full":"Moosbr\u00fcnneli 5 Sins Aargau 5643",
    "addr:housenumber":"5",
    "addr:postcode":"5643",
    "addr:street":"Moosbruenneli",
    "iso:country":"CH",
    "sg:address":"Moosbr\u00fcnneli 5",
    "sg:city":"Sins",
    "sg:orig_category":"Dachdeckerei Zimmerei, Dachdeckerei, Bauspenglerei U Abdichtung",
    "sg:phone":"+41 41 787 06 06",
    "sg:postcode":"5643",
    "sg:province":"Aargau",
    "wof:name":"Wyder Bedachungen",
    "wof:placetype":"venue"
},
  "geometry": {"coordinates":[8.384152,47.191841],"type":"Point"}
}