{
  "type": "Feature",
  "properties": {
    "iso:country":"CH",
    "sg:address":"Messeplatz 1 4058 Basel. Postfach",
    "sg:city":"Basel",
    "sg:orig_category":"Messeorganisationen Sonstige Finanzierungsinstitutionen",
    "sg:phone":"+41 61 686 20 20",
    "sg:postcode":"4021",
    "wof:name":"Mch Messe Schweiz Ag",
    "wof:placetype":"venue"
},
  "geometry": {"coordinates":[7.5995140076,47.5636901855],"type":"Point"}
}