{
  "type": "Feature",
  "properties": {
    "iso:country":"CH",
    "sg:address":"Castelver Chemin 2",
    "sg:city":"Veyrier",
    "sg:orig_category":"Dienstleistungen von Beteiligungsgesellschaften",
    "sg:postcode":"1255",
    "sg:province":"Gen\u00e8ve",
    "wof:name":"Team-timing, Charles Andr\u00e9 Roh",
    "wof:placetype":"venue"
},
  "geometry": {"coordinates":[6.1876478195,46.1664543152],"type":"Point"}
}