{
  "type": "Feature",
  "properties": {
    "iso:country":"CH",
    "sg:address":"Feldstrasse 24 8004 Z\u00fcrich. Postfach",
    "sg:city":"Z\u00fcrich",
    "sg:orig_category":"Non-Classified Establishments",
    "sg:postcode":"8004",
    "sg:province":"Z\u00fcrich",
    "wof:name":"Carpenteria Bernet Sa",
    "wof:placetype":"venue"
},
  "geometry": {"coordinates":[9.0057678223,45.8628349304],"type":"Point"}
}