{
  "type": "Feature",
  "properties": {
    "iso:country":"CH",
    "sg:address":"Rue De Pr\u00e9-fleuri 5",
    "sg:city":"Sion",
    "sg:orig_category":"Architektur U Ingenieurb\u00fcros",
    "sg:phone":"+41 27 329 09 90",
    "sg:postcode":"1950",
    "sg:province":"Valais",
    "wof:name":"Mat\u00e9riel \u00e9lectrique Lamon",
    "wof:placetype":"venue"
},
  "geometry": {"coordinates":[7.356769,46.228737],"type":"Point"}
}