{
  "type": "Feature",
  "properties": {
    "iso:country":"CH",
    "sg:address":"Avenue Bertrand 20",
    "sg:city":"Gen\u00e8ve",
    "sg:orig_category":"Vorschulen, Kinderg\u00e4rten",
    "sg:phone":"+41 22 346 97 01",
    "sg:postcode":"1206",
    "sg:province":"Gen\u00e8ve",
    "wof:name":"Ecole Enfantine Bertrand I-v",
    "wof:placetype":"venue"
},
  "geometry": {"coordinates":[6.1570291519,46.194606781],"type":"Point"}
}