{
  "type": "Feature",
  "properties": {
    "iso:country":"CH",
    "sg:address":"Amriswilerstrasse 52 8589 Sitterdorf. Postfach",
    "sg:city":"Sitterdorf",
    "sg:orig_category":"RESTAURANTS: TEA-ROOMS",
    "sg:postcode":"8589",
    "sg:province":"Thurgau",
    "wof:name":"E. & R. Bonnichon",
    "wof:placetype":"venue"
},
  "geometry": {"coordinates":[9.2471818924,47.5023574829],"type":"Point"}
}