{
  "type": "Feature",
  "properties": {
    "addr:full":"Tribschenstrasse 38 6005 Luzern. Postfach Luzern Luzern 6003",
    "addr:housenumber":"38",
    "addr:postcode":"6005;postfach;6003",
    "addr:street":"Tribschenstrasse",
    "iso:country":"CH",
    "sg:address":"Tribschenstrasse 38 6005 Luzern. Postfach",
    "sg:city":"Luzern",
    "sg:orig_category":"Architektur U Ingenieurb\u00fcros",
    "sg:phone":"+41 41 361 04 24",
    "sg:postcode":"6003",
    "sg:province":"Luzern",
    "wof:name":"Bl\u00e4ttler Bauplanung Gmbh Bauplanungs, Bauleitungsb\u00fcro",
    "wof:placetype":"venue"
},
  "geometry": {"coordinates":[8.314673,47.042976],"type":"Point"}
}