{
  "type": "Feature",
  "properties": {
    "iso:country":"CH",
    "sg:address":"Chemin Du Fr\u00eane 9",
    "sg:city":"Lausanne",
    "sg:orig_category":"P\u00e9dicure",
    "sg:phone":"+41 21 648 10 02",
    "sg:postcode":"1004",
    "sg:province":"Vaud",
    "wof:name":"Elsy Loup P\u00e9dicure",
    "wof:placetype":"venue"
},
  "geometry": {"coordinates":[6.627933979,46.5253982544],"type":"Point"}
}