{
  "type": "Feature",
  "properties": {
    "iso:country":"CH",
    "sg:address":"Kirchgasse 25",
    "sg:city":"Olten",
    "sg:orig_category":"Non-Classified Establishments",
    "sg:postcode":"4600",
    "sg:province":"Solothurn",
    "wof:name":"Schneider Elektro, Solar, \u00d6kologie",
    "wof:placetype":"venue"
},
  "geometry": {"coordinates":[8.1798152924,46.7494354248],"type":"Point"}
}