{
  "type": "Feature",
  "properties": {
    "iso:country":"CH",
    "sg:address":"Rikonerstrasse 22",
    "sg:city":"Effretikon",
    "sg:orig_category":"Druck ohne Zeitungsdruck Offsetdruck",
    "sg:phone":"+41 52 355 19 50",
    "sg:postcode":"8307",
    "sg:province":"Z\u00fcrich",
    "wof:name":"Sommertype Ag Offsetdruckerei",
    "wof:placetype":"venue"
},
  "geometry": {"coordinates":[8.6871747971,47.4298057556],"type":"Point"}
}