{
  "type": "Feature",
  "properties": {
    "addr:full":"Schwalbenweg 57 Frauenfeld Thurgau 8500",
    "addr:housenumber":"57",
    "addr:postcode":"8500",
    "addr:street":"Schwalbenweg",
    "iso:country":"CH",
    "sg:address":"Schwalbenweg 57",
    "sg:city":"Frauenfeld",
    "sg:orig_category":"Architekturb\u00fcros",
    "sg:phone":"+41 52 720 70 73",
    "sg:postcode":"8500",
    "sg:province":"Thurgau",
    "wof:name":"Peter Frei Architekturb\u00fcro",
    "wof:placetype":"venue"
},
  "geometry": {"coordinates":[8.90049,47.551361],"type":"Point"}
}