{
  "type": "Feature",
  "properties": {
    "iso:country":"CH",
    "sg:address":"Via Al Dosso 1",
    "sg:city":"Mendrisio",
    "sg:orig_category":"Geb\u00e4ude, Wohnungsreinigung",
    "sg:phone":"+41 61 701 37 37",
    "sg:postcode":"6850",
    "sg:province":"Ticino",
    "wof:name":"Fix Helvetia Gmbh",
    "wof:placetype":"venue"
},
  "geometry": {"coordinates":[7.6148738861,47.4765357971],"type":"Point"}
}