{
  "type": "Feature",
  "properties": {
    "iso:country":"CH",
    "sg:address":"Route De Morges 25",
    "sg:city":"St-prex",
    "sg:orig_category":"Werbeagenturen",
    "sg:phone":"+41 21 806 44 45",
    "sg:postcode":"1162",
    "sg:province":"Vaud",
    "wof:name":"Smart Communications Sa",
    "wof:placetype":"venue"
},
  "geometry": {"coordinates":[6.4650521278,46.4889526367],"type":"Point"}
}