{
  "type": "Feature",
  "properties": {
    "iso:country":"CH",
    "sg:address":"Belpbergstrasse 5a",
    "sg:city":"M\u00fcnsingen",
    "sg:orig_category":"Elektroinstallation",
    "sg:phone":"+41 31 701 10 81",
    "sg:postcode":"3110",
    "sg:province":"Bern",
    "wof:name":"Uwer Michael, Neutrale Elektroplanung",
    "wof:placetype":"venue"
},
  "geometry": {"coordinates":[7.5615038872,46.8727989197],"type":"Point"}
}