{
  "type": "Feature",
  "properties": {
    "addr:full":"Sch\u00fcracherstrasse 42 Br\u00fcttisellen 8602 Wangen Zh. Postfach Br\u00fcttisellen Z\u00fcrich 8306",
    "addr:housenumber":"42",
    "addr:postcode":"8602;8306",
    "addr:street":"Schueracherstrasse;Zuerich",
    "iso:country":"CH",
    "sg:address":"Sch\u00fcracherstrasse 42 Br\u00fcttisellen 8602 Wangen Zh. Postfach",
    "sg:city":"Br\u00fcttisellen",
    "sg:orig_category":"Allgemeiner Hoch U Tiefbau",
    "sg:postcode":"8306",
    "sg:province":"Z\u00fcrich",
    "wof:name":"Schumacher Bau Ag",
    "wof:placetype":"venue"
},
  "geometry": {"coordinates":[8.645645,47.410656],"type":"Point"}
}