{
  "type": "Feature",
  "properties": {
    "addr:full":"G\u00fcterstrasse 147 Basel Basel-Stadt 4053",
    "addr:housenumber":"147",
    "addr:postcode":"4053",
    "addr:street":"Gueterstrasse",
    "iso:country":"CH",
    "sg:address":"G\u00fcterstrasse 147",
    "sg:city":"Basel",
    "sg:orig_category":"Detailhandel mit Antiquit\u00e4ten",
    "sg:phone":"+41 61 271 08 76",
    "sg:postcode":"4053",
    "sg:province":"Basel-Stadt",
    "wof:name":"Tamara Pfau Antiquit\u00e4ten",
    "wof:placetype":"venue"
},
  "geometry": {"coordinates":[7.590056,47.544704],"type":"Point"}
}