{
  "type": "Feature",
  "properties": {
    "iso:country":"CH",
    "sg:address":"Delsbergerstrasse 120",
    "sg:city":"Laufen",
    "sg:orig_category":"Sportvereine Turnen Damen",
    "sg:phone":"+41 61 761 78 00",
    "sg:postcode":"4242",
    "sg:province":"Basel-Landschaft",
    "wof:name":"Damenturnverein Stv Laufen",
    "wof:placetype":"venue"
},
  "geometry": {"coordinates":[7.4993491173,47.416973114],"type":"Point"}
}