{
  "type": "Feature",
  "properties": {
    "iso:country":"CH",
    "sg:address":"Heckenweg 27 3007 Bern. Postfach",
    "sg:city":"Bern",
    "sg:orig_category":"Maler U Glasergewerbe",
    "sg:phone":"+41 31 978 17 17",
    "sg:postcode":"3005",
    "sg:province":"Bern",
    "wof:name":"Meyer & Co., Malerei Und Gipserei",
    "wof:placetype":"venue"
},
  "geometry": {"coordinates":[7.4308300018,46.9333000183],"type":"Point"}
}