{
  "type": "Feature",
  "properties": {
    "iso:country":"CH",
    "sg:address":"Avenue De Montbenon 2 1003 Lausanne Case Postale 2435",
    "sg:city":"Lausanne",
    "sg:orig_category":"Konsulate",
    "sg:phone":"+41 21 351 13 00",
    "sg:postcode":"1002",
    "sg:province":"Vaud",
    "wof:name":"Consulat G\u00e9n\u00e9ral De Su\u00e8de",
    "wof:placetype":"venue"
},
  "geometry": {"coordinates":[6.6285300255,46.5197067261],"type":"Point"}
}