{
  "type": "Feature",
  "properties": {
    "iso:country":"CH",
    "sg:address":"Schachenstrasse 30",
    "sg:city":"Oberg\u00f6sgen",
    "sg:orig_category":"Fernmeldedienste",
    "sg:postcode":"4653",
    "sg:province":"Solothurn",
    "wof:name":"Fernsehgenossenschaft Oberg\u00f6sgen",
    "wof:placetype":"venue"
},
  "geometry": {"coordinates":[7.952753067,47.3625183105],"type":"Point"}
}