{
  "type": "Feature",
  "properties": {
    "iso:country":"CH",
    "sg:address":"Sch\u00f6neggweg 26 Goldau 6415 Arth. Postfach",
    "sg:city":"Goldau",
    "sg:orig_category":"Gesundheitswesen",
    "sg:postcode":"6410",
    "sg:province":"Schwyz",
    "wof:name":"Probst Daniel Naturheilpraxis",
    "wof:placetype":"venue"
},
  "geometry": {"coordinates":[8.5223703384,47.0628089905],"type":"Point"}
}