{
  "type": "Feature",
  "properties": {
    "iso:country":"CH",
    "sg:address":"R\u00f6ssligasse 17",
    "sg:city":"Muttenz",
    "sg:orig_category":"Erschliessung von Grundst\u00fccken",
    "sg:postcode":"4132",
    "sg:province":"Basel-Landschaft",
    "wof:name":"Wohnbaugenossenschaft Rote Leu",
    "wof:placetype":"venue"
},
  "geometry": {"coordinates":[7.6497340202,47.5250320435],"type":"Point"}
}