{
  "type": "Feature",
  "properties": {
    "iso:country":"CH",
    "sg:address":"Gorgenstrasse 2 6074 Giswil. Postfach 68",
    "sg:city":"Giswil",
    "sg:orig_category":"Bauschreinerei Herstellung von Sportger\u00e4ten",
    "sg:phone":"+41 41 675 11 31",
    "sg:postcode":"6074",
    "sg:province":"Obwalden",
    "wof:name":"Mathis Sport Und Schreinerei Gmbh",
    "wof:placetype":"venue"
},
  "geometry": {"coordinates":[8.188562,46.838165],"type":"Point"}
}