{
  "type": "Feature",
  "properties": {
    "iso:country":"CH",
    "sg:address":"Tour Chemin De La 27",
    "sg:city":"Meyrin",
    "sg:orig_category":"Instandhaltung U Reparatur von Automobilen",
    "sg:postcode":"1217",
    "sg:province":"Gen\u00e8ve",
    "wof:name":"Carrosserie Quiblier",
    "wof:placetype":"venue"
},
  "geometry": {"coordinates":[6.080370903,46.2385673523],"type":"Point"}
}