{
  "type": "Feature",
  "properties": {
    "iso:country":"CH",
    "sg:address":"St. Urbanstrasse 4",
    "sg:city":"Langenthal",
    "sg:orig_category":"Detailhandel mit Tabakwaren Grosshandel mit Tabakwaren",
    "sg:phone":"+41 62 922 31 55",
    "sg:postcode":"4900",
    "sg:province":"Bern",
    "wof:name":"Zigarrenstube Egger",
    "wof:placetype":"venue"
},
  "geometry": {"coordinates":[7.7899980545,47.2118606567],"type":"Point"}
}