{
  "type": "Feature",
  "properties": {
    "iso:country":"CH",
    "sg:address":"Sihlhaldenstrasse 1c 8136 Gattikon. Postfach",
    "sg:city":"Gattikon",
    "sg:orig_category":"Markt U Meinungsforschung",
    "sg:postcode":"8136",
    "sg:province":"Z\u00fcrich",
    "wof:name":"Zimmermann Barbara",
    "wof:placetype":"venue"
},
  "geometry": {"coordinates":[8.5502586365,47.2849617004],"type":"Point"}
}