{
  "type": "Feature",
  "properties": {
    "iso:country":"CH",
    "sg:address":"Sagenstrasse 29",
    "sg:city":"Walchwil",
    "sg:orig_category":"Sonstiger Grosshandel",
    "sg:phone":"+41 41 758 01 21",
    "sg:postcode":"6318",
    "sg:province":"Zug",
    "wof:name":"Madons Gmbh",
    "wof:placetype":"venue"
},
  "geometry": {"coordinates":[8.5119180679,47.1044998169],"type":"Point"}
}