{
  "type": "Feature",
  "properties": {
    "iso:country":"CH",
    "sg:address":"Via Serafino Balestra 7",
    "sg:city":"Lugano",
    "sg:orig_category":"Verwaltung von Immobilien",
    "sg:phone":"+41 61 963 92 10",
    "sg:postcode":"6900",
    "sg:province":"Ticino",
    "wof:name":"Gki Handels Und Immobilien Gmbh",
    "wof:placetype":"venue"
},
  "geometry": {"coordinates":[7.7498478889,47.3910903931],"type":"Point"}
}