{
  "type": "Feature",
  "properties": {
    "addr:full":"Kernstrasse 10 8004 Z\u00fcrich. Postfach 1639 Z\u00fcrich Z\u00fcrich 8026",
    "addr:housenumber":"10",
    "addr:postcode":"8004 zuerich. postfach 1639;8026",
    "addr:street":"Kernstrasse",
    "iso:country":"CH",
    "sg:address":"Kernstrasse 10 8004 Z\u00fcrich. Postfach 1639",
    "sg:city":"Z\u00fcrich",
    "sg:orig_category":"Advokaturb\u00fcros",
    "sg:phone":"+41 12411060",
    "sg:postcode":"8026",
    "sg:province":"Z\u00fcrich",
    "wof:name":"Ren\u00e9 Horlacher Advokaturb\u00fcro",
    "wof:placetype":"venue"
},
  "geometry": {"coordinates":[8.523966,47.375309],"type":"Point"}
}