{
  "type": "Feature",
  "properties": {
    "iso:country":"CH",
    "sg:address":"Thunstrasse 54 3110 M\u00fcnsingen. Postfach 2009",
    "sg:city":"M\u00fcnsingen",
    "sg:orig_category":"Allgemeiner Gartenbau Dauerkulturbau",
    "sg:phone":"+41 71 474 70 70",
    "sg:postcode":"3110",
    "sg:province":"Bern",
    "wof:name":"H\u00e4berli Obst Und Beerenzentrum Ag",
    "wof:placetype":"venue"
},
  "geometry": {"coordinates":[9.369273,47.528889],"type":"Point"}
}