{
  "type": "Feature",
  "properties": {
    "iso:country":"CH",
    "sg:address":"V\u00f6geling\u00e4sschen 56",
    "sg:city":"Schaffhausen",
    "sg:orig_category":"Fachdetailhandel in Verkaufsr\u00e4umen",
    "sg:phone":"+41 52 624 83 76",
    "sg:postcode":"8200",
    "sg:province":"Schaffhausen",
    "wof:name":"Fahr Hannes",
    "wof:placetype":"venue"
},
  "geometry": {"coordinates":[8.6639900208,47.6881484985],"type":"Point"}
}