{
  "type": "Feature",
  "properties": {
    "iso:country":"CH",
    "sg:address":"Kalkbreitestrasse 136",
    "sg:city":"Z\u00fcrich",
    "sg:orig_category":"Elektroinstallation",
    "sg:phone":"+41 14623888",
    "sg:postcode":"8003",
    "sg:province":"Z\u00fcrich",
    "wof:name":"Hans Ramseier Elektro-installationsgesch\u00e4ft",
    "wof:placetype":"venue"
},
  "geometry": {"coordinates":[8.5137662888,47.3706016541],"type":"Point"}
}