{
  "type": "Feature",
  "properties": {
    "iso:country":"CH",
    "sg:address":"Freiburgstrasse 348 3018 Bern. Postfach",
    "sg:city":"Bern",
    "sg:orig_category":"Sonstiger Grosshandel",
    "sg:phone":"+41 71 274 00 10",
    "sg:postcode":"3018",
    "sg:province":"Bern",
    "wof:name":"Oivt Gmbh Leistungen Im Medienbereich U. Im Grafischen Gewerbe Usw",
    "wof:placetype":"venue"
},
  "geometry": {"coordinates":[9.267829895,46.8157691956],"type":"Point"}
}