{
  "type": "Feature",
  "properties": {
    "iso:country":"CH",
    "sg:address":"Dorfbachstrasse 5",
    "sg:city":"Schwyz",
    "sg:orig_category":"Softwareentwicklung U beratung",
    "sg:postcode":"6430",
    "sg:province":"Schwyz",
    "wof:name":"Stephan Schlegel, Sts Elektronik/informatik",
    "wof:placetype":"venue"
},
  "geometry": {"coordinates":[8.6584186554,47.0223121643],"type":"Point"}
}