{
  "type": "Feature",
  "properties": {
    "iso:country":"CH",
    "sg:address":"Stockistrasse 11 8192 Glattfelden. Postfach",
    "sg:city":"Glattfelden",
    "sg:orig_category":"Reiseb\u00fcros U Reiseveranstalter",
    "sg:postcode":"8192",
    "sg:province":"Z\u00fcrich",
    "wof:name":"Stoll Travel Service Reisedienstleistungen U. Organisation Von Reisen Usw",
    "wof:placetype":"venue"
},
  "geometry": {"coordinates":[8.4998006821,47.5574913025],"type":"Point"}
}