{
  "type": "Feature",
  "properties": {
    "iso:country":"CH",
    "sg:address":"3098 K\u00f6niz. Postfach",
    "sg:city":"Mittelh\u00e4usern",
    "sg:orig_category":"Allgemeiner Hoch U Tiefbau",
    "sg:phone":"+41 41 372 16 00",
    "sg:postcode":"3147",
    "sg:province":"Bern",
    "wof:name":"Bp, Bianchi & Partner Gmbh",
    "wof:placetype":"venue"
},
  "geometry": {"coordinates":[8.356977,47.054745],"type":"Point"}
}