{
  "type": "Feature",
  "properties": {
    "iso:country":"CH",
    "sg:address":"Scheidwegstrasse 20",
    "sg:city":"St.gallen",
    "sg:orig_category":"Maler U Glasergewerbe Malerei",
    "sg:phone":"+41 27 932 11 45",
    "sg:postcode":"9000",
    "sg:province":"St. Gallen",
    "wof:name":"Gnesa Roman, Maler- + Sandstrahlarbeiten",
    "wof:placetype":"venue"
},
  "geometry": {"coordinates":[7.7446789742,46.3072509766],"type":"Point"}
}