{
  "type": "Feature",
  "properties": {
    "iso:country":"CH",
    "sg:address":"6802",
    "sg:city":"Rivera",
    "sg:orig_category":"Personenbef\u00f6rderung im Linienverkehr zu Land",
    "sg:phone":"+41 91 946 11 21",
    "sg:postcode":"6802",
    "sg:province":"Ticino",
    "wof:name":"Ghezzi Giorgio E Roberto",
    "wof:placetype":"venue"
},
  "geometry": {"coordinates":[8.9231395721,46.1164894104],"type":"Point"}
}