{
  "type": "Feature",
  "properties": {
    "iso:country":"CH",
    "sg:address":"Chemin De La Baume 12 2533 Evilard Case Postale 39",
    "sg:city":"Evilard",
    "sg:orig_category":"Herstellung anderer Uhrenbestandteile Herstellung der Ausstattung von Uhren",
    "sg:phone":"+41 32 323 86 44",
    "sg:postcode":"2533",
    "sg:province":"Bern",
    "wof:name":"Karl Hartmann Fabrication De Pierres Fines",
    "wof:placetype":"venue"
},
  "geometry": {"coordinates":[7.2375650406,47.1483078003],"type":"Point"}
}