{
  "type": "Feature",
  "properties": {
    "iso:country":"CH",
    "sg:address":"Obernauerstrasse 89",
    "sg:city":"Kriens",
    "sg:orig_category":"Kauf U Verkauf von Immobilien auf eigene Rechnung",
    "sg:postcode":"6010",
    "sg:province":"Luzern",
    "wof:name":"Obim Ag",
    "wof:placetype":"venue"
},
  "geometry": {"coordinates":[8.2624702454,47.0348815918],"type":"Point"}
}