{
  "type": "Feature",
  "properties": {
    "iso:country":"CH",
    "sg:address":"Irchelstr. 25",
    "sg:city":"Rorbas-freienstein",
    "sg:classifiers":[
        {
            "category":"Manufacturing",
            "subcategory":"Metals",
            "type":"Manufacturing & Wholesale Goods"
        }
    ],
    "sg:phone":"+41 4118668181",
    "sg:postcode":"8427",
    "sg:province":"Z\u00fcrich",
    "sg:tags":[
        "metallurgy",
        "metalworking",
        "processing"
    ],
    "wof:name":"Xaloy Ag",
    "wof:placetype":"venue"
},
  "geometry": {"coordinates":[8.5813026428,47.5329055786],"type":"Point"}
}