{
  "type": "Feature",
  "properties": {
    "iso:country":"CH",
    "sg:address":"B\u00f6hnirain 11 8800 Thalwil. Postfach",
    "sg:city":"Thalwil",
    "sg:orig_category":"Markt U Meinungsforschung",
    "sg:phone":"+41 848 808 157",
    "sg:postcode":"8800",
    "sg:province":"Z\u00fcrich",
    "wof:name":"Ppm Phone Promotion & Marketing Ag",
    "wof:placetype":"venue"
},
  "geometry": {"coordinates":[8.5642871857,47.2840461731],"type":"Point"}
}