{
  "type": "Feature",
  "properties": {
    "addr:full":"Grosszelgstrasse 20 W\u00fcrenlos Aargau 5436",
    "addr:housenumber":"20",
    "addr:postcode":"5436",
    "addr:street":"Grosszelgstrasse",
    "iso:country":"CH",
    "sg:address":"Grosszelgstrasse 20",
    "sg:city":"W\u00fcrenlos",
    "sg:orig_category":"Bauschreinerei Innenausbau",
    "sg:phone":"+41 56 424 24 74",
    "sg:postcode":"5436",
    "sg:province":"Aargau",
    "wof:name":"Ki Design Ag",
    "wof:placetype":"venue"
},
  "geometry": {"coordinates":[8.357056,47.445183],"type":"Point"}
}