{
  "type": "Feature",
  "properties": {
    "addr:full":"Kirchgasse 20 Russikon Z\u00fcrich 8332",
    "addr:housenumber":"20",
    "addr:postcode":"8332",
    "addr:street":"Kirchgasse",
    "iso:country":"CH",
    "sg:address":"Kirchgasse 20",
    "sg:city":"Russikon",
    "sg:orig_category":"Bauspenglerei Zimmerei, Dachdeckerei, Bauspenglerei U Abdichtung",
    "sg:phone":"+41 19540947",
    "sg:postcode":"8332",
    "sg:province":"Z\u00fcrich",
    "wof:name":"Neuenschwander Heinz",
    "wof:placetype":"venue"
},
  "geometry": {"coordinates":[8.775355,47.395527],"type":"Point"}
}