{
  "type": "Feature",
  "properties": {
    "iso:country":"CH",
    "sg:address":"Z\u00fcrcherstrasse 237",
    "sg:city":"Frauenfeld",
    "sg:orig_category":"Architektur U Ingenieurb\u00fcros",
    "sg:phone":"+41 52 722 45 15",
    "sg:postcode":"8500",
    "sg:province":"Thurgau",
    "wof:name":"Zapag Arzuma Ag Engineering Consulting",
    "wof:placetype":"venue"
},
  "geometry": {"coordinates":[8.901703,47.56002],"type":"Point"}
}