{
  "type": "Feature",
  "properties": {
    "iso:country":"CH",
    "sg:address":"Zugerstrasse 36 8816 Hirzel. Postfach",
    "sg:city":"Hirzel",
    "sg:orig_category":"Wirtschaftspr\u00fcfung, Steuerberatung U Treuhand",
    "sg:phone":"+41 17299262",
    "sg:postcode":"8816",
    "sg:province":"Z\u00fcrich",
    "wof:name":"Isac Consulting Walder & Co Treuhandb\u00fcro, Beratung Auf Diesem Gebiet",
    "wof:placetype":"venue"
},
  "geometry": {"coordinates":[8.6106176376,47.215801239],"type":"Point"}
}