{
  "type": "Feature",
  "properties": {
    "iso:country":"CH",
    "sg:address":"Obergasse 1",
    "sg:city":"Bischofszell",
    "sg:orig_category":"Werbegrafikateliers",
    "sg:phone":"+41 71 420 07 77",
    "sg:postcode":"9220",
    "sg:province":"Thurgau",
    "wof:name":"Helena Vicentini Grafisches Atelier",
    "wof:placetype":"venue"
},
  "geometry": {"coordinates":[9.2418222427,47.4939231873],"type":"Point"}
}