{
  "type": "Feature",
  "properties": {
    "iso:country":"CH",
    "sg:address":"Hauptstrasse 24",
    "sg:city":"Binningen",
    "sg:orig_category":"Solarien",
    "sg:phone":"+41 61 421 14 74",
    "sg:postcode":"4102",
    "sg:province":"Basel-Landschaft",
    "wof:name":"Marianne Klodel Solarium",
    "wof:placetype":"venue"
},
  "geometry": {"coordinates":[7.5746049881,47.5425796509],"type":"Point"}
}