{
  "type": "Feature",
  "properties": {
    "iso:country":"CH",
    "sg:address":"D\u00fcbendorfstrasse 339",
    "sg:city":"Z\u00fcrich",
    "sg:orig_category":"Non-Classified Establishments",
    "sg:postcode":"8051",
    "sg:province":"Z\u00fcrich",
    "wof:name":"Caf\u00e9-conditorei Sp\u00f6rri Teufen Ag",
    "wof:placetype":"venue"
},
  "geometry": {"coordinates":[9.3885755539,47.3904495239],"type":"Point"}
}