{
  "type": "Feature",
  "properties": {
    "iso:country":"CH",
    "sg:address":"Untere Lettenstrasse 3",
    "sg:city":"Adliswil",
    "sg:orig_category":"Fahrschulen, Flugschulen",
    "sg:phone":"+41 32 931 27 25",
    "sg:postcode":"8134",
    "sg:province":"Z\u00fcrich",
    "wof:name":"Maurice Jacot Auto-\u00e9cole",
    "wof:placetype":"venue"
},
  "geometry": {"coordinates":[6.742620945,47.0554504395],"type":"Point"}
}