{
  "type": "Feature",
  "properties": {
    "iso:country":"CH",
    "sg:address":"Riaz Route De 1630 Bulle. Postfach",
    "sg:city":"Bulle",
    "sg:orig_category":"Pensionskassen",
    "sg:phone":"+41 26 913 63 33",
    "sg:postcode":"1630",
    "sg:province":"Fribourg",
    "wof:name":"Fonds De Pr\u00e9voyance En Faveur Du Personnel De La Maison E. Glasson & Cie Sa",
    "wof:placetype":"venue"
},
  "geometry": {"coordinates":[7.0573811531,46.6186027527],"type":"Point"}
}