{
  "type": "Feature",
  "properties": {
    "iso:country":"CH",
    "sg:address":"6928",
    "sg:city":"Manno",
    "sg:orig_category":"Gartenbau",
    "sg:phone":"+41 81 322 65 62",
    "sg:postcode":"6928",
    "sg:province":"Ticino",
    "wof:name":"Schaniel N., Chnurli-garten",
    "wof:placetype":"venue"
},
  "geometry": {"coordinates":[9.5770788193,46.9832305908],"type":"Point"}
}