{
  "type": "Feature",
  "properties": {
    "iso:country":"CH",
    "sg:address":"Via Monnet 8",
    "sg:city":"Vernier",
    "sg:orig_category":"Vermietung U Verpachtung von eigenen Immobilien",
    "sg:postcode":"1214",
    "sg:province":"Gen\u00e8ve",
    "wof:name":"Virex Sa",
    "wof:placetype":"venue"
},
  "geometry": {"coordinates":[6.0820851326,46.2177886963],"type":"Point"}
}