{
  "type": "Feature",
  "properties": {
    "iso:country":"CH",
    "sg:address":"Pelzacker 245",
    "sg:city":"Staffelbach",
    "sg:orig_category":"Saunas, Solarien, Fitnesszentren U \u00e4hnliches",
    "sg:phone":"+41 62 721 27 28",
    "sg:postcode":"5053",
    "sg:province":"Aargau",
    "wof:name":"Sauna Staffelbach",
    "wof:placetype":"venue"
},
  "geometry": {"coordinates":[8.0499267578,47.2836837769],"type":"Point"}
}