{
  "type": "Feature",
  "properties": {
    "iso:country":"CH",
    "sg:address":"Jargonnant Rue De 2 1207 Gen\u00e8ve. Postfach",
    "sg:city":"Gen\u00e8ve",
    "sg:orig_category":"Pensionskassen",
    "sg:phone":"+41 32 720 09 00",
    "sg:postcode":"1201",
    "sg:province":"Gen\u00e8ve",
    "wof:name":"Fondation De Pr\u00e9voyance Du Centre Suisse D'electronique Et De Microtechnique Sa Recherche Et D\u00e9veloppement",
    "wof:placetype":"venue"
},
  "geometry": {"coordinates":[6.9453201294,46.9974517822],"type":"Point"}
}