{
  "type": "Feature",
  "properties": {
    "iso:country":"CH",
    "sg:address":"Zi Route De Berne Nord",
    "sg:city":"Br\u00fcgg",
    "sg:classifiers":[
        {
            "category":"Communications",
            "subcategory":"Newspaper",
            "type":"Services"
        }
    ],
    "sg:phone":"+41 21 966 81 81",
    "sg:postcode":"2555",
    "sg:province":"Bern",
    "sg:tags":[
        "printing",
        "publishing"
    ],
    "wof:name":"Imprimerie Corbaz Sa",
    "wof:placetype":"venue"
},
  "geometry": {"coordinates":[6.9138278961,46.4307937622],"type":"Point"}
}