{
  "type": "Feature",
  "properties": {
    "iso:country":"CH",
    "sg:address":"Chirchb\u00fcnt",
    "sg:city":"Sevelen",
    "sg:orig_category":"Vermietung U Verpachtung von eigenen Immobilien",
    "sg:postcode":"9475",
    "sg:province":"St. Gallen",
    "wof:name":"Spitz Immobilien Ag",
    "wof:placetype":"venue"
},
  "geometry": {"coordinates":[9.4863901138,47.122795105],"type":"Point"}
}