{
  "type": "Feature",
  "properties": {
    "iso:country":"CH",
    "sg:address":"Schindellegistrasse 3",
    "sg:city":"Freienbach",
    "sg:orig_category":"Unternehmensberatung",
    "sg:phone":"+41 56 241 23 24",
    "sg:postcode":"8807",
    "sg:province":"Schwyz",
    "wof:name":"Gup, Gemoets Unternehmensberatung Und Projekte",
    "wof:placetype":"venue"
},
  "geometry": {"coordinates":[8.7582454681,47.195098877],"type":"Point"}
}