{
  "type": "Feature",
  "properties": {
    "iso:country":"CH",
    "sg:address":"M\u00fcselweg 10",
    "sg:city":"Sarmenstorf",
    "sg:orig_category":"Gesundheitswesen",
    "sg:postcode":"5614",
    "sg:province":"Aargau",
    "wof:name":"Xel-ha Gmbh",
    "wof:placetype":"venue"
},
  "geometry": {"coordinates":[8.2511224747,47.3052597046],"type":"Point"}
}