{
  "type": "Feature",
  "properties": {
    "iso:country":"CH",
    "sg:address":"Hauptstrasse 32",
    "sg:city":"Bellmund",
    "sg:orig_category":"Bauspenglerei Zimmerei, Dachdeckerei, Bauspenglerei U Abdichtung",
    "sg:phone":"+41 32 331 73 68",
    "sg:postcode":"2564",
    "sg:province":"Bern",
    "wof:name":"K\u00fcffer Paul",
    "wof:placetype":"venue"
},
  "geometry": {"coordinates":[7.245446,47.105953],"type":"Point"}
}