{
  "type": "Feature",
  "properties": {
    "iso:country":"CH",
    "sg:address":"Landis + Gyr-strasse 1 6300 Zug. Postfach",
    "sg:city":"Zug",
    "sg:orig_category":"Softwareentwicklung U beratung",
    "sg:postcode":"6300",
    "sg:province":"Zug",
    "wof:name":"Pixel Paradise Ag Entwicklung Von Informationstechnologien, Die Der F\u00f6rderung Des Dialogs Zwischen Handel U. Verbraucher Dienen Im Hard, Softwarebereich",
    "wof:placetype":"venue"
},
  "geometry": {"coordinates":[8.5122509003,47.1759338379],"type":"Point"}
}