{
  "type": "Feature",
  "properties": {
    "iso:country":"CH",
    "sg:address":"Wiesenstrasse 13",
    "sg:city":"Effretikon",
    "sg:orig_category":"Erschliessung von Grundst\u00fccken",
    "sg:phone":"+41 52 343 50 70",
    "sg:postcode":"8307",
    "sg:province":"Z\u00fcrich",
    "wof:name":"Wohnbaugenos.effretikon-illnau",
    "wof:placetype":"venue"
},
  "geometry": {"coordinates":[8.6880750656,47.4335708618],"type":"Point"}
}