{
  "type": "Feature",
  "properties": {
    "iso:country":"CH",
    "sg:address":"L\u00e4rchenstrasse 38",
    "sg:city":"Winterthur",
    "sg:orig_category":"Kinesiologie",
    "sg:phone":"+41 52 213 17 35",
    "sg:postcode":"8400",
    "sg:province":"Z\u00fcrich",
    "wof:name":"Nicole Henger Kinesiologie",
    "wof:placetype":"venue"
},
  "geometry": {"coordinates":[8.719452858,47.4921417236],"type":"Point"}
}