{
  "type": "Feature",
  "properties": {
    "addr:full":"Chemin De La Fiole 17 Tavannes Bern 2710",
    "addr:housenumber":"17",
    "addr:postcode":"2710",
    "addr:street":"Chemin De La Fiole",
    "iso:country":"CH",
    "sg:address":"Chemin De La Fiole 17",
    "sg:city":"Tavannes",
    "sg:orig_category":"Bauschreinerei Herstellung von Konstruktionsteilen, Fertigbauteilen U Ausbauelementen aus Holz",
    "sg:phone":"+41 32 481 29 72",
    "sg:postcode":"2710",
    "sg:province":"Bern",
    "wof:name":"Wolfsberger Et L\u00fcthi S\u00e0rl",
    "wof:placetype":"venue"
},
  "geometry": {"coordinates":[7.202057,47.227459],"type":"Point"}
}