{
  "type": "Feature",
  "properties": {
    "iso:country":"CH",
    "sg:address":"Hauptstrasse 10",
    "sg:city":"Pratteln",
    "sg:orig_category":"Herstellung von Teppichen Verlegen von Fussboden",
    "sg:phone":"+41 61 821 22 35",
    "sg:postcode":"4133",
    "sg:province":"Basel-Landschaft",
    "wof:name":"Bbs Ag Bodenbelag Service Ag Teppich-parkett Pvc-bel\u00e4ge",
    "wof:placetype":"venue"
},
  "geometry": {"coordinates":[7.693461895,47.5181121826],"type":"Point"}
}