{
  "type": "Feature",
  "properties": {
    "iso:country":"CH",
    "sg:address":"Drosselweg 7",
    "sg:city":"Zuchwil",
    "sg:classifiers":[
        {
            "category":"Home & Garden",
            "subcategory":"Household Appliances",
            "type":"Retail Goods"
        }
    ],
    "sg:phone":"+41 32 685 49 91",
    "sg:postcode":"4528",
    "sg:province":"Solothurn",
    "sg:tags":[
        "improvement",
        "air-humidifiers",
        "air",
        "ambient"
    ],
    "wof:name":"Maxvit",
    "wof:placetype":"venue"
},
  "geometry": {"coordinates":[7.559265,47.210339],"type":"Point"}
}