{
  "type": "Feature",
  "properties": {
    "iso:country":"CH",
    "sg:address":"Pilatusstrasse 20 6003 Luzern. Postfach",
    "sg:city":"Luzern",
    "sg:orig_category":"Wirtschaftsverb\u00e4nde Gastgewerbe",
    "sg:phone":"+41 41 418 56 56",
    "sg:postcode":"6002",
    "sg:province":"Luzern",
    "wof:name":"Schweizerischer Kursaalverband",
    "wof:placetype":"venue"
},
  "geometry": {"coordinates":[8.3057117462,47.0487213135],"type":"Point"}
}