{
  "type": "Feature",
  "properties": {
    "iso:country":"CH",
    "sg:address":"Asylstrasse 1",
    "sg:city":"Aarau",
    "sg:orig_category":"RESTAURANTS: TEA-ROOMS",
    "sg:postcode":"5000",
    "sg:province":"Aargau",
    "wof:name":"Asima Gmbh",
    "wof:placetype":"venue"
},
  "geometry": {"coordinates":[8.0421590805,47.3914756775],"type":"Point"}
}