{
  "type": "Feature",
  "properties": {
    "addr:full":"Tannenb\u00fcel 10 Flawil St. Gallen 9230",
    "addr:housenumber":"10",
    "addr:postcode":"9230",
    "addr:street":"Tannenbueel",
    "iso:country":"CH",
    "sg:address":"Tannenb\u00fcel 10",
    "sg:city":"Flawil",
    "sg:orig_category":"Datenverarbeitungsdienste",
    "sg:phone":"+41 71 393 52 18",
    "sg:postcode":"9230",
    "sg:province":"St. Gallen",
    "wof:name":"Walter M\u00fcller Micro Top Edv-projekte",
    "wof:placetype":"venue"
},
  "geometry": {"coordinates":[9.193735,47.416874],"type":"Point"}
}