{
  "type": "Feature",
  "properties": {
    "iso:country":"CH",
    "sg:address":"Breite 20",
    "sg:city":"Merenschwand",
    "sg:orig_category":"Sportvereine Sch\u00fctzen Bogen",
    "sg:phone":"+41 56 664 35 78",
    "sg:postcode":"5634",
    "sg:province":"Aargau",
    "wof:name":"Bogensch\u00fctzen-verein",
    "wof:placetype":"venue"
},
  "geometry": {"coordinates":[8.375629425,47.2620925903],"type":"Point"}
}