{
  "type": "Feature",
  "properties": {
    "iso:country":"CH",
    "sg:address":"Moos 117",
    "sg:city":"Diemerswil",
    "sg:orig_category":"Landw. Genossenschaften Viehzucht",
    "sg:phone":"+41 31 869 05 00",
    "sg:postcode":"3053",
    "sg:province":"Bern",
    "wof:name":"Viehzuchtgenossenschaft M\u00fcnchenbuchsee Ii Hs.mindert",
    "wof:placetype":"venue"
},
  "geometry": {"coordinates":[7.4232130051,47.0145454407],"type":"Point"}
}