{
  "type": "Feature",
  "properties": {
    "iso:country":"CH",
    "sg:address":"Zeughausplatz 27",
    "sg:city":"Liestal",
    "sg:orig_category":"Vermietung U Verpachtung von eigenen Immobilien",
    "sg:postcode":"4410",
    "sg:province":"Basel-Landschaft",
    "wof:name":"Gbh Gewerkschaftshaus Ag",
    "wof:placetype":"venue"
},
  "geometry": {"coordinates":[7.7357239723,47.4852676392],"type":"Point"}
}