{
  "type": "Feature",
  "properties": {
    "addr:full":"Solenbergstrasse 5 Schaffhausen Schaffhausen 8207",
    "addr:housenumber":"5",
    "addr:postcode":"8207",
    "addr:street":"Solenbergstrasse",
    "iso:country":"CH",
    "sg:address":"Solenbergstrasse 5",
    "sg:city":"Schaffhausen",
    "sg:classifiers":[
        {
            "category":"Autos & Motor Vehicles",
            "subcategory":"Boat Sales",
            "type":"Retail Goods"
        }
    ],
    "sg:phone":"+41 52 631 17 17",
    "sg:postcode":"8207",
    "sg:province":"Schaffhausen",
    "sg:tags":[
        "machine",
        "equipment",
        "blasting"
    ],
    "wof:name":"Disa Industrie Ag",
    "wof:placetype":"venue"
},
  "geometry": {"coordinates":[8.659426,47.712517],"type":"Point"}
}