{
  "type": "Feature",
  "properties": {
    "iso:country":"CH",
    "sg:address":"Neubr\u00fcckstrasse 155 3012 Bern. Postfach 155",
    "sg:city":"Bern",
    "sg:orig_category":"Interessenvertretungen U sonstige Vereinigungen",
    "sg:phone":"+41 31 302 87 27",
    "sg:postcode":"3012",
    "sg:province":"Bern",
    "wof:name":"Schweiz.verband F\u00fcr Sport In Der Schule Svss",
    "wof:placetype":"venue"
},
  "geometry": {"coordinates":[7.4327888489,46.961856842],"type":"Point"}
}