{
  "type": "Feature",
  "properties": {
    "iso:country":"CH",
    "sg:address":"Bahnhofstrasse 21",
    "sg:city":"Zug",
    "sg:orig_category":"Handelsvermittlung von Brennstoffen, Erzen, Metallen U Chemikalien",
    "sg:postcode":"6300",
    "sg:province":"Zug",
    "wof:name":"Tristar Products",
    "wof:placetype":"venue"
},
  "geometry": {"coordinates":[9.1527996063,47.5484695435],"type":"Point"}
}