{
  "type": "Feature",
  "properties": {
    "iso:country":"CH",
    "sg:address":"Glattwiesenstrasse 2",
    "sg:city":"Z\u00fcrich",
    "sg:orig_category":"Detailhandel mit Waren verschiedener Art, Hauptrichtung Nahrungsmittel",
    "sg:phone":"+41 13211221",
    "sg:postcode":"8051",
    "sg:province":"Z\u00fcrich",
    "wof:name":"Pazarak Lebensmittel",
    "wof:placetype":"venue"
},
  "geometry": {"coordinates":[8.58162117,47.4018096924],"type":"Point"}
}