{
  "type": "Feature",
  "properties": {
    "iso:country":"CH",
    "sg:address":"Rue De L'h\u00f4tel-de-ville 21",
    "sg:city":"Vevey",
    "sg:orig_category":"Detailhandel mit B\u00fcchern, Zeitungen, Schreib U Papeteriewaren Detailhandel mit Schreib U Papeteriewa",
    "sg:postcode":"1800",
    "sg:province":"Vaud",
    "wof:name":"Kurt Heiz",
    "wof:placetype":"venue"
},
  "geometry": {"coordinates":[8.183158,47.253349],"type":"Point"}
}