{
  "type": "Feature",
  "properties": {
    "iso:country":"CH",
    "sg:address":"Rebhaldenstrasse 14",
    "sg:city":"Wettingen",
    "sg:classifiers":[
        {
            "category":"Insurance",
            "subcategory":"Insurance Agent",
            "type":"Services"
        }
    ],
    "sg:phone":"+41 56 426 00 85",
    "sg:postcode":"5430",
    "sg:province":"Aargau",
    "sg:tags":[
        "versicherungsagenturen",
        "-broker"
    ],
    "wof:name":"Elvia Versicherungen Agentur Erwin Cajacob",
    "wof:placetype":"venue"
},
  "geometry": {"coordinates":[8.3241147995,47.47108078],"type":"Point"}
}