{
  "type": "Feature",
  "properties": {
    "iso:country":"CH",
    "sg:address":"Sch\u00e4dr\u00fctihalde 16",
    "sg:city":"Luzern",
    "sg:orig_category":"Public-Relations-Agenturen Werbegrafikateliers",
    "sg:phone":"+41 41 370 52 12",
    "sg:postcode":"6006",
    "sg:province":"Luzern",
    "wof:name":"Teddy & Doris Achermann Grafik & Oeffentlichkeitsarb.",
    "wof:placetype":"venue"
},
  "geometry": {"coordinates":[8.3474082947,47.0580673218],"type":"Point"}
}