{
  "type": "Feature",
  "properties": {
    "iso:country":"CH",
    "sg:address":"Eyhof 28",
    "sg:city":"Z\u00fcrich",
    "sg:orig_category":"Sportvereine Sch\u00fctzen Pistolen-& Gewehr",
    "sg:phone":"+41 13624255",
    "sg:postcode":"8047",
    "sg:province":"Z\u00fcrich",
    "wof:name":"Sch\u00fctzenverein Z\u00fcrich",
    "wof:placetype":"venue"
},
  "geometry": {"coordinates":[8.4893398285,47.3721504211],"type":"Point"}
}