{
  "type": "Feature",
  "properties": {
    "iso:country":"CH",
    "sg:address":"Chemin Du Foron 14 1226 Th\u00f4nex Case Postale 216",
    "sg:city":"Th\u00f4nex",
    "sg:orig_category":"Installation von Heizungs, L\u00fcftungs U Klimaanlagen Sanit\u00e4r U Heizungsinstallation",
    "sg:phone":"+41 22 348 68 30",
    "sg:postcode":"1226",
    "sg:province":"Gen\u00e8ve",
    "wof:name":"Cgcm Sa Compagnie G\u00e9n\u00e9rale De Climatisation & De Maintenance",
    "wof:placetype":"venue"
},
  "geometry": {"coordinates":[6.2109060287,46.1933021545],"type":"Point"}
}