{
  "type": "Feature",
  "properties": {
    "iso:country":"CH",
    "sg:address":"Courtelary",
    "sg:city":"Courtelary",
    "sg:classifiers":[
        {
            "category":"Banks & Credit Unions",
            "subcategory":"Bank",
            "type":"Services"
        }
    ],
    "sg:phone":"+41 32 944 10 44",
    "sg:postcode":"2608",
    "sg:province":"Bern",
    "wof:name":"Caisse D'epargne Du, District De Courtelary",
    "wof:placetype":"venue"
},
  "geometry": {"coordinates":[7.073368,47.178558],"type":"Point"}
}