{
  "type": "Feature",
  "properties": {
    "iso:country":"CH",
    "sg:address":"Habsburgstrasse 11",
    "sg:city":"Rudolfstetten",
    "sg:orig_category":"Kinderkrippen U horte",
    "sg:phone":"+41 56 622 60 88",
    "sg:postcode":"8964",
    "sg:province":"Aargau",
    "wof:name":"Adelheid Huser Kindermittagstisch Mutschellen",
    "wof:placetype":"venue"
},
  "geometry": {"coordinates":[8.3734359741,47.3637275696],"type":"Point"}
}