{
  "type": "Feature",
  "properties": {
    "iso:country":"CH",
    "sg:address":"Welschmattstrasse 30",
    "sg:city":"Basel",
    "sg:orig_category":"Primarschulen",
    "sg:phone":"+41 61 385 90 29",
    "sg:postcode":"4055",
    "sg:province":"Basel-Stadt",
    "wof:name":"Primarschule Wasgenring West",
    "wof:placetype":"venue"
},
  "geometry": {"coordinates":[7.5626330376,47.5622787476],"type":"Point"}
}