{
  "type": "Feature",
  "properties": {
    "iso:country":"CH",
    "sg:address":"Hirschmattstrasse 16",
    "sg:city":"Luzern",
    "sg:orig_category":"Grosshandel mit Nahrungsmitteln, Getr\u00e4nken U Tabakwaren ohne ausgepr\u00e4gten Schwerpunkt",
    "sg:phone":"+41 41 210 04 60",
    "sg:postcode":"6003",
    "sg:province":"Luzern",
    "wof:name":"Chuchig\u00e4nterli Lebensmittel Salzmann & K\u00e4ppeli",
    "wof:placetype":"venue"
},
  "geometry": {"coordinates":[8.3059539795,47.0489463806],"type":"Point"}
}