{
  "type": "Feature",
  "properties": {
    "iso:country":"CH",
    "sg:address":"Spitalgasse 1",
    "sg:city":"Winterthur",
    "sg:classifiers":[
        {
            "category":"Travel",
            "subcategory":"Hotels & Motels",
            "type":"Entertainment"
        }
    ],
    "sg:postcode":"8400",
    "sg:province":"Z\u00fcrich",
    "sg:tags":[
        "oder",
        "bar",
        "restaurant"
    ],
    "wof:name":"Bar.& Cafe Kafisatz",
    "wof:placetype":"venue"
},
  "geometry": {"coordinates":[8.727464,47.498932],"type":"Point"}
}