{
  "type": "Feature",
  "properties": {
    "iso:country":"CH",
    "sg:address":"Gewerbestrasse 3a",
    "sg:city":"Sissach",
    "sg:orig_category":"Instandhaltung U Reparatur von Automobilen",
    "sg:phone":"+41 79 353 06 00",
    "sg:postcode":"4450",
    "sg:province":"Basel-Landschaft",
    "wof:name":"Eggimann Fahrzeugelektrik-garage",
    "wof:placetype":"venue"
},
  "geometry": {"coordinates":[7.8016738892,47.4676322937],"type":"Point"}
}