{
  "type": "Feature",
  "properties": {
    "iso:country":"CH",
    "sg:address":"Via Del Sole",
    "sg:city":"Tenero",
    "sg:orig_category":"Herstellung von sonstigen Produkten aus nichtmetallischen Mineralien",
    "sg:phone":"+41 32 373 54 20",
    "sg:postcode":"6598",
    "sg:province":"Ticino",
    "wof:name":"Pan-isovit Ag",
    "wof:placetype":"venue"
},
  "geometry": {"coordinates":[7.2785029411,47.1245613098],"type":"Point"}
}