{
  "type": "Feature",
  "properties": {
    "iso:country":"CH",
    "sg:address":"St. Jakobs-strasse 399",
    "sg:city":"Basel",
    "sg:orig_category":"Tankstellen",
    "sg:postcode":"4052",
    "sg:province":"Basel-Stadt",
    "wof:name":"Shell-service-station Stadion Gebhard H. Ch.",
    "wof:placetype":"venue"
},
  "geometry": {"coordinates":[7.6212849617,47.5404205322],"type":"Point"}
}