{
  "type": "Feature",
  "properties": {
    "addr:full":"Lintheschergasse 19 8001 Z\u00fcrich. Postfach Z\u00fcrich Z\u00fcrich 8023",
    "addr:housenumber":"19",
    "addr:postcode":"8001 zuerich. postfach;8023",
    "addr:street":"Lintheschergasse",
    "iso:country":"CH",
    "sg:address":"Lintheschergasse 19 8001 Z\u00fcrich. Postfach",
    "sg:city":"Z\u00fcrich",
    "sg:orig_category":"Aktivit\u00e4t der Bankinstitute",
    "sg:phone":"+41 22 312 03 12",
    "sg:postcode":"8023",
    "sg:province":"Z\u00fcrich",
    "wof:name":"Anker Bank",
    "wof:placetype":"venue"
},
  "geometry": {"coordinates":[6.1515,46.204948],"type":"Point"}
}