{
  "type": "Feature",
  "properties": {
    "addr:full":"Rue De Romont 4 Fribourg Fribourg 1700",
    "addr:housenumber":"4",
    "addr:postcode":"1700",
    "addr:street":"Rue De Romont",
    "iso:country":"CH",
    "sg:address":"Rue De Romont 4",
    "sg:city":"Fribourg",
    "sg:classifiers":[
        {
            "category":"Banks & Credit Unions",
            "subcategory":"Bank",
            "type":"Services"
        }
    ],
    "sg:phone":"+41 26 322 02 02",
    "sg:postcode":"1700",
    "sg:province":"Fribourg",
    "wof:name":"Migros Bank",
    "wof:placetype":"venue"
},
  "geometry": {"coordinates":[7.155386,46.804844],"type":"Point"}
}