{
  "type": "Feature",
  "properties": {
    "iso:country":"CH",
    "sg:address":"Hinterdorf 7312 Pf\u00e4fers. Postfach",
    "sg:city":"Valens",
    "sg:orig_category":"Zimmerei, Dachdeckerei, Bauspenglerei U Abdichtung",
    "sg:postcode":"7317",
    "sg:province":"St. Gallen",
    "wof:name":"K\u00fchne Bernhard, Zimmerei",
    "wof:placetype":"venue"
},
  "geometry": {"coordinates":[9.4363002777,46.9087409973],"type":"Point"}
}