{
  "type": "Feature",
  "properties": {
    "iso:country":"CH",
    "sg:address":"F\u00f6hrenstrasse 33",
    "sg:city":"Schaffhausen",
    "sg:orig_category":"Detailhandel mit Getr\u00e4nken Detailhandel mit Waren verschiedener Art, Hauptrichtung Nahrungsmittel",
    "sg:phone":"+41 24 492 39 49",
    "sg:postcode":"8200",
    "sg:province":"Schaffhausen",
    "wof:name":"Alimentation Supermarch\u00e9 Grand-bazar Des Alpes",
    "wof:placetype":"venue"
},
  "geometry": {"coordinates":[7.1578531265,46.3495140076],"type":"Point"}
}