{
  "type": "Feature",
  "properties": {
    "iso:country":"CH",
    "sg:address":"Turbinenstrasse 30 8005 Z\u00fcrich. Postfach",
    "sg:city":"Z\u00fcrich",
    "sg:orig_category":"Detailhandel mit Waren verschiedener Art, Hauptrichtung Nahrungsmittel Grosshandel mit Nahrungsmitte",
    "sg:phone":"+41 12754411",
    "sg:postcode":"8021",
    "sg:province":"Z\u00fcrich",
    "wof:name":"Coop Zentralverwaltung Zentralschweiz-z\u00fcrich",
    "wof:placetype":"venue"
},
  "geometry": {"coordinates":[8.5148859024,47.3873977661],"type":"Point"}
}