{
  "type": "Feature",
  "properties": {
    "iso:country":"CH",
    "sg:address":"Chalet Giltstein Tenne",
    "sg:city":"Bettmeralp",
    "sg:orig_category":"Sportvereine Ski",
    "sg:phone":"+41 27 927 31 66",
    "sg:postcode":"3992",
    "sg:province":"Valais",
    "wof:name":"Skiclub Bettmeralp Betten",
    "wof:placetype":"venue"
},
  "geometry": {"coordinates":[8.0611810684,46.3895072937],"type":"Point"}
}