{
  "type": "Feature",
  "properties": {
    "iso:country":"CH",
    "sg:address":"Lindstrasse 439",
    "sg:city":"Erstfeld",
    "sg:orig_category":"Vereine Frauen Vereine Gemeinn\u00fctzige",
    "sg:postcode":"6472",
    "sg:province":"Uri",
    "wof:name":"Coop Frauenbund Sekt.erstfeld",
    "wof:placetype":"venue"
},
  "geometry": {"coordinates":[8.6507797241,46.8171882629],"type":"Point"}
}