{
  "type": "Feature",
  "properties": {
    "iso:country":"CH",
    "sg:address":"S\u00e4gereistrasse 24",
    "sg:city":"Glattbrugg",
    "sg:classifiers":[
        {
            "category":"Professional",
            "subcategory":"Accounting & Tax Preparation",
            "type":"Services"
        }
    ],
    "sg:phone":"+41 71 282 42 00",
    "sg:postcode":"8152",
    "sg:province":"Z\u00fcrich",
    "sg:tags":[
        "electrocardiograph"
    ],
    "wof:name":"Cc Med Ag",
    "wof:placetype":"venue"
},
  "geometry": {"coordinates":[9.418274,47.44632],"type":"Point"}
}