{
  "type": "Feature",
  "properties": {
    "iso:country":"CH",
    "sg:address":"Industriestrasse 22",
    "sg:city":"Kronb\u00fchl",
    "sg:classifiers":[
        {
            "category":"Shopping",
            "subcategory":"Optical Goods",
            "type":"Retail Goods"
        }
    ],
    "sg:phone":"+41 71 292 10 80",
    "sg:postcode":"9302",
    "sg:tags":[
        "optic",
        "endoscope"
    ],
    "wof:name":"Mikrop Ag",
    "wof:placetype":"venue"
},
  "geometry": {"coordinates":[9.394865036,47.4597816467],"type":"Point"}
}