{
  "type": "Feature",
  "properties": {
    "iso:country":"CH",
    "sg:address":"Buchstrasse 10",
    "sg:city":"M\u00fchleberg",
    "sg:orig_category":"Primarschulen",
    "sg:phone":"+41 31 751 11 84",
    "sg:postcode":"3203",
    "sg:province":"Bern",
    "wof:name":"Primarschule M\u00fchleberg",
    "wof:placetype":"venue"
},
  "geometry": {"coordinates":[7.2624678612,46.9532241821],"type":"Point"}
}