{
  "type": "Feature",
  "properties": {
    "iso:country":"CH",
    "sg:address":"Avenue De La Roseraie 72",
    "sg:city":"Gen\u00e8ve",
    "sg:orig_category":"Medizinische Labors",
    "sg:phone":"+41 22 346 31 00",
    "sg:postcode":"1205",
    "sg:province":"Gen\u00e8ve",
    "wof:name":"Ams Analyses M\u00e9dicales Services Sa",
    "wof:placetype":"venue"
},
  "geometry": {"coordinates":[6.1491189003,46.1910209656],"type":"Point"}
}