{
  "type": "Feature",
  "properties": {
    "addr:full":"Baslerstrasse 5 Laufenburg Aargau 5080",
    "addr:housenumber":"5",
    "addr:postcode":"5080",
    "addr:street":"Baslerstrasse",
    "iso:country":"CH",
    "sg:address":"Baslerstrasse 5",
    "sg:city":"Laufenburg",
    "sg:orig_category":"Allgemeiner Hoch U Tiefbau Herstellung von Fenstern U T\u00fcren aus Holz",
    "sg:phone":"+41 34 402 10 69",
    "sg:postcode":"5080",
    "sg:province":"Aargau",
    "wof:name":"Hofer & Co",
    "wof:placetype":"venue"
},
  "geometry": {"coordinates":[7.75759,46.949127],"type":"Point"}
}