{
  "type": "Feature",
  "properties": {
    "iso:country":"CH",
    "sg:address":"Waisenhausstrasse 16",
    "sg:city":"St.gallen",
    "sg:orig_category":"Interessenvertretungen",
    "sg:postcode":"9000",
    "sg:province":"St. Gallen",
    "wof:name":"Dietschweiler-stiftung Ria Und Arthur",
    "wof:placetype":"venue"
},
  "geometry": {"coordinates":[9.3728704453,47.4251937866],"type":"Point"}
}