{
  "type": "Feature",
  "properties": {
    "addr:full":"Fabrikstr. 50 Z\u00fcrich Z\u00fcrich 8031",
    "addr:housenumber":"50",
    "addr:postcode":"8031",
    "addr:street":"Fabrikstr.",
    "iso:country":"CH",
    "sg:address":"Fabrikstr. 50",
    "sg:city":"Z\u00fcrich",
    "sg:classifiers":[
        {
            "category":"Professional",
            "subcategory":"Advertising",
            "type":"Services"
        }
    ],
    "sg:phone":"+41 71 243 57 57",
    "sg:postcode":"8031",
    "sg:province":"Z\u00fcrich",
    "sg:tags":[
        "information",
        "medium",
        "communication"
    ],
    "wof:name":"Bsg Unternehmensberatung",
    "wof:placetype":"venue"
},
  "geometry": {"coordinates":[9.37605,47.426479],"type":"Point"}
}