{
  "type": "Feature",
  "properties": {
    "iso:country":"CH",
    "sg:address":"Vorstadtstrasse 48",
    "sg:city":"Gr\u00e4nichen",
    "sg:orig_category":"Politische Parteien SVP",
    "sg:phone":"+41 62 842 26 83",
    "sg:postcode":"5722",
    "sg:province":"Aargau",
    "wof:name":"Svp Ortspartei Gr\u00e4nichen",
    "wof:placetype":"venue"
},
  "geometry": {"coordinates":[8.0981311798,47.3650817871],"type":"Point"}
}