{
  "type": "Feature",
  "properties": {
    "iso:country":"CH",
    "sg:address":"Hinter-r\u00f6telberg",
    "sg:city":"Menznau",
    "sg:orig_category":"Verwertung von Milch",
    "sg:postcode":"6122",
    "sg:province":"Luzern",
    "wof:name":"Milchverwertungsgenossenschaft R\u00f6telberg & Umgebung",
    "wof:placetype":"venue"
},
  "geometry": {"coordinates":[8.0270757675,47.0991096497],"type":"Point"}
}