{
  "type": "Feature",
  "properties": {
    "iso:country":"CH",
    "sg:address":"Sulzer-hirzel-strasse 7b",
    "sg:city":"Winterthur",
    "sg:orig_category":"Erwachsenenbildung U Unterricht Unternehmensberatung",
    "sg:phone":"+41 52 212 48 48",
    "sg:postcode":"8400",
    "sg:province":"Z\u00fcrich",
    "wof:name":"Stoll Marco Training + Development Gmbh",
    "wof:placetype":"venue"
},
  "geometry": {"coordinates":[8.722951889,47.4951667786],"type":"Point"}
}