{
  "type": "Feature",
  "properties": {
    "iso:country":"CH",
    "sg:address":"Schlossstrasse 56 8207 Schaffhausen. Postfach",
    "sg:city":"Schaffhausen",
    "sg:orig_category":"RESTAURANTS: TEA-ROOMS",
    "sg:postcode":"8207",
    "sg:province":"Schaffhausen",
    "wof:name":"Theater Restaurant Berger Werl\u00e9 Renate",
    "wof:placetype":"venue"
},
  "geometry": {"coordinates":[8.6625566483,47.7259750366],"type":"Point"}
}