{
  "type": "Feature",
  "properties": {
    "iso:country":"CH",
    "sg:address":"Schulstrasse 7",
    "sg:city":"Sutz",
    "sg:orig_category":"Primarschulen",
    "sg:phone":"+41 32 397 22 04",
    "sg:postcode":"2572",
    "sg:province":"Bern",
    "wof:name":"Primarschule",
    "wof:placetype":"venue"
},
  "geometry": {"coordinates":[7.213809967,47.0986099243],"type":"Point"}
}