{
  "type": "Feature",
  "properties": {
    "iso:country":"CH",
    "sg:address":"Chemin Des Palettes 33",
    "sg:city":"Grand-lancy",
    "sg:orig_category":"Geb\u00e4ude, Wohnungsreinigung",
    "sg:phone":"+41 32 841 37 47",
    "sg:postcode":"1212",
    "sg:province":"Gen\u00e8ve",
    "wof:name":"Entreprise De Nettoyage La Mob Jacques-edy Perrenoud",
    "wof:placetype":"venue"
},
  "geometry": {"coordinates":[6.8604841232,46.9645042419],"type":"Point"}
}