{
  "type": "Feature",
  "properties": {
    "iso:country":"CH",
    "sg:address":"Br\u00fcggligasse 10 6004 Luzern. Postfach",
    "sg:city":"Luzern",
    "sg:orig_category":"Zimmerei, Dachdeckerei, Bauspenglerei U Abdichtung",
    "sg:phone":"+41 79 311 03 06",
    "sg:postcode":"6003",
    "sg:province":"Luzern",
    "wof:name":"Schoy Josef, Erben Spenglerei, Blitzschutzanlagen, Flachbedachungen",
    "wof:placetype":"venue"
},
  "geometry": {"coordinates":[8.3010253906,47.0530929565],"type":"Point"}
}