{
  "type": "Feature",
  "properties": {
    "iso:country":"CH",
    "sg:address":"Sch\u00f6ngrundstrasse 19",
    "sg:city":"Horw",
    "sg:orig_category":"Malerei Tapeziererei",
    "sg:phone":"+41 41 340 15 59",
    "sg:postcode":"6048",
    "sg:province":"Luzern",
    "wof:name":"Manfred Wulf Maler-& Tapezierergesch\u00e4ft",
    "wof:placetype":"venue"
},
  "geometry": {"coordinates":[8.3082733154,47.0148353577],"type":"Point"}
}