{
  "type": "Feature",
  "properties": {
    "addr:full":"St. German St. German 3936",
    "addr:postcode":"3936",
    "iso:country":"CH",
    "sg:address":"St. German",
    "sg:city":"St. German",
    "sg:classifiers":[
        {
            "category":"Banks & Credit Unions",
            "subcategory":"Bank",
            "type":"Services"
        }
    ],
    "sg:phone":"+41 28442044",
    "sg:postcode":"3936",
    "wof:name":"Raiffeisenbank",
    "wof:placetype":"venue"
},
  "geometry": {"coordinates":[7.82745,46.350071],"type":"Point"}
}