{
  "type": "Feature",
  "properties": {
    "iso:country":"CH",
    "sg:address":"Baselstrasse 56",
    "sg:city":"Luzern",
    "sg:orig_category":"Detailhandel mit Radio U Fernsehger\u00e4ten",
    "sg:phone":"+41 41 240 66 55",
    "sg:postcode":"6003",
    "sg:province":"Luzern",
    "wof:name":"Oronzo Semeraro Radio-tv",
    "wof:placetype":"venue"
},
  "geometry": {"coordinates":[8.2940397263,47.0535926819],"type":"Point"}
}