{
  "type": "Feature",
  "properties": {
    "iso:country":"CH",
    "sg:address":"Rue Adrien-lachenal 13",
    "sg:city":"Gen\u00e8ve",
    "sg:orig_category":"Herstellung von Konstruktionsteilen, Fertigbauteilen U Ausbauelementen aus Holz Innenausbau",
    "sg:phone":"+41 71 994 10 94",
    "sg:postcode":"1207",
    "sg:province":"Gen\u00e8ve",
    "wof:name":"Scherrer & B\u00fcrkler Gmbh Schreinerei Innenausbau K\u00fcchen",
    "wof:placetype":"venue"
},
  "geometry": {"coordinates":[9.2270326614,47.1988601685],"type":"Point"}
}