{
  "type": "Feature",
  "properties": {
    "iso:country":"CH",
    "sg:address":"Kirchenstrasse 15 6300 Zug. Postfach",
    "sg:city":"Zug",
    "sg:classifiers":[
        {
            "category":"Education",
            "subcategory":"Library",
            "type":"Public Place"
        }
    ],
    "sg:phone":"+41 41 710 62 34",
    "sg:postcode":"6301",
    "sg:province":"Zug",
    "sg:tags":[
        "u",
        "bibliotheken",
        "archive"
    ],
    "wof:name":"Bibliothek Der Katholischen Kirchgemeinde",
    "wof:placetype":"venue"
},
  "geometry": {"coordinates":[8.517024,47.164658],"type":"Point"}
}