{
  "type": "Feature",
  "properties": {
    "iso:country":"CH",
    "sg:address":"Engelbergerstrasse 41",
    "sg:city":"Engelberg",
    "sg:orig_category":"Mit dem Versicherungsgewerbe verbundene T\u00e4tigkeiten",
    "sg:postcode":"6390",
    "sg:province":"Obwalden",
    "wof:name":"Schleiss Reto Versicherungsberatung",
    "wof:placetype":"venue"
},
  "geometry": {"coordinates":[8.3979120255,46.8182525635],"type":"Point"}
}