{
  "type": "Feature",
  "properties": {
    "iso:country":"CH",
    "sg:address":"Via Delle Scuole",
    "sg:city":"Tenero",
    "sg:orig_category":"Reiseb\u00fcros U Reiseveranstalter",
    "sg:phone":"+41 32 724 52 62",
    "sg:postcode":"6598",
    "sg:province":"Ticino",
    "wof:name":"R Voyages, De Carvalho",
    "wof:placetype":"venue"
},
  "geometry": {"coordinates":[6.9200549126,46.9925956726],"type":"Point"}
}