{
  "type": "Feature",
  "properties": {
    "iso:country":"CH",
    "sg:address":"M\u00fchlehofstrasse 2",
    "sg:city":"Reiden",
    "sg:orig_category":"Sportvereine Hornussen",
    "sg:postcode":"6260",
    "sg:province":"Luzern",
    "wof:name":"Hornussergesell.hintermoos",
    "wof:placetype":"venue"
},
  "geometry": {"coordinates":[7.9686961174,47.2400894165],"type":"Point"}
}