{
  "type": "Feature",
  "properties": {
    "iso:country":"CH",
    "sg:address":"Hertensteinstrasse 34",
    "sg:city":"Weggis",
    "sg:classifiers":[
        {
            "category":"Travel",
            "subcategory":"Hotels & Motels",
            "type":"Entertainment"
        }
    ],
    "sg:phone":"+41 41 390 13 13",
    "sg:postcode":"6353",
    "sg:province":"Luzern",
    "sg:tags":[
        "hotels",
        "mit",
        "restaurant"
    ],
    "wof:name":"Parkhotel Weggis Ag",
    "wof:placetype":"venue"
},
  "geometry": {"coordinates":[8.4218149185,47.0295333862],"type":"Point"}
}