{
  "type": "Feature",
  "properties": {
    "addr:full":"Amthausgasse 3 Bern Bern 3011",
    "addr:housenumber":"3",
    "addr:postcode":"3011",
    "addr:street":"Amthausgasse",
    "iso:country":"CH",
    "sg:address":"Amthausgasse 3",
    "sg:city":"Bern",
    "sg:orig_category":"Advokaturb\u00fcros Notariate",
    "sg:phone":"+41 31 311 25 55",
    "sg:postcode":"3011",
    "sg:province":"Bern",
    "wof:name":"Reinhard P. Moeri Advokatur-& Notariatsb\u00fcro",
    "wof:placetype":"venue"
},
  "geometry": {"coordinates":[7.446665,46.947186],"type":"Point"}
}