{
  "type": "Feature",
  "properties": {
    "iso:country":"CH",
    "sg:address":"Allmendstrasse 1",
    "sg:city":"Villmergen",
    "sg:orig_category":"Autospenglereien Wohnwagen and Wohnmobile Grosshandel",
    "sg:phone":"+41 71 311 38 39",
    "sg:postcode":"5612",
    "sg:province":"Aargau",
    "wof:name":"Hans Holliger",
    "wof:placetype":"venue"
},
  "geometry": {"coordinates":[9.3108682632,47.4045791626],"type":"Point"}
}