{
  "type": "Feature",
  "properties": {
    "iso:country":"CH",
    "sg:address":"Birchstrasse 4 8472 Seuzach. Postfach",
    "sg:city":"Seuzach",
    "sg:orig_category":"Kantonalbanken",
    "sg:phone":"+41 52 320 00 10",
    "sg:postcode":"8472",
    "sg:province":"Z\u00fcrich",
    "wof:name":"Z\u00fcrcher Kantonalbank",
    "wof:placetype":"venue"
},
  "geometry": {"coordinates":[8.736117363,47.5364265442],"type":"Point"}
}