{
  "type": "Feature",
  "properties": {
    "iso:country":"CH",
    "sg:address":"Oberdorfstrasse 12",
    "sg:city":"Ueken",
    "sg:orig_category":"Herstellung von konfektionierten Textilwaren ohne Bekleidung",
    "sg:phone":"+41 62 871 71 41",
    "sg:postcode":"5028",
    "sg:province":"Aargau",
    "wof:name":"Peter Mahrer Rolladen-& Storenreparaturen",
    "wof:placetype":"venue"
},
  "geometry": {"coordinates":[8.0504789352,47.4837493896],"type":"Point"}
}