{
  "type": "Feature",
  "properties": {
    "iso:country":"CH",
    "sg:address":"3806",
    "sg:city":"B\u00f6nigen",
    "sg:orig_category":"Vereine Gesang",
    "sg:postcode":"3806",
    "sg:province":"Bern",
    "wof:name":"Arbeiter-s\u00e4ngerbund",
    "wof:placetype":"venue"
},
  "geometry": {"coordinates":[7.8937749863,46.6859436035],"type":"Point"}
}