{
  "type": "Feature",
  "properties": {
    "iso:country":"CH",
    "sg:address":"Chemin De La Vironde 23",
    "sg:city":"Plan-les-ouates",
    "sg:orig_category":"Fachdetailhandel in Verkaufsr\u00e4umen",
    "sg:phone":"+41 22 771 19 94",
    "sg:postcode":"1228",
    "sg:province":"Gen\u00e8ve",
    "wof:name":"Haas Elsbeth",
    "wof:placetype":"venue"
},
  "geometry": {"coordinates":[6.1171097755,46.1606216431],"type":"Point"}
}