{
  "type": "Feature",
  "properties": {
    "iso:country":"CH",
    "sg:address":"1946",
    "sg:city":"Bourg-st-pierre",
    "sg:orig_category":"Detailhandel mit Waren verschiedener Art, Hauptrichtung Nahrungsmittel Tankstellen",
    "sg:phone":"+41 61 811 11 39",
    "sg:postcode":"1946",
    "sg:province":"Valais",
    "wof:name":"Gertrud M\u00fcller Avia Shop & Tankstelle",
    "wof:placetype":"venue"
},
  "geometry": {"coordinates":[7.7101249695,47.5348358154],"type":"Point"}
}