{
  "type": "Feature",
  "properties": {
    "iso:country":"CH",
    "sg:address":"Schulhausstrasse 4",
    "sg:city":"Baldingen",
    "sg:orig_category":"Gemeindeverwaltungen",
    "sg:phone":"+41 56 249 11 22",
    "sg:postcode":"5333",
    "sg:province":"Aargau",
    "wof:name":"Gemeindeverwaltung Baldingen",
    "wof:placetype":"venue"
},
  "geometry": {"coordinates":[8.3165903091,47.5550804138],"type":"Point"}
}