{
  "type": "Feature",
  "properties": {
    "iso:country":"CH",
    "sg:address":"Schachenallee 29",
    "sg:city":"Aarau",
    "sg:classifiers":[
        {
            "category":"Professional",
            "subcategory":"Advertising",
            "type":"Services"
        }
    ],
    "sg:phone":"+41 62 822 95 10",
    "sg:postcode":"5000",
    "sg:province":"Aargau",
    "sg:tags":[
        "athletic"
    ],
    "wof:name":"Zobrist Sport- Und Freizeit",
    "wof:placetype":"venue"
},
  "geometry": {"coordinates":[8.04062,47.39027],"type":"Point"}
}