{
  "type": "Feature",
  "properties": {
    "iso:country":"CH",
    "sg:address":"Langrietstrasse 8212 Neuhausen. Postfach 557",
    "sg:city":"Neuhausen",
    "sg:orig_category":"Sportvereine Boccia",
    "sg:phone":"+41 52 672 15 53",
    "sg:postcode":"8212",
    "sg:province":"Schaffhausen",
    "wof:name":"Boccia-club Avanti",
    "wof:placetype":"venue"
},
  "geometry": {"coordinates":[8.6019649506,47.6787567139],"type":"Point"}
}