{
  "type": "Feature",
  "properties": {
    "iso:country":"CH",
    "sg:address":"Via Muraccio 2",
    "sg:city":"Ascona",
    "sg:orig_category":"Revision Wirtschaftspr\u00fcfung, Steuerberatung U Treuhand",
    "sg:phone":"+41 91 792 24 55",
    "sg:postcode":"6612",
    "sg:province":"Ticino",
    "wof:name":"Ufficio Fiduciario Cocconi Willy",
    "wof:placetype":"venue"
},
  "geometry": {"coordinates":[8.7735757828,46.1541862488],"type":"Point"}
}