{
  "type": "Feature",
  "properties": {
    "iso:country":"CH",
    "sg:address":"Casa Rigetti",
    "sg:city":"Cama",
    "sg:orig_category":"Non-Classified Establishments",
    "sg:postcode":"6557",
    "sg:province":"Graubunden",
    "wof:name":"Mabefid Sa",
    "wof:placetype":"venue"
},
  "geometry": {"coordinates":[9.1691150665,46.2709541321],"type":"Point"}
}