{
  "type": "Feature",
  "properties": {
    "iso:country":"CH",
    "sg:address":"Industriestrasse 32",
    "sg:city":"Lenzburg",
    "sg:classifiers":[
        {
            "category":"Shopping",
            "subcategory":"Stationery & Office Supplies",
            "type":"Retail Goods"
        }
    ],
    "sg:phone":"+41 62 891 37 56",
    "sg:postcode":"5600",
    "sg:province":"Aargau",
    "sg:tags":[
        "bookbinding"
    ],
    "wof:name":"B-b-l Ag",
    "wof:placetype":"venue"
},
  "geometry": {"coordinates":[8.163909,47.392117],"type":"Point"}
}