{
  "type": "Feature",
  "properties": {
    "iso:country":"CH",
    "sg:address":"Zwillikerstrasse 40",
    "sg:city":"Hedingen",
    "sg:orig_category":"Grosshandel mit Geschenkartikeln U Souvenirs Herstellung von sonstigen Metallwaren",
    "sg:phone":"+41 17614828",
    "sg:postcode":"8908",
    "sg:province":"Z\u00fcrich",
    "wof:name":"Magnetas, Sch\u00f6nenberger August",
    "wof:placetype":"venue"
},
  "geometry": {"coordinates":[8.4461336136,47.2946662903],"type":"Point"}
}