{
  "type": "Feature",
  "properties": {
    "iso:country":"CH",
    "sg:address":"Asylstrasse 25",
    "sg:city":"Spiez",
    "sg:orig_category":"Sonstiges Gesundheitswesen",
    "sg:phone":"+41 41 630 22 54",
    "sg:postcode":"3700",
    "sg:province":"Bern",
    "wof:name":"Krankenmobilienmagazin Frau J.kaiser",
    "wof:placetype":"venue"
},
  "geometry": {"coordinates":[8.3105154037,46.9811897278],"type":"Point"}
}