{
  "type": "Feature",
  "properties": {
    "iso:country":"CH",
    "sg:address":"Madeleine Rue 5 1003 Lausanne. Postfach",
    "sg:city":"Lausanne",
    "sg:orig_category":"Interessenvertretungen",
    "sg:postcode":"1003",
    "sg:province":"Vaud",
    "wof:name":"Association Avenir",
    "wof:placetype":"venue"
},
  "geometry": {"coordinates":[6.126830101,46.2368164062],"type":"Point"}
}