{
  "type": "Feature",
  "properties": {
    "iso:country":"CH",
    "sg:address":"Boulevard Du Th\u00e9\u00e2tre 4-6",
    "sg:city":"Gen\u00e8ve",
    "sg:orig_category":"Alters U Hinterlassenenversicherung AHV, Invalidenversicherung IV, Arbeitslosenversicherung ALV",
    "sg:phone":"+41 22 308 09 78",
    "sg:postcode":"1204",
    "sg:province":"Gen\u00e8ve",
    "wof:name":"Union Industrielle Genevoise Uig",
    "wof:placetype":"venue"
},
  "geometry": {"coordinates":[6.141539,46.202217],"type":"Point"}
}