{
  "type": "Feature",
  "properties": {
    "addr:full":"Stadtbachstrasse 77 Baden Aargau 5400",
    "addr:housenumber":"77",
    "addr:postcode":"5400",
    "addr:street":"Stadtbachstrasse",
    "iso:country":"CH",
    "sg:address":"Stadtbachstrasse 77",
    "sg:city":"Baden",
    "sg:orig_category":"Architektur U Ingenieurb\u00fcros",
    "sg:phone":"+41 56 222 16 93",
    "sg:postcode":"5400",
    "sg:province":"Aargau",
    "wof:name":"Nikolakopulos Dimitrios",
    "wof:placetype":"venue"
},
  "geometry": {"coordinates":[8.291054,47.466404],"type":"Point"}
}