{
  "type": "Feature",
  "properties": {
    "iso:country":"CH",
    "sg:address":"Chemin De L' Orio 30a",
    "sg:city":"Romanel-sur-lausanne",
    "sg:classifiers":[
        {
            "category":"Communications",
            "subcategory":"Film & Video Production",
            "type":"Services"
        }
    ],
    "sg:phone":"+41 21 641 43 43",
    "sg:postcode":"1032",
    "sg:province":"Vaud",
    "sg:tags":[
        "frame",
        "part",
        "bicycle"
    ],
    "wof:name":"Fuchs-movesa Ag",
    "wof:placetype":"venue"
},
  "geometry": {"coordinates":[6.6079,46.56493],"type":"Point"}
}