{
  "type": "Feature",
  "properties": {
    "iso:country":"CH",
    "sg:address":"Gewerbezentrum M\u00fchlefuhr",
    "sg:city":"Ennenda",
    "sg:orig_category":"Herstellung von Metallkonstruktionen",
    "sg:phone":"+41 71 923 78 64",
    "sg:postcode":"8755",
    "sg:province":"Glarus",
    "wof:name":"Menert Schumacher Ren\u00e9",
    "wof:placetype":"venue"
},
  "geometry": {"coordinates":[9.0330972672,47.449256897],"type":"Point"}
}