{
  "type": "Feature",
  "properties": {
    "iso:country":"CH",
    "sg:address":"Blumengasse 3",
    "sg:city":"Basel",
    "sg:orig_category":"Detailhandel mit Bekleidung",
    "sg:phone":"+41 61 261 14 90",
    "sg:postcode":"4051",
    "sg:province":"Basel-Stadt",
    "wof:name":"E Dopo Susanne Stark",
    "wof:placetype":"venue"
},
  "geometry": {"coordinates":[7.587507,47.559799],"type":"Point"}
}