{
  "type": "Feature",
  "properties": {
    "iso:country":"CH",
    "sg:address":"Schwanenplatz 8 6004 Luzern. Postfach 3164",
    "sg:city":"Luzern",
    "sg:orig_category":"Vermietung U Verpachtung von eigenen Immobilien",
    "sg:phone":"+41 41 248 70 80",
    "sg:postcode":"6004",
    "sg:province":"Luzern",
    "wof:name":"Hirtenhof Immobilien Ag",
    "wof:placetype":"venue"
},
  "geometry": {"coordinates":[8.3090372086,47.0536766052],"type":"Point"}
}