{
  "type": "Feature",
  "properties": {
    "iso:country":"CH",
    "sg:address":"L\u00e4uferberg 4 8752 N\u00e4fels. Postfach",
    "sg:city":"N\u00e4fels",
    "sg:orig_category":"Softwareentwicklung U beratung",
    "sg:postcode":"8752",
    "sg:province":"Glarus",
    "wof:name":"Blumer International Consulting Internationale Informatikberatung, Bes. In Den Ber. E-commerce U. Gastronomie",
    "wof:placetype":"venue"
},
  "geometry": {"coordinates":[9.0343790054,47.1014633179],"type":"Point"}
}