{
  "type": "Feature",
  "properties": {
    "iso:country":"CH",
    "sg:address":"Eymattstrasse 7",
    "sg:city":"Bern",
    "sg:orig_category":"Einbau von Schreinerwaren Herstellung von K\u00fcchenm\u00f6beln",
    "sg:postcode":"3027",
    "sg:province":"Bern",
    "wof:name":"Veriset K\u00fcchen Ag K\u00fcchen & Schr\u00e4nke Zweigniederlassung Bern",
    "wof:placetype":"venue"
},
  "geometry": {"coordinates":[7.3933501244,46.9503631592],"type":"Point"}
}