{
  "type": "Feature",
  "properties": {
    "iso:country":"CH",
    "sg:address":"Luzernerstrasse 33c",
    "sg:city":"Kriens",
    "sg:orig_category":"Fussboden, Fliesen U Plattenlegerei, Tapeziererei",
    "sg:phone":"+41 71 278 22 85",
    "sg:postcode":"6010",
    "sg:province":"Luzern",
    "wof:name":"Sch\u00e4llebaum Parkett Ag",
    "wof:placetype":"venue"
},
  "geometry": {"coordinates":[9.3336420059,47.4094810486],"type":"Point"}
}