{
  "type": "Feature",
  "properties": {
    "iso:country":"CH",
    "sg:address":"Kirchstrasse 4",
    "sg:city":"G\u00e4hwil",
    "sg:orig_category":"Maler U Glasergewerbe",
    "sg:postcode":"9534",
    "sg:province":"St. Gallen",
    "wof:name":"G\u00c4hwiler Steve Gmbh",
    "wof:placetype":"venue"
},
  "geometry": {"coordinates":[9.0020885468,47.3979797363],"type":"Point"}
}