{
  "type": "Feature",
  "properties": {
    "iso:country":"CH",
    "sg:address":"M\u00fcliwiesstrasse 95",
    "sg:city":"Zell",
    "sg:classifiers":[
        {
            "category":"Organizations",
            "subcategory":"Labor Organization",
            "type":"Services"
        }
    ],
    "sg:phone":"+41 52 394 01 25",
    "sg:postcode":"8487",
    "sg:province":"Z\u00fcrich",
    "sg:tags":[
        "work",
        "assembling",
        "assembly",
        "contract"
    ],
    "wof:name":"Rolf Waltert Montagen",
    "wof:placetype":"venue"
},
  "geometry": {"coordinates":[8.820244,47.441914],"type":"Point"}
}