{
  "type": "Feature",
  "properties": {
    "iso:country":"CH",
    "sg:address":"Fulenbacherstrasse 45",
    "sg:city":"Wolfwil",
    "sg:orig_category":"Vereine Musik/Blasmusik",
    "sg:phone":"+41 71 994 13 77",
    "sg:postcode":"4628",
    "sg:province":"Solothurn",
    "wof:name":"Musikgesellschaft Harmonie",
    "wof:placetype":"venue"
},
  "geometry": {"coordinates":[9.1951990128,47.2326202393],"type":"Point"}
}