{
  "type": "Feature",
  "properties": {
    "iso:country":"CH",
    "sg:address":"9404 Rorschacherberg. Postfach 239",
    "sg:city":"Rorschacherberg",
    "sg:orig_category":"Sportvereine Ballsport Badminton",
    "sg:postcode":"9404",
    "sg:province":"St. Gallen",
    "wof:name":"Badminton-club Reinach-wyna",
    "wof:placetype":"venue"
},
  "geometry": {"coordinates":[8.1501808167,47.2220344543],"type":"Point"}
}