{
  "type": "Feature",
  "properties": {
    "iso:country":"CH",
    "sg:address":"1255",
    "sg:city":"Veyrier",
    "sg:orig_category":"Vereine Gesang",
    "sg:phone":"+41 22 784 16 43",
    "sg:postcode":"1255",
    "sg:province":"Gen\u00e8ve",
    "wof:name":"Chorale Catholique",
    "wof:placetype":"venue"
},
  "geometry": {"coordinates":[6.1743302345,46.1731300354],"type":"Point"}
}