{
  "type": "Feature",
  "properties": {
    "iso:country":"CH",
    "sg:address":"Schulstrasse 7",
    "sg:city":"Frenkendorf",
    "sg:orig_category":"Bauspenglerei Sanit\u00e4r, Heizungs U L\u00fcftungsinstallation",
    "sg:phone":"+41 61 901 15 92",
    "sg:postcode":"4402",
    "sg:province":"Basel-Landschaft",
    "wof:name":"Dr\u00e4yer Ag Sanit\u00e4r Spenglerei Heizung",
    "wof:placetype":"venue"
},
  "geometry": {"coordinates":[7.7163,47.501991],"type":"Point"}
}