{
  "type": "Feature",
  "properties": {
    "iso:country":"CH",
    "sg:address":"Churerstrasse",
    "sg:city":"Rorschach",
    "sg:orig_category":"RESTAURANTS: TEA-ROOMS",
    "sg:postcode":"9400",
    "sg:province":"St. Gallen",
    "wof:name":"Seerestaurant, Capuano Gionatan",
    "wof:placetype":"venue"
},
  "geometry": {"coordinates":[9.5026750565,47.4780158997],"type":"Point"}
}