{
  "type": "Feature",
  "properties": {
    "iso:country":"CH",
    "sg:address":"6952 Canobbio. Postfach Caselle Postale 61",
    "sg:city":"Canobbio",
    "sg:orig_category":"Sportschulen Fern\u00f6stliche Kampfsportarten Sportvereine Judo and Karate",
    "sg:postcode":"6952",
    "sg:province":"Ticino",
    "wof:name":"Nenryu Karate Lugano 1 & 2",
    "wof:placetype":"venue"
},
  "geometry": {"coordinates":[8.9687299728,46.0362205505],"type":"Point"}
}