{
  "type": "Feature",
  "properties": {
    "iso:country":"CH",
    "sg:address":"K\u00e4rpfstrasse 39b 8752 N\u00e4fels. Postfach",
    "sg:city":"N\u00e4fels",
    "sg:orig_category":"Handel mit Automobilen",
    "sg:postcode":"8752",
    "sg:province":"Glarus",
    "wof:name":"Exim Gmbh",
    "wof:placetype":"venue"
},
  "geometry": {"coordinates":[9.0590934753,47.0912094116],"type":"Point"}
}