{
  "type": "Feature",
  "properties": {
    "iso:country":"CH",
    "sg:address":"Alpenstrasse 2 3800 Interlaken. Postfach 219",
    "sg:city":"Interlaken",
    "sg:orig_category":"Unternehmensberatung Wirtschaftspr\u00fcfung, Steuerberatung U Treuhand",
    "sg:phone":"+41 79 411 57 58",
    "sg:postcode":"3800",
    "sg:province":"Bern",
    "wof:name":"K\u00e4mpf & Stauffer Treuhand Ag",
    "wof:placetype":"venue"
},
  "geometry": {"coordinates":[7.8577327728,46.6841468811],"type":"Point"}
}