{
  "type": "Feature",
  "properties": {
    "iso:country":"CH",
    "sg:address":"Kelchbachstrasse 5",
    "sg:city":"Naters",
    "sg:orig_category":"Arztpraxen",
    "sg:phone":"+41 27 924 44 04",
    "sg:postcode":"3904",
    "sg:province":"Valais",
    "wof:name":"Dr.med.anton Werner Kreuzer Spezialarzt Fmh",
    "wof:placetype":"venue"
},
  "geometry": {"coordinates":[7.990446,46.324215],"type":"Point"}
}