{
  "type": "Feature",
  "properties": {
    "iso:country":"CH",
    "sg:address":"Hauptstrasse 28",
    "sg:city":"Speicher",
    "sg:classifiers":[
        {
            "category":"Restaurant",
            "type":"Food & Drink"
        }
    ],
    "sg:phone":"+41 71 344 15 77",
    "sg:postcode":"9042",
    "sg:province":"Appenzell Ausserrhoden",
    "wof:name":"Restaurant Spycher-st\u00f6bli",
    "wof:placetype":"venue"
},
  "geometry": {"coordinates":[9.4415378571,47.4118728638],"type":"Point"}
}