{
  "type": "Feature",
  "properties": {
    "iso:country":"CH",
    "sg:address":"Dennigkofenweg 79",
    "sg:city":"G\u00fcmligen",
    "sg:orig_category":"Non-Classified Establishments",
    "sg:postcode":"3073",
    "sg:province":"Bern",
    "wof:name":"Domenico Zaccaria Gmbh",
    "wof:placetype":"venue"
},
  "geometry": {"coordinates":[7.5016231537,46.9367103577],"type":"Point"}
}