{
  "type": "Feature",
  "properties": {
    "iso:country":"CH",
    "sg:address":"Kreuzfeldstrasse 52 4932 Lotzwil. Postfach 126",
    "sg:city":"Lotzwil",
    "sg:orig_category":"Architektur U Ingenieurb\u00fcros",
    "sg:phone":"+41 62 922 62 82",
    "sg:postcode":"4932",
    "sg:province":"Bern",
    "wof:name":"Fritz Wyss",
    "wof:placetype":"venue"
},
  "geometry": {"coordinates":[7.787471,47.196198],"type":"Point"}
}