{
  "type": "Feature",
  "properties": {
    "iso:country":"CH",
    "sg:address":"Malagnou Route De 26",
    "sg:city":"Gen\u00e8ve",
    "sg:orig_category":"Unclassifiable Establishments",
    "sg:postcode":"1208",
    "sg:province":"Gen\u00e8ve",
    "wof:name":"Newiss Holding Sa",
    "wof:placetype":"venue"
},
  "geometry": {"coordinates":[6.1595749855,46.1975708008],"type":"Point"}
}