{
  "type": "Feature",
  "properties": {
    "iso:country":"CH",
    "sg:address":"Glockengasse 5",
    "sg:city":"Z\u00fcrich",
    "sg:orig_category":"Finanzierungsinstitutionen",
    "sg:phone":"+41 12127575",
    "sg:postcode":"8001",
    "sg:province":"Z\u00fcrich",
    "wof:name":"Hunkeler Franz Finanzberatung, Verm\u00f6gensverwaltung",
    "wof:placetype":"venue"
},
  "geometry": {"coordinates":[8.5406303406,47.3717803955],"type":"Point"}
}