{
  "type": "Feature",
  "properties": {
    "iso:country":"CH",
    "sg:address":"Via Leoncavallo 6614 Brissago. Postfach Caselle Postale 248",
    "sg:city":"Brissago",
    "sg:orig_category":"Detailhandel mit fotografischen Artikeln Fachdetailhandel in Verkaufsr\u00e4umen",
    "sg:phone":"+41 91 793 12 27",
    "sg:postcode":"6614",
    "sg:province":"Ticino",
    "wof:name":"Bischof Karl",
    "wof:placetype":"venue"
},
  "geometry": {"coordinates":[8.7111787796,46.1198768616],"type":"Point"}
}