{
  "type": "Feature",
  "properties": {
    "iso:country":"CH",
    "sg:address":"Neuhofstrasse 50",
    "sg:city":"Lindau",
    "sg:classifiers":[
        {
            "category":"Structure",
            "subcategory":"Tunnel",
            "type":"Public Place"
        }
    ],
    "sg:phone":"+41 52 355 01 55",
    "sg:postcode":"8315",
    "sg:province":"Z\u00fcrich",
    "sg:tags":[
        "aluminium",
        "fence"
    ],
    "wof:name":"Walter Benz Zaunfabrik",
    "wof:placetype":"venue"
},
  "geometry": {"coordinates":[8.676951,47.44038],"type":"Point"}
}