{
  "type": "Feature",
  "properties": {
    "iso:country":"CH",
    "sg:address":"Corso San Gottardo 14",
    "sg:city":"Chiasso",
    "sg:orig_category":"Verwaltung von Immobilien",
    "sg:phone":"+41 71 944 19 66",
    "sg:postcode":"6830",
    "sg:province":"Ticino",
    "wof:name":"Shop Rastst\u00e4tte Thurau Ag Zuzwil",
    "wof:placetype":"venue"
},
  "geometry": {"coordinates":[9.0534296036,47.4628791809],"type":"Point"}
}