{
  "type": "Feature",
  "properties": {
    "iso:country":"CH",
    "sg:address":"B\u00fc\u00fcndering 20 3312 Fraubrunnen. Postfach",
    "sg:city":"Fraubrunnen",
    "sg:orig_category":"Herstellung von elektronischen Bauelementen",
    "sg:phone":"+41 31 767 75 67",
    "sg:postcode":"3312",
    "sg:province":"Bern",
    "wof:name":"Welec W\u00fcthrich Christoph Electronic Elektro-dienstleistungen",
    "wof:placetype":"venue"
},
  "geometry": {"coordinates":[7.5301132202,47.0842514038],"type":"Point"}
}