{
  "type": "Feature",
  "properties": {
    "iso:country":"CH",
    "sg:address":"Riedlistrasse 56",
    "sg:city":"Belp",
    "sg:orig_category":"Unternehmensberatung",
    "sg:phone":"+41 31 812 01 02",
    "sg:postcode":"3123",
    "sg:province":"Bern",
    "wof:name":"Sauter Urs",
    "wof:placetype":"venue"
},
  "geometry": {"coordinates":[7.5069408417,46.8788719177],"type":"Point"}
}