{
  "type": "Feature",
  "properties": {
    "iso:country":"CH",
    "sg:address":"Poststrasse 8",
    "sg:city":"Schleitheim",
    "sg:orig_category":"Malerei",
    "sg:phone":"+41 52 680 19 88",
    "sg:postcode":"8226",
    "sg:province":"Schaffhausen",
    "wof:name":"Christian Fl\u00f6rchinger Malergesch\u00e4ft",
    "wof:placetype":"venue"
},
  "geometry": {"coordinates":[8.4847583771,47.7500457764],"type":"Point"}
}