{
  "type": "Feature",
  "properties": {
    "iso:country":"CH",
    "sg:address":"Mittlere Strasse 36",
    "sg:city":"Basel",
    "sg:orig_category":"Interessenvertretungen",
    "sg:postcode":"4056",
    "sg:province":"Basel-Stadt",
    "wof:name":"Jacob Burckhardt-stiftung",
    "wof:placetype":"venue"
},
  "geometry": {"coordinates":[7.5785360336,47.5613632202],"type":"Point"}
}