{
  "type": "Feature",
  "properties": {
    "iso:country":"CH",
    "sg:address":"Rue Du Pr\u00e9-de-la-reine 7",
    "sg:city":"Cartigny",
    "sg:orig_category":"Gemeindeverwaltungen",
    "sg:phone":"+41 26 927 11 66",
    "sg:postcode":"1236",
    "sg:province":"Gen\u00e8ve",
    "wof:name":"Administration Communale De Cerniat",
    "wof:placetype":"venue"
},
  "geometry": {"coordinates":[7.157790184,46.6337089539],"type":"Point"}
}