{
  "type": "Feature",
  "properties": {
    "iso:country":"CH",
    "sg:address":"Piazza Riscossa 16 6900 Lugano. Postfach",
    "sg:city":"Lugano",
    "sg:orig_category":"Dienstleistungen von Beteiligungsgesellschaften",
    "sg:postcode":"6900",
    "sg:province":"Ticino",
    "wof:name":"Enthusia Capital Management Sa, Lussemburgo, Succursale Di Lugano",
    "wof:placetype":"venue"
},
  "geometry": {"coordinates":[8.9680137634,46.0066375732],"type":"Point"}
}