{
  "type": "Feature",
  "properties": {
    "iso:country":"CH",
    "sg:address":"3856",
    "sg:city":"Brienzwiler",
    "sg:orig_category":"Sportvereine Sch\u00fctzen",
    "sg:phone":"+41 31 751 05 11",
    "sg:postcode":"3856",
    "sg:province":"Bern",
    "wof:name":"Freisch\u00fctzengesellschaft",
    "wof:placetype":"venue"
},
  "geometry": {"coordinates":[8.0995616913,46.752281189],"type":"Point"}
}