{
  "type": "Feature",
  "properties": {
    "addr:full":"Baltenswilerstrasse 2 N\u00fcrensdorf Z\u00fcrich 8309",
    "addr:housenumber":"2",
    "addr:postcode":"8309",
    "addr:street":"Baltenswilerstrasse",
    "iso:country":"CH",
    "sg:address":"Baltenswilerstrasse 2",
    "sg:city":"N\u00fcrensdorf",
    "sg:orig_category":"Detailhandel mit Brot, Back U S\u00fcsswaren",
    "sg:phone":"+41 18365890",
    "sg:postcode":"8309",
    "sg:province":"Z\u00fcrich",
    "wof:name":"Confiserie Mathys Ag",
    "wof:placetype":"venue"
},
  "geometry": {"coordinates":[8.649467,47.445976],"type":"Point"}
}