{
  "type": "Feature",
  "properties": {
    "iso:country":"CH",
    "sg:address":"Rieserstrasse 25",
    "sg:city":"Muttenz",
    "sg:orig_category":"Sportvereine Jagd",
    "sg:phone":"+41 31 747 85 20",
    "sg:postcode":"4132",
    "sg:province":"Basel-Landschaft",
    "wof:name":"Jagd-& Wildschutzverein",
    "wof:placetype":"venue"
},
  "geometry": {"coordinates":[7.2639498711,46.9152984619],"type":"Point"}
}