{
  "type": "Feature",
  "properties": {
    "iso:country":"CH",
    "sg:address":"Z\u00fcrichstrasse 34",
    "sg:city":"Adliswil",
    "sg:orig_category":"Softwareentwicklung U beratung",
    "sg:postcode":"8134",
    "sg:province":"Z\u00fcrich",
    "wof:name":"Elcasys Ag",
    "wof:placetype":"venue"
},
  "geometry": {"coordinates":[9.5634069443,47.3186531067],"type":"Point"}
}