{
  "type": "Feature",
  "properties": {
    "iso:country":"CH",
    "sg:address":"Schafb\u00fcchelstrasse 1",
    "sg:city":"Ebnat-kappel",
    "sg:orig_category":"Primarschulen",
    "sg:phone":"+41 41 448 15 88",
    "sg:postcode":"9642",
    "sg:province":"St. Gallen",
    "wof:name":"Primarschule Lindenfeld",
    "wof:placetype":"venue"
},
  "geometry": {"coordinates":[8.3200302124,47.13256073],"type":"Point"}
}