{
  "type": "Feature",
  "properties": {
    "iso:country":"CH",
    "sg:address":"Bonnstrasse 22",
    "sg:city":"D\u00fcdingen",
    "sg:orig_category":"Fachdetailhandel in Verkaufsr\u00e4umen Grosshandel mit Sportartikeln",
    "sg:phone":"+41 71 311 41 72",
    "sg:postcode":"3186",
    "sg:province":"Fribourg",
    "wof:name":"Henke Sports Ag",
    "wof:placetype":"venue"
},
  "geometry": {"coordinates":[9.3178453445,47.4253807068],"type":"Point"}
}