{
  "type": "Feature",
  "properties": {
    "iso:country":"CH",
    "sg:address":"Schulstrasse 13",
    "sg:city":"Rheinau",
    "sg:orig_category":"Primarschulen",
    "sg:phone":"+41 52 319 19 40",
    "sg:postcode":"8462",
    "sg:province":"Z\u00fcrich",
    "wof:name":"Primarschule",
    "wof:placetype":"venue"
},
  "geometry": {"coordinates":[8.6015110016,47.6433029175],"type":"Point"}
}