{
  "type": "Feature",
  "properties": {
    "iso:country":"CH",
    "sg:address":"1969 St-martin Vs. Postfach",
    "sg:city":"Vernami\u00e8ge",
    "sg:orig_category":"Architektur U Ingenieurb\u00fcros",
    "sg:postcode":"1961",
    "sg:province":"Valais",
    "wof:name":"Pralong Dr. Jean Et Ass. Sa",
    "wof:placetype":"venue"
},
  "geometry": {"coordinates":[7.438925,46.177898],"type":"Point"}
}