{
  "type": "Feature",
  "properties": {
    "iso:country":"CH",
    "sg:address":"Chemin St-hubert 2",
    "sg:city":"Sion",
    "sg:orig_category":"Detailhandel mit Metallwaren, Anstrichmitteln, Glaswaren, Bau U Heimwerkerbedarf Handelsvermittlung ",
    "sg:phone":"+41 27 322 08 00",
    "sg:postcode":"1950",
    "sg:province":"Valais",
    "wof:name":"A-t Technologies Gmbh",
    "wof:placetype":"venue"
},
  "geometry": {"coordinates":[7.3508491516,46.2247123718],"type":"Point"}
}