{
  "type": "Feature",
  "properties": {
    "iso:country":"CH",
    "sg:address":"Grand Rue 46",
    "sg:city":"Montreux",
    "sg:classifiers":[
        {
            "category":"Train Station",
            "subcategory":"Rail",
            "type":"Transportation"
        }
    ],
    "sg:phone":"+41 32 930 83 11",
    "sg:postcode":"1820",
    "sg:province":"Vaud",
    "sg:tags":[
        "watch",
        "jewel",
        "movement"
    ],
    "wof:name":"Comadur S.a.",
    "wof:placetype":"venue"
},
  "geometry": {"coordinates":[6.7565307617,47.0619659424],"type":"Point"}
}