{
  "type": "Feature",
  "properties": {
    "iso:country":"CH",
    "sg:address":"Wittenberg 36",
    "sg:city":"Golaten",
    "sg:orig_category":"Offsetdruck Satzherstellung U Reproduktion",
    "sg:phone":"+41 31 755 50 80",
    "sg:postcode":"3207",
    "sg:province":"Bern",
    "wof:name":"Arsenus Druck",
    "wof:placetype":"venue"
},
  "geometry": {"coordinates":[7.2387070656,46.9708595276],"type":"Point"}
}