{
  "type": "Feature",
  "properties": {
    "iso:country":"CH",
    "sg:address":"Bordackerstrasse 37",
    "sg:city":"Uster",
    "sg:orig_category":"Zahntechnische Laboratorien",
    "sg:phone":"+41 19404794",
    "sg:postcode":"8610",
    "sg:province":"Z\u00fcrich",
    "wof:name":"Georges Kunz Zahntechnisches Labor",
    "wof:placetype":"venue"
},
  "geometry": {"coordinates":[8.7330169678,47.349697113],"type":"Point"}
}