{
  "type": "Feature",
  "properties": {
    "iso:country":"CH",
    "sg:address":"Route De Frontenex 45",
    "sg:city":"Gen\u00e8ve",
    "sg:orig_category":"Detailhandel mit Fleisch U Fleischwaren",
    "sg:phone":"+41 22 736 53 00",
    "sg:postcode":"1207",
    "sg:province":"Gen\u00e8ve",
    "wof:name":"Boucherie De Frontenex, Monticelli",
    "wof:placetype":"venue"
},
  "geometry": {"coordinates":[6.1632809639,46.2021827698],"type":"Point"}
}