{
  "type": "Feature",
  "properties": {
    "iso:country":"CH",
    "sg:address":"Kaspar Pfeiffer-strasse 21",
    "sg:city":"M\u00fcnchenstein",
    "sg:orig_category":"Architektur U Ingenieurb\u00fcros Herstellung von elektrischen Lampen U Leuchten",
    "sg:phone":"+41 61 413 10 77",
    "sg:postcode":"4142",
    "sg:province":"Basel-Landschaft",
    "wof:name":"Innotech Innovation Technologies Ag",
    "wof:placetype":"venue"
},
  "geometry": {"coordinates":[7.608052,47.521866],"type":"Point"}
}