{
  "type": "Feature",
  "properties": {
    "iso:country":"CH",
    "sg:address":"Werkhofstrasse 11 2503 Biel/bienne Case Postale 883",
    "sg:city":"Biel/bienne",
    "sg:orig_category":"Herstellung U Zusammensetzung von Uhren Herstellung von Uhren",
    "sg:phone":"+41 32 953 19 80",
    "sg:postcode":"2501",
    "sg:province":"Bern",
    "wof:name":"Montres Erard Louis Sa",
    "wof:placetype":"venue"
},
  "geometry": {"coordinates":[6.9546117783,47.2242927551],"type":"Point"}
}