{
  "type": "Feature",
  "properties": {
    "iso:country":"CH",
    "sg:address":"Am Schanzengraben 15",
    "sg:city":"Z\u00fcrich",
    "sg:orig_category":"Interessenvertretungen U sonstige Vereinigungen Organisationen der Wohlfahrtspflege",
    "sg:postcode":"8002",
    "sg:province":"Z\u00fcrich",
    "wof:name":"Sve-der Schweiz.fachverband F\u00fcr Sozial-& Heilp\u00e4dagogik",
    "wof:placetype":"venue"
},
  "geometry": {"coordinates":[8.5362234116,47.3686676025],"type":"Point"}
}