{
  "type": "Feature",
  "properties": {
    "iso:country":"CH",
    "sg:address":"Immeuble La Fr\u00e9gate",
    "sg:city":"Montana-vermala",
    "sg:orig_category":"Vermietung U Verpachtung von eigenen Immobilien",
    "sg:postcode":"3962",
    "wof:name":"Chappeli Immobilien Ag",
    "wof:placetype":"venue"
},
  "geometry": {"coordinates":[7.8954749107,46.7019309998],"type":"Point"}
}