{
  "type": "Feature",
  "properties": {
    "iso:country":"CH",
    "sg:address":"Brit",
    "sg:city":"Granges-marnand",
    "sg:orig_category":"Zimmerei, Dachdeckerei, Bauspenglerei U Abdichtung",
    "sg:phone":"+41 26 668 11 94",
    "sg:postcode":"1523",
    "sg:province":"Vaud",
    "wof:name":"Duc S\u00e9bastien",
    "wof:placetype":"venue"
},
  "geometry": {"coordinates":[6.8885741234,46.7652359009],"type":"Point"}
}