{
  "type": "Feature",
  "properties": {
    "iso:country":"CH",
    "sg:address":"Z\u00fcrcherstrasse 73",
    "sg:city":"Thalwil",
    "sg:orig_category":"Einzelhandel mit Automobilteilen U Zubeh\u00f6r Instandhaltung U Reparatur von Automobilen",
    "sg:postcode":"8800",
    "sg:province":"Z\u00fcrich",
    "wof:name":"Thomas M\u00fcller Tyco-servicestelle",
    "wof:placetype":"venue"
},
  "geometry": {"coordinates":[8.5639724731,47.2857093811],"type":"Point"}
}