{
  "type": "Feature",
  "properties": {
    "iso:country":"CH",
    "sg:address":"Bergstrasse 173 8707 Uetikon Am See. Postfach",
    "sg:city":"Z\u00fcrich",
    "sg:orig_category":"Unclassifiable Establishments",
    "sg:postcode":"8046",
    "sg:province":"Z\u00fcrich",
    "wof:name":"Trilog Holding Ag",
    "wof:placetype":"venue"
},
  "geometry": {"coordinates":[8.6763925552,47.2661056519],"type":"Point"}
}