{
  "type": "Feature",
  "properties": {
    "iso:country":"CH",
    "sg:address":"Via Gismonda 13",
    "sg:city":"Mendrisio",
    "sg:classifiers":[
        {
            "category":"Restaurant",
            "type":"Food & Drink"
        }
    ],
    "sg:phone":"+41 91 751 14 13",
    "sg:postcode":"6850",
    "sg:province":"Ticino",
    "wof:name":"Birreria Rondalli",
    "wof:placetype":"venue"
},
  "geometry": {"coordinates":[8.7908401489,46.1678886414],"type":"Point"}
}