{
  "type": "Feature",
  "properties": {
    "iso:country":"CH",
    "sg:address":"In H\u00f6fen 9 8180 B\u00fclach. Postfach",
    "sg:city":"B\u00fclach",
    "sg:orig_category":"Betrieb von Taxis",
    "sg:postcode":"8180",
    "sg:province":"Z\u00fcrich",
    "wof:name":"Taxi Stumpf Hilda B.",
    "wof:placetype":"venue"
},
  "geometry": {"coordinates":[8.52658,47.514095],"type":"Point"}
}