{
  "type": "Feature",
  "properties": {
    "iso:country":"CH",
    "sg:address":"Hauptstrasse 14",
    "sg:city":"Kreuzlingen",
    "sg:orig_category":"Herstellung von medizinischen U chirurgischen Ger\u00e4ten sowie orthop\u00e4dischen Vorrichtungen",
    "sg:postcode":"8280",
    "sg:province":"Thurgau",
    "wof:name":"Ke-dentaltechnik Gmbh",
    "wof:placetype":"venue"
},
  "geometry": {"coordinates":[8.3366804123,47.3527145386],"type":"Point"}
}