{
  "type": "Feature",
  "properties": {
    "iso:country":"CH",
    "sg:address":"Obere Gasse 45",
    "sg:city":"Chur",
    "sg:orig_category":"Grosshandel mit Nahrungsmitteln, Getr\u00e4nken U Tabakwaren ohne ausgepr\u00e4gten Schwerpunkt",
    "sg:postcode":"7000",
    "sg:province":"Graubunden",
    "wof:name":"Trepp's Erben M. Inh. Hartmann-trepp Dora.",
    "wof:placetype":"venue"
},
  "geometry": {"coordinates":[9.5300807953,46.8479194641],"type":"Point"}
}