{
  "type": "Feature",
  "properties": {
    "iso:country":"CH",
    "sg:address":"Constant Place Benjamin- 2 1003 Lausanne Case Postale 111",
    "sg:city":"Lausanne",
    "sg:orig_category":"Vermietung U Verpachtung von eigenen Immobilien",
    "sg:phone":"+41 21 310 19 92",
    "sg:postcode":"1003",
    "sg:province":"Vaud",
    "wof:name":"Rue De La Louve Sa C/o Perrin, Zahnd & Habs Martin",
    "wof:placetype":"venue"
},
  "geometry": {"coordinates":[6.6373381615,46.5192108154],"type":"Point"}
}