{
  "type": "Feature",
  "properties": {
    "iso:country":"CH",
    "sg:address":"Witikonerstrasse 229",
    "sg:city":"Z\u00fcrich",
    "sg:orig_category":"Fahrschulen, Flugschulen",
    "sg:phone":"+41 13815333",
    "sg:postcode":"8053",
    "sg:province":"Z\u00fcrich",
    "wof:name":"Josef Achermann Fahrschule",
    "wof:placetype":"venue"
},
  "geometry": {"coordinates":[8.724896431,47.2737960815],"type":"Point"}
}