{
  "type": "Feature",
  "properties": {
    "iso:country":"CH",
    "sg:address":"Hauptstrasse 14",
    "sg:city":"Amlikon",
    "sg:orig_category":"Detailhandel mit Fleisch U Fleischwaren Grosshandel mit lebenden Tieren",
    "sg:phone":"+41 71 651 12 12",
    "sg:postcode":"8514",
    "sg:province":"Thurgau",
    "wof:name":"Robert Berger Ag Metzgerei & Viehhandel",
    "wof:placetype":"venue"
},
  "geometry": {"coordinates":[9.0586919785,47.5704307556],"type":"Point"}
}