{
  "type": "Feature",
  "properties": {
    "iso:country":"CH",
    "sg:address":"Diolly",
    "sg:city":"Sion",
    "sg:orig_category":"Geometerb\u00fcros",
    "sg:phone":"+41 27 323 15 24",
    "sg:postcode":"1950",
    "sg:province":"Valais",
    "wof:name":"Benjamin Luyet G\u00e9om\u00e8tre Officiel",
    "wof:placetype":"venue"
},
  "geometry": {"coordinates":[7.3425841331,46.235534668],"type":"Point"}
}