{
  "type": "Feature",
  "properties": {
    "iso:country":"CH",
    "sg:address":"Route De Saint-julien 255",
    "sg:city":"Perly",
    "sg:classifiers":[
        {
            "category":"Home & Garden",
            "subcategory":"Building Materials",
            "type":"Retail Goods"
        }
    ],
    "sg:phone":"+41 22 771 38 78",
    "sg:postcode":"1258",
    "sg:province":"Gen\u00e8ve",
    "sg:tags":[
        "sheath",
        "tubular"
    ],
    "wof:name":"Spaggiari Ventilation S.a.",
    "wof:placetype":"venue"
},
  "geometry": {"coordinates":[6.0981349945,46.1580429077],"type":"Point"}
}