{
  "type": "Feature",
  "properties": {
    "iso:country":"CH",
    "sg:address":"Bahnhofstrasse 96",
    "sg:city":"Ilanz",
    "sg:orig_category":"Reiseb\u00fcros U Reiseveranstalter",
    "sg:postcode":"7130",
    "sg:province":"Graubunden",
    "wof:name":"Eden Montana Ferienclub Ag Ilanz",
    "wof:placetype":"venue"
},
  "geometry": {"coordinates":[9.207485199,46.7749977112],"type":"Point"}
}