{
  "type": "Feature",
  "properties": {
    "iso:country":"CH",
    "sg:address":"K\u00e4rpfgasse 10",
    "sg:city":"Glarus",
    "sg:orig_category":"Sonstige Institutionen des Sozialwesens ohne Beherbergung",
    "sg:phone":"+41 55 640 62 82",
    "sg:postcode":"8750",
    "sg:province":"Glarus",
    "wof:name":"Beratungsstelle F\u00fcr Ehe, Familien-& Sexualfragen",
    "wof:placetype":"venue"
},
  "geometry": {"coordinates":[9.0693998337,47.0370559692],"type":"Point"}
}