{
  "type": "Feature",
  "properties": {
    "iso:country":"CH",
    "sg:address":"Chemin Des Pilons 3",
    "sg:city":"Bulle",
    "sg:orig_category":"Unclassifiable Establishments",
    "sg:postcode":"1630",
    "sg:province":"Fribourg",
    "wof:name":"Oligoc\u00e9an Produits Pour Animaux",
    "wof:placetype":"venue"
},
  "geometry": {"coordinates":[7.0613059998,46.6243629456],"type":"Point"}
}