{
  "type": "Feature",
  "properties": {
    "iso:country":"CH",
    "sg:address":"Kleinfeldstrasse 156",
    "sg:city":"Winznau",
    "sg:orig_category":"Bauschreinerei Herstellung von Konstruktionsteilen, Fertigbauteilen U Ausbauelementen aus Holz",
    "sg:phone":"+41 62 295 13 20",
    "sg:postcode":"4652",
    "sg:province":"Solothurn",
    "wof:name":"Gr\u00fctter Josef Innenausbau",
    "wof:placetype":"venue"
},
  "geometry": {"coordinates":[7.9378008842,47.361995697],"type":"Point"}
}