{
  "type": "Feature",
  "properties": {
    "iso:country":"CH",
    "sg:address":"Lausanne Rue De 43 1201 Gen\u00e8ve. Postfach",
    "sg:city":"Gen\u00e8ve",
    "sg:orig_category":"Technische, physikalische U chemische Untersuchung",
    "sg:postcode":"1201",
    "sg:province":"Gen\u00e8ve",
    "wof:name":"Environmental Services For Industry (e.s.i)",
    "wof:placetype":"venue"
},
  "geometry": {"coordinates":[6.1452798843,46.2133369446],"type":"Point"}
}