{
  "type": "Feature",
  "properties": {
    "iso:country":"CH",
    "sg:address":"Via Bramantino 1",
    "sg:city":"Locarno",
    "sg:orig_category":"Zahnarztpraxen",
    "sg:phone":"+41 91 751 62 12",
    "sg:postcode":"6600",
    "sg:province":"Ticino",
    "wof:name":"Dottori Med.dent. Franscini Dentisti",
    "wof:placetype":"venue"
},
  "geometry": {"coordinates":[8.8017988205,46.1675567627],"type":"Point"}
}