{
  "type": "Feature",
  "properties": {
    "iso:country":"CH",
    "sg:address":"Bahnhofstrasse 3",
    "sg:city":"Sch\u00fcpfheim",
    "sg:orig_category":"Konkurs- and Betreibungs\u00e4mter",
    "sg:phone":"+41 41 484 18 86",
    "sg:postcode":"6170",
    "sg:province":"Luzern",
    "wof:name":"Konkursamt Des Amtes Entlebuch",
    "wof:placetype":"venue"
},
  "geometry": {"coordinates":[8.0165958405,46.9507713318],"type":"Point"}
}