{
  "type": "Feature",
  "properties": {
    "addr:full":"Dorfstrasse 19a 6340 Baar. Postfach 394 Baar Zug 6341",
    "addr:housenumber":"19a;394",
    "addr:postcode":"6340 baar.;6341",
    "addr:street":"Dorfstrasse;Postfach;Zug",
    "iso:country":"CH",
    "sg:address":"Dorfstrasse 19a 6340 Baar. Postfach 394",
    "sg:city":"Baar",
    "sg:orig_category":"Architektur U Ingenieurb\u00fcros Schiffsbau ohne Boots U Yachtbau",
    "sg:phone":"+41 41 761 14 77",
    "sg:postcode":"6341",
    "sg:province":"Zug",
    "wof:name":"Techconsult Ag",
    "wof:placetype":"venue"
},
  "geometry": {"coordinates":[8.524756,47.19392],"type":"Point"}
}