{
  "type": "Feature",
  "properties": {
    "addr:full":"Im Hof 4 Gipf-oberfrick Aargau 5073",
    "addr:housenumber":"4",
    "addr:postcode":"5073",
    "addr:street":"Im Hof",
    "iso:country":"CH",
    "sg:address":"Im Hof 4",
    "sg:city":"Gipf-oberfrick",
    "sg:orig_category":"Bauspenglerei Sanit\u00e4rinstallation",
    "sg:phone":"+41 61 851 28 22",
    "sg:postcode":"5073",
    "sg:province":"Aargau",
    "wof:name":"Hans Walker Sanit\u00e4r-heizung-spenglerei",
    "wof:placetype":"venue"
},
  "geometry": {"coordinates":[7.998161,47.493603],"type":"Point"}
}