{
  "type": "Feature",
  "properties": {
    "iso:country":"CH",
    "sg:address":"Haldenstrasse 65",
    "sg:city":"Z\u00fcrich",
    "sg:orig_category":"Datenbanken Softwareentwicklung U beratung",
    "sg:phone":"+41 14542000",
    "sg:postcode":"8045",
    "sg:province":"Z\u00fcrich",
    "wof:name":"Catsoft Development Dipl. Ing. Eth Gmbh",
    "wof:placetype":"venue"
},
  "geometry": {"coordinates":[8.516211,47.365162],"type":"Point"}
}