{
  "type": "Feature",
  "properties": {
    "iso:country":"CH",
    "sg:address":"Weggisgasse 32",
    "sg:city":"Luzern",
    "sg:orig_category":"Detailhandel mit Schuhen",
    "sg:phone":"+41 56 621 84 77",
    "sg:postcode":"6004",
    "sg:province":"Luzern",
    "wof:name":"Dosenbach Schuhe",
    "wof:placetype":"venue"
},
  "geometry": {"coordinates":[8.2733049393,47.3495101929],"type":"Point"}
}