{
  "type": "Feature",
  "properties": {
    "iso:country":"CH",
    "sg:address":"Via Crusch 27",
    "sg:city":"Rh\u00e4z\u00fcns",
    "sg:orig_category":"Kaminfeger",
    "sg:phone":"+41 81 641 22 30",
    "sg:postcode":"7403",
    "sg:province":"Graubunden",
    "wof:name":"Lorenz Camenisch Kaminfegermeister",
    "wof:placetype":"venue"
},
  "geometry": {"coordinates":[9.3948259354,46.8006439209],"type":"Point"}
}