{
  "type": "Feature",
  "properties": {
    "iso:country":"CH",
    "sg:address":"Vorstadt 5 6130 Willisau. Postfach",
    "sg:city":"Willisau",
    "sg:orig_category":"Elektroinstallation",
    "sg:phone":"+41 41 970 22 40",
    "sg:postcode":"6130",
    "sg:province":"Luzern",
    "wof:name":"El-be F\u00fcr Moderne Elektrik Ag Willisau",
    "wof:placetype":"venue"
},
  "geometry": {"coordinates":[7.9943971634,47.1210021973],"type":"Point"}
}