{
  "type": "Feature",
  "properties": {
    "iso:country":"CH",
    "sg:address":"Schafmattweg 46",
    "sg:city":"B\u00f6singen",
    "sg:orig_category":"Non-Classified Establishments",
    "sg:postcode":"3178",
    "sg:province":"Fribourg",
    "wof:name":"Future Care Trading Grossen Daniel",
    "wof:placetype":"venue"
},
  "geometry": {"coordinates":[7.2370009422,46.8956642151],"type":"Point"}
}