{
  "type": "Feature",
  "properties": {
    "iso:country":"CH",
    "sg:address":"Alte Strasse 35",
    "sg:city":"Adelboden",
    "sg:orig_category":"Primarschulen",
    "sg:phone":"+41 33 673 31 03",
    "sg:postcode":"3715",
    "sg:province":"Bern",
    "wof:name":"Primarschule Hirzboden",
    "wof:placetype":"venue"
},
  "geometry": {"coordinates":[7.5837898254,46.4998512268],"type":"Point"}
}