{
  "type": "Feature",
  "properties": {
    "iso:country":"CH",
    "sg:address":"Emil Frey-strasse 120",
    "sg:city":"M\u00fcnchenstein",
    "sg:orig_category":"Unternehmensberatung Wirtschaftspr\u00fcfung, Steuerberatung U Treuhand",
    "sg:phone":"+41 61 411 33 13",
    "sg:postcode":"4142",
    "sg:province":"Basel-Landschaft",
    "wof:name":"Tobler Treuhand",
    "wof:placetype":"venue"
},
  "geometry": {"coordinates":[7.6113181114,47.5283813477],"type":"Point"}
}