{
  "type": "Feature",
  "properties": {
    "iso:country":"CH",
    "sg:address":"R\u00fcegisingerstr. 5 6032 Emmen. Postfach",
    "sg:city":"Emmenbr\u00fccke",
    "sg:orig_category":"Softwareentwicklung U beratung",
    "sg:phone":"+41 41 260 05 17",
    "sg:postcode":"6020",
    "sg:province":"Luzern",
    "wof:name":"J.r. Computer-service Roos Josef",
    "wof:placetype":"venue"
},
  "geometry": {"coordinates":[8.2929477692,47.0859069824],"type":"Point"}
}