{
  "type": "Feature",
  "properties": {
    "iso:country":"CH",
    "sg:address":"Eichenweg 1",
    "sg:city":"Liestal",
    "sg:orig_category":"Autogaragen Autospenglereien",
    "sg:phone":"+41 61 901 63 00",
    "sg:postcode":"4410",
    "sg:province":"Basel-Landschaft",
    "wof:name":"Bingo Garage & Carrosserie",
    "wof:placetype":"venue"
},
  "geometry": {"coordinates":[7.72748,47.490936],"type":"Point"}
}