{
  "type": "Feature",
  "properties": {
    "iso:country":"CH",
    "sg:address":"Mutschellenstrasse 22",
    "sg:city":"Bellikon",
    "sg:orig_category":"Maurerarbeiten",
    "sg:phone":"+41 56 496 69 09",
    "sg:postcode":"5454",
    "sg:province":"Aargau",
    "wof:name":"Andreas Mordasini Kundenmaurer",
    "wof:placetype":"venue"
},
  "geometry": {"coordinates":[8.3455524445,47.3870048523],"type":"Point"}
}