{
  "type": "Feature",
  "properties": {
    "iso:country":"CH",
    "sg:address":"Burgfelderstrasse 9",
    "sg:city":"Basel",
    "sg:orig_category":"Arztpraxen",
    "sg:phone":"+41 61 301 14 24",
    "sg:postcode":"4055",
    "sg:province":"Basel-Stadt",
    "wof:name":"Dr.med.hans-ruedi Banderet Spezialarzt",
    "wof:placetype":"venue"
},
  "geometry": {"coordinates":[7.57301,47.562229],"type":"Point"}
}