{
  "type": "Feature",
  "properties": {
    "iso:country":"CH",
    "sg:address":"Riedstrasse 14",
    "sg:city":"Dietikon",
    "sg:classifiers":[
        {
            "category":"Building & Trades",
            "subcategory":"Electrical",
            "type":"Services"
        }
    ],
    "sg:phone":"+41 17406676",
    "sg:postcode":"8953",
    "sg:province":"Z\u00fcrich",
    "sg:tags":[
        "repair",
        "installation"
    ],
    "wof:name":"Abc Installationen Ag",
    "wof:placetype":"venue"
},
  "geometry": {"coordinates":[8.3954296112,47.4204406738],"type":"Point"}
}