{
  "type": "Feature",
  "properties": {
    "iso:country":"CH",
    "sg:address":"Horbengasse 1",
    "sg:city":"Sch\u00fcpfen",
    "sg:orig_category":"Zahnarztpraxen",
    "sg:phone":"+41 31 879 12 39",
    "sg:postcode":"3054",
    "sg:province":"Bern",
    "wof:name":"Dr. Med. Dent. Peter Remund Zahnarzt",
    "wof:placetype":"venue"
},
  "geometry": {"coordinates":[7.3784399033,47.0410881042],"type":"Point"}
}