{
  "type": "Feature",
  "properties": {
    "iso:country":"CH",
    "sg:address":"Industriestrasse 36",
    "sg:city":"Rorschach",
    "sg:orig_category":"Grosshandel mit Parf\u00fcmerieartikeln U K\u00f6rperpflegemitteln Herstellung von Duft U K\u00f6rperpflegemitteln",
    "sg:phone":"+41 71 845 14 45",
    "sg:postcode":"9400",
    "sg:province":"St. Gallen",
    "wof:name":"Alpine Herbs Produkte Ag",
    "wof:placetype":"venue"
},
  "geometry": {"coordinates":[9.4834537506,47.4754867554],"type":"Point"}
}