{
  "type": "Feature",
  "properties": {
    "iso:country":"CH",
    "sg:address":"Pr\u00e8s Du Ch\u00e2teau",
    "sg:city":"Daillens",
    "sg:orig_category":"Detailhandel mit elektrischen Haushalts-,Radio U Fernsehger\u00e4ten sowie Musikinstrumenten",
    "sg:postcode":"1306",
    "sg:province":"Vaud",
    "wof:name":"Pam Dienstleistungs Gmbh Dienstl. Im Bereich Haushalt Usw",
    "wof:placetype":"venue"
},
  "geometry": {"coordinates":[7.8671069145,47.3444023132],"type":"Point"}
}