{
  "type": "Feature",
  "properties": {
    "iso:country":"CH",
    "sg:address":"Langensandstrasse 23 6000 Luzern. Postfach",
    "sg:city":"Luzern",
    "sg:orig_category":"Fachdetailhandel in Verkaufsr\u00e4umen",
    "sg:postcode":"6003",
    "sg:province":"Luzern",
    "wof:name":"Marti Optik Gmbh",
    "wof:placetype":"venue"
},
  "geometry": {"coordinates":[8.3275680542,47.0372085571],"type":"Point"}
}