{
  "type": "Feature",
  "properties": {
    "addr:full":"Fabrikstrasse 10 Herzogenbuchsee Bern 3360",
    "addr:housenumber":"10",
    "addr:postcode":"3360",
    "addr:street":"Fabrikstrasse;Bern",
    "iso:country":"CH",
    "sg:address":"Fabrikstrasse 10",
    "sg:city":"Herzogenbuchsee",
    "sg:orig_category":"Detailhandel mit Bekleidung Detailhandel mit Herrenbekleidung",
    "sg:phone":"+41 62 961 22 45",
    "sg:postcode":"3360",
    "sg:province":"Bern",
    "wof:name":"Boutique New-point, Gissi Christine",
    "wof:placetype":"venue"
},
  "geometry": {"coordinates":[7.704664,47.188862],"type":"Point"}
}