{
  "type": "Feature",
  "properties": {
    "iso:country":"CH",
    "sg:address":"Place Du March\u00e9 10",
    "sg:city":"Montreux",
    "sg:orig_category":"Wirtschaftspr\u00fcfung, Steuerberatung U Treuhand",
    "sg:phone":"+41 79 240 37 58",
    "sg:postcode":"1820",
    "sg:province":"Vaud",
    "wof:name":"Fiduciaire Donz\u00e9 Micheline Fiduciaire, Comptabilit\u00e9s, Fiscalit\u00e9s Etc",
    "wof:placetype":"venue"
},
  "geometry": {"coordinates":[6.9157271385,46.9912185669],"type":"Point"}
}