{
  "type": "Feature",
  "properties": {
    "iso:country":"CH",
    "sg:address":"Route De Suisse 137",
    "sg:city":"Versoix",
    "sg:orig_category":"Fachdetailhandel in Verkaufsr\u00e4umen",
    "sg:postcode":"1290",
    "sg:province":"Gen\u00e8ve",
    "wof:name":"Next One S\u00e0rl",
    "wof:placetype":"venue"
},
  "geometry": {"coordinates":[6.1655898094,46.2895851135],"type":"Point"}
}