{
  "type": "Feature",
  "properties": {
    "iso:country":"CH",
    "sg:address":"Grossmattstrasse 13",
    "sg:city":"H\u00e4gendorf",
    "sg:orig_category":"Unternehmensberatung",
    "sg:postcode":"4614",
    "sg:province":"Solothurn",
    "wof:name":"Egloff + Wettstein Unternehmensberatung",
    "wof:placetype":"venue"
},
  "geometry": {"coordinates":[7.8457298279,47.3287582397],"type":"Point"}
}