{
  "type": "Feature",
  "properties": {
    "iso:country":"CH",
    "sg:address":"Hohengasse 15",
    "sg:city":"Burgdorf",
    "sg:orig_category":"Detailhandel mit Uhren U Schmuck Fachdetailhandel in Verkaufsr\u00e4umen",
    "sg:phone":"+41 34 422 04 22",
    "sg:postcode":"3400",
    "sg:province":"Bern",
    "wof:name":"Paul David, Nachf. Jost Marlyse",
    "wof:placetype":"venue"
},
  "geometry": {"coordinates":[7.6269397736,47.0565795898],"type":"Point"}
}