{
  "type": "Feature",
  "properties": {
    "iso:country":"CH",
    "sg:address":"La Douay",
    "sg:city":"Orsi\u00e8res",
    "sg:orig_category":"RESTAURANTS: TEA-ROOMS",
    "sg:phone":"+41 27 783 31 22",
    "sg:postcode":"1937",
    "sg:province":"Valais",
    "wof:name":"Favez Serge",
    "wof:placetype":"venue"
},
  "geometry": {"coordinates":[7.1494970322,46.053653717],"type":"Point"}
}