{
  "type": "Feature",
  "properties": {
    "iso:country":"CH",
    "sg:address":"Lutherstrasse 32",
    "sg:city":"Z\u00fcrich",
    "sg:orig_category":"Unclassifiable Establishments",
    "sg:phone":"+41 12423890",
    "sg:postcode":"8004",
    "sg:province":"Z\u00fcrich",
    "wof:name":"Kosmetik Salon Oasis, W. Peter",
    "wof:placetype":"venue"
},
  "geometry": {"coordinates":[8.5286149979,47.3747024536],"type":"Point"}
}