{
  "type": "Feature",
  "properties": {
    "iso:country":"CH",
    "sg:address":"Gerenweg 7",
    "sg:city":"Gipf-oberfrick",
    "sg:orig_category":"Detailhandel mit Blumen U Pflanzen Fachdetailhandel in Verkaufsr\u00e4umen",
    "sg:phone":"+41 62 871 76 36",
    "sg:postcode":"5073",
    "sg:province":"Aargau",
    "wof:name":"Atelier Floral S.biland & M.rickenbach",
    "wof:placetype":"venue"
},
  "geometry": {"coordinates":[8.009336,47.501259],"type":"Point"}
}