{
  "type": "Feature",
  "properties": {
    "iso:country":"CH",
    "sg:address":"Rue Des Terreaux 25",
    "sg:city":"Lausanne",
    "sg:orig_category":"Detailhandel mit Damenbekleidung Grosshandel mit Textilien",
    "sg:phone":"+41 21 310 40 80",
    "sg:postcode":"1003",
    "sg:province":"Vaud",
    "wof:name":"H & M Hennes & Mauritz Sa",
    "wof:placetype":"venue"
},
  "geometry": {"coordinates":[6.6273927689,46.5227928162],"type":"Point"}
}