{
  "type": "Feature",
  "properties": {
    "addr:full":"Zinzikerstrasse 18 Stadel(winterthur) Z\u00fcrich 8404",
    "addr:housenumber":"18",
    "addr:postcode":"8404",
    "addr:street":"Zinzikerstrasse",
    "iso:country":"CH",
    "sg:address":"Zinzikerstrasse 18",
    "sg:city":"Stadel(winterthur)",
    "sg:orig_category":"Detailhandel mit Beleuchtungs U Haushaltsgegenst\u00e4nden Herstellung von sonstigen elektrischen Ausr\u00fcst",
    "sg:phone":"+41 52 246 00 00",
    "sg:postcode":"8404",
    "sg:province":"Z\u00fcrich",
    "wof:name":"Roman Edelmann Cash Electronics",
    "wof:placetype":"venue"
},
  "geometry": {"coordinates":[8.758223,47.506569],"type":"Point"}
}