{
  "type": "Feature",
  "properties": {
    "iso:country":"CH",
    "sg:address":"Agnesstrasse 22 8000 Z\u00fcrich. Postfach",
    "sg:city":"Z\u00fcrich",
    "sg:orig_category":"Sonstiger Grosshandel",
    "sg:postcode":"8001",
    "sg:province":"Z\u00fcrich",
    "wof:name":"Eiz Zbukvic K. Export-import",
    "wof:placetype":"venue"
},
  "geometry": {"coordinates":[8.514172554,47.3780899048],"type":"Point"}
}