{
  "type": "Feature",
  "properties": {
    "iso:country":"CH",
    "sg:address":"Via Dragoni 1",
    "sg:city":"Gravesano",
    "sg:orig_category":"Parf\u00fcmerien U sonstiger Detailhandel mit kosmetischen Artikeln U K\u00f6rperpflegemitteln",
    "sg:phone":"+41 91 994 88 42",
    "sg:postcode":"6929",
    "sg:province":"Ticino",
    "wof:name":"Rose-marie Daminelli",
    "wof:placetype":"venue"
},
  "geometry": {"coordinates":[8.921210289,46.0388717651],"type":"Point"}
}