{
  "type": "Feature",
  "properties": {
    "iso:country":"CH",
    "sg:address":"H\u00f6rnliweg 2",
    "sg:city":"Adelboden",
    "sg:orig_category":"Wirtschaftspr\u00fcfung, Steuerberatung U Treuhand",
    "sg:postcode":"3715",
    "sg:province":"Bern",
    "wof:name":"Germann Treuhand + Revision Ag",
    "wof:placetype":"venue"
},
  "geometry": {"coordinates":[7.5626058578,46.4946861267],"type":"Point"}
}