{
  "type": "Feature",
  "properties": {
    "iso:country":"CH",
    "sg:address":"Via Baraggie 8",
    "sg:city":"Ascona",
    "sg:orig_category":"Non-Classified Establishments",
    "sg:phone":"+41 91 792 11 93",
    "sg:postcode":"6612",
    "sg:province":"Ticino",
    "wof:name":"Schmidlin & Co",
    "wof:placetype":"venue"
},
  "geometry": {"coordinates":[8.7716741562,46.1567153931],"type":"Point"}
}