{
  "type": "Feature",
  "properties": {
    "iso:country":"CH",
    "sg:address":"Tannerstrasse 37",
    "sg:city":"D\u00fcrnten",
    "sg:orig_category":"Sanit\u00e4r, Heizungs U L\u00fcftungsinstallation",
    "sg:phone":"+41 17370926",
    "sg:postcode":"8635",
    "sg:province":"Z\u00fcrich",
    "wof:name":"As Sanit\u00e4r Schweizer A.",
    "wof:placetype":"venue"
},
  "geometry": {"coordinates":[8.4461584091,47.3567504883],"type":"Point"}
}