{
  "type": "Feature",
  "properties": {
    "iso:country":"CH",
    "sg:address":"Hinterr\u00fcti",
    "sg:city":"Horgen",
    "sg:orig_category":"Malerei",
    "sg:phone":"+41 17256605",
    "sg:postcode":"8810",
    "sg:province":"Z\u00fcrich",
    "wof:name":"Raymond Wangler Malergesch\u00e4ft",
    "wof:placetype":"venue"
},
  "geometry": {"coordinates":[8.6070556641,47.2357177734],"type":"Point"}
}