{
  "type": "Feature",
  "properties": {
    "iso:country":"CH",
    "sg:address":"Comercialstrasse 24",
    "sg:city":"Chur",
    "sg:orig_category":"Architektur U Ingenieurb\u00fcros",
    "sg:phone":"+41 81 252 10 60",
    "sg:postcode":"7000",
    "sg:province":"Graubunden",
    "wof:name":"Meisser Vermessungen Ag",
    "wof:placetype":"venue"
},
  "geometry": {"coordinates":[9.508854,46.846725],"type":"Point"}
}