{
  "type": "Feature",
  "properties": {
    "iso:country":"CH",
    "sg:address":"Brandbachstrasse 7",
    "sg:city":"Dietlikon",
    "sg:orig_category":"Einzelhandel mit Automobilteilen U Zubeh\u00f6r Herstellung von Bereifungen",
    "sg:phone":"+41 18358170",
    "sg:postcode":"8305",
    "sg:province":"Z\u00fcrich",
    "wof:name":"Romer Pneu-service Ag",
    "wof:placetype":"venue"
},
  "geometry": {"coordinates":[8.6228981018,47.416179657],"type":"Point"}
}