{
  "type": "Feature",
  "properties": {
    "iso:country":"CH",
    "sg:address":"Robert-durrerstrasse 2 6370 Stans. Postfach 1143",
    "sg:city":"Stans",
    "sg:orig_category":"Fachdetailhandel mit pharmazeutischen Produkten",
    "sg:phone":"+41 41 610 11 19",
    "sg:postcode":"6371",
    "sg:province":"Nidwalden",
    "wof:name":"Apotheke Zelger, Inh. Frau E. Balbi-zelger",
    "wof:placetype":"venue"
},
  "geometry": {"coordinates":[8.36810112,46.9586029053],"type":"Point"}
}