{
  "type": "Feature",
  "properties": {
    "iso:country":"CH",
    "sg:address":"6711",
    "sg:orig_category":"Herstellung von Metallkonstruktionen",
    "sg:postcode":"6711",
    "wof:name":"Vescovi Brenno",
    "wof:placetype":"venue"
},
  "geometry": {"coordinates":[114.99825286870001,-21.4580001831],"type":"Point"}
}