{
  "type": "Feature",
  "properties": {
    "iso:country":"CH",
    "sg:address":"Riedgasse 18",
    "sg:city":"Aarwangen",
    "sg:orig_category":"Arztpraxen",
    "sg:phone":"+41 62 919 80 00",
    "sg:postcode":"4912",
    "sg:province":"Bern",
    "wof:name":"Dres Med. Gerster & Isenschmid Spezial\u00e4rzte Fmh",
    "wof:placetype":"venue"
},
  "geometry": {"coordinates":[7.770047,47.24173],"type":"Point"}
}