{
  "type": "Feature",
  "properties": {
    "iso:country":"CH",
    "sg:address":"Spannortstrasse 11",
    "sg:city":"Luzern",
    "sg:orig_category":"Fussboden, Fliesen U Plattenlegerei, Tapeziererei Stukkateurgewerbe, Gipserei U Verputzerei",
    "sg:phone":"+41 41 360 65 09",
    "sg:postcode":"6003",
    "sg:province":"Luzern",
    "wof:name":"Basler P. Platten Und Gipsergesch\u00e4ft",
    "wof:placetype":"venue"
},
  "geometry": {"coordinates":[8.3075008392,47.042930603],"type":"Point"}
}