{
  "type": "Feature",
  "properties": {
    "iso:country":"CH",
    "sg:address":"Chemin Bizot 4-6",
    "sg:city":"Gen\u00e8ve",
    "sg:orig_category":"Rolladen- and Storenmontage",
    "sg:phone":"+41 22 346 51 97",
    "sg:postcode":"1208",
    "sg:province":"Gen\u00e8ve",
    "wof:name":"Alain Bottiglieri R\u00e9paration De Stores",
    "wof:placetype":"venue"
},
  "geometry": {"coordinates":[6.166903019,46.1939125061],"type":"Point"}
}