{
  "type": "Feature",
  "properties": {
    "iso:country":"CH",
    "sg:address":"Zukunftstrasse 19",
    "sg:city":"Biel/bienne",
    "sg:orig_category":"Vorschulen, Kinderg\u00e4rten",
    "sg:postcode":"2503",
    "sg:province":"Bern",
    "wof:name":"Kindergarten",
    "wof:placetype":"venue"
},
  "geometry": {"coordinates":[7.248363018,47.1332626343],"type":"Point"}
}