{
  "type": "Feature",
  "properties": {
    "iso:country":"CH",
    "sg:address":"L\u00f6wenstrasse 22",
    "sg:city":"Kreuzlingen",
    "sg:orig_category":"Herstellung von Teppichen Verlegen von Fussboden",
    "sg:phone":"+41 71 672 59 77",
    "sg:postcode":"8280",
    "sg:province":"Thurgau",
    "wof:name":"Neukom & Pfirter Ag Teppiche & Bodenbel\u00e4ge",
    "wof:placetype":"venue"
},
  "geometry": {"coordinates":[9.1707010269,47.6475791931],"type":"Point"}
}