{
  "type": "Feature",
  "properties": {
    "iso:country":"CH",
    "sg:address":"Via S.gottardo",
    "sg:city":"Faido",
    "sg:orig_category":"Malerei",
    "sg:phone":"+41 91 866 17 58",
    "sg:postcode":"6760",
    "sg:province":"Ticino",
    "wof:name":"Giovanni Rocco Impresa Di Pittura",
    "wof:placetype":"venue"
},
  "geometry": {"coordinates":[8.7980575562,46.4786872864],"type":"Point"}
}