{
  "type": "Feature",
  "properties": {
    "iso:country":"CH",
    "sg:address":"Altweg",
    "sg:city":"Pfaffnau",
    "sg:orig_category":"Detailhandel mit Fleisch U Fleischwaren",
    "sg:phone":"+41 75 373 11 31",
    "sg:postcode":"6264",
    "sg:province":"Luzern",
    "wof:name":"Anton Hersche Metzgerei",
    "wof:placetype":"venue"
},
  "geometry": {"coordinates":[9.5421199799,47.2191505432],"type":"Point"}
}