{
  "type": "Feature",
  "properties": {
    "iso:country":"CH",
    "sg:address":"Rue Des Moulins 5",
    "sg:city":"Del\u00e9mont",
    "sg:orig_category":"Detailhandel mit Teppichen Verlegen von Fussboden",
    "sg:phone":"+41 32 422 42 81",
    "sg:postcode":"2800",
    "sg:province":"Jura",
    "wof:name":"Laurent Int\u00e9rieurs",
    "wof:placetype":"venue"
},
  "geometry": {"coordinates":[7.3452210426,47.3651008606],"type":"Point"}
}