{
  "type": "Feature",
  "properties": {
    "iso:country":"CH",
    "sg:address":"Konradstrasse 39",
    "sg:city":"Z\u00fcrich",
    "sg:classifiers":[
        {
            "category":"Travel",
            "subcategory":"Hotels & Motels",
            "type":"Entertainment"
        }
    ],
    "sg:phone":"+41 27 956 13 12",
    "sg:postcode":"8005",
    "sg:province":"Z\u00fcrich",
    "sg:tags":[
        "hotels",
        "mit",
        "restaurant"
    ],
    "wof:name":"Hotel Montana",
    "wof:placetype":"venue"
},
  "geometry": {"coordinates":[7.8230800629,46.1897583008],"type":"Point"}
}