{
  "type": "Feature",
  "properties": {
    "iso:country":"CH",
    "sg:address":"Luzernerstrasse 236",
    "sg:city":"Merlischachen",
    "sg:orig_category":"Werbegrafikateliers",
    "sg:phone":"+41 41 852 08 60",
    "sg:postcode":"6402",
    "sg:province":"Schwyz",
    "wof:name":"Raffael Bachmann Grafisches Atelier",
    "wof:placetype":"venue"
},
  "geometry": {"coordinates":[8.4042987823,47.0630073547],"type":"Point"}
}