{
  "type": "Feature",
  "properties": {
    "iso:country":"CH",
    "sg:address":"Zentralstrasse 36",
    "sg:city":"Z\u00fcrich",
    "sg:orig_category":"RESTAURANTS: TEA-ROOMS",
    "sg:phone":"+41 14636434",
    "sg:postcode":"8003",
    "sg:province":"Z\u00fcrich",
    "wof:name":"Lukas Brandl Spuntino Ristorante Bar Caf\u00e9 Pery",
    "wof:placetype":"venue"
},
  "geometry": {"coordinates":[8.5197467804,47.3716964722],"type":"Point"}
}