{
  "type": "Feature",
  "properties": {
    "iso:country":"CH",
    "sg:address":"Obergrundstrasse 110",
    "sg:city":"Luzern",
    "sg:orig_category":"Pensionskassen",
    "sg:phone":"+41 41 319 11 11",
    "sg:postcode":"6005",
    "sg:province":"Luzern",
    "wof:name":"Wohlfahrtsfonds Der Brauerei Eichhof",
    "wof:placetype":"venue"
},
  "geometry": {"coordinates":[8.3003902435,47.0397872925],"type":"Point"}
}