{
  "type": "Feature",
  "properties": {
    "iso:country":"CH",
    "sg:address":"Route De Saint-cergue 39 1260 Nyon. Postfach",
    "sg:city":"Nyon",
    "sg:orig_category":"Grosshandel mit keramischen Erzeugnissen, Glaswaren U Reinigungsmitteln",
    "sg:postcode":"1260",
    "sg:province":"Vaud",
    "wof:name":"Y.d.nouvelles, Di Natale Yvan",
    "wof:placetype":"venue"
},
  "geometry": {"coordinates":[6.2331728935,46.3879470825],"type":"Point"}
}