{
  "type": "Feature",
  "properties": {
    "addr:full":"P\u00eacheurs Rue Des 11 1400 Yverdon-les-bains. Postfach Giez Vaud 1429",
    "addr:postcode":"1400;postfach giez;1429",
    "addr:street":"Rue Des 11",
    "iso:country":"CH",
    "sg:address":"P\u00eacheurs Rue Des 11 1400 Yverdon-les-bains. Postfach",
    "sg:city":"Giez",
    "sg:orig_category":"Allgemeiner Hoch U Tiefbau",
    "sg:postcode":"1429",
    "sg:province":"Vaud",
    "wof:name":"Yobatech-services, Schubert Johann R\u00e9novation Et Transformation Dans Le B\u00e2timent, Entretien De Jardin",
    "wof:placetype":"venue"
},
  "geometry": {"coordinates":[6.645408,46.782322],"type":"Point"}
}