{
  "type": "Feature",
  "properties": {
    "iso:country":"CH",
    "sg:address":"Kleinweid 8",
    "sg:city":"Cham",
    "sg:orig_category":"Handels-H\u00e4user U Gesellschaften",
    "sg:postcode":"6330",
    "sg:province":"Zug",
    "wof:name":"B.h. Blum Investrade",
    "wof:placetype":"venue"
},
  "geometry": {"coordinates":[8.452381134,47.1804046631],"type":"Point"}
}