{
  "type": "Feature",
  "properties": {
    "iso:country":"CH",
    "sg:address":"Schatzenboden 61a",
    "sg:city":"Jenaz",
    "sg:orig_category":"Sonstiger Grosshandel",
    "sg:phone":"+41 81 332 44 59",
    "sg:postcode":"7233",
    "sg:province":"Graubunden",
    "wof:name":"Von Allmen Dienstleistungen",
    "wof:placetype":"venue"
},
  "geometry": {"coordinates":[9.7184915543,46.9288673401],"type":"Point"}
}