{
  "type": "Feature",
  "properties": {
    "iso:country":"CH",
    "sg:address":"Fabrikstrasse 74 3800 Interlaken. Postfach 658",
    "sg:city":"Interlaken",
    "sg:orig_category":"Allgemeiner Hoch U Tiefbau Herstellung von Fenstern U T\u00fcren aus Holz",
    "sg:phone":"+41 33 822 33 41",
    "sg:postcode":"3800",
    "sg:province":"Bern",
    "wof:name":"Peter R\u00fcegsegger Ag",
    "wof:placetype":"venue"
},
  "geometry": {"coordinates":[7.846979,46.675949],"type":"Point"}
}