{
  "type": "Feature",
  "properties": {
    "iso:country":"CH",
    "sg:address":"Gewerbehalle Kleinzaun",
    "sg:city":"Netstal",
    "sg:classifiers":[
        {
            "category":"Train Station",
            "subcategory":"Light Rail",
            "type":"Transportation"
        }
    ],
    "sg:phone":"+41 55 640 20 57",
    "sg:postcode":"8754",
    "sg:province":"Glarus",
    "sg:tags":[
        "hiring",
        "event",
        "special",
        "equipment"
    ],
    "wof:name":"Schnyder Festzelte Ag",
    "wof:placetype":"venue"
},
  "geometry": {"coordinates":[9.057393074,47.0656394958],"type":"Point"}
}