{
  "type": "Feature",
  "properties": {
    "iso:country":"CH",
    "sg:address":"Saint-michel Place 6",
    "sg:city":"Martigny",
    "sg:orig_category":"Unclassifiable Establishments",
    "sg:postcode":"1920",
    "sg:province":"Valais",
    "wof:name":"Cimen S\u00e0rl",
    "wof:placetype":"venue"
},
  "geometry": {"coordinates":[7.060790062,46.088809967],"type":"Point"}
}