{
  "type": "Feature",
  "properties": {
    "iso:country":"CH",
    "sg:address":"Kirchweg 17",
    "sg:city":"Gunzgen",
    "sg:orig_category":"Non-Classified Establishments",
    "sg:postcode":"4617",
    "sg:province":"Solothurn",
    "wof:name":"Mk Consulting Kaldeck M.",
    "wof:placetype":"venue"
},
  "geometry": {"coordinates":[8.7998867035,47.320224762],"type":"Point"}
}