{
  "type": "Feature",
  "properties": {
    "iso:country":"CH",
    "sg:address":"Rue De L'industrie 2-4",
    "sg:city":"Bussigny-lausanne",
    "sg:classifiers":[
        {
            "category":"Restaurant",
            "type":"Food & Drink"
        }
    ],
    "sg:phone":"+41 21 701 59 15",
    "sg:postcode":"1030",
    "sg:province":"Vaud",
    "wof:name":"Caf\u00e9 Les Arcades",
    "wof:placetype":"venue"
},
  "geometry": {"coordinates":[6.5537319183,46.5481567383],"type":"Point"}
}