{
  "type": "Feature",
  "properties": {
    "iso:country":"CH",
    "sg:address":"Chemin Des M\u00e9mises 42",
    "sg:city":"Jouxtens-m\u00e9zery",
    "sg:orig_category":"Bauspenglerei Sanit\u00e4rinstallation",
    "sg:phone":"+41 31 311 04 93",
    "sg:postcode":"1008",
    "sg:province":"Vaud",
    "wof:name":"Ammann Peter Ag Spenglerarbeiten, Sanit\u00e4r Und Heizungsinstallationen Usw.",
    "wof:placetype":"venue"
},
  "geometry": {"coordinates":[7.456736,46.946877],"type":"Point"}
}