{
  "type": "Feature",
  "properties": {
    "iso:country":"CH",
    "sg:address":"Leopoldstrasse 6 6210 Sursee. Postfach 80",
    "sg:city":"Sursee",
    "sg:orig_category":"Grosshandel mit Holz U Baustoffen",
    "sg:phone":"+41 41 921 09 03",
    "sg:postcode":"6210",
    "sg:province":"Luzern",
    "wof:name":"Cargo-green Ag",
    "wof:placetype":"venue"
},
  "geometry": {"coordinates":[8.0987510681,47.1721496582],"type":"Point"}
}