{
  "type": "Feature",
  "properties": {
    "iso:country":"CH",
    "sg:address":"Rothenring 15",
    "sg:city":"Reussb\u00fchl",
    "sg:orig_category":"Instandhaltung U Reparatur von Automobilen",
    "sg:phone":"+41 41 260 70 60",
    "sg:postcode":"6015",
    "sg:province":"Luzern",
    "wof:name":"Troxler Josef Rothenring-garage",
    "wof:placetype":"venue"
},
  "geometry": {"coordinates":[8.2776088715,47.0665435791],"type":"Point"}
}