{
  "type": "Feature",
  "properties": {
    "iso:country":"CH",
    "sg:address":"Hotel Calanda",
    "sg:city":"V\u00e4ttis",
    "sg:orig_category":"Sportvereine Ski",
    "sg:postcode":"7315",
    "sg:province":"St. Gallen",
    "wof:name":"Skiclub V\u00e4ttis",
    "wof:placetype":"venue"
},
  "geometry": {"coordinates":[9.4401321411,46.9076576233],"type":"Point"}
}