{
  "type": "Feature",
  "properties": {
    "iso:country":"CH",
    "sg:address":"6914",
    "sg:city":"Carona",
    "sg:orig_category":"Vorschulen, Kinderg\u00e4rten",
    "sg:postcode":"6914",
    "sg:province":"Ticino",
    "wof:name":"Scuola Materna",
    "wof:placetype":"venue"
},
  "geometry": {"coordinates":[8.9291400909,45.9598388672],"type":"Point"}
}