{
  "type": "Feature",
  "properties": {
    "iso:country":"CH",
    "sg:address":"Avenue Dumas 24",
    "sg:city":"Gen\u00e8ve",
    "sg:classifiers":[
        {
            "category":"Building & Trades",
            "subcategory":"Electrical",
            "type":"Services"
        }
    ],
    "sg:phone":"+41 22 346 18 43",
    "sg:postcode":"1206",
    "sg:province":"Gen\u00e8ve",
    "sg:tags":[
        "installation"
    ],
    "wof:name":"Imp\u00e9rial Electronic Sa",
    "wof:placetype":"venue"
},
  "geometry": {"coordinates":[6.1574110985,46.1908187866],"type":"Point"}
}