{
  "type": "Feature",
  "properties": {
    "iso:country":"CH",
    "sg:address":"Le Margy 1628 Vuadens. Postfach",
    "sg:city":"Vuadens",
    "sg:orig_category":"Instandhaltung U Reparatur von Automobilen",
    "sg:postcode":"1628",
    "sg:province":"Fribourg",
    "wof:name":"Auto Access, Colella Vito Garage",
    "wof:placetype":"venue"
},
  "geometry": {"coordinates":[7.0232739449,46.6213264465],"type":"Point"}
}