{
  "type": "Feature",
  "properties": {
    "iso:country":"CH",
    "sg:address":"Au Sau",
    "sg:city":"Yverdon-les-bains",
    "sg:orig_category":"Grosshandel mit sonstigen Maschinen U Ausr\u00fcstungen f\u00fcr Industrie, Handel U Schiffahrt",
    "sg:postcode":"1400",
    "sg:province":"Vaud",
    "wof:name":"H\u00e9rold Intec",
    "wof:placetype":"venue"
},
  "geometry": {"coordinates":[6.6232910156,46.7668151855],"type":"Point"}
}