{
  "type": "Feature",
  "properties": {
    "iso:country":"CH",
    "sg:address":"Frutigenstrasse 16 3600 Thun. Postfach 1030",
    "sg:city":"Thun",
    "sg:orig_category":"Architekturb\u00fcros",
    "sg:phone":"+41 71 245 95 37",
    "sg:postcode":"3601",
    "sg:province":"Bern",
    "wof:name":"Martin Beck Architekturb\u00fcro",
    "wof:placetype":"venue"
},
  "geometry": {"coordinates":[9.377991,47.439877],"type":"Point"}
}