{
  "type": "Feature",
  "properties": {
    "iso:country":"CH",
    "sg:address":"Aarburgerstrasse 111",
    "sg:city":"Olten",
    "sg:orig_category":"Pneus Detailhandel",
    "sg:phone":"+41 62 296 38 48",
    "sg:postcode":"4600",
    "sg:province":"Solothurn",
    "wof:name":"Pneu Egger Ag",
    "wof:placetype":"venue"
},
  "geometry": {"coordinates":[7.9071650505,47.3454208374],"type":"Point"}
}