{
  "type": "Feature",
  "properties": {
    "iso:country":"CH",
    "sg:address":"Luzernerstrasse 17",
    "sg:city":"Sins",
    "sg:orig_category":"Detailhandel mit Teppichen Verlegen von Fussboden",
    "sg:phone":"+41 41 787 27 32",
    "sg:postcode":"5643",
    "sg:province":"Aargau",
    "wof:name":"Herbert Strebel Teppiche Bodenbel\u00e4ge Vorh\u00e4nge",
    "wof:placetype":"venue"
},
  "geometry": {"coordinates":[8.3960580826,47.1894302368],"type":"Point"}
}