{
  "type": "Feature",
  "properties": {
    "iso:country":"CH",
    "sg:address":"Steiggasse 2",
    "sg:city":"Winterthur",
    "sg:orig_category":"Grafikateliers, Design Sonstiges Druckgewerbe",
    "sg:phone":"+41 52 214 30 33",
    "sg:postcode":"8400",
    "sg:province":"Z\u00fcrich",
    "wof:name":"Urs Barak In & Out Line",
    "wof:placetype":"venue"
},
  "geometry": {"coordinates":[8.7280979156,47.4978179932],"type":"Point"}
}