{
  "type": "Feature",
  "properties": {
    "iso:country":"CH",
    "sg:address":"Hohe Winde-strasse 20",
    "sg:city":"Basel",
    "sg:orig_category":"Interessenvertretungen",
    "sg:postcode":"4059",
    "sg:province":"Basel-Stadt",
    "wof:name":"Hans Huber-stiftung",
    "wof:placetype":"venue"
},
  "geometry": {"coordinates":[7.5884718895,47.5346412659],"type":"Point"}
}