{
  "type": "Feature",
  "properties": {
    "iso:country":"CH",
    "sg:address":"Alte Landstrasse 1",
    "sg:city":"Oberurnen",
    "sg:classifiers":[
        {
            "category":"Restaurant",
            "type":"Food & Drink"
        }
    ],
    "sg:phone":"+41 55 610 17 06",
    "sg:postcode":"8868",
    "sg:province":"Glarus",
    "wof:name":"Restaurant Hirschen & Hirsch\u00e4-bar",
    "wof:placetype":"venue"
},
  "geometry": {"coordinates":[9.0579662323,47.113910675],"type":"Point"}
}