{
  "type": "Feature",
  "properties": {
    "iso:country":"CH",
    "sg:address":"6983",
    "sg:city":"Magliaso",
    "sg:orig_category":"Beherbergungsgewerbe",
    "sg:postcode":"6983",
    "sg:province":"Ticino",
    "wof:name":"Genossenschaft Ferienhaus Laueli-s\u00f6renberg",
    "wof:placetype":"venue"
},
  "geometry": {"coordinates":[8.073943,47.390511],"type":"Point"}
}