{
  "type": "Feature",
  "properties": {
    "iso:country":"CH",
    "sg:address":"Dennlerstrasse 22 8000 Z\u00fcrich. Postfach",
    "sg:city":"Z\u00fcrich",
    "sg:orig_category":"Saunas, Solarien, Fitnesszentren U \u00e4hnliches",
    "sg:postcode":"8047",
    "sg:province":"Z\u00fcrich",
    "wof:name":"Fit Und Fun Rosenberger",
    "wof:placetype":"venue"
},
  "geometry": {"coordinates":[8.4978017807,47.3815803528],"type":"Point"}
}