{
  "type": "Feature",
  "properties": {
    "iso:country":"CH",
    "sg:address":"Mittlere Haltenstrasse 13",
    "sg:city":"Heiligenschwendi",
    "sg:orig_category":"Fotografisches Gewerbe U fotografische Laboratorien",
    "sg:postcode":"3625",
    "sg:province":"Bern",
    "wof:name":"Si-report Gmbh",
    "wof:placetype":"venue"
},
  "geometry": {"coordinates":[7.6688480377,46.7470550537],"type":"Point"}
}