{
  "type": "Feature",
  "properties": {
    "iso:country":"CH",
    "sg:address":"Gr\u00fcttermatt 7",
    "sg:city":"Wynigen",
    "sg:orig_category":"Sportvereine Turnen",
    "sg:phone":"+41 34 415 18 53",
    "sg:postcode":"3472",
    "sg:province":"Bern",
    "wof:name":"Turnverein Stv Wynigen",
    "wof:placetype":"venue"
},
  "geometry": {"coordinates":[7.6670770645,47.1075134277],"type":"Point"}
}