{
  "type": "Feature",
  "properties": {
    "iso:country":"CH",
    "sg:address":"Boulevard James-fazy 3",
    "sg:city":"Gen\u00e8ve",
    "sg:orig_category":"Erbringung von Dienstleistungen f\u00fcr Unternehmen Unterhaltung, Kultur U Sport",
    "sg:phone":"+41 22 731 88 39",
    "sg:postcode":"1201",
    "sg:province":"Gen\u00e8ve",
    "wof:name":"Vivre Autrement At\u00e9liers De Developpement Personnel",
    "wof:placetype":"venue"
},
  "geometry": {"coordinates":[6.1393389702,46.2066383362],"type":"Point"}
}