{
  "type": "Feature",
  "properties": {
    "addr:full":"Gr\u00fcnaustrasse 14 Sirnach Thurgau 8370",
    "addr:housenumber":"14",
    "addr:postcode":"8370",
    "addr:street":"Gruenaustrasse",
    "iso:country":"CH",
    "sg:address":"Gr\u00fcnaustrasse 14",
    "sg:city":"Sirnach",
    "sg:orig_category":"Ausbaugewerbe Sonstiger spezialisierter Hoch U Tiefbau",
    "sg:phone":"+41 71 966 53 26",
    "sg:postcode":"8370",
    "sg:province":"Thurgau",
    "wof:name":"Thoma Bauaustrocknung",
    "wof:placetype":"venue"
},
  "geometry": {"coordinates":[8.997132,47.463814],"type":"Point"}
}