{
  "type": "Feature",
  "properties": {
    "iso:country":"CH",
    "sg:address":"Innere G\u00fcterstrasse 4",
    "sg:city":"Zug",
    "sg:orig_category":"Non-Classified Establishments",
    "sg:postcode":"6300",
    "sg:province":"Zug",
    "wof:name":"Top Sun, Leder",
    "wof:placetype":"venue"
},
  "geometry": {"coordinates":[8.2938108444,47.4864234924],"type":"Point"}
}