{
  "type": "Feature",
  "properties": {
    "iso:country":"CH",
    "sg:address":"Bahnhofstrasse 7 3400 Burgdorf. Postfach",
    "sg:city":"Burgdorf",
    "sg:orig_category":"Sportvereine Turnen",
    "sg:postcode":"3401",
    "sg:province":"Bern",
    "wof:name":"M\u00e4nnerturnverein Stv Burgdorf",
    "wof:placetype":"venue"
},
  "geometry": {"coordinates":[7.6229500771,47.0589904785],"type":"Point"}
}