{
  "type": "Feature",
  "properties": {
    "iso:country":"CH",
    "sg:address":"Gellertstrasse 212",
    "sg:city":"Basel",
    "sg:classifiers":[
        {
            "category":"Home & Garden",
            "subcategory":"Kitchen Supply",
            "type":"Retail Goods"
        }
    ],
    "sg:phone":"+41 61 312 43 12",
    "sg:postcode":"4052",
    "sg:province":"Basel-Stadt",
    "sg:tags":[
        "utensil",
        "household",
        "appliance"
    ],
    "wof:name":"Dreba K\u00fcchen Ag",
    "wof:placetype":"venue"
},
  "geometry": {"coordinates":[7.6188430786,47.5449066162],"type":"Point"}
}