{
  "type": "Feature",
  "properties": {
    "iso:country":"CH",
    "sg:address":"Z\u00fcrcher Strasse 117",
    "sg:city":"St.gallen",
    "sg:orig_category":"Instandhaltung U Reparatur von Automobilen",
    "sg:postcode":"9000",
    "sg:province":"St. Gallen",
    "wof:name":"Immo-garage S\u00e0rl",
    "wof:placetype":"venue"
},
  "geometry": {"coordinates":[6.8282241821,47.1015625],"type":"Point"}
}