{
  "type": "Feature",
  "properties": {
    "iso:country":"CH",
    "sg:address":"Tribschenstrasse 98",
    "sg:city":"Luzern",
    "sg:orig_category":"Detailhandel mit Damenbekleidung",
    "sg:phone":"+41 41 360 76 78",
    "sg:postcode":"6005",
    "sg:province":"Luzern",
    "wof:name":"Irma Kaufmann Couture Irma",
    "wof:placetype":"venue"
},
  "geometry": {"coordinates":[8.319336,47.041237],"type":"Point"}
}