{
  "type": "Feature",
  "properties": {
    "iso:country":"CH",
    "sg:address":"Feldenstrasse",
    "sg:city":"Sigriswil",
    "sg:orig_category":"Allgemeiner Hoch U Tiefbau",
    "sg:phone":"+41 71 223 35 23",
    "sg:postcode":"3655",
    "sg:province":"Bern",
    "wof:name":"Frutiger Ag",
    "wof:placetype":"venue"
},
  "geometry": {"coordinates":[7.72264,46.715115],"type":"Point"}
}