{
  "type": "Feature",
  "properties": {
    "iso:country":"CH",
    "sg:address":"Route Suisse",
    "sg:city":"Coppet",
    "sg:orig_category":"Unclassifiable Establishments",
    "sg:postcode":"1296",
    "sg:province":"Vaud",
    "wof:name":"Si Le Grand Lac",
    "wof:placetype":"venue"
},
  "geometry": {"coordinates":[6.1947250366,46.3183174133],"type":"Point"}
}