{
  "type": "Feature",
  "properties": {
    "iso:country":"CH",
    "sg:address":"Karlshausen",
    "sg:city":"Muolen",
    "sg:orig_category":"Elektrizit\u00e4tsversorgung",
    "sg:postcode":"9313",
    "sg:province":"St. Gallen",
    "wof:name":"Elektrizit\u00e4tsgenossenschaft Muolen",
    "wof:placetype":"venue"
},
  "geometry": {"coordinates":[9.3291797638,47.5160598755],"type":"Point"}
}