{
  "type": "Feature",
  "properties": {
    "iso:country":"CH",
    "sg:address":"Industriestrasse 4 8590 Romanshorn. Postfach",
    "sg:city":"Romanshorn",
    "sg:orig_category":"Non-Classified Establishments",
    "sg:postcode":"8590",
    "sg:province":"Thurgau",
    "wof:name":"Romanshorn Ultrasonics Company Beteiligungen Usw",
    "wof:placetype":"venue"
},
  "geometry": {"coordinates":[9.3683462143,47.5567550659],"type":"Point"}
}