{
  "type": "Feature",
  "properties": {
    "iso:country":"CH",
    "sg:address":"Schl\u00f6sslistrasse 1 3700 Spiez. Postfach 300",
    "sg:city":"Spiez",
    "sg:orig_category":"Gesundheitswesen",
    "sg:phone":"+41 33 655 07 06",
    "sg:postcode":"3700",
    "sg:province":"Bern",
    "wof:name":"Trc Trainings Und Rehabilitationscenter Spiez, Kernen Adrian",
    "wof:placetype":"venue"
},
  "geometry": {"coordinates":[7.68227911,46.6855125427],"type":"Point"}
}