{
  "type": "Feature",
  "properties": {
    "iso:country":"CH",
    "sg:address":"3963",
    "sg:city":"Crans-sur-sierre",
    "sg:orig_category":"Detailhandel mit Damenbekleidung Detailhandel mit Herrenbekleidung",
    "sg:phone":"+41 27 481 40 61",
    "sg:postcode":"3963",
    "sg:province":"Valais",
    "wof:name":"Alex Sports M.barras Boutique",
    "wof:placetype":"venue"
},
  "geometry": {"coordinates":[7.46177,46.307621],"type":"Point"}
}