{
  "type": "Feature",
  "properties": {
    "iso:country":"CH",
    "sg:address":"Flurlingerweg 3",
    "sg:city":"Feuerthalen",
    "sg:classifiers":[
        {
            "category":"Manufacturing",
            "subcategory":"Printing",
            "type":"Manufacturing & Wholesale Goods"
        }
    ],
    "sg:phone":"+41 52 633 33 33",
    "sg:postcode":"8245",
    "sg:province":"Z\u00fcrich",
    "sg:tags":[
        "house",
        "book"
    ],
    "wof:name":"Meier & Cie Ag",
    "wof:placetype":"venue"
},
  "geometry": {"coordinates":[8.644551,47.687565],"type":"Point"}
}