{
  "type": "Feature",
  "properties": {
    "iso:country":"CH",
    "sg:address":"Rue Du Lac 20",
    "sg:city":"Yverdon-les-bains",
    "sg:orig_category":"Detailhandel mit Damenbekleidung Grosshandel mit Textilien",
    "sg:phone":"+41 24 425 56 66",
    "sg:postcode":"1400",
    "sg:province":"Vaud",
    "wof:name":"Pullv\u00e9 Sa",
    "wof:placetype":"venue"
},
  "geometry": {"coordinates":[6.6401209831,46.7793045044],"type":"Point"}
}