{
  "type": "Feature",
  "properties": {
    "addr:full":"Blauortstrasse 8272 Ermatingen. Postfach Ermatingen Thurgau 8272",
    "addr:postcode":"8272 ermatingen. postfach;8272",
    "addr:street":"Blauortstrasse",
    "iso:country":"CH",
    "sg:address":"Blauortstrasse 8272 Ermatingen. Postfach",
    "sg:city":"Ermatingen",
    "sg:orig_category":"Berufliche Weiterbildung, Erwachsenenbildung Erwachsenenbildung U Unterricht",
    "sg:phone":"+41 71 663 23 23",
    "sg:postcode":"8272",
    "sg:province":"Thurgau",
    "wof:name":"Lilienberg Unternehmerforum",
    "wof:placetype":"venue"
},
  "geometry": {"coordinates":[9.07248,47.667042],"type":"Point"}
}