{
  "type": "Feature",
  "properties": {
    "iso:country":"CH",
    "sg:address":"Freudenbergstrasse 132",
    "sg:city":"Z\u00fcrich",
    "sg:orig_category":"Vermietung U Verpachtung von eigenen Immobilien",
    "sg:postcode":"8044",
    "sg:province":"Z\u00fcrich",
    "wof:name":"Elmer's Friedrich S\u00f6hne Immobilien Ag",
    "wof:placetype":"venue"
},
  "geometry": {"coordinates":[8.9413003922,47.2884101868],"type":"Point"}
}