{
  "type": "Feature",
  "properties": {
    "iso:country":"CH",
    "sg:address":"Allmendstrasse 40",
    "sg:city":"Basel",
    "sg:orig_category":"Alters U Pflegeheime Wohnheime",
    "sg:phone":"+41 61 601 21 20",
    "sg:postcode":"4058",
    "sg:province":"Basel-Stadt",
    "wof:name":"St. Elisabethenheim",
    "wof:placetype":"venue"
},
  "geometry": {"coordinates":[7.618609,47.568386],"type":"Point"}
}