{
  "type": "Feature",
  "properties": {
    "iso:country":"CH",
    "sg:address":"Missionsstrasse 44",
    "sg:city":"Basel",
    "sg:orig_category":"Mit dem Versicherungsgewerbe verbundene T\u00e4tigkeiten",
    "sg:postcode":"4055",
    "sg:province":"Basel-Stadt",
    "wof:name":"Versicherungsberatung Tyche, Maurer",
    "wof:placetype":"venue"
},
  "geometry": {"coordinates":[7.5765151978,47.5606040955],"type":"Point"}
}