{
  "type": "Feature",
  "properties": {
    "iso:country":"CH",
    "sg:address":"T\u00e4liweg 7",
    "sg:city":"Gretzenbach",
    "sg:orig_category":"Sportvereine Sch\u00fctzen Pistolen-& Gewehr",
    "sg:phone":"+41 79 204 88 53",
    "sg:postcode":"5014",
    "sg:province":"Solothurn",
    "wof:name":"Sch\u00fctzenclub Niederg\u00f6sgen",
    "wof:placetype":"venue"
},
  "geometry": {"coordinates":[7.9973249435,47.3556632996],"type":"Point"}
}