{
  "type": "Feature",
  "properties": {
    "iso:country":"CH",
    "sg:address":"Mettmenegg",
    "sg:city":"Hofstatt",
    "sg:orig_category":"Landw. Genossenschaften Alpgenossenschaften",
    "sg:postcode":"6154",
    "sg:province":"Luzern",
    "wof:name":"Alpengenossenschaft Willisau & Umg.hans Birrer",
    "wof:placetype":"venue"
},
  "geometry": {"coordinates":[7.9148750305,47.0844955444],"type":"Point"}
}