{
  "type": "Feature",
  "properties": {
    "iso:country":"CH",
    "sg:address":"Wildbachstrasse 16",
    "sg:city":"Solothurn",
    "sg:orig_category":"Fotografische Ateliers Fotografisches Gewerbe U fotografische Laboratorien",
    "sg:phone":"+41 32 623 53 12",
    "sg:postcode":"4500",
    "sg:province":"Solothurn",
    "wof:name":"Stouder Alain",
    "wof:placetype":"venue"
},
  "geometry": {"coordinates":[7.5166130066,47.2117462158],"type":"Point"}
}