{
  "type": "Feature",
  "properties": {
    "iso:country":"CH",
    "sg:address":"Listrighalde 16 6020 Emmenbr\u00fccke. Postfach",
    "sg:city":"Emmenbr\u00fccke",
    "sg:orig_category":"Sonstige mit der Informatik verbundene T\u00e4tigkeiten",
    "sg:postcode":"6020",
    "sg:province":"Luzern",
    "wof:name":"Rb Informatik B\u00e4ckert",
    "wof:placetype":"venue"
},
  "geometry": {"coordinates":[8.2672100067,47.077167511],"type":"Point"}
}