{
  "type": "Feature",
  "properties": {
    "addr:full":"Glaubtenstrasse 32 Z\u00fcrich Z\u00fcrich 8046",
    "addr:housenumber":"32",
    "addr:postcode":"8046",
    "addr:street":"Glaubtenstrasse",
    "iso:country":"CH",
    "sg:address":"Glaubtenstrasse 32",
    "sg:city":"Z\u00fcrich",
    "sg:orig_category":"Architektur U Ingenieurb\u00fcros",
    "sg:postcode":"8046",
    "sg:province":"Z\u00fcrich",
    "wof:name":"Bes Buiter R. Ingenieurb\u00fcro",
    "wof:placetype":"venue"
},
  "geometry": {"coordinates":[8.516195,47.412609],"type":"Point"}
}