{
  "type": "Feature",
  "properties": {
    "iso:country":"CH",
    "sg:address":"Geissensteinring 45",
    "sg:city":"Luzern",
    "sg:orig_category":"Softwareentwicklung U beratung Sonstige mit der Informatik verbundene T\u00e4tigkeiten",
    "sg:postcode":"6005",
    "sg:province":"Luzern",
    "wof:name":"Sicap Ag",
    "wof:placetype":"venue"
},
  "geometry": {"coordinates":[8.3141374588,47.0413551331],"type":"Point"}
}