{
  "type": "Feature",
  "properties": {
    "iso:country":"CH",
    "sg:address":"L\u00e4ngenr\u00fcppstrasse 15",
    "sg:city":"Sch\u00f6nb\u00fchl-urtenen",
    "sg:orig_category":"Architektur U Ingenieurb\u00fcros Architekturb\u00fcros",
    "sg:phone":"+41 71 330 03 45",
    "sg:postcode":"3322",
    "sg:province":"Bern",
    "wof:name":"Blumer Christian, Dipl. Arch. Eth/sia, Architekturb\u00fcro",
    "wof:placetype":"venue"
},
  "geometry": {"coordinates":[9.362168,47.386242],"type":"Point"}
}