{
  "type": "Feature",
  "properties": {
    "iso:country":"CH",
    "sg:address":"Rickenbachstr. 147",
    "sg:city":"Schwyz",
    "sg:orig_category":"Grosshandel mit Nahrungsmitteln, Getr\u00e4nken U Tabakwaren ohne ausgepr\u00e4gten Schwerpunkt",
    "sg:postcode":"6430",
    "sg:province":"Schwyz",
    "wof:name":"Mettler-zihlmann Markus",
    "wof:placetype":"venue"
},
  "geometry": {"coordinates":[8.6640396118,47.0179786682],"type":"Point"}
}