{
  "type": "Feature",
  "properties": {
    "iso:country":"CH",
    "sg:address":"Landis+gyr-strasse 1 6300 Zug. Postfach 4262",
    "sg:city":"Zug",
    "sg:orig_category":"Grosshandel mit chemischen Erzeugnissen Grosshandel mit pharmazeutischen Erzeugnissen",
    "sg:phone":"+41 21 311 73 31",
    "sg:postcode":"6304",
    "sg:province":"Zug",
    "wof:name":"Deresa Sa",
    "wof:placetype":"venue"
},
  "geometry": {"coordinates":[6.6331410408,46.5215072632],"type":"Point"}
}