{
  "type": "Feature",
  "properties": {
    "iso:country":"CH",
    "sg:address":"Rue Du Port 2 1095 Ch\u00e2telard-lutry. Postfach",
    "sg:city":"Ch\u00e2telard-lutry",
    "sg:orig_category":"Detailhandel mit Sportartikeln Schiffsbau ohne Boots U Yachtbau",
    "sg:phone":"+41 21 792 19 29",
    "sg:postcode":"1095",
    "sg:province":"Vaud",
    "wof:name":"Boutique Nautique Lutry, Birbaum M. & Bovet Ph. Articles Nautiques, \u00e9cole De Pilotage De Canots \u00e0 Moteur",
    "wof:placetype":"venue"
},
  "geometry": {"coordinates":[6.6858301163,46.5017700195],"type":"Point"}
}