{
  "type": "Feature",
  "properties": {
    "iso:country":"CH",
    "sg:address":"Kirch\u00e4gerten 3 4223 Blauen. Postfach",
    "sg:city":"Blauen",
    "sg:orig_category":"Erbringung von Dienstleistungen f\u00fcr Unternehmen",
    "sg:postcode":"4223",
    "sg:province":"Basel-Landschaft",
    "wof:name":"Docu Ag",
    "wof:placetype":"venue"
},
  "geometry": {"coordinates":[7.516187191,47.4524536133],"type":"Point"}
}