{
  "type": "Feature",
  "properties": {
    "iso:country":"CH",
    "sg:address":"3972",
    "sg:city":"Mi\u00e8ge",
    "sg:orig_category":"Rebbau",
    "sg:phone":"+41 27 455 29 80",
    "sg:postcode":"3972",
    "sg:province":"Valais",
    "wof:name":"Hermann Clavien Propri\u00e9taire-encaveur",
    "wof:placetype":"venue"
},
  "geometry": {"coordinates":[7.5438199043,46.3178100586],"type":"Point"}
}