{
  "type": "Feature",
  "properties": {
    "iso:country":"CH",
    "sg:address":"Charels Suot",
    "sg:city":"Bever",
    "sg:orig_category":"Grosshandel mit Eisenwaren sowie Installationsbedarf f\u00fcr Gas, Wasser U Heizung",
    "sg:phone":"+41 81 851 10 80",
    "sg:postcode":"7502",
    "sg:province":"Graubunden",
    "wof:name":"Jenny Sa, Fierramainta",
    "wof:placetype":"venue"
},
  "geometry": {"coordinates":[9.8904647827,46.5516357422],"type":"Point"}
}