{
  "type": "Feature",
  "properties": {
    "iso:country":"CH",
    "sg:address":"Neud\u00f6rfli 9",
    "sg:city":"Lenzburg",
    "sg:orig_category":"Sportvereine Ballsport Volleyball Vereine Damen",
    "sg:phone":"+41 62 891 73 69",
    "sg:postcode":"5600",
    "sg:province":"Aargau",
    "wof:name":"Volleyball-club Dtv Lenzburg",
    "wof:placetype":"venue"
},
  "geometry": {"coordinates":[8.1787919998,47.3867912292],"type":"Point"}
}