{
  "type": "Feature",
  "properties": {
    "iso:country":"CH",
    "sg:address":"Mar\u00e8che Immeuble",
    "sg:city":"Montana",
    "sg:orig_category":"RESTAURANTS: TEA-ROOMS",
    "sg:phone":"+41 62 291 17 06",
    "sg:postcode":"3962",
    "wof:name":"Hagmann, Urs.",
    "wof:placetype":"venue"
},
  "geometry": {"coordinates":[7.9785652161,47.355140686],"type":"Point"}
}