{
  "type": "Feature",
  "properties": {
    "iso:country":"CH",
    "sg:address":"R\u00e9sidences De La C\u00f4te 20",
    "sg:city":"Morges",
    "sg:orig_category":"Sonstiger Grosshandel",
    "sg:postcode":"1110",
    "sg:province":"Vaud",
    "wof:name":"Bucher + Co.",
    "wof:placetype":"venue"
},
  "geometry": {"coordinates":[6.4974617958,46.5185050964],"type":"Point"}
}