{
  "type": "Feature",
  "properties": {
    "iso:country":"CH",
    "sg:address":"Feldbergstrasse 28",
    "sg:city":"Basel",
    "sg:orig_category":"Allgemeiner Hoch U Tiefbau",
    "sg:postcode":"4057",
    "sg:province":"Basel-Stadt",
    "wof:name":"Lito Ismailji",
    "wof:placetype":"venue"
},
  "geometry": {"coordinates":[7.589682,47.565922],"type":"Point"}
}