{
  "type": "Feature",
  "properties": {
    "iso:country":"CH",
    "sg:address":"Alberich Zwyssigstrasse 37",
    "sg:city":"Wettingen",
    "sg:orig_category":"Arztpraxen",
    "sg:phone":"+41 56 430 07 33",
    "sg:postcode":"5430",
    "sg:province":"Aargau",
    "wof:name":"Dr.med.reinhard Weisshaupt Arzt F.allgemeine Medizin Fmh",
    "wof:placetype":"venue"
},
  "geometry": {"coordinates":[8.321848,47.462437],"type":"Point"}
}