{
  "type": "Feature",
  "properties": {
    "iso:country":"CH",
    "sg:address":"Weissbadstrasse 26 9050 Appenzell. Postfach",
    "sg:city":"Appenzell",
    "sg:orig_category":"Rechtsberatung",
    "sg:phone":"+41 71 787 80 80",
    "sg:postcode":"9050",
    "sg:province":"Appenzell Innerhoden",
    "wof:name":"Retec",
    "wof:placetype":"venue"
},
  "geometry": {"coordinates":[9.412115097,47.3291473389],"type":"Point"}
}