{
  "type": "Feature",
  "properties": {
    "iso:country":"CH",
    "sg:address":"Vieux-march\u00e9 Rue Du 8",
    "sg:city":"Gen\u00e8ve",
    "sg:orig_category":"Herstellung von Lederbekleidung",
    "sg:postcode":"1207",
    "sg:province":"Gen\u00e8ve",
    "wof:name":"Fabiana Sa",
    "wof:placetype":"venue"
},
  "geometry": {"coordinates":[6.159386158,46.2007026672],"type":"Point"}
}