{
  "type": "Feature",
  "properties": {
    "iso:country":"CH",
    "sg:address":"Papierm\u00fchlestrasse 130 3063 Ittigen. Postfach",
    "sg:city":"Ittigen",
    "sg:orig_category":"Sonstiges Versicherungsgewerbe",
    "sg:phone":"+41 31 925 11 11",
    "sg:postcode":"3063",
    "sg:province":"Bern",
    "wof:name":"Geb\u00e4udeversicherung Des Kantons Bern",
    "wof:placetype":"venue"
},
  "geometry": {"coordinates":[7.4718298912,46.9711418152],"type":"Point"}
}