{
  "type": "Feature",
  "properties": {
    "iso:country":"CH",
    "sg:address":"Bommerstein",
    "sg:city":"Mols",
    "sg:orig_category":"Instandhaltung U Reparatur von Automobilen",
    "sg:phone":"+41 71 385 38 33",
    "sg:postcode":"8885",
    "sg:province":"St. Gallen",
    "wof:name":"Thoma Hanspeter Bp-service",
    "wof:placetype":"venue"
},
  "geometry": {"coordinates":[9.2519626617,47.4088058472],"type":"Point"}
}