{
  "type": "Feature",
  "properties": {
    "iso:country":"CH",
    "sg:address":"Lotzwilstrasse 14a",
    "sg:city":"Langenthal",
    "sg:orig_category":"Unclassifiable Establishments",
    "sg:postcode":"4900",
    "sg:province":"Bern",
    "wof:name":"Dr.med.christoph Urech Spezialarzt Fmh",
    "wof:placetype":"venue"
},
  "geometry": {"coordinates":[8.2067556381,47.4809684753],"type":"Point"}
}