{
  "type": "Feature",
  "properties": {
    "addr:full":"Rue Du March\u00e9 26 Gen\u00e8ve Gen\u00e8ve 1204",
    "addr:housenumber":"26",
    "addr:postcode":"1204",
    "addr:street":"Rue Du Marche\u0301",
    "iso:country":"CH",
    "sg:address":"Rue Du March\u00e9 26",
    "sg:city":"Gen\u00e8ve",
    "sg:orig_category":"Detailhandel mit Bekleidung Grosshandel mit Bekleidung",
    "sg:phone":"+41 22 311 34 00",
    "sg:postcode":"1204",
    "sg:province":"Gen\u00e8ve",
    "wof:name":"Fc Diffusion Sa Pr\u00eat-\u00e0-porter F\u00e9minin Promod",
    "wof:placetype":"venue"
},
  "geometry": {"coordinates":[6.147139,46.203007],"type":"Point"}
}