{
  "type": "Feature",
  "properties": {
    "iso:country":"CH",
    "sg:address":"Rue Des Rangiers 1",
    "sg:city":"Saignel\u00e9gier",
    "sg:orig_category":"Fleischverarbeitung Schlachten ohne Schlachten von Gefl\u00fcgel",
    "sg:phone":"+41 32 951 11 05",
    "sg:postcode":"2350",
    "sg:province":"Jura",
    "wof:name":"Romain Paratte Boucherie",
    "wof:placetype":"venue"
},
  "geometry": {"coordinates":[6.9971299171,47.256061554],"type":"Point"}
}