{
  "type": "Feature",
  "properties": {
    "iso:country":"CH",
    "sg:address":"Spielhof 3",
    "sg:city":"Glarus",
    "sg:orig_category":"Rechtsberatung",
    "sg:phone":"+41 55 640 25 44",
    "sg:postcode":"8750",
    "sg:province":"Glarus",
    "wof:name":"News Ag",
    "wof:placetype":"venue"
},
  "geometry": {"coordinates":[9.0664224625,47.0417480469],"type":"Point"}
}