{
  "type": "Feature",
  "properties": {
    "iso:country":"CH",
    "sg:address":"Route Du Ch\u00e2teau-d'affry 10",
    "sg:city":"Givisiez",
    "sg:orig_category":"Detailhandel mit Bekleidung Detailhandel mit Damenbekleidung",
    "sg:phone":"+41 26 466 34 48",
    "sg:postcode":"1762",
    "sg:province":"Fribourg",
    "wof:name":"Blanc Monique.",
    "wof:placetype":"venue"
},
  "geometry": {"coordinates":[1.553038,49.24778],"type":"Point"}
}