{
  "type": "Feature",
  "properties": {
    "iso:country":"CH",
    "sg:address":"1687",
    "sg:city":"Vuisternens-romont",
    "sg:classifiers":[
        {
            "category":"Social Services",
            "subcategory":"Retirement Home",
            "type":"Services"
        }
    ],
    "sg:phone":"+41 26 655 12 00",
    "sg:postcode":"1687",
    "sg:province":"Fribourg",
    "sg:tags":[
        "pflegeheime",
        "u",
        "alters"
    ],
    "wof:name":"Foyer Ste-marguerite Hospice Paroissial",
    "wof:placetype":"venue"
},
  "geometry": {"coordinates":[6.92887,46.656399],"type":"Point"}
}