{
  "type": "Feature",
  "properties": {
    "iso:country":"CH",
    "sg:address":"Hinterlenzligenweg 1",
    "sg:city":"Z\u00e4ziwil",
    "sg:orig_category":"Herstellung von Konstruktionsteilen, Fertigbauteilen U Ausbauelementen aus Holz Innenausbau",
    "sg:phone":"+41 31 711 14 91",
    "sg:postcode":"3532",
    "sg:province":"Bern",
    "wof:name":"Schreinerei Hofer + Cie",
    "wof:placetype":"venue"
},
  "geometry": {"coordinates":[7.6548199654,46.9034080505],"type":"Point"}
}