{
  "type": "Feature",
  "properties": {
    "iso:country":"CH",
    "sg:address":"Bruy\u00e8res Chemin Des 13 1000 Lausanne Case Postale 1152",
    "sg:city":"Lausanne",
    "sg:orig_category":"Grosshandel mit Getreide, Saatgut U Futtermitteln",
    "sg:phone":"+41 21 617 32 33",
    "sg:postcode":"1001",
    "sg:province":"Vaud",
    "wof:name":"Owg-tapex Sa",
    "wof:placetype":"venue"
},
  "geometry": {"coordinates":[6.6947751045,46.5545883179],"type":"Point"}
}