{
  "type": "Feature",
  "properties": {
    "iso:country":"CH",
    "sg:address":"L'oujonnet",
    "sg:city":"Bursinel",
    "sg:classifiers":[
        {
            "category":"Marine",
            "type":"Transportation"
        }
    ],
    "sg:phone":"+41 21 824 20 11",
    "sg:postcode":"1195",
    "sg:province":"Vaud",
    "sg:tags":[
        "transport",
        "sea"
    ],
    "wof:name":"Care Offshore Sa",
    "wof:placetype":"venue"
},
  "geometry": {"coordinates":[6.310254097,46.4460830688],"type":"Point"}
}