{
  "type": "Feature",
  "properties": {
    "iso:country":"CH",
    "sg:address":"Bahnhofstrasse 48",
    "sg:city":"B\u00fclach",
    "sg:orig_category":"Organisationen des Gesundheitswesen",
    "sg:phone":"+41 18602917",
    "sg:postcode":"8180",
    "sg:province":"Z\u00fcrich",
    "wof:name":"Beratungsstelle F\u00fcr Cerebral Gel\u00e4hmte Kinder",
    "wof:placetype":"venue"
},
  "geometry": {"coordinates":[8.5390377045,47.5224189758],"type":"Point"}
}