{
  "type": "Feature",
  "properties": {
    "iso:country":"CH",
    "sg:address":"St. Niklausstrasse 30 4500 Solothurn. Postfach",
    "sg:city":"Solothurn",
    "sg:orig_category":"Pensionskassen",
    "sg:postcode":"4500",
    "sg:province":"Solothurn",
    "wof:name":"Stiftung D\u00fcbi-m\u00fcller Dr. O. Solothurn",
    "wof:placetype":"venue"
},
  "geometry": {"coordinates":[7.5419797897,47.2141494751],"type":"Point"}
}