{
  "type": "Feature",
  "properties": {
    "iso:country":"CH",
    "sg:address":"Neuengasse 24 3011 Bern. Postfach",
    "sg:city":"Bern",
    "sg:orig_category":"Non-Classified Establishments",
    "sg:phone":"+41 71 744 81 81",
    "sg:postcode":"3001",
    "sg:province":"Bern",
    "wof:name":"Mcdonald's Restaurant",
    "wof:placetype":"venue"
},
  "geometry": {"coordinates":[9.6528787613,47.4475059509],"type":"Point"}
}