{
  "type": "Feature",
  "properties": {
    "iso:country":"CH",
    "sg:address":"Konradstrasse 20 8005 Z\u00fcrich. Postfach 141",
    "sg:city":"Z\u00fcrich",
    "sg:orig_category":"Interessenvertretungen U sonstige Vereinigungen Organisationen der Wohlfahrtspflege",
    "sg:phone":"+41 12734242",
    "sg:postcode":"8031",
    "sg:province":"Z\u00fcrich",
    "wof:name":"Aids-hilfe Schweiz Ahs",
    "wof:placetype":"venue"
},
  "geometry": {"coordinates":[8.536444664,47.3804740906],"type":"Point"}
}