{
  "type": "Feature",
  "properties": {
    "iso:country":"CH",
    "sg:address":"Alte M\u00fchle",
    "sg:city":"Sevelen",
    "sg:orig_category":"RESTAURANTS: TEA-ROOMS",
    "sg:phone":"+41 81 785 24 60",
    "sg:postcode":"9475",
    "sg:province":"St. Gallen",
    "wof:name":"Alte M\u00fchle Sevelen Ag",
    "wof:placetype":"venue"
},
  "geometry": {"coordinates":[9.4796829224,47.1254692078],"type":"Point"}
}