{
  "type": "Feature",
  "properties": {
    "iso:country":"CH",
    "sg:address":"6503",
    "sg:city":"Bellinzona",
    "sg:classifiers":[
        {
            "category":"Restaurant",
            "type":"Food & Drink"
        }
    ],
    "sg:phone":"+41 91 825 16 95",
    "sg:postcode":"6503",
    "sg:province":"Ticino",
    "wof:name":"Osteria-grotto Da Lele",
    "wof:placetype":"venue"
},
  "geometry": {"coordinates":[8.9959402084,46.2088088989],"type":"Point"}
}