{
  "type": "Feature",
  "properties": {
    "iso:country":"CH",
    "sg:address":"Via Zurigo 5",
    "sg:city":"Lugano",
    "sg:orig_category":"Detailhandel mit Damenbekleidung",
    "sg:phone":"+41 91 923 27 28",
    "sg:postcode":"6900",
    "sg:province":"Ticino",
    "wof:name":"Mariella Bassi Boutique A Modo Mio",
    "wof:placetype":"venue"
},
  "geometry": {"coordinates":[8.955317,46.011349],"type":"Point"}
}