{
  "type": "Feature",
  "properties": {
    "iso:country":"CH",
    "sg:address":"1913",
    "sg:city":"Saillon",
    "sg:classifiers":[
        {
            "category":"Restaurant",
            "type":"Food & Drink"
        }
    ],
    "sg:phone":"+41 27 473 12 05",
    "sg:postcode":"1913",
    "sg:province":"Valais",
    "wof:name":"Restaurant De La Poste",
    "wof:placetype":"venue"
},
  "geometry": {"coordinates":[7.6346597672,46.3163299561],"type":"Point"}
}