{
  "type": "Feature",
  "properties": {
    "iso:country":"CH",
    "sg:address":"Via Moretto 1",
    "sg:city":"Sorengo",
    "sg:orig_category":"Grosshandel mit H\u00e4uten, Fellen U Leder",
    "sg:phone":"+41 91 960 18 40",
    "sg:postcode":"6924",
    "sg:province":"Ticino",
    "wof:name":"Ryffel Pelli Sa",
    "wof:placetype":"venue"
},
  "geometry": {"coordinates":[8.9353609085,46.0046577454],"type":"Point"}
}