{
  "type": "Feature",
  "properties": {
    "iso:country":"CH",
    "sg:address":"Rothenegg 3818 Grindelwald. Postfach 82",
    "sg:city":"Grindelwald",
    "sg:orig_category":"Herstellung von sonstigen landwirtschaftlichen Maschinen Instandhaltung U Reparatur von Automobilen",
    "sg:phone":"+41 33 853 15 07",
    "sg:postcode":"3818",
    "sg:province":"Bern",
    "wof:name":"Bohren & Co., Rothenegg-garage",
    "wof:placetype":"venue"
},
  "geometry": {"coordinates":[8.0190792084,46.6258277893],"type":"Point"}
}