{
  "type": "Feature",
  "properties": {
    "iso:country":"CH",
    "sg:address":"Klosterstrasse 12a",
    "sg:city":"Luzern",
    "sg:orig_category":"P\u00e9dicure",
    "sg:phone":"+41 41 240 38 91",
    "sg:postcode":"6003",
    "sg:province":"Luzern",
    "wof:name":"Edith Helg P\u00e9dicure",
    "wof:placetype":"venue"
},
  "geometry": {"coordinates":[8.3003835678,47.0493507385],"type":"Point"}
}