{
  "type": "Feature",
  "properties": {
    "iso:country":"CH",
    "sg:address":"Schongauerstrasse 12",
    "sg:city":"Fahrwangen",
    "sg:orig_category":"Bauschreinerei Herstellung von M\u00f6beln verschiedener Art",
    "sg:phone":"+41 56 667 12 32",
    "sg:postcode":"5615",
    "sg:province":"Aargau",
    "wof:name":"Walter Fischer Bau-& M\u00f6belschreinerei",
    "wof:placetype":"venue"
},
  "geometry": {"coordinates":[8.24615,47.29311],"type":"Point"}
}