{
  "type": "Feature",
  "properties": {
    "iso:country":"CH",
    "sg:address":"Fichtenstrasse 1",
    "sg:city":"Emmenbr\u00fccke",
    "sg:orig_category":"Detailhandel mit Waren verschiedener Art, Hauptrichtung Nahrungsmittel",
    "sg:phone":"+41 41 260 05 35",
    "sg:postcode":"6020",
    "sg:province":"Luzern",
    "wof:name":"Coop Super Center",
    "wof:placetype":"venue"
},
  "geometry": {"coordinates":[8.2907571793,47.0723152161],"type":"Point"}
}