{
  "type": "Feature",
  "properties": {
    "iso:country":"CH",
    "sg:address":"Breitenstrasse 18",
    "sg:city":"D\u00e4llikon",
    "sg:orig_category":"Unclassifiable Establishments",
    "sg:postcode":"8108",
    "sg:province":"Z\u00fcrich",
    "wof:name":"A\u00e9rolineas Argentinas Sa",
    "wof:placetype":"venue"
},
  "geometry": {"coordinates":[8.4476747513,47.4371643066],"type":"Point"}
}