{
  "type": "Feature",
  "properties": {
    "iso:country":"CH",
    "sg:address":"Varenna Via Bartolomeo 2 6600 Locarno. Postfach",
    "sg:city":"Locarno",
    "sg:orig_category":"Sonstiges Versicherungsgewerbe",
    "sg:postcode":"6600",
    "sg:province":"Ticino",
    "wof:name":"Belotti Angelo Assicurazioni Agente Generale Di Assicurazioni",
    "wof:placetype":"venue"
},
  "geometry": {"coordinates":[8.7898111343,46.1679916382],"type":"Point"}
}