{
  "type": "Feature",
  "properties": {
    "iso:country":"CH",
    "sg:address":"Hirschengraben 7 3011 Bern. Postfach",
    "sg:city":"Bern",
    "sg:orig_category":"Herstellung von medizinischen U chirurgischen Ger\u00e4ten sowie orthop\u00e4dischen Vorrichtungen",
    "sg:phone":"+41 31118220",
    "sg:postcode":"3005",
    "sg:province":"Bern",
    "wof:name":"Dental Labor Simmen Zahntechn. Labor",
    "wof:placetype":"venue"
},
  "geometry": {"coordinates":[7.4381461143,46.946559906],"type":"Point"}
}