{
  "type": "Feature",
  "properties": {
    "iso:country":"CH",
    "sg:address":"Mythenquai 60 8002 Z\u00fcrich. Postfach",
    "sg:city":"Z\u00fcrich",
    "sg:orig_category":"Pensionskassen",
    "sg:postcode":"8001",
    "sg:province":"Z\u00fcrich",
    "wof:name":"Stiftung F\u00fcr Personalvorsorge Hiestand & Steinmetz, Ingenieurb\u00fcro.",
    "wof:placetype":"venue"
},
  "geometry": {"coordinates":[8.7582454681,47.195098877],"type":"Point"}
}