{
  "type": "Feature",
  "properties": {
    "iso:country":"CH",
    "sg:address":"Schulhaus",
    "sg:city":"Alvaschein",
    "sg:orig_category":"Primarschulen",
    "sg:phone":"+41 41 787 25 18",
    "sg:postcode":"7451",
    "sg:province":"Graubunden",
    "wof:name":"Primarschule",
    "wof:placetype":"venue"
},
  "geometry": {"coordinates":[8.3546152115,47.1746406555],"type":"Point"}
}