{
  "type": "Feature",
  "properties": {
    "iso:country":"CH",
    "sg:address":"Rue Du Coll\u00e8ge 11",
    "sg:city":"Nyon",
    "sg:orig_category":"Detailhandel mit Fleisch U Fleischwaren",
    "sg:phone":"+41 22 361 17 57",
    "sg:postcode":"1260",
    "sg:province":"Vaud",
    "wof:name":"Jemmely G.",
    "wof:placetype":"venue"
},
  "geometry": {"coordinates":[6.2375760078,46.381980896],"type":"Point"}
}