{
  "type": "Feature",
  "properties": {
    "iso:country":"CH",
    "sg:address":"Via Camminata 9",
    "sg:city":"Bellinzona",
    "sg:orig_category":"Flachsaufbereitung U spinnerei Saatgut and Samen Grosshandel",
    "sg:phone":"+41 22 342 26 20",
    "sg:postcode":"6500",
    "sg:province":"Ticino",
    "wof:name":"Hydro-chanvre, Drevoux Yvan Et Eric Produits De D\u00e9riv\u00e9s Du Chanvre, Produits Naturels Et Biologiques; Commerce",
    "wof:placetype":"venue"
},
  "geometry": {"coordinates":[6.1417188644,46.1874656677],"type":"Point"}
}