{
  "type": "Feature",
  "properties": {
    "iso:country":"CH",
    "sg:address":"Gertrudstrasse 59 8003 Z\u00fcrich. Postfach",
    "sg:city":"Z\u00fcrich",
    "sg:orig_category":"Vereine Gesang",
    "sg:postcode":"8036",
    "sg:province":"Z\u00fcrich",
    "wof:name":"Tarcisius-chor Der Pfarrei Herz-jesu",
    "wof:placetype":"venue"
},
  "geometry": {"coordinates":[8.5142736435,47.3727607727],"type":"Point"}
}