{
  "type": "Feature",
  "properties": {
    "iso:country":"CH",
    "sg:address":"Grosshaus",
    "sg:city":"Diemtigen",
    "sg:orig_category":"Erziehungsheime Wohnheime",
    "sg:phone":"+41 33 681 17 69",
    "sg:postcode":"3754",
    "sg:province":"Bern",
    "wof:name":"Internat Grosshaus Ag",
    "wof:placetype":"venue"
},
  "geometry": {"coordinates":[7.5645580292,46.648235321],"type":"Point"}
}