{
  "type": "Feature",
  "properties": {
    "iso:country":"CH",
    "sg:address":"Juch 732",
    "sg:city":"Unterkulm",
    "sg:orig_category":"Interessenvertretungen U sonstige Vereinigungen",
    "sg:phone":"+41 62 776 27 57",
    "sg:postcode":"5726",
    "sg:province":"Aargau",
    "wof:name":"Aargauische Tennisvereinigung",
    "wof:placetype":"venue"
},
  "geometry": {"coordinates":[8.1186800003,47.3132514954],"type":"Point"}
}