{
  "type": "Feature",
  "properties": {
    "iso:country":"CH",
    "sg:address":"Route Des Creux Verbier 1934 Bagnes. Postfach",
    "sg:city":"Verbier",
    "sg:orig_category":"Sanit\u00e4r, Heizungs U L\u00fcftungsinstallation",
    "sg:postcode":"1936",
    "sg:province":"Valais",
    "wof:name":"Jacquier Michel",
    "wof:placetype":"venue"
},
  "geometry": {"coordinates":[7.2226920128,46.0892524719],"type":"Point"}
}