{
  "type": "Feature",
  "properties": {
    "iso:country":"CH",
    "sg:address":"Kottenring 12",
    "sg:city":"Sursee",
    "sg:orig_category":"Herstellung von Schmuck, Gold U Silberschmiedwaren Maler U Glasergewerbe",
    "sg:phone":"+41 41 921 32 82",
    "sg:postcode":"6210",
    "sg:province":"Luzern",
    "wof:name":"Daniel Trenkle Malergesch\u00e4ft",
    "wof:placetype":"venue"
},
  "geometry": {"coordinates":[8.0939159393,47.1719818115],"type":"Point"}
}