{
  "type": "Feature",
  "properties": {
    "iso:country":"CH",
    "sg:address":"Dornacherstrasse 82 4053 Basel. Postfach",
    "sg:city":"Basel",
    "sg:orig_category":"Allgemeiner Hoch U Tiefbau",
    "sg:postcode":"4053",
    "sg:province":"Basel-Stadt",
    "wof:name":"G D Renovationen Ag",
    "wof:placetype":"venue"
},
  "geometry": {"coordinates":[7.58734,47.543957],"type":"Point"}
}