{
  "type": "Feature",
  "properties": {
    "iso:country":"CH",
    "sg:address":"Niederfeld 4 9320 Stachen. Postfach",
    "sg:city":"Arbon",
    "sg:orig_category":"Architektur U Ingenieurb\u00fcros Architekturb\u00fcros",
    "sg:phone":"+41 71 447 89 79",
    "sg:postcode":"9320",
    "sg:province":"Thurgau",
    "wof:name":"Morgenegg Roland - Innenarchitektur",
    "wof:placetype":"venue"
},
  "geometry": {"coordinates":[9.4115,47.506729],"type":"Point"}
}