{
  "type": "Feature",
  "properties": {
    "iso:country":"CH",
    "sg:address":"Chisenmattweg 1",
    "sg:city":"Oberdiessbach",
    "sg:classifiers":[
        {
            "category":"Insurance",
            "subcategory":"Insurance Agent",
            "type":"Services"
        }
    ],
    "sg:phone":"+41 31 771 22 02",
    "sg:postcode":"3672",
    "sg:province":"Bern",
    "sg:tags":[
        "versicherungsagenturen",
        "-broker"
    ],
    "wof:name":"Winterthur-versicherungen Agentur Heinz Weissbaum",
    "wof:placetype":"venue"
},
  "geometry": {"coordinates":[7.6165161133,46.8373527527],"type":"Point"}
}