{
  "type": "Feature",
  "properties": {
    "iso:country":"CH",
    "sg:address":"Solothurnstrasse 3",
    "sg:city":"Olten",
    "sg:orig_category":"Gartenbau",
    "sg:phone":"+41 62 212 44 84",
    "sg:postcode":"4600",
    "sg:province":"Solothurn",
    "wof:name":"Wyss Gartenbau",
    "wof:placetype":"venue"
},
  "geometry": {"coordinates":[7.9002699852,47.3498382568],"type":"Point"}
}