{
  "type": "Feature",
  "properties": {
    "iso:country":"CH",
    "sg:address":"Ch. De La Zyma 2 Case Postale 80",
    "sg:city":"Prangins",
    "sg:classifiers":[
        {
            "category":"Autos & Motor Vehicles",
            "subcategory":"Automobile Sales",
            "type":"Retail Goods"
        }
    ],
    "sg:phone":"+41 22 363 67 40",
    "sg:postcode":"1197",
    "sg:province":"Vaud",
    "sg:tags":[
        "equipment",
        "motor-cars",
        "transport"
    ],
    "wof:name":"Lauber Sa",
    "wof:placetype":"venue"
},
  "geometry": {"coordinates":[8.2241401672,46.8130912781],"type":"Point"}
}