{
  "type": "Feature",
  "properties": {
    "iso:country":"CH",
    "sg:address":"Webergasse 15",
    "sg:city":"Basel",
    "sg:orig_category":"Non-Classified Establishments",
    "sg:phone":"+41 61 693 33 22",
    "sg:postcode":"4058",
    "sg:province":"Basel-Stadt",
    "wof:name":"Blinx Grafik Stoecklin",
    "wof:placetype":"venue"
},
  "geometry": {"coordinates":[7.5907931328,47.5619659424],"type":"Point"}
}