{
  "type": "Feature",
  "properties": {
    "iso:country":"CH",
    "sg:address":"Rue Des Terreaux 25",
    "sg:city":"Lausanne",
    "sg:classifiers":[
        {
            "category":"Government",
            "subcategory":"Post Office",
            "type":"Public Place"
        }
    ],
    "sg:phone":"+41 21 320 79 52",
    "sg:postcode":"1003",
    "sg:province":"Vaud",
    "sg:tags":[
        "caf\u00e9s",
        "tea-rooms"
    ],
    "wof:name":"Tea-room Chez Yassin",
    "wof:placetype":"venue"
},
  "geometry": {"coordinates":[6.6273927689,46.5227928162],"type":"Point"}
}