{
  "type": "Feature",
  "properties": {
    "iso:country":"CH",
    "sg:address":"Rue Du Simplon 18",
    "sg:city":"Vevey",
    "sg:orig_category":"Notariate",
    "sg:phone":"+41 21 921 97 25",
    "sg:postcode":"1800",
    "sg:province":"Vaud",
    "wof:name":"Ren\u00e9 Horisberger Etude De Notaire",
    "wof:placetype":"venue"
},
  "geometry": {"coordinates":[6.8459730148,46.4596481323],"type":"Point"}
}