{
  "type": "Feature",
  "properties": {
    "iso:country":"CH",
    "sg:address":"San Gottardo Corso 9",
    "sg:city":"Chiasso",
    "sg:orig_category":"Herstellung von Radio U Fernsehger\u00e4ten sowie phono U videotechnischen Ger\u00e4ten",
    "sg:phone":"+41 91 690 07 60",
    "sg:postcode":"6830",
    "sg:province":"Ticino",
    "wof:name":"Controtempo Sagl",
    "wof:placetype":"venue"
},
  "geometry": {"coordinates":[9.0331754684,45.8325386047],"type":"Point"}
}