{
  "type": "Feature",
  "properties": {
    "iso:country":"CH",
    "sg:address":"Dorfplatz 24",
    "sg:city":"Horgen",
    "sg:orig_category":"Detailhandel mit B\u00fcchern Detailhandel mit Ton U Bildtr\u00e4gern",
    "sg:phone":"+41 17250919",
    "sg:postcode":"8810",
    "sg:province":"Z\u00fcrich",
    "wof:name":"Ex Libris Ag",
    "wof:placetype":"venue"
},
  "geometry": {"coordinates":[8.597402,47.259865],"type":"Point"}
}