{
  "type": "Feature",
  "properties": {
    "iso:country":"CH",
    "sg:address":"Eichenweg 22",
    "sg:city":"Tafers",
    "sg:orig_category":"Autogaragen Autospenglereien",
    "sg:phone":"+41 26 494 16 44",
    "sg:postcode":"1712",
    "sg:province":"Fribourg",
    "wof:name":"Garage & Carrosserie Moderne",
    "wof:placetype":"venue"
},
  "geometry": {"coordinates":[7.19536,46.812908],"type":"Point"}
}