{
  "type": "Feature",
  "properties": {
    "iso:country":"CH",
    "sg:address":"Gartenstrasse 2",
    "sg:city":"Zug",
    "sg:orig_category":"Non-Classified Establishments",
    "sg:postcode":"6300",
    "sg:province":"Zug",
    "wof:name":"Petmos Gmbh Waren Im Baubereich; Dienstleistungen, Handel Usw.",
    "wof:placetype":"venue"
},
  "geometry": {"coordinates":[7.355173111,47.1125984192],"type":"Point"}
}