{
  "type": "Feature",
  "properties": {
    "iso:country":"CH",
    "sg:address":"Rue De La Justice 2",
    "sg:city":"Del\u00e9mont",
    "sg:orig_category":"Landesverteidigung, Sozialversicherung \u00d6ffentliche Verwaltung",
    "sg:phone":"+41 32 421 51 11",
    "sg:postcode":"2800",
    "sg:province":"Jura",
    "wof:name":"Administ.cantonale Jurassienne Service De L'informatique",
    "wof:placetype":"venue"
},
  "geometry": {"coordinates":[7.3445868492,47.3661575317],"type":"Point"}
}