{
  "type": "Feature",
  "properties": {
    "iso:country":"CH",
    "sg:address":"4936",
    "sg:city":"Kleindietwil",
    "sg:orig_category":"Mechanik",
    "sg:postcode":"4936",
    "sg:province":"Bern",
    "wof:name":"Joh. Wenger",
    "wof:placetype":"venue"
},
  "geometry": {"coordinates":[7.7905201912,47.1418495178],"type":"Point"}
}