{
  "type": "Feature",
  "properties": {
    "iso:country":"CH",
    "sg:address":"Freiburgstrasse 435 3018 Bern. Postfach 611",
    "sg:city":"Bern",
    "sg:orig_category":"Sanit\u00e4r U Heizungsinstallation Sanit\u00e4rinstallation",
    "sg:phone":"+41 31 991 45 55",
    "sg:postcode":"3018",
    "sg:province":"Bern",
    "wof:name":"K\u00f6nig Haustechnik Und Service Ag",
    "wof:placetype":"venue"
},
  "geometry": {"coordinates":[7.3944039345,46.9344406128],"type":"Point"}
}