{
  "type": "Feature",
  "properties": {
    "iso:country":"CH",
    "sg:address":"Stockacherweg 3 5615 Fahrwangen. Postfach 80",
    "sg:city":"Fahrwangen",
    "sg:orig_category":"Erwachsenenbildung U Unterricht K\u00fcnstlerische Schulen",
    "sg:phone":"+41 56 667 02 25",
    "sg:postcode":"5615",
    "sg:province":"Aargau",
    "wof:name":"Orgel- U. Keyboardschule Edelweiss, Schwarz Monika",
    "wof:placetype":"venue"
},
  "geometry": {"coordinates":[8.2420463562,47.2981452942],"type":"Point"}
}