{
  "type": "Feature",
  "properties": {
    "iso:country":"CH",
    "sg:address":"Aletschstrasse",
    "sg:city":"Naters",
    "sg:orig_category":"Interessenvertretungen",
    "sg:phone":"+41 27 923 04 26",
    "sg:postcode":"3904",
    "sg:province":"Valais",
    "wof:name":"Stiftung F\u00fcr Kurortseinrichtungen Naters-blatten-belalp",
    "wof:placetype":"venue"
},
  "geometry": {"coordinates":[7.994134903,46.3262443542],"type":"Point"}
}