{
  "type": "Feature",
  "properties": {
    "iso:country":"CH",
    "sg:address":"Route De Berne 228",
    "sg:city":"Epalinges",
    "sg:orig_category":"Innendekorationsateliers",
    "sg:phone":"+41 21 784 07 62",
    "sg:postcode":"1066",
    "sg:province":"Vaud",
    "wof:name":"Adrien Richon D\u00e9coration D'int\u00e9rieurs",
    "wof:placetype":"venue"
},
  "geometry": {"coordinates":[6.6771821976,46.5491294861],"type":"Point"}
}