{
  "type": "Feature",
  "properties": {
    "iso:country":"CH",
    "sg:address":"Dorfstrasse 27",
    "sg:city":"Z\u00fcrich",
    "sg:classifiers":[
        {
            "category":"Banks & Credit Unions",
            "subcategory":"Bureau De Change",
            "type":"Services"
        }
    ],
    "sg:phone":"+41 14468300",
    "sg:postcode":"8037",
    "sg:province":"Z\u00fcrich",
    "sg:tags":[
        "image",
        "processing",
        "system",
        "digital"
    ],
    "wof:name":"Aaa Ag",
    "wof:placetype":"venue"
},
  "geometry": {"coordinates":[8.5228796005,47.3942146301],"type":"Point"}
}