{
  "type": "Feature",
  "properties": {
    "iso:country":"CH",
    "sg:address":"Buchlenweg 6",
    "sg:city":"Uettligen",
    "sg:orig_category":"Unclassifiable Establishments",
    "sg:postcode":"3043",
    "sg:province":"Bern",
    "wof:name":"Restorent Ag",
    "wof:placetype":"venue"
},
  "geometry": {"coordinates":[7.3876581192,46.9888839722],"type":"Point"}
}