{
  "type": "Feature",
  "properties": {
    "iso:country":"CH",
    "sg:address":"Muhenstrasse 56 5036 Oberentfelden. Postfach",
    "sg:city":"Oberentfelden",
    "sg:orig_category":"Veterin\u00e4rwesen",
    "sg:phone":"+41 62 723 51 71",
    "sg:postcode":"5036",
    "sg:province":"Aargau",
    "wof:name":"Casura & Br\u00e4ndli Ag",
    "wof:placetype":"venue"
},
  "geometry": {"coordinates":[8.0484380722,47.3507003784],"type":"Point"}
}