{
  "type": "Feature",
  "properties": {
    "iso:country":"CH",
    "sg:address":"Rue Du Lac 18",
    "sg:city":"B\u00f4le",
    "sg:orig_category":"Alters U Pflegeheime Wohnheime",
    "sg:phone":"+41 21 634 74 66",
    "sg:postcode":"2014",
    "sg:province":"Neuch\u00e2tel",
    "wof:name":"R\u00e9sidence Les Novalles Sa",
    "wof:placetype":"venue"
},
  "geometry": {"coordinates":[6.589302,46.540054],"type":"Point"}
}