{
  "type": "Feature",
  "properties": {
    "iso:country":"CH",
    "sg:address":"Im Walder 29 8702 Zollikon. Postfach",
    "sg:city":"Zollikon",
    "sg:orig_category":"Grosshandel mit Schmuck Grosshandel mit sonstigen Gebrauchs U Verbrauchsg\u00fctern",
    "sg:phone":"+41 13902080",
    "sg:postcode":"8702",
    "sg:province":"Z\u00fcrich",
    "wof:name":"Michael Gumuchdjian Diamant-& Edelsteinhandel",
    "wof:placetype":"venue"
},
  "geometry": {"coordinates":[8.5751991272,47.3457183838],"type":"Point"}
}