{
  "type": "Feature",
  "properties": {
    "addr:full":"Marktgasse 14 Z\u00fcrich Z\u00fcrich 8001",
    "addr:housenumber":"14",
    "addr:postcode":"8001",
    "addr:street":"Marktgasse",
    "iso:country":"CH",
    "sg:address":"Marktgasse 14",
    "sg:city":"Z\u00fcrich",
    "sg:classifiers":[
        {
            "category":"Bars & Pubs",
            "type":"Food & Drink"
        }
    ],
    "sg:phone":"+41 12661877",
    "sg:postcode":"8001",
    "sg:province":"Z\u00fcrich",
    "wof:name":"Cocoon Bar @ Pigalle",
    "wof:placetype":"venue"
},
  "geometry": {"coordinates":[8.543874,47.371975],"type":"Point"}
}