{
  "type": "Feature",
  "properties": {
    "iso:country":"CH",
    "sg:address":"Via Cantonale 33 6815 Melide. Postfach",
    "sg:city":"Melide",
    "sg:orig_category":"Herstellung von sonstigen elektrischen Ausr\u00fcstungen",
    "sg:postcode":"6815",
    "sg:province":"Ticino",
    "wof:name":"Qonix Sa",
    "wof:placetype":"venue"
},
  "geometry": {"coordinates":[8.9472875595,45.9566764832],"type":"Point"}
}