{
  "type": "Feature",
  "properties": {
    "iso:country":"CH",
    "sg:address":"Rossweid 14",
    "sg:city":"Guntershausen",
    "sg:orig_category":"Herstellung von k\u00e4lte U lufttechnischen Erzeugnissen f\u00fcr gewerbliche Zwecke Sanit\u00e4r U Heizungsinstal",
    "sg:phone":"+41 17602777",
    "sg:postcode":"8357",
    "sg:province":"Thurgau",
    "wof:name":"Hea Holzenergie Ag",
    "wof:placetype":"venue"
},
  "geometry": {"coordinates":[8.4541101456,47.2813072205],"type":"Point"}
}