{
  "type": "Feature",
  "properties": {
    "iso:country":"CH",
    "sg:address":"Avenue Du Mont-blanc 38",
    "sg:city":"Gland",
    "sg:orig_category":"Einzelhandel mit Automobilteilen U Zubeh\u00f6r Handel mit Automobilteilen U Zubeh\u00f6r",
    "sg:phone":"+41 22 364 10 16",
    "sg:postcode":"1196",
    "sg:province":"Vaud",
    "wof:name":"Simili Andr\u00e9",
    "wof:placetype":"venue"
},
  "geometry": {"coordinates":[6.2730379105,46.4142951965],"type":"Point"}
}