{
  "type": "Feature",
  "properties": {
    "iso:country":"CH",
    "sg:address":"Bernstrasse 388",
    "sg:city":"Dietikon",
    "sg:orig_category":"Allgemeiner Hoch U Tiefbau Architekturb\u00fcros",
    "sg:phone":"+41 17410700",
    "sg:postcode":"8953",
    "sg:province":"Z\u00fcrich",
    "wof:name":"Wermuth Und Leu Ag",
    "wof:placetype":"venue"
},
  "geometry": {"coordinates":[8.395272,47.383579],"type":"Point"}
}