{
  "type": "Feature",
  "properties": {
    "iso:country":"CH",
    "sg:address":"Les Auvattes 6",
    "sg:city":"Sorvilier",
    "sg:orig_category":"Bauspenglerei Dachdeckerei",
    "sg:phone":"+41 79 204 49 25",
    "sg:postcode":"2736",
    "sg:province":"Bern",
    "wof:name":"Pierre-andr\u00e9 Nater Entreprise De Couverture",
    "wof:placetype":"venue"
},
  "geometry": {"coordinates":[6.832992,47.102772],"type":"Point"}
}