{
  "type": "Feature",
  "properties": {
    "iso:country":"CH",
    "sg:address":"Paradiesrain 30 4123 Allschwil. Postfach 324",
    "sg:city":"Basel",
    "sg:orig_category":"Grosshandel mit chemischen Erzeugnissen",
    "sg:phone":"+41 79 322 77 11",
    "sg:postcode":"4015",
    "sg:province":"Basel-Stadt",
    "wof:name":"M. & T. Graf Ag Reinigungsmaterial",
    "wof:placetype":"venue"
},
  "geometry": {"coordinates":[7.5523428917,47.5459098816],"type":"Point"}
}