{
  "type": "Feature",
  "properties": {
    "iso:country":"CH",
    "sg:address":"6804 Bironico. Postfach Caselle Postale 41",
    "sg:city":"Bironico",
    "sg:orig_category":"Sportvereine Ballsport Fussball",
    "sg:phone":"+41 91 946 23 18",
    "sg:postcode":"6804",
    "sg:province":"Ticino",
    "wof:name":"Fc Rapid Bironico",
    "wof:placetype":"venue"
},
  "geometry": {"coordinates":[8.9307699203,46.1260910034],"type":"Point"}
}