{
  "type": "Feature",
  "properties": {
    "iso:country":"CH",
    "sg:address":"Scuole Via Delle 3",
    "sg:city":"Viganello",
    "sg:orig_category":"Erschliessung von Grundst\u00fccken",
    "sg:postcode":"6962",
    "sg:province":"Ticino",
    "wof:name":"Christl. Immobiliengenossenschaft Im Gr\u00fct",
    "wof:placetype":"venue"
},
  "geometry": {"coordinates":[9.00025177,47.4761390686],"type":"Point"}
}