{
  "type": "Feature",
  "properties": {
    "iso:country":"CH",
    "sg:address":"Gewerbepark Obholten",
    "sg:city":"Egliswil",
    "sg:orig_category":"Instandhaltung U Reparatur von Automobilen",
    "sg:postcode":"5704",
    "sg:province":"Aargau",
    "wof:name":"Garage R. Varela",
    "wof:placetype":"venue"
},
  "geometry": {"coordinates":[8.1889467239,47.3499946594],"type":"Point"}
}