{
  "type": "Feature",
  "properties": {
    "iso:country":"CH",
    "sg:address":"Cadruvi",
    "sg:city":"Breil/brigels",
    "sg:orig_category":"Sportvereine Ballsport Tennis",
    "sg:postcode":"7165",
    "sg:province":"Graubunden",
    "wof:name":"Tc Brigels",
    "wof:placetype":"venue"
},
  "geometry": {"coordinates":[9.061164856,46.7677764893],"type":"Point"}
}