{
  "type": "Feature",
  "properties": {
    "addr:full":"Industrie Rue De L' 30 Bulle Fribourg 1630",
    "addr:housenumber":"30",
    "addr:postcode":"1630",
    "addr:street":"Rue De L '",
    "iso:country":"CH",
    "sg:address":"Industrie Rue De L' 30",
    "sg:city":"Bulle",
    "sg:orig_category":"Allgemeiner Hoch U Tiefbau",
    "sg:phone":"+41 22 788 28 13",
    "sg:postcode":"1630",
    "sg:province":"Fribourg",
    "wof:name":"Bat-system, Gabino Gino",
    "wof:placetype":"venue"
},
  "geometry": {"coordinates":[6.125349,46.235039],"type":"Point"}
}