{
  "type": "Feature",
  "properties": {
    "iso:country":"CH",
    "sg:address":"Altisbergstrasse 12",
    "sg:city":"Biberist",
    "sg:orig_category":"Sportvereine Orientierungslauf",
    "sg:phone":"+41 32 672 43 49",
    "sg:postcode":"4562",
    "sg:province":"Solothurn",
    "wof:name":"Bucheggberger Ol-l\u00e4ufer",
    "wof:placetype":"venue"
},
  "geometry": {"coordinates":[7.5541682243,47.1751785278],"type":"Point"}
}