{
  "type": "Feature",
  "properties": {
    "iso:country":"CH",
    "sg:address":"Rue Bubenberg 34 2500 Biel/bienne. Postfach",
    "sg:city":"Biel/bienne",
    "sg:orig_category":"Vermietung U Verpachtung von eigenen Immobilien",
    "sg:postcode":"2500",
    "sg:province":"Bern",
    "wof:name":"Immohyp Ag",
    "wof:placetype":"venue"
},
  "geometry": {"coordinates":[7.2504501343,47.1431999207],"type":"Point"}
}