{
  "type": "Feature",
  "properties": {
    "iso:country":"CH",
    "sg:address":"Kirchgasse 4",
    "sg:city":"Derendingen",
    "sg:orig_category":"Bauschreinerei Zimmerei, Ingenieurholzbau",
    "sg:phone":"+41 32 682 47 24",
    "sg:postcode":"4552",
    "sg:province":"Solothurn",
    "wof:name":"Roland Hostettler Schreinerei & Zimmerei",
    "wof:placetype":"venue"
},
  "geometry": {"coordinates":[7.587682,47.19236],"type":"Point"}
}