{
  "type": "Feature",
  "properties": {
    "iso:country":"CH",
    "sg:address":"Bahnhofstrasse 13",
    "sg:city":"Z\u00fcrich",
    "sg:classifiers":[
        {
            "category":"Banks & Credit Unions",
            "subcategory":"Financial Services",
            "type":"Services"
        }
    ],
    "sg:phone":"+41 4112171000",
    "sg:postcode":"8001",
    "sg:province":"Z\u00fcrich",
    "sg:tags":[
        "banking",
        "finance",
        "insurance"
    ],
    "wof:name":"Niederer Kraft & Frey",
    "wof:placetype":"venue"
},
  "geometry": {"coordinates":[8.539453,47.368908],"type":"Point"}
}