{
  "type": "Feature",
  "properties": {
    "iso:country":"CH",
    "sg:address":"Rosenfeldweg 4",
    "sg:city":"Horw",
    "sg:orig_category":"P\u00e9dicure",
    "sg:phone":"+41 19324975",
    "sg:postcode":"6048",
    "sg:province":"Luzern",
    "wof:name":"Olga Farner P\u00e9dicure",
    "wof:placetype":"venue"
},
  "geometry": {"coordinates":[8.7878780365,47.3304595947],"type":"Point"}
}