{
  "type": "Feature",
  "properties": {
    "iso:country":"CH",
    "sg:address":"Rorschacherstrasse 342",
    "sg:city":"M\u00f6rschwil",
    "sg:orig_category":"Kauf U Verkauf von Immobilien auf eigene Rechnung",
    "sg:phone":"+41 71 245 81 42",
    "sg:postcode":"9402",
    "sg:province":"St. Gallen",
    "wof:name":"Litho-san Ag",
    "wof:placetype":"venue"
},
  "geometry": {"coordinates":[9.4225225449,47.4542236328],"type":"Point"}
}