{
  "type": "Feature",
  "properties": {
    "iso:country":"CH",
    "sg:address":"Rue De La Gare",
    "sg:city":"Vernayaz",
    "sg:orig_category":"Non-Classified Establishments",
    "sg:postcode":"1904",
    "sg:province":"Valais",
    "wof:name":"Denis Delcey",
    "wof:placetype":"venue"
},
  "geometry": {"coordinates":[7.0397891998,46.1404876709],"type":"Point"}
}