{
  "type": "Feature",
  "properties": {
    "iso:country":"CH",
    "sg:address":"Industriestrasse 50a 8304 Wallisellen. Postfach",
    "sg:city":"Wallisellen",
    "sg:orig_category":"Markt U Meinungsforschung",
    "sg:phone":"+41 18773535",
    "sg:postcode":"8304",
    "sg:province":"Z\u00fcrich",
    "wof:name":"Ferring International Center Ag Koordination Der Produktion, Des Marketings Und Verkaufs Innerhalb Der Gesellschaften Usw",
    "wof:placetype":"venue"
},
  "geometry": {"coordinates":[8.5939188004,47.4097557068],"type":"Point"}
}