{
  "type": "Feature",
  "properties": {
    "iso:country":"CH",
    "sg:address":"Z\u00fcrcherstrasse 47",
    "sg:city":"Lachen",
    "sg:classifiers":[
        {
            "category":"Manufacturing",
            "subcategory":"Wood Products",
            "type":"Manufacturing & Wholesale Goods"
        }
    ],
    "sg:phone":"+41 55 442 11 51",
    "sg:postcode":"8853",
    "sg:province":"Schwyz",
    "sg:tags":[
        "firewood"
    ],
    "wof:name":"Karl Risi S\u00e4ge-, Spalt- Und Hobelwerk",
    "wof:placetype":"venue"
},
  "geometry": {"coordinates":[8.845142,47.190613],"type":"Point"}
}