{
  "type": "Feature",
  "properties": {
    "iso:country":"CH",
    "sg:address":"Immenstall 15",
    "sg:city":"Ermatingen",
    "sg:orig_category":"Herstellung von medizinischen U chirurgischen Ger\u00e4ten sowie orthop\u00e4dischen Vorrichtungen",
    "sg:phone":"+41 71 664 28 01",
    "sg:postcode":"8272",
    "sg:province":"Thurgau",
    "wof:name":"Medizin-technik, Frau Meier Iris",
    "wof:placetype":"venue"
},
  "geometry": {"coordinates":[9.0893220901,47.6644058228],"type":"Point"}
}