{
  "type": "Feature",
  "properties": {
    "iso:country":"CH",
    "sg:address":"Bauertacherstrasse 12a",
    "sg:city":"St\u00e4fa",
    "sg:orig_category":"Siebdruck",
    "sg:phone":"+41 19266122",
    "sg:postcode":"8712",
    "sg:province":"Z\u00fcrich",
    "wof:name":"Max Rey Siebdruck",
    "wof:placetype":"venue"
},
  "geometry": {"coordinates":[8.7217130661,47.2509613037],"type":"Point"}
}