{
  "type": "Feature",
  "properties": {
    "iso:country":"CH",
    "sg:address":"St. Wolfgangstrasse 18",
    "sg:city":"Balsthal",
    "sg:orig_category":"Zahnarztpraxen",
    "sg:phone":"+41 62 391 13 13",
    "sg:postcode":"4710",
    "sg:province":"Solothurn",
    "wof:name":"Dr. Med. Dent. Rudolf Galasse Zahnarzt",
    "wof:placetype":"venue"
},
  "geometry": {"coordinates":[7.7006092072,47.3197898865],"type":"Point"}
}