{
  "type": "Feature",
  "properties": {
    "addr:full":"Hirschengasse 10 Appenzell Appenzell Innerhoden 9050",
    "addr:housenumber":"10",
    "addr:postcode":"9050",
    "addr:street":"Hirschengasse",
    "iso:country":"CH",
    "sg:address":"Hirschengasse 10",
    "sg:city":"Appenzell",
    "sg:orig_category":"Detailhandel mit Antiquit\u00e4ten U Gebrauchtwaren in Verkaufsr\u00e4umen",
    "sg:postcode":"9050",
    "sg:province":"Appenzell Innerhoden",
    "wof:name":"Caton Gmbh",
    "wof:placetype":"venue"
},
  "geometry": {"coordinates":[9.408705,47.330238],"type":"Point"}
}