{
  "type": "Feature",
  "properties": {
    "iso:country":"CH",
    "sg:address":"Route Des Avouillons 4 1196 Gland Case Postale 212",
    "sg:city":"Gland",
    "sg:orig_category":"Gesundheitswesen Sonstiger Grosshandel",
    "sg:phone":"+41 22 738 32 32",
    "sg:postcode":"1196",
    "sg:province":"Vaud",
    "wof:name":"Sms - Safety Management Systems",
    "wof:placetype":"venue"
},
  "geometry": {"coordinates":[6.2690029144,46.4162101746],"type":"Point"}
}