{
  "type": "Feature",
  "properties": {
    "addr:full":"1247 Ani\u00e8res Gen\u00e8ve 1247",
    "addr:housenumber":"1247",
    "addr:postcode":"1247",
    "addr:street":"Anie\u0300Res",
    "iso:country":"CH",
    "sg:address":"1247",
    "sg:city":"Ani\u00e8res",
    "sg:orig_category":"Architekturb\u00fcros",
    "sg:phone":"+41 22 751 09 88",
    "sg:postcode":"1247",
    "sg:province":"Gen\u00e8ve",
    "wof:name":"Claude Suter Sa Bureau D'architecture",
    "wof:placetype":"venue"
},
  "geometry": {"coordinates":[6.224495,46.275982],"type":"Point"}
}