{
  "type": "Feature",
  "properties": {
    "iso:country":"CH",
    "sg:address":"Blumenweg 3",
    "sg:city":"Attiswil",
    "sg:orig_category":"D\u00e4mmung gegen K\u00e4lte, W\u00e4rme, Schall U Ersch\u00fctterung",
    "sg:phone":"+41 32 637 20 27",
    "sg:postcode":"4536",
    "sg:province":"Bern",
    "wof:name":"Walter Jost Fugendichtungen & Montagen",
    "wof:placetype":"venue"
},
  "geometry": {"coordinates":[7.6179437637,47.2487945557],"type":"Point"}
}