{
  "type": "Feature",
  "properties": {
    "iso:country":"CH",
    "sg:address":"Madretschstrasse 35 2503 Biel/bienne. Postfach",
    "sg:city":"Biel/bienne",
    "sg:orig_category":"Grafikateliers, Design",
    "sg:phone":"+41 32 365 27 06",
    "sg:postcode":"2502",
    "sg:province":"Bern",
    "wof:name":"Globeline Internetsolutions",
    "wof:placetype":"venue"
},
  "geometry": {"coordinates":[7.2531871796,47.1328392029],"type":"Point"}
}