{
  "type": "Feature",
  "properties": {
    "addr:full":"Leuengasse 22 Lenzburg Aargau 5600",
    "addr:housenumber":"22",
    "addr:postcode":"5600",
    "addr:street":"Leuengasse",
    "iso:country":"CH",
    "sg:address":"Leuengasse 22",
    "sg:city":"Lenzburg",
    "sg:orig_category":"Detailhandel mit B\u00fcromaschinen U einrichtungen",
    "sg:phone":"+41 62 892 95 55",
    "sg:postcode":"5600",
    "sg:province":"Aargau",
    "wof:name":"Kms B\u00fcromaschinen Maurer B.",
    "wof:placetype":"venue"
},
  "geometry": {"coordinates":[8.181715,47.387444],"type":"Point"}
}