{
  "type": "Feature",
  "properties": {
    "iso:country":"CH",
    "sg:address":"3963",
    "sg:city":"Crans-sur-sierre",
    "sg:orig_category":"Detailhandel mit Antiquit\u00e4ten",
    "sg:phone":"+41 27 481 52 89",
    "sg:postcode":"3963",
    "sg:province":"Valais",
    "wof:name":"Rosemonde De Croon Mayfair Antiquit\u00e9s",
    "wof:placetype":"venue"
},
  "geometry": {"coordinates":[7.46177,46.307621],"type":"Point"}
}