{
  "type": "Feature",
  "properties": {
    "iso:country":"CH",
    "sg:address":"Muttenzerstrasse 2",
    "sg:city":"Birsfelden",
    "sg:classifiers":[
        {
            "category":"Utilities",
            "subcategory":"Electric",
            "type":"Services"
        }
    ],
    "sg:phone":"+41 61 313 27 52",
    "sg:postcode":"4127",
    "sg:province":"Basel-Landschaft",
    "sg:tags":[
        "wheelchair"
    ],
    "wof:name":"Diamex Ag",
    "wof:placetype":"venue"
},
  "geometry": {"coordinates":[7.6238517761,47.5518417358],"type":"Point"}
}