{
  "type": "Feature",
  "properties": {
    "iso:country":"CH",
    "sg:address":"Rauchemur 2802 Develier. Postfach",
    "sg:city":"Develier",
    "sg:orig_category":"Unclassifiable Establishments",
    "sg:postcode":"2802",
    "sg:province":"Jura",
    "wof:name":"Start-finance Holding S\u00e0rl",
    "wof:placetype":"venue"
},
  "geometry": {"coordinates":[7.302880764,47.3618507385],"type":"Point"}
}