{
  "type": "Feature",
  "properties": {
    "iso:country":"CH",
    "sg:address":"Meierh\u00f6fliring 3 6017 Ruswil. Postfach",
    "sg:city":"Ruswil",
    "sg:orig_category":"Herstellung von Konstruktionsteilen, Fertigbauteilen U Ausbauelementen aus Holz",
    "sg:postcode":"6017",
    "sg:province":"Luzern",
    "wof:name":"T\u00fcremat Ag",
    "wof:placetype":"venue"
},
  "geometry": {"coordinates":[8.1354122162,47.0839271545],"type":"Point"}
}