{
  "type": "Feature",
  "properties": {
    "iso:country":"CH",
    "sg:address":"Avenue De Lavaux 36 1009 Pully Case Postale 198",
    "sg:city":"Pully",
    "sg:orig_category":"Einbau von Schreinerwaren",
    "sg:phone":"+41 21 728 32 44",
    "sg:postcode":"1009",
    "sg:province":"Vaud",
    "wof:name":"Imco-waterless Sa Agencements De Cuisines",
    "wof:placetype":"venue"
},
  "geometry": {"coordinates":[6.6583919525,46.5123062134],"type":"Point"}
}