{
  "type": "Feature",
  "properties": {
    "iso:country":"CH",
    "sg:address":"Widenholzstrasse 4 8305 Dietlikon. Postfach",
    "sg:city":"Dietlikon",
    "sg:orig_category":"Autogaragen",
    "sg:phone":"+41 18334957",
    "sg:postcode":"8305",
    "sg:province":"Z\u00fcrich",
    "wof:name":"Kurt Busslinger Garage",
    "wof:placetype":"venue"
},
  "geometry": {"coordinates":[8.615645,47.411953],"type":"Point"}
}