{
  "type": "Feature",
  "properties": {
    "iso:country":"CH",
    "sg:address":"Baselstrasse 19",
    "sg:city":"Dagmersellen",
    "sg:orig_category":"Detailhandel mit M\u00f6beln U Haushaltsgegenst\u00e4nden Detailhandel mit Textilien",
    "sg:phone":"+41 62 756 12 15",
    "sg:postcode":"6252",
    "sg:province":"Luzern",
    "wof:name":"Kronenberg Lina",
    "wof:placetype":"venue"
},
  "geometry": {"coordinates":[7.9867181778,47.2144393921],"type":"Point"}
}