{
  "type": "Feature",
  "properties": {
    "iso:country":"CH",
    "sg:address":"Rotenwies 2 9056 Gais. Postfach",
    "sg:city":"Gais",
    "sg:orig_category":"Pensionskassen",
    "sg:phone":"+41 71 791 07 20",
    "sg:postcode":"9056",
    "sg:province":"Appenzell Ausserrhoden",
    "wof:name":"Personalf\u00fcrsorgestiftung Der Firma Eisenhut & Co Ag",
    "wof:placetype":"venue"
},
  "geometry": {"coordinates":[9.460859,47.365276],"type":"Point"}
}