{
  "type": "Feature",
  "properties": {
    "iso:country":"CH",
    "sg:address":"Tour-ma\u00eetresse Rue De La 4 1204 Gen\u00e8ve. Postfach",
    "sg:city":"Gen\u00e8ve",
    "sg:orig_category":"RESTAURANTS: TEA-ROOMS",
    "sg:phone":"+41 21 944 54 33",
    "sg:postcode":"1201",
    "sg:province":"Gen\u00e8ve",
    "wof:name":"Pin's Bar, Loubet Anne-lise Et Isabella Fernand",
    "wof:placetype":"venue"
},
  "geometry": {"coordinates":[6.8555250168,46.4543266296],"type":"Point"}
}