{
  "type": "Feature",
  "properties": {
    "iso:country":"CH",
    "sg:address":"Unterdorf",
    "sg:city":"Illhart",
    "sg:orig_category":"G\u00fcterbef\u00f6rderung im Strassenverkehr",
    "sg:phone":"+41 52 763 30 80",
    "sg:postcode":"8558",
    "sg:province":"Thurgau",
    "wof:name":"Edi B\u00fchler Transporte",
    "wof:placetype":"venue"
},
  "geometry": {"coordinates":[9.0388126373,47.6168212891],"type":"Point"}
}