{
  "type": "Feature",
  "properties": {
    "iso:country":"CH",
    "sg:address":"Rigiweg 3",
    "sg:city":"Rotkreuz",
    "sg:orig_category":"Instandhaltung U Reparatur von Automobilen",
    "sg:postcode":"6343",
    "sg:province":"Zug",
    "wof:name":"Garage Hans Peter Dummermuth",
    "wof:placetype":"venue"
},
  "geometry": {"coordinates":[7.6589541435,46.7946090698],"type":"Point"}
}