{
  "type": "Feature",
  "properties": {
    "addr:full":"G\u00e4ssli 6a 7000 Chur. Postfach 19 Chur Graubunden 7001",
    "addr:housenumber":"6a;19;7001",
    "addr:postcode":"7000",
    "addr:street":"Gaessli;Postfach",
    "iso:country":"CH",
    "sg:address":"G\u00e4ssli 6a 7000 Chur. Postfach 19",
    "sg:city":"Chur",
    "sg:orig_category":"Arbeitnehmerverb\u00e4nde",
    "sg:phone":"+41 81 353 51 59",
    "sg:postcode":"7001",
    "sg:province":"Graubunden",
    "wof:name":"Verband Schweiz.postbeamter",
    "wof:placetype":"venue"
},
  "geometry": {"coordinates":[9.531171,46.850197],"type":"Point"}
}