{
  "type": "Feature",
  "properties": {
    "iso:country":"CH",
    "sg:address":"Le Muveran 1884 Villars-sur-ollon. Postfach",
    "sg:city":"Villars-sur-ollon",
    "sg:orig_category":"Non-Classified Establishments",
    "sg:postcode":"1884",
    "sg:province":"Vaud",
    "wof:name":"Si Saint Jean Bosquet",
    "wof:placetype":"venue"
},
  "geometry": {"coordinates":[6.1406159401,46.1853218079],"type":"Point"}
}