{
  "type": "Feature",
  "properties": {
    "iso:country":"CH",
    "sg:address":"Althardstrasse 257",
    "sg:city":"Regensdorf",
    "sg:orig_category":"G\u00fcterbef\u00f6rderung im Strassenverkehr",
    "sg:phone":"+41 55 410 33 00",
    "sg:postcode":"8105",
    "sg:province":"Z\u00fcrich",
    "wof:name":"Wessner Peter, M\u00f6beltransporte",
    "wof:placetype":"venue"
},
  "geometry": {"coordinates":[8.7756347656,47.1977844238],"type":"Point"}
}