{
  "type": "Feature",
  "properties": {
    "iso:country":"CH",
    "sg:address":"Oberriedenstrasse 65",
    "sg:city":"Gebenstorf",
    "sg:orig_category":"Sonstige mit der Informatik verbundene T\u00e4tigkeiten",
    "sg:postcode":"5412",
    "sg:province":"Aargau",
    "wof:name":"Lawrence Edp Consulting",
    "wof:placetype":"venue"
},
  "geometry": {"coordinates":[8.2314834595,47.4769363403],"type":"Point"}
}