{
  "type": "Feature",
  "properties": {
    "addr:full":"Hubelstrasse 244 Arosa Graubunden 7050",
    "addr:housenumber":"244",
    "addr:postcode":"7050",
    "addr:street":"Hubelstrasse;Graubunden",
    "iso:country":"CH",
    "sg:address":"Hubelstrasse 244",
    "sg:city":"Arosa",
    "sg:orig_category":"Bauspenglerei Zimmerei, Dachdeckerei, Bauspenglerei U Abdichtung",
    "sg:phone":"+41 61 811 54 00",
    "sg:postcode":"7050",
    "sg:province":"Graubunden",
    "wof:name":"Waldmeier Werner Ag",
    "wof:placetype":"venue"
},
  "geometry": {"coordinates":[7.715163,47.535141],"type":"Point"}
}