{
  "type": "Feature",
  "properties": {
    "iso:country":"CH",
    "sg:address":"Kleinweid 5",
    "sg:city":"Cham",
    "sg:orig_category":"Zahnarztpraxen",
    "sg:phone":"+41 41 780 21 22",
    "sg:postcode":"6330",
    "sg:province":"Zug",
    "wof:name":"Dr. Med. Dent. Frank Hobi Zahnarzt",
    "wof:placetype":"venue"
},
  "geometry": {"coordinates":[8.4517841339,47.1799163818],"type":"Point"}
}