{
  "type": "Feature",
  "properties": {
    "iso:country":"CH",
    "sg:address":"Forgerons Rue Des 14",
    "sg:city":"Fribourg",
    "sg:orig_category":"Maler U Glasergewerbe",
    "sg:postcode":"1700",
    "sg:province":"Fribourg",
    "wof:name":"Stoll Hans-ruedi",
    "wof:placetype":"venue"
},
  "geometry": {"coordinates":[7.1696949005,46.8047447205],"type":"Point"}
}