{
  "type": "Feature",
  "properties": {
    "iso:country":"CH",
    "sg:address":"2610 St-imier Case Postale 1",
    "sg:city":"St-imier",
    "sg:orig_category":"Herstellung von sonstigen Maschinen f\u00fcr unspezifische Verwendung",
    "sg:phone":"+41 32 942 84 50",
    "sg:postcode":"2610",
    "sg:province":"Bern",
    "wof:name":"Arcomec Sa",
    "wof:placetype":"venue"
},
  "geometry": {"coordinates":[6.9958171844,47.1520423889],"type":"Point"}
}