{
  "type": "Feature",
  "properties": {
    "iso:country":"CH",
    "sg:address":"R\u00f6merg\u00e4ssli 6 2502 Biel/bienne. Postfach",
    "sg:city":"Biel/bienne",
    "sg:orig_category":"Interessenvertretungen",
    "sg:postcode":"2502",
    "sg:province":"Bern",
    "wof:name":"Genossenschaft Progressiahaus",
    "wof:placetype":"venue"
},
  "geometry": {"coordinates":[7.2457809448,47.1419677734],"type":"Point"}
}