{
  "type": "Feature",
  "properties": {
    "iso:country":"CH",
    "sg:address":"Hauptstrasse 15 8259 Kaltenbach. Postfach",
    "sg:city":"Kaltenbach",
    "sg:orig_category":"Herstellung von sonstigen organischen Grundstoffen U Chemikalien",
    "sg:phone":"+41 52 742 00 15",
    "sg:postcode":"8259",
    "sg:province":"Thurgau",
    "wof:name":"Suchema Ag",
    "wof:placetype":"venue"
},
  "geometry": {"coordinates":[8.8466968536,47.6518974304],"type":"Point"}
}