{
  "type": "Feature",
  "properties": {
    "iso:country":"CH",
    "sg:address":"Bahnhofstrasse 26",
    "sg:city":"Oberrieden",
    "sg:orig_category":"Unternehmensberatung",
    "sg:phone":"+41 17209734",
    "sg:postcode":"8942",
    "sg:province":"Z\u00fcrich",
    "wof:name":"Stucki Unternehmensberatung",
    "wof:placetype":"venue"
},
  "geometry": {"coordinates":[8.5789299011,47.2804069519],"type":"Point"}
}