{
  "type": "Feature",
  "properties": {
    "iso:country":"CH",
    "sg:address":"Zeughausstrasse 69",
    "sg:city":"Z\u00fcrich",
    "sg:orig_category":"Detailhandel mit B\u00fcchern, Zeitungen, Schreib U Papeteriewaren",
    "sg:postcode":"8004",
    "sg:province":"Z\u00fcrich",
    "wof:name":"Kokomiko, L\u00f6hrer Claudio Buchhandlung, Bes. Comics U. Lithographien",
    "wof:placetype":"venue"
},
  "geometry": {"coordinates":[8.528786,47.376667],"type":"Point"}
}