{
  "type": "Feature",
  "properties": {
    "iso:country":"CH",
    "sg:address":"Ebnet",
    "sg:city":"Escholzmatt",
    "sg:orig_category":"Verwertung von Milch",
    "sg:postcode":"6182",
    "sg:province":"Luzern",
    "wof:name":"K\u00e4sereigenossenschaft Wegmatten",
    "wof:placetype":"venue"
},
  "geometry": {"coordinates":[7.9511599541,46.9129066467],"type":"Point"}
}