{
  "type": "Feature",
  "properties": {
    "iso:country":"CH",
    "sg:address":"Brunnmattstrasse 18",
    "sg:city":"Zuchwil",
    "sg:orig_category":"Mechanik Mechanische Werkst\u00e4tten",
    "sg:phone":"+41 32 685 38 25",
    "sg:postcode":"4528",
    "sg:province":"Solothurn",
    "wof:name":"Morand, Walter.",
    "wof:placetype":"venue"
},
  "geometry": {"coordinates":[7.559486866,47.2018928528],"type":"Point"}
}