{
  "type": "Feature",
  "properties": {
    "addr:full":"Ermitagestrasse 9 Arlesheim Basel-Landschaft 4144",
    "addr:housenumber":"9",
    "addr:postcode":"4144",
    "addr:street":"Ermitagestrasse",
    "iso:country":"CH",
    "sg:address":"Ermitagestrasse 9",
    "sg:city":"Arlesheim",
    "sg:orig_category":"Arztpraxen",
    "sg:phone":"+41 71 385 04 14",
    "sg:postcode":"4144",
    "sg:province":"Basel-Landschaft",
    "wof:name":"Dr.med.georges Meyer Arzt F.allgemeine Medizin Fmh",
    "wof:placetype":"venue"
},
  "geometry": {"coordinates":[9.247914,47.414635],"type":"Point"}
}