{
  "type": "Feature",
  "properties": {
    "iso:country":"CH",
    "sg:address":"Riedmattstrasse 5",
    "sg:city":"R\u00fcmlang",
    "sg:orig_category":"Autospenglereien",
    "sg:phone":"+41 800 837 465",
    "sg:postcode":"8153",
    "sg:province":"Z\u00fcrich",
    "wof:name":"Rolf Stocker Carrosserie",
    "wof:placetype":"venue"
},
  "geometry": {"coordinates":[8.52583,47.46114],"type":"Point"}
}