{
  "type": "Feature",
  "properties": {
    "iso:country":"CH",
    "sg:address":"Mittlerer Bielweg 42f",
    "sg:city":"T\u00fcscherz-alferm\u00e9e",
    "sg:orig_category":"Herstellung von Reiseartikeln, Leder U Sattlerwaren Markt U Meinungsforschung",
    "sg:phone":"+41 32 331 85 51",
    "sg:postcode":"2512",
    "sg:province":"Bern",
    "wof:name":"Inter-cr\u00e9ation Ag",
    "wof:placetype":"venue"
},
  "geometry": {"coordinates":[7.2033982277,47.1198005676],"type":"Point"}
}