{
  "type": "Feature",
  "properties": {
    "iso:country":"CH",
    "sg:address":"Spitalackerstrasse 10 3013 Bern. Postfach",
    "sg:city":"Bern",
    "sg:orig_category":"Pensionskassen",
    "sg:postcode":"3005",
    "sg:province":"Bern",
    "wof:name":"F\u00fcrsorge-stiftung Des Rabatt-sparvereins Bern",
    "wof:placetype":"venue"
},
  "geometry": {"coordinates":[7.4583959579,46.9538459778],"type":"Point"}
}