{
  "type": "Feature",
  "properties": {
    "iso:country":"CH",
    "sg:address":"Obgardirain 4",
    "sg:city":"Adligenswil",
    "sg:orig_category":"Architektur U Ingenieurb\u00fcros",
    "sg:postcode":"6043",
    "sg:province":"Luzern",
    "wof:name":"Schmidig Ungerer Gmbh, Zweigniederlassung Adligenswil",
    "wof:placetype":"venue"
},
  "geometry": {"coordinates":[8.361787,47.071144],"type":"Point"}
}