{
  "type": "Feature",
  "properties": {
    "iso:country":"CH",
    "sg:address":"Zentralstr. 16.",
    "sg:city":"Neuhausen",
    "sg:orig_category":"Grosshandel mit sonstigen Nahrungsmitteln Sonstiger Fachdetailhandel mit Nahrungsmitteln, Getr\u00e4nken ",
    "sg:phone":"+41 52 672 68 88",
    "sg:postcode":"8212",
    "sg:province":"Schaffhausen",
    "wof:name":"Reformlade Bernath.",
    "wof:placetype":"venue"
},
  "geometry": {"coordinates":[8.6190948486,47.680721283],"type":"Point"}
}