{
  "type": "Feature",
  "properties": {
    "iso:country":"CH",
    "sg:address":"Route St-pierre 3",
    "sg:city":"Estavayer-le-lac",
    "sg:orig_category":"Grosshandel mit festen Brennstoffen U Mineral\u00f6lerzeugnissen",
    "sg:postcode":"1470",
    "sg:province":"Fribourg",
    "wof:name":"Sev Mazout Broye Sa",
    "wof:placetype":"venue"
},
  "geometry": {"coordinates":[6.8451771736,46.8469543457],"type":"Point"}
}