{
  "type": "Feature",
  "properties": {
    "iso:country":"CH",
    "sg:address":"Rue Adolphe-gandon 3",
    "sg:city":"Courgenay",
    "sg:classifiers":[
        {
            "category":"Insurance",
            "subcategory":"Insurance Agent",
            "type":"Services"
        }
    ],
    "sg:phone":"+41 32 465 92 92",
    "sg:postcode":"2950",
    "sg:province":"Jura",
    "sg:tags":[
        "versicherungsagenturen",
        "-broker"
    ],
    "wof:name":"R\u00e9my Gu\u00e9niat Agence D'ass.mobili\u00e8re Suisse",
    "wof:placetype":"venue"
},
  "geometry": {"coordinates":[7.126388073,47.4036064148],"type":"Point"}
}