{
  "type": "Feature",
  "properties": {
    "iso:country":"CH",
    "sg:address":"Rte Des Rottes 6",
    "sg:city":"Conthey",
    "sg:classifiers":[
        {
            "category":"Shopping",
            "subcategory":"Hobbies, Toys, & Games",
            "type":"Retail Goods"
        }
    ],
    "sg:phone":"+41 27 345 37 37",
    "sg:postcode":"1964",
    "sg:province":"Valais",
    "sg:tags":[
        "product",
        "miscellaneous",
        "entertainment"
    ],
    "wof:name":"Jumbo Moncor Sa Do-it Deco Garden",
    "wof:placetype":"venue"
},
  "geometry": {"coordinates":[7.2978582382,46.2217941284],"type":"Point"}
}