{
  "type": "Feature",
  "properties": {
    "addr:full":"Industriestrasse 49 Zug Zug 6300",
    "addr:housenumber":"49",
    "addr:postcode":"6300",
    "addr:street":"Industriestrasse;Zug",
    "iso:country":"CH",
    "sg:address":"Industriestrasse 49",
    "sg:city":"Zug",
    "sg:orig_category":"Architektur U Ingenieurb\u00fcros",
    "sg:phone":"+41 41 763 00 70",
    "sg:postcode":"6300",
    "sg:province":"Zug",
    "wof:name":"Jp-finanz Ag",
    "wof:placetype":"venue"
},
  "geometry": {"coordinates":[8.521089,47.182945],"type":"Point"}
}