{
  "type": "Feature",
  "properties": {
    "iso:country":"CH",
    "sg:address":"6537",
    "sg:city":"Grono",
    "sg:orig_category":"Non-Classified Establishments",
    "sg:postcode":"6537",
    "sg:province":"Graubunden",
    "wof:name":"Pacciarelli Emanuele E Luigi",
    "wof:placetype":"venue"
},
  "geometry": {"coordinates":[9.1464338303,46.2478141785],"type":"Point"}
}