{
  "type": "Feature",
  "properties": {
    "iso:country":"CH",
    "sg:address":"Limmatquai 116",
    "sg:city":"Z\u00fcrich",
    "sg:orig_category":"Detailhandel mit Brot, Back U S\u00fcsswaren",
    "sg:phone":"+41 12616937",
    "sg:postcode":"8001",
    "sg:province":"Z\u00fcrich",
    "wof:name":"Kleiner Konditorei-b\u00e4ckerei Ag",
    "wof:placetype":"venue"
},
  "geometry": {"coordinates":[8.543511,47.375294],"type":"Point"}
}