{
  "type": "Feature",
  "properties": {
    "iso:country":"CH",
    "sg:address":"Langnaustrasse 16 3432 L\u00fctzelfl\u00fch-goldb. Postfach 54",
    "sg:city":"L\u00fctzelfl\u00fch-goldb",
    "sg:orig_category":"Grosshandel mit Milch, Milcherzeugnissen, Eiern, Speise\u00f6len U Nahrungsfetten Sonstiger Fachdetailhan",
    "sg:phone":"+41 34 461 16 15",
    "sg:postcode":"3432",
    "sg:province":"Bern",
    "wof:name":"Goldbach + Roth Ag",
    "wof:placetype":"venue"
},
  "geometry": {"coordinates":[7.685172081,47.0023078918],"type":"Point"}
}