{
  "type": "Feature",
  "properties": {
    "iso:country":"CH",
    "sg:address":"Fritz-oppliger-strasse 15 2504 Biel/bienne Case Postale 1144",
    "sg:city":"Biel/bienne",
    "sg:orig_category":"Druck ohne Zeitungsdruck Verlagsgewerbe",
    "sg:phone":"+41 32 465 89 39",
    "sg:postcode":"2501",
    "sg:province":"Bern",
    "wof:name":"Editions Et Imprimerie Le Pays Sa",
    "wof:placetype":"venue"
},
  "geometry": {"coordinates":[7.0758571625,47.4175415039],"type":"Point"}
}