{
  "type": "Feature",
  "properties": {
    "iso:country":"CH",
    "sg:address":"Rathausstrasse 40/42 4410 Liestal. Postfach",
    "sg:city":"Liestal",
    "sg:orig_category":"K\u00fcnstlerische Schulen",
    "sg:phone":"+41 61 921 91 45",
    "sg:postcode":"4410",
    "sg:province":"Basel-Landschaft",
    "wof:name":"Reg. Jugendmusikschule Liestal Sekretariat",
    "wof:placetype":"venue"
},
  "geometry": {"coordinates":[7.7348461151,47.4841003418],"type":"Point"}
}