{
  "type": "Feature",
  "properties": {
    "iso:country":"CH",
    "sg:address":"M\u00fclisacker 222",
    "sg:city":"Hallwil",
    "sg:orig_category":"Instandhaltung U Reparatur von Automobilen",
    "sg:phone":"+41 79 642 63 75",
    "sg:postcode":"5705",
    "sg:province":"Aargau",
    "wof:name":"M\u00fchle-garage Kocer H\u00fcseyin",
    "wof:placetype":"venue"
},
  "geometry": {"coordinates":[8.1720142365,47.3338661194],"type":"Point"}
}