{
  "type": "Feature",
  "properties": {
    "iso:country":"CH",
    "sg:address":"Spielwiese 12 8854 Galgenen. Postfach",
    "sg:city":"Galgenen",
    "sg:orig_category":"Sonstige mit der Informatik verbundene T\u00e4tigkeiten",
    "sg:postcode":"8854",
    "sg:province":"Schwyz",
    "wof:name":"Meier Software Engineering Informatik-dienstleistungen",
    "wof:placetype":"venue"
},
  "geometry": {"coordinates":[8.8753538132,47.1796035767],"type":"Point"}
}