{
  "type": "Feature",
  "properties": {
    "iso:country":"CH",
    "sg:address":"Grossm\u00fcnsterplatz 9 8001 Z\u00fcrich. Postfach",
    "sg:city":"Z\u00fcrich",
    "sg:orig_category":"Hochschulen U h\u00f6here Ausbildung",
    "sg:postcode":"8001",
    "sg:province":"Z\u00fcrich",
    "wof:name":"Bs B&f Business School Of Banking & Finance Business School, Aus- U. Weiterbildungsinstitutionen Usw",
    "wof:placetype":"venue"
},
  "geometry": {"coordinates":[8.5436477661,47.3699302673],"type":"Point"}
}