{
  "type": "Feature",
  "properties": {
    "iso:country":"CH",
    "sg:address":"Luzernerring 95 4056 Basel. Postfach",
    "sg:city":"Basel",
    "sg:orig_category":"Geb\u00e4ude, Wohnungsreinigung",
    "sg:phone":"+41 61 321 03 31",
    "sg:postcode":"4025",
    "sg:province":"Basel-Stadt",
    "wof:name":"E. Schelker & Sohn Ag Hauswartung, Reinigung, Gartenpflege Usw.",
    "wof:placetype":"venue"
},
  "geometry": {"coordinates":[7.5673699379,47.5682144165],"type":"Point"}
}