{
  "type": "Feature",
  "properties": {
    "iso:country":"CH",
    "sg:address":"Rue They 1",
    "sg:city":"Territet-veytaux",
    "sg:orig_category":"Berufsberatungen",
    "sg:phone":"+41 21 963 33 64",
    "sg:postcode":"1820",
    "sg:province":"Vaud",
    "wof:name":"Orientation Professionnelle",
    "wof:placetype":"venue"
},
  "geometry": {"coordinates":[6.928599,46.419296],"type":"Point"}
}