{
  "type": "Feature",
  "properties": {
    "iso:country":"CH",
    "sg:address":"Chemin Des Fours 4 1223 Cologny Case Postale 88",
    "sg:city":"Cologny",
    "sg:orig_category":"Detailhandel mit Blumen U Pflanzen Fachdetailhandel in Verkaufsr\u00e4umen",
    "sg:phone":"+41 22 736 92 02",
    "sg:postcode":"1223",
    "sg:province":"Gen\u00e8ve",
    "wof:name":"Marcelle Becler Cologny-fleurs",
    "wof:placetype":"venue"
},
  "geometry": {"coordinates":[6.18312,46.217136],"type":"Point"}
}