{
  "type": "Feature",
  "properties": {
    "iso:country":"CH",
    "sg:address":"Neuhauserstrasse 101",
    "sg:city":"Frauenfeld",
    "sg:orig_category":"Wirtschaftsverb\u00e4nde Informatik",
    "sg:phone":"+41 21 636 32 39",
    "sg:postcode":"8500",
    "sg:province":"Thurgau",
    "wof:name":"Clusis Assoc.suisse De La S\u00e9curit\u00e9 Informatique",
    "wof:placetype":"venue"
},
  "geometry": {"coordinates":[6.5860791206,46.5377807617],"type":"Point"}
}