{
  "type": "Feature",
  "properties": {
    "iso:country":"CH",
    "sg:address":"Beckenhofstrasse 16",
    "sg:city":"Z\u00fcrich",
    "sg:orig_category":"Sonstige pers\u00f6nliche Dienstleistungen",
    "sg:postcode":"8006",
    "sg:province":"Z\u00fcrich",
    "wof:name":"Katholischer Bekanntschaftsring",
    "wof:placetype":"venue"
},
  "geometry": {"coordinates":[8.5421590805,47.3836135864],"type":"Point"}
}