{
  "type": "Feature",
  "properties": {
    "iso:country":"CH",
    "sg:address":"H\u00fcgelweg 10",
    "sg:city":"Luzern",
    "sg:orig_category":"Sportvereine Wassersport Segeln",
    "sg:phone":"+41 41 360 62 06",
    "sg:postcode":"6005",
    "sg:province":"Luzern",
    "wof:name":"Jollen-vereinig.luzern Jvl",
    "wof:placetype":"venue"
},
  "geometry": {"coordinates":[8.3143730164,47.037776947],"type":"Point"}
}