{
  "type": "Feature",
  "properties": {
    "iso:country":"CH",
    "sg:address":"Chemin Des Longs-pr\u00e9s 28",
    "sg:city":"Bernex",
    "sg:orig_category":"Detailhandel mit Metallwaren, Anstrichmitteln, Glaswaren, Bau U Heimwerkerbedarf",
    "sg:postcode":"1233",
    "sg:province":"Gen\u00e8ve",
    "wof:name":"Microboum, Baumgartner J.-c.",
    "wof:placetype":"venue"
},
  "geometry": {"coordinates":[6.2226071358,46.6013870239],"type":"Point"}
}