{
  "type": "Feature",
  "properties": {
    "iso:country":"CH",
    "sg:address":"Althardstrasse 185",
    "sg:city":"Regensdorf",
    "sg:orig_category":"Institutionen des Sozialwesens ohne Beherbergung",
    "sg:phone":"+41 17374237",
    "sg:postcode":"8105",
    "sg:province":"Z\u00fcrich",
    "wof:name":"Inresa Gmbh",
    "wof:placetype":"venue"
},
  "geometry": {"coordinates":[8.4358453751,47.352191925],"type":"Point"}
}