{
  "type": "Feature",
  "properties": {
    "addr:full":"Haselstrasse 1 Baden Aargau 5400",
    "addr:housenumber":"1",
    "addr:postcode":"5400",
    "addr:street":"Haselstrasse",
    "iso:country":"CH",
    "sg:address":"Haselstrasse 1",
    "sg:city":"Baden",
    "sg:orig_category":"Architektur U Ingenieurb\u00fcros",
    "sg:phone":"+41 19772989",
    "sg:postcode":"5400",
    "sg:province":"Aargau",
    "wof:name":"Sulser P. Gmbh F\u00fcr Baubiologie Und Schallschutz",
    "wof:placetype":"venue"
},
  "geometry": {"coordinates":[8.84353,47.30233],"type":"Point"}
}