{
  "type": "Feature",
  "properties": {
    "iso:country":"CH",
    "sg:address":"Immeuble Continental A 3963 Crans-sur-sierre Case Postale 108",
    "sg:city":"Crans-sur-sierre",
    "sg:orig_category":"Wirtschaftspr\u00fcfung, Steuerberatung U Treuhand",
    "sg:phone":"+41 27 481 76 66",
    "sg:postcode":"3963",
    "sg:province":"Valais",
    "wof:name":"Fiduciaire Fidag Sa, Succursale De Crans-montana",
    "wof:placetype":"venue"
},
  "geometry": {"coordinates":[7.4691519737,46.3059539795],"type":"Point"}
}