{
  "type": "Feature",
  "properties": {
    "iso:country":"CH",
    "sg:address":"Bifangstrasse 10",
    "sg:city":"Sumiswald",
    "sg:orig_category":"Architektur U Ingenieurb\u00fcros",
    "sg:phone":"+41 34 431 26 12",
    "sg:postcode":"3454",
    "sg:province":"Bern",
    "wof:name":"Eugen Kramer Ingenieurb\u00fcro",
    "wof:placetype":"venue"
},
  "geometry": {"coordinates":[7.750267,47.034428],"type":"Point"}
}