{
  "type": "Feature",
  "properties": {
    "iso:country":"CH",
    "sg:address":"Chemin Des Rottaz 1816 Chailly-montreux Case Postale 51",
    "sg:city":"Chailly-montreux",
    "sg:orig_category":"Instandhaltung U Reparatur von Automobilen",
    "sg:phone":"+41 21 964 64 71",
    "sg:postcode":"1816",
    "sg:province":"Vaud",
    "wof:name":"Jean-pierre Nafzger & Fils Garage Des Bonnettes",
    "wof:placetype":"venue"
},
  "geometry": {"coordinates":[6.8992538452,46.452003479],"type":"Point"}
}