{
  "type": "Feature",
  "properties": {
    "iso:country":"CH",
    "sg:address":"Rte Fayards 60",
    "sg:city":"Collex",
    "sg:classifiers":[
        {
            "category":"Autos & Motor Vehicles",
            "subcategory":"Automobile Sales",
            "type":"Retail Goods"
        }
    ],
    "sg:phone":"+41 22 774 11 55",
    "sg:postcode":"1239",
    "sg:province":"Gen\u00e8ve",
    "sg:tags":[
        "equipment",
        "industrial",
        "transport"
    ],
    "wof:name":"Umm Unites Medicales Mobiles Sa",
    "wof:placetype":"venue"
},
  "geometry": {"coordinates":[6.1250801086,46.2722396851],"type":"Point"}
}