{
  "type": "Feature",
  "properties": {
    "iso:country":"CH",
    "sg:address":"Neubr\u00fcckstrasse 106 3012 Bern. Postfach",
    "sg:city":"Bern",
    "sg:orig_category":"Vermietung U Verpachtung von eigenen Immobilien",
    "sg:phone":"+41 31 302 85 85",
    "sg:postcode":"3005",
    "sg:province":"Bern",
    "wof:name":"Wylerholz-immobilien Ag Immobilien Usw.",
    "wof:placetype":"venue"
},
  "geometry": {"coordinates":[7.4357128143,46.9594192505],"type":"Point"}
}