{
  "type": "Feature",
  "properties": {
    "iso:country":"CH",
    "sg:address":"5042",
    "sg:city":"Hirschthal",
    "sg:orig_category":"Sportvereine Sch\u00fctzen",
    "sg:postcode":"5042",
    "sg:province":"Aargau",
    "wof:name":"Sch\u00fctzengesellschaft",
    "wof:placetype":"venue"
},
  "geometry": {"coordinates":[8.0659999847,47.3176193237],"type":"Point"}
}