{
  "type": "Feature",
  "properties": {
    "iso:country":"CH",
    "sg:address":"Erlenstrasse 13",
    "sg:city":"Emmenbr\u00fccke",
    "sg:orig_category":"Vereine Gesang",
    "sg:phone":"+41 41 260 00 07",
    "sg:postcode":"6020",
    "sg:province":"Luzern",
    "wof:name":"S\u00e4ngerbund Emmen/emmenbr\u00fccke",
    "wof:placetype":"venue"
},
  "geometry": {"coordinates":[8.2708120346,47.079410553],"type":"Point"}
}