{
  "type": "Feature",
  "properties": {
    "iso:country":"CH",
    "sg:address":"Eichtalstrasse 23",
    "sg:city":"Hombrechtikon",
    "sg:orig_category":"Vorschulen, Kinderg\u00e4rten",
    "sg:phone":"+41 34 437 13 55",
    "sg:postcode":"8634",
    "sg:province":"Z\u00fcrich",
    "wof:name":"Kindergarten Gm\u00fcnden",
    "wof:placetype":"venue"
},
  "geometry": {"coordinates":[7.7976818085,47.041683197],"type":"Point"}
}