{
  "type": "Feature",
  "properties": {
    "iso:country":"CH",
    "sg:address":"St. Ulrichweg 16",
    "sg:city":"Strengelbach",
    "sg:orig_category":"G\u00fcterbef\u00f6rderung im Strassenverkehr Sonstige pers\u00f6nliche Dienstleistungen",
    "sg:phone":"+41 55 283 45 88",
    "sg:postcode":"4802",
    "sg:province":"Aargau",
    "wof:name":"Ernst V\u00f6geli Chauffeur-dienste",
    "wof:placetype":"venue"
},
  "geometry": {"coordinates":[9.0454998016,47.2270812988],"type":"Point"}
}