{
  "type": "Feature",
  "properties": {
    "iso:country":"CH",
    "sg:address":"Huebstrasse 7",
    "sg:city":"M\u00f6rschwil",
    "sg:orig_category":"Herstellung von Duft U K\u00f6rperpflegemitteln",
    "sg:phone":"+41 71 866 15 83",
    "sg:postcode":"9402",
    "sg:province":"St. Gallen",
    "wof:name":"Alve-center Theler",
    "wof:placetype":"venue"
},
  "geometry": {"coordinates":[9.4179935455,47.473274231],"type":"Point"}
}