{
  "type": "Feature",
  "properties": {
    "iso:country":"CH",
    "sg:address":"Dornacherstrasse 122",
    "sg:city":"Basel",
    "sg:orig_category":"Vorschulen, Kinderg\u00e4rten",
    "sg:phone":"+41 61 361 38 30",
    "sg:postcode":"4053",
    "sg:province":"Basel-Stadt",
    "wof:name":"Kindergarten",
    "wof:placetype":"venue"
},
  "geometry": {"coordinates":[7.5901479721,47.5428924561],"type":"Point"}
}