{
  "type": "Feature",
  "properties": {
    "iso:country":"CH",
    "sg:address":"Tatroz 1612 Ecoteaux. Postfach",
    "sg:city":"Ecoteaux",
    "sg:orig_category":"S\u00e4ge, Hobel U Holzimpr\u00e4gnierwerke",
    "sg:postcode":"1612",
    "sg:province":"Vaud",
    "wof:name":"Scierie Beaud Bernard",
    "wof:placetype":"venue"
},
  "geometry": {"coordinates":[6.8615651131,46.5451965332],"type":"Point"}
}