{
  "type": "Feature",
  "properties": {
    "iso:country":"CH",
    "sg:address":"Tramstrasse 111",
    "sg:city":"Suhr",
    "sg:orig_category":"Grosshandel mit Getr\u00e4nken",
    "sg:phone":"+41 62 824 21 09",
    "sg:postcode":"5034",
    "sg:province":"Aargau",
    "wof:name":"Zervakis Import",
    "wof:placetype":"venue"
},
  "geometry": {"coordinates":[8.0667543411,47.3868408203],"type":"Point"}
}