{
  "type": "Feature",
  "properties": {
    "iso:country":"CH",
    "sg:address":"Aarbergergasse 19 3000 Bern. Postfach",
    "sg:city":"Bern",
    "sg:orig_category":"Detailhandel mit Bekleidung",
    "sg:postcode":"3005",
    "sg:province":"Bern",
    "wof:name":"Liberty, Ibiza Mode Salman",
    "wof:placetype":"venue"
},
  "geometry": {"coordinates":[7.443111,46.949432],"type":"Point"}
}