{
  "type": "Feature",
  "properties": {
    "iso:country":"CH",
    "sg:address":"Wingertlistrasse 31",
    "sg:city":"Winterthur",
    "sg:orig_category":"Wirtschaftspr\u00fcfung, Steuerberatung U Treuhand",
    "sg:phone":"+41 52 238 14 15",
    "sg:postcode":"8400",
    "sg:province":"Z\u00fcrich",
    "wof:name":"W&g Treuhand Wiederkehr & Co",
    "wof:placetype":"venue"
},
  "geometry": {"coordinates":[8.7603082657,47.488494873],"type":"Point"}
}