{
  "type": "Feature",
  "properties": {
    "iso:country":"CH",
    "sg:address":"Bircher-bennerweg 2",
    "sg:city":"Aarau",
    "sg:orig_category":"Cnc Engraving Workshops, Cnc Engravings",
    "sg:phone":"+41 62 824 52 15",
    "sg:postcode":"5000",
    "sg:province":"Aargau",
    "wof:name":"Graviertechnik Heidersberger",
    "wof:placetype":"venue"
},
  "geometry": {"coordinates":[8.043972,47.388817],"type":"Point"}
}