{
  "type": "Feature",
  "properties": {
    "iso:country":"CH",
    "sg:address":"Chemin Des Ormes 3 1225 Ch\u00eane-bourg. Postfach",
    "sg:city":"Gen\u00e8ve",
    "sg:orig_category":"Sanit\u00e4r, Heizungs U L\u00fcftungsinstallation",
    "sg:postcode":"1205",
    "sg:province":"Gen\u00e8ve",
    "wof:name":"Perrina A.",
    "wof:placetype":"venue"
},
  "geometry": {"coordinates":[6.1948518753,46.1980323792],"type":"Point"}
}