{
  "type": "Feature",
  "properties": {
    "addr:full":"Stalden 3 Fribourg Fribourg 1700",
    "addr:housenumber":"3",
    "addr:postcode":"1700",
    "addr:street":"Stalden",
    "iso:country":"CH",
    "sg:address":"Stalden 3",
    "sg:city":"Fribourg",
    "sg:orig_category":"Architekturb\u00fcros",
    "sg:phone":"+41 26 323 27 58",
    "sg:postcode":"1700",
    "sg:province":"Fribourg",
    "wof:name":"Peter Olexa Bureau D'architecture",
    "wof:placetype":"venue"
},
  "geometry": {"coordinates":[7.165544,46.804951],"type":"Point"}
}