{
  "type": "Feature",
  "properties": {
    "iso:country":"CH",
    "sg:address":"Grande Piazza 51",
    "sg:city":"Giubiasco",
    "sg:orig_category":"Non-Classified Establishments",
    "sg:postcode":"6512",
    "sg:province":"Ticino",
    "wof:name":"Dba Sa Decollogny Broker D'assicurazione",
    "wof:placetype":"venue"
},
  "geometry": {"coordinates":[9.0102539062,46.1711082458],"type":"Point"}
}