{
  "type": "Feature",
  "properties": {
    "iso:country":"CH",
    "sg:address":"Am Guggenberg 20",
    "sg:city":"Z\u00fcrich",
    "sg:orig_category":"Detailhandel mit Metallwaren, Anstrichmitteln, Glaswaren, Bau U Heimwerkerbedarf",
    "sg:phone":"+41 14226640",
    "sg:postcode":"8053",
    "sg:province":"Z\u00fcrich",
    "wof:name":"Vendema",
    "wof:placetype":"venue"
},
  "geometry": {"coordinates":[8.5850076675,47.3569908142],"type":"Point"}
}