{
  "type": "Feature",
  "properties": {
    "addr:full":"Avenue Des Alpes 3 Sierre Valais 3960",
    "addr:housenumber":"3",
    "addr:postcode":"3960",
    "addr:street":"Avenue Des Alpes",
    "iso:country":"CH",
    "sg:address":"Avenue Des Alpes 3",
    "sg:city":"Sierre",
    "sg:orig_category":"Arztpraxen",
    "sg:phone":"+41 27 455 00 52",
    "sg:postcode":"3960",
    "sg:province":"Valais",
    "wof:name":"Dr M\u00e9d. Madeleine Devanth\u00e9ry M\u00e9decin Sp\u00e9cialiste Fmh",
    "wof:placetype":"venue"
},
  "geometry": {"coordinates":[7.530293,46.293255],"type":"Point"}
}