{
  "type": "Feature",
  "properties": {
    "iso:country":"CH",
    "sg:address":"Hinterlohstrasse 23",
    "sg:city":"Romanshorn",
    "sg:orig_category":"Herstellung von K\u00fcchenm\u00f6beln",
    "sg:postcode":"8590",
    "sg:province":"Thurgau",
    "wof:name":"Greminger & Juon, Nachfolger Andrea Juon",
    "wof:placetype":"venue"
},
  "geometry": {"coordinates":[9.3235216141,47.4291763306],"type":"Point"}
}