{
  "type": "Feature",
  "properties": {
    "iso:country":"CH",
    "sg:address":"Rue De Savoie 1950 Sitten. Postfach",
    "sg:city":"Pont-de-la-morge",
    "sg:orig_category":"RESTAURANTS: TEA-ROOMS",
    "sg:postcode":"1962",
    "sg:province":"Valais",
    "wof:name":"Crettenand Marguerite",
    "wof:placetype":"venue"
},
  "geometry": {"coordinates":[7.2086448669,46.1864585876],"type":"Point"}
}