{
  "type": "Feature",
  "properties": {
    "iso:country":"CH",
    "sg:address":"Karolinenheim",
    "sg:city":"Wynigen",
    "sg:orig_category":"Interessenvertretungen",
    "sg:postcode":"3472",
    "sg:province":"Bern",
    "wof:name":"Hansruedi Gloor-stiftung",
    "wof:placetype":"venue"
},
  "geometry": {"coordinates":[7.667828083,47.1060791016],"type":"Point"}
}