{
  "type": "Feature",
  "properties": {
    "iso:country":"CH",
    "sg:address":"Bahnhofstrasse 24",
    "sg:city":"Widnau",
    "sg:orig_category":"Grosshandel mit B\u00fcromaschinen Grosshandel mit Datenverarbeitungsger\u00e4ten",
    "sg:phone":"+41 71 720 04 71",
    "sg:postcode":"9443",
    "sg:province":"St. Gallen",
    "wof:name":"Newa Computer Gmbh",
    "wof:placetype":"venue"
},
  "geometry": {"coordinates":[9.6337432861,47.406085968],"type":"Point"}
}