{
  "type": "Feature",
  "properties": {
    "addr:full":"Chr\u00fcmigstrasse 16 Wimmis Bern 3752",
    "addr:housenumber":"16",
    "addr:postcode":"3752",
    "addr:street":"Chruemigstrasse;Bern",
    "iso:country":"CH",
    "sg:address":"Chr\u00fcmigstrasse 16",
    "sg:city":"Wimmis",
    "sg:orig_category":"Arztpraxen",
    "sg:phone":"+41 33 657 12 12",
    "sg:postcode":"3752",
    "sg:province":"Bern",
    "wof:name":"Dr.med.urs Kamber Spezialarzt Fmh",
    "wof:placetype":"venue"
},
  "geometry": {"coordinates":[7.640668,46.678082],"type":"Point"}
}