{
  "type": "Feature",
  "properties": {
    "iso:country":"CH",
    "sg:address":"Rosenweg",
    "sg:city":"Rothrist",
    "sg:orig_category":"Sportvereine Ballsport Tennis",
    "sg:phone":"+41 31 932 30 00",
    "sg:postcode":"4852",
    "sg:province":"Aargau",
    "wof:name":"Tennis-club Ostermundigen",
    "wof:placetype":"venue"
},
  "geometry": {"coordinates":[7.5616087914,46.9298439026],"type":"Point"}
}