{
  "type": "Feature",
  "properties": {
    "iso:country":"CH",
    "sg:address":"Ch. Des Cressonnex 6",
    "sg:city":"Aire-la-ville",
    "sg:orig_category":"Zimmerei, Dachdeckerei, Bauspenglerei U Abdichtung",
    "sg:phone":"+41 22 757 12 13",
    "sg:postcode":"1288",
    "sg:province":"Gen\u00e8ve",
    "wof:name":"Duvillard Bernard",
    "wof:placetype":"venue"
},
  "geometry": {"coordinates":[6.0430450439,46.1931266785],"type":"Point"}
}