{
  "type": "Feature",
  "properties": {
    "iso:country":"CH",
    "sg:address":"Burenweg 5",
    "sg:city":"Birsfelden",
    "sg:orig_category":"Grosshandel mit Parf\u00fcmerieartikeln U K\u00f6rperpflegemitteln Grosshandel mit medizinischen U orthop\u00e4disc",
    "sg:phone":"+41 61 281 83 23",
    "sg:postcode":"4127",
    "sg:province":"Basel-Landschaft",
    "wof:name":"Aesthetik Vertrieb, Breitenmoser J\u00fcrg",
    "wof:placetype":"venue"
},
  "geometry": {"coordinates":[7.6290259361,47.5442085266],"type":"Point"}
}