{
  "type": "Feature",
  "properties": {
    "iso:country":"CH",
    "sg:address":"K\u00e4rpfstrasse 19",
    "sg:city":"N\u00e4fels",
    "sg:classifiers":[
        {
            "category":"Arena",
            "subcategory":"Sports Club",
            "type":"Entertainment"
        }
    ],
    "sg:phone":"+41 55 612 16 86",
    "sg:postcode":"8752",
    "sg:province":"Glarus",
    "sg:tags":[
        "karate",
        "judo",
        "sportvereine"
    ],
    "wof:name":"Jc Yawara R\u00fcti",
    "wof:placetype":"venue"
},
  "geometry": {"coordinates":[9.060297966,47.0907821655],"type":"Point"}
}