{
  "type": "Feature",
  "properties": {
    "iso:country":"CH",
    "sg:city":"Basel",
    "sg:orig_category":"Finanzen, B\u00f6rse",
    "sg:postcode":"4002",
    "sg:province":"Basel-Stadt",
    "wof:name":"Discount Direct Ag",
    "wof:placetype":"venue"
},
  "geometry": {"coordinates":[7.58053,47.559662],"type":"Point"}
}