{
  "type": "Feature",
  "properties": {
    "iso:country":"CH",
    "sg:address":"Untergober",
    "sg:city":"Doppleschwand",
    "sg:orig_category":"Zimmerei, Dachdeckerei, Bauspenglerei U Abdichtung",
    "sg:postcode":"6112",
    "sg:province":"Luzern",
    "wof:name":"Bieri Holz",
    "wof:placetype":"venue"
},
  "geometry": {"coordinates":[8.0411815643,47.0158042908],"type":"Point"}
}