{
  "type": "Feature",
  "properties": {
    "iso:country":"CH",
    "sg:address":"Hofmattstrasse 12",
    "sg:city":"Herzogenbuchsee",
    "sg:orig_category":"Sonstiger spezialisierter Hoch U Tiefbau",
    "sg:postcode":"3360",
    "sg:province":"Bern",
    "wof:name":"Innotank Gmbh",
    "wof:placetype":"venue"
},
  "geometry": {"coordinates":[7.6993641853,47.1927719116],"type":"Point"}
}