{
  "type": "Feature",
  "properties": {
    "iso:country":"CH",
    "sg:address":"Im Eichen 10",
    "sg:city":"Salenstein",
    "sg:orig_category":"Herstellung von Konstruktionsteilen, Fertigbauteilen U Ausbauelementen aus Holz",
    "sg:postcode":"8268",
    "sg:province":"Thurgau",
    "wof:name":"Bellberg Gmbh Renovation Und Restauration",
    "wof:placetype":"venue"
},
  "geometry": {"coordinates":[9.0668096542,47.6598625183],"type":"Point"}
}