{
  "type": "Feature",
  "properties": {
    "iso:country":"CH",
    "sg:address":"Fabrikstrasse 14 8152 Glattbrugg. Postfach 1072",
    "sg:city":"Opfikon",
    "sg:orig_category":"Allgemeiner Hochbau Maler U Glasergewerbe",
    "sg:phone":"+41 79 236 62 44",
    "sg:postcode":"8152",
    "sg:province":"Z\u00fcrich",
    "wof:name":"Willi Reimers Ag Malerei & Ger\u00fcstbau",
    "wof:placetype":"venue"
},
  "geometry": {"coordinates":[8.565476,47.433914],"type":"Point"}
}