{
  "type": "Feature",
  "properties": {
    "addr:full":"Z\u00fcrcherstrasse 125 Frauenfeld Thurgau 8500",
    "addr:housenumber":"125",
    "addr:postcode":"8500",
    "addr:street":"Zuercherstrasse",
    "iso:country":"CH",
    "sg:address":"Z\u00fcrcherstrasse 125",
    "sg:city":"Frauenfeld",
    "sg:orig_category":"Architektur U Ingenieurb\u00fcros",
    "sg:phone":"+41 52 728 09 99",
    "sg:postcode":"8500",
    "sg:province":"Thurgau",
    "wof:name":"Antoniol, Huber Und Partner Ahp Ag",
    "wof:placetype":"venue"
},
  "geometry": {"coordinates":[8.893856,47.554001],"type":"Point"}
}