{
  "type": "Feature",
  "properties": {
    "iso:country":"CH",
    "sg:address":"Moosstrasse 31b 9014 St. Gallen 14 Zust. Postfach 9014 St. Gallen",
    "sg:city":"Zust",
    "sg:orig_category":"Mechanik",
    "sg:phone":"+41 71 279 11 38",
    "sg:postcode":"14",
    "wof:name":"Alp Metalart Gmbh Kunstschlosser- U. Schlosserarbeiten Usw.",
    "wof:placetype":"venue"
},
  "geometry": {"coordinates":[9.3363304138,47.4099197388],"type":"Point"}
}