{
  "type": "Feature",
  "properties": {
    "iso:country":"CH",
    "sg:address":"Sch\u00f6neggweg 42",
    "sg:city":"M\u00fcnchenbuchsee",
    "sg:orig_category":"Elektroinstallation",
    "sg:phone":"+41 31 869 15 20",
    "sg:postcode":"3053",
    "sg:province":"Bern",
    "wof:name":"Elektro Fahrni Ag",
    "wof:placetype":"venue"
},
  "geometry": {"coordinates":[7.4403729439,47.0224609375],"type":"Point"}
}