{
  "type": "Feature",
  "properties": {
    "iso:country":"CH",
    "sg:address":"Sonnhaldenweg 6",
    "sg:city":"Grossh\u00f6chstetten",
    "sg:orig_category":"Erbringung von Dienstleistungen f\u00fcr Unternehmen",
    "sg:phone":"+41 31 712 15 03",
    "sg:postcode":"3506",
    "sg:province":"Bern",
    "wof:name":"Data Collection Jezler Claudia",
    "wof:placetype":"venue"
},
  "geometry": {"coordinates":[7.6386990547,46.9097137451],"type":"Point"}
}