{
  "type": "Feature",
  "properties": {
    "addr:full":"Rue Principale Morgins Valais 1875",
    "addr:postcode":"1875",
    "addr:street":"Rue Principale",
    "iso:country":"CH",
    "sg:address":"Rue Principale",
    "sg:city":"Morgins",
    "sg:classifiers":[
        {
            "category":"Banks & Credit Unions",
            "subcategory":"Bank",
            "type":"Services"
        }
    ],
    "sg:phone":"+41 24 477 12 11",
    "sg:postcode":"1875",
    "sg:province":"Valais",
    "wof:name":"Raiffeisen",
    "wof:placetype":"venue"
},
  "geometry": {"coordinates":[6.858753,46.237522],"type":"Point"}
}