{
  "type": "Feature",
  "properties": {
    "iso:country":"CH",
    "sg:address":"R\u00f6merfeldstrasse 11",
    "sg:city":"Riehen",
    "sg:orig_category":"Sonstige Aktivit\u00e4ten der nicht-\u00e4rztlichen Medizinalberufe",
    "sg:phone":"+41 61 601 16 26",
    "sg:postcode":"4125",
    "sg:province":"Basel-Stadt",
    "wof:name":"Rolf B\u00e4r Kinesiologie & Hom\u00f6opathie",
    "wof:placetype":"venue"
},
  "geometry": {"coordinates":[7.6390509605,47.5694046021],"type":"Point"}
}