{
  "type": "Feature",
  "properties": {
    "iso:country":"CH",
    "sg:address":"Rond-point De Plainpalais 7",
    "sg:city":"Gen\u00e8ve",
    "sg:orig_category":"Arztpraxen",
    "sg:phone":"+41 32 931 22 50",
    "sg:postcode":"1205",
    "sg:province":"Gen\u00e8ve",
    "wof:name":"Dr M\u00e9d. Eric Perrot M\u00e9decin G\u00e9n\u00e9raliste Fmh",
    "wof:placetype":"venue"
},
  "geometry": {"coordinates":[6.747687,47.056286],"type":"Point"}
}