{
  "type": "Feature",
  "properties": {
    "iso:country":"CH",
    "sg:address":"Birmensdorferstrasse 299",
    "sg:city":"Z\u00fcrich",
    "sg:orig_category":"W\u00e4schereien",
    "sg:phone":"+41 14636212",
    "sg:postcode":"8055",
    "sg:province":"Z\u00fcrich",
    "wof:name":"Angela Kromjong W\u00e4scherei Gl\u00e4tterei",
    "wof:placetype":"venue"
},
  "geometry": {"coordinates":[8.5097837448,47.3696632385],"type":"Point"}
}