{
  "type": "Feature",
  "properties": {
    "addr:full":"Seefeldstrasse 75 Z\u00fcrich Z\u00fcrich 8008",
    "addr:housenumber":"75",
    "addr:postcode":"8008",
    "addr:street":"Seefeldstrasse",
    "iso:country":"CH",
    "sg:address":"Seefeldstrasse 75",
    "sg:city":"Z\u00fcrich",
    "sg:classifiers":[
        {
            "category":"Shopping",
            "subcategory":"Clothing, Apparel, & Fashions",
            "type":"Retail Goods"
        }
    ],
    "sg:phone":"+41 13832283",
    "sg:postcode":"8008",
    "sg:province":"Z\u00fcrich",
    "sg:tags":[
        "haberdashery"
    ],
    "wof:name":"Multifort Handels Ag",
    "wof:placetype":"venue"
},
  "geometry": {"coordinates":[8.552205,47.360592],"type":"Point"}
}