{
  "type": "Feature",
  "properties": {
    "iso:country":"CH",
    "sg:address":"Grossgurmels",
    "sg:city":"Gurmels",
    "sg:orig_category":"Bauspenglerei Sanit\u00e4rinstallation U Spenglerei",
    "sg:phone":"+41 26 674 17 24",
    "sg:postcode":"3212",
    "sg:province":"Fribourg",
    "wof:name":"Pius Auderset Spenglerei",
    "wof:placetype":"venue"
},
  "geometry": {"coordinates":[7.173195,46.893665],"type":"Point"}
}