{
  "type": "Feature",
  "properties": {
    "iso:country":"CH",
    "sg:address":"Place De La Pierre-\u00e0-voir",
    "sg:city":"Saxon",
    "sg:orig_category":"Herstellung von Metallerzeugnissen ohne Maschinenbau",
    "sg:phone":"+41 81 422 24 12",
    "sg:postcode":"1907",
    "sg:province":"Valais",
    "wof:name":"Bernhard L\u00e4ser Apparatebau",
    "wof:placetype":"venue"
},
  "geometry": {"coordinates":[9.8693141937,46.8826370239],"type":"Point"}
}