{
  "type": "Feature",
  "properties": {
    "iso:country":"CH",
    "sg:address":"Gotthardstrasse 41",
    "sg:city":"Arth",
    "sg:orig_category":"Zimmerei, Dachdeckerei, Bauspenglerei U Abdichtung",
    "sg:phone":"+41 79 607 01 14",
    "sg:postcode":"6415",
    "sg:province":"Schwyz",
    "wof:name":"Ulrich Anton Gmbh",
    "wof:placetype":"venue"
},
  "geometry": {"coordinates":[8.5240106583,47.0618476868],"type":"Point"}
}