{
  "type": "Feature",
  "properties": {
    "iso:country":"CH",
    "sg:address":"Casa Nelda",
    "sg:city":"Morcote",
    "sg:orig_category":"Mit dem Versicherungsgewerbe verbundene T\u00e4tigkeiten",
    "sg:postcode":"6922",
    "sg:province":"Ticino",
    "wof:name":"Anlage-info Herrmann Erika",
    "wof:placetype":"venue"
},
  "geometry": {"coordinates":[8.9184484482,45.9235954285],"type":"Point"}
}