{
  "type": "Feature",
  "properties": {
    "iso:country":"CH",
    "sg:address":"Domaine Des M\u00fbriers",
    "sg:city":"Bex",
    "sg:orig_category":"Grosshandel mit Nahrungsmitteln, Getr\u00e4nken U Tabakwaren ohne ausgepr\u00e4gten Schwerpunkt",
    "sg:phone":"+41 24 463 35 43",
    "sg:postcode":"1880",
    "sg:province":"Vaud",
    "wof:name":"Meylan Michel.",
    "wof:placetype":"venue"
},
  "geometry": {"coordinates":[7.0058350563,46.2401847839],"type":"Point"}
}