{
  "type": "Feature",
  "properties": {
    "iso:country":"CH",
    "sg:address":"Einsiedlerstrasse 34",
    "sg:city":"W\u00e4denswil",
    "sg:orig_category":"Herstellung von Schmuck, Gold U Silberschmiedwaren",
    "sg:postcode":"8820",
    "sg:province":"Z\u00fcrich",
    "wof:name":"Huszak Goldschmied",
    "wof:placetype":"venue"
},
  "geometry": {"coordinates":[8.6860837936,47.2197227478],"type":"Point"}
}