{
  "type": "Feature",
  "properties": {
    "iso:country":"CH",
    "sg:address":"Castagnola Viale 6900 Lugano. Postfach",
    "sg:city":"Calprino",
    "sg:orig_category":"RESTAURANTS: TEA-ROOMS",
    "sg:postcode":"6900",
    "sg:province":"Ticino",
    "wof:name":"Mascioni Augusto",
    "wof:placetype":"venue"
},
  "geometry": {"coordinates":[8.9607286453,46.0058898926],"type":"Point"}
}