{
  "type": "Feature",
  "properties": {
    "iso:country":"CH",
    "sg:address":"H\u00fcssiweg 23",
    "sg:city":"Strengelbach",
    "sg:orig_category":"Sonstige Aktivit\u00e4ten der nicht-\u00e4rztlichen Medizinalberufe",
    "sg:phone":"+41 62 751 05 64",
    "sg:postcode":"4802",
    "sg:province":"Aargau",
    "wof:name":"Marl\u00e8ne Basler Kinesiologie & Fussreflexzonen",
    "wof:placetype":"venue"
},
  "geometry": {"coordinates":[7.9325327873,47.284286499],"type":"Point"}
}