{
  "type": "Feature",
  "properties": {
    "iso:country":"CH",
    "sg:address":"3961",
    "sg:city":"Chandolin",
    "sg:orig_category":"Detailhandel mit B\u00fcchern, Zeitungen, Schreib U Papeteriewaren Detailhandel mit Geschenkartikeln U So",
    "sg:phone":"+41 27 475 15 42",
    "sg:postcode":"3961",
    "sg:province":"Valais",
    "wof:name":"V\u00e9ronique Zufferey Boutique Service",
    "wof:placetype":"venue"
},
  "geometry": {"coordinates":[7.597637,46.252079],"type":"Point"}
}