{
  "type": "Feature",
  "properties": {
    "iso:country":"CH",
    "sg:address":"Talackerstrasse 90 8400 Winterthur. Postfach",
    "sg:city":"Oberwinterthur",
    "sg:orig_category":"Non-Classified Establishments",
    "sg:postcode":"8404",
    "sg:province":"Z\u00fcrich",
    "wof:name":"Alphawolf Hundeschule Hirz Remo",
    "wof:placetype":"venue"
},
  "geometry": {"coordinates":[8.751625061,47.5012626648],"type":"Point"}
}