{
  "type": "Feature",
  "properties": {
    "iso:country":"CH",
    "sg:address":"Spitalgasse 4",
    "sg:city":"Bern",
    "sg:orig_category":"Fahrschulen, Flugschulen",
    "sg:phone":"+41 76 394 00 00",
    "sg:postcode":"3011",
    "sg:province":"Bern",
    "wof:name":"B\u00e9at Esseiva Auto-\u00e9cole",
    "wof:placetype":"venue"
},
  "geometry": {"coordinates":[7.1484980583,46.7536048889],"type":"Point"}
}