{
  "type": "Feature",
  "properties": {
    "iso:country":"CH",
    "sg:address":"Chasseral Route De",
    "sg:city":"Nods",
    "sg:orig_category":"RESTAURANTS: TEA-ROOMS",
    "sg:phone":"+41 32 751 22 02",
    "sg:postcode":"2518",
    "sg:province":"Bern",
    "wof:name":"Cuesta Ignacio",
    "wof:placetype":"venue"
},
  "geometry": {"coordinates":[7.0458607674,47.1272315979],"type":"Point"}
}