{
  "type": "Feature",
  "properties": {
    "iso:country":"CH",
    "sg:address":"Leiernstrasse 3",
    "sg:city":"Sch\u00fcpfen",
    "sg:orig_category":"Zahnarztpraxen",
    "sg:phone":"+41 31 872 10 50",
    "sg:postcode":"3054",
    "sg:province":"Bern",
    "wof:name":"Dr. Med. Dent. Daniel Wagner Zahnarzt",
    "wof:placetype":"venue"
},
  "geometry": {"coordinates":[7.3793978691,47.0412445068],"type":"Point"}
}