{
  "type": "Feature",
  "properties": {
    "iso:country":"CH",
    "sg:address":"Gemeindemattstrasse 20 3860 Meiringen. Postfach 264",
    "sg:city":"Meiringen",
    "sg:orig_category":"Allgemeiner Hoch U Tiefbau Allgemeiner Hochbau",
    "sg:postcode":"3860",
    "sg:province":"Bern",
    "wof:name":"Blatter Hoch Und Tiefbau Ag",
    "wof:placetype":"venue"
},
  "geometry": {"coordinates":[8.189304,46.724449],"type":"Point"}
}