{
  "type": "Feature",
  "properties": {
    "iso:country":"CH",
    "sg:address":"Via Linoleum 14",
    "sg:city":"Giubiasco",
    "sg:orig_category":"Architekturb\u00fcros",
    "sg:phone":"+41 32 751 30 30",
    "sg:postcode":"6512",
    "sg:province":"Ticino",
    "wof:name":"G. Perrenoud & M. Maire Bureau D'architecture",
    "wof:placetype":"venue"
},
  "geometry": {"coordinates":[7.064269,47.050735],"type":"Point"}
}