{
  "type": "Feature",
  "properties": {
    "addr:full":"Klosterweg 9 Z\u00fcrich Z\u00fcrich 8044",
    "addr:housenumber":"9",
    "addr:postcode":"8044",
    "addr:street":"Klosterweg",
    "iso:country":"CH",
    "sg:address":"Klosterweg 9",
    "sg:city":"Z\u00fcrich",
    "sg:orig_category":"Botanische U zoologische G\u00e4rten sowie Naturparks",
    "sg:phone":"+41 12625997",
    "sg:postcode":"8044",
    "sg:province":"Z\u00fcrich",
    "wof:name":"Zoologischer Garten Z\u00fcrich",
    "wof:placetype":"venue"
},
  "geometry": {"coordinates":[8.574789,47.384785],"type":"Point"}
}