{
  "type": "Feature",
  "properties": {
    "addr:full":"Langgasse 4 V\u00e4ttis St. Gallen 7315",
    "addr:housenumber":"4;st.",
    "addr:postcode":"7315",
    "addr:street":"Langgasse",
    "iso:country":"CH",
    "sg:address":"Langgasse 4",
    "sg:city":"V\u00e4ttis",
    "sg:orig_category":"Shopping U Fachgesch\u00e4fte, Sonstige Shoppinggelegenheiten",
    "sg:postcode":"7315",
    "sg:province":"St. Gallen",
    "wof:name":"Pegastar Co-verlag",
    "wof:placetype":"venue"
},
  "geometry": {"coordinates":[9.440785,46.908714],"type":"Point"}
}