{
  "type": "Feature",
  "properties": {
    "iso:country":"CH",
    "sg:address":"Sch\u00f6nisteig 2",
    "sg:city":"Bassersdorf",
    "sg:orig_category":"Tierarztpraxis",
    "sg:phone":"+41 41 871 00 03",
    "sg:postcode":"8303",
    "sg:province":"Z\u00fcrich",
    "wof:name":"Dres Hofstetter & Wehrle Tier\u00e4rzte",
    "wof:placetype":"venue"
},
  "geometry": {"coordinates":[8.6755800247,46.8743362427],"type":"Point"}
}