{
  "type": "Feature",
  "properties": {
    "iso:country":"CH",
    "sg:address":"Quadaraweg 202j",
    "sg:city":"Schiers",
    "sg:orig_category":"G\u00fcterbef\u00f6rderung im Strassenverkehr",
    "sg:phone":"+41 81 328 18 88",
    "sg:postcode":"7220",
    "sg:province":"Graubunden",
    "wof:name":"J. Guyan, Muldenservice",
    "wof:placetype":"venue"
},
  "geometry": {"coordinates":[9.6811628342,46.9738998413],"type":"Point"}
}