{
  "type": "Feature",
  "properties": {
    "addr:full":"3935 B\u00fcrchen Valais 3935",
    "addr:housenumber":"3935",
    "addr:postcode":"3935",
    "addr:street":"Buerchen Valais",
    "iso:country":"CH",
    "sg:address":"3935",
    "sg:city":"B\u00fcrchen",
    "sg:orig_category":"Architektur U Ingenieurb\u00fcros",
    "sg:phone":"+41 52 741 33 30",
    "sg:postcode":"3935",
    "sg:province":"Valais",
    "wof:name":"Ingenieurplanung Kiefer Ag",
    "wof:placetype":"venue"
},
  "geometry": {"coordinates":[8.859101,47.655582],"type":"Point"}
}