{
  "type": "Feature",
  "properties": {
    "iso:country":"CH",
    "sg:address":"Ch. De Malessert",
    "sg:city":"Perroy",
    "sg:orig_category":"Herstellung von Verpackungsmittelnaus Holz",
    "sg:phone":"+41 79 417 55 01",
    "sg:postcode":"1166",
    "sg:province":"Vaud",
    "wof:name":"Dutoit Pierre",
    "wof:placetype":"venue"
},
  "geometry": {"coordinates":[6.3567042351,46.4735527039],"type":"Point"}
}