{
  "type": "Feature",
  "properties": {
    "addr:full":"Dornimatte 5 6047 Kastanienbaum. Postfach Kastanienbaum Luzern 6047",
    "addr:housenumber":"5",
    "addr:postcode":"6047 kastanienbaum. postfach kastanienbaum;6047",
    "addr:street":"Dornimatte",
    "iso:country":"CH",
    "sg:address":"Dornimatte 5 6047 Kastanienbaum. Postfach",
    "sg:city":"Kastanienbaum",
    "sg:orig_category":"Architektur U Ingenieurb\u00fcros",
    "sg:postcode":"6047",
    "sg:province":"Luzern",
    "wof:name":"Koch Mariette.",
    "wof:placetype":"venue"
},
  "geometry": {"coordinates":[6.23548,46.477505],"type":"Point"}
}