{
  "type": "Feature",
  "properties": {
    "iso:country":"CH",
    "sg:address":"Rue Du Simplon 12",
    "sg:city":"Saxon",
    "sg:orig_category":"Fahrschulen, Flugschulen",
    "sg:postcode":"1907",
    "sg:province":"Valais",
    "wof:name":"Lenzin Alex",
    "wof:placetype":"venue"
},
  "geometry": {"coordinates":[7.9926548004,47.5531082153],"type":"Point"}
}