{
  "type": "Feature",
  "properties": {
    "iso:country":"CH",
    "sg:address":"Rue Du Milieu 5",
    "sg:city":"Buttes",
    "sg:orig_category":"Herstellung von Metallerzeugnissen ohne Maschinenbau Herstellung von sonstigen Metallwaren",
    "sg:phone":"+41 79 643 11 20",
    "sg:postcode":"2115",
    "sg:province":"Neuch\u00e2tel",
    "wof:name":"Metalinox Sa",
    "wof:placetype":"venue"
},
  "geometry": {"coordinates":[6.5507650375,46.8878135681],"type":"Point"}
}