{
  "type": "Feature",
  "properties": {
    "iso:country":"CH",
    "sg:address":"2735",
    "sg:city":"Champoz",
    "sg:orig_category":"Landw. Genossenschaften Viehzucht",
    "sg:postcode":"2735",
    "sg:province":"Bern",
    "wof:name":"Synd.d'\u00e9levage De La Race Tach.rouge De Noirmont & Env.",
    "wof:placetype":"venue"
},
  "geometry": {"coordinates":[6.9572901726,47.2244682312],"type":"Point"}
}