{
  "type": "Feature",
  "properties": {
    "iso:country":"CH",
    "sg:address":"Buchthalerstrasse 142",
    "sg:city":"Schaffhausen",
    "sg:orig_category":"Handelsvermittlung U Grosshandel Herstellung von sonstiger Bekleidung U Bekleidungszubeh\u00f6r",
    "sg:phone":"+41 52 624 35 67",
    "sg:postcode":"8203",
    "sg:province":"Schaffhausen",
    "wof:name":"Indisposables Hauser Katrin",
    "wof:placetype":"venue"
},
  "geometry": {"coordinates":[8.653963089,47.6962356567],"type":"Point"}
}