{
  "type": "Feature",
  "properties": {
    "iso:country":"CH",
    "sg:address":"Lommiserstrasse",
    "sg:city":"W\u00e4ngi",
    "sg:orig_category":"Non-Classified Establishments",
    "sg:postcode":"9545",
    "sg:province":"Thurgau",
    "wof:name":"Blumen B\u00e4r Gmbh",
    "wof:placetype":"venue"
},
  "geometry": {"coordinates":[8.9562797546,47.5017433167],"type":"Point"}
}