{
  "type": "Feature",
  "properties": {
    "iso:country":"CH",
    "sg:address":"G\u00e4uggelistrasse 4 7000 Chur. Postfach",
    "sg:city":"Chur",
    "sg:orig_category":"Finanzierungsinstitutionen",
    "sg:phone":"+41 81 257 10 40",
    "sg:postcode":"7000",
    "sg:province":"Graubunden",
    "wof:name":"Schulh\u00f6fli Ag",
    "wof:placetype":"venue"
},
  "geometry": {"coordinates":[9.53120327,46.8509292603],"type":"Point"}
}