{
  "type": "Feature",
  "properties": {
    "iso:country":"CH",
    "sg:address":"Tir F\u00e9d\u00e9ral Avenue Du 83",
    "sg:city":"Chavannes-renens",
    "sg:classifiers":[
        {
            "category":"Travel",
            "subcategory":"Hotels & Motels",
            "type":"Entertainment"
        }
    ],
    "sg:phone":"+41 21 869 91 24",
    "sg:postcode":"1022",
    "sg:province":"Vaud",
    "sg:tags":[
        "hotels",
        "mit",
        "restaurant"
    ],
    "wof:name":"Arn Cl.",
    "wof:placetype":"venue"
},
  "geometry": {"coordinates":[6.5772900581,46.5327987671],"type":"Point"}
}