{
  "type": "Feature",
  "properties": {
    "iso:country":"CH",
    "sg:address":"Thalgutstrasse 57",
    "sg:city":"Oberwichtrach",
    "sg:orig_category":"Instandhaltung U Reparatur von Automobilen",
    "sg:phone":"+41 34 493 31 22",
    "sg:postcode":"3114",
    "sg:province":"Bern",
    "wof:name":"Thalmann Josef Garage",
    "wof:placetype":"venue"
},
  "geometry": {"coordinates":[7.9064021111,46.8651771545],"type":"Point"}
}