{
  "type": "Feature",
  "properties": {
    "iso:country":"CH",
    "sg:address":"Dorfstr. 24",
    "sg:city":"Teufenthal",
    "sg:classifiers":[
        {
            "category":"Banks & Credit Unions",
            "subcategory":"Bank",
            "type":"Services"
        }
    ],
    "sg:phone":"+41 62 776 23 33",
    "sg:postcode":"5723",
    "sg:province":"Aargau",
    "wof:name":"Bank In Reinach, Filiale",
    "wof:placetype":"venue"
},
  "geometry": {"coordinates":[8.118963,47.328331],"type":"Point"}
}