{
  "type": "Feature",
  "properties": {
    "addr:full":"Passaggio San Pietro Ascona Ticino 6612",
    "addr:postcode":"6612",
    "addr:street":"Passaggio San Pietro",
    "iso:country":"CH",
    "sg:address":"Passaggio San Pietro",
    "sg:city":"Ascona",
    "sg:orig_category":"Chemische Reinigung",
    "sg:phone":"+41 91 791 21 07",
    "sg:postcode":"6612",
    "sg:province":"Ticino",
    "wof:name":"Luigi Laloli Lavanderia Chimica Ascosec",
    "wof:placetype":"venue"
},
  "geometry": {"coordinates":[8.76728,46.155006],"type":"Point"}
}