{
  "type": "Feature",
  "properties": {
    "iso:country":"CH",
    "sg:address":"Spinnereistrasse 8 9008 St. Gallen. Postfach",
    "sg:city":"Kleind\u00f6ttingen",
    "sg:orig_category":"Unclassifiable Establishments",
    "sg:phone":"+41 56 250 03 70",
    "sg:postcode":"5314",
    "sg:province":"Aargau",
    "wof:name":"Silion (switzerland) Ag",
    "wof:placetype":"venue"
},
  "geometry": {"coordinates":[9.3947887421,47.4363136292],"type":"Point"}
}