{
  "type": "Feature",
  "properties": {
    "iso:country":"CH",
    "sg:address":"Rue De La Servette 45",
    "sg:city":"Gen\u00e8ve",
    "sg:orig_category":"Detailhandel mit Fleisch U Fleischwaren",
    "sg:phone":"+41 22 733 81 28",
    "sg:postcode":"1202",
    "sg:province":"Gen\u00e8ve",
    "wof:name":"Boucherie Du Gastronome Martinez Matias.",
    "wof:placetype":"venue"
},
  "geometry": {"coordinates":[6.1346797943,46.2112693787],"type":"Point"}
}