{
  "type": "Feature",
  "properties": {
    "iso:country":"CH",
    "sg:address":"Gewerbestrasse 16 8225 Siblingen. Postfach",
    "sg:city":"Siblingen",
    "sg:orig_category":"Instandhaltung U Reparatur von Automobilen",
    "sg:postcode":"8225",
    "sg:province":"Schaffhausen",
    "wof:name":"Carrosserie Britschgi Gmbh",
    "wof:placetype":"venue"
},
  "geometry": {"coordinates":[8.5153427124,47.713432312],"type":"Point"}
}