{
  "type": "Feature",
  "properties": {
    "iso:country":"CH",
    "sg:address":"Grenzacherstrasse 79 4058 Basel. Postfach",
    "sg:city":"Basel",
    "sg:orig_category":"Architektur U Ingenieurb\u00fcros",
    "sg:phone":"+41 61 690 95 00",
    "sg:postcode":"4051",
    "sg:province":"Basel-Stadt",
    "wof:name":"Sch\u00fcssler + Cramer Ag Ingenieurb\u00fcro Usw",
    "wof:placetype":"venue"
},
  "geometry": {"coordinates":[7.602146,47.558872],"type":"Point"}
}