{
  "type": "Feature",
  "properties": {
    "iso:country":"CH",
    "sg:address":"Leonhardstrasse 18",
    "sg:city":"Z\u00fcrich",
    "sg:orig_category":"Alters U Pflegeheime Sonstige Wohnheime",
    "sg:phone":"+41 26 917 81 92",
    "sg:postcode":"8001",
    "sg:province":"Z\u00fcrich",
    "wof:name":"Foyer St-joseph",
    "wof:placetype":"venue"
},
  "geometry": {"coordinates":[6.974406,46.63554],"type":"Point"}
}