{
  "type": "Feature",
  "properties": {
    "iso:country":"CH",
    "sg:address":"Chemin Des Maladi\u00e8res",
    "sg:city":"Bevaix",
    "sg:classifiers":[
        {
            "category":"Travel",
            "subcategory":"Hotels & Motels",
            "type":"Entertainment"
        }
    ],
    "sg:phone":"+41 32 846 18 84",
    "sg:postcode":"2022",
    "sg:province":"Neuch\u00e2tel",
    "sg:tags":[
        "hotels",
        "mit",
        "restaurant"
    ],
    "wof:name":"Hotz Fran\u00e7ois",
    "wof:placetype":"venue"
},
  "geometry": {"coordinates":[6.8072152138,46.9224205017],"type":"Point"}
}