{
  "type": "Feature",
  "properties": {
    "iso:country":"CH",
    "sg:address":"Route De Chavannes 65",
    "sg:city":"Lausanne",
    "sg:orig_category":"Instandhaltung U Reparatur von Automobilen",
    "sg:phone":"+41 21 624 61 62",
    "sg:postcode":"1007",
    "sg:province":"Vaud",
    "wof:name":"Garage Sud-ouest Sa",
    "wof:placetype":"venue"
},
  "geometry": {"coordinates":[6.5920581818,46.5231018066],"type":"Point"}
}