{
  "type": "Feature",
  "properties": {
    "iso:country":"CH",
    "sg:address":"Lognerstr. 8 9472 Grabs. Postfach",
    "sg:city":"Werdenberg",
    "sg:orig_category":"Abwasserreinigung, Abfallbeseitigung U sonstige Entsorgung",
    "sg:postcode":"9470",
    "sg:province":"St. Gallen",
    "wof:name":"Eggenberger Michael",
    "wof:placetype":"venue"
},
  "geometry": {"coordinates":[9.453125,47.170395],"type":"Point"}
}