{
  "type": "Feature",
  "properties": {
    "iso:country":"CH",
    "sg:address":"Marktgasse 18 3600 Thun. Postfach",
    "sg:city":"Thun",
    "sg:orig_category":"Architekturb\u00fcros",
    "sg:phone":"+41 71 222 14 66",
    "sg:postcode":"3601",
    "sg:province":"Bern",
    "wof:name":"Fioravante Cattozzo Architekturb\u00fcro",
    "wof:placetype":"venue"
},
  "geometry": {"coordinates":[9.371526,47.427185],"type":"Point"}
}