{
  "type": "Feature",
  "properties": {
    "iso:country":"CH",
    "sg:address":"Frisco Chemin 11 1208 Gen\u00e8ve. Postfach",
    "sg:city":"Gen\u00e8ve",
    "sg:orig_category":"Kauf U Verkauf von Immobilien auf eigene Rechnung",
    "sg:postcode":"1201",
    "sg:province":"Gen\u00e8ve",
    "wof:name":"Union Suisse Des Grands Domaines, Titulaire Calabrese Raphael Grands Domaines, Propri\u00e9t\u00e9 De Ma\u00eetres Et Ch\u00e2teaux Etc.; Vente, Achat, Promotion",
    "wof:placetype":"venue"
},
  "geometry": {"coordinates":[6.1751317978,46.2014579773],"type":"Point"}
}