{
  "type": "Feature",
  "properties": {
    "addr:full":"Lagerhausweg 41 3000 Bern. Postfach Bern Bern 3003",
    "addr:housenumber":"41",
    "addr:postcode":"3000;postfach;3003",
    "addr:street":"Lagerhausweg",
    "iso:country":"CH",
    "sg:address":"Lagerhausweg 41 3000 Bern. Postfach",
    "sg:city":"Bern",
    "sg:orig_category":"Allgemeiner Hoch U Tiefbau",
    "sg:postcode":"3003",
    "sg:province":"Bern",
    "wof:name":"Zentrum F\u00fcr Lehmbau Bern Gmbh",
    "wof:placetype":"venue"
},
  "geometry": {"coordinates":[7.389854,46.934246],"type":"Point"}
}