{
  "type": "Feature",
  "properties": {
    "iso:country":"CH",
    "sg:address":"8865 Bilten. Postfach 49",
    "sg:city":"Bilten",
    "sg:orig_category":"Elektrizit\u00e4tsversorgung Wasserversorgung",
    "sg:phone":"+41 55 615 22 57",
    "sg:postcode":"8865",
    "sg:province":"Glarus",
    "wof:name":"Gemeindeverwaltung Bilten",
    "wof:placetype":"venue"
},
  "geometry": {"coordinates":[9.0205802917,47.1507148743],"type":"Point"}
}