{
  "type": "Feature",
  "properties": {
    "iso:country":"CH",
    "sg:address":"Dufourstrasse 40a",
    "sg:city":"Zollikon",
    "sg:orig_category":"Non-Classified Establishments",
    "sg:postcode":"8702",
    "sg:province":"Z\u00fcrich",
    "wof:name":"Swissonmail Ag",
    "wof:placetype":"venue"
},
  "geometry": {"coordinates":[8.5695409775,47.3430633545],"type":"Point"}
}