{
  "type": "Feature",
  "properties": {
    "iso:country":"CH",
    "sg:address":"Ackerstrasse 10",
    "sg:city":"Zurzach",
    "sg:orig_category":"Herstellung von Radio U Fernsehger\u00e4ten sowie phono U videotechnischen Ger\u00e4ten",
    "sg:postcode":"5330",
    "sg:province":"Aargau",
    "wof:name":"L + M Elektronik B\u00f6niger R.",
    "wof:placetype":"venue"
},
  "geometry": {"coordinates":[8.2928733826,47.5902175903],"type":"Point"}
}