{
  "type": "Feature",
  "properties": {
    "iso:country":"CH",
    "sg:address":"Lindenstrasse 3a",
    "sg:city":"Bellach",
    "sg:orig_category":"Detailhandel mit Fleisch U Fleischwaren",
    "sg:phone":"+41 79 609 97 91",
    "sg:postcode":"4512",
    "sg:province":"Solothurn",
    "wof:name":"Urs Hofer Metzgerei-wursterei",
    "wof:placetype":"venue"
},
  "geometry": {"coordinates":[7.5030651093,47.2159156799],"type":"Point"}
}