{
  "type": "Feature",
  "properties": {
    "iso:country":"CH",
    "sg:address":"Sonnenstrasse 17",
    "sg:city":"Biel/bienne",
    "sg:orig_category":"Erschliessung von Grundst\u00fccken",
    "sg:postcode":"2504",
    "sg:province":"Bern",
    "wof:name":"Baugenossenschaft Awo",
    "wof:placetype":"venue"
},
  "geometry": {"coordinates":[7.2653179169,47.1500282288],"type":"Point"}
}