{
  "type": "Feature",
  "properties": {
    "iso:country":"CH",
    "sg:address":"Rue Des Fleurettes",
    "sg:city":"Yvonand",
    "sg:orig_category":"Zimmerei, Dachdeckerei, Bauspenglerei U Abdichtung",
    "sg:postcode":"1462",
    "sg:province":"Vaud",
    "wof:name":"Binggeli Roger",
    "wof:placetype":"venue"
},
  "geometry": {"coordinates":[6.7393078804,46.802696228],"type":"Point"}
}