{
  "type": "Feature",
  "properties": {
    "iso:country":"CH",
    "sg:address":"St.-anna-strasse 32",
    "sg:city":"Luzern",
    "sg:classifiers":[
        {
            "category":"Education",
            "subcategory":"Library",
            "type":"Public Place"
        }
    ],
    "sg:phone":"+41 19134111",
    "sg:postcode":"6006",
    "sg:province":"Luzern",
    "sg:tags":[
        "u",
        "bibliotheken",
        "archive"
    ],
    "wof:name":"Klinik St.raphael",
    "wof:placetype":"venue"
},
  "geometry": {"coordinates":[8.59813,47.329826],"type":"Point"}
}