{
  "type": "Feature",
  "properties": {
    "iso:country":"CH",
    "sg:address":"Industriestrasse 26",
    "sg:city":"Stadel(winterthur)",
    "sg:orig_category":"Druck ohne Zeitungsdruck Offsetdruck",
    "sg:phone":"+41 81 413 63 53",
    "sg:postcode":"8404",
    "sg:province":"Z\u00fcrich",
    "wof:name":"Typoprint, Birkenmaier J.",
    "wof:placetype":"venue"
},
  "geometry": {"coordinates":[9.8182134628,46.7882385254],"type":"Point"}
}