{
  "type": "Feature",
  "properties": {
    "iso:country":"CH",
    "sg:address":"Hafenstrasse 124",
    "sg:city":"Birsfelden",
    "sg:orig_category":"Herstellung von Brot U Backwaren Herstellung von Dauerbackwaren",
    "sg:phone":"+41 61 313 22 55",
    "sg:postcode":"4127",
    "sg:province":"Basel-Landschaft",
    "wof:name":"Jowa Ag",
    "wof:placetype":"venue"
},
  "geometry": {"coordinates":[7.6341428757,47.5576858521],"type":"Point"}
}