{
  "type": "Feature",
  "properties": {
    "iso:country":"CH",
    "sg:address":"Klingentalgraben 37 4057 Basel. Postfach",
    "sg:city":"Basel",
    "sg:orig_category":"Korrespondenz U Nachrichtenb\u00fcros, selbst\u00e4ndige Journalisten",
    "sg:phone":"+41 61 382 60 25",
    "sg:postcode":"4051",
    "sg:province":"Basel-Stadt",
    "wof:name":"Gambino Francesco Video-reportagen U. -dokumentationen",
    "wof:placetype":"venue"
},
  "geometry": {"coordinates":[7.5911130905,47.5641479492],"type":"Point"}
}