{
  "type": "Feature",
  "properties": {
    "iso:country":"CH",
    "sg:address":"Unterdorfstrasse 9",
    "sg:city":"Gr\u00e4nichen",
    "sg:orig_category":"Detailhandel mit Sportartikeln Fachdetailhandel in Verkaufsr\u00e4umen",
    "sg:phone":"+41 62 842 04 05",
    "sg:postcode":"5722",
    "sg:province":"Aargau",
    "wof:name":"Hang-loose, Zehnder Sport",
    "wof:placetype":"venue"
},
  "geometry": {"coordinates":[8.0945177078,47.3612594604],"type":"Point"}
}