{
  "type": "Feature",
  "properties": {
    "iso:country":"CH",
    "sg:address":"Bahnhofstrasse 34",
    "sg:city":"Oberburg",
    "sg:orig_category":"Herstellung von Metallkonstruktionen",
    "sg:postcode":"3414",
    "sg:province":"Bern",
    "wof:name":"Stallungen Aller Art, Steiner Walter.",
    "wof:placetype":"venue"
},
  "geometry": {"coordinates":[9.6307153702,47.4540061951],"type":"Point"}
}