{
  "type": "Feature",
  "properties": {
    "iso:country":"CH",
    "sg:address":"Stockenstrasse 3",
    "sg:city":"Balterswil",
    "sg:classifiers":[
        {
            "category":"Utilities",
            "subcategory":"Recycling",
            "type":"Services"
        }
    ],
    "sg:phone":"+41 71 973 90 30",
    "sg:postcode":"8362",
    "sg:province":"Thurgau",
    "sg:tags":[
        "anodizing",
        "hardcoat"
    ],
    "wof:name":"Altefco Ag",
    "wof:placetype":"venue"
},
  "geometry": {"coordinates":[8.9421024323,47.4551048279],"type":"Point"}
}