{
  "type": "Feature",
  "properties": {
    "iso:country":"CH",
    "sg:address":"Hinterdorf 7312 Pf\u00e4fers. Postfach",
    "sg:city":"Valens",
    "sg:orig_category":"Zimmerei, Dachdeckerei, Bauspenglerei U Abdichtung",
    "sg:phone":"+41 55 615 12 15",
    "sg:postcode":"7317",
    "sg:province":"St. Gallen",
    "wof:name":"K\u00fchne Holzbau Ag",
    "wof:placetype":"venue"
},
  "geometry": {"coordinates":[9.0545148849,47.1724510193],"type":"Point"}
}