{
  "type": "Feature",
  "properties": {
    "iso:country":"CH",
    "sg:address":"L\u00e4ngenbold 18b",
    "sg:city":"Root",
    "sg:orig_category":"Maschinen and Apparate divers Grosshandel Vermietung von sonstigen Maschinen U Ger\u00e4ten",
    "sg:phone":"+41 41 450 40 04",
    "sg:postcode":"6037",
    "sg:province":"Luzern",
    "wof:name":"Cool-rex Ag",
    "wof:placetype":"venue"
},
  "geometry": {"coordinates":[8.3781528473,47.1062469482],"type":"Point"}
}