{
  "type": "Feature",
  "properties": {
    "iso:country":"CH",
    "sg:address":"Glarnerstrasse 8854 Siebnen. Postfach",
    "sg:city":"Siebnen",
    "sg:orig_category":"RESTAURANTS: TEA-ROOMS",
    "sg:postcode":"8854",
    "sg:province":"Schwyz",
    "wof:name":"Actinia Gastro Gmbh",
    "wof:placetype":"venue"
},
  "geometry": {"coordinates":[8.8967399597,47.1743583679],"type":"Point"}
}