{
  "type": "Feature",
  "properties": {
    "iso:country":"CH",
    "sg:address":"M\u00fclacher 44",
    "sg:city":"Buttisholz",
    "sg:orig_category":"Herstellung von Elektrizit\u00e4tsverteilungs U schalteinrichtungen Herstellung von industriellen Prozess",
    "sg:phone":"+41 41 929 00 40",
    "sg:postcode":"6018",
    "sg:province":"Luzern",
    "wof:name":"E. H\u00e4ller Elektrotechnik",
    "wof:placetype":"venue"
},
  "geometry": {"coordinates":[8.1012153625,47.1173171997],"type":"Point"}
}