{
  "type": "Feature",
  "properties": {
    "iso:country":"CH",
    "sg:address":"Senggi",
    "sg:city":"Schwenden",
    "sg:classifiers":[
        {
            "category":"Travel",
            "subcategory":"Hotels & Motels",
            "type":"Entertainment"
        }
    ],
    "sg:phone":"+41 33 684 12 84",
    "sg:postcode":"3757",
    "sg:province":"Bern",
    "sg:tags":[
        "hotels",
        "mit",
        "restaurant"
    ],
    "wof:name":"Hotel Spillgerten",
    "wof:placetype":"venue"
},
  "geometry": {"coordinates":[7.4830498695,46.5687255859],"type":"Point"}
}