{
  "type": "Feature",
  "properties": {
    "iso:country":"CH",
    "sg:address":"Au Vernaz",
    "sg:city":"Echichens",
    "sg:orig_category":"Herstellung von Betonerzeugnissen f\u00fcr den Bau Herstellung von Drahtwaren",
    "sg:phone":"+41 21 801 58 83",
    "sg:postcode":"1112",
    "sg:province":"Vaud",
    "wof:name":"Ferropose Sa",
    "wof:placetype":"venue"
},
  "geometry": {"coordinates":[6.5030679703,46.5297889709],"type":"Point"}
}