{
  "type": "Feature",
  "properties": {
    "iso:country":"CH",
    "sg:address":"Holtenstrasse 1",
    "sg:city":"Gr\u00e4nichen",
    "sg:orig_category":"Sanit\u00e4r, Heizungs U L\u00fcftungsinstallation",
    "sg:postcode":"5722",
    "sg:province":"Aargau",
    "wof:name":"Bertschi Mario Heizungen Und San. Anlagen",
    "wof:placetype":"venue"
},
  "geometry": {"coordinates":[8.0950145721,47.3676757812],"type":"Point"}
}