{
  "type": "Feature",
  "properties": {
    "iso:country":"CH",
    "sg:address":"Habsburgstrasse 21 8037 Z\u00fcrich. Postfach",
    "sg:city":"Z\u00fcrich",
    "sg:orig_category":"Gesundheitswesen",
    "sg:phone":"+41 81 413 52 06",
    "sg:postcode":"8037",
    "sg:province":"Z\u00fcrich",
    "wof:name":"Strobel Hans-peter, Konsiliarapotheker Spital Davos",
    "wof:placetype":"venue"
},
  "geometry": {"coordinates":[9.819272995,46.7925987244],"type":"Point"}
}