{
  "type": "Feature",
  "properties": {
    "iso:country":"CH",
    "sg:address":"L\u00e4nggasse 22",
    "sg:city":"Krauchthal",
    "sg:orig_category":"Kaminfeger",
    "sg:phone":"+41 34 411 20 14",
    "sg:postcode":"3326",
    "sg:province":"Bern",
    "wof:name":"Gerhard Streit Kaminfegergesch\u00e4ft",
    "wof:placetype":"venue"
},
  "geometry": {"coordinates":[7.5648889542,47.0067825317],"type":"Point"}
}