{
  "type": "Feature",
  "properties": {
    "iso:country":"CH",
    "sg:address":"Flughofstrasse 50 8152 Glattbrugg. Postfach",
    "sg:city":"Opfikon",
    "sg:orig_category":"Reiseb\u00fcros U Reiseveranstalter",
    "sg:phone":"+41 17614405",
    "sg:postcode":"8152",
    "sg:province":"Z\u00fcrich",
    "wof:name":"Ari Reisen + Handel Arik Berrin Und Arik Mustafa",
    "wof:placetype":"venue"
},
  "geometry": {"coordinates":[8.4507780075,47.2830314636],"type":"Point"}
}