{
  "type": "Feature",
  "properties": {
    "iso:country":"CH",
    "sg:address":"Rue Du Mont-tendre 11",
    "sg:city":"Sullens",
    "sg:orig_category":"Erbringung von Dienstleistungen f\u00fcr Unternehmen",
    "sg:phone":"+41 21 731 26 54",
    "sg:postcode":"1036",
    "sg:province":"Vaud",
    "wof:name":"Badan Josiane",
    "wof:placetype":"venue"
},
  "geometry": {"coordinates":[6.5665831566,46.58801651],"type":"Point"}
}