{
  "type": "Feature",
  "properties": {
    "iso:country":"CH",
    "sg:address":"Vrenikerstrasse 39 8152 Opfikon. Postfach",
    "sg:city":"Opfikon",
    "sg:orig_category":"Herstellung von Teppichen",
    "sg:postcode":"8152",
    "sg:province":"Z\u00fcrich",
    "wof:name":"Tq-parkett- U. Bodenbel\u00e4ge Gmbh",
    "wof:placetype":"venue"
},
  "geometry": {"coordinates":[8.5793466568,47.4282913208],"type":"Point"}
}