{
  "type": "Feature",
  "properties": {
    "addr:full":"Dorfstrasse 44 Ersigen Bern 3423",
    "addr:housenumber":"44",
    "addr:postcode":"3423",
    "addr:street":"Dorfstrasse",
    "iso:country":"CH",
    "sg:address":"Dorfstrasse 44",
    "sg:city":"Ersigen",
    "sg:orig_category":"Bauschreinerei M\u00f6belschreinerei",
    "sg:phone":"+41 34 445 21 12",
    "sg:postcode":"3423",
    "sg:province":"Bern",
    "wof:name":"Isenring Andreas, Tischlerwerkstatt",
    "wof:placetype":"venue"
},
  "geometry": {"coordinates":[7.597186,47.096272],"type":"Point"}
}