{
  "type": "Feature",
  "properties": {
    "iso:country":"CH",
    "sg:address":"Birkenstrasse 49 6343 Rotkreuz. Postfach",
    "sg:city":"Rotkreuz",
    "sg:orig_category":"Herstellung von sonstigen Produkten aus nichtmetallischen Mineralien",
    "sg:postcode":"6343",
    "sg:province":"Zug",
    "wof:name":"Halcyonics Ag Schwingungsisolations-systeme; Entwicklung, Produktion Usw",
    "wof:placetype":"venue"
},
  "geometry": {"coordinates":[8.435385704,47.1471481323],"type":"Point"}
}