{
  "type": "Feature",
  "properties": {
    "iso:country":"CH",
    "sg:address":"G\u00f6schenenstrasse 74",
    "sg:city":"Basel",
    "sg:orig_category":"Malerei",
    "sg:phone":"+41 61 301 32 15",
    "sg:postcode":"4054",
    "sg:province":"Basel-Stadt",
    "wof:name":"Ren\u00e9 Jung Malergesch\u00e4ft",
    "wof:placetype":"venue"
},
  "geometry": {"coordinates":[7.5592908859,47.5471534729],"type":"Point"}
}