{
  "type": "Feature",
  "properties": {
    "iso:country":"CH",
    "sg:address":"Brusata 6998 Termine. Postfach",
    "sg:city":"Termine",
    "sg:orig_category":"Werbung",
    "sg:phone":"+41 91 608 23 05",
    "sg:postcode":"6998",
    "sg:province":"Ticino",
    "wof:name":"Ferrazzini Felice Sagl",
    "wof:placetype":"venue"
},
  "geometry": {"coordinates":[8.8096218109,45.9958229065],"type":"Point"}
}