{
  "type": "Feature",
  "properties": {
    "iso:country":"CH",
    "sg:address":"Weid 31",
    "sg:city":"Menzingen",
    "sg:orig_category":"Sportvereine Ballsport Tennis",
    "sg:phone":"+41 41 755 17 21",
    "sg:postcode":"6313",
    "sg:province":"Zug",
    "wof:name":"Tc Unter\u00e4geri",
    "wof:placetype":"venue"
},
  "geometry": {"coordinates":[8.5948915482,47.1771392822],"type":"Point"}
}