{
  "type": "Feature",
  "properties": {
    "iso:country":"CH",
    "sg:address":"Rue De L'orangerie 3",
    "sg:city":"Gen\u00e8ve",
    "sg:orig_category":"Detektivb\u00fcros U \u00dcberwachung",
    "sg:phone":"+41 22 734 43 60",
    "sg:postcode":"1202",
    "sg:province":"Gen\u00e8ve",
    "wof:name":"Roland Chablais D\u00e9tective Priv\u00e9",
    "wof:placetype":"venue"
},
  "geometry": {"coordinates":[6.1323180199,46.2146072388],"type":"Point"}
}