{
  "type": "Feature",
  "properties": {
    "addr:full":"Bahnhofstrasse 15 Flums St. Gallen 8890",
    "addr:housenumber":"15",
    "addr:postcode":"8890",
    "addr:street":"Bahnhofstrasse",
    "iso:country":"CH",
    "sg:address":"Bahnhofstrasse 15",
    "sg:city":"Flums",
    "sg:orig_category":"Detailhandel mit Boden U Wandbel\u00e4gen ohne Teppiche Herstellung von Teppichen",
    "sg:phone":"+41 81 710 11 11",
    "sg:postcode":"8890",
    "sg:province":"St. Gallen",
    "wof:name":"Peter Lukas Ag",
    "wof:placetype":"venue"
},
  "geometry": {"coordinates":[9.346532,47.094212],"type":"Point"}
}