{
  "type": "Feature",
  "properties": {
    "iso:country":"CH",
    "sg:address":"Bachstrasse 1",
    "sg:city":"Oberehrendingen",
    "sg:orig_category":"Detailhandel mit Waren verschiedener Art, Hauptrichtung Nahrungsmittel",
    "sg:phone":"+41 62 771 31 15",
    "sg:postcode":"5422",
    "wof:name":"Othmar Meyer Denner-satellit",
    "wof:placetype":"venue"
},
  "geometry": {"coordinates":[8.2045660019,47.2664070129],"type":"Point"}
}