{
  "type": "Feature",
  "properties": {
    "iso:country":"CH",
    "sg:address":"Im Rebh\u00fcgel 4 5445 Eggenwil. Postfach",
    "sg:city":"Eggenwil",
    "sg:orig_category":"Erbringung von Dienstleistungen f\u00fcr Unternehmen",
    "sg:postcode":"5445",
    "sg:province":"Aargau",
    "wof:name":"Wohnwende Gmbh",
    "wof:placetype":"venue"
},
  "geometry": {"coordinates":[8.338973999,47.3703994751],"type":"Point"}
}