{
  "type": "Feature",
  "properties": {
    "iso:country":"CH",
    "sg:address":"Sch\u00fctzengartenstrasse 14",
    "sg:city":"Flums",
    "sg:orig_category":"Herstellung von Metallkonstruktionen Mechanische Werkst\u00e4tten",
    "sg:phone":"+41 81 733 12 45",
    "sg:postcode":"8890",
    "sg:province":"St. Gallen",
    "wof:name":"Mannhart Toni",
    "wof:placetype":"venue"
},
  "geometry": {"coordinates":[9.344083786,47.0959968567],"type":"Point"}
}