{
  "type": "Feature",
  "properties": {
    "iso:country":"CH",
    "sg:address":"Alpsteinstrasse 7",
    "sg:city":"Horn",
    "sg:orig_category":"Softwareentwicklung U beratung",
    "sg:phone":"+41 71 841 04 52",
    "sg:postcode":"9326",
    "sg:province":"Thurgau",
    "wof:name":"Baiker Informatik",
    "wof:placetype":"venue"
},
  "geometry": {"coordinates":[9.4577732086,47.4902114868],"type":"Point"}
}