{
  "type": "Feature",
  "properties": {
    "iso:country":"CH",
    "sg:address":"Seefeldstrasse 299 8008 Z\u00fcrich. Postfach",
    "sg:city":"Z\u00fcrich",
    "sg:orig_category":"Unternehmensberatung",
    "sg:phone":"+41 14220933",
    "sg:postcode":"8001",
    "sg:province":"Z\u00fcrich",
    "wof:name":"Widmer Bruno Consulting",
    "wof:placetype":"venue"
},
  "geometry": {"coordinates":[8.5644178391,47.3476905823],"type":"Point"}
}