{
  "type": "Feature",
  "properties": {
    "iso:country":"CH",
    "sg:address":"Freiestrasse 5",
    "sg:city":"Liebefeld",
    "sg:orig_category":"Erschliessung von Grundst\u00fccken",
    "sg:postcode":"3097",
    "sg:province":"Bern",
    "wof:name":"Baugen.heckenweg Schwarzenburg",
    "wof:placetype":"venue"
},
  "geometry": {"coordinates":[7.4256930351,46.9300041199],"type":"Point"}
}