{
  "type": "Feature",
  "properties": {
    "iso:country":"CH",
    "sg:address":"Hirzbodenweg 10",
    "sg:city":"Basel",
    "sg:orig_category":"Fahrschulen, Flugschulen",
    "sg:phone":"+41 79 219 71 71",
    "sg:postcode":"4052",
    "sg:province":"Basel-Stadt",
    "wof:name":"Arthur Huber Fahrschule Gellert",
    "wof:placetype":"venue"
},
  "geometry": {"coordinates":[7.6087350845,47.5516891479],"type":"Point"}
}