{
  "type": "Feature",
  "properties": {
    "iso:country":"CH",
    "sg:address":"Wolfgasse 2",
    "sg:city":"Lausen",
    "sg:orig_category":"Schl\u00fcsselservice",
    "sg:phone":"+41 79 674 40 71",
    "sg:postcode":"4415",
    "sg:province":"Basel-Landschaft",
    "wof:name":"Heinimann Ag",
    "wof:placetype":"venue"
},
  "geometry": {"coordinates":[7.7598910332,47.4723052979],"type":"Point"}
}