{
  "type": "Feature",
  "properties": {
    "iso:country":"CH",
    "sg:address":"1515",
    "sg:city":"Neyruz-sur-moudon",
    "sg:orig_category":"Mechanik",
    "sg:postcode":"1515",
    "sg:province":"Vaud",
    "wof:name":"D\u00e4hler-ryser, Hans Peter",
    "wof:placetype":"venue"
},
  "geometry": {"coordinates":[7.6937937737,46.7762184143],"type":"Point"}
}