{
  "type": "Feature",
  "properties": {
    "iso:country":"CH",
    "sg:address":"Kr\u00e4merackerstrasse 15",
    "sg:city":"Uster",
    "sg:orig_category":"Kaufm\u00e4nnische Berufsschulen",
    "sg:phone":"+41 55 442 36 55",
    "sg:postcode":"8610",
    "sg:province":"Z\u00fcrich",
    "wof:name":"Kaufm\u00e4nnische Berufs-& Verk\u00e4uferinnenschule",
    "wof:placetype":"venue"
},
  "geometry": {"coordinates":[8.8496608734,47.190032959],"type":"Point"}
}