{
  "type": "Feature",
  "properties": {
    "iso:country":"CH",
    "sg:address":"Seidenweg 19 3012 Bern. Postfach",
    "sg:city":"Bern",
    "sg:orig_category":"Herstellung von medizinischen U chirurgischen Ger\u00e4ten sowie orthop\u00e4dischen Vorrichtungen",
    "sg:postcode":"3005",
    "sg:province":"Bern",
    "wof:name":"Graf J. Und L. Zahntechn. Laboratorium",
    "wof:placetype":"venue"
},
  "geometry": {"coordinates":[7.432844162,46.9550933838],"type":"Point"}
}