{
  "type": "Feature",
  "properties": {
    "iso:country":"CH",
    "sg:address":"Bergermoosstrasse 4 8902 Urdorf. Postfach",
    "sg:city":"Urdorf",
    "sg:orig_category":"Handel mit Automobilen Handelsvermittlung U Grosshandel",
    "sg:phone":"+41 17365511",
    "sg:postcode":"8902",
    "sg:province":"Z\u00fcrich",
    "wof:name":"Renault Nissan Suisse Sa",
    "wof:placetype":"venue"
},
  "geometry": {"coordinates":[8.4240112305,47.370174408],"type":"Point"}
}