{
  "type": "Feature",
  "properties": {
    "addr:full":"Rue Des Murs 1 Coppet Vaud 1296",
    "addr:housenumber":"1",
    "addr:postcode":"1296",
    "addr:street":"Rue Des Murs",
    "iso:country":"CH",
    "sg:address":"Rue Des Murs 1",
    "sg:city":"Coppet",
    "sg:orig_category":"Architekturb\u00fcros",
    "sg:phone":"+41 22 776 32 41",
    "sg:postcode":"1296",
    "sg:province":"Vaud",
    "wof:name":"Jean-michel & Ren\u00e9 Delisle Bureau D'architecture",
    "wof:placetype":"venue"
},
  "geometry": {"coordinates":[6.191769,46.316067],"type":"Point"}
}