{
  "type": "Feature",
  "properties": {
    "iso:country":"CH",
    "sg:address":"K\u00f6nizstrasse 230 3097 Liebefeld. Postfach",
    "sg:city":"Liebefeld",
    "sg:orig_category":"Offsetdruck",
    "sg:phone":"+41 31 971 04 72",
    "sg:postcode":"3097",
    "sg:province":"Bern",
    "wof:name":"Otto Binz Druckerei",
    "wof:placetype":"venue"
},
  "geometry": {"coordinates":[7.4156341553,46.9303588867],"type":"Point"}
}