{
  "type": "Feature",
  "properties": {
    "iso:country":"CH",
    "sg:address":"Pfaffenholzstrasse 21",
    "sg:city":"Frauenfeld",
    "sg:orig_category":"Pensionskassen",
    "sg:phone":"+41 52 721 93 10",
    "sg:postcode":"8500",
    "sg:province":"Thurgau",
    "wof:name":"Personalf\u00fcrsorgestiftung Der Genossenschaft F\u00fcr Den Betrieb Alkoholfreier Volksh\u00e4user",
    "wof:placetype":"venue"
},
  "geometry": {"coordinates":[8.910533905,47.551448822],"type":"Point"}
}