{
  "type": "Feature",
  "properties": {
    "iso:country":"CH",
    "sg:address":"Route De Moncor 2 1752 Villars-sur-gl\u00e2ne. Postfach",
    "sg:city":"Cormanon",
    "sg:orig_category":"Grosshandel mit Datenverarbeitungsger\u00e4ten Softwareentwicklung U beratung",
    "sg:phone":"+41 26 401 04 03",
    "sg:postcode":"1752",
    "sg:province":"Fribourg",
    "wof:name":"Xpert Technologies Sa Softwares Originaux De Management, De Direction Etc.; D\u00e9velopp.",
    "wof:placetype":"venue"
},
  "geometry": {"coordinates":[7.1267280579,46.7985572815],"type":"Point"}
}