{
  "type": "Feature",
  "properties": {
    "iso:country":"CH",
    "sg:address":"Hofstrasse 3 8590 Romanshorn. Postfach",
    "sg:city":"Romanshorn",
    "sg:orig_category":"Herstellung von Armaturen",
    "sg:phone":"+41 71 466 90 10",
    "sg:postcode":"8590",
    "sg:province":"Thurgau",
    "wof:name":"Sidler Metallwaren Ag Metallwaren; Herst, Handel",
    "wof:placetype":"venue"
},
  "geometry": {"coordinates":[9.3685369492,47.5583572388],"type":"Point"}
}