{
  "type": "Feature",
  "properties": {
    "iso:country":"CH",
    "sg:address":"Unterer Quai 102a",
    "sg:city":"Biel/bienne",
    "sg:orig_category":"Unternehmensberatung",
    "sg:phone":"+41 32 322 51 66",
    "sg:postcode":"2502",
    "sg:province":"Bern",
    "wof:name":"Dieter Feller & Partner Management & Pers.ber. Gmbh",
    "wof:placetype":"venue"
},
  "geometry": {"coordinates":[7.2453417778,47.1361846924],"type":"Point"}
}