{
  "type": "Feature",
  "properties": {
    "iso:country":"CH",
    "sg:address":"Rosenbergstrasse 69",
    "sg:city":"St.gallen",
    "sg:orig_category":"Herstellung von sonstigen Metallwaren",
    "sg:phone":"+41 19321262",
    "sg:postcode":"9000",
    "sg:province":"St. Gallen",
    "wof:name":"Reinhold K\u00f6hli Gravuren",
    "wof:placetype":"venue"
},
  "geometry": {"coordinates":[8.7934789658,47.3201560974],"type":"Point"}
}