{
  "type": "Feature",
  "properties": {
    "iso:country":"CH",
    "sg:address":"H\u00fchnerhubelstrasse 87",
    "sg:city":"Belp",
    "sg:orig_category":"Instandhaltung U Reparatur von Automobilen",
    "sg:phone":"+41 77523775",
    "sg:postcode":"3123",
    "sg:province":"Bern",
    "wof:name":"Abag Nutzfahrzeug Center",
    "wof:placetype":"venue"
},
  "geometry": {"coordinates":[7.4943599701,46.9054946899],"type":"Point"}
}