{
  "type": "Feature",
  "properties": {
    "iso:country":"CH",
    "sg:address":"Atrium 1 3175 Flamatt. Postfach",
    "sg:city":"Flamatt",
    "sg:orig_category":"Grosshandel mit sonstigen Gebrauchs U Verbrauchsg\u00fctern",
    "sg:postcode":"3175",
    "sg:province":"Fribourg",
    "wof:name":"Schlatter Trading",
    "wof:placetype":"venue"
},
  "geometry": {"coordinates":[7.325302124,46.8909759521],"type":"Point"}
}