{
  "type": "Feature",
  "properties": {
    "iso:country":"CH",
    "sg:address":"Kohlenweg 24 3097 Liebefeld. Postfach",
    "sg:city":"Liebefeld",
    "sg:orig_category":"Zahnarztpraxen",
    "sg:phone":"+41 31 971 53 19",
    "sg:postcode":"3097",
    "sg:province":"Bern",
    "wof:name":"Dr. Med. Dent. Peter Spycher Zahnarzt",
    "wof:placetype":"venue"
},
  "geometry": {"coordinates":[7.420814991,46.9329338074],"type":"Point"}
}