{
  "type": "Feature",
  "properties": {
    "iso:country":"CH",
    "sg:address":"Via Cantonale 3",
    "sg:city":"Savosa",
    "sg:classifiers":[
        {
            "category":"Bars & Pubs",
            "type":"Food & Drink"
        }
    ],
    "sg:phone":"+41 91 966 62 97",
    "sg:postcode":"6942",
    "sg:province":"Ticino",
    "wof:name":"Bar Siesta",
    "wof:placetype":"venue"
},
  "geometry": {"coordinates":[8.949513,46.022968],"type":"Point"}
}