{
  "type": "Feature",
  "properties": {
    "iso:country":"CH",
    "sg:address":"Poststrasse 13",
    "sg:city":"Liestal",
    "sg:orig_category":"Pensionskassen",
    "sg:phone":"+41 61 921 08 44",
    "sg:postcode":"4410",
    "sg:province":"Basel-Landschaft",
    "wof:name":"Personalvorsorgestiftung Der Firma Werner Koller Ag Und Aff. Firmen",
    "wof:placetype":"venue"
},
  "geometry": {"coordinates":[7.7341899872,47.4826698303],"type":"Point"}
}