{
  "type": "Feature",
  "properties": {
    "iso:country":"CH",
    "sg:address":"Hertistrasse 29",
    "sg:city":"Wallisellen",
    "sg:orig_category":"Architektur U Ingenieurb\u00fcros",
    "sg:postcode":"8304",
    "sg:province":"Z\u00fcrich",
    "wof:name":"Hans Stadtmann",
    "wof:placetype":"venue"
},
  "geometry": {"coordinates":[8.576237,47.416195],"type":"Point"}
}