{
  "type": "Feature",
  "properties": {
    "iso:country":"CH",
    "sg:address":"Seefeldquai 3",
    "sg:city":"Walchwil",
    "sg:orig_category":"Verkehrsmittel, Automobil, Sonstige Automobilthemen",
    "sg:phone":"+41 41 758 11 77",
    "sg:postcode":"6318",
    "sg:province":"Zug",
    "wof:name":"Zugerseegarage Walchwil",
    "wof:placetype":"venue"
},
  "geometry": {"coordinates":[8.517592,47.095753],"type":"Point"}
}