{
  "type": "Feature",
  "properties": {
    "iso:country":"CH",
    "sg:address":"Schulhausgasse 16",
    "sg:city":"M\u00fcnsingen",
    "sg:orig_category":"W\u00e4scherei U chemische Reinigung",
    "sg:phone":"+41 81 833 32 44",
    "sg:postcode":"3110",
    "sg:province":"Bern",
    "wof:name":"Knecht Ag Chemische Reinigung St. Moritz",
    "wof:placetype":"venue"
},
  "geometry": {"coordinates":[9.8377103806,46.4975395203],"type":"Point"}
}