{
  "type": "Feature",
  "properties": {
    "iso:country":"CH",
    "sg:address":"Route D'yverdon 3",
    "sg:city":"Cheseaux-lausanne",
    "sg:orig_category":"Fachdetailhandel mit pharmazeutischen Produkten",
    "sg:phone":"+41 21 731 36 36",
    "sg:postcode":"1033",
    "sg:province":"Vaud",
    "wof:name":"Pharmacie Du Centre Alexandra Monney",
    "wof:placetype":"venue"
},
  "geometry": {"coordinates":[6.6070861816,46.590637207],"type":"Point"}
}