{
  "type": "Feature",
  "properties": {
    "iso:country":"CH",
    "sg:address":"M\u00fchlebachstrasse 20",
    "sg:city":"Z\u00fcrich",
    "sg:orig_category":"Interessenvertretungen",
    "sg:postcode":"8008",
    "sg:province":"Z\u00fcrich",
    "wof:name":"Heinrich-huber-stiftung F\u00fcr Ueberseer",
    "wof:placetype":"venue"
},
  "geometry": {"coordinates":[8.5497961044,47.3651123047],"type":"Point"}
}