{
  "type": "Feature",
  "properties": {
    "iso:country":"CH",
    "sg:address":"Dornacherstrasse 18",
    "sg:city":"Solothurn",
    "sg:orig_category":"RESTAURANTS: TEA-ROOMS",
    "sg:phone":"+41 32 622 21 10",
    "sg:postcode":"4500",
    "sg:province":"Solothurn",
    "wof:name":"China-restaurant Fu-lin",
    "wof:placetype":"venue"
},
  "geometry": {"coordinates":[7.5390868187,47.2036972046],"type":"Point"}
}