{
  "type": "Feature",
  "properties": {
    "iso:country":"CH",
    "sg:address":"Grande-rue 14",
    "sg:city":"Ponts-de-martel",
    "sg:orig_category":"Detailhandel mit Geschenkartikeln U Souvenirs",
    "sg:phone":"+41 41 480 42 12",
    "sg:postcode":"2316",
    "sg:province":"Neuch\u00e2tel",
    "wof:name":"Richard Marti Gravuren Zinnwaren",
    "wof:placetype":"venue"
},
  "geometry": {"coordinates":[8.0542221069,46.9802818298],"type":"Point"}
}