{
  "type": "Feature",
  "properties": {
    "addr:full":"Grendelstr 5 Luzern Luzern 6000",
    "addr:housenumber":"5",
    "addr:postcode":"6000",
    "addr:street":"Grendelstr",
    "iso:country":"CH",
    "sg:address":"Grendelstr 5",
    "sg:city":"Luzern",
    "sg:classifiers":[
        {
            "category":"Banks & Credit Unions",
            "subcategory":"Bank",
            "type":"Services"
        }
    ],
    "sg:phone":"+41 4141292915",
    "sg:postcode":"6000",
    "sg:province":"Luzern",
    "wof:name":"Luzerner Kantonalbank",
    "wof:placetype":"venue"
},
  "geometry": {"coordinates":[8.308235,47.053368],"type":"Point"}
}