{
  "type": "Feature",
  "properties": {
    "iso:country":"CH",
    "sg:address":"Schachenstrasse 17 6010 Kriens. Postfach 89",
    "sg:city":"Kriens",
    "sg:orig_category":"Druck ohne Zeitungsdruck Offsetdruck",
    "sg:phone":"+41 19292681",
    "sg:postcode":"6011",
    "sg:province":"Luzern",
    "wof:name":"Dzo Druck Oetwil A.s. Ag",
    "wof:placetype":"venue"
},
  "geometry": {"coordinates":[8.72676754,47.2749938965],"type":"Point"}
}