{
  "type": "Feature",
  "properties": {
    "addr:full":"M\u00e4schacker 14 Rottenschwil Aargau 8919",
    "addr:housenumber":"14",
    "addr:postcode":"8919",
    "addr:street":"Maeschacker",
    "iso:country":"CH",
    "sg:address":"M\u00e4schacker 14",
    "sg:city":"Rottenschwil",
    "sg:classifiers":[
        {
            "category":"Shopping",
            "subcategory":"Thrift Store",
            "type":"Retail Goods"
        }
    ],
    "sg:phone":"+41 56 634 22 21",
    "sg:postcode":"8919",
    "sg:province":"Aargau",
    "sg:tags":[
        "gesundheit",
        "u",
        "fachgesch\u00e4fte"
    ],
    "wof:name":"Caretex Hygiene Und Allergie-center",
    "wof:placetype":"venue"
},
  "geometry": {"coordinates":[8.360089,47.309738],"type":"Point"}
}