{
  "type": "Feature",
  "properties": {
    "iso:country":"CH",
    "sg:address":"Freimettigenstrasse 12",
    "sg:city":"Konolfingen",
    "sg:classifiers":[
        {
            "category":"Government",
            "subcategory":"Fire Station",
            "type":"Public Place"
        }
    ],
    "sg:phone":"+41 31 791 14 12",
    "sg:postcode":"3510",
    "sg:province":"Bern",
    "sg:tags":[
        "supraregional",
        "plant",
        "installation",
        "heating"
    ],
    "wof:name":"Brechb\u00fchl Ag",
    "wof:placetype":"venue"
},
  "geometry": {"coordinates":[7.6229009628,46.871547699],"type":"Point"}
}