{
  "type": "Feature",
  "properties": {
    "iso:country":"CH",
    "sg:address":"Bahnhofstrasse 16",
    "sg:city":"Sursee",
    "sg:orig_category":"K\u00fcnstlerische Schulen",
    "sg:phone":"+41 41 921 71 04",
    "sg:postcode":"6210",
    "sg:province":"Luzern",
    "wof:name":"Musikschule Der Stadt Sekretariat",
    "wof:placetype":"venue"
},
  "geometry": {"coordinates":[8.1051187515,47.1727180481],"type":"Point"}
}