{
  "type": "Feature",
  "properties": {
    "iso:country":"CH",
    "sg:address":"Gr\u00fcnaustrasse 25",
    "sg:city":"Burgdorf",
    "sg:orig_category":"Softwareentwicklung U beratung",
    "sg:postcode":"3400",
    "sg:province":"Bern",
    "wof:name":"Programmierb\u00fcro Jost",
    "wof:placetype":"venue"
},
  "geometry": {"coordinates":[7.6243829727,47.052898407],"type":"Point"}
}