{
  "type": "Feature",
  "properties": {
    "iso:country":"CH",
    "sg:address":"Apfelseestrasse 11 4143 Dornach. Postfach",
    "sg:city":"Dornach",
    "sg:orig_category":"Instandhaltung U Reparatur von Automobilen",
    "sg:postcode":"4143",
    "sg:province":"Solothurn",
    "wof:name":"L-s-l, Land-see Und Luftfahrzeuge, Gabriele Krauss",
    "wof:placetype":"venue"
},
  "geometry": {"coordinates":[7.6087670326,47.4755935669],"type":"Point"}
}