{
  "type": "Feature",
  "properties": {
    "iso:country":"CH",
    "sg:address":"Durisolstrasse 11",
    "sg:city":"Villmergen",
    "sg:orig_category":"Pensionskassen",
    "sg:phone":"+41 61 811 12 95",
    "sg:postcode":"5612",
    "sg:province":"Aargau",
    "wof:name":"Vorsorgestiftung Der Moritz Ag Malergesch\u00e4ft",
    "wof:placetype":"venue"
},
  "geometry": {"coordinates":[7.7236819267,47.5327301025],"type":"Point"}
}