{
  "type": "Feature",
  "properties": {
    "iso:country":"CH",
    "sg:address":"Tivoli",
    "sg:city":"Spreitenbach",
    "sg:orig_category":"Detailhandel mit Haustieren U zoologischem Bedarf Fachdetailhandel in Verkaufsr\u00e4umen",
    "sg:phone":"+41 56 621 12 81",
    "sg:postcode":"8957",
    "sg:province":"Aargau",
    "wof:name":"Tropic-zoo Schmid Gmbh Tropic-zoo Westernshop",
    "wof:placetype":"venue"
},
  "geometry": {"coordinates":[8.2762060165,47.3496170044],"type":"Point"}
}