{
  "type": "Feature",
  "properties": {
    "iso:country":"CH",
    "sg:address":"Mittelstrasse 45d",
    "sg:city":"Kirchlindach",
    "sg:classifiers":[
        {
            "category":"Travel",
            "subcategory":"Hotels & Motels",
            "type":"Entertainment"
        }
    ],
    "sg:phone":"+41 31 829 07 58",
    "sg:postcode":"3038",
    "sg:province":"Bern",
    "sg:tags":[
        "hotels",
        "mit",
        "restaurant"
    ],
    "wof:name":"Gala Restaurationsbetriebe Ag",
    "wof:placetype":"venue"
},
  "geometry": {"coordinates":[7.4232711792,46.9949302673],"type":"Point"}
}