{
  "type": "Feature",
  "properties": {
    "iso:country":"CH",
    "sg:address":"Forelstrasse 1",
    "sg:city":"Ostermundigen",
    "sg:orig_category":"Sonstiger Fachdetailhandel mit Nahrungsmitteln, Getr\u00e4nken U Tabak in Verkaufsr\u00e4umen",
    "sg:phone":"+41 31 930 21 11",
    "sg:postcode":"3072",
    "sg:province":"Bern",
    "wof:name":"Toni Holding Ag",
    "wof:placetype":"venue"
},
  "geometry": {"coordinates":[7.4820199013,46.9598808289],"type":"Point"}
}