{
  "type": "Feature",
  "properties": {
    "iso:country":"CH",
    "sg:address":"Oberdorfstrasse 356",
    "sg:city":"Wernetshausen",
    "sg:orig_category":"Instandhaltung U Reparatur von Automobilen",
    "sg:phone":"+41 32 924 54 54",
    "sg:postcode":"8342",
    "sg:province":"Z\u00fcrich",
    "wof:name":"Entilles-stand Sa",
    "wof:placetype":"venue"
},
  "geometry": {"coordinates":[6.7602138519,47.0635910034],"type":"Point"}
}