{
  "type": "Feature",
  "properties": {
    "iso:country":"CH",
    "sg:address":"Sterenweg 3",
    "sg:city":"Zug",
    "sg:orig_category":"Wirtschaftspr\u00fcfung, Steuerberatung U Treuhand",
    "sg:postcode":"6300",
    "sg:province":"Zug",
    "wof:name":"Peter Knaus, Treuhand Und Revisionsb\u00fcro",
    "wof:placetype":"venue"
},
  "geometry": {"coordinates":[9.4216632843,47.3971443176],"type":"Point"}
}