{
  "type": "Feature",
  "properties": {
    "iso:country":"CH",
    "sg:address":"An Der Wart 7 6142 Gettnau. Postfach",
    "sg:city":"Gettnau",
    "sg:orig_category":"Sonstige mit Sport verbundene T\u00e4tigkeiten",
    "sg:phone":"+41 32 652 88 44",
    "sg:postcode":"6142",
    "sg:province":"Luzern",
    "wof:name":"Segel Und Motorfluggruppe Grenchen",
    "wof:placetype":"venue"
},
  "geometry": {"coordinates":[7.4042401314,47.1997337341],"type":"Point"}
}