{
  "type": "Feature",
  "properties": {
    "iso:country":"CH",
    "sg:address":"Rheinstrasse 64",
    "sg:city":"Chur",
    "sg:orig_category":"Sportvereine Unihockey",
    "sg:phone":"+41 81 284 71 77",
    "sg:postcode":"7000",
    "sg:province":"Graubunden",
    "wof:name":"Uhc Rot-weiss Chur",
    "wof:placetype":"venue"
},
  "geometry": {"coordinates":[9.5219669342,46.854850769],"type":"Point"}
}