{
  "type": "Feature",
  "properties": {
    "iso:country":"CH",
    "sg:address":"Gr\u00e4nicherstrasse 1 5034 Suhr. Postfach",
    "sg:city":"Suhr",
    "sg:orig_category":"Detailhandel mit Waren verschiedener Art, Hauptrichtung Nahrungsmittel Verarbeitung von Milch",
    "sg:phone":"+41 62 842 33 07",
    "sg:postcode":"5034",
    "sg:province":"Aargau",
    "wof:name":"Landi Suhr Und Umgebung",
    "wof:placetype":"venue"
},
  "geometry": {"coordinates":[8.079750061,47.3702545166],"type":"Point"}
}