{
  "type": "Feature",
  "properties": {
    "iso:country":"CH",
    "sg:address":"Place Du Bourg-de-four 31",
    "sg:city":"Gen\u00e8ve",
    "sg:classifiers":[
        {
            "category":"Bars & Pubs",
            "type":"Food & Drink"
        }
    ],
    "sg:phone":"+41 22 310 44 98",
    "sg:postcode":"1204",
    "sg:province":"Gen\u00e8ve",
    "sg:tags":[
        "restaurant"
    ],
    "wof:name":"Bar-pizzeria Navy Club",
    "wof:placetype":"venue"
},
  "geometry": {"coordinates":[6.148558,46.199783],"type":"Point"}
}