{
  "type": "Feature",
  "properties": {
    "iso:country":"CH",
    "sg:address":"Avenue De La Fusion 66",
    "sg:city":"Martigny",
    "sg:orig_category":"Architektur U Ingenieurb\u00fcros",
    "sg:phone":"+41 27 722 67 67",
    "sg:postcode":"1920",
    "sg:province":"Valais",
    "wof:name":"Cuypers & Maret Sa",
    "wof:placetype":"venue"
},
  "geometry": {"coordinates":[7.065401,46.098083],"type":"Point"}
}