{
  "type": "Feature",
  "properties": {
    "iso:country":"CH",
    "sg:address":"Hanfp\u00fcnt 14",
    "sg:city":"Schaffhausen",
    "sg:orig_category":"Sonstige Institutionen des Sozialwesens ohne Beherbergung",
    "sg:phone":"+41 52 624 76 47",
    "sg:postcode":"8207",
    "sg:province":"Schaffhausen",
    "wof:name":"La Leche Liga",
    "wof:placetype":"venue"
},
  "geometry": {"coordinates":[8.6600885391,47.7243118286],"type":"Point"}
}