{
  "type": "Feature",
  "properties": {
    "iso:country":"CH",
    "sg:address":"Messinastrasse 33",
    "sg:city":"Triesen",
    "sg:orig_category":"Autogaragen",
    "sg:phone":"+423 392 45 80",
    "sg:postcode":"9495",
    "wof:name":"Negele Automobile Ag Garage",
    "wof:placetype":"venue"
},
  "geometry": {"coordinates":[9.5190105438,47.1221580505],"type":"Point"}
}