{
  "type": "Feature",
  "properties": {
    "iso:country":"CH",
    "sg:address":"Kapfweid 21",
    "sg:city":"Emmenbr\u00fccke",
    "sg:orig_category":"Sanit\u00e4r U Heizungsinstallation Sanit\u00e4rinstallation",
    "sg:phone":"+41 41 280 10 70",
    "sg:postcode":"6020",
    "sg:province":"Luzern",
    "wof:name":"Aspa Ag,planung & Installation F.heizung/sanit\u00e4r & Klima",
    "wof:placetype":"venue"
},
  "geometry": {"coordinates":[8.2758893967,47.0883102417],"type":"Point"}
}