{
  "type": "Feature",
  "properties": {
    "iso:country":"CH",
    "sg:address":"Ebenaustrasse 8",
    "sg:city":"Horw",
    "sg:orig_category":"Herstellung von Betonerzeugnissen f\u00fcr den Bau",
    "sg:postcode":"6048",
    "sg:province":"Luzern",
    "wof:name":"Gut Element Ag",
    "wof:placetype":"venue"
},
  "geometry": {"coordinates":[8.3126506805,46.9965934753],"type":"Point"}
}