{
  "type": "Feature",
  "properties": {
    "iso:country":"CH",
    "sg:address":"Schachenstrasse 23",
    "sg:city":"Oensingen",
    "sg:orig_category":"Sonstige pers\u00f6nliche Dienstleistungen",
    "sg:postcode":"4702",
    "sg:province":"Solothurn",
    "wof:name":"Sun-schein Marti-schaad Christina",
    "wof:placetype":"venue"
},
  "geometry": {"coordinates":[7.7106099129,47.2896232605],"type":"Point"}
}