{
  "type": "Feature",
  "properties": {
    "iso:country":"CH",
    "sg:address":"Les P\u00e2quis",
    "sg:city":"Curtilles",
    "sg:orig_category":"Grosshandel mit Schmuck Grosshandel mit Uhren",
    "sg:phone":"+41 21 906 96 80",
    "sg:postcode":"1521",
    "sg:province":"Vaud",
    "wof:name":"Patrick Coutaz Repr\u00e9sent.d'horlogerie Bijout.",
    "wof:placetype":"venue"
},
  "geometry": {"coordinates":[6.8480348587,46.6969566345],"type":"Point"}
}