{
  "type": "Feature",
  "properties": {
    "iso:country":"CH",
    "sg:address":"Gartenstrasse 35",
    "sg:city":"Sarnen",
    "sg:orig_category":"Instandhaltung U Reparatur von Automobilen",
    "sg:phone":"+41 41 662 02 02",
    "sg:postcode":"6060",
    "sg:province":"Obwalden",
    "wof:name":"Thomas Garage Burch & Britschgi",
    "wof:placetype":"venue"
},
  "geometry": {"coordinates":[8.2497596741,46.9018859863],"type":"Point"}
}