{
  "type": "Feature",
  "properties": {
    "iso:country":"CH",
    "sg:address":"Zellfeld",
    "sg:city":"Schenkon",
    "sg:orig_category":"Herstellung von Automobilen Herstellung von Metallerzeugnissen ohne Maschinenbau",
    "sg:phone":"+41 79 641 53 41",
    "sg:postcode":"6214",
    "sg:province":"Luzern",
    "wof:name":"Rast Ernst Armeefahrzeuge",
    "wof:placetype":"venue"
},
  "geometry": {"coordinates":[8.1263837814,47.1813163757],"type":"Point"}
}