{
  "type": "Feature",
  "properties": {
    "iso:country":"CH",
    "sg:address":"Diolly",
    "sg:city":"Sion",
    "sg:orig_category":"Medizinische Anstalten",
    "sg:phone":"+41 27 395 34 30",
    "sg:postcode":"1950",
    "sg:province":"Valais",
    "wof:name":"Diollymed Centre M\u00e9dical Chirurgie De Jour",
    "wof:placetype":"venue"
},
  "geometry": {"coordinates":[7.3425841331,46.235534668],"type":"Point"}
}