{
  "type": "Feature",
  "properties": {
    "iso:country":"CH",
    "sg:address":"H\u00f6henweg 3b",
    "sg:city":"Zug",
    "sg:orig_category":"Architekturb\u00fcros",
    "sg:phone":"+41 41 711 11 28",
    "sg:postcode":"6300",
    "sg:province":"Zug",
    "wof:name":"Walter Flueler Architekturb\u00fcro",
    "wof:placetype":"venue"
},
  "geometry": {"coordinates":[8.520055,47.166336],"type":"Point"}
}