{
  "type": "Feature",
  "properties": {
    "iso:country":"CH",
    "sg:address":"Tuffi\u00e8re Route De La 126",
    "sg:city":"Magnedens",
    "sg:orig_category":"Betrieb von Sportanlagen",
    "sg:postcode":"1727",
    "sg:province":"Fribourg",
    "wof:name":"Minigolf Ag Murten",
    "wof:placetype":"venue"
},
  "geometry": {"coordinates":[7.108453,46.925232],"type":"Point"}
}