{
  "type": "Feature",
  "properties": {
    "iso:country":"CH",
    "sg:address":"Pr\u00e9barreau Rue De 5",
    "sg:city":"Neuch\u00e2tel",
    "sg:orig_category":"Herstellung von sonstigen Maschinen f\u00fcr unspezifische Verwendung",
    "sg:postcode":"2000",
    "sg:province":"Neuch\u00e2tel",
    "wof:name":"Accebel Sa",
    "wof:placetype":"venue"
},
  "geometry": {"coordinates":[6.9238181114,46.9918861389],"type":"Point"}
}