{
  "type": "Feature",
  "properties": {
    "iso:country":"CH",
    "sg:address":"Hauptstrasse Gundetswil 8546 Islikon. Postfach",
    "sg:city":"Islikon",
    "sg:orig_category":"Bauschreinerei Zimmerei, Ingenieurholzbau",
    "sg:phone":"+41 52 375 10 37",
    "sg:postcode":"8546",
    "sg:province":"Thurgau",
    "wof:name":"Andreas Huggler Zimmerei & Schreinerei",
    "wof:placetype":"venue"
},
  "geometry": {"coordinates":[8.84183,47.545471],"type":"Point"}
}