{
  "type": "Feature",
  "properties": {
    "iso:country":"CH",
    "sg:address":"Lindachstrasse 7",
    "sg:city":"Kirchlindach",
    "sg:orig_category":"Vorschulen, Kinderg\u00e4rten",
    "sg:phone":"+41 31 829 18 42",
    "sg:postcode":"3038",
    "sg:province":"Bern",
    "wof:name":"Kindergarten",
    "wof:placetype":"venue"
},
  "geometry": {"coordinates":[7.4107308388,46.9992141724],"type":"Point"}
}