{
  "type": "Feature",
  "properties": {
    "iso:country":"CH",
    "sg:address":"Dorfstrasse 24",
    "sg:city":"Triesen",
    "sg:orig_category":"Unternehmensberatung",
    "sg:phone":"+41 75 392 33 23",
    "sg:postcode":"9495",
    "wof:name":"Wagner Communications Gmbh",
    "wof:placetype":"venue"
},
  "geometry": {"coordinates":[9.5265855789,47.1083183289],"type":"Point"}
}