{
  "type": "Feature",
  "properties": {
    "addr:full":"Badhaus Heimenschwand Bern 3615",
    "addr:postcode":"3615",
    "iso:country":"CH",
    "sg:address":"Badhaus",
    "sg:city":"Heimenschwand",
    "sg:classifiers":[
        {
            "category":"Banks & Credit Unions",
            "subcategory":"Bank",
            "type":"Services"
        }
    ],
    "sg:phone":"+41 33532533",
    "sg:postcode":"3615",
    "sg:province":"Bern",
    "wof:name":"Raiffeisenbank",
    "wof:placetype":"venue"
},
  "geometry": {"coordinates":[7.696945,46.828621],"type":"Point"}
}