{
  "type": "Feature",
  "properties": {
    "iso:country":"CH",
    "sg:address":"Sous Le Ch\u00e2teau-grillet",
    "sg:city":"Vich",
    "sg:orig_category":"HOTELS: MIT RESTAURANT RESTAURANTS: NICHT EIGENST\u00c4NDIG",
    "sg:phone":"+41 81 833 20 60",
    "sg:postcode":"1267",
    "sg:province":"Vaud",
    "wof:name":"Landgasthof Meierei",
    "wof:placetype":"venue"
},
  "geometry": {"coordinates":[9.8605985641,46.4949035645],"type":"Point"}
}