{
  "type": "Feature",
  "properties": {
    "iso:country":"CH",
    "sg:address":"Hinteres Werd 4",
    "sg:city":"Heiden",
    "sg:orig_category":"Sonstige mit der Informatik verbundene T\u00e4tigkeiten",
    "sg:postcode":"9410",
    "sg:province":"Appenzell Ausserrhoden",
    "wof:name":"Huss Individual Informatik Training & Consulting",
    "wof:placetype":"venue"
},
  "geometry": {"coordinates":[9.5280160904,47.4488525391],"type":"Point"}
}