{
  "type": "Feature",
  "properties": {
    "iso:country":"CH",
    "sg:address":"Tellerweg 17 4102 Binningen. Postfach",
    "sg:city":"Binningen",
    "sg:orig_category":"Vermietung U Verpachtung von eigenen Immobilien",
    "sg:postcode":"4102",
    "sg:province":"Basel-Landschaft",
    "wof:name":"Bpz Immobilien Ag",
    "wof:placetype":"venue"
},
  "geometry": {"coordinates":[7.5603852272,47.5317306519],"type":"Point"}
}