{
  "type": "Feature",
  "properties": {
    "iso:country":"CH",
    "sg:address":"Feldblumenstrasse 27",
    "sg:city":"Adliswil",
    "sg:orig_category":"Wirtschaftspr\u00fcfung, Steuerberatung U Treuhand",
    "sg:phone":"+41 41 920 35 64",
    "sg:postcode":"8134",
    "sg:province":"Z\u00fcrich",
    "wof:name":"Zendron Consulting",
    "wof:placetype":"venue"
},
  "geometry": {"coordinates":[8.5162725449,47.3145942688],"type":"Point"}
}