{
  "type": "Feature",
  "properties": {
    "iso:country":"CH",
    "sg:address":"H\u00e4rdlistrasse 11",
    "sg:city":"Eichberg",
    "sg:orig_category":"Interessenvertretungen",
    "sg:postcode":"9453",
    "sg:province":"St. Gallen",
    "wof:name":"Bossert-walt Emma Stiftung",
    "wof:placetype":"venue"
},
  "geometry": {"coordinates":[9.5316867828,47.3432197571],"type":"Point"}
}