{
  "type": "Feature",
  "properties": {
    "iso:country":"CH",
    "sg:address":"Chileweid 1",
    "sg:city":"Rain",
    "sg:orig_category":"Wirtschaftspr\u00fcfung, Steuerberatung U Treuhand",
    "sg:phone":"+41 41 458 15 75",
    "sg:postcode":"6026",
    "sg:province":"Luzern",
    "wof:name":"Btr Buchhaltung Und Treuhand Rain H.r. Waldis",
    "wof:placetype":"venue"
},
  "geometry": {"coordinates":[8.2591743469,47.1283073425],"type":"Point"}
}