{
  "type": "Feature",
  "properties": {
    "iso:country":"CH",
    "sg:address":"Brisenstrasse 4",
    "sg:city":"Kriens",
    "sg:classifiers":[
        {
            "category":"Food & Beverages",
            "subcategory":"Bakery",
            "type":"Retail Goods"
        }
    ],
    "sg:phone":"+41 41 310 66 16",
    "sg:postcode":"6010",
    "sg:province":"Luzern",
    "sg:tags":[
        "baking",
        "powder"
    ],
    "wof:name":"Kurt Burkart Ag",
    "wof:placetype":"venue"
},
  "geometry": {"coordinates":[8.290987,47.032047],"type":"Point"}
}