{
  "type": "Feature",
  "properties": {
    "iso:country":"CH",
    "sg:address":"Frohburgstr. 100",
    "sg:city":"Zuerich",
    "sg:classifiers":[
        {
            "category":"Professional",
            "subcategory":"Computer Services",
            "type":"Services"
        }
    ],
    "sg:postcode":"8006",
    "sg:tags":[
        "mobile",
        "mobile-social-networking",
        "mobile-community",
        "ugc",
        "mobile-space",
        "white-label",
        "hosted-solution",
        "java-client"
    ],
    "sg:website":"http://www.mpw.mobi",
    "wof:name":"mpw Technologies",
    "wof:placetype":"venue"
},
  "geometry": {"coordinates":[8.550481,47.392111],"type":"Point"}
}