{
  "type": "Feature",
  "properties": {
    "iso:country":"CH",
    "sg:address":"Neustrasse 17",
    "sg:city":"Triboltingen",
    "sg:orig_category":"Sanit\u00e4r, Heizungs U L\u00fcftungsinstallation Sanit\u00e4rinstallation",
    "sg:phone":"+41 71 660 06 70",
    "sg:postcode":"8273",
    "sg:province":"Thurgau",
    "wof:name":"Fugo Ag",
    "wof:placetype":"venue"
},
  "geometry": {"coordinates":[9.1074867249,47.6604766846],"type":"Point"}
}