{
  "type": "Feature",
  "properties": {
    "iso:country":"CH",
    "sg:address":"4574",
    "sg:city":"Nennigkofen",
    "sg:orig_category":"Verwertung von Milch",
    "sg:postcode":"4574",
    "sg:province":"Solothurn",
    "wof:name":"K\u00e4sereigenossenschaft L\u00fcsslingen",
    "wof:placetype":"venue"
},
  "geometry": {"coordinates":[7.4929361343,47.1867485046],"type":"Point"}
}