{
  "type": "Feature",
  "properties": {
    "iso:country":"CH",
    "sg:address":"Neugasse 18",
    "sg:city":"Zug",
    "sg:orig_category":"Fachdetailhandel in Verkaufsr\u00e4umen",
    "sg:phone":"+41 41 711 17 38",
    "sg:postcode":"6300",
    "sg:province":"Zug",
    "wof:name":"Schorro Ernst",
    "wof:placetype":"venue"
},
  "geometry": {"coordinates":[8.5153312683,47.1667518616],"type":"Point"}
}