{
  "type": "Feature",
  "properties": {
    "iso:country":"CH",
    "sg:address":"Route Du Ch\u00e2teau-d'affry 8 1762 Givisiez. Postfach",
    "sg:city":"Givisiez",
    "sg:orig_category":"Detailhandel mit Blumen U Pflanzen Fachdetailhandel in Verkaufsr\u00e4umen",
    "sg:phone":"+41 26 466 65 85",
    "sg:postcode":"1762",
    "sg:province":"Fribourg",
    "wof:name":"La Fleur D'oranger, Waeber-deschenaux Yvette Fleurs; Commerce",
    "wof:placetype":"venue"
},
  "geometry": {"coordinates":[1.553038,49.24778],"type":"Point"}
}