{
  "type": "Feature",
  "properties": {
    "iso:country":"CH",
    "sg:address":"K\u00f6llikerstr. 80",
    "sg:city":"Oberentfelden",
    "sg:classifiers":[
        {
            "category":"Home & Garden",
            "subcategory":"Furniture",
            "type":"Retail Goods"
        }
    ],
    "sg:phone":"+41 31 311 70 11",
    "sg:postcode":"5036",
    "sg:province":"Aargau",
    "sg:tags":[
        "household",
        "wood"
    ],
    "wof:name":"Utiger M\u00d6bel Und Bettenhaus",
    "wof:placetype":"venue"
},
  "geometry": {"coordinates":[7.4009480476,46.942199707],"type":"Point"}
}