{
  "type": "Feature",
  "properties": {
    "iso:country":"CH",
    "sg:address":"Stutzstrasse 135",
    "sg:city":"Schellenberg",
    "sg:orig_category":"Malerei-Gipserei Stukkateurgewerbe, Gipserei U Verputzerei",
    "sg:phone":"+423 373 12 78",
    "sg:postcode":"9488",
    "wof:name":"Josef Goop Gipsergesch\u00e4ft",
    "wof:placetype":"venue"
},
  "geometry": {"coordinates":[9.5486297607,47.2276115417],"type":"Point"}
}