{
  "type": "Feature",
  "properties": {
    "iso:country":"CH",
    "sg:address":"Montchoisy Rue De 17 1207 Gen\u00e8ve. Postfach",
    "sg:city":"Gen\u00e8ve",
    "sg:orig_category":"Herstellung von konfektionierten Textilwaren ohne Bekleidung",
    "sg:postcode":"1201",
    "sg:province":"Gen\u00e8ve",
    "wof:name":"Arr\u00eat D\u00e9co, Ballivet Loredana Et Lamonato Ada",
    "wof:placetype":"venue"
},
  "geometry": {"coordinates":[6.1601309776,46.2033576965],"type":"Point"}
}