{
  "type": "Feature",
  "properties": {
    "iso:country":"CH",
    "sg:address":"Sonnfeldstrasse 51",
    "sg:city":"Trimbach",
    "sg:orig_category":"Handel mit Automobilen",
    "sg:phone":"+41 62 293 41 51",
    "sg:postcode":"4632",
    "sg:province":"Solothurn",
    "wof:name":"W. Flury & Co",
    "wof:placetype":"venue"
},
  "geometry": {"coordinates":[7.9078979492,47.3618736267],"type":"Point"}
}