{
  "type": "Feature",
  "properties": {
    "iso:country":"CH",
    "sg:address":"Am Suteracher 80",
    "sg:city":"Z\u00fcrich",
    "sg:orig_category":"Detektivb\u00fcros U \u00dcberwachung",
    "sg:postcode":"8048",
    "sg:province":"Z\u00fcrich",
    "wof:name":"Personenschutz-team Von Arx M.",
    "wof:placetype":"venue"
},
  "geometry": {"coordinates":[7.8711690903,47.3493309021],"type":"Point"}
}