{
  "type": "Feature",
  "properties": {
    "iso:country":"CH",
    "sg:address":"Burgstrasse 107",
    "sg:city":"Schlossrued",
    "sg:orig_category":"Sportvereine Sch\u00fctzen",
    "sg:phone":"+41 62 721 49 02",
    "sg:postcode":"5044",
    "sg:province":"Aargau",
    "wof:name":"Sch\u00fctzengesell.staffelbach",
    "wof:placetype":"venue"
},
  "geometry": {"coordinates":[8.0899553299,47.289024353],"type":"Point"}
}