{
  "type": "Feature",
  "properties": {
    "iso:country":"CH",
    "sg:address":"Fontaine Place De La 5",
    "sg:city":"Peseux",
    "sg:orig_category":"Architektur U Ingenieurb\u00fcros",
    "sg:phone":"+41 79 412 82 84",
    "sg:postcode":"2034",
    "sg:province":"Neuch\u00e2tel",
    "wof:name":"Arteg S\u00e0rl",
    "wof:placetype":"venue"
},
  "geometry": {"coordinates":[6.889827,46.987637],"type":"Point"}
}