{
  "type": "Feature",
  "properties": {
    "iso:country":"CH",
    "sg:address":"Niederlenzerstrasse 29 5600 Lenzburg. Postfach",
    "sg:city":"Lenzburg",
    "sg:orig_category":"RESTAURANTS: TEA-ROOMS",
    "sg:postcode":"5600",
    "sg:province":"Aargau",
    "wof:name":"Cantina Gastro Gmbh Restaurant Mit Musik Usw",
    "wof:placetype":"venue"
},
  "geometry": {"coordinates":[8.1803503036,47.3912696838],"type":"Point"}
}