{
  "type": "Feature",
  "properties": {
    "iso:country":"CH",
    "sg:address":"St.gallerstrasse 63",
    "sg:city":"Jona",
    "sg:orig_category":"Reparatur von Schuhen U Lederwaren",
    "sg:phone":"+41 55 212 33 13",
    "sg:postcode":"8645",
    "sg:province":"St. Gallen",
    "wof:name":"Fritz Menzi Schuhmacherei",
    "wof:placetype":"venue"
},
  "geometry": {"coordinates":[8.8410558701,47.2297973633],"type":"Point"}
}