{
  "type": "Feature",
  "properties": {
    "iso:country":"CH",
    "sg:address":"Schwertgasse 4",
    "sg:city":"Glarus",
    "sg:orig_category":"Herstellung von sonstiger Bekleidung U Bekleidungszubeh\u00f6r",
    "sg:phone":"+41 55 640 15 10",
    "sg:postcode":"8750",
    "sg:province":"Glarus",
    "wof:name":"Z\u00fcger-kerber Franziska",
    "wof:placetype":"venue"
},
  "geometry": {"coordinates":[9.0683574677,47.0374603271],"type":"Point"}
}