{
  "type": "Feature",
  "properties": {
    "iso:country":"CH",
    "sg:address":"Temple Rue Du 20",
    "sg:city":"Moudon",
    "sg:orig_category":"RESTAURANTS: TEA-ROOMS",
    "sg:phone":"+41 21 905 12 08",
    "sg:postcode":"1510",
    "sg:province":"Vaud",
    "wof:name":"Gastrogest Sa",
    "wof:placetype":"venue"
},
  "geometry": {"coordinates":[6.7982640266,46.6681213379],"type":"Point"}
}