{
  "type": "Feature",
  "properties": {
    "iso:country":"CH",
    "sg:address":"Kornweg 105",
    "sg:city":"Bern",
    "sg:orig_category":"Schulpflegen",
    "sg:postcode":"3027",
    "sg:province":"Bern",
    "wof:name":"Primarschulkommission Breitfeld",
    "wof:placetype":"venue"
},
  "geometry": {"coordinates":[7.4542298317,46.9628982544],"type":"Point"}
}