{
  "type": "Feature",
  "properties": {
    "iso:country":"CH",
    "sg:address":"Stauftelh\u00fcbel 4",
    "sg:city":"Zeihen",
    "sg:orig_category":"Architekturb\u00fcros",
    "sg:phone":"+41 62 876 17 52",
    "sg:postcode":"5079",
    "sg:province":"Aargau",
    "wof:name":"Eduard W\u00fclser Architekturb\u00fcro",
    "wof:placetype":"venue"
},
  "geometry": {"coordinates":[8.08751,47.476547],"type":"Point"}
}