{
  "type": "Feature",
  "properties": {
    "iso:country":"CH",
    "sg:address":"Heinrichstrasse 109",
    "sg:city":"Z\u00fcrich",
    "sg:orig_category":"Textilveredlung",
    "sg:phone":"+41 12713446",
    "sg:postcode":"8005",
    "sg:province":"Z\u00fcrich",
    "wof:name":"Siebdruckerei T-shirtdruck Atelier Schugk",
    "wof:placetype":"venue"
},
  "geometry": {"coordinates":[8.5285654068,47.3856620789],"type":"Point"}
}