{
  "type": "Feature",
  "properties": {
    "iso:country":"CH",
    "sg:address":"B\u00fcschikon 1",
    "sg:city":"T\u00e4gerig",
    "sg:orig_category":"Schreib U \u00dcbersetzungsb\u00fcros",
    "sg:postcode":"5522",
    "sg:province":"Aargau",
    "wof:name":"Stoll Elisabeth Schreibb\u00fcro",
    "wof:placetype":"venue"
},
  "geometry": {"coordinates":[8.2794570923,47.391002655],"type":"Point"}
}