{
  "type": "Feature",
  "properties": {
    "iso:country":"CH",
    "sg:address":"Gerberstrasse 2",
    "sg:city":"Liestal",
    "sg:classifiers":[
        {
            "category":"Restaurant",
            "type":"Food & Drink"
        }
    ],
    "sg:phone":"+41 61 921 13 11",
    "sg:postcode":"4410",
    "sg:province":"Basel-Landschaft",
    "wof:name":"Restaurant R\u00fctli",
    "wof:placetype":"venue"
},
  "geometry": {"coordinates":[7.7355031967,47.4860420227],"type":"Point"}
}