{
  "type": "Feature",
  "properties": {
    "iso:country":"CH",
    "sg:address":"Wannengut 23",
    "sg:city":"M\u00fchlethal",
    "sg:orig_category":"Unternehmensberatung",
    "sg:phone":"+41 62 751 71 05",
    "sg:postcode":"4812",
    "sg:province":"Aargau",
    "wof:name":"Wypromot Wyser Consulting",
    "wof:placetype":"venue"
},
  "geometry": {"coordinates":[7.9714422226,47.3027839661],"type":"Point"}
}