{
  "type": "Feature",
  "properties": {
    "addr:full":"Granois Savi\u00e8se Valais 1965",
    "addr:postcode":"1965",
    "iso:country":"CH",
    "sg:address":"Granois",
    "sg:city":"Savi\u00e8se",
    "sg:orig_category":"Detailhandel mit Beleuchtungs U Haushaltsgegenst\u00e4nden Elektroinstallation",
    "sg:phone":"+41 22 361 30 31",
    "sg:postcode":"1965",
    "sg:province":"Valais",
    "wof:name":"Bally Louis Et Fils Sa",
    "wof:placetype":"venue"
},
  "geometry": {"coordinates":[6.225828,46.396461],"type":"Point"}
}