{
  "type": "Feature",
  "properties": {
    "addr:full":"Marstallweg 11 Z\u00fcrich Z\u00fcrich 8005",
    "addr:housenumber":"11",
    "addr:postcode":"8005",
    "addr:street":"Marstallweg",
    "iso:country":"CH",
    "sg:address":"Marstallweg 11",
    "sg:city":"Z\u00fcrich",
    "sg:orig_category":"Architektur U Ingenieurb\u00fcros Architekturb\u00fcros",
    "sg:phone":"+41 79 215 44 25",
    "sg:postcode":"8005",
    "sg:province":"Z\u00fcrich",
    "wof:name":"Werner Kaufmann Und Partner Architektur Ag",
    "wof:placetype":"venue"
},
  "geometry": {"coordinates":[7.302385,47.11208],"type":"Point"}
}