{
  "type": "Feature",
  "properties": {
    "iso:country":"CH",
    "sg:address":"Hummelweg 11",
    "sg:city":"Niederuzwil",
    "sg:orig_category":"Bauschreinerei Innenausbau",
    "sg:phone":"+41 71 744 33 15",
    "sg:postcode":"9244",
    "sg:province":"St. Gallen",
    "wof:name":"Friedrich Gois M\u00f6bel-innenausbau",
    "wof:placetype":"venue"
},
  "geometry": {"coordinates":[9.629836,47.453022],"type":"Point"}
}