{
  "type": "Feature",
  "properties": {
    "iso:country":"CH",
    "sg:address":"In B\u00fcten",
    "sg:city":"Thayngen",
    "sg:orig_category":"Detailhandel mit Zeitungen U Zeitschriften Kioske",
    "sg:phone":"+41 52 649 14 00",
    "sg:postcode":"8240",
    "sg:province":"Schaffhausen",
    "wof:name":"Schwimmbad B\u00fcte",
    "wof:placetype":"venue"
},
  "geometry": {"coordinates":[8.7063655853,47.7516326904],"type":"Point"}
}