{
  "type": "Feature",
  "properties": {
    "iso:country":"CH",
    "sg:address":"Z\u00fcrcherstrasse 285",
    "sg:city":"Frauenfeld",
    "sg:classifiers":[
        {
            "category":"Professional",
            "subcategory":"Employment Agencies",
            "type":"Services"
        }
    ],
    "sg:phone":"+41 71 913 36 26",
    "sg:postcode":"8500",
    "sg:province":"Thurgau",
    "sg:tags":[
        "personal",
        "u",
        "stellenvermittlung"
    ],
    "wof:name":"Optima Personal Wil Gmbh",
    "wof:placetype":"venue"
},
  "geometry": {"coordinates":[9.0411729813,47.4646987915],"type":"Point"}
}