{
  "type": "Feature",
  "properties": {
    "addr:full":"Rosenstrasse Henau St. Gallen 9247",
    "addr:postcode":"9247",
    "addr:street":"Rosenstrasse",
    "iso:country":"CH",
    "sg:address":"Rosenstrasse",
    "sg:city":"Henau",
    "sg:orig_category":"Werbung",
    "sg:phone":"+41 71 951 06 86",
    "sg:postcode":"9247",
    "sg:province":"St. Gallen",
    "wof:name":"Visual-design Raschle",
    "wof:placetype":"venue"
},
  "geometry": {"coordinates":[9.11299,47.45335],"type":"Point"}
}