{
  "type": "Feature",
  "properties": {
    "addr:full":"Chalet Le Pommier Les Mourets Rougemont 1838",
    "addr:postcode":"1838",
    "addr:street":"Rougemont",
    "iso:country":"CH",
    "sg:address":"Chalet Le Pommier Les Mourets",
    "sg:city":"Rougemont",
    "sg:orig_category":"Arztpraxen",
    "sg:phone":"+41 26 925 87 00",
    "sg:postcode":"1838",
    "wof:name":"Dr M\u00e9d. Benoit Zurkinden M\u00e9decin G\u00e9n\u00e9raliste",
    "wof:placetype":"venue"
},
  "geometry": {"coordinates":[-78.926056,36.217854],"type":"Point"}
}