{
  "type": "Feature",
  "properties": {
    "iso:country":"CH",
    "sg:address":"Falkenstrasse 3 8317 Tagelswangen. Postfach",
    "sg:city":"Tagelswangen",
    "sg:orig_category":"Berufsorganisationen",
    "sg:postcode":"8317",
    "sg:province":"Z\u00fcrich",
    "wof:name":"Knowbau",
    "wof:placetype":"venue"
},
  "geometry": {"coordinates":[8.670913,47.433647],"type":"Point"}
}