{
  "type": "Feature",
  "properties": {
    "iso:country":"CH",
    "sg:address":"4663 Aarburg. Postfach",
    "sg:city":"Aarburg",
    "sg:orig_category":"Allgemeiner Hoch U Tiefbau Allgemeiner Hochbau",
    "sg:phone":"+41 62 791 12 50",
    "sg:postcode":"4663",
    "sg:province":"Aargau",
    "wof:name":"Rema-service Gmbh",
    "wof:placetype":"venue"
},
  "geometry": {"coordinates":[7.899079,47.32019],"type":"Point"}
}