{
  "type": "Feature",
  "properties": {
    "iso:country":"CH",
    "sg:address":"Rue Du Petit-ch\u00eane 22 1003 Lausanne Case Postale 2685",
    "sg:city":"Lausanne",
    "sg:orig_category":"Hochschulen U h\u00f6here Ausbildung",
    "sg:phone":"+41 21 312 24 61",
    "sg:postcode":"1002",
    "sg:province":"Vaud",
    "wof:name":"Ecole Minerva S\u00e0rl Ecole Donnant Des Cours P. Assistantes M\u00e9dicales Etc",
    "wof:placetype":"venue"
},
  "geometry": {"coordinates":[6.6316270828,46.5190467834],"type":"Point"}
}