{
  "type": "Feature",
  "properties": {
    "addr:full":"Haus Valbella Rothenbrunnen Graubunden 7405",
    "addr:postcode":"7405",
    "iso:country":"CH",
    "sg:address":"Haus Valbella",
    "sg:city":"Rothenbrunnen",
    "sg:orig_category":"Detailhandel mit Brot, Back U S\u00fcsswaren",
    "sg:postcode":"7405",
    "sg:province":"Graubunden",
    "wof:name":"Rolf Schmid Gmbh",
    "wof:placetype":"venue"
},
  "geometry": {"coordinates":[9.427705,46.768024],"type":"Point"}
}