{
  "type": "Feature",
  "properties": {
    "iso:country":"CH",
    "sg:address":"Brunnenweid 62 5643 Sins. Postfach",
    "sg:city":"Sins",
    "sg:orig_category":"Softwareentwicklung U beratung",
    "sg:postcode":"5643",
    "sg:province":"Aargau",
    "wof:name":"Q-solutions By Michel & Jeremic Softwareprogramme; Entwicklung. Hard Und Software; Handel",
    "wof:placetype":"venue"
},
  "geometry": {"coordinates":[8.3875484467,47.1997032166],"type":"Point"}
}