{
  "type": "Feature",
  "properties": {
    "addr:full":"Rue Du Nord 8 Echallens Vaud 1040",
    "addr:housenumber":"8",
    "addr:postcode":"1040",
    "addr:street":"Rue Du Nord",
    "iso:country":"CH",
    "sg:address":"Rue Du Nord 8",
    "sg:city":"Echallens",
    "sg:orig_category":"Bauschreinerei Innenausbau",
    "sg:phone":"+41 14507960",
    "sg:postcode":"1040",
    "sg:province":"Vaud",
    "wof:name":"Sicherheitszentrum Z\u00fcrich",
    "wof:placetype":"venue"
},
  "geometry": {"coordinates":[8.598186,47.328686],"type":"Point"}
}