{
  "type": "Feature",
  "properties": {
    "iso:country":"CH",
    "sg:address":"Impasse Aurore",
    "sg:city":"Sierre",
    "sg:orig_category":"Non-Classified Establishments",
    "sg:postcode":"3960",
    "sg:province":"Valais",
    "wof:name":"Alain Babey Coiffeur",
    "wof:placetype":"venue"
},
  "geometry": {"coordinates":[7.5187449455,46.2855033875],"type":"Point"}
}