{
  "type": "Feature",
  "properties": {
    "iso:country":"CH",
    "sg:address":"Riethaldenstieg 11",
    "sg:city":"Schaffhausen",
    "sg:orig_category":"Interessenvertretungen",
    "sg:postcode":"8200",
    "sg:province":"Schaffhausen",
    "wof:name":"Fischer Johann Conrad - Stiftung",
    "wof:placetype":"venue"
},
  "geometry": {"coordinates":[8.6138858795,47.7041511536],"type":"Point"}
}