{
  "type": "Feature",
  "properties": {
    "iso:country":"CH",
    "sg:address":"Steinhaus 72",
    "sg:city":"Hospental",
    "sg:orig_category":"Non-Classified Establishments",
    "sg:postcode":"6493",
    "sg:province":"Uri",
    "wof:name":"Gotthardserpentin Und Specksteinwerke Ursern, Regli Gedeon & Sohn Gmbh",
    "wof:placetype":"venue"
},
  "geometry": {"coordinates":[8.5654888153,46.6179351807],"type":"Point"}
}