{
  "type": "Feature",
  "properties": {
    "iso:country":"CH",
    "sg:address":"Saladin Rue Ant.",
    "sg:city":"Crans-pr\u00e8s-c\u00e9ligny",
    "sg:orig_category":"Grosshandel mit Erzen U Metallen",
    "sg:postcode":"1299",
    "sg:province":"Vaud",
    "wof:name":"Sni Sa",
    "wof:placetype":"venue"
},
  "geometry": {"coordinates":[6.2066340446,46.3573226929],"type":"Point"}
}