{
  "type": "Feature",
  "properties": {
    "iso:country":"CH",
    "sg:address":"Baldeggstrasse 24",
    "sg:city":"Hochdorf",
    "sg:orig_category":"Fachdetailhandel in Verkaufsr\u00e4umen",
    "sg:postcode":"6280",
    "sg:province":"Luzern",
    "wof:name":"Zoohaus Hochdorf Rolf Und Silvia Jost",
    "wof:placetype":"venue"
},
  "geometry": {"coordinates":[8.2859039307,47.17237854],"type":"Point"}
}