{
  "type": "Feature",
  "properties": {
    "iso:country":"CH",
    "sg:address":"Dorfgasse 2 3454 Sumiswald. Postfach 6",
    "sg:city":"Sumiswald",
    "sg:orig_category":"Fachdetailhandel mit pharmazeutischen Produkten",
    "sg:phone":"+41 8006337258",
    "sg:postcode":"3454",
    "sg:province":"Bern",
    "wof:name":"Apotheke Sunne M\u00e4rt Ag",
    "wof:placetype":"venue"
},
  "geometry": {"coordinates":[8.3488235474,47.3519325256],"type":"Point"}
}