{
  "type": "Feature",
  "properties": {
    "iso:country":"CH",
    "sg:address":"Route De La Frasse 559",
    "sg:city":"Ch\u00e2tel-st-denis",
    "sg:orig_category":"Herstellung von Ger\u00e4ten der Elektrizit\u00e4tserzeugung, -verteilung u.\u00e4. -Herstellung von elektronischen",
    "sg:phone":"+41 18444811",
    "sg:postcode":"1618",
    "sg:province":"Fribourg",
    "wof:name":"Mauell Ag Elektromech. Erzeugnisse, Bes. Relaisbau Usw.; Fabr., Vertrieb",
    "wof:placetype":"venue"
},
  "geometry": {"coordinates":[8.4322557449,47.4509162903],"type":"Point"}
}