{
  "type": "Feature",
  "properties": {
    "iso:country":"CH",
    "sg:address":"Frohburgstrasse 4",
    "sg:city":"Zofingen",
    "sg:orig_category":"Architektur U Ingenieurb\u00fcros Architekturb\u00fcros",
    "sg:phone":"+41 62 751 59 59",
    "sg:postcode":"4800",
    "sg:province":"Aargau",
    "wof:name":"Batimo Ag, Bau Und Energie",
    "wof:placetype":"venue"
},
  "geometry": {"coordinates":[7.944337,47.294685],"type":"Point"}
}