{
  "type": "Feature",
  "properties": {
    "addr:full":"Rue Du Jura 12 Gen\u00e8ve Gen\u00e8ve 1201",
    "addr:housenumber":"12",
    "addr:postcode":"1201",
    "addr:street":"Rue Du Jura",
    "iso:country":"CH",
    "sg:address":"Rue Du Jura 12",
    "sg:city":"Gen\u00e8ve",
    "sg:orig_category":"Detailhandel mit Beleuchtungs U Haushaltsgegenst\u00e4nden Detailhandel mit elektrischen Haushalts-,Radio",
    "sg:phone":"+41 22 345 62 63",
    "sg:postcode":"1201",
    "sg:province":"Gen\u00e8ve",
    "wof:name":"Poly-services-m\u00e9nagers, Wenger",
    "wof:placetype":"venue"
},
  "geometry": {"coordinates":[6.137095,46.209579],"type":"Point"}
}