{
  "type": "Feature",
  "properties": {
    "iso:country":"CH",
    "sg:address":"Neudorfstrasse 17",
    "sg:city":"Uzwil",
    "sg:classifiers":[
        {
            "category":"Bars & Pubs",
            "type":"Food & Drink"
        }
    ],
    "sg:postcode":"9240",
    "sg:province":"St. Gallen",
    "wof:name":"Gschwind Anita",
    "wof:placetype":"venue"
},
  "geometry": {"coordinates":[9.13205,47.440052],"type":"Point"}
}