{
  "type": "Feature",
  "properties": {
    "iso:country":"CH",
    "sg:address":"Wilerstr. 6 Gasthaus Sch\u00e4fle",
    "sg:city":"Wattwil",
    "sg:classifiers":[
        {
            "category":"Travel",
            "subcategory":"Hotels & Motels",
            "type":"Entertainment"
        }
    ],
    "sg:postcode":"9630",
    "sg:province":"St. Gallen",
    "sg:tags":[
        "hotels",
        "mit",
        "restaurant"
    ],
    "wof:name":"Ruoss Werner.",
    "wof:placetype":"venue"
},
  "geometry": {"coordinates":[9.0868349075,47.2996559143],"type":"Point"}
}