{
  "type": "Feature",
  "properties": {
    "iso:country":"CH",
    "sg:address":"Deinikonerstrasse 38",
    "sg:city":"Baar",
    "sg:orig_category":"Malerei-Gipserei Stukkateurgewerbe, Gipserei U Verputzerei",
    "sg:phone":"+41 41 761 44 67",
    "sg:postcode":"6340",
    "sg:province":"Zug",
    "wof:name":"Felix Lucian Gipsergesch\u00e4ft",
    "wof:placetype":"venue"
},
  "geometry": {"coordinates":[8.5343294144,47.2010574341],"type":"Point"}
}