{
  "type": "Feature",
  "properties": {
    "iso:country":"CH",
    "sg:address":"Ausserdorf.",
    "sg:city":"Fl\u00e4sch",
    "sg:orig_category":"RESTAURANTS: TEA-ROOMS",
    "sg:phone":"+41 81 302 38 49",
    "sg:postcode":"7306",
    "sg:province":"Graubunden",
    "wof:name":"Hermann M.",
    "wof:placetype":"venue"
},
  "geometry": {"coordinates":[9.5121612549,47.0253334045],"type":"Point"}
}