{
  "type": "Feature",
  "properties": {
    "iso:country":"CH",
    "sg:address":"Rebackerweg 15",
    "sg:city":"Dietlikon",
    "sg:orig_category":"Unterhalt U Reparatur im Hoch U Tiefbau",
    "sg:phone":"+41 18340280",
    "sg:postcode":"8305",
    "sg:province":"Z\u00fcrich",
    "wof:name":"Rosan R.gfeller Bausanierungen",
    "wof:placetype":"venue"
},
  "geometry": {"coordinates":[8.6186819077,47.4284858704],"type":"Point"}
}