{
  "type": "Feature",
  "properties": {
    "iso:country":"CH",
    "sg:address":"Kirchweg 24",
    "sg:city":"Sarmenstorf",
    "sg:classifiers":[
        {
            "category":"Education",
            "subcategory":"Vocational School",
            "type":"Public Place"
        }
    ],
    "sg:phone":"+41 56 667 23 01",
    "sg:postcode":"5614",
    "sg:province":"Aargau",
    "sg:tags":[
        "assembly",
        "testing",
        "printed",
        "circuit",
        "pcb",
        "board"
    ],
    "wof:name":"F\u00fcrtronic",
    "wof:placetype":"venue"
},
  "geometry": {"coordinates":[8.250529,47.312271],"type":"Point"}
}