{
  "type": "Feature",
  "properties": {
    "iso:country":"CH",
    "sg:address":"Vieux-pont Rue Du 73",
    "sg:city":"Bulle",
    "sg:orig_category":"Non-Classified Establishments",
    "sg:postcode":"1630",
    "sg:province":"Fribourg",
    "wof:name":"Campo Arias Angel",
    "wof:placetype":"venue"
},
  "geometry": {"coordinates":[7.0610618591,46.6134796143],"type":"Point"}
}