{
  "type": "Feature",
  "properties": {
    "iso:country":"CH",
    "sg:address":"Hauptstrasse 46",
    "sg:city":"Bichelsee",
    "sg:orig_category":"Sonstiger Fachdetailhandel mit Nahrungsmitteln, Getr\u00e4nken U Tabak in Verkaufsr\u00e4umen",
    "sg:postcode":"8363",
    "sg:province":"Thurgau",
    "wof:name":"Meyer Josef",
    "wof:placetype":"venue"
},
  "geometry": {"coordinates":[8.9201078415,47.4491348267],"type":"Point"}
}