{
  "type": "Feature",
  "properties": {
    "iso:country":"CH",
    "sg:address":"Via Como 1",
    "sg:city":"Chiasso",
    "sg:orig_category":"Herstellung der Ausstattung von Uhren",
    "sg:phone":"+41 32 913 73 21",
    "sg:postcode":"6830",
    "sg:province":"Ticino",
    "wof:name":"Pierre Galli Cadrans De Montres",
    "wof:placetype":"venue"
},
  "geometry": {"coordinates":[6.8197979927,47.0996170044],"type":"Point"}
}