{
  "type": "Feature",
  "properties": {
    "iso:country":"CH",
    "sg:address":"Rosengartenstrasse 1a 8037 Z\u00fcrich. Postfach",
    "sg:city":"Z\u00fcrich",
    "sg:orig_category":"Sonstige pers\u00f6nliche Dienstleistungen",
    "sg:phone":"+41 26 477 15 50",
    "sg:postcode":"8037",
    "sg:province":"Z\u00fcrich",
    "wof:name":"S.a.r. Repond J.l.r. Service D'accueil Rapide",
    "wof:placetype":"venue"
},
  "geometry": {"coordinates":[7.0305480957,46.7511405945],"type":"Point"}
}