{
  "type": "Feature",
  "properties": {
    "iso:country":"CH",
    "sg:address":"Postgasse 12",
    "sg:city":"Flaach",
    "sg:orig_category":"Informatikdienste",
    "sg:phone":"+41 52 318 18 68",
    "sg:postcode":"8416",
    "sg:province":"Z\u00fcrich",
    "wof:name":"Inter-com Internet Nach Mass!",
    "wof:placetype":"venue"
},
  "geometry": {"coordinates":[8.6074171066,47.5762557983],"type":"Point"}
}