{
  "type": "Feature",
  "properties": {
    "iso:country":"CH",
    "sg:address":"H\u00fchnerhubelstrasse 64",
    "sg:city":"Belp",
    "sg:classifiers":[
        {
            "category":"Sports & Exercise",
            "subcategory":"Tennis Court",
            "type":"Entertainment"
        }
    ],
    "sg:phone":"+41 31 812 11 33",
    "sg:postcode":"3123",
    "sg:province":"Bern",
    "sg:tags":[
        "squash-centers",
        "hallen",
        "tennis-"
    ],
    "wof:name":"Walter Jossi Airport-fitness",
    "wof:placetype":"venue"
},
  "geometry": {"coordinates":[7.4951591492,46.9051742554],"type":"Point"}
}