{
  "type": "Feature",
  "properties": {
    "iso:country":"CH",
    "sg:address":"Brislachstrasse 2 4242 Laufen. Postfach",
    "sg:city":"Laufen",
    "sg:orig_category":"Sonstiges Versicherungsgewerbe",
    "sg:phone":"+41 62 765 44 44",
    "sg:postcode":"4242",
    "sg:province":"Basel-Landschaft",
    "wof:name":"Die Mobiliar, Generalagentur Reinach, Andreas Huber",
    "wof:placetype":"venue"
},
  "geometry": {"coordinates":[8.1832714081,47.2522773743],"type":"Point"}
}