{
  "type": "Feature",
  "properties": {
    "iso:country":"CH",
    "sg:address":"Buseno 6549 Laura. Postfach",
    "sg:city":"Laura",
    "sg:orig_category":"Interessenvertretungen",
    "sg:postcode":"6549",
    "sg:province":"Graubunden",
    "wof:name":"Fondazione Don Enrico Per La Giovent\u00f9",
    "wof:placetype":"venue"
},
  "geometry": {"coordinates":[9.1016216278,46.212146759],"type":"Point"}
}