{
  "type": "Feature",
  "properties": {
    "addr:full":"Z\u00fcrcherstrasse 107 Neuenhof Aargau 5432",
    "addr:housenumber":"107",
    "addr:postcode":"5432",
    "addr:street":"Zuercherstrasse",
    "iso:country":"CH",
    "sg:address":"Z\u00fcrcherstrasse 107",
    "sg:city":"Neuenhof",
    "sg:orig_category":"Bau\u00e4mter",
    "sg:phone":"+41 56 416 21 11",
    "sg:postcode":"5432",
    "sg:province":"Aargau",
    "wof:name":"Bauverwaltung Neuenhof",
    "wof:placetype":"venue"
},
  "geometry": {"coordinates":[8.326066,47.450733],"type":"Point"}
}