{
  "type": "Feature",
  "properties": {
    "iso:country":"CH",
    "sg:address":"Oberch\u00e4rns 2",
    "sg:city":"Rothenburg",
    "sg:orig_category":"Binnenschiffahrt",
    "sg:postcode":"6023",
    "sg:province":"Luzern",
    "wof:name":"Gesellschaft F\u00fcr Meer Und Fluss-schiffahrt",
    "wof:placetype":"venue"
},
  "geometry": {"coordinates":[8.271192,47.103653],"type":"Point"}
}