{
  "type": "Feature",
  "properties": {
    "iso:country":"CH",
    "sg:address":"Cours Des Bastions 5 1204 Gen\u00e8ve. Postfach",
    "sg:city":"Gen\u00e8ve",
    "sg:orig_category":"Finanzierungsinstitutionen",
    "sg:phone":"+41 22 817 01 01",
    "sg:postcode":"1201",
    "sg:province":"Gen\u00e8ve",
    "wof:name":"Euro Brokers (switzerland) Sa",
    "wof:placetype":"venue"
},
  "geometry": {"coordinates":[6.1483311653,46.1980018616],"type":"Point"}
}