{
  "type": "Feature",
  "properties": {
    "iso:country":"CH",
    "sg:address":"Poststrasse 1 3427 Utzenstorf. Postfach 123",
    "sg:city":"Utzenstorf",
    "sg:orig_category":"Detailhandel mit Damenbekleidung Herstellung von Oberbekleidung",
    "sg:phone":"+41 32 666 40 00",
    "sg:postcode":"3427",
    "sg:province":"Bern",
    "wof:name":"Burren Ag",
    "wof:placetype":"venue"
},
  "geometry": {"coordinates":[7.557079792,47.1304283142],"type":"Point"}
}