{
  "type": "Feature",
  "properties": {
    "iso:country":"CH",
    "sg:address":"Campagnora Via 35 6532 Castione. Postfach",
    "sg:city":"Castione",
    "sg:orig_category":"Dienstleistungen von Beteiligungsgesellschaften",
    "sg:postcode":"6532",
    "sg:province":"Ticino",
    "wof:name":"Micra Sagl",
    "wof:placetype":"venue"
},
  "geometry": {"coordinates":[9.0468950272,46.2276153564],"type":"Point"}
}