{
  "type": "Feature",
  "properties": {
    "iso:country":"CH",
    "sg:address":"Bernstrasse 34a",
    "sg:city":"Wattenwil",
    "sg:orig_category":"Zimmerei, Ingenieurholzbau",
    "sg:phone":"+41 33 356 26 38",
    "sg:postcode":"3665",
    "sg:province":"Bern",
    "wof:name":"Armin Megert Holzbau",
    "wof:placetype":"venue"
},
  "geometry": {"coordinates":[7.5149130821,46.7717628479],"type":"Point"}
}