{
  "type": "Feature",
  "properties": {
    "iso:country":"CH",
    "sg:address":"B\u00e4lliz 17",
    "sg:city":"Thun",
    "sg:classifiers":[
        {
            "category":"Banks & Credit Unions",
            "subcategory":"Investment Brokerage",
            "type":"Services"
        }
    ],
    "sg:phone":"+41 33 223 33 38",
    "sg:postcode":"3600",
    "sg:province":"Bern",
    "sg:tags":[
        "case",
        "spectacle"
    ],
    "wof:name":"Duplex Systems Swiss Gmbh",
    "wof:placetype":"venue"
},
  "geometry": {"coordinates":[7.627099,46.759274],"type":"Point"}
}