{
  "type": "Feature",
  "properties": {
    "iso:country":"CH",
    "sg:address":"Viale Stazione 5",
    "sg:city":"Bellinzona",
    "sg:orig_category":"Warenh\u00e4user",
    "sg:phone":"+41 91 825 02 11",
    "sg:postcode":"6500",
    "sg:province":"Ticino",
    "wof:name":"Manor",
    "wof:placetype":"venue"
},
  "geometry": {"coordinates":[9.0236730576,46.1921157837],"type":"Point"}
}