{
  "type": "Feature",
  "properties": {
    "iso:country":"CH",
    "sg:address":"Dufourstrasse 47 -",
    "sg:city":"Bern",
    "sg:classifiers":[
        {
            "category":"Professional",
            "subcategory":"Art Services",
            "type":"Services"
        }
    ],
    "sg:phone":"+41 21 312 77 64",
    "sg:postcode":"3005",
    "sg:province":"Bern",
    "sg:tags":[
        "export-import"
    ],
    "wof:name":"Costa Rica Consulate General Honorary",
    "wof:placetype":"venue"
},
  "geometry": {"coordinates":[6.63345,46.519428],"type":"Point"}
}