{
  "type": "Feature",
  "properties": {
    "iso:country":"CH",
    "sg:address":"Schimmelstrasse 2",
    "sg:city":"Z\u00fcrich",
    "sg:orig_category":"Herstellung von Kakao, Schokoladeerzeugnissen U Zuckerwaren",
    "sg:postcode":"8003",
    "sg:province":"Z\u00fcrich",
    "wof:name":"Candy Land Ag",
    "wof:placetype":"venue"
},
  "geometry": {"coordinates":[8.525891304,47.3695144653],"type":"Point"}
}