{
  "type": "Feature",
  "properties": {
    "iso:country":"CH",
    "sg:address":"R\u00fctliweid 10",
    "sg:city":"Adligenswil",
    "sg:orig_category":"Sportvereine Eissport Curling",
    "sg:phone":"+41 41 370 77 00",
    "sg:postcode":"6043",
    "sg:province":"Luzern",
    "wof:name":"C.c.luzern-blauweiss",
    "wof:placetype":"venue"
},
  "geometry": {"coordinates":[8.3630981445,47.0640945435],"type":"Point"}
}