{
  "type": "Feature",
  "properties": {
    "iso:country":"CH",
    "sg:address":"Dorfstrasse 27 6300 Zug. Postfach 903",
    "sg:city":"Zug",
    "sg:orig_category":"Museen",
    "sg:phone":"+41 41 711 11 50",
    "sg:postcode":"6301",
    "sg:province":"Zug",
    "wof:name":"Kunsthaus Zug Zuger Kunstgesellschaft",
    "wof:placetype":"venue"
},
  "geometry": {"coordinates":[8.5174331665,47.1649932861],"type":"Point"}
}