{
  "type": "Feature",
  "properties": {
    "iso:country":"CH",
    "sg:address":"M\u00fchlebachstr. 20",
    "sg:city":"Z\u00fcrich",
    "sg:classifiers":[
        {
            "category":"Banks & Credit Unions",
            "subcategory":"Financial Services",
            "type":"Services"
        }
    ],
    "sg:phone":"+41 4112653300",
    "sg:postcode":"8032",
    "sg:province":"Z\u00fcrich",
    "sg:tags":[
        "banking",
        "insurance",
        "institution",
        "finance"
    ],
    "wof:name":"Diethelm Keller Holding Ltd",
    "wof:placetype":"venue"
},
  "geometry": {"coordinates":[8.549796,47.365112],"type":"Point"}
}