{
  "type": "Feature",
  "properties": {
    "iso:country":"CH",
    "sg:address":"Aargauerstrasse 1",
    "sg:city":"Z\u00fcrich",
    "sg:orig_category":"Berufsorganisationen",
    "sg:postcode":"8048",
    "sg:province":"Z\u00fcrich",
    "wof:name":"Gzb Gewerbezentrum Brienz Ag",
    "wof:placetype":"venue"
},
  "geometry": {"coordinates":[8.048602,46.752075],"type":"Point"}
}