{
  "type": "Feature",
  "properties": {
    "iso:country":"CH",
    "sg:address":"Rosengartenhalde 11",
    "sg:city":"Luzern",
    "sg:orig_category":"Erschliessung von Grundst\u00fccken",
    "sg:phone":"+41 41 226 31 81",
    "sg:postcode":"6006",
    "sg:province":"Luzern",
    "wof:name":"Bau-genossenschaft Wilubau",
    "wof:placetype":"venue"
},
  "geometry": {"coordinates":[8.3408222198,47.0556602478],"type":"Point"}
}