{
  "type": "Feature",
  "properties": {
    "iso:country":"CH",
    "sg:address":"Bachacherweg 12",
    "sg:city":"M\u00fchleberg",
    "sg:orig_category":"Reiseb\u00fcros U Reiseveranstalter",
    "sg:phone":"+41 33 244 14 44",
    "sg:postcode":"3203",
    "sg:province":"Bern",
    "wof:name":"Fis Travel Service Ag",
    "wof:placetype":"venue"
},
  "geometry": {"coordinates":[7.6728010178,46.7296447754],"type":"Point"}
}