{
  "type": "Feature",
  "properties": {
    "iso:country":"CH",
    "sg:address":"Oberdorf 27",
    "sg:city":"Rafz",
    "sg:orig_category":"Softwareentwicklung U beratung",
    "sg:phone":"+41 18693322",
    "sg:postcode":"8197",
    "sg:province":"Z\u00fcrich",
    "wof:name":"Psb-informatik Gmbh",
    "wof:placetype":"venue"
},
  "geometry": {"coordinates":[8.5370960236,47.616569519],"type":"Point"}
}