{
  "type": "Feature",
  "properties": {
    "addr:full":"Hauptstr 31 Arlesheim Basel-Landschaft 4144",
    "addr:housenumber":"31",
    "addr:postcode":"4144",
    "addr:street":"Hauptstr",
    "iso:country":"CH",
    "sg:address":"Hauptstr 31",
    "sg:city":"Arlesheim",
    "sg:classifiers":[
        {
            "category":"Banks & Credit Unions",
            "subcategory":"Bank",
            "type":"Services"
        }
    ],
    "sg:phone":"+41 61 706 22 22",
    "sg:postcode":"4144",
    "sg:province":"Basel-Landschaft",
    "wof:name":"Schweizerischer Bankverein",
    "wof:placetype":"venue"
},
  "geometry": {"coordinates":[7.620307,47.493916],"type":"Point"}
}