{
  "type": "Feature",
  "properties": {
    "iso:country":"CH",
    "sg:address":"8607 Aathal-seegr\u00e4ben. Postfach",
    "sg:city":"Aathal-seegr\u00e4ben",
    "sg:orig_category":"Pensionskassen",
    "sg:postcode":"8607",
    "sg:province":"Z\u00fcrich",
    "wof:name":"Pensionskasse Der Spinnerei Und Weberei Dietfurt Ag",
    "wof:placetype":"venue"
},
  "geometry": {"coordinates":[8.9413003922,47.2884101868],"type":"Point"}
}