{
  "type": "Feature",
  "properties": {
    "iso:country":"CH",
    "sg:address":"Laurenzenvorstadt 19",
    "sg:city":"Aarau",
    "sg:orig_category":"Architekturb\u00fcros",
    "sg:phone":"+41 71 393 50 10",
    "sg:postcode":"5000",
    "sg:province":"Aargau",
    "wof:name":"Architektengemeinschaft Flawil",
    "wof:placetype":"venue"
},
  "geometry": {"coordinates":[9.191295,47.416225],"type":"Point"}
}