{
  "type": "Feature",
  "properties": {
    "iso:country":"CH",
    "sg:address":"Eschmattweg 1",
    "sg:city":"Mellingen",
    "sg:orig_category":"Grosshandel mit B\u00fcromaschinen U einrichtungen Hardwareberatung",
    "sg:phone":"+41 56 491 01 41",
    "sg:postcode":"5507",
    "sg:province":"Aargau",
    "wof:name":"H. Landolt L & L Edv-beratung Z\u00fcrich",
    "wof:placetype":"venue"
},
  "geometry": {"coordinates":[8.2712574005,47.4105148315],"type":"Point"}
}