{
  "type": "Feature",
  "properties": {
    "iso:country":"CH",
    "sg:address":"Place De La Navigation 3",
    "sg:city":"Lausanne",
    "sg:orig_category":"Sonstige Hilfs U Nebent\u00e4tigkeiten f\u00fcr den Landverkehr",
    "sg:phone":"+41 21 617 08 80",
    "sg:postcode":"1006",
    "sg:province":"Vaud",
    "wof:name":"Parking De La Place De La Navigation Sa",
    "wof:placetype":"venue"
},
  "geometry": {"coordinates":[6.6266560555,46.5067672729],"type":"Point"}
}