{
  "type": "Feature",
  "properties": {
    "addr:full":"Bahnhofstrasse 10 Ins Bern 3232",
    "addr:housenumber":"10",
    "addr:postcode":"3232",
    "addr:street":"Bahnhofstrasse;Bern",
    "iso:country":"CH",
    "sg:address":"Bahnhofstrasse 10",
    "sg:city":"Ins",
    "sg:orig_category":"Architekturb\u00fcros",
    "sg:phone":"+41 32 313 10 20",
    "sg:postcode":"3232",
    "sg:province":"Bern",
    "wof:name":"Rita Ruprecht Architekturb\u00fcro",
    "wof:placetype":"venue"
},
  "geometry": {"coordinates":[7.103483,47.005348],"type":"Point"}
}