{
  "type": "Feature",
  "properties": {
    "iso:country":"CH",
    "sg:address":"Pilatusstrasse 70",
    "sg:city":"Luzern",
    "sg:classifiers":[
        {
            "category":"Professional",
            "subcategory":"Employment Agencies",
            "type":"Services"
        }
    ],
    "sg:phone":"+41 71 622 56 58",
    "sg:postcode":"6003",
    "sg:province":"Luzern",
    "sg:tags":[
        "personal",
        "u",
        "stellenvermittlung"
    ],
    "wof:name":"Pro Filia Stellenvermittlungsb\u00fcro",
    "wof:placetype":"venue"
},
  "geometry": {"coordinates":[9.1364603043,47.567741394],"type":"Point"}
}