{
  "type": "Feature",
  "properties": {
    "iso:country":"CH",
    "sg:address":"Emmenhofallee 3",
    "sg:city":"Derendingen",
    "sg:orig_category":"Non-Classified Establishments",
    "sg:postcode":"4552",
    "sg:province":"Solothurn",
    "wof:name":"Monk Idea.com",
    "wof:placetype":"venue"
},
  "geometry": {"coordinates":[9.8381910324,46.4970664978],"type":"Point"}
}