{
  "type": "Feature",
  "properties": {
    "iso:country":"CH",
    "sg:address":"Dorfrebenstrasse 32",
    "sg:city":"Sch\u00f6fflisdorf",
    "sg:orig_category":"Grosshandel mit Maschinen U Ausr\u00fcstungen",
    "sg:phone":"+41 18561555",
    "sg:postcode":"8165",
    "sg:province":"Z\u00fcrich",
    "wof:name":"Eazymatic Ag",
    "wof:placetype":"venue"
},
  "geometry": {"coordinates":[8.4171895981,47.5028305054],"type":"Point"}
}