{
  "type": "Feature",
  "properties": {
    "iso:country":"CH",
    "sg:address":"Zeitglockenlaube 6",
    "sg:city":"Bern",
    "sg:orig_category":"Arztpraxen",
    "sg:phone":"+41 31 311 52 89",
    "sg:postcode":"3011",
    "sg:province":"Bern",
    "wof:name":"Dr.med.john Dunn Spezialarzt Fmh",
    "wof:placetype":"venue"
},
  "geometry": {"coordinates":[7.447795,46.948151],"type":"Point"}
}