{
  "type": "Feature",
  "properties": {
    "iso:country":"CH",
    "sg:address":"H\u00f6henweg 6",
    "sg:city":"Herisau",
    "sg:orig_category":"Non-Classified Establishments",
    "sg:postcode":"9100",
    "sg:province":"Appenzell Ausserrhoden",
    "wof:name":"Grub Immobilien Ag Herisau",
    "wof:placetype":"venue"
},
  "geometry": {"coordinates":[9.2794542313,47.3825531006],"type":"Point"}
}