{
  "type": "Feature",
  "properties": {
    "iso:country":"CH",
    "sg:address":"Parkstrasse 13 6410 Goldau. Postfach 427",
    "sg:city":"Goldau",
    "sg:orig_category":"Fahrschulen, Flugschulen",
    "sg:phone":"+41 41 855 20 38",
    "sg:postcode":"6410",
    "sg:province":"Schwyz",
    "wof:name":"Remo L\u00e4derach Autofahrschule",
    "wof:placetype":"venue"
},
  "geometry": {"coordinates":[8.549074173,47.0503387451],"type":"Point"}
}