{
  "type": "Feature",
  "properties": {
    "iso:country":"CH",
    "sg:address":"Untergass 4 8193 Eglisau. Postfach",
    "sg:city":"Eglisau",
    "sg:classifiers":[
        {
            "category":"Restaurant",
            "type":"Food & Drink"
        }
    ],
    "sg:phone":"+41 81 833 34 34",
    "sg:postcode":"8193",
    "sg:province":"Z\u00fcrich",
    "wof:name":"Restaurant Krone",
    "wof:placetype":"venue"
},
  "geometry": {"coordinates":[9.8400058746,46.4990882874],"type":"Point"}
}