{
  "type": "Feature",
  "properties": {
    "addr:full":"Spalentorweg 2 Basel Basel-Stadt 4051",
    "addr:housenumber":"2",
    "addr:postcode":"4051",
    "addr:street":"Spalentorweg",
    "iso:country":"CH",
    "sg:address":"Spalentorweg 2",
    "sg:city":"Basel",
    "sg:orig_category":"Arztpraxen",
    "sg:phone":"+41 61 302 29 29",
    "sg:postcode":"4051",
    "sg:province":"Basel-Stadt",
    "wof:name":"Dr.med.josef Forrer Spezialarzt Fmh",
    "wof:placetype":"venue"
},
  "geometry": {"coordinates":[7.580576,47.557537],"type":"Point"}
}