{
  "type": "Feature",
  "properties": {
    "iso:country":"CH",
    "sg:address":"Lange Gasse 11",
    "sg:city":"Basel",
    "sg:orig_category":"Religi\u00f6se Vereinigungen divers",
    "sg:phone":"+41 61 693 33 91",
    "sg:postcode":"4052",
    "sg:province":"Basel-Stadt",
    "wof:name":"Christengemeinschaft",
    "wof:placetype":"venue"
},
  "geometry": {"coordinates":[7.5981931686,47.5499382019],"type":"Point"}
}