{
  "type": "Feature",
  "properties": {
    "iso:country":"CH",
    "sg:address":"Egga",
    "sg:city":"Zeneggen",
    "sg:orig_category":"Herstellung von K\u00fcchenm\u00f6beln",
    "sg:phone":"+41 27 945 16 60",
    "sg:postcode":"3934",
    "sg:province":"Valais",
    "wof:name":"Hll - M\u00f6bel Und K\u00fcchenbau Gmbh",
    "wof:placetype":"venue"
},
  "geometry": {"coordinates":[7.8644828796,46.2712516785],"type":"Point"}
}