{
  "type": "Feature",
  "properties": {
    "iso:country":"CH",
    "sg:address":"Steinenring 10",
    "sg:city":"Basel",
    "sg:orig_category":"Unternehmensberatung",
    "sg:phone":"+41 61 225 98 98",
    "sg:postcode":"4051",
    "sg:province":"Basel-Stadt",
    "wof:name":"Plattner Schulz Partner Ag",
    "wof:placetype":"venue"
},
  "geometry": {"coordinates":[7.5776338577,47.5525360107],"type":"Point"}
}