{
  "type": "Feature",
  "properties": {
    "iso:country":"CH",
    "sg:address":"Maiens\u00e4ss 9479 Oberschan. Postfach",
    "sg:city":"Oberschan",
    "sg:orig_category":"RESTAURANTS: TEA-ROOMS",
    "sg:postcode":"9479",
    "sg:province":"St. Gallen",
    "wof:name":"Freuler Fritz, Rest. Maiens\u00e4ss",
    "wof:placetype":"venue"
},
  "geometry": {"coordinates":[9.4745855331,47.0991020203],"type":"Point"}
}