{
  "type": "Feature",
  "properties": {
    "iso:country":"CH",
    "sg:address":"Farnsburgerstrasse 45",
    "sg:city":"Basel",
    "sg:orig_category":"Grosshandel mit Getr\u00e4nken",
    "sg:phone":"+41 61 311 09 47",
    "sg:postcode":"4052",
    "sg:province":"Basel-Stadt",
    "wof:name":"Antonio Spina",
    "wof:placetype":"venue"
},
  "geometry": {"coordinates":[7.6139669418,47.5548248291],"type":"Point"}
}