{
  "type": "Feature",
  "properties": {
    "iso:country":"CH",
    "sg:address":"Einsiedlerstrasse 242",
    "sg:city":"Horgen",
    "sg:orig_category":"Sportvereine Renn-& Reitsport",
    "sg:phone":"+41 17255904",
    "sg:postcode":"8810",
    "sg:province":"Z\u00fcrich",
    "wof:name":"Reitverein Horgen",
    "wof:placetype":"venue"
},
  "geometry": {"coordinates":[8.5994195938,47.2532463074],"type":"Point"}
}