{
  "type": "Feature",
  "properties": {
    "iso:country":"CH",
    "sg:address":"B\u00fcttenenstrasse 33",
    "sg:city":"Luzern",
    "sg:orig_category":"Arztpraxen",
    "sg:phone":"+41 41 370 61 66",
    "sg:postcode":"6006",
    "sg:province":"Luzern",
    "wof:name":"Dr.med.guido Pfister Arzt F.allgemeine Medizin Fmh",
    "wof:placetype":"venue"
},
  "geometry": {"coordinates":[8.353926,47.053322],"type":"Point"}
}