{
  "type": "Feature",
  "properties": {
    "iso:country":"CH",
    "sg:address":"Hegenheimerstrasse 39 4055 Basel. Postfach",
    "sg:city":"Basel",
    "sg:orig_category":"Pensionskassen",
    "sg:phone":"+41 17626200",
    "sg:postcode":"4051",
    "sg:province":"Basel-Stadt",
    "wof:name":"Wohlfahrtsfonds Der Ebersp\u00e4cher Ag",
    "wof:placetype":"venue"
},
  "geometry": {"coordinates":[8.44452,47.270287],"type":"Point"}
}