{
  "type": "Feature",
  "properties": {
    "iso:country":"CH",
    "sg:address":"Grand Rue 14",
    "sg:city":"Echallens",
    "sg:orig_category":"Detailhandel mit B\u00fcromaschinen U einrichtungen Detailhandel mit Schreib U Papeteriewaren",
    "sg:phone":"+41 79 290 28 12",
    "sg:postcode":"1040",
    "sg:province":"Vaud",
    "wof:name":"R\u00e9my Cruchon Papeterie Pap\u00e9chal",
    "wof:placetype":"venue"
},
  "geometry": {"coordinates":[6.633065,46.641541],"type":"Point"}
}