{
  "type": "Feature",
  "properties": {
    "iso:country":"CH",
    "sg:address":"Hauptstrasse 64",
    "sg:city":"B\u00f6nigen",
    "sg:orig_category":"Verarbeitung von Milch Verwertung von Milch",
    "sg:phone":"+41 34 435 14 03",
    "sg:postcode":"3806",
    "sg:province":"Bern",
    "wof:name":"Jungfrau Milch Gmbh",
    "wof:placetype":"venue"
},
  "geometry": {"coordinates":[7.8949079514,46.6861572266],"type":"Point"}
}