{
  "type": "Feature",
  "properties": {
    "iso:country":"CH",
    "sg:address":"Badstubenstrasse",
    "sg:city":"Walenstadt",
    "sg:orig_category":"Pensionskassen",
    "sg:postcode":"8880",
    "sg:province":"St. Gallen",
    "wof:name":"Personalf\u00fcrsorgestiftung Der Gema Ag Walenstadt.",
    "wof:placetype":"venue"
},
  "geometry": {"coordinates":[9.3130989075,47.1236038208],"type":"Point"}
}