{
  "type": "Feature",
  "properties": {
    "iso:country":"CH",
    "sg:address":"Rue Principale 25",
    "sg:city":"Villeret",
    "sg:orig_category":"Gemeindeverwaltungen",
    "sg:phone":"+41 32 941 13 14",
    "sg:postcode":"2613",
    "sg:province":"Bern",
    "wof:name":"Administration Communale De Villeret",
    "wof:placetype":"venue"
},
  "geometry": {"coordinates":[7.0181260109,47.1573753357],"type":"Point"}
}