{
  "type": "Feature",
  "properties": {
    "iso:country":"CH",
    "sg:address":"Rue Des Tisserands 12",
    "sg:city":"Porrentruy",
    "sg:orig_category":"Organisationen der Wohlfahrtspflege",
    "sg:phone":"+41 41 850 19 18",
    "sg:postcode":"2900",
    "sg:province":"Jura",
    "wof:name":"Monika Christen Pro Juventute",
    "wof:placetype":"venue"
},
  "geometry": {"coordinates":[8.4433689117,47.0894355774],"type":"Point"}
}