{
  "type": "Feature",
  "properties": {
    "iso:country":"CH",
    "sg:address":"Industriestrasse 13",
    "sg:city":"Menzingen",
    "sg:orig_category":"Sonstiger spezialisierter Hoch U Tiefbau",
    "sg:phone":"+41 79 340 81 57",
    "sg:postcode":"6313",
    "sg:province":"Zug",
    "wof:name":"Foro Ag",
    "wof:placetype":"venue"
},
  "geometry": {"coordinates":[8.6023368835,47.173324585],"type":"Point"}
}