{
  "type": "Feature",
  "properties": {
    "iso:country":"CH",
    "sg:address":"1950",
    "sg:city":"Sion",
    "sg:orig_category":"Grosshandel mit Getr\u00e4nken",
    "sg:phone":"+41 32 358 11 89",
    "sg:postcode":"1950",
    "sg:province":"Valais",
    "wof:name":"Jeandrevin Yvonne.",
    "wof:placetype":"venue"
},
  "geometry": {"coordinates":[-112.009475708,43.5343589783],"type":"Point"}
}