{
  "type": "Feature",
  "properties": {
    "iso:country":"CH",
    "sg:address":"Munotstieg 2",
    "sg:city":"Schaffhausen",
    "sg:orig_category":"Herstellung von medizinischen U chirurgischen Ger\u00e4ten sowie orthop\u00e4dischen Vorrichtungen Medizinisch",
    "sg:phone":"+41 55 420 40 01",
    "sg:postcode":"8200",
    "sg:province":"Schaffhausen",
    "wof:name":"Cryo-cell Switzerland Ag Medizinalprodukte; Handel. Lizenzen; Verwaltung Usw",
    "wof:placetype":"venue"
},
  "geometry": {"coordinates":[8.7834892273,47.2015571594],"type":"Point"}
}