{
  "type": "Feature",
  "properties": {
    "iso:country":"CH",
    "sg:address":"Centro Logistico 6593 Cadenazzo. Postfach",
    "sg:city":"Cadenazzo",
    "sg:orig_category":"Grosshandel mit Holz U Baustoffen",
    "sg:postcode":"6593",
    "sg:province":"Ticino",
    "wof:name":"Autela Sagl Materiali Di Costruzione, Macchinari Ecc.; Comm.",
    "wof:placetype":"venue"
},
  "geometry": {"coordinates":[8.9523019791,46.1495780945],"type":"Point"}
}