{
  "type": "Feature",
  "properties": {
    "iso:country":"CH",
    "sg:address":"5737",
    "sg:city":"Menziken",
    "sg:orig_category":"Wirtschaftsverb\u00e4nde Gewerbeverb\u00e4nde/-vereine",
    "sg:postcode":"5737",
    "sg:province":"Aargau",
    "wof:name":"Handwerker-& Gewerbeverein",
    "wof:placetype":"venue"
},
  "geometry": {"coordinates":[8.1877918243,47.2399864197],"type":"Point"}
}