{
  "type": "Feature",
  "properties": {
    "iso:country":"CH",
    "sg:address":"6154",
    "sg:city":"Hofstatt",
    "sg:orig_category":"Primarschulen",
    "sg:postcode":"6154",
    "sg:province":"Luzern",
    "wof:name":"Primarschule",
    "wof:placetype":"venue"
},
  "geometry": {"coordinates":[7.925620079,47.0269317627],"type":"Point"}
}