{
  "type": "Feature",
  "properties": {
    "iso:country":"CH",
    "sg:address":"Fruthwilerstr. 83 8268 Salenstein. Postfach",
    "sg:city":"Salenstein",
    "sg:orig_category":"Herstellung von Konstruktionsteilen, Fertigbauteilen U Ausbauelementen aus Holz",
    "sg:phone":"+41 56 633 15 23",
    "sg:postcode":"8268",
    "sg:province":"Thurgau",
    "wof:name":"W. Baumgartner",
    "wof:placetype":"venue"
},
  "geometry": {"coordinates":[8.3369007111,47.3504562378],"type":"Point"}
}