{
  "type": "Feature",
  "properties": {
    "iso:country":"CH",
    "sg:address":"Kreuzbleichestrasse 8",
    "sg:city":"St.gallen",
    "sg:orig_category":"Vermietung U Verpachtung von eigenen Immobilien",
    "sg:postcode":"9000",
    "sg:province":"St. Gallen",
    "wof:name":"El-carno Verwaltungs-ag",
    "wof:placetype":"venue"
},
  "geometry": {"coordinates":[9.3562736511,47.4200134277],"type":"Point"}
}