{
  "type": "Feature",
  "properties": {
    "iso:country":"CH",
    "sg:address":"Pfosigart 16",
    "sg:city":"Besenb\u00fcren",
    "sg:orig_category":"Arztpraxen",
    "sg:phone":"+41 71 222 88 66",
    "sg:postcode":"5627",
    "sg:province":"Aargau",
    "wof:name":"Dr.med. Roman Graemiger Spezialarzt Fmh",
    "wof:placetype":"venue"
},
  "geometry": {"coordinates":[9.370963,47.423321],"type":"Point"}
}