{
  "type": "Feature",
  "properties": {
    "iso:country":"CH",
    "sg:address":"Rue Saint-georges 3",
    "sg:city":"Sierre",
    "sg:classifiers":[
        {
            "category":"Restaurant",
            "type":"Food & Drink"
        }
    ],
    "sg:phone":"+41 27 455 07 80",
    "sg:postcode":"3960",
    "sg:province":"Valais",
    "wof:name":"Restaurant Noyers",
    "wof:placetype":"venue"
},
  "geometry": {"coordinates":[7.5231847763,46.2913589478],"type":"Point"}
}