{
  "type": "Feature",
  "properties": {
    "iso:country":"CH",
    "sg:city":"Heerbrugg",
    "sg:classifiers":[
        {
            "category":"Banks & Credit Unions",
            "subcategory":"Bank",
            "type":"Services"
        }
    ],
    "sg:phone":"+41 4171725755",
    "sg:postcode":"9435",
    "sg:province":"St. Gallen",
    "wof:name":"Sparkassa Berneck",
    "wof:placetype":"venue"
},
  "geometry": {"coordinates":[9.626956,47.411705],"type":"Point"}
}