{
  "type": "Feature",
  "properties": {
    "iso:country":"CH",
    "sg:address":"Werdenbergerweg 14",
    "sg:city":"Vaduz",
    "sg:orig_category":"D\u00e4mmung gegen K\u00e4lte, W\u00e4rme, Schall U Ersch\u00fctterung",
    "sg:postcode":"9490",
    "wof:name":"Peter Wachter Bauabdichtungen",
    "wof:placetype":"venue"
},
  "geometry": {"coordinates":[9.516163826,47.1467285156],"type":"Point"}
}