{
  "type": "Feature",
  "properties": {
    "iso:country":"CH",
    "sg:address":"Zipfelstrasse 13b",
    "sg:city":"Kloten",
    "sg:orig_category":"Malerei",
    "sg:phone":"+41 18130074",
    "sg:postcode":"8302",
    "sg:province":"Z\u00fcrich",
    "wof:name":"Edwin Sulzer Malergesch\u00e4ft",
    "wof:placetype":"venue"
},
  "geometry": {"coordinates":[8.5808286667,47.4680480957],"type":"Point"}
}