{
  "type": "Feature",
  "properties": {
    "iso:country":"CH",
    "sg:address":"Im Rank 52 6300 Zug. Postfach 2329",
    "sg:city":"Zug",
    "sg:orig_category":"Softwareentwicklung U beratung",
    "sg:phone":"+41 41 711 61 11",
    "sg:postcode":"6302",
    "sg:province":"Zug",
    "wof:name":"Innoventis (the Intelligence Capital Company) Ag",
    "wof:placetype":"venue"
},
  "geometry": {"coordinates":[8.490655899,47.1804618835],"type":"Point"}
}