{
  "type": "Feature",
  "properties": {
    "iso:country":"CH",
    "sg:address":"Avenue De La Gare 52 1003 Lausanne. Postfach",
    "sg:city":"Lausanne",
    "sg:orig_category":"Grosshandel mit pharmazeutischen Erzeugnissen, medizinischen U orthop\u00e4dischen Artikeln",
    "sg:phone":"+41 21 341 11 67",
    "sg:postcode":"1001",
    "sg:province":"Vaud",
    "wof:name":"Centre M\u00e9dical De La Gare Et Institut De Canc\u00e9rologie Sa",
    "wof:placetype":"venue"
},
  "geometry": {"coordinates":[6.630751133,46.5173454285],"type":"Point"}
}