{
  "type": "Feature",
  "properties": {
    "iso:country":"CH",
    "sg:address":"6286",
    "sg:city":"Altwis",
    "sg:orig_category":"Wasserversorgung",
    "sg:postcode":"6286",
    "sg:province":"Luzern",
    "wof:name":"Brunnengenossenschaft B\u00fchlberg-brand Lenk I.s.",
    "wof:placetype":"venue"
},
  "geometry": {"coordinates":[7.4413700104,46.4569587708],"type":"Point"}
}