{
  "type": "Feature",
  "properties": {
    "iso:country":"CH",
    "sg:address":"Rothmattweg 12",
    "sg:city":"Rothrist",
    "sg:orig_category":"Unclassifiable Establishments",
    "sg:postcode":"4852",
    "sg:province":"Aargau",
    "wof:name":"Stalder & Partner",
    "wof:placetype":"venue"
},
  "geometry": {"coordinates":[7.8756780624,47.3028793335],"type":"Point"}
}