{
  "type": "Feature",
  "properties": {
    "iso:country":"CH",
    "sg:address":"6916",
    "sg:city":"Grancia",
    "sg:orig_category":"Sonstiger Grosshandel",
    "sg:phone":"+41 32 836 36 36",
    "sg:postcode":"6916",
    "sg:province":"Ticino",
    "wof:name":"Nalkho Techno Sa",
    "wof:placetype":"venue"
},
  "geometry": {"coordinates":[6.857986927,46.9656143188],"type":"Point"}
}