{
  "type": "Feature",
  "properties": {
    "iso:country":"CH",
    "sg:address":"Sonnenrainstrasse 1",
    "sg:city":"Riedholz",
    "sg:orig_category":"Arztpraxen",
    "sg:phone":"+41 32 622 35 42",
    "sg:postcode":"4533",
    "sg:province":"Solothurn",
    "wof:name":"Dr.med.alfons Studer Arzt F.allgemeine Medizin Fmh",
    "wof:placetype":"venue"
},
  "geometry": {"coordinates":[7.568053,47.230946],"type":"Point"}
}