{
  "type": "Feature",
  "properties": {
    "iso:country":"CH",
    "sg:address":"Eternitstrasse 3",
    "sg:city":"Glarus",
    "sg:orig_category":"Unternehmensberatung",
    "sg:phone":"+41 22 343 99 33",
    "sg:postcode":"8750",
    "sg:province":"Glarus",
    "wof:name":"Amext Sarl",
    "wof:placetype":"venue"
},
  "geometry": {"coordinates":[6.1434750557,46.1856079102],"type":"Point"}
}