{
  "type": "Feature",
  "properties": {
    "iso:country":"CH",
    "sg:address":"2542 Pieterlen. Postfach 236",
    "sg:city":"Pieterlen",
    "sg:orig_category":"Sportvereine Ballsport Fussball",
    "sg:postcode":"2542",
    "sg:province":"Bern",
    "wof:name":"Fc Pieterlen",
    "wof:placetype":"venue"
},
  "geometry": {"coordinates":[7.3368191719,47.1748771667],"type":"Point"}
}