{
  "type": "Feature",
  "properties": {
    "iso:country":"CH",
    "sg:address":"Rue Du Vieux-moulin 36",
    "sg:city":"Bassecourt",
    "sg:orig_category":"Detailhandel mit Textilien",
    "sg:phone":"+41 32 426 73 41",
    "sg:postcode":"2854",
    "sg:province":"Jura",
    "wof:name":"Eliane Montavon Laine-mercerie",
    "wof:placetype":"venue"
},
  "geometry": {"coordinates":[7.2479858398,47.3396148682],"type":"Point"}
}