{
  "type": "Feature",
  "properties": {
    "addr:full":"Goldschl\u00e4gistrasse 16 Schlieren Z\u00fcrich 8952",
    "addr:housenumber":"16",
    "addr:postcode":"8952",
    "addr:street":"Goldschlaegistrasse",
    "iso:country":"CH",
    "sg:address":"Goldschl\u00e4gistrasse 16",
    "sg:city":"Schlieren",
    "sg:classifiers":[
        {
            "category":"Autos & Motor Vehicles",
            "subcategory":"Boat Sales",
            "type":"Retail Goods"
        }
    ],
    "sg:phone":"+41 17304050",
    "sg:postcode":"8952",
    "sg:province":"Z\u00fcrich",
    "sg:tags":[
        "varnish"
    ],
    "wof:name":"Anwander & Co Ag",
    "wof:placetype":"venue"
},
  "geometry": {"coordinates":[8.440847,47.400192],"type":"Point"}
}