{
  "type": "Feature",
  "properties": {
    "iso:country":"CH",
    "sg:address":"Chemin De La Pereuse 3",
    "sg:city":"Vernier",
    "sg:orig_category":"Instandhaltung U Reparatur von Automobilen",
    "sg:phone":"+41 22 797 53 03",
    "sg:postcode":"1214",
    "sg:province":"Gen\u00e8ve",
    "wof:name":"Little Cars Garage, Zehfus Marc",
    "wof:placetype":"venue"
},
  "geometry": {"coordinates":[6.0763778687,46.2082138062],"type":"Point"}
}