{
  "type": "Feature",
  "properties": {
    "iso:country":"CH",
    "sg:address":"Rue Des Finettes 65 1920 Martigny. Postfach",
    "sg:city":"Martigny",
    "sg:orig_category":"Druck ohne Zeitungsdruck",
    "sg:postcode":"1920",
    "sg:province":"Valais",
    "wof:name":"Cri, Centre Rhodanien D'impression Sa",
    "wof:placetype":"venue"
},
  "geometry": {"coordinates":[7.0919628143,46.1068916321],"type":"Point"}
}