{
  "type": "Feature",
  "properties": {
    "iso:country":"CH",
    "sg:address":"2207",
    "sg:city":"Coffrane",
    "sg:orig_category":"Schulpflegen",
    "sg:postcode":"2207",
    "sg:province":"Neuch\u00e2tel",
    "wof:name":"Commission Scolaire De L'ecole Primaire",
    "wof:placetype":"venue"
},
  "geometry": {"coordinates":[6.9842767715,47.2712631226],"type":"Point"}
}