{
  "type": "Feature",
  "properties": {
    "iso:country":"CH",
    "sg:address":"Kempttalstrasse 74",
    "sg:city":"Fehraltorf",
    "sg:orig_category":"Handel mit Automobilen",
    "sg:postcode":"8320",
    "sg:province":"Z\u00fcrich",
    "wof:name":"Auto Top Discount Gmbh",
    "wof:placetype":"venue"
},
  "geometry": {"coordinates":[8.7559108734,47.3852615356],"type":"Point"}
}