{
  "type": "Feature",
  "properties": {
    "iso:country":"CH",
    "sg:address":"4410",
    "sg:city":"Liestal",
    "sg:orig_category":"Bezirks, Sekundar, Realschulen, Oberstufe der Primarschulen",
    "sg:phone":"+41 56 441 63 36",
    "sg:postcode":"4410",
    "sg:province":"Basel-Landschaft",
    "wof:name":"Sekundarschule Freudenstein",
    "wof:placetype":"venue"
},
  "geometry": {"coordinates":[8.204995,47.484962],"type":"Point"}
}