{
  "type": "Feature",
  "properties": {
    "iso:country":"CH",
    "sg:address":"Albisstr. 20",
    "sg:city":"Adliswil",
    "sg:classifiers":[
        {
            "category":"Sports & Exercise",
            "subcategory":"Tennis Court",
            "type":"Entertainment"
        }
    ],
    "sg:phone":"+41 4117102070",
    "sg:postcode":"8134",
    "sg:province":"Z\u00fcrich",
    "sg:tags":[
        "textile",
        "product",
        "clothing",
        "miscellaneous",
        "clothes"
    ],
    "wof:name":"Sport Helmi Ag",
    "wof:placetype":"venue"
},
  "geometry": {"coordinates":[8.525448,47.310196],"type":"Point"}
}