{
  "type": "Feature",
  "properties": {
    "iso:country":"CH",
    "sg:address":"Hauptstrasse 43 9552 Bronschhofen. Postfach",
    "sg:city":"Bronschhofen",
    "sg:orig_category":"Vermittlung von Immobilien Verwaltung von Immobilien",
    "sg:phone":"+41 22 735 93 50",
    "sg:postcode":"9552",
    "sg:province":"St. Gallen",
    "wof:name":"Le Forum Immobilier Sa",
    "wof:placetype":"venue"
},
  "geometry": {"coordinates":[6.1570820808,46.2054100037],"type":"Point"}
}