{
  "type": "Feature",
  "properties": {
    "iso:country":"CH",
    "sg:address":"Br\u00f6l 17",
    "sg:city":"Ardez",
    "sg:orig_category":"Herstellung von Konstruktionsteilen, Fertigbauteilen U Ausbauelementen aus Holz",
    "sg:phone":"+41 33 654 18 09",
    "sg:postcode":"7546",
    "sg:province":"Graubunden",
    "wof:name":"Thomann Gebr., Holzbau Ag",
    "wof:placetype":"venue"
},
  "geometry": {"coordinates":[7.6955251694,46.6565361023],"type":"Point"}
}