{
  "type": "Feature",
  "properties": {
    "iso:country":"CH",
    "sg:address":"Enrambuz",
    "sg:city":"Etagni\u00e8res",
    "sg:orig_category":"Handel mit Automobilen",
    "sg:postcode":"1037",
    "sg:province":"Vaud",
    "wof:name":"Shadicars, Al-moussawi",
    "wof:placetype":"venue"
},
  "geometry": {"coordinates":[6.608194828,46.5963401794],"type":"Point"}
}