{
  "type": "Feature",
  "properties": {
    "iso:country":"CH",
    "sg:address":"Baarerstrasse 82",
    "sg:city":"Zug",
    "sg:orig_category":"Grosshandel mit Erzen U Metallen",
    "sg:postcode":"6300",
    "sg:province":"Zug",
    "wof:name":"Mombelli Edy.",
    "wof:placetype":"venue"
},
  "geometry": {"coordinates":[8.9471750259,45.9904403687],"type":"Point"}
}