{
  "type": "Feature",
  "properties": {
    "iso:country":"CH",
    "sg:address":"Schulgasse 4",
    "sg:city":"Hunzenschwil",
    "sg:orig_category":"RESTAURANTS: TEA-ROOMS",
    "sg:phone":"+41 55 284 14 21",
    "sg:postcode":"5502",
    "sg:province":"Aargau",
    "wof:name":"Rest. Frohsinn H\u00fcppi Agnes.",
    "wof:placetype":"venue"
},
  "geometry": {"coordinates":[8.9707317352,47.2459182739],"type":"Point"}
}