{
  "type": "Feature",
  "properties": {
    "iso:country":"CH",
    "sg:address":"Hauptstrasse 10 4415 Lausen. Postfach",
    "sg:city":"Lausen",
    "sg:orig_category":"Herstellung der Ausstattung von Uhren Herstellung von Uhren",
    "sg:phone":"+41 61 921 90 00",
    "sg:postcode":"4415",
    "sg:province":"Basel-Landschaft",
    "wof:name":"Ronda Ag",
    "wof:placetype":"venue"
},
  "geometry": {"coordinates":[7.7526578903,47.4743728638],"type":"Point"}
}