{
  "type": "Feature",
  "properties": {
    "iso:country":"CH",
    "sg:address":"Kaspar-steinerstrasse 1",
    "sg:city":"Emmen",
    "sg:orig_category":"Detailhandel mit Radio U Fernsehger\u00e4ten Detailhandel mit elektrischen Haushalts-,Radio U Fernsehger\u00e4",
    "sg:phone":"+41 41 260 79 28",
    "sg:postcode":"6032",
    "sg:province":"Luzern",
    "wof:name":"Gutknecht Alfred, Radio Und Fernsehservice",
    "wof:placetype":"venue"
},
  "geometry": {"coordinates":[8.2998189926,47.0786857605],"type":"Point"}
}