{
  "type": "Feature",
  "properties": {
    "iso:country":"CH",
    "sg:address":"B\u00f6cklinstrasse 39",
    "sg:city":"Z\u00fcrich",
    "sg:orig_category":"Non-Classified Establishments",
    "sg:postcode":"8032",
    "sg:province":"Z\u00fcrich",
    "wof:name":"Alltec Holding Ag",
    "wof:placetype":"venue"
},
  "geometry": {"coordinates":[8.5620059967,47.3628196716],"type":"Point"}
}