{
  "type": "Feature",
  "properties": {
    "iso:country":"CH",
    "sg:address":"Gerra Piano 6516 Cugnasco. Postfach",
    "sg:city":"Cugnasco",
    "sg:orig_category":"RESTAURANTS: TEA-ROOMS",
    "sg:postcode":"6516",
    "sg:province":"Ticino",
    "wof:name":"Pedrazzi Ivano",
    "wof:placetype":"venue"
},
  "geometry": {"coordinates":[8.91264534,46.1754837036],"type":"Point"}
}