{
  "type": "Feature",
  "properties": {
    "iso:country":"CH",
    "sg:address":"Hofstrasse 56",
    "sg:city":"Z\u00fcrich",
    "sg:orig_category":"Schwimmb\u00e4der",
    "sg:phone":"+41 12517730",
    "sg:postcode":"8032",
    "sg:province":"Z\u00fcrich",
    "wof:name":"Hallenbad Bungertwies",
    "wof:placetype":"venue"
},
  "geometry": {"coordinates":[8.5601463318,47.3719902039],"type":"Point"}
}