{
  "type": "Feature",
  "properties": {
    "iso:country":"CH",
    "sg:address":"Seestrasse 177",
    "sg:city":"W\u00e4denswil",
    "sg:orig_category":"Herstellung von Radio U Fernsehger\u00e4ten sowie phono U videotechnischen Ger\u00e4ten",
    "sg:phone":"+41 17808668",
    "sg:postcode":"8820",
    "sg:province":"Z\u00fcrich",
    "wof:name":"Sle -electronic J. Furrer",
    "wof:placetype":"venue"
},
  "geometry": {"coordinates":[8.6678533554,47.2333717346],"type":"Point"}
}