{
  "type": "Feature",
  "properties": {
    "iso:country":"CH",
    "sg:address":"Stadthofstrasse 3",
    "sg:city":"Luzern",
    "sg:orig_category":"Unclassifiable Establishments",
    "sg:postcode":"6004",
    "sg:province":"Luzern",
    "wof:name":"Dr.med.ernst-josef Marty Spezialarzt Fmh",
    "wof:placetype":"venue"
},
  "geometry": {"coordinates":[8.643573761,46.8793716431],"type":"Point"}
}