{
  "type": "Feature",
  "properties": {
    "iso:country":"CH",
    "sg:address":"Route De La Gl\u00e2ne 107",
    "sg:city":"Villars-sur-gl\u00e2ne",
    "sg:classifiers":[
        {
            "category":"Communications",
            "subcategory":"Radio Station",
            "type":"Services"
        }
    ],
    "sg:phone":"+41 61 712 05 15",
    "sg:postcode":"1752",
    "sg:province":"Fribourg",
    "sg:tags":[
        "fernsehanstalten",
        "u"
    ],
    "wof:name":"Leuthardt & Partner",
    "wof:placetype":"venue"
},
  "geometry": {"coordinates":[7.5977578163,47.5044746399],"type":"Point"}
}