{
  "type": "Feature",
  "properties": {
    "iso:country":"CH",
    "sg:address":"Chemin De Chermet 12",
    "sg:city":"Moudon",
    "sg:orig_category":"Vereine Hundedressur",
    "sg:phone":"+41 21 905 50 39",
    "sg:postcode":"1510",
    "sg:province":"Vaud",
    "wof:name":"Spaniel Club Suisse",
    "wof:placetype":"venue"
},
  "geometry": {"coordinates":[6.7909221649,46.6758766174],"type":"Point"}
}