{
  "type": "Feature",
  "properties": {
    "iso:country":"CH",
    "sg:address":"L\u00e9man Route Du 55",
    "sg:city":"Mayens-de-saxon",
    "sg:orig_category":"Instandhaltung U Reparatur von Automobilen",
    "sg:phone":"+41 71 622 54 32",
    "sg:postcode":"1907",
    "sg:province":"Valais",
    "wof:name":"Morf J\u00fcrg Gmbh",
    "wof:placetype":"venue"
},
  "geometry": {"coordinates":[9.1381845474,47.5666694641],"type":"Point"}
}