{
  "type": "Feature",
  "properties": {
    "iso:country":"CH",
    "sg:address":"Gottfried-kellerstrasse 3",
    "sg:city":"Kriens",
    "sg:orig_category":"Arztpraxen",
    "sg:phone":"+41 41 310 75 70",
    "sg:postcode":"6010",
    "sg:province":"Luzern",
    "wof:name":"Dr.med.werner Wiget Spezialarzt Fmh",
    "wof:placetype":"venue"
},
  "geometry": {"coordinates":[8.284368,47.033241],"type":"Point"}
}