{
  "type": "Feature",
  "properties": {
    "iso:country":"CH",
    "sg:address":"Palduinstrasse 56",
    "sg:city":"Balzers",
    "sg:orig_category":"Zahntechnische Laboratorien",
    "sg:phone":"+423 384 14 71",
    "sg:postcode":"9496",
    "wof:name":"Ak-dental Annelies Klotz",
    "wof:placetype":"venue"
},
  "geometry": {"coordinates":[9.5128135681,47.0646476746],"type":"Point"}
}