{
  "type": "Feature",
  "properties": {
    "iso:country":"CH",
    "sg:address":"Stadthausgasse 11",
    "sg:city":"Basel",
    "sg:orig_category":"Detailhandel mit Uhren U Schmuck",
    "sg:phone":"+41 71 755 70 57",
    "sg:postcode":"4051",
    "sg:province":"Basel-Stadt",
    "wof:name":"Goldschmiede Steiner",
    "wof:placetype":"venue"
},
  "geometry": {"coordinates":[9.5401954651,47.3782081604],"type":"Point"}
}