{
  "type": "Feature",
  "properties": {
    "iso:country":"CH",
    "sg:address":"Industriestrasse 4",
    "sg:city":"D\u00e4llikon",
    "sg:orig_category":"Reinigungsgewerbe",
    "sg:phone":"+41 18450015",
    "sg:postcode":"8108",
    "sg:province":"Z\u00fcrich",
    "wof:name":"Gbu Geb\u00e4ude- Unterhalt Service Gmbh",
    "wof:placetype":"venue"
},
  "geometry": {"coordinates":[8.4413290024,47.4443664551],"type":"Point"}
}