{
  "type": "Feature",
  "properties": {
    "iso:country":"CH",
    "sg:address":"Route De Denges 8",
    "sg:city":"Lonay",
    "sg:classifiers":[
        {
            "category":"Manufacturing",
            "subcategory":"Metals",
            "type":"Manufacturing & Wholesale Goods"
        }
    ],
    "sg:phone":"+41 21 811 31 31",
    "sg:postcode":"1027",
    "sg:province":"Vaud",
    "sg:tags":[
        "flat",
        "pressing",
        "iron"
    ],
    "wof:name":"Hebor S.a.",
    "wof:placetype":"venue"
},
  "geometry": {"coordinates":[6.52238,46.52496],"type":"Point"}
}