{
  "type": "Feature",
  "properties": {
    "iso:country":"CH",
    "sg:address":"L\u00f6rracherstrasse 174",
    "sg:city":"Riehen",
    "sg:orig_category":"Autotransporte international",
    "sg:phone":"+41 61 641 34 12",
    "sg:postcode":"4125",
    "sg:province":"Basel-Stadt",
    "wof:name":"Karl Streck & Co Internationale Spedition Grenzb\u00fcro Riehen",
    "wof:placetype":"venue"
},
  "geometry": {"coordinates":[7.655577,47.595135],"type":"Point"}
}