{
  "type": "Feature",
  "properties": {
    "addr:full":"Post Ebersecken Luzern 6245",
    "addr:postcode":"6245",
    "iso:country":"CH",
    "sg:address":"Post",
    "sg:city":"Ebersecken",
    "sg:classifiers":[
        {
            "category":"Banks & Credit Unions",
            "subcategory":"Bank",
            "type":"Services"
        }
    ],
    "sg:phone":"+41 4162862400",
    "sg:postcode":"6245",
    "sg:province":"Luzern",
    "wof:name":"Luzerner Kantonalbank",
    "wof:placetype":"venue"
},
  "geometry": {"coordinates":[7.932855,47.1824],"type":"Point"}
}