{
  "type": "Feature",
  "properties": {
    "iso:country":"CH",
    "sg:address":"Liestalerstrasse 11",
    "sg:city":"Birsfelden",
    "sg:orig_category":"Vereine Fasnacht",
    "sg:phone":"+41 61 313 03 51",
    "sg:postcode":"4127",
    "sg:province":"Basel-Landschaft",
    "wof:name":"Glunggi",
    "wof:placetype":"venue"
},
  "geometry": {"coordinates":[7.6266131401,47.5491371155],"type":"Point"}
}