{
  "type": "Feature",
  "properties": {
    "iso:country":"CH",
    "sg:address":"Cattedrale Via 9 6900 Lugano. Postfach",
    "sg:city":"Lugano",
    "sg:orig_category":"RESTAURANTS: TEA-ROOMS",
    "sg:phone":"+41 91 923 43 72",
    "sg:postcode":"6900",
    "sg:province":"Ticino",
    "wof:name":"Gulissani Sa Ristorante",
    "wof:placetype":"venue"
},
  "geometry": {"coordinates":[8.9493436813,46.0046310425],"type":"Point"}
}