{
  "type": "Feature",
  "properties": {
    "iso:country":"CH",
    "sg:address":"Ebmatingerstrasse 22",
    "sg:city":"Zumikon",
    "sg:orig_category":"Wirtschaftspr\u00fcfung, Steuerberatung U Treuhand",
    "sg:phone":"+41 19180551",
    "sg:postcode":"8126",
    "sg:province":"Z\u00fcrich",
    "wof:name":"Fischer Annarose Buchhaltung/treuhand",
    "wof:placetype":"venue"
},
  "geometry": {"coordinates":[8.6237230301,47.3372879028],"type":"Point"}
}