{
  "type": "Feature",
  "properties": {
    "iso:country":"CH",
    "sg:address":"Erlenstrasse 36",
    "sg:city":"Richterswil",
    "sg:orig_category":"Rechtsberatung",
    "sg:phone":"+41 17848439",
    "sg:postcode":"8805",
    "sg:province":"Z\u00fcrich",
    "wof:name":"Immobilienberatung Zur Erle Eva Caflisch-hartmann",
    "wof:placetype":"venue"
},
  "geometry": {"coordinates":[8.7005720139,47.2121696472],"type":"Point"}
}