{
  "type": "Feature",
  "properties": {
    "iso:country":"CH",
    "sg:address":"Avenue De Ch\u00e2telaine 83",
    "sg:city":"Ch\u00e2telaine",
    "sg:classifiers":[
        {
            "category":"Education",
            "subcategory":"Library",
            "type":"Public Place"
        }
    ],
    "sg:phone":"+41 22 796 06 22",
    "sg:postcode":"1219",
    "sg:province":"Gen\u00e8ve",
    "sg:tags":[
        "u",
        "bibliotheken",
        "archive"
    ],
    "wof:name":"Biblioth\u00e8que Municipale De Ch\u00e2telaine",
    "wof:placetype":"venue"
},
  "geometry": {"coordinates":[6.112737,46.210648],"type":"Point"}
}