{
  "type": "Feature",
  "properties": {
    "iso:country":"CH",
    "sg:address":"Stampfenmattsstrasse 12",
    "sg:city":"Zwillikon",
    "sg:orig_category":"Malerei",
    "sg:phone":"+41 17610973",
    "sg:postcode":"8909",
    "sg:province":"Z\u00fcrich",
    "wof:name":"Martin Fuchs Malerarbeiten",
    "wof:placetype":"venue"
},
  "geometry": {"coordinates":[8.4336748123,47.2863540649],"type":"Point"}
}