{
  "type": "Feature",
  "properties": {
    "iso:country":"CH",
    "sg:address":"Barcelonastrasse 16",
    "sg:city":"M\u00fcnchenstein",
    "sg:orig_category":"Instandhaltung U Reparatur von Automobilen",
    "sg:postcode":"4142",
    "sg:province":"Basel-Landschaft",
    "wof:name":"Autospritzwerk Lazarevic",
    "wof:placetype":"venue"
},
  "geometry": {"coordinates":[7.6066799164,47.5299377441],"type":"Point"}
}