{
  "type": "Feature",
  "properties": {
    "iso:country":"CH",
    "sg:address":"Rue Louis-curtat 1",
    "sg:city":"Lausanne",
    "sg:orig_category":"Detailhandel mit Geschenkartikeln U Souvenirs Detailhandel mit Schreib U Papeteriewaren",
    "sg:phone":"+41 21 320 71 49",
    "sg:postcode":"1005",
    "sg:province":"Vaud",
    "wof:name":"L'ecritoire Design S\u00e0rl Papeterie",
    "wof:placetype":"venue"
},
  "geometry": {"coordinates":[6.6359968185,46.522403717],"type":"Point"}
}