{
  "type": "Feature",
  "properties": {
    "iso:country":"CH",
    "sg:address":"Kanonengasse 31 4051 Basel. Postfach",
    "sg:city":"Basel",
    "sg:orig_category":"Erwachsenenbildung U Unterricht",
    "sg:postcode":"4051",
    "sg:province":"Basel-Stadt",
    "wof:name":"Bleu Blanc Rouge Ecole De Fran\u00e7ais Gmbh Sprachunterricht, Bes. Franz\u00f6sisch. Sprachaufenthalte; Organisation. Beratung U. Vermittlugn In Den Bereichen Versicherungen Usw",
    "wof:placetype":"venue"
},
  "geometry": {"coordinates":[7.5853729248,47.5530776978],"type":"Point"}
}