{
  "type": "Feature",
  "properties": {
    "iso:country":"CH",
    "sg:address":"Frankfurt-strasse 78a",
    "sg:city":"M\u00fcnchenstein",
    "sg:orig_category":"Non-Classified Establishments",
    "sg:phone":"+41 61 416 36 36",
    "sg:postcode":"4142",
    "sg:province":"Basel-Landschaft",
    "wof:name":"Penta-electric Ag Zweigniederlassung M\u00fcnchenstein",
    "wof:placetype":"venue"
},
  "geometry": {"coordinates":[7.60623,47.527306],"type":"Point"}
}