{
  "type": "Feature",
  "properties": {
    "addr:full":"Hohensteinweg 10 Z\u00fcrich Z\u00fcrich 8055",
    "addr:housenumber":"10",
    "addr:postcode":"8055",
    "addr:street":"Hohensteinweg",
    "iso:country":"CH",
    "sg:address":"Hohensteinweg 10",
    "sg:city":"Z\u00fcrich",
    "sg:orig_category":"Coiffeursalons Parf\u00fcmerien U sonstiger Detailhandel mit kosmetischen Artikeln U K\u00f6rperpflegemitteln",
    "sg:phone":"+41 14626482",
    "sg:postcode":"8055",
    "sg:province":"Z\u00fcrich",
    "wof:name":"Walter Siegele",
    "wof:placetype":"venue"
},
  "geometry": {"coordinates":[8.49407,47.36504],"type":"Point"}
}