{
  "type": "Feature",
  "properties": {
    "iso:country":"CH",
    "sg:address":"Tiefweg 56",
    "sg:city":"Riehen",
    "sg:orig_category":"Softwareentwicklung U beratung",
    "sg:phone":"+41 61 602 00 17",
    "sg:postcode":"4125",
    "sg:province":"Basel-Stadt",
    "wof:name":"Cad Design + Support Rolf Leuzinger",
    "wof:placetype":"venue"
},
  "geometry": {"coordinates":[7.6455030441,47.5719680786],"type":"Point"}
}