{
  "type": "Feature",
  "properties": {
    "iso:country":"CH",
    "sg:address":"Pilgerweg 6 3007 Bern. Postfach",
    "sg:city":"Bern",
    "sg:orig_category":"Mechanik",
    "sg:postcode":"3005",
    "sg:province":"Bern",
    "wof:name":"Art Decor Wyss U. Kunstschlosserei",
    "wof:placetype":"venue"
},
  "geometry": {"coordinates":[7.4217967987,46.942741394],"type":"Point"}
}