{
  "type": "Feature",
  "properties": {
    "iso:country":"CH",
    "sg:address":"B\u00e4ndlistrasse 62",
    "sg:city":"Z\u00fcrich",
    "sg:orig_category":"Betrieb von Taxis",
    "sg:phone":"+41 81 302 32 08",
    "sg:postcode":"8064",
    "sg:province":"Z\u00fcrich",
    "wof:name":"Tamina Taxi W. Cadurisch",
    "wof:placetype":"venue"
},
  "geometry": {"coordinates":[9.497303,47.004868],"type":"Point"}
}