{
  "type": "Feature",
  "properties": {
    "iso:country":"CH",
    "sg:address":"Avenue Rosemont 11",
    "sg:city":"Gen\u00e8ve",
    "sg:orig_category":"Grosshandel mit Foto U Kinoger\u00e4ten, feinmechanischen U optischen Erzeugnissen",
    "sg:phone":"+41 22 840 05 60",
    "sg:postcode":"1208",
    "sg:province":"Gen\u00e8ve",
    "wof:name":"M & D Distribution Sa",
    "wof:placetype":"venue"
},
  "geometry": {"coordinates":[6.1724081039,46.2020378113],"type":"Point"}
}