{
  "type": "Feature",
  "properties": {
    "iso:country":"CH",
    "sg:address":"Steinbruchstrasse 18",
    "sg:city":"Chur",
    "sg:orig_category":"Zivilschutz",
    "sg:phone":"+41 81 257 21 21",
    "sg:postcode":"7000",
    "sg:province":"Graubunden",
    "wof:name":"Kant. Amt F\u00fcr Zivilschutz",
    "wof:placetype":"venue"
},
  "geometry": {"coordinates":[9.5361289978,46.8522987366],"type":"Point"}
}