{
  "type": "Feature",
  "properties": {
    "iso:country":"CH",
    "sg:address":"Hauptstrasse 18",
    "sg:city":"Auenstein",
    "sg:orig_category":"Unclassifiable Establishments",
    "sg:phone":"+41 62 897 11 85",
    "sg:postcode":"5105",
    "sg:province":"Aargau",
    "wof:name":"Curo Gmbh",
    "wof:placetype":"venue"
},
  "geometry": {"coordinates":[8.1369132996,47.4167823792],"type":"Point"}
}