{
  "type": "Feature",
  "properties": {
    "iso:country":"CH",
    "sg:address":"Hinterfeld 6c",
    "sg:city":"Altendorf",
    "sg:orig_category":"Architektur U Ingenieurb\u00fcros Architekturb\u00fcros",
    "sg:phone":"+41 55 442 32 05",
    "sg:postcode":"8852",
    "sg:province":"Schwyz",
    "wof:name":"H\u00f6rner R. + K",
    "wof:placetype":"venue"
},
  "geometry": {"coordinates":[8.834389,47.190273],"type":"Point"}
}