{
  "type": "Feature",
  "properties": {
    "iso:country":"CH",
    "sg:address":"Riedhofstrasse 71 8105 Regensdorf. Postfach 93",
    "sg:city":"Regensdorf",
    "sg:orig_category":"Sportvereine Eissport Eisstock",
    "sg:phone":"+41 18401365",
    "sg:postcode":"8105",
    "sg:province":"Z\u00fcrich",
    "wof:name":"Esc Regensdorf",
    "wof:placetype":"venue"
},
  "geometry": {"coordinates":[8.4674386978,47.4367980957],"type":"Point"}
}