{
  "type": "Feature",
  "properties": {
    "iso:country":"CH",
    "sg:address":"Chemin De La Chapelle",
    "sg:city":"St-cergue",
    "sg:orig_category":"Sportschulen Ski-& Snowboardschulen",
    "sg:phone":"+41 81 422 66 60",
    "sg:postcode":"1264",
    "sg:province":"Vaud",
    "wof:name":"Duty Snowboardschool Madrisa Snowboardschule Ssgs",
    "wof:placetype":"venue"
},
  "geometry": {"coordinates":[9.8762979507,46.8830718994],"type":"Point"}
}