{
  "type": "Feature",
  "properties": {
    "iso:country":"CH",
    "sg:address":"Winterthurerstrasse 655 8051 Z\u00fcrich. Postfach",
    "sg:city":"Z\u00fcrich",
    "sg:orig_category":"Interessenvertretungen",
    "sg:postcode":"8051",
    "sg:province":"Z\u00fcrich",
    "wof:name":"New Inter Hkb Ag",
    "wof:placetype":"venue"
},
  "geometry": {"coordinates":[8.3113193512,46.9970169067],"type":"Point"}
}