{
  "type": "Feature",
  "properties": {
    "iso:country":"CH",
    "sg:address":"Mitteldorfstrasse 9",
    "sg:city":"H\u00e4gglingen",
    "sg:orig_category":"Detailhandel mit Waren verschiedener Art, Hauptrichtung Nahrungsmittel",
    "sg:phone":"+41 56 624 12 55",
    "sg:postcode":"5607",
    "sg:province":"Aargau",
    "wof:name":"Walter Stutz Lebensmittel",
    "wof:placetype":"venue"
},
  "geometry": {"coordinates":[8.2535934448,47.3889122009],"type":"Point"}
}