{
  "type": "Feature",
  "properties": {
    "iso:country":"CH",
    "sg:address":"Baslerstrasse 87",
    "sg:city":"Trimbach",
    "sg:orig_category":"Herstellung von Radio U Fernsehger\u00e4ten sowie phono U videotechnischen Ger\u00e4ten",
    "sg:phone":"+41 62 293 48 48",
    "sg:postcode":"4632",
    "sg:province":"Solothurn",
    "wof:name":"Vonesch Ag Hifi/tv/video",
    "wof:placetype":"venue"
},
  "geometry": {"coordinates":[7.8991479874,47.3614311218],"type":"Point"}
}