{
  "type": "Feature",
  "properties": {
    "iso:country":"CH",
    "sg:address":"Pr\u00e9-cartelier Chemin Du 20 1202 Gen\u00e8ve. Postfach",
    "sg:city":"Gen\u00e8ve",
    "sg:orig_category":"Gesundheitswesen",
    "sg:postcode":"1202",
    "sg:province":"Gen\u00e8ve",
    "wof:name":"Edel Therapeutics Sa",
    "wof:placetype":"venue"
},
  "geometry": {"coordinates":[6.1309108734,46.2197685242],"type":"Point"}
}