{
  "type": "Feature",
  "properties": {
    "iso:country":"CH",
    "sg:address":"1613",
    "sg:city":"Maracon",
    "sg:orig_category":"K\u00fcnstlerische U schriftstellerische T\u00e4tigkeiten U Darbietungen",
    "sg:phone":"+41 71 222 59 11",
    "sg:postcode":"1613",
    "sg:province":"Vaud",
    "wof:name":"Schmitt Roland E. Ag",
    "wof:placetype":"venue"
},
  "geometry": {"coordinates":[9.3854026794,47.4142684937],"type":"Point"}
}