{
  "type": "Feature",
  "properties": {
    "iso:country":"CH",
    "sg:address":"Monnet Via 10",
    "sg:city":"Vernier",
    "sg:orig_category":"RESTAURANTS: TEA-ROOMS",
    "sg:phone":"+41 22 788 59 14",
    "sg:postcode":"1214",
    "sg:province":"Gen\u00e8ve",
    "wof:name":"Costanza Anna-lisa",
    "wof:placetype":"venue"
},
  "geometry": {"coordinates":[6.0813560486,46.2183113098],"type":"Point"}
}