{
  "type": "Feature",
  "properties": {
    "iso:country":"CH",
    "sg:address":"Route Du Stadtberg 5a",
    "sg:city":"Fribourg",
    "sg:orig_category":"Autospenglereien",
    "sg:phone":"+41 26 475 28 24",
    "sg:postcode":"1700",
    "sg:province":"Fribourg",
    "wof:name":"Andr\u00e9 Bulliard Carrosserie",
    "wof:placetype":"venue"
},
  "geometry": {"coordinates":[7.165565,46.810131],"type":"Point"}
}