{
  "type": "Feature",
  "properties": {
    "iso:country":"CH",
    "sg:address":"Arenenbergstrasse 2",
    "sg:city":"Salenstein",
    "sg:orig_category":"Wirtschaftspr\u00fcfung, Steuerberatung U Treuhand",
    "sg:postcode":"8268",
    "sg:province":"Thurgau",
    "wof:name":"Pharmaceutical And Chemical Services Sa",
    "wof:placetype":"venue"
},
  "geometry": {"coordinates":[8.9218196869,45.9306106567],"type":"Point"}
}