{
  "type": "Feature",
  "properties": {
    "iso:country":"CH",
    "sg:address":"Zelgstrasse 9",
    "sg:city":"Uster",
    "sg:orig_category":"Vereine Geselligkeit",
    "sg:postcode":"8610",
    "sg:province":"Z\u00fcrich",
    "wof:name":"Appenzeller-& St.gallerverein",
    "wof:placetype":"venue"
},
  "geometry": {"coordinates":[8.7082719803,47.3434486389],"type":"Point"}
}