{
  "type": "Feature",
  "properties": {
    "iso:country":"CH",
    "sg:address":"3961",
    "sg:city":"Vissoie",
    "sg:orig_category":"Campingpl\u00e4tze Detailhandel mit Zeitungen U Zeitschriften Kioske",
    "sg:phone":"+41 27 475 14 09",
    "sg:postcode":"3961",
    "sg:province":"Valais",
    "wof:name":"Camping D'anniviers",
    "wof:placetype":"venue"
},
  "geometry": {"coordinates":[7.586425,46.214684],"type":"Point"}
}