{
  "type": "Feature",
  "properties": {
    "iso:country":"CH",
    "sg:address":"Schmiedgasse 33",
    "sg:city":"Herisau",
    "sg:orig_category":"Vermietung U Verpachtung von eigenen Immobilien Vermittlung von Immobilien",
    "sg:phone":"+41 71 351 10 86",
    "sg:postcode":"9100",
    "sg:province":"Appenzell Ausserrhoden",
    "wof:name":"Realbau Ag F\u00fcr Immobilien Und Projektmanagement",
    "wof:placetype":"venue"
},
  "geometry": {"coordinates":[9.276881218,47.3845901489],"type":"Point"}
}