{
  "type": "Feature",
  "properties": {
    "iso:country":"CH",
    "sg:address":"Avenue De Rumine 7",
    "sg:city":"Lausanne",
    "sg:orig_category":"Architektur U Ingenieurb\u00fcros Architekturb\u00fcros",
    "sg:phone":"+41 21 323 03 61",
    "sg:postcode":"1005",
    "sg:province":"Vaud",
    "wof:name":"De Rham Herv\u00e9 Architecte Sa",
    "wof:placetype":"venue"
},
  "geometry": {"coordinates":[6.638789,46.517696],"type":"Point"}
}