{
  "type": "Feature",
  "properties": {
    "iso:country":"CH",
    "sg:address":"Industriestrasse 592 4625 Oberbuchsiten. Postfach",
    "sg:city":"Oberbuchsiten",
    "sg:classifiers":[
        {
            "category":"Travel",
            "subcategory":"Hotels & Motels",
            "type":"Entertainment"
        }
    ],
    "sg:postcode":"4625",
    "sg:province":"Solothurn",
    "sg:tags":[
        "hotels",
        "mit",
        "restaurant"
    ],
    "wof:name":"R\u00f6merbad Betriebs Gmbh Hotel, Restaurant Mit Showbetrieb",
    "wof:placetype":"venue"
},
  "geometry": {"coordinates":[7.7752728462,47.3074302673],"type":"Point"}
}