{
  "type": "Feature",
  "properties": {
    "iso:country":"CH",
    "sg:address":"Cuves-la-tine",
    "sg:city":"Rossini\u00e8re",
    "sg:orig_category":"Herstellung von sonstigen landwirtschaftlichen Maschinen Schmieden",
    "sg:phone":"+41 26 924 65 56",
    "sg:postcode":"1836",
    "wof:name":"Andr\u00e9 Pilet Forge",
    "wof:placetype":"venue"
},
  "geometry": {"coordinates":[7.051680088,46.469959259],"type":"Point"}
}