{
  "type": "Feature",
  "properties": {
    "iso:country":"CH",
    "sg:address":"Rue Joseph Trouillat 16",
    "sg:city":"Porrentruy",
    "sg:classifiers":[
        {
            "category":"Professional",
            "subcategory":"Employment Agencies",
            "type":"Services"
        }
    ],
    "sg:phone":"+41 32 465 70 00",
    "sg:postcode":"2900",
    "sg:province":"Jura",
    "sg:tags":[
        "personal",
        "u",
        "stellenvermittlung"
    ],
    "wof:name":"Paul Cramatte Sa, Placement De Personnel",
    "wof:placetype":"venue"
},
  "geometry": {"coordinates":[7.0735168457,47.417678833],"type":"Point"}
}