{
  "type": "Feature",
  "properties": {
    "iso:country":"CH",
    "sg:address":"Eisenbahnweg 6",
    "sg:city":"Basel",
    "sg:orig_category":"Sportvereine Ballsport Tennis",
    "sg:phone":"+41 62 929 37 07",
    "sg:postcode":"4058",
    "sg:province":"Basel-Stadt",
    "wof:name":"Tennisclub Roggwil",
    "wof:placetype":"venue"
},
  "geometry": {"coordinates":[7.8228058815,47.2411155701],"type":"Point"}
}