{
  "type": "Feature",
  "properties": {
    "iso:country":"CH",
    "sg:address":"Witzwil",
    "sg:city":"Gampelen",
    "sg:orig_category":"Institutionen f\u00fcr Suchtkranke",
    "sg:phone":"+41 32 312 94 34",
    "sg:postcode":"3236",
    "sg:province":"Bern",
    "wof:name":"Heim F\u00fcr Halbfreiheit Eschenhof",
    "wof:placetype":"venue"
},
  "geometry": {"coordinates":[7.0605697632,46.9881706238],"type":"Point"}
}