{
  "type": "Feature",
  "properties": {
    "iso:country":"CH",
    "sg:address":"Av. De La Gare 46 1000 Lausanne. Postfach",
    "sg:city":"Lausanne",
    "sg:classifiers":[
        {
            "category":"Travel",
            "subcategory":"Hotels & Motels",
            "type":"Entertainment"
        }
    ],
    "sg:postcode":"1003",
    "sg:province":"Vaud",
    "sg:tags":[
        "hotels",
        "mit",
        "restaurant"
    ],
    "wof:name":"H\u00f4tel Victoria, H\u00e4berli R.",
    "wof:placetype":"venue"
},
  "geometry": {"coordinates":[6.6314339638,46.5174446106],"type":"Point"}
}