{
  "type": "Feature",
  "properties": {
    "iso:country":"CH",
    "sg:address":"Challstrasse 27",
    "sg:city":"Metzerlen",
    "sg:orig_category":"Zahntechnische Laboratorien",
    "sg:phone":"+41 79 356 38 00",
    "sg:postcode":"4116",
    "sg:province":"Solothurn",
    "wof:name":"Daniela Haberth\u00fcr Zahntechnisches Labor",
    "wof:placetype":"venue"
},
  "geometry": {"coordinates":[7.4639201164,47.4619255066],"type":"Point"}
}