{
  "type": "Feature",
  "properties": {
    "iso:country":"CH",
    "sg:address":"Rue De L'orbe 1337 Vallorbe. Postfach",
    "sg:city":"Vallorbe",
    "sg:orig_category":"G\u00fcterbef\u00f6rderung im Strassenverkehr",
    "sg:phone":"+41 21 843 15 46",
    "sg:postcode":"1337",
    "sg:province":"Vaud",
    "wof:name":"Transports Vallorbe Sa",
    "wof:placetype":"venue"
},
  "geometry": {"coordinates":[6.3765912056,46.7088851929],"type":"Point"}
}