{
  "type": "Feature",
  "properties": {
    "iso:country":"CH",
    "sg:address":"Badenerstrasse 85",
    "sg:city":"Z\u00fcrich",
    "sg:orig_category":"Caterer Fast-Foodrestaurants",
    "sg:phone":"+41 12429814",
    "sg:postcode":"8004",
    "sg:province":"Z\u00fcrich",
    "wof:name":"Sandwiches, Catering Quick",
    "wof:placetype":"venue"
},
  "geometry": {"coordinates":[8.526211,47.373848],"type":"Point"}
}