{
  "type": "Feature",
  "properties": {
    "iso:country":"CH",
    "sg:address":"Seestrasse 39 8596 Scherzingen. Postfach 138",
    "sg:city":"Scherzingen",
    "sg:orig_category":"Finanzierungsinstitutionen",
    "sg:phone":"+41 71 688 80 82",
    "sg:postcode":"8596",
    "sg:province":"Thurgau",
    "wof:name":"Marin Ag",
    "wof:placetype":"venue"
},
  "geometry": {"coordinates":[9.2257156372,47.6330718994],"type":"Point"}
}