{
  "type": "Feature",
  "properties": {
    "iso:country":"CH",
    "sg:address":"Alte Bernstrasse 23",
    "sg:city":"Aegerten",
    "sg:orig_category":"Bauspenglerei Zimmerei, Dachdeckerei, Bauspenglerei U Abdichtung",
    "sg:postcode":"2558",
    "sg:province":"Bern",
    "wof:name":"Schenk Max.",
    "wof:placetype":"venue"
},
  "geometry": {"coordinates":[7.291615,47.119049],"type":"Point"}
}