{
  "type": "Feature",
  "properties": {
    "iso:country":"CH",
    "sg:address":"Akazienstrasse 7",
    "sg:city":"Z\u00fcrich",
    "sg:orig_category":"Kunsthandel",
    "sg:phone":"+41 31 951 11 21",
    "sg:postcode":"8008",
    "sg:province":"Z\u00fcrich",
    "wof:name":"Ruth Mentha Galerie",
    "wof:placetype":"venue"
},
  "geometry": {"coordinates":[7.4783267975,46.933265686],"type":"Point"}
}