{
  "type": "Feature",
  "properties": {
    "iso:country":"CH",
    "sg:address":"Besmerstrasse 25",
    "sg:city":"Kreuzlingen",
    "sg:orig_category":"Sonstiger Grosshandel",
    "sg:phone":"+41 71 688 32 70",
    "sg:postcode":"8280",
    "sg:province":"Thurgau",
    "wof:name":"Handels Und Verkaufs Ag Kreuzlingen.",
    "wof:placetype":"venue"
},
  "geometry": {"coordinates":[9.1874752045,47.6406135559],"type":"Point"}
}