{
  "type": "Feature",
  "properties": {
    "iso:country":"CH",
    "sg:address":"Seegartenstrasse 4",
    "sg:city":"Schmerikon",
    "sg:orig_category":"Zimmerei, Dachdeckerei, Bauspenglerei U Abdichtung",
    "sg:postcode":"8716",
    "sg:province":"St. Gallen",
    "wof:name":"Engeli Reto B\u00fcro F\u00fcr Holzbauplanungen",
    "wof:placetype":"venue"
},
  "geometry": {"coordinates":[8.9512500763,47.2256584167],"type":"Point"}
}