{
  "type": "Feature",
  "properties": {
    "iso:country":"CH",
    "sg:address":"Flughafenstrasse 1",
    "sg:city":"Altenrhein",
    "sg:orig_category":"Mechanik Schlossereien",
    "sg:phone":"+41 71 855 10 66",
    "sg:postcode":"9423",
    "sg:province":"St. Gallen",
    "wof:name":"J\u00fcrg Rufer Schlosserei",
    "wof:placetype":"venue"
},
  "geometry": {"coordinates":[9.5526638031,47.4885635376],"type":"Point"}
}