{
  "type": "Feature",
  "properties": {
    "iso:country":"CH",
    "sg:address":"Agnesstrasse 1 8004 Z\u00fcrich. Postfach",
    "sg:city":"Z\u00fcrich",
    "sg:orig_category":"Erbringung von sonstigen Dienstleistungen f\u00fcr Unterhaltung, Erholung U Freizeit",
    "sg:postcode":"8001",
    "sg:province":"Z\u00fcrich",
    "wof:name":"Tour Service, Kurt Ernst Planung, Organisation U. Durchf\u00fchrung Von Tourneen Und Auftritten, Beratung In Beschallungs Und Tontechnik",
    "wof:placetype":"venue"
},
  "geometry": {"coordinates":[8.5158548355,47.3771247864],"type":"Point"}
}