{
  "type": "Feature",
  "properties": {
    "iso:country":"CH",
    "sg:address":"Schulstrasse 7 8413 Neftenbach. Postfach 332",
    "sg:city":"Neftenbach",
    "sg:orig_category":"Landesverteidigung, Sozialversicherung \u00d6ffentliche Verwaltung",
    "sg:phone":"+41 52 305 06 66",
    "sg:postcode":"8413",
    "sg:province":"Z\u00fcrich",
    "wof:name":"Zivilschutzstelle Neftenbach",
    "wof:placetype":"venue"
},
  "geometry": {"coordinates":[8.6669597626,47.52684021],"type":"Point"}
}