{
  "type": "Feature",
  "properties": {
    "iso:country":"CH",
    "sg:address":"9052",
    "sg:city":"Niederteufen",
    "sg:orig_category":"Wohnheime",
    "sg:phone":"+41 71 333 13 61",
    "sg:postcode":"9052",
    "sg:province":"Appenzell Ausserrhoden",
    "wof:name":"Kloster Wonnenstein",
    "wof:placetype":"venue"
},
  "geometry": {"coordinates":[9.3625898361,47.3931999207],"type":"Point"}
}