{
  "type": "Feature",
  "properties": {
    "iso:country":"CH",
    "sg:address":"Im Ch\u00fcchelacher 5",
    "sg:city":"Sch\u00f6fflisdorf",
    "sg:orig_category":"Herstellung von Duft U K\u00f6rperpflegemitteln",
    "sg:phone":"+41 18561025",
    "sg:postcode":"8165",
    "sg:province":"Z\u00fcrich",
    "wof:name":"Pro Natura De Silva",
    "wof:placetype":"venue"
},
  "geometry": {"coordinates":[8.4189138412,47.5022315979],"type":"Point"}
}