{
  "type": "Feature",
  "properties": {
    "addr:full":"R\u00fcegsaustr. 35 Hasle Bern 3415",
    "addr:housenumber":"35",
    "addr:postcode":"3415",
    "addr:street":"Rueegsaustr.",
    "iso:country":"CH",
    "sg:address":"R\u00fcegsaustr. 35",
    "sg:city":"Hasle",
    "sg:classifiers":[
        {
            "category":"Banks & Credit Unions",
            "subcategory":"Bank",
            "type":"Services"
        }
    ],
    "sg:phone":"+41 62 927 22 66",
    "sg:postcode":"3415",
    "sg:province":"Bern",
    "wof:name":"Spar-und Leihkasse Melchnau",
    "wof:placetype":"venue"
},
  "geometry": {"coordinates":[7.832543,47.185917],"type":"Point"}
}