{
  "type": "Feature",
  "properties": {
    "iso:country":"CH",
    "sg:address":"Vorderhasle 1106",
    "sg:city":"Wolfhalden",
    "sg:orig_category":"Herstellung von K\u00fcchenm\u00f6beln",
    "sg:phone":"+41 71 888 20 20",
    "sg:postcode":"9427",
    "sg:province":"Appenzell Ausserrhoden",
    "wof:name":"Royal Norm Gmbh",
    "wof:placetype":"venue"
},
  "geometry": {"coordinates":[9.5577526093,47.4618263245],"type":"Point"}
}