{
  "type": "Feature",
  "properties": {
    "iso:country":"CH",
    "sg:address":"Spitalgasse 6",
    "sg:city":"Langenthal",
    "sg:orig_category":"Kinos",
    "sg:phone":"+41 62 922 14 50",
    "sg:postcode":"4900",
    "sg:province":"Bern",
    "wof:name":"Kino Capitol",
    "wof:placetype":"venue"
},
  "geometry": {"coordinates":[7.7895421982,47.2111206055],"type":"Point"}
}