{
  "type": "Feature",
  "properties": {
    "iso:country":"CH",
    "sg:address":"Hofstrasse 70 8032 Z\u00fcrich",
    "sg:city":"Zust",
    "sg:orig_category":"Pensionskassen",
    "sg:postcode":"32",
    "wof:name":"Wohlfahrtsstiftung Der Firma Gugelmann & Cie Ag",
    "wof:placetype":"venue"
},
  "geometry": {"coordinates":[7.8092489243,47.2483177185],"type":"Point"}
}