{
  "type": "Feature",
  "properties": {
    "iso:country":"CH",
    "sg:address":"Konstanzerstrasse 14a",
    "sg:city":"Rossr\u00fcti",
    "sg:orig_category":"Einzelhandel mit Automobilteilen U Zubeh\u00f6r Handel mit Motorr\u00e4dern, Teilen U Zubeh\u00f6r Instandhaltung U",
    "sg:phone":"+41 71 911 85 15",
    "sg:postcode":"9512",
    "sg:province":"St. Gallen",
    "wof:name":"Gebr. Roland & Urs Egli",
    "wof:placetype":"venue"
},
  "geometry": {"coordinates":[9.0606145859,47.4736251831],"type":"Point"}
}