{
  "type": "Feature",
  "properties": {
    "iso:country":"CH",
    "sg:address":"4303",
    "sg:city":"Kaiseraugst",
    "sg:orig_category":"Vereine Musik/Blasmusik",
    "sg:phone":"+41 61 811 26 69",
    "sg:postcode":"4303",
    "sg:province":"Aargau",
    "wof:name":"Musikgesellschaft",
    "wof:placetype":"venue"
},
  "geometry": {"coordinates":[7.7361001968,47.5354118347],"type":"Point"}
}