{
  "type": "Feature",
  "properties": {
    "iso:country":"CH",
    "sg:address":"Pr\u00e9 Yonnet Chemin De 31",
    "sg:city":"Aigle",
    "sg:orig_category":"Allgemeiner Hoch U Tiefbau",
    "sg:phone":"+41 24 466 71 79",
    "sg:postcode":"1860",
    "sg:province":"Vaud",
    "wof:name":"Claude Guillard S\u00e0rl",
    "wof:placetype":"venue"
},
  "geometry": {"coordinates":[6.964694,46.321033],"type":"Point"}
}