{
  "type": "Feature",
  "properties": {
    "iso:country":"CH",
    "sg:address":"8604",
    "sg:city":"Volketswil",
    "sg:orig_category":"Wirtschaftspr\u00fcfung, Steuerberatung U Treuhand",
    "sg:phone":"+41 19462333",
    "sg:postcode":"8604",
    "sg:province":"Z\u00fcrich",
    "wof:name":"Hans R. Bolliger Bireva-consulting B\u00fcrosoftware F\u00fc Kmu",
    "wof:placetype":"venue"
},
  "geometry": {"coordinates":[8.6897258759,47.3896369934],"type":"Point"}
}