{
  "type": "Feature",
  "properties": {
    "iso:country":"CH",
    "sg:address":"Pelikanstrasse 37 8021 Z\u00fcrich. Postfach 1376",
    "sg:city":"Z\u00fcrich",
    "sg:orig_category":"Wirtschaftspr\u00fcfung, Steuerberatung U Treuhand",
    "sg:phone":"+41 12275200",
    "sg:postcode":"8021",
    "sg:province":"Z\u00fcrich",
    "wof:name":"Aig Global Investment Ag",
    "wof:placetype":"venue"
},
  "geometry": {"coordinates":[8.5356121063,47.3708000183],"type":"Point"}
}