{
  "type": "Feature",
  "properties": {
    "iso:country":"CH",
    "sg:address":"Hauts-cr\u00eats Chemin Des 86",
    "sg:city":"Cologny",
    "sg:orig_category":"Unternehmensberatung",
    "sg:postcode":"1223",
    "sg:province":"Gen\u00e8ve",
    "wof:name":"Maurice, International Business Consulting",
    "wof:placetype":"venue"
},
  "geometry": {"coordinates":[6.1876049042,46.2167701721],"type":"Point"}
}