{
  "type": "Feature",
  "properties": {
    "iso:country":"CH",
    "sg:address":"Strohwiesstrasse 5",
    "sg:city":"Horgen",
    "sg:orig_category":"Detailhandel mit Zeitungen U Zeitschriften Kioske Sonstige mit der Informatik verbundene T\u00e4tigkeiten",
    "sg:phone":"+41 17260322",
    "sg:postcode":"8810",
    "sg:province":"Z\u00fcrich",
    "wof:name":"D\u00f6ssegger Dienstleistungen",
    "wof:placetype":"venue"
},
  "geometry": {"coordinates":[8.5848999023,47.2657203674],"type":"Point"}
}