{
  "type": "Feature",
  "properties": {
    "iso:country":"CH",
    "sg:address":"Alte Simplonstrasse 29 3900 Brig. Postfach",
    "sg:city":"Brig",
    "sg:orig_category":"RESTAURANTS: TEA-ROOMS",
    "sg:phone":"+41 21 946 38 40",
    "sg:postcode":"3900",
    "sg:province":"Valais",
    "wof:name":"Restaurant De La Place, Schwery Rolf",
    "wof:placetype":"venue"
},
  "geometry": {"coordinates":[7.9902839661,46.3158912659],"type":"Point"}
}