{
  "type": "Feature",
  "properties": {
    "iso:country":"CH",
    "sg:address":"Ottisbergstrasse 21 3186 D\u00fcdingen. Postfach 195",
    "sg:city":"D\u00fcdingen",
    "sg:orig_category":"Sonstiger spezialisierter Hoch U Tiefbau Strassenbau",
    "sg:phone":"+41 79 446 24 66",
    "sg:postcode":"3186",
    "sg:province":"Fribourg",
    "wof:name":"Riedo & Etter Ag",
    "wof:placetype":"venue"
},
  "geometry": {"coordinates":[7.180316925,46.848110199],"type":"Point"}
}