{
  "type": "Feature",
  "properties": {
    "iso:country":"CH",
    "sg:address":"Pal. Pianscari 6916 Grancia. Postfach",
    "sg:city":"Grancia",
    "sg:orig_category":"Erbringung von sonstigen Dienstleistungen f\u00fcr Unterhaltung, Erholung U Freizeit",
    "sg:postcode":"6916",
    "sg:province":"Ticino",
    "wof:name":"Comedil Racing Team, Titolare Comini Pietro Gestione Di Una Squadra Di Kart. Kart, Pezzi Di Ricambio Ecc.; Acquisto, Vendita",
    "wof:placetype":"venue"
},
  "geometry": {"coordinates":[8.9250659943,45.9669761658],"type":"Point"}
}