{
  "type": "Feature",
  "properties": {
    "iso:country":"CH",
    "sg:address":"Buchenstrasse 10",
    "sg:city":"Basel",
    "sg:orig_category":"Sonstige Aktivit\u00e4ten der nicht-\u00e4rztlichen Medizinalberufe",
    "sg:phone":"+41 61 301 53 34",
    "sg:postcode":"4054",
    "sg:province":"Basel-Stadt",
    "wof:name":"Ursula Scherrer Atemtherapie",
    "wof:placetype":"venue"
},
  "geometry": {"coordinates":[7.5712862015,47.556312561],"type":"Point"}
}