{
  "type": "Feature",
  "properties": {
    "iso:country":"CH",
    "sg:address":"Ringstrasse 44 7000 Chur. Postfach",
    "sg:city":"Chur",
    "sg:orig_category":"Institutionen f\u00fcr Suchtkranke",
    "sg:phone":"+41 81 284 50 90",
    "sg:postcode":"7004",
    "sg:province":"Graubunden",
    "wof:name":"Nestw\u00e4rme Therapeutische Wohngemeinschaft F.drogenabh.",
    "wof:placetype":"venue"
},
  "geometry": {"coordinates":[9.5169658661,46.8551559448],"type":"Point"}
}