{
  "type": "Feature",
  "properties": {
    "iso:country":"CH",
    "sg:address":"Dorf 27",
    "sg:city":"Peterzell",
    "sg:classifiers":[
        {
            "category":"Travel",
            "subcategory":"Hotels & Motels",
            "type":"Entertainment"
        }
    ],
    "sg:phone":"+41 71 377 17 54",
    "sg:postcode":"9127",
    "sg:province":"St. Gallen",
    "sg:tags":[
        "hotels",
        "mit",
        "restaurant"
    ],
    "wof:name":"Nef Hansruedi",
    "wof:placetype":"venue"
},
  "geometry": {"coordinates":[8.4661121368,48.324432373],"type":"Point"}
}