{
  "type": "Feature",
  "properties": {
    "iso:country":"CH",
    "sg:address":"Rooststrasse 15 5417 Untersiggenthal. Postfach",
    "sg:city":"Untersiggenthal",
    "sg:orig_category":"RESTAURANTS: TEA-ROOMS",
    "sg:postcode":"5417",
    "sg:province":"Aargau",
    "wof:name":"Feu Sacr\u00e9 Gmbh Restaurant Mit Bar Usw",
    "wof:placetype":"venue"
},
  "geometry": {"coordinates":[8.2382955551,47.5057296753],"type":"Point"}
}