{
  "type": "Feature",
  "properties": {
    "iso:country":"CH",
    "sg:address":"Winkelmattenweg 18 3920 Zermatt. Postfach 430",
    "sg:city":"Zermatt",
    "sg:classifiers":[
        {
            "category":"Travel",
            "subcategory":"Hotels & Motels",
            "type":"Entertainment"
        }
    ],
    "sg:phone":"+41 27 967 54 00",
    "sg:postcode":"3920",
    "sg:province":"Valais",
    "sg:tags":[
        "hotels",
        "mit",
        "restaurant"
    ],
    "wof:name":"Hotel Berghof, Perren Regina",
    "wof:placetype":"venue"
},
  "geometry": {"coordinates":[7.7429118156,46.0148239136],"type":"Point"}
}