{
  "type": "Feature",
  "properties": {
    "iso:country":"CH",
    "sg:address":"Ettenbergstrasse 16 8907 Wettswil. Postfach 129",
    "sg:city":"Wettswil",
    "sg:orig_category":"Wirtschaftspr\u00fcfung, Steuerberatung U Treuhand",
    "sg:phone":"+41 41 729 61 61",
    "sg:postcode":"8907",
    "sg:province":"Z\u00fcrich",
    "wof:name":"Batev Bau-treuhand Und Immobilien-verwaltungs Ag",
    "wof:placetype":"venue"
},
  "geometry": {"coordinates":[8.2906999588,47.4518051147],"type":"Point"}
}