{
  "type": "Feature",
  "properties": {
    "iso:country":"CH",
    "sg:address":"Seefeldstrasse 173 8008 Z\u00fcrich. Postfach",
    "sg:city":"Z\u00fcrich",
    "sg:orig_category":"Detailhandel mit Antiquit\u00e4ten U Gebrauchtwaren in Verkaufsr\u00e4umen",
    "sg:phone":"+41 14226389",
    "sg:postcode":"8001",
    "sg:province":"Z\u00fcrich",
    "wof:name":"Kluge Ag Antiquit\u00e4ten Und Inneneinrichtungen; Handel",
    "wof:placetype":"venue"
},
  "geometry": {"coordinates":[8.557158,47.355141],"type":"Point"}
}