{
  "type": "Feature",
  "properties": {
    "iso:country":"CH",
    "sg:address":"La Forge",
    "sg:city":"Goumoens-la-ville",
    "sg:orig_category":"Detailhandel mit Beleuchtungs U Haushaltsgegenst\u00e4nden Detailhandel mit elektrischen Haushalts, Radio",
    "sg:phone":"+41 21 881 41 09",
    "sg:postcode":"1376",
    "sg:province":"Vaud",
    "wof:name":"Tony M\u00e9n\u00e9gon Appareils M\u00e9nagers",
    "wof:placetype":"venue"
},
  "geometry": {"coordinates":[6.604105,46.658161],"type":"Point"}
}