{
  "type": "Feature",
  "properties": {
    "iso:country":"CH",
    "sg:address":"Hauptstrasse 30 4528 Zuchwil. Postfach",
    "sg:city":"Zuchwil",
    "sg:classifiers":[
        {
            "category":"Restaurant",
            "type":"Food & Drink"
        }
    ],
    "sg:phone":"+41 71 222 86 61",
    "sg:postcode":"4528",
    "sg:province":"Solothurn",
    "wof:name":"Restaurant Birkenfeld",
    "wof:placetype":"venue"
},
  "geometry": {"coordinates":[9.3672380447,47.4181976318],"type":"Point"}
}