{
  "type": "Feature",
  "properties": {
    "addr:full":"Bahnhofstrasse 24 5000 Aarau. Postfach Aarau Aargau 5001",
    "addr:housenumber":"24",
    "addr:postcode":"5000 aarau. postfach;5001",
    "addr:street":"Bahnhofstrasse",
    "iso:country":"CH",
    "sg:address":"Bahnhofstrasse 24 5000 Aarau. Postfach",
    "sg:city":"Aarau",
    "sg:orig_category":"Bau von Strassen, Sportanlagen U Bahnverkehrsstrecken",
    "sg:postcode":"5001",
    "sg:province":"Aargau",
    "wof:name":"Batigroup (ticino) Sa",
    "wof:placetype":"venue"
},
  "geometry": {"coordinates":[9.12836,46.237598],"type":"Point"}
}