{
  "type": "Feature",
  "properties": {
    "iso:country":"CH",
    "sg:address":"Fr\u00f6belstrasse 33 8032 Z\u00fcrich. Postfach",
    "sg:city":"Z\u00fcrich",
    "sg:orig_category":"Werbung",
    "sg:phone":"+41 13885000",
    "sg:postcode":"8029",
    "wof:name":"Spool Ag",
    "wof:placetype":"venue"
},
  "geometry": {"coordinates":[8.567782402,47.3606376648],"type":"Point"}
}