{
  "type": "Feature",
  "properties": {
    "iso:country":"CH",
    "sg:address":"6315",
    "sg:city":"Ober\u00e4geri",
    "sg:orig_category":"Verwertung von Milch",
    "sg:postcode":"6315",
    "sg:province":"Zug",
    "wof:name":"K\u00e4sereigenossenschaft Haltenb\u00fchl.",
    "wof:placetype":"venue"
},
  "geometry": {"coordinates":[8.6155376434,47.1342010498],"type":"Point"}
}