{
  "type": "Feature",
  "properties": {
    "iso:country":"CH",
    "sg:address":"1632",
    "sg:city":"Riaz",
    "sg:orig_category":"S\u00e4ge, Hobel U Holzimpr\u00e4gnierwerke",
    "sg:phone":"+41 26 912 63 32",
    "sg:postcode":"1632",
    "sg:province":"Fribourg",
    "wof:name":"Pugin Louis",
    "wof:placetype":"venue"
},
  "geometry": {"coordinates":[7.0612578392,46.6383972168],"type":"Point"}
}