{
  "type": "Feature",
  "properties": {
    "iso:country":"CH",
    "sg:address":"Bachtelstr. 3",
    "sg:city":"Schaffhausen",
    "sg:orig_category":"Sportvereine Ballsport Handball",
    "sg:phone":"+41 52 625 52 46",
    "sg:postcode":"8200",
    "sg:province":"Schaffhausen",
    "wof:name":"Kjs Schaffhausen C/o Madi F\u00fchrer",
    "wof:placetype":"venue"
},
  "geometry": {"coordinates":[8.6217889786,47.7080917358],"type":"Point"}
}