{
  "type": "Feature",
  "properties": {
    "addr:full":"Avenue D'ouchy 18 Lausanne Vaud 1006",
    "addr:housenumber":"18",
    "addr:postcode":"1006",
    "addr:street":"Avenue D'Ouchy",
    "iso:country":"CH",
    "sg:address":"Avenue D'ouchy 18",
    "sg:city":"Lausanne",
    "sg:orig_category":"Detailhandel mit Antiquit\u00e4ten Kunsthandel",
    "sg:phone":"+41 21 616 37 37",
    "sg:postcode":"1006",
    "sg:province":"Vaud",
    "wof:name":"Nico Zachmann Galerie Panth\u00e9on",
    "wof:placetype":"venue"
},
  "geometry": {"coordinates":[6.63853,46.510639],"type":"Point"}
}