{
  "type": "Feature",
  "properties": {
    "iso:country":"CH",
    "sg:address":"Rudwies 17",
    "sg:city":"Egnach",
    "sg:orig_category":"Unternehmensberatung",
    "sg:phone":"+41 71 470 03 30",
    "sg:postcode":"9322",
    "sg:province":"Thurgau",
    "wof:name":"Katz & Partner",
    "wof:placetype":"venue"
},
  "geometry": {"coordinates":[9.3873710632,47.5439453125],"type":"Point"}
}