{
  "type": "Feature",
  "properties": {
    "iso:country":"CH",
    "sg:address":"H\u00f6henstrasse 15 8342 Wernetshausen. Postfach",
    "sg:city":"Wernetshausen",
    "sg:classifiers":[
        {
            "category":"Travel",
            "subcategory":"Hotels & Motels",
            "type":"Entertainment"
        }
    ],
    "sg:postcode":"8342",
    "sg:province":"Z\u00fcrich",
    "sg:tags":[
        "hotels",
        "mit",
        "restaurant"
    ],
    "wof:name":"B\u00fcchli Ernst",
    "wof:placetype":"venue"
},
  "geometry": {"coordinates":[8.8679037094,47.2963867188],"type":"Point"}
}