{
  "type": "Feature",
  "properties": {
    "iso:country":"CH",
    "sg:address":"Rue De La Conf\u00e9deration 8",
    "sg:city":"Gen\u00e8ve",
    "sg:classifiers":[
        {
            "category":"Restaurant",
            "type":"Food & Drink"
        }
    ],
    "sg:phone":"+41 22 311 42 35",
    "sg:postcode":"1204",
    "sg:province":"Gen\u00e8ve",
    "wof:name":"Cr\u00eaperie Bo\u00eete \u00e0 Cr\u00eapes",
    "wof:placetype":"venue"
},
  "geometry": {"coordinates":[6.1450438499,46.203453064],"type":"Point"}
}