{
  "type": "Feature",
  "properties": {
    "iso:country":"CH",
    "sg:address":"Route De La Gare 7",
    "sg:city":"Estavayer-le-lac",
    "sg:orig_category":"Geb\u00e4ude, Wohnungsreinigung",
    "sg:phone":"+41 79 606 10 76",
    "sg:postcode":"1470",
    "sg:province":"Fribourg",
    "wof:name":"Pierre Renout Entreprise De Nettoyage",
    "wof:placetype":"venue"
},
  "geometry": {"coordinates":[6.8419251442,46.8436164856],"type":"Point"}
}