{
  "type": "Feature",
  "properties": {
    "iso:country":"CH",
    "sg:address":"Rue Centrale 47",
    "sg:city":"Montagne-moutier",
    "sg:orig_category":"Interessenvertretungen",
    "sg:postcode":"2740",
    "sg:province":"Bern",
    "wof:name":"Institution Sociale Pour La Jeunesse",
    "wof:placetype":"venue"
},
  "geometry": {"coordinates":[7.3738098145,47.2794876099],"type":"Point"}
}