{
  "type": "Feature",
  "properties": {
    "iso:country":"CH",
    "sg:address":"Place Central 3",
    "sg:city":"Penthalaz",
    "sg:orig_category":"W\u00e4scherei U chemische Reinigung",
    "sg:phone":"+41 21 861 01 42",
    "sg:postcode":"1305",
    "sg:province":"Vaud",
    "wof:name":"Yvette Golay Pressing Central",
    "wof:placetype":"venue"
},
  "geometry": {"coordinates":[6.5245060921,46.6100387573],"type":"Point"}
}