{
  "type": "Feature",
  "properties": {
    "iso:country":"CH",
    "sg:address":"Schlottermilch 4a 6210 Sursee. Postfach 3189",
    "sg:city":"Sursee",
    "sg:orig_category":"Detailhandel mit elektrischen Haushalts-,Radio U Fernsehger\u00e4ten sowie Musikinstrumenten Grosshandel ",
    "sg:phone":"+41 41 921 11 10",
    "sg:postcode":"6210",
    "sg:province":"Luzern",
    "wof:name":"J.b. Musikbedarf Ag",
    "wof:placetype":"venue"
},
  "geometry": {"coordinates":[8.110001564,47.174369812],"type":"Point"}
}