{
  "type": "Feature",
  "properties": {
    "iso:country":"CH",
    "sg:address":"Bimerweg 19 3303 Jegenstorf. Postfach",
    "sg:city":"Jegenstorf",
    "sg:orig_category":"Grosshandel mit sonstigen Nahrungsmitteln",
    "sg:postcode":"3303",
    "sg:province":"Bern",
    "wof:name":"Tiefk\u00fchlservice Hirschi Daniel",
    "wof:placetype":"venue"
},
  "geometry": {"coordinates":[7.504901886,47.0534667969],"type":"Point"}
}