{
  "type": "Feature",
  "properties": {
    "iso:country":"CH",
    "sg:address":"Quai Gustave-ador 1200 Gen\u00e8ve. Postfach",
    "sg:city":"Gen\u00e8ve",
    "sg:orig_category":"Herstellung von Metallkonstruktionen",
    "sg:postcode":"1207",
    "sg:province":"Gen\u00e8ve",
    "wof:name":"Cauderay Yves",
    "wof:placetype":"venue"
},
  "geometry": {"coordinates":[6.1547250748,46.2041091919],"type":"Point"}
}