{
  "type": "Feature",
  "properties": {
    "iso:country":"CH",
    "sg:address":"Seebacherstrasse 12",
    "sg:city":"Z\u00fcrich",
    "sg:orig_category":"Detailhandel mit Ton U Bildtr\u00e4gern Detailhandel mit elektrischen Haushalts-,Radio U Fernsehger\u00e4ten s",
    "sg:phone":"+41 13025355",
    "sg:postcode":"8052",
    "sg:province":"Z\u00fcrich",
    "wof:name":"Musik Reich",
    "wof:placetype":"venue"
},
  "geometry": {"coordinates":[8.5471553802,47.4208908081],"type":"Point"}
}