{
  "type": "Feature",
  "properties": {
    "addr:full":"Rue De La Gare 5 Cully Vaud 1096",
    "addr:housenumber":"5",
    "addr:postcode":"1096",
    "addr:street":"Rue De La Gare",
    "iso:country":"CH",
    "sg:address":"Rue De La Gare 5",
    "sg:city":"Cully",
    "sg:orig_category":"Detailhandel mit Bekleidung MANUFACTURERS: DETAILHANDEL",
    "sg:phone":"+41 21 799 18 43",
    "sg:postcode":"1096",
    "sg:province":"Vaud",
    "wof:name":"Guy Bugnon Tissus Confection",
    "wof:placetype":"venue"
},
  "geometry": {"coordinates":[6.728306,46.488487],"type":"Point"}
}