{
  "type": "Feature",
  "properties": {
    "iso:country":"CH",
    "sg:address":"Landenbergstrasse 35",
    "sg:city":"Luzern",
    "sg:orig_category":"Vermietung U Verpachtung von eigenen Immobilien",
    "sg:postcode":"6005",
    "sg:province":"Luzern",
    "wof:name":"Smartbauag",
    "wof:placetype":"venue"
},
  "geometry": {"coordinates":[8.3165903091,47.0457954407],"type":"Point"}
}