{
  "type": "Feature",
  "properties": {
    "addr:full":"Neudorf 16 Niederhelfenschwil St. Gallen 9527",
    "addr:housenumber":"16;st.",
    "addr:postcode":"9527",
    "addr:street":"Neudorf",
    "iso:country":"CH",
    "sg:address":"Neudorf 16",
    "sg:city":"Niederhelfenschwil",
    "sg:orig_category":"Allgemeiner Hoch U Tiefbau",
    "sg:phone":"+41 71 947 13 04",
    "sg:postcode":"9527",
    "sg:province":"St. Gallen",
    "wof:name":"Zwick Bauunternehmung Ag",
    "wof:placetype":"venue"
},
  "geometry": {"coordinates":[9.18801,47.477936],"type":"Point"}
}