{
  "type": "Feature",
  "properties": {
    "iso:country":"CH",
    "sg:address":"Gipserstrasse 55",
    "sg:city":"Oberehrendingen",
    "sg:orig_category":"Interessenvertretungen",
    "sg:phone":"+41 56 222 19 00",
    "sg:postcode":"5422",
    "wof:name":"Genossenschaft Gypsgrueb Oberehrendingen",
    "wof:placetype":"venue"
},
  "geometry": {"coordinates":[8.3418102264,47.4908294678],"type":"Point"}
}