{
  "type": "Feature",
  "properties": {
    "iso:country":"CH",
    "sg:address":"Ruelle Des Templiers 5",
    "sg:city":"Gen\u00e8ve",
    "sg:orig_category":"Datenverarbeitungsdienste",
    "sg:phone":"+41 22 786 58 48",
    "sg:postcode":"1207",
    "sg:province":"Gen\u00e8ve",
    "wof:name":"Informatique Tech-systems Farokh Afrough",
    "wof:placetype":"venue"
},
  "geometry": {"coordinates":[6.156857,46.200638],"type":"Point"}
}