{
  "type": "Feature",
  "properties": {
    "addr:full":"Route De Villarepos 16 Donatyre Vaud 1582",
    "addr:housenumber":"16",
    "addr:postcode":"1582",
    "addr:street":"Route De Villarepos",
    "iso:country":"CH",
    "sg:address":"Route De Villarepos 16",
    "sg:city":"Donatyre",
    "sg:orig_category":"Architektur U Ingenieurb\u00fcros Architekturb\u00fcros",
    "sg:phone":"+41 26 675 22 83",
    "sg:postcode":"1582",
    "sg:province":"Vaud",
    "wof:name":"Arcad Architectes Sa, Succursale De Donatyre",
    "wof:placetype":"venue"
},
  "geometry": {"coordinates":[7.06078,46.878052],"type":"Point"}
}