{
  "type": "Feature",
  "properties": {
    "iso:country":"CH",
    "sg:address":"Twing",
    "sg:city":"Wasserwendi",
    "sg:orig_category":"Detailhandel mit Sportartikeln Fachdetailhandel in Verkaufsr\u00e4umen",
    "sg:phone":"+41 33 971 12 29",
    "sg:postcode":"6084",
    "sg:province":"Bern",
    "wof:name":"Fahner Sport Gmbh",
    "wof:placetype":"venue"
},
  "geometry": {"coordinates":[8.1957149506,46.7446708679],"type":"Point"}
}