{
  "type": "Feature",
  "properties": {
    "iso:country":"CH",
    "sg:address":"M\u00f6\u00f6slistrasse 3",
    "sg:city":"Z\u00fcrich",
    "sg:orig_category":"Architektur U Ingenieurb\u00fcros Mechanische Werkst\u00e4tten",
    "sg:phone":"+41 32 484 95 68",
    "sg:postcode":"8000",
    "sg:province":"Z\u00fcrich",
    "wof:name":"Vogatec S\u00e0rl",
    "wof:placetype":"venue"
},
  "geometry": {"coordinates":[7.13783,47.27882],"type":"Point"}
}