{
  "type": "Feature",
  "properties": {
    "iso:country":"CH",
    "sg:address":"Clos-de-la-theilaz",
    "sg:city":"Chessel",
    "sg:orig_category":"Gem\u00fcsebau",
    "sg:phone":"+41 24 481 11 84",
    "sg:postcode":"1846",
    "sg:province":"Vaud",
    "wof:name":"Jean-ren\u00e9 Jordan Cultures Maraich\u00e8res",
    "wof:placetype":"venue"
},
  "geometry": {"coordinates":[6.8944749832,46.3490867615],"type":"Point"}
}