{
  "type": "Feature",
  "properties": {
    "iso:country":"CH",
    "sg:address":"Br\u00fc\u00f6l 13",
    "sg:city":"Schwyz",
    "sg:orig_category":"Arztpraxen",
    "sg:phone":"+41 19101020",
    "sg:postcode":"6430",
    "sg:province":"Schwyz",
    "wof:name":"Dr.med.werner Bauer Spezialarzt Fmh",
    "wof:placetype":"venue"
},
  "geometry": {"coordinates":[8.578733,47.321205],"type":"Point"}
}