{
  "type": "Feature",
  "properties": {
    "iso:country":"CH",
    "sg:address":"Mail Avenue Du 1 1205 Gen\u00e8ve. Postfach",
    "sg:city":"Gen\u00e8ve",
    "sg:classifiers":[
        {
            "category":"Bars & Pubs",
            "type":"Food & Drink"
        }
    ],
    "sg:postcode":"1205",
    "sg:province":"Gen\u00e8ve",
    "wof:name":"Alain Bolay",
    "wof:placetype":"venue"
},
  "geometry": {"coordinates":[6.142701,46.208359],"type":"Point"}
}