{
  "type": "Feature",
  "properties": {
    "iso:country":"CH",
    "sg:address":"Weberg\u00e4sschen 8",
    "sg:city":"Riehen",
    "sg:orig_category":"Detailhandel mit Waren verschiedener Art, Hauptrichtung Nahrungsmittel",
    "sg:phone":"+41 61 641 06 11",
    "sg:postcode":"4125",
    "sg:province":"Basel-Stadt",
    "wof:name":"Migros-markt",
    "wof:placetype":"venue"
},
  "geometry": {"coordinates":[7.6516489983,47.585357666],"type":"Point"}
}