{
  "type": "Feature",
  "properties": {
    "iso:country":"CH",
    "sg:address":"Libellenstrasse 46",
    "sg:city":"Luzern",
    "sg:orig_category":"Arztpraxen",
    "sg:phone":"+41 52 763 35 25",
    "sg:postcode":"6004",
    "sg:province":"Luzern",
    "wof:name":"Dres Med. M. & F. Damur Aerzte F\u00fcr Allg.medizin Fmh",
    "wof:placetype":"venue"
},
  "geometry": {"coordinates":[9.008182,47.60445],"type":"Point"}
}