{
  "type": "Feature",
  "properties": {
    "iso:country":"CH",
    "sg:address":"D\u00fcngerstrasse 89b",
    "sg:city":"Pratteln",
    "sg:orig_category":"Architektur U Ingenieurb\u00fcros Bauingenieurb\u00fcros allgemein",
    "sg:phone":"+41 61 823 10 90",
    "sg:postcode":"4133",
    "sg:province":"Basel-Landschaft",
    "wof:name":"Liedek Engineering Gmbh",
    "wof:placetype":"venue"
},
  "geometry": {"coordinates":[7.676506,47.529182],"type":"Point"}
}