{
  "type": "Feature",
  "properties": {
    "iso:country":"CH",
    "sg:address":"Bielstrasse 12",
    "sg:city":"Grenchen",
    "sg:orig_category":"Bibliotheken U Archive Sonstige mit der \u00f6ffentlichen Verwaltung verbundene T\u00e4tigkeiten",
    "sg:phone":"+41 32 652 87 15",
    "sg:postcode":"2540",
    "sg:province":"Solothurn",
    "wof:name":"Amt F\u00fcr Kultur",
    "wof:placetype":"venue"
},
  "geometry": {"coordinates":[7.394887,47.19212],"type":"Point"}
}