{
  "type": "Feature",
  "properties": {
    "iso:country":"CH",
    "sg:address":"Technikumstrasse 79",
    "sg:city":"Winterthur",
    "sg:orig_category":"Wirtschaftspr\u00fcfung, Steuerberatung U Treuhand",
    "sg:phone":"+41 52 654 17 00",
    "sg:postcode":"8400",
    "sg:province":"Z\u00fcrich",
    "wof:name":"Cti Treuhand Gmbh",
    "wof:placetype":"venue"
},
  "geometry": {"coordinates":[8.725435257,47.4981422424],"type":"Point"}
}