{
  "type": "Feature",
  "properties": {
    "iso:country":"CH",
    "sg:address":"Termerweg 21",
    "sg:city":"Brig",
    "sg:orig_category":"G\u00fcterbef\u00f6rderung im Strassenverkehr",
    "sg:phone":"+41 27 923 47 83",
    "sg:postcode":"3900",
    "sg:province":"Valais",
    "wof:name":"Camionnage Brunner Ag",
    "wof:placetype":"venue"
},
  "geometry": {"coordinates":[7.9950499535,46.3163452148],"type":"Point"}
}