{
  "type": "Feature",
  "properties": {
    "iso:country":"CH",
    "sg:address":"Saliciolo Via",
    "sg:city":"Tenero",
    "sg:orig_category":"Grosshandel mit Nahrungsmitteln, Getr\u00e4nken U Tabakwaren ohne ausgepr\u00e4gten Schwerpunkt",
    "sg:postcode":"6598",
    "sg:province":"Ticino",
    "wof:name":"Urban Amedeo",
    "wof:placetype":"venue"
},
  "geometry": {"coordinates":[8.8529891968,46.1775817871],"type":"Point"}
}