{
  "type": "Feature",
  "properties": {
    "iso:country":"CH",
    "sg:address":"Studenrain 6 8122 Binz. Postfach",
    "sg:city":"Binz",
    "sg:orig_category":"Zimmerei, Dachdeckerei, Bauspenglerei U Abdichtung",
    "sg:phone":"+41 21 921 51 93",
    "sg:postcode":"8122",
    "sg:province":"Z\u00fcrich",
    "wof:name":"G\u00fcntensperger J.-p. S\u00e0rl.",
    "wof:placetype":"venue"
},
  "geometry": {"coordinates":[5.1808700562,45.8973388672],"type":"Point"}
}