{
  "type": "Feature",
  "properties": {
    "iso:country":"CH",
    "sg:address":"B\u00fcndtenweg 4 4133 Pratteln. Postfach",
    "sg:city":"Pratteln",
    "sg:orig_category":"Herstellung von Konstruktionsteilen, Fertigbauteilen U Ausbauelementen aus Holz",
    "sg:phone":"+41 61 823 80 48",
    "sg:postcode":"4133",
    "sg:province":"Basel-Landschaft",
    "wof:name":"Pfirter Samuel Bau- U. Kundenschreinerei",
    "wof:placetype":"venue"
},
  "geometry": {"coordinates":[7.700761795,47.5199928284],"type":"Point"}
}