{
  "type": "Feature",
  "properties": {
    "iso:country":"CH",
    "sg:address":"Bahnstrasse 41",
    "sg:city":"Winterthur",
    "sg:orig_category":"Architektur U Ingenieurb\u00fcros",
    "sg:phone":"+41 52 213 28 26",
    "sg:postcode":"8400",
    "sg:province":"Z\u00fcrich",
    "wof:name":"Schnewlin + K\u00fcttel Ag",
    "wof:placetype":"venue"
},
  "geometry": {"coordinates":[8.735062,47.503502],"type":"Point"}
}