{
  "type": "Feature",
  "properties": {
    "iso:country":"CH",
    "sg:address":"H\u00f6henackerweg 16n",
    "sg:city":"Roggenburg",
    "sg:orig_category":"Chemin\u00e9e- and Ofenbau Hafner",
    "sg:phone":"+41 61 731 21 11",
    "sg:postcode":"2814",
    "sg:province":"Basel-Landschaft",
    "wof:name":"Kachelofenbau Pargmann Ag",
    "wof:placetype":"venue"
},
  "geometry": {"coordinates":[7.438508,47.457363],"type":"Point"}
}