{
  "type": "Feature",
  "properties": {
    "iso:country":"CH",
    "sg:address":"Sonnenweg 17",
    "sg:city":"Liestal",
    "sg:orig_category":"Markt U Meinungsforschung Unternehmensberatung",
    "sg:phone":"+41 61 923 06 50",
    "sg:postcode":"4410",
    "sg:province":"Basel-Landschaft",
    "wof:name":"Fse Gmbh F\u00fcr Vereins Und Firmenmarketing",
    "wof:placetype":"venue"
},
  "geometry": {"coordinates":[7.7321882248,47.4814147949],"type":"Point"}
}