{
  "type": "Feature",
  "properties": {
    "iso:country":"CH",
    "sg:address":"Dorfstrasse 6",
    "sg:city":"Brittnau",
    "sg:classifiers":[
        {
            "category":"Travel",
            "subcategory":"Hotels & Motels",
            "type":"Entertainment"
        }
    ],
    "sg:phone":"+41 62 752 11 12",
    "sg:postcode":"4805",
    "sg:province":"Aargau",
    "sg:tags":[
        "hotels",
        "mit",
        "restaurant"
    ],
    "wof:name":"Hans Haas",
    "wof:placetype":"venue"
},
  "geometry": {"coordinates":[7.9475970268,47.2584877014],"type":"Point"}
}