{
  "type": "Feature",
  "properties": {
    "iso:country":"CH",
    "sg:address":"Ressiga Via 12/b",
    "sg:city":"Giubiasco",
    "sg:orig_category":"Vermietung U Verpachtung von eigenen Immobilien",
    "sg:postcode":"6512",
    "sg:province":"Ticino",
    "wof:name":"Alpropria F Immobilien Ag",
    "wof:placetype":"venue"
},
  "geometry": {"coordinates":[8.579366684,47.3207511902],"type":"Point"}
}