{
  "type": "Feature",
  "properties": {
    "iso:country":"CH",
    "sg:address":"Rue Louis-favre 6",
    "sg:city":"Neuenburg",
    "sg:orig_category":"Verwaltung von Immobilien Wirtschaftspr\u00fcfung, Steuerberatung U Treuhand",
    "sg:phone":"+41 32 725 41 32",
    "sg:postcode":"2000",
    "sg:province":"Neuch\u00e2tel",
    "wof:name":"Christen Albert, Bureau Fiduciaire",
    "wof:placetype":"venue"
},
  "geometry": {"coordinates":[6.9322237968,46.9953079224],"type":"Point"}
}