{
  "type": "Feature",
  "properties": {
    "addr:full":"Via Gaggiolo 55 Stabio Ticino 6855",
    "addr:housenumber":"55",
    "addr:postcode":"6855",
    "addr:street":"Via Gaggiolo",
    "iso:country":"CH",
    "sg:address":"Via Gaggiolo 55",
    "sg:city":"Stabio",
    "sg:classifiers":[
        {
            "category":"Bars & Pubs",
            "type":"Food & Drink"
        }
    ],
    "sg:phone":"+41 91 647 23 15",
    "sg:postcode":"6855",
    "sg:province":"Ticino",
    "wof:name":"Bar Gino",
    "wof:placetype":"venue"
},
  "geometry": {"coordinates":[8.918883,45.842617],"type":"Point"}
}