{
  "type": "Feature",
  "properties": {
    "addr:full":"Burgernzielrain 5 Bern Bern 3006",
    "addr:housenumber":"5",
    "addr:postcode":"3006",
    "addr:street":"Burgernzielrain",
    "iso:country":"CH",
    "sg:address":"Burgernzielrain 5",
    "sg:city":"Bern",
    "sg:orig_category":"Aktivit\u00e4ten der Generalunternehmen im Baugewerbe Vermittlung von Immobilien",
    "sg:phone":"+41 31 351 10 50",
    "sg:postcode":"3006",
    "sg:province":"Bern",
    "wof:name":"Ringgenberg Paul Immobilien Ag Liegenschaftenhandel, Generalunternehmung Usw.",
    "wof:placetype":"venue"
},
  "geometry": {"coordinates":[7.469605,46.941788],"type":"Point"}
}