{
  "type": "Feature",
  "properties": {
    "iso:country":"CH",
    "sg:address":"1568",
    "sg:city":"Portalban",
    "sg:orig_category":"Schulpflegen",
    "sg:postcode":"1568",
    "sg:province":"Fribourg",
    "wof:name":"Commission Scolaire De L'ecole Primaire",
    "wof:placetype":"venue"
},
  "geometry": {"coordinates":[6.9551901817,46.9181594849],"type":"Point"}
}