{
  "type": "Feature",
  "properties": {
    "iso:country":"CH",
    "sg:address":"Oedlehn 427",
    "sg:city":"Wolfhalden",
    "sg:orig_category":"G\u00fcterbef\u00f6rderung im Strassenverkehr",
    "sg:phone":"+41 71 891 20 26",
    "sg:postcode":"9427",
    "sg:province":"Appenzell Ausserrhoden",
    "wof:name":"Ernst Aemisegger, Transporte",
    "wof:placetype":"venue"
},
  "geometry": {"coordinates":[9.5521306992,47.4461402893],"type":"Point"}
}