{
  "type": "Feature",
  "properties": {
    "iso:country":"CH",
    "sg:address":"1913",
    "sg:city":"Saillon",
    "sg:orig_category":"Autospenglereien",
    "sg:phone":"+41 62 212 59 59",
    "sg:postcode":"1913",
    "sg:province":"Valais",
    "wof:name":"Geiger Carrosserie Ag",
    "wof:placetype":"venue"
},
  "geometry": {"coordinates":[7.874644,47.344219],"type":"Point"}
}