{
  "type": "Feature",
  "properties": {
    "iso:country":"CH",
    "sg:address":"H\u00f6nggerstrasse 14a",
    "sg:city":"Oberengstringen",
    "sg:orig_category":"Vorschulen, Kinderg\u00e4rten",
    "sg:phone":"+41 17502802",
    "sg:postcode":"8102",
    "sg:province":"Z\u00fcrich",
    "wof:name":"Kindergarten Haggenacker",
    "wof:placetype":"venue"
},
  "geometry": {"coordinates":[8.4568109512,47.4102592468],"type":"Point"}
}