{
  "type": "Feature",
  "properties": {
    "iso:country":"CH",
    "sg:address":"Gufenhaldenweg 5",
    "sg:city":"M\u00e4nnedorf",
    "sg:orig_category":"Zimmerei, Dachdeckerei, Bauspenglerei U Abdichtung",
    "sg:phone":"+41 19202431",
    "sg:postcode":"8708",
    "sg:province":"Z\u00fcrich",
    "wof:name":"Buess Mario Gmbh Steil Und Flachbedachungen",
    "wof:placetype":"venue"
},
  "geometry": {"coordinates":[8.689956665,47.2586631775],"type":"Point"}
}