{
  "type": "Feature",
  "properties": {
    "iso:country":"CH",
    "sg:address":"Grand-vennes Chemin De 7 1010 Lausanne. Postfach",
    "sg:city":"Lausanne",
    "sg:orig_category":"Unclassifiable Establishments",
    "sg:postcode":"1010",
    "sg:province":"Vaud",
    "wof:name":"Guilde Des Propri\u00e9taires Fonciers Sa. Organisat. En Suisse De Services \u00e0 L'intention Des Propri\u00e9taires Fonciers Et Op\u00e9rations Immob.",
    "wof:placetype":"venue"
},
  "geometry": {"coordinates":[6.6535072327,46.5426063538],"type":"Point"}
}