{
  "type": "Feature",
  "properties": {
    "iso:country":"CH",
    "sg:address":"W\u00fchrestrasse 1",
    "sg:city":"Appenzell",
    "sg:orig_category":"Unclassifiable Establishments",
    "sg:phone":"+41 71 787 90 90",
    "sg:postcode":"9050",
    "sg:province":"Appenzell Innerhoden",
    "wof:name":"Blumen Gassner, Gartenbau",
    "wof:placetype":"venue"
},
  "geometry": {"coordinates":[9.4080562592,47.3293418884],"type":"Point"}
}