{
  "type": "Feature",
  "properties": {
    "iso:country":"CH",
    "sg:address":"4005 Basel. Postfach",
    "sg:city":"Basel",
    "sg:classifiers":[
        {
            "category":"Education",
            "subcategory":"Library",
            "type":"Public Place"
        }
    ],
    "sg:phone":"+41 61 685 65 65",
    "sg:postcode":"4005",
    "sg:province":"Basel-Stadt",
    "sg:tags":[
        "u",
        "bibliotheken",
        "archive"
    ],
    "wof:name":"Universit\u00e4ts-kinderspital Beider Basel",
    "wof:placetype":"venue"
},
  "geometry": {"coordinates":[7.58053,47.559662],"type":"Point"}
}