{
  "type": "Feature",
  "properties": {
    "iso:country":"CH",
    "sg:address":"Hochfeldstrasse 33",
    "sg:city":"Bern",
    "sg:orig_category":"Non-Classified Establishments",
    "sg:postcode":"3012",
    "sg:province":"Bern",
    "wof:name":"Andrea Bhend Naturheilpraxis",
    "wof:placetype":"venue"
},
  "geometry": {"coordinates":[7.4293899536,46.9566040039],"type":"Point"}
}