{
  "type": "Feature",
  "properties": {
    "iso:country":"CH",
    "sg:address":"Isenrietstrasse 1",
    "sg:city":"M\u00f6nchaltorf",
    "sg:orig_category":"Herstellung von Kunststoff in Prim\u00e4rformen Herstellung von Werkzeugen",
    "sg:phone":"+41 55 246 51 00",
    "sg:postcode":"8617",
    "sg:province":"Z\u00fcrich",
    "wof:name":"Sks Ag Kunststoffe Und Werkzeugbau",
    "wof:placetype":"venue"
},
  "geometry": {"coordinates":[8.9309206009,47.2640647888],"type":"Point"}
}