{
  "type": "Feature",
  "properties": {
    "iso:country":"CH",
    "sg:address":"Riburgerstrasse 27",
    "sg:city":"M\u00f6hlin",
    "sg:orig_category":"RESTAURANTS: TEA-ROOMS",
    "sg:phone":"+41 61 851 10 05",
    "sg:postcode":"4313",
    "sg:province":"Aargau",
    "wof:name":"Restaurant Ryburg, Mitterer Robert",
    "wof:placetype":"venue"
},
  "geometry": {"coordinates":[7.8401517868,47.5661697388],"type":"Point"}
}