{
  "type": "Feature",
  "properties": {
    "iso:country":"CH",
    "sg:address":"Via Moree 6",
    "sg:city":"Mendrisio",
    "sg:orig_category":"Instandhaltung U Reparatur von Automobilen",
    "sg:phone":"+41 32 967 90 90",
    "sg:postcode":"6850",
    "sg:province":"Ticino",
    "wof:name":"Bonny Maurice Sa",
    "wof:placetype":"venue"
},
  "geometry": {"coordinates":[6.8342828751,47.1060752869],"type":"Point"}
}