{
  "type": "Feature",
  "properties": {
    "iso:country":"CH",
    "sg:address":"Rigistrasse 57",
    "sg:city":"Luzern",
    "sg:orig_category":"Gesundheitswesen",
    "sg:postcode":"6006",
    "sg:province":"Luzern",
    "wof:name":"Schweiz. Gesellschaft F\u00fcr Kranken Und W\u00f6chnerinnenpflege",
    "wof:placetype":"venue"
},
  "geometry": {"coordinates":[8.3244600296,47.05809021],"type":"Point"}
}