{
  "type": "Feature",
  "properties": {
    "iso:country":"CH",
    "sg:address":"Unter-grundhof 24",
    "sg:city":"Emmen",
    "sg:orig_category":"Gartenbau",
    "sg:phone":"+41 41 260 26 09",
    "sg:postcode":"6032",
    "sg:province":"Luzern",
    "wof:name":"Peter Inderbitzin Gartengestaltung",
    "wof:placetype":"venue"
},
  "geometry": {"coordinates":[8.3088598251,47.0811004639],"type":"Point"}
}