{
  "type": "Feature",
  "properties": {
    "iso:country":"CH",
    "sg:address":"Quai De La Thi\u00e8le 32 1400 Cheseaux-nor\u00e9az. Postfach",
    "sg:city":"Cheseaux-nor\u00e9az",
    "sg:orig_category":"Non-Classified Establishments",
    "sg:postcode":"1400",
    "sg:province":"Vaud",
    "wof:name":"Travys - Transports Vall\u00e9e-de-joux - Yverdon-les-bains - Sainte-croix Sa",
    "wof:placetype":"venue"
},
  "geometry": {"coordinates":[6.6414198875,46.7786331177],"type":"Point"}
}