{
  "type": "Feature",
  "properties": {
    "iso:country":"CH",
    "sg:address":"8767",
    "sg:city":"Elm",
    "sg:orig_category":"Detailhandel mit Waren verschiedener Art, Hauptrichtung Nahrungsmittel Verarbeitung von Milch",
    "sg:phone":"+41 55 642 13 03",
    "sg:postcode":"8767",
    "sg:province":"Glarus",
    "wof:name":"Landw. Genossenschaft Milchzentrale Lebensmittel",
    "wof:placetype":"venue"
},
  "geometry": {"coordinates":[9.1728467941,46.9213943481],"type":"Point"}
}