{
  "type": "Feature",
  "properties": {
    "iso:country":"CH",
    "sg:address":"Hochstrasse 51 8044 Z\u00fcrich. Postfach",
    "sg:city":"Z\u00fcrich",
    "sg:orig_category":"Sonstige mit der Informatik verbundene T\u00e4tigkeiten",
    "sg:phone":"+41 12532043",
    "sg:postcode":"8044",
    "sg:province":"Z\u00fcrich",
    "wof:name":"Landolt Dominique Virtoffice Office-support, Organisation, Marketing, Webpublishing",
    "wof:placetype":"venue"
},
  "geometry": {"coordinates":[8.5546922684,47.3789367676],"type":"Point"}
}