{
  "type": "Feature",
  "properties": {
    "iso:country":"CH",
    "sg:address":"Bonzaglio Via 6997 Sessa. Postfach",
    "sg:city":"Sessa",
    "sg:orig_category":"Elektroinstallation",
    "sg:phone":"+41 91 608 20 33",
    "sg:postcode":"6997",
    "sg:province":"Ticino",
    "wof:name":"Elettromeccanica Di Zimmermann David, Montaggi E Riparazioni",
    "wof:placetype":"venue"
},
  "geometry": {"coordinates":[8.8085346222,46.0039596558],"type":"Point"}
}