{
  "type": "Feature",
  "properties": {
    "addr:full":"Hauptstrasse 81 Murgenthal Aargau 4853",
    "addr:housenumber":"81",
    "addr:postcode":"4853",
    "addr:street":"Hauptstrasse",
    "iso:country":"CH",
    "sg:address":"Hauptstrasse 81",
    "sg:city":"Murgenthal",
    "sg:orig_category":"Detailhandel mit Damenbekleidung Detailhandel mit Herrenbekleidung",
    "sg:phone":"+41 62 917 40 88",
    "sg:postcode":"4853",
    "sg:province":"Aargau",
    "wof:name":"Blackout Mode",
    "wof:placetype":"venue"
},
  "geometry": {"coordinates":[7.840693,47.271694],"type":"Point"}
}