{
  "type": "Feature",
  "properties": {
    "iso:country":"CH",
    "sg:address":"S\u00e4gegasse 27",
    "sg:city":"M\u00fcnsingen",
    "sg:orig_category":"Sportvereine Hornussen",
    "sg:phone":"+41 31 721 11 38",
    "sg:postcode":"3110",
    "sg:province":"Bern",
    "wof:name":"Hornusserges.wichtrach",
    "wof:placetype":"venue"
},
  "geometry": {"coordinates":[7.5546708107,46.8736038208],"type":"Point"}
}