{
  "type": "Feature",
  "properties": {
    "addr:full":"Hauptstrasse 54 Fanas Graubunden 7215",
    "addr:housenumber":"54;7215",
    "addr:street":"Hauptstrasse",
    "iso:country":"CH",
    "sg:address":"Hauptstrasse 54",
    "sg:city":"Fanas",
    "sg:orig_category":"Bauschreinerei",
    "sg:phone":"+41 81 325 10 57",
    "sg:postcode":"7215",
    "sg:province":"Graubunden",
    "wof:name":"Heinrich Davatz Schreinerei",
    "wof:placetype":"venue"
},
  "geometry": {"coordinates":[9.665533,46.985378],"type":"Point"}
}