{
  "type": "Feature",
  "properties": {
    "iso:country":"CH",
    "sg:address":"Matte",
    "sg:city":"Stechelberg",
    "sg:orig_category":"Grosshandel mit Holz U Baustoffen Vermietung von Baumaschinen U ger\u00e4ten",
    "sg:phone":"+41 21 691 16 58",
    "sg:postcode":"3824",
    "sg:province":"Bern",
    "wof:name":"Boissenot Philippe",
    "wof:placetype":"venue"
},
  "geometry": {"coordinates":[6.5609917641,46.5309181213],"type":"Point"}
}