{
  "type": "Feature",
  "properties": {
    "addr:full":"Chemin Du Carreau Fully Valais 1926",
    "addr:postcode":"1926",
    "addr:street":"Chemin Du Carreau",
    "iso:country":"CH",
    "sg:address":"Chemin Du Carreau",
    "sg:city":"Fully",
    "sg:orig_category":"Autogaragen",
    "sg:phone":"+41 79 449 17 32",
    "sg:postcode":"1926",
    "sg:province":"Valais",
    "wof:name":"Jean-bernard Peronetti Garage",
    "wof:placetype":"venue"
},
  "geometry": {"coordinates":[7.46364,46.258438],"type":"Point"}
}