{
  "type": "Feature",
  "properties": {
    "iso:country":"CH",
    "sg:address":"R\u00fcbeldorf",
    "sg:city":"Saanen",
    "sg:orig_category":"Verlegen von Fliesen U Platten",
    "sg:phone":"+41 33 744 42 91",
    "sg:postcode":"3792",
    "sg:province":"Bern",
    "wof:name":"Remo Casagranda Platten-& Chemin\u00e9ebau",
    "wof:placetype":"venue"
},
  "geometry": {"coordinates":[7.2713661194,46.4807510376],"type":"Point"}
}