{
  "type": "Feature",
  "properties": {
    "iso:country":"CH",
    "sg:address":"Passage De L'auberge 8",
    "sg:city":"Territet-veytaux",
    "sg:orig_category":"Jugendherbergen U H\u00fctten",
    "sg:phone":"+41 21 963 49 34",
    "sg:postcode":"1820",
    "sg:province":"Vaud",
    "wof:name":"Auberge De La Jeunesse Haut-lac",
    "wof:placetype":"venue"
},
  "geometry": {"coordinates":[6.9248828888,46.4240913391],"type":"Point"}
}