{
  "type": "Feature",
  "properties": {
    "iso:country":"CH",
    "sg:address":"Bremgartnerstrasse 32 8003 Z\u00fcrich. Postfach",
    "sg:city":"Z\u00fcrich",
    "sg:orig_category":"RESTAURANTS: TEA-ROOMS",
    "sg:postcode":"8003",
    "sg:province":"Z\u00fcrich",
    "wof:name":"La Notte Gmbh",
    "wof:placetype":"venue"
},
  "geometry": {"coordinates":[8.5188026428,47.3714523315],"type":"Point"}
}