{
  "type": "Feature",
  "properties": {
    "iso:country":"CH",
    "sg:address":"Maienbrunnenstrasse 9",
    "sg:city":"Hedingen",
    "sg:orig_category":"Instandhaltung U Reparatur von Automobilen",
    "sg:phone":"+41 17613233",
    "sg:postcode":"8908",
    "sg:province":"Z\u00fcrich",
    "wof:name":"Autohilfe Hedingen K.hofmann & P.attenhofer",
    "wof:placetype":"venue"
},
  "geometry": {"coordinates":[8.4415235519,47.3005867004],"type":"Point"}
}