{
  "type": "Feature",
  "properties": {
    "iso:country":"CH",
    "sg:address":"Wis",
    "sg:city":"Quarten",
    "sg:orig_category":"Elektroinstallation",
    "sg:postcode":"8883",
    "sg:province":"St. Gallen",
    "wof:name":"Walser & Co. Elektromontagen",
    "wof:placetype":"venue"
},
  "geometry": {"coordinates":[9.2411050797,47.108253479],"type":"Point"}
}