{
  "type": "Feature",
  "properties": {
    "addr:full":"Lindenhof Engelburg St. Gallen 9032",
    "addr:postcode":"9032",
    "addr:street":"Engelburg",
    "iso:country":"CH",
    "sg:address":"Lindenhof",
    "sg:city":"Engelburg",
    "sg:orig_category":"Allgemeiner Hoch U Tiefbau Hoch U Tiefbau",
    "sg:postcode":"9032",
    "sg:province":"St. Gallen",
    "wof:name":"Alexander Rutz",
    "wof:placetype":"venue"
},
  "geometry": {"coordinates":[9.346641,47.437164],"type":"Point"}
}