{
  "type": "Feature",
  "properties": {
    "iso:country":"CH",
    "sg:address":"Florastrasse 13 3005 Bern. Postfach 148",
    "sg:city":"Bern",
    "sg:orig_category":"Non-Classified Establishments",
    "sg:phone":"+41 31 352 72 44",
    "sg:postcode":"3005",
    "sg:province":"Bern",
    "wof:name":"Baumeisterverband Bern",
    "wof:placetype":"venue"
},
  "geometry": {"coordinates":[7.4546689987,46.9430198669],"type":"Point"}
}