{
  "type": "Feature",
  "properties": {
    "iso:country":"CH",
    "sg:address":"Eichenweg 49 3052 Zollikofen. Postfach",
    "sg:city":"Zollikofen",
    "sg:orig_category":"Grosshandel mit Milch, Milcherzeugnissen, Eiern, Speise\u00f6len U Nahrungsfetten Sonstiger Fachdetailhan",
    "sg:phone":"+41 26 674 22 22",
    "sg:postcode":"3052",
    "sg:province":"Bern",
    "wof:name":"Bongrain Ag",
    "wof:placetype":"venue"
},
  "geometry": {"coordinates":[7.140021801,46.8987121582],"type":"Point"}
}