{
  "type": "Feature",
  "properties": {
    "iso:country":"CH",
    "sg:address":"Hotel Praval",
    "sg:city":"Arosa",
    "sg:classifiers":[
        {
            "category":"Travel",
            "subcategory":"Hotels & Motels",
            "type":"Entertainment"
        }
    ],
    "sg:phone":"+41 62 390 15 15",
    "sg:postcode":"7050",
    "sg:province":"Graubunden",
    "sg:tags":[
        "hotels",
        "mit",
        "restaurant"
    ],
    "wof:name":"Steiner Otto",
    "wof:placetype":"venue"
},
  "geometry": {"coordinates":[7.7498688698,47.3323554993],"type":"Point"}
}