{
  "type": "Feature",
  "properties": {
    "iso:country":"CH",
    "sg:address":"Rue Des Murs 8",
    "sg:city":"Coppet",
    "sg:orig_category":"Architekturb\u00fcros",
    "sg:phone":"+41 22 960 05 05",
    "sg:postcode":"1296",
    "sg:province":"Vaud",
    "wof:name":"Widmer & Lacourt Atelier D'architecture",
    "wof:placetype":"venue"
},
  "geometry": {"coordinates":[6.192025,46.316284],"type":"Point"}
}