{
  "type": "Feature",
  "properties": {
    "iso:country":"CH",
    "sg:address":"Hosenruck 9514 Wuppenau. Postfach",
    "sg:city":"Hosenruck",
    "sg:orig_category":"Interessenvertretungen",
    "sg:postcode":"9515",
    "sg:province":"Thurgau",
    "wof:name":"Elektra Hosenruck",
    "wof:placetype":"venue"
},
  "geometry": {"coordinates":[9.1058082581,47.4948806763],"type":"Point"}
}