{
  "type": "Feature",
  "properties": {
    "addr:full":"Simmentalstrasse 33 Spiez Bern 3700",
    "addr:housenumber":"33",
    "addr:postcode":"3700",
    "addr:street":"Simmentalstrasse",
    "iso:country":"CH",
    "sg:address":"Simmentalstrasse 33",
    "sg:city":"Spiez",
    "sg:classifiers":[
        {
            "category":"Retail",
            "subcategory":"Repair Shop",
            "type":"Services"
        }
    ],
    "sg:phone":"+41 33 654 44 46",
    "sg:postcode":"3700",
    "sg:province":"Bern",
    "sg:tags":[
        "agricultural",
        "machinery"
    ],
    "wof:name":"Simon Minnig Landmaschinen",
    "wof:placetype":"venue"
},
  "geometry": {"coordinates":[7.660076,46.684875],"type":"Point"}
}