{
  "type": "Feature",
  "properties": {
    "iso:country":"CH",
    "sg:address":"Marktgasse 33 3800 Interlaken. Postfach 196",
    "sg:city":"Interlaken",
    "sg:orig_category":"Polizei",
    "sg:phone":"+41 33 823 29 90",
    "sg:postcode":"3800",
    "sg:province":"Bern",
    "wof:name":"Kantonale Polizei",
    "wof:placetype":"venue"
},
  "geometry": {"coordinates":[7.8531990051,46.6857414246],"type":"Point"}
}