{
  "type": "Feature",
  "properties": {
    "iso:country":"CH",
    "sg:address":"Neuhausstrasse 32",
    "sg:city":"D\u00fcbendorf",
    "sg:orig_category":"Zimmerei, Dachdeckerei, Bauspenglerei U Abdichtung",
    "sg:phone":"+41 18219136",
    "sg:postcode":"8600",
    "sg:province":"Z\u00fcrich",
    "wof:name":"B\u00fctler Remo Holzbau Ag",
    "wof:placetype":"venue"
},
  "geometry": {"coordinates":[8.6193342209,47.3950653076],"type":"Point"}
}