{
  "type": "Feature",
  "properties": {
    "addr:full":"Gemeindehaus St. Niklaus Valais 3924",
    "addr:postcode":"3924",
    "iso:country":"CH",
    "sg:address":"Gemeindehaus",
    "sg:city":"St. Niklaus",
    "sg:classifiers":[
        {
            "category":"Banks & Credit Unions",
            "subcategory":"Bank",
            "type":"Services"
        }
    ],
    "sg:phone":"+41 27 956 22 23",
    "sg:postcode":"3924",
    "sg:province":"Valais",
    "wof:name":"Raiffeisenbank",
    "wof:placetype":"venue"
},
  "geometry": {"coordinates":[7.802101,46.175663],"type":"Point"}
}