{
  "type": "Feature",
  "properties": {
    "iso:country":"CH",
    "sg:address":"8166",
    "sg:city":"Niederweningen",
    "sg:orig_category":"Landw. Genossenschaften Viehzucht",
    "sg:postcode":"8166",
    "sg:province":"Z\u00fcrich",
    "wof:name":"Fleckviehzuchtgenossenschaft Wehntal",
    "wof:placetype":"venue"
},
  "geometry": {"coordinates":[8.3766899109,47.5043640137],"type":"Point"}
}