{
  "type": "Feature",
  "properties": {
    "iso:country":"CH",
    "sg:address":"1423",
    "sg:city":"Villars-burquin",
    "sg:orig_category":"Forst\u00e4mter",
    "sg:phone":"+41 24 436 30 02",
    "sg:postcode":"1423",
    "sg:province":"Vaud",
    "wof:name":"Inspections Des For\u00eats 7\u00e8me Arrdt",
    "wof:placetype":"venue"
},
  "geometry": {"coordinates":[6.6263198853,46.8477592468],"type":"Point"}
}