{
  "type": "Feature",
  "properties": {
    "iso:country":"CH",
    "sg:address":"Bergstrasse 22",
    "sg:city":"Z\u00fcrich",
    "sg:orig_category":"Unternehmensberatung",
    "sg:phone":"+41 12521633",
    "sg:postcode":"8044",
    "sg:province":"Z\u00fcrich",
    "wof:name":"Gutjahr + Partner.",
    "wof:placetype":"venue"
},
  "geometry": {"coordinates":[8.5606641769,47.374584198],"type":"Point"}
}