{
  "type": "Feature",
  "properties": {
    "iso:country":"CH",
    "sg:address":"Alfred-schindlerstrasse 24",
    "sg:city":"Ebikon",
    "sg:orig_category":"Handel mit Automobilen",
    "sg:postcode":"6030",
    "sg:province":"Luzern",
    "wof:name":"Autohandel Sehanovic",
    "wof:placetype":"venue"
},
  "geometry": {"coordinates":[8.3528604507,47.0871696472],"type":"Point"}
}