{
  "type": "Feature",
  "properties": {
    "iso:country":"CH",
    "sg:address":"Uitikonerstrasse 4",
    "sg:city":"Schlieren",
    "sg:orig_category":"Arztpraxen",
    "sg:phone":"+41 81 833 17 77",
    "sg:postcode":"8952",
    "sg:province":"Z\u00fcrich",
    "wof:name":"Dr.med.peter O. Steiner Spezialarzt Fmh",
    "wof:placetype":"venue"
},
  "geometry": {"coordinates":[9.84016,46.498749],"type":"Point"}
}