{
  "type": "Feature",
  "properties": {
    "iso:country":"CH",
    "sg:address":"Kanalstrasse 9",
    "sg:city":"Mollis",
    "sg:orig_category":"Grosshandel mit Textilien",
    "sg:postcode":"8753",
    "sg:province":"Glarus",
    "wof:name":"Zingg Heinrich Ag",
    "wof:placetype":"venue"
},
  "geometry": {"coordinates":[9.0716981888,47.0953102112],"type":"Point"}
}