{
  "type": "Feature",
  "properties": {
    "iso:country":"CH",
    "sg:address":"Huobweg 2a",
    "sg:city":"Cham",
    "sg:orig_category":"Sportvereine Ballsport Tischtennis",
    "sg:phone":"+41 41 780 59 13",
    "sg:postcode":"6330",
    "sg:province":"Zug",
    "wof:name":"Ttc Steinhausen",
    "wof:placetype":"venue"
},
  "geometry": {"coordinates":[8.4477748871,47.1768684387],"type":"Point"}
}