{
  "type": "Feature",
  "properties": {
    "iso:country":"CH",
    "sg:address":"Schmiedengasse 13 3400 Burgdorf. Postfach",
    "sg:city":"Burgdorf",
    "sg:orig_category":"Sonstige Kultur U Unterhaltungseinrichtungen",
    "sg:phone":"+41 34 422 81 99",
    "sg:postcode":"3402",
    "sg:province":"Bern",
    "wof:name":"Centro Espanol De Burgdorf",
    "wof:placetype":"venue"
},
  "geometry": {"coordinates":[7.6260781288,47.0555496216],"type":"Point"}
}