{
  "type": "Feature",
  "properties": {
    "addr:full":"Lukmaniergasse 6 7000 Chur. Postfach Chur Graubunden 7000",
    "addr:housenumber":"6",
    "addr:postcode":"7000;postfach;7000",
    "addr:street":"Lukmaniergasse",
    "iso:country":"CH",
    "sg:address":"Lukmaniergasse 6 7000 Chur. Postfach",
    "sg:city":"Chur",
    "sg:orig_category":"Detailhandel mit B\u00fcchern Detailhandel mit B\u00fcchern, Zeitungen, Schreib U Papeteriewaren",
    "sg:phone":"+41 81 252 14 73",
    "sg:postcode":"7000",
    "sg:province":"Graubunden",
    "wof:name":"Buchhandlung Provini Berther & Co",
    "wof:placetype":"venue"
},
  "geometry": {"coordinates":[9.532381,46.850616],"type":"Point"}
}