{
  "type": "Feature",
  "properties": {
    "iso:country":"CH",
    "sg:address":"Z\u00fcrcherstrasse 184",
    "sg:city":"Winterthur",
    "sg:orig_category":"Detailhandel mit Beleuchtungs U Haushaltsgegenst\u00e4nden Detailhandel mit Radio U Fernsehger\u00e4ten",
    "sg:phone":"+41 800 559 111",
    "sg:postcode":"8406",
    "sg:province":"Z\u00fcrich",
    "wof:name":"Fust Ag Elektro Tv Video Foto",
    "wof:placetype":"venue"
},
  "geometry": {"coordinates":[8.449186,47.277096],"type":"Point"}
}