{
  "type": "Feature",
  "properties": {
    "iso:country":"CH",
    "sg:address":"Holbeinstrasse 81",
    "sg:city":"Basel",
    "sg:orig_category":"Zahnarztpraxen",
    "sg:phone":"+41 61 281 60 05",
    "sg:postcode":"4051",
    "sg:province":"Basel-Stadt",
    "wof:name":"Dr.med.dent.rudolf K. M\u00fcller Zahnarzt",
    "wof:placetype":"venue"
},
  "geometry": {"coordinates":[7.5827360153,47.5509529114],"type":"Point"}
}