{
  "type": "Feature",
  "properties": {
    "iso:country":"CH",
    "sg:address":"2875",
    "sg:city":"Montfaucon",
    "sg:orig_category":"Schulpflegen",
    "sg:postcode":"2875",
    "sg:province":"Jura",
    "wof:name":"Commission Scolaire De L'ecole Primaire",
    "wof:placetype":"venue"
},
  "geometry": {"coordinates":[7.0132098198,47.2637939453],"type":"Point"}
}