{
  "type": "Feature",
  "properties": {
    "iso:country":"CH",
    "sg:address":"Blumenweg 20",
    "sg:city":"Bolken",
    "sg:orig_category":"Sportvereine Ballsport Tischtennis",
    "sg:postcode":"4556",
    "sg:province":"Solothurn",
    "wof:name":"Ttc Solothurn",
    "wof:placetype":"venue"
},
  "geometry": {"coordinates":[7.6660399437,47.193321228],"type":"Point"}
}