{
  "type": "Feature",
  "properties": {
    "iso:country":"CH",
    "sg:address":"Valentin Rue Du 56 1400 Cheseaux-nor\u00e9az Case Postale 657",
    "sg:city":"Cheseaux-nor\u00e9az",
    "sg:orig_category":"Herstellung von \u00d6fen U Brennern",
    "sg:phone":"+41 24 426 27 11",
    "sg:postcode":"1400",
    "sg:province":"Vaud",
    "wof:name":"Gendroz, Colantonio & Cie",
    "wof:placetype":"venue"
},
  "geometry": {"coordinates":[6.6414198875,46.7786331177],"type":"Point"}
}