{
  "type": "Feature",
  "properties": {
    "iso:country":"CH",
    "sg:address":"Josefstrasse 59 8005 Z\u00fcrich. Postfach 1428",
    "sg:city":"Z\u00fcrich",
    "sg:orig_category":"Wirtschaftspr\u00fcfung, Steuerberatung U Treuhand",
    "sg:phone":"+41 14555000",
    "sg:postcode":"8031",
    "sg:province":"Z\u00fcrich",
    "wof:name":"Fondvest Ag",
    "wof:placetype":"venue"
},
  "geometry": {"coordinates":[8.5318098068,47.3821487427],"type":"Point"}
}