{
  "type": "Feature",
  "properties": {
    "iso:country":"CH",
    "sg:address":"Kleinholz 2a",
    "sg:city":"Graben",
    "sg:orig_category":"Sportvereine Renn-& Reitsport",
    "sg:phone":"+41 62 956 51 71",
    "sg:postcode":"3376",
    "sg:province":"Bern",
    "wof:name":"Reitverein Herzogenbuchsee",
    "wof:placetype":"venue"
},
  "geometry": {"coordinates":[7.7105507851,47.2136459351],"type":"Point"}
}