{
  "type": "Feature",
  "properties": {
    "iso:country":"CH",
    "sg:address":"Eterpaz 26 1337 Vallorbe Case Postale",
    "sg:city":"Vallorbe",
    "sg:orig_category":"Sanit\u00e4r, Heizungs U L\u00fcftungsinstallation",
    "sg:phone":"+41 91 859 32 16",
    "sg:postcode":"1337",
    "sg:province":"Vaud",
    "wof:name":"Safi Spazzacamino Sagl",
    "wof:placetype":"venue"
},
  "geometry": {"coordinates":[8.8010902405,46.3217811584],"type":"Point"}
}