{
  "type": "Feature",
  "properties": {
    "iso:country":"CH",
    "sg:address":"Sarganserstrasse 8880 Walenstadt. Postfach 88",
    "sg:city":"Walenstadt",
    "sg:orig_category":"Instandhaltung U Reparatur von Automobilen",
    "sg:phone":"+41 79 409 76 00",
    "sg:postcode":"8880",
    "sg:province":"St. Gallen",
    "wof:name":"Klauser Bruno",
    "wof:placetype":"venue"
},
  "geometry": {"coordinates":[9.3381767273,47.1129570007],"type":"Point"}
}