{
  "type": "Feature",
  "properties": {
    "iso:country":"CH",
    "sg:address":"8775",
    "sg:city":"H\u00e4tzingen",
    "sg:orig_category":"Primarschulen",
    "sg:phone":"+41 55 643 34 08",
    "sg:postcode":"8775",
    "sg:province":"Glarus",
    "wof:name":"Primarschule",
    "wof:placetype":"venue"
},
  "geometry": {"coordinates":[9.0328502655,46.9526405334],"type":"Point"}
}