{
  "type": "Feature",
  "properties": {
    "iso:country":"CH",
    "sg:address":"1674",
    "sg:city":"Vuarmarens",
    "sg:orig_category":"Kalb U Schweine-M\u00e4sterei U Zucht",
    "sg:phone":"+41 21 909 52 88",
    "sg:postcode":"1674",
    "sg:province":"Fribourg",
    "wof:name":"Bovet Robert.",
    "wof:placetype":"venue"
},
  "geometry": {"coordinates":[6.8242897987,46.6457290649],"type":"Point"}
}