{
  "type": "Feature",
  "properties": {
    "iso:country":"CH",
    "sg:address":"Stauden\u00e4ckerstrasse 62",
    "sg:city":"Goldach",
    "sg:orig_category":"Herstellung von Schl\u00f6ssern U Beschl\u00e4gen",
    "sg:postcode":"9403",
    "sg:province":"St. Gallen",
    "wof:name":"Alther Verbindungstechnik",
    "wof:placetype":"venue"
},
  "geometry": {"coordinates":[9.4626541138,47.4812011719],"type":"Point"}
}