{
  "type": "Feature",
  "properties": {
    "iso:country":"CH",
    "sg:address":"Arisd\u00f6rferstrasse 39",
    "sg:city":"Liestal",
    "sg:orig_category":"Kaminfeger",
    "sg:phone":"+41 61 921 32 22",
    "sg:postcode":"4410",
    "sg:province":"Basel-Landschaft",
    "wof:name":"Werner Ricklin Kaminfegergesch\u00e4ft",
    "wof:placetype":"venue"
},
  "geometry": {"coordinates":[7.7443819046,47.4853858948],"type":"Point"}
}