{
  "type": "Feature",
  "properties": {
    "iso:country":"CH",
    "sg:address":"Route De Founex",
    "sg:city":"Coppet",
    "sg:orig_category":"Druck ohne Zeitungsdruck Offsetdruck",
    "sg:phone":"+41 22 776 15 11",
    "sg:postcode":"1296",
    "sg:province":"Vaud",
    "wof:name":"Gilbert Riesen Imprimerie De Coppet",
    "wof:placetype":"venue"
},
  "geometry": {"coordinates":[6.1902098656,46.3278770447],"type":"Point"}
}