{
  "type": "Feature",
  "properties": {
    "iso:country":"CH",
    "sg:address":"Kesslerstrasse 13",
    "sg:city":"Schlieren",
    "sg:orig_category":"Geb\u00e4ude, Wohnungsreinigung",
    "sg:phone":"+41 17300437",
    "sg:postcode":"8952",
    "sg:province":"Z\u00fcrich",
    "wof:name":"Florim Kadri F.k.reinigung",
    "wof:placetype":"venue"
},
  "geometry": {"coordinates":[8.4372558594,47.3956260681],"type":"Point"}
}