{
  "type": "Feature",
  "properties": {
    "iso:country":"CH",
    "sg:address":"Bruchstrasse 44",
    "sg:city":"Luzern",
    "sg:orig_category":"Herstellung von Sportger\u00e4ten",
    "sg:phone":"+41 41 240 66 33",
    "sg:postcode":"6003",
    "sg:province":"Luzern",
    "wof:name":"Centersport Ag",
    "wof:placetype":"venue"
},
  "geometry": {"coordinates":[8.3006782532,47.0491294861],"type":"Point"}
}