{
  "type": "Feature",
  "properties": {
    "iso:country":"CH",
    "sg:address":"Sonneggstrasse 66 8006 Z\u00fcrich. Postfach",
    "sg:city":"Z\u00fcrich",
    "sg:orig_category":"Erschliessung von Grundst\u00fccken",
    "sg:phone":"+41 13610808",
    "sg:postcode":"8033",
    "sg:province":"Z\u00fcrich",
    "wof:name":"Z\u00fcrcher Bau Und Wohngenossenschaft",
    "wof:placetype":"venue"
},
  "geometry": {"coordinates":[8.5455684662,47.3815536499],"type":"Point"}
}