{
  "type": "Feature",
  "properties": {
    "iso:country":"CH",
    "sg:address":"Boeuferrant",
    "sg:city":"Monthey",
    "sg:classifiers":[
        {
            "category":"Restaurant",
            "type":"Food & Drink"
        }
    ],
    "sg:phone":"+41 24 472 80 40",
    "sg:postcode":"1870",
    "sg:province":"Valais",
    "wof:name":"Caf\u00e9 Pont-du-rh\u00f4ne",
    "wof:placetype":"venue"
},
  "geometry": {"coordinates":[6.9584798813,46.2775840759],"type":"Point"}
}