{
  "type": "Feature",
  "properties": {
    "iso:country":"CH",
    "sg:address":"Waldeggstr. 16",
    "sg:city":"Kriechenwil",
    "sg:classifiers":[
        {
            "category":"Professional",
            "subcategory":"Engineering",
            "type":"Services"
        }
    ],
    "sg:phone":"+41 31 747 77 19",
    "sg:postcode":"3179",
    "sg:province":"Bern",
    "sg:tags":[
        "machine",
        "-",
        "mechanical"
    ],
    "wof:name":"E. H\u00c4mmerli Landmaschinen",
    "wof:placetype":"venue"
},
  "geometry": {"coordinates":[7.2267370224,46.9119758606],"type":"Point"}
}