{
  "type": "Feature",
  "properties": {
    "iso:country":"CH",
    "sg:address":"Badenerstrasse 90 8004 Z\u00fcrich. Postfach",
    "sg:city":"Z\u00fcrich",
    "sg:orig_category":"Verwaltung der Rechtspflege, Gerichte",
    "sg:phone":"+41 12482111",
    "sg:postcode":"8026",
    "sg:province":"Z\u00fcrich",
    "wof:name":"Bezirksgericht Z\u00fcrich",
    "wof:placetype":"venue"
},
  "geometry": {"coordinates":[8.52622509,47.3739051819],"type":"Point"}
}