{
  "type": "Feature",
  "properties": {
    "iso:country":"CH",
    "sg:address":"Dorfstrasse 15",
    "sg:city":"Kloten",
    "sg:orig_category":"Elektroinstallation Herstellung von Elektromotoren, Generatoren U Transformatoren",
    "sg:phone":"+41 18001029",
    "sg:postcode":"8302",
    "sg:province":"Z\u00fcrich",
    "wof:name":"Ulrich Isler Licht Kraft Telefon",
    "wof:placetype":"venue"
},
  "geometry": {"coordinates":[8.5822715759,47.4534263611],"type":"Point"}
}