{
  "type": "Feature",
  "properties": {
    "iso:country":"CH",
    "sg:address":"Rue De Gen\u00e8ve 72 1004 Lausanne. Postfach",
    "sg:city":"Gen\u00e8ve",
    "sg:orig_category":"Pensionskassen Verwaltung von Immobilien",
    "sg:phone":"+41 21 626 33 91",
    "sg:postcode":"1204",
    "sg:province":"Gen\u00e8ve",
    "wof:name":"Fondation De Pr\u00e9voyance En Faveur Du Personnel Du Comptoir Genevois Immobilier Et De Ses Soci\u00e9t\u00e9s Connexes",
    "wof:placetype":"venue"
},
  "geometry": {"coordinates":[6.6170520782,46.524471283],"type":"Point"}
}