{
  "type": "Feature",
  "properties": {
    "iso:country":"CH",
    "sg:address":"Gr\u00fctzestrasse 2",
    "sg:city":"Freienbach",
    "sg:orig_category":"Malerei",
    "sg:phone":"+41 55 410 47 05",
    "sg:postcode":"8807",
    "sg:province":"Schwyz",
    "wof:name":"Ren\u00e9 G\u00f6ldi Malergesch\u00e4ft",
    "wof:placetype":"venue"
},
  "geometry": {"coordinates":[8.7637910843,47.204158783],"type":"Point"}
}