{
  "type": "Feature",
  "properties": {
    "iso:country":"CH",
    "sg:address":"3268",
    "sg:city":"Lobsigen",
    "sg:orig_category":"Detailhandel mit Milcherzeugnissen U Eiern Verarbeitung von Milch",
    "sg:phone":"+41 32 392 25 58",
    "sg:postcode":"3268",
    "sg:province":"Bern",
    "wof:name":"Ch\u00e4si Lobsigen Gabriela Heiniger",
    "wof:placetype":"venue"
},
  "geometry": {"coordinates":[7.2958297729,47.0246810913],"type":"Point"}
}