{
  "type": "Feature",
  "properties": {
    "iso:country":"CH",
    "sg:address":"6383",
    "sg:city":"Dallenwil",
    "sg:orig_category":"Landesverteidigung, Sozialversicherung \u00d6ffentliche Verwaltung",
    "sg:phone":"+41 41 628 14 55",
    "sg:postcode":"6383",
    "sg:province":"Nidwalden",
    "wof:name":"Zivilschutzstelle Dallenwil",
    "wof:placetype":"venue"
},
  "geometry": {"coordinates":[8.392159462,46.9343948364],"type":"Point"}
}