{
  "type": "Feature",
  "properties": {
    "iso:country":"CH",
    "sg:address":"Bahnhofstrasse 21",
    "sg:city":"Mollis",
    "sg:orig_category":"Sportvereine Velo Rad-& Motorfahrer-Bund SRB",
    "sg:phone":"+41 62 926 22 54",
    "sg:postcode":"8753",
    "sg:province":"Glarus",
    "wof:name":"Veloclub Murgenthal",
    "wof:placetype":"venue"
},
  "geometry": {"coordinates":[7.8490958214,47.276725769],"type":"Point"}
}