{
  "type": "Feature",
  "properties": {
    "iso:country":"CH",
    "sg:address":"Plong-muling",
    "sg:city":"Domat/ems",
    "sg:orig_category":"Herstellung von Konstruktionsteilen, Fertigbauteilen U Ausbauelementen aus Holz",
    "sg:postcode":"7013",
    "sg:province":"Graubunden",
    "wof:name":"Schreinerei, M\u00f6bel - Innenausbau, Andreas Ladner",
    "wof:placetype":"venue"
},
  "geometry": {"coordinates":[9.4588518143,46.8373641968],"type":"Point"}
}