{
  "type": "Feature",
  "properties": {
    "iso:country":"CH",
    "sg:address":"G\u00fcterstrasse 2 2502 Biel/bienne. Postfach",
    "sg:city":"Biel/bienne",
    "sg:classifiers":[
        {
            "category":"Professional",
            "subcategory":"Employment Agencies",
            "type":"Services"
        }
    ],
    "sg:phone":"+41 32 323 87 17",
    "sg:postcode":"2501",
    "sg:province":"Bern",
    "sg:tags":[
        "personal",
        "u",
        "stellenvermittlung"
    ],
    "wof:name":"Bova-service Personalvermittlung",
    "wof:placetype":"venue"
},
  "geometry": {"coordinates":[7.2450590134,47.1345901489],"type":"Point"}
}