{
  "type": "Feature",
  "properties": {
    "iso:country":"CH",
    "sg:address":"Seminarstrasse 2",
    "sg:city":"Muttenz",
    "sg:orig_category":"Diskotheken, Dancings, Night Clubs RESTAURANTS: TEA-ROOMS",
    "sg:phone":"+41 55 445 11 21",
    "sg:postcode":"4132",
    "sg:province":"Basel-Landschaft",
    "wof:name":"Bolenberg Gastro Gmbh",
    "wof:placetype":"venue"
},
  "geometry": {"coordinates":[8.8964147568,47.1912956238],"type":"Point"}
}