{
  "type": "Feature",
  "properties": {
    "iso:country":"CH",
    "sg:address":"Vogelackerstrasse 12",
    "sg:city":"Guntershausen",
    "sg:orig_category":"Wasserversorgung",
    "sg:phone":"+41 71 311 34 31",
    "sg:postcode":"8357",
    "sg:province":"Thurgau",
    "wof:name":"Wasserkorporation Abtwil-st.josefen",
    "wof:placetype":"venue"
},
  "geometry": {"coordinates":[9.3150453568,47.4203453064],"type":"Point"}
}