{
  "type": "Feature",
  "properties": {
    "iso:country":"CH",
    "sg:address":"Oberdorf 6",
    "sg:city":"Treiten",
    "sg:orig_category":"Gem\u00fcsebau",
    "sg:phone":"+41 32 313 25 05",
    "sg:postcode":"3226",
    "sg:province":"Bern",
    "wof:name":"Beat Weber Gem\u00fcsebau",
    "wof:placetype":"venue"
},
  "geometry": {"coordinates":[7.1620588303,47.0091056824],"type":"Point"}
}