{
  "type": "Feature",
  "properties": {
    "iso:country":"CH",
    "sg:address":"8784 Braunwald. Postfach",
    "sg:city":"Braunwald",
    "sg:classifiers":[
        {
            "category":"Travel",
            "subcategory":"Hotels & Motels",
            "type":"Entertainment"
        }
    ],
    "sg:phone":"+41 55 643 10 45",
    "sg:postcode":"8784",
    "sg:province":"Glarus",
    "sg:tags":[
        "hotels",
        "mit",
        "restaurant"
    ],
    "wof:name":"Cristal Garni Schilling-k\u00fcndig H.",
    "wof:placetype":"venue"
},
  "geometry": {"coordinates":[8.9982004166,46.9389533997],"type":"Point"}
}