{
  "type": "Feature",
  "properties": {
    "iso:country":"CH",
    "sg:address":"Dickistrasse 4",
    "sg:city":"Hallau",
    "sg:orig_category":"Plastic Animal Figures",
    "sg:phone":"+41 52 687 06 06",
    "sg:postcode":"8215",
    "sg:province":"Schaffhausen",
    "wof:name":"Klarer Freizeitanlagen Ag",
    "wof:placetype":"venue"
},
  "geometry": {"coordinates":[8.4683742523,47.6922187805],"type":"Point"}
}