{
  "type": "Feature",
  "properties": {
    "iso:country":"CH",
    "sg:address":"Poststrasse 74",
    "sg:city":"Spreitenbach",
    "sg:orig_category":"Sportvereine Unihockey",
    "sg:postcode":"8957",
    "sg:province":"Aargau",
    "wof:name":"Stv Spreitenbach",
    "wof:placetype":"venue"
},
  "geometry": {"coordinates":[8.3619499207,47.4230766296],"type":"Point"}
}