{
  "type": "Feature",
  "properties": {
    "iso:country":"CH",
    "sg:address":"Via Turconi 32",
    "sg:city":"Mendrisio",
    "sg:orig_category":"Handel mit Motorr\u00e4dern, Teilen U Zubeh\u00f6r Instandhaltung U Reparatur von Motorr\u00e4dern",
    "sg:phone":"+41 91 646 10 38",
    "sg:postcode":"6850",
    "sg:province":"Ticino",
    "wof:name":"Alain Rezzonico Cicli & Moto",
    "wof:placetype":"venue"
},
  "geometry": {"coordinates":[8.9841594696,45.8670921326],"type":"Point"}
}