{
  "type": "Feature",
  "properties": {
    "iso:country":"CH",
    "sg:address":"H\u00f6hestrasse 93",
    "sg:city":"Zollikon",
    "sg:orig_category":"Markt U Meinungsforschung",
    "sg:postcode":"8702",
    "sg:province":"Z\u00fcrich",
    "wof:name":"Golton Gmbh",
    "wof:placetype":"venue"
},
  "geometry": {"coordinates":[8.581867218,47.3384628296],"type":"Point"}
}