{
  "type": "Feature",
  "properties": {
    "iso:country":"CH",
    "sg:address":"Sch\u00f6nenb\u00fchl 418",
    "sg:city":"Wolfhalden",
    "sg:classifiers":[
        {
            "category":"Restaurant",
            "type":"Food & Drink"
        }
    ],
    "sg:phone":"+41 71 891 25 43",
    "sg:postcode":"9427",
    "sg:province":"Appenzell Ausserrhoden",
    "wof:name":"Restaurant Bad Sch\u00f6nenb\u00fchl",
    "wof:placetype":"venue"
},
  "geometry": {"coordinates":[9.5642900467,47.4374580383],"type":"Point"}
}