{
  "type": "Feature",
  "properties": {
    "iso:country":"CH",
    "sg:address":"H\u00fcnenbergweg 10",
    "sg:city":"Arth",
    "sg:orig_category":"Handelsvermittlung U Grosshandel Sonstiger Grosshandel",
    "sg:phone":"+41 41 855 32 16",
    "sg:postcode":"6415",
    "sg:province":"Schwyz",
    "wof:name":"Sigi Fassbind, Handel Und Vertrieb",
    "wof:placetype":"venue"
},
  "geometry": {"coordinates":[8.5291576385,47.071975708],"type":"Point"}
}