{
  "type": "Feature",
  "properties": {
    "iso:country":"CH",
    "sg:address":"Oberer Quai 30a",
    "sg:city":"Biel/bienne",
    "sg:orig_category":"Werbeagenturen",
    "sg:phone":"+41 32 322 55 66",
    "sg:postcode":"2503",
    "sg:province":"Bern",
    "wof:name":"Jeannine & Marco Botteron Werbung",
    "wof:placetype":"venue"
},
  "geometry": {"coordinates":[7.2493138313,47.1379241943],"type":"Point"}
}