{
  "type": "Feature",
  "properties": {
    "iso:country":"CH",
    "sg:address":"Bahnhofstrasse 23 7320 Sargans. Postfach",
    "sg:city":"Sargans",
    "sg:orig_category":"Wirtschaftspr\u00fcfung, Steuerberatung U Treuhand",
    "sg:postcode":"7320",
    "sg:province":"St. Gallen",
    "wof:name":"Maienberg-service Czamek Ilse B\u00fcrodienst, Buchhaltung, Vereinsverwaltung Usw",
    "wof:placetype":"venue"
},
  "geometry": {"coordinates":[9.4437503815,47.0457801819],"type":"Point"}
}