{
  "type": "Feature",
  "properties": {
    "iso:country":"CH",
    "sg:address":"Alti Ruedelfingerstrass 26",
    "sg:city":"Marthalen",
    "sg:classifiers":[
        {
            "category":"Food & Beverages",
            "subcategory":"Meat & Fish",
            "type":"Retail Goods"
        }
    ],
    "sg:phone":"+41 52 319 10 49",
    "sg:postcode":"8460",
    "sg:province":"Z\u00fcrich",
    "sg:tags":[
        "bacon",
        "ham"
    ],
    "wof:name":"Martin Rubli",
    "wof:placetype":"venue"
},
  "geometry": {"coordinates":[8.6599187851,47.6356048584],"type":"Point"}
}