{
  "type": "Feature",
  "properties": {
    "addr:full":"Hertensteinstrasse 19a Ennetbaden Aargau 5408",
    "addr:housenumber":"19a",
    "addr:postcode":"5408",
    "addr:street":"Hertensteinstrasse",
    "iso:country":"CH",
    "sg:address":"Hertensteinstrasse 19a",
    "sg:city":"Ennetbaden",
    "sg:orig_category":"Arztpraxen",
    "sg:phone":"+41 56 221 13 62",
    "sg:postcode":"5408",
    "sg:province":"Aargau",
    "wof:name":"Dr.med.peter Federer Arzt F\u00fcr Allgemeine Medizin",
    "wof:placetype":"venue"
},
  "geometry": {"coordinates":[8.316097,47.481709],"type":"Point"}
}