{
  "type": "Feature",
  "properties": {
    "iso:country":"CH",
    "sg:address":"H\u00f6lzlistrasse 55",
    "sg:city":"Binningen",
    "sg:orig_category":"Herstellung von sonstigen organischen Grundstoffen U Chemikalien",
    "sg:phone":"+41 61 421 81 83",
    "sg:postcode":"4102",
    "sg:province":"Basel-Landschaft",
    "wof:name":"Chemar M\u00e4rklin",
    "wof:placetype":"venue"
},
  "geometry": {"coordinates":[7.5631480217,47.5332489014],"type":"Point"}
}