{
  "type": "Feature",
  "properties": {
    "iso:country":"CH",
    "sg:address":"Chemin De Royer",
    "sg:city":"Venth\u00f4ne",
    "sg:orig_category":"Grosshandel mit Holz U Baustoffen",
    "sg:phone":"+41 19502929",
    "sg:postcode":"3973",
    "sg:province":"Valais",
    "wof:name":"Emil Bachmann Bautechnik Marketing",
    "wof:placetype":"venue"
},
  "geometry": {"coordinates":[8.781539917,47.36743927],"type":"Point"}
}