{
  "type": "Feature",
  "properties": {
    "iso:country":"CH",
    "sg:address":"Rue Du Simplon 1",
    "sg:city":"Paudex",
    "sg:orig_category":"Handel mit Motorr\u00e4dern, Teilen U Zubeh\u00f6r Instandhaltung U Reparatur von Motorr\u00e4dern",
    "sg:phone":"+41 55 442 67 07",
    "sg:postcode":"1094",
    "sg:province":"Vaud",
    "wof:name":"Freeride Gmbh",
    "wof:placetype":"venue"
},
  "geometry": {"coordinates":[8.8627977371,47.189289093],"type":"Point"}
}