{
  "type": "Feature",
  "properties": {
    "iso:country":"CH",
    "sg:address":"Rankhof 4",
    "sg:city":"Basel",
    "sg:orig_category":"Erbringung von Dienstleistungen f\u00fcr Unternehmen",
    "sg:phone":"+41 61 321 66 55",
    "sg:postcode":"4070",
    "sg:province":"Basel-Stadt",
    "wof:name":"Sidler Bernhard Design + Werbung",
    "wof:placetype":"venue"
},
  "geometry": {"coordinates":[7.6169099808,47.5609893799],"type":"Point"}
}