{
  "type": "Feature",
  "properties": {
    "iso:country":"CH",
    "sg:address":"Fin De Meyriez 15",
    "sg:city":"Meyriez",
    "sg:orig_category":"Grosshandel mit Textilien",
    "sg:phone":"+41 26 670 58 55",
    "sg:postcode":"3280",
    "sg:province":"Fribourg",
    "wof:name":"Ria Guggisberg Textil Engros",
    "wof:placetype":"venue"
},
  "geometry": {"coordinates":[7.103831768,46.9201622009],"type":"Point"}
}