{
  "type": "Feature",
  "properties": {
    "iso:country":"CH",
    "sg:address":"Letzistrasse 21/23",
    "sg:city":"Z\u00fcrich",
    "sg:orig_category":"Maler U Glasergewerbe Malerei",
    "sg:phone":"+41 81 833 18 17",
    "sg:postcode":"8006",
    "sg:province":"Z\u00fcrich",
    "wof:name":"Kleger Oskar, Malergesch\u00e4ft",
    "wof:placetype":"venue"
},
  "geometry": {"coordinates":[9.8400564194,46.4876098633],"type":"Point"}
}