{
  "type": "Feature",
  "properties": {
    "iso:country":"CH",
    "sg:address":"Kapuzinerstrasse 29",
    "sg:city":"Glis",
    "sg:orig_category":"Non-Classified Establishments",
    "sg:postcode":"3902",
    "sg:province":"Valais",
    "wof:name":"Gonit Ag",
    "wof:placetype":"venue"
},
  "geometry": {"coordinates":[7.987724781,46.3143463135],"type":"Point"}
}