{
  "type": "Feature",
  "properties": {
    "iso:country":"CH",
    "sg:address":"1110",
    "sg:city":"Morges",
    "sg:orig_category":"Vorschulen, Kinderg\u00e4rten",
    "sg:postcode":"1110",
    "sg:province":"Vaud",
    "wof:name":"Ecole Enfantine Pr\u00e9-maudry I & Ii",
    "wof:placetype":"venue"
},
  "geometry": {"coordinates":[6.4987850189,46.5085639954],"type":"Point"}
}