{
  "type": "Feature",
  "properties": {
    "iso:country":"CH",
    "sg:address":"Rte De Torgon",
    "sg:city":"Vionnaz",
    "sg:orig_category":"Fleischverarbeitung",
    "sg:phone":"+41 24 481 34 81",
    "sg:postcode":"1895",
    "sg:province":"Valais",
    "wof:name":"Viandes S\u00e9ch\u00e9es - Wiedmer",
    "wof:placetype":"venue"
},
  "geometry": {"coordinates":[6.8827929497,46.3157501221],"type":"Point"}
}