{
  "type": "Feature",
  "properties": {
    "iso:country":"CH",
    "sg:address":"Altgonzenbach 26 9604 L\u00fctisburg. Postfach",
    "sg:city":"L\u00fctisburg",
    "sg:orig_category":"Softwareentwicklung U beratung",
    "sg:postcode":"9604",
    "sg:province":"St. Gallen",
    "wof:name":"Huser Lukas Hard- U. Software; Kauf U. Verkauf Usw.",
    "wof:placetype":"venue"
},
  "geometry": {"coordinates":[9.0713968277,47.3891639709],"type":"Point"}
}