{
  "type": "Feature",
  "properties": {
    "iso:country":"CH",
    "sg:address":"Chemin De La Fin-dessus 8",
    "sg:city":"Mies-tannay",
    "sg:orig_category":"Satzherstellung U Reproduktion",
    "sg:phone":"+41 22 776 32 64",
    "sg:postcode":"1295",
    "sg:province":"Vaud",
    "wof:name":"Charles Dassio Reproduction Lithographies",
    "wof:placetype":"venue"
},
  "geometry": {"coordinates":[6.1724500656,46.3060684204],"type":"Point"}
}