{
  "type": "Feature",
  "properties": {
    "iso:country":"CH",
    "sg:address":"Postgasse 17",
    "sg:city":"Wattenwil",
    "sg:orig_category":"Detailhandel mit Beleuchtungs U Haushaltsgegenst\u00e4nden",
    "sg:phone":"+41 19305050",
    "sg:postcode":"3665",
    "sg:province":"Bern",
    "wof:name":"Schneider Eisenwaren & Haushalt Ag",
    "wof:placetype":"venue"
},
  "geometry": {"coordinates":[8.811494,47.332863],"type":"Point"}
}