{
  "type": "Feature",
  "properties": {
    "addr:full":"Route De L'etraz 138 1290 Versoix Case Postale 276 Versoix Gen\u00e8ve 1290",
    "addr:housenumber":"138;276",
    "addr:postcode":"1290;1290",
    "addr:street":"Route De L'Etraz;Postale",
    "iso:country":"CH",
    "sg:address":"Route De L'etraz 138 1290 Versoix Case Postale 276",
    "sg:city":"Versoix",
    "sg:orig_category":"Bauingenieurb\u00fcros allgemein",
    "sg:phone":"+41 22 755 15 96",
    "sg:postcode":"1290",
    "sg:province":"Gen\u00e8ve",
    "wof:name":"Fran\u00e7ois Bapst Bureau D'ing\u00e9nieur",
    "wof:placetype":"venue"
},
  "geometry": {"coordinates":[6.16715,46.280289],"type":"Point"}
}