{
  "type": "Feature",
  "properties": {
    "iso:country":"CH",
    "sg:address":"Seestrasse 30",
    "sg:city":"Spiez",
    "sg:orig_category":"Kauf U Verkauf von Immobilien auf eigene Rechnung",
    "sg:phone":"+41 33 655 02 77",
    "sg:postcode":"3700",
    "sg:province":"Bern",
    "wof:name":"Minerbau Ag",
    "wof:placetype":"venue"
},
  "geometry": {"coordinates":[7.6794037819,46.6887168884],"type":"Point"}
}