{
  "type": "Feature",
  "properties": {
    "iso:country":"CH",
    "sg:address":"1854",
    "sg:city":"Leysin",
    "sg:orig_category":"Schulpflegen",
    "sg:postcode":"1854",
    "sg:province":"Vaud",
    "wof:name":"Commission Scolaire De L'\u00e9cole Primaire",
    "wof:placetype":"venue"
},
  "geometry": {"coordinates":[7.1587100029,46.3500404358],"type":"Point"}
}