{
  "type": "Feature",
  "properties": {
    "iso:country":"CH",
    "sg:address":"Allmendweg 7",
    "sg:city":"Cham",
    "sg:orig_category":"Sportvereine Unihockey",
    "sg:postcode":"6330",
    "sg:province":"Zug",
    "wof:name":"Uhc Horgen",
    "wof:placetype":"venue"
},
  "geometry": {"coordinates":[8.4538125992,47.180065155],"type":"Point"}
}