{
  "type": "Feature",
  "properties": {
    "addr:full":"Steinweid Sumiswald Bern 3454",
    "addr:postcode":"3454",
    "iso:country":"CH",
    "sg:address":"Steinweid",
    "sg:city":"Sumiswald",
    "sg:orig_category":"Blumen U Zierpflanzenbau",
    "sg:postcode":"3454",
    "sg:province":"Bern",
    "wof:name":"Hans Rudolf Gfeller",
    "wof:placetype":"venue"
},
  "geometry": {"coordinates":[7.769796,47.021606],"type":"Point"}
}