{
  "type": "Feature",
  "properties": {
    "iso:country":"CH",
    "sg:address":"Sennh\u00fcttenstrasse 15",
    "sg:city":"Horgen",
    "sg:orig_category":"Softwareentwicklung U beratung",
    "sg:postcode":"8810",
    "sg:province":"Z\u00fcrich",
    "wof:name":"Tsms Trade Soft M. Segalini",
    "wof:placetype":"venue"
},
  "geometry": {"coordinates":[8.6005735397,47.2534713745],"type":"Point"}
}