{
  "type": "Feature",
  "properties": {
    "iso:country":"CH",
    "sg:address":"Route De Courroux 14 2830 Courrendlin Case Postale 9",
    "sg:city":"Courrendlin",
    "sg:orig_category":"Herstellung von Tanks U Sammelbeh\u00e4ltern aus Metall Reinigungsgewerbe",
    "sg:phone":"+41 32 435 56 87",
    "sg:postcode":"2830",
    "sg:province":"Jura",
    "wof:name":"Cuttat Sa Revision De Citernes Tarag",
    "wof:placetype":"venue"
},
  "geometry": {"coordinates":[7.3748960495,47.3449554443],"type":"Point"}
}