{
  "type": "Feature",
  "properties": {
    "iso:country":"CH",
    "sg:address":"Th\u00fcrn 62",
    "sg:city":"T\u00e4gerschen",
    "sg:orig_category":"Non-Classified Establishments",
    "sg:postcode":"9554",
    "sg:province":"Thurgau",
    "wof:name":"Andr\u00e9 Holenstein Reparatur & Service Radio",
    "wof:placetype":"venue"
},
  "geometry": {"coordinates":[9.0301923752,47.5089416504],"type":"Point"}
}