{
  "type": "Feature",
  "properties": {
    "iso:country":"CH",
    "sg:address":"Industriestrasse 4",
    "sg:city":"Bonaduz",
    "sg:orig_category":"Herstellung von Mess U Kontrollinstrumenten U vorrichtungen",
    "sg:phone":"+41 81 641 21 35",
    "sg:postcode":"7402",
    "sg:province":"Graubunden",
    "wof:name":"Kupper Urs",
    "wof:placetype":"venue"
},
  "geometry": {"coordinates":[9.3859777451,46.8102645874],"type":"Point"}
}