{
  "type": "Feature",
  "properties": {
    "iso:country":"CH",
    "sg:address":"Fabrikstr. 6",
    "sg:city":"Hinwil",
    "sg:classifiers":[
        {
            "category":"Manufacturing",
            "subcategory":"Metals",
            "type":"Manufacturing & Wholesale Goods"
        }
    ],
    "sg:phone":"+41 4119389888",
    "sg:postcode":"8340",
    "sg:province":"Z\u00fcrich",
    "sg:tags":[
        "-",
        "machine",
        "equipment",
        "engineering",
        "machinery",
        "mechanical"
    ],
    "wof:name":"Soma Ag Maschinenbau",
    "wof:placetype":"venue"
},
  "geometry": {"coordinates":[8.8376350403,47.3005714417],"type":"Point"}
}