{
  "type": "Feature",
  "properties": {
    "iso:country":"CH",
    "sg:address":"Rheinstrasse 119",
    "sg:city":"Frenkendorf",
    "sg:orig_category":"Non-Classified Establishments",
    "sg:postcode":"4402",
    "sg:province":"Basel-Landschaft",
    "wof:name":"Bp Service Station",
    "wof:placetype":"venue"
},
  "geometry": {"coordinates":[7.7198739052,47.5144309998],"type":"Point"}
}