{
  "type": "Feature",
  "properties": {
    "iso:country":"CH",
    "sg:address":"Rue Pr\u00e9 Borvey 8",
    "sg:city":"Martigny",
    "sg:orig_category":"Malerei",
    "sg:phone":"+41 27 722 84 49",
    "sg:postcode":"1920",
    "sg:province":"Valais",
    "wof:name":"Roland Meyer Entreprise De Peinture",
    "wof:placetype":"venue"
},
  "geometry": {"coordinates":[7.0704498291,46.0956459045],"type":"Point"}
}