{
  "type": "Feature",
  "properties": {
    "iso:country":"CH",
    "sg:address":"Route De Fontanivent 32",
    "sg:city":"Chernex",
    "sg:orig_category":"Bauingenieurb\u00fcros Heizung L\u00fcftung Klima Bauingenieurb\u00fcros allgemein",
    "sg:phone":"+41 71 245 65 34",
    "sg:postcode":"1822",
    "sg:province":"Vaud",
    "wof:name":"Dieter Hirsekorn Ingenieurb\u00fcro",
    "wof:placetype":"venue"
},
  "geometry": {"coordinates":[9.3918819427,47.4399337769],"type":"Point"}
}