{
  "type": "Feature",
  "properties": {
    "iso:country":"CH",
    "sg:address":"Tieracker 34",
    "sg:city":"Bolligen",
    "sg:orig_category":"Unternehmensberatung",
    "sg:postcode":"3065",
    "sg:province":"Bern",
    "wof:name":"Fischer & Co",
    "wof:placetype":"venue"
},
  "geometry": {"coordinates":[7.4976000786,46.977230072],"type":"Point"}
}