{
  "type": "Feature",
  "properties": {
    "addr:full":"Po Box 161 Avenue Louis-casaii 84 Cointrin Geneva Gen\u00e8ve 1216",
    "addr:housenumber":"po;84",
    "addr:postcode":"1216",
    "addr:street":"Box 161 Avenue Louis-Casaii",
    "iso:country":"CH",
    "sg:address":"Po Box 161 Avenue Louis-casaii 84 Cointrin",
    "sg:city":"Geneva",
    "sg:classifiers":[
        {
            "category":"Banks & Credit Unions",
            "subcategory":"Bank",
            "type":"Services"
        }
    ],
    "sg:phone":"+41 22 708 60 00",
    "sg:postcode":"1216",
    "sg:province":"Gen\u00e8ve",
    "wof:name":"Darier Hentsch & Cie",
    "wof:placetype":"venue"
},
  "geometry": {"coordinates":[6.142701,46.208359],"type":"Point"}
}