{
  "type": "Feature",
  "properties": {
    "addr:full":"Katzenseestrasse 4 Z\u00fcrich Z\u00fcrich 8046",
    "addr:housenumber":"4",
    "addr:postcode":"8046",
    "addr:street":"Katzenseestrasse",
    "iso:country":"CH",
    "sg:address":"Katzenseestrasse 4",
    "sg:city":"Z\u00fcrich",
    "sg:orig_category":"Dachdeckerei Zimmerei, Dachdeckerei, Bauspenglerei U Abdichtung",
    "sg:postcode":"8046",
    "sg:province":"Z\u00fcrich",
    "wof:name":"Hanspeter R\u00f6sti",
    "wof:placetype":"venue"
},
  "geometry": {"coordinates":[7.445949,46.463657],"type":"Point"}
}