{
  "type": "Feature",
  "properties": {
    "iso:country":"CH",
    "sg:address":"Winkelstrasse 31",
    "sg:city":"Oftringen",
    "sg:orig_category":"Elektroinstallation",
    "sg:phone":"+41 62 797 07 37",
    "sg:postcode":"4665",
    "sg:province":"Aargau",
    "wof:name":"Joao Nogueira Elektroinstallationen",
    "wof:placetype":"venue"
},
  "geometry": {"coordinates":[7.9325780869,47.299823761],"type":"Point"}
}