{
  "type": "Feature",
  "properties": {
    "iso:country":"CH",
    "sg:address":"Arbonerstrasse 28",
    "sg:city":"Romanshorn",
    "sg:orig_category":"Personal U Stellenvermittlung Unternehmensberatung",
    "sg:phone":"+41 41 790 25 46",
    "sg:postcode":"8590",
    "sg:province":"Thurgau",
    "wof:name":"M\u00e4rchy & Partner",
    "wof:placetype":"venue"
},
  "geometry": {"coordinates":[8.4399642944,47.1532440186],"type":"Point"}
}