{
  "type": "Feature",
  "properties": {
    "iso:country":"CH",
    "sg:address":"Sp\u00e4tzerenstrasse 3",
    "sg:city":"Oberiberg",
    "sg:orig_category":"Grosshandel mit Eisenwaren sowie Installationsbedarf f\u00fcr Gas, Wasser U Heizung Herstellung von Werkz",
    "sg:phone":"+41 55 414 21 66",
    "sg:postcode":"8843",
    "sg:province":"Schwyz",
    "wof:name":"Manfred King Holzbearbeitungswerkzeuge",
    "wof:placetype":"venue"
},
  "geometry": {"coordinates":[8.7770938873,47.0382499695],"type":"Point"}
}