{
  "type": "Feature",
  "properties": {
    "iso:country":"CH",
    "sg:address":"Dorfstrasse 13",
    "sg:city":"Kyburg-buchegg",
    "sg:orig_category":"RESTAURANTS: TEA-ROOMS",
    "sg:phone":"+41 32 661 18 18",
    "sg:postcode":"4586",
    "sg:province":"Solothurn",
    "wof:name":"Schl\u00f6ssli Buchegg Gmbh",
    "wof:placetype":"venue"
},
  "geometry": {"coordinates":[7.5138998032,47.1444702148],"type":"Point"}
}