{
  "type": "Feature",
  "properties": {
    "iso:country":"CH",
    "sg:address":"Chemin De La Damataire 9 1009 Pully Case Postale 371",
    "sg:city":"Pully",
    "sg:orig_category":"Herstellung von Elektrizit\u00e4tsverteilungs U schalteinrichtungen",
    "sg:phone":"+41 21 729 04 04",
    "sg:postcode":"1009",
    "sg:province":"Vaud",
    "wof:name":"Rte R\u00e9alisations Techniques Electriques Sa",
    "wof:placetype":"venue"
},
  "geometry": {"coordinates":[6.6694288254,46.5070991516],"type":"Point"}
}