{
  "type": "Feature",
  "properties": {
    "iso:country":"CH",
    "sg:address":"Johann-veresius-strasse 18 2500 Biel/bienne. Postfach",
    "sg:city":"Biel/bienne",
    "sg:orig_category":"Sonstiges Versicherungsgewerbe",
    "sg:postcode":"2502",
    "sg:province":"Bern",
    "wof:name":"Cuche Nicolas",
    "wof:placetype":"venue"
},
  "geometry": {"coordinates":[7.2461190224,47.132434845],"type":"Point"}
}