{
  "type": "Feature",
  "properties": {
    "iso:country":"CH",
    "sg:address":"Sch\u00f6nb\u00fchlstrasse 4",
    "sg:city":"Z\u00fcrich",
    "sg:orig_category":"Webdesign",
    "sg:phone":"+41 12620202",
    "sg:postcode":"8032",
    "sg:province":"Z\u00fcrich",
    "wof:name":"Frameset Gmbh Webhosting",
    "wof:placetype":"venue"
},
  "geometry": {"coordinates":[8.5573129654,47.3696861267],"type":"Point"}
}