{
  "type": "Feature",
  "properties": {
    "iso:country":"CH",
    "sg:address":"Place De La Paix 1",
    "sg:city":"Montreux",
    "sg:orig_category":"Vorschulen, Kinderg\u00e4rten",
    "sg:phone":"+41 21 963 59 75",
    "sg:postcode":"1820",
    "sg:province":"Vaud",
    "wof:name":"Ecole Nouvelle Ecole Enfantine",
    "wof:placetype":"venue"
},
  "geometry": {"coordinates":[6.9110908508,46.4314498901],"type":"Point"}
}