{
  "type": "Feature",
  "properties": {
    "iso:country":"CH",
    "sg:address":"Kaiserackerweg 15",
    "sg:city":"W\u00fcrenlingen",
    "sg:orig_category":"Arztpraxen",
    "sg:phone":"+41 56 281 20 10",
    "sg:postcode":"5303",
    "sg:province":"Aargau",
    "wof:name":"Dres Med.r. Mahler & R. Meyer Aerzte F\u00fcr Allg.medizin Fmh",
    "wof:placetype":"venue"
},
  "geometry": {"coordinates":[8.252707,47.529099],"type":"Point"}
}