{
  "type": "Feature",
  "properties": {
    "iso:country":"CH",
    "sg:address":"Im Gut Muracher",
    "sg:city":"Vitznau",
    "sg:orig_category":"Kauf U Verkauf von Immobilien auf eigene Rechnung",
    "sg:postcode":"6354",
    "sg:province":"Luzern",
    "wof:name":"Oikia Ag",
    "wof:placetype":"venue"
},
  "geometry": {"coordinates":[8.4751930237,47.0169029236],"type":"Point"}
}