{
  "type": "Feature",
  "properties": {
    "iso:country":"CH",
    "sg:address":"Kleinwangenstrasse 2",
    "sg:city":"Hochdorf",
    "sg:orig_category":"Erbringung von sonstigen Dienstleistungen f\u00fcr Unternehmen",
    "sg:phone":"+41 41 910 01 88",
    "sg:postcode":"6280",
    "sg:province":"Luzern",
    "wof:name":"Claro Weltladen",
    "wof:placetype":"venue"
},
  "geometry": {"coordinates":[8.2919549942,47.1670570374],"type":"Point"}
}