{
  "type": "Feature",
  "properties": {
    "iso:country":"CH",
    "sg:address":"Lerchenweg 12",
    "sg:city":"Utzenstorf",
    "sg:orig_category":"Architektur U Ingenieurb\u00fcros",
    "sg:phone":"+41 41 850 25 10",
    "sg:postcode":"3427",
    "sg:province":"Bern",
    "wof:name":"Baumberger Projekt Ag, Ingenieurb\u00fcro F\u00fcr Planen Und Bauen",
    "wof:placetype":"venue"
},
  "geometry": {"coordinates":[8.437692,47.070221],"type":"Point"}
}