{
  "type": "Feature",
  "properties": {
    "iso:country":"CH",
    "sg:address":"Zentrum",
    "sg:city":"Regensdorf",
    "sg:orig_category":"Detailhandel mit Waren verschiedener Art, Hauptrichtung Nahrungsmittel",
    "sg:phone":"+41 18843131",
    "sg:postcode":"8105",
    "sg:province":"Z\u00fcrich",
    "wof:name":"Pick Pay Betriebs Ag",
    "wof:placetype":"venue"
},
  "geometry": {"coordinates":[8.4675598145,47.4321556091],"type":"Point"}
}