{
  "type": "Feature",
  "properties": {
    "iso:country":"CH",
    "sg:address":"Grand-rue 1a",
    "sg:city":"Neuch\u00e2tel",
    "sg:orig_category":"Sprachschulen",
    "sg:phone":"+41 32 724 07 77",
    "sg:postcode":"2000",
    "sg:province":"Neuch\u00e2tel",
    "wof:name":"Interlangues Ecoles De Langues",
    "wof:placetype":"venue"
},
  "geometry": {"coordinates":[6.9290719032,46.9919052124],"type":"Point"}
}