{
  "type": "Feature",
  "properties": {
    "iso:country":"CH",
    "sg:address":"Weingartstrasse 18",
    "sg:city":"Bern",
    "sg:orig_category":"Primarschulen",
    "sg:phone":"+41 31 331 85 45",
    "sg:postcode":"3014",
    "sg:province":"Bern",
    "wof:name":"Primarschule Markus",
    "wof:placetype":"venue"
},
  "geometry": {"coordinates":[7.4574661255,46.9622077942],"type":"Point"}
}