{
  "type": "Feature",
  "properties": {
    "iso:country":"CH",
    "sg:address":"Fangh\u00f6fli 14",
    "sg:city":"Littau",
    "sg:orig_category":"Detailhandel mit Waren verschiedener Art, Hauptrichtung Nahrungsmittel",
    "sg:phone":"+41 41 250 27 57",
    "sg:postcode":"6014",
    "sg:province":"Luzern",
    "wof:name":"Migros-markt Fangh\u00f6fli",
    "wof:placetype":"venue"
},
  "geometry": {"coordinates":[8.2616558075,47.0496673584],"type":"Point"}
}