{
  "type": "Feature",
  "properties": {
    "addr:full":"Grand-rue 19 Ballaigues Vaud 1338",
    "addr:housenumber":"19",
    "addr:postcode":"1338",
    "addr:street":"Grand-Rue",
    "iso:country":"CH",
    "sg:address":"Grand-rue 19",
    "sg:city":"Ballaigues",
    "sg:classifiers":[
        {
            "category":"Banks & Credit Unions",
            "subcategory":"Bank",
            "type":"Services"
        }
    ],
    "sg:phone":"+41 21 843 24 17",
    "sg:postcode":"1338",
    "sg:province":"Vaud",
    "wof:name":"Banque Cantonale Vaudoise",
    "wof:placetype":"venue"
},
  "geometry": {"coordinates":[6.413946,46.729275],"type":"Point"}
}