{
  "type": "Feature",
  "properties": {
    "iso:country":"CH",
    "sg:address":"Klus 29g",
    "sg:city":"K\u00fcblis",
    "sg:orig_category":"Grosshandel mit Eisenwaren sowie Installationsbedarf f\u00fcr Gas, Wasser U Heizung Herstellung von \u00d6fen ",
    "sg:phone":"+41 81 332 19 84",
    "sg:postcode":"7240",
    "sg:province":"Graubunden",
    "wof:name":"Joos Luzi Handelsunternehmung",
    "wof:placetype":"venue"
},
  "geometry": {"coordinates":[9.7756757736,46.9143066406],"type":"Point"}
}