{
  "type": "Feature",
  "properties": {
    "iso:country":"CH",
    "sg:address":"3088",
    "sg:city":"R\u00fceggisberg",
    "sg:orig_category":"Primarschulen",
    "sg:phone":"+41 31 839 10 27",
    "sg:postcode":"3088",
    "sg:province":"Bern",
    "wof:name":"Primarschule",
    "wof:placetype":"venue"
},
  "geometry": {"coordinates":[7.4389481544,46.8215065002],"type":"Point"}
}