{
  "type": "Feature",
  "properties": {
    "iso:country":"CH",
    "sg:address":"Hauptstrasse 97",
    "sg:city":"Bleienbach",
    "sg:orig_category":"Detailhandel mit Brot, Back U S\u00fcsswaren",
    "sg:postcode":"3368",
    "sg:province":"Bern",
    "wof:name":"B\u00e4ckerei, Lebensmittel Rickli",
    "wof:placetype":"venue"
},
  "geometry": {"coordinates":[7.75629,47.185207],"type":"Point"}
}