{
  "type": "Feature",
  "properties": {
    "iso:country":"CH",
    "sg:address":"Route De Boudry 22",
    "sg:city":"Cortaillod",
    "sg:classifiers":[
        {
            "category":"Autos & Motor Vehicles",
            "subcategory":"Auto Supplies",
            "type":"Retail Goods"
        }
    ],
    "sg:phone":"+41 79 240 60 80",
    "sg:postcode":"2016",
    "sg:province":"Neuch\u00e2tel",
    "sg:tags":[
        "car",
        "radio",
        "accessory"
    ],
    "wof:name":"Powertech",
    "wof:placetype":"venue"
},
  "geometry": {"coordinates":[6.843228,46.94492],"type":"Point"}
}