{
  "type": "Feature",
  "properties": {
    "iso:country":"CH",
    "sg:address":"Watterstrasse 41",
    "sg:city":"Regensdorf",
    "sg:orig_category":"Sonstige Kultur U Unterhaltungseinrichtungen",
    "sg:postcode":"8105",
    "sg:province":"Z\u00fcrich",
    "wof:name":"Casino Regensdorf Ag",
    "wof:placetype":"venue"
},
  "geometry": {"coordinates":[8.4661931992,47.4317016602],"type":"Point"}
}