{
  "type": "Feature",
  "properties": {
    "iso:country":"CH",
    "sg:address":"Langnaustrasse 14",
    "sg:city":"Z\u00e4ziwil",
    "sg:orig_category":"Grosshandel mit Nahrungsmitteln, Getr\u00e4nken U Tabakwaren ohne ausgepr\u00e4gten Schwerpunkt Grosshandel mi",
    "sg:phone":"+41 31 711 44 77",
    "sg:postcode":"3532",
    "sg:province":"Bern",
    "wof:name":"Siani Food Import-export-vertrieb",
    "wof:placetype":"venue"
},
  "geometry": {"coordinates":[7.6640410423,46.9019699097],"type":"Point"}
}