{
  "type": "Feature",
  "properties": {
    "iso:country":"CH",
    "sg:address":"Le Centre",
    "sg:city":"Courtepin",
    "sg:orig_category":"RESTAURANTS: TEA-ROOMS",
    "sg:postcode":"1784",
    "sg:province":"Fribourg",
    "wof:name":"Restaurant Le Centre Courtepin S\u00e0rl",
    "wof:placetype":"venue"
},
  "geometry": {"coordinates":[7.1241049767,46.8650283813],"type":"Point"}
}