{
  "type": "Feature",
  "properties": {
    "iso:country":"CH",
    "sg:address":"Langwattstr. 27",
    "sg:city":"Zollikerberg",
    "sg:classifiers":[
        {
            "category":"Farming",
            "subcategory":"Livestock Farm",
            "type":"Manufacturing & Wholesale Goods"
        }
    ],
    "sg:phone":"+41 4118648088",
    "sg:postcode":"8125",
    "sg:province":"Z\u00fcrich",
    "sg:tags":[
        "breeding",
        "agriculture",
        "animal"
    ],
    "wof:name":"Lobstair Ag",
    "wof:placetype":"venue"
},
  "geometry": {"coordinates":[8.605674,47.342178],"type":"Point"}
}