{
  "type": "Feature",
  "properties": {
    "iso:country":"CH",
    "sg:address":"Chemin Du Calvaire 7",
    "sg:city":"Lausanne",
    "sg:orig_category":"Bauschreinerei Herstellung von M\u00f6beln verschiedener Art",
    "sg:postcode":"1005",
    "sg:province":"Vaud",
    "wof:name":"Schmied Philippe.",
    "wof:placetype":"venue"
},
  "geometry": {"coordinates":[6.638075,46.525524],"type":"Point"}
}