{
  "type": "Feature",
  "properties": {
    "iso:country":"CH",
    "sg:address":"Eisenburgstrasse 1",
    "sg:city":"Sch\u00fcbelbach",
    "sg:orig_category":"Allgemeiner Hoch U Tiefbau",
    "sg:phone":"+41 55 440 58 50",
    "sg:postcode":"8862",
    "sg:province":"Schwyz",
    "wof:name":"Andenmatten K.",
    "wof:placetype":"venue"
},
  "geometry": {"coordinates":[8.927621,47.172951],"type":"Point"}
}