{
  "type": "Feature",
  "properties": {
    "iso:country":"CH",
    "sg:address":"L\u00e4uferberg 4",
    "sg:city":"N\u00e4fels",
    "sg:orig_category":"Hardwareberatung Softwareentwicklung U beratung",
    "sg:phone":"+41 55 622 36 80",
    "sg:postcode":"8752",
    "sg:province":"Glarus",
    "wof:name":"Emil Blumer Blumer Internat. Consulting",
    "wof:placetype":"venue"
},
  "geometry": {"coordinates":[9.0343790054,47.1014633179],"type":"Point"}
}