{
  "type": "Feature",
  "properties": {
    "iso:country":"CH",
    "sg:address":"Rue Du Ch\u00e2teau 42a",
    "sg:city":"Cornol",
    "sg:orig_category":"Herstellung U Zusammensetzung von Uhren",
    "sg:phone":"+41 32 462 26 34",
    "sg:postcode":"2952",
    "sg:province":"Jura",
    "wof:name":"Pierre Marzolo Polissage De Boites De Montres",
    "wof:placetype":"venue"
},
  "geometry": {"coordinates":[7.1590199471,47.4090194702],"type":"Point"}
}