{
  "type": "Feature",
  "properties": {
    "iso:country":"CH",
    "sg:address":"Rheinstrasse 8 4410 Liestal. Postfach 641",
    "sg:city":"Liestal",
    "sg:orig_category":"Vermietung U Verpachtung von eigenen Immobilien",
    "sg:postcode":"4410",
    "sg:province":"Basel-Landschaft",
    "wof:name":"Frepa Immobilien Ag",
    "wof:placetype":"venue"
},
  "geometry": {"coordinates":[7.321103096,47.0973701477],"type":"Point"}
}