{
  "type": "Feature",
  "properties": {
    "iso:country":"CH",
    "sg:address":"Waldhof",
    "sg:city":"Langenthal",
    "sg:classifiers":[
        {
            "category":"Education",
            "subcategory":"Vocational School",
            "type":"Public Place"
        }
    ],
    "sg:postcode":"4900",
    "sg:province":"Bern",
    "sg:tags":[
        "koch-",
        "haushaltschulen"
    ],
    "wof:name":"Inforama Waldhof Bildungs-beratungs & Tagungsz.",
    "wof:placetype":"venue"
},
  "geometry": {"coordinates":[7.8018398285,47.2185707092],"type":"Point"}
}