{
  "type": "Feature",
  "properties": {
    "iso:country":"CH",
    "sg:address":"Bohlstrasse 20",
    "sg:city":"Zug",
    "sg:orig_category":"Unclassifiable Establishments",
    "sg:postcode":"6300",
    "sg:province":"Zug",
    "wof:name":"Tc Generales Entreprises Sa",
    "wof:placetype":"venue"
},
  "geometry": {"coordinates":[8.5211591721,47.1638908386],"type":"Point"}
}