{
  "type": "Feature",
  "properties": {
    "iso:country":"CH",
    "sg:address":"Chemin Isaac-anken 5",
    "sg:city":"A\u00efre",
    "sg:orig_category":"Herstellung von Drahtwaren Maurerarbeiten",
    "sg:phone":"+41 22 797 15 95",
    "sg:postcode":"1219",
    "sg:province":"Gen\u00e8ve",
    "wof:name":"Giuseppe Garofalo Ma\u00e7onnerie & B\u00e9ton Arm\u00e9",
    "wof:placetype":"venue"
},
  "geometry": {"coordinates":[6.1047511101,46.2051849365],"type":"Point"}
}