{
  "type": "Feature",
  "properties": {
    "addr:full":"Ruesserain 121 Moosleerau Aargau 5054",
    "addr:housenumber":"121",
    "addr:postcode":"5054",
    "iso:country":"CH",
    "sg:address":"Ruesserain 121",
    "sg:city":"Moosleerau",
    "sg:orig_category":"Arztpraxen",
    "sg:phone":"+41 62 726 10 60",
    "sg:postcode":"5054",
    "sg:province":"Aargau",
    "wof:name":"Dr.med.hansj\u00f6rg Sprenger Arzt F.allgemeine Medizin Fmh",
    "wof:placetype":"venue"
},
  "geometry": {"coordinates":[8.065017,47.270329],"type":"Point"}
}