{
  "type": "Feature",
  "properties": {
    "iso:country":"CH",
    "sg:address":"Fegistr. 1",
    "sg:city":"Spreitenbach",
    "sg:classifiers":[
        {
            "category":"Wholesale",
            "subcategory":"Machinery & Supplies",
            "type":"Manufacturing & Wholesale Goods"
        }
    ],
    "sg:phone":"+41 56 401 26 25",
    "sg:postcode":"8957",
    "sg:province":"Aargau",
    "sg:tags":[
        "equipment",
        "optical",
        "precision",
        "instrument"
    ],
    "wof:name":"Germann & Gsell Service Gmbh",
    "wof:placetype":"venue"
},
  "geometry": {"coordinates":[8.3696537018,47.4301528931],"type":"Point"}
}