{
  "type": "Feature",
  "properties": {
    "iso:country":"CH",
    "sg:address":"Spannerstrasse 6",
    "sg:city":"Frauenfeld",
    "sg:orig_category":"Vorschulen, Kinderg\u00e4rten",
    "sg:phone":"+41 52 722 44 36",
    "sg:postcode":"8500",
    "sg:province":"Thurgau",
    "wof:name":"Kindergarten Stadt",
    "wof:placetype":"venue"
},
  "geometry": {"coordinates":[8.9008951187,47.5550880432],"type":"Point"}
}