{
  "type": "Feature",
  "properties": {
    "iso:country":"CH",
    "sg:address":"Dorfstrasse 53",
    "sg:city":"Wangs",
    "sg:orig_category":"Detailhandel mit Geschenkartikeln U Souvenirs",
    "sg:phone":"+41 55 210 81 58",
    "sg:postcode":"7323",
    "sg:province":"St. Gallen",
    "wof:name":"Annette Brenner Kunstecke",
    "wof:placetype":"venue"
},
  "geometry": {"coordinates":[8.8173294067,47.2268066406],"type":"Point"}
}