{
  "type": "Feature",
  "properties": {
    "iso:country":"CH",
    "sg:address":"La C\u00f4te 857",
    "sg:city":"Fontenais",
    "sg:orig_category":"Ausbaugewerbe",
    "sg:phone":"+41 32 466 11 25",
    "sg:postcode":"2902",
    "sg:province":"Jura",
    "wof:name":"Chariatte Pierre-andr\u00e9, Pac Inox",
    "wof:placetype":"venue"
},
  "geometry": {"coordinates":[7.080865,47.40572],"type":"Point"}
}