{
  "type": "Feature",
  "properties": {
    "iso:country":"CH",
    "sg:address":"Neustrasse 26",
    "sg:city":"Melchnau",
    "sg:orig_category":"Gartenbau",
    "sg:phone":"+41 62 927 18 02",
    "sg:postcode":"4917",
    "sg:province":"Bern",
    "wof:name":"Leo Brunschwiler G\u00e4rtnerei",
    "wof:placetype":"venue"
},
  "geometry": {"coordinates":[7.8569231033,47.1818847656],"type":"Point"}
}