{
  "type": "Feature",
  "properties": {
    "iso:country":"CH",
    "sg:address":"Stationsstrasse 62",
    "sg:city":"Wetzikon",
    "sg:classifiers":[
        {
            "category":"Government",
            "subcategory":"Post Office",
            "type":"Public Place"
        }
    ],
    "sg:phone":"+41 19304664",
    "sg:postcode":"8623",
    "sg:province":"Z\u00fcrich",
    "sg:tags":[
        "picket",
        "fence",
        "pales"
    ],
    "wof:name":"Zweifel & Co",
    "wof:placetype":"venue"
},
  "geometry": {"coordinates":[8.809170723,47.3325424194],"type":"Point"}
}