{
  "type": "Feature",
  "properties": {
    "iso:country":"CH",
    "sg:address":"Industriestrasse 1",
    "sg:city":"Volketswil",
    "sg:orig_category":"Chemische Reinigung",
    "sg:phone":"+41 19454977",
    "sg:postcode":"8604",
    "sg:province":"Z\u00fcrich",
    "wof:name":"Marius Kempf Chemische Reinigung",
    "wof:placetype":"venue"
},
  "geometry": {"coordinates":[8.668141,47.381966],"type":"Point"}
}