{
  "type": "Feature",
  "properties": {
    "iso:country":"CH",
    "sg:address":"Engelpr\u00e4chtigen",
    "sg:city":"Ufhusen",
    "sg:orig_category":"Herstellung von Reiseartikeln, Leder U Sattlerwaren",
    "sg:phone":"+41 41 988 19 19",
    "sg:postcode":"6153",
    "sg:province":"Luzern",
    "wof:name":"Huber-h\u00e4fliger Kaspar",
    "wof:placetype":"venue"
},
  "geometry": {"coordinates":[7.888903141,47.1234130859],"type":"Point"}
}