{
  "type": "Feature",
  "properties": {
    "iso:country":"CH",
    "sg:address":"Route De Montena 65",
    "sg:city":"Rossens",
    "sg:classifiers":[
        {
            "category":"Utilities",
            "subcategory":"Electric",
            "type":"Services"
        }
    ],
    "sg:phone":"+41 26 411 85 00",
    "sg:postcode":"1728",
    "sg:province":"Fribourg",
    "sg:tags":[
        "high-voltage",
        "capacitor"
    ],
    "wof:name":"Montena Components Sa",
    "wof:placetype":"venue"
},
  "geometry": {"coordinates":[7.0936379433,46.7260055542],"type":"Point"}
}