{
  "type": "Feature",
  "properties": {
    "iso:country":"CH",
    "sg:address":"Asylstrasse 9",
    "sg:city":"Z\u00fcrich",
    "sg:orig_category":"Architektur U Ingenieurb\u00fcros Architekturb\u00fcros",
    "sg:postcode":"8032",
    "sg:province":"Z\u00fcrich",
    "wof:name":"Rebmann & Eichenberger Architekten",
    "wof:placetype":"venue"
},
  "geometry": {"coordinates":[8.557125,47.369671],"type":"Point"}
}