{
  "type": "Feature",
  "properties": {
    "iso:country":"CH",
    "sg:address":"Hinter Der M\u00fchle 3",
    "sg:city":"Riehen",
    "sg:orig_category":"Erschliessung von Grundst\u00fccken",
    "sg:phone":"+41 61 641 52 63",
    "sg:postcode":"4125",
    "sg:province":"Basel-Stadt",
    "wof:name":"Wohngenossenschaft Hinter Der M\u00fchle",
    "wof:placetype":"venue"
},
  "geometry": {"coordinates":[7.6531438828,47.5926742554],"type":"Point"}
}