{
  "type": "Feature",
  "properties": {
    "iso:country":"CH",
    "sg:address":"Comprovasco",
    "sg:city":"Acquarossa",
    "sg:orig_category":"Allgemeiner Hoch U Tiefbau Hoch U Tiefbau",
    "sg:phone":"+41 91 871 12 59",
    "sg:postcode":"6716",
    "sg:province":"Ticino",
    "wof:name":"De Leoni Odis B.",
    "wof:placetype":"venue"
},
  "geometry": {"coordinates":[8.932168,46.454445],"type":"Point"}
}