{
  "type": "Feature",
  "properties": {
    "iso:country":"CH",
    "sg:address":"Hohliebeweg",
    "sg:city":"Adelboden",
    "sg:classifiers":[
        {
            "category":"Restaurant",
            "type":"Food & Drink"
        }
    ],
    "sg:phone":"+41 33 673 10 69",
    "sg:postcode":"3715",
    "sg:province":"Bern",
    "wof:name":"Hohliebe-st\u00fcbli Alkoholfreies Restaurant",
    "wof:placetype":"venue"
},
  "geometry": {"coordinates":[7.5739798546,46.4914855957],"type":"Point"}
}