{
  "type": "Feature",
  "properties": {
    "iso:country":"CH",
    "sg:address":"Platanes Les 1070 Puidoux. Postfach",
    "sg:city":"Puidoux",
    "sg:orig_category":"Dauerkulturbau",
    "sg:postcode":"1070",
    "sg:province":"Vaud",
    "wof:name":"Janine Champignons, Buchs & Pavid",
    "wof:placetype":"venue"
},
  "geometry": {"coordinates":[6.78276,46.502048],"type":"Point"}
}