{
  "type": "Feature",
  "properties": {
    "iso:country":"CH",
    "sg:address":"Blotzheimerstrasse 28",
    "sg:city":"Basel",
    "sg:orig_category":"Schl\u00fcsselservice",
    "sg:phone":"+41 61 301 22 11",
    "sg:postcode":"4055",
    "sg:province":"Basel-Stadt",
    "wof:name":"Eric Chabloz Schl\u00fcssel-service",
    "wof:placetype":"venue"
},
  "geometry": {"coordinates":[7.5658931732,47.5615272522],"type":"Point"}
}