{
  "type": "Feature",
  "properties": {
    "iso:country":"CH",
    "sg:address":"Rue De La Gare 7 1030 Bussigny-lausanne Case Postale 42",
    "sg:city":"Bussigny-lausanne",
    "sg:orig_category":"Architektur U Ingenieurb\u00fcros",
    "sg:phone":"+41 21 701 32 76",
    "sg:postcode":"1030",
    "sg:province":"Vaud",
    "wof:name":"Aquatec, Muller M. Ing\u00e9nieurs Civils Sa",
    "wof:placetype":"venue"
},
  "geometry": {"coordinates":[6.552704,46.548351],"type":"Point"}
}