{
  "type": "Feature",
  "properties": {
    "iso:country":"CH",
    "sg:address":"Romont Rue De 14",
    "sg:city":"Fribourg",
    "sg:orig_category":"Handels-H\u00e4user U Gesellschaften",
    "sg:postcode":"1700",
    "sg:province":"Fribourg",
    "wof:name":"Magnevie Sa",
    "wof:placetype":"venue"
},
  "geometry": {"coordinates":[7.1549191475,46.8045845032],"type":"Point"}
}