{
  "type": "Feature",
  "properties": {
    "iso:country":"CH",
    "sg:address":"Rue Du Simplon 33",
    "sg:city":"Lausanne",
    "sg:orig_category":"RESTAURANTS: TEA-ROOMS",
    "sg:phone":"+41 21 616 55 85",
    "sg:postcode":"1006",
    "sg:province":"Vaud",
    "wof:name":"Rollinet A. Caf\u00e9-restaurant De L'europe.",
    "wof:placetype":"venue"
},
  "geometry": {"coordinates":[6.6289601326,46.5160217285],"type":"Point"}
}