{
  "type": "Feature",
  "properties": {
    "iso:country":"CH",
    "sg:address":"Sch\u00fctzenstrasse 3",
    "sg:city":"Schwyz",
    "sg:orig_category":"Unclassifiable Establishments",
    "sg:postcode":"6430",
    "sg:province":"Schwyz",
    "wof:name":"Dres Med. Tr\u00fctsch & Gal Spezial\u00e4rztinnen Fmh",
    "wof:placetype":"venue"
},
  "geometry": {"coordinates":[8.6556825638,47.0195503235],"type":"Point"}
}