{
  "type": "Feature",
  "properties": {
    "iso:country":"CH",
    "sg:address":"Oberhofen I.e.",
    "sg:city":"Bowil",
    "sg:orig_category":"Sportvereine Unihockey",
    "sg:postcode":"3533",
    "sg:province":"Bern",
    "wof:name":"Uhc Brienz",
    "wof:placetype":"venue"
},
  "geometry": {"coordinates":[8.0579385757,46.7520484924],"type":"Point"}
}