{
  "type": "Feature",
  "properties": {
    "iso:country":"CH",
    "sg:address":"Lisano Via 3 6900 Massagno. Postfach",
    "sg:city":"Massagno",
    "sg:orig_category":"Markt U Meinungsforschung",
    "sg:phone":"+41 91 967 40 13",
    "sg:postcode":"6900",
    "sg:province":"Ticino",
    "wof:name":"Karren Marketing Sa",
    "wof:placetype":"venue"
},
  "geometry": {"coordinates":[8.9428453445,46.0092735291],"type":"Point"}
}