{
  "type": "Feature",
  "properties": {
    "iso:country":"CH",
    "sg:address":"Rue Beau-s\u00e9jour 29",
    "sg:city":"Lausanne",
    "sg:orig_category":"Psychotherapie",
    "sg:phone":"+41 21 340 70 10",
    "sg:postcode":"1003",
    "sg:province":"Vaud",
    "wof:name":"Cabinet Didisheim E. S\u00e0rl",
    "wof:placetype":"venue"
},
  "geometry": {"coordinates":[6.6376609802,46.5175514221],"type":"Point"}
}