{
  "type": "Feature",
  "properties": {
    "iso:country":"CH",
    "sg:address":"Zulgstrasse 63",
    "sg:city":"Steffisburg",
    "sg:orig_category":"Detailhandel mit elektrischen Haushalts-,Radio U Fernsehger\u00e4ten sowie Musikinstrumenten",
    "sg:phone":"+41 33 437 29 79",
    "sg:postcode":"3612",
    "sg:province":"Bern",
    "wof:name":"Haushaltapparate Schoch",
    "wof:placetype":"venue"
},
  "geometry": {"coordinates":[7.6263952255,46.7750053406],"type":"Point"}
}