{
  "type": "Feature",
  "properties": {
    "iso:country":"CH",
    "sg:address":"Waldmeisterstrasse 63 3018 Bern. Postfach",
    "sg:city":"Bern",
    "sg:orig_category":"Softwareentwicklung U beratung",
    "sg:phone":"+41 31 991 38 78",
    "sg:postcode":"3018",
    "sg:province":"Bern",
    "wof:name":"Alva Hugo, Infotronix Informatik, Elektronikdienstleistungen",
    "wof:placetype":"venue"
},
  "geometry": {"coordinates":[7.3832278252,46.9394111633],"type":"Point"}
}