{
  "type": "Feature",
  "properties": {
    "iso:country":"CH",
    "sg:address":"Emanuel B\u00fcchel-strasse 16",
    "sg:city":"Basel",
    "sg:orig_category":"Wohnheime f\u00fcr Kinder U Jugendliche",
    "sg:phone":"+41 61 311 56 66",
    "sg:postcode":"4052",
    "sg:province":"Basel-Stadt",
    "wof:name":"Kinderheim Auf Dem Gellert",
    "wof:placetype":"venue"
},
  "geometry": {"coordinates":[7.6130361557,47.5502166748],"type":"Point"}
}