{
  "type": "Feature",
  "properties": {
    "iso:country":"CH",
    "sg:address":"Corso San Gottardo 88",
    "sg:city":"Chiasso",
    "sg:orig_category":"Detailhandel mit B\u00fcchern Detailhandel mit B\u00fcchern, Zeitungen, Schreib U Papeteriewaren",
    "sg:phone":"+41 22 736 11 92",
    "sg:postcode":"6830",
    "sg:province":"Ticino",
    "wof:name":"Libraire Meyer Heino",
    "wof:placetype":"venue"
},
  "geometry": {"coordinates":[6.162353,46.205761],"type":"Point"}
}