{
  "type": "Feature",
  "properties": {
    "iso:country":"CH",
    "sg:address":"R\u00f6merstrasse 2",
    "sg:city":"Hunzenschwil",
    "sg:orig_category":"Herstellung von Metallerzeugnissen ohne Maschinenbau Herstellung von elektrischen Haushaltsger\u00e4ten",
    "sg:phone":"+41 62 889 42 01",
    "sg:postcode":"5502",
    "sg:province":"Aargau",
    "wof:name":"Cafina Ag",
    "wof:placetype":"venue"
},
  "geometry": {"coordinates":[8.1280107498,47.3903503418],"type":"Point"}
}