{
  "type": "Feature",
  "properties": {
    "iso:country":"CH",
    "sg:address":"Feldstrasse 12",
    "sg:city":"B\u00fclach",
    "sg:orig_category":"Softwareentwicklung U beratung",
    "sg:postcode":"8180",
    "sg:province":"Z\u00fcrich",
    "wof:name":"Hard Und Softwarevertrieb Hp. Menzi",
    "wof:placetype":"venue"
},
  "geometry": {"coordinates":[8.532623291,47.5143203735],"type":"Point"}
}