{
  "type": "Feature",
  "properties": {
    "iso:country":"CH",
    "sg:address":"Chemin Frisco 13",
    "sg:city":"Gen\u00e8ve",
    "sg:classifiers":[
        {
            "category":"Restaurant",
            "type":"Food & Drink"
        }
    ],
    "sg:phone":"+41 22 700 53 90",
    "sg:postcode":"1208",
    "sg:province":"Gen\u00e8ve",
    "wof:name":"Caf\u00e9-restaurant Les Tulipiers",
    "wof:placetype":"venue"
},
  "geometry": {"coordinates":[6.1753878593,46.2013397217],"type":"Point"}
}