{
  "type": "Feature",
  "properties": {
    "addr:full":"75-77 Avenue Louis-casa\u00ef Cointrin Cointrin Gen\u00e8ve 1216",
    "addr:housenumber":"75-77",
    "addr:postcode":"1216",
    "addr:street":"Avenue Louis-Casai\u0308",
    "iso:country":"CH",
    "sg:address":"75-77 Avenue Louis-casa\u00ef Cointrin",
    "sg:city":"Cointrin",
    "sg:classifiers":[
        {
            "category":"Travel",
            "subcategory":"Hotels & Motels",
            "type":"Entertainment"
        }
    ],
    "sg:phone":"+41 22 710 30 00",
    "sg:postcode":"1216",
    "sg:province":"Gen\u00e8ve",
    "sg:tags":[
        "hotels",
        "business",
        "restaurant"
    ],
    "wof:name":"Ramada Park Hotel",
    "wof:placetype":"venue"
},
  "geometry": {"coordinates":[6.107143,46.22496],"type":"Point"}
}