{
  "type": "Feature",
  "properties": {
    "iso:country":"CH",
    "sg:address":"Obergrundstrasse 28",
    "sg:city":"Luzern",
    "sg:orig_category":"Dachdeckerei",
    "sg:phone":"+41 79 445 04 06",
    "sg:postcode":"6003",
    "sg:province":"Luzern",
    "wof:name":"Daniel Rossel Bedachungen",
    "wof:placetype":"venue"
},
  "geometry": {"coordinates":[7.867384,46.682938],"type":"Point"}
}