{
  "type": "Feature",
  "properties": {
    "iso:country":"CH",
    "sg:address":"Balterswiler Strasse 10 8360 Wallenwil. Postfach",
    "sg:city":"Wallenwil",
    "sg:orig_category":"Detailhandel mit Schuhen Reparatur von Schuhen U Lederwaren",
    "sg:phone":"+41 71 971 21 66",
    "sg:postcode":"8360",
    "sg:province":"Thurgau",
    "wof:name":"Rolf Adam Orthop\u00e4die-schuhmacher",
    "wof:placetype":"venue"
},
  "geometry": {"coordinates":[8.9543123245,47.4549179077],"type":"Point"}
}