{
  "type": "Feature",
  "properties": {
    "iso:country":"CH",
    "sg:address":"G\u00fctschrain",
    "sg:city":"Willisau",
    "sg:orig_category":"Architekturb\u00fcros",
    "sg:phone":"+41 21 791 33 11",
    "sg:postcode":"6130",
    "sg:province":"Luzern",
    "wof:name":"Rudolf Bernhard Bureau D'architecture",
    "wof:placetype":"venue"
},
  "geometry": {"coordinates":[6.75005,46.50248],"type":"Point"}
}