{
  "type": "Feature",
  "properties": {
    "iso:country":"CH",
    "sg:address":"Laubisr\u00fctistrasse 77",
    "sg:city":"Uerikon",
    "sg:orig_category":"Grosshandel mit sonstigen Maschinen U Ausr\u00fcstungen f\u00fcr Industrie, Handel U Schiffahrt Handelsvermitt",
    "sg:phone":"+41 19267124",
    "sg:postcode":"8713",
    "sg:province":"Z\u00fcrich",
    "wof:name":"Relstatic Ag",
    "wof:placetype":"venue"
},
  "geometry": {"coordinates":[8.758769989,47.2344284058],"type":"Point"}
}