{
  "type": "Feature",
  "properties": {
    "iso:country":"CH",
    "sg:address":"Hauptstrasse 51",
    "sg:city":"L\u00e4ufelfingen",
    "sg:orig_category":"Bauschreinerei Erbringung von Dienstleistungen f\u00fcr Unternehmen",
    "sg:phone":"+41 62 299 11 64",
    "sg:postcode":"4448",
    "sg:province":"Basel-Landschaft",
    "wof:name":"Stalder R.",
    "wof:placetype":"venue"
},
  "geometry": {"coordinates":[7.860833,47.392532],"type":"Point"}
}