{
  "type": "Feature",
  "properties": {
    "iso:country":"CH",
    "sg:address":"Oberneuhofstrasse 8",
    "sg:city":"Baar",
    "sg:classifiers":[
        {
            "category":"Restaurant",
            "type":"Food & Drink"
        }
    ],
    "sg:phone":"+41 41 761 81 25",
    "sg:postcode":"6340",
    "sg:province":"Zug",
    "wof:name":"Restaurant Neuhof",
    "wof:placetype":"venue"
},
  "geometry": {"coordinates":[8.5162916183,47.1882781982],"type":"Point"}
}