{
  "type": "Feature",
  "properties": {
    "iso:country":"CH",
    "sg:address":"In Der Luberzen 34",
    "sg:city":"Urdorf",
    "sg:orig_category":"Maturit\u00e4tsschulen, Lehrerseminarien",
    "sg:phone":"+41 17353190",
    "sg:postcode":"8902",
    "sg:province":"Z\u00fcrich",
    "wof:name":"Kantonsschule Limmattal",
    "wof:placetype":"venue"
},
  "geometry": {"coordinates":[8.4235839844,47.3934516907],"type":"Point"}
}