{
  "type": "Feature",
  "properties": {
    "iso:country":"CH",
    "sg:address":"Rue Principale 33",
    "sg:city":"Villeret",
    "sg:orig_category":"G\u00fcterbef\u00f6rderung im Strassenverkehr",
    "sg:phone":"+41 32 941 29 71",
    "sg:postcode":"2613",
    "sg:province":"Bern",
    "wof:name":"Raymond Boillet Transports & Camionnage Off.",
    "wof:placetype":"venue"
},
  "geometry": {"coordinates":[7.0167460442,47.1561660767],"type":"Point"}
}