{
  "type": "Feature",
  "properties": {
    "iso:country":"CH",
    "sg:address":"Zone Industrielle Le Grand-pr\u00e9",
    "sg:city":"Moudon",
    "sg:orig_category":"Einzelhandel mit Automobilteilen U Zubeh\u00f6r Herstellung von Bereifungen",
    "sg:phone":"+41 21 905 34 77",
    "sg:postcode":"1510",
    "sg:province":"Vaud",
    "wof:name":"Pneus-service De La Palaz Sa, Succursale De Moudon",
    "wof:placetype":"venue"
},
  "geometry": {"coordinates":[6.8003668785,46.6674957275],"type":"Point"}
}