{
  "type": "Feature",
  "properties": {
    "iso:country":"CH",
    "sg:address":"Plan-conthey",
    "sg:city":"Conthey",
    "sg:orig_category":"RESTAURANTS: TEA-ROOMS",
    "sg:phone":"+41 27 346 18 94",
    "sg:postcode":"1964",
    "sg:province":"Valais",
    "wof:name":"Udry Chantal",
    "wof:placetype":"venue"
},
  "geometry": {"coordinates":[7.3089599609,46.2315216064],"type":"Point"}
}