{
  "type": "Feature",
  "properties": {
    "addr:full":"Rue Des Pr\u00e9s-du-lac 30 Yverdon-les-bains Vaud 1400",
    "addr:housenumber":"30",
    "addr:postcode":"1400",
    "addr:street":"Rue Des Pre\u0301S-Du-Lac",
    "iso:country":"CH",
    "sg:address":"Rue Des Pr\u00e9s-du-lac 30",
    "sg:city":"Yverdon-les-bains",
    "sg:orig_category":"Allgemeiner Hoch U Tiefbau",
    "sg:postcode":"1400",
    "sg:province":"Vaud",
    "wof:name":"Perroud Travaux Sa, Succursale De Renens",
    "wof:placetype":"venue"
},
  "geometry": {"coordinates":[6.586171,46.544666],"type":"Point"}
}