{
  "type": "Feature",
  "properties": {
    "iso:country":"CH",
    "sg:address":"Technikumstrasse 60",
    "sg:city":"Winterthur",
    "sg:classifiers":[
        {
            "category":"Restaurant",
            "type":"Food & Drink"
        }
    ],
    "sg:phone":"+41 52 212 07 71",
    "sg:postcode":"8400",
    "sg:province":"Z\u00fcrich",
    "wof:name":"Altstadtchuchi Hot Pot",
    "wof:placetype":"venue"
},
  "geometry": {"coordinates":[8.7275323868,47.4978523254],"type":"Point"}
}