{
  "type": "Feature",
  "properties": {
    "iso:country":"CH",
    "sg:address":"Vie Des Cr\u00eates",
    "sg:city":"Reconvilier",
    "sg:orig_category":"Non-Classified Establishments",
    "sg:postcode":"2732",
    "sg:province":"Bern",
    "wof:name":"Jmc Constructions M\u00e9talliques S.a.",
    "wof:placetype":"venue"
},
  "geometry": {"coordinates":[7.2227230072,47.233707428],"type":"Point"}
}