{
  "type": "Feature",
  "properties": {
    "iso:country":"CH",
    "sg:address":"Route De Suisse 94",
    "sg:city":"Versoix",
    "sg:orig_category":"Grosshandel mit Getreide, Saatgut U Futtermitteln",
    "sg:phone":"+41 26 673 21 50",
    "sg:postcode":"1290",
    "sg:province":"Gen\u00e8ve",
    "wof:name":"Vistico Ag",
    "wof:placetype":"venue"
},
  "geometry": {"coordinates":[7.0847039223,46.9489021301],"type":"Point"}
}