{
  "type": "Feature",
  "properties": {
    "iso:country":"CH",
    "sg:address":"Cit\u00e9-ouest Route De 19",
    "sg:city":"Gland",
    "sg:orig_category":"Herstellung von medizinischen U chirurgischen Ger\u00e4ten sowie orthop\u00e4dischen Vorrichtungen",
    "sg:postcode":"1196",
    "sg:province":"Vaud",
    "wof:name":"Meditron Sa",
    "wof:placetype":"venue"
},
  "geometry": {"coordinates":[6.2614498138,46.4224014282],"type":"Point"}
}