{
  "type": "Feature",
  "properties": {
    "iso:country":"CH",
    "sg:address":"Marktgasse 9 9220 Bischofszell. Postfach 52",
    "sg:city":"Bischofszell",
    "sg:orig_category":"Advokaturb\u00fcros",
    "sg:phone":"+41 71 420 01 15",
    "sg:postcode":"9220",
    "sg:province":"Thurgau",
    "wof:name":"August Biedermann Advokaturb\u00fcro",
    "wof:placetype":"venue"
},
  "geometry": {"coordinates":[9.239864,47.49395],"type":"Point"}
}