{
  "type": "Feature",
  "properties": {
    "iso:country":"CH",
    "sg:address":"Waffenplatzstrasse 34",
    "sg:city":"Z\u00fcrich",
    "sg:orig_category":"Malerei",
    "sg:phone":"+41 12025770",
    "sg:postcode":"8002",
    "sg:province":"Z\u00fcrich",
    "wof:name":"Prospero Vaccaro Malergesch\u00e4ft",
    "wof:placetype":"venue"
},
  "geometry": {"coordinates":[8.5265989304,47.3599472046],"type":"Point"}
}