{
  "type": "Feature",
  "properties": {
    "addr:full":"Bahnhofstr. 11 Pratteln Basel-Landschaft 4133",
    "addr:housenumber":"11",
    "addr:postcode":"4133",
    "addr:street":"Bahnhofstr.",
    "iso:country":"CH",
    "sg:address":"Bahnhofstr. 11",
    "sg:city":"Pratteln",
    "sg:classifiers":[
        {
            "category":"Banks & Credit Unions",
            "subcategory":"Bank",
            "type":"Services"
        }
    ],
    "sg:phone":"+41 61 826 15 15",
    "sg:postcode":"4133",
    "sg:province":"Basel-Landschaft",
    "wof:name":"Credit Suisse",
    "wof:placetype":"venue"
},
  "geometry": {"coordinates":[7.692034,47.521328],"type":"Point"}
}