{
  "type": "Feature",
  "properties": {
    "addr:full":"Ch. De La Californie 35 1245 Collonge-bellerive. Postfach V\u00e9senaz Gen\u00e8ve 1222",
    "addr:housenumber":"35",
    "addr:postcode":"1245 collonge-bellerive. postfach ve\u0301senaz;1222",
    "addr:street":"Ch. De La Californie",
    "iso:country":"CH",
    "sg:address":"Ch. De La Californie 35 1245 Collonge-bellerive. Postfach",
    "sg:city":"V\u00e9senaz",
    "sg:orig_category":"Allgemeiner Hoch U Tiefbau",
    "sg:phone":"+41 22 751 14 63",
    "sg:postcode":"1222",
    "sg:province":"Gen\u00e8ve",
    "wof:name":"Bonnet Christian",
    "wof:placetype":"venue"
},
  "geometry": {"coordinates":[6.20649,46.242577],"type":"Point"}
}