{
  "type": "Feature",
  "properties": {
    "addr:full":"St. Gallerstrasse 161 8645 Jona. Postfach Jona St. Gallen 8645",
    "addr:housenumber":"161",
    "addr:postcode":"8645;8645",
    "addr:street":"St. Gallerstrasse",
    "iso:country":"CH",
    "sg:address":"St. Gallerstrasse 161 8645 Jona. Postfach",
    "sg:city":"Jona",
    "sg:orig_category":"Buchf\u00fchrung Wirtschaftspr\u00fcfung, Steuerberatung U Treuhand",
    "sg:phone":"+41 55 212 63 60",
    "sg:postcode":"8645",
    "sg:province":"St. Gallen",
    "wof:name":"Bs-dynamic Ag Dienstleistungsgesellschaft Im Ber. Der Buchhaltung, Revision, Administration Usw.",
    "wof:placetype":"venue"
},
  "geometry": {"coordinates":[8.851541,47.230484],"type":"Point"}
}