{
  "type": "Feature",
  "properties": {
    "iso:country":"CH",
    "sg:address":"Promenadenstrasse 13",
    "sg:city":"Rorschach",
    "sg:orig_category":"Herstellung von Radio U Fernsehger\u00e4ten sowie phono U videotechnischen Ger\u00e4ten",
    "sg:postcode":"9400",
    "sg:province":"St. Gallen",
    "wof:name":"Bumann Kassian Unterhaltungselektronik; Verkauf, Reparatur, Installation Usw",
    "wof:placetype":"venue"
},
  "geometry": {"coordinates":[7.926926136,46.108795166],"type":"Point"}
}