{
  "type": "Feature",
  "properties": {
    "iso:country":"CH",
    "sg:address":"Chamerstrasse 41",
    "sg:city":"Zug",
    "sg:classifiers":[
        {
            "category":"Restaurant",
            "type":"Food & Drink"
        }
    ],
    "sg:phone":"+41 41 710 53 83",
    "sg:postcode":"6300",
    "sg:province":"Zug",
    "wof:name":"Jugendbeiz Chaotikum",
    "wof:placetype":"venue"
},
  "geometry": {"coordinates":[8.506893158,47.1731758118],"type":"Point"}
}