{
  "type": "Feature",
  "properties": {
    "iso:country":"CH",
    "sg:address":"6927",
    "sg:city":"Agra",
    "sg:orig_category":"Malerei",
    "sg:phone":"+41 91 994 80 45",
    "sg:postcode":"6927",
    "sg:province":"Ticino",
    "wof:name":"Enrico Del Fante Impresa Di Pittura",
    "wof:placetype":"venue"
},
  "geometry": {"coordinates":[8.9113197327,45.968208313],"type":"Point"}
}