{
  "type": "Feature",
  "properties": {
    "iso:country":"CH",
    "sg:address":"Bahnhofstrasse 76",
    "sg:city":"M\u00f6hlin",
    "sg:orig_category":"Physiotherapie",
    "sg:phone":"+41 61 851 00 41",
    "sg:postcode":"4313",
    "sg:province":"Aargau",
    "wof:name":"Alma Fouradoulas Physiotherapie",
    "wof:placetype":"venue"
},
  "geometry": {"coordinates":[7.8441948891,47.5566864014],"type":"Point"}
}