{
  "type": "Feature",
  "properties": {
    "iso:country":"CH",
    "sg:address":"Dorf",
    "sg:city":"Wildhaus",
    "sg:orig_category":"Religi\u00f6se Vereinigungen divers Vereine Gemeinn\u00fctzige",
    "sg:postcode":"9658",
    "sg:province":"St. Gallen",
    "wof:name":"Evangelischer Frauenverein",
    "wof:placetype":"venue"
},
  "geometry": {"coordinates":[9.351433754,47.2034492493],"type":"Point"}
}