{
  "type": "Feature",
  "properties": {
    "iso:country":"CH",
    "sg:address":"Steinenvorstadt 63 4051 Basel. Postfach",
    "sg:city":"Basel",
    "sg:orig_category":"Berufsbildende weiterf\u00fchrende Schulen Hochschulen U h\u00f6here Ausbildung",
    "sg:phone":"+41 61 271 16 16",
    "sg:postcode":"4051",
    "sg:province":"Basel-Stadt",
    "wof:name":"Stift + Co. Hairstylers Gmbh Aus- U. Weiterbildung Von Lehrlingen U. Jungcoiffeuren Usw",
    "wof:placetype":"venue"
},
  "geometry": {"coordinates":[7.588369,47.552261],"type":"Point"}
}