{
  "type": "Feature",
  "properties": {
    "iso:country":"CH",
    "sg:address":"Fr\u00f6schmattstrasse 20 3018 Bern. Postfach",
    "sg:city":"Bern",
    "sg:orig_category":"Sanit\u00e4r, Heizungs U L\u00fcftungsinstallation",
    "sg:phone":"+41 81 854 05 14",
    "sg:postcode":"3018",
    "sg:province":"Bern",
    "wof:name":"Steger Sanit\u00e4r",
    "wof:placetype":"venue"
},
  "geometry": {"coordinates":[9.9318580627,46.5749511719],"type":"Point"}
}