{
  "type": "Feature",
  "properties": {
    "iso:country":"CH",
    "sg:address":"Hauptstrasse 31 4414 F\u00fcllinsdorf. Postfach",
    "sg:city":"F\u00fcllinsdorf",
    "sg:orig_category":"Grosshandel mit Obst U Gem\u00fcse",
    "sg:phone":"+41 81 410 11 33",
    "sg:postcode":"4414",
    "sg:province":"Basel-Landschaft",
    "wof:name":"Fr\u00fcchte Waser",
    "wof:placetype":"venue"
},
  "geometry": {"coordinates":[9.8362779617,46.8012771606],"type":"Point"}
}