{
  "type": "Feature",
  "properties": {
    "iso:country":"CH",
    "sg:address":"Baarerstrasse 110a 6300 Zug. Postfach 2648",
    "sg:city":"Zug",
    "sg:orig_category":"Fernmeldedienste Grosshandel mit Radio U Fernsehger\u00e4ten",
    "sg:phone":"+41 22 705 11 11",
    "sg:postcode":"6302",
    "sg:province":"Zug",
    "wof:name":"Coditel S\u00e0rl",
    "wof:placetype":"venue"
},
  "geometry": {"coordinates":[6.1367020607,46.1973495483],"type":"Point"}
}