{
  "type": "Feature",
  "properties": {
    "iso:country":"CH",
    "sg:address":"Epinassey Route D'",
    "sg:city":"St-maurice",
    "sg:orig_category":"Herstellung von konfektionierten Textilwaren ohne Bekleidung",
    "sg:phone":"+41 24 485 26 11",
    "sg:postcode":"1890",
    "sg:province":"Valais",
    "wof:name":"Frossard R.",
    "wof:placetype":"venue"
},
  "geometry": {"coordinates":[7.0088157654,46.1924819946],"type":"Point"}
}