{
  "type": "Feature",
  "properties": {
    "iso:country":"CH",
    "sg:address":"8542",
    "sg:city":"Wiesendangen",
    "sg:orig_category":"Organisationen des Gesundheitswesen",
    "sg:phone":"+41 71 633 18 52",
    "sg:postcode":"8542",
    "sg:province":"Z\u00fcrich",
    "wof:name":"Samariterverein",
    "wof:placetype":"venue"
},
  "geometry": {"coordinates":[9.1522397995,47.5501708984],"type":"Point"}
}