{
  "type": "Feature",
  "properties": {
    "addr:full":"Poststrasse 21 Amriswil Thurgau 8580",
    "addr:housenumber":"21",
    "addr:postcode":"8580",
    "addr:street":"Poststrasse",
    "iso:country":"CH",
    "sg:address":"Poststrasse 21",
    "sg:city":"Amriswil",
    "sg:orig_category":"Bauschreinerei Hobel U Holzimpr\u00e4gnierwerke",
    "sg:phone":"+41 71 411 30 08",
    "sg:postcode":"8580",
    "sg:province":"Thurgau",
    "wof:name":"Leopold Vovk M\u00f6belbeizerei Restaurierungen",
    "wof:placetype":"venue"
},
  "geometry": {"coordinates":[9.30035,47.550381],"type":"Point"}
}