{
  "type": "Feature",
  "properties": {
    "iso:country":"CH",
    "sg:address":"Untermattstrasse 28",
    "sg:city":"Horw",
    "sg:orig_category":"Grosshandel mit sonstigen Maschinen U Ausr\u00fcstungen f\u00fcr Industrie, Handel U Schiffahrt",
    "sg:phone":"+41 41 340 50 00",
    "sg:postcode":"6048",
    "sg:province":"Luzern",
    "wof:name":"Reitec Gmbh",
    "wof:placetype":"venue"
},
  "geometry": {"coordinates":[8.3146734238,47.0213012695],"type":"Point"}
}