{
  "type": "Feature",
  "properties": {
    "iso:country":"CH",
    "sg:address":"Dorfstrasse 534",
    "sg:city":"Uhwiesen",
    "sg:orig_category":"Herstellung von nachrichtentechnischen Ger\u00e4ten U Einrichtungen",
    "sg:postcode":"8248",
    "sg:province":"Z\u00fcrich",
    "wof:name":"Rapold Paul",
    "wof:placetype":"venue"
},
  "geometry": {"coordinates":[8.6271076202,47.6730003357],"type":"Point"}
}