{
  "type": "Feature",
  "properties": {
    "iso:country":"CH",
    "sg:address":"Hagenbuchenstrasse 22",
    "sg:city":"Bassersdorf",
    "sg:orig_category":"Grosshandel mit B\u00fcromaschinen Grosshandel mit Datenverarbeitungsger\u00e4ten",
    "sg:phone":"+41 18886464",
    "sg:postcode":"8303",
    "sg:province":"Z\u00fcrich",
    "wof:name":"M & M B\u00fcroautomation Ag",
    "wof:placetype":"venue"
},
  "geometry": {"coordinates":[8.6212482452,47.4476966858],"type":"Point"}
}