{
  "type": "Feature",
  "properties": {
    "iso:country":"CH",
    "sg:address":"Place De La Gare 7",
    "sg:city":"Rolle",
    "sg:classifiers":[
        {
            "category":"Wholesale",
            "subcategory":"Petroleum",
            "type":"Manufacturing & Wholesale Goods"
        }
    ],
    "sg:phone":"+41 21 822 02 02",
    "sg:postcode":"1180",
    "sg:province":"Vaud",
    "sg:tags":[
        "swiss",
        "wine"
    ],
    "wof:name":"Schenk S.a.",
    "wof:placetype":"venue"
},
  "geometry": {"coordinates":[6.336977005,46.4633140564],"type":"Point"}
}