{
  "type": "Feature",
  "properties": {
    "addr:full":"Chli Ratihard 8253 Willisdorf. Postfach Diessenhofen Thurgau 8253",
    "addr:postcode":"8253 willisdorf. postfach;8253",
    "addr:street":"Ratihard",
    "iso:country":"CH",
    "sg:address":"Chli Ratihard 8253 Willisdorf. Postfach",
    "sg:city":"Diessenhofen",
    "sg:orig_category":"Boots U Yachtbau Fachdetailhandel in Verkaufsr\u00e4umen",
    "sg:phone":"+41 41 671 01 77",
    "sg:postcode":"8253",
    "sg:province":"Thurgau",
    "wof:name":"Marine Service Halter",
    "wof:placetype":"venue"
},
  "geometry": {"coordinates":[8.276051,46.938446],"type":"Point"}
}