{
  "type": "Feature",
  "properties": {
    "iso:country":"CH",
    "sg:address":"Bruchstrasse 26",
    "sg:city":"Luzern",
    "sg:orig_category":"Grosshandel mit sonstigen Nahrungsmitteln",
    "sg:phone":"+41 62 822 22 12",
    "sg:postcode":"6003",
    "sg:province":"Luzern",
    "wof:name":"Hirt Salmon House, Lachsr\u00e4ucherei - Frischfisch Gmbh",
    "wof:placetype":"venue"
},
  "geometry": {"coordinates":[8.0669851303,47.3902206421],"type":"Point"}
}