{
  "type": "Feature",
  "properties": {
    "iso:country":"CH",
    "sg:address":"Rabengasse 7",
    "sg:city":"Chur",
    "sg:orig_category":"Arztpraxen",
    "sg:phone":"+41 81 253 34 35",
    "sg:postcode":"7000",
    "sg:province":"Graubunden",
    "wof:name":"Dr.med.fritz Hasler Spezialarzt Fmh",
    "wof:placetype":"venue"
},
  "geometry": {"coordinates":[9.532788,46.848618],"type":"Point"}
}