{
  "type": "Feature",
  "properties": {
    "iso:country":"CH",
    "sg:address":"St. Gallerstr. 1 Am B\u00e4renplat 9230 Flawil. Postfach",
    "sg:city":"Flawil",
    "sg:orig_category":"Detailhandel mit Bekleidung",
    "sg:postcode":"9230",
    "sg:province":"St. Gallen",
    "wof:name":"Huldis Mode-lade H. Holderegger.",
    "wof:placetype":"venue"
},
  "geometry": {"coordinates":[9.188875,47.414837],"type":"Point"}
}