{
  "type": "Feature",
  "properties": {
    "iso:country":"CH",
    "sg:address":"Chemin De Curtinaux 14 1095 Ch\u00e2telard-lutry Case Postale 228",
    "sg:city":"Ch\u00e2telard-lutry",
    "sg:orig_category":"Alters U Pflegeheime Vermietung U Verpachtung von eigenen Immobilien",
    "sg:phone":"+41 21 791 10 41",
    "sg:postcode":"1095",
    "sg:province":"Vaud",
    "wof:name":"Ch\u00e2teau De La Rive Sa",
    "wof:placetype":"venue"
},
  "geometry": {"coordinates":[6.691171,46.501793],"type":"Point"}
}