{
  "type": "Feature",
  "properties": {
    "iso:country":"CH",
    "sg:address":"Ch\u00e2teau",
    "sg:city":"Monnaz",
    "sg:orig_category":"Detailhandel mit Metallwaren, Anstrichmitteln, Glaswaren, Bau U Heimwerkerbedarf Handelsvermittlung ",
    "sg:phone":"+41 21 802 32 64",
    "sg:postcode":"1125",
    "sg:province":"Vaud",
    "wof:name":"Rabuffo Distribution Sa",
    "wof:placetype":"venue"
},
  "geometry": {"coordinates":[6.4783101082,46.5312805176],"type":"Point"}
}