{
  "type": "Feature",
  "properties": {
    "iso:country":"CH",
    "sg:address":"Im L\u00f6hr 9",
    "sg:city":"Diepflingen",
    "sg:orig_category":"Handels-H\u00e4user U Gesellschaften",
    "sg:phone":"+41 61 971 50 55",
    "sg:postcode":"4442",
    "sg:province":"Basel-Landschaft",
    "wof:name":"Hans Mohler Farbspritzwerk",
    "wof:placetype":"venue"
},
  "geometry": {"coordinates":[7.8390231133,47.4439315796],"type":"Point"}
}