{
  "type": "Feature",
  "properties": {
    "iso:country":"CH",
    "sg:address":"St-jean Rue 22",
    "sg:city":"Nyon",
    "sg:orig_category":"Non-Classified Establishments",
    "sg:postcode":"1260",
    "sg:province":"Vaud",
    "wof:name":"Vitotel S\u00e0rl",
    "wof:placetype":"venue"
},
  "geometry": {"coordinates":[6.2400679588,46.3835258484],"type":"Point"}
}