{
  "type": "Feature",
  "properties": {
    "iso:country":"CH",
    "sg:address":"Altgasse 82",
    "sg:city":"Baar",
    "sg:classifiers":[
        {
            "category":"Communications",
            "subcategory":"Film & Video Production",
            "type":"Services"
        }
    ],
    "sg:phone":"+41 22 344 60 30",
    "sg:postcode":"6340",
    "sg:province":"Zug",
    "sg:tags":[
        "videofilmherstellung",
        "u"
    ],
    "wof:name":"Hermann Wetter Production De Films",
    "wof:placetype":"venue"
},
  "geometry": {"coordinates":[6.1374897957,46.2063713074],"type":"Point"}
}