{
  "type": "Feature",
  "properties": {
    "iso:country":"CH",
    "sg:address":"Dorf 1",
    "sg:city":"St-ours",
    "sg:orig_category":"Allgemeiner Hoch U Tiefbau Strassenbau",
    "sg:phone":"+41 26 494 27 12",
    "sg:postcode":"1717",
    "sg:province":"Fribourg",
    "wof:name":"Fribag Tief- & Strassenbau Ag",
    "wof:placetype":"venue"
},
  "geometry": {"coordinates":[7.217808,46.790848],"type":"Point"}
}