{
  "type": "Feature",
  "properties": {
    "iso:country":"CH",
    "sg:address":"Karmaad 9473 Gams. Postfach",
    "sg:city":"Gams",
    "sg:orig_category":"Grosshandel mit Nahrungsmitteln, Getr\u00e4nken U Tabakwaren ohne ausgepr\u00e4gten Schwerpunkt",
    "sg:postcode":"9473",
    "sg:province":"St. Gallen",
    "wof:name":"Pilzhandel Klag Lebensmittel, Bes. Fr\u00fcchte, Gem\u00fcse U. Pilze; Handel, Vertrieb Usw",
    "wof:placetype":"venue"
},
  "geometry": {"coordinates":[9.4550199509,47.2044906616],"type":"Point"}
}