{
  "type": "Feature",
  "properties": {
    "iso:country":"CH",
    "sg:address":"Gartenstrasse 3",
    "sg:city":"Egnach",
    "sg:orig_category":"Elektrizit\u00e4tsversorgung",
    "sg:phone":"+41 71 477 16 07",
    "sg:postcode":"9322",
    "sg:province":"Thurgau",
    "wof:name":"Elektra Egnach",
    "wof:placetype":"venue"
},
  "geometry": {"coordinates":[9.3827571869,47.5425262451],"type":"Point"}
}