{
  "type": "Feature",
  "properties": {
    "iso:country":"CH",
    "sg:address":"Hauptstrasse 32",
    "sg:city":"Birwinken",
    "sg:classifiers":[
        {
            "category":"Restaurant",
            "type":"Food & Drink"
        }
    ],
    "sg:phone":"+41 71 648 11 73",
    "sg:postcode":"8585",
    "sg:province":"Thurgau",
    "wof:name":"Restaurant Sonne",
    "wof:placetype":"venue"
},
  "geometry": {"coordinates":[9.1968746185,47.5825958252],"type":"Point"}
}