{
  "type": "Feature",
  "properties": {
    "iso:country":"CH",
    "sg:address":"Schachenallee 29",
    "sg:city":"Aarau",
    "sg:orig_category":"Markt U Meinungsforschung",
    "sg:phone":"+41 21 943 55 43",
    "sg:postcode":"5000",
    "sg:province":"Aargau",
    "wof:name":"Fischer Consulting",
    "wof:placetype":"venue"
},
  "geometry": {"coordinates":[6.8796749115,46.4768257141],"type":"Point"}
}