{
  "type": "Feature",
  "properties": {
    "iso:country":"CH",
    "sg:address":"Hotel Adler",
    "sg:city":"Kandersteg",
    "sg:orig_category":"Sportvereine Eissport Curling",
    "sg:phone":"+41 33 675 81 81",
    "sg:postcode":"3718",
    "sg:province":"Bern",
    "wof:name":"Curling Club Kandersteg",
    "wof:placetype":"venue"
},
  "geometry": {"coordinates":[7.6730470657,46.4949836731],"type":"Point"}
}