{
  "type": "Feature",
  "properties": {
    "iso:country":"CH",
    "sg:address":"Chemin Du Tunnel 2 2740 Montagne-moutier Case Postale 256",
    "sg:city":"Montagne-moutier",
    "sg:orig_category":"Herstellung von Werkzeugen Mechanische Werkst\u00e4tten",
    "sg:phone":"+41 32 493 11 52",
    "sg:postcode":"2740",
    "sg:province":"Bern",
    "wof:name":"Walter D\u00fcnner Sa",
    "wof:placetype":"venue"
},
  "geometry": {"coordinates":[7.3719911575,47.2767333984],"type":"Point"}
}