{
  "type": "Feature",
  "properties": {
    "iso:country":"CH",
    "sg:address":"Ehrendingerstrasse 3",
    "sg:city":"Ennetbaden",
    "sg:orig_category":"Non-Classified Establishments",
    "sg:phone":"+41 56 427 20 88",
    "sg:postcode":"5408",
    "sg:province":"Aargau",
    "wof:name":"Doris Reich Haenni Gesundheitspraxis Sunnehuet",
    "wof:placetype":"venue"
},
  "geometry": {"coordinates":[8.3120079041,47.4747962952],"type":"Point"}
}