{
  "type": "Feature",
  "properties": {
    "iso:country":"CH",
    "sg:address":"Riehenring 175 4058 Basel. Postfach",
    "sg:city":"Basel",
    "sg:orig_category":"Verlagsgewerbe Zeitschriftenverlag",
    "sg:phone":"+41 61 690 77 77",
    "sg:postcode":"4021",
    "wof:name":"Regio Zeitschriften Gmbh",
    "wof:placetype":"venue"
},
  "geometry": {"coordinates":[7.5973858833,47.569316864],"type":"Point"}
}