{
  "type": "Feature",
  "properties": {
    "iso:country":"CH",
    "sg:address":"Gartenstrasse 6",
    "sg:city":"Thalwil",
    "sg:orig_category":"Innenarchitekturb\u00fcros",
    "sg:phone":"+41 17207351",
    "sg:postcode":"8800",
    "sg:province":"Z\u00fcrich",
    "wof:name":"Walter M\u00fcller Innenarchitektur",
    "wof:placetype":"venue"
},
  "geometry": {"coordinates":[8.5648727417,47.2893257141],"type":"Point"}
}