{
  "type": "Feature",
  "properties": {
    "iso:country":"CH",
    "sg:address":"Schwerzistrasse 6 8807 Freienbach. Postfach",
    "sg:city":"Freienbach",
    "sg:orig_category":"Personal U Stellenvermittlung Unternehmensberatung",
    "sg:phone":"+41 17254748",
    "sg:postcode":"8807",
    "sg:province":"Schwyz",
    "wof:name":"Ebe Consult Ag",
    "wof:placetype":"venue"
},
  "geometry": {"coordinates":[8.6020059586,47.2587471008],"type":"Point"}
}