{
  "type": "Feature",
  "properties": {
    "iso:country":"CH",
    "sg:address":"San Bastiaun 17",
    "sg:city":"Samedan",
    "sg:classifiers":[
        {
            "category":"Travel",
            "subcategory":"Hotels & Motels",
            "type":"Entertainment"
        }
    ],
    "sg:phone":"+41 81 852 52 47",
    "sg:postcode":"7503",
    "sg:province":"Graubunden",
    "sg:tags":[
        "hotels",
        "mit",
        "restaurant"
    ],
    "wof:name":"Hotel Central",
    "wof:placetype":"venue"
},
  "geometry": {"coordinates":[9.8694190979,46.5329818726],"type":"Point"}
}