{
  "type": "Feature",
  "properties": {
    "iso:country":"CH",
    "sg:address":"8750 Glarus. Postfach 533",
    "sg:city":"Glarus",
    "sg:orig_category":"Alters U Hinterlassenenversicherung AHV, Invalidenversicherung IV, Arbeitslosenversicherung ALV",
    "sg:phone":"+41 41 228 51 11",
    "sg:postcode":"8750",
    "sg:province":"Glarus",
    "wof:name":"Arbeitslosenkasse Des Kantons Luzern",
    "wof:placetype":"venue"
},
  "geometry": {"coordinates":[8.303141,47.048424],"type":"Point"}
}