{
  "type": "Feature",
  "properties": {
    "iso:country":"CH",
    "sg:address":"Hallwilerweg 16",
    "sg:city":"Luzern",
    "sg:orig_category":"Kosmetikinstitute",
    "sg:phone":"+41 41 240 17 55",
    "sg:postcode":"6003",
    "sg:province":"Luzern",
    "wof:name":"Margit B\u00fcrgi Kosmetik-& Schlankheitsstudio",
    "wof:placetype":"venue"
},
  "geometry": {"coordinates":[8.3030061722,47.048122406],"type":"Point"}
}