{
  "type": "Feature",
  "properties": {
    "iso:country":"CH",
    "sg:address":"4112",
    "sg:city":"Fl\u00fch",
    "sg:orig_category":"Mahl U Sch\u00e4lm\u00fchlen",
    "sg:phone":"+41 56 241 16 51",
    "sg:postcode":"4112",
    "sg:province":"Solothurn",
    "wof:name":"Gebr\u00fcder Suter M\u00fchle",
    "wof:placetype":"venue"
},
  "geometry": {"coordinates":[8.3312911987,47.5197525024],"type":"Point"}
}