{
  "type": "Feature",
  "properties": {
    "iso:country":"CH",
    "sg:address":"Untere Grabenstrasse",
    "sg:city":"Zofingen",
    "sg:orig_category":"Kinos",
    "sg:phone":"+41 62 751 24 33",
    "sg:postcode":"4800",
    "sg:province":"Aargau",
    "wof:name":"Blum Kino Ag",
    "wof:placetype":"venue"
},
  "geometry": {"coordinates":[7.9431800842,47.2895812988],"type":"Point"}
}