{
  "type": "Feature",
  "properties": {
    "iso:country":"CH",
    "sg:address":"R\u00fceggisingerstrasse 92",
    "sg:city":"Emmen",
    "sg:orig_category":"Einbau von Schreinerwaren Herstellung von sonstigen Maschinen f\u00fcr unspezifische Verwendung",
    "sg:phone":"+41 32 926 14 40",
    "sg:postcode":"6032",
    "sg:province":"Luzern",
    "wof:name":"Grezet Ch. Et Anthoine P.",
    "wof:placetype":"venue"
},
  "geometry": {"coordinates":[6.8156218529,47.0940284729],"type":"Point"}
}