{
  "type": "Feature",
  "properties": {
    "iso:country":"CH",
    "sg:address":"Rue Goetz-monin 8",
    "sg:city":"Gen\u00e8ve",
    "sg:orig_category":"Grafikateliers, Design Maler U Glasergewerbe",
    "sg:phone":"+41 79 202 52 81",
    "sg:postcode":"1205",
    "sg:province":"Gen\u00e8ve",
    "wof:name":"Michel Richardone",
    "wof:placetype":"venue"
},
  "geometry": {"coordinates":[6.1466059685,46.194644928],"type":"Point"}
}