{
  "type": "Feature",
  "properties": {
    "iso:country":"CH",
    "sg:address":"Waisenhausplatz 28",
    "sg:city":"Bern",
    "sg:orig_category":"Non-Classified Establishments",
    "sg:postcode":"3011",
    "sg:province":"Bern",
    "wof:name":"Salerno Holding Ag",
    "wof:placetype":"venue"
},
  "geometry": {"coordinates":[7.4439878464,46.9496612549],"type":"Point"}
}