{
  "type": "Feature",
  "properties": {
    "addr:full":"Alte Poststrasse 10 Gunzgen Solothurn 4617",
    "addr:housenumber":"10",
    "addr:postcode":"4617",
    "addr:street":"Alte Poststrasse",
    "iso:country":"CH",
    "sg:address":"Alte Poststrasse 10",
    "sg:city":"Gunzgen",
    "sg:orig_category":"Architektur U Ingenieurb\u00fcros Architekturb\u00fcros",
    "sg:phone":"+41 62 216 34 00",
    "sg:postcode":"4617",
    "sg:province":"Solothurn",
    "wof:name":"Lack Gmbh Ingenieur Und Architekturb\u00fcro",
    "wof:placetype":"venue"
},
  "geometry": {"coordinates":[7.831466,47.316856],"type":"Point"}
}