{
  "type": "Feature",
  "properties": {
    "iso:country":"CH",
    "sg:address":"Untere Gst\u00fccktstrasse 11",
    "sg:city":"B\u00fclach",
    "sg:orig_category":"Kaminfeger",
    "sg:phone":"+41 79 205 58 14",
    "sg:postcode":"8180",
    "sg:province":"Z\u00fcrich",
    "wof:name":"Max Maag Kaminfegergesch\u00e4ft",
    "wof:placetype":"venue"
},
  "geometry": {"coordinates":[8.5486421585,47.522518158],"type":"Point"}
}