{
  "type": "Feature",
  "properties": {
    "iso:country":"CH",
    "sg:address":"Kirchgasse 2",
    "sg:city":"K\u00f6lliken",
    "sg:orig_category":"Detailhandel mit elektrischen Haushalts-,Radio U Fernsehger\u00e4ten sowie Musikinstrumenten",
    "sg:phone":"+41 62 723 91 21",
    "sg:postcode":"5742",
    "sg:province":"Aargau",
    "wof:name":"Musikservice, Hunziker Daniel",
    "wof:placetype":"venue"
},
  "geometry": {"coordinates":[8.0246477127,47.3358383179],"type":"Point"}
}