{
  "type": "Feature",
  "properties": {
    "iso:country":"CH",
    "sg:address":"Treycovagnes Chauss\u00e9e De 5 1400 Yverdon-les-bains. Postfach",
    "sg:city":"Cheseaux-nor\u00e9az",
    "sg:orig_category":"Oberfl\u00e4chenveredlung U W\u00e4rmebehandlung",
    "sg:phone":"+41 24 445 07 10",
    "sg:postcode":"1400",
    "sg:province":"Vaud",
    "wof:name":"Pro-tech H\u00fcgli Produits Industriels, Notamm. Dans Le Domaine Du Traitement De Surfaces; Commerce Et Fabrication",
    "wof:placetype":"venue"
},
  "geometry": {"coordinates":[6.625726223,46.7787208557],"type":"Point"}
}