{
  "type": "Feature",
  "properties": {
    "iso:country":"CH",
    "sg:address":"Industriestrasse 14 8712 St\u00e4fa. Postfach 562",
    "sg:city":"St\u00e4fa",
    "sg:orig_category":"Sanit\u00e4r, Heizungs U L\u00fcftungsinstallation Sanit\u00e4rinstallation",
    "sg:phone":"+41 19262649",
    "sg:postcode":"8712",
    "sg:province":"Z\u00fcrich",
    "wof:name":"Casatech Ag",
    "wof:placetype":"venue"
},
  "geometry": {"coordinates":[8.7423143387,47.2378311157],"type":"Point"}
}