{
  "type": "Feature",
  "properties": {
    "iso:country":"CH",
    "sg:address":"Chriesiweg",
    "sg:city":"Jonen",
    "sg:orig_category":"Herstellung von Medikamenten U sonstigen pharmazeutischen Erzeugnissen",
    "sg:postcode":"8916",
    "sg:province":"Aargau",
    "wof:name":"Gremag",
    "wof:placetype":"venue"
},
  "geometry": {"coordinates":[8.3931808472,47.3024749756],"type":"Point"}
}