{
  "type": "Feature",
  "properties": {
    "iso:country":"CH",
    "sg:address":"Vis \u00e0 Vis Post",
    "sg:city":"Obstalden",
    "sg:classifiers":[
        {
            "category":"Banks & Credit Unions",
            "subcategory":"Bank",
            "type":"Services"
        }
    ],
    "sg:phone":"+41 55 614 18 83",
    "sg:postcode":"8758",
    "sg:province":"Glarus",
    "wof:name":"Glarner Kantonalbank, Agentur",
    "wof:placetype":"venue"
},
  "geometry": {"coordinates":[9.15054,47.117245],"type":"Point"}
}