{
  "type": "Feature",
  "properties": {
    "iso:country":"CH",
    "sg:address":"Friedbergstrasse 7",
    "sg:city":"W\u00e4denswil",
    "sg:orig_category":"Zahnarztpraxen",
    "sg:phone":"+41 17800304",
    "sg:postcode":"8820",
    "sg:province":"Z\u00fcrich",
    "wof:name":"Dr.med.dent.j.-m. Ruchenstein Zahnarzt",
    "wof:placetype":"venue"
},
  "geometry": {"coordinates":[8.6739263535,47.2290382385],"type":"Point"}
}