{
  "type": "Feature",
  "properties": {
    "iso:country":"CH",
    "sg:address":"Binzm\u00fchlestrasse 170 8050 Z\u00fcrich",
    "sg:city":"Zust",
    "sg:orig_category":"Unternehmensberatung",
    "sg:postcode":"50",
    "wof:name":"Inpuncto Gmbh",
    "wof:placetype":"venue"
},
  "geometry": {"coordinates":[7.5597457886,47.5235061646],"type":"Point"}
}