{
  "type": "Feature",
  "properties": {
    "iso:country":"CH",
    "sg:address":"Seewenstrasse 11",
    "sg:city":"Hochwald",
    "sg:orig_category":"Landesverteidigung, Sozialversicherung \u00d6ffentliche Verwaltung",
    "sg:phone":"+41 61 751 40 10",
    "sg:postcode":"4146",
    "sg:province":"Solothurn",
    "wof:name":"Zivilschutzstelle Hochwald",
    "wof:placetype":"venue"
},
  "geometry": {"coordinates":[7.6395258904,47.4553108215],"type":"Point"}
}