{
  "type": "Feature",
  "properties": {
    "iso:country":"CH",
    "sg:address":"Grabackerstrasse 2",
    "sg:city":"H\u00f6ri",
    "sg:classifiers":[
        {
            "category":"Building & Trades",
            "subcategory":"Construction",
            "type":"Services"
        }
    ],
    "sg:phone":"+41 18604953",
    "sg:postcode":"8181",
    "sg:province":"Z\u00fcrich",
    "sg:tags":[
        "machine"
    ],
    "wof:name":"De Bastiani - Mechanik Ag",
    "wof:placetype":"venue"
},
  "geometry": {"coordinates":[8.5181665421,47.5107765198],"type":"Point"}
}