{
  "type": "Feature",
  "properties": {
    "iso:country":"CH",
    "sg:address":"Serodine Via Giovanni 12",
    "sg:city":"Bellinzona",
    "sg:orig_category":"Non-Classified Establishments",
    "sg:postcode":"6500",
    "sg:province":"Ticino",
    "wof:name":"O.g.s. Sa",
    "wof:placetype":"venue"
},
  "geometry": {"coordinates":[9.0138158798,46.1824455261],"type":"Point"}
}