{
  "type": "Feature",
  "properties": {
    "iso:country":"CH",
    "sg:address":"Damiano Via San 2",
    "sg:city":"Mendrisio",
    "sg:orig_category":"Detailhandel mit Bekleidung",
    "sg:phone":"+41 91 646 69 73",
    "sg:postcode":"6850",
    "sg:province":"Ticino",
    "wof:name":"Boutique Rina Sagl",
    "wof:placetype":"venue"
},
  "geometry": {"coordinates":[8.988405,45.870747],"type":"Point"}
}