{
  "type": "Feature",
  "properties": {
    "iso:country":"CH",
    "sg:address":"Obstgarten 3",
    "sg:city":"Merlischachen",
    "sg:orig_category":"Wirtschaftspr\u00fcfung, Steuerberatung U Treuhand",
    "sg:phone":"+41 41 850 85 84",
    "sg:postcode":"6402",
    "sg:province":"Schwyz",
    "wof:name":"Rolf F\u00f6lmli Treuhand",
    "wof:placetype":"venue"
},
  "geometry": {"coordinates":[8.4093103409,47.0664749146],"type":"Point"}
}