{
  "type": "Feature",
  "properties": {
    "iso:country":"CH",
    "sg:address":"Daillettes Chemin Des 6",
    "sg:city":"Pully",
    "sg:orig_category":"Linienflugverkehr",
    "sg:phone":"+41 21 345 11 14",
    "sg:postcode":"1009",
    "sg:province":"Vaud",
    "wof:name":"A\u00e9ropro Sa",
    "wof:placetype":"venue"
},
  "geometry": {"coordinates":[6.6649742126,46.523979187],"type":"Point"}
}