{
  "type": "Feature",
  "properties": {
    "iso:country":"CH",
    "sg:address":"Lochmattestrasse 29 3752 Wimmis. Postfach 60",
    "sg:city":"Wimmis",
    "sg:orig_category":"Softwareentwicklung U beratung",
    "sg:phone":"+41 33 657 25 82",
    "sg:postcode":"3752",
    "sg:province":"Bern",
    "wof:name":"Software Tscheulin",
    "wof:placetype":"venue"
},
  "geometry": {"coordinates":[7.6332211494,46.6689796448],"type":"Point"}
}