{
  "type": "Feature",
  "properties": {
    "iso:country":"CH",
    "sg:address":"Hardackerstrasse 19",
    "sg:city":"Kloten",
    "sg:orig_category":"Handelsvermittlung von Maschinen, technischem Bedarf, Wasser U Luftfahrzeugen",
    "sg:postcode":"8302",
    "sg:province":"Z\u00fcrich",
    "wof:name":"Dick Peter Ag",
    "wof:placetype":"venue"
},
  "geometry": {"coordinates":[8.5730581284,47.440612793],"type":"Point"}
}