{
  "type": "Feature",
  "properties": {
    "iso:country":"CH",
    "sg:address":"Alte Landstrasse 29",
    "sg:city":"H\u00f6rhausen",
    "sg:classifiers":[
        {
            "category":"Building & Trades",
            "subcategory":"Construction",
            "type":"Services"
        }
    ],
    "sg:phone":"+41 52 761 19 42",
    "sg:postcode":"8507",
    "sg:province":"Thurgau",
    "sg:tags":[
        "engineering",
        "apparatus"
    ],
    "wof:name":"Beerli Holzwaren Ag",
    "wof:placetype":"venue"
},
  "geometry": {"coordinates":[8.971179,47.632641],"type":"Point"}
}