{
  "type": "Feature",
  "properties": {
    "iso:country":"CH",
    "sg:address":"Wesemlinstrasse 15",
    "sg:city":"Luzern",
    "sg:orig_category":"Architekturb\u00fcros",
    "sg:phone":"+41 12013360",
    "sg:postcode":"6006",
    "sg:province":"Luzern",
    "wof:name":"Tomaso & Brigitta Zanoni Architekturb\u00fcro",
    "wof:placetype":"venue"
},
  "geometry": {"coordinates":[8.309785,47.060242],"type":"Point"}
}