{
  "type": "Feature",
  "properties": {
    "iso:country":"CH",
    "sg:address":"Dorfmatt-zentrum 1",
    "sg:city":"Rotkreuz",
    "sg:orig_category":"Gemeindeverwaltungen",
    "sg:phone":"+41 41 790 14 20",
    "sg:postcode":"6343",
    "sg:province":"Zug",
    "wof:name":"Gemeindeverwaltung Risch",
    "wof:placetype":"venue"
},
  "geometry": {"coordinates":[8.4314098358,47.1412849426],"type":"Point"}
}