{
  "type": "Feature",
  "properties": {
    "iso:country":"CH",
    "sg:address":"Dietschiberg 6006 Luzern. Postfach",
    "sg:city":"Luzern",
    "sg:orig_category":"RESTAURANTS: TEA-ROOMS",
    "sg:postcode":"6003",
    "sg:province":"Luzern",
    "wof:name":"Bucher O. Golf-club-restaurant.",
    "wof:placetype":"venue"
},
  "geometry": {"coordinates":[8.3386287689,47.0649909973],"type":"Point"}
}