{
  "type": "Feature",
  "properties": {
    "iso:country":"CH",
    "sg:address":"Pr\u00e9vostch.dr.-jean-louis 1",
    "sg:city":"Gen\u00e8ve",
    "sg:orig_category":"Unclassifiable Establishments",
    "sg:postcode":"1202",
    "sg:province":"Gen\u00e8ve",
    "wof:name":"Les Jardins De Laurent S\u00e0rl",
    "wof:placetype":"venue"
},
  "geometry": {"coordinates":[6.1236610413,46.2156906128],"type":"Point"}
}