{
  "type": "Feature",
  "properties": {
    "iso:country":"CH",
    "sg:address":"Postg\u00e4ssli 14",
    "sg:city":"Thun",
    "sg:orig_category":"Vereine Vogel-& Naturschutz",
    "sg:phone":"+41 33 336 69 08",
    "sg:postcode":"3604",
    "sg:province":"Bern",
    "wof:name":"Ornitholog.verein Thun & Umg.",
    "wof:placetype":"venue"
},
  "geometry": {"coordinates":[7.623415947,46.7457771301],"type":"Point"}
}