{
  "type": "Feature",
  "properties": {
    "iso:country":"CH",
    "sg:address":"G\u00fcterstrasse 1",
    "sg:city":"Pratteln",
    "sg:orig_category":"Wirtschafts- and Arbeitgeberverb\u00e4nde",
    "sg:postcode":"4133",
    "sg:province":"Basel-Landschaft",
    "wof:name":"Anwaltsverband Baselland Herrn Dr.iur.walter Linsi",
    "wof:placetype":"venue"
},
  "geometry": {"coordinates":[7.6915860176,47.5223197937],"type":"Point"}
}