{
  "type": "Feature",
  "properties": {
    "iso:country":"CH",
    "sg:address":"Sterna 93a",
    "sg:city":"Scharans",
    "sg:orig_category":"Architekturb\u00fcros",
    "sg:phone":"+41 61 701 70 21",
    "sg:postcode":"7412",
    "sg:province":"Graubunden",
    "wof:name":"Christian Glaser Architekturb\u00fcro",
    "wof:placetype":"venue"
},
  "geometry": {"coordinates":[7.621185,47.479515],"type":"Point"}
}