{
  "type": "Feature",
  "properties": {
    "iso:country":"CH",
    "sg:address":"Via Municipio 3",
    "sg:city":"Muralto",
    "sg:orig_category":"Friedhofs- and Stadtg\u00e4rtnereien",
    "sg:phone":"+41 21 944 31 35",
    "sg:postcode":"6600",
    "sg:province":"Ticino",
    "wof:name":"Urbanisme & Travaux Publics",
    "wof:placetype":"venue"
},
  "geometry": {"coordinates":[6.8697252274,46.4539604187],"type":"Point"}
}