{
  "type": "Feature",
  "properties": {
    "iso:country":"CH",
    "sg:address":"Les Sciernes-picats",
    "sg:city":"Rougemont",
    "sg:orig_category":"Abbruch U Sprenggewerbe, Erdbewegungsarbeiten",
    "sg:postcode":"1838",
    "wof:name":"Balsiger-yersin Erwin",
    "wof:placetype":"venue"
},
  "geometry": {"coordinates":[-78.926056,36.217854],"type":"Point"}
}