{
  "type": "Feature",
  "properties": {
    "addr:full":"Lauterbachstrasse 137l Utzigen Bern 3068",
    "addr:housenumber":"137l",
    "addr:postcode":"3068",
    "addr:street":"Lauterbachstrasse",
    "iso:country":"CH",
    "sg:address":"Lauterbachstrasse 137l",
    "sg:city":"Utzigen",
    "sg:orig_category":"Bauschreinerei Herstellung von Konstruktionsteilen, Fertigbauteilen U Ausbauelementen aus Holz",
    "sg:phone":"+41 31 839 42 44",
    "sg:postcode":"3068",
    "sg:province":"Bern",
    "wof:name":"Utos Bauatelier",
    "wof:placetype":"venue"
},
  "geometry": {"coordinates":[7.565586,46.961544],"type":"Point"}
}