{
  "type": "Feature",
  "properties": {
    "iso:country":"CH",
    "sg:address":"Feldbergstrasse 70 4057 Basel. Postfach",
    "sg:city":"Basel",
    "sg:orig_category":"RESTAURANTS: TEA-ROOMS",
    "sg:postcode":"4051",
    "sg:province":"Basel-Stadt",
    "wof:name":"Baris Bar Gmbh Restaurants, Bars Usw",
    "wof:placetype":"venue"
},
  "geometry": {"coordinates":[7.5923428535,47.5664405823],"type":"Point"}
}