{
  "type": "Feature",
  "properties": {
    "iso:country":"CH",
    "sg:address":"Fennern 399",
    "sg:city":"Brittnau",
    "sg:classifiers":[
        {
            "category":"Travel",
            "subcategory":"Hotels & Motels",
            "type":"Entertainment"
        }
    ],
    "sg:postcode":"4805",
    "sg:province":"Aargau",
    "sg:tags":[
        "hotels",
        "mit",
        "restaurant"
    ],
    "wof:name":"K\u00fcnzli Andr\u00e9",
    "wof:placetype":"venue"
},
  "geometry": {"coordinates":[7.8954749107,46.7019309998],"type":"Point"}
}