{
  "type": "Feature",
  "properties": {
    "iso:country":"CH",
    "sg:address":"Rotzwinkel 8",
    "sg:city":"Stans",
    "sg:orig_category":"Herstellung von Musikinstrumenten",
    "sg:phone":"+41 41 610 51 86",
    "sg:postcode":"6370",
    "sg:province":"Nidwalden",
    "wof:name":"Erwin Erni Orgelbau",
    "wof:placetype":"venue"
},
  "geometry": {"coordinates":[8.3433103561,46.9675865173],"type":"Point"}
}