{
  "type": "Feature",
  "properties": {
    "iso:country":"CH",
    "sg:address":"Mittlere R\u00fcti",
    "sg:city":"W\u00e4denswil",
    "sg:orig_category":"Allgemeiner Hoch U Tiefbau",
    "sg:phone":"+41 17813142",
    "sg:postcode":"8820",
    "sg:province":"Z\u00fcrich",
    "wof:name":"Streuli Fritz Gmbh",
    "wof:placetype":"venue"
},
  "geometry": {"coordinates":[8.641329,47.235359],"type":"Point"}
}