{
  "type": "Feature",
  "properties": {
    "iso:country":"CH",
    "sg:address":"Lombachweg 9",
    "sg:city":"Bern",
    "sg:orig_category":"Sportschulen Fern\u00f6stliche Kampfsportarten",
    "sg:phone":"+41 31 971 15 18",
    "sg:postcode":"3006",
    "sg:province":"Bern",
    "wof:name":"Dani\u00e8le Gosling Yoga-schule",
    "wof:placetype":"venue"
},
  "geometry": {"coordinates":[7.4684491158,46.9397239685],"type":"Point"}
}