{
  "type": "Feature",
  "properties": {
    "iso:country":"CH",
    "sg:address":"Bahnhofplatz 7 5400 Baden. Postfach",
    "sg:city":"Baden",
    "sg:orig_category":"Fachdetailhandel mit pharmazeutischen Produkten",
    "sg:phone":"+41 17616320",
    "sg:postcode":"5401",
    "sg:province":"Aargau",
    "wof:name":"Bahnhof-apotheke Und Drogerie, Frau Cerny-mosca A.",
    "wof:placetype":"venue"
},
  "geometry": {"coordinates":[8.4521379471,47.2810134888],"type":"Point"}
}