{
  "type": "Feature",
  "properties": {
    "iso:country":"CH",
    "sg:address":"Schulhausstrasse 1",
    "sg:city":"Feusisberg",
    "sg:orig_category":"G\u00fcterbef\u00f6rderung im Strassenverkehr",
    "sg:phone":"+41 17841276",
    "sg:postcode":"8835",
    "sg:province":"Schwyz",
    "wof:name":"Willy Zumbach Transporte",
    "wof:placetype":"venue"
},
  "geometry": {"coordinates":[8.7490062714,47.1876068115],"type":"Point"}
}