{
  "type": "Feature",
  "properties": {
    "iso:country":"CH",
    "sg:address":"Gemperenstrasse 28",
    "sg:city":"Berneck",
    "sg:classifiers":[
        {
            "category":"Shopping",
            "type":"Retail Goods"
        }
    ],
    "sg:phone":"+41 71 747 83 83",
    "sg:postcode":"9442",
    "sg:province":"St. Gallen",
    "sg:tags":[
        "metallurgy",
        "finished",
        "-",
        "metalworking",
        "metallic"
    ],
    "wof:name":"Elkuch Mobil Ag",
    "wof:placetype":"venue"
},
  "geometry": {"coordinates":[9.623550415,47.426738739],"type":"Point"}
}