{
  "type": "Feature",
  "properties": {
    "iso:country":"CH",
    "sg:address":"Avenue Pr\u00e9 Du Ch\u00e2teau 4",
    "sg:city":"Payerne",
    "sg:orig_category":"Malerei Stukkateurgewerbe, Gipserei U Verputzerei",
    "sg:phone":"+41 79 206 89 01",
    "sg:postcode":"1530",
    "sg:province":"Vaud",
    "wof:name":"Tettamanti Silvio",
    "wof:placetype":"venue"
},
  "geometry": {"coordinates":[6.9440498352,46.8253707886],"type":"Point"}
}