{
  "type": "Feature",
  "properties": {
    "iso:country":"CH",
    "sg:address":"Bouchet Avenue Du 5 B 1209 Gen\u00e8ve. Postfach",
    "sg:city":"Gen\u00e8ve",
    "sg:orig_category":"Herstellung von sonstigen elektrischen Ausr\u00fcstungen",
    "sg:phone":"+41 56 460 89 89",
    "sg:postcode":"1209",
    "sg:province":"Gen\u00e8ve",
    "wof:name":"Jost Electric Ag",
    "wof:placetype":"venue"
},
  "geometry": {"coordinates":[8.1846828461,47.4679679871],"type":"Point"}
}