{
  "type": "Feature",
  "properties": {
    "iso:country":"CH",
    "sg:address":"Boulevard James-fazy 4bis 1200 Genf. Postfach",
    "sg:city":"Gen\u00e8ve",
    "sg:orig_category":"Handel mit Motorr\u00e4dern, Teilen U Zubeh\u00f6r Instandhaltung U Reparatur von Motorr\u00e4dern",
    "sg:phone":"+41 79 210 25 64",
    "sg:postcode":"1201",
    "sg:province":"Gen\u00e8ve",
    "wof:name":"Moto-d\u00e9clic, Aeberhard Jean-claude",
    "wof:placetype":"venue"
},
  "geometry": {"coordinates":[6.6639499664,46.5902061462],"type":"Point"}
}