{
  "type": "Feature",
  "properties": {
    "iso:country":"CH",
    "sg:address":"Robert-durrerstrasse 4",
    "sg:city":"Stans",
    "sg:orig_category":"Unclassifiable Establishments",
    "sg:postcode":"6370",
    "sg:province":"Nidwalden",
    "wof:name":"Stiftung Bineton",
    "wof:placetype":"venue"
},
  "geometry": {"coordinates":[8.3685388565,46.9593315125],"type":"Point"}
}