{
  "type": "Feature",
  "properties": {
    "iso:country":"CH",
    "sg:address":"Unterdettigenstrasse 27",
    "sg:city":"Hinterkappelen",
    "sg:orig_category":"Fahrschulen, Flugschulen",
    "sg:phone":"+41 31 901 23 62",
    "sg:postcode":"3032",
    "sg:province":"Bern",
    "wof:name":"Walter K\u00e4mpf Autofahrlehrer",
    "wof:placetype":"venue"
},
  "geometry": {"coordinates":[7.3869009018,46.9680099487],"type":"Point"}
}