{
  "type": "Feature",
  "properties": {
    "iso:country":"CH",
    "sg:address":"Neuenhoferstrasse 101",
    "sg:city":"Baden",
    "sg:orig_category":"Unternehmensberatung",
    "sg:phone":"+41 17842645",
    "sg:postcode":"5400",
    "sg:province":"Aargau",
    "wof:name":"T Und C Trainingsconsult Ag",
    "wof:placetype":"venue"
},
  "geometry": {"coordinates":[8.7341480255,47.1973953247],"type":"Point"}
}