{
  "type": "Feature",
  "properties": {
    "iso:country":"CH",
    "sg:address":"Staatsstrasse 158",
    "sg:city":"H\u00fcnibach",
    "sg:orig_category":"P\u00e9dicure",
    "sg:phone":"+41 33 243 33 00",
    "sg:postcode":"3626",
    "sg:province":"Bern",
    "wof:name":"Elisabeth Walther P\u00e9dicure",
    "wof:placetype":"venue"
},
  "geometry": {"coordinates":[7.6421518326,46.7466392517],"type":"Point"}
}