{
  "type": "Feature",
  "properties": {
    "iso:country":"CH",
    "sg:address":"Dorfstrasse 26a",
    "sg:city":"Buochs",
    "sg:orig_category":"Sportvereine Turnen Damen",
    "sg:phone":"+41 41 622 05 05",
    "sg:postcode":"6374",
    "sg:province":"Nidwalden",
    "wof:name":"Damenturnverein",
    "wof:placetype":"venue"
},
  "geometry": {"coordinates":[8.4208860397,46.9719085693],"type":"Point"}
}