{
  "type": "Feature",
  "properties": {
    "iso:country":"CH",
    "sg:address":"Holzackerweg 1",
    "sg:city":"Glis",
    "sg:orig_category":"Kinesiologie",
    "sg:phone":"+41 27 924 38 12",
    "sg:postcode":"3902",
    "sg:province":"Valais",
    "wof:name":"Ruth Zimmermann Kinesiologie",
    "wof:placetype":"venue"
},
  "geometry": {"coordinates":[7.9867801666,46.3101158142],"type":"Point"}
}