{
  "type": "Feature",
  "properties": {
    "iso:country":"CH",
    "sg:address":"Lehenmattstrasse",
    "sg:city":"Basel",
    "sg:orig_category":"Freizeit, Kunst U Kultur",
    "sg:postcode":"4052",
    "sg:province":"Basel-Stadt",
    "wof:name":"Esm-music",
    "wof:placetype":"venue"
},
  "geometry": {"coordinates":[7.613705,47.553902],"type":"Point"}
}