{
  "type": "Feature",
  "properties": {
    "iso:country":"CH",
    "sg:address":"Zentrum",
    "sg:city":"Regensdorf",
    "sg:orig_category":"Grossbanken",
    "sg:phone":"+41 22 321 18 88",
    "sg:postcode":"8105",
    "sg:province":"Z\u00fcrich",
    "wof:name":"Ubs Sa Agence Jonction",
    "wof:placetype":"venue"
},
  "geometry": {"coordinates":[6.1313090324,46.2003936768],"type":"Point"}
}