{
  "type": "Feature",
  "properties": {
    "iso:country":"CH",
    "sg:address":"Rosenfeldweg 6 6353 Weggis. Postfach",
    "sg:city":"Horw",
    "sg:orig_category":"Rechtsberatung",
    "sg:phone":"+41 41 390 24 44",
    "sg:postcode":"6048",
    "sg:province":"Luzern",
    "wof:name":"Berz & Co.",
    "wof:placetype":"venue"
},
  "geometry": {"coordinates":[8.4343938828,47.0322952271],"type":"Point"}
}