{
  "type": "Feature",
  "properties": {
    "iso:country":"CH",
    "sg:address":"Bilstenstrasse 48",
    "sg:city":"Altendorf",
    "sg:orig_category":"RESTAURANTS: TEA-ROOMS",
    "sg:postcode":"8852",
    "sg:province":"Schwyz",
    "wof:name":"Gastrobetriebe Cid-gr\u00e4tzer Herminio Und Marlis",
    "wof:placetype":"venue"
},
  "geometry": {"coordinates":[8.8061637878,47.1820678711],"type":"Point"}
}