{
  "type": "Feature",
  "properties": {
    "addr:full":"Mittelgasse 22 W\u00fcrenlingen Aargau 5303",
    "addr:housenumber":"22",
    "addr:postcode":"5303",
    "addr:street":"Mittelgasse",
    "iso:country":"CH",
    "sg:address":"Mittelgasse 22",
    "sg:city":"W\u00fcrenlingen",
    "sg:classifiers":[
        {
            "category":"Professional",
            "subcategory":"Advertising",
            "type":"Services"
        }
    ],
    "sg:phone":"+41 56 290 03 60",
    "sg:postcode":"5303",
    "sg:province":"Aargau",
    "sg:tags":[
        "gift"
    ],
    "wof:name":"Firmen & Sport Promotion Baier",
    "wof:placetype":"venue"
},
  "geometry": {"coordinates":[8.245,47.519833],"type":"Point"}
}