{
  "type": "Feature",
  "properties": {
    "iso:country":"CH",
    "sg:address":"Rue Des Petits Champs 1",
    "sg:city":"Yverdon-les-bains",
    "sg:orig_category":"Non-Classified Establishments",
    "sg:phone":"+41 24 425 56 52",
    "sg:postcode":"1400",
    "sg:province":"Vaud",
    "wof:name":"G.m. Viande Chevaline En Gros, M\u00fcller G.",
    "wof:placetype":"venue"
},
  "geometry": {"coordinates":[6.6387968063,46.7715835571],"type":"Point"}
}