{
  "type": "Feature",
  "properties": {
    "iso:country":"CH",
    "sg:address":"Fl\u00fcelastrasse 54 8000 Z\u00fcrich. Postfach",
    "sg:city":"Z\u00fcrich",
    "sg:orig_category":"Architektur U Ingenieurb\u00fcros",
    "sg:postcode":"8047",
    "sg:province":"Z\u00fcrich",
    "wof:name":"Riboni G.f. & P. Gmbh",
    "wof:placetype":"venue"
},
  "geometry": {"coordinates":[8.4939,47.380917],"type":"Point"}
}