{
  "type": "Feature",
  "properties": {
    "iso:country":"CH",
    "sg:address":"Bernstrasse 66",
    "sg:city":"Ostermundigen",
    "sg:orig_category":"Unternehmensberatung",
    "sg:phone":"+41 31 931 24 88",
    "sg:postcode":"3072",
    "sg:province":"Bern",
    "wof:name":"Wymann",
    "wof:placetype":"venue"
},
  "geometry": {"coordinates":[7.4891829491,46.9581336975],"type":"Point"}
}