{
  "type": "Feature",
  "properties": {
    "iso:country":"CH",
    "sg:address":"Rue Des Tisserands 12",
    "sg:city":"Porrentruy",
    "sg:orig_category":"Organisationen der Wohlfahrtspflege",
    "sg:phone":"+41 21 694 35 35",
    "sg:postcode":"2900",
    "sg:province":"Jura",
    "wof:name":"Medair Agence D'aide Humanitaire",
    "wof:placetype":"venue"
},
  "geometry": {"coordinates":[6.5639967918,46.5350608826],"type":"Point"}
}