{
  "type": "Feature",
  "properties": {
    "iso:country":"CH",
    "sg:address":"Berglistr. 36",
    "sg:city":"Bergdietikon",
    "sg:orig_category":"Kauf U Verkauf von Immobilien auf eigene Rechnung",
    "sg:postcode":"8962",
    "sg:province":"Aargau",
    "wof:name":"Bergli Immobilien Ag",
    "wof:placetype":"venue"
},
  "geometry": {"coordinates":[8.3787021637,47.3949394226],"type":"Point"}
}