{
  "type": "Feature",
  "properties": {
    "iso:country":"CH",
    "sg:address":"Bachelin Avenue 11",
    "sg:city":"St-blaise",
    "sg:orig_category":"Wirtschaftspr\u00fcfung, Steuerberatung U Treuhand",
    "sg:postcode":"2072",
    "sg:province":"Neuch\u00e2tel",
    "wof:name":"Jaquier J.",
    "wof:placetype":"venue"
},
  "geometry": {"coordinates":[7.0653457642,47.0592918396],"type":"Point"}
}