{
  "type": "Feature",
  "properties": {
    "addr:full":"Via Pioda 8 6900 Lugano. Postfach Lugano Ticino 6901",
    "addr:housenumber":"8",
    "addr:postcode":"6900;6901",
    "addr:street":"Via Pioda",
    "iso:country":"CH",
    "sg:address":"Via Pioda 8 6900 Lugano. Postfach",
    "sg:city":"Lugano",
    "sg:orig_category":"Advokaturb\u00fcros",
    "sg:phone":"+41 91 923 37 44",
    "sg:postcode":"6901",
    "sg:province":"Ticino",
    "wof:name":"Elio Fiscalini Studio Legale & Notarile",
    "wof:placetype":"venue"
},
  "geometry": {"coordinates":[8.951305,46.002975],"type":"Point"}
}