{
  "type": "Feature",
  "properties": {
    "iso:country":"CH",
    "sg:address":"Bockenweg 31",
    "sg:city":"Horgen",
    "sg:orig_category":"Interessenvertretungen",
    "sg:postcode":"8810",
    "sg:province":"Z\u00fcrich",
    "wof:name":"Verein Zur Erforschung Und Verwirklichung Des Werkes Von Rudolf Steiner",
    "wof:placetype":"venue"
},
  "geometry": {"coordinates":[8.6149578094,47.2405014038],"type":"Point"}
}