{
  "type": "Feature",
  "properties": {
    "iso:country":"CH",
    "sg:address":"Staffelstrasse 12 8000 Z\u00fcrich. Postfach 8045 Z\u00fcrich",
    "sg:city":"Zust",
    "sg:orig_category":"Werbung",
    "sg:postcode":"45",
    "wof:name":"Textmann - Portmann Dani Texte/konzepte",
    "wof:placetype":"venue"
},
  "geometry": {"coordinates":[8.5072469711,47.3622817993],"type":"Point"}
}