{
  "type": "Feature",
  "properties": {
    "iso:country":"CH",
    "sg:address":"Bahnhofstrasse 6 2540 Grenchen. Postfach 729",
    "sg:city":"Grenchen",
    "sg:orig_category":"Kauf U Verkauf von Immobilien auf eigene Rechnung",
    "sg:phone":"+41 32 653 86 66",
    "sg:postcode":"2540",
    "sg:province":"Solothurn",
    "wof:name":"Leimer Urs Immobilien Ag Liegenschaften; Kauf, Verkauf, Vermittlung Usw",
    "wof:placetype":"venue"
},
  "geometry": {"coordinates":[7.3957929611,47.1917037964],"type":"Point"}
}