{
  "type": "Feature",
  "properties": {
    "iso:country":"CH",
    "sg:address":"K\u00e4nelmattweg 1 4106 Therwil. Postfach",
    "sg:city":"Therwil",
    "sg:orig_category":"Arztpraxen",
    "sg:phone":"+41 18335022",
    "sg:postcode":"4106",
    "sg:province":"Basel-Landschaft",
    "wof:name":"Dr.med.pierre-albert Bozzone Arzt F.allgemeine Medizin Fmh",
    "wof:placetype":"venue"
},
  "geometry": {"coordinates":[8.654421,47.40155],"type":"Point"}
}