{
  "type": "Feature",
  "properties": {
    "iso:country":"CH",
    "sg:address":"Zuzgerstrasse 8",
    "sg:city":"Buus",
    "sg:orig_category":"Sonstige mit der Informatik verbundene T\u00e4tigkeiten",
    "sg:phone":"+41 61 843 02 22",
    "sg:postcode":"4463",
    "sg:province":"Basel-Landschaft",
    "wof:name":"Neos Consulting Ag",
    "wof:placetype":"venue"
},
  "geometry": {"coordinates":[7.8653421402,47.5058517456],"type":"Point"}
}