{
  "type": "Feature",
  "properties": {
    "iso:country":"CH",
    "sg:address":"H\u00f6chweid 10a",
    "sg:city":"Rothenburg",
    "sg:orig_category":"Sonstige mit der Informatik verbundene T\u00e4tigkeiten",
    "sg:phone":"+41 41 360 54 01",
    "sg:postcode":"6023",
    "sg:province":"Luzern",
    "wof:name":"A Plus Gipser Gmbh",
    "wof:placetype":"venue"
},
  "geometry": {"coordinates":[8.2681655884,47.1046218872],"type":"Point"}
}