{
  "type": "Feature",
  "properties": {
    "iso:country":"CH",
    "sg:address":"R\u00fctistrasse 13",
    "sg:city":"Sarnen",
    "sg:orig_category":"Detailhandel mit Fahrr\u00e4dern Handel mit Motorr\u00e4dern, Teilen U Zubeh\u00f6r Instandhaltung U Reparatur von ",
    "sg:phone":"+41 31 829 18 88",
    "sg:postcode":"6060",
    "sg:province":"Obwalden",
    "wof:name":"Bendicht Kipfer Velos Mofas",
    "wof:placetype":"venue"
},
  "geometry": {"coordinates":[7.3595900536,46.9707794189],"type":"Point"}
}