{
  "type": "Feature",
  "properties": {
    "iso:country":"CH",
    "sg:address":"Kreuzhaldenstrasse 1921",
    "sg:city":"Glattfelden",
    "sg:orig_category":"Allgemeiner Hoch U Tiefbau",
    "sg:postcode":"8192",
    "sg:province":"Z\u00fcrich",
    "wof:name":"Baugesch\u00e4ft Gerhard Hidegh.",
    "wof:placetype":"venue"
},
  "geometry": {"coordinates":[8.49914,47.56123],"type":"Point"}
}