{
  "type": "Feature",
  "properties": {
    "iso:country":"CH",
    "sg:address":"Stadthausgasse 17",
    "sg:city":"Schaffhausen",
    "sg:orig_category":"RESTAURANTS: TEA-ROOMS",
    "sg:phone":"+41 19505253",
    "sg:postcode":"8200",
    "sg:province":"Schaffhausen",
    "wof:name":"Restaurant Zur Krone Pf\u00e4ffikon, Palermo Giuseppe",
    "wof:placetype":"venue"
},
  "geometry": {"coordinates":[8.7821521759,47.3670654297],"type":"Point"}
}