{
  "type": "Feature",
  "properties": {
    "iso:country":"CH",
    "sg:address":"Stanserstrasse 107",
    "sg:city":"Kerns",
    "sg:orig_category":"Handel mit Motorr\u00e4dern, Teilen U Zubeh\u00f6r Instandhaltung U Reparatur von Motorr\u00e4dern",
    "sg:phone":"+41 41 660 22 05",
    "sg:postcode":"6064",
    "sg:province":"Obwalden",
    "wof:name":"Bike-shop Windlin",
    "wof:placetype":"venue"
},
  "geometry": {"coordinates":[8.279299736,46.903339386],"type":"Point"}
}