{
  "type": "Feature",
  "properties": {
    "iso:country":"CH",
    "sg:address":"Freiestrasse 196",
    "sg:city":"Z\u00fcrich",
    "sg:orig_category":"Personal U Stellenvermittlung Unternehmensberatung",
    "sg:phone":"+41 22 827 21 50",
    "sg:postcode":"8032",
    "sg:province":"Z\u00fcrich",
    "wof:name":"Pierre-alain Boillet",
    "wof:placetype":"venue"
},
  "geometry": {"coordinates":[6.1383857727,46.1757926941],"type":"Point"}
}