{
  "type": "Feature",
  "properties": {
    "iso:country":"CH",
    "sg:address":"Avenue De La Gare 3b",
    "sg:city":"Bulle",
    "sg:orig_category":"Organisationen des Gesundheitswesen",
    "sg:phone":"+41 26 912 01 01",
    "sg:postcode":"1630",
    "sg:province":"Fribourg",
    "wof:name":"Centre M\u00e9dico-social De La Gruy\u00e8re",
    "wof:placetype":"venue"
},
  "geometry": {"coordinates":[7.056579113,46.6177062988],"type":"Point"}
}