{
  "type": "Feature",
  "properties": {
    "iso:country":"CH",
    "sg:address":"Via Tavernola 10",
    "sg:city":"Comano",
    "sg:orig_category":"Kosmetikinstitute",
    "sg:phone":"+41 91 941 92 30",
    "sg:postcode":"6949",
    "sg:province":"Ticino",
    "wof:name":"Tatiana De Ambrosis Istituto Di Bellezza",
    "wof:placetype":"venue"
},
  "geometry": {"coordinates":[8.9596853256,46.0343475342],"type":"Point"}
}