{
  "type": "Feature",
  "properties": {
    "addr:full":"Bergstrasse 13 8712 St\u00e4fa. Postfach St\u00e4fa Z\u00fcrich 8712",
    "addr:housenumber":"13",
    "addr:postcode":"8712;8712",
    "addr:street":"Bergstrasse;Postfach Staefa Zuerich",
    "iso:country":"CH",
    "sg:address":"Bergstrasse 13 8712 St\u00e4fa. Postfach",
    "sg:city":"St\u00e4fa",
    "sg:orig_category":"Detailhandel mit B\u00fcchern Detailhandel mit B\u00fcchern, Zeitungen, Schreib U Papeteriewaren",
    "sg:phone":"+41 17961080",
    "sg:postcode":"8712",
    "sg:province":"Z\u00fcrich",
    "wof:name":"Buchhandlung Kupper",
    "wof:placetype":"venue"
},
  "geometry": {"coordinates":[8.720876,47.241871],"type":"Point"}
}