{
  "type": "Feature",
  "properties": {
    "iso:country":"CH",
    "sg:address":"Gen\u00e8ve Rue De 73 1225 Ch\u00eane-bourg. Postfach",
    "sg:city":"Ch\u00eane-bourg",
    "sg:orig_category":"Sonstiger Fachdetailhandel mit Nahrungsmitteln, Getr\u00e4nken U Tabak in Verkaufsr\u00e4umen",
    "sg:phone":"+41 71 245 61 55",
    "sg:postcode":"1225",
    "sg:province":"Gen\u00e8ve",
    "wof:name":"Alpsenn-senn Ag",
    "wof:placetype":"venue"
},
  "geometry": {"coordinates":[9.0563354492,47.5365982056],"type":"Point"}
}