{
  "type": "Feature",
  "properties": {
    "addr:full":"Baarerstrasse 8 Zug Zug 6300",
    "addr:housenumber":"8",
    "addr:postcode":"6300",
    "addr:street":"Baarerstrasse;Zug",
    "iso:country":"CH",
    "sg:address":"Baarerstrasse 8",
    "sg:city":"Zug",
    "sg:orig_category":"Detailhandel mit Brillen U anderen Sehhilfen Fachdetailhandel in Verkaufsr\u00e4umen",
    "sg:phone":"+41 41 725 29 90",
    "sg:postcode":"6300",
    "sg:province":"Zug",
    "wof:name":"Visilab Zug Optiker, H\u00f6rger\u00e4te Usw",
    "wof:placetype":"venue"
},
  "geometry": {"coordinates":[8.516387,47.171398],"type":"Point"}
}