{
  "type": "Feature",
  "properties": {
    "iso:country":"CH",
    "sg:address":"Plattenstrasse 9",
    "sg:city":"Diepoldsau",
    "sg:orig_category":"Herstellung von Fenstern U T\u00fcren aus Holz Herstellung von Konstruktionsteilen, Fertigbauteilen U Aus",
    "sg:phone":"+41 71 733 25 60",
    "sg:postcode":"9444",
    "sg:province":"St. Gallen",
    "wof:name":"Bruno Frei-kuster Ag Fenster-t\u00fcren-l\u00e4den",
    "wof:placetype":"venue"
},
  "geometry": {"coordinates":[9.6508703232,47.3805503845],"type":"Point"}
}