{
  "type": "Feature",
  "properties": {
    "iso:country":"CH",
    "sg:address":"B\u00e4chweidstrasse 23",
    "sg:city":"Vorderthal",
    "sg:orig_category":"Kaminfeger",
    "sg:phone":"+41 71 966 21 77",
    "sg:postcode":"8857",
    "sg:province":"Schwyz",
    "wof:name":"Josef Sch\u00e4fli Kaminfegergesch\u00e4ft",
    "wof:placetype":"venue"
},
  "geometry": {"coordinates":[9.0022296906,47.4901809692],"type":"Point"}
}