{
  "type": "Feature",
  "properties": {
    "iso:country":"CH",
    "sg:address":"Lagerhausstrasse 1 4500 Solothurn. Postfach 1247",
    "sg:city":"Solothurn",
    "sg:orig_category":"Versicherungen Generalagenturen",
    "sg:phone":"+41 32 625 24 50",
    "sg:postcode":"4501",
    "sg:province":"Solothurn",
    "wof:name":"Coop Versicherungen Generalagentur Solothurn",
    "wof:placetype":"venue"
},
  "geometry": {"coordinates":[7.5336508751,47.2063941956],"type":"Point"}
}