{
  "type": "Feature",
  "properties": {
    "iso:country":"CH",
    "sg:address":"Spannortstrasse 7",
    "sg:city":"Luzern",
    "sg:orig_category":"Advokaturb\u00fcros Notariate",
    "sg:phone":"+41 41 360 33 37",
    "sg:postcode":"6003",
    "sg:province":"Luzern",
    "wof:name":"Dr.emil Greber Advokatur-& Notariatsb\u00fcro",
    "wof:placetype":"venue"
},
  "geometry": {"coordinates":[8.307381,47.042156],"type":"Point"}
}