{
  "type": "Feature",
  "properties": {
    "iso:country":"CH",
    "sg:address":"Friedeggstrasse 4",
    "sg:city":"St.gallen",
    "sg:orig_category":"Herstellung von Teppichen Verlegen von Fussboden",
    "sg:phone":"+41 81 854 21 58",
    "sg:postcode":"9000",
    "sg:province":"St. Gallen",
    "wof:name":"Lasave Ag",
    "wof:placetype":"venue"
},
  "geometry": {"coordinates":[9.9337463379,46.576007843],"type":"Point"}
}