{
  "type": "Feature",
  "properties": {
    "iso:country":"CH",
    "sg:address":"Schuleweg 14",
    "sg:city":"Oberentfelden",
    "sg:orig_category":"Unternehmensberatung",
    "sg:phone":"+41 62 723 65 25",
    "sg:postcode":"5036",
    "sg:province":"Aargau",
    "wof:name":"Hans-theo Schiffer Dr. Rer. Pol.",
    "wof:placetype":"venue"
},
  "geometry": {"coordinates":[8.0491886139,47.3526000977],"type":"Point"}
}