{
  "type": "Feature",
  "properties": {
    "iso:country":"CH",
    "sg:address":"Hauptstrasse 120",
    "sg:city":"T\u00e4uffelen",
    "sg:orig_category":"Architekturb\u00fcros",
    "sg:phone":"+41 32 396 14 46",
    "sg:postcode":"2575",
    "sg:province":"Bern",
    "wof:name":"Willi Haid Architekturb\u00fcro",
    "wof:placetype":"venue"
},
  "geometry": {"coordinates":[7.195971,47.063034],"type":"Point"}
}