{
  "type": "Feature",
  "properties": {
    "iso:country":"CH",
    "sg:address":"Haushaldenstrasse 13",
    "sg:city":"Fischingen",
    "sg:orig_category":"Kauf U Verkauf von Immobilien auf eigene Rechnung",
    "sg:postcode":"8376",
    "sg:province":"Thurgau",
    "wof:name":"Inamag Ag",
    "wof:placetype":"venue"
},
  "geometry": {"coordinates":[8.9571800232,47.4382019043],"type":"Point"}
}