{
  "type": "Feature",
  "properties": {
    "iso:country":"CH",
    "sg:address":"Seefeldstrasse 86 8008 Z\u00fcrich. Postfach",
    "sg:city":"Z\u00fcrich",
    "sg:orig_category":"Handelsvermittlung von Textilien, Bekleidung, Schuhen U Lederwaren",
    "sg:postcode":"8001",
    "sg:province":"Z\u00fcrich",
    "wof:name":"Textrade Textilagentur, Casimiro A. Textilien; Imp., Handel",
    "wof:placetype":"venue"
},
  "geometry": {"coordinates":[8.5518636703,47.3604545593],"type":"Point"}
}