{
  "type": "Feature",
  "properties": {
    "iso:country":"CH",
    "sg:address":"Seestrasse 5",
    "sg:city":"Z\u00fcrich",
    "sg:orig_category":"Arztpraxen",
    "sg:phone":"+41 12029430",
    "sg:postcode":"8002",
    "sg:province":"Z\u00fcrich",
    "wof:name":"Dr.med.thomas Ledermann Spezialarzt Fmh",
    "wof:placetype":"venue"
},
  "geometry": {"coordinates":[8.531927,47.365314],"type":"Point"}
}