{
  "type": "Feature",
  "properties": {
    "iso:country":"CH",
    "sg:address":"Roveredo",
    "sg:city":"Lostallo",
    "sg:orig_category":"Elektrizit\u00e4tsversorgung",
    "sg:phone":"+41 91 827 13 85",
    "sg:postcode":"6558",
    "sg:province":"Graubunden",
    "wof:name":"Calancasca Sa",
    "wof:placetype":"venue"
},
  "geometry": {"coordinates":[9.1959848404,46.3131256104],"type":"Point"}
}