{
  "type": "Feature",
  "properties": {
    "iso:country":"CH",
    "sg:address":"Weidstrasse 3d",
    "sg:city":"Binz",
    "sg:orig_category":"Herstellung von sonstigen elektrischen Ausr\u00fcstungen",
    "sg:phone":"+41 18877555",
    "sg:postcode":"8122",
    "sg:province":"Z\u00fcrich",
    "wof:name":"Ferrotech Pawlaczek",
    "wof:placetype":"venue"
},
  "geometry": {"coordinates":[8.6233606339,47.3595275879],"type":"Point"}
}