{
  "type": "Feature",
  "properties": {
    "iso:country":"CH",
    "sg:address":"Weinmarkt 9",
    "sg:city":"Luzern",
    "sg:orig_category":"Sprachschulen",
    "sg:phone":"+41 41 410 10 20",
    "sg:postcode":"6004",
    "sg:province":"Luzern",
    "wof:name":"Sprachenschule Luzern Sekretariat",
    "wof:placetype":"venue"
},
  "geometry": {"coordinates":[8.3039951324,47.0519218445],"type":"Point"}
}