{
  "type": "Feature",
  "properties": {
    "addr:full":"Chemin Des Ouches 12 2072 St-blaise Case Postale 145 St-blaise Neuch\u00e2tel 2072",
    "addr:housenumber":"12;145",
    "addr:postcode":"2072;2072",
    "addr:street":"Chemin Des Ouches;Postale;Neucha\u0302Tel",
    "iso:country":"CH",
    "sg:address":"Chemin Des Ouches 12 2072 St-blaise Case Postale 145",
    "sg:city":"St-blaise",
    "sg:orig_category":"HERSTELLUNG VON GER\u00c4TEN DER ELEKTRIZIT\u00c4TSERZEUGUNG, -VERTEILUNG U.\u00c4 Herstellung von Metallerzeugniss",
    "sg:phone":"+41 32 753 16 16",
    "sg:postcode":"2072",
    "sg:province":"Neuch\u00e2tel",
    "wof:name":"Cadenzia Sa",
    "wof:placetype":"venue"
},
  "geometry": {"coordinates":[6.988867,47.015804],"type":"Point"}
}