{
  "type": "Feature",
  "properties": {
    "iso:country":"CH",
    "sg:address":"Bruchstrasse 33",
    "sg:city":"Luzern",
    "sg:orig_category":"Fotografische Ateliers Herstellung von Duft U K\u00f6rperpflegemitteln",
    "sg:phone":"+41 41 240 16 91",
    "sg:postcode":"6003",
    "sg:province":"Luzern",
    "wof:name":"Brigitte Adjirackor Fotografisches Atelier",
    "wof:placetype":"venue"
},
  "geometry": {"coordinates":[8.3006343842,47.0495605469],"type":"Point"}
}