{
  "type": "Feature",
  "properties": {
    "iso:country":"CH",
    "sg:address":"Chesalet",
    "sg:city":"Troistorrents",
    "sg:orig_category":"Erbringung von Dienstleistungen f\u00fcr Unternehmen",
    "sg:phone":"+41 24 477 10 15",
    "sg:postcode":"1872",
    "sg:province":"Valais",
    "wof:name":"Boegli Serge",
    "wof:placetype":"venue"
},
  "geometry": {"coordinates":[6.9209527969,46.2326698303],"type":"Point"}
}