{
  "type": "Feature",
  "properties": {
    "iso:country":"CH",
    "sg:address":"Bahnstrasse 102",
    "sg:city":"Regensdorf",
    "sg:orig_category":"Grosshandel mit Schmuck Sonstiger Grosshandel",
    "sg:phone":"+41 18702024",
    "sg:postcode":"8105",
    "sg:province":"Z\u00fcrich",
    "wof:name":"Rk Intertrade Service Ltd Import Export Schmuckvertrieb",
    "wof:placetype":"venue"
},
  "geometry": {"coordinates":[8.4584140778,47.4442024231],"type":"Point"}
}