{
  "type": "Feature",
  "properties": {
    "iso:country":"CH",
    "sg:address":"8933",
    "sg:city":"Maschwanden",
    "sg:orig_category":"Vorschulen, Kinderg\u00e4rten",
    "sg:phone":"+41 71 891 48 07",
    "sg:postcode":"8933",
    "sg:province":"Z\u00fcrich",
    "wof:name":"Kindergarten",
    "wof:placetype":"venue"
},
  "geometry": {"coordinates":[9.5031204224,47.4540405273],"type":"Point"}
}