{
  "type": "Feature",
  "properties": {
    "iso:country":"CH",
    "sg:address":"B\u00fchlenstrasse 11",
    "sg:city":"Riggisberg",
    "sg:orig_category":"Erbringung von Dienstleistungen f\u00fcr Unternehmen Werbeberatung",
    "sg:phone":"+41 31 809 36 15",
    "sg:postcode":"3132",
    "sg:province":"Bern",
    "wof:name":"The Colour Company Ltd Ausstellungen. Verlagshaus, Kunst Usw.; Dienstl.",
    "wof:placetype":"venue"
},
  "geometry": {"coordinates":[7.4817848206,46.8117713928],"type":"Point"}
}