{
  "type": "Feature",
  "properties": {
    "iso:country":"CH",
    "sg:address":"Schulstrasse 17",
    "sg:city":"Felsberg",
    "sg:orig_category":"Gem\u00fcsebau",
    "sg:phone":"+41 71 971 10 46",
    "sg:postcode":"7012",
    "sg:province":"Graubunden",
    "wof:name":"Heidi Lorenz Gem\u00fcsebau",
    "wof:placetype":"venue"
},
  "geometry": {"coordinates":[8.9732885361,47.4655418396],"type":"Point"}
}