{
  "type": "Feature",
  "properties": {
    "iso:country":"CH",
    "sg:address":"1580",
    "sg:city":"Avenches",
    "sg:orig_category":"Campingpl\u00e4tze Detailhandel Reparatur von Gebrauchsg\u00fctern",
    "sg:phone":"+41 26 675 17 50",
    "sg:postcode":"1580",
    "sg:province":"Vaud",
    "wof:name":"Plage-camping",
    "wof:placetype":"venue"
},
  "geometry": {"coordinates":[7.040785,46.880058],"type":"Point"}
}