{
  "type": "Feature",
  "properties": {
    "iso:country":"CH",
    "sg:address":"Landstrasse 15 8197 Rafz. Postfach",
    "sg:city":"Rafz",
    "sg:orig_category":"Gasth\u00f6fe/Gasth\u00e4user mit Restaurant",
    "sg:phone":"+41 18690424",
    "sg:postcode":"8197",
    "sg:province":"Z\u00fcrich",
    "wof:name":"Gasthof Zum Goldenen Kreuz",
    "wof:placetype":"venue"
},
  "geometry": {"coordinates":[8.5406103134,47.6118392944],"type":"Point"}
}