{
  "type": "Feature",
  "properties": {
    "iso:country":"CH",
    "sg:address":"Rue Du Franc-alleu 17",
    "sg:city":"Ligni\u00e8res",
    "sg:orig_category":"G\u00fcterbef\u00f6rderung im Strassenverkehr",
    "sg:phone":"+41 32 751 11 09",
    "sg:postcode":"2523",
    "sg:province":"Neuch\u00e2tel",
    "wof:name":"Fr\u00e9dy Bl\u00f6sch Transports",
    "wof:placetype":"venue"
},
  "geometry": {"coordinates":[7.0670552254,47.0846672058],"type":"Point"}
}