{
  "type": "Feature",
  "properties": {
    "iso:country":"CH",
    "sg:address":"Kongresszentrum Rondo",
    "sg:city":"Pontresina",
    "sg:orig_category":"Sportschulen Ski-& Snowboardschulen",
    "sg:phone":"+41 81 838 83 83",
    "sg:postcode":"7504",
    "sg:province":"Graubunden",
    "wof:name":"Snowboardschule Schweizer Skischule & Langlaufschule",
    "wof:placetype":"venue"
},
  "geometry": {"coordinates":[9.9019098282,46.4935150146],"type":"Point"}
}