{
  "type": "Feature",
  "properties": {
    "iso:country":"CH",
    "sg:address":"Boulevard Des Philosophes 12",
    "sg:city":"Gen\u00e8ve",
    "sg:classifiers":[
        {
            "category":"Restaurant",
            "type":"Food & Drink"
        }
    ],
    "sg:phone":"+41 22 320 02 40",
    "sg:postcode":"1205",
    "sg:province":"Gen\u00e8ve",
    "wof:name":"Caf\u00e9-restaurant La Com\u00e9die",
    "wof:placetype":"venue"
},
  "geometry": {"coordinates":[6.1445212364,46.1970443726],"type":"Point"}
}