{
  "type": "Feature",
  "properties": {
    "iso:country":"CH",
    "sg:address":"Im Werk 9",
    "sg:city":"Uster",
    "sg:orig_category":"Sonstige Aktivit\u00e4ten der nicht-\u00e4rztlichen Medizinalberufe",
    "sg:phone":"+41 79 239 21 14",
    "sg:postcode":"8610",
    "sg:province":"Z\u00fcrich",
    "wof:name":"Irene Stelzer Kinesiologie",
    "wof:placetype":"venue"
},
  "geometry": {"coordinates":[8.7237815857,47.3501472473],"type":"Point"}
}