{
  "type": "Feature",
  "properties": {
    "iso:country":"CH",
    "sg:address":"Plaines-du-loup Rte Des 78 1018 Lausanne. Postfach",
    "sg:city":"Lausanne",
    "sg:orig_category":"RESTAURANTS: TEA-ROOMS",
    "sg:postcode":"1018",
    "sg:province":"Vaud",
    "wof:name":"Vallat Jean-claude. Caf\u00e9-restaurant Chalet De La Bl\u00e9cherette.",
    "wof:placetype":"venue"
},
  "geometry": {"coordinates":[6.6204681396,46.5410003662],"type":"Point"}
}