{
  "type": "Feature",
  "properties": {
    "iso:country":"CH",
    "sg:address":"B\u00e4ndlistrasse 28",
    "sg:city":"Z\u00fcrich",
    "sg:orig_category":"Vorschulen, Kinderg\u00e4rten",
    "sg:phone":"+41 14319927",
    "sg:postcode":"8064",
    "sg:province":"Z\u00fcrich",
    "wof:name":"St\u00e4dtischer Kindergarten Pavillon",
    "wof:placetype":"venue"
},
  "geometry": {"coordinates":[8.4878635406,47.3956565857],"type":"Point"}
}