{
  "type": "Feature",
  "properties": {
    "iso:country":"CH",
    "sg:address":"Stationsstr. 41",
    "sg:city":"Richterswil",
    "sg:orig_category":"Instandhaltung U Reparatur von Automobilen",
    "sg:postcode":"8805",
    "sg:province":"Z\u00fcrich",
    "wof:name":"W\u00fcest H. P.",
    "wof:placetype":"venue"
},
  "geometry": {"coordinates":[8.6817436218,47.1926574707],"type":"Point"}
}