{
  "type": "Feature",
  "properties": {
    "iso:country":"CH",
    "sg:address":"4001 Basel. Postfach 1351",
    "sg:city":"Basel",
    "sg:orig_category":"Sportvereine Ballsport Fussball",
    "sg:phone":"+41 61 331 64 95",
    "sg:postcode":"4001",
    "sg:province":"Basel-Stadt",
    "wof:name":"Fc Alemannia Bs",
    "wof:placetype":"venue"
},
  "geometry": {"coordinates":[7.5887598991,47.5569915771],"type":"Point"}
}