{
  "type": "Feature",
  "properties": {
    "iso:country":"CH",
    "sg:address":"Hauptstrasse 47",
    "sg:city":"Reitnau",
    "sg:orig_category":"Allgemeiner Hoch U Tiefbau",
    "sg:phone":"+41 62 726 28 76",
    "sg:postcode":"5057",
    "sg:province":"Aargau",
    "wof:name":"Hunziker U. Tiefbau Gmbh",
    "wof:placetype":"venue"
},
  "geometry": {"coordinates":[8.045578,47.251175],"type":"Point"}
}