{
  "type": "Feature",
  "properties": {
    "iso:country":"CH",
    "sg:address":"6802",
    "sg:city":"Rivera",
    "sg:orig_category":"Grosshandel mit Erzen U Metallen Grosshandel mit Schmuck",
    "sg:phone":"+41 18444047",
    "sg:postcode":"6802",
    "sg:province":"Ticino",
    "wof:name":"Ag Oehrli F.h., Gold Und Silberwaren En Gros",
    "wof:placetype":"venue"
},
  "geometry": {"coordinates":[8.4365673065,47.4585914612],"type":"Point"}
}