{
  "type": "Feature",
  "properties": {
    "iso:country":"CH",
    "sg:address":"Rue De La Gare 32",
    "sg:city":"B\u00f4le",
    "sg:orig_category":"RESTAURANTS: TEA-ROOMS",
    "sg:postcode":"2014",
    "sg:province":"Neuch\u00e2tel",
    "wof:name":"Fleury-bar, Margot Francine Bar \u00e0 Caf\u00e9",
    "wof:placetype":"venue"
},
  "geometry": {"coordinates":[6.5015058517,46.8230285645],"type":"Point"}
}