{
  "type": "Feature",
  "properties": {
    "iso:country":"CH",
    "sg:address":"Industriestrasse 28",
    "sg:city":"Wittenbach",
    "sg:orig_category":"Vermietung U Verpachtung von eigenen Immobilien",
    "sg:postcode":"9303",
    "wof:name":"Wit-immo Ag",
    "wof:placetype":"venue"
},
  "geometry": {"coordinates":[9.3932647705,47.4628143311],"type":"Point"}
}