{
  "type": "Feature",
  "properties": {
    "iso:country":"CH",
    "sg:address":"Month\u00e9olo 20a 1870 Monthey. Postfach",
    "sg:city":"Monthey",
    "sg:orig_category":"Korrespondenz U Nachrichtenb\u00fcros, selbst\u00e4ndige Journalisten",
    "sg:postcode":"1870",
    "sg:province":"Valais",
    "wof:name":"Maire St\u00e9phane Photographie-reportage",
    "wof:placetype":"venue"
},
  "geometry": {"coordinates":[6.9496808052,46.2566757202],"type":"Point"}
}