{
  "type": "Feature",
  "properties": {
    "iso:country":"CH",
    "sg:address":"Im Majorenacker 8207 Schaffhausen. Postfach 1169",
    "sg:city":"Schaffhausen",
    "sg:orig_category":"Grosshandel mit Holz U Baustoffen",
    "sg:phone":"+41 52 644 24 42",
    "sg:postcode":"8207",
    "sg:province":"Schaffhausen",
    "wof:name":"Hg Commerciale Handelsgenossenschaft Des Schweizerischen Baumeisterverbandes",
    "wof:placetype":"venue"
},
  "geometry": {"coordinates":[8.6598052979,47.7172546387],"type":"Point"}
}