{
  "type": "Feature",
  "properties": {
    "iso:country":"CH",
    "sg:address":"Im Stampf 8340 Girenbad B. Hinwil. Postfach",
    "sg:city":"Wernetshausen",
    "sg:orig_category":"Interessenvertretungen",
    "sg:postcode":"8342",
    "sg:province":"Z\u00fcrich",
    "wof:name":"Stiftung Stampf Sgbl",
    "wof:placetype":"venue"
},
  "geometry": {"coordinates":[8.8435297012,47.3023300171],"type":"Point"}
}