{
  "type": "Feature",
  "properties": {
    "iso:country":"CH",
    "sg:address":"Wilhelmsh\u00f6he",
    "sg:city":"Luzern",
    "sg:orig_category":"Satzherstellung U Reproduktion",
    "sg:phone":"+41 41 249 24 31",
    "sg:postcode":"6000",
    "sg:province":"Luzern",
    "wof:name":"Prepress Center Ag",
    "wof:placetype":"venue"
},
  "geometry": {"coordinates":[8.2978544235,47.050655365],"type":"Point"}
}