{
  "type": "Feature",
  "properties": {
    "iso:country":"CH",
    "sg:address":"Bachserstrasse 9",
    "sg:city":"Stadel",
    "sg:orig_category":"Herstellung von Metallkonstruktionen Stahl U Leichtmetallbau",
    "sg:phone":"+41 18580794",
    "sg:postcode":"8174",
    "sg:province":"Z\u00fcrich",
    "wof:name":"Schellenberg Kurt Ag, Metallbau",
    "wof:placetype":"venue"
},
  "geometry": {"coordinates":[8.4643115997,47.5280761719],"type":"Point"}
}