{
  "type": "Feature",
  "properties": {
    "iso:country":"CH",
    "sg:address":"Leimgrubenweg 9",
    "sg:city":"Basel",
    "sg:orig_category":"Fachdetailhandel in Verkaufsr\u00e4umen",
    "sg:postcode":"4053",
    "sg:province":"Basel-Stadt",
    "wof:name":"Pro Fashion Tsch\u00fcmperlin Daniel",
    "wof:placetype":"venue"
},
  "geometry": {"coordinates":[7.6081728935,47.5368499756],"type":"Point"}
}