{
  "type": "Feature",
  "properties": {
    "iso:country":"CH",
    "sg:address":"3970",
    "sg:city":"Salgesch",
    "sg:orig_category":"Handelsvermittlung U Grosshandel mit Automobilen Herstellung von Automobilen",
    "sg:phone":"+41 27 456 26 56",
    "sg:postcode":"3970",
    "sg:province":"Valais",
    "wof:name":"Prinoth Valais Pistenfahrzeuge",
    "wof:placetype":"venue"
},
  "geometry": {"coordinates":[7.5696148872,46.3114013672],"type":"Point"}
}