{
  "type": "Feature",
  "properties": {
    "iso:country":"CH",
    "sg:address":"Grosswiesenstrasse 153",
    "sg:city":"Z\u00fcrich",
    "sg:orig_category":"Vereine Heimatschutz",
    "sg:phone":"+41 13221342",
    "sg:postcode":"8051",
    "sg:province":"Z\u00fcrich",
    "wof:name":"Z\u00fcrcher Heimatschutz",
    "wof:placetype":"venue"
},
  "geometry": {"coordinates":[8.5877332687,47.4033050537],"type":"Point"}
}