{
  "type": "Feature",
  "properties": {
    "iso:country":"CH",
    "sg:city":"Vissoie",
    "sg:classifiers":[
        {
            "category":"Banks & Credit Unions",
            "subcategory":"Bank",
            "type":"Services"
        }
    ],
    "sg:phone":"+41 4127651159",
    "sg:postcode":"3961",
    "sg:province":"Valais",
    "wof:name":"Banque Raiffeisen D'anniviers",
    "wof:placetype":"venue"
},
  "geometry": {"coordinates":[7.586425,46.214684],"type":"Point"}
}