{
  "type": "Feature",
  "properties": {
    "iso:country":"CH",
    "sg:address":"Nefenstrasse 30",
    "sg:city":"Heerbrugg",
    "sg:orig_category":"Steuerberatung Verwaltung von Immobilien",
    "sg:phone":"+41 71 727 51 51",
    "sg:postcode":"9435",
    "sg:province":"St. Gallen",
    "wof:name":"Sfs Services Ag",
    "wof:placetype":"venue"
},
  "geometry": {"coordinates":[9.6203422546,47.4066009521],"type":"Point"}
}