{
  "type": "Feature",
  "properties": {
    "addr:full":"Avenue Haldimand 19bis Yverdon-les-bains Vaud 1400",
    "addr:housenumber":"19bis",
    "addr:postcode":"1400",
    "addr:street":"Avenue Haldimand",
    "iso:country":"CH",
    "sg:address":"Avenue Haldimand 19bis",
    "sg:city":"Yverdon-les-bains",
    "sg:orig_category":"Arztpraxen",
    "sg:phone":"+41 24 425 53 44",
    "sg:postcode":"1400",
    "sg:province":"Vaud",
    "wof:name":"Dr M\u00e9d. Enrico Realini M\u00e9decin Sp\u00e9cialiste Fmh",
    "wof:placetype":"venue"
},
  "geometry": {"coordinates":[6.64468,46.779419],"type":"Point"}
}