{
  "type": "Feature",
  "properties": {
    "iso:country":"CH",
    "sg:address":"Schleusenweg 20",
    "sg:city":"Nidau",
    "sg:orig_category":"Allgemeiner Hoch U Tiefbau Hoch U Tiefbau",
    "sg:postcode":"2560",
    "sg:province":"Bern",
    "wof:name":"Gallus Heinz",
    "wof:placetype":"venue"
},
  "geometry": {"coordinates":[7.245872,47.120377],"type":"Point"}
}