{
  "type": "Feature",
  "properties": {
    "iso:country":"CH",
    "sg:address":"Bahnhofstrasse",
    "sg:city":"Laufen",
    "sg:orig_category":"Detailhandel mit Damenbekleidung",
    "sg:phone":"+41 61 761 32 42",
    "sg:postcode":"4242",
    "sg:province":"Basel-Landschaft",
    "wof:name":"Modeva Ag",
    "wof:placetype":"venue"
},
  "geometry": {"coordinates":[7.501459,47.420376],"type":"Point"}
}