{
  "type": "Feature",
  "properties": {
    "iso:country":"CH",
    "sg:address":"Oberebenestr. 57",
    "sg:city":"Bremgarten",
    "sg:classifiers":[
        {
            "category":"Home & Garden",
            "subcategory":"Furniture",
            "type":"Retail Goods"
        }
    ],
    "sg:phone":"+41 56 633 53 54",
    "sg:postcode":"5620",
    "sg:province":"Aargau",
    "sg:tags":[
        "wood"
    ],
    "wof:name":"Notter Ag",
    "wof:placetype":"venue"
},
  "geometry": {"coordinates":[8.3271389008,47.3515205383],"type":"Point"}
}