{
  "type": "Feature",
  "properties": {
    "iso:country":"CH",
    "sg:address":"Sonnengutstrasse 1 8363 Bichelsee. Postfach",
    "sg:city":"Bichelsee",
    "sg:orig_category":"Architektur U Ingenieurb\u00fcros",
    "sg:postcode":"8363",
    "sg:province":"Thurgau",
    "wof:name":"Niederer Rolf Ag",
    "wof:placetype":"venue"
},
  "geometry": {"coordinates":[8.928086,47.449875],"type":"Point"}
}