{
  "type": "Feature",
  "properties": {
    "iso:country":"CH",
    "sg:address":"Avenue De Rumine 64",
    "sg:city":"Lausanne",
    "sg:orig_category":"Gesundheitswesen",
    "sg:postcode":"1000",
    "sg:province":"Vaud",
    "wof:name":"Code Cabinet Ophtalmologique De L'esplanade S\u00e0rl",
    "wof:placetype":"venue"
},
  "geometry": {"coordinates":[6.6444530487,46.5155448914],"type":"Point"}
}