{
  "type": "Feature",
  "properties": {
    "iso:country":"CH",
    "sg:address":"S\u00e4gestrasse 17 8865 Bilten. Postfach 150",
    "sg:city":"Bilten",
    "sg:orig_category":"Non-Classified Establishments",
    "sg:phone":"+41 55 615 27 00",
    "sg:postcode":"8865",
    "sg:province":"Glarus",
    "wof:name":"Sbs Naturstein-bilten Ag Marmor-& Granitwerk",
    "wof:placetype":"venue"
},
  "geometry": {"coordinates":[9.0262145996,47.1531829834],"type":"Point"}
}