{
  "type": "Feature",
  "properties": {
    "iso:country":"CH",
    "sg:address":"Falkensteinerstrasse 6",
    "sg:city":"Basel",
    "sg:orig_category":"Architektur U Ingenieurb\u00fcros",
    "sg:postcode":"4053",
    "sg:province":"Basel-Stadt",
    "wof:name":"Cpc Chemical Engineering Sa",
    "wof:placetype":"venue"
},
  "geometry": {"coordinates":[6.56686,46.576405],"type":"Point"}
}