{
  "type": "Feature",
  "properties": {
    "iso:country":"CH",
    "sg:address":"Rindermarkt 26 8001 Z\u00fcrich. Postfach",
    "sg:city":"Z\u00fcrich",
    "sg:orig_category":"Herstellung von Haus, Bett U Tischw\u00e4sche Herstellung von konfektionierten Textilwaren ohne Bekleidun",
    "sg:phone":"+41 12512284",
    "sg:postcode":"8025",
    "wof:name":"Mertzlufft Storen Ag",
    "wof:placetype":"venue"
},
  "geometry": {"coordinates":[8.5454711914,47.3722953796],"type":"Point"}
}