{
  "type": "Feature",
  "properties": {
    "iso:country":"CH",
    "sg:address":"Hinterb\u00e4chlistrasse 5",
    "sg:city":"Oberrohrdorf",
    "sg:orig_category":"Primarschulen",
    "sg:phone":"+41 56 496 17 06",
    "sg:postcode":"5452",
    "sg:province":"Aargau",
    "wof:name":"Primarschule",
    "wof:placetype":"venue"
},
  "geometry": {"coordinates":[8.3155021667,47.4226570129],"type":"Point"}
}