{
  "type": "Feature",
  "properties": {
    "iso:country":"CH",
    "sg:address":"Lautengartenstrasse 14",
    "sg:city":"Basel",
    "sg:orig_category":"Fachdetailhandel in Verkaufsr\u00e4umen",
    "sg:phone":"+41 61 271 70 34",
    "sg:postcode":"4052",
    "sg:province":"Basel-Stadt",
    "wof:name":"Allflor Ag",
    "wof:placetype":"venue"
},
  "geometry": {"coordinates":[7.5967311859,47.5527000427],"type":"Point"}
}