{
  "type": "Feature",
  "properties": {
    "addr:full":"Rue Des Bercles 5 Neuch\u00e2tel Neuch\u00e2tel 2000",
    "addr:housenumber":"5",
    "addr:postcode":"2000",
    "addr:street":"Rue Des Bercles",
    "iso:country":"CH",
    "sg:address":"Rue Des Bercles 5",
    "sg:city":"Neuch\u00e2tel",
    "sg:orig_category":"Arztpraxen",
    "sg:phone":"+41 32 724 63 49",
    "sg:postcode":"2000",
    "sg:province":"Neuch\u00e2tel",
    "wof:name":"Dr M\u00e9d. Carole Weil M\u00e9decin Sp\u00e9cialiste Fmh",
    "wof:placetype":"venue"
},
  "geometry": {"coordinates":[6.927984,46.993279],"type":"Point"}
}