{
  "type": "Feature",
  "properties": {
    "iso:country":"CH",
    "sg:address":"3204 Rossh\u00e4usern. Postfach",
    "sg:city":"Rossh\u00e4usern",
    "sg:orig_category":"Herstellung von Konstruktionsteilen, Fertigbauteilen U Ausbauelementen aus Holz",
    "sg:postcode":"3204",
    "sg:province":"Bern",
    "wof:name":"R. + H. Bart Ag",
    "wof:placetype":"venue"
},
  "geometry": {"coordinates":[7.2762799263,46.9320983887],"type":"Point"}
}