{
  "type": "Feature",
  "properties": {
    "iso:country":"CH",
    "sg:address":"Waldrainstrasse 8",
    "sg:city":"K\u00f6niz",
    "sg:orig_category":"Sonstige Kurierdienste",
    "sg:postcode":"3098",
    "sg:province":"Bern",
    "wof:name":"Dex Kurier-service, Weitzel Sven",
    "wof:placetype":"venue"
},
  "geometry": {"coordinates":[7.4075942039,46.9247817993],"type":"Point"}
}