{
  "type": "Feature",
  "properties": {
    "iso:country":"CH",
    "sg:address":"Hirschmattstrasse 25 6003 Luzern. Postfach 4219",
    "sg:city":"Luzern",
    "sg:orig_category":"Detektivb\u00fcros U \u00dcberwachung",
    "sg:phone":"+41 800 808 590",
    "sg:postcode":"6002",
    "sg:province":"Luzern",
    "wof:name":"Securitas Ag Schweizerische Bewachungsgesellschaft",
    "wof:placetype":"venue"
},
  "geometry": {"coordinates":[8.3078231812,47.0472717285],"type":"Point"}
}