{
  "type": "Feature",
  "properties": {
    "iso:country":"CH",
    "sg:address":"Stapfenackerstrasse 72 3018 Bern. Postfach",
    "sg:city":"Bern",
    "sg:orig_category":"Wirtschaftspr\u00fcfung, Steuerberatung U Treuhand",
    "sg:phone":"+41 17613206",
    "sg:postcode":"3004",
    "sg:province":"Bern",
    "wof:name":"Treuhandb\u00fcro Kradolfer",
    "wof:placetype":"venue"
},
  "geometry": {"coordinates":[8.4863624573,47.2672576904],"type":"Point"}
}