{
  "type": "Feature",
  "properties": {
    "iso:country":"CH",
    "sg:address":"Luzernerstrasse 67",
    "sg:city":"Neudorf",
    "sg:orig_category":"Instandhaltung U Reparatur von Automobilen",
    "sg:phone":"+41 41 930 20 65",
    "sg:postcode":"6025",
    "sg:province":"Luzern",
    "wof:name":"Meier Carrosserie",
    "wof:placetype":"venue"
},
  "geometry": {"coordinates":[8.2169771194,47.1687507629],"type":"Point"}
}