{
  "type": "Feature",
  "properties": {
    "iso:country":"CH",
    "sg:address":"Bachstrasse 7",
    "sg:city":"Z\u00fcrich",
    "sg:orig_category":"Sonstige Kultur U Unterhaltungseinrichtungen",
    "sg:phone":"+41 13629944",
    "sg:postcode":"8038",
    "sg:province":"Z\u00fcrich",
    "wof:name":"Gemeinschaftszentr.wollishofen",
    "wof:placetype":"venue"
},
  "geometry": {"coordinates":[8.5353403091,47.3451576233],"type":"Point"}
}