{
  "type": "Feature",
  "properties": {
    "iso:country":"CH",
    "sg:address":"Chaley Route Joseph- 27",
    "sg:city":"Freiburg",
    "sg:orig_category":"Unclassifiable Establishments",
    "sg:postcode":"1700",
    "sg:province":"Fribourg",
    "wof:name":"March\u00e9 Biolley Schoenberg Sa",
    "wof:placetype":"venue"
},
  "geometry": {"coordinates":[7.1766881943,46.8055496216],"type":"Point"}
}