{
  "type": "Feature",
  "properties": {
    "iso:country":"CH",
    "sg:address":"Altmattweg 57 4600 Olten. Postfach",
    "sg:city":"Olten",
    "sg:orig_category":"Grosshandel mit B\u00fcromaschinen Grosshandel mit Datenverarbeitungsger\u00e4ten",
    "sg:phone":"+41 62 212 02 20",
    "sg:postcode":"4603",
    "sg:province":"Solothurn",
    "wof:name":"Baudata Buser",
    "wof:placetype":"venue"
},
  "geometry": {"coordinates":[7.8909368515,47.3491668701],"type":"Point"}
}