{
  "type": "Feature",
  "properties": {
    "iso:country":"CH",
    "sg:address":"Industriestrasse 11",
    "sg:city":"Langendorf",
    "sg:classifiers":[
        {
            "category":"Manufacturing",
            "subcategory":"Metals",
            "type":"Manufacturing & Wholesale Goods"
        }
    ],
    "sg:phone":"+41 32 618 21 38",
    "sg:postcode":"4513",
    "sg:province":"Solothurn",
    "sg:tags":[
        "finishing",
        "surface"
    ],
    "wof:name":"Strahltechnik Pfs Ag",
    "wof:placetype":"venue"
},
  "geometry": {"coordinates":[7.5115537643,47.216884613],"type":"Point"}
}