{
  "type": "Feature",
  "properties": {
    "iso:country":"CH",
    "sg:address":"Schulstrasse 637",
    "sg:city":"Wolfwil",
    "sg:classifiers":[
        {
            "category":"Arena",
            "subcategory":"Sports Club",
            "type":"Entertainment"
        }
    ],
    "sg:phone":"+41 62 398 40 01",
    "sg:postcode":"4628",
    "sg:province":"Solothurn",
    "sg:tags":[
        "karate",
        "judo",
        "sportvereine"
    ],
    "wof:name":"Karate-do Wolfwil",
    "wof:placetype":"venue"
},
  "geometry": {"coordinates":[7.7934141159,47.2696266174],"type":"Point"}
}