{
  "type": "Feature",
  "properties": {
    "iso:country":"CH",
    "sg:address":"Huguenin Rue Oscar- 14",
    "sg:city":"Boudry",
    "sg:orig_category":"Zimmerei, Dachdeckerei, Bauspenglerei U Abdichtung",
    "sg:postcode":"2017",
    "sg:province":"Neuch\u00e2tel",
    "wof:name":"Vuillemin Claude.",
    "wof:placetype":"venue"
},
  "geometry": {"coordinates":[7.0905928612,47.0661506653],"type":"Point"}
}