{
  "type": "Feature",
  "properties": {
    "iso:country":"CH",
    "sg:address":"Kirchgasse 6 9472 Grabs. Postfach",
    "sg:city":"Grabs",
    "sg:orig_category":"Sanit\u00e4r, Heizungs U L\u00fcftungsinstallation Sanit\u00e4rinstallation",
    "sg:phone":"+41 81 771 33 66",
    "sg:postcode":"9472",
    "sg:province":"St. Gallen",
    "wof:name":"Wettler Sanit\u00e4r & Heizung Ag",
    "wof:placetype":"venue"
},
  "geometry": {"coordinates":[9.4428453445,47.1811027527],"type":"Point"}
}