{
  "type": "Feature",
  "properties": {
    "addr:full":"Oberlandstrasse 23 Spiez Bern 3700",
    "addr:housenumber":"23",
    "addr:postcode":"3700",
    "addr:street":"Oberlandstrasse",
    "iso:country":"CH",
    "sg:address":"Oberlandstrasse 23",
    "sg:city":"Spiez",
    "sg:orig_category":"Architektur U Ingenieurb\u00fcros",
    "sg:phone":"+41 33 654 24 33",
    "sg:postcode":"3700",
    "sg:province":"Bern",
    "wof:name":"H\u00e4berli Markus Ag",
    "wof:placetype":"venue"
},
  "geometry": {"coordinates":[7.678127,46.688931],"type":"Point"}
}