{
  "type": "Feature",
  "properties": {
    "iso:country":"CH",
    "sg:address":"Binzm\u00fchlestrasse 48 8050 Z\u00fcrich. Postfach 8050 Z\u00fcrich",
    "sg:city":"Zust",
    "sg:classifiers":[
        {
            "category":"Travel",
            "subcategory":"Hotels & Motels",
            "type":"Entertainment"
        }
    ],
    "sg:postcode":"50",
    "sg:tags":[
        "hotels",
        "mit",
        "restaurant"
    ],
    "wof:name":"Gesellschaft F\u00fcr Selbsterkenntnis Durch Meditation (gsm) Ag",
    "wof:placetype":"venue"
},
  "geometry": {"coordinates":[8.5451107025,47.4139976501],"type":"Point"}
}