{
  "type": "Feature",
  "properties": {
    "iso:country":"CH",
    "sg:address":"Rietwiesenstrasse 10",
    "sg:city":"Kefikon",
    "sg:classifiers":[
        {
            "category":"Retail",
            "subcategory":"Repair Shop",
            "type":"Services"
        }
    ],
    "sg:phone":"+41 52 375 23 55",
    "sg:postcode":"8546",
    "sg:province":"Thurgau",
    "sg:tags":[
        "item",
        "decorating",
        "window"
    ],
    "wof:name":"Dekomat Ag",
    "wof:placetype":"venue"
},
  "geometry": {"coordinates":[8.833828,47.550213],"type":"Point"}
}