{
  "type": "Feature",
  "properties": {
    "iso:country":"CH",
    "sg:address":"Rue De La Moli\u00e8re 5 2800 Del\u00e9mont Case Postale 135",
    "sg:city":"Delsberg",
    "sg:orig_category":"Druck ohne Zeitungsdruck Offsetdruck",
    "sg:phone":"+41 32 422 11 49",
    "sg:postcode":"2800",
    "sg:province":"Jura",
    "wof:name":"Imprimerie Goffinet Sa",
    "wof:placetype":"venue"
},
  "geometry": {"coordinates":[7.3475117683,47.3637466431],"type":"Point"}
}