{
  "type": "Feature",
  "properties": {
    "iso:country":"CH",
    "sg:address":"1967",
    "sg:city":"Bramois",
    "sg:orig_category":"Wirtschafts- and Arbeitgeberverb\u00e4nde",
    "sg:phone":"+41 27 203 15 86",
    "sg:postcode":"1967",
    "sg:province":"Valais",
    "wof:name":"Gpe Des Producteurs De Fruits Varone & Cons.,bernard Varone",
    "wof:placetype":"venue"
},
  "geometry": {"coordinates":[7.4026799202,46.2301216125],"type":"Point"}
}