{
  "type": "Feature",
  "properties": {
    "iso:country":"CH",
    "sg:address":"Friedheimweg 53",
    "sg:city":"Bern",
    "sg:orig_category":"Sportvereine Turnen",
    "sg:phone":"+41 31 371 35 73",
    "sg:postcode":"3007",
    "sg:province":"Bern",
    "wof:name":"M\u00e4nnerturnverein Bern",
    "wof:placetype":"venue"
},
  "geometry": {"coordinates":[7.4381718636,46.9347877502],"type":"Point"}
}