{
  "type": "Feature",
  "properties": {
    "iso:country":"CH",
    "sg:address":"Kronbergstrasse 1a",
    "sg:city":"Amriswil",
    "sg:orig_category":"Verarbeitung von Milch Verwertung von Milch",
    "sg:phone":"+41 71 411 64 10",
    "sg:postcode":"8580",
    "sg:province":"Thurgau",
    "wof:name":"Wild Niklaus",
    "wof:placetype":"venue"
},
  "geometry": {"coordinates":[9.2939252853,47.554485321],"type":"Point"}
}