{
  "type": "Feature",
  "properties": {
    "iso:country":"CH",
    "sg:address":"Grand-rue 7",
    "sg:city":"Peseux",
    "sg:classifiers":[
        {
            "category":"Bars & Pubs",
            "type":"Food & Drink"
        }
    ],
    "sg:phone":"+41 32 731 75 75",
    "sg:postcode":"2034",
    "sg:province":"Neuch\u00e2tel",
    "wof:name":"Caf\u00e9 Bar Des Arcades S\u00e0rl",
    "wof:placetype":"venue"
},
  "geometry": {"coordinates":[6.887836,46.98682],"type":"Point"}
}