{
  "type": "Feature",
  "properties": {
    "iso:country":"CH",
    "sg:address":"Houelbachstrasse 8",
    "sg:city":"Kriens",
    "sg:orig_category":"Herstellung von konfektionierten Textilwaren ohne Bekleidung",
    "sg:postcode":"6010",
    "sg:province":"Luzern",
    "wof:name":"Alcu-tech Montagen Gmbh",
    "wof:placetype":"venue"
},
  "geometry": {"coordinates":[8.2714061737,47.0301513672],"type":"Point"}
}