{
  "type": "Feature",
  "properties": {
    "addr:full":"Hauptstrasse 48 Niedererlinsbach Solothurn 5015",
    "addr:housenumber":"48",
    "addr:postcode":"5015",
    "addr:street":"Hauptstrasse;Solothurn",
    "iso:country":"CH",
    "sg:address":"Hauptstrasse 48",
    "sg:city":"Niedererlinsbach",
    "sg:classifiers":[
        {
            "category":"Museum",
            "subcategory":"Art Museum",
            "type":"Entertainment"
        }
    ],
    "sg:phone":"+41 62 844 39 21",
    "sg:postcode":"5015",
    "sg:province":"Solothurn",
    "sg:tags":[
        "artwork"
    ],
    "wof:name":"D'arco Druck",
    "wof:placetype":"venue"
},
  "geometry": {"coordinates":[8.008598,47.400173],"type":"Point"}
}