{
  "type": "Feature",
  "properties": {
    "iso:country":"CH",
    "sg:address":"Neuenschwand 3536 Aeschau. Postfach",
    "sg:city":"Aeschau",
    "sg:orig_category":"Sonstige mit der Informatik verbundene T\u00e4tigkeiten",
    "sg:phone":"+41 34 497 22 55",
    "sg:postcode":"3536",
    "sg:province":"Bern",
    "wof:name":"Resphering, B\u00fchler Patrick",
    "wof:placetype":"venue"
},
  "geometry": {"coordinates":[7.7637271881,46.9094047546],"type":"Point"}
}