{
  "type": "Feature",
  "properties": {
    "iso:country":"CH",
    "sg:address":"Auhafenstrasse 51",
    "sg:city":"Muttenz",
    "sg:orig_category":"RESTAURANTS: TEA-ROOMS",
    "sg:phone":"+41 61 313 22 48",
    "sg:postcode":"4132",
    "sg:province":"Basel-Landschaft",
    "wof:name":"Restaurant Auhafen",
    "wof:placetype":"venue"
},
  "geometry": {"coordinates":[7.6526288986,47.545539856],"type":"Point"}
}