{
  "type": "Feature",
  "properties": {
    "iso:country":"CH",
    "sg:address":"Ringstrasse 3 2560 Nidau. Postfach",
    "sg:city":"Nidau",
    "sg:orig_category":"Detailhandel mit Schuhen U Lederwaren",
    "sg:phone":"+41 32 331 85 53",
    "sg:postcode":"2560",
    "sg:province":"Bern",
    "wof:name":"Inter-gaine Ag",
    "wof:placetype":"venue"
},
  "geometry": {"coordinates":[7.24038,47.125866],"type":"Point"}
}