{
  "type": "Feature",
  "properties": {
    "iso:country":"CH",
    "sg:address":"Reitimatt 8783 Linthal. Postfach",
    "sg:city":"Linthal",
    "sg:orig_category":"Erschliessung von Grundst\u00fccken",
    "sg:postcode":"8783",
    "sg:province":"Glarus",
    "wof:name":"Genossenschaft F\u00fcr Landwirtschaftliches Bauen Linthal Und Umgebung",
    "wof:placetype":"venue"
},
  "geometry": {"coordinates":[8.986125946,46.8920707703],"type":"Point"}
}