{
  "type": "Feature",
  "properties": {
    "addr:full":"Avenue Du Rothorn 10 Sierre Valais 3960",
    "addr:housenumber":"10",
    "addr:postcode":"3960",
    "addr:street":"Avenue Du Rothorn",
    "iso:country":"CH",
    "sg:address":"Avenue Du Rothorn 10",
    "sg:city":"Sierre",
    "sg:orig_category":"Detailhandel mit Damenbekleidung Detailhandel mit Herrenbekleidung",
    "sg:phone":"+41 32 913 81 23",
    "sg:postcode":"3960",
    "sg:province":"Valais",
    "wof:name":"Boutique Benetton",
    "wof:placetype":"venue"
},
  "geometry": {"coordinates":[6.830273,47.102707],"type":"Point"}
}