{
  "type": "Feature",
  "properties": {
    "addr:full":"Rue Du Rh\u00f4ne 86 Gen\u00e8ve Gen\u00e8ve 1204",
    "addr:housenumber":"86",
    "addr:postcode":"1204",
    "addr:street":"Rue Du Rho\u0302Ne",
    "iso:country":"CH",
    "sg:address":"Rue Du Rh\u00f4ne 86",
    "sg:city":"Gen\u00e8ve",
    "sg:classifiers":[
        {
            "category":"Banks & Credit Unions",
            "subcategory":"Bank",
            "type":"Services"
        }
    ],
    "sg:postcode":"1204",
    "sg:province":"Gen\u00e8ve",
    "wof:name":"Compagnie Bancaire Espirito Santo Sa",
    "wof:placetype":"venue"
},
  "geometry": {"coordinates":[6.633629,46.513535],"type":"Point"}
}