{
  "type": "Feature",
  "properties": {
    "addr:full":"Corso Pestalozzi 11 Lugano Ticino 6900",
    "addr:housenumber":"11",
    "addr:postcode":"6900",
    "addr:street":"Corso Pestalozzi",
    "iso:country":"CH",
    "sg:address":"Corso Pestalozzi 11",
    "sg:city":"Lugano",
    "sg:orig_category":"Advokaturb\u00fcros Notariate",
    "sg:phone":"+41 26 323 27 15",
    "sg:postcode":"6900",
    "sg:province":"Ticino",
    "wof:name":"R\u00e9mi Brodard Etude D'avocat & Notaire",
    "wof:placetype":"venue"
},
  "geometry": {"coordinates":[7.152463,46.799637],"type":"Point"}
}