{
  "type": "Feature",
  "properties": {
    "iso:country":"CH",
    "sg:address":"Unterfeldweg 17",
    "sg:city":"Gunzgen",
    "sg:orig_category":"Detailhandel mit Radio U Fernsehger\u00e4ten",
    "sg:phone":"+41 62 216 38 41",
    "sg:postcode":"4617",
    "sg:province":"Solothurn",
    "wof:name":"Hans Rufener Radio-television",
    "wof:placetype":"venue"
},
  "geometry": {"coordinates":[7.8328738213,47.3165779114],"type":"Point"}
}