{
  "type": "Feature",
  "properties": {
    "iso:country":"CH",
    "sg:address":"Untere Roostmatt 6",
    "sg:city":"Zug",
    "sg:orig_category":"Elektroinstallation",
    "sg:phone":"+41 41 720 09 06",
    "sg:postcode":"6300",
    "sg:province":"Zug",
    "wof:name":"Ossio D. Electronics",
    "wof:placetype":"venue"
},
  "geometry": {"coordinates":[8.5119132996,47.1566238403],"type":"Point"}
}