{
  "type": "Feature",
  "properties": {
    "iso:country":"CH",
    "sg:address":"M\u00fchlebachstrasse 1",
    "sg:city":"Flawil",
    "sg:orig_category":"Detailhandel mit Waren verschiedener Art, Hauptrichtung Nahrungsmittel",
    "sg:phone":"+41 71 385 55 25",
    "sg:postcode":"9230",
    "sg:province":"St. Gallen",
    "wof:name":"Spar-supermarkt",
    "wof:placetype":"venue"
},
  "geometry": {"coordinates":[9.2684783936,47.4150695801],"type":"Point"}
}