{
  "type": "Feature",
  "properties": {
    "iso:country":"CH",
    "sg:address":"Schwalbenweg 4",
    "sg:city":"Werdenberg",
    "sg:orig_category":"Herstellung von Reiseartikeln, Leder U Sattlerwaren Innendekorationsateliers",
    "sg:phone":"+41 81 771 29 48",
    "sg:postcode":"9470",
    "sg:province":"St. Gallen",
    "wof:name":"Ernst Rutz Sattlerei-polsterei",
    "wof:placetype":"venue"
},
  "geometry": {"coordinates":[9.4626512527,47.1728477478],"type":"Point"}
}