{
  "type": "Feature",
  "properties": {
    "iso:country":"CH",
    "sg:address":"Witikonerstrasse 499",
    "sg:city":"Z\u00fcrich",
    "sg:orig_category":"Herstellung von Metallkonstruktionen Verlegen von Fussboden",
    "sg:phone":"+41 13824741",
    "sg:postcode":"8053",
    "sg:province":"Z\u00fcrich",
    "wof:name":"Suter Baumontagen Gmbh Doppelbodensysteme; Montage. Deckenbau, Innenausbau Usw",
    "wof:placetype":"venue"
},
  "geometry": {"coordinates":[8.601184845,47.3617477417],"type":"Point"}
}