{
  "type": "Feature",
  "properties": {
    "iso:country":"CH",
    "sg:address":"Zielmatte 1",
    "sg:city":"Stansstad",
    "sg:orig_category":"Zahnarztpraxen",
    "sg:phone":"+41 33 951 29 51",
    "sg:postcode":"6362",
    "sg:province":"Nidwalden",
    "wof:name":"Dr.med.dent.predrag Marjanovic Zahnarzt",
    "wof:placetype":"venue"
},
  "geometry": {"coordinates":[8.0404491425,46.7549743652],"type":"Point"}
}