{
  "type": "Feature",
  "properties": {
    "iso:country":"CH",
    "sg:address":"1809",
    "sg:city":"Fenil-sur-corsier",
    "sg:orig_category":"D\u00e4mmung gegen K\u00e4lte, W\u00e4rme, Schall U Ersch\u00fctterung Herstellung von Konstruktionsteilen, Fertigbautei",
    "sg:phone":"+41 21 921 18 31",
    "sg:postcode":"1809",
    "sg:province":"Vaud",
    "wof:name":"Piralli Sa El\u00e9m\u00e9nts Pr\u00e9fabriqu\u00e9s En Pl\u00e2tre; Pose, Commerce",
    "wof:placetype":"venue"
},
  "geometry": {"coordinates":[6.8668298721,46.4836502075],"type":"Point"}
}