{
  "type": "Feature",
  "properties": {
    "iso:country":"CH",
    "sg:address":"Unter-altstadt 34",
    "sg:city":"Zug",
    "sg:orig_category":"Arztpraxen",
    "sg:phone":"+41 41 710 14 77",
    "sg:postcode":"6300",
    "sg:province":"Zug",
    "wof:name":"Dr.med.hansueli Bussmann Spezialarzt Fmh",
    "wof:placetype":"venue"
},
  "geometry": {"coordinates":[8.513876,47.16523],"type":"Point"}
}