{
  "type": "Feature",
  "properties": {
    "iso:country":"CH",
    "sg:address":"Unteres Ziel 4",
    "sg:city":"Appenzell",
    "sg:orig_category":"Instandhaltung U Reparatur von Automobilen",
    "sg:phone":"+41 71 787 30 63",
    "sg:postcode":"9050",
    "sg:province":"Appenzell Innerhoden",
    "wof:name":"Autospritzwerk Manser Karl",
    "wof:placetype":"venue"
},
  "geometry": {"coordinates":[9.4082012177,47.3346099854],"type":"Point"}
}