{
  "type": "Feature",
  "properties": {
    "iso:country":"CH",
    "sg:address":"Pavement Route Du 14",
    "sg:city":"Lausanne",
    "sg:orig_category":"Softwareentwicklung U beratung",
    "sg:phone":"+41 21 312 29 49",
    "sg:postcode":"1018",
    "sg:province":"Vaud",
    "wof:name":"Bb Soft, Bruno Barth\u00e9lemy",
    "wof:placetype":"venue"
},
  "geometry": {"coordinates":[6.6357631683,46.531211853],"type":"Point"}
}