{
  "type": "Feature",
  "properties": {
    "iso:country":"CH",
    "sg:address":"Alemannengasse 56",
    "sg:city":"Basel",
    "sg:orig_category":"Pensionskassen",
    "sg:phone":"+41 61 691 46 00",
    "sg:postcode":"4058",
    "sg:province":"Basel-Stadt",
    "wof:name":"Wohlfahrtsfonds Danzeisen S\u00f6hne Ag",
    "wof:placetype":"venue"
},
  "geometry": {"coordinates":[7.601875782,47.5575904846],"type":"Point"}
}