{
  "type": "Feature",
  "properties": {
    "iso:country":"CH",
    "sg:address":"B\u00e4chlihalde 2",
    "sg:city":"Rudolfstetten",
    "sg:orig_category":"Innendekorationsateliers",
    "sg:phone":"+41 56 633 83 53",
    "sg:postcode":"8964",
    "sg:province":"Aargau",
    "wof:name":"Armin Morgenthaler Innendekoration",
    "wof:placetype":"venue"
},
  "geometry": {"coordinates":[8.3781347275,47.3712043762],"type":"Point"}
}