{
  "type": "Feature",
  "properties": {
    "iso:country":"CH",
    "sg:address":"Route Du Buron",
    "sg:city":"Villars-le-terroir",
    "sg:orig_category":"Schmieden",
    "sg:phone":"+41 21 881 21 49",
    "sg:postcode":"1040",
    "sg:province":"Vaud",
    "wof:name":"G\u00e9rald Allaz Forge-mar\u00e9chalerie",
    "wof:placetype":"venue"
},
  "geometry": {"coordinates":[6.6268100739,46.6747436523],"type":"Point"}
}