{
  "type": "Feature",
  "properties": {
    "iso:country":"CH",
    "sg:address":"Schwalbenweg 43b",
    "sg:city":"Heimberg",
    "sg:orig_category":"Sanit\u00e4r, Heizungs U L\u00fcftungsinstallation Sanit\u00e4rinstallation",
    "sg:phone":"+41 33 437 54 65",
    "sg:postcode":"3627",
    "sg:province":"Bern",
    "wof:name":"Walter Stegmann Sanit\u00e4re Anlagen & Heizungen",
    "wof:placetype":"venue"
},
  "geometry": {"coordinates":[7.6075649261,46.7765083313],"type":"Point"}
}