{
  "type": "Feature",
  "properties": {
    "iso:country":"CH",
    "sg:address":"4437",
    "sg:city":"Waldenburg",
    "sg:orig_category":"Sportvereine Turnen Vereine Damen",
    "sg:phone":"+41 61 961 19 03",
    "sg:postcode":"4437",
    "sg:province":"Basel-Landschaft",
    "wof:name":"Damenriege",
    "wof:placetype":"venue"
},
  "geometry": {"coordinates":[7.7533798218,47.3781585693],"type":"Point"}
}