{
  "type": "Feature",
  "properties": {
    "iso:country":"CH",
    "sg:address":"Holbeinstrasse 102 4000 Basel. Postfach",
    "sg:city":"Basel",
    "sg:orig_category":"Interessenvertretungen",
    "sg:postcode":"4051",
    "sg:province":"Basel-Stadt",
    "wof:name":"Schutzverband Der Sairgroup-obligation\u00e4re Ssgo",
    "wof:placetype":"venue"
},
  "geometry": {"coordinates":[7.5814142227,47.5508499146],"type":"Point"}
}