{
  "type": "Feature",
  "properties": {
    "iso:country":"CH",
    "sg:address":"Scheitermatt 228",
    "sg:city":"Blumenstein",
    "sg:orig_category":"Instandhaltung U Reparatur von Automobilen",
    "sg:phone":"+41 33 356 32 43",
    "sg:postcode":"3638",
    "sg:province":"Bern",
    "wof:name":"Franz Rufener Garage & Baumaschinenservice",
    "wof:placetype":"venue"
},
  "geometry": {"coordinates":[7.5115709305,46.7368431091],"type":"Point"}
}