{
  "type": "Feature",
  "properties": {
    "iso:country":"CH",
    "sg:address":"Ursy-centre",
    "sg:city":"Ursy",
    "sg:orig_category":"Detailhandel mit Fleisch U Fleischwaren",
    "sg:phone":"+41 21 909 58 58",
    "sg:postcode":"1670",
    "sg:province":"Fribourg",
    "wof:name":"Bernadette Vorlet Boucherie",
    "wof:placetype":"venue"
},
  "geometry": {"coordinates":[6.8359251022,46.6341934204],"type":"Point"}
}