{
  "type": "Feature",
  "properties": {
    "iso:country":"CH",
    "sg:address":"R\u00fcmikerstrasse 5b",
    "sg:city":"R\u00e4terschen",
    "sg:orig_category":"Non-Classified Establishments",
    "sg:postcode":"8352",
    "sg:province":"Z\u00fcrich",
    "wof:name":"Restaurant R\u00fcmispitz, Waldenberger U. Partner",
    "wof:placetype":"venue"
},
  "geometry": {"coordinates":[8.7840900421,47.5038795471],"type":"Point"}
}