{
  "type": "Feature",
  "properties": {
    "iso:country":"CH",
    "sg:address":"Bruggwiesenstrasse 3",
    "sg:city":"Effretikon",
    "sg:orig_category":"Wirtschafts- and Arbeitgeberverb\u00e4nde",
    "sg:phone":"+41 71 343 10 27",
    "sg:postcode":"8307",
    "sg:province":"Z\u00fcrich",
    "wof:name":"Verb.schweiz.radiofachgesch. Fumagalli & Gonser Ag",
    "wof:placetype":"venue"
},
  "geometry": {"coordinates":[8.6858987808,47.4262428284],"type":"Point"}
}