{
  "type": "Feature",
  "properties": {
    "iso:country":"CH",
    "sg:address":"Via Boschetto 10",
    "sg:city":"Novazzano",
    "sg:orig_category":"Betrieb U technische Hilfsdienste des Kultur U Unterhaltungswesens",
    "sg:phone":"+41 91 796 18 63",
    "sg:postcode":"6883",
    "sg:province":"Ticino",
    "wof:name":"Trickster Teatro Sagl",
    "wof:placetype":"venue"
},
  "geometry": {"coordinates":[8.97706,45.840385],"type":"Point"}
}