{
  "type": "Feature",
  "properties": {
    "iso:country":"CH",
    "sg:address":"Rue Du Simplon 31",
    "sg:city":"Vevey",
    "sg:orig_category":"Detailhandel mit Lederwaren U Reiseartikeln Detailhandel mit Schuhen U Lederwaren",
    "sg:phone":"+41 21 921 20 87",
    "sg:postcode":"1800",
    "sg:province":"Vaud",
    "wof:name":"Dubois R. Et D.",
    "wof:placetype":"venue"
},
  "geometry": {"coordinates":[6.8443861008,46.4604606628],"type":"Point"}
}