{
  "type": "Feature",
  "properties": {
    "iso:country":"CH",
    "sg:address":"Dorfstrasse 1",
    "sg:city":"Urdorf",
    "sg:orig_category":"RESTAURANTS: TEA-ROOMS",
    "sg:phone":"+41 17341131",
    "sg:postcode":"8902",
    "sg:province":"Z\u00fcrich",
    "wof:name":"Jenny Frau A., Restaurant Pappel",
    "wof:placetype":"venue"
},
  "geometry": {"coordinates":[8.4183578491,47.390422821],"type":"Point"}
}