{
  "type": "Feature",
  "properties": {
    "addr:full":"Neuhausweg 25 3027 Bern. Postfach Bern Bern 3027",
    "addr:housenumber":"25",
    "addr:postcode":"3027;postfach;3027",
    "addr:street":"Neuhausweg",
    "iso:country":"CH",
    "sg:address":"Neuhausweg 25 3027 Bern. Postfach",
    "sg:city":"Bern",
    "sg:orig_category":"Detailhandel mit B\u00fcchern, Zeitungen, Schreib U Papeteriewaren",
    "sg:postcode":"3027",
    "sg:province":"Bern",
    "wof:name":"Grand Beat. B\u00fccher-vertrieb.",
    "wof:placetype":"venue"
},
  "geometry": {"coordinates":[7.394504,46.95015],"type":"Point"}
}