{
  "type": "Feature",
  "properties": {
    "iso:country":"CH",
    "sg:address":"Falknerstrasse 3 4000 Basel. Postfach",
    "sg:city":"Basel",
    "sg:orig_category":"Unternehmensberatung",
    "sg:postcode":"4001",
    "sg:province":"Basel-Stadt",
    "wof:name":"Grass & Partner Ag",
    "wof:placetype":"venue"
},
  "geometry": {"coordinates":[7.5889649391,47.5565605164],"type":"Point"}
}