{
  "type": "Feature",
  "properties": {
    "iso:country":"CH",
    "sg:address":"Avenue Des Morgines 1",
    "sg:city":"Petit-lancy",
    "sg:orig_category":"Detailhandel mit Waren verschiedener Art, Hauptrichtung Nahrungsmittel Sonstiger Fachdetailhandel mi",
    "sg:phone":"+41 32 931 19 65",
    "sg:postcode":"1213",
    "sg:province":"Gen\u00e8ve",
    "wof:name":"Louis-gilbert Simon-vermot Epicerie Primeurs",
    "wof:placetype":"venue"
},
  "geometry": {"coordinates":[6.754447937,47.0612106323],"type":"Point"}
}