{
  "type": "Feature",
  "properties": {
    "iso:country":"CH",
    "sg:address":"Lerchenplatz 5",
    "sg:city":"Meggen",
    "sg:orig_category":"Architektur U Ingenieurb\u00fcros Detailhandel mit Beleuchtungs U Haushaltsgegenst\u00e4nden",
    "sg:phone":"+41 41 377 08 02",
    "sg:postcode":"6045",
    "sg:province":"Luzern",
    "wof:name":"Alain Othenin-girard Architekturatelier Sia",
    "wof:placetype":"venue"
},
  "geometry": {"coordinates":[8.360952,47.04274],"type":"Point"}
}