{
  "type": "Feature",
  "properties": {
    "addr:full":"H\u00fchnerhubelstrasse 62 Belp Bern 3123",
    "addr:housenumber":"62",
    "addr:postcode":"3123",
    "addr:street":"Huehnerhubelstrasse",
    "iso:country":"CH",
    "sg:address":"H\u00fchnerhubelstrasse 62",
    "sg:city":"Belp",
    "sg:classifiers":[
        {
            "category":"Building & Trades",
            "subcategory":"Construction",
            "type":"Services"
        }
    ],
    "sg:phone":"+41 31 818 24 24",
    "sg:postcode":"3123",
    "sg:province":"Bern",
    "sg:tags":[
        "installation",
        "air-conditioning",
        "system"
    ],
    "wof:name":"Mmp Klima Ag",
    "wof:placetype":"venue"
},
  "geometry": {"coordinates":[7.495435,46.904728],"type":"Point"}
}