{
  "type": "Feature",
  "properties": {
    "iso:country":"CH",
    "sg:address":"Adlerfeldstrasse 72",
    "sg:city":"Frenkendorf",
    "sg:orig_category":"R\u00fcckgewinnung U Vorbereitung f\u00fcr die Wiederverwertung Recycling von nichtmetallischen Altmaterialien",
    "sg:phone":"+41 61 901 94 65",
    "sg:postcode":"4402",
    "sg:province":"Basel-Landschaft",
    "wof:name":"Reto Ag",
    "wof:placetype":"venue"
},
  "geometry": {"coordinates":[7.6957201958,47.5040283203],"type":"Point"}
}