{
  "type": "Feature",
  "properties": {
    "iso:country":"CH",
    "sg:address":"H\u00f6schgasse 66",
    "sg:city":"Z\u00fcrich",
    "sg:orig_category":"Interessenvertretungen",
    "sg:postcode":"8008",
    "sg:province":"Z\u00fcrich",
    "wof:name":"F\u00f6rderungs Und Unterst\u00fctzungsfonds Der Sektion Z\u00fcrich Des Sia",
    "wof:placetype":"venue"
},
  "geometry": {"coordinates":[8.5556850433,47.3579597473],"type":"Point"}
}