{
  "type": "Feature",
  "properties": {
    "iso:country":"CH",
    "sg:address":"Dorfstrasse 34",
    "sg:city":"Buchberg",
    "sg:orig_category":"Mechanische Werkst\u00e4tten",
    "sg:phone":"+41 18670850",
    "sg:postcode":"8454",
    "sg:province":"Schaffhausen",
    "wof:name":"Konrad Fehr Mechanische Werkstatt",
    "wof:placetype":"venue"
},
  "geometry": {"coordinates":[8.5637598038,47.5730133057],"type":"Point"}
}