{
  "type": "Feature",
  "properties": {
    "iso:country":"CH",
    "sg:address":"Eschenstrasse 34",
    "sg:city":"Thunstetten",
    "sg:orig_category":"Bau von Strassen, Sportanlagen U Bahnverkehrsstrecken Malerei",
    "sg:phone":"+41 62 963 20 40",
    "sg:postcode":"4922",
    "sg:province":"Bern",
    "wof:name":"Lenherr Markierungen Gmbh",
    "wof:placetype":"venue"
},
  "geometry": {"coordinates":[7.76116,47.205601],"type":"Point"}
}