{
  "type": "Feature",
  "properties": {
    "iso:country":"CH",
    "sg:address":"6301 Zug. Postfach 116",
    "sg:city":"Zug",
    "sg:orig_category":"Sportvereine Wassersport Schwimmen",
    "sg:phone":"+41 18692054",
    "sg:postcode":"6301",
    "sg:province":"Zug",
    "wof:name":"Slrg Sektion Rafzerfeld",
    "wof:placetype":"venue"
},
  "geometry": {"coordinates":[8.5015201569,47.6061706543],"type":"Point"}
}