{
  "type": "Feature",
  "properties": {
    "addr:full":"Bahnhofplatz 5 Adliswil Z\u00fcrich 8134",
    "addr:housenumber":"5",
    "addr:postcode":"8134",
    "addr:street":"Bahnhofplatz",
    "iso:country":"CH",
    "sg:address":"Bahnhofplatz 5",
    "sg:city":"Adliswil",
    "sg:classifiers":[
        {
            "category":"Education",
            "subcategory":"Library",
            "type":"Public Place"
        }
    ],
    "sg:phone":"+41 17117788",
    "sg:postcode":"8134",
    "sg:province":"Z\u00fcrich",
    "sg:tags":[
        "u",
        "bibliotheken",
        "archive"
    ],
    "wof:name":"Bibliothek/ludothek",
    "wof:placetype":"venue"
},
  "geometry": {"coordinates":[8.52532,47.312572],"type":"Point"}
}