{
  "type": "Feature",
  "properties": {
    "iso:country":"CH",
    "sg:address":"Hauptstrasse 19 8554 Eschikofen. Postfach",
    "sg:city":"Eschikofen",
    "sg:classifiers":[
        {
            "category":"Travel",
            "subcategory":"Hotels & Motels",
            "type":"Entertainment"
        }
    ],
    "sg:postcode":"8554",
    "sg:province":"Thurgau",
    "sg:tags":[
        "hotels",
        "mit",
        "restaurant"
    ],
    "wof:name":"Thurtal Gastronomie Gmbh Hotel, Restaurant Usw",
    "wof:placetype":"venue"
},
  "geometry": {"coordinates":[9.005317688,47.5806236267],"type":"Point"}
}