{
  "type": "Feature",
  "properties": {
    "iso:country":"CH",
    "sg:address":"W\u00e4ndh\u00fcslenstrasse",
    "sg:city":"Bubikon",
    "sg:orig_category":"Herstellung von Konstruktionsteilen, Fertigbauteilen U Ausbauelementen aus Holz",
    "sg:phone":"+41 55 243 36 00",
    "sg:postcode":"8608",
    "sg:province":"Z\u00fcrich",
    "wof:name":"Polyfen Gmbh",
    "wof:placetype":"venue"
},
  "geometry": {"coordinates":[8.8173131943,47.2808380127],"type":"Point"}
}