{
  "type": "Feature",
  "properties": {
    "iso:country":"CH",
    "sg:address":"Giacomettistrasse 34",
    "sg:city":"Chur",
    "sg:orig_category":"Detailhandel mit Waren verschiedener Art, Hauptrichtung Nahrungsmittel",
    "sg:phone":"+41 81 284 12 62",
    "sg:postcode":"7000",
    "sg:province":"Graubunden",
    "wof:name":"Denner Top Superdiscount",
    "wof:placetype":"venue"
},
  "geometry": {"coordinates":[9.5250301361,46.8619995117],"type":"Point"}
}