{
  "type": "Feature",
  "properties": {
    "iso:country":"CH",
    "sg:address":"Willadingweg 56 3006 Bern. Postfach",
    "sg:city":"Bern",
    "sg:orig_category":"Unternehmensberatung",
    "sg:phone":"+41 31 352 24 76",
    "sg:postcode":"3005",
    "sg:province":"Bern",
    "wof:name":"Heuer, Jack W. Unternehmensberatung",
    "wof:placetype":"venue"
},
  "geometry": {"coordinates":[7.4633398056,46.9355812073],"type":"Point"}
}