{
  "type": "Feature",
  "properties": {
    "iso:country":"CH",
    "sg:address":"In Der Gr\u00fcze 13",
    "sg:city":"D\u00fcbendorf",
    "sg:orig_category":"Stukkateurgewerbe, Gipserei U Verputzerei",
    "sg:phone":"+41 18218124",
    "sg:postcode":"8600",
    "sg:province":"Z\u00fcrich",
    "wof:name":"Casati & Stoller Gipsergesch\u00e4ft",
    "wof:placetype":"venue"
},
  "geometry": {"coordinates":[8.6214504242,47.3937759399],"type":"Point"}
}