{
  "type": "Feature",
  "properties": {
    "iso:country":"CH",
    "sg:address":"Quai De Nogent 5",
    "sg:city":"Yverdon-les-bains",
    "sg:orig_category":"Mechanik",
    "sg:phone":"+41 17641177",
    "sg:postcode":"1400",
    "sg:province":"Vaud",
    "wof:name":"H\u00e4berling Moritz Ag",
    "wof:placetype":"venue"
},
  "geometry": {"coordinates":[8.4977798462,47.2228088379],"type":"Point"}
}