{
  "type": "Feature",
  "properties": {
    "iso:country":"CH",
    "sg:address":"8832 Wollerau. Postfach 358",
    "sg:city":"Wollerau",
    "sg:orig_category":"Sportvereine Ballsport Tennis",
    "sg:phone":"+41 17846784",
    "sg:postcode":"8832",
    "sg:province":"Schwyz",
    "wof:name":"Tennsiclub Ried",
    "wof:placetype":"venue"
},
  "geometry": {"coordinates":[8.7199296951,47.1958427429],"type":"Point"}
}