{
  "type": "Feature",
  "properties": {
    "iso:country":"CH",
    "sg:address":"Storchengasse 15",
    "sg:city":"Z\u00fcrich",
    "sg:orig_category":"Herstellung von Schmuck, Gold U Silberschmiedwaren",
    "sg:phone":"+41 12210750",
    "sg:postcode":"8001",
    "sg:province":"Z\u00fcrich",
    "wof:name":"Murbach Rudolf, Nachfolger Meier Peter",
    "wof:placetype":"venue"
},
  "geometry": {"coordinates":[8.5413303375,47.3709640503],"type":"Point"}
}