{
  "type": "Feature",
  "properties": {
    "iso:country":"CH",
    "sg:address":"6963 Pregassona. Postfach Caselle Postale 151",
    "sg:city":"Pregassona",
    "sg:orig_category":"Sportvereine Triathlon Laufen, Schwimmen, Velo",
    "sg:postcode":"6963",
    "sg:province":"Ticino",
    "wof:name":"Triathlon Team Lugano",
    "wof:placetype":"venue"
},
  "geometry": {"coordinates":[8.9781703949,46.0223617554],"type":"Point"}
}