{
  "type": "Feature",
  "properties": {
    "iso:country":"CH",
    "sg:address":"Zi Les Petits-champs 13 1400 Yverdon-les-bains Case Postale",
    "sg:city":"Yverdon-les-bains",
    "sg:orig_category":"Druck ohne Zeitungsdruck",
    "sg:phone":"+41 24 425 90 19",
    "sg:postcode":"1400",
    "sg:province":"Vaud",
    "wof:name":"Fleury, Iph & Cie, Isenschmid Successeur",
    "wof:placetype":"venue"
},
  "geometry": {"coordinates":[6.6413450241,46.7651748657],"type":"Point"}
}