{
  "type": "Feature",
  "properties": {
    "iso:country":"CH",
    "sg:address":"Sch\u00fctzengasse 40",
    "sg:city":"Heiden",
    "sg:orig_category":"Fahrschulen, Flugschulen",
    "sg:phone":"+41 32 926 49 30",
    "sg:postcode":"9410",
    "sg:province":"Appenzell Ausserrhoden",
    "wof:name":"Paul-andr\u00e9 Freitag Auto-\u00e9cole",
    "wof:placetype":"venue"
},
  "geometry": {"coordinates":[6.8214588165,47.0893630981],"type":"Point"}
}