{
  "type": "Feature",
  "properties": {
    "iso:country":"CH",
    "sg:address":"Industriering 43",
    "sg:city":"Lyss",
    "sg:orig_category":"Grafikateliers, Design Webdesign",
    "sg:phone":"+41 32 623 27 45",
    "sg:postcode":"3250",
    "sg:province":"Bern",
    "wof:name":"Rdw Ryter Dokumentationen",
    "wof:placetype":"venue"
},
  "geometry": {"coordinates":[7.3057222366,47.0877685547],"type":"Point"}
}