{
  "type": "Feature",
  "properties": {
    "iso:country":"CH",
    "sg:address":"Hertizentrum 10 6300 Zug. Postfach 3353",
    "sg:city":"Zug",
    "sg:orig_category":"Kantonalbanken",
    "sg:phone":"+41 41 709 11 11",
    "sg:postcode":"6303",
    "sg:province":"Zug",
    "wof:name":"Zuger Kantonalbank",
    "wof:placetype":"venue"
},
  "geometry": {"coordinates":[8.505613327,47.1769218445],"type":"Point"}
}