{
  "type": "Feature",
  "properties": {
    "addr:full":"Schosshaldenstrasse 12 3006 Bern. Postfach Bern Bern 3005",
    "addr:housenumber":"12",
    "addr:postcode":"3006;postfach;3005",
    "addr:street":"Schosshaldenstrasse",
    "iso:country":"CH",
    "sg:address":"Schosshaldenstrasse 12 3006 Bern. Postfach",
    "sg:city":"Bern",
    "sg:orig_category":"Architektur U Ingenieurb\u00fcros",
    "sg:phone":"+41 31 351 90 30",
    "sg:postcode":"3005",
    "sg:province":"Bern",
    "wof:name":"Dimension X Ag",
    "wof:placetype":"venue"
},
  "geometry": {"coordinates":[7.462494,46.945297],"type":"Point"}
}