{
  "type": "Feature",
  "properties": {
    "iso:country":"CH",
    "sg:address":"St. Georgsweg 1",
    "sg:city":"Arth",
    "sg:orig_category":"Detailhandel Reparatur von Gebrauchsg\u00fctern Vermietung von Gebrauchsg\u00fctern",
    "sg:phone":"+41 41 855 20 59",
    "sg:postcode":"6415",
    "sg:province":"Schwyz",
    "wof:name":"Space Videothek",
    "wof:placetype":"venue"
},
  "geometry": {"coordinates":[8.5227909088,47.0615615845],"type":"Point"}
}