{
  "type": "Feature",
  "properties": {
    "iso:country":"CH",
    "sg:address":"Stampfistrasse 87b",
    "sg:city":"Summaprada",
    "sg:classifiers":[
        {
            "category":"Retail",
            "subcategory":"Auto Repair",
            "type":"Services"
        }
    ],
    "sg:phone":"+41 81 651 02 60",
    "sg:postcode":"7421",
    "sg:province":"Graubunden",
    "sg:tags":[
        "machine",
        "equipment",
        "anchor",
        "drilling"
    ],
    "wof:name":"Btd Bohrtechnik Ag",
    "wof:placetype":"venue"
},
  "geometry": {"coordinates":[9.433805,46.713943],"type":"Point"}
}