{
  "type": "Feature",
  "properties": {
    "addr:full":"Industriestrasse 7 Luzern Luzern 6005",
    "addr:housenumber":"7",
    "addr:postcode":"6005",
    "addr:street":"Industriestrasse",
    "iso:country":"CH",
    "sg:address":"Industriestrasse 7",
    "sg:city":"Luzern",
    "sg:classifiers":[
        {
            "category":"Banks & Credit Unions",
            "subcategory":"Bureau De Change",
            "type":"Services"
        }
    ],
    "sg:phone":"+41 32 637 59 59",
    "sg:postcode":"6005",
    "sg:province":"Luzern",
    "sg:tags":[
        "asbestos",
        "abatement"
    ],
    "wof:name":"Menz Ger\u00fcste Ag",
    "wof:placetype":"venue"
},
  "geometry": {"coordinates":[7.658335,47.231762],"type":"Point"}
}