{
  "type": "Feature",
  "properties": {
    "iso:country":"CH",
    "sg:address":"Schiltweid 2 6363 Obb\u00fcrgen. Postfach",
    "sg:city":"Obb\u00fcrgen",
    "sg:orig_category":"Interessenvertretungen",
    "sg:postcode":"6363",
    "sg:province":"Nidwalden",
    "wof:name":"Strassengenossenschaft Schiltweid F\u00fcrigen",
    "wof:placetype":"venue"
},
  "geometry": {"coordinates":[8.3625602722,46.9820289612],"type":"Point"}
}