{
  "type": "Feature",
  "properties": {
    "iso:country":"CH",
    "sg:address":"Pourtal\u00e8s Rue J.-l.- 10",
    "sg:city":"Neuch\u00e2tel",
    "sg:orig_category":"Herstellung von Konstruktionsteilen, Fertigbauteilen U Ausbauelementen aus Holz",
    "sg:phone":"+41 32 725 27 77",
    "sg:postcode":"2000",
    "sg:province":"Neuch\u00e2tel",
    "wof:name":"Sprunger S\u00e0rl",
    "wof:placetype":"venue"
},
  "geometry": {"coordinates":[6.9369449615,46.9926567078],"type":"Point"}
}