{
  "type": "Feature",
  "properties": {
    "iso:country":"CH",
    "sg:address":"Sporthotel R\u00fctti Gsteigstrass 3780 Gruben B. Gstaad. Postfach",
    "sg:city":"Sch\u00f6nried",
    "sg:orig_category":"RESTAURANTS: TEA-ROOMS",
    "sg:phone":"+41 27 957 20 44",
    "sg:postcode":"3778",
    "sg:province":"Bern",
    "wof:name":"Sporthotel Und Restaurant Christallina Bumann Christoph",
    "wof:placetype":"venue"
},
  "geometry": {"coordinates":[7.933672905,46.1117172241],"type":"Point"}
}