{
  "type": "Feature",
  "properties": {
    "iso:country":"CH",
    "sg:address":"Hauptstrasse 7",
    "sg:city":"Arbon",
    "sg:classifiers":[
        {
            "category":"Restaurant",
            "type":"Food & Drink"
        }
    ],
    "sg:phone":"+41 71 244 91 51",
    "sg:postcode":"9320",
    "sg:province":"Thurgau",
    "wof:name":"Restaurant Schweizerbund",
    "wof:placetype":"venue"
},
  "geometry": {"coordinates":[9.392074585,47.4361152649],"type":"Point"}
}