{
  "type": "Feature",
  "properties": {
    "iso:country":"CH",
    "sg:address":"Via Berna 9",
    "sg:city":"Lugano",
    "sg:orig_category":"Sonstiges Versicherungsgewerbe",
    "sg:phone":"+41 91 647 40 93",
    "sg:postcode":"6900",
    "sg:province":"Ticino",
    "wof:name":"Garanta (svizzera) Assicurazioni Sa",
    "wof:placetype":"venue"
},
  "geometry": {"coordinates":[8.9513425827,46.0101852417],"type":"Point"}
}