{
  "type": "Feature",
  "properties": {
    "iso:country":"CH",
    "sg:address":"Arcas 3.",
    "sg:city":"Chur",
    "sg:orig_category":"RESTAURANTS: TEA-ROOMS",
    "sg:postcode":"7000",
    "sg:province":"Graubunden",
    "wof:name":"Wolf Manfred.",
    "wof:placetype":"venue"
},
  "geometry": {"coordinates":[9.5317897797,46.847869873],"type":"Point"}
}