{
  "type": "Feature",
  "properties": {
    "addr:full":"Vordergasse 17 Neunkirch Schaffhausen 8213",
    "addr:housenumber":"17",
    "addr:postcode":"8213",
    "addr:street":"Vordergasse",
    "iso:country":"CH",
    "sg:address":"Vordergasse 17",
    "sg:city":"Neunkirch",
    "sg:orig_category":"Architekturb\u00fcros",
    "sg:phone":"+41 52 681 19 16",
    "sg:postcode":"8213",
    "sg:province":"Schaffhausen",
    "wof:name":"Alex Klingenfuss Architekturb\u00fcro",
    "wof:placetype":"venue"
},
  "geometry": {"coordinates":[8.499735,47.69014],"type":"Point"}
}