{
  "type": "Feature",
  "properties": {
    "addr:full":"F\u00fcrigen F\u00fcrigen Nidwalden 6363",
    "addr:postcode":"6363",
    "iso:country":"CH",
    "sg:address":"F\u00fcrigen",
    "sg:city":"F\u00fcrigen",
    "sg:classifiers":[
        {
            "category":"Travel",
            "subcategory":"Hotels & Motels",
            "type":"Entertainment"
        }
    ],
    "sg:phone":"+41 4112862222",
    "sg:postcode":"6363",
    "sg:province":"Nidwalden",
    "sg:tags":[
        "hotels",
        "business",
        "restaurant"
    ],
    "wof:name":"Hotel Gl\u00c4rnischhof",
    "wof:placetype":"venue"
},
  "geometry": {"coordinates":[8.537463,47.367569],"type":"Point"}
}