{
  "type": "Feature",
  "properties": {
    "iso:country":"CH",
    "sg:address":"Tannackerstrasse 2 3073 G\u00fcmligen. Postfach",
    "sg:city":"G\u00fcmligen",
    "sg:orig_category":"Sonstige mit Sport verbundene T\u00e4tigkeiten",
    "sg:postcode":"3073",
    "sg:province":"Bern",
    "wof:name":"Genossenschaft Clubhaus Fc Muri-g\u00fcmligen",
    "wof:placetype":"venue"
},
  "geometry": {"coordinates":[7.5081429482,46.9319572449],"type":"Point"}
}