{
  "type": "Feature",
  "properties": {
    "iso:country":"CH",
    "sg:address":"Rue De La Moli\u00e8re 22",
    "sg:city":"Del\u00e9mont",
    "sg:orig_category":"Versicherungen Generalagenturen",
    "sg:phone":"+41 32 727 60 60",
    "sg:postcode":"2800",
    "sg:province":"Jura",
    "wof:name":"La Mobili\u00e8re Assurances & Pr\u00e9voyance",
    "wof:placetype":"venue"
},
  "geometry": {"coordinates":[6.9294819832,46.9904098511],"type":"Point"}
}