{
  "type": "Feature",
  "properties": {
    "iso:country":"CH",
    "sg:address":"Chemin Du Bois-de-vaux 20",
    "sg:city":"Lausanne",
    "sg:classifiers":[
        {
            "category":"Travel",
            "subcategory":"Hotels & Motels",
            "type":"Entertainment"
        }
    ],
    "sg:phone":"+41 79 412 72 21",
    "sg:postcode":"1007",
    "sg:province":"Vaud",
    "sg:tags":[
        "hotels",
        "mit",
        "restaurant"
    ],
    "wof:name":"H\u00f4tel Relais Equestre",
    "wof:placetype":"venue"
},
  "geometry": {"coordinates":[6.9519948959,47.2108001709],"type":"Point"}
}