{
  "type": "Feature",
  "properties": {
    "iso:country":"CH",
    "sg:address":"Dorfstrasse 12",
    "sg:city":"Bauma",
    "sg:classifiers":[
        {
            "category":"Restaurant",
            "type":"Food & Drink"
        }
    ],
    "sg:phone":"+41 52 386 11 16",
    "sg:postcode":"8494",
    "sg:province":"Z\u00fcrich",
    "wof:name":"Restaurant Frohsinn",
    "wof:placetype":"venue"
},
  "geometry": {"coordinates":[8.8763856888,47.3676223755],"type":"Point"}
}