{
  "type": "Feature",
  "properties": {
    "iso:country":"CH",
    "sg:address":"Saleinaz",
    "sg:city":"Praz-de-fort",
    "sg:orig_category":"Museen",
    "sg:phone":"+41 21 799 14 12",
    "sg:postcode":"1943",
    "sg:province":"Valais",
    "wof:name":"Mus\u00e9e Maison Buttin-de-lo\u00ebs",
    "wof:placetype":"venue"
},
  "geometry": {"coordinates":[23.8774108887,47.1442298889],"type":"Point"}
}