{
  "type": "Feature",
  "properties": {
    "iso:country":"CH",
    "sg:address":"Grossholzstrasse 24",
    "sg:city":"Diessenhofen",
    "sg:orig_category":"Herstellung von Drahtwaren Herstellung von isolierten Elektrokabeln, -leitungen U dr\u00e4hten",
    "sg:phone":"+41 52 625 54 25",
    "sg:postcode":"8253",
    "sg:province":"Thurgau",
    "wof:name":"Lapp Kabel Ag",
    "wof:placetype":"venue"
},
  "geometry": {"coordinates":[8.7565402985,47.683429718],"type":"Point"}
}