{
  "type": "Feature",
  "properties": {
    "iso:country":"CH",
    "sg:address":"Niederlenzer-kirchweg",
    "sg:city":"Lenzburg",
    "sg:orig_category":"Detailhandel mit Brot, Back U S\u00fcsswaren Herstellung von Dauerbackwaren",
    "sg:phone":"+41 62 891 25 98",
    "sg:postcode":"5600",
    "sg:province":"Aargau",
    "wof:name":"Vatansever B\u00e4ckerei Gmbh",
    "wof:placetype":"venue"
},
  "geometry": {"coordinates":[8.1734609604,47.3915863037],"type":"Point"}
}