{
  "type": "Feature",
  "properties": {
    "iso:country":"CH",
    "sg:address":"Seestrasse 177",
    "sg:city":"Thalwil",
    "sg:orig_category":"Handel, Instandhaltung U Reparatur von Automobilen Tankstellen",
    "sg:phone":"+41 17200330",
    "sg:postcode":"8800",
    "sg:province":"Z\u00fcrich",
    "wof:name":"Ausee-garage Ag",
    "wof:placetype":"venue"
},
  "geometry": {"coordinates":[8.5623626709,47.3008308411],"type":"Point"}
}