{
  "type": "Feature",
  "properties": {
    "iso:country":"CH",
    "sg:address":"Seestrasse 78",
    "sg:city":"Gunten",
    "sg:orig_category":"Erbringung von Dienstleistungen f\u00fcr Unternehmen",
    "sg:phone":"+41 33 251 24 94",
    "sg:postcode":"3654",
    "sg:province":"Bern",
    "wof:name":"Atelier F\u00fcr Gestaltung R.guggisberg & L.steudler",
    "wof:placetype":"venue"
},
  "geometry": {"coordinates":[7.6976208687,46.7143096924],"type":"Point"}
}