{
  "type": "Feature",
  "properties": {
    "iso:country":"CH",
    "sg:address":"H\u00f6henstrasse Ost 75",
    "sg:city":"Olten",
    "sg:classifiers":[
        {
            "category":"Communications",
            "subcategory":"Film & Video Production",
            "type":"Services"
        }
    ],
    "sg:phone":"+41 62 296 41 85",
    "sg:postcode":"4600",
    "sg:province":"Solothurn",
    "sg:tags":[
        "videofilmherstellung",
        "u"
    ],
    "wof:name":"Film-& Videotechnik Berner",
    "wof:placetype":"venue"
},
  "geometry": {"coordinates":[7.9212827682,47.3452568054],"type":"Point"}
}