{
  "type": "Feature",
  "properties": {
    "addr:full":"Dammerkirchstrasse 17 Basel Basel-Stadt 4056",
    "addr:housenumber":"17",
    "addr:postcode":"4056",
    "addr:street":"Dammerkirchstrasse",
    "iso:country":"CH",
    "sg:address":"Dammerkirchstrasse 17",
    "sg:city":"Basel",
    "sg:orig_category":"Allgemeiner Hoch U Tiefbau Stukkateurgewerbe, Gipserei U Verputzerei",
    "sg:postcode":"4056",
    "sg:province":"Basel-Stadt",
    "wof:name":"Dumas Albert, Fassaden",
    "wof:placetype":"venue"
},
  "geometry": {"coordinates":[7.568039,47.567608],"type":"Point"}
}