{
  "type": "Feature",
  "properties": {
    "iso:country":"CH",
    "sg:address":"6720",
    "sg:city":"Ghirone",
    "sg:classifiers":[
        {
            "category":"Restaurant",
            "type":"Food & Drink"
        }
    ],
    "sg:phone":"+41 91 872 18 33",
    "sg:postcode":"6720",
    "sg:province":"Ticino",
    "wof:name":"Osteria Greina",
    "wof:placetype":"venue"
},
  "geometry": {"coordinates":[8.9437999725,46.5650482178],"type":"Point"}
}