{
  "type": "Feature",
  "properties": {
    "iso:country":"CH",
    "sg:address":"Alpenstrasse 14",
    "sg:city":"Zug",
    "sg:orig_category":"Advokaturb\u00fcros",
    "sg:phone":"+41 41 729 30 72",
    "sg:postcode":"6300",
    "sg:province":"Zug",
    "wof:name":"Dr.karel Zoller Advokaturb\u00fcro",
    "wof:placetype":"venue"
},
  "geometry": {"coordinates":[8.515057,47.172684],"type":"Point"}
}