{
  "type": "Feature",
  "properties": {
    "iso:country":"CH",
    "sg:address":"Morgenstrasse 136 A",
    "sg:city":"Bern",
    "sg:orig_category":"Handelsvermittlung U Grosshandel Sonstiger Grosshandel",
    "sg:phone":"+41 31 991 72 44",
    "sg:postcode":"3000",
    "sg:province":"Bern",
    "wof:name":"Tubidor Gmbh",
    "wof:placetype":"venue"
},
  "geometry": {"coordinates":[7.388299942,46.9342651367],"type":"Point"}
}