{
  "type": "Feature",
  "properties": {
    "iso:country":"CH",
    "sg:address":"7545",
    "sg:city":"Guarda",
    "sg:orig_category":"Bauschreinerei Herstellung von Konstruktionsteilen, Fertigbauteilen U Ausbauelementen aus Holz",
    "sg:phone":"+41 81 862 21 67",
    "sg:postcode":"7545",
    "sg:province":"Graubunden",
    "wof:name":"Paul Bonorand Schreinerei",
    "wof:placetype":"venue"
},
  "geometry": {"coordinates":[10.15055,46.775314],"type":"Point"}
}