{
  "type": "Feature",
  "properties": {
    "iso:country":"CH",
    "sg:address":"Hauptstrasse 102",
    "sg:city":"Rohr",
    "sg:classifiers":[
        {
            "category":"Banks & Credit Unions",
            "subcategory":"Financial Services",
            "type":"Services"
        }
    ],
    "sg:phone":"+41 62 824 14 07",
    "sg:postcode":"5032",
    "sg:province":"Aargau",
    "sg:tags":[
        "made",
        "door",
        "plastic"
    ],
    "wof:name":"Erich Gautschy",
    "wof:placetype":"venue"
},
  "geometry": {"coordinates":[8.09276,47.404587],"type":"Point"}
}