{
  "type": "Feature",
  "properties": {
    "iso:country":"CH",
    "sg:address":"Avenue De Frontenex 6",
    "sg:city":"Gen\u00e8ve",
    "sg:orig_category":"Detailhandel mit Damenbekleidung",
    "sg:phone":"+41 22 735 72 37",
    "sg:postcode":"1207",
    "sg:province":"Gen\u00e8ve",
    "wof:name":"Patricia Girardini Milano-roma Boutique",
    "wof:placetype":"venue"
},
  "geometry": {"coordinates":[6.157,46.201668],"type":"Point"}
}