{
  "type": "Feature",
  "properties": {
    "iso:country":"CH",
    "sg:address":"Avenue De S\u00e9cheron 6",
    "sg:city":"Gen\u00e8ve",
    "sg:classifiers":[
        {
            "category":"Airport",
            "type":"Transportation"
        }
    ],
    "sg:phone":"+41 22 906 15 15",
    "sg:postcode":"1202",
    "sg:province":"Gen\u00e8ve",
    "sg:tags":[
        "air-freight",
        "forwarders"
    ],
    "wof:name":"Natural Le Coultre S.a.",
    "wof:placetype":"venue"
},
  "geometry": {"coordinates":[6.149114,46.220501],"type":"Point"}
}