{
  "type": "Feature",
  "properties": {
    "iso:country":"CH",
    "sg:address":"Temple Rue Du 1",
    "sg:city":"Court",
    "sg:orig_category":"RESTAURANTS: TEA-ROOMS",
    "sg:postcode":"2738",
    "sg:province":"Bern",
    "wof:name":"Chapelot Meyer Florence",
    "wof:placetype":"venue"
},
  "geometry": {"coordinates":[7.3365769386,47.2393951416],"type":"Point"}
}