{
  "type": "Feature",
  "properties": {
    "iso:country":"CH",
    "sg:address":"Corso Enrico Pestalozzi 12",
    "sg:city":"Lugano",
    "sg:orig_category":"Nahrungsmittel-Industrie: Rohstoffe",
    "sg:phone":"+41 91 922 82 26",
    "sg:postcode":"6900",
    "sg:province":"Ticino",
    "wof:name":"Taqueria El Chilicuil Sagl",
    "wof:placetype":"venue"
},
  "geometry": {"coordinates":[8.9544916153,46.0055427551],"type":"Point"}
}