{
  "type": "Feature",
  "properties": {
    "iso:country":"CH",
    "sg:address":"St. Jodernstrasse 47",
    "sg:city":"Visp",
    "sg:orig_category":"Gesundheitswesen",
    "sg:phone":"+41 27 946 65 55",
    "sg:postcode":"3930",
    "sg:province":"Valais",
    "wof:name":"Ambulante Kinderkrankenpflege Oberwallis",
    "wof:placetype":"venue"
},
  "geometry": {"coordinates":[7.8847198486,46.2838783264],"type":"Point"}
}