{
  "type": "Feature",
  "properties": {
    "addr:full":"R\u00fcmelinsplatz 1 4001 Basel. Postfach Basel Basel-Stadt 4001",
    "addr:housenumber":"1",
    "addr:postcode":"4001;4001",
    "addr:street":"Ruemelinsplatz;Postfach",
    "iso:country":"CH",
    "sg:address":"R\u00fcmelinsplatz 1 4001 Basel. Postfach",
    "sg:city":"Basel",
    "sg:orig_category":"Detailhandel mit Damenbekleidung",
    "sg:phone":"+41 61 261 39 30",
    "sg:postcode":"4001",
    "sg:province":"Basel-Stadt",
    "wof:name":"R\u00fcmelin La Mode Ag Textilien, Bes. Damenkonfektion Usw; Herst., Handel Beteiligungen Usw",
    "wof:placetype":"venue"
},
  "geometry": {"coordinates":[7.587651,47.556561],"type":"Point"}
}