{
  "type": "Feature",
  "properties": {
    "addr:full":"Avenue De Beauregard 38 Fribourg Fribourg 1700",
    "addr:housenumber":"38",
    "addr:postcode":"1700",
    "addr:street":"Avenue De Beauregard",
    "iso:country":"CH",
    "sg:address":"Avenue De Beauregard 38",
    "sg:city":"Fribourg",
    "sg:orig_category":"Detailhandel mit Beleuchtungs U Haushaltsgegenst\u00e4nden Detailhandel mit Radio U Fernsehger\u00e4ten",
    "sg:phone":"+41 21 310 20 60",
    "sg:postcode":"1700",
    "sg:province":"Fribourg",
    "wof:name":"Radio Sonora Pellegrino Sa Mat\u00e9riels, Machines Et Appareils M\u00e9nagers Et De Divertissement Etc; Comm, Location",
    "wof:placetype":"venue"
},
  "geometry": {"coordinates":[6.627255,46.523022],"type":"Point"}
}