{
  "type": "Feature",
  "properties": {
    "iso:country":"CH",
    "sg:address":"Dorfstrasse 17",
    "sg:city":"Oberegg",
    "sg:orig_category":"Herstellung von medizinischen U chirurgischen Ger\u00e4ten sowie orthop\u00e4dischen Vorrichtungen Zahntechnis",
    "sg:phone":"+41 71 891 66 10",
    "sg:postcode":"9413",
    "sg:province":"Appenzell Innerhoden",
    "wof:name":"Ramadan Sadiku Zahntechnisches Labor",
    "wof:placetype":"venue"
},
  "geometry": {"coordinates":[9.5523891449,47.4222831726],"type":"Point"}
}