{
  "type": "Feature",
  "properties": {
    "iso:country":"CH",
    "sg:address":"Vuary 3",
    "sg:city":"Payerne",
    "sg:orig_category":"Architektur U Ingenieurb\u00fcros",
    "sg:phone":"+41 26 660 09 80",
    "sg:postcode":"1530",
    "sg:province":"Vaud",
    "wof:name":"Reymond Blaise",
    "wof:placetype":"venue"
},
  "geometry": {"coordinates":[6.934741,46.820869],"type":"Point"}
}