{
  "type": "Feature",
  "properties": {
    "iso:country":"CH",
    "sg:address":"Bahnhofstrasse",
    "sg:city":"Grossh\u00f6chstetten",
    "sg:orig_category":"Zimmerei, Dachdeckerei, Bauspenglerei U Abdichtung",
    "sg:postcode":"3506",
    "sg:province":"Bern",
    "wof:name":"Amstutz R.",
    "wof:placetype":"venue"
},
  "geometry": {"coordinates":[7.6371049881,46.9063110352],"type":"Point"}
}