{
  "type": "Feature",
  "properties": {
    "iso:country":"CH",
    "sg:address":"Grod 282",
    "sg:city":"Brittnau",
    "sg:orig_category":"Einzelhandel mit Automobilteilen U Zubeh\u00f6r Herstellung von Bereifungen",
    "sg:phone":"+41 41 670 23 77",
    "sg:postcode":"4805",
    "sg:province":"Aargau",
    "wof:name":"Prag Pneu Ruckstuhl Ag",
    "wof:placetype":"venue"
},
  "geometry": {"coordinates":[8.2753677368,46.9360389709],"type":"Point"}
}