{
  "type": "Feature",
  "properties": {
    "iso:country":"CH",
    "sg:address":"Kirchstrasse 10 9490 Vaduz. Postfach 930",
    "sg:city":"Vaduz",
    "sg:orig_category":"Versicherungen Generalagenturen",
    "sg:phone":"+41 75 384 20 75",
    "sg:postcode":"9490",
    "wof:name":"Winterthur-versicherungen Generalagentur",
    "wof:placetype":"venue"
},
  "geometry": {"coordinates":[9.520157814,47.1369247437],"type":"Point"}
}