{
  "type": "Feature",
  "properties": {
    "iso:country":"CH",
    "sg:address":"Untermattweg 8 3027 Bern. Postfach",
    "sg:city":"Bern",
    "sg:orig_category":"Grosshandel mit pharmazeutischen Erzeugnissen",
    "sg:phone":"+41 31 992 45 45",
    "sg:postcode":"3027",
    "sg:province":"Bern",
    "wof:name":"Solvay Pharma Ag Bet\u00e4tigung A Handels Und Industriellen Gebieten Der Pharmazie Usw",
    "wof:placetype":"venue"
},
  "geometry": {"coordinates":[7.40020895,46.9491577148],"type":"Point"}
}