{
  "type": "Feature",
  "properties": {
    "iso:country":"CH",
    "sg:address":"2052",
    "sg:city":"Fontainemelon",
    "sg:classifiers":[
        {
            "category":"Education",
            "subcategory":"Library",
            "type":"Public Place"
        }
    ],
    "sg:postcode":"2052",
    "sg:province":"Neuch\u00e2tel",
    "sg:tags":[
        "u",
        "bibliotheken",
        "archive"
    ],
    "wof:name":"Biblioth\u00e8que Populaire",
    "wof:placetype":"venue"
},
  "geometry": {"coordinates":[6.88933,47.055859],"type":"Point"}
}