{
  "type": "Feature",
  "properties": {
    "iso:country":"CH",
    "sg:address":"Via Luigi Canonica",
    "sg:city":"Lugano",
    "sg:orig_category":"Verwaltung von Immobilien",
    "sg:postcode":"6900",
    "sg:province":"Ticino",
    "wof:name":"Nicemont Sa",
    "wof:placetype":"venue"
},
  "geometry": {"coordinates":[8.9598503113,46.0068244934],"type":"Point"}
}