{
  "type": "Feature",
  "properties": {
    "iso:country":"CH",
    "sg:address":"Borde Rue De La 34c 1018 Lausanne. Postfach",
    "sg:city":"Lausanne",
    "sg:orig_category":"Grosshandel mit Holz U Baustoffen",
    "sg:postcode":"1002",
    "sg:province":"Vaud",
    "wof:name":"L\u00fcdi Und Zahnd",
    "wof:placetype":"venue"
},
  "geometry": {"coordinates":[7.5228800774,47.1698608398],"type":"Point"}
}