{
  "type": "Feature",
  "properties": {
    "iso:country":"CH",
    "sg:address":"St. Gallerstrasse 19 8353 Elgg. Postfach 22",
    "sg:city":"Elgg",
    "sg:orig_category":"G\u00fcterbef\u00f6rderung im Strassenverkehr Lagerung",
    "sg:phone":"+41 62 822 20 35",
    "sg:postcode":"8353",
    "sg:province":"Z\u00fcrich",
    "wof:name":"Bircher Transport Ag",
    "wof:placetype":"venue"
},
  "geometry": {"coordinates":[8.0715122223,47.3920135498],"type":"Point"}
}