{
  "type": "Feature",
  "properties": {
    "iso:country":"CH",
    "sg:address":"Neumattstrasse 13 3400 Burgdorf. Postfach",
    "sg:city":"Burgdorf",
    "sg:orig_category":"Elektroinstallation",
    "sg:phone":"+41 34 422 85 96",
    "sg:postcode":"3400",
    "sg:province":"Bern",
    "wof:name":"Elektro Wichelhaus",
    "wof:placetype":"venue"
},
  "geometry": {"coordinates":[7.611784935,47.0665740967],"type":"Point"}
}