{
  "type": "Feature",
  "properties": {
    "iso:country":"CH",
    "sg:address":"Malervastrasse 12a 7320 Sargans. Postfach",
    "sg:city":"Sargans",
    "sg:orig_category":"Mit dem Versicherungsgewerbe verbundene T\u00e4tigkeiten",
    "sg:phone":"+41 81 723 79 55",
    "sg:postcode":"7320",
    "sg:province":"St. Gallen",
    "wof:name":"Ovt Bircher Andy Consulting Versicherungstreuhand, Allfinenzberatung Usw.",
    "wof:placetype":"venue"
},
  "geometry": {"coordinates":[9.441860199,47.0493164062],"type":"Point"}
}