{
  "type": "Feature",
  "properties": {
    "iso:country":"CH",
    "sg:address":"Mittelg\u00e4ustrasse 52",
    "sg:city":"Gunzgen",
    "sg:classifiers":[
        {
            "category":"Banks & Credit Unions",
            "subcategory":"Bank",
            "type":"Services"
        }
    ],
    "sg:phone":"+41 26 674 30 30",
    "sg:postcode":"4617",
    "sg:province":"Solothurn",
    "wof:name":"Raiffeisenbank Gurmels",
    "wof:placetype":"venue"
},
  "geometry": {"coordinates":[7.17323,46.888309],"type":"Point"}
}