{
  "type": "Feature",
  "properties": {
    "iso:country":"CH",
    "sg:address":"Untergummeln 6018 Buttisholz. Postfach 22",
    "sg:city":"Buttisholz",
    "sg:orig_category":"Unclassifiable Establishments",
    "sg:postcode":"6018",
    "sg:province":"Luzern",
    "wof:name":"J\u00fcrg Tschannen & Pia Jaeger",
    "wof:placetype":"venue"
},
  "geometry": {"coordinates":[7.4019579887,46.7949676514],"type":"Point"}
}