{
  "type": "Feature",
  "properties": {
    "iso:country":"CH",
    "sg:address":"Rue De Fer 13",
    "sg:city":"Del\u00e9mont",
    "sg:classifiers":[
        {
            "category":"Education",
            "subcategory":"Library",
            "type":"Public Place"
        }
    ],
    "sg:phone":"+41 32 931 35 31",
    "sg:postcode":"2800",
    "sg:province":"Jura",
    "sg:tags":[
        "u",
        "bibliotheken",
        "archive"
    ],
    "wof:name":"Biblioth\u00e8que Des Jeunes",
    "wof:placetype":"venue"
},
  "geometry": {"coordinates":[6.750088,47.058556],"type":"Point"}
}