{
  "type": "Feature",
  "properties": {
    "iso:country":"CH",
    "sg:address":"Route De Malagnou 6",
    "sg:city":"Gen\u00e8ve",
    "sg:classifiers":[
        {
            "category":"Banks & Credit Unions",
            "subcategory":"Bank",
            "type":"Services"
        }
    ],
    "sg:phone":"+41 22 839 44 00",
    "sg:postcode":"1208",
    "sg:province":"Gen\u00e8ve",
    "wof:name":"Mees Pierson (suisse) Sa",
    "wof:placetype":"venue"
},
  "geometry": {"coordinates":[6.157469,46.198345],"type":"Point"}
}