{
  "type": "Feature",
  "properties": {
    "iso:country":"CH",
    "sg:address":"Rue De Neuch\u00e2tel 15a",
    "sg:city":"St-blaise",
    "sg:orig_category":"Herstellung anderer Uhrenbestandteile Herstellung von Uhren",
    "sg:phone":"+41 32 913 27 88",
    "sg:postcode":"2072",
    "sg:province":"Neuch\u00e2tel",
    "wof:name":"Revor, Brusa Walter",
    "wof:placetype":"venue"
},
  "geometry": {"coordinates":[6.819549,47.102146],"type":"Point"}
}