{
  "type": "Feature",
  "properties": {
    "iso:country":"CH",
    "sg:address":"Konsumstrasse 20",
    "sg:city":"Uzwil",
    "sg:orig_category":"G\u00fcterbef\u00f6rderung im Strassenverkehr",
    "sg:phone":"+41 71 923 51 51",
    "sg:postcode":"9240",
    "sg:province":"St. Gallen",
    "wof:name":"Sutter Internationale Transport Ag",
    "wof:placetype":"venue"
},
  "geometry": {"coordinates":[9.0759983063,47.4403686523],"type":"Point"}
}