{
  "type": "Feature",
  "properties": {
    "iso:country":"CH",
    "sg:address":"Vorstadt 8",
    "sg:city":"Egerkingen",
    "sg:classifiers":[
        {
            "category":"Restaurant",
            "type":"Food & Drink"
        }
    ],
    "sg:phone":"+41 62 398 15 54",
    "sg:postcode":"4622",
    "sg:province":"Solothurn",
    "wof:name":"Restaurant Sternen",
    "wof:placetype":"venue"
},
  "geometry": {"coordinates":[7.793762207,47.3239173889],"type":"Point"}
}