{
  "type": "Feature",
  "properties": {
    "iso:country":"CH",
    "sg:address":"Rathausgasse 29",
    "sg:city":"Aarau",
    "sg:orig_category":"Allgemeiner Hoch U Tiefbau",
    "sg:phone":"+41 62 822 11 77",
    "sg:postcode":"5000",
    "sg:province":"Aargau",
    "wof:name":"Waldburger & Partner Ag",
    "wof:placetype":"venue"
},
  "geometry": {"coordinates":[8.044198,47.392441],"type":"Point"}
}