{
  "type": "Feature",
  "properties": {
    "iso:country":"CH",
    "sg:address":"Route Du Simplon",
    "sg:city":"Bex",
    "sg:orig_category":"Architektur U Ingenieurb\u00fcros",
    "sg:phone":"+41 24 472 81 86",
    "sg:postcode":"1880",
    "sg:province":"Vaud",
    "wof:name":"A Sa, Succursale De Collombey",
    "wof:placetype":"venue"
},
  "geometry": {"coordinates":[6.933785,46.280434],"type":"Point"}
}