{
  "type": "Feature",
  "properties": {
    "iso:country":"CH",
    "sg:address":"4654",
    "sg:city":"Lostorf",
    "sg:orig_category":"Vereine Gesang",
    "sg:phone":"+41 62 291 12 16",
    "sg:postcode":"4654",
    "sg:province":"Solothurn",
    "wof:name":"Reformierter Kirchenchor",
    "wof:placetype":"venue"
},
  "geometry": {"coordinates":[7.9811601639,47.3500900269],"type":"Point"}
}