{
  "type": "Feature",
  "properties": {
    "addr:full":"Bahnhof Glarus Glarus 8750",
    "addr:postcode":"8750",
    "addr:street":"Glarus Glarus",
    "iso:country":"CH",
    "sg:address":"Bahnhof",
    "sg:city":"Glarus",
    "sg:orig_category":"Bahnhofbuffets",
    "sg:phone":"+41 27 932 12 68",
    "sg:postcode":"8750",
    "sg:province":"Glarus",
    "wof:name":"Buffet Gampel-steg",
    "wof:placetype":"venue"
},
  "geometry": {"coordinates":[7.750284,46.306492],"type":"Point"}
}