{
  "type": "Feature",
  "properties": {
    "iso:country":"CH",
    "sg:address":"Spalenberg 41",
    "sg:city":"Basel",
    "sg:orig_category":"Fachdetailhandel mit pharmazeutischen Produkten",
    "sg:phone":"+41 19100404",
    "sg:postcode":"4051",
    "sg:province":"Basel-Stadt",
    "wof:name":"Apotheke Hotz K\u00fcsnacht, Nachfolgerin B. Bretscher-hotz",
    "wof:placetype":"venue"
},
  "geometry": {"coordinates":[8.5815420151,47.3186225891],"type":"Point"}
}