{
  "type": "Feature",
  "properties": {
    "iso:country":"CH",
    "sg:address":"Route De Platy 38",
    "sg:city":"Villars-sur-gl\u00e2ne",
    "sg:orig_category":"Fahrschulen, Flugschulen",
    "sg:phone":"+41 26 402 14 54",
    "sg:postcode":"1752",
    "sg:province":"Fribourg",
    "wof:name":"Auguste Chassot Auto-\u00e9cole Tcr",
    "wof:placetype":"venue"
},
  "geometry": {"coordinates":[7.1323800087,46.7894096375],"type":"Point"}
}