{
  "type": "Feature",
  "properties": {
    "iso:country":"CH",
    "sg:address":"Ch. De Sauges 14",
    "sg:city":"Boudry",
    "sg:orig_category":"Sanit\u00e4r, Heizungs U L\u00fcftungsinstallation",
    "sg:postcode":"2017",
    "sg:province":"Neuch\u00e2tel",
    "wof:name":"F. Borgeat Chauffage",
    "wof:placetype":"venue"
},
  "geometry": {"coordinates":[6.8511691093,46.9524917603],"type":"Point"}
}