{
  "type": "Feature",
  "properties": {
    "iso:country":"CH",
    "sg:address":"Im Gr\u00fcene 35",
    "sg:city":"Uster",
    "sg:orig_category":"Sportvereine Turnen Vereine Damen",
    "sg:postcode":"8610",
    "sg:province":"Z\u00fcrich",
    "wof:name":"Damenturnverein Tv Uster",
    "wof:placetype":"venue"
},
  "geometry": {"coordinates":[8.7005653381,47.3500900269],"type":"Point"}
}