{
  "type": "Feature",
  "properties": {
    "iso:country":"CH",
    "sg:address":"6370 Stans. Postfach 923",
    "sg:city":"Stans",
    "sg:orig_category":"Politische Parteien SP",
    "sg:phone":"+41 52 741 15 11",
    "sg:postcode":"6371",
    "sg:province":"Nidwalden",
    "wof:name":"Sp Des Kantons Schaffhausen",
    "wof:placetype":"venue"
},
  "geometry": {"coordinates":[8.8517971039,47.6556015015],"type":"Point"}
}