{
  "type": "Feature",
  "properties": {
    "iso:country":"CH",
    "sg:address":"Halmacker 352",
    "sg:city":"Oberbuchsiten",
    "sg:orig_category":"Unclassifiable Establishments",
    "sg:postcode":"4625",
    "sg:province":"Solothurn",
    "wof:name":"Hirschi's Dienstleistungen",
    "wof:placetype":"venue"
},
  "geometry": {"coordinates":[7.772465229,47.3049468994],"type":"Point"}
}