{
  "type": "Feature",
  "properties": {
    "addr:full":"Le Ch\u00e2ble Valais 1934",
    "addr:postcode":"1934",
    "iso:country":"CH",
    "sg:city":"Le Ch\u00e2ble",
    "sg:classifiers":[
        {
            "category":"Banks & Credit Unions",
            "subcategory":"Bank",
            "type":"Services"
        }
    ],
    "sg:phone":"+41 27 776 19 20",
    "sg:postcode":"1934",
    "sg:province":"Valais",
    "wof:name":"Banque Cantonale Du Valais",
    "wof:placetype":"venue"
},
  "geometry": {"coordinates":[7.212595,46.080231],"type":"Point"}
}