{
  "type": "Feature",
  "properties": {
    "iso:country":"CH",
    "sg:address":"Dorfstrasse 29 6300 Zug. Postfach",
    "sg:city":"Zug",
    "sg:orig_category":"Non-Classified Establishments",
    "sg:postcode":"6300",
    "sg:province":"Zug",
    "wof:name":"Dbhz Holding Ag Gesellschaften; Erwerb, Beteiligung, Gr\u00fcndung, Finanzierung Usw",
    "wof:placetype":"venue"
},
  "geometry": {"coordinates":[8.5172595978,47.1645965576],"type":"Point"}
}