{
  "type": "Feature",
  "properties": {
    "iso:country":"CH",
    "sg:address":"Rue Du Bourg 1323 Romainm\u00f4tier. Postfach",
    "sg:city":"Romainm\u00f4tier",
    "sg:orig_category":"Non-Classified Establishments",
    "sg:postcode":"1323",
    "sg:province":"Vaud",
    "wof:name":"Didwedo, Gaudard M. Strat\u00e9gies De Communication, Multim\u00e9dia, Etc.; Cr\u00e9ation, D\u00e9veloppement Et Int\u00e9gration",
    "wof:placetype":"venue"
},
  "geometry": {"coordinates":[6.4622240067,46.6938095093],"type":"Point"}
}