{
  "type": "Feature",
  "properties": {
    "iso:country":"CH",
    "sg:address":"Bachstrasse 44",
    "sg:city":"Schaffhausen",
    "sg:orig_category":"Unclassifiable Establishments",
    "sg:postcode":"8200",
    "sg:province":"Schaffhausen",
    "wof:name":"Behrend Ag Heizungen & L\u00fcftungen",
    "wof:placetype":"venue"
},
  "geometry": {"coordinates":[7.5847458839,47.4971466064],"type":"Point"}
}