{
  "type": "Feature",
  "properties": {
    "iso:country":"CH",
    "sg:address":"Hauptstrasse 35 8750 Glarus. Postfach",
    "sg:city":"Glarus",
    "sg:orig_category":"Finanzierungsinstitutionen Wirtschaftspr\u00fcfung, Steuerberatung U Treuhand",
    "sg:phone":"+41 55 650 10 38",
    "sg:postcode":"8750",
    "sg:province":"Glarus",
    "wof:name":"Allfinanz-zentrum Glarus - Baitella & Tr\u00fcmpi Allfinanzberatungs, -planungs, -vermittlungs- U. -verwaltungsb\u00fcros F\u00fcr Private U. Unternehmungen Usw.",
    "wof:placetype":"venue"
},
  "geometry": {"coordinates":[9.0675516129,47.040271759],"type":"Point"}
}