{
  "type": "Feature",
  "properties": {
    "iso:country":"CH",
    "sg:address":"Luserte Via 7b 6572 Quartino. Postfach",
    "sg:city":"Quartino",
    "sg:orig_category":"Non-Classified Establishments",
    "sg:postcode":"6572",
    "sg:province":"Ticino",
    "wof:name":"Nw Holding Sa Partecipazione Ad Imprese Industriali Ecc",
    "wof:placetype":"venue"
},
  "geometry": {"coordinates":[8.9112138748,46.1508293152],"type":"Point"}
}