{
  "type": "Feature",
  "properties": {
    "iso:country":"CH",
    "sg:address":"Landstrasse 34 9494 Schaan. Postfach 556",
    "sg:city":"Schaan",
    "sg:orig_category":"Elektrizit\u00e4tsversorgung Elektroinstallation",
    "sg:phone":"+41 27 722 37 48",
    "sg:postcode":"9494",
    "wof:name":"Luyet Michel Et Fils",
    "wof:placetype":"venue"
},
  "geometry": {"coordinates":[7.0691509247,46.0968666077],"type":"Point"}
}