{
  "type": "Feature",
  "properties": {
    "iso:country":"CH",
    "sg:address":"Micheli-du-crest Rue 4 1205 Gen\u00e8ve. Postfach",
    "sg:city":"Gen\u00e8ve",
    "sg:orig_category":"Non-Classified Establishments",
    "sg:postcode":"1205",
    "sg:province":"Gen\u00e8ve",
    "wof:name":"Winx Ag",
    "wof:placetype":"venue"
},
  "geometry": {"coordinates":[8.7837400436,47.1990585327],"type":"Point"}
}