{
  "type": "Feature",
  "properties": {
    "iso:country":"CH",
    "sg:address":"H\u00f6henweg 32",
    "sg:city":"Bettlach",
    "sg:orig_category":"G\u00fcterbef\u00f6rderung im Strassenverkehr",
    "sg:phone":"+41 32 645 16 41",
    "sg:postcode":"2544",
    "sg:province":"Solothurn",
    "wof:name":"Heinz Moll Transporte",
    "wof:placetype":"venue"
},
  "geometry": {"coordinates":[7.4105291367,47.2079315186],"type":"Point"}
}