{
  "type": "Feature",
  "properties": {
    "iso:country":"CH",
    "sg:address":"Hauptstrasse 10 9562 Buch B. M\u00e4rwil. Postfach",
    "sg:city":"M\u00e4rwil",
    "sg:orig_category":"Herstellung von Bergwerks U Baumaschinen",
    "sg:postcode":"9562",
    "sg:province":"Thurgau",
    "wof:name":"Desax M. Bauaufz\u00fcge Und Bauger\u00e4te",
    "wof:placetype":"venue"
},
  "geometry": {"coordinates":[9.0563354492,47.5365982056],"type":"Point"}
}