{
  "type": "Feature",
  "properties": {
    "iso:country":"CH",
    "sg:address":"Leuenweg 4 5022 Rombach. Postfach",
    "sg:city":"Rombach",
    "sg:orig_category":"Herstellung von sonstigen chemischen Erzeugnissen",
    "sg:postcode":"5022",
    "sg:province":"Aargau",
    "wof:name":"A-tech Rota Marcel",
    "wof:placetype":"venue"
},
  "geometry": {"coordinates":[8.047246933,47.4036254883],"type":"Point"}
}