{
  "type": "Feature",
  "properties": {
    "iso:country":"CH",
    "sg:address":"Bahnhofstrasse 15 8852 Altendorf. Postfach",
    "sg:city":"Altendorf",
    "sg:orig_category":"Erwachsenenbildung U Unterricht",
    "sg:phone":"+41 55 442 24 66",
    "sg:postcode":"8852",
    "sg:province":"Schwyz",
    "wof:name":"Huesmann + Benz, Didacconsult Management Consulting, Lernmedienberatung, Lernmedienentwicklung Usw",
    "wof:placetype":"venue"
},
  "geometry": {"coordinates":[8.8223829269,47.1933860779],"type":"Point"}
}