{
  "type": "Feature",
  "properties": {
    "addr:full":"Voltastrasse 1 Z\u00fcrich Z\u00fcrich 8044",
    "addr:housenumber":"1",
    "addr:postcode":"8044",
    "addr:street":"Voltastrasse",
    "iso:country":"CH",
    "sg:address":"Voltastrasse 1",
    "sg:city":"Z\u00fcrich",
    "sg:orig_category":"Architekturb\u00fcros",
    "sg:phone":"+41 12423791",
    "sg:postcode":"8044",
    "sg:province":"Z\u00fcrich",
    "wof:name":"Schader, Hegnauer, Ammann Architekten Ag Architekturauftr\u00e4ge Usw",
    "wof:placetype":"venue"
},
  "geometry": {"coordinates":[8.555295,47.376865],"type":"Point"}
}