{
  "type": "Feature",
  "properties": {
    "iso:country":"CH",
    "sg:address":"R\u00e9sidence Bernerhof",
    "sg:city":"Kandersteg",
    "sg:orig_category":"Arztpraxen",
    "sg:phone":"+41 17151484",
    "sg:postcode":"3718",
    "sg:province":"Bern",
    "wof:name":"Dr.med.lorenz Felder Arzt F\u00fcr Allgemeine Medizin",
    "wof:placetype":"venue"
},
  "geometry": {"coordinates":[8.547991,47.31937],"type":"Point"}
}