{
  "type": "Feature",
  "properties": {
    "iso:country":"CH",
    "sg:address":"Obernauerstrasse 45",
    "sg:city":"Kriens",
    "sg:orig_category":"Detailhandel mit B\u00fcchern, Zeitungen, Schreib U Papeteriewaren",
    "sg:phone":"+41 41 320 00 80",
    "sg:postcode":"6010",
    "sg:province":"Luzern",
    "wof:name":"Buch C Buchhandlung Clausetto S. Bissig & Co",
    "wof:placetype":"venue"
},
  "geometry": {"coordinates":[8.26503,47.034325],"type":"Point"}
}