{
  "type": "Feature",
  "properties": {
    "iso:country":"CH",
    "sg:address":"Binningerstrasse 112",
    "sg:city":"Allschwil",
    "sg:orig_category":"Detailhandel mit Getr\u00e4nken",
    "sg:phone":"+41 61 481 34 75",
    "sg:postcode":"4123",
    "sg:province":"Basel-Landschaft",
    "wof:name":"Ren\u00e9's Getr\u00e4nkemarkt Gmbh",
    "wof:placetype":"venue"
},
  "geometry": {"coordinates":[7.5507230759,47.5469703674],"type":"Point"}
}