{
  "type": "Feature",
  "properties": {
    "iso:country":"CH",
    "sg:address":"Huttwilstrasse 11",
    "sg:city":"Lotzwil",
    "sg:orig_category":"Detailhandel mit Milcherzeugnissen U Eiern Verarbeitung von Milch",
    "sg:phone":"+41 31 747 84 25",
    "sg:postcode":"4932",
    "sg:province":"Bern",
    "wof:name":"K\u00e4serei Laupen",
    "wof:placetype":"venue"
},
  "geometry": {"coordinates":[7.2639498711,46.9152984619],"type":"Point"}
}