{
  "type": "Feature",
  "properties": {
    "iso:country":"CH",
    "sg:address":"8248",
    "sg:city":"Uhwiesen",
    "sg:orig_category":"Sportvereine Sch\u00fctzen",
    "sg:phone":"+41 18691515",
    "sg:postcode":"8248",
    "sg:province":"Z\u00fcrich",
    "wof:name":"Schiessverein",
    "wof:placetype":"venue"
},
  "geometry": {"coordinates":[8.6926898956,47.4565010071],"type":"Point"}
}