{
  "type": "Feature",
  "properties": {
    "iso:country":"CH",
    "sg:address":"General Aviation Center 8302 Kloten. Postfach 1351",
    "sg:city":"Z\u00fcrich",
    "sg:orig_category":"Herstellung von Metallerzeugnissen ohne Maschinenbau Luft U Raumfahrzeugbau",
    "sg:phone":"+41 77659863",
    "sg:postcode":"8058",
    "sg:province":"Z\u00fcrich",
    "wof:name":"Avionitec Ag",
    "wof:placetype":"venue"
},
  "geometry": {"coordinates":[8.5806808472,47.4521408081],"type":"Point"}
}