{
  "type": "Feature",
  "properties": {
    "addr:full":"M\u00fchlehofstrasse 61 6030 Ebikon. Postfach 104 Ebikon Luzern 6031",
    "addr:housenumber":"61;104",
    "addr:postcode":"6030 ebikon.;6031",
    "addr:street":"Muehlehofstrasse;Postfach",
    "iso:country":"CH",
    "sg:address":"M\u00fchlehofstrasse 61 6030 Ebikon. Postfach 104",
    "sg:city":"Ebikon",
    "sg:orig_category":"Bauingenieurb\u00fcros Heizung L\u00fcftung Klima",
    "sg:phone":"+41 41 440 64 24",
    "sg:postcode":"6031",
    "sg:province":"Luzern",
    "wof:name":"Lothar Brenner Ingenieurb\u00fcro",
    "wof:placetype":"venue"
},
  "geometry": {"coordinates":[8.340958,47.076561],"type":"Point"}
}