{
  "type": "Feature",
  "properties": {
    "iso:country":"CH",
    "sg:address":"Kirchplatz 117. 4116 Metzerlen. Postfach",
    "sg:city":"Mariastein",
    "sg:orig_category":"RESTAURANTS: TEA-ROOMS",
    "sg:postcode":"4115",
    "sg:province":"Solothurn",
    "wof:name":"Camenzind Josef.",
    "wof:placetype":"venue"
},
  "geometry": {"coordinates":[7.4650850296,47.4655647278],"type":"Point"}
}