{
  "type": "Feature",
  "properties": {
    "iso:country":"CH",
    "sg:address":"Rue Des Moulins 1",
    "sg:city":"Del\u00e9mont",
    "sg:classifiers":[
        {
            "category":"Travel",
            "subcategory":"Hotels & Motels",
            "type":"Entertainment"
        }
    ],
    "sg:phone":"+41 32 422 12 70",
    "sg:postcode":"2800",
    "sg:province":"Jura",
    "sg:tags":[
        "hotels",
        "mit",
        "restaurant"
    ],
    "wof:name":"Herrmann Claudine",
    "wof:placetype":"venue"
},
  "geometry": {"coordinates":[7.3454008102,47.365486145],"type":"Point"}
}