{
  "type": "Feature",
  "properties": {
    "iso:country":"CH",
    "sg:address":"Mattengasse 29",
    "sg:city":"Z\u00fcrich",
    "sg:orig_category":"RESTAURANTS: TEA-ROOMS",
    "sg:postcode":"8005",
    "sg:province":"Z\u00fcrich",
    "wof:name":"Hannelies Thomas-schl\u00e4pfer",
    "wof:placetype":"venue"
},
  "geometry": {"coordinates":[6.1042528152,46.1490287781],"type":"Point"}
}