{
  "type": "Feature",
  "properties": {
    "iso:country":"CH",
    "sg:address":"Letzigasse 1",
    "sg:city":"Zofingen",
    "sg:orig_category":"RESTAURANTS: TEA-ROOMS",
    "sg:phone":"+41 62 751 01 22",
    "sg:postcode":"4800",
    "sg:province":"Aargau",
    "wof:name":"Pizzeria/bar Letzi",
    "wof:placetype":"venue"
},
  "geometry": {"coordinates":[7.9465417862,47.2870140076],"type":"Point"}
}