{
  "type": "Feature",
  "properties": {
    "addr:full":"Route De Fornet 105 Lajoux Jura 2718",
    "addr:housenumber":"105",
    "addr:postcode":"2718",
    "addr:street":"Route De Fornet;Jura",
    "iso:country":"CH",
    "sg:address":"Route De Fornet 105",
    "sg:city":"Lajoux",
    "sg:classifiers":[
        {
            "category":"Food & Beverages",
            "subcategory":"Cheese",
            "type":"Retail Goods"
        }
    ],
    "sg:phone":"+41 32 484 70 70",
    "sg:postcode":"2718",
    "sg:province":"Jura",
    "sg:tags":[
        "machine",
        "cutting"
    ],
    "wof:name":"M\u00e9tafil La Girolle Sa",
    "wof:placetype":"venue"
},
  "geometry": {"coordinates":[7.143321,47.279007],"type":"Point"}
}