{
  "type": "Feature",
  "properties": {
    "iso:country":"CH",
    "sg:address":"Vers-chez-montandon 2105 Travers Case Postale 52",
    "sg:city":"Travers",
    "sg:orig_category":"Herstellung von Transportbeton Herstellung von sonstigen Produkten aus nichtmetallischen Mineralien",
    "sg:phone":"+41 32 863 22 77",
    "sg:postcode":"2105",
    "sg:province":"Neuch\u00e2tel",
    "wof:name":"Valbitume Sa",
    "wof:placetype":"venue"
},
  "geometry": {"coordinates":[6.6732201576,46.9389686584],"type":"Point"}
}