{
  "type": "Feature",
  "properties": {
    "iso:country":"CH",
    "sg:address":"Route De Thonon 153 1222 V\u00e9senaz. Postfach",
    "sg:city":"V\u00e9senaz",
    "sg:orig_category":"Datenbanken",
    "sg:phone":"+41 21 803 44 17",
    "sg:postcode":"1222",
    "sg:province":"Gen\u00e8ve",
    "wof:name":"Reuters On-line Sa",
    "wof:placetype":"venue"
},
  "geometry": {"coordinates":[6.211565,46.24675],"type":"Point"}
}