{
  "type": "Feature",
  "properties": {
    "iso:country":"CH",
    "sg:address":"St.-martins-ring 32 9492 Eschen. Postfach 62",
    "sg:city":"Eschen",
    "sg:orig_category":"Gemeindeverwaltungen",
    "sg:phone":"+41 41 449 90 10",
    "sg:postcode":"9492",
    "wof:name":"Gemeindeverwaltung Eschenbach",
    "wof:placetype":"venue"
},
  "geometry": {"coordinates":[8.3200302124,47.13256073],"type":"Point"}
}