{
  "type": "Feature",
  "properties": {
    "iso:country":"CH",
    "sg:address":"Alte Saline 31 Postfach",
    "sg:city":"Rheinfelden",
    "sg:orig_category":"Markt U Meinungsforschung Werbeberatung",
    "sg:phone":"+41 61 833 95 70",
    "sg:postcode":"4310",
    "sg:province":"Aargau",
    "wof:name":"Feger Marketing & Analysen Marktforschung / Online-umfragen / Beratung",
    "wof:placetype":"venue"
},
  "geometry": {"coordinates":[11.7567501068,42.253276825],"type":"Point"}
}