{
  "type": "Feature",
  "properties": {
    "iso:country":"CH",
    "sg:address":"Rue Charles-l'eplattenier 10",
    "sg:city":"Geneveys-coffrane",
    "sg:orig_category":"Polizei",
    "sg:phone":"+41 32 857 11 50",
    "sg:postcode":"2206",
    "sg:province":"Neuch\u00e2tel",
    "wof:name":"Police Cantonale",
    "wof:placetype":"venue"
},
  "geometry": {"coordinates":[6.8518400192,47.0164413452],"type":"Point"}
}