{
  "type": "Feature",
  "properties": {
    "iso:country":"CH",
    "sg:address":"Klosterhofstrasse 2",
    "sg:city":"Bottighofen",
    "sg:orig_category":"Architektur U Ingenieurb\u00fcros Architekturb\u00fcros",
    "sg:phone":"+41 71 688 29 94",
    "sg:postcode":"8598",
    "sg:province":"Thurgau",
    "wof:name":"Architekturb\u00fcro Wacker Bruno",
    "wof:placetype":"venue"
},
  "geometry": {"coordinates":[9.206257,47.636356],"type":"Point"}
}