{
  "type": "Feature",
  "properties": {
    "addr:full":"Leutschentalstrasse 16 6252 Dagmersellen. Postfach 9 Dagmersellen Luzern 6252",
    "addr:housenumber":"16;9",
    "addr:postcode":"6252 dagmersellen.;6252",
    "addr:street":"Leutschentalstrasse;Postfach",
    "iso:country":"CH",
    "sg:address":"Leutschentalstrasse 16 6252 Dagmersellen. Postfach 9",
    "sg:city":"Dagmersellen",
    "sg:orig_category":"Datenverarbeitungsdienste Softwareentwicklung U beratung",
    "sg:phone":"+41 62 756 28 33",
    "sg:postcode":"6252",
    "sg:province":"Luzern",
    "wof:name":"Karosoft Roger F\u00e4ssler",
    "wof:placetype":"venue"
},
  "geometry": {"coordinates":[7.994266,47.21666],"type":"Point"}
}