{
  "type": "Feature",
  "properties": {
    "iso:country":"CH",
    "sg:address":"Worbstrasse 164",
    "sg:city":"G\u00fcmligen",
    "sg:orig_category":"Ingenieurb\u00fcros Vermessung",
    "sg:phone":"+41 31 950 95 75",
    "sg:postcode":"3073",
    "sg:province":"Bern",
    "wof:name":"Marcel Perrinjaquet Vermessungsb\u00fcro",
    "wof:placetype":"venue"
},
  "geometry": {"coordinates":[7.4994268417,46.9349021912],"type":"Point"}
}