{
  "type": "Feature",
  "properties": {
    "iso:country":"CH",
    "sg:address":"Alpenstrasse 6",
    "sg:city":"Zug",
    "sg:orig_category":"Sonstiger Grosshandel",
    "sg:postcode":"6300",
    "sg:province":"Zug",
    "wof:name":"Import & Export Naoui",
    "wof:placetype":"venue"
},
  "geometry": {"coordinates":[8.5139732361,47.1711196899],"type":"Point"}
}