{
  "type": "Feature",
  "properties": {
    "iso:country":"CH",
    "sg:address":"Bahnhofstrasse 21",
    "sg:city":"Biel/bienne",
    "sg:orig_category":"Detailhandel mit Uhren U Schmuck Fachdetailhandel in Verkaufsr\u00e4umen",
    "sg:phone":"+41 32 322 31 81",
    "sg:postcode":"2502",
    "sg:province":"Bern",
    "wof:name":"R. Villiger Ag",
    "wof:placetype":"venue"
},
  "geometry": {"coordinates":[7.244576931,47.1352806091],"type":"Point"}
}