{
  "type": "Feature",
  "properties": {
    "iso:country":"CH",
    "sg:address":"Clarastrasse 9",
    "sg:city":"Basel",
    "sg:orig_category":"Herstellung von Schmuck, Gold U Silberschmiedwaren",
    "sg:phone":"+41 61 681 85 88",
    "sg:postcode":"4058",
    "sg:province":"Basel-Stadt",
    "wof:name":"Goldfinger Tognetti James",
    "wof:placetype":"venue"
},
  "geometry": {"coordinates":[7.5952181816,47.5623512268],"type":"Point"}
}