{
  "type": "Feature",
  "properties": {
    "iso:country":"CH",
    "sg:address":"Eschikerstrasse 15",
    "sg:city":"Effretikon",
    "sg:orig_category":"Advokaturb\u00fcros",
    "sg:phone":"+41 55 220 64 84",
    "sg:postcode":"8307",
    "sg:province":"Z\u00fcrich",
    "wof:name":"Peter Bietenharder Advokaturb\u00fcro",
    "wof:placetype":"venue"
},
  "geometry": {"coordinates":[8.819443,47.229603],"type":"Point"}
}