{
  "type": "Feature",
  "properties": {
    "addr:full":"Hofacher 6 Diegten Basel-Landschaft 4457",
    "addr:housenumber":"6",
    "addr:postcode":"4457",
    "addr:street":"Hofacher",
    "iso:country":"CH",
    "sg:address":"Hofacher 6",
    "sg:city":"Diegten",
    "sg:orig_category":"Bauschreinerei Herstellung von K\u00fcchenm\u00f6beln",
    "sg:phone":"+41 61 971 41 47",
    "sg:postcode":"4457",
    "sg:province":"Basel-Landschaft",
    "wof:name":"Weiss Max Einbauk\u00fcchen Schreinereiarbeiten",
    "wof:placetype":"venue"
},
  "geometry": {"coordinates":[7.809769,47.41275],"type":"Point"}
}