{
  "type": "Feature",
  "properties": {
    "iso:country":"CH",
    "sg:address":"Chemin Messidor 5 1006 Lausanne. Postfach",
    "sg:city":"Lausanne",
    "sg:orig_category":"Wirtschaftspr\u00fcfung, Steuerberatung U Treuhand",
    "sg:postcode":"1002",
    "sg:province":"Vaud",
    "wof:name":"Fiduciaire Du Commerce Et De L'artisanat G\u00e9rard Pittet",
    "wof:placetype":"venue"
},
  "geometry": {"coordinates":[6.1414251328,46.1833114624],"type":"Point"}
}