{
  "type": "Feature",
  "properties": {
    "iso:country":"CH",
    "sg:address":"Meientalstrasse 83 8048 Z\u00fcrich. Postfach",
    "sg:city":"Z\u00fcrich",
    "sg:orig_category":"Detailhandel mit Metallwaren, Anstrichmitteln, Glaswaren, Bau U Heimwerkerbedarf",
    "sg:postcode":"8048",
    "sg:province":"Z\u00fcrich",
    "wof:name":"C & M Consulting Keller",
    "wof:placetype":"venue"
},
  "geometry": {"coordinates":[8.4762077332,47.386554718],"type":"Point"}
}