{
  "type": "Feature",
  "properties": {
    "iso:country":"CH",
    "sg:address":"Bvd Georges-favon 6",
    "sg:city":"Gen\u00e8ve",
    "sg:orig_category":"Reiseb\u00fcros",
    "sg:phone":"+41 52 366 20 50",
    "sg:postcode":"1204",
    "sg:province":"Gen\u00e8ve",
    "wof:name":"Eitzinger Sport Und Aktiv-ferien Gmbh",
    "wof:placetype":"venue"
},
  "geometry": {"coordinates":[8.8942966461,47.4792327881],"type":"Point"}
}