{
  "type": "Feature",
  "properties": {
    "iso:country":"CH",
    "sg:address":"Gemeindehausstrasse 8",
    "sg:city":"Kriens",
    "sg:orig_category":"Primarschulen",
    "sg:phone":"+41 41 320 40 59",
    "sg:postcode":"6010",
    "sg:province":"Luzern",
    "wof:name":"Primarschule Bleiche",
    "wof:placetype":"venue"
},
  "geometry": {"coordinates":[8.2792758942,47.0362930298],"type":"Point"}
}