{
  "type": "Feature",
  "properties": {
    "iso:country":"CH",
    "sg:address":"Guggisbergstrasse 1",
    "sg:city":"Schwarzenburg",
    "sg:classifiers":[
        {
            "category":"Education",
            "subcategory":"Library",
            "type":"Public Place"
        }
    ],
    "sg:phone":"+41 31 734 35 35",
    "sg:postcode":"3150",
    "sg:province":"Bern",
    "sg:tags":[
        "u",
        "bibliotheken",
        "archive"
    ],
    "wof:name":"Bezirksspital",
    "wof:placetype":"venue"
},
  "geometry": {"coordinates":[7.339924,46.814758],"type":"Point"}
}