{
  "type": "Feature",
  "properties": {
    "iso:country":"CH",
    "sg:address":"Saint-martin Rue 36 1005 Lausanne. Postfach",
    "sg:city":"Lausanne",
    "sg:orig_category":"Werbung",
    "sg:postcode":"1003",
    "sg:province":"Vaud",
    "wof:name":"Matthey-dupraz F. Conseils En Publicit\u00e9.",
    "wof:placetype":"venue"
},
  "geometry": {"coordinates":[6.6372938156,46.5239486694],"type":"Point"}
}