{
  "type": "Feature",
  "properties": {
    "iso:country":"CH",
    "sg:address":"Gl\u00fctschbachstrasse 5 3661 Uetendorf. Postfach",
    "sg:city":"Uetendorf",
    "sg:orig_category":"Handel mit Automobilteilen U Zubeh\u00f6r Herstellung von Automobilen",
    "sg:phone":"+41 33 437 86 86",
    "sg:postcode":"3661",
    "sg:province":"Bern",
    "wof:name":"Fankhauser Oberland Ag",
    "wof:placetype":"venue"
},
  "geometry": {"coordinates":[7.582280159,46.7774734497],"type":"Point"}
}