{
  "type": "Feature",
  "properties": {
    "iso:country":"CH",
    "sg:address":"Mattenweg 2",
    "sg:city":"Niederbipp",
    "sg:orig_category":"Bauspenglerei Sanit\u00e4rinstallation",
    "sg:phone":"+41 32 633 16 72",
    "sg:postcode":"4704",
    "sg:province":"Bern",
    "wof:name":"Hanspeter Anderegg Sanit\u00e4re Anlagen & Spenglerei",
    "wof:placetype":"venue"
},
  "geometry": {"coordinates":[7.698928,47.265678],"type":"Point"}
}