{
  "type": "Feature",
  "properties": {
    "iso:country":"CH",
    "sg:address":"Brunnmattstrasse 5",
    "sg:city":"Th\u00f6rishaus",
    "sg:classifiers":[
        {
            "category":"Shopping",
            "subcategory":"Pharmacy",
            "type":"Retail Goods"
        }
    ],
    "sg:phone":"+41 31 888 22 22",
    "sg:postcode":"3174",
    "sg:province":"Bern",
    "sg:tags":[
        "preparation",
        "pharmaceutical"
    ],
    "wof:name":"Glaxosmithkline Ag",
    "wof:placetype":"venue"
},
  "geometry": {"coordinates":[7.3482651711,46.8911628723],"type":"Point"}
}