{
  "type": "Feature",
  "properties": {
    "iso:country":"CH",
    "sg:address":"Dorfstrasse 32b",
    "sg:city":"Ipsach",
    "sg:orig_category":"Detailhandel mit Computern U Software Softwareentwicklung U beratung",
    "sg:phone":"+41 32 331 11 22",
    "sg:postcode":"2563",
    "sg:province":"Bern",
    "wof:name":"Toolfit Software Gmbh",
    "wof:placetype":"venue"
},
  "geometry": {"coordinates":[7.233142,47.110962],"type":"Point"}
}