{
  "type": "Feature",
  "properties": {
    "addr:full":"Bodengasse 1 8803 R\u00fcschlikon. Postfach R\u00fcschlikon Z\u00fcrich 8803",
    "addr:housenumber":"1",
    "addr:postcode":"8803;8803",
    "addr:street":"Bodengasse;Postfach Rueschlikon Zuerich",
    "iso:country":"CH",
    "sg:address":"Bodengasse 1 8803 R\u00fcschlikon. Postfach",
    "sg:city":"R\u00fcschlikon",
    "sg:classifiers":[
        {
            "category":"Education",
            "subcategory":"Library",
            "type":"Public Place"
        }
    ],
    "sg:phone":"+41 17243208",
    "sg:postcode":"8803",
    "sg:province":"Z\u00fcrich",
    "sg:tags":[
        "u",
        "bibliotheken",
        "archive"
    ],
    "wof:name":"Gemeindebibliothek",
    "wof:placetype":"venue"
},
  "geometry": {"coordinates":[8.552323,47.310211],"type":"Point"}
}