{
  "type": "Feature",
  "properties": {
    "iso:country":"CH",
    "sg:address":"Weissensteinstrasse 15",
    "sg:city":"Solothurn",
    "sg:classifiers":[
        {
            "category":"Professional",
            "subcategory":"Engineering",
            "type":"Services"
        }
    ],
    "sg:phone":"+41 71 278 68 05",
    "sg:postcode":"4500",
    "sg:province":"Solothurn",
    "sg:tags":[
        "organizational",
        "information",
        "consulting",
        "technology"
    ],
    "wof:name":"C-norm Ag",
    "wof:placetype":"venue"
},
  "geometry": {"coordinates":[9.3582420349,47.4177284241],"type":"Point"}
}