{
  "type": "Feature",
  "properties": {
    "iso:country":"CH",
    "sg:address":"Via Della Posta 2",
    "sg:city":"Lugano",
    "sg:orig_category":"Detailhandel mit Geschenkartikeln U Souvenirs",
    "sg:phone":"+41 21 636 49 53",
    "sg:postcode":"6900",
    "sg:province":"Ticino",
    "wof:name":"Atelier Le Panda N.viredaz Objets Artisanaux Boutique",
    "wof:placetype":"venue"
},
  "geometry": {"coordinates":[6.9295902252,46.3618087769],"type":"Point"}
}