{
  "type": "Feature",
  "properties": {
    "iso:country":"CH",
    "sg:address":"Weid",
    "sg:city":"B\u00fctschwil",
    "sg:orig_category":"Herstellung von sonstigen landwirtschaftlichen Maschinen",
    "sg:phone":"+41 71 983 28 82",
    "sg:postcode":"9606",
    "sg:province":"St. Gallen",
    "wof:name":"Louis Bartholet Alfa-laval-service",
    "wof:placetype":"venue"
},
  "geometry": {"coordinates":[9.0604496002,47.3765106201],"type":"Point"}
}