{
  "type": "Feature",
  "properties": {
    "iso:country":"CH",
    "sg:address":"Avenue De Montchoisi 22",
    "sg:city":"Lausanne",
    "sg:orig_category":"Handelsvermittlung U Grosshandel Unternehmensberatung",
    "sg:phone":"+41 21 617 82 83",
    "sg:postcode":"1006",
    "sg:province":"Vaud",
    "wof:name":"Gen-consulting Company Sa",
    "wof:placetype":"venue"
},
  "geometry": {"coordinates":[6.6357269287,46.5115242004],"type":"Point"}
}