{
  "type": "Feature",
  "properties": {
    "iso:country":"CH",
    "sg:address":"Veyrot Rue De 7",
    "sg:city":"Meyrin",
    "sg:orig_category":"Instandhaltung U Reparatur von Automobilen",
    "sg:postcode":"1217",
    "sg:province":"Gen\u00e8ve",
    "wof:name":"Garage Carrosserie Du Nant-d'avril, Christian Pillet",
    "wof:placetype":"venue"
},
  "geometry": {"coordinates":[6.0609788895,46.2274246216],"type":"Point"}
}