{
  "type": "Feature",
  "properties": {
    "iso:country":"CH",
    "sg:address":"M\u00fchlegasse 23",
    "sg:city":"Gerlafingen",
    "sg:classifiers":[
        {
            "category":"Bars & Pubs",
            "type":"Food & Drink"
        }
    ],
    "sg:phone":"+41 71 245 89 39",
    "sg:postcode":"4563",
    "sg:province":"Solothurn",
    "wof:name":"Bar Guacci's",
    "wof:placetype":"venue"
},
  "geometry": {"coordinates":[9.389434,47.429604],"type":"Point"}
}