{
  "type": "Feature",
  "properties": {
    "iso:country":"CH",
    "sg:address":"Postplatz 8890 Flums. Postfach 30",
    "sg:city":"Flums",
    "sg:orig_category":"Elektrizit\u00e4tsversorgung Elektroinstallation",
    "sg:phone":"+41 81 733 13 09",
    "sg:postcode":"8890",
    "sg:province":"St. Gallen",
    "wof:name":"Zeller Martin Ag, Elektrizit\u00e4tswerk",
    "wof:placetype":"venue"
},
  "geometry": {"coordinates":[9.3425388336,47.0917549133],"type":"Point"}
}