{
  "type": "Feature",
  "properties": {
    "iso:country":"CH",
    "sg:address":"7142",
    "sg:city":"Cumbel",
    "sg:orig_category":"Elektrizit\u00e4tsversorgung",
    "sg:postcode":"7142",
    "sg:province":"Graubunden",
    "wof:name":"Capeder Energia Alternativa",
    "wof:placetype":"venue"
},
  "geometry": {"coordinates":[9.2005901337,46.7329292297],"type":"Point"}
}