{
  "type": "Feature",
  "properties": {
    "iso:country":"CH",
    "sg:address":"Hardstrasse 10",
    "sg:city":"Basel",
    "sg:orig_category":"Non-Classified Establishments",
    "sg:postcode":"4052",
    "sg:province":"Basel-Stadt",
    "wof:name":"Focus Design",
    "wof:placetype":"venue"
},
  "geometry": {"coordinates":[7.6017417908,47.5516357422],"type":"Point"}
}