{
  "type": "Feature",
  "properties": {
    "iso:country":"CH",
    "sg:address":"R\u00f6telstrasse 53",
    "sg:city":"Z\u00fcrich",
    "sg:orig_category":"Wohnheime f\u00fcr Kinder U Jugendliche",
    "sg:phone":"+41 13619753",
    "sg:postcode":"8037",
    "sg:province":"Z\u00fcrich",
    "wof:name":"St\u00e4dtisches Jugendheim",
    "wof:placetype":"venue"
},
  "geometry": {"coordinates":[8.5315103531,47.395690918],"type":"Point"}
}