{
  "type": "Feature",
  "properties": {
    "iso:country":"CH",
    "sg:address":"Lindentalstrasse 112",
    "sg:city":"Boll",
    "sg:classifiers":[
        {
            "category":"Banks & Credit Unions",
            "subcategory":"Investment Brokerage",
            "type":"Services"
        }
    ],
    "sg:phone":"+41 31 838 51 61",
    "sg:postcode":"3067",
    "sg:province":"Bern",
    "sg:tags":[
        "fork",
        "lift",
        "truck",
        "electric"
    ],
    "wof:name":"Arbor Ag",
    "wof:placetype":"venue"
},
  "geometry": {"coordinates":[7.5496439934,46.9552345276],"type":"Point"}
}