{
  "type": "Feature",
  "properties": {
    "iso:country":"CH",
    "sg:address":"1088",
    "sg:city":"Ropraz",
    "sg:orig_category":"Elektroinstallation",
    "sg:phone":"+41 32 485 13 06",
    "sg:postcode":"1088",
    "sg:province":"Vaud",
    "wof:name":"Liechti Arnold, \u00e9lectricit\u00e9, T\u00e9l\u00e9phone",
    "wof:placetype":"venue"
},
  "geometry": {"coordinates":[6.7550001144,46.6073799133],"type":"Point"}
}