{
  "type": "Feature",
  "properties": {
    "iso:country":"CH",
    "sg:address":"Klosbachstrasse 54 8032 Z\u00fcrich. Postfach 8032 Z\u00fcrich",
    "sg:city":"Zust",
    "sg:orig_category":"Non-Classified Establishments",
    "sg:postcode":"32",
    "wof:name":"Atable Gmbh",
    "wof:placetype":"venue"
},
  "geometry": {"coordinates":[8.5584506989,47.3667144775],"type":"Point"}
}