{
  "type": "Feature",
  "properties": {
    "iso:country":"CH",
    "sg:address":"Chemin Du Coteau 4",
    "sg:city":"Moutier",
    "sg:orig_category":"Dachdeckerei",
    "sg:phone":"+41 52 741 12 40",
    "sg:postcode":"2740",
    "sg:province":"Bern",
    "wof:name":"Hans Br\u00fctsch Dachdeckergesch\u00e4ft",
    "wof:placetype":"venue"
},
  "geometry": {"coordinates":[8.848573,47.664761],"type":"Point"}
}