{
  "type": "Feature",
  "properties": {
    "iso:country":"CH",
    "sg:address":"Thunstrasse 101 A",
    "sg:city":"Bern",
    "sg:orig_category":"Softwareentwicklung U beratung",
    "sg:phone":"+41 55 462 34 43",
    "sg:postcode":"3006",
    "sg:province":"Bern",
    "wof:name":"K+h Software Ag",
    "wof:placetype":"venue"
},
  "geometry": {"coordinates":[8.8548851013,47.1939811707],"type":"Point"}
}