{
  "type": "Feature",
  "properties": {
    "iso:country":"CH",
    "sg:address":"Seymaz Chemin De La 36 B",
    "sg:city":"Vandoeuvres",
    "sg:orig_category":"Betrieb U technische Hilfsdienste des Kultur U Unterhaltungswesens",
    "sg:postcode":"1253",
    "sg:province":"Gen\u00e8ve",
    "wof:name":"Sme Star Music And Entertainment Gmbh",
    "wof:placetype":"venue"
},
  "geometry": {"coordinates":[7.597158,47.469616],"type":"Point"}
}