{
  "type": "Feature",
  "properties": {
    "iso:country":"CH",
    "sg:address":"In Samstagern.",
    "sg:city":"Richterswil",
    "sg:orig_category":"Grosshandel mit Getreide, Saatgut U Futtermitteln",
    "sg:phone":"+41 81 740 34 70",
    "sg:postcode":"8805",
    "sg:province":"Z\u00fcrich",
    "wof:name":"Bolter Ag",
    "wof:placetype":"venue"
},
  "geometry": {"coordinates":[9.4876050949,47.2050666809],"type":"Point"}
}