{
  "type": "Feature",
  "properties": {
    "iso:country":"CH",
    "sg:address":"Kirchstrasse 7",
    "sg:city":"Wiesendangen",
    "sg:orig_category":"Wirtschaftspr\u00fcfung, Steuerberatung U Treuhand",
    "sg:phone":"+41 52 338 21 21",
    "sg:postcode":"8542",
    "sg:province":"Z\u00fcrich",
    "wof:name":"Keller Erbschafts-treuhand",
    "wof:placetype":"venue"
},
  "geometry": {"coordinates":[8.7890787125,47.5213241577],"type":"Point"}
}