{
  "type": "Feature",
  "properties": {
    "iso:country":"CH",
    "sg:address":"Rosenweg 12",
    "sg:city":"Solothurn",
    "sg:orig_category":"Technische, physikalische U chemische Untersuchung",
    "sg:phone":"+41 32 622 40 27",
    "sg:postcode":"4500",
    "sg:province":"Solothurn",
    "wof:name":"Axis Agentur F\u00fcr Umwelt Und Raumplanung Gmbh",
    "wof:placetype":"venue"
},
  "geometry": {"coordinates":[7.5431289673,47.2085227966],"type":"Point"}
}