{
  "type": "Feature",
  "properties": {
    "iso:country":"CH",
    "sg:address":"Seilerweg 3 8200 Schaffhausen. Postfach 430",
    "sg:city":"Schaffhausen",
    "sg:orig_category":"Oberfl\u00e4chenveredlung U W\u00e4rmebehandlung",
    "sg:phone":"+41 52 625 42 03",
    "sg:postcode":"8201",
    "sg:province":"Schaffhausen",
    "wof:name":"Felox Ag Eloxal-& Metallveredlungswerk",
    "wof:placetype":"venue"
},
  "geometry": {"coordinates":[8.641643,47.706257],"type":"Point"}
}