{
  "type": "Feature",
  "properties": {
    "addr:full":"Bankstrasse 6 Chur Graubunden 7000",
    "addr:housenumber":"6",
    "addr:postcode":"7000",
    "addr:street":"Bankstrasse",
    "iso:country":"CH",
    "sg:address":"Bankstrasse 6",
    "sg:city":"Chur",
    "sg:classifiers":[
        {
            "category":"Bars & Pubs",
            "type":"Food & Drink"
        }
    ],
    "sg:phone":"+41 81 252 05 08",
    "sg:postcode":"7000",
    "sg:province":"Graubunden",
    "wof:name":"Ap\u00e9ro-bar La Strega",
    "wof:placetype":"venue"
},
  "geometry": {"coordinates":[9.532486,46.849636],"type":"Point"}
}