{
  "type": "Feature",
  "properties": {
    "iso:country":"CH",
    "sg:address":"Bonnesfontaines Rte Des 46",
    "sg:city":"Freiburg",
    "sg:orig_category":"Herstellung von Teppichen",
    "sg:postcode":"1700",
    "sg:province":"Fribourg",
    "wof:name":"Radojevic D. Carrelage",
    "wof:placetype":"venue"
},
  "geometry": {"coordinates":[7.1429290771,46.8140678406],"type":"Point"}
}