{
  "type": "Feature",
  "properties": {
    "iso:country":"CH",
    "sg:address":"Ifangstrasse 9 8952 Schlieren. Postfach",
    "sg:city":"Schlieren",
    "sg:orig_category":"Herstellung von Dauerbackwaren",
    "sg:phone":"+41 17384343",
    "sg:postcode":"8952",
    "sg:province":"Z\u00fcrich",
    "wof:name":"Hiestand A. Ag",
    "wof:placetype":"venue"
},
  "geometry": {"coordinates":[8.4555606842,47.4010848999],"type":"Point"}
}