{
  "type": "Feature",
  "properties": {
    "iso:country":"CH",
    "sg:address":"M\u00fchligutstrasse 16",
    "sg:city":"Goldach",
    "sg:orig_category":"Sonstiger spezialisierter Hoch U Tiefbau",
    "sg:phone":"+41 71 278 42 08",
    "sg:postcode":"9403",
    "sg:province":"St. Gallen",
    "wof:name":"Hoxhaj Ger\u00fcstbau",
    "wof:placetype":"venue"
},
  "geometry": {"coordinates":[9.4628543854,47.476272583],"type":"Point"}
}