{
  "type": "Feature",
  "properties": {
    "iso:country":"CH",
    "sg:address":"Montjolweg 8",
    "sg:city":"Sevelen",
    "sg:orig_category":"Architektur U Ingenieurb\u00fcros",
    "sg:phone":"+41 79 349 46 72",
    "sg:postcode":"9475",
    "sg:province":"St. Gallen",
    "wof:name":"Hofm\u00e4nner A. Technisches B\u00fcro",
    "wof:placetype":"venue"
},
  "geometry": {"coordinates":[9.489758,47.111221],"type":"Point"}
}