{
  "type": "Feature",
  "properties": {
    "iso:country":"CH",
    "sg:address":"Steinengraben 5 4051 Basel. Postfach",
    "sg:city":"Basel",
    "sg:orig_category":"Unclassifiable Establishments",
    "sg:phone":"+41 61 275 20 00",
    "sg:postcode":"4003",
    "sg:province":"Basel-Stadt",
    "wof:name":"Schweizerische National Versicherungs-gesellschaft",
    "wof:placetype":"venue"
},
  "geometry": {"coordinates":[7.5848340988,47.5556983948],"type":"Point"}
}