{
  "type": "Feature",
  "properties": {
    "addr:full":"Rue Du Puits-godet 10a Neuch\u00e2tel Neuch\u00e2tel 2000",
    "addr:housenumber":"10a",
    "addr:postcode":"2000",
    "addr:street":"Rue Du Puits-Godet",
    "iso:country":"CH",
    "sg:address":"Rue Du Puits-godet 10a",
    "sg:city":"Neuch\u00e2tel",
    "sg:classifiers":[
        {
            "category":"Communications",
            "subcategory":"Film & Video Production",
            "type":"Services"
        }
    ],
    "sg:phone":"+41 32 720 23 00",
    "sg:postcode":"2000",
    "sg:province":"Neuch\u00e2tel",
    "sg:tags":[
        "belt",
        "scale",
        "batch",
        "conveyor"
    ],
    "wof:name":"Hasler Suisse S\u00e0rl (hasler Group)",
    "wof:placetype":"venue"
},
  "geometry": {"coordinates":[6.913326,46.998596],"type":"Point"}
}