{
  "type": "Feature",
  "properties": {
    "iso:country":"CH",
    "sg:address":"Seewisstrasse 4",
    "sg:city":"Maur",
    "sg:orig_category":"Satzherstellung U Reproduktion",
    "sg:phone":"+41 18876815",
    "sg:postcode":"8124",
    "sg:province":"Z\u00fcrich",
    "wof:name":"Sch\u00e4tti Dtp",
    "wof:placetype":"venue"
},
  "geometry": {"coordinates":[8.6707525253,47.3414573669],"type":"Point"}
}