{
  "type": "Feature",
  "properties": {
    "iso:country":"CH",
    "sg:address":"Englischgrusstrasse 46 3902 Glis. Postfach",
    "sg:city":"Glis",
    "sg:classifiers":[
        {
            "category":"Professional",
            "subcategory":"Employment Agencies",
            "type":"Services"
        }
    ],
    "sg:phone":"+41 27 924 20 70",
    "sg:postcode":"3902",
    "sg:province":"Valais",
    "sg:tags":[
        "personal",
        "u",
        "stellenvermittlung"
    ],
    "wof:name":"Wag Akkord Gruppe Gmbh",
    "wof:placetype":"venue"
},
  "geometry": {"coordinates":[7.9826140404,46.3159484863],"type":"Point"}
}