{
  "type": "Feature",
  "properties": {
    "iso:country":"CH",
    "sg:address":"1489 Murist Case Postale 49",
    "sg:city":"Murist",
    "sg:orig_category":"Herstellung von Konstruktionsteilen, Fertigbauteilen U Ausbauelementen aus Holz",
    "sg:phone":"+41 56 664 28 55",
    "sg:postcode":"1489",
    "sg:province":"Fribourg",
    "wof:name":"I.d. Individual Doors Sa",
    "wof:placetype":"venue"
},
  "geometry": {"coordinates":[6.8069529533,46.7899894714],"type":"Point"}
}