{
  "type": "Feature",
  "properties": {
    "iso:country":"CH",
    "sg:address":"H\u00f6heweg 22",
    "sg:city":"Liebefeld",
    "sg:orig_category":"Maurerarbeiten",
    "sg:phone":"+41 21 625 89 92",
    "sg:postcode":"3097",
    "sg:province":"Bern",
    "wof:name":"Antonio Cauz Travaux De Ma\u00e7onnerie",
    "wof:placetype":"venue"
},
  "geometry": {"coordinates":[6.5982751846,46.533039093],"type":"Point"}
}