{
  "type": "Feature",
  "properties": {
    "iso:country":"CH",
    "sg:address":"Ebnatstrasse 162 8207 Schaffhausen. Postfach 1240",
    "sg:city":"Schaffhausen",
    "sg:orig_category":"Herstellung von Ausbauelementen aus Metall Mechanik",
    "sg:phone":"+41 26 413 21 31",
    "sg:postcode":"8207",
    "sg:province":"Schaffhausen",
    "wof:name":"Charles Brodard Sa",
    "wof:placetype":"venue"
},
  "geometry": {"coordinates":[7.1380701065,46.6968002319],"type":"Point"}
}