{
  "type": "Feature",
  "properties": {
    "iso:country":"CH",
    "sg:address":"Hardstrasse 72-74 5430 Wettingen. Postfach",
    "sg:city":"Wettingen",
    "sg:orig_category":"Herstellung von Elektrizit\u00e4tsverteilungs U schalteinrichtungen Herstellung von sonstigen elektrische",
    "sg:phone":"+41 13819988",
    "sg:postcode":"5430",
    "sg:province":"Aargau",
    "wof:name":"Heeb + Enzler Ag",
    "wof:placetype":"venue"
},
  "geometry": {"coordinates":[8.5804328918,47.315372467],"type":"Point"}
}