{
  "type": "Feature",
  "properties": {
    "iso:country":"CH",
    "sg:address":"Bahnhofstrasse 29",
    "sg:city":"Schaffhausen",
    "sg:orig_category":"Organisationen der Wohlfahrtspflege",
    "sg:phone":"+41 52 624 72 05",
    "sg:postcode":"8200",
    "sg:province":"Schaffhausen",
    "wof:name":"Pflegekinder-aktion Sh",
    "wof:placetype":"venue"
},
  "geometry": {"coordinates":[8.6326417923,47.6980514526],"type":"Point"}
}