{
  "type": "Feature",
  "properties": {
    "addr:full":"Grimisuat Grimisuat Valais 1971",
    "addr:postcode":"1971",
    "iso:country":"CH",
    "sg:address":"Grimisuat",
    "sg:city":"Grimisuat",
    "sg:classifiers":[
        {
            "category":"Banks & Credit Unions",
            "subcategory":"Bank",
            "type":"Services"
        }
    ],
    "sg:phone":"+41 27 398 27 17",
    "sg:postcode":"1971",
    "sg:province":"Valais",
    "wof:name":"Banque Cantonale Du Valais",
    "wof:placetype":"venue"
},
  "geometry": {"coordinates":[7.37887,46.254509],"type":"Point"}
}