{
  "type": "Feature",
  "properties": {
    "iso:country":"CH",
    "sg:address":"Stationsstrasse 54",
    "sg:city":"Wettswil",
    "sg:orig_category":"Malerei",
    "sg:postcode":"8907",
    "sg:province":"Z\u00fcrich",
    "wof:name":"Marcel K\u00e4ppeli Kundenmalerei",
    "wof:placetype":"venue"
},
  "geometry": {"coordinates":[8.3111553192,46.9950714111],"type":"Point"}
}