{
  "type": "Feature",
  "properties": {
    "iso:country":"CH",
    "sg:address":"Vanetscha 11",
    "sg:city":"Triesen",
    "sg:orig_category":"Verwaltung von Immobilien Wirtschaftspr\u00fcfung, Steuerberatung U Treuhand",
    "sg:phone":"+41 55 451 52 30",
    "sg:postcode":"9495",
    "wof:name":"Adfida Ag, Treuhand Und Revisionsgesellschaft",
    "wof:placetype":"venue"
},
  "geometry": {"coordinates":[8.8636655807,47.1902389526],"type":"Point"}
}