{
  "type": "Feature",
  "properties": {
    "iso:country":"CH",
    "sg:address":"B\u00e4chlihalde 5",
    "sg:city":"Rudolfstetten",
    "sg:orig_category":"Sonstige Kurierdienste",
    "sg:phone":"+41 56 631 06 06",
    "sg:postcode":"8964",
    "sg:province":"Aargau",
    "wof:name":"Sport-hit Media Gmbh",
    "wof:placetype":"venue"
},
  "geometry": {"coordinates":[8.3781747818,47.3711738586],"type":"Point"}
}