{
  "type": "Feature",
  "properties": {
    "iso:country":"CH",
    "sg:address":"Gemeindezentrum",
    "sg:city":"Muhen",
    "sg:orig_category":"Nationale Postdienste",
    "sg:phone":"+41 62 723 24 27",
    "sg:postcode":"5037",
    "sg:province":"Aargau",
    "wof:name":"Die Schweizerische Post",
    "wof:placetype":"venue"
},
  "geometry": {"coordinates":[8.0539398193,47.3407707214],"type":"Point"}
}