{
  "type": "Feature",
  "properties": {
    "iso:country":"CH",
    "sg:address":"M\u00fcnchwiler Strasse 21",
    "sg:city":"T\u00e4gerschen",
    "sg:orig_category":"Herstellung von Erzeugnissen aus Beton, Gips U Zement N\u00e4gel and Nadeln Herstellung",
    "sg:phone":"+41 71 918 60 70",
    "sg:postcode":"9554",
    "sg:province":"Thurgau",
    "wof:name":"F. & L. Bachmann Ag",
    "wof:placetype":"venue"
},
  "geometry": {"coordinates":[9.0265636444,47.5077629089],"type":"Point"}
}