{
  "type": "Feature",
  "properties": {
    "iso:country":"CH",
    "sg:address":"Langstrasse 200 8005 Z\u00fcrich. Postfach",
    "sg:city":"Z\u00fcrich",
    "sg:orig_category":"Elektroinstallation",
    "sg:phone":"+41 17641414",
    "sg:postcode":"8005",
    "sg:province":"Z\u00fcrich",
    "wof:name":"Schneebeli Jack, Elektrofachgesch\u00e4ft",
    "wof:placetype":"venue"
},
  "geometry": {"coordinates":[8.5268201828,47.2278633118],"type":"Point"}
}