{
  "type": "Feature",
  "properties": {
    "iso:country":"CH",
    "sg:address":"Soodstrasse 32 8134 Adliswil. Postfach",
    "sg:city":"Adliswil",
    "sg:orig_category":"Herstellung von Elektrizit\u00e4tsverteilungs U schalteinrichtungen",
    "sg:postcode":"8134",
    "sg:province":"Z\u00fcrich",
    "wof:name":"Huber Msr Technik Mess, Steuer- U. Regeltechnik; Wartung, Reparatur, Neuinstallation, Fehlersuche, Verkauf",
    "wof:placetype":"venue"
},
  "geometry": {"coordinates":[8.5248565674,47.3176345825],"type":"Point"}
}