{
  "type": "Feature",
  "properties": {
    "iso:country":"CH",
    "sg:address":"Schwerzistrasse 30 8807 Freienbach. Postfach 363",
    "sg:city":"Freienbach",
    "sg:orig_category":"Handelsvermittlung U Grosshandel",
    "sg:phone":"+41 17752424",
    "sg:postcode":"8807",
    "sg:province":"Schwyz",
    "wof:name":"Ruia Ag Warenimport, -export Usw",
    "wof:placetype":"venue"
},
  "geometry": {"coordinates":[8.4450368881,47.4173240662],"type":"Point"}
}