{
  "type": "Feature",
  "properties": {
    "iso:country":"CH",
    "sg:address":"G\u00fcterstrasse 18",
    "sg:city":"Luzern",
    "sg:orig_category":"Bauschreinerei",
    "sg:phone":"+41 41 360 16 20",
    "sg:postcode":"6005",
    "sg:province":"Luzern",
    "wof:name":"Markus Vogel M\u00f6belwerkstatt",
    "wof:placetype":"venue"
},
  "geometry": {"coordinates":[8.311487,47.044895],"type":"Point"}
}