{
  "type": "Feature",
  "properties": {
    "iso:country":"CH",
    "sg:address":"La Gollette",
    "sg:city":"Is\u00e9rables",
    "sg:orig_category":"Abwasserreinigung Wasserversorgung",
    "sg:phone":"+41 27 306 21 23",
    "sg:postcode":"1914",
    "sg:province":"Valais",
    "wof:name":"Station D'\u00e9puration",
    "wof:placetype":"venue"
},
  "geometry": {"coordinates":[7.24518,46.160439],"type":"Point"}
}