{
  "type": "Feature",
  "properties": {
    "iso:country":"CH",
    "sg:address":"Thunstrasse 9",
    "sg:city":"M\u00fcnsingen",
    "sg:orig_category":"Detailhandel mit Sportartikeln Sonstige mit Sport verbundene T\u00e4tigkeiten",
    "sg:phone":"+41 31 722 10 23",
    "sg:postcode":"3110",
    "sg:province":"Bern",
    "wof:name":"Olivos Gmbh",
    "wof:placetype":"venue"
},
  "geometry": {"coordinates":[7.5626749992,46.8731040955],"type":"Point"}
}