{
  "type": "Feature",
  "properties": {
    "iso:country":"CH",
    "sg:address":"Seemattstrasse 64",
    "sg:city":"Cham",
    "sg:orig_category":"Schulpflegen",
    "sg:postcode":"6330",
    "sg:province":"Zug",
    "wof:name":"Bezirksschulpflege Affoltern Am Albis",
    "wof:placetype":"venue"
},
  "geometry": {"coordinates":[8.4532852173,47.2772254944],"type":"Point"}
}