{
  "type": "Feature",
  "properties": {
    "iso:country":"CH",
    "sg:address":"Vogelsangweg 11",
    "sg:city":"Boll",
    "sg:orig_category":"Unternehmensberatung",
    "sg:phone":"+41 31 839 46 89",
    "sg:postcode":"3067",
    "sg:province":"Bern",
    "wof:name":"B\u00fcro F\u00fcr Baumanagement Gmbh, Boll",
    "wof:placetype":"venue"
},
  "geometry": {"coordinates":[7.5616650581,46.9468002319],"type":"Point"}
}