{
  "type": "Feature",
  "properties": {
    "iso:country":"CH",
    "sg:address":"Forchstrasse 195",
    "sg:city":"Hinteregg",
    "sg:orig_category":"Bauschreinerei Herstellung von Konstruktionsteilen, Fertigbauteilen U Ausbauelementen aus Holz",
    "sg:phone":"+41 19550709",
    "sg:postcode":"8132",
    "sg:province":"Z\u00fcrich",
    "wof:name":"Schreinerei Sch\u00e4tti R. + R. Ag",
    "wof:placetype":"venue"
},
  "geometry": {"coordinates":[8.681878,47.30759],"type":"Point"}
}