{
  "type": "Feature",
  "properties": {
    "addr:full":"Route De La Scie 5 Estavayer-le-lac Fribourg 1470",
    "addr:housenumber":"5",
    "addr:postcode":"1470",
    "addr:street":"Route De La Scie;Fribourg",
    "iso:country":"CH",
    "sg:address":"Route De La Scie 5",
    "sg:city":"Estavayer-le-lac",
    "sg:orig_category":"Autospenglereien Handel mit Automobilen",
    "sg:postcode":"1470",
    "sg:province":"Fribourg",
    "wof:name":"Johnny Niederh\u00e4user S\u00e0rl Carosserie De La Scie",
    "wof:placetype":"venue"
},
  "geometry": {"coordinates":[6.848852,46.843845],"type":"Point"}
}