{
  "type": "Feature",
  "properties": {
    "iso:country":"CH",
    "sg:address":"Chemin Du Devin 8a 1000 Lausanne. Postfach",
    "sg:city":"Lausanne",
    "sg:orig_category":"Architektur U Ingenieurb\u00fcros",
    "sg:postcode":"1002",
    "sg:province":"Vaud",
    "wof:name":"Meylan Georges Arthur - Bureau D'architectes Ets S\u00e0rl",
    "wof:placetype":"venue"
},
  "geometry": {"coordinates":[6.652131,46.527584],"type":"Point"}
}