{
  "type": "Feature",
  "properties": {
    "iso:country":"CH",
    "sg:address":"1026",
    "sg:city":"Denges",
    "sg:orig_category":"Grosshandel mit Holz U Baustoffen Sonstiger Detailhandel mit Metallwaren, Anstrichmitteln, Glaswaren",
    "sg:phone":"+41 79 401 23 08",
    "sg:postcode":"1026",
    "sg:province":"Vaud",
    "wof:name":"Rosat M. Sa",
    "wof:placetype":"venue"
},
  "geometry": {"coordinates":[6.5408349037,46.5242347717],"type":"Point"}
}