{
  "type": "Feature",
  "properties": {
    "iso:country":"CH",
    "sg:address":"Kirchgasse 1",
    "sg:city":"Russikon",
    "sg:orig_category":"Detailhandel mit Brot, Back U S\u00fcsswaren Detailhandel mit Waren verschiedener Art, Hauptrichtung Nahr",
    "sg:phone":"+41 19540046",
    "sg:postcode":"8332",
    "sg:province":"Z\u00fcrich",
    "wof:name":"Famila Sa",
    "wof:placetype":"venue"
},
  "geometry": {"coordinates":[8.776438,47.394577],"type":"Point"}
}