{
  "type": "Feature",
  "properties": {
    "iso:country":"CH",
    "sg:address":"Bellikonerstrasse 239",
    "sg:city":"Widen",
    "sg:orig_category":"Detailhandel mit Brot, Back U S\u00fcsswaren",
    "sg:phone":"+41 56 633 78 44",
    "sg:postcode":"8967",
    "sg:province":"Aargau",
    "wof:name":"Peter Moos B\u00e4ckerei-konditorei",
    "wof:placetype":"venue"
},
  "geometry": {"coordinates":[8.362803,47.368019],"type":"Point"}
}