{
  "type": "Feature",
  "properties": {
    "iso:country":"CH",
    "sg:address":"Rosenbergstrasse 91",
    "sg:city":"St.gallen",
    "sg:orig_category":"Sonstige mit der Informatik verbundene T\u00e4tigkeiten",
    "sg:phone":"+41 71 260 22 50",
    "sg:postcode":"9000",
    "sg:province":"St. Gallen",
    "wof:name":"Gschwend Baumanagement",
    "wof:placetype":"venue"
},
  "geometry": {"coordinates":[9.3653059006,47.4222183228],"type":"Point"}
}