{
  "type": "Feature",
  "properties": {
    "iso:country":"CH",
    "sg:address":"Im Heimgarten 15",
    "sg:city":"Basel",
    "sg:orig_category":"Werbegrafikateliers",
    "sg:phone":"+41 61 301 40 60",
    "sg:postcode":"4054",
    "sg:province":"Basel-Stadt",
    "wof:name":"Hans Marti Grafisches Atelier",
    "wof:placetype":"venue"
},
  "geometry": {"coordinates":[7.5660839081,47.5467300415],"type":"Point"}
}