{
  "type": "Feature",
  "properties": {
    "iso:country":"CH",
    "sg:address":"Kleinnaumattweg 2",
    "sg:city":"Meggen",
    "sg:classifiers":[
        {
            "category":"Health Services",
            "subcategory":"Hospital",
            "type":"Services"
        }
    ],
    "sg:phone":"+41 41 377 36 27",
    "sg:postcode":"6045",
    "sg:province":"Luzern",
    "sg:tags":[
        "hygiene"
    ],
    "wof:name":"Hygiene + Mikrobiologie-labor B. Anderhub",
    "wof:placetype":"venue"
},
  "geometry": {"coordinates":[8.3664588928,47.037071228],"type":"Point"}
}