{
  "type": "Feature",
  "properties": {
    "iso:country":"CH",
    "sg:address":"Winterhalten 6487 G\u00f6schenen. Postfach",
    "sg:city":"G\u00f6schenen",
    "sg:orig_category":"Wasserversorgung",
    "sg:phone":"+41 41 885 11 91",
    "sg:postcode":"6487",
    "sg:province":"Uri",
    "wof:name":"Gotthardwasser Ag Nachhaltige Nutzung Von Nat\u00fcrlichem Wasser Usw",
    "wof:placetype":"venue"
},
  "geometry": {"coordinates":[8.5888061523,46.6691894531],"type":"Point"}
}