{
  "type": "Feature",
  "properties": {
    "iso:country":"CH",
    "sg:address":"Gwattstr. 81",
    "sg:city":"Thun",
    "sg:orig_category":"Kauf U Verkauf von Immobilien auf eigene Rechnung",
    "sg:phone":"+41 33 336 88 39",
    "sg:postcode":"3600",
    "sg:province":"Bern",
    "wof:name":"Schlaefli H. E.",
    "wof:placetype":"venue"
},
  "geometry": {"coordinates":[7.6277470589,46.7310295105],"type":"Point"}
}