{
  "type": "Feature",
  "properties": {
    "iso:country":"CH",
    "sg:address":"Rennweg 26 2504 Biel/bienne. Postfach",
    "sg:city":"Biel/bienne",
    "sg:orig_category":"Erschliessung von Grundst\u00fccken",
    "sg:phone":"+41 32 342 00 54",
    "sg:postcode":"2504",
    "sg:province":"Bern",
    "wof:name":"Coop\u00e9rative Rennweg 26",
    "wof:placetype":"venue"
},
  "geometry": {"coordinates":[7.2659702301,47.1444206238],"type":"Point"}
}