{
  "type": "Feature",
  "properties": {
    "iso:country":"CH",
    "sg:address":"Hauacher",
    "sg:city":"Schenkon",
    "sg:orig_category":"Hoch U Tiefbau",
    "sg:phone":"+41 41 448 10 40",
    "sg:postcode":"6214",
    "sg:province":"Luzern",
    "wof:name":"Julius Salzmann Bauunternehmung",
    "wof:placetype":"venue"
},
  "geometry": {"coordinates":[8.3223896027,47.1305160522],"type":"Point"}
}