{
  "type": "Feature",
  "properties": {
    "iso:country":"CH",
    "sg:address":"Hermetschloostrasse 77",
    "sg:city":"Z\u00fcrich",
    "sg:orig_category":"Herstellung von Schuhen",
    "sg:phone":"+41 14310077",
    "sg:postcode":"8048",
    "sg:province":"Z\u00fcrich",
    "wof:name":"Bretscher & Co Fabrikationsmaschinen F. D. Schuh- U. Gerbereiindustrie Usw; Handel",
    "wof:placetype":"venue"
},
  "geometry": {"coordinates":[8.4737081528,47.3937301636],"type":"Point"}
}