{
  "type": "Feature",
  "properties": {
    "iso:country":"CH",
    "sg:address":"Platanes Rue Des 1958 St-l\u00e9onard. Postfach",
    "sg:city":"St-l\u00e9onard",
    "sg:classifiers":[
        {
            "category":"Restaurant",
            "type":"Food & Drink"
        }
    ],
    "sg:phone":"+41 27 203 24 95",
    "sg:postcode":"1958",
    "sg:province":"Valais",
    "sg:tags":[
        "tea-rooms",
        "restaurants"
    ],
    "wof:name":"Caf\u00e9-restaurant Du Rawyl, Benhammou \u00abchez Amina\u00bb",
    "wof:placetype":"venue"
},
  "geometry": {"coordinates":[7.4169597626,46.2535552979],"type":"Point"}
}