{
  "type": "Feature",
  "properties": {
    "iso:country":"CH",
    "sg:address":"Tarn 8342 Wernetshausen. Postfach",
    "sg:city":"Wernetshausen",
    "sg:orig_category":"Wohnheime",
    "sg:phone":"+41 19371700",
    "sg:postcode":"8342",
    "sg:province":"Z\u00fcrich",
    "wof:name":"Stiftung Landwirtschaft Und Behinderte",
    "wof:placetype":"venue"
},
  "geometry": {"coordinates":[8.8664503098,47.2987556458],"type":"Point"}
}