{
  "type": "Feature",
  "properties": {
    "iso:country":"CH",
    "sg:address":"Rue Pierre-aeby 4",
    "sg:city":"Fribourg",
    "sg:classifiers":[
        {
            "category":"Restaurant",
            "type":"Food & Drink"
        }
    ],
    "sg:phone":"+41 26 322 14 55",
    "sg:postcode":"1700",
    "sg:province":"Fribourg",
    "wof:name":"Restaurant Taberna Espanola",
    "wof:placetype":"venue"
},
  "geometry": {"coordinates":[7.1608371735,46.807220459],"type":"Point"}
}