{
  "type": "Feature",
  "properties": {
    "iso:country":"CH",
    "sg:address":"Hauptstrasse 47",
    "sg:city":"Nidau",
    "sg:orig_category":"Detailhandel mit Beleuchtungs U Haushaltsgegenst\u00e4nden Detailhandel mit Spielwaren",
    "sg:phone":"+41 32 331 96 16",
    "sg:postcode":"2560",
    "sg:province":"Bern",
    "wof:name":"Martin Heiniger Haushalt Sport Spielwaren",
    "wof:placetype":"venue"
},
  "geometry": {"coordinates":[7.240856,47.125191],"type":"Point"}
}