{
  "type": "Feature",
  "properties": {
    "iso:country":"CH",
    "sg:address":"Dorfstrasse 89",
    "sg:city":"Geroldswil",
    "sg:orig_category":"Detailhandel mit elektrischen Haushalts-,Radio U Fernsehger\u00e4ten sowie Musikinstrumenten",
    "sg:phone":"+41 17484847",
    "sg:postcode":"8954",
    "sg:province":"Z\u00fcrich",
    "wof:name":"Stefis Radio-tv, Nemeth",
    "wof:placetype":"venue"
},
  "geometry": {"coordinates":[8.4106645584,47.4238586426],"type":"Point"}
}