{
  "type": "Feature",
  "properties": {
    "iso:country":"CH",
    "sg:address":"Hauptstrasse 37",
    "sg:city":"Arisdorf",
    "sg:orig_category":"Datenverarbeitungsdienste Softwareentwicklung U beratung",
    "sg:phone":"+41 61 813 01 01",
    "sg:postcode":"4422",
    "sg:province":"Basel-Landschaft",
    "wof:name":"Idea Inter Data Equipment Association Gmbh",
    "wof:placetype":"venue"
},
  "geometry": {"coordinates":[7.764898,47.513546],"type":"Point"}
}