{
  "type": "Feature",
  "properties": {
    "iso:country":"CH",
    "sg:address":"Gotthelfstrasse 38 8000 Z\u00fcrich. Postfach",
    "sg:city":"Z\u00fcrich",
    "sg:orig_category":"Sonstige Kurierdienste",
    "sg:postcode":"8001",
    "sg:province":"Z\u00fcrich",
    "wof:name":"Kurierdienste Pint\u00e9r M.i., Z\u00fcrich",
    "wof:placetype":"venue"
},
  "geometry": {"coordinates":[8.5215349197,47.3687553406],"type":"Point"}
}