{
  "type": "Feature",
  "properties": {
    "iso:country":"CH",
    "sg:address":"Mittendorfstrasse 15",
    "sg:city":"B\u00fctschwil",
    "sg:orig_category":"Vorschulen, Kinderg\u00e4rten",
    "sg:postcode":"9606",
    "sg:province":"St. Gallen",
    "wof:name":"Kindergarten Schulhaus",
    "wof:placetype":"venue"
},
  "geometry": {"coordinates":[9.0714817047,47.3612518311],"type":"Point"}
}