{
  "type": "Feature",
  "properties": {
    "iso:country":"CH",
    "sg:address":"Rue Jacquet-droz 1 2000 Neuch\u00e2tel Case Postale 41",
    "sg:city":"Neuenburg",
    "sg:orig_category":"Herstellung von Mess U Kontrollinstrumenten U vorrichtungen Herstellung von elektronischen Bauelemen",
    "sg:phone":"+41 71 622 66 63",
    "sg:postcode":"2000",
    "sg:province":"Neuch\u00e2tel",
    "wof:name":"Etb Sensortechnik Gmbh",
    "wof:placetype":"venue"
},
  "geometry": {"coordinates":[9.1381845474,47.5666694641],"type":"Point"}
}