{
  "type": "Feature",
  "properties": {
    "iso:country":"CH",
    "sg:address":"Bahnhofstrasse 2",
    "sg:city":"Netstal",
    "sg:orig_category":"Elektroinstallation",
    "sg:phone":"+41 55 640 10 86",
    "sg:postcode":"8754",
    "sg:province":"Glarus",
    "wof:name":"Elektro L.friedrich",
    "wof:placetype":"venue"
},
  "geometry": {"coordinates":[9.0568408966,47.0639228821],"type":"Point"}
}