{
  "type": "Feature",
  "properties": {
    "iso:country":"CH",
    "sg:address":"St-jean Rue 17",
    "sg:city":"Nyon",
    "sg:orig_category":"Fachdetailhandel in Verkaufsr\u00e4umen",
    "sg:phone":"+41 22 361 46 24",
    "sg:postcode":"1260",
    "sg:province":"Vaud",
    "wof:name":"Mp Piguet Marc Horloger",
    "wof:placetype":"venue"
},
  "geometry": {"coordinates":[6.2391448021,46.3828277588],"type":"Point"}
}