{
  "type": "Feature",
  "properties": {
    "iso:country":"CH",
    "sg:address":"Constant Galeries B.- 1 1003 Lausanne. Postfach",
    "sg:city":"Lausanne",
    "sg:orig_category":"Finanzierungsinstitutionen",
    "sg:postcode":"1003",
    "sg:province":"Vaud",
    "wof:name":"Jauch, Marfin",
    "wof:placetype":"venue"
},
  "geometry": {"coordinates":[8.6357097626,47.024597168],"type":"Point"}
}