{
  "type": "Feature",
  "properties": {
    "iso:country":"CH",
    "sg:address":"Wehntalerstrasse 160",
    "sg:city":"Z\u00fcrich",
    "sg:orig_category":"Interessenvertretungen",
    "sg:postcode":"8057",
    "sg:province":"Z\u00fcrich",
    "wof:name":"Karamsin-gesellschaft",
    "wof:placetype":"venue"
},
  "geometry": {"coordinates":[8.5323238373,47.4060516357],"type":"Point"}
}