{
  "type": "Feature",
  "properties": {
    "iso:country":"CH",
    "sg:address":"2000",
    "sg:city":"Neuenburg",
    "sg:orig_category":"Pensionskassen",
    "sg:phone":"+41 32 723 61 11",
    "sg:postcode":"2000",
    "sg:province":"Neuch\u00e2tel",
    "wof:name":"Caisse De Retraite Et D'invalidit\u00e9 Du Personnel De La Banque Cantonale Neuch\u00e2teloise",
    "wof:placetype":"venue"
},
  "geometry": {"coordinates":[6.941450119,46.9826812744],"type":"Point"}
}