{
  "type": "Feature",
  "properties": {
    "iso:country":"CH",
    "sg:address":"Angensteinerstrasse 32 4052 Basel. Postfach",
    "sg:city":"Basel",
    "sg:orig_category":"Werbung",
    "sg:postcode":"4052",
    "sg:province":"Basel-Stadt",
    "wof:name":"Bum Brodmann Und M\u00f6sch Ag Werbeagentur Usw",
    "wof:placetype":"venue"
},
  "geometry": {"coordinates":[7.6041870117,47.549407959],"type":"Point"}
}