{
  "type": "Feature",
  "properties": {
    "iso:country":"CH",
    "sg:address":"B\u00fcrglen 209",
    "sg:city":"Rietheim",
    "sg:orig_category":"Architektur U Ingenieurb\u00fcros",
    "sg:phone":"+41 56 249 43 06",
    "sg:postcode":"5323",
    "sg:province":"Aargau",
    "wof:name":"Riemenschneider",
    "wof:placetype":"venue"
},
  "geometry": {"coordinates":[8.275536,47.60331],"type":"Point"}
}