{
  "type": "Feature",
  "properties": {
    "iso:country":"CH",
    "sg:address":"Lettstrasse 2 9490 Vaduz. Postfach",
    "sg:city":"Vaduz",
    "sg:classifiers":[
        {
            "category":"Insurance",
            "subcategory":"Insurance Agent",
            "type":"Services"
        }
    ],
    "sg:phone":"+423 232 24 05",
    "sg:postcode":"9490",
    "sg:tags":[
        "versicherungsagenturen",
        "-broker"
    ],
    "wof:name":"Theo J\u00e4ger Versicherungen",
    "wof:placetype":"venue"
},
  "geometry": {"coordinates":[9.5204248428,47.1407966614],"type":"Point"}
}