{
  "type": "Feature",
  "properties": {
    "iso:country":"CH",
    "sg:address":"Talstrasse 33a",
    "sg:city":"Ennetmoos",
    "sg:orig_category":"Datenverarbeitungsdienste Sonstige mit der Informatik verbundene T\u00e4tigkeiten",
    "sg:phone":"+41 41 610 31 33",
    "sg:postcode":"6372",
    "sg:province":"Nidwalden",
    "wof:name":"Rst-beratung Ag",
    "wof:placetype":"venue"
},
  "geometry": {"coordinates":[8.336337,46.955341],"type":"Point"}
}