{
  "type": "Feature",
  "properties": {
    "iso:country":"CH",
    "sg:address":"Bitzistrasse 2",
    "sg:city":"Stans",
    "sg:orig_category":"Aktivit\u00e4t der Bankinstitute",
    "sg:phone":"+41 800 811 820",
    "sg:postcode":"6370",
    "sg:province":"Nidwalden",
    "wof:name":"Migrosbank Einkaufszentrum Wynecenter",
    "wof:placetype":"venue"
},
  "geometry": {"coordinates":[8.090435,47.386078],"type":"Point"}
}