{
  "type": "Feature",
  "properties": {
    "iso:country":"CH",
    "sg:address":"Via Cantonale 6572 Quartino. Postfach",
    "sg:city":"Quartino",
    "sg:orig_category":"Detailhandel mit Waren verschiedener Art, Hauptrichtung Nahrungsmittel Herstellung von Speiseeis U S",
    "sg:phone":"+41 91 858 01 03",
    "sg:postcode":"6572",
    "sg:province":"Ticino",
    "wof:name":"Rcm Distribuzioni Sagl Prodotti Alimentari; Acquisto, Vendita, Import, Esport",
    "wof:placetype":"venue"
},
  "geometry": {"coordinates":[8.9064464569,46.1532821655],"type":"Point"}
}