{
  "type": "Feature",
  "properties": {
    "iso:country":"CH",
    "sg:address":"Obere Aegertenstrasse 12",
    "sg:city":"Stallikon",
    "sg:orig_category":"Herstellung von optischen U fotografischen Ger\u00e4ten",
    "sg:phone":"+41 17000695",
    "sg:postcode":"8143",
    "sg:province":"Z\u00fcrich",
    "wof:name":"Keiser Heinz Mechtronic",
    "wof:placetype":"venue"
},
  "geometry": {"coordinates":[8.4919204712,47.320148468],"type":"Point"}
}