{
  "type": "Feature",
  "properties": {
    "iso:country":"CH",
    "sg:address":"Gotthardstrasse 52",
    "sg:city":"Andermatt",
    "sg:orig_category":"RESTAURANTS: TEA-ROOMS",
    "sg:phone":"+41 41 887 10 50",
    "sg:postcode":"6490",
    "sg:province":"Uri",
    "wof:name":"Restaurant City-bar, Roth-bleisch A. Und M.",
    "wof:placetype":"venue"
},
  "geometry": {"coordinates":[8.5975112915,46.6339492798],"type":"Point"}
}