{
  "type": "Feature",
  "properties": {
    "iso:country":"CH",
    "sg:address":"Grand-rue 32",
    "sg:city":"Bulle",
    "sg:orig_category":"RESTAURANTS: TEA-ROOMS",
    "sg:postcode":"1630",
    "sg:province":"Fribourg",
    "wof:name":"Esseiva Juliette",
    "wof:placetype":"venue"
},
  "geometry": {"coordinates":[7.0577559471,46.6192741394],"type":"Point"}
}