{
  "type": "Feature",
  "properties": {
    "iso:country":"CH",
    "sg:address":"6986",
    "sg:city":"Curio",
    "sg:orig_category":"Architekturb\u00fcros",
    "sg:phone":"+41 91 606 33 72",
    "sg:postcode":"6986",
    "sg:province":"Ticino",
    "wof:name":"Daniel M\u00fcller Studio D'architettura",
    "wof:placetype":"venue"
},
  "geometry": {"coordinates":[8.860815,46.002316],"type":"Point"}
}