{
  "type": "Feature",
  "properties": {
    "iso:country":"CH",
    "sg:address":"Baarerstrasse 8 6300 Zug. Postfach",
    "sg:city":"Zug",
    "sg:orig_category":"Herstellung von Werkzeugen",
    "sg:phone":"+41 41 720 10 90",
    "sg:postcode":"6301",
    "sg:province":"Zug",
    "wof:name":"Brigadier Werkzeuge Ag Werkzeuge, Garten- U. Elektroger\u00e4te, Usw.; Entwicklung, Herstellung, Vertrieb",
    "wof:placetype":"venue"
},
  "geometry": {"coordinates":[8.5163869858,47.1713981628],"type":"Point"}
}