{
  "type": "Feature",
  "properties": {
    "iso:country":"CH",
    "sg:address":"Pr\u00e4tschliweg 2",
    "sg:city":"Chur",
    "sg:orig_category":"Versicherungsagenturen and -broker -Verm\u00f6gensverwaltung",
    "sg:phone":"+41 81 354 99 11",
    "sg:postcode":"7000",
    "sg:province":"Graubunden",
    "wof:name":"Innovative Independent Trust Ag Iitag",
    "wof:placetype":"venue"
},
  "geometry": {"coordinates":[9.5406837463,46.8658256531],"type":"Point"}
}