{
  "type": "Feature",
  "properties": {
    "iso:country":"CH",
    "sg:address":"Tiefenaustrasse 52 3012 Bern. Postfach",
    "sg:city":"Bern",
    "sg:orig_category":"Unternehmensberatung",
    "sg:postcode":"3005",
    "sg:province":"Bern",
    "wof:name":"Symbiont Consulting Gmbh Unternehmensberatung, -unterst\u00fctzung, Bes. Rechnungswesen, Marketing Usw",
    "wof:placetype":"venue"
},
  "geometry": {"coordinates":[7.4403629303,46.9599266052],"type":"Point"}
}