{
  "type": "Feature",
  "properties": {
    "iso:country":"CH",
    "sg:address":"Ziegelei-m\u00e4rit",
    "sg:city":"Zollikofen",
    "sg:orig_category":"Herstellung von Erzeugnissen aus Beton, Gips U Zement Mahl U Sch\u00e4lm\u00fchlen",
    "sg:phone":"+41 56 464 68 28",
    "sg:postcode":"3052",
    "sg:province":"Bern",
    "wof:name":"Opalit Ag",
    "wof:placetype":"venue"
},
  "geometry": {"coordinates":[8.1662406921,47.4364585876],"type":"Point"}
}