{
  "type": "Feature",
  "properties": {
    "iso:country":"CH",
    "sg:address":"Tramstrasse 53",
    "sg:city":"Suhr",
    "sg:orig_category":"Tankstellen",
    "sg:phone":"+41 62 842 44 64",
    "sg:postcode":"5034",
    "sg:province":"Aargau",
    "wof:name":"Ernst Christen Migrol-service-station",
    "wof:placetype":"venue"
},
  "geometry": {"coordinates":[8.0774374008,47.3776283264],"type":"Point"}
}