{
  "type": "Feature",
  "properties": {
    "addr:full":"Imm. Multiservices Onnens Fribourg 1756",
    "addr:postcode":"1756",
    "iso:country":"CH",
    "sg:address":"Imm. Multiservices",
    "sg:city":"Onnens",
    "sg:classifiers":[
        {
            "category":"Banks & Credit Unions",
            "subcategory":"Bank",
            "type":"Services"
        }
    ],
    "sg:phone":"+41 26 470 19 18",
    "sg:postcode":"1756",
    "sg:province":"Fribourg",
    "wof:name":"Raiffeisen De Sarine Ouest",
    "wof:placetype":"venue"
},
  "geometry": {"coordinates":[7.038205,46.776009],"type":"Point"}
}