{
  "type": "Feature",
  "properties": {
    "iso:country":"CH",
    "sg:address":"Sternmatt 1 6010 Kriens. Postfach",
    "sg:city":"Kriens",
    "sg:orig_category":"Unclassifiable Establishments",
    "sg:postcode":"6010",
    "sg:province":"Luzern",
    "wof:name":"New Future World Ag Dienstleistungen U. Handel Mit Waren \u00fcber Das Internet, Bes. E-commerce Usw",
    "wof:placetype":"venue"
},
  "geometry": {"coordinates":[8.2974510193,47.0274620056],"type":"Point"}
}