{
  "type": "Feature",
  "properties": {
    "iso:country":"CH",
    "sg:address":"W\u00e4gitalstrasse 2",
    "sg:city":"Vorderthal",
    "sg:orig_category":"Museen",
    "sg:phone":"+41 55 440 18 74",
    "sg:postcode":"8857",
    "sg:province":"Schwyz",
    "wof:name":"Marchmuseum Kw-zentrale Rempen",
    "wof:placetype":"venue"
},
  "geometry": {"coordinates":[8.8976688385,47.1384849548],"type":"Point"}
}