{
  "type": "Feature",
  "properties": {
    "iso:country":"CH",
    "sg:address":"St. Galler-ring 87",
    "sg:city":"Basel",
    "sg:orig_category":"Zimmerei, Dachdeckerei, Bauspenglerei U Abdichtung",
    "sg:phone":"+41 61 301 27 58",
    "sg:postcode":"4055",
    "sg:province":"Basel-Stadt",
    "wof:name":"Yvonne Toffol Holzbau & Renovationen",
    "wof:placetype":"venue"
},
  "geometry": {"coordinates":[7.5674657822,47.5567932129],"type":"Point"}
}