{
  "type": "Feature",
  "properties": {
    "iso:country":"CH",
    "sg:address":"Mittelweg 3",
    "sg:city":"Lyssach",
    "sg:orig_category":"Stukkateurgewerbe, Gipserei U Verputzerei",
    "sg:phone":"+41 34 445 46 18",
    "sg:postcode":"3421",
    "sg:province":"Bern",
    "wof:name":"Zbinden Urs",
    "wof:placetype":"venue"
},
  "geometry": {"coordinates":[7.5812439919,47.0651092529],"type":"Point"}
}