{
  "type": "Feature",
  "properties": {
    "iso:country":"CH",
    "sg:address":"Seftigenstrasse 321 3084 Wabern. Postfach",
    "sg:city":"Wabern",
    "sg:orig_category":"Wirtschaftspr\u00fcfung, Steuerberatung U Treuhand",
    "sg:postcode":"3084",
    "sg:province":"Bern",
    "wof:name":"Hinni Treuhand-consulting",
    "wof:placetype":"venue"
},
  "geometry": {"coordinates":[7.4567108154,46.9258804321],"type":"Point"}
}