{
  "type": "Feature",
  "properties": {
    "iso:country":"CH",
    "sg:address":"Route Coudres 10",
    "sg:city":"C\u00e9ligny",
    "sg:classifiers":[
        {
            "category":"Travel",
            "subcategory":"Hotels & Motels",
            "type":"Entertainment"
        }
    ],
    "sg:phone":"+41 22 776 23 12",
    "sg:postcode":"1298",
    "sg:province":"Gen\u00e8ve",
    "sg:tags":[
        "hotels",
        "mit",
        "restaurant"
    ],
    "wof:name":"H\u00f4tel Du Soleil",
    "wof:placetype":"venue"
},
  "geometry": {"coordinates":[6.1947741508,46.3507194519],"type":"Point"}
}