{
  "type": "Feature",
  "properties": {
    "iso:country":"CH",
    "sg:address":"Rue Principale 41",
    "sg:city":"B\u00e9vilard",
    "sg:orig_category":"Detailhandel mit Milcherzeugnissen U Eiern Detailhandel mit Waren verschiedener Art, Hauptrichtung N",
    "sg:phone":"+41 32 492 17 77",
    "sg:postcode":"2735",
    "sg:province":"Bern",
    "wof:name":"Alimentation Bircher",
    "wof:placetype":"venue"
},
  "geometry": {"coordinates":[7.2824378014,47.2368164062],"type":"Point"}
}