{
  "type": "Feature",
  "properties": {
    "iso:country":"CH",
    "sg:address":"K\u00e4ferholzstrasse 41",
    "sg:city":"Basel",
    "sg:orig_category":"Detailhandel mit Schuhen",
    "sg:phone":"+41 61 601 06 29",
    "sg:postcode":"4058",
    "sg:province":"Basel-Stadt",
    "wof:name":"Saba Schuhhaus",
    "wof:placetype":"venue"
},
  "geometry": {"coordinates":[7.6175808907,47.5671577454],"type":"Point"}
}