{
  "type": "Feature",
  "properties": {
    "iso:country":"CH",
    "sg:address":"Rohrerstrasse 64 5000 Aarau. Postfach",
    "sg:city":"Aarau",
    "sg:orig_category":"Grosshandel mit Getr\u00e4nken",
    "sg:phone":"+41 62 838 00 30",
    "sg:postcode":"5000",
    "sg:province":"Aargau",
    "wof:name":"Z\u00fcrcher, M\u00e4chler & Cie Sa",
    "wof:placetype":"venue"
},
  "geometry": {"coordinates":[8.0605621338,47.3952522278],"type":"Point"}
}