{
  "type": "Feature",
  "properties": {
    "iso:country":"CH",
    "sg:address":"Riedenhaldenstrasse 245",
    "sg:city":"Z\u00fcrich",
    "sg:orig_category":"Unternehmensberatung",
    "sg:phone":"+41 13810903",
    "sg:postcode":"8046",
    "sg:province":"Z\u00fcrich",
    "wof:name":"Experts Consulting Gmbh",
    "wof:placetype":"venue"
},
  "geometry": {"coordinates":[8.5098028183,47.4194068909],"type":"Point"}
}