{
  "type": "Feature",
  "properties": {
    "iso:country":"CH",
    "sg:address":"Via Rondonico 50",
    "sg:city":"Ascona",
    "sg:orig_category":"Unclassifiable Establishments",
    "sg:postcode":"6612",
    "sg:province":"Ticino",
    "wof:name":"Hellmich Bau Ag Ticino",
    "wof:placetype":"venue"
},
  "geometry": {"coordinates":[8.7637491226,46.1558380127],"type":"Point"}
}