{
  "type": "Feature",
  "properties": {
    "iso:country":"CH",
    "sg:address":"Glockengasse 8",
    "sg:city":"Z\u00fcrich",
    "sg:orig_category":"RESTAURANTS: TEA-ROOMS",
    "sg:phone":"+41 12111262",
    "sg:postcode":"8001",
    "sg:province":"Z\u00fcrich",
    "wof:name":"Taverna Catalana, J. Ledesma Restaurant",
    "wof:placetype":"venue"
},
  "geometry": {"coordinates":[8.5403814316,47.3721656799],"type":"Point"}
}