{
  "type": "Feature",
  "properties": {
    "iso:country":"CH",
    "sg:address":"Rue De Locarno 3 1700 Fribourg Case Postale 740",
    "sg:city":"Fribourg",
    "sg:orig_category":"Interessenvertretungen U sonstige Vereinigungen Organisationen der Wohlfahrtspflege",
    "sg:phone":"+41 56 441 99 33",
    "sg:postcode":"1701",
    "sg:province":"Fribourg",
    "wof:name":"Beratungsstelle F\u00fcr Sucht & Pr\u00e4vention Avs",
    "wof:placetype":"venue"
},
  "geometry": {"coordinates":[8.2020521164,47.4825553894],"type":"Point"}
}