{
  "type": "Feature",
  "properties": {
    "iso:country":"CH",
    "sg:address":"Wilstrasse 21",
    "sg:city":"Lenzburg",
    "sg:orig_category":"Verwaltung von Immobilien",
    "sg:postcode":"5600",
    "sg:province":"Aargau",
    "wof:name":"Silvera Management Ag",
    "wof:placetype":"venue"
},
  "geometry": {"coordinates":[8.1768836975,47.380821228],"type":"Point"}
}