{
  "type": "Feature",
  "properties": {
    "iso:country":"CH",
    "sg:address":"1795",
    "sg:city":"Courlevon",
    "sg:orig_category":"Verwertung von Milch",
    "sg:postcode":"1795",
    "sg:province":"Fribourg",
    "wof:name":"Demierre Th.",
    "wof:placetype":"venue"
},
  "geometry": {"coordinates":[6.8859200478,46.6864814758],"type":"Point"}
}