{
  "type": "Feature",
  "properties": {
    "iso:country":"CH",
    "sg:address":"Kaserne",
    "sg:city":"Walenstadt",
    "sg:orig_category":"Kantinen",
    "sg:postcode":"8880",
    "sg:province":"St. Gallen",
    "wof:name":"G. + A. Chiecchi Restaurant Huba-st\u00fcbli",
    "wof:placetype":"venue"
},
  "geometry": {"coordinates":[8.1995038986,47.4742126465],"type":"Point"}
}