{
  "type": "Feature",
  "properties": {
    "iso:country":"CH",
    "sg:address":"Via Luigi Lavizzari 14",
    "sg:city":"Chiasso",
    "sg:orig_category":"Wirtschafts U Arbeitgeberverb\u00e4nde",
    "sg:postcode":"6830",
    "sg:province":"Ticino",
    "wof:name":"Associazione Ticinese Fa\u00e7onneurs, Atif.",
    "wof:placetype":"venue"
},
  "geometry": {"coordinates":[9.031006813,45.8363647461],"type":"Point"}
}