{
  "type": "Feature",
  "properties": {
    "iso:country":"CH",
    "sg:address":"Steinengraben 8",
    "sg:city":"Basel",
    "sg:orig_category":"Architektur U Ingenieurb\u00fcros Unternehmensberatung",
    "sg:phone":"+41 61 283 70 32",
    "sg:postcode":"4051",
    "sg:province":"Basel-Stadt",
    "wof:name":"Qs-b Qualit\u00e4tsmanagement",
    "wof:placetype":"venue"
},
  "geometry": {"coordinates":[7.584879,47.555016],"type":"Point"}
}