{
  "type": "Feature",
  "properties": {
    "iso:country":"CH",
    "sg:address":"Wiesenstrasse 8 8008 Z\u00fcrich. Postfach Postfach",
    "sg:city":"Z\u00fcrich",
    "sg:orig_category":"Wirtschaftspr\u00fcfung, Steuerberatung U Treuhand",
    "sg:phone":"+41 12599495",
    "sg:postcode":"8034",
    "sg:province":"Z\u00fcrich",
    "wof:name":"Ifp Indipendent Financial Partners Ag",
    "wof:placetype":"venue"
},
  "geometry": {"coordinates":[8.5518550873,47.3620567322],"type":"Point"}
}