{
  "type": "Feature",
  "properties": {
    "iso:country":"CH",
    "sg:address":"Rhihaldenstrasse 42",
    "sg:city":"Eglisau",
    "sg:orig_category":"Detailhandel mit M\u00f6beln U Haushaltsgegenst\u00e4nden",
    "sg:phone":"+41 18673325",
    "sg:postcode":"8193",
    "sg:province":"Z\u00fcrich",
    "wof:name":"Fermob, Hans L\u00fctolf",
    "wof:placetype":"venue"
},
  "geometry": {"coordinates":[8.5374107361,47.5700149536],"type":"Point"}
}