{
  "type": "Feature",
  "properties": {
    "iso:country":"CH",
    "sg:address":"Hauptstrasse 77",
    "sg:city":"Einsiedeln",
    "sg:orig_category":"RESTAURANTS: TEA-ROOMS",
    "sg:postcode":"8840",
    "sg:province":"Schwyz",
    "wof:name":"Restaurant New China, Danh Frau Thi-dep",
    "wof:placetype":"venue"
},
  "geometry": {"coordinates":[8.7492465973,47.1270599365],"type":"Point"}
}