{
  "type": "Feature",
  "properties": {
    "iso:country":"CH",
    "sg:address":"Poststrasse 9",
    "sg:city":"Zug",
    "sg:orig_category":"Finanzierungsinstitutionen",
    "sg:postcode":"6300",
    "sg:province":"Zug",
    "wof:name":"Zeidler Dr. Investor & Treuhand",
    "wof:placetype":"venue"
},
  "geometry": {"coordinates":[9.4750080109,47.166305542],"type":"Point"}
}