{
  "type": "Feature",
  "properties": {
    "iso:country":"CH",
    "sg:address":"Lauriedstrasse 7",
    "sg:city":"Zug",
    "sg:orig_category":"Mit dem Versicherungsgewerbe verbundene T\u00e4tigkeiten",
    "sg:phone":"+41 17154003",
    "sg:postcode":"6300",
    "sg:province":"Zug",
    "wof:name":"Vi Vorsorgeinvest Ag",
    "wof:placetype":"venue"
},
  "geometry": {"coordinates":[8.517999649,47.1746368408],"type":"Point"}
}