{
  "type": "Feature",
  "properties": {
    "addr:full":"Elisabethenstrasse 4 Basel Basel-Stadt 4051",
    "addr:housenumber":"4",
    "addr:postcode":"4051",
    "addr:street":"Elisabethenstrasse",
    "iso:country":"CH",
    "sg:address":"Elisabethenstrasse 4",
    "sg:city":"Basel",
    "sg:orig_category":"Detailhandel mit Bekleidung",
    "sg:phone":"+41 61 281 33 03",
    "sg:postcode":"4051",
    "sg:province":"Basel-Stadt",
    "wof:name":"Inflagranti.pi\u00f9 Gmbh",
    "wof:placetype":"venue"
},
  "geometry": {"coordinates":[7.591699,47.553486],"type":"Point"}
}