{
  "type": "Feature",
  "properties": {
    "iso:country":"CH",
    "sg:address":"Lehengasse 38",
    "sg:city":"M\u00fcnchenstein",
    "sg:orig_category":"Vorschulen, Kinderg\u00e4rten",
    "sg:phone":"+41 61 411 83 37",
    "sg:postcode":"4142",
    "sg:province":"Basel-Landschaft",
    "wof:name":"Kindergarten B\u00fcndten",
    "wof:placetype":"venue"
},
  "geometry": {"coordinates":[7.6191358566,47.5090484619],"type":"Point"}
}