{
  "type": "Feature",
  "properties": {
    "iso:country":"CH",
    "sg:address":"Schaffhauserstrasse 333",
    "sg:city":"Z\u00fcrich",
    "sg:orig_category":"Architekturb\u00fcros Erbringung von Dienstleistungen f\u00fcr Unternehmen",
    "sg:phone":"+41 13127080",
    "sg:postcode":"8050",
    "sg:province":"Z\u00fcrich",
    "wof:name":"Archibox Gmbh",
    "wof:placetype":"venue"
},
  "geometry": {"coordinates":[8.546506,47.408302],"type":"Point"}
}