{
  "type": "Feature",
  "properties": {
    "iso:country":"CH",
    "sg:address":"La Piodella",
    "sg:city":"Muzzano",
    "sg:orig_category":"Hundesalons",
    "sg:phone":"+41 91 994 54 60",
    "sg:postcode":"6933",
    "sg:province":"Ticino",
    "wof:name":"Luciano Belluco Salone Per Cani Boby",
    "wof:placetype":"venue"
},
  "geometry": {"coordinates":[8.9097499847,45.9974212646],"type":"Point"}
}