{
  "type": "Feature",
  "properties": {
    "iso:country":"CH",
    "sg:address":"Volkensbergerstrasse 11",
    "sg:city":"Basel",
    "sg:orig_category":"Erschliessung von Grundst\u00fccken",
    "sg:postcode":"4055",
    "sg:province":"Basel-Stadt",
    "wof:name":"Wohngenossenschaft B\u00e4ren",
    "wof:placetype":"venue"
},
  "geometry": {"coordinates":[7.6055488586,47.5087776184],"type":"Point"}
}