{
  "type": "Feature",
  "properties": {
    "iso:country":"CH",
    "sg:address":"Hauptstrasse",
    "sg:city":"M\u00fcrren",
    "sg:orig_category":"Nationale Postdienste",
    "sg:phone":"+41 33 855 14 05",
    "sg:postcode":"3825",
    "sg:province":"Bern",
    "wof:name":"Die Schweizerische Post",
    "wof:placetype":"venue"
},
  "geometry": {"coordinates":[7.8951401711,46.560218811],"type":"Point"}
}