{
  "type": "Feature",
  "properties": {
    "iso:country":"CH",
    "sg:address":"Allmeindstrasse 19 8645 Jona. Postfach 2131",
    "sg:city":"Jona",
    "sg:orig_category":"Arztpraxen",
    "sg:phone":"+41 55 212 35 44",
    "sg:postcode":"8645",
    "sg:province":"St. Gallen",
    "wof:name":"Dr.med.josaphat Ratmoko Arzt F\u00fcr Allgemeine Medizin",
    "wof:placetype":"venue"
},
  "geometry": {"coordinates":[8.836647,47.231712],"type":"Point"}
}