{
  "type": "Feature",
  "properties": {
    "iso:country":"CH",
    "sg:address":"6593",
    "sg:city":"Cadenazzo",
    "sg:classifiers":[
        {
            "category":"Restaurant",
            "type":"Food & Drink"
        }
    ],
    "sg:phone":"+41 91 858 23 12",
    "sg:postcode":"6593",
    "sg:province":"Ticino",
    "wof:name":"Osteria Marzorati",
    "wof:placetype":"venue"
},
  "geometry": {"coordinates":[8.9563798904,46.1506309509],"type":"Point"}
}