{
  "type": "Feature",
  "properties": {
    "iso:country":"CH",
    "sg:address":"Rosenbergstrasse 87",
    "sg:city":"St.gallen",
    "sg:orig_category":"Personal U Stellenvermittlung Unternehmensberatung",
    "sg:phone":"+41 71 260 15 75",
    "sg:postcode":"9000",
    "sg:province":"St. Gallen",
    "wof:name":"Mtm-consulting Bolt Daniel",
    "wof:placetype":"venue"
},
  "geometry": {"coordinates":[9.3655700684,47.4223251343],"type":"Point"}
}