{
  "type": "Feature",
  "properties": {
    "iso:country":"CH",
    "sg:address":"Kl\u00fcnenfeldstr. 22",
    "sg:city":"Birsfelden",
    "sg:classifiers":[
        {
            "category":"Manufacturing",
            "subcategory":"Wood Products",
            "type":"Manufacturing & Wholesale Goods"
        }
    ],
    "sg:phone":"+41 61 377 00 00",
    "sg:postcode":"4127",
    "sg:province":"Basel-Landschaft",
    "sg:tags":[
        "professional",
        "furniture"
    ],
    "wof:name":"Vitra (international) Ag",
    "wof:placetype":"venue"
},
  "geometry": {"coordinates":[7.6200728416,47.554069519],"type":"Point"}
}