{
  "type": "Feature",
  "properties": {
    "iso:country":"CH",
    "sg:address":"Talstrasse 12",
    "sg:city":"Altendorf",
    "sg:orig_category":"Gymnastik U Fitnesszentren",
    "sg:phone":"+41 19721555",
    "sg:postcode":"8852",
    "sg:province":"Schwyz",
    "wof:name":"Badminton Center Wetzikon",
    "wof:placetype":"venue"
},
  "geometry": {"coordinates":[8.781993866,47.3276367188],"type":"Point"}
}