{
  "type": "Feature",
  "properties": {
    "iso:country":"CH",
    "sg:address":"Belalpstrasse 1 3900 Brig. Postfach",
    "sg:city":"Brig",
    "sg:orig_category":"Werbevermittlung",
    "sg:phone":"+41 27 923 88 23",
    "sg:postcode":"3900",
    "sg:province":"Valais",
    "wof:name":"Publicitas Ag",
    "wof:placetype":"venue"
},
  "geometry": {"coordinates":[7.9894189835,46.3187484741],"type":"Point"}
}