{
  "type": "Feature",
  "properties": {
    "iso:country":"CH",
    "sg:address":"Zugerstrasse 18b",
    "sg:city":"Oberlunkhofen",
    "sg:orig_category":"Arztpraxen",
    "sg:phone":"+41 56 634 26 15",
    "sg:postcode":"8917",
    "sg:province":"Aargau",
    "wof:name":"Dr.med.marcel Butti Arzt F\u00fcr Allgemeine Medizin",
    "wof:placetype":"venue"
},
  "geometry": {"coordinates":[8.390172,47.31126],"type":"Point"}
}