{
  "type": "Feature",
  "properties": {
    "iso:country":"CH",
    "sg:address":"Robert-z\u00fcnd-strasse 2 6005 Luzern. Postfach",
    "sg:city":"Luzern",
    "sg:orig_category":"Informatikschulen",
    "sg:phone":"+41 41 226 61 11",
    "sg:postcode":"6002",
    "sg:province":"Luzern",
    "wof:name":"Digicomp Ag",
    "wof:placetype":"venue"
},
  "geometry": {"coordinates":[8.311340332,47.0505104065],"type":"Point"}
}