{
  "type": "Feature",
  "properties": {
    "iso:country":"CH",
    "sg:address":"Place De La Gare 15",
    "sg:city":"Moudon",
    "sg:orig_category":"Elektroinstallation",
    "sg:phone":"+41 21 905 80 80",
    "sg:postcode":"1510",
    "sg:province":"Vaud",
    "wof:name":"Dubrit Sa \u00e9lectricit\u00e9",
    "wof:placetype":"venue"
},
  "geometry": {"coordinates":[6.8048372269,46.6704521179],"type":"Point"}
}