{
  "type": "Feature",
  "properties": {
    "iso:country":"CH",
    "sg:address":"Bahnhofstrasse 46 8200 Schaffhausen. Postfach 234",
    "sg:city":"Schaffhausen",
    "sg:classifiers":[
        {
            "category":"Travel",
            "subcategory":"Hotels & Motels",
            "type":"Entertainment"
        }
    ],
    "sg:phone":"+41 52 624 19 24",
    "sg:postcode":"8200",
    "sg:province":"Schaffhausen",
    "sg:tags":[
        "hotels",
        "mit",
        "restaurant"
    ],
    "wof:name":"Hotel Bahnhof Ag",
    "wof:placetype":"venue"
},
  "geometry": {"coordinates":[8.6333179474,47.698387146],"type":"Point"}
}