{
  "type": "Feature",
  "properties": {
    "iso:country":"CH",
    "sg:address":"Zelgli 27 5614 Sarmenstorf. Postfach 64",
    "sg:city":"Sarmenstorf",
    "sg:orig_category":"Bau von Sportanlagen",
    "sg:phone":"+41 31 832 10 80",
    "sg:postcode":"5614",
    "sg:province":"Aargau",
    "wof:name":"Jank & Blatter Ag Sportbau & Bodensysteme",
    "wof:placetype":"venue"
},
  "geometry": {"coordinates":[7.558529,46.936375],"type":"Point"}
}