{
  "type": "Feature",
  "properties": {
    "iso:country":"CH",
    "sg:address":"Chemin De La Toffeyre 11",
    "sg:city":"Lutry",
    "sg:orig_category":"Fachdetailhandel in Verkaufsr\u00e4umen Handel mit Motorr\u00e4dern, Teilen U Zubeh\u00f6r Instandhaltung U Reparat",
    "sg:phone":"+41 21 791 64 03",
    "sg:postcode":"1095",
    "sg:province":"Vaud",
    "wof:name":"Zim. Bike, Zimmermann Jean-claude",
    "wof:placetype":"venue"
},
  "geometry": {"coordinates":[6.6808900833,46.5044784546],"type":"Point"}
}