{
  "type": "Feature",
  "properties": {
    "iso:country":"CH",
    "sg:address":"Marienstrasse 33a",
    "sg:city":"Thun",
    "sg:orig_category":"Sonstige Aktivit\u00e4ten der nicht-\u00e4rztlichen Medizinalberufe",
    "sg:phone":"+41 33 335 25 45",
    "sg:postcode":"3604",
    "sg:province":"Bern",
    "wof:name":"Dr.heidi Borer Kinesiologie",
    "wof:placetype":"venue"
},
  "geometry": {"coordinates":[7.6282072067,46.7438774109],"type":"Point"}
}