{
  "type": "Feature",
  "properties": {
    "iso:country":"CH",
    "sg:address":"Waldeggweg 208 3633 Amsoldingen. Postfach",
    "sg:city":"Amsoldingen",
    "sg:orig_category":"RESTAURANTS: TEA-ROOMS",
    "sg:phone":"+41 32 373 51 48",
    "sg:postcode":"3633",
    "sg:province":"Bern",
    "wof:name":"Bg Sternen Br\u00fcgg Gmbh",
    "wof:placetype":"venue"
},
  "geometry": {"coordinates":[7.281129837,47.1238975525],"type":"Point"}
}