{
  "type": "Feature",
  "properties": {
    "iso:country":"CH",
    "sg:address":"Rheinstrasse 11",
    "sg:city":"Frauenfeld",
    "sg:orig_category":"Detailhandel mit Tabakwaren Grosshandel mit Tabakwaren",
    "sg:phone":"+41 32 932 10 85",
    "sg:postcode":"8500",
    "sg:province":"Thurgau",
    "wof:name":"Scarpella Alceste.",
    "wof:placetype":"venue"
},
  "geometry": {"coordinates":[6.7048549652,47.0676841736],"type":"Point"}
}