{
  "type": "Feature",
  "properties": {
    "iso:country":"CH",
    "sg:address":"Hubstrasse 5",
    "sg:city":"Oberrieden",
    "sg:orig_category":"Wirtschaftsverb\u00e4nde Gewerbeverb\u00e4nde/-vereine",
    "sg:phone":"+41 17208686",
    "sg:postcode":"8942",
    "sg:province":"Z\u00fcrich",
    "wof:name":"Gewerbeverein Oberrieden",
    "wof:placetype":"venue"
},
  "geometry": {"coordinates":[8.5742387772,47.2791519165],"type":"Point"}
}