{
  "type": "Feature",
  "properties": {
    "iso:country":"CH",
    "sg:address":"Seestrasse 151",
    "sg:city":"W\u00e4denswil",
    "sg:orig_category":"Wirtschaftspr\u00fcfung, Steuerberatung U Treuhand",
    "sg:phone":"+41 17806966",
    "sg:postcode":"8820",
    "sg:province":"Z\u00fcrich",
    "wof:name":"Treuhand- & Beratungsb\u00fcro, A. Inci",
    "wof:placetype":"venue"
},
  "geometry": {"coordinates":[8.6700639725,47.232093811],"type":"Point"}
}