{
  "type": "Feature",
  "properties": {
    "iso:country":"CH",
    "sg:address":"Klettgauerplatz 5",
    "sg:city":"Neunkirch",
    "sg:classifiers":[
        {
            "category":"Banks & Credit Unions",
            "subcategory":"Bank",
            "type":"Services"
        }
    ],
    "sg:phone":"+41 52 687 07 07",
    "sg:postcode":"8213",
    "sg:province":"Schaffhausen",
    "wof:name":"Spar- Und Leihkasse Neunkirch",
    "wof:placetype":"venue"
},
  "geometry": {"coordinates":[8.49726,47.689632],"type":"Point"}
}