{
  "type": "Feature",
  "properties": {
    "iso:country":"CH",
    "sg:address":"Via Patocchi 5 6644 Orselina. Postfach",
    "sg:city":"Orselina",
    "sg:orig_category":"Non-Classified Establishments",
    "sg:phone":"+41 27 722 44 88",
    "sg:postcode":"6644",
    "sg:province":"Ticino",
    "wof:name":"Les Tilleuls Du Lac Sa",
    "wof:placetype":"venue"
},
  "geometry": {"coordinates":[8.7995119095,46.1798019409],"type":"Point"}
}