{
  "type": "Feature",
  "properties": {
    "iso:country":"CH",
    "sg:address":"Avenue Du Ch\u00e2teau 4",
    "sg:city":"Sierre",
    "sg:orig_category":"Non-Classified Establishments",
    "sg:postcode":"3960",
    "sg:province":"Valais",
    "wof:name":"55 55 55 Location Antille Et Zufferey Et Cie",
    "wof:placetype":"venue"
},
  "geometry": {"coordinates":[7.5317559242,46.2958145142],"type":"Point"}
}