{
  "type": "Feature",
  "properties": {
    "iso:country":"CH",
    "sg:address":"Via Cantonale 6595 Riazzino. Postfach",
    "sg:city":"Riazzino",
    "sg:orig_category":"Erzeugung U Erstbearbeitung von NE-Metallen Mechanik",
    "sg:phone":"+41 18335960",
    "sg:postcode":"6595",
    "sg:province":"Ticino",
    "wof:name":"Vescovo Metallschleiferei + Polierwerkstatt, Inhaber Frangiosa Cosimo",
    "wof:placetype":"venue"
},
  "geometry": {"coordinates":[8.6459159851,47.4089317322],"type":"Point"}
}