{
  "type": "Feature",
  "properties": {
    "iso:country":"CH",
    "sg:address":"Dufourstrasse 103",
    "sg:city":"St.gallen",
    "sg:orig_category":"Vermietung U Verpachtung von eigenen Immobilien",
    "sg:phone":"+41 71 222 95 31",
    "sg:postcode":"9000",
    "sg:province":"St. Gallen",
    "wof:name":"Sufi Immobilien Ag St. Gallen",
    "wof:placetype":"venue"
},
  "geometry": {"coordinates":[9.3651227951,47.4244995117],"type":"Point"}
}