{
  "type": "Feature",
  "properties": {
    "iso:country":"CH",
    "sg:address":"Rue Du Pr\u00e9-des-cloches 26",
    "sg:city":"Vouvry",
    "sg:orig_category":"Herstellung von Metallkonstruktionen Installation von Heizungs, L\u00fcftungs U Klimaanlagen",
    "sg:phone":"+41 24 481 29 54",
    "sg:postcode":"1896",
    "sg:province":"Valais",
    "wof:name":"Philippe Brouze Constr.m\u00e9talliques-ventilation",
    "wof:placetype":"venue"
},
  "geometry": {"coordinates":[6.8886728287,46.3406600952],"type":"Point"}
}