{
  "type": "Feature",
  "properties": {
    "iso:country":"CH",
    "sg:address":"Via Crano 6946 Ponte Capriasca. Postfach",
    "sg:city":"Bogno",
    "sg:orig_category":"Vermietung U Verpachtung von eigenen Immobilien",
    "sg:postcode":"6951",
    "sg:province":"Ticino",
    "wof:name":"Crano Sa",
    "wof:placetype":"venue"
},
  "geometry": {"coordinates":[8.9475250244,46.0586738586],"type":"Point"}
}