{
  "type": "Feature",
  "properties": {
    "iso:country":"CH",
    "sg:address":"1977",
    "sg:city":"Icogne",
    "sg:orig_category":"Vermietung U Verpachtung von eigenen Immobilien",
    "sg:postcode":"1977",
    "sg:province":"Valais",
    "wof:name":"Sepro Sa, Soci\u00e9t\u00e9 D'\u00e9tudes Et De Promotions Immobili\u00e8res",
    "wof:placetype":"venue"
},
  "geometry": {"coordinates":[7.438272953,46.2908935547],"type":"Point"}
}