{
  "type": "Feature",
  "properties": {
    "iso:country":"CH",
    "sg:address":"Avenue Du La Gare 15",
    "sg:city":"Sion",
    "sg:orig_category":"Detailhandel mit Brillen U anderen Sehhilfen Fachdetailhandel in Verkaufsr\u00e4umen",
    "sg:phone":"+41 27 322 57 40",
    "sg:postcode":"1950",
    "sg:province":"Valais",
    "wof:name":"Visilab Sion Sa",
    "wof:placetype":"venue"
},
  "geometry": {"coordinates":[7.35837,46.229504],"type":"Point"}
}