{
  "type": "Feature",
  "properties": {
    "iso:country":"CH",
    "sg:address":"Industriestrasse 17",
    "sg:city":"W\u00fcrenlos",
    "sg:orig_category":"Piezo-Resistive Pressure Sensors",
    "sg:phone":"+41 56 436 82 00",
    "sg:postcode":"5436",
    "sg:province":"Aargau",
    "wof:name":"Huba Control Ag",
    "wof:placetype":"venue"
},
  "geometry": {"coordinates":[8.3505182266,47.4482498169],"type":"Point"}
}