{
  "type": "Feature",
  "properties": {
    "iso:country":"CH",
    "sg:address":"Blumenrainweg 3 9050 Appenzell. Postfach",
    "sg:city":"Appenzell",
    "sg:orig_category":"Interessenvertretungen",
    "sg:phone":"+41 33 222 71 76",
    "sg:postcode":"9050",
    "sg:province":"Appenzell Innerhoden",
    "wof:name":"Pro Senectute Kanton Appenzell I.rh.- F\u00fcr Das Alter",
    "wof:placetype":"venue"
},
  "geometry": {"coordinates":[9.4126062393,47.331401825],"type":"Point"}
}