{
  "type": "Feature",
  "properties": {
    "iso:country":"CH",
    "sg:address":"Schwanenstrasse 41",
    "sg:city":"Einsiedeln",
    "sg:classifiers":[
        {
            "category":"Travel",
            "subcategory":"Hotels & Motels",
            "type":"Entertainment"
        }
    ],
    "sg:phone":"+41 55 412 62 84",
    "sg:postcode":"8840",
    "sg:province":"Schwyz",
    "sg:tags":[
        "hotels",
        "mit",
        "restaurant"
    ],
    "wof:name":"Hotel Rebstock",
    "wof:placetype":"venue"
},
  "geometry": {"coordinates":[8.7490501404,47.1264572144],"type":"Point"}
}