{
  "type": "Feature",
  "properties": {
    "iso:country":"CH",
    "sg:address":"Unterf\u00fchrungsstrasse 18",
    "sg:city":"Olten",
    "sg:orig_category":"Unclassifiable Establishments",
    "sg:postcode":"4600",
    "sg:province":"Solothurn",
    "wof:name":"Ernst Mattmann Dipl. Architekt Eth",
    "wof:placetype":"venue"
},
  "geometry": {"coordinates":[7.9087162018,47.3495101929],"type":"Point"}
}