{
  "type": "Feature",
  "properties": {
    "addr:full":"Casa Da Scola Andiast Graubunden 7159",
    "addr:housenumber":"7159",
    "iso:country":"CH",
    "sg:address":"Casa Da Scola",
    "sg:city":"Andiast",
    "sg:classifiers":[
        {
            "category":"Banks & Credit Unions",
            "subcategory":"Bank",
            "type":"Services"
        }
    ],
    "sg:phone":"+41 91 960 37 70",
    "sg:postcode":"7159",
    "sg:province":"Graubunden",
    "wof:name":"Banca Raiffeisen Breganzona",
    "wof:placetype":"venue"
},
  "geometry": {"coordinates":[8.92793,46.009159],"type":"Point"}
}