{
  "type": "Feature",
  "properties": {
    "iso:country":"CH",
    "sg:address":"Thomas-wyttenbach-strasse 2 2502 Biel/bienne Case Postale 328",
    "sg:city":"Biel/bienne",
    "sg:orig_category":"Grosshandel mit Uhren Herstellung von Uhren",
    "sg:phone":"+41 22 310 61 78",
    "sg:postcode":"2501",
    "sg:province":"Bern",
    "wof:name":"Roberge Watches Sa",
    "wof:placetype":"venue"
},
  "geometry": {"coordinates":[6.1342182159,46.185798645],"type":"Point"}
}