{
  "type": "Feature",
  "properties": {
    "iso:country":"CH",
    "sg:address":"Schmittlistrasse 19",
    "sg:city":"Ebnat",
    "sg:orig_category":"Abbruch U Sprenggewerbe, Erdbewegungsarbeiten",
    "sg:phone":"+41 71 993 23 16",
    "sg:postcode":"9642",
    "sg:province":"St. Gallen",
    "wof:name":"Bsa Burtscher Ag",
    "wof:placetype":"venue"
},
  "geometry": {"coordinates":[9.129583,47.264465],"type":"Point"}
}