{
  "type": "Feature",
  "properties": {
    "iso:country":"CH",
    "sg:address":"Tittwiesenstrasse 61",
    "sg:city":"Chur",
    "sg:orig_category":"Darlehenskassen U Raiffeisenbanken",
    "sg:phone":"+41 81 286 92 80",
    "sg:postcode":"7000",
    "sg:province":"Graubunden",
    "wof:name":"Raiffeisenbank B\u00fcndner Rheintal",
    "wof:placetype":"venue"
},
  "geometry": {"coordinates":[9.526549,46.85854],"type":"Point"}
}