{
  "type": "Feature",
  "properties": {
    "iso:country":"CH",
    "sg:address":"Moderna Via 1 6512 Giubiasco. Postfach",
    "sg:city":"Giubiasco",
    "sg:orig_category":"Herstellung von medizinischen U chirurgischen Ger\u00e4ten sowie orthop\u00e4dischen Vorrichtungen",
    "sg:postcode":"6512",
    "sg:province":"Ticino",
    "wof:name":"Dental Labor Di Turano",
    "wof:placetype":"venue"
},
  "geometry": {"coordinates":[9.0014657974,46.1731643677],"type":"Point"}
}