{
  "type": "Feature",
  "properties": {
    "iso:country":"CH",
    "sg:address":"Route Des Martines 52",
    "sg:city":"Mont-sur-lausanne",
    "sg:orig_category":"Fussboden, Fliesen U Plattenlegerei, Tapeziererei Verlegen von Fliesen U Platten",
    "sg:phone":"+41 21 653 15 25",
    "sg:postcode":"1052",
    "sg:province":"Vaud",
    "wof:name":"Servisol Sa",
    "wof:placetype":"venue"
},
  "geometry": {"coordinates":[6.6350989342,46.5472564697],"type":"Point"}
}