{
  "type": "Feature",
  "properties": {
    "iso:country":"CH",
    "sg:address":"Luzernerstrasse 15 6030 Ebikon. Postfach",
    "sg:city":"Ebikon",
    "sg:orig_category":"RESTAURANTS: TEA-ROOMS",
    "sg:postcode":"6030",
    "sg:province":"Luzern",
    "wof:name":"Kebab-house Yagbasan Oruc Imbissstand, Bes. Verkauf Von Kebab. Hauslieferdienst Von Pizzas",
    "wof:placetype":"venue"
},
  "geometry": {"coordinates":[8.3353452682,47.0780563354],"type":"Point"}
}