{
  "type": "Feature",
  "properties": {
    "iso:country":"CH",
    "sg:address":"Ch. De La Tour-de-champel 20 1206 Gen\u00e8ve. Postfach",
    "sg:city":"Gen\u00e8ve",
    "sg:orig_category":"Interessenvertretungen",
    "sg:postcode":"1206",
    "sg:province":"Gen\u00e8ve",
    "wof:name":"Stiftung John Ringling North Und Ida Von Zedlitz-truetzschler",
    "wof:placetype":"venue"
},
  "geometry": {"coordinates":[6.1523900032,46.1878395081],"type":"Point"}
}