{
  "type": "Feature",
  "properties": {
    "iso:country":"CH",
    "sg:address":"L\u00f6wenstrasse 17",
    "sg:city":"Z\u00fcrich",
    "sg:orig_category":"Sonstige pers\u00f6nliche Dienstleistungen",
    "sg:postcode":"8001",
    "sg:province":"Z\u00fcrich",
    "wof:name":"Steiert Arthur Consulting",
    "wof:placetype":"venue"
},
  "geometry": {"coordinates":[8.5350837708,47.3739013672],"type":"Point"}
}