{
  "type": "Feature",
  "properties": {
    "iso:country":"CH",
    "sg:address":"Niederholzstrasse 9 8593 Kesswil. Postfach",
    "sg:city":"Kesswil",
    "sg:orig_category":"Dienstleistungen von Beteiligungsgesellschaften",
    "sg:postcode":"8593",
    "sg:province":"Thurgau",
    "wof:name":"Wehage-verwaltungen W\u00fcst E.",
    "wof:placetype":"venue"
},
  "geometry": {"coordinates":[9.3195466995,47.5961151123],"type":"Point"}
}