{
  "type": "Feature",
  "properties": {
    "iso:country":"CH",
    "sg:address":"Via Vallaa 17 6952 Canobbio. Postfach",
    "sg:city":"Canobbio",
    "sg:orig_category":"Handels-H\u00e4user U Gesellschaften",
    "sg:postcode":"6952",
    "sg:province":"Ticino",
    "wof:name":"Bergi Sa",
    "wof:placetype":"venue"
},
  "geometry": {"coordinates":[8.9704589844,46.0327301025],"type":"Point"}
}