{
  "type": "Feature",
  "properties": {
    "iso:country":"CH",
    "sg:address":"Kasernenstrasse 23",
    "sg:city":"Thun",
    "sg:orig_category":"RESTAURANTS: TEA-ROOMS",
    "sg:phone":"+41 33 222 36 32",
    "sg:postcode":"3600",
    "sg:province":"Bern",
    "wof:name":"Von Siebenthal Ernst",
    "wof:placetype":"venue"
},
  "geometry": {"coordinates":[7.6216320992,46.7579193115],"type":"Point"}
}