{
  "type": "Feature",
  "properties": {
    "iso:country":"CH",
    "sg:address":"Rue Des Aub\u00e9pines 15 1950 Sion Case Postale",
    "sg:city":"Sitten",
    "sg:orig_category":"Architektur U Ingenieurb\u00fcros",
    "sg:phone":"+41 27 323 56 54",
    "sg:postcode":"1950",
    "sg:province":"Valais",
    "wof:name":"Roten & Dubuis, Ing. Civils Sa",
    "wof:placetype":"venue"
},
  "geometry": {"coordinates":[7.365378,46.231541],"type":"Point"}
}