{
  "type": "Feature",
  "properties": {
    "iso:country":"CH",
    "sg:address":"Neumarkt 16",
    "sg:city":"Z\u00fcrich",
    "sg:orig_category":"Detailhandel mit Damenbekleidung",
    "sg:phone":"+41 12513468",
    "sg:postcode":"8001",
    "sg:province":"Z\u00fcrich",
    "wof:name":"Edith Gasser Modes Natascha",
    "wof:placetype":"venue"
},
  "geometry": {"coordinates":[8.546205,47.372623],"type":"Point"}
}