{
  "type": "Feature",
  "properties": {
    "iso:country":"CH",
    "sg:address":"Hauptstrasse 63",
    "sg:city":"Derendingen",
    "sg:orig_category":"RESTAURANTS: TEA-ROOMS",
    "sg:phone":"+41 32 682 22 40",
    "sg:postcode":"4552",
    "sg:province":"Solothurn",
    "wof:name":"Tanner Lotty",
    "wof:placetype":"venue"
},
  "geometry": {"coordinates":[7.5873250961,47.1923828125],"type":"Point"}
}