{
  "type": "Feature",
  "properties": {
    "iso:country":"CH",
    "sg:address":"Waffenplatzstrasse 49",
    "sg:city":"Z\u00fcrich",
    "sg:orig_category":"Chemische Reinigung",
    "sg:phone":"+41 12014150",
    "sg:postcode":"8002",
    "sg:province":"Z\u00fcrich",
    "wof:name":"Marcus Rack Textilreinigung",
    "wof:placetype":"venue"
},
  "geometry": {"coordinates":[8.526762,47.358841],"type":"Point"}
}