{
  "type": "Feature",
  "properties": {
    "iso:country":"CH",
    "sg:address":"Pittard Avenue Eug\u00e8ne- 24 1206 Gen\u00e8ve. Postfach",
    "sg:city":"Gen\u00e8ve",
    "sg:orig_category":"Pensionskassen",
    "sg:postcode":"1201",
    "sg:province":"Gen\u00e8ve",
    "wof:name":"Fondation Pour Favoriser Les Loisirs Du Personnel De Api Portescap",
    "wof:placetype":"venue"
},
  "geometry": {"coordinates":[6.8133649826,47.0942764282],"type":"Point"}
}