{
  "type": "Feature",
  "properties": {
    "iso:country":"CH",
    "sg:address":"Altmatt",
    "sg:city":"Rothenthurm",
    "sg:orig_category":"Instandhaltung U Reparatur von Automobilen",
    "sg:postcode":"6418",
    "sg:province":"Schwyz",
    "wof:name":"K\u00e4lin Rudolf, Avia-garage",
    "wof:placetype":"venue"
},
  "geometry": {"coordinates":[8.6863698959,47.119430542],"type":"Point"}
}