{
  "type": "Feature",
  "properties": {
    "iso:country":"CH",
    "sg:address":"Obere Rebgasse 17",
    "sg:city":"Zeiningen",
    "sg:orig_category":"Mechanik Mechanische Werkst\u00e4tten",
    "sg:phone":"+41 61 851 49 62",
    "sg:postcode":"4314",
    "sg:province":"Aargau",
    "wof:name":"Td Tudisco Domenico Mech. Werkst\u00e4tte",
    "wof:placetype":"venue"
},
  "geometry": {"coordinates":[7.8769888878,47.5383605957],"type":"Point"}
}