{
  "type": "Feature",
  "properties": {
    "iso:country":"CH",
    "sg:address":"Freie Strasse 42 4000 Basel. Postfach",
    "sg:city":"Basel",
    "sg:orig_category":"Detailhandel mit Bekleidung",
    "sg:phone":"+41 61 281 81 16",
    "sg:postcode":"4001",
    "sg:province":"Basel-Stadt",
    "wof:name":"Magmod Herrenmode Ag",
    "wof:placetype":"venue"
},
  "geometry": {"coordinates":[7.589985,47.555969],"type":"Point"}
}