{
  "type": "Feature",
  "properties": {
    "iso:country":"CH",
    "sg:address":"Bachstrasse 10",
    "sg:city":"Kreuzlingen",
    "sg:orig_category":"Herstellung von medizinischen U chirurgischen Ger\u00e4ten sowie orthop\u00e4dischen Vorrichtungen",
    "sg:phone":"+41 71 672 88 10",
    "sg:postcode":"8280",
    "sg:province":"Thurgau",
    "wof:name":"Byk Roland Gmbh",
    "wof:placetype":"venue"
},
  "geometry": {"coordinates":[9.1698570251,47.6459999084],"type":"Point"}
}