{
  "type": "Feature",
  "properties": {
    "iso:country":"CH",
    "sg:address":"Alte Landstrasse 31",
    "sg:city":"Oberrieden",
    "sg:orig_category":"Sonstige Kultur U Unterhaltungseinrichtungen",
    "sg:phone":"+41 17210279",
    "sg:postcode":"8942",
    "sg:province":"Z\u00fcrich",
    "wof:name":"Jugendtreff",
    "wof:placetype":"venue"
},
  "geometry": {"coordinates":[8.5761108398,47.2779655457],"type":"Point"}
}