{
  "type": "Feature",
  "properties": {
    "iso:country":"CH",
    "sg:address":"Casinostrasse 6",
    "sg:city":"Basel",
    "sg:classifiers":[
        {
            "category":"Sports & Exercise",
            "subcategory":"Tennis Court",
            "type":"Entertainment"
        }
    ],
    "sg:phone":"+41 61 313 36 08",
    "sg:postcode":"4052",
    "sg:province":"Basel-Stadt",
    "sg:tags":[
        "squash-centers",
        "hallen",
        "tennis-",
        "sportschulen"
    ],
    "wof:name":"Tenniscenter Duggingen C/o Herrn Hans Albrecht",
    "wof:placetype":"venue"
},
  "geometry": {"coordinates":[7.599088192,47.5464286804],"type":"Point"}
}