{
  "type": "Feature",
  "properties": {
    "iso:country":"CH",
    "sg:address":"Avenue France 6",
    "sg:city":"Monthey",
    "sg:orig_category":"Institutionen f\u00fcr Behinderte Institutionen f\u00fcr psychosoziale F\u00e4lle",
    "sg:phone":"+41 56 437 28 38",
    "sg:postcode":"1870",
    "sg:province":"Valais",
    "wof:name":"Stiftung F\u00fcr Behinderte Arwo Wohnheim Kirchzelg",
    "wof:placetype":"venue"
},
  "geometry": {"coordinates":[8.3284893036,47.4695281982],"type":"Point"}
}