{
  "type": "Feature",
  "properties": {
    "iso:country":"CH",
    "sg:address":"Stoffelbachstrasse 23",
    "sg:city":"Dietikon",
    "sg:orig_category":"Reparatur von Schuhen U Lederwaren",
    "sg:phone":"+41 17406006",
    "sg:postcode":"8953",
    "sg:province":"Z\u00fcrich",
    "wof:name":"Eugen Gerosa Schuhreparaturen",
    "wof:placetype":"venue"
},
  "geometry": {"coordinates":[8.3982019424,47.3938827515],"type":"Point"}
}