{
  "type": "Feature",
  "properties": {
    "iso:country":"CH",
    "sg:address":"Rebbergstrasse 79d",
    "sg:city":"Oberengstringen",
    "sg:orig_category":"G\u00fcterbef\u00f6rderung im Strassenverkehr",
    "sg:phone":"+41 17503965",
    "sg:postcode":"8102",
    "sg:province":"Z\u00fcrich",
    "wof:name":"Haldi-tscholl D. & E.",
    "wof:placetype":"venue"
},
  "geometry": {"coordinates":[8.4676542282,47.4082984924],"type":"Point"}
}