{
  "type": "Feature",
  "properties": {
    "iso:country":"CH",
    "sg:address":"Im Tiergarten 41",
    "sg:city":"Z\u00fcrich",
    "sg:orig_category":"Softwareentwicklung U beratung",
    "sg:phone":"+41 41 920 20 22",
    "sg:postcode":"8055",
    "sg:province":"Z\u00fcrich",
    "wof:name":"Usr Soft Ag",
    "wof:placetype":"venue"
},
  "geometry": {"coordinates":[8.0744695663,47.1829185486],"type":"Point"}
}