{
  "type": "Feature",
  "properties": {
    "iso:country":"CH",
    "sg:address":"Winkelriedstrasse 2",
    "sg:city":"Wettingen",
    "sg:orig_category":"Werbeagenturen Werbung",
    "sg:phone":"+41 56 426 51 46",
    "sg:postcode":"5430",
    "sg:province":"Aargau",
    "wof:name":"Reklamefabrik Steullet Michel",
    "wof:placetype":"venue"
},
  "geometry": {"coordinates":[8.3199558258,47.4686012268],"type":"Point"}
}