{
  "type": "Feature",
  "properties": {
    "iso:country":"CH",
    "sg:address":"R\u00fcegsaustrasse 39 3415 R\u00fcegsauschachen. Postfach 278",
    "sg:city":"Hasle-r\u00fcegsau",
    "sg:orig_category":"Handelsvermittlung U Grosshandel",
    "sg:phone":"+41 34 461 61 20",
    "sg:postcode":"3415",
    "sg:province":"Bern",
    "wof:name":"Variotech Ag",
    "wof:placetype":"venue"
},
  "geometry": {"coordinates":[7.6618189812,47.0187835693],"type":"Point"}
}