{
  "type": "Feature",
  "properties": {
    "iso:country":"CH",
    "sg:address":"Schwimmbadstrasse 15",
    "sg:city":"B\u00fclach",
    "sg:orig_category":"Maschinen-Fabrikation",
    "sg:phone":"+41 18607812",
    "sg:postcode":"8180",
    "sg:province":"Z\u00fcrich",
    "wof:name":"Rotondo U. Siegrist Gmbh",
    "wof:placetype":"venue"
},
  "geometry": {"coordinates":[8.5377283096,47.5149383545],"type":"Point"}
}