{
  "type": "Feature",
  "properties": {
    "addr:full":"6473 Silenen Uri 6473",
    "addr:housenumber":"6473",
    "addr:postcode":"6473",
    "addr:street":"Silenen Uri",
    "iso:country":"CH",
    "sg:address":"6473",
    "sg:city":"Silenen",
    "sg:classifiers":[
        {
            "category":"Education",
            "subcategory":"Library",
            "type":"Public Place"
        }
    ],
    "sg:phone":"+41 41 883 11 26",
    "sg:postcode":"6473",
    "sg:province":"Uri",
    "sg:tags":[
        "u",
        "bibliotheken",
        "archive"
    ],
    "wof:name":"Katholische Pfarrbibliothek",
    "wof:placetype":"venue"
},
  "geometry": {"coordinates":[8.669721,46.785789],"type":"Point"}
}