{
  "type": "Feature",
  "properties": {
    "iso:country":"CH",
    "sg:address":"Via Minigera",
    "sg:city":"Montagnola",
    "sg:orig_category":"Detailhandel mit Fleisch U Fleischwaren",
    "sg:phone":"+41 91 994 82 10",
    "sg:postcode":"6926",
    "sg:province":"Ticino",
    "wof:name":"Daniele Cassina Macelleria & Salumeria",
    "wof:placetype":"venue"
},
  "geometry": {"coordinates":[8.9166002274,45.9817466736],"type":"Point"}
}