{
  "type": "Feature",
  "properties": {
    "iso:country":"CH",
    "sg:address":"Widen 199",
    "sg:city":"Urn\u00e4sch",
    "sg:orig_category":"Dachdeckerei Zimmerei, Dachdeckerei, Bauspenglerei U Abdichtung",
    "sg:phone":"+41 71 787 44 40",
    "sg:postcode":"9107",
    "sg:province":"Appenzell Ausserrhoden",
    "wof:name":"Haueis Bedachungen Ag",
    "wof:placetype":"venue"
},
  "geometry": {"coordinates":[9.285654,47.319401],"type":"Point"}
}