{
  "type": "Feature",
  "properties": {
    "iso:country":"CH",
    "sg:address":"Montezillon",
    "sg:city":"Montmollin",
    "sg:orig_category":"Architekturb\u00fcros",
    "sg:phone":"+41 32 731 32 74",
    "sg:postcode":"2205",
    "wof:name":"Jeanneret & Glauser Bureau D'architecture",
    "wof:placetype":"venue"
},
  "geometry": {"coordinates":[6.798516,46.988811],"type":"Point"}
}