{
  "type": "Feature",
  "properties": {
    "iso:country":"CH",
    "sg:address":"Hochstrasse 201",
    "sg:city":"Schaffhausen",
    "sg:classifiers":[
        {
            "category":"Shopping",
            "subcategory":"Pharmacy",
            "type":"Retail Goods"
        }
    ],
    "sg:phone":"+41 52 630 91 11",
    "sg:postcode":"8200",
    "sg:province":"Schaffhausen",
    "sg:tags":[
        "herbal",
        "pharmaceutical"
    ],
    "wof:name":"Cilag Ag",
    "wof:placetype":"venue"
},
  "geometry": {"coordinates":[8.6402826309,47.7112617493],"type":"Point"}
}