{
  "type": "Feature",
  "properties": {
    "iso:country":"CH",
    "sg:address":"Stauffacherstrasse 197/99",
    "sg:city":"Z\u00fcrich",
    "sg:orig_category":"Wirtschaftspr\u00fcfung, Steuerberatung U Treuhand",
    "sg:phone":"+41 12418405",
    "sg:postcode":"8004",
    "sg:province":"Z\u00fcrich",
    "wof:name":"Bkw Treuhand + Immobilien, Bruno K. Weber",
    "wof:placetype":"venue"
},
  "geometry": {"coordinates":[8.5187721252,47.3787689209],"type":"Point"}
}