{
  "type": "Feature",
  "properties": {
    "iso:country":"CH",
    "sg:address":"Rue Veyrot 12",
    "sg:city":"Meyrin",
    "sg:orig_category":"Geb\u00e4ude, Wohnungsreinigung Reinigungsgewerbe",
    "sg:phone":"+41 22 785 56 50",
    "sg:postcode":"1217",
    "sg:province":"Gen\u00e8ve",
    "wof:name":"Mg Services Manhente Entreprise De Nettoyages",
    "wof:placetype":"venue"
},
  "geometry": {"coordinates":[6.0630807877,46.2277374268],"type":"Point"}
}