{
  "type": "Feature",
  "properties": {
    "iso:country":"CH",
    "sg:address":"6939",
    "sg:city":"Arosio",
    "sg:orig_category":"Allgemeiner Hochbau Strassenbau",
    "sg:phone":"+41 71 393 15 43",
    "sg:postcode":"6939",
    "sg:province":"Ticino",
    "wof:name":"Viktor Bruggmann Baugesch\u00e4ft",
    "wof:placetype":"venue"
},
  "geometry": {"coordinates":[9.2117,47.442467],"type":"Point"}
}