{
  "type": "Feature",
  "properties": {
    "iso:country":"CH",
    "sg:address":"Via Stazione 1",
    "sg:city":"Locarno",
    "sg:orig_category":"Non-Classified Establishments",
    "sg:postcode":"6600",
    "sg:province":"Ticino",
    "wof:name":"Starnini Sergio, Assuntore Postale E Trasporti",
    "wof:placetype":"venue"
},
  "geometry": {"coordinates":[8.8003940582,46.1705741882],"type":"Point"}
}