{
  "type": "Feature",
  "properties": {
    "iso:country":"CH",
    "sg:address":"Seestrasse 5",
    "sg:city":"Horw",
    "sg:orig_category":"Erwachsenenbildung U Unterricht H\u00f6here Fachschulen",
    "sg:phone":"+41 41 340 13 14",
    "sg:postcode":"6048",
    "sg:province":"Luzern",
    "wof:name":"Fachinstitut F\u00fcr Nlp Schulungen",
    "wof:placetype":"venue"
},
  "geometry": {"coordinates":[8.3175821304,47.0115585327],"type":"Point"}
}