{
  "type": "Feature",
  "properties": {
    "iso:country":"CH",
    "sg:address":"Hammerstrasse 14 4058 Basel. Postfach",
    "sg:city":"Basel",
    "sg:orig_category":"Mit dem Versicherungsgewerbe verbundene T\u00e4tigkeiten",
    "sg:phone":"+41 61 691 99 20",
    "sg:postcode":"4005",
    "sg:province":"Basel-Stadt",
    "wof:name":"Balsiger Werner",
    "wof:placetype":"venue"
},
  "geometry": {"coordinates":[7.5982818604,47.560005188],"type":"Point"}
}