{
  "type": "Feature",
  "properties": {
    "iso:country":"CH",
    "sg:address":"Schulgasse 2",
    "sg:city":"Grossh\u00f6chstetten",
    "sg:orig_category":"Gartenbau",
    "sg:phone":"+41 79 652 22 05",
    "sg:postcode":"3506",
    "sg:province":"Bern",
    "wof:name":"Maurer Gartenbau, Inh. Jenni Peter",
    "wof:placetype":"venue"
},
  "geometry": {"coordinates":[7.6391510963,46.907333374],"type":"Point"}
}