{
  "type": "Feature",
  "properties": {
    "iso:country":"CH",
    "sg:address":"Via Cantonale 31 6815 Melide Casella Postale 332",
    "sg:city":"Melide",
    "sg:orig_category":"Instandhaltung U Reparatur von Automobilen Tankstellen",
    "sg:phone":"+41 91 649 91 91",
    "sg:postcode":"6815",
    "sg:province":"Ticino",
    "wof:name":"Garage G. E P. Di Gianni Bassanini",
    "wof:placetype":"venue"
},
  "geometry": {"coordinates":[8.9472846985,45.9547462463],"type":"Point"}
}