{
  "type": "Feature",
  "properties": {
    "iso:country":"CH",
    "sg:address":"4410",
    "sg:city":"Liestal",
    "sg:orig_category":"Sportvereine Sch\u00fctzen",
    "sg:phone":"+41 61 921 99 78",
    "sg:postcode":"4410",
    "sg:province":"Basel-Landschaft",
    "wof:name":"Sch\u00fctzengesellschaft",
    "wof:placetype":"venue"
},
  "geometry": {"coordinates":[7.7324171066,47.485458374],"type":"Point"}
}