{
  "type": "Feature",
  "properties": {
    "iso:country":"CH",
    "sg:address":"Sandrainstrasse 2",
    "sg:city":"Bern",
    "sg:orig_category":"Schaustellergewerbe U Vergn\u00fcgungsparks",
    "sg:postcode":"3007",
    "sg:province":"Bern",
    "wof:name":"Issi Agentur Seljimi",
    "wof:placetype":"venue"
},
  "geometry": {"coordinates":[7.4414730072,46.940536499],"type":"Point"}
}