{
  "type": "Feature",
  "properties": {
    "iso:country":"CH",
    "sg:address":"Vordere Vorstadt 5 5000 Aarau. Postfach",
    "sg:city":"Aarau",
    "sg:orig_category":"Versicherungen Generalagenturen",
    "sg:phone":"+41 21 310 38 12",
    "sg:postcode":"5001",
    "sg:province":"Aargau",
    "wof:name":"Nationale Suisse Assurances Agence G\u00e9n\u00e9rale",
    "wof:placetype":"venue"
},
  "geometry": {"coordinates":[6.6271348,46.5233535767],"type":"Point"}
}