{
  "type": "Feature",
  "properties": {
    "iso:country":"CH",
    "sg:address":"Florastrasse 3",
    "sg:city":"Wallisellen",
    "sg:orig_category":"Sonstige mit der Informatik verbundene T\u00e4tigkeiten",
    "sg:phone":"+41 18312625",
    "sg:postcode":"8304",
    "sg:province":"Z\u00fcrich",
    "wof:name":"Datinforg Beratungs-ag",
    "wof:placetype":"venue"
},
  "geometry": {"coordinates":[8.5974645615,47.4123191833],"type":"Point"}
}