{
  "type": "Feature",
  "properties": {
    "iso:country":"CH",
    "sg:address":"Heinrich Gujer-strasse 28",
    "sg:city":"Bauma",
    "sg:orig_category":"Detailhandel mit Waren verschiedener Art, Hauptrichtung Nahrungsmittel",
    "sg:phone":"+41 52 394 14 74",
    "sg:postcode":"8494",
    "sg:province":"Z\u00fcrich",
    "wof:name":"Epa Superdiscount",
    "wof:placetype":"venue"
},
  "geometry": {"coordinates":[8.8798141479,47.3681945801],"type":"Point"}
}