{
  "type": "Feature",
  "properties": {
    "addr:full":"Immeuble Victoria B Montana-vermala 3962",
    "addr:housenumber":"3962",
    "iso:country":"CH",
    "sg:address":"Immeuble Victoria B",
    "sg:city":"Montana-vermala",
    "sg:orig_category":"Detailhandel mit Bekleidung Detailhandel mit Herrenbekleidung",
    "sg:phone":"+41 27 481 88 28",
    "sg:postcode":"3962",
    "wof:name":"Ronchi Franco Sa",
    "wof:placetype":"venue"
},
  "geometry": {"coordinates":[146.329544,-38.66684],"type":"Point"}
}