{
  "type": "Feature",
  "properties": {
    "iso:country":"CH",
    "sg:address":"Bahnhofstrasse 14",
    "sg:city":"Walenstadt",
    "sg:orig_category":"Detailhandel mit Textilien Grosshandel mit Textilien",
    "sg:phone":"+41 81 735 16 82",
    "sg:postcode":"8880",
    "sg:province":"St. Gallen",
    "wof:name":"Textil Dietsche Pia",
    "wof:placetype":"venue"
},
  "geometry": {"coordinates":[9.3139095306,47.12317276],"type":"Point"}
}