{
  "type": "Feature",
  "properties": {
    "iso:country":"CH",
    "sg:address":"S\u00e9beillon Rue De 9a",
    "sg:city":"Lausanne",
    "sg:orig_category":"Softwareentwicklung U beratung",
    "sg:phone":"+41 21 624 19 08",
    "sg:postcode":"1004",
    "sg:province":"Vaud",
    "wof:name":"Arcad'site Sa",
    "wof:placetype":"venue"
},
  "geometry": {"coordinates":[6.6164569855,46.5233573914],"type":"Point"}
}