{
  "type": "Feature",
  "properties": {
    "iso:country":"CH",
    "sg:address":"H\u00fcnzikerstrtasse 15",
    "sg:city":"Schneisingen",
    "sg:orig_category":"Verwertung von Milch",
    "sg:postcode":"5425",
    "sg:province":"Aargau",
    "wof:name":"Milchgenossenschaft Schneisingen",
    "wof:placetype":"venue"
},
  "geometry": {"coordinates":[8.3664999008,47.5165481567],"type":"Point"}
}