{
  "type": "Feature",
  "properties": {
    "iso:country":"CH",
    "sg:address":"Rue De L'eglise 1",
    "sg:city":"Alle",
    "sg:orig_category":"Detailhandel mit Waren verschiedener Art, Hauptrichtung Nahrungsmittel",
    "sg:phone":"+41 32 471 13 16",
    "sg:postcode":"2942",
    "sg:province":"Jura",
    "wof:name":"Coop Neuch\u00e2tel-jura",
    "wof:placetype":"venue"
},
  "geometry": {"coordinates":[7.1278820038,47.4262123108],"type":"Point"}
}