{
  "type": "Feature",
  "properties": {
    "iso:country":"CH",
    "sg:address":"Rue Petit-rocher 6",
    "sg:city":"Lausanne",
    "sg:orig_category":"Sportschulen Fern\u00f6stliche Kampfsportarten",
    "sg:phone":"+41 71 912 15 45",
    "sg:postcode":"1003",
    "sg:province":"Vaud",
    "wof:name":"Kung Fu & Eskrima",
    "wof:placetype":"venue"
},
  "geometry": {"coordinates":[9.0447406769,47.4597244263],"type":"Point"}
}