{
  "type": "Feature",
  "properties": {
    "iso:country":"CH",
    "sg:address":"Murtenstrasse 19",
    "sg:city":"Aarberg",
    "sg:orig_category":"Detailhandel mit Fahrr\u00e4dern Fachdetailhandel in Verkaufsr\u00e4umen",
    "sg:phone":"+41 32 392 68 08",
    "sg:postcode":"3270",
    "sg:province":"Bern",
    "wof:name":"Thomet Radsport",
    "wof:placetype":"venue"
},
  "geometry": {"coordinates":[7.2703461647,47.0420684814],"type":"Point"}
}