{
  "type": "Feature",
  "properties": {
    "iso:country":"CH",
    "sg:address":"Bachofenstrasse 14",
    "sg:city":"Basel",
    "sg:orig_category":"Non-Classified Establishments",
    "sg:phone":"+41 71 311 55 11",
    "sg:postcode":"4053",
    "sg:province":"Basel-Stadt",
    "wof:name":"Wdata Ag",
    "wof:placetype":"venue"
},
  "geometry": {"coordinates":[9.3179769516,47.4226875305],"type":"Point"}
}