{
  "type": "Feature",
  "properties": {
    "iso:country":"CH",
    "sg:address":"Langackerstrasse 37",
    "sg:city":"Cham",
    "sg:orig_category":"Detailhandel mit Metallwaren, Anstrichmitteln, Glaswaren, Bau U Heimwerkerbedarf",
    "sg:phone":"+41 33 952 16 18",
    "sg:postcode":"6330",
    "sg:province":"Zug",
    "wof:name":"Tenag Brienz Ag",
    "wof:placetype":"venue"
},
  "geometry": {"coordinates":[8.0486021042,46.7520751953],"type":"Point"}
}