{
  "type": "Feature",
  "properties": {
    "iso:country":"CH",
    "sg:address":"Sch\u00f6nmattstrasse 5",
    "sg:city":"Aarburg",
    "sg:orig_category":"Vereine Musik/Blasmusik",
    "sg:postcode":"4663",
    "sg:province":"Aargau",
    "wof:name":"Stadtmusik Aarburg",
    "wof:placetype":"venue"
},
  "geometry": {"coordinates":[7.903801918,47.3347053528],"type":"Point"}
}