{
  "type": "Feature",
  "properties": {
    "iso:country":"CH",
    "sg:address":"Rosenaustrasse 8a",
    "sg:city":"Emmen",
    "sg:orig_category":"Sonstige mit der Informatik verbundene T\u00e4tigkeiten",
    "sg:postcode":"6032",
    "sg:province":"Luzern",
    "wof:name":"Informatik-systeme Schwander",
    "wof:placetype":"venue"
},
  "geometry": {"coordinates":[8.2890062332,47.0747108459],"type":"Point"}
}