{
  "type": "Feature",
  "properties": {
    "iso:country":"CH",
    "sg:address":"Giessenweg 8",
    "sg:city":"Diepoldsau",
    "sg:orig_category":"G\u00fcterbef\u00f6rderung im Strassenverkehr",
    "sg:postcode":"9444",
    "sg:province":"St. Gallen",
    "wof:name":"Gtrans Transport Und Handel Ag",
    "wof:placetype":"venue"
},
  "geometry": {"coordinates":[9.6574802399,47.3816719055],"type":"Point"}
}