{
  "type": "Feature",
  "properties": {
    "iso:country":"CH",
    "sg:address":"Webergasse 11 4058 Basel. Postfach",
    "sg:city":"Basel",
    "sg:classifiers":[
        {
            "category":"Utilities",
            "subcategory":"Water",
            "type":"Services"
        }
    ],
    "sg:phone":"+41 61 691 90 41",
    "sg:postcode":"4051",
    "sg:province":"Basel-Stadt",
    "sg:tags":[
        "tea-rooms",
        "bar",
        "restaurants"
    ],
    "wof:name":"Emmenegger-aerni Silvia Und Beat, Bermuda-bar Bar Mit Restaurationsbetrieb",
    "wof:placetype":"venue"
},
  "geometry": {"coordinates":[7.590639,47.561886],"type":"Point"}
}