{
  "type": "Feature",
  "properties": {
    "iso:country":"CH",
    "sg:address":"Seestrasse 153",
    "sg:city":"St\u00e4fa",
    "sg:orig_category":"Saunas, Solarien, Fitnesszentren U \u00e4hnliches",
    "sg:phone":"+41 79 412 89 16",
    "sg:postcode":"8712",
    "sg:province":"Z\u00fcrich",
    "wof:name":"Sunrent Ag",
    "wof:placetype":"venue"
},
  "geometry": {"coordinates":[8.7938747406,47.3109474182],"type":"Point"}
}