{
  "type": "Feature",
  "properties": {
    "iso:country":"CH",
    "sg:address":"Vicolo Al Porto 6",
    "sg:city":"Gordola",
    "sg:orig_category":"Gem\u00fcsebau",
    "sg:phone":"+41 91 745 18 03",
    "sg:postcode":"6596",
    "sg:province":"Ticino",
    "wof:name":"Pia Gianettoni Orticolture",
    "wof:placetype":"venue"
},
  "geometry": {"coordinates":[8.8652057648,46.1809043884],"type":"Point"}
}