{
  "type": "Feature",
  "properties": {
    "iso:country":"CH",
    "sg:address":"Neugasse 7 6300 Zug. Postfach",
    "sg:city":"Zug",
    "sg:orig_category":"Fernmeldedienste",
    "sg:postcode":"6300",
    "sg:province":"Zug",
    "wof:name":"Ineo Netzwerkf\u00e4hige Applikationen; Entwicklung U. Vertrieb Usw",
    "wof:placetype":"venue"
},
  "geometry": {"coordinates":[8.5157108307,47.1673927307],"type":"Point"}
}