{
  "type": "Feature",
  "properties": {
    "iso:country":"CH",
    "sg:address":"Ch. Du Jonc 13. 1217 Meyrin. Postfach",
    "sg:city":"Cointrin",
    "sg:orig_category":"Detailhandel mit M\u00f6beln U Haushaltsgegenst\u00e4nden",
    "sg:postcode":"1216",
    "sg:province":"Gen\u00e8ve",
    "wof:name":"Selection Ameublement, Germain Pierre.",
    "wof:placetype":"venue"
},
  "geometry": {"coordinates":[6.1089258194,46.2269554138],"type":"Point"}
}