{
  "type": "Feature",
  "properties": {
    "iso:country":"CH",
    "sg:address":"1077",
    "sg:city":"Servion",
    "sg:orig_category":"Grosshandel mit Getr\u00e4nken",
    "sg:phone":"+41 21 903 02 80",
    "sg:postcode":"1077",
    "sg:province":"Vaud",
    "wof:name":"Les Caves Priv\u00e9es Epb Sa",
    "wof:placetype":"venue"
},
  "geometry": {"coordinates":[6.7798299789,46.5735092163],"type":"Point"}
}