{
  "type": "Feature",
  "properties": {
    "iso:country":"CH",
    "sg:address":"Seewadelstrasse 7c 8444 Henggart. Postfach",
    "sg:city":"Rudolfingen",
    "sg:orig_category":"W\u00e4scherei U chemische Reinigung",
    "sg:postcode":"8465",
    "sg:province":"Z\u00fcrich",
    "wof:name":"Bracktikum Brack H.",
    "wof:placetype":"venue"
},
  "geometry": {"coordinates":[8.6869869232,47.5628929138],"type":"Point"}
}