{
  "type": "Feature",
  "properties": {
    "iso:country":"CH",
    "sg:address":"Grabenstr. 34",
    "sg:city":"Chur",
    "sg:classifiers":[
        {
            "category":"Wholesale",
            "subcategory":"Machinery & Supplies",
            "type":"Manufacturing & Wholesale Goods"
        }
    ],
    "sg:phone":"+41 81 252 94 54",
    "sg:postcode":"7000",
    "sg:province":"Graubunden",
    "sg:tags":[
        "equipment",
        "optical",
        "precision",
        "instrument"
    ],
    "wof:name":"Wuffli Foto Video Ag",
    "wof:placetype":"venue"
},
  "geometry": {"coordinates":[9.5302438736,46.849609375],"type":"Point"}
}