{
  "type": "Feature",
  "properties": {
    "addr:full":"Entre-deux-fossaux 3 Collombey Valais 1868",
    "addr:housenumber":"3",
    "addr:postcode":"1868",
    "addr:street":"Entre-Deux-Fossaux",
    "iso:country":"CH",
    "sg:address":"Entre-deux-fossaux 3",
    "sg:city":"Collombey",
    "sg:orig_category":"Allgemeiner Hoch U Tiefbau",
    "sg:phone":"+41 24 472 27 38",
    "sg:postcode":"1868",
    "sg:province":"Valais",
    "wof:name":"Batifeu S\u00e0rl",
    "wof:placetype":"venue"
},
  "geometry": {"coordinates":[6.945828,46.270473],"type":"Point"}
}