{
  "type": "Feature",
  "properties": {
    "addr:full":"K\u00f6llikerstrasse 30 Safenwil Aargau 5745",
    "addr:housenumber":"30",
    "addr:postcode":"5745",
    "addr:street":"Koellikerstrasse",
    "iso:country":"CH",
    "sg:address":"K\u00f6llikerstrasse 30",
    "sg:city":"Safenwil",
    "sg:classifiers":[
        {
            "category":"Autos & Motor Vehicles",
            "subcategory":"Auto Supplies",
            "type":"Retail Goods"
        }
    ],
    "sg:phone":"+41 62 788 40 20",
    "sg:postcode":"5745",
    "sg:province":"Aargau",
    "sg:tags":[
        "automobile",
        "accessory"
    ],
    "wof:name":"Aerni Ag",
    "wof:placetype":"venue"
},
  "geometry": {"coordinates":[7.991337,47.321281],"type":"Point"}
}