{
  "type": "Feature",
  "properties": {
    "iso:country":"CH",
    "sg:address":"Grandes Forges 2",
    "sg:city":"Vallorbe",
    "sg:orig_category":"Sportvereine P\u00e9tanque",
    "sg:phone":"+41 78 749 98 05",
    "sg:postcode":"1337",
    "sg:province":"Vaud",
    "wof:name":"P\u00e9tanque-club L'avenir",
    "wof:placetype":"venue"
},
  "geometry": {"coordinates":[6.3793067932,46.7119445801],"type":"Point"}
}