{
  "type": "Feature",
  "properties": {
    "iso:country":"CH",
    "sg:address":"Hafenstrasse 34",
    "sg:city":"Kreuzlingen",
    "sg:orig_category":"Unternehmensberatung",
    "sg:phone":"+41 71 670 05 20",
    "sg:postcode":"8280",
    "sg:province":"Thurgau",
    "wof:name":"Sofdes Unternehmens-& Organisationsberatungs-ag",
    "wof:placetype":"venue"
},
  "geometry": {"coordinates":[9.1793575287,47.6503829956],"type":"Point"}
}