{
  "type": "Feature",
  "properties": {
    "addr:full":"Ehretstrasse 37 H\u00fcnenberg Zug 6331",
    "addr:housenumber":"37",
    "addr:postcode":"6331",
    "addr:street":"Ehretstrasse;Huenenberg Zug",
    "iso:country":"CH",
    "sg:address":"Ehretstrasse 37",
    "sg:city":"H\u00fcnenberg",
    "sg:orig_category":"Betrieb von Taxis G\u00fcterbef\u00f6rderung im Strassenverkehr",
    "sg:phone":"+41 41 780 19 19",
    "sg:postcode":"6331",
    "sg:province":"Zug",
    "wof:name":"Burgtaxi Thomas Gisler",
    "wof:placetype":"venue"
},
  "geometry": {"coordinates":[8.428618,47.171928],"type":"Point"}
}