{
  "type": "Feature",
  "properties": {
    "iso:country":"CH",
    "sg:address":"Schossenrietstrasse 2 9442 Berneck. Postfach",
    "sg:city":"Berneck",
    "sg:orig_category":"Grosshandel mit Flachglas, Sanit\u00e4rkeramik U Anstrichmitteln Herstellung von Anstrichmitteln, Druckfa",
    "sg:phone":"+41 71 744 13 70",
    "sg:postcode":"9442",
    "sg:province":"St. Gallen",
    "wof:name":"Mipa Lacke + Farben Ag",
    "wof:placetype":"venue"
},
  "geometry": {"coordinates":[9.6099843979,47.4226646423],"type":"Point"}
}