{
  "type": "Feature",
  "properties": {
    "iso:country":"CH",
    "sg:address":"Ch\u00e2teau-bloch Chemin 2",
    "sg:city":"Vernier",
    "sg:orig_category":"Fernmeldedienste",
    "sg:postcode":"1214",
    "sg:province":"Gen\u00e8ve",
    "wof:name":"Tdc Suisse Sa",
    "wof:placetype":"venue"
},
  "geometry": {"coordinates":[6.0804748535,46.2123451233],"type":"Point"}
}