{
  "type": "Feature",
  "properties": {
    "iso:country":"CH",
    "sg:address":"Jungfraustrasse 4",
    "sg:city":"Burgdorf",
    "sg:orig_category":"Softwareentwicklung U beratung",
    "sg:phone":"+41 34 424 02 83",
    "sg:postcode":"3400",
    "sg:province":"Bern",
    "wof:name":"Creactiv Information Technologies Gmbh",
    "wof:placetype":"venue"
},
  "geometry": {"coordinates":[7.6189980507,47.0573234558],"type":"Point"}
}