{
  "type": "Feature",
  "properties": {
    "iso:country":"CH",
    "sg:address":"Rue Du Bourg 15 3960 Sierre Case Postale 133",
    "sg:city":"Sierre",
    "sg:orig_category":"Fachdetailhandel mit pharmazeutischen Produkten",
    "sg:phone":"+41 79 418 66 30",
    "sg:postcode":"3960",
    "sg:province":"Valais",
    "wof:name":"Pharmacie Cina",
    "wof:placetype":"venue"
},
  "geometry": {"coordinates":[7.5334300995,46.2933502197],"type":"Point"}
}