{
  "type": "Feature",
  "properties": {
    "iso:country":"CH",
    "sg:address":"Hungerb\u00fchlstrasse 7",
    "sg:city":"Embrach",
    "sg:classifiers":[
        {
            "category":"Organizations",
            "subcategory":"Labor Organization",
            "type":"Services"
        }
    ],
    "sg:phone":"+41 43 444 14 40",
    "sg:postcode":"8424",
    "sg:province":"Z\u00fcrich",
    "sg:tags":[
        "work",
        "assembling",
        "assembly",
        "contract"
    ],
    "wof:name":"Am Bauf\u00fchrungen Und Montagen Gmbh",
    "wof:placetype":"venue"
},
  "geometry": {"coordinates":[8.594826,47.50602],"type":"Point"}
}