{
  "type": "Feature",
  "properties": {
    "iso:country":"CH",
    "sg:address":"Eugstisriert",
    "sg:city":"Sennwald",
    "sg:orig_category":"Detailhandel mit Brot, Back U S\u00fcsswaren",
    "sg:phone":"+41 81 757 16 45",
    "sg:postcode":"9466",
    "sg:province":"St. Gallen",
    "wof:name":"B\u00e4ckerei Konditorei Siegrist Gmbh",
    "wof:placetype":"venue"
},
  "geometry": {"coordinates":[9.50362,47.260658],"type":"Point"}
}