{
  "type": "Feature",
  "properties": {
    "iso:country":"CH",
    "sg:address":"1617",
    "sg:city":"Remaufens",
    "sg:orig_category":"Landw. Genossenschaften Viehzucht",
    "sg:postcode":"1617",
    "sg:province":"Fribourg",
    "wof:name":"Syndicat D'\u00e9levage Grv",
    "wof:placetype":"venue"
},
  "geometry": {"coordinates":[6.9744057655,46.6355400085],"type":"Point"}
}