{
  "type": "Feature",
  "properties": {
    "iso:country":"CH",
    "sg:address":"Winterthurerstrasse 460",
    "sg:city":"Z\u00fcrich",
    "sg:orig_category":"Detailhandel mit Fleisch U Fleischwaren",
    "sg:phone":"+41 71 744 90 10",
    "sg:postcode":"8051",
    "sg:province":"Z\u00fcrich",
    "wof:name":"Walter Kast Metzgerei",
    "wof:placetype":"venue"
},
  "geometry": {"coordinates":[9.636048317,47.4517478943],"type":"Point"}
}