{
  "type": "Feature",
  "properties": {
    "iso:country":"CH",
    "sg:address":"Via Camminata",
    "sg:city":"Bellinzona",
    "sg:orig_category":"Detailhandel mit B\u00fcchern Detailhandel mit B\u00fcchern, Zeitungen, Schreib U Papeteriewaren",
    "sg:phone":"+41 91 826 24 25",
    "sg:postcode":"6500",
    "sg:province":"Ticino",
    "wof:name":"Libreria Taborelli.",
    "wof:placetype":"venue"
},
  "geometry": {"coordinates":[9.02255,46.190445],"type":"Point"}
}