{
  "type": "Feature",
  "properties": {
    "iso:country":"CH",
    "sg:address":"Stadthausstrasse 3",
    "sg:city":"Luzern",
    "sg:orig_category":"Unclassifiable Establishments",
    "sg:postcode":"6003",
    "sg:province":"Luzern",
    "wof:name":"Dr. Werner M. Heller Chiropraktor",
    "wof:placetype":"venue"
},
  "geometry": {"coordinates":[8.3055067062,47.0491104126],"type":"Point"}
}