{
  "type": "Feature",
  "properties": {
    "addr:full":"Unterbergstrasse 52 Biberstein Aargau 5023",
    "addr:housenumber":"52",
    "addr:postcode":"5023",
    "addr:street":"Unterbergstrasse",
    "iso:country":"CH",
    "sg:address":"Unterbergstrasse 52",
    "sg:city":"Biberstein",
    "sg:classifiers":[
        {
            "category":"Building & Trades",
            "subcategory":"Construction",
            "type":"Services"
        }
    ],
    "sg:phone":"+41 62 827 49 49",
    "sg:postcode":"5023",
    "sg:province":"Aargau",
    "sg:tags":[
        "operations",
        "hiring",
        "crane"
    ],
    "wof:name":"Meyer Kran + Transport Gmbh",
    "wof:placetype":"venue"
},
  "geometry": {"coordinates":[8.08919,47.413509],"type":"Point"}
}