{
  "type": "Feature",
  "properties": {
    "iso:country":"CH",
    "sg:address":"Moorschwand 1601",
    "sg:city":"Horgenberg",
    "sg:orig_category":"Architekturb\u00fcros Unternehmensberatung",
    "sg:phone":"+41 17258865",
    "sg:postcode":"8815",
    "sg:province":"Z\u00fcrich",
    "wof:name":"Siro-team Gmbh",
    "wof:placetype":"venue"
},
  "geometry": {"coordinates":[8.579424,47.251888],"type":"Point"}
}