{
  "type": "Feature",
  "properties": {
    "iso:country":"CH",
    "sg:address":"3665",
    "sg:city":"Wattenwil",
    "sg:orig_category":"Verarbeitung von Milch Verwertung von Milch",
    "sg:postcode":"3665",
    "sg:province":"Bern",
    "wof:name":"K\u00e4sereigenossenschaft Grundbach",
    "wof:placetype":"venue"
},
  "geometry": {"coordinates":[7.5096979141,46.7696723938],"type":"Point"}
}