{
  "type": "Feature",
  "properties": {
    "iso:country":"CH",
    "sg:address":"Cosenzstrasse 1",
    "sg:city":"Untervaz",
    "sg:orig_category":"Sonstiger spezialisierter Hoch U Tiefbau",
    "sg:phone":"+41 81 322 18 23",
    "sg:postcode":"7204",
    "sg:province":"Graubunden",
    "wof:name":"Betab Hersche",
    "wof:placetype":"venue"
},
  "geometry": {"coordinates":[9.5377645493,46.9258041382],"type":"Point"}
}