{
  "type": "Feature",
  "properties": {
    "iso:country":"CH",
    "sg:address":"9410 Heiden. Postfach 8",
    "sg:city":"Heiden",
    "sg:orig_category":"Vereine Abstinenten",
    "sg:postcode":"9410",
    "sg:province":"Appenzell Ausserrhoden",
    "wof:name":"Blaues Kreuz",
    "wof:placetype":"venue"
},
  "geometry": {"coordinates":[9.5325603485,47.4444046021],"type":"Point"}
}