{
  "type": "Feature",
  "properties": {
    "iso:country":"CH",
    "sg:address":"Schachenstrasse",
    "sg:city":"Winznau",
    "sg:orig_category":"Herstellung von Kunststoffwaren",
    "sg:phone":"+41 71 466 70 30",
    "sg:postcode":"4652",
    "sg:province":"Solothurn",
    "wof:name":"St\u00fcdli Plastikfabrik Ag",
    "wof:placetype":"venue"
},
  "geometry": {"coordinates":[9.3715181351,47.5576133728],"type":"Point"}
}