{
  "type": "Feature",
  "properties": {
    "iso:country":"CH",
    "sg:address":"Wartenfelsstrasse 51",
    "sg:city":"Lostorf",
    "sg:orig_category":"Zimmerei, Dachdeckerei, Bauspenglerei U Abdichtung",
    "sg:postcode":"4654",
    "sg:province":"Solothurn",
    "wof:name":"Aebersold R.",
    "wof:placetype":"venue"
},
  "geometry": {"coordinates":[7.9435691833,47.3895721436],"type":"Point"}
}