{
  "type": "Feature",
  "properties": {
    "iso:country":"CH",
    "sg:address":"Bachtelstrasse 66 8342 Wernetshausen. Postfach",
    "sg:city":"Wernetshausen",
    "sg:orig_category":"Detailhandel mit Metallwaren, Anstrichmitteln, Glaswaren, Bau U Heimwerkerbedarf",
    "sg:postcode":"8342",
    "sg:province":"Z\u00fcrich",
    "wof:name":"Gdv International Gmbh Technische Erzeugnisse U. Deren Zubeh\u00f6r; Entwicklung, Produktion, Vertrieb Usw",
    "wof:placetype":"venue"
},
  "geometry": {"coordinates":[8.8655290604,47.2973861694],"type":"Point"}
}