{
  "type": "Feature",
  "properties": {
    "iso:country":"CH",
    "sg:address":"St. Gallerstrasse 82",
    "sg:city":"Lachen",
    "sg:classifiers":[
        {
            "category":"Transit Center",
            "subcategory":"Freight",
            "type":"Transportation"
        }
    ],
    "sg:phone":"+41 55 451 84 84",
    "sg:postcode":"8853",
    "sg:province":"Schwyz",
    "sg:tags":[
        "milling",
        "cnc"
    ],
    "wof:name":"Haas Ag",
    "wof:placetype":"venue"
},
  "geometry": {"coordinates":[8.861802,47.19347],"type":"Point"}
}