{
  "type": "Feature",
  "properties": {
    "iso:country":"CH",
    "sg:address":"Mattweg",
    "sg:city":"Neuheim",
    "sg:orig_category":"Architektur U Ingenieurb\u00fcros",
    "sg:phone":"+41 41 870 67 00",
    "sg:postcode":"6345",
    "sg:province":"Zug",
    "wof:name":"Architekturb\u00fcro Meier Heinz Ag",
    "wof:placetype":"venue"
},
  "geometry": {"coordinates":[8.63385,46.877281],"type":"Point"}
}