{
  "type": "Feature",
  "properties": {
    "iso:country":"CH",
    "sg:address":"Werkhofstrasse 2",
    "sg:city":"Solothurn",
    "sg:orig_category":"Zahnarztpraxen",
    "sg:phone":"+41 61 721 19 19",
    "sg:postcode":"4500",
    "sg:province":"Solothurn",
    "wof:name":"Dr. Med. Dent. Urs Schraner Zahnarzt",
    "wof:placetype":"venue"
},
  "geometry": {"coordinates":[7.5256428719,47.5068397522],"type":"Point"}
}