{
  "type": "Feature",
  "properties": {
    "iso:country":"CH",
    "sg:address":"Gasterstrasse 44",
    "sg:city":"Kaltbrunn",
    "sg:orig_category":"Autogaragen",
    "sg:phone":"+41 55 283 24 22",
    "sg:postcode":"8722",
    "sg:province":"St. Gallen",
    "wof:name":"Urs Ziegler Garage",
    "wof:placetype":"venue"
},
  "geometry": {"coordinates":[9.031998,47.208591],"type":"Point"}
}