{
  "type": "Feature",
  "properties": {
    "iso:country":"CH",
    "sg:address":"Bahnhofstrasse 26",
    "sg:city":"St\u00e4fa",
    "sg:classifiers":[
        {
            "category":"Banks & Credit Unions",
            "subcategory":"Bank",
            "type":"Services"
        }
    ],
    "sg:phone":"+41 12191111",
    "sg:postcode":"8712",
    "sg:province":"Z\u00fcrich",
    "wof:name":"Bank Leu Ag",
    "wof:placetype":"venue"
},
  "geometry": {"coordinates":[8.539035,47.370888],"type":"Point"}
}