{
  "type": "Feature",
  "properties": {
    "iso:country":"CH",
    "sg:address":"Schwellistrasse 61",
    "sg:city":"Z\u00fcrich",
    "sg:orig_category":"Bauingenieurb\u00fcros allgemein",
    "sg:phone":"+41 13023066",
    "sg:postcode":"8052",
    "sg:province":"Z\u00fcrich",
    "wof:name":"Hans R. Wiesendanger Ingenieurb\u00fcro",
    "wof:placetype":"venue"
},
  "geometry": {"coordinates":[8.53797,47.425056],"type":"Point"}
}