{
  "type": "Feature",
  "properties": {
    "iso:country":"CH",
    "sg:address":"St\u00fcssistrasse 83",
    "sg:city":"Z\u00fcrich",
    "sg:classifiers":[
        {
            "category":"Professional",
            "subcategory":"Employment Agencies",
            "type":"Services"
        }
    ],
    "sg:phone":"+41 13636020",
    "sg:postcode":"8057",
    "sg:province":"Z\u00fcrich",
    "sg:tags":[
        "personal",
        "u",
        "stellenvermittlung"
    ],
    "wof:name":"Om Option Model Agency Ag",
    "wof:placetype":"venue"
},
  "geometry": {"coordinates":[8.5410547256,47.3948554993],"type":"Point"}
}