{
  "type": "Feature",
  "properties": {
    "iso:country":"CH",
    "sg:address":"Bachstrasse 10",
    "sg:city":"Pfyn",
    "sg:orig_category":"Bau U Wohngenossenschaften Erschliessung von Grundst\u00fccken",
    "sg:phone":"+41 52 765 12 26",
    "sg:postcode":"8505",
    "sg:province":"Thurgau",
    "wof:name":"Gen.alterssiedlung Pfyn/umg.",
    "wof:placetype":"venue"
},
  "geometry": {"coordinates":[8.950637,47.599594],"type":"Point"}
}