{
  "type": "Feature",
  "properties": {
    "iso:country":"CH",
    "sg:address":"T\u00f6ssstrasse 8",
    "sg:city":"Neftenbach",
    "sg:orig_category":"Freizeit, Gastst\u00e4tten",
    "sg:phone":"+41 52",
    "sg:postcode":"8413",
    "sg:province":"Z\u00fcrich",
    "wof:name":"Bio Top Handels Ag",
    "wof:placetype":"venue"
},
  "geometry": {"coordinates":[8.658668,47.517639],"type":"Point"}
}