{
  "type": "Feature",
  "properties": {
    "iso:country":"CH",
    "sg:address":"Tiefriet",
    "sg:city":"Sargans",
    "sg:classifiers":[
        {
            "category":"Bars & Pubs",
            "type":"Food & Drink"
        }
    ],
    "sg:postcode":"7320",
    "sg:province":"St. Gallen",
    "wof:name":"Disco Gestion S\u00e0rl",
    "wof:placetype":"venue"
},
  "geometry": {"coordinates":[6.997537,47.153015],"type":"Point"}
}