{
  "type": "Feature",
  "properties": {
    "iso:country":"CH",
    "sg:address":"Stegm\u00fchleweg 35 4123 Allschwil. Postfach",
    "sg:city":"Allschwil",
    "sg:orig_category":"Sonstige mit der Informatik verbundene T\u00e4tigkeiten",
    "sg:postcode":"4123",
    "sg:province":"Basel-Landschaft",
    "wof:name":"Erra Edv-beratung",
    "wof:placetype":"venue"
},
  "geometry": {"coordinates":[7.5271501541,47.5520515442],"type":"Point"}
}