{
  "type": "Feature",
  "properties": {
    "iso:country":"CH",
    "sg:address":"Oberm\u00fchlestrasse 22 6330 Cham. Postfach 481",
    "sg:city":"Cham",
    "sg:orig_category":"Aktivit\u00e4ten der Generalunternehmen im Baugewerbe Kauf U Verkauf von Immobilien auf eigene Rechnung",
    "sg:phone":"+41 31 332 88 55",
    "sg:postcode":"6330",
    "sg:province":"Zug",
    "wof:name":"Huber & Ploerer Verwaltungen",
    "wof:placetype":"venue"
},
  "geometry": {"coordinates":[7.451741,46.957829],"type":"Point"}
}