{
  "type": "Feature",
  "properties": {
    "addr:full":"Tribschenstrasse 7 6005 Luzern. Postfach 3045 Luzern Luzern 6002",
    "addr:housenumber":"7",
    "addr:postcode":"6005;3045;6002",
    "addr:street":"Tribschenstrasse;Postfach",
    "iso:country":"CH",
    "sg:address":"Tribschenstrasse 7 6005 Luzern. Postfach 3045",
    "sg:city":"Luzern",
    "sg:orig_category":"Arbeitnehmerverb\u00e4nde",
    "sg:phone":"+41 56 631 69 00",
    "sg:postcode":"6002",
    "sg:province":"Luzern",
    "wof:name":"Schweiz.verband Hauswirtsch. Betriebsleiter-innen (svhbl)",
    "wof:placetype":"venue"
},
  "geometry": {"coordinates":[8.312529,47.044052],"type":"Point"}
}