{
  "type": "Feature",
  "properties": {
    "iso:country":"CH",
    "sg:address":"Bitzistrasse 5",
    "sg:city":"Stans",
    "sg:orig_category":"Sportvereine Sch\u00fctzen Pistolen-& Gewehr",
    "sg:phone":"+41 41 610 28 78",
    "sg:postcode":"6370",
    "sg:province":"Nidwalden",
    "wof:name":"Pistolensektion",
    "wof:placetype":"venue"
},
  "geometry": {"coordinates":[8.3555116653,46.9637336731],"type":"Point"}
}