{
  "type": "Feature",
  "properties": {
    "iso:country":"CH",
    "sg:address":"Village D'en Haut",
    "sg:city":"Charmey",
    "sg:classifiers":[
        {
            "category":"Banks & Credit Unions",
            "subcategory":"Bank",
            "type":"Services"
        }
    ],
    "sg:phone":"+41 2971616",
    "sg:postcode":"1637",
    "sg:province":"Fribourg",
    "wof:name":"Banque De L'etat De Fribourg",
    "wof:placetype":"venue"
},
  "geometry": {"coordinates":[7.1670150757,46.6194267273],"type":"Point"}
}