{
  "type": "Feature",
  "properties": {
    "iso:country":"CH",
    "sg:address":"Hohengasse 12 3400 Burgdorf. Postfach",
    "sg:city":"Burgdorf",
    "sg:classifiers":[
        {
            "category":"Restaurant",
            "type":"Food & Drink"
        }
    ],
    "sg:phone":"+41 34 422 21 05",
    "sg:postcode":"3402",
    "sg:province":"Bern",
    "wof:name":"Restaurant Zu Metzgern",
    "wof:placetype":"venue"
},
  "geometry": {"coordinates":[7.6267309189,47.0559234619],"type":"Point"}
}