{
  "type": "Feature",
  "properties": {
    "iso:country":"CH",
    "sg:address":"Loretoh\u00f6he 3",
    "sg:city":"Zug",
    "sg:classifiers":[
        {
            "category":"Travel",
            "subcategory":"Hotels & Motels",
            "type":"Entertainment"
        }
    ],
    "sg:postcode":"6300",
    "sg:province":"Zug",
    "sg:tags":[
        "hotels",
        "mit",
        "restaurant"
    ],
    "wof:name":"Salsa Kongress Gmbh",
    "wof:placetype":"venue"
},
  "geometry": {"coordinates":[8.5235691071,47.172454834],"type":"Point"}
}