{
  "type": "Feature",
  "properties": {
    "iso:country":"CH",
    "sg:address":"Forrerstrasse 23",
    "sg:city":"Bern",
    "sg:orig_category":"Fachdetailhandel in Verkaufsr\u00e4umen",
    "sg:phone":"+41 31 351 91 31",
    "sg:postcode":"3006",
    "sg:province":"Bern",
    "wof:name":"Panic Sports Modler",
    "wof:placetype":"venue"
},
  "geometry": {"coordinates":[7.4657568932,46.9344100952],"type":"Point"}
}