{
  "type": "Feature",
  "properties": {
    "iso:country":"CH",
    "sg:address":"Burgfelderstrasse 160",
    "sg:city":"Basel",
    "sg:classifiers":[
        {
            "category":"Insurance",
            "subcategory":"Insurance Agent",
            "type":"Services"
        }
    ],
    "sg:phone":"+41 61 322 06 71",
    "sg:postcode":"4055",
    "sg:province":"Basel-Stadt",
    "sg:tags":[
        "versicherungsagenturen",
        "-broker"
    ],
    "wof:name":"Ufg Unternehmens-&finanz- Group Ag",
    "wof:placetype":"venue"
},
  "geometry": {"coordinates":[7.5661492348,47.5658416748],"type":"Point"}
}