{
  "type": "Feature",
  "properties": {
    "iso:country":"CH",
    "sg:address":"Chalet Sierra",
    "sg:city":"Wiggen",
    "sg:orig_category":"G\u00fcterbef\u00f6rderung im Strassenverkehr",
    "sg:phone":"+41 79 441 11 45",
    "sg:postcode":"6192",
    "sg:province":"Luzern",
    "wof:name":"Trans-portmann Ag",
    "wof:placetype":"venue"
},
  "geometry": {"coordinates":[7.9097008705,46.8958778381],"type":"Point"}
}