{
  "type": "Feature",
  "properties": {
    "iso:country":"CH",
    "sg:address":"R\u00fceggental",
    "sg:city":"B\u00e4retswil",
    "sg:orig_category":"Verwertung von Milch",
    "sg:postcode":"8344",
    "sg:province":"Z\u00fcrich",
    "wof:name":"Milchverwertungsgenossenschaft Wirzwil",
    "wof:placetype":"venue"
},
  "geometry": {"coordinates":[8.8841657639,47.3412017822],"type":"Point"}
}