{
  "type": "Feature",
  "properties": {
    "iso:country":"CH",
    "sg:address":"Oberwilerweg 6",
    "sg:city":"Frauenfeld",
    "sg:orig_category":"Gesundheitswesen",
    "sg:phone":"+41 52 720 27 83",
    "sg:postcode":"8500",
    "sg:province":"Thurgau",
    "wof:name":"Heilen Mit Klang + Psychiatrischer Beratung Ilse Ernst",
    "wof:placetype":"venue"
},
  "geometry": {"coordinates":[8.8867998123,47.5522079468],"type":"Point"}
}