{
  "type": "Feature",
  "properties": {
    "iso:country":"CH",
    "sg:address":"Werchlaubeng\u00e4ssli 14",
    "sg:city":"Luzern",
    "sg:orig_category":"Detailhandel mit Bekleidung Detailhandel mit Damenbekleidung",
    "sg:phone":"+41 41 410 19 12",
    "sg:postcode":"6004",
    "sg:province":"Luzern",
    "wof:name":"Maison De Boer Ag",
    "wof:placetype":"venue"
},
  "geometry": {"coordinates":[8.305897,47.052731],"type":"Point"}
}