{
  "type": "Feature",
  "properties": {
    "iso:country":"CH",
    "sg:address":"Chemin De L'esplanade 16",
    "sg:city":"Vernier",
    "sg:orig_category":"Zahnarztpraxen",
    "sg:phone":"+41 32 953 12 12",
    "sg:postcode":"1214",
    "sg:province":"Gen\u00e8ve",
    "wof:name":"Dr Joanna Widlicka-pamierna M\u00e9decin-dentiste",
    "wof:placetype":"venue"
},
  "geometry": {"coordinates":[6.9561729431,47.2241325378],"type":"Point"}
}