{
  "type": "Feature",
  "properties": {
    "iso:country":"CH",
    "sg:address":"En Tr\u00eame",
    "sg:city":"Epagny",
    "sg:orig_category":"Maurerarbeiten",
    "sg:phone":"+41 33 442 12 25",
    "sg:postcode":"1664",
    "wof:name":"Peter Buchser Chemin\u00e9ebau & Kundenmaurer",
    "wof:placetype":"venue"
},
  "geometry": {"coordinates":[7.6639351845,46.7642707825],"type":"Point"}
}