{
  "type": "Feature",
  "properties": {
    "iso:country":"CH",
    "sg:address":"Runatsch 153",
    "sg:city":"Zernez",
    "sg:classifiers":[
        {
            "category":"Travel",
            "subcategory":"Hotels & Motels",
            "type":"Entertainment"
        }
    ],
    "sg:phone":"+41 81 856 12 13",
    "sg:postcode":"7530",
    "sg:province":"Graubunden",
    "sg:tags":[
        "hotels",
        "mit",
        "restaurant"
    ],
    "wof:name":"Hotel Adler",
    "wof:placetype":"venue"
},
  "geometry": {"coordinates":[10.0982208252,46.6969985962],"type":"Point"}
}