{
  "type": "Feature",
  "properties": {
    "iso:country":"CH",
    "sg:address":"Via Vallemaggia 31",
    "sg:city":"Locarno",
    "sg:classifiers":[
        {
            "category":"Travel",
            "subcategory":"Hotels & Motels",
            "type":"Entertainment"
        }
    ],
    "sg:phone":"+41 91 751 80 13",
    "sg:postcode":"6600",
    "sg:province":"Ticino",
    "sg:tags":[
        "hotels",
        "mit",
        "restaurant"
    ],
    "wof:name":"Albergo Elvetico",
    "wof:placetype":"venue"
},
  "geometry": {"coordinates":[8.7891702652,46.169719696],"type":"Point"}
}