{
  "type": "Feature",
  "properties": {
    "iso:country":"CH",
    "sg:address":"Vorder-katzenbalg",
    "sg:city":"Kriens",
    "sg:orig_category":"Vermietung U Verpachtung von eigenen Immobilien",
    "sg:postcode":"6010",
    "sg:province":"Luzern",
    "wof:name":"Katzenbalg Ag",
    "wof:placetype":"venue"
},
  "geometry": {"coordinates":[8.2707843781,47.02602005],"type":"Point"}
}