{
  "type": "Feature",
  "properties": {
    "iso:country":"CH",
    "sg:address":"Bahnhofstrasse 19",
    "sg:city":"Subingen",
    "sg:classifiers":[
        {
            "category":"Insurance",
            "subcategory":"Insurance Agent",
            "type":"Services"
        }
    ],
    "sg:phone":"+41 32 614 16 95",
    "sg:postcode":"4553",
    "sg:province":"Solothurn",
    "sg:tags":[
        "versicherungsagenturen",
        "-broker"
    ],
    "wof:name":"Fritz Fankhauser Lokalagentur National Versich.",
    "wof:placetype":"venue"
},
  "geometry": {"coordinates":[7.6123528481,47.1930923462],"type":"Point"}
}