{
  "type": "Feature",
  "properties": {
    "iso:country":"CH",
    "sg:address":"Sonnenhof 1",
    "sg:city":"B\u00fclach",
    "sg:orig_category":"Detailhandel mit Brot, Back U S\u00fcsswaren",
    "sg:phone":"+41 18863135",
    "sg:postcode":"8180",
    "sg:province":"Z\u00fcrich",
    "wof:name":"Ren\u00e9 Fleischli B\u00e4ckerei-konditorei",
    "wof:placetype":"venue"
},
  "geometry": {"coordinates":[8.540528,47.52177],"type":"Point"}
}