{
  "type": "Feature",
  "properties": {
    "iso:country":"CH",
    "sg:address":"Turnhallestrasse 4",
    "sg:city":"Luterbach",
    "sg:orig_category":"Primarschulen",
    "sg:phone":"+41 32 682 21 51",
    "sg:postcode":"4542",
    "sg:province":"Solothurn",
    "wof:name":"Primarschule",
    "wof:placetype":"venue"
},
  "geometry": {"coordinates":[7.5847511292,47.2144393921],"type":"Point"}
}