{
  "type": "Feature",
  "properties": {
    "iso:country":"CH",
    "sg:address":"Reinacherstrasse 55",
    "sg:city":"Basel",
    "sg:orig_category":"Detailhandel mit Waren verschiedener Art, Hauptrichtung Nahrungsmittel Sonstiger Detailhandel mit Me",
    "sg:phone":"+41 21 632 97 31",
    "sg:postcode":"4053",
    "sg:province":"Basel-Stadt",
    "wof:name":"Migros M\u00e9tropole Renens",
    "wof:placetype":"venue"
},
  "geometry": {"coordinates":[6.5807681084,46.5384216309],"type":"Point"}
}