{
  "type": "Feature",
  "properties": {
    "iso:country":"CH",
    "sg:address":"Bahnhofstrasse 105",
    "sg:city":"Niederbuchsiten",
    "sg:orig_category":"Verwertung von Milch",
    "sg:postcode":"4626",
    "sg:province":"Solothurn",
    "wof:name":"Milchgenossenschaft Niederbuchsiten",
    "wof:placetype":"venue"
},
  "geometry": {"coordinates":[7.7718029022,47.2997512817],"type":"Point"}
}