{
  "type": "Feature",
  "properties": {
    "iso:country":"CH",
    "sg:address":"Kantonsstrasse 38 3930 Visp. Postfach",
    "sg:city":"Visp",
    "sg:orig_category":"Herstellung von Anstrichmitteln, Druckfarben U Kitten Herstellung von sonstigen organischen Grundsto",
    "sg:phone":"+41 26 913 51 11",
    "sg:postcode":"3930",
    "sg:province":"Valais",
    "wof:name":"Verniplast Ag",
    "wof:placetype":"venue"
},
  "geometry": {"coordinates":[7.0450839996,46.6152114868],"type":"Point"}
}