{
  "type": "Feature",
  "properties": {
    "iso:country":"CH",
    "sg:address":"Im Halbiacker 5a",
    "sg:city":"R\u00e4terschen",
    "sg:classifiers":[
        {
            "category":"Home & Garden",
            "subcategory":"Building Materials",
            "type":"Retail Goods"
        }
    ],
    "sg:phone":"+41 22 796 33 11",
    "sg:postcode":"8352",
    "sg:province":"Z\u00fcrich",
    "sg:tags":[
        "current",
        "meter"
    ],
    "wof:name":"Actaris Sa",
    "wof:placetype":"venue"
},
  "geometry": {"coordinates":[6.10329,46.206078],"type":"Point"}
}