{
  "type": "Feature",
  "properties": {
    "iso:country":"CH",
    "sg:address":"Visura 235",
    "sg:city":"Trin",
    "sg:orig_category":"Sportvereine Ski",
    "sg:phone":"+41 81 635 15 10",
    "sg:postcode":"7014",
    "sg:province":"Graubunden",
    "wof:name":"Skiclub Trin",
    "wof:placetype":"venue"
},
  "geometry": {"coordinates":[9.3629713058,46.8291740417],"type":"Point"}
}