{
  "type": "Feature",
  "properties": {
    "iso:country":"CH",
    "sg:address":"Centralstrasse 11",
    "sg:city":"Sursee",
    "sg:orig_category":"Fachdetailhandel in Verkaufsr\u00e4umen",
    "sg:phone":"+41 41 921 11 33",
    "sg:postcode":"6210",
    "sg:province":"Luzern",
    "wof:name":"Blumenwerkstatt Helfenstein Bernadette",
    "wof:placetype":"venue"
},
  "geometry": {"coordinates":[8.1060752869,47.1713638306],"type":"Point"}
}