{
  "type": "Feature",
  "properties": {
    "iso:country":"CH",
    "sg:address":"Rue Des P\u00e2quis 17",
    "sg:city":"Gen\u00e8ve",
    "sg:orig_category":"Detailhandel mit Brot, Back U S\u00fcsswaren",
    "sg:phone":"+41 71 622 71 89",
    "sg:postcode":"1201",
    "sg:province":"Gen\u00e8ve",
    "wof:name":"Strassmann Fritz Ag",
    "wof:placetype":"venue"
},
  "geometry": {"coordinates":[9.138185,47.566669],"type":"Point"}
}