{
  "type": "Feature",
  "properties": {
    "iso:country":"CH",
    "sg:address":"J.-h.-pestalozzi-allee 80 2500 Biel/bienne. Postfach",
    "sg:city":"Biel/bienne",
    "sg:orig_category":"Schreib U \u00dcbersetzungsb\u00fcros",
    "sg:phone":"+41 32 365 50 81",
    "sg:postcode":"2503",
    "sg:province":"Bern",
    "wof:name":"Dalcher's Allan English Language Interface",
    "wof:placetype":"venue"
},
  "geometry": {"coordinates":[7.2899799347,47.1467399597],"type":"Point"}
}