{
  "type": "Feature",
  "properties": {
    "iso:country":"CH",
    "sg:address":"Strickerstrasse 3",
    "sg:city":"Winterthur",
    "sg:orig_category":"Detailhandel mit Waren verschiedener Art, Hauptrichtung Nahrungsmittel",
    "sg:phone":"+41 52 202 12 55",
    "sg:postcode":"8400",
    "sg:province":"Z\u00fcrich",
    "wof:name":"Denner Top Superdiscount",
    "wof:placetype":"venue"
},
  "geometry": {"coordinates":[8.7202596664,47.4992370605],"type":"Point"}
}