{
  "type": "Feature",
  "properties": {
    "iso:country":"CH",
    "sg:address":"Mittelstrasse 26",
    "sg:city":"Steffisburg",
    "sg:orig_category":"Non-Classified Establishments",
    "sg:postcode":"3613",
    "sg:province":"Bern",
    "wof:name":"Cosmos Finanz Ag",
    "wof:placetype":"venue"
},
  "geometry": {"coordinates":[7.6195921898,46.7656860352],"type":"Point"}
}