{
  "type": "Feature",
  "properties": {
    "iso:country":"CH",
    "sg:address":"Uhlandstrasse 8",
    "sg:city":"Basel",
    "sg:orig_category":"Sonstige Aktivit\u00e4ten der nicht-\u00e4rztlichen Medizinalberufe",
    "sg:phone":"+41 61 331 91 69",
    "sg:postcode":"4053",
    "sg:province":"Basel-Stadt",
    "wof:name":"Sarah Ruth Buser Atemtherapie",
    "wof:placetype":"venue"
},
  "geometry": {"coordinates":[7.5968699455,47.5436515808],"type":"Point"}
}