{
  "type": "Feature",
  "properties": {
    "addr:full":"Rue Centrale 14 1350 Orbe. Postfach Orbe Vaud 1350",
    "addr:housenumber":"14",
    "addr:postcode":"1350 orbe. postfach;1350",
    "addr:street":"Rue Centrale",
    "iso:country":"CH",
    "sg:address":"Rue Centrale 14 1350 Orbe. Postfach",
    "sg:city":"Orbe",
    "sg:orig_category":"Detailhandel mit B\u00fcchern Detailhandel mit Schreib U Papeteriewaren",
    "sg:phone":"+41 24 441 12 77",
    "sg:postcode":"1350",
    "sg:province":"Vaud",
    "wof:name":"Schaer Librairie-papeterie Sa",
    "wof:placetype":"venue"
},
  "geometry": {"coordinates":[6.532178,46.72327],"type":"Point"}
}