{
  "type": "Feature",
  "properties": {
    "iso:country":"CH",
    "sg:address":"Sebleten 685 4717 M\u00fcmliswil. Postfach 121",
    "sg:city":"M\u00fcmliswil",
    "sg:orig_category":"Verwertung von Milch",
    "sg:postcode":"4717",
    "sg:province":"Solothurn",
    "wof:name":"K\u00e4sereigenossenschaft M\u00fcmliswil",
    "wof:placetype":"venue"
},
  "geometry": {"coordinates":[7.716509819,47.3465957642],"type":"Point"}
}