{
  "type": "Feature",
  "properties": {
    "iso:country":"CH",
    "sg:address":"Via Fabrizia 21",
    "sg:city":"Giubiasco",
    "sg:orig_category":"Arztpraxen",
    "sg:phone":"+41 91 857 44 22",
    "sg:postcode":"6512",
    "sg:province":"Ticino",
    "wof:name":"Dott.med.pietro Duchini Medico Generico Fmh",
    "wof:placetype":"venue"
},
  "geometry": {"coordinates":[9.020206,46.181026],"type":"Point"}
}