{
  "type": "Feature",
  "properties": {
    "iso:country":"CH",
    "sg:address":"R\u00fctiweg 2 8803 R\u00fcschlikon. Postfach",
    "sg:city":"R\u00fcschlikon",
    "sg:orig_category":"Unternehmensberatung",
    "sg:postcode":"8803",
    "sg:province":"Z\u00fcrich",
    "wof:name":"Meier Ulrich Consulting",
    "wof:placetype":"venue"
},
  "geometry": {"coordinates":[8.5563144684,47.3023529053],"type":"Point"}
}