{
  "type": "Feature",
  "properties": {
    "iso:country":"CH",
    "sg:address":"Tufertschwil 20",
    "sg:city":"L\u00fctisburg",
    "sg:classifiers":[
        {
            "category":"Travel",
            "subcategory":"Hotels & Motels",
            "type":"Entertainment"
        }
    ],
    "sg:phone":"+41 71 931 11 85",
    "sg:postcode":"9604",
    "sg:province":"St. Gallen",
    "sg:tags":[
        "hotels",
        "mit",
        "restaurant"
    ],
    "wof:name":"Landgasthof R\u00f6ssli Thalmann Magnus",
    "wof:placetype":"venue"
},
  "geometry": {"coordinates":[9.0956697464,47.3934211731],"type":"Point"}
}