{
  "type": "Feature",
  "properties": {
    "iso:country":"CH",
    "sg:address":"Luzernerstrasse 110",
    "sg:city":"Littau",
    "sg:orig_category":"Detailhandel mit Fleisch U Fleischwaren",
    "sg:phone":"+41 41 250 52 52",
    "sg:postcode":"6014",
    "sg:province":"Luzern",
    "wof:name":"Littauer-metzg Hans-j\u00f6rg M\u00fcller",
    "wof:placetype":"venue"
},
  "geometry": {"coordinates":[8.2669582367,47.050201416],"type":"Point"}
}