{
  "type": "Feature",
  "properties": {
    "iso:country":"CH",
    "sg:address":"Unterer Aareweg 1",
    "sg:city":"Lyss",
    "sg:orig_category":"Lichtpause U Reprografiebetriebe Schnelldruck U Kopierservice",
    "sg:phone":"+41 32 384 04 04",
    "sg:postcode":"3250",
    "sg:province":"Bern",
    "wof:name":"Copytrend",
    "wof:placetype":"venue"
},
  "geometry": {"coordinates":[7.298169136,47.0805969238],"type":"Point"}
}