{
  "type": "Feature",
  "properties": {
    "iso:country":"CH",
    "sg:address":"Forte Via Al 2",
    "sg:city":"Lugano",
    "sg:orig_category":"Herstellung von medizinischen U chirurgischen Ger\u00e4ten sowie orthop\u00e4dischen Vorrichtungen",
    "sg:phone":"+41 26 674 33 78",
    "sg:postcode":"6900",
    "sg:province":"Ticino",
    "wof:name":"Tr R\u00f6ntgen Ag",
    "wof:placetype":"venue"
},
  "geometry": {"coordinates":[7.140021801,46.8987121582],"type":"Point"}
}