{
  "type": "Feature",
  "properties": {
    "addr:full":"Z\u00fcrichstrasse 53 Oftringen Aargau 4665",
    "addr:housenumber":"53",
    "addr:postcode":"4665",
    "addr:street":"Zuerichstrasse",
    "iso:country":"CH",
    "sg:address":"Z\u00fcrichstrasse 53",
    "sg:city":"Oftringen",
    "sg:orig_category":"Bauspenglerei Zimmerei, Dachdeckerei, Bauspenglerei U Abdichtung",
    "sg:phone":"+41 62 797 16 57",
    "sg:postcode":"4665",
    "sg:province":"Aargau",
    "wof:name":"Werder Roland",
    "wof:placetype":"venue"
},
  "geometry": {"coordinates":[7.930653,47.312572],"type":"Point"}
}