{
  "type": "Feature",
  "properties": {
    "iso:country":"CH",
    "sg:address":"Kornquaderweg 8",
    "sg:city":"Chur",
    "sg:orig_category":"Sanit\u00e4r U Heizungsinstallation Sanit\u00e4rinstallation",
    "sg:phone":"+41 81 252 10 12",
    "sg:postcode":"7000",
    "sg:province":"Graubunden",
    "wof:name":"Hans Kessler San.installationen & Heizungen",
    "wof:placetype":"venue"
},
  "geometry": {"coordinates":[9.5203580856,46.8462257385],"type":"Point"}
}