{
  "type": "Feature",
  "properties": {
    "iso:country":"CH",
    "sg:address":"7077 Valbella. Postfach",
    "sg:city":"Valbella",
    "sg:orig_category":"Museen",
    "sg:phone":"+41 81 413 24 84",
    "sg:postcode":"7077",
    "sg:province":"Graubunden",
    "wof:name":"Wintersport-museum Davos",
    "wof:placetype":"venue"
},
  "geometry": {"coordinates":[9.8206195831,46.7934570312],"type":"Point"}
}