{
  "type": "Feature",
  "properties": {
    "iso:country":"CH",
    "sg:address":"Folla Vicolo Dei",
    "sg:city":"Chiasso",
    "sg:orig_category":"Reinigungsgewerbe",
    "sg:postcode":"6830",
    "sg:province":"Ticino",
    "wof:name":"Manuedil Sa",
    "wof:placetype":"venue"
},
  "geometry": {"coordinates":[9.0313053131,45.8347244263],"type":"Point"}
}