{
  "type": "Feature",
  "properties": {
    "iso:country":"CH",
    "sg:address":"Chemin St-hubert 5 1950 Sitten. Postfach",
    "sg:city":"Sion",
    "sg:orig_category":"Softwareentwicklung U beratung",
    "sg:postcode":"1951",
    "sg:province":"Valais",
    "wof:name":"Biodietetics Sa",
    "wof:placetype":"venue"
},
  "geometry": {"coordinates":[7.3512010574,46.2248268127],"type":"Point"}
}