{
  "type": "Feature",
  "properties": {
    "iso:country":"CH",
    "sg:address":"Arnikaweg 21",
    "sg:city":"Chur",
    "sg:orig_category":"Architektur U Ingenieurb\u00fcros",
    "sg:phone":"+41 81 250 31 31",
    "sg:postcode":"7000",
    "sg:province":"Graubunden",
    "wof:name":"Gruber Bauorganisation",
    "wof:placetype":"venue"
},
  "geometry": {"coordinates":[9.522863,46.860992],"type":"Point"}
}