{
  "type": "Feature",
  "properties": {
    "iso:country":"CH",
    "sg:address":"Hauptstrasse 78-80",
    "sg:city":"Muttenz",
    "sg:orig_category":"Detailhandel mit Radio U Fernsehger\u00e4ten Detailhandel mit fotografischen Artikeln",
    "sg:phone":"+41 61 463 94 31",
    "sg:postcode":"4132",
    "sg:province":"Basel-Landschaft",
    "wof:name":"Interdiscount Ag Hi-fi Video Photo Radio",
    "wof:placetype":"venue"
},
  "geometry": {"coordinates":[7.6478757858,47.5274009705],"type":"Point"}
}