{
  "type": "Feature",
  "properties": {
    "iso:country":"CH",
    "sg:address":"Vorderhof 172",
    "sg:city":"Untereggen",
    "sg:orig_category":"Einbau von Schreinerwaren Verarbeitung U Veredlung von Flachglas",
    "sg:phone":"+41 71 866 23 60",
    "sg:postcode":"9033",
    "sg:province":"St. Gallen",
    "wof:name":"Ihasz Heinz Montagen",
    "wof:placetype":"venue"
},
  "geometry": {"coordinates":[9.4517736435,47.4559745789],"type":"Point"}
}