{
  "type": "Feature",
  "properties": {
    "iso:country":"CH",
    "sg:address":"Cassarinetta Via 10",
    "sg:city":"Lugano",
    "sg:orig_category":"Mit dem Versicherungsgewerbe verbundene T\u00e4tigkeiten",
    "sg:postcode":"6900",
    "sg:province":"Ticino",
    "wof:name":"Duemila Beratungsstelle F\u00fcr Versicherungsfragen Ag",
    "wof:placetype":"venue"
},
  "geometry": {"coordinates":[8.9419708252,45.9932861328],"type":"Point"}
}