{
  "type": "Feature",
  "properties": {
    "iso:country":"CH",
    "sg:address":"R\u00fctirain 3f",
    "sg:city":"Zwillikon",
    "sg:orig_category":"Herstellung von Teppichen",
    "sg:postcode":"8909",
    "sg:province":"Z\u00fcrich",
    "wof:name":"Boden Design & Blitzsauber, Altherr",
    "wof:placetype":"venue"
},
  "geometry": {"coordinates":[8.4292564392,47.2873077393],"type":"Point"}
}