{
  "type": "Feature",
  "properties": {
    "iso:country":"CH",
    "sg:address":"6122",
    "sg:city":"Menznau",
    "sg:orig_category":"Vorschulen, Kinderg\u00e4rten",
    "sg:phone":"+41 41 480 41 43",
    "sg:postcode":"6122",
    "sg:province":"Luzern",
    "wof:name":"Kindergarten",
    "wof:placetype":"venue"
},
  "geometry": {"coordinates":[8.0390977859,47.082950592],"type":"Point"}
}