{
  "type": "Feature",
  "properties": {
    "iso:country":"CH",
    "sg:address":"Adlerstrasse 4",
    "sg:city":"Siebnen",
    "sg:orig_category":"Herstellung von medizinischen U chirurgischen Ger\u00e4ten sowie orthop\u00e4dischen Vorrichtungen Zahntechnis",
    "sg:phone":"+41 55 440 41 12",
    "sg:postcode":"8854",
    "sg:province":"Schwyz",
    "wof:name":"Kurt L\u00e4uffer Dental-labor Ag",
    "wof:placetype":"venue"
},
  "geometry": {"coordinates":[8.8996591568,47.1757392883],"type":"Point"}
}