{
  "type": "Feature",
  "properties": {
    "iso:country":"CH",
    "sg:address":"Chemin Des Pav\u00e9s 8",
    "sg:city":"Peseux",
    "sg:orig_category":"Zimmerei, Dachdeckerei, Bauspenglerei U Abdichtung",
    "sg:phone":"+41 32 731 23 63",
    "sg:postcode":"2034",
    "sg:province":"Neuch\u00e2tel",
    "wof:name":"Vuillemin Fran\u00e7ois",
    "wof:placetype":"venue"
},
  "geometry": {"coordinates":[6.8888411522,46.9886741638],"type":"Point"}
}