{
  "type": "Feature",
  "properties": {
    "iso:country":"CH",
    "sg:address":"Ai Gagiurasc 7",
    "sg:city":"Camorino",
    "sg:orig_category":"Unclassifiable Establishments",
    "sg:postcode":"6528",
    "sg:province":"Ticino",
    "wof:name":"Medaglia & Moro Sa Imp.sanitari & Riscaldamenti",
    "wof:placetype":"venue"
},
  "geometry": {"coordinates":[9.0038290024,46.168006897],"type":"Point"}
}