{
  "type": "Feature",
  "properties": {
    "iso:country":"CH",
    "sg:address":"Pulverm\u00fchlestrasse 41",
    "sg:city":"Chur",
    "sg:orig_category":"Sonstige Aktivit\u00e4ten der nicht-\u00e4rztlichen Medizinalberufe",
    "sg:phone":"+41 81 284 79 72",
    "sg:postcode":"7000",
    "sg:province":"Graubunden",
    "wof:name":"Hanna Danz Atemtherapie",
    "wof:placetype":"venue"
},
  "geometry": {"coordinates":[9.5153188705,46.8521881104],"type":"Point"}
}