{
  "type": "Feature",
  "properties": {
    "iso:country":"CH",
    "sg:address":"Route De Soleure 10",
    "sg:city":"St-blaise",
    "sg:orig_category":"Visions And Solutions For Processes Of Change",
    "sg:phone":"+41 32 753 13 33",
    "sg:postcode":"2072",
    "sg:province":"Neuch\u00e2tel",
    "wof:name":"Microcim Sa",
    "wof:placetype":"venue"
},
  "geometry": {"coordinates":[6.9925022125,47.0146636963],"type":"Point"}
}