{
  "type": "Feature",
  "properties": {
    "iso:country":"CH",
    "sg:address":"M\u00fchlestrasse 2p",
    "sg:city":"Herisau",
    "sg:orig_category":"Maler U Glasergewerbe Malerei",
    "sg:phone":"+41 71 352 53 43",
    "sg:postcode":"9100",
    "sg:province":"Appenzell Ausserrhoden",
    "wof:name":"Malerei Geisser Ag",
    "wof:placetype":"venue"
},
  "geometry": {"coordinates":[9.2743377686,47.3887252808],"type":"Point"}
}