{
  "type": "Feature",
  "properties": {
    "iso:country":"CH",
    "sg:address":"Scheurenstrasse 14",
    "sg:city":"Dotzigen",
    "sg:orig_category":"Unclassifiable Establishments",
    "sg:postcode":"3293",
    "sg:province":"Bern",
    "wof:name":"Lico Gmbh",
    "wof:placetype":"venue"
},
  "geometry": {"coordinates":[7.3351511955,47.1207084656],"type":"Point"}
}