{
  "type": "Feature",
  "properties": {
    "iso:country":"CH",
    "sg:address":"Bleicheweg 6",
    "sg:city":"Goldach",
    "sg:classifiers":[
        {
            "category":"Recreation",
            "subcategory":"Boat Charter",
            "type":"Entertainment"
        }
    ],
    "sg:phone":"+41 71 841 11 46",
    "sg:postcode":"9403",
    "sg:province":"St. Gallen",
    "sg:tags":[
        "engine"
    ],
    "wof:name":"Morsag Ag Motorentechnologie",
    "wof:placetype":"venue"
},
  "geometry": {"coordinates":[9.474299,47.485378],"type":"Point"}
}