{
  "type": "Feature",
  "properties": {
    "iso:country":"CH",
    "sg:address":"Eisenbahnstrasse 16 D",
    "sg:city":"Thun",
    "sg:orig_category":"P\u00e9dicure",
    "sg:phone":"+41 55 210 80 60",
    "sg:postcode":"3604",
    "sg:province":"Bern",
    "wof:name":"Harry Schnurrenberger P\u00e9dicure",
    "wof:placetype":"venue"
},
  "geometry": {"coordinates":[8.820098877,47.2289581299],"type":"Point"}
}