{
  "type": "Feature",
  "properties": {
    "iso:country":"CH",
    "sg:address":"Steinenvorstadt 38 4051 Basel. Postfach",
    "sg:city":"Basel",
    "sg:orig_category":"Grosshandel mit sonstigen Maschinen U Ausr\u00fcstungen f\u00fcr Industrie, Handel U Schiffahrt",
    "sg:postcode":"4051",
    "sg:province":"Basel-Stadt",
    "wof:name":"Eta-services Taiani Handel Mit Zubeh\u00f6r F\u00fcr Die Papier, Chemie, Lebensmittelindustrie Usw",
    "wof:placetype":"venue"
},
  "geometry": {"coordinates":[7.5882191658,47.5525932312],"type":"Point"}
}