{
  "type": "Feature",
  "properties": {
    "addr:full":"Widackerstrasse 4 Egerkingen Solothurn 4622",
    "addr:housenumber":"4",
    "addr:postcode":"4622",
    "addr:street":"Widackerstrasse",
    "iso:country":"CH",
    "sg:address":"Widackerstrasse 4",
    "sg:city":"Egerkingen",
    "sg:orig_category":"Arbeitnehmerverb\u00e4nde",
    "sg:postcode":"4622",
    "sg:province":"Solothurn",
    "wof:name":"Verband Schweiz.zollbeamter",
    "wof:placetype":"venue"
},
  "geometry": {"coordinates":[9.45011,47.168571],"type":"Point"}
}