{
  "type": "Feature",
  "properties": {
    "iso:country":"CH",
    "sg:address":"Langenthalstrasse 5",
    "sg:city":"Aarwangen",
    "sg:orig_category":"Nationale Postdienste",
    "sg:phone":"+41 19351305",
    "sg:postcode":"4912",
    "sg:province":"Bern",
    "wof:name":"Die Schweizerische Post",
    "wof:placetype":"venue"
},
  "geometry": {"coordinates":[8.7583827972,47.3051719666],"type":"Point"}
}