{
  "type": "Feature",
  "properties": {
    "iso:country":"CH",
    "sg:address":"Alpenstrasse 9",
    "sg:city":"Zug",
    "sg:orig_category":"Vermietung U Verpachtung von eigenen Immobilien",
    "sg:postcode":"6300",
    "sg:province":"Zug",
    "wof:name":"Etrag Immobilien Ag",
    "wof:placetype":"venue"
},
  "geometry": {"coordinates":[8.5144662857,47.1723403931],"type":"Point"}
}