{
  "type": "Feature",
  "properties": {
    "iso:country":"CH",
    "sg:address":"Viale Stefano Franscini 22",
    "sg:city":"Lugano",
    "sg:orig_category":"Vermietung U Verpachtung von eigenen Immobilien",
    "sg:postcode":"6900",
    "sg:province":"Ticino",
    "wof:name":"Katco Kontrol And Trading Company Sa",
    "wof:placetype":"venue"
},
  "geometry": {"coordinates":[8.9541196823,46.0100631714],"type":"Point"}
}