{
  "type": "Feature",
  "properties": {
    "iso:country":"CH",
    "sg:address":"Hubel 170a",
    "sg:city":"Sch\u00f6ftland",
    "sg:orig_category":"Stukkateurgewerbe, Gipserei U Verputzerei",
    "sg:postcode":"5040",
    "sg:province":"Aargau",
    "wof:name":"Cescato Ennio",
    "wof:placetype":"venue"
},
  "geometry": {"coordinates":[8.0504999161,47.3001098633],"type":"Point"}
}