{
  "type": "Feature",
  "properties": {
    "iso:country":"CH",
    "sg:address":"Kastelsstrasse 20",
    "sg:city":"Grenchen",
    "sg:orig_category":"Kunststoff-Produkte",
    "sg:phone":"+41 32 653 39 57",
    "sg:postcode":"2540",
    "sg:province":"Solothurn",
    "wof:name":"Jg-kunststoffe, Von Gunten J\u00fcrg",
    "wof:placetype":"venue"
},
  "geometry": {"coordinates":[7.3994069099,47.1960792542],"type":"Point"}
}