{
  "type": "Feature",
  "properties": {
    "iso:country":"CH",
    "sg:address":"Rue De L'abb\u00e9-bovet 12 1700 Fribourg Case Postale 286",
    "sg:city":"Fribourg",
    "sg:orig_category":"Grosshandel mit Textilien",
    "sg:phone":"+41 26 422 41 27",
    "sg:postcode":"1701",
    "sg:province":"Fribourg",
    "wof:name":"Croenert Sa",
    "wof:placetype":"venue"
},
  "geometry": {"coordinates":[7.1550917625,46.8044662476],"type":"Point"}
}