{
  "type": "Feature",
  "properties": {
    "iso:country":"CH",
    "sg:address":"Spalenring 40",
    "sg:city":"Basel",
    "sg:orig_category":"Non-Classified Establishments",
    "sg:phone":"+41 61 383 20 35",
    "sg:postcode":"4055",
    "sg:province":"Basel-Stadt",
    "wof:name":"Grafik Atelier Sch\u00f6nholzer Erwin",
    "wof:placetype":"venue"
},
  "geometry": {"coordinates":[7.5740990639,47.5598640442],"type":"Point"}
}