{
  "type": "Feature",
  "properties": {
    "iso:country":"CH",
    "sg:address":"H\u00f6heweg 2 3800 Interlaken. Postfach 309",
    "sg:city":"Interlaken",
    "sg:orig_category":"Personenbef\u00f6rderung im Linienverkehr zu Land",
    "sg:phone":"+41 33 823 14 44",
    "sg:postcode":"3800",
    "sg:province":"Bern",
    "wof:name":"Schilthornbahn Ag",
    "wof:placetype":"venue"
},
  "geometry": {"coordinates":[7.8552260399,46.6851463318],"type":"Point"}
}