{
  "type": "Feature",
  "properties": {
    "iso:country":"CH",
    "sg:address":"Rue De L'h\u00f4tel-de-ville 12",
    "sg:city":"Moutier",
    "sg:orig_category":"Detailhandel mit Radio U Fernsehger\u00e4ten Herstellung von sonstigen elektrischen Ausr\u00fcstungen",
    "sg:phone":"+41 32 493 23 08",
    "sg:postcode":"2740",
    "sg:province":"Bern",
    "wof:name":"H\u00e4nzi Electronique S\u00e0rl",
    "wof:placetype":"venue"
},
  "geometry": {"coordinates":[7.3704447746,47.2789154053],"type":"Point"}
}