{
  "type": "Feature",
  "properties": {
    "iso:country":"CH",
    "sg:address":"R\u00f6schenzstrasse 49 4242 Laufen. Postfach",
    "sg:city":"Laufen",
    "sg:orig_category":"Architektur U Ingenieurb\u00fcros Architekturb\u00fcros",
    "sg:phone":"+41 61 761 58 22",
    "sg:postcode":"4242",
    "sg:province":"Basel-Landschaft",
    "wof:name":"Scheidegger Daniel, Architekturb\u00fcro",
    "wof:placetype":"venue"
},
  "geometry": {"coordinates":[7.495557,47.421757],"type":"Point"}
}