{
  "type": "Feature",
  "properties": {
    "iso:country":"CH",
    "sg:address":"Fatiostrasse 29",
    "sg:city":"Basel",
    "sg:orig_category":"Malerei",
    "sg:phone":"+41 61 321 05 80",
    "sg:postcode":"4056",
    "sg:province":"Basel-Stadt",
    "wof:name":"Klauser Heinz Ag Maleratelier",
    "wof:placetype":"venue"
},
  "geometry": {"coordinates":[7.5796089172,47.5668487549],"type":"Point"}
}