{
  "type": "Feature",
  "properties": {
    "iso:country":"CH",
    "sg:address":"Watterstrasse 10",
    "sg:city":"Regensdorf",
    "sg:orig_category":"Fachdetailhandel in Verkaufsr\u00e4umen",
    "sg:postcode":"8105",
    "sg:province":"Z\u00fcrich",
    "wof:name":"Meier B., Bijoutier.",
    "wof:placetype":"venue"
},
  "geometry": {"coordinates":[8.4659729004,47.4302177429],"type":"Point"}
}