{
  "type": "Feature",
  "properties": {
    "iso:country":"CH",
    "sg:address":"2345",
    "sg:city":"Chaux-des-breuleux",
    "sg:orig_category":"Gemeindeverwaltungen",
    "sg:phone":"+41 21 907 80 30",
    "sg:postcode":"2345",
    "sg:province":"Jura",
    "wof:name":"Administration Communale De La Rogivue",
    "wof:placetype":"venue"
},
  "geometry": {"coordinates":[6.895070076,46.5640983582],"type":"Point"}
}