{
  "type": "Feature",
  "properties": {
    "iso:country":"CH",
    "sg:address":"Giessenweg 17 6403 K\u00fcssnacht Am Rigi. Postfach",
    "sg:city":"Merlischachen",
    "sg:orig_category":"Wirtschaftspr\u00fcfung, Steuerberatung U Treuhand",
    "sg:postcode":"6402",
    "sg:province":"Schwyz",
    "wof:name":"Abc - Benz Andrea Consulting Buchhaltungen, Treuhandgesch\u00e4ft",
    "wof:placetype":"venue"
},
  "geometry": {"coordinates":[8.4387569427,47.0850563049],"type":"Point"}
}