{
  "type": "Feature",
  "properties": {
    "iso:country":"CH",
    "sg:address":"Augartenstrasse",
    "sg:city":"Rheinfelden",
    "sg:classifiers":[
        {
            "category":"Restaurant",
            "type":"Food & Drink"
        }
    ],
    "sg:phone":"+41 61 831 38 83",
    "sg:postcode":"4310",
    "sg:province":"Aargau",
    "wof:name":"Restaurant Weiher",
    "wof:placetype":"venue"
},
  "geometry": {"coordinates":[7.7711510658,47.5479011536],"type":"Point"}
}