{
  "type": "Feature",
  "properties": {
    "iso:country":"CH",
    "sg:address":"Rosenstrasse 5",
    "sg:city":"Feuerthalen",
    "sg:orig_category":"Herstellung von Fahrr\u00e4dern",
    "sg:phone":"+41 79 354 86 12",
    "sg:postcode":"8245",
    "sg:province":"Z\u00fcrich",
    "wof:name":"Ringli Consulting",
    "wof:placetype":"venue"
},
  "geometry": {"coordinates":[8.6466169357,47.6893196106],"type":"Point"}
}