{
  "type": "Feature",
  "properties": {
    "iso:country":"CH",
    "sg:address":"Langendorfstrasse 2",
    "sg:city":"Langendorf",
    "sg:orig_category":"Hardwareberatung Softwareentwicklung U beratung",
    "sg:phone":"+41 32 618 04 34",
    "sg:postcode":"4513",
    "sg:province":"Solothurn",
    "wof:name":"B & G Engineering Ag",
    "wof:placetype":"venue"
},
  "geometry": {"coordinates":[7.5151081085,47.2164840698],"type":"Point"}
}