{
  "type": "Feature",
  "properties": {
    "iso:country":"CH",
    "sg:address":"Blumenstrasse 50 8500 Frauenfeld. Postfach",
    "sg:city":"Frauenfeld",
    "sg:orig_category":"Betrieb von Sportanlagen",
    "sg:phone":"+41 71 626 70 51",
    "sg:postcode":"8500",
    "sg:province":"Thurgau",
    "wof:name":"Genossenschaft Curlinghalle Weinfelden",
    "wof:placetype":"venue"
},
  "geometry": {"coordinates":[8.889745,47.550346],"type":"Point"}
}