{
  "type": "Feature",
  "properties": {
    "iso:country":"CH",
    "sg:address":"Wiesenstrasse 33",
    "sg:city":"Schlieren",
    "sg:orig_category":"Unternehmensberatung",
    "sg:phone":"+41 17309858",
    "sg:postcode":"8952",
    "sg:province":"Z\u00fcrich",
    "wof:name":"Hipol Beratungs-ag",
    "wof:placetype":"venue"
},
  "geometry": {"coordinates":[8.4383916855,47.3990936279],"type":"Point"}
}