{
  "type": "Feature",
  "properties": {
    "iso:country":"CH",
    "sg:address":"M\u00fchlegasse 18",
    "sg:city":"Baar",
    "sg:orig_category":"Non-Classified Establishments",
    "sg:postcode":"6340",
    "sg:province":"Zug",
    "wof:name":"Continental Grafix Limited, Hong Kong, Zweigniederlassung Baar",
    "wof:placetype":"venue"
},
  "geometry": {"coordinates":[8.5264730453,47.1992111206],"type":"Point"}
}