{
  "type": "Feature",
  "properties": {
    "iso:country":"CH",
    "sg:address":"Madonnetta Via 27",
    "sg:city":"Lugano",
    "sg:orig_category":"Interessenvertretungen",
    "sg:postcode":"6900",
    "sg:province":"Ticino",
    "wof:name":"Associazione Rws Robot Wars Swiss",
    "wof:placetype":"venue"
},
  "geometry": {"coordinates":[8.9596290588,46.0113182068],"type":"Point"}
}