{
  "type": "Feature",
  "properties": {
    "iso:country":"CH",
    "sg:address":"L\u00f6renstrasse 38",
    "sg:city":"Flawil",
    "sg:orig_category":"Detailhandel mit elektrischen Haushalts-,Radio U Fernsehger\u00e4ten sowie Musikinstrumenten Grosshandel ",
    "sg:phone":"+41 61 702 11 44",
    "sg:postcode":"9230",
    "sg:province":"St. Gallen",
    "wof:name":"Mpc Rec. Gmbh",
    "wof:placetype":"venue"
},
  "geometry": {"coordinates":[7.6210670471,47.4754219055],"type":"Point"}
}