{
  "type": "Feature",
  "properties": {
    "iso:country":"CH",
    "sg:address":"Avenue Benjamin-constant 5 1003 Lausanne. Postfach",
    "sg:city":"Lausanne",
    "sg:orig_category":"HOTELS: MIT RESTAURANT Kongress- and Tagungshotels mit Restaurant",
    "sg:phone":"+41 21 944 96 96",
    "sg:postcode":"1002",
    "sg:province":"Vaud",
    "wof:name":"H\u00f4tel De La Vieille Tour",
    "wof:placetype":"venue"
},
  "geometry": {"coordinates":[6.856194973,46.4535942078],"type":"Point"}
}