{
  "type": "Feature",
  "properties": {
    "iso:country":"CH",
    "sg:address":"Sch\u00e4nzlihalde 11 3013 Bern. Postfach",
    "sg:city":"Bern",
    "sg:orig_category":"Pensionskassen",
    "sg:phone":"+41 31 335 33 33",
    "sg:postcode":"3005",
    "sg:province":"Bern",
    "wof:name":"F\u00fcrsorgestiftung Der Klinik Beau-site Stiftung Zugunsten Der Schwestern U. Angestellten",
    "wof:placetype":"venue"
},
  "geometry": {"coordinates":[7.4486050606,46.9527587891],"type":"Point"}
}