{
  "type": "Feature",
  "properties": {
    "iso:country":"CH",
    "sg:address":"Furkastrasse 71",
    "sg:city":"Basel",
    "sg:classifiers":[
        {
            "category":"Home & Garden",
            "subcategory":"Carpets & Floor Coverings",
            "type":"Retail Goods"
        }
    ],
    "sg:phone":"+41 61 301 14 34",
    "sg:postcode":"4054",
    "sg:province":"Basel-Stadt",
    "sg:tags":[
        "grout",
        "adhesive",
        "tiles"
    ],
    "wof:name":"F. Koch Ag",
    "wof:placetype":"venue"
},
  "geometry": {"coordinates":[7.561294,47.549042],"type":"Point"}
}