{
  "type": "Feature",
  "properties": {
    "iso:country":"CH",
    "sg:address":"Chemin De Montelly 13bis",
    "sg:city":"Lausanne",
    "sg:orig_category":"Primarschulen",
    "sg:phone":"+41 26 660 56 07",
    "sg:postcode":"1007",
    "sg:province":"Vaud",
    "wof:name":"Ecole Primaire Montheron",
    "wof:placetype":"venue"
},
  "geometry": {"coordinates":[6.640250206,46.5850296021],"type":"Point"}
}