{
  "type": "Feature",
  "properties": {
    "iso:country":"CH",
    "sg:address":"Breitenrainstrasse 31",
    "sg:city":"Bern",
    "sg:orig_category":"Sportschulen Fern\u00f6stliche Kampfsportarten Sportvereine Judo and Karate",
    "sg:phone":"+41 31 331 26 98",
    "sg:postcode":"3013",
    "sg:province":"Bern",
    "wof:name":"Kinderjudoschule Bern",
    "wof:placetype":"venue"
},
  "geometry": {"coordinates":[7.4507918358,46.9573135376],"type":"Point"}
}