{
  "type": "Feature",
  "properties": {
    "iso:country":"CH",
    "sg:address":"Rosengasse 7",
    "sg:city":"Z\u00fcrich",
    "sg:orig_category":"Herstellung von sonstigen elektrischen Ausr\u00fcstungen",
    "sg:postcode":"8001",
    "sg:province":"Z\u00fcrich",
    "wof:name":"Liaisons Electroniques-m\u00e9caniques Lem Sa, Lem Elmes, Zweigniederlassung Pf\u00e4ffikon",
    "wof:placetype":"venue"
},
  "geometry": {"coordinates":[8.778427124,47.2024307251],"type":"Point"}
}