{
  "type": "Feature",
  "properties": {
    "iso:country":"CH",
    "sg:address":"Hofstr. 30a",
    "sg:city":"Romanshorn",
    "sg:orig_category":"Maschinen-Fabrikation",
    "sg:phone":"+41 79 406 95 05",
    "sg:postcode":"8590",
    "sg:province":"Thurgau",
    "wof:name":"Hug & Jung",
    "wof:placetype":"venue"
},
  "geometry": {"coordinates":[9.3626127243,47.5578651428],"type":"Point"}
}