{
  "type": "Feature",
  "properties": {
    "iso:country":"CH",
    "sg:address":"Wiggis Park",
    "sg:city":"Netstal",
    "sg:orig_category":"Grosshandel mit B\u00fcromaschinen Softwareentwicklung U beratung",
    "sg:phone":"+41 55 645 32 80",
    "sg:postcode":"8754",
    "sg:province":"Glarus",
    "wof:name":"Hcc Hunziker Computer + Consulting Gmbh",
    "wof:placetype":"venue"
},
  "geometry": {"coordinates":[9.057393074,47.0656394958],"type":"Point"}
}