{
  "type": "Feature",
  "properties": {
    "iso:country":"CH",
    "sg:address":"1041",
    "sg:city":"Dommartin",
    "sg:orig_category":"Gemeindeverwaltungen",
    "sg:phone":"+41 21 881 38 58",
    "sg:postcode":"1041",
    "sg:province":"Vaud",
    "wof:name":"Administration Communale De Dommartin",
    "wof:placetype":"venue"
},
  "geometry": {"coordinates":[6.7010231018,46.6474990845],"type":"Point"}
}