{
  "type": "Feature",
  "properties": {
    "iso:country":"CH",
    "sg:address":"Waldmannstrasse 21 3027 Bern. Postfach 280",
    "sg:city":"Bern",
    "sg:orig_category":"Restaurants W\u00e4scherei U chemische Reinigung",
    "sg:phone":"+41 31 992 66 74",
    "sg:postcode":"3027",
    "sg:province":"Bern",
    "wof:name":"W\u00e4scherei Ag Im Tscharnergut",
    "wof:placetype":"venue"
},
  "geometry": {"coordinates":[7.3894572258,46.9480400085],"type":"Point"}
}