{
  "type": "Feature",
  "properties": {
    "iso:country":"CH",
    "sg:address":"Althardstrasse 238 8105 Regensdorf. Postfach 122",
    "sg:city":"Regensdorf",
    "sg:orig_category":"Detailhandel mit elektrischen Haushalts-,Radio U Fernsehger\u00e4ten sowie Musikinstrumenten Grosshandel ",
    "sg:phone":"+41 18400144",
    "sg:postcode":"8105",
    "sg:province":"Z\u00fcrich",
    "wof:name":"Gotham Ag",
    "wof:placetype":"venue"
},
  "geometry": {"coordinates":[8.4631891251,47.4439201355],"type":"Point"}
}