{
  "type": "Feature",
  "properties": {
    "iso:country":"CH",
    "sg:address":"Verbier",
    "sg:city":"Verbier",
    "sg:orig_category":"Unclassifiable Establishments",
    "sg:postcode":"1936",
    "sg:province":"Valais",
    "wof:name":"Marli\u00e9re Christian",
    "wof:placetype":"venue"
},
  "geometry": {"coordinates":[7.2192759514,46.0961456299],"type":"Point"}
}