{
  "type": "Feature",
  "properties": {
    "iso:country":"CH",
    "sg:address":"Via Tuma Platta 13",
    "sg:city":"Domat/ems",
    "sg:orig_category":"Elektroinstallation",
    "sg:phone":"+41 71 655 15 15",
    "sg:postcode":"7013",
    "sg:province":"Graubunden",
    "wof:name":"Gebr. Willi Elektro Ag",
    "wof:placetype":"venue"
},
  "geometry": {"coordinates":[9.0557451248,47.5373420715],"type":"Point"}
}