{
  "type": "Feature",
  "properties": {
    "iso:country":"CH",
    "sg:address":"Chemin Du Pont-de-ville 9",
    "sg:city":"Ch\u00eane-bougeries",
    "sg:orig_category":"Betrieb U technische Hilfsdienste des Kultur U Unterhaltungswesens",
    "sg:postcode":"1224",
    "sg:province":"Gen\u00e8ve",
    "wof:name":"Production Musicale Raymond Marc",
    "wof:placetype":"venue"
},
  "geometry": {"coordinates":[6.191344,46.197254],"type":"Point"}
}