{
  "type": "Feature",
  "properties": {
    "iso:country":"CH",
    "sg:address":"Im Seewadel 3",
    "sg:city":"N\u00fcrensdorf",
    "sg:orig_category":"Innenarchitekturb\u00fcros Innenausbau",
    "sg:phone":"+41 32 342 41 10",
    "sg:postcode":"8309",
    "sg:province":"Z\u00fcrich",
    "wof:name":"Weidmann Gmbh Innenausbau",
    "wof:placetype":"venue"
},
  "geometry": {"coordinates":[7.2518630028,47.1409797668],"type":"Point"}
}