{
  "type": "Feature",
  "properties": {
    "iso:country":"CH",
    "sg:address":"Wilson Quai 45 1201 Gen\u00e8ve. Postfach",
    "sg:city":"Gen\u00e8ve",
    "sg:orig_category":"Finanzierungsinstitutionen",
    "sg:postcode":"1201",
    "sg:province":"Gen\u00e8ve",
    "wof:name":"G & R Finance Sa",
    "wof:placetype":"venue"
},
  "geometry": {"coordinates":[6.1519899368,46.2136878967],"type":"Point"}
}