{
  "type": "Feature",
  "properties": {
    "iso:country":"CH",
    "sg:address":"Rue Du G\u00e9n\u00e9ral-dufour 15",
    "sg:city":"Gen\u00e8ve",
    "sg:orig_category":"Softwareentwicklung U beratung",
    "sg:postcode":"1204",
    "sg:province":"Gen\u00e8ve",
    "wof:name":"St\u00f6cklin Edv Gmbh",
    "wof:placetype":"venue"
},
  "geometry": {"coordinates":[8.6681747437,47.0146865845],"type":"Point"}
}