{
  "type": "Feature",
  "properties": {
    "iso:country":"CH",
    "sg:address":"Rue Des Oeuches 17",
    "sg:city":"Montagne-moutier",
    "sg:orig_category":"Sportvereine Turnen",
    "sg:phone":"+41 32 494 64 15",
    "sg:postcode":"2740",
    "sg:province":"Bern",
    "wof:name":"St\u00e9 De Gymnastique",
    "wof:placetype":"venue"
},
  "geometry": {"coordinates":[7.3704481125,47.2765579224],"type":"Point"}
}