{
  "type": "Feature",
  "properties": {
    "iso:country":"CH",
    "sg:address":"Baarerstrasse 11 6300 Zug. Postfach",
    "sg:city":"Zug",
    "sg:orig_category":"Unternehmensberatung",
    "sg:phone":"+41 79 634 48 48",
    "sg:postcode":"6304",
    "sg:province":"Zug",
    "wof:name":"Innohouse Ag Unternehmensberatung",
    "wof:placetype":"venue"
},
  "geometry": {"coordinates":[8.5160207748,47.1715316772],"type":"Point"}
}