{
  "type": "Feature",
  "properties": {
    "iso:country":"CH",
    "sg:address":"Badenerstrasse 15 8004 Z\u00fcrich. Postfach",
    "sg:city":"Z\u00fcrich",
    "sg:orig_category":"Finanzierungsinstitutionen",
    "sg:phone":"+41 12992310",
    "sg:postcode":"8037",
    "sg:province":"Z\u00fcrich",
    "wof:name":"Kleeb & Partner Wirtschaftstreuhand Und Unternehmensberatung Ag",
    "wof:placetype":"venue"
},
  "geometry": {"coordinates":[8.5300960541,47.3734817505],"type":"Point"}
}