{
  "type": "Feature",
  "properties": {
    "iso:country":"CH",
    "sg:address":"Bahnhofstrasse 50",
    "sg:city":"Dietikon",
    "sg:classifiers":[
        {
            "category":"Banks & Credit Unions",
            "subcategory":"Bank",
            "type":"Services"
        }
    ],
    "sg:phone":"+41 18334262",
    "sg:postcode":"8305",
    "sg:province":"Z\u00fcrich",
    "wof:name":"Z\u00fcrcher Kantonalbank",
    "wof:placetype":"venue"
},
  "geometry": {"coordinates":[8.618219,47.423634],"type":"Point"}
}