{
  "type": "Feature",
  "properties": {
    "iso:country":"CH",
    "sg:address":"Via Maistra",
    "sg:city":"Bever",
    "sg:orig_category":"Bahnhofbuffets",
    "sg:phone":"+41 81 852 52 07",
    "sg:postcode":"7502",
    "sg:province":"Graubunden",
    "wof:name":"Bahnhofbuffet",
    "wof:placetype":"venue"
},
  "geometry": {"coordinates":[9.888955,46.551525],"type":"Point"}
}