{
  "type": "Feature",
  "properties": {
    "iso:country":"CH",
    "sg:address":"W\u00e4ssermattstrasse 6",
    "sg:city":"Aarau",
    "sg:orig_category":"Bauspenglerei Zimmerei, Dachdeckerei, Bauspenglerei U Abdichtung",
    "sg:phone":"+41 62 822 28 32",
    "sg:postcode":"5000",
    "sg:province":"Aargau",
    "wof:name":"E. Kull Spenglerei Ag",
    "wof:placetype":"venue"
},
  "geometry": {"coordinates":[8.06787,47.398888],"type":"Point"}
}