{
  "type": "Feature",
  "properties": {
    "iso:country":"CH",
    "sg:address":"Haus Iltis Klosters Dorf.",
    "sg:city":"Klosters",
    "sg:orig_category":"Detailhandel mit M\u00f6beln U Haushaltsgegenst\u00e4nden",
    "sg:postcode":"7250",
    "sg:province":"Graubunden",
    "wof:name":"Beyeler Michel.",
    "wof:placetype":"venue"
},
  "geometry": {"coordinates":[9.8801698685,46.8800468445],"type":"Point"}
}