{
  "type": "Feature",
  "properties": {
    "iso:country":"CH",
    "sg:address":"Closalet Chemin De 7",
    "sg:city":"Crissier",
    "sg:orig_category":"Verwaltung von Immobilien",
    "sg:postcode":"1023",
    "sg:province":"Vaud",
    "wof:name":"Ogay & Partenaires",
    "wof:placetype":"venue"
},
  "geometry": {"coordinates":[6.5774769783,46.5531997681],"type":"Point"}
}