{
  "type": "Feature",
  "properties": {
    "iso:country":"CH",
    "sg:address":"Gewerbestrasse 7",
    "sg:city":"Sissach",
    "sg:orig_category":"Grosshandel mit Baumaschinen Herstellung von Hebezeugen U F\u00f6rdermitteln",
    "sg:phone":"+41 61 971 51 55",
    "sg:postcode":"4450",
    "sg:province":"Basel-Landschaft",
    "wof:name":"Up Bs Ag",
    "wof:placetype":"venue"
},
  "geometry": {"coordinates":[7.8024587631,47.4674415588],"type":"Point"}
}