{
  "type": "Feature",
  "properties": {
    "addr:full":"Solari Via Dei 4 Lugano Ticino 6900",
    "addr:housenumber":"4",
    "addr:postcode":"6900",
    "addr:street":"Via Dei",
    "iso:country":"CH",
    "sg:address":"Solari Via Dei 4",
    "sg:city":"Lugano",
    "sg:orig_category":"Detailhandel mit Bekleidung",
    "sg:postcode":"6900",
    "sg:province":"Ticino",
    "wof:name":"Senix Fashion Sa",
    "wof:placetype":"venue"
},
  "geometry": {"coordinates":[8.950166,46.003716],"type":"Point"}
}