{
  "type": "Feature",
  "properties": {
    "iso:country":"CH",
    "sg:address":"Chemin Des Ecoliers",
    "sg:city":"Fully",
    "sg:classifiers":[
        {
            "category":"Government",
            "subcategory":"Post Office",
            "type":"Public Place"
        }
    ],
    "sg:phone":"+41 27 746 16 17",
    "sg:postcode":"1926",
    "sg:province":"Valais",
    "sg:tags":[
        "caf\u00e9s",
        "tea-rooms"
    ],
    "wof:name":"Tea-room Moulins",
    "wof:placetype":"venue"
},
  "geometry": {"coordinates":[7.1146121025,46.1390342712],"type":"Point"}
}