{
  "type": "Feature",
  "properties": {
    "iso:country":"CH",
    "sg:address":"Sangenstrasse 22",
    "sg:city":"Weinfelden",
    "sg:orig_category":"Herstellung von Frucht U Gem\u00fcses\u00e4ften Herstellung von Obst U Fruchtweinen",
    "sg:phone":"+41 71 622 59 16",
    "sg:postcode":"8570",
    "sg:province":"Thurgau",
    "wof:name":"Erwin L\u00fcthi",
    "wof:placetype":"venue"
},
  "geometry": {"coordinates":[9.1092357635,47.5601081848],"type":"Point"}
}