{
  "type": "Feature",
  "properties": {
    "iso:country":"CH",
    "sg:address":"H\u00f6henstrasse 45",
    "sg:city":"Flurlingen",
    "sg:orig_category":"Unternehmensberatung",
    "sg:postcode":"8247",
    "sg:province":"Z\u00fcrich",
    "wof:name":"Clerici Hans U., Technische Beratungen Und Projektierungen",
    "wof:placetype":"venue"
},
  "geometry": {"coordinates":[8.6326847076,47.6837387085],"type":"Point"}
}