{
  "type": "Feature",
  "properties": {
    "iso:country":"CH",
    "sg:address":"Schmiedestrasse 1",
    "sg:city":"Bellach",
    "sg:orig_category":"Ausbaugewerbe Geb\u00e4ude, Wohnungsreinigung",
    "sg:phone":"+41 32 618 44 30",
    "sg:postcode":"4512",
    "sg:province":"Solothurn",
    "wof:name":"Novosan Ag Brand-& Wasserschadensanierung",
    "wof:placetype":"venue"
},
  "geometry": {"coordinates":[7.500987,47.213707],"type":"Point"}
}