{
  "type": "Feature",
  "properties": {
    "addr:full":"Rue Du Village 37 Corseaux Vaud 1802",
    "addr:housenumber":"37",
    "addr:postcode":"1802",
    "addr:street":"Rue Du Village",
    "iso:country":"CH",
    "sg:address":"Rue Du Village 37",
    "sg:city":"Corseaux",
    "sg:orig_category":"Architektur U Ingenieurb\u00fcros",
    "sg:phone":"+41 21 921 56 46",
    "sg:postcode":"1802",
    "sg:province":"Vaud",
    "wof:name":"Georges Charotton Bureau D'ing\u00e9nieur",
    "wof:placetype":"venue"
},
  "geometry": {"coordinates":[6.832424,46.472141],"type":"Point"}
}