{
  "type": "Feature",
  "properties": {
    "iso:country":"CH",
    "sg:address":"Felsenweg 34",
    "sg:city":"Allschwil",
    "sg:orig_category":"Kauf U Verkauf von Immobilien auf eigene Rechnung",
    "sg:phone":"+41 61 481 48 22",
    "sg:postcode":"4123",
    "sg:province":"Basel-Landschaft",
    "wof:name":"A & O Verwaltungen Und Hausdienste Hans Zingg",
    "wof:placetype":"venue"
},
  "geometry": {"coordinates":[7.5422492027,47.5482521057],"type":"Point"}
}