{
  "type": "Feature",
  "properties": {
    "iso:country":"CH",
    "sg:address":"Route De Neuch\u00e2tel 34",
    "sg:city":"Cressier",
    "sg:classifiers":[
        {
            "category":"Autos & Motor Vehicles",
            "subcategory":"Auto Supplies",
            "type":"Retail Goods"
        }
    ],
    "sg:phone":"+41 32 757 18 33",
    "sg:postcode":"2088",
    "sg:province":"Neuch\u00e2tel",
    "sg:tags":[
        "body",
        "car",
        "truck",
        "trailer",
        "superstructure"
    ],
    "wof:name":"Metanova S.a.",
    "wof:placetype":"venue"
},
  "geometry": {"coordinates":[7.033669,47.048119],"type":"Point"}
}