{
  "type": "Feature",
  "properties": {
    "iso:country":"CH",
    "sg:address":"Route De Lausanne 50",
    "sg:city":"Mont-sur-lausanne",
    "sg:orig_category":"Bauschreinerei Herstellung von M\u00f6beln verschiedener Art",
    "sg:phone":"+41 21 652 01 36",
    "sg:postcode":"1052",
    "sg:province":"Vaud",
    "wof:name":"Menuiserie Rauschert Sa",
    "wof:placetype":"venue"
},
  "geometry": {"coordinates":[6.632966,46.552319],"type":"Point"}
}