{
  "type": "Feature",
  "properties": {
    "iso:country":"CH",
    "sg:address":"Oberdorfstrasse 259",
    "sg:city":"Leibstadt",
    "sg:orig_category":"Herstellung von Frucht U Gem\u00fcses\u00e4ften Herstellung von Obst U Fruchtweinen",
    "sg:phone":"+41 56 247 18 62",
    "sg:postcode":"5325",
    "sg:province":"Aargau",
    "wof:name":"Lukas Schilling Mosterei",
    "wof:placetype":"venue"
},
  "geometry": {"coordinates":[8.1753740311,47.5883903503],"type":"Point"}
}