{
  "type": "Feature",
  "properties": {
    "addr:full":"Im R\u00f6tel 18 Zug Zug 6300",
    "addr:housenumber":"18",
    "addr:postcode":"6300",
    "addr:street":"Im Roetel;Zug",
    "iso:country":"CH",
    "sg:address":"Im R\u00f6tel 18",
    "sg:city":"Zug",
    "sg:orig_category":"Architektur U Ingenieurb\u00fcros Architekturb\u00fcros",
    "sg:phone":"+41 41 711 28 38",
    "sg:postcode":"6300",
    "sg:province":"Zug",
    "wof:name":"Cordes, Sch\u00f6pflin + Twerenbold Ag",
    "wof:placetype":"venue"
},
  "geometry": {"coordinates":[8.526035,47.165493],"type":"Point"}
}