{
  "type": "Feature",
  "properties": {
    "iso:country":"CH",
    "sg:address":"Bas De Fin 1",
    "sg:city":"Froideville",
    "sg:orig_category":"Nationale Postdienste",
    "sg:phone":"+41 21 881 15 05",
    "sg:postcode":"1055",
    "sg:province":"Vaud",
    "wof:name":"La Poste Suisse",
    "wof:placetype":"venue"
},
  "geometry": {"coordinates":[6.6813941002,46.6017303467],"type":"Point"}
}