{
  "type": "Feature",
  "properties": {
    "iso:country":"CH",
    "sg:address":"Route Du Centre 15",
    "sg:city":"Belfaux",
    "sg:orig_category":"Kunsthandel",
    "sg:phone":"+41 32 931 64 54",
    "sg:postcode":"1782",
    "sg:province":"Fribourg",
    "wof:name":"Jean-pierre Tripet Brocante",
    "wof:placetype":"venue"
},
  "geometry": {"coordinates":[6.7490720749,47.058467865],"type":"Point"}
}