{
  "type": "Feature",
  "properties": {
    "iso:country":"CH",
    "sg:address":"P\u00fcntenstrasse 1",
    "sg:city":"Opfikon",
    "sg:orig_category":"Zahnarztpraxen",
    "sg:phone":"+41 18105511",
    "sg:postcode":"8152",
    "sg:province":"Z\u00fcrich",
    "wof:name":"Dr. Med. Dent. T. Madzarevic Zahnarzt",
    "wof:placetype":"venue"
},
  "geometry": {"coordinates":[8.5743455887,47.4334754944],"type":"Point"}
}