{
  "type": "Feature",
  "properties": {
    "iso:country":"CH",
    "sg:address":"Fabrikmattenweg 4 4144 Arlesheim. Postfach",
    "sg:city":"Arlesheim",
    "sg:orig_category":"Detailhandel mit M\u00f6beln U Haushaltsgegenst\u00e4nden Sonstiger Grosshandel",
    "sg:phone":"+41 22 309 06 20",
    "sg:postcode":"4144",
    "sg:province":"Basel-Landschaft",
    "wof:name":"Ipso Facto Sa",
    "wof:placetype":"venue"
},
  "geometry": {"coordinates":[6.1407899857,46.1805877686],"type":"Point"}
}