{
  "type": "Feature",
  "properties": {
    "iso:country":"CH",
    "sg:address":"Schulhausgasse 8",
    "sg:city":"Meiringen",
    "sg:orig_category":"Architektur U Ingenieurb\u00fcros Architekturb\u00fcros",
    "sg:phone":"+41 33 971 10 51",
    "sg:postcode":"3860",
    "sg:province":"Bern",
    "wof:name":"J\u00fcrg Weiss + Partner Ag Architekten Htl & Vsi",
    "wof:placetype":"venue"
},
  "geometry": {"coordinates":[8.189203,46.727528],"type":"Point"}
}