{
  "type": "Feature",
  "properties": {
    "iso:country":"CH",
    "sg:address":"Dorfstrasse 75",
    "sg:city":"Embrach",
    "sg:orig_category":"Fachdetailhandel in Verkaufsr\u00e4umen Fotografische Laboratorien",
    "sg:phone":"+41 18760000",
    "sg:postcode":"8424",
    "sg:province":"Z\u00fcrich",
    "wof:name":"Foto Flair, Utzinger Silvia",
    "wof:placetype":"venue"
},
  "geometry": {"coordinates":[8.5933847427,47.506072998],"type":"Point"}
}