{
  "type": "Feature",
  "properties": {
    "iso:country":"CH",
    "sg:address":"Studerswilen",
    "sg:city":"Kronb\u00fchl",
    "sg:orig_category":"Politische Parteien SVP",
    "sg:phone":"+41 71 298 40 10",
    "sg:postcode":"9302",
    "wof:name":"Svp Wittenbach-kronb\u00fchl",
    "wof:placetype":"venue"
},
  "geometry": {"coordinates":[9.3903799057,47.4585838318],"type":"Point"}
}