{
  "type": "Feature",
  "properties": {
    "iso:country":"CH",
    "sg:address":"Z\u00fcrichstrasse 22",
    "sg:city":"Merenschwand",
    "sg:orig_category":"Erbringung von Dienstleistungen f\u00fcr Unternehmen",
    "sg:phone":"+41 56 664 27 94",
    "sg:postcode":"5634",
    "sg:province":"Aargau",
    "wof:name":"Fabu Airbrush-atelier, Bruno Facheris",
    "wof:placetype":"venue"
},
  "geometry": {"coordinates":[8.3796710968,47.259021759],"type":"Point"}
}