{
  "type": "Feature",
  "properties": {
    "iso:country":"CH",
    "sg:address":"St. Urbanstrasse 22",
    "sg:city":"Langenthal",
    "sg:classifiers":[
        {
            "category":"Professional",
            "subcategory":"Employment Agencies",
            "type":"Services"
        }
    ],
    "sg:phone":"+41 62 922 91 22",
    "sg:postcode":"4900",
    "sg:province":"Bern",
    "sg:tags":[
        "personal",
        "u",
        "stellenvermittlung"
    ],
    "wof:name":"Manpower Ag",
    "wof:placetype":"venue"
},
  "geometry": {"coordinates":[7.7911920547,47.2121200562],"type":"Point"}
}