{
  "type": "Feature",
  "properties": {
    "iso:country":"CH",
    "sg:address":"Rue Grand-st-jean 18 1003 Lausanne Case Postale 3203",
    "sg:city":"Lausanne",
    "sg:classifiers":[
        {
            "category":"Restaurant",
            "type":"Food & Drink"
        }
    ],
    "sg:phone":"+41 21 312 02 66",
    "sg:postcode":"1002",
    "sg:province":"Vaud",
    "wof:name":"Restaurant La Bodega",
    "wof:placetype":"venue"
},
  "geometry": {"coordinates":[6.6312618256,46.5216331482],"type":"Point"}
}