{
  "type": "Feature",
  "properties": {
    "iso:country":"CH",
    "sg:address":"Blattengasse 10",
    "sg:city":"M\u00e4nnedorf",
    "sg:orig_category":"Grosshandel mit Software Hardwareberatung",
    "sg:postcode":"8708",
    "sg:province":"Z\u00fcrich",
    "wof:name":"Futureteam Gmbh Edv Handels-& Dienstleitungen",
    "wof:placetype":"venue"
},
  "geometry": {"coordinates":[7.598801136,47.4688606262],"type":"Point"}
}