{
  "type": "Feature",
  "properties": {
    "iso:country":"CH",
    "sg:address":"Wild\u00e4 Maa Hoch-ybrig",
    "sg:city":"Oberiberg",
    "sg:orig_category":"RESTAURANTS: TEA-ROOMS",
    "sg:postcode":"8843",
    "sg:province":"Schwyz",
    "wof:name":"Holdener Martin, Rest. Wild\u00e4 Maa",
    "wof:placetype":"venue"
},
  "geometry": {"coordinates":[8.7898454666,47.0042877197],"type":"Point"}
}