{
  "type": "Feature",
  "properties": {
    "iso:country":"CH",
    "sg:address":"Gewerbestr. 8 6330 Cham. Postfach",
    "sg:city":"Cham",
    "sg:orig_category":"Elektroinstallation",
    "sg:phone":"+41 41 748 18 18",
    "sg:postcode":"6330",
    "sg:province":"Zug",
    "wof:name":"Canepa C.",
    "wof:placetype":"venue"
},
  "geometry": {"coordinates":[8.4724349976,47.1890296936],"type":"Point"}
}