{
  "type": "Feature",
  "properties": {
    "iso:country":"CH",
    "sg:address":"Obere Hauptgasse 3",
    "sg:city":"Thun",
    "sg:orig_category":"Herstellung von keramischen Haushaltswaren U Ziergegenst\u00e4nden",
    "sg:phone":"+41 26 912 31 35",
    "sg:postcode":"3600",
    "sg:province":"Bern",
    "wof:name":"Antoniette Dubuis",
    "wof:placetype":"venue"
},
  "geometry": {"coordinates":[7.0581102371,46.6218414307],"type":"Point"}
}