{
  "type": "Feature",
  "properties": {
    "iso:country":"CH",
    "sg:address":"Via Cantonale",
    "sg:city":"Melano",
    "sg:orig_category":"Einzelhandel mit Automobilteilen U Zubeh\u00f6r",
    "sg:phone":"+41 91 648 22 19",
    "sg:postcode":"6818",
    "sg:province":"Ticino",
    "wof:name":"Angelo Anzalone Gomme",
    "wof:placetype":"venue"
},
  "geometry": {"coordinates":[8.9752750397,45.9309043884],"type":"Point"}
}