{
  "type": "Feature",
  "properties": {
    "iso:country":"CH",
    "sg:address":"Bierh\u00fcbeliweg 1 3000 Bern. Postfach",
    "sg:city":"Bern",
    "sg:orig_category":"Verwaltung von Immobilien",
    "sg:postcode":"3005",
    "sg:province":"Bern",
    "wof:name":"Dead End Immobilien Gmbh",
    "wof:placetype":"venue"
},
  "geometry": {"coordinates":[7.4386649132,46.9543228149],"type":"Point"}
}