{
  "type": "Feature",
  "properties": {
    "iso:country":"CH",
    "sg:address":"Poststrasse 7",
    "sg:city":"Ostermundigen",
    "sg:orig_category":"Non-Classified Establishments",
    "sg:postcode":"3072",
    "sg:province":"Bern",
    "wof:name":"Acifer Ostermundigen Ag",
    "wof:placetype":"venue"
},
  "geometry": {"coordinates":[7.4825778008,46.9562988281],"type":"Point"}
}