{
  "type": "Feature",
  "properties": {
    "iso:country":"CH",
    "sg:address":"Alte Poststrasse 252",
    "sg:city":"Gunzgen",
    "sg:orig_category":"Architektur U Ingenieurb\u00fcros",
    "sg:phone":"+41 62 216 34 05",
    "sg:postcode":"4617",
    "sg:province":"Solothurn",
    "wof:name":"Lack Ignaz Architekturb\u00fcro",
    "wof:placetype":"venue"
},
  "geometry": {"coordinates":[7.83201,47.317032],"type":"Point"}
}