{
  "type": "Feature",
  "properties": {
    "iso:country":"CH",
    "sg:address":"Hauptstrasse 111",
    "sg:city":"Waldenburg",
    "sg:classifiers":[
        {
            "category":"Travel",
            "subcategory":"Hotels & Motels",
            "type":"Entertainment"
        }
    ],
    "sg:postcode":"4437",
    "sg:province":"Basel-Landschaft",
    "sg:tags":[
        "hotels",
        "mit",
        "restaurant"
    ],
    "wof:name":"Hotel Restaurant Eden, Peter Meyer",
    "wof:placetype":"venue"
},
  "geometry": {"coordinates":[7.7467160225,47.3784942627],"type":"Point"}
}