{
  "type": "Feature",
  "properties": {
    "iso:country":"CH",
    "sg:address":"Windwurfstrasse 20",
    "sg:city":"Unter\u00e4geri",
    "sg:orig_category":"Erwachsenenbildung U Unterricht",
    "sg:phone":"+41 41 750 62 78",
    "sg:postcode":"6314",
    "sg:province":"Zug",
    "wof:name":"Qubira Ag",
    "wof:placetype":"venue"
},
  "geometry": {"coordinates":[8.5759887695,47.133556366],"type":"Point"}
}