{
  "type": "Feature",
  "properties": {
    "iso:country":"CH",
    "sg:address":"Heimeliweg 5 6370 Stans. Postfach 162",
    "sg:city":"Stans",
    "sg:orig_category":"Luft U Raumfahrzeugbau",
    "sg:phone":"+41 41 610 70 70",
    "sg:postcode":"6370",
    "sg:province":"Nidwalden",
    "wof:name":"Amstutz Toni, Flugsport",
    "wof:placetype":"venue"
},
  "geometry": {"coordinates":[8.365904808,46.9572486877],"type":"Point"}
}