{
  "type": "Feature",
  "properties": {
    "iso:country":"CH",
    "sg:address":"Dahlienweg 1.",
    "sg:city":"M\u00fclligen",
    "sg:orig_category":"Technische, physikalische U chemische Untersuchung",
    "sg:phone":"+41 56 225 16 26",
    "sg:postcode":"5243",
    "sg:province":"Aargau",
    "wof:name":"Lhm Ag, Labor F\u00fcr Hygiene Und Praktische Mikrobiologie.",
    "wof:placetype":"venue"
},
  "geometry": {"coordinates":[8.2393951416,47.4577484131],"type":"Point"}
}