{
  "type": "Feature",
  "properties": {
    "addr:full":"Via San Gottardo 89 Massagno Ticino 6900",
    "addr:housenumber":"89",
    "addr:postcode":"6900",
    "addr:street":"Via San Gottardo",
    "iso:country":"CH",
    "sg:address":"Via San Gottardo 89",
    "sg:city":"Massagno",
    "sg:orig_category":"Advokaturb\u00fcros Notariate",
    "sg:phone":"+41 91 827 17 26",
    "sg:postcode":"6900",
    "sg:province":"Ticino",
    "wof:name":"Ornella Nicoli Studio Legale & Notarile",
    "wof:placetype":"venue"
},
  "geometry": {"coordinates":[8.944021,46.013233],"type":"Point"}
}