{
  "type": "Feature",
  "properties": {
    "iso:country":"CH",
    "sg:address":"Oberau",
    "sg:city":"Weite",
    "sg:orig_category":"Fahrschulen, Flugschulen",
    "sg:phone":"+41 81 783 28 00",
    "sg:postcode":"9476",
    "sg:province":"St. Gallen",
    "wof:name":"Luigi Della Santa Autofahrschule",
    "wof:placetype":"venue"
},
  "geometry": {"coordinates":[9.4974250793,47.0933837891],"type":"Point"}
}