{
  "type": "Feature",
  "properties": {
    "iso:country":"CH",
    "sg:address":"Rue Des Bonnes-luites 8",
    "sg:city":"Martigny",
    "sg:orig_category":"Kaufm\u00e4nnische Berufsschulen",
    "sg:phone":"+41 27 722 03 14",
    "sg:postcode":"1920",
    "sg:province":"Valais",
    "wof:name":"Ecole Sup\u00e9rieure De Commerce",
    "wof:placetype":"venue"
},
  "geometry": {"coordinates":[7.0795707703,46.107131958],"type":"Point"}
}