{
  "type": "Feature",
  "properties": {
    "iso:country":"CH",
    "sg:address":"3186 D\u00fcdingen. Postfach",
    "sg:city":"D\u00fcdingen",
    "sg:orig_category":"Pensionskassen",
    "sg:postcode":"3186",
    "sg:province":"Fribourg",
    "wof:name":"Vorsorgewerk Der Genossenschaft Agro-center Sense",
    "wof:placetype":"venue"
},
  "geometry": {"coordinates":[7.1900749207,46.8504104614],"type":"Point"}
}