{
  "type": "Feature",
  "properties": {
    "iso:country":"CH",
    "sg:address":"St-cl\u00e9ment 3978 Flanthey. Postfach",
    "sg:city":"Flanthey",
    "sg:orig_category":"Grosshandel mit Getr\u00e4nken",
    "sg:phone":"+41 27 458 44 37",
    "sg:postcode":"3978",
    "sg:province":"Valais",
    "wof:name":"Cave La Tour Carr\u00e9e, Nanchen St\u00e9phane Vigne En G\u00e9n\u00e9ral, Soit Travaux, Entretien De Vignes Et Commerce De Vins",
    "wof:placetype":"venue"
},
  "geometry": {"coordinates":[7.4497947693,46.2690734863],"type":"Point"}
}