{
  "type": "Feature",
  "properties": {
    "iso:country":"CH",
    "sg:address":"Sunnestrahl 7 Schindellegi 8835 Feusisberg. Postfach",
    "sg:city":"Schindellegi",
    "sg:orig_category":"Detektivb\u00fcros U \u00dcberwachung",
    "sg:phone":"+41 71 313 06 93",
    "sg:postcode":"8834",
    "sg:province":"Schwyz",
    "wof:name":"Wpn Waypoint Network Ag",
    "wof:placetype":"venue"
},
  "geometry": {"coordinates":[9.3737154007,47.4263916016],"type":"Point"}
}