{
  "type": "Feature",
  "properties": {
    "iso:country":"CH",
    "sg:address":"Zentralstrasse 76 B",
    "sg:city":"Z\u00fcrich",
    "sg:orig_category":"Fachdetailhandel in Verkaufsr\u00e4umen",
    "sg:phone":"+41 14614151",
    "sg:postcode":"8003",
    "sg:province":"Z\u00fcrich",
    "wof:name":"Fibertec K\u00f6yl\u00fcer",
    "wof:placetype":"venue"
},
  "geometry": {"coordinates":[8.5178251266,47.373336792],"type":"Point"}
}