{
  "type": "Feature",
  "properties": {
    "iso:country":"CH",
    "sg:address":"Aarauerstrasse 13",
    "sg:city":"Sch\u00f6nenwerd",
    "sg:orig_category":"Maler U Glasergewerbe Malerei",
    "sg:phone":"+41 71 912 44 11",
    "sg:postcode":"5012",
    "sg:province":"Solothurn",
    "wof:name":"Maler Klein Ag",
    "wof:placetype":"venue"
},
  "geometry": {"coordinates":[9.0372447968,47.4614295959],"type":"Point"}
}