{
  "type": "Feature",
  "properties": {
    "iso:country":"CH",
    "sg:address":"Tann\u00e4gertenstrasse 2",
    "sg:city":"Bubikon",
    "sg:orig_category":"Herstellung von Ger\u00e4ten der Elektrizit\u00e4tserzeugung, -verteilung u.\u00e4. -Herstellung von Mess U Kontrol",
    "sg:phone":"+41 71 744 33 44",
    "sg:postcode":"8608",
    "sg:province":"Z\u00fcrich",
    "wof:name":"Afriso-euro-index Ag",
    "wof:placetype":"venue"
},
  "geometry": {"coordinates":[9.6437206268,47.4248580933],"type":"Point"}
}