{
  "type": "Feature",
  "properties": {
    "iso:country":"CH",
    "sg:address":"M\u00fchleweg 15",
    "sg:city":"Langenthal",
    "sg:orig_category":"Bauschreinerei",
    "sg:phone":"+41 62 922 12 75",
    "sg:postcode":"4900",
    "sg:province":"Bern",
    "wof:name":"Paul Bachmann Bauschreinerei",
    "wof:placetype":"venue"
},
  "geometry": {"coordinates":[7.791744,47.213642],"type":"Point"}
}