{
  "type": "Feature",
  "properties": {
    "iso:country":"CH",
    "sg:address":"Ettiswilerstrasse 46",
    "sg:city":"Willisau",
    "sg:orig_category":"Sonstiger Detailhandel mit Metallwaren, Anstrichmitteln, Glaswaren, Bau U Heimwerkerbedarf",
    "sg:phone":"+41 17635080",
    "sg:postcode":"6130",
    "sg:province":"Luzern",
    "wof:name":"Jumbo Bau & Freizeit",
    "wof:placetype":"venue"
},
  "geometry": {"coordinates":[8.4423875809,47.2730178833],"type":"Point"}
}