{
  "type": "Feature",
  "properties": {
    "addr:full":"Chemin Du Grand-pr\u00e9 29 Le Mont Vaud 1052",
    "addr:housenumber":"29",
    "addr:postcode":"1052",
    "addr:street":"Chemin Du Grand-Pre\u0301",
    "iso:country":"CH",
    "sg:address":"Chemin Du Grand-pr\u00e9 29",
    "sg:city":"Le Mont",
    "sg:classifiers":[
        {
            "category":"Banks & Credit Unions",
            "subcategory":"Bank",
            "type":"Services"
        }
    ],
    "sg:phone":"+41 21 652 27 40",
    "sg:postcode":"1052",
    "sg:province":"Vaud",
    "wof:name":"Soci\u00e9t\u00e9 De Banque Suisse",
    "wof:placetype":"venue"
},
  "geometry": {"coordinates":[6.636791,46.543831],"type":"Point"}
}