{
  "type": "Feature",
  "properties": {
    "iso:country":"CH",
    "sg:address":"3756",
    "sg:city":"Zwischenfl\u00fch",
    "sg:orig_category":"Schulpflegen",
    "sg:postcode":"3756",
    "sg:province":"Bern",
    "wof:name":"Primarschulkommission Der Gemeinde Zwischenfl\u00fch",
    "wof:placetype":"venue"
},
  "geometry": {"coordinates":[7.5157699585,46.6070518494],"type":"Point"}
}