{
  "type": "Feature",
  "properties": {
    "iso:country":"CH",
    "sg:address":"Burgstrasse 2b",
    "sg:city":"Thun",
    "sg:orig_category":"Instandhaltung U Reparatur von Automobilen",
    "sg:phone":"+41 33 222 06 66",
    "sg:postcode":"3600",
    "sg:province":"Bern",
    "wof:name":"Rudo Martinovic Turm-garage",
    "wof:placetype":"venue"
},
  "geometry": {"coordinates":[7.6323308945,46.7594070435],"type":"Point"}
}