{
  "type": "Feature",
  "properties": {
    "iso:country":"CH",
    "sg:address":"Mor\u00e4nenweg 8",
    "sg:city":"Bettlach",
    "sg:orig_category":"Unternehmensberatung",
    "sg:phone":"+41 32 645 47 56",
    "sg:postcode":"2544",
    "sg:province":"Solothurn",
    "wof:name":"Bigler Bernadette Reka-beratung",
    "wof:placetype":"venue"
},
  "geometry": {"coordinates":[7.4289698601,47.2035942078],"type":"Point"}
}