{
  "type": "Feature",
  "properties": {
    "iso:country":"CH",
    "sg:address":"Jomini Avenue 10",
    "sg:city":"Avenches",
    "sg:orig_category":"Detailhandel mit Waren verschiedener Art, Hauptrichtung Nahrungsmittel",
    "sg:postcode":"1580",
    "sg:province":"Vaud",
    "wof:name":"Avigel Sa",
    "wof:placetype":"venue"
},
  "geometry": {"coordinates":[7.044148922,46.8812713623],"type":"Point"}
}