{
  "type": "Feature",
  "properties": {
    "iso:country":"CH",
    "sg:address":"Chemin Pr\u00e9-cornillons 19",
    "sg:city":"Chamb\u00e9sy",
    "sg:orig_category":"Grosshandel mit Nahrungsmitteln, Getr\u00e4nken U Tabakwaren Grosshandel mit Schuhen",
    "sg:phone":"+41 22 758 18 90",
    "sg:postcode":"1292",
    "sg:province":"Gen\u00e8ve",
    "wof:name":"Gaby Beyeler Import-export",
    "wof:placetype":"venue"
},
  "geometry": {"coordinates":[6.1452050209,46.2415962219],"type":"Point"}
}