{
  "type": "Feature",
  "properties": {
    "iso:country":"CH",
    "sg:address":"Aarauerstrasse 12",
    "sg:city":"Oberentfelden",
    "sg:orig_category":"Primarschulen",
    "sg:phone":"+41 79 670 40 38",
    "sg:postcode":"5036",
    "sg:province":"Aargau",
    "wof:name":"Primarschule Dorf",
    "wof:placetype":"venue"
},
  "geometry": {"coordinates":[8.0466632843,47.3578491211],"type":"Point"}
}