{
  "type": "Feature",
  "properties": {
    "iso:country":"CH",
    "sg:address":"Baarerstrasse 112 6300 Zug. Postfach 2215",
    "sg:city":"Zug",
    "sg:orig_category":"Grosshandel mit sonstigen Maschinen U Ausr\u00fcstungen f\u00fcr Industrie, Handel U Schiffahrt Herstellung vo",
    "sg:phone":"+41 41 767 25 54",
    "sg:postcode":"6302",
    "sg:province":"Zug",
    "wof:name":"Interfaserbedarf Ag",
    "wof:placetype":"venue"
},
  "geometry": {"coordinates":[8.5190229416,47.1802215576],"type":"Point"}
}