{
  "type": "Feature",
  "properties": {
    "iso:country":"CH",
    "sg:address":"Eschenbachstrasse 7",
    "sg:city":"Oetwil",
    "sg:orig_category":"Herstellung von sonstigen elektrischen Ausr\u00fcstungen",
    "sg:phone":"+41 52 741 42 48",
    "sg:postcode":"8955",
    "sg:province":"Z\u00fcrich",
    "wof:name":"Erma Electronic Gmbh",
    "wof:placetype":"venue"
},
  "geometry": {"coordinates":[8.8558330536,47.6582374573],"type":"Point"}
}