{
  "type": "Feature",
  "properties": {
    "iso:country":"CH",
    "sg:address":"Urtenenstrasse 50",
    "sg:city":"Mattstetten",
    "sg:classifiers":[
        {
            "category":"Banks & Credit Unions",
            "subcategory":"Bureau De Change",
            "type":"Services"
        }
    ],
    "sg:phone":"+41 31 852 15 45",
    "sg:postcode":"3322",
    "sg:province":"Bern",
    "sg:tags":[
        "flat",
        "construction",
        "roof"
    ],
    "wof:name":"Pulver Dawa Partner Ag",
    "wof:placetype":"venue"
},
  "geometry": {"coordinates":[7.5110449791,47.0299835205],"type":"Point"}
}