{
  "type": "Feature",
  "properties": {
    "iso:country":"CH",
    "sg:address":"Flugplatz",
    "sg:city":"Fehraltorf",
    "sg:orig_category":"Sonstige Hilfs U Nebent\u00e4tigkeiten f\u00fcr die Luftfahrt",
    "sg:phone":"+41 19541252",
    "sg:postcode":"8320",
    "sg:province":"Z\u00fcrich",
    "wof:name":"Restaurant Flugplatz Speck",
    "wof:placetype":"venue"
},
  "geometry": {"coordinates":[8.7523164749,47.3878517151],"type":"Point"}
}