{
  "type": "Feature",
  "properties": {
    "iso:country":"CH",
    "sg:address":"Bahnhofstrasse 9b",
    "sg:city":"Aarberg",
    "sg:orig_category":"Detailhandel mit Gebrauchtwaren in Verkaufsr\u00e4umen",
    "sg:phone":"+41 79 210 16 72",
    "sg:postcode":"3270",
    "sg:province":"Bern",
    "wof:name":"Brockenhaus Horizont",
    "wof:placetype":"venue"
},
  "geometry": {"coordinates":[7.2788081169,47.0449066162],"type":"Point"}
}