{
  "type": "Feature",
  "properties": {
    "iso:country":"CH",
    "sg:address":"Centralstrasse 42",
    "sg:city":"Interlaken",
    "sg:orig_category":"Detailhandel mit Waren verschiedener Art, Hauptrichtung Nahrungsmittel",
    "sg:phone":"+41 81 844 01 89",
    "sg:postcode":"3800",
    "sg:province":"Bern",
    "wof:name":"Caseificio Sociale Di San Carlo & Dintorni",
    "wof:placetype":"venue"
},
  "geometry": {"coordinates":[10.0616703033,46.3435783386],"type":"Point"}
}