{
  "type": "Feature",
  "properties": {
    "iso:country":"CH",
    "sg:address":"Via Alle Scuole",
    "sg:city":"Taverne",
    "sg:orig_category":"Stukkateurgewerbe, Gipserei U Verputzerei",
    "sg:phone":"+41 71 923 34 55",
    "sg:postcode":"6807",
    "sg:province":"Ticino",
    "wof:name":"Lo Riso G. Ag",
    "wof:placetype":"venue"
},
  "geometry": {"coordinates":[9.0699739456,47.4417457581],"type":"Point"}
}