{
  "type": "Feature",
  "properties": {
    "iso:country":"CH",
    "sg:address":"Chemin De B\u00e9goudaz",
    "sg:city":"Eysins",
    "sg:orig_category":"Bauschreinerei Innenausbau",
    "sg:phone":"+41 22 361 66 46",
    "sg:postcode":"1262",
    "sg:province":"Vaud",
    "wof:name":"Willy Geier Entreprise De Menuiserie",
    "wof:placetype":"venue"
},
  "geometry": {"coordinates":[6.206785,46.383179],"type":"Point"}
}