{
  "type": "Feature",
  "properties": {
    "iso:country":"CH",
    "sg:address":"L\u00e4ndliweg 24",
    "sg:city":"Baden",
    "sg:orig_category":"Disc Brakes, Industrial",
    "sg:phone":"+41 32 751 33 09",
    "sg:postcode":"5400",
    "sg:province":"Aargau",
    "wof:name":"Pfl Antralux Sa",
    "wof:placetype":"venue"
},
  "geometry": {"coordinates":[7.0694022179,47.064704895],"type":"Point"}
}