{
  "type": "Feature",
  "properties": {
    "iso:country":"CH",
    "sg:address":"St\u00e4dtchen 28",
    "sg:city":"Uznach",
    "sg:orig_category":"RESTAURANTS: TEA-ROOMS",
    "sg:phone":"+41 55 280 23 82",
    "sg:postcode":"8730",
    "sg:province":"St. Gallen",
    "wof:name":"Gasthof Sch\u00e4fli, Maria Dorizzi",
    "wof:placetype":"venue"
},
  "geometry": {"coordinates":[8.98716259,47.2252540588],"type":"Point"}
}