{
  "type": "Feature",
  "properties": {
    "iso:country":"CH",
    "sg:address":"Industriestrasse 3",
    "sg:city":"Neuheim",
    "sg:orig_category":"Wirtschaftspr\u00fcfung, Steuerberatung U Treuhand",
    "sg:phone":"+41 41 756 00 35",
    "sg:postcode":"6345",
    "sg:province":"Zug",
    "wof:name":"Treuhandb\u00fcro Susanna Gallmann Treuhandb\u00fcro",
    "wof:placetype":"venue"
},
  "geometry": {"coordinates":[8.5762796402,47.2021102905],"type":"Point"}
}