{
  "type": "Feature",
  "properties": {
    "iso:country":"CH",
    "sg:address":"Arenenbergstrasse 43",
    "sg:city":"Salenstein",
    "sg:orig_category":"Architekturb\u00fcros",
    "sg:phone":"+41 71 664 19 19",
    "sg:postcode":"8268",
    "sg:province":"Thurgau",
    "wof:name":"Hubert Iten Architekturb\u00fcro",
    "wof:placetype":"venue"
},
  "geometry": {"coordinates":[9.05623,47.671833],"type":"Point"}
}