{
  "type": "Feature",
  "properties": {
    "iso:country":"CH",
    "sg:address":"Aegelseestrasse 2",
    "sg:city":"Inkwil",
    "sg:classifiers":[
        {
            "category":"Manufacturing",
            "subcategory":"Rubber & Plastics",
            "type":"Manufacturing & Wholesale Goods"
        }
    ],
    "sg:phone":"+41 62 956 50 80",
    "sg:postcode":"3375",
    "sg:province":"Bern",
    "sg:tags":[
        "injection",
        "part",
        "moulded"
    ],
    "wof:name":"Wesa Ag",
    "wof:placetype":"venue"
},
  "geometry": {"coordinates":[7.6749949455,47.1967010498],"type":"Point"}
}