{
  "type": "Feature",
  "properties": {
    "iso:country":"CH",
    "sg:address":"Oberer Flooz",
    "sg:city":"Lichtensteig",
    "sg:orig_category":"Gewinnung von Kies U Sand Herstellung von sonstigen Produkten aus nichtmetallischen Mineralien",
    "sg:phone":"+41 62 836 94 04",
    "sg:postcode":"9620",
    "sg:province":"St. Gallen",
    "wof:name":"Hans Keiser Kies Und Sandwerk Ag Kies Und Sand, Kieszerkleinerungsmaschinen; Handel Usw",
    "wof:placetype":"venue"
},
  "geometry": {"coordinates":[8.1016283035,47.3880157471],"type":"Point"}
}