{
  "type": "Feature",
  "properties": {
    "iso:country":"CH",
    "sg:address":"G\u00e4brisstrasse 4 9400 Rorschach. Postfach",
    "sg:city":"Rorschach",
    "sg:orig_category":"Grosshandel mit sonstigen Maschinen U Ausr\u00fcstungen f\u00fcr Industrie, Handel U Schiffahrt",
    "sg:phone":"+41 71 841 63 63",
    "sg:postcode":"9401",
    "sg:province":"St. Gallen",
    "wof:name":"Schemaro-befestigungstechnik Scherrer Markus.",
    "wof:placetype":"venue"
},
  "geometry": {"coordinates":[9.4805316925,47.4782371521],"type":"Point"}
}