{
  "type": "Feature",
  "properties": {
    "iso:country":"CH",
    "sg:address":"Hauptstrasse 45",
    "sg:city":"Kleind\u00f6ttingen",
    "sg:orig_category":"Personenbef\u00f6rderung im Linienverkehr zu Land Personenbef\u00f6rderung im Nahverkehr",
    "sg:phone":"+41 56 245 80 40",
    "sg:postcode":"5314",
    "sg:province":"Aargau",
    "wof:name":"Forster Andreas Personentransporte",
    "wof:placetype":"venue"
},
  "geometry": {"coordinates":[8.2416696548,47.5724983215],"type":"Point"}
}