{
  "type": "Feature",
  "properties": {
    "iso:country":"CH",
    "sg:address":"Segantinistrasse 49",
    "sg:city":"Z\u00fcrich",
    "sg:orig_category":"G\u00fcterbef\u00f6rderung im Strassenverkehr",
    "sg:phone":"+41 18504630",
    "sg:postcode":"8049",
    "sg:province":"Z\u00fcrich",
    "wof:name":"Page-kaegi Transporte.",
    "wof:placetype":"venue"
},
  "geometry": {"coordinates":[8.524895668,47.4790916443],"type":"Point"}
}