{
  "type": "Feature",
  "properties": {
    "iso:country":"CH",
    "sg:address":"Lausanne Rue De 64-66 1202 Gen\u00e8ve. Postfach",
    "sg:city":"Gen\u00e8ve",
    "sg:orig_category":"Instandhaltung U Reparatur von Automobilen",
    "sg:phone":"+41 56 633 27 60",
    "sg:postcode":"1202",
    "sg:province":"Gen\u00e8ve",
    "wof:name":"N. Oswald Ag, Autospenglerei",
    "wof:placetype":"venue"
},
  "geometry": {"coordinates":[8.3937015533,47.3410224915],"type":"Point"}
}