{
  "type": "Feature",
  "properties": {
    "iso:country":"CH",
    "sg:address":"Herrengasse 81",
    "sg:city":"Untersteckholz",
    "sg:orig_category":"Bauschreinerei",
    "sg:phone":"+41 81 756 19 75",
    "sg:postcode":"4916",
    "sg:province":"Bern",
    "wof:name":"Heinrich K\u00fcng Schreinerei",
    "wof:placetype":"venue"
},
  "geometry": {"coordinates":[9.4746818542,47.1627349854],"type":"Point"}
}