{
  "type": "Feature",
  "properties": {
    "iso:country":"CH",
    "sg:address":"Alte Bubikerstrasse 5 Ottikon 8625 Gossau Zh. Postfach",
    "sg:city":"Ottikon",
    "sg:orig_category":"Herstellung von Werkzeugmaschinen",
    "sg:postcode":"8626",
    "sg:province":"Z\u00fcrich",
    "wof:name":"Bhb + Partner Gmbh",
    "wof:placetype":"venue"
},
  "geometry": {"coordinates":[8.7609901428,47.3074913025],"type":"Point"}
}