{
  "type": "Feature",
  "properties": {
    "iso:country":"CH",
    "sg:address":"F\u00fcrst Franz Josef Strasse 5",
    "sg:city":"Vaduz",
    "sg:orig_category":"Herstellung von Metallerzeugnissen ohne Maschinenbau Maschinenbau",
    "sg:phone":"+41 75 233 32 39",
    "sg:postcode":"9490",
    "wof:name":"Risa-tech Anstalt Maschinenbau",
    "wof:placetype":"venue"
},
  "geometry": {"coordinates":[9.5116767883,47.1523208618],"type":"Point"}
}