{
  "type": "Feature",
  "properties": {
    "iso:country":"CH",
    "sg:address":"Alpenstrasse 1 8580 Amriswil. Postfach 1809",
    "sg:city":"Amriswil",
    "sg:orig_category":"Herstellung von Elektrizit\u00e4tsverteilungs U schalteinrichtungen Herstellung von Elektromotoren, Gener",
    "sg:phone":"+41 33 821 03 30",
    "sg:postcode":"8580",
    "sg:province":"Thurgau",
    "wof:name":"Frey + Cie, Elektrotechnische Unternehmungen Ag, Matten B. Interlaken",
    "wof:placetype":"venue"
},
  "geometry": {"coordinates":[7.8571481705,46.6707344055],"type":"Point"}
}