{
  "type": "Feature",
  "properties": {
    "iso:country":"CH",
    "sg:address":"Bergstrasse 6",
    "sg:city":"Balgach",
    "sg:orig_category":"Rechtsberatung Wirtschaftspr\u00fcfung, Steuerberatung U Treuhand",
    "sg:phone":"+41 71 722 81 79",
    "sg:postcode":"9436",
    "sg:province":"St. Gallen",
    "wof:name":"Slb Treuhand Ag",
    "wof:placetype":"venue"
},
  "geometry": {"coordinates":[9.6060304642,47.4078521729],"type":"Point"}
}