{
  "type": "Feature",
  "properties": {
    "iso:country":"CH",
    "sg:address":"Muespacherstrasse 44",
    "sg:city":"Basel",
    "sg:orig_category":"Unclassifiable Establishments",
    "sg:postcode":"4055",
    "sg:province":"Basel-Stadt",
    "wof:name":"Hlk Consulting Gmbh Andreas Hauser",
    "wof:placetype":"venue"
},
  "geometry": {"coordinates":[7.5674738884,47.5626487732],"type":"Point"}
}