{
  "type": "Feature",
  "properties": {
    "iso:country":"CH",
    "sg:address":"Rue Du Coll\u00e8ge 3",
    "sg:city":"Vevey",
    "sg:orig_category":"Detailhandel mit Sportartikeln Fachdetailhandel in Verkaufsr\u00e4umen",
    "sg:phone":"+41 21 925 20 90",
    "sg:postcode":"1800",
    "sg:province":"Vaud",
    "wof:name":"Wild Duck Sa Snowboards",
    "wof:placetype":"venue"
},
  "geometry": {"coordinates":[6.8498888016,46.4582557678],"type":"Point"}
}