{
  "type": "Feature",
  "properties": {
    "iso:country":"CH",
    "sg:address":"Kreuzfeldstrasse 54",
    "sg:city":"Lotzwil",
    "sg:classifiers":[
        {
            "category":"Professional",
            "subcategory":"Employment Agencies",
            "type":"Services"
        }
    ],
    "sg:phone":"+41 62 923 05 55",
    "sg:postcode":"4932",
    "sg:province":"Bern",
    "sg:tags":[
        "personal",
        "u",
        "stellenvermittlung"
    ],
    "wof:name":"Gv Service W.j\u00f6rg Gastro Vermittlungsservice",
    "wof:placetype":"venue"
},
  "geometry": {"coordinates":[7.7874522209,47.1963157654],"type":"Point"}
}