{
  "type": "Feature",
  "properties": {
    "iso:country":"CH",
    "sg:address":"Viale Franscini 9",
    "sg:city":"Lugano",
    "sg:orig_category":"Museen",
    "sg:phone":"+41 91 800 72 01",
    "sg:postcode":"6900",
    "sg:province":"Ticino",
    "wof:name":"Museo Storico Villa Saroli",
    "wof:placetype":"venue"
},
  "geometry": {"coordinates":[8.9531364441,46.0092124939],"type":"Point"}
}