{
  "type": "Feature",
  "properties": {
    "iso:country":"CH",
    "sg:address":"Vigne Via Delle 145",
    "sg:city":"Minusio",
    "sg:orig_category":"Architektur U Ingenieurb\u00fcros",
    "sg:phone":"+41 91 743 28 03",
    "sg:postcode":"6648",
    "sg:province":"Ticino",
    "wof:name":"Pedrotta Luca Falegname/progettista",
    "wof:placetype":"venue"
},
  "geometry": {"coordinates":[8.821657,46.18021],"type":"Point"}
}