{
  "type": "Feature",
  "properties": {
    "iso:country":"CH",
    "sg:address":"H\u00fcniweg 12",
    "sg:city":"Meilen",
    "sg:orig_category":"Innenarchitekturb\u00fcros",
    "sg:phone":"+41 19232131",
    "sg:postcode":"8706",
    "sg:province":"Z\u00fcrich",
    "wof:name":"Carl Kaufmann Innenarchitektur",
    "wof:placetype":"venue"
},
  "geometry": {"coordinates":[8.6422138214,47.2694206238],"type":"Point"}
}