{
  "type": "Feature",
  "properties": {
    "iso:country":"CH",
    "sg:address":"Sch\u00fctzenstr. 19",
    "sg:city":"Schwyz",
    "sg:orig_category":"Pensionskassen",
    "sg:postcode":"6430",
    "sg:province":"Schwyz",
    "wof:name":"Personalf\u00fcrsorgestiftung Der Firma Buchdruckerei Nider\u00f6st, Nachfolger M. Gleissner-nider\u00f6st, Schwyz",
    "wof:placetype":"venue"
},
  "geometry": {"coordinates":[8.6551208496,47.0190162659],"type":"Point"}
}