{
  "type": "Feature",
  "properties": {
    "iso:country":"CH",
    "sg:address":"Seiten",
    "sg:city":"Mirchel",
    "sg:orig_category":"Sportvereine Turnen",
    "sg:postcode":"3532",
    "sg:province":"Bern",
    "wof:name":"Altersturnen Mirchel",
    "wof:placetype":"venue"
},
  "geometry": {"coordinates":[7.6440439224,46.8932952881],"type":"Point"}
}