{
  "type": "Feature",
  "properties": {
    "iso:country":"CH",
    "sg:address":"Hirzbodenweg 50",
    "sg:city":"Basel",
    "sg:orig_category":"Vermietung U Verpachtung von eigenen Immobilien",
    "sg:postcode":"4001",
    "sg:province":"Basel-Stadt",
    "wof:name":"Els Caials Ag",
    "wof:placetype":"venue"
},
  "geometry": {"coordinates":[7.6078228951,47.5496063232],"type":"Point"}
}