{
  "type": "Feature",
  "properties": {
    "iso:country":"CH",
    "sg:address":"3932",
    "sg:city":"Visperterminen",
    "sg:orig_category":"Detailhandel mit Sportartikeln Detailhandel mit Waren verschiedener Art, Hauptrichtung Nahrungsmitte",
    "sg:phone":"+41 27 946 45 52",
    "sg:postcode":"3932",
    "sg:province":"Valais",
    "wof:name":"Alex Heinzmann Handlung Sport",
    "wof:placetype":"venue"
},
  "geometry": {"coordinates":[7.9026641846,46.2593460083],"type":"Point"}
}