{
  "type": "Feature",
  "properties": {
    "iso:country":"CH",
    "sg:address":"Lyssstrasse 75",
    "sg:city":"Nidau",
    "sg:orig_category":"Sonstige pers\u00f6nliche Dienstleistungen",
    "sg:phone":"+41 32 365 83 52",
    "sg:postcode":"2560",
    "sg:province":"Bern",
    "wof:name":"Deep Colours, Michel Voirol",
    "wof:placetype":"venue"
},
  "geometry": {"coordinates":[7.250166893,47.1248168945],"type":"Point"}
}