{
  "type": "Feature",
  "properties": {
    "iso:country":"CH",
    "sg:address":"Cond\u00e9mine Rue De La 56",
    "sg:city":"Bulle",
    "sg:orig_category":"Non-Classified Establishments",
    "sg:postcode":"1630",
    "sg:province":"Fribourg",
    "wof:name":"Aur\u00e9co S\u00e0rl",
    "wof:placetype":"venue"
},
  "geometry": {"coordinates":[7.060300827,46.6209983826],"type":"Point"}
}