{
  "type": "Feature",
  "properties": {
    "iso:country":"CH",
    "sg:address":"Hauptstr. 4",
    "sg:city":"Muttenz",
    "sg:classifiers":[
        {
            "category":"Travel",
            "subcategory":"Hotels & Motels",
            "type":"Entertainment"
        }
    ],
    "sg:phone":"+41 81 415 60 00",
    "sg:postcode":"4132",
    "sg:province":"Basel-Landschaft",
    "sg:tags":[
        "professional",
        "hotels",
        "fair",
        "business",
        "restaurant"
    ],
    "wof:name":"Steigenberger Hotel Belvedere",
    "wof:placetype":"venue"
},
  "geometry": {"coordinates":[9.825842,46.800434],"type":"Point"}
}