{
  "type": "Feature",
  "properties": {
    "addr:full":"Rue St-pierre 12 Fribourg Fribourg 1700",
    "addr:housenumber":"12",
    "addr:postcode":"1700",
    "addr:street":"Rue St-Pierre",
    "iso:country":"CH",
    "sg:address":"Rue St-pierre 12",
    "sg:city":"Fribourg",
    "sg:orig_category":"Arztpraxen",
    "sg:phone":"+41 26 401 91 44",
    "sg:postcode":"1700",
    "sg:province":"Fribourg",
    "wof:name":"Dr M\u00e9d. Fr\u00e9d\u00e9rique Zihlmann M\u00e9decin Sp\u00e9cialiste Fmh",
    "wof:placetype":"venue"
},
  "geometry": {"coordinates":[7.114826,46.794781],"type":"Point"}
}