{
  "type": "Feature",
  "properties": {
    "iso:country":"CH",
    "sg:address":"Ruggh\u00f6lzli 5",
    "sg:city":"Busslingen",
    "sg:classifiers":[
        {
            "category":"Home & Garden",
            "subcategory":"Home Furnishings",
            "type":"Retail Goods"
        }
    ],
    "sg:phone":"+41 56 496 36 24",
    "sg:postcode":"5453",
    "sg:province":"Aargau",
    "sg:tags":[
        "medicine",
        "bathroom",
        "cupboards",
        "cabinet"
    ],
    "wof:name":"Badex Ag",
    "wof:placetype":"venue"
},
  "geometry": {"coordinates":[8.313141,47.410381],"type":"Point"}
}