{
  "type": "Feature",
  "properties": {
    "iso:country":"CH",
    "sg:address":"Neugutstrasse 5 8425 Oberembrach. Postfach",
    "sg:city":"Oberembrach",
    "sg:orig_category":"Herstellung von rohen \u00d6len U Fetten",
    "sg:postcode":"8425",
    "sg:province":"Z\u00fcrich",
    "wof:name":"Botega Di Olio Gmbh",
    "wof:placetype":"venue"
},
  "geometry": {"coordinates":[8.3763141632,46.9528541565],"type":"Point"}
}