{
  "type": "Feature",
  "properties": {
    "iso:country":"CH",
    "sg:address":"Richard Wagner-strasse 23",
    "sg:city":"Z\u00fcrich",
    "sg:orig_category":"Sonstige pers\u00f6nliche Dienstleistungen",
    "sg:postcode":"8002",
    "sg:province":"Z\u00fcrich",
    "wof:name":"Susanne Sandor, Private Residence Management Gmbh",
    "wof:placetype":"venue"
},
  "geometry": {"coordinates":[8.5330257416,47.3593940735],"type":"Point"}
}