{
  "type": "Feature",
  "properties": {
    "iso:country":"CH",
    "sg:address":"Stegenweg 31 3172 Niederwangen Be. Postfach",
    "sg:city":"Bern",
    "sg:orig_category":"Haltung von Rindern",
    "sg:postcode":"3018",
    "sg:province":"Bern",
    "wof:name":"Viehzuchtgenossenschaft Niederbottigen",
    "wof:placetype":"venue"
},
  "geometry": {"coordinates":[7.3705000877,46.9264183044],"type":"Point"}
}