{
  "type": "Feature",
  "properties": {
    "addr:full":"Burgerstrasse 35 Thun Bern 3600",
    "addr:housenumber":"35",
    "addr:postcode":"3600",
    "addr:street":"Burgerstrasse;Bern",
    "iso:country":"CH",
    "sg:address":"Burgerstrasse 35",
    "sg:city":"Thun",
    "sg:orig_category":"Architekturb\u00fcros",
    "sg:phone":"+41 33 223 33 85",
    "sg:postcode":"3600",
    "sg:province":"Bern",
    "wof:name":"Feller & Kohler Ag Architekturb\u00fcro",
    "wof:placetype":"venue"
},
  "geometry": {"coordinates":[7.613034,46.746212],"type":"Point"}
}