{
  "type": "Feature",
  "properties": {
    "iso:country":"CH",
    "sg:address":"Oberwil",
    "sg:city":"Cham",
    "sg:orig_category":"Strassenbau",
    "sg:phone":"+41 41 780 36 34",
    "sg:postcode":"6330",
    "sg:province":"Zug",
    "wof:name":"Walo Bertschinger Ag Bauunternehmung",
    "wof:placetype":"venue"
},
  "geometry": {"coordinates":[8.4593954086,47.2092208862],"type":"Point"}
}