{
  "type": "Feature",
  "properties": {
    "iso:country":"CH",
    "sg:address":"Schwerzistrasse 37",
    "sg:city":"Freienbach",
    "sg:orig_category":"Unclassifiable Establishments",
    "sg:phone":"+41 27 474 61 71",
    "sg:postcode":"8807",
    "sg:province":"Schwyz",
    "wof:name":"Kraftwerk Dala Ag",
    "wof:placetype":"venue"
},
  "geometry": {"coordinates":[7.6346597672,46.3163299561],"type":"Point"}
}