{
  "type": "Feature",
  "properties": {
    "iso:country":"CH",
    "sg:address":"Zellgut 11",
    "sg:city":"Schenkon",
    "sg:orig_category":"Zimmerei, Ingenieurholzbau",
    "sg:phone":"+41 41 926 71 80",
    "sg:postcode":"6214",
    "sg:province":"Luzern",
    "wof:name":"Tr\u00fcssel Datentechnik Ag",
    "wof:placetype":"venue"
},
  "geometry": {"coordinates":[8.1235942841,47.1769714355],"type":"Point"}
}