{
  "type": "Feature",
  "properties": {
    "iso:country":"CH",
    "sg:address":"Grand-rue 63",
    "sg:city":"Gland",
    "sg:classifiers":[
        {
            "category":"Insurance",
            "subcategory":"Insurance Agent",
            "type":"Services"
        }
    ],
    "sg:phone":"+41 22 364 42 44",
    "sg:postcode":"1196",
    "sg:province":"Vaud",
    "sg:tags":[
        "versicherungsagenturen",
        "-broker"
    ],
    "wof:name":"Winterthur Assurances Agence De Gland",
    "wof:placetype":"venue"
},
  "geometry": {"coordinates":[6.2653331757,46.4241523743],"type":"Point"}
}