{
  "type": "Feature",
  "properties": {
    "iso:country":"CH",
    "sg:address":"Stadthausstrasse 2 4950 Huttwil. Postfach",
    "sg:city":"Huttwil",
    "sg:orig_category":"Sonstige mit Sport verbundene T\u00e4tigkeiten",
    "sg:phone":"+41 41 210 43 33",
    "sg:postcode":"4950",
    "sg:province":"Bern",
    "wof:name":"Rowing World Championships 2001",
    "wof:placetype":"venue"
},
  "geometry": {"coordinates":[7.8483939171,47.1136016846],"type":"Point"}
}