{
  "type": "Feature",
  "properties": {
    "iso:country":"CH",
    "sg:address":"Clausiusstrasse 6",
    "sg:city":"Z\u00fcrich",
    "sg:orig_category":"Pensionskassen",
    "sg:postcode":"8006",
    "sg:province":"Z\u00fcrich",
    "wof:name":"Personalf\u00fcrsorge-stiftung Der Schweizerischen Bundesfeier-spende",
    "wof:placetype":"venue"
},
  "geometry": {"coordinates":[8.547170639,47.377784729],"type":"Point"}
}