{
  "type": "Feature",
  "properties": {
    "iso:country":"CH",
    "sg:address":"Ennetb\u00fcrgerstrasse 10",
    "sg:city":"Buochs",
    "sg:orig_category":"RESTAURANTS: TEA-ROOMS",
    "sg:phone":"+41 41 620 34 34",
    "sg:postcode":"6374",
    "sg:province":"Nidwalden",
    "wof:name":"Th\u00fcring-prodanova Veska",
    "wof:placetype":"venue"
},
  "geometry": {"coordinates":[8.4199962616,46.9749679565],"type":"Point"}
}