{
  "type": "Feature",
  "properties": {
    "addr:full":"Steinenring 40 Basel Basel-Stadt 4051",
    "addr:housenumber":"40",
    "addr:postcode":"4051",
    "addr:street":"Steinenring",
    "iso:country":"CH",
    "sg:address":"Steinenring 40",
    "sg:city":"Basel",
    "sg:orig_category":"Architektur U Ingenieurb\u00fcros",
    "sg:phone":"+41 61 281 02 02",
    "sg:postcode":"4051",
    "sg:province":"Basel-Stadt",
    "wof:name":"Baso Ag",
    "wof:placetype":"venue"
},
  "geometry": {"coordinates":[7.579632,47.551102],"type":"Point"}
}