{
  "type": "Feature",
  "properties": {
    "iso:country":"CH",
    "sg:address":"Avenue Florimont 9",
    "sg:city":"Lausanne",
    "sg:orig_category":"Verlegen von Fliesen U Platten",
    "sg:phone":"+41 21 323 21 90",
    "sg:postcode":"1006",
    "sg:province":"Vaud",
    "wof:name":"Elio Fiore Entreprise De Carrelage",
    "wof:placetype":"venue"
},
  "geometry": {"coordinates":[6.6388268471,46.5156822205],"type":"Point"}
}