{
  "type": "Feature",
  "properties": {
    "iso:country":"CH",
    "sg:address":"Kraftstrasse 28",
    "sg:city":"Z\u00fcrich",
    "sg:orig_category":"Sonstiger Grosshandel",
    "sg:postcode":"8044",
    "sg:province":"Z\u00fcrich",
    "wof:name":"Rainbow Mineralien, M. B\u00e4chtold",
    "wof:placetype":"venue"
},
  "geometry": {"coordinates":[8.559762001,47.377696991],"type":"Point"}
}