{
  "type": "Feature",
  "properties": {
    "iso:country":"CH",
    "sg:address":"Stansstaderstrasse 20 6370 Stans. Postfach 34",
    "sg:city":"Stans",
    "sg:orig_category":"Zahnarztpraxen",
    "sg:phone":"+41 81 756 26 49",
    "sg:postcode":"6371",
    "sg:province":"Nidwalden",
    "wof:name":"Dr. Med. Dent. Hugo Kostezer Zahnarzt",
    "wof:placetype":"venue"
},
  "geometry": {"coordinates":[9.4771289825,47.1660881042],"type":"Point"}
}