{
  "type": "Feature",
  "properties": {
    "iso:country":"CH",
    "sg:address":"Via Leoncavallo 46",
    "sg:city":"Brissago",
    "sg:orig_category":"RESTAURANTS: TEA-ROOMS",
    "sg:postcode":"6614",
    "sg:province":"Ticino",
    "wof:name":"Storelli Pier Carlo",
    "wof:placetype":"venue"
},
  "geometry": {"coordinates":[8.7080802917,46.1171112061],"type":"Point"}
}