{
  "type": "Feature",
  "properties": {
    "iso:country":"CH",
    "sg:address":"Route De Tramelan 2",
    "sg:city":"Tavannes",
    "sg:orig_category":"Handel mit Motorr\u00e4dern, Teilen U Zubeh\u00f6r Instandhaltung U Reparatur von Automobilen Instandhaltung U",
    "sg:phone":"+41 32 481 32 20",
    "sg:postcode":"2710",
    "sg:province":"Bern",
    "wof:name":"Garage Vuilleumier S\u00e0rl",
    "wof:placetype":"venue"
},
  "geometry": {"coordinates":[7.1982159615,47.2206115723],"type":"Point"}
}