{
  "type": "Feature",
  "properties": {
    "iso:country":"CH",
    "sg:address":"Wilerstrasse 8",
    "sg:city":"Rorbas",
    "sg:orig_category":"Schnelldruck U Kopierservice Siebdruck",
    "sg:phone":"+41 56 664 32 28",
    "sg:postcode":"8427",
    "sg:province":"Z\u00fcrich",
    "wof:name":"Brugger's Copy-shop Kopiercenter Usw",
    "wof:placetype":"venue"
},
  "geometry": {"coordinates":[8.3174819946,47.2825775146],"type":"Point"}
}