{
  "type": "Feature",
  "properties": {
    "iso:country":"CH",
    "sg:address":"Centralstrasse 325",
    "sg:city":"Berom\u00fcnster",
    "sg:orig_category":"Erbringung von Dienstleistungen f\u00fcr Unternehmen",
    "sg:phone":"+41 41 931 00 56",
    "sg:postcode":"6215",
    "sg:province":"Luzern",
    "wof:name":"Design By Bole Polesel Adriano",
    "wof:placetype":"venue"
},
  "geometry": {"coordinates":[8.1906604767,47.2065696716],"type":"Point"}
}