{
  "type": "Feature",
  "properties": {
    "iso:country":"CH",
    "sg:address":"Schwarzenburgstrasse 1021",
    "sg:city":"Mittelh\u00e4usern",
    "sg:orig_category":"Oberfl\u00e4chenveredlung U W\u00e4rmebehandlung",
    "sg:phone":"+41 31 849 01 11",
    "sg:postcode":"3147",
    "sg:province":"Bern",
    "wof:name":"R. Schlierholz Ag",
    "wof:placetype":"venue"
},
  "geometry": {"coordinates":[7.3654398918,46.8747520447],"type":"Point"}
}