{
  "type": "Feature",
  "properties": {
    "iso:country":"CH",
    "sg:address":"Talb\u00e4chliweg 5 8048 Z\u00fcrich. Postfach",
    "sg:city":"Z\u00fcrich",
    "sg:orig_category":"Gartenbau",
    "sg:phone":"+41 14300370",
    "sg:postcode":"8048",
    "sg:province":"Z\u00fcrich",
    "wof:name":"Berner F. Gartenbau Ag",
    "wof:placetype":"venue"
},
  "geometry": {"coordinates":[8.4676837921,47.3890533447],"type":"Point"}
}