{
  "type": "Feature",
  "properties": {
    "iso:country":"CH",
    "sg:address":"Neugutstrasse 54",
    "sg:city":"D\u00fcbendorf",
    "sg:classifiers":[
        {
            "category":"Insurance",
            "subcategory":"Insurance Agent",
            "type":"Services"
        }
    ],
    "sg:phone":"+41 18222520",
    "sg:postcode":"8600",
    "sg:province":"Z\u00fcrich",
    "sg:tags":[
        "versicherungsagenturen",
        "-broker"
    ],
    "wof:name":"Swissbroke Ag",
    "wof:placetype":"venue"
},
  "geometry": {"coordinates":[8.6084766388,47.3999977112],"type":"Point"}
}