{
  "type": "Feature",
  "properties": {
    "iso:country":"CH",
    "sg:address":"Zentralstrasse 99",
    "sg:city":"Biel/bienne",
    "sg:orig_category":"Herstellung von Schl\u00f6ssern U Beschl\u00e4gen",
    "sg:phone":"+41 32 322 00 22",
    "sg:postcode":"2503",
    "sg:province":"Bern",
    "wof:name":"Schl\u00fcssel Fischer Ag Biel",
    "wof:placetype":"venue"
},
  "geometry": {"coordinates":[7.2500500679,47.1336936951],"type":"Point"}
}