{
  "type": "Feature",
  "properties": {
    "iso:country":"CH",
    "sg:address":"Mara\u00eechers Rue Des 10 Bis 1205 Gen\u00e8ve. Postfach",
    "sg:city":"Gen\u00e8ve",
    "sg:orig_category":"Herstellung von sonstigen Erzeugnissen",
    "sg:postcode":"1205",
    "sg:province":"Gen\u00e8ve",
    "wof:name":"Raymann Rita, Blumen-dekorationen",
    "wof:placetype":"venue"
},
  "geometry": {"coordinates":[8.9753503799,47.2459716797],"type":"Point"}
}