{
  "type": "Feature",
  "properties": {
    "iso:country":"CH",
    "sg:address":"Schmalzgrubenstrasse 6",
    "sg:city":"Unteriberg",
    "sg:orig_category":"Unclassifiable Establishments",
    "sg:phone":"+41 55 414 11 83",
    "sg:postcode":"8842",
    "sg:province":"Schwyz",
    "wof:name":"Ott Walter",
    "wof:placetype":"venue"
},
  "geometry": {"coordinates":[8.8024082184,47.0596961975],"type":"Point"}
}