{
  "type": "Feature",
  "properties": {
    "iso:country":"CH",
    "sg:address":"Ottilienstrasse 17",
    "sg:city":"Z\u00fcrich",
    "sg:orig_category":"Satzherstellung U Reproduktion Werbung",
    "sg:phone":"+41 31 386 10 10",
    "sg:postcode":"8003",
    "sg:province":"Z\u00fcrich",
    "wof:name":"Quer Werbefabrik Ag",
    "wof:placetype":"venue"
},
  "geometry": {"coordinates":[7.4181890488,46.9477767944],"type":"Point"}
}