{
  "type": "Feature",
  "properties": {
    "iso:country":"CH",
    "sg:address":"Schlossbergstr. 6",
    "sg:city":"Tr\u00fcllikon",
    "sg:orig_category":"Detailhandel mit B\u00fcchern, Zeitungen, Schreib U Papeteriewaren",
    "sg:phone":"+41 52 319 28 90",
    "sg:postcode":"8466",
    "sg:province":"Z\u00fcrich",
    "wof:name":"Idea Pool Gmbh",
    "wof:placetype":"venue"
},
  "geometry": {"coordinates":[8.67546,47.641022],"type":"Point"}
}