{
  "type": "Feature",
  "properties": {
    "iso:country":"CH",
    "sg:address":"Hauptstrasse",
    "sg:city":"Einsiedeln",
    "sg:orig_category":"Detailhandel mit Fleisch U Fleischwaren",
    "sg:postcode":"8840",
    "sg:province":"Schwyz",
    "wof:name":"Keller Rudolf",
    "wof:placetype":"venue"
},
  "geometry": {"coordinates":[8.7440900803,47.127456665],"type":"Point"}
}