{
  "type": "Feature",
  "properties": {
    "iso:country":"CH",
    "sg:address":"Grands-pr\u00e9s Rue Des 7",
    "sg:city":"Bassecourt",
    "sg:orig_category":"Non-Classified Establishments",
    "sg:postcode":"2854",
    "sg:province":"Jura",
    "wof:name":"Mahy Philippe S\u00e0rl",
    "wof:placetype":"venue"
},
  "geometry": {"coordinates":[7.2413349152,47.338809967],"type":"Point"}
}