{
  "type": "Feature",
  "properties": {
    "iso:country":"CH",
    "sg:address":"6487",
    "sg:city":"G\u00f6schenen",
    "sg:orig_category":"Vorschulen, Kinderg\u00e4rten",
    "sg:phone":"+41 41 885 16 58",
    "sg:postcode":"6487",
    "sg:province":"Uri",
    "wof:name":"Kindergarten Schulhaus",
    "wof:placetype":"venue"
},
  "geometry": {"coordinates":[8.5886049271,46.6678733826],"type":"Point"}
}