{
  "type": "Feature",
  "properties": {
    "iso:country":"CH",
    "sg:address":"Allmendstrasse 6",
    "sg:city":"Ebertswil",
    "sg:orig_category":"Handelsvermittlung U Grosshandel R\u00fcckgewinnung U Vorbereitung f\u00fcr die Wiederverwertung Recycling von",
    "sg:phone":"+41 17640567",
    "sg:postcode":"8925",
    "sg:province":"Z\u00fcrich",
    "wof:name":"Wilhelm Nydegger",
    "wof:placetype":"venue"
},
  "geometry": {"coordinates":[8.5506305695,47.2265663147],"type":"Point"}
}