{
  "type": "Feature",
  "properties": {
    "iso:country":"CH",
    "sg:address":"Friedengasse 72",
    "sg:city":"Basel",
    "sg:orig_category":"Institutionen des Sozialwesens ohne Beherbergung",
    "sg:postcode":"4000",
    "sg:province":"Basel-Stadt",
    "wof:name":"Podere Fiorli Toscana O.n.l.u.s.",
    "wof:placetype":"venue"
},
  "geometry": {"coordinates":[7.5758261681,47.5611114502],"type":"Point"}
}