{
  "type": "Feature",
  "properties": {
    "iso:country":"CH",
    "sg:address":"St. Johanns-vorstadt 38 4056 Basel. Postfach",
    "sg:city":"Basel",
    "sg:orig_category":"Offsetdruck Satzherstellung U Reproduktion",
    "sg:phone":"+41 61 322 54 55",
    "sg:postcode":"4004",
    "sg:province":"Basel-Stadt",
    "wof:name":"Lichtpaus Basel A. K\u00e4mpf",
    "wof:placetype":"venue"
},
  "geometry": {"coordinates":[7.5845241547,47.563785553],"type":"Point"}
}