{
  "type": "Feature",
  "properties": {
    "iso:country":"CH",
    "sg:address":"Route Cantonale",
    "sg:city":"Vernayaz",
    "sg:classifiers":[
        {
            "category":"Restaurant",
            "type":"Food & Drink"
        }
    ],
    "sg:phone":"+41 27 764 14 52",
    "sg:postcode":"1904",
    "sg:province":"Valais",
    "wof:name":"Restaurant Progr\u00e8s",
    "wof:placetype":"venue"
},
  "geometry": {"coordinates":[7.0310292244,46.1540145874],"type":"Point"}
}