{
  "type": "Feature",
  "properties": {
    "iso:country":"CH",
    "sg:address":"Rue De La Promenade 29",
    "sg:city":"Tramlingen",
    "sg:orig_category":"Herstellung U Zusammensetzung von Uhren Herstellung von Uhren",
    "sg:phone":"+41 32 953 20 10",
    "sg:postcode":"2720",
    "sg:province":"Bern",
    "wof:name":"A\u00e9ro Watch Sa",
    "wof:placetype":"venue"
},
  "geometry": {"coordinates":[6.9546117783,47.2242927551],"type":"Point"}
}