{
  "type": "Feature",
  "properties": {
    "iso:country":"CH",
    "sg:address":"6918",
    "sg:city":"Figino",
    "sg:orig_category":"Gartenbau",
    "sg:phone":"+41 91 995 16 50",
    "sg:postcode":"6918",
    "sg:province":"Ticino",
    "wof:name":"Claudio Atti Costruzione & Manut.giardini",
    "wof:placetype":"venue"
},
  "geometry": {"coordinates":[8.9106302261,45.9521484375],"type":"Point"}
}