{
  "type": "Feature",
  "properties": {
    "iso:country":"CH",
    "sg:address":"Trom 3780 Gruben B. Gstaad. Postfach",
    "sg:city":"Gstaad",
    "sg:orig_category":"Zimmerei, Dachdeckerei, Bauspenglerei U Abdichtung",
    "sg:phone":"+41 62 291 46 46",
    "sg:postcode":"3780",
    "sg:province":"Bern",
    "wof:name":"Voney R. Gmbh",
    "wof:placetype":"venue"
},
  "geometry": {"coordinates":[7.9947161674,47.3377456665],"type":"Point"}
}