{
  "type": "Feature",
  "properties": {
    "iso:country":"CH",
    "sg:address":"M\u00fcnteschmiergasse 30",
    "sg:city":"Ins",
    "sg:orig_category":"Mechanik Mechanische Werkst\u00e4tten",
    "sg:phone":"+41 32 926 79 66",
    "sg:postcode":"3232",
    "sg:province":"Bern",
    "wof:name":"Revisa, Giorgini G.",
    "wof:placetype":"venue"
},
  "geometry": {"coordinates":[6.8021578789,47.086566925],"type":"Point"}
}