{
  "type": "Feature",
  "properties": {
    "iso:country":"CH",
    "sg:address":"Gr\u00fcningerstrasse 292 8626 Ottikon. Postfach",
    "sg:city":"Ottikon",
    "sg:orig_category":"Sonstiger Fachdetailhandel mit Nahrungsmitteln, Getr\u00e4nken U Tabak in Verkaufsr\u00e4umen",
    "sg:postcode":"8626",
    "sg:province":"Z\u00fcrich",
    "wof:name":"K\u00e4serei Berger",
    "wof:placetype":"venue"
},
  "geometry": {"coordinates":[8.7757902145,47.2921714783],"type":"Point"}
}