{
  "type": "Feature",
  "properties": {
    "iso:country":"CH",
    "sg:address":"Am Suteracher 35",
    "sg:city":"Z\u00fcrich",
    "sg:orig_category":"Sportvereine Ballsport Tischtennis",
    "sg:phone":"+41 14328310",
    "sg:postcode":"8048",
    "sg:province":"Z\u00fcrich",
    "wof:name":"Ttc Weiningen",
    "wof:placetype":"venue"
},
  "geometry": {"coordinates":[8.4705915451,47.3900985718],"type":"Point"}
}