{
  "type": "Feature",
  "properties": {
    "iso:country":"CH",
    "sg:address":"Schulweg 12",
    "sg:city":"Niederhasli",
    "sg:orig_category":"Bau von Strassen, Sportanlagen U Bahnverkehrsstrecken",
    "sg:postcode":"8155",
    "sg:province":"Z\u00fcrich",
    "wof:name":"Minder & Pfister, Bio-clean",
    "wof:placetype":"venue"
},
  "geometry": {"coordinates":[8.500403,47.4646],"type":"Point"}
}