{
  "type": "Feature",
  "properties": {
    "iso:country":"CH",
    "sg:address":"Eugen Huber-strasse 19a",
    "sg:city":"Z\u00fcrich",
    "sg:orig_category":"Markt U Meinungsforschung",
    "sg:phone":"+41 14353000",
    "sg:postcode":"8000",
    "sg:province":"Z\u00fcrich",
    "wof:name":"Cks Marketing Agency Ag",
    "wof:placetype":"venue"
},
  "geometry": {"coordinates":[8.4809503555,47.3614616394],"type":"Point"}
}