{
  "type": "Feature",
  "properties": {
    "iso:country":"CH",
    "sg:address":"8754",
    "sg:city":"Netstal",
    "sg:orig_category":"Verkehrs- and Tourismusb\u00fcros",
    "sg:postcode":"8754",
    "sg:province":"Glarus",
    "wof:name":"Verkehrsverein",
    "wof:placetype":"venue"
},
  "geometry": {"coordinates":[9.0356998444,47.0660896301],"type":"Point"}
}