{
  "type": "Feature",
  "properties": {
    "iso:country":"CH",
    "sg:address":"Chemin Franoz 11 1038 Bercher. Postfach",
    "sg:city":"Bercher",
    "sg:orig_category":"Forschung U Entwicklung im Bereich der Naturwissenschaften",
    "sg:postcode":"1038",
    "sg:province":"Vaud",
    "wof:name":"Gg Consulting S\u00e0rl, Bercher Etudes Et Projets, Principalement D. Le Dom. E La For\u00eat, Du Bois, De La Protection De La Nature Etc",
    "wof:placetype":"venue"
},
  "geometry": {"coordinates":[6.7061100006,46.6944084167],"type":"Point"}
}