{
  "type": "Feature",
  "properties": {
    "addr:full":"Villettaz Nax Valais 1973",
    "addr:housenumber":"1973",
    "iso:country":"CH",
    "sg:address":"Villettaz",
    "sg:city":"Nax",
    "sg:orig_category":"Campingpl\u00e4tze Detailhandel mit Zeitungen U Zeitschriften Kioske",
    "sg:phone":"+41 27 203 17 95",
    "sg:postcode":"1973",
    "sg:province":"Valais",
    "wof:name":"Camping Piscine Petit-paradis",
    "wof:placetype":"venue"
},
  "geometry": {"coordinates":[7.426714,46.22781],"type":"Point"}
}