{
  "type": "Feature",
  "properties": {
    "iso:country":"CH",
    "sg:address":"Goldgrubenweg 2",
    "sg:city":"Biel/bienne",
    "sg:orig_category":"Fotografische Ateliers",
    "sg:phone":"+41 32 322 45 62",
    "sg:postcode":"2504",
    "sg:province":"Bern",
    "wof:name":"Friedrich Achermann Fotografisches Atelier",
    "wof:placetype":"venue"
},
  "geometry": {"coordinates":[7.2783660889,47.1473388672],"type":"Point"}
}