{
  "type": "Feature",
  "properties": {
    "addr:full":"Rue De La Pran 17 Glovelier Jura 2855",
    "addr:housenumber":"17",
    "addr:postcode":"2855",
    "addr:street":"Rue De La Pran;Jura",
    "iso:country":"CH",
    "sg:address":"Rue De La Pran 17",
    "sg:city":"Glovelier",
    "sg:orig_category":"Arztpraxen",
    "sg:phone":"+41 32 426 58 28",
    "sg:postcode":"2855",
    "sg:province":"Jura",
    "wof:name":"Dr M\u00e9d. Armand Rion M\u00e9decin G\u00e9n\u00e9raliste",
    "wof:placetype":"venue"
},
  "geometry": {"coordinates":[7.202592,47.334484],"type":"Point"}
}