{
  "type": "Feature",
  "properties": {
    "iso:country":"CH",
    "sg:address":"Lischenweg 34",
    "sg:city":"Biel/bienne",
    "sg:orig_category":"Sportschulen Wassersport",
    "sg:phone":"+41 61 365 22 22",
    "sg:postcode":"2503",
    "sg:province":"Bern",
    "wof:name":"Aebo Holding Ag Beteiligungen Usw",
    "wof:placetype":"venue"
},
  "geometry": {"coordinates":[7.257376194,47.1253128052],"type":"Point"}
}