{
  "type": "Feature",
  "properties": {
    "iso:country":"CH",
    "sg:address":"Rte D'echallens",
    "sg:city":"Froideville",
    "sg:orig_category":"Softwareentwicklung U beratung",
    "sg:postcode":"1055",
    "sg:province":"Vaud",
    "wof:name":"Backup Associates Snc, Ferr\u00e9ol M.-c. & Rodriguez E.",
    "wof:placetype":"venue"
},
  "geometry": {"coordinates":[6.6692647934,46.6014938354],"type":"Point"}
}