{
  "type": "Feature",
  "properties": {
    "iso:country":"CH",
    "sg:address":"Thermenstrasse 15",
    "sg:city":"Rheinfelden",
    "sg:orig_category":"Herstellung von keramischen Wand U Bodenfliesen U platten Verlegen von Fliesen U Platten",
    "sg:postcode":"4310",
    "sg:province":"Aargau",
    "wof:name":"Peter Ganz",
    "wof:placetype":"venue"
},
  "geometry": {"coordinates":[7.8020858765,47.549785614],"type":"Point"}
}