{
  "type": "Feature",
  "properties": {
    "iso:country":"CH",
    "sg:address":"Ch\u00e2teau Verd 6 1170 Aubonne. Postfach",
    "sg:city":"Aubonne",
    "sg:orig_category":"Herstellung von Karosserien U Anh\u00e4ngern",
    "sg:phone":"+41 24 454 43 28",
    "sg:postcode":"1170",
    "sg:province":"Vaud",
    "wof:name":"Caravanes Du Ch\u00e2teau, Walthert G. Caravanes Et Accessoires; Commerce, R\u00e9paration, Entretien",
    "wof:placetype":"venue"
},
  "geometry": {"coordinates":[6.5316710472,46.8241958618],"type":"Point"}
}