{
  "type": "Feature",
  "properties": {
    "iso:country":"CH",
    "sg:address":"Oberdorf",
    "sg:city":"T\u00fcscherz-alferm\u00e9e",
    "sg:orig_category":"Detailhandel mit Getr\u00e4nken Rebbau",
    "sg:phone":"+41 32 322 82 78",
    "sg:postcode":"2512",
    "sg:province":"Bern",
    "wof:name":"Lydia Hirt",
    "wof:placetype":"venue"
},
  "geometry": {"coordinates":[7.1903748512,47.1124458313],"type":"Point"}
}