{
  "type": "Feature",
  "properties": {
    "iso:country":"CH",
    "sg:address":"Bergstrasse 103",
    "sg:city":"Meilen",
    "sg:orig_category":"Bentonite Pumps",
    "sg:phone":"+41 19254111",
    "sg:postcode":"8706",
    "sg:province":"Z\u00fcrich",
    "wof:name":"H\u00e4ny Ag",
    "wof:placetype":"venue"
},
  "geometry": {"coordinates":[8.655,47.268124],"type":"Point"}
}