{
  "type": "Feature",
  "properties": {
    "iso:country":"CH",
    "sg:address":"Weststrasse 49 8003 Z\u00fcrich. Postfach 440",
    "sg:city":"Z\u00fcrich",
    "sg:orig_category":"Grosshandel mit sonstigen Gebrauchs U Verbrauchsg\u00fctern Grosshandel mit sonstigen Halbwaren",
    "sg:phone":"+41 14616264",
    "sg:postcode":"8027",
    "sg:province":"Z\u00fcrich",
    "wof:name":"Quality Paper Gmbh Papier; Handel",
    "wof:placetype":"venue"
},
  "geometry": {"coordinates":[8.5227174759,47.369972229],"type":"Point"}
}