{
  "type": "Feature",
  "properties": {
    "iso:country":"CH",
    "sg:address":"Via Camara 58",
    "sg:city":"Breganzona",
    "sg:orig_category":"Vereine Radio, Film and Foto",
    "sg:postcode":"6932",
    "sg:province":"Ticino",
    "wof:name":"Ass.lugan.foto-cine-dilettanti",
    "wof:placetype":"venue"
},
  "geometry": {"coordinates":[8.9299478531,46.0096664429],"type":"Point"}
}