{
  "type": "Feature",
  "properties": {
    "iso:country":"CH",
    "sg:address":"Bundesplatz 16 6300 Zug. Postfach",
    "sg:city":"Zug",
    "sg:orig_category":"Vermietung U Verpachtung von eigenen Immobilien",
    "sg:phone":"+41 71 966 29 77",
    "sg:postcode":"6300",
    "sg:province":"Zug",
    "wof:name":"Konrad Hansruedi",
    "wof:placetype":"venue"
},
  "geometry": {"coordinates":[8.9856271744,47.4749412537],"type":"Point"}
}