{
  "type": "Feature",
  "properties": {
    "iso:country":"CH",
    "sg:address":"Rotterdam-strasse 21",
    "sg:city":"Basel",
    "sg:orig_category":"Verlegen von Fliesen U Platten",
    "sg:phone":"+41 61 721 37 57",
    "sg:postcode":"4053",
    "sg:province":"Basel-Stadt",
    "wof:name":"Ganter Ag Keram. Wand, Bodenbel\u00e4ge, Natursteinbearbeitung Usw",
    "wof:placetype":"venue"
},
  "geometry": {"coordinates":[7.6056852341,47.5343437195],"type":"Point"}
}