{
  "type": "Feature",
  "properties": {
    "iso:country":"CH",
    "sg:address":"Sulgenheimweg 21 3007 Bern. Postfach 5261",
    "sg:city":"Bern",
    "sg:orig_category":"Konsulate",
    "sg:phone":"+41 31 359 41 11",
    "sg:postcode":"3001",
    "sg:province":"Bern",
    "wof:name":"Ambassade De La R\u00e9publique F\u00e9d\u00e9rale D'allemagne",
    "wof:placetype":"venue"
},
  "geometry": {"coordinates":[7.462553978,46.9349555969],"type":"Point"}
}