{
  "type": "Feature",
  "properties": {
    "iso:country":"CH",
    "sg:address":"Landstrasse 1",
    "sg:city":"Rothenthurm",
    "sg:orig_category":"Cardboard Mailing Envelopes",
    "sg:phone":"+41 41 838 17 17",
    "sg:postcode":"6418",
    "sg:province":"Schwyz",
    "wof:name":"Gasser H\u00fclsen Gmbh",
    "wof:placetype":"venue"
},
  "geometry": {"coordinates":[8.669482,47.094849],"type":"Point"}
}