{
  "type": "Feature",
  "properties": {
    "iso:country":"CH",
    "sg:address":"Wettsteinstrasse 6",
    "sg:city":"Riehen",
    "sg:orig_category":"Detailhandel mit Bekleidung Detailhandel mit Damenbekleidung",
    "sg:phone":"+41 61 641 63 83",
    "sg:postcode":"4125",
    "sg:province":"Basel-Stadt",
    "wof:name":"A La Mode, Littmann Christiane",
    "wof:placetype":"venue"
},
  "geometry": {"coordinates":[7.650537,47.584328],"type":"Point"}
}