{
  "type": "Feature",
  "properties": {
    "iso:country":"CH",
    "sg:address":"Allmendstrasse 8",
    "sg:city":"Fehraltorf",
    "sg:orig_category":"Grosshandel mit Maschinen U Ausr\u00fcstungen Herstellung von sonstigen Maschinen f\u00fcr unspezifische Verwe",
    "sg:phone":"+41 19365151",
    "sg:postcode":"8320",
    "sg:province":"Z\u00fcrich",
    "wof:name":"Euronova Ag",
    "wof:placetype":"venue"
},
  "geometry": {"coordinates":[8.7439899445,47.391166687],"type":"Point"}
}