{
  "type": "Feature",
  "properties": {
    "iso:country":"CH",
    "sg:address":"Emil-staub-strasse 1",
    "sg:city":"M\u00e4nnedorf",
    "sg:orig_category":"Non-Classified Establishments",
    "sg:postcode":"8708",
    "sg:province":"Z\u00fcrich",
    "wof:name":"Rpiw Ag",
    "wof:placetype":"venue"
},
  "geometry": {"coordinates":[8.6843757629,47.2568626404],"type":"Point"}
}