{
  "type": "Feature",
  "properties": {
    "iso:country":"CH",
    "sg:address":"Chemin Alfred-borel 2022 Bevaix. Postfach",
    "sg:city":"St-aubin-sauges",
    "sg:orig_category":"Abwasserreinigung",
    "sg:phone":"+41 32 717 76 50",
    "sg:postcode":"2024",
    "sg:province":"Neuch\u00e2tel",
    "wof:name":"Station D'\u00e9puration Des Eaux Us\u00e9es",
    "wof:placetype":"venue"
},
  "geometry": {"coordinates":[6.946195,46.994957],"type":"Point"}
}