{
  "type": "Feature",
  "properties": {
    "iso:country":"CH",
    "sg:address":"Bahnhofstrasse 67",
    "sg:city":"Wettingen",
    "sg:classifiers":[
        {
            "category":"Insurance",
            "subcategory":"Insurance Agent",
            "type":"Services"
        }
    ],
    "sg:phone":"+41 81 302 14 67",
    "sg:postcode":"5430",
    "sg:province":"Aargau",
    "sg:tags":[
        "versicherungsagenturen",
        "-broker"
    ],
    "wof:name":"National Versicherung Agentur",
    "wof:placetype":"venue"
},
  "geometry": {"coordinates":[9.5016126633,47.0044288635],"type":"Point"}
}