{
  "type": "Feature",
  "properties": {
    "iso:country":"CH",
    "sg:address":"4938",
    "sg:city":"Rohrbach",
    "sg:orig_category":"Wirtschafts- and Arbeitgeberverb\u00e4nde",
    "sg:phone":"+41 62 922 84 56",
    "sg:postcode":"4938",
    "sg:province":"Bern",
    "wof:name":"Metzgermeisterverein Oberaargau",
    "wof:placetype":"venue"
},
  "geometry": {"coordinates":[7.8123750687,47.1359062195],"type":"Point"}
}