{
  "type": "Feature",
  "properties": {
    "iso:country":"CH",
    "sg:address":"Birmensdorferstrasse 20 8902 Urdorf. Postfach",
    "sg:city":"Urdorf",
    "sg:orig_category":"Herstellung von Holzstoff, Papier, Karton U Pappe Herstellung von Wellpapier U pappe sowie von Verpa",
    "sg:phone":"+41 17340222",
    "sg:postcode":"8902",
    "sg:province":"Z\u00fcrich",
    "wof:name":"Peg Kartonagen Ag",
    "wof:placetype":"venue"
},
  "geometry": {"coordinates":[8.4179887772,47.3925857544],"type":"Point"}
}