{
  "type": "Feature",
  "properties": {
    "iso:country":"CH",
    "sg:address":"Wyderstrasse 2",
    "sg:city":"Eggenwil",
    "sg:orig_category":"Sonstige mit Sport verbundene T\u00e4tigkeiten",
    "sg:postcode":"5445",
    "sg:province":"Aargau",
    "wof:name":"Hofor Ag",
    "wof:placetype":"venue"
},
  "geometry": {"coordinates":[8.3479528427,47.3735160828],"type":"Point"}
}