{
  "type": "Feature",
  "properties": {
    "iso:country":"CH",
    "sg:address":"Avenue Du Mont-blanc 1196 Gland Case Postale 151",
    "sg:city":"Gland",
    "sg:orig_category":"Instandhaltung U Reparatur von Automobilen",
    "sg:phone":"+41 22 364 46 22",
    "sg:postcode":"1196",
    "sg:province":"Vaud",
    "wof:name":"Palermo Giovanni Et Ignazio.",
    "wof:placetype":"venue"
},
  "geometry": {"coordinates":[6.2616271973,46.4224128723],"type":"Point"}
}