{
  "type": "Feature",
  "properties": {
    "iso:country":"CH",
    "sg:address":"Steinacherstrasse 150",
    "sg:city":"W\u00e4denswil",
    "sg:orig_category":"Detailhandel mit Fahrr\u00e4dern",
    "sg:phone":"+41 55 240 18 32",
    "sg:postcode":"8820",
    "sg:province":"Z\u00fcrich",
    "wof:name":"Mike Bike A.michael",
    "wof:placetype":"venue"
},
  "geometry": {"coordinates":[8.8635568619,47.2610626221],"type":"Point"}
}