{
  "type": "Feature",
  "properties": {
    "iso:country":"CH",
    "sg:address":"Feldstrasse 135",
    "sg:city":"Feuerthalen",
    "sg:orig_category":"Non-Classified Establishments",
    "sg:phone":"+41 52 659 28 28",
    "sg:postcode":"8245",
    "sg:province":"Z\u00fcrich",
    "wof:name":"Lottenbach Jost",
    "wof:placetype":"venue"
},
  "geometry": {"coordinates":[8.644944191,47.6890563965],"type":"Point"}
}