{
  "type": "Feature",
  "properties": {
    "iso:country":"CH",
    "sg:address":"Bernstrasse 41 3175 Flamatt. Postfach",
    "sg:city":"Flamatt",
    "sg:orig_category":"Non-Classified Establishments",
    "sg:phone":"+41 31 744 11 99",
    "sg:postcode":"3175",
    "sg:province":"Fribourg",
    "wof:name":"Mercateo Ag Eletronische Marktpl\u00e4tze; Entwicklung, Betrieb Usw",
    "wof:placetype":"venue"
},
  "geometry": {"coordinates":[7.3206992149,46.8903541565],"type":"Point"}
}