{
  "type": "Feature",
  "properties": {
    "iso:country":"CH",
    "sg:address":"Saint-jean Rue De 34 1203 Gen\u00e8ve. Postfach",
    "sg:city":"Gen\u00e8ve",
    "sg:orig_category":"Sonstige mit der Informatik verbundene T\u00e4tigkeiten",
    "sg:postcode":"1203",
    "sg:province":"Gen\u00e8ve",
    "wof:name":"Mitchell Management Systems Sa.",
    "wof:placetype":"venue"
},
  "geometry": {"coordinates":[6.1289110184,46.20470047],"type":"Point"}
}