{
  "type": "Feature",
  "properties": {
    "iso:country":"CH",
    "sg:address":"Giselistrasse 13/15",
    "sg:city":"Luzern",
    "sg:orig_category":"Elektroinstallation",
    "sg:phone":"+41 41 370 10 10",
    "sg:postcode":"6006",
    "sg:province":"Luzern",
    "wof:name":"Daniel Pfenninger Ag Elektrische Anlagen",
    "wof:placetype":"venue"
},
  "geometry": {"coordinates":[8.3431749344,47.0524024963],"type":"Point"}
}