{
  "type": "Feature",
  "properties": {
    "iso:country":"CH",
    "sg:address":"Ringstrasse 5 8603 Schwerzenbach. Postfach",
    "sg:city":"Volketswil",
    "sg:orig_category":"Grosshandel mit Holz U Baustoffen Herstellung von Anstrichmitteln, Druckfarben U Kitten",
    "sg:phone":"+41 18515353",
    "sg:postcode":"8604",
    "sg:province":"Z\u00fcrich",
    "wof:name":"Sto Ag",
    "wof:placetype":"venue"
},
  "geometry": {"coordinates":[8.5045061111,47.4872665405],"type":"Point"}
}