{
  "type": "Feature",
  "properties": {
    "iso:country":"CH",
    "sg:address":"Untere Sonnenbergstrasse 29",
    "sg:city":"Kradolf",
    "sg:orig_category":"Schulpflegen",
    "sg:postcode":"9214",
    "sg:province":"Thurgau",
    "wof:name":"Oberstufenschulkommission Der Gemeinde Berg",
    "wof:placetype":"venue"
},
  "geometry": {"coordinates":[9.1668395996,47.5790901184],"type":"Point"}
}