{
  "type": "Feature",
  "properties": {
    "iso:country":"CH",
    "sg:address":"Johanniterstrasse 5",
    "sg:city":"Basel",
    "sg:orig_category":"Sprachschulen \u00dcbersetzungsb\u00fcros",
    "sg:phone":"+41 61 263 37 00",
    "sg:postcode":"4056",
    "sg:province":"Basel-Stadt",
    "wof:name":"M\u00ebrgata Languages & Translation",
    "wof:placetype":"venue"
},
  "geometry": {"coordinates":[7.582244873,47.5650672913],"type":"Point"}
}