{
  "type": "Feature",
  "properties": {
    "iso:country":"CH",
    "sg:address":"H\u00f6lzliwisenstrasse 5",
    "sg:city":"Volketswil",
    "sg:orig_category":"Herstellung von Metallkonstruktionen Stahl U Leichtmetallbau",
    "sg:phone":"+41 79 403 28 76",
    "sg:postcode":"8604",
    "sg:province":"Z\u00fcrich",
    "wof:name":"Farei Ag",
    "wof:placetype":"venue"
},
  "geometry": {"coordinates":[8.6792039871,47.3781166077],"type":"Point"}
}