{
  "type": "Feature",
  "properties": {
    "iso:country":"CH",
    "sg:address":"Weid\u00e4cherstrasse 58",
    "sg:city":"Meilen",
    "sg:orig_category":"Informatikdienste Unternehmensberatung",
    "sg:phone":"+41 19233761",
    "sg:postcode":"8706",
    "sg:province":"Z\u00fcrich",
    "wof:name":"Interactive Consulting Gmbh",
    "wof:placetype":"venue"
},
  "geometry": {"coordinates":[8.6649951935,47.2662162781],"type":"Point"}
}