{
  "type": "Feature",
  "properties": {
    "iso:country":"CH",
    "sg:address":"Schulstrasse 3",
    "sg:city":"R\u00fcmlang",
    "sg:orig_category":"Reiseb\u00fcros U Reiseveranstalter",
    "sg:phone":"+41 18180204",
    "sg:postcode":"8153",
    "sg:province":"Z\u00fcrich",
    "wof:name":"Patrick Schneider Travel",
    "wof:placetype":"venue"
},
  "geometry": {"coordinates":[8.5326299667,47.452583313],"type":"Point"}
}