{
  "type": "Feature",
  "properties": {
    "iso:country":"CH",
    "sg:address":"Lavaterstrasse 33",
    "sg:city":"Z\u00fcrich",
    "sg:orig_category":"Interessenvertretungen",
    "sg:postcode":"8001",
    "sg:province":"Z\u00fcrich",
    "wof:name":"Brian Roy Stiftung",
    "wof:placetype":"venue"
},
  "geometry": {"coordinates":[8.390627861,46.9584846497],"type":"Point"}
}