{
  "type": "Feature",
  "properties": {
    "iso:country":"CH",
    "sg:address":"Sonnhalde 176",
    "sg:city":"Oeschgen",
    "sg:orig_category":"Non-Classified Establishments",
    "sg:postcode":"5072",
    "sg:province":"Aargau",
    "wof:name":"Satworld Benz",
    "wof:placetype":"venue"
},
  "geometry": {"coordinates":[8.0192899704,47.5212898254],"type":"Point"}
}