{
  "type": "Feature",
  "properties": {
    "iso:country":"CH",
    "sg:address":"Jungfrauweg 15",
    "sg:city":"Lyss",
    "sg:orig_category":"Non-Classified Establishments",
    "sg:postcode":"3250",
    "sg:province":"Bern",
    "wof:name":"Lbm Consulting Gmbh",
    "wof:placetype":"venue"
},
  "geometry": {"coordinates":[7.3166332245,47.0746459961],"type":"Point"}
}