{
  "type": "Feature",
  "properties": {
    "iso:country":"CH",
    "sg:address":"Bachtalen 22",
    "sg:city":"Hagendorn",
    "sg:orig_category":"P\u00e9dicure",
    "sg:phone":"+41 41 780 30 08",
    "sg:postcode":"6332",
    "sg:province":"Zug",
    "wof:name":"Agnes Br\u00fcndler P\u00e9dicure",
    "wof:placetype":"venue"
},
  "geometry": {"coordinates":[8.4376573563,47.2079849243],"type":"Point"}
}