{
  "type": "Feature",
  "properties": {
    "iso:country":"CH",
    "sg:address":"Avenue Du Midi 11",
    "sg:city":"Fribourg",
    "sg:orig_category":"Detailhandel mit Waren verschiedener Art, Hauptrichtung Nahrungsmittel",
    "sg:phone":"+41 26 424 53 30",
    "sg:postcode":"1700",
    "sg:province":"Fribourg",
    "wof:name":"Torgomes S\u00e0rl Alimentation G\u00e9n\u00e9rale",
    "wof:placetype":"venue"
},
  "geometry": {"coordinates":[7.1483387947,46.8011474609],"type":"Point"}
}