{
  "type": "Feature",
  "properties": {
    "iso:country":"CH",
    "sg:address":"R\u00f6sslimattstrasse 37",
    "sg:city":"Luzern",
    "sg:orig_category":"Unclassifiable Establishments",
    "sg:postcode":"6005",
    "sg:province":"Luzern",
    "wof:name":"Des Management Ag",
    "wof:placetype":"venue"
},
  "geometry": {"coordinates":[8.3141860962,47.0448493958],"type":"Point"}
}