{
  "type": "Feature",
  "properties": {
    "iso:country":"CH",
    "sg:address":"Oberhofstrasse 25",
    "sg:city":"Emmenbr\u00fccke",
    "sg:classifiers":[
        {
            "category":"Social Services",
            "subcategory":"Retirement Home",
            "type":"Services"
        }
    ],
    "sg:phone":"+41 41 268 56 56",
    "sg:postcode":"6020",
    "sg:province":"Luzern",
    "sg:tags":[
        "pflegeheime",
        "u",
        "alters"
    ],
    "wof:name":"Betagtenzentrum Herdschwand",
    "wof:placetype":"venue"
},
  "geometry": {"coordinates":[8.284416,47.074661],"type":"Point"}
}