{
  "type": "Feature",
  "properties": {
    "iso:country":"CH",
    "sg:address":"B\u00f6zingenstrasse 9 2502 Biel/bienne. Postfach",
    "sg:city":"Biel/bienne",
    "sg:orig_category":"Pensionskassen",
    "sg:postcode":"2502",
    "sg:province":"Bern",
    "wof:name":"Georges Und Henri Schaeren-stiftung",
    "wof:placetype":"venue"
},
  "geometry": {"coordinates":[7.2536802292,47.1459388733],"type":"Point"}
}