{
  "type": "Feature",
  "properties": {
    "iso:country":"CH",
    "sg:address":"Vilanstrasse 11",
    "sg:city":"Landquart",
    "sg:orig_category":"Jugendorganisationen",
    "sg:phone":"+41 81 322 83 65",
    "sg:postcode":"7302",
    "sg:province":"Graubunden",
    "wof:name":"Damenturnverein Dtv Malans",
    "wof:placetype":"venue"
},
  "geometry": {"coordinates":[9.5604906082,46.9657592773],"type":"Point"}
}