{
  "type": "Feature",
  "properties": {
    "addr:full":"D\u00e4nikerstr. 31 D\u00e4llikon Z\u00fcrich 8108",
    "addr:housenumber":"31",
    "addr:postcode":"8108",
    "addr:street":"Daenikerstr.;Zuerich",
    "iso:country":"CH",
    "sg:address":"D\u00e4nikerstr. 31",
    "sg:city":"D\u00e4llikon",
    "sg:classifiers":[
        {
            "category":"Farming",
            "subcategory":"Crops",
            "type":"Manufacturing & Wholesale Goods"
        }
    ],
    "sg:phone":"+41 22 343 73 50",
    "sg:postcode":"8108",
    "sg:province":"Z\u00fcrich",
    "sg:tags":[
        "vegetable",
        "fruit",
        "agriculture",
        "livestock"
    ],
    "wof:name":"Fran\u00c7ois Brasier Sa",
    "wof:placetype":"venue"
},
  "geometry": {"coordinates":[6.132383,46.180485],"type":"Point"}
}