{
  "type": "Feature",
  "properties": {
    "iso:country":"CH",
    "sg:address":"Oberstadt 6",
    "sg:city":"Sursee",
    "sg:orig_category":"Detailhandel mit S\u00e4uglings U Kinderbekleidung Herstellung von sonstiger Bekleidung U Bekleidungszube",
    "sg:phone":"+41 41 921 54 45",
    "sg:postcode":"6210",
    "sg:province":"Luzern",
    "wof:name":"Kinderboutique Pinocchio Cozzio Beatrice",
    "wof:placetype":"venue"
},
  "geometry": {"coordinates":[8.110247612,47.1722488403],"type":"Point"}
}