{
  "type": "Feature",
  "properties": {
    "iso:country":"CH",
    "sg:address":"Bahnhofstrasse 10",
    "sg:city":"Meiringen",
    "sg:classifiers":[
        {
            "category":"Bars & Pubs",
            "type":"Food & Drink"
        }
    ],
    "sg:phone":"+41 33 971 63 69",
    "sg:postcode":"3860",
    "sg:province":"Bern",
    "wof:name":"Lyon's Pub",
    "wof:placetype":"venue"
},
  "geometry": {"coordinates":[8.185939,46.727783],"type":"Point"}
}