{
  "type": "Feature",
  "properties": {
    "iso:country":"CH",
    "sg:address":"Bottigenstrasse 394 3020 Bern. Postfach",
    "sg:city":"Bern",
    "sg:orig_category":"Sonstiger Fachdetailhandel mit Nahrungsmitteln, Getr\u00e4nken U Tabak in Verkaufsr\u00e4umen",
    "sg:postcode":"3020",
    "sg:province":"Bern",
    "wof:name":"A. Mumenthaler Milch U. Milchprodukte; Handel.",
    "wof:placetype":"venue"
},
  "geometry": {"coordinates":[7.3368301392,46.9399452209],"type":"Point"}
}