{
  "type": "Feature",
  "properties": {
    "iso:country":"CH",
    "sg:address":"Dufourstrasse 18",
    "sg:city":"Bern",
    "sg:orig_category":"K\u00fcnstlerische U schriftstellerische T\u00e4tigkeiten U Darbietungen",
    "sg:postcode":"3005",
    "sg:province":"Bern",
    "wof:name":"Arv Autoren-recht-verwaltungs Ag",
    "wof:placetype":"venue"
},
  "geometry": {"coordinates":[7.4542660713,46.9424591064],"type":"Point"}
}