{
  "type": "Feature",
  "properties": {
    "iso:country":"CH",
    "sg:address":"Erlenstrasse 1",
    "sg:city":"Fislisbach",
    "sg:classifiers":[
        {
            "category":"Restaurant",
            "type":"Food & Drink"
        }
    ],
    "sg:phone":"+41 56 493 22 10",
    "sg:postcode":"5442",
    "sg:province":"Aargau",
    "wof:name":"Restaurant Erle",
    "wof:placetype":"venue"
},
  "geometry": {"coordinates":[8.2887516022,47.4396743774],"type":"Point"}
}