{
  "type": "Feature",
  "properties": {
    "iso:country":"CH",
    "sg:address":"Aspstrasse 8 8472 Seuzach. Postfach 393",
    "sg:city":"Seuzach",
    "sg:orig_category":"Druck ohne Zeitungsdruck Verlagsgewerbe",
    "sg:phone":"+41 41 850 16 31",
    "sg:postcode":"8472",
    "sg:province":"Z\u00fcrich",
    "wof:name":"Kreienb\u00fchl Druck Ag K\u00fcssnacht",
    "wof:placetype":"venue"
},
  "geometry": {"coordinates":[8.4373245239,47.0828475952],"type":"Point"}
}