{
  "type": "Feature",
  "properties": {
    "iso:country":"CH",
    "sg:address":"La Pinte De Lys 1669 Albeuve. Postfach",
    "sg:city":"Albeuve",
    "sg:classifiers":[
        {
            "category":"Travel",
            "subcategory":"Hotels & Motels",
            "type":"Entertainment"
        }
    ],
    "sg:postcode":"1669",
    "sg:province":"Fribourg",
    "sg:tags":[
        "hotels",
        "mit",
        "restaurant"
    ],
    "wof:name":"La Pinte De Lys S\u00e0rl",
    "wof:placetype":"venue"
},
  "geometry": {"coordinates":[7.0558848381,46.5188217163],"type":"Point"}
}