{
  "type": "Feature",
  "properties": {
    "iso:country":"CH",
    "sg:address":"San Bastiaun 7503 Samedan. Postfach",
    "sg:city":"Samedan",
    "sg:orig_category":"Verwaltung von Immobilien",
    "sg:postcode":"7503",
    "sg:province":"Graubunden",
    "wof:name":"Pc Paun E Chasch\u00f6l Gmbh Betrieb Der Lebensmittelbranche",
    "wof:placetype":"venue"
},
  "geometry": {"coordinates":[9.8704996109,46.5340385437],"type":"Point"}
}