{
  "type": "Feature",
  "properties": {
    "iso:country":"CH",
    "sg:address":"3982",
    "sg:city":"Bitsch",
    "sg:orig_category":"Sportvereine Sch\u00fctzen",
    "sg:postcode":"3982",
    "sg:province":"Valais",
    "wof:name":"Milit\u00e4rschiessverein",
    "wof:placetype":"venue"
},
  "geometry": {"coordinates":[8.2618379593,46.4867591858],"type":"Point"}
}