{
  "type": "Feature",
  "properties": {
    "iso:country":"CH",
    "sg:address":"Baslerstrasse 35",
    "sg:city":"Birsfelden",
    "sg:orig_category":"Herstellung von Ger\u00e4ten der Elektrizit\u00e4tserzeugung, -verteilung u.\u00e4. -Herstellung von Mess U Kontrol",
    "sg:phone":"+41 61 312 11 35",
    "sg:postcode":"4127",
    "sg:province":"Basel-Landschaft",
    "wof:name":"Idag Druckregler",
    "wof:placetype":"venue"
},
  "geometry": {"coordinates":[7.6188659668,47.5565910339],"type":"Point"}
}