{
  "type": "Feature",
  "properties": {
    "iso:country":"CH",
    "sg:address":"Staldenweg 1",
    "sg:city":"Menzingen",
    "sg:orig_category":"Maler U Glasergewerbe Malerei",
    "sg:phone":"+41 41 755 32 52",
    "sg:postcode":"6313",
    "sg:province":"Zug",
    "wof:name":"M & S Malerarbeiten Ag",
    "wof:placetype":"venue"
},
  "geometry": {"coordinates":[8.5977363586,47.1811752319],"type":"Point"}
}