{
  "type": "Feature",
  "properties": {
    "iso:country":"CH",
    "sg:address":"Im Wechsel 23",
    "sg:city":"Hirschthal",
    "sg:orig_category":"Infrared Dryers",
    "sg:phone":"+41 62 739 30 70",
    "sg:postcode":"5042",
    "sg:province":"Aargau",
    "wof:name":"Krelus Ag",
    "wof:placetype":"venue"
},
  "geometry": {"coordinates":[8.0530738831,47.3219604492],"type":"Point"}
}