{
  "type": "Feature",
  "properties": {
    "iso:country":"CH",
    "sg:address":"Dienerstrasse 90",
    "sg:city":"Z\u00fcrich",
    "sg:orig_category":"Sonstige Kultur U Unterhaltungseinrichtungen",
    "sg:phone":"+41 12428098",
    "sg:postcode":"8004",
    "sg:province":"Z\u00fcrich",
    "wof:name":"Jugendtreff Kreis 4",
    "wof:placetype":"venue"
},
  "geometry": {"coordinates":[8.5250968933,47.3796691895],"type":"Point"}
}