{
  "type": "Feature",
  "properties": {
    "iso:country":"CH",
    "sg:address":"Rosenstrasse 6 4142 M\u00fcnchenstein. Postfach",
    "sg:city":"M\u00fcnchenstein",
    "sg:orig_category":"Forschung U Entwicklung im Bereich der Naturwissenschaften",
    "sg:postcode":"4142",
    "sg:province":"Basel-Landschaft",
    "wof:name":"Stiftung Zur F\u00f6rderung Der Ms-forschung",
    "wof:placetype":"venue"
},
  "geometry": {"coordinates":[7.6151528358,47.522354126],"type":"Point"}
}