{
  "type": "Feature",
  "properties": {
    "iso:country":"CH",
    "sg:address":"Thiersteinerstrasse 3",
    "sg:city":"Muttenz",
    "sg:orig_category":"Non-Classified Establishments",
    "sg:postcode":"4132",
    "sg:province":"Basel-Landschaft",
    "wof:name":"Karl & Desanka L\u00e4ng Kunststoffverarbeitung",
    "wof:placetype":"venue"
},
  "geometry": {"coordinates":[9.1539001465,47.5529785156],"type":"Point"}
}