{
  "type": "Feature",
  "properties": {
    "iso:country":"CH",
    "sg:address":"In Der W\u00e4sseri 12",
    "sg:city":"Z\u00fcrich",
    "sg:orig_category":"Kosmetikinstitute",
    "sg:phone":"+41 14932737",
    "sg:postcode":"8047",
    "sg:province":"Z\u00fcrich",
    "wof:name":"Bruna B\u00fchrer Kosmetikinstitut Bellissima",
    "wof:placetype":"venue"
},
  "geometry": {"coordinates":[8.4865341187,47.3745918274],"type":"Point"}
}