{
  "type": "Feature",
  "properties": {
    "iso:country":"CH",
    "sg:address":"Chemin Des Buclines 3",
    "sg:city":"Cologny",
    "sg:orig_category":"Non-Classified Establishments",
    "sg:phone":"+41 22 860 26 60",
    "sg:postcode":"1223",
    "sg:province":"Gen\u00e8ve",
    "wof:name":"Castana Sa",
    "wof:placetype":"venue"
},
  "geometry": {"coordinates":[6.191411972,46.2056312561],"type":"Point"}
}