{
  "type": "Feature",
  "properties": {
    "iso:country":"CH",
    "sg:address":"Pr\u00e9vost-martin Rue 23",
    "sg:city":"Gen\u00e8ve",
    "sg:orig_category":"Herstellung von Duft U K\u00f6rperpflegemitteln",
    "sg:phone":"+41 22 328 02 60",
    "sg:postcode":"1205",
    "sg:province":"Gen\u00e8ve",
    "wof:name":"Shop Coiffure S\u00e0rl",
    "wof:placetype":"venue"
},
  "geometry": {"coordinates":[6.1458940506,46.1946678162],"type":"Point"}
}