{
  "type": "Feature",
  "properties": {
    "iso:country":"CH",
    "sg:address":"Aemmertweg 9",
    "sg:city":"Schneisingen",
    "sg:orig_category":"Elektrizit\u00e4tsversorgung",
    "sg:phone":"+41 56 241 19 92",
    "sg:postcode":"5425",
    "sg:province":"Aargau",
    "wof:name":"Genossenschaft Elektra Schneisingen",
    "wof:placetype":"venue"
},
  "geometry": {"coordinates":[8.3632898331,47.5165596008],"type":"Point"}
}