{
  "type": "Feature",
  "properties": {
    "iso:country":"CH",
    "sg:address":"3928",
    "sg:city":"Randa",
    "sg:orig_category":"Mechanische Werkst\u00e4tten",
    "sg:phone":"+41 27 967 61 65",
    "sg:postcode":"3928",
    "sg:province":"Valais",
    "wof:name":"Guido Brantschen Mechanische Werkstatt",
    "wof:placetype":"venue"
},
  "geometry": {"coordinates":[7.7803549767,46.0985984802],"type":"Point"}
}