{
  "type": "Feature",
  "properties": {
    "iso:country":"CH",
    "sg:address":"Dornacherstrasse 79 4053 Basel. Postfach",
    "sg:city":"Basel",
    "sg:orig_category":"Non-Classified Establishments",
    "sg:phone":"+41 62 216 59 86",
    "sg:postcode":"4053",
    "sg:province":"Basel-Stadt",
    "wof:name":"Transport Matic",
    "wof:placetype":"venue"
},
  "geometry": {"coordinates":[7.5877170563,47.5441246033],"type":"Point"}
}