{
  "type": "Feature",
  "properties": {
    "iso:country":"CH",
    "sg:address":"Rosenbergstrasse 1 8370 Sirnach. Postfach",
    "sg:city":"Sirnach",
    "sg:orig_category":"Grosshandel mit Erzen U Metallen Herstellung von Schl\u00f6ssern U Beschl\u00e4gen",
    "sg:phone":"+41 32 341 71 09",
    "sg:postcode":"8370",
    "sg:province":"Thurgau",
    "wof:name":"Focair S\u00e0rl",
    "wof:placetype":"venue"
},
  "geometry": {"coordinates":[7.2548317909,47.1455421448],"type":"Point"}
}