{
  "type": "Feature",
  "properties": {
    "iso:country":"CH",
    "sg:address":"Limmatstrasse 12",
    "sg:city":"Spreitenbach",
    "sg:classifiers":[
        {
            "category":"Building & Trades",
            "subcategory":"Cleaning & Sanitation",
            "type":"Services"
        }
    ],
    "sg:phone":"+41 56 419 70 40",
    "sg:postcode":"8957",
    "sg:province":"Aargau",
    "sg:tags":[
        "technical",
        "services"
    ],
    "wof:name":"Ags Glas- Und Geb\u00e4udereinigungs Gmbh",
    "wof:placetype":"venue"
},
  "geometry": {"coordinates":[8.373364,47.428192],"type":"Point"}
}