{
  "type": "Feature",
  "properties": {
    "iso:country":"CH",
    "sg:address":"Rorschacher Strasse 127",
    "sg:city":"St.gallen",
    "sg:orig_category":"Herstellung von Metallkonstruktionen",
    "sg:phone":"+41 71 245 03 10",
    "sg:postcode":"9000",
    "sg:province":"St. Gallen",
    "wof:name":"Ainhauser Josef",
    "wof:placetype":"venue"
},
  "geometry": {"coordinates":[9.393529892,47.4309921265],"type":"Point"}
}