{
  "type": "Feature",
  "properties": {
    "addr:full":"Wiesstrasse 6 Ennenda Glarus 8755",
    "addr:housenumber":"6",
    "addr:postcode":"8755",
    "addr:street":"Wiesstrasse",
    "iso:country":"CH",
    "sg:address":"Wiesstrasse 6",
    "sg:city":"Ennenda",
    "sg:orig_category":"Detailhandel mit Blumen U Pflanzen Fachdetailhandel in Verkaufsr\u00e4umen",
    "sg:phone":"+41 55 640 70 61",
    "sg:postcode":"8755",
    "sg:province":"Glarus",
    "wof:name":"Blueme-st\u00fcbli, Wagner-hofmann Annagret",
    "wof:placetype":"venue"
},
  "geometry": {"coordinates":[9.079196,47.032814],"type":"Point"}
}