{
  "type": "Feature",
  "properties": {
    "iso:country":"CH",
    "sg:address":"Grenzacherstrasse 79 4058 Basel. Postfach",
    "sg:city":"Basel",
    "sg:orig_category":"Unclassifiable Establishments",
    "sg:phone":"+41 61 690 92 20",
    "sg:postcode":"4058",
    "sg:province":"Basel-Stadt",
    "wof:name":"Warteck Sport Holding Ag",
    "wof:placetype":"venue"
},
  "geometry": {"coordinates":[7.6021461487,47.5588722229],"type":"Point"}
}