{
  "type": "Feature",
  "properties": {
    "iso:country":"CH",
    "sg:address":"3960",
    "sg:city":"Sierre",
    "sg:orig_category":"RESTAURANTS: TEA-ROOMS",
    "sg:phone":"+41 32 841 34 42",
    "sg:postcode":"3960",
    "sg:province":"Valais",
    "wof:name":"Brigand Mme Sophie",
    "wof:placetype":"venue"
},
  "geometry": {"coordinates":[6.8699297905,46.9704017639],"type":"Point"}
}