{
  "type": "Feature",
  "properties": {
    "iso:country":"CH",
    "sg:address":"Rue Centrale 69",
    "sg:city":"Conthey",
    "sg:orig_category":"Architekturb\u00fcros",
    "sg:phone":"+41 27 346 25 54",
    "sg:postcode":"1964",
    "sg:province":"Valais",
    "wof:name":"Samy Suter Bureau D'architecture",
    "wof:placetype":"venue"
},
  "geometry": {"coordinates":[7.306993,46.230991],"type":"Point"}
}