{
  "type": "Feature",
  "properties": {
    "iso:country":"CH",
    "sg:address":"Hauptstrasse 40 4434 H\u00f6lstein. Postfach",
    "sg:city":"H\u00f6lstein",
    "sg:orig_category":"Instandhaltung U Reparatur von Automobilen",
    "sg:phone":"+41 79 358 23 54",
    "sg:postcode":"4434",
    "sg:province":"Basel-Landschaft",
    "wof:name":"Garage Eintracht Ag",
    "wof:placetype":"venue"
},
  "geometry": {"coordinates":[7.7683391571,47.4238929749],"type":"Point"}
}