{
  "type": "Feature",
  "properties": {
    "iso:country":"CH",
    "sg:address":"Birmensdorferstrasse 157 8003 Z\u00fcrich. Postfach",
    "sg:city":"Z\u00fcrich",
    "sg:orig_category":"Reiseb\u00fcros",
    "sg:phone":"+41 17252627",
    "sg:postcode":"8036",
    "sg:province":"Z\u00fcrich",
    "wof:name":"Bti Kuoni Switzerland Kuoni Reisen Ag",
    "wof:placetype":"venue"
},
  "geometry": {"coordinates":[8.5975809097,47.2598724365],"type":"Point"}
}