{
  "type": "Feature",
  "properties": {
    "iso:country":"CH",
    "sg:address":"Terrassenweg 36",
    "sg:city":"Konolfingen",
    "sg:orig_category":"Unternehmensberatung",
    "sg:phone":"+41 31 791 17 07",
    "sg:postcode":"3510",
    "sg:province":"Bern",
    "wof:name":"Bodes Gerber Beat",
    "wof:placetype":"venue"
},
  "geometry": {"coordinates":[7.617524147,46.8830413818],"type":"Point"}
}