{
  "type": "Feature",
  "properties": {
    "iso:country":"CH",
    "sg:address":"3513",
    "sg:city":"Bigenthal",
    "sg:orig_category":"Herstellung von Reiseartikeln, Leder U Sattlerwaren Innendekorationsateliers",
    "sg:phone":"+41 31 701 14 87",
    "sg:postcode":"3513",
    "sg:province":"Bern",
    "wof:name":"Walter Frey Sattler & Tapezierer",
    "wof:placetype":"venue"
},
  "geometry": {"coordinates":[7.6249299049,46.9669494629],"type":"Point"}
}