{
  "type": "Feature",
  "properties": {
    "iso:country":"CH",
    "sg:address":"Platy Route Du 5",
    "sg:city":"Villars-sur-gl\u00e2ne",
    "sg:orig_category":"Herstellung von sonstigen elektrischen Ausr\u00fcstungen",
    "sg:phone":"+41 26 401 11 41",
    "sg:postcode":"1752",
    "sg:province":"Fribourg",
    "wof:name":"Dolcom S\u00e0rl",
    "wof:placetype":"venue"
},
  "geometry": {"coordinates":[7.130428791,46.7955818176],"type":"Point"}
}