{
  "type": "Feature",
  "properties": {
    "iso:country":"CH",
    "sg:address":"Usines M\u00e9tallurgiques De Vallorbe",
    "sg:city":"Vallorbe",
    "sg:orig_category":"Pensionskassen",
    "sg:postcode":"1337",
    "sg:province":"Vaud",
    "wof:name":"Fondation Jules Chavannes",
    "wof:placetype":"venue"
},
  "geometry": {"coordinates":[6.3790950775,46.7119598389],"type":"Point"}
}