{
  "type": "Feature",
  "properties": {
    "iso:country":"CH",
    "sg:address":"Chermignon-dessous",
    "sg:city":"Chermignon",
    "sg:orig_category":"Mechanik",
    "sg:phone":"+41 27 483 33 18",
    "sg:postcode":"3971",
    "sg:province":"Valais",
    "wof:name":"Lagger Eric",
    "wof:placetype":"venue"
},
  "geometry": {"coordinates":[7.4752230644,46.2944602966],"type":"Point"}
}