{
  "type": "Feature",
  "properties": {
    "iso:country":"CH",
    "sg:address":"Geerenstrasse 13",
    "sg:city":"Volketswil",
    "sg:orig_category":"Instandhaltung U Reparatur von Automobilen",
    "sg:phone":"+41 79 358 86 59",
    "sg:postcode":"8604",
    "sg:province":"Z\u00fcrich",
    "wof:name":"Agostino Bertoletti Autogarage & Carrosserie",
    "wof:placetype":"venue"
},
  "geometry": {"coordinates":[8.6838359833,47.4090003967],"type":"Point"}
}