{
  "type": "Feature",
  "properties": {
    "iso:country":"CH",
    "sg:address":"Neuweilerplatz 1",
    "sg:city":"Basel",
    "sg:orig_category":"Kantonalbanken",
    "sg:phone":"+41 61 266 27 22",
    "sg:postcode":"4054",
    "sg:province":"Basel-Stadt",
    "wof:name":"Basler Kantonalbank - Bkb Agentur Riehen-rauracher",
    "wof:placetype":"venue"
},
  "geometry": {"coordinates":[7.6325259209,47.5709838867],"type":"Point"}
}