{
  "type": "Feature",
  "properties": {
    "addr:full":"Rathausgasse 62 Bern Bern 3011",
    "addr:housenumber":"62",
    "addr:postcode":"3011",
    "addr:street":"Rathausgasse",
    "iso:country":"CH",
    "sg:address":"Rathausgasse 62",
    "sg:city":"Bern",
    "sg:orig_category":"Detailhandel mit Bekleidung",
    "sg:phone":"+41 22 343 58 85",
    "sg:postcode":"3011",
    "sg:province":"Bern",
    "wof:name":"Cintr S\u00e0rl V\u00eatements Et Articles Dans Le Domaine De La Mode Etc.; Commerce",
    "wof:placetype":"venue"
},
  "geometry": {"coordinates":[6.141381,46.183949],"type":"Point"}
}