{
  "type": "Feature",
  "properties": {
    "iso:country":"CH",
    "sg:address":"Badhausstrasse 19 2503 Biel/bienne. Postfach",
    "sg:city":"Biel/bienne",
    "sg:orig_category":"Detailhandel mit Damenbekleidung",
    "sg:phone":"+41 32 323 15 13",
    "sg:postcode":"2501",
    "sg:province":"Bern",
    "wof:name":"Erika Pieczonka Haute Couture",
    "wof:placetype":"venue"
},
  "geometry": {"coordinates":[7.2379159927,47.1322364807],"type":"Point"}
}