{
  "type": "Feature",
  "properties": {
    "addr:full":"Herrengasse 19 Bern Bern 3011",
    "addr:housenumber":"19",
    "addr:postcode":"3011",
    "addr:street":"Herrengasse",
    "iso:country":"CH",
    "sg:address":"Herrengasse 19",
    "sg:city":"Bern",
    "sg:orig_category":"Blumen U Zierpflanzenbau Detailhandel mit Blumen U Pflanzen",
    "sg:phone":"+41 31 311 63 19",
    "sg:postcode":"3011",
    "sg:province":"Bern",
    "wof:name":"Blumeng\u00e4rtnerei Ellenberger Susanne Und Fuhrimann Ursi",
    "wof:placetype":"venue"
},
  "geometry": {"coordinates":[7.449503,46.946941],"type":"Point"}
}