{
  "type": "Feature",
  "properties": {
    "iso:country":"CH",
    "sg:address":"Andr\u00fcti 248",
    "sg:city":"Schweizersholz",
    "sg:orig_category":"Sportvereine Velo Rad-& Motorfahrer-Bund SRB",
    "sg:postcode":"9223",
    "sg:province":"Thurgau",
    "wof:name":"Radfahrerv.kradolf-sch\u00f6nenb.",
    "wof:placetype":"venue"
},
  "geometry": {"coordinates":[9.2093801498,47.5044059753],"type":"Point"}
}