{
  "type": "Feature",
  "properties": {
    "iso:country":"CH",
    "sg:address":"1784",
    "sg:city":"Courtepin",
    "sg:orig_category":"Detailhandel mit Fleisch U Fleischwaren",
    "sg:postcode":"1784",
    "sg:province":"Fribourg",
    "wof:name":"Metzgerei Lor\u00e9tan Ag",
    "wof:placetype":"venue"
},
  "geometry": {"coordinates":[7.1240501404,46.8647003174],"type":"Point"}
}