{
  "type": "Feature",
  "properties": {
    "iso:country":"CH",
    "sg:address":"1918",
    "sg:city":"Mayens-de-riddes",
    "sg:orig_category":"Vermietung U Verpachtung von eigenen Immobilien Vermittlung von Immobilien",
    "sg:phone":"+41 27 306 37 53",
    "sg:postcode":"1918",
    "sg:province":"Valais",
    "wof:name":"Carron Immobilier Sa",
    "wof:placetype":"venue"
},
  "geometry": {"coordinates":[7.2335600853,46.1444511414],"type":"Point"}
}