{
  "type": "Feature",
  "properties": {
    "iso:country":"CH",
    "sg:address":"6528",
    "sg:city":"Camorino",
    "sg:orig_category":"Zivilschutz",
    "sg:phone":"+41 71 333 30 89",
    "sg:postcode":"6528",
    "sg:province":"Ticino",
    "wof:name":"Zivilschutzstelle Region Mittelland",
    "wof:placetype":"venue"
},
  "geometry": {"coordinates":[9.3892240524,47.3899993896],"type":"Point"}
}