{
  "type": "Feature",
  "properties": {
    "iso:country":"CH",
    "sg:address":"F\u00fcllerichstrasse 53 3073 G\u00fcmligen. Postfach",
    "sg:city":"G\u00fcmligen",
    "sg:orig_category":"Kauf U Verkauf von Immobilien auf eigene Rechnung Wohnheime",
    "sg:phone":"+41 21 944 42 26",
    "sg:postcode":"3073",
    "sg:province":"Bern",
    "wof:name":"Soci\u00e9t\u00e9 De Bon Rivage",
    "wof:placetype":"venue"
},
  "geometry": {"coordinates":[6.8584179878,46.4515724182],"type":"Point"}
}