{
  "type": "Feature",
  "properties": {
    "iso:country":"CH",
    "sg:address":"Sagiweg 1",
    "sg:city":"Wiesendangen",
    "sg:orig_category":"S\u00e4ge, Hobel U Holzimpr\u00e4gnierwerke",
    "sg:phone":"+41 52 337 12 10",
    "sg:postcode":"8542",
    "sg:province":"Z\u00fcrich",
    "wof:name":"Schreiber Werner",
    "wof:placetype":"venue"
},
  "geometry": {"coordinates":[8.7913665771,47.5228500366],"type":"Point"}
}