{
  "type": "Feature",
  "properties": {
    "iso:country":"CH",
    "sg:address":"Wisserlen",
    "sg:city":"Kerns",
    "sg:orig_category":"Kalb U Schweine-M\u00e4sterei U Zucht",
    "sg:postcode":"6064",
    "sg:province":"Obwalden",
    "wof:name":"Alois Wagner Sennerei Und Schweinehaltung Gmbh",
    "wof:placetype":"venue"
},
  "geometry": {"coordinates":[8.2921104431,46.9083709717],"type":"Point"}
}