{
  "type": "Feature",
  "properties": {
    "iso:country":"CH",
    "sg:address":"Clos-perroud 207",
    "sg:city":"Siviriez",
    "sg:orig_category":"Nationale Postdienste",
    "sg:phone":"+41 26 656 13 02",
    "sg:postcode":"1678",
    "sg:province":"Fribourg",
    "wof:name":"La Poste Suisse",
    "wof:placetype":"venue"
},
  "geometry": {"coordinates":[6.8809862137,46.6567153931],"type":"Point"}
}