{
  "type": "Feature",
  "properties": {
    "iso:country":"CH",
    "sg:address":"Rue Du Temple 10",
    "sg:city":"Bevaix",
    "sg:orig_category":"Elektroinstallation",
    "sg:phone":"+41 32 846 22 42",
    "sg:postcode":"2022",
    "sg:province":"Neuch\u00e2tel",
    "wof:name":"Fuligno N. Et Fils Install. \u00e9lectr. Et T\u00e9l\u00e9ph. Etc",
    "wof:placetype":"venue"
},
  "geometry": {"coordinates":[6.8153219223,46.9309577942],"type":"Point"}
}