{
  "type": "Feature",
  "properties": {
    "iso:country":"CH",
    "sg:address":"Stationsstrasse 3",
    "sg:city":"Br\u00fcttisellen",
    "sg:orig_category":"Fachdetailhandel in Verkaufsr\u00e4umen",
    "sg:phone":"+41 12116016",
    "sg:postcode":"8306",
    "sg:province":"Z\u00fcrich",
    "wof:name":"Gemax Ag Inkassoauftr\u00e4ge Usw",
    "wof:placetype":"venue"
},
  "geometry": {"coordinates":[8.6301403046,47.4195594788],"type":"Point"}
}