{
  "type": "Feature",
  "properties": {
    "iso:country":"CH",
    "sg:address":"Giselihalde 1",
    "sg:city":"Luzern",
    "sg:orig_category":"Lagerh\u00e4user, G\u00fcterumschlag, Verteilzentren",
    "sg:postcode":"6006",
    "sg:province":"Luzern",
    "wof:name":"L. Und R. Lagerhaus Luzern Ag",
    "wof:placetype":"venue"
},
  "geometry": {"coordinates":[8.3451786041,47.0535697937],"type":"Point"}
}