{
  "type": "Feature",
  "properties": {
    "iso:country":"CH",
    "sg:address":"Hardhof 32",
    "sg:city":"Z\u00fcrich",
    "sg:orig_category":"Fussboden, Fliesen U Plattenlegerei, Tapeziererei",
    "sg:postcode":"8064",
    "sg:province":"Z\u00fcrich",
    "wof:name":"L\u00f6tscher Wabo",
    "wof:placetype":"venue"
},
  "geometry": {"coordinates":[8.4954910278,47.3963623047],"type":"Point"}
}