{
  "type": "Feature",
  "properties": {
    "iso:country":"CH",
    "sg:address":"Via Angelo Baroffio 4",
    "sg:city":"Lugano",
    "sg:orig_category":"Unclassifiable Establishments",
    "sg:phone":"+41 91 922 05 36",
    "sg:postcode":"6900",
    "sg:province":"Ticino",
    "wof:name":"Lombardi Web Sagl",
    "wof:placetype":"venue"
},
  "geometry": {"coordinates":[8.947766304,46.0064239502],"type":"Point"}
}