{
  "type": "Feature",
  "properties": {
    "addr:full":"Kreuzplatz 2 Z\u00fcrich Z\u00fcrich 8032",
    "addr:housenumber":"2",
    "addr:postcode":"8032",
    "addr:street":"Kreuzplatz",
    "iso:country":"CH",
    "sg:address":"Kreuzplatz 2",
    "sg:city":"Z\u00fcrich",
    "sg:orig_category":"Arztpraxen",
    "sg:phone":"+41 12615560",
    "sg:postcode":"8032",
    "sg:province":"Z\u00fcrich",
    "wof:name":"Dres Med. M. & M.-c. Guldin Spezial\u00e4rzte Fmh",
    "wof:placetype":"venue"
},
  "geometry": {"coordinates":[8.554125,47.364792],"type":"Point"}
}