{
  "type": "Feature",
  "properties": {
    "iso:country":"CH",
    "sg:address":"Buchmattstrasse 112",
    "sg:city":"Burgdorf",
    "sg:orig_category":"Oberfl\u00e4chenveredlung U W\u00e4rmebehandlung",
    "sg:phone":"+41 34 422 10 86",
    "sg:postcode":"3400",
    "sg:province":"Bern",
    "wof:name":"H\u00e4rterei Blessing Ag H\u00e4rterei, Bes. Technische W\u00e4rmebehandlung U. Oberfl\u00e4chenveredelung",
    "wof:placetype":"venue"
},
  "geometry": {"coordinates":[7.6009821892,47.0665855408],"type":"Point"}
}