{
  "type": "Feature",
  "properties": {
    "iso:country":"CH",
    "sg:address":"Asylweg 27",
    "sg:city":"Zuchwil",
    "sg:orig_category":"Malerei",
    "sg:phone":"+41 32 685 51 75",
    "sg:postcode":"4528",
    "sg:province":"Solothurn",
    "wof:name":"Bernhard Floreani Malergesch\u00e4ft",
    "wof:placetype":"venue"
},
  "geometry": {"coordinates":[7.5590901375,47.200969696],"type":"Point"}
}