{
  "type": "Feature",
  "properties": {
    "iso:country":"CH",
    "sg:address":"Rankrain 3 4853 Murgenthal. Postfach",
    "sg:city":"Murgenthal",
    "sg:orig_category":"Fernmeldedienste",
    "sg:phone":"+41 62 926 18 58",
    "sg:postcode":"4853",
    "sg:province":"Aargau",
    "wof:name":"Fernsehgenossenschaft Murgenthal",
    "wof:placetype":"venue"
},
  "geometry": {"coordinates":[7.8477201462,47.2818565369],"type":"Point"}
}