{
  "type": "Feature",
  "properties": {
    "iso:country":"CH",
    "sg:address":"Staatsstrasse 133",
    "sg:city":"Rebstein",
    "sg:orig_category":"Datenverarbeitungsdienste Sonstige mit der Informatik verbundene T\u00e4tigkeiten",
    "sg:phone":"+41 71 775 97 75",
    "sg:postcode":"9445",
    "sg:province":"St. Gallen",
    "wof:name":"Keel + Frei Ag",
    "wof:placetype":"venue"
},
  "geometry": {"coordinates":[9.580812,47.396759],"type":"Point"}
}