{
  "type": "Feature",
  "properties": {
    "iso:country":"CH",
    "sg:address":"Bahnstrasse 9 8603 Schwerzenbach. Postfach",
    "sg:city":"Schwerzenbach",
    "sg:orig_category":"Unternehmensberatung",
    "sg:phone":"+41 17132071",
    "sg:postcode":"8603",
    "sg:province":"Z\u00fcrich",
    "wof:name":"Henry Baumann Treuhandb\u00fcro",
    "wof:placetype":"venue"
},
  "geometry": {"coordinates":[8.5228700638,47.2765388489],"type":"Point"}
}