{
  "type": "Feature",
  "properties": {
    "iso:country":"CH",
    "sg:address":"Zipartenstrasse 55",
    "sg:city":"D\u00fcbendorf",
    "sg:orig_category":"Grosshandel mit Datenverarbeitungsger\u00e4ten Softwareentwicklung U beratung",
    "sg:phone":"+41 18225151",
    "sg:postcode":"8600",
    "sg:province":"Z\u00fcrich",
    "wof:name":"Mpc Mac & Pc Consulting Faic Jiri",
    "wof:placetype":"venue"
},
  "geometry": {"coordinates":[8.6060056686,47.3944168091],"type":"Point"}
}