{
  "type": "Feature",
  "properties": {
    "iso:country":"CH",
    "sg:address":"Sch\u00fctzenweg 28",
    "sg:city":"Allschwil",
    "sg:orig_category":"Detailhandel mit Damenbekleidung",
    "sg:phone":"+41 61 301 72 61",
    "sg:postcode":"4123",
    "sg:province":"Basel-Landschaft",
    "wof:name":"Alex Rossi Damen-konfektion",
    "wof:placetype":"venue"
},
  "geometry": {"coordinates":[7.562017,47.556381],"type":"Point"}
}