{
  "type": "Feature",
  "properties": {
    "iso:country":"CH",
    "sg:address":"Hauptstrasse 14",
    "sg:city":"Bettingen",
    "sg:orig_category":"Sportvereine Turnen Vereine Damen",
    "sg:phone":"+41 62 873 10 69",
    "sg:postcode":"4126",
    "sg:province":"Basel-Stadt",
    "wof:name":"Aarg.frauenturnverband",
    "wof:placetype":"venue"
},
  "geometry": {"coordinates":[7.9673762321,47.5383415222],"type":"Point"}
}