{
  "type": "Feature",
  "properties": {
    "iso:country":"CH",
    "sg:address":"Hauptstrasse",
    "sg:city":"Berg\u00fcn/bravuogn",
    "sg:orig_category":"Detailhandel mit Waren verschiedener Art, Hauptrichtung Nahrungsmittel",
    "sg:phone":"+41 33 251 14 87",
    "sg:postcode":"7482",
    "sg:province":"Graubunden",
    "wof:name":"Ernst Menetrey Lebensmittelgesch\u00e4ft",
    "wof:placetype":"venue"
},
  "geometry": {"coordinates":[7.729932785,46.7567596436],"type":"Point"}
}