{
  "type": "Feature",
  "properties": {
    "iso:country":"CH",
    "sg:address":"Ebnetstrasse 17c",
    "sg:city":"St\u00e4fa",
    "sg:orig_category":"Erschliessung von Grundst\u00fccken",
    "sg:phone":"+41 19265213",
    "sg:postcode":"8712",
    "sg:province":"Z\u00fcrich",
    "wof:name":"Baugenossenschaft B\u00e4nklen",
    "wof:placetype":"venue"
},
  "geometry": {"coordinates":[8.735830307,47.2359886169],"type":"Point"}
}