{
  "type": "Feature",
  "properties": {
    "iso:country":"CH",
    "sg:address":"Gumi",
    "sg:city":"Sigriswil",
    "sg:orig_category":"Malerei",
    "sg:phone":"+41 33 251 21 71",
    "sg:postcode":"3655",
    "sg:province":"Bern",
    "wof:name":"Christian Sieber Malergesch\u00e4ft",
    "wof:placetype":"venue"
},
  "geometry": {"coordinates":[7.7118911743,46.7180862427],"type":"Point"}
}