{
  "type": "Feature",
  "properties": {
    "addr:full":"Rheinstrasse 53 Pratteln Basel-Landschaft 4133",
    "addr:housenumber":"53",
    "addr:postcode":"4133",
    "addr:street":"Rheinstrasse",
    "iso:country":"CH",
    "sg:address":"Rheinstrasse 53",
    "sg:city":"Pratteln",
    "sg:orig_category":"Bauingenieurb\u00fcros Heizung L\u00fcftung Klima Herstellung von k\u00e4lte U lufttechnischen Erzeugnissen f\u00fcr gew",
    "sg:phone":"+41 61 813 03 28",
    "sg:postcode":"4133",
    "sg:province":"Basel-Landschaft",
    "wof:name":"S&s Ing. Gmbh",
    "wof:placetype":"venue"
},
  "geometry": {"coordinates":[7.710791,47.534691],"type":"Point"}
}