{
  "type": "Feature",
  "properties": {
    "iso:country":"CH",
    "sg:address":"Rue Du Mol\u00e9son 51",
    "sg:city":"Broc",
    "sg:orig_category":"Sportvereine Ski",
    "sg:phone":"+41 26 921 26 32",
    "sg:postcode":"1636",
    "sg:province":"Fribourg",
    "wof:name":"Ski-club Broc",
    "wof:placetype":"venue"
},
  "geometry": {"coordinates":[7.1003780365,46.6067657471],"type":"Point"}
}