{
  "type": "Feature",
  "properties": {
    "iso:country":"CH",
    "sg:address":"Rue Du Milieu 43",
    "sg:city":"Yverdon-les-bains",
    "sg:classifiers":[
        {
            "category":"Restaurant",
            "type":"Food & Drink"
        }
    ],
    "sg:phone":"+41 24 425 26 74",
    "sg:postcode":"1400",
    "sg:province":"Vaud",
    "wof:name":"Caf\u00e9 Twin's",
    "wof:placetype":"venue"
},
  "geometry": {"coordinates":[6.638628006,46.7788734436],"type":"Point"}
}