{
  "type": "Feature",
  "properties": {
    "iso:country":"CH",
    "sg:address":"Hintere Gasse 2",
    "sg:city":"Remetschwil",
    "sg:orig_category":"Architektur U Ingenieurb\u00fcros",
    "sg:phone":"+41 56 496 30 14",
    "sg:postcode":"5453",
    "sg:province":"Aargau",
    "wof:name":"Intellisys Gmbh",
    "wof:placetype":"venue"
},
  "geometry": {"coordinates":[8.315017,47.411118],"type":"Point"}
}