{
  "type": "Feature",
  "properties": {
    "addr:full":"Oberfeld Gelfingen Luzern 6284",
    "addr:postcode":"6284",
    "iso:country":"CH",
    "sg:address":"Oberfeld",
    "sg:city":"Gelfingen",
    "sg:orig_category":"Bauschreinerei",
    "sg:phone":"+41 41 917 38 91",
    "sg:postcode":"6284",
    "sg:province":"Luzern",
    "wof:name":"Josef & Monika Bl\u00e4ttler Schreinerei",
    "wof:placetype":"venue"
},
  "geometry": {"coordinates":[8.271545,47.211002],"type":"Point"}
}