{
  "type": "Feature",
  "properties": {
    "iso:country":"CH",
    "sg:address":"Ibrigweidstrasse 25",
    "sg:city":"Eich",
    "sg:orig_category":"Grosshandel mit Kaffee, Tee, Kakao U Gew\u00fcrzen Verarbeitung von Tee U Kaffee",
    "sg:phone":"+41 41 460 10 40",
    "sg:postcode":"6205",
    "sg:province":"Luzern",
    "wof:name":"Ruedi Lipp Kaffee & N\u00e4hrmittel",
    "wof:placetype":"venue"
},
  "geometry": {"coordinates":[8.165886879,47.1618919373],"type":"Point"}
}