{
  "type": "Feature",
  "properties": {
    "iso:country":"CH",
    "sg:address":"Z\u00fcrcherstrasse 120",
    "sg:city":"Winterthur",
    "sg:orig_category":"Tierkliniken",
    "sg:phone":"+41 52 202 80 00",
    "sg:postcode":"8406",
    "sg:province":"Z\u00fcrich",
    "wof:name":"Kleintierklinik Acr",
    "wof:placetype":"venue"
},
  "geometry": {"coordinates":[8.7077503204,47.4606933594],"type":"Point"}
}