{
  "type": "Feature",
  "properties": {
    "iso:country":"CH",
    "sg:address":"Rue De Lausanne 30",
    "sg:city":"Payerne",
    "sg:orig_category":"Detailhandel mit Brot, Back U S\u00fcsswaren",
    "sg:phone":"+41 26 660 21 39",
    "sg:postcode":"1530",
    "sg:province":"Vaud",
    "wof:name":"Jean-marc Ducrot Boulangerie",
    "wof:placetype":"venue"
},
  "geometry": {"coordinates":[6.936481,46.819767],"type":"Point"}
}