{
  "type": "Feature",
  "properties": {
    "iso:country":"CH",
    "sg:address":"Solothurnstrasse 3",
    "sg:city":"Biel/bienne",
    "sg:orig_category":"Bauspenglerei Herstellung von Metallerzeugnissen ohne Maschinenbau",
    "sg:phone":"+41 32 344 60 00",
    "sg:postcode":"2504",
    "sg:province":"Bern",
    "wof:name":"Agt Abgassysteme F\u00fcr Feuerst\u00e4tten Ag",
    "wof:placetype":"venue"
},
  "geometry": {"coordinates":[7.268002,47.153866],"type":"Point"}
}