{
  "type": "Feature",
  "properties": {
    "iso:country":"CH",
    "sg:address":"Paulstrasse 19",
    "sg:city":"Winterthur",
    "sg:orig_category":"Arztpraxen",
    "sg:phone":"+41 19722828",
    "sg:postcode":"8400",
    "sg:province":"Z\u00fcrich",
    "wof:name":"Dr.med.hans Neracher Spezialarzt Fmh",
    "wof:placetype":"venue"
},
  "geometry": {"coordinates":[8.800595,47.320938],"type":"Point"}
}