{
  "type": "Feature",
  "properties": {
    "iso:country":"CH",
    "sg:address":"Les Motteresses 11",
    "sg:city":"Thielle-wavre",
    "sg:orig_category":"Unclassifiable Establishments",
    "sg:postcode":"2075",
    "sg:province":"Neuch\u00e2tel",
    "wof:name":"Menuiserie-charpente-toiture, Paul Ch\u00e9del",
    "wof:placetype":"venue"
},
  "geometry": {"coordinates":[6.5663738251,46.9102096558],"type":"Point"}
}