{
  "type": "Feature",
  "properties": {
    "iso:country":"CH",
    "sg:address":"Schaffhauserstr.",
    "sg:city":"Frauenfeld",
    "sg:classifiers":[
        {
            "category":"Manufacturing",
            "subcategory":"Rubber & Plastics",
            "type":"Manufacturing & Wholesale Goods"
        }
    ],
    "sg:phone":"+41 52 720 59 50",
    "sg:postcode":"8500",
    "sg:province":"Thurgau",
    "wof:name":"Thurplast Ag",
    "wof:placetype":"venue"
},
  "geometry": {"coordinates":[8.8808050156,47.5625762939],"type":"Point"}
}