{
  "type": "Feature",
  "properties": {
    "iso:country":"CH",
    "sg:address":"Neuenburgstrasse 162c 2505 Biel/bienne Case Postale 246",
    "sg:city":"Biel/bienne",
    "sg:orig_category":"Sportvereine Wassersport",
    "sg:phone":"+41 41 870 47 70",
    "sg:postcode":"2501",
    "sg:province":"Bern",
    "wof:name":"See-club Fl\u00fcelen",
    "wof:placetype":"venue"
},
  "geometry": {"coordinates":[8.6689882278,46.87657547],"type":"Point"}
}