{
  "type": "Feature",
  "properties": {
    "addr:full":"Les Hauts Du Golf Rte Des M\u00e9l\u00e8ze Lens Valais 1978",
    "addr:postcode":"1978",
    "addr:street":"Les;Du Golf Rte Des Me\u0301Le\u0300Ze",
    "iso:country":"CH",
    "sg:address":"Les Hauts Du Golf Rte Des M\u00e9l\u00e8ze",
    "sg:city":"Lens",
    "sg:orig_category":"Architektur U Ingenieurb\u00fcros",
    "sg:postcode":"1978",
    "sg:province":"Valais",
    "wof:name":"Atelier D'architecture Jean-pierre Emery Sa",
    "wof:placetype":"venue"
},
  "geometry": {"coordinates":[7.44605,46.279324],"type":"Point"}
}