{
  "type": "Feature",
  "properties": {
    "iso:country":"CH",
    "sg:address":"Ch.jean-baptiste Vandelle 16",
    "sg:city":"Versoix",
    "sg:orig_category":"Vereine Gesang",
    "sg:postcode":"1290",
    "sg:province":"Gen\u00e8ve",
    "wof:name":"Chorale Catholique",
    "wof:placetype":"venue"
},
  "geometry": {"coordinates":[6.1655230522,46.2820091248],"type":"Point"}
}