{
  "type": "Feature",
  "properties": {
    "iso:country":"CH",
    "sg:address":"Place Dufour 5",
    "sg:city":"Morges",
    "sg:orig_category":"Interessenvertretungen",
    "sg:postcode":"1110",
    "sg:province":"Vaud",
    "wof:name":"Fondation Chr\u00e9tiens Pour L'an 2000",
    "wof:placetype":"venue"
},
  "geometry": {"coordinates":[6.138874054,46.1853179932],"type":"Point"}
}