{
  "type": "Feature",
  "properties": {
    "iso:country":"CH",
    "sg:address":"Churerstrasse 7",
    "sg:city":"Domat/ems",
    "sg:orig_category":"Mechanische Werkst\u00e4tten Vermietung von Baumaschinen U ger\u00e4ten",
    "sg:postcode":"7013",
    "sg:province":"Graubunden",
    "wof:name":"Ivo Mannhart",
    "wof:placetype":"venue"
},
  "geometry": {"coordinates":[9.4625835419,46.8376541138],"type":"Point"}
}