{
  "type": "Feature",
  "properties": {
    "iso:country":"CH",
    "sg:address":"Standstrasse 2",
    "sg:city":"Arbon",
    "sg:orig_category":"Berufsbildende weiterf\u00fchrende Schulen",
    "sg:phone":"+41 56 441 10 66",
    "sg:postcode":"9320",
    "sg:province":"Thurgau",
    "wof:name":"Berufsschule Brugg",
    "wof:placetype":"venue"
},
  "geometry": {"coordinates":[8.208389,47.484089],"type":"Point"}
}