{
  "type": "Feature",
  "properties": {
    "iso:country":"CH",
    "sg:address":"Ettiswilerstrasse 24 6130 Willisau. Postfach",
    "sg:city":"Willisau",
    "sg:orig_category":"Detailhandel mit M\u00f6beln",
    "sg:phone":"+41 41 970 49 71",
    "sg:postcode":"6130",
    "sg:province":"Luzern",
    "wof:name":"Team-m\u00f6bel Ag",
    "wof:placetype":"venue"
},
  "geometry": {"coordinates":[7.996527195,47.1253738403],"type":"Point"}
}