{
  "type": "Feature",
  "properties": {
    "iso:country":"CH",
    "sg:address":"Egg.",
    "sg:city":"Krummenau",
    "sg:orig_category":"Eisenbahnverkehr",
    "sg:phone":"+41 71 994 27 27",
    "sg:postcode":"9643",
    "sg:province":"St. Gallen",
    "wof:name":"Breitenmoser A.",
    "wof:placetype":"venue"
},
  "geometry": {"coordinates":[9.1713256836,47.2484703064],"type":"Point"}
}