{
  "type": "Feature",
  "properties": {
    "iso:country":"CH",
    "sg:address":"Schulweg 24a",
    "sg:city":"Untervaz",
    "sg:orig_category":"Primarschulen",
    "sg:phone":"+41 81 322 10 67",
    "sg:postcode":"7204",
    "sg:province":"Graubunden",
    "wof:name":"Primarschule",
    "wof:placetype":"venue"
},
  "geometry": {"coordinates":[9.5364637375,46.9292869568],"type":"Point"}
}