{
  "type": "Feature",
  "properties": {
    "iso:country":"CH",
    "sg:address":"Glarnerstrasse 15",
    "sg:city":"Richterswil",
    "sg:orig_category":"P\u00e9dicure",
    "sg:phone":"+41 17846693",
    "sg:postcode":"8805",
    "sg:province":"Z\u00fcrich",
    "wof:name":"Marianne Jucker P\u00e9dicure",
    "wof:placetype":"venue"
},
  "geometry": {"coordinates":[8.7117414474,47.2033538818],"type":"Point"}
}