{
  "type": "Feature",
  "properties": {
    "iso:country":"CH",
    "sg:address":"Kirchgass 5",
    "sg:city":"Berneck",
    "sg:orig_category":"Detailhandel mit Geschenkartikeln U Souvenirs",
    "sg:phone":"+41 71 744 69 15",
    "sg:postcode":"9442",
    "sg:province":"St. Gallen",
    "wof:name":"Antonio Giuliano Boutique Incontro",
    "wof:placetype":"venue"
},
  "geometry": {"coordinates":[9.6120786667,47.424495697],"type":"Point"}
}