{
  "type": "Feature",
  "properties": {
    "iso:country":"CH",
    "sg:address":"Zugerstrasse 51",
    "sg:city":"Cham",
    "sg:orig_category":"Detailhandel mit Radio U Fernsehger\u00e4ten",
    "sg:phone":"+41 41 780 51 22",
    "sg:postcode":"6330",
    "sg:province":"Zug",
    "wof:name":"Gubler Radio Tv",
    "wof:placetype":"venue"
},
  "geometry": {"coordinates":[8.4674320221,47.1821098328],"type":"Point"}
}