{
  "type": "Feature",
  "properties": {
    "iso:country":"CH",
    "sg:address":"Route De Florissant 62",
    "sg:city":"Gen\u00e8ve",
    "sg:orig_category":"Zahnarztpraxen",
    "sg:phone":"+41 22 346 27 93",
    "sg:postcode":"1206",
    "sg:province":"Gen\u00e8ve",
    "wof:name":"Dr M\u00e9d.dent. Jacques-o. Rappo M\u00e9decin-dentiste",
    "wof:placetype":"venue"
},
  "geometry": {"coordinates":[6.1616368294,46.193271637],"type":"Point"}
}