{
  "type": "Feature",
  "properties": {
    "addr:full":"Village Rue Du Sion Valais 1950",
    "addr:postcode":"1950",
    "addr:street":"Rue Du Sion Valais",
    "iso:country":"CH",
    "sg:address":"Village Rue Du",
    "sg:city":"Sion",
    "sg:orig_category":"Allgemeiner Hoch U Tiefbau",
    "sg:postcode":"1950",
    "sg:province":"Valais",
    "wof:name":"Moren Fr\u00e8res Sa",
    "wof:placetype":"venue"
},
  "geometry": {"coordinates":[7.358857,46.228092],"type":"Point"}
}