{
  "type": "Feature",
  "properties": {
    "iso:country":"CH",
    "sg:address":"Schlossweg 12",
    "sg:city":"Naters",
    "sg:orig_category":"Unclassifiable Establishments",
    "sg:postcode":"3904",
    "sg:province":"Valais",
    "wof:name":"Webdream Design Gmbh",
    "wof:placetype":"venue"
},
  "geometry": {"coordinates":[7.9877758026,46.3279800415],"type":"Point"}
}