{
  "type": "Feature",
  "properties": {
    "iso:country":"CH",
    "sg:address":"Guntibachstrasse 10",
    "sg:city":"Ossingen",
    "sg:orig_category":"Vorschulen, Kinderg\u00e4rten",
    "sg:phone":"+41 52 317 15 45",
    "sg:postcode":"8475",
    "sg:province":"Z\u00fcrich",
    "wof:name":"Kindergarten",
    "wof:placetype":"venue"
},
  "geometry": {"coordinates":[8.7287092209,47.6123771667],"type":"Point"}
}