{
  "type": "Feature",
  "properties": {
    "iso:country":"CH",
    "sg:address":"Landhusweg 5",
    "sg:city":"Seebach",
    "sg:orig_category":"Elektroinstallation",
    "sg:phone":"+41 71 311 36 17",
    "sg:postcode":"8052",
    "sg:province":"Z\u00fcrich",
    "wof:name":"Weishaupt Montagen Fenster- U. Baumontagen",
    "wof:placetype":"venue"
},
  "geometry": {"coordinates":[9.3018121719,47.416595459],"type":"Point"}
}