{
  "type": "Feature",
  "properties": {
    "iso:country":"CH",
    "sg:address":"Oltenstrasse 34",
    "sg:city":"Attiswil",
    "sg:orig_category":"Mechanik Mechanische Werkst\u00e4tten",
    "sg:phone":"+41 32 637 12 52",
    "sg:postcode":"4536",
    "sg:province":"Bern",
    "wof:name":"Feinmechanik Mathys",
    "wof:placetype":"venue"
},
  "geometry": {"coordinates":[7.6177282333,47.2477264404],"type":"Point"}
}