{
  "type": "Feature",
  "properties": {
    "iso:country":"CH",
    "sg:address":"Ernst-sch\u00fcler-strasse 66 2502 Biel/bienne Case Postale 449",
    "sg:city":"Biel/bienne",
    "sg:orig_category":"Unternehmensberatung Werbung",
    "sg:phone":"+41 22 308 09 80",
    "sg:postcode":"2502",
    "sg:province":"Bern",
    "wof:name":"Phron\u00e8sis Consulting, Bari Jean-paul Cabinet-conseil En Gestion Publique",
    "wof:placetype":"venue"
},
  "geometry": {"coordinates":[6.1440529823,46.1822662354],"type":"Point"}
}