{
  "type": "Feature",
  "properties": {
    "iso:country":"CH",
    "sg:address":"Bruggmatt 3 6130 Willisau. Postfach 3133",
    "sg:city":"Willisau",
    "sg:orig_category":"Elektroinstallation",
    "sg:phone":"+41 41 972 70 20",
    "sg:postcode":"6130",
    "sg:province":"Luzern",
    "wof:name":"Elektro Illi Ag",
    "wof:placetype":"venue"
},
  "geometry": {"coordinates":[7.9925818443,47.1226119995],"type":"Point"}
}