{
  "type": "Feature",
  "properties": {
    "iso:country":"CH",
    "sg:address":"Chemin Des P\u00e9toleyres 25 1110 Morges. Postfach",
    "sg:city":"Morges",
    "sg:orig_category":"Berufsbildende weiterf\u00fchrende Schulen",
    "sg:phone":"+41 21 803 76 20",
    "sg:postcode":"1110",
    "sg:province":"Vaud",
    "wof:name":"R A F, Arn Roland Formation Formation Dans Le Domaine De La Vente Et De La Communication, Conseil D'entreprise",
    "wof:placetype":"venue"
},
  "geometry": {"coordinates":[6.501881,46.522491],"type":"Point"}
}