{
  "type": "Feature",
  "properties": {
    "iso:country":"CH",
    "sg:address":"Cl\u00e9menty Route De 37 1260 Nyon. Postfach",
    "sg:city":"Nyon",
    "sg:orig_category":"Softwareentwicklung U beratung",
    "sg:phone":"+41 22 362 14 62",
    "sg:postcode":"1260",
    "sg:province":"Vaud",
    "wof:name":"Kandas Concepts S\u00e0rl Syst\u00e8mes D'informations Pour La Finance Des March\u00e9s; Conception, D\u00e9veloppement Et Commercialisation",
    "wof:placetype":"venue"
},
  "geometry": {"coordinates":[6.2328538895,46.3806228638],"type":"Point"}
}