{
  "type": "Feature",
  "properties": {
    "iso:country":"CH",
    "sg:address":"Am Dorfplatz 6",
    "sg:city":"Meggen",
    "sg:orig_category":"Physiotherapie",
    "sg:phone":"+41 41 377 31 62",
    "sg:postcode":"6045",
    "sg:province":"Luzern",
    "wof:name":"S. Kauranen & B. Kunz Physiotherapie",
    "wof:placetype":"venue"
},
  "geometry": {"coordinates":[8.3735589981,47.0463981628],"type":"Point"}
}