{
  "type": "Feature",
  "properties": {
    "iso:country":"CH",
    "sg:address":"1623",
    "sg:city":"Semsales",
    "sg:orig_category":"Sportvereine Sch\u00fctzen",
    "sg:postcode":"1623",
    "sg:province":"Fribourg",
    "wof:name":"St\u00e9 Des Carabiniers",
    "wof:placetype":"venue"
},
  "geometry": {"coordinates":[7.1380701065,46.6968002319],"type":"Point"}
}