{
  "type": "Feature",
  "properties": {
    "iso:country":"CH",
    "sg:address":"7482",
    "sg:city":"Berg\u00fcn/bravuogn",
    "sg:classifiers":[
        {
            "category":"Restaurant",
            "type":"Food & Drink"
        }
    ],
    "sg:phone":"+41 81 407 12 03",
    "sg:postcode":"7482",
    "sg:province":"Graubunden",
    "wof:name":"Rotisserie Fuschena",
    "wof:placetype":"venue"
},
  "geometry": {"coordinates":[9.7946901321,46.621471405],"type":"Point"}
}