{
  "type": "Feature",
  "properties": {
    "iso:country":"CH",
    "sg:address":"Sch\u00f6ngrund 26",
    "sg:city":"Rotkreuz",
    "sg:orig_category":"Verwaltung von Immobilien Wirtschaftspr\u00fcfung, Steuerberatung U Treuhand",
    "sg:phone":"+41 41 790 57 87",
    "sg:postcode":"6343",
    "sg:province":"Zug",
    "wof:name":"Kn\u00fcsel Treuhand Und Verwaltungs Ag",
    "wof:placetype":"venue"
},
  "geometry": {"coordinates":[8.4281053543,47.1457672119],"type":"Point"}
}