{
  "type": "Feature",
  "properties": {
    "iso:country":"CH",
    "sg:address":"Via Alla Campagna 18",
    "sg:city":"Lugano",
    "sg:orig_category":"Verwaltung von Immobilien",
    "sg:postcode":"6900",
    "sg:province":"Ticino",
    "wof:name":"Tamara Entreprise S\u00e0rl Exploitation D'un Etablissement Public",
    "wof:placetype":"venue"
},
  "geometry": {"coordinates":[6.8302731514,47.1027069092],"type":"Point"}
}