{
  "type": "Feature",
  "properties": {
    "iso:country":"CH",
    "sg:address":"Grand-rue 114",
    "sg:city":"Montreux",
    "sg:orig_category":"Detailhandel mit Computern U Software Softwareentwicklung U beratung",
    "sg:phone":"+41 21 962 10 17",
    "sg:postcode":"1820",
    "sg:province":"Vaud",
    "wof:name":"Avct S\u00e0rl",
    "wof:placetype":"venue"
},
  "geometry": {"coordinates":[6.903834,46.440121],"type":"Point"}
}