{
  "type": "Feature",
  "properties": {
    "iso:country":"CH",
    "sg:address":"Sihlhallenstrasse 19 8004 Z\u00fcrich. Postfach",
    "sg:city":"Z\u00fcrich",
    "sg:orig_category":"Herstellung von sonstigen elektrischen Ausr\u00fcstungen",
    "sg:postcode":"8004",
    "sg:province":"Z\u00fcrich",
    "wof:name":"Proseconsulta Ag",
    "wof:placetype":"venue"
},
  "geometry": {"coordinates":[8.5074367523,47.1491966248],"type":"Point"}
}