{
  "type": "Feature",
  "properties": {
    "iso:country":"CH",
    "sg:address":"Duggingerstrasse 10",
    "sg:city":"Reinach",
    "sg:classifiers":[
        {
            "category":"Home & Garden",
            "subcategory":"Household Appliances",
            "type":"Retail Goods"
        }
    ],
    "sg:phone":"+41 61 715 99 11",
    "sg:postcode":"4153",
    "sg:province":"Basel-Landschaft",
    "sg:tags":[
        "stove",
        "chimney"
    ],
    "wof:name":"Armaka Ag",
    "wof:placetype":"venue"
},
  "geometry": {"coordinates":[7.595554,47.487873],"type":"Point"}
}