{
  "type": "Feature",
  "properties": {
    "iso:country":"CH",
    "sg:address":"2946",
    "sg:city":"Mi\u00e9court",
    "sg:orig_category":"Zoll- and Grenzb\u00fcros",
    "sg:phone":"+41 32 462 24 30",
    "sg:postcode":"2946",
    "sg:province":"Jura",
    "wof:name":"Douane Suisse",
    "wof:placetype":"venue"
},
  "geometry": {"coordinates":[7.1752929688,47.4272918701],"type":"Point"}
}