{
  "type": "Feature",
  "properties": {
    "iso:country":"CH",
    "sg:address":"Wenkenr\u00fctistrasse 23",
    "sg:city":"Wattwil",
    "sg:orig_category":"Sanit\u00e4r, Heizungs U L\u00fcftungsinstallation Sanit\u00e4rinstallation",
    "sg:phone":"+41 71 988 17 73",
    "sg:postcode":"9630",
    "sg:province":"St. Gallen",
    "wof:name":"Windirsch Ag Sanit\u00e4r & L\u00fcftung",
    "wof:placetype":"venue"
},
  "geometry": {"coordinates":[9.0795612335,47.3066825867],"type":"Point"}
}