{
  "type": "Feature",
  "properties": {
    "iso:country":"CH",
    "sg:address":"W\u00e4chterweg 5 4614 H\u00e4gendorf. Postfach",
    "sg:city":"H\u00e4gendorf",
    "sg:orig_category":"Reinigungsgewerbe",
    "sg:postcode":"4614",
    "sg:province":"Solothurn",
    "wof:name":"Aerni Pulitop",
    "wof:placetype":"venue"
},
  "geometry": {"coordinates":[7.8420081139,47.3390884399],"type":"Point"}
}