{
  "type": "Feature",
  "properties": {
    "iso:country":"CH",
    "sg:address":"Fehrenstrasse 52",
    "sg:city":"Breitenbach",
    "sg:orig_category":"Non-Classified Establishments",
    "sg:phone":"+41 61 781 21 31",
    "sg:postcode":"4226",
    "sg:province":"Solothurn",
    "wof:name":"Dr.med.dent. Antonio Guarneri Zahnarzt",
    "wof:placetype":"venue"
},
  "geometry": {"coordinates":[7.5498180389,47.40650177],"type":"Point"}
}