{
  "type": "Feature",
  "properties": {
    "iso:country":"CH",
    "sg:address":"Rue Basse 62 2500 Biel/bienne. Postfach",
    "sg:city":"Biel/bienne",
    "sg:orig_category":"Interessenvertretungen",
    "sg:postcode":"2502",
    "sg:province":"Bern",
    "wof:name":"Association Biennoise Des Marchands D'antiquit\u00e9s Et Brocanteurs",
    "wof:placetype":"venue"
},
  "geometry": {"coordinates":[7.2475972176,47.1426048279],"type":"Point"}
}