{
  "type": "Feature",
  "properties": {
    "iso:country":"CH",
    "sg:address":"Baslerstrasse 41",
    "sg:city":"Z\u00fcrich",
    "sg:orig_category":"Saunas Solarien",
    "sg:phone":"+41 14918350",
    "sg:postcode":"8048",
    "sg:province":"Z\u00fcrich",
    "wof:name":"Berta Feyer",
    "wof:placetype":"venue"
},
  "geometry": {"coordinates":[8.5002622604,47.3851890564],"type":"Point"}
}