{
  "type": "Feature",
  "properties": {
    "iso:country":"CH",
    "sg:address":"Hafnerwisenstrasse 1 9442 Berneck. Postfach",
    "sg:city":"Berneck",
    "sg:orig_category":"Papier U Kartongewerbe Verlagsgewerbe",
    "sg:phone":"+41 19511500",
    "sg:postcode":"9442",
    "sg:province":"St. Gallen",
    "wof:name":"Schellenberg Druck Ag Druckerei, Verlag Usw",
    "wof:placetype":"venue"
},
  "geometry": {"coordinates":[8.7730283737,47.3658180237],"type":"Point"}
}