{
  "type": "Feature",
  "properties": {
    "iso:country":"CH",
    "sg:address":"Kreuzplatz 1",
    "sg:city":"Z\u00fcrich",
    "sg:orig_category":"Berufsberatungen",
    "sg:phone":"+41 56 441 58 40",
    "sg:postcode":"8032",
    "sg:province":"Z\u00fcrich",
    "wof:name":"Dr.walter T. Haesler Berufsberatung",
    "wof:placetype":"venue"
},
  "geometry": {"coordinates":[8.201763,47.479538],"type":"Point"}
}