{
  "type": "Feature",
  "properties": {
    "iso:country":"CH",
    "sg:address":"Marktstrasse 34",
    "sg:city":"Sarmenstorf",
    "sg:orig_category":"Gasth\u00f6fe/Gasth\u00e4user mit Restaurant",
    "sg:phone":"+41 56 667 15 77",
    "sg:postcode":"5614",
    "sg:province":"Aargau",
    "wof:name":"Gasthof Wilden Mann",
    "wof:placetype":"venue"
},
  "geometry": {"coordinates":[8.2516183853,47.3105888367],"type":"Point"}
}