{
  "type": "Feature",
  "properties": {
    "iso:country":"CH",
    "sg:address":"1955",
    "sg:city":"Chamoson",
    "sg:orig_category":"Vermietung von Baumaschinen U ger\u00e4ten",
    "sg:postcode":"1955",
    "sg:province":"Valais",
    "wof:name":"Factor Gmbh",
    "wof:placetype":"venue"
},
  "geometry": {"coordinates":[8.466050148,47.4309883118],"type":"Point"}
}