{
  "type": "Feature",
  "properties": {
    "iso:country":"CH",
    "sg:address":"Niederdorfstrasse 11",
    "sg:city":"Z\u00fcrich",
    "sg:orig_category":"Grosshandel mit Zucker, Schokolade U S\u00fcsswaren Herstellung von Dauerbackwaren",
    "sg:phone":"+41 12606540",
    "sg:postcode":"8001",
    "sg:province":"Z\u00fcrich",
    "wof:name":"Sv S\u00fcsswaren Vertriebs Ag",
    "wof:placetype":"venue"
},
  "geometry": {"coordinates":[8.5436296463,47.3732643127],"type":"Point"}
}