{
  "type": "Feature",
  "properties": {
    "iso:country":"CH",
    "sg:address":"Neptunstrasse 96 8032 Z\u00fcrich. Postfach 1858",
    "sg:city":"Z\u00fcrich",
    "sg:orig_category":"HERSTELLUNG VON GER\u00c4TEN DER ELEKTRIZIT\u00c4TSERZEUGUNG, -VERTEILUNG U.\u00c4 Mechanische Werkst\u00e4tten",
    "sg:phone":"+41 13839222",
    "sg:postcode":"8032",
    "sg:province":"Z\u00fcrich",
    "wof:name":"Alpa Capaul & Weber",
    "wof:placetype":"venue"
},
  "geometry": {"coordinates":[8.5585079193,47.3641662598],"type":"Point"}
}