{
  "type": "Feature",
  "properties": {
    "iso:country":"CH",
    "sg:address":"Avenue De La C\u00f4te 20",
    "sg:city":"Vouvry",
    "sg:orig_category":"Zimmerei, Dachdeckerei, Bauspenglerei U Abdichtung",
    "sg:phone":"+41 24 481 13 48",
    "sg:postcode":"1896",
    "sg:province":"Valais",
    "wof:name":"Fercoupo S\u00e0rl",
    "wof:placetype":"venue"
},
  "geometry": {"coordinates":[6.8873968124,46.3351364136],"type":"Point"}
}