{
  "type": "Feature",
  "properties": {
    "iso:country":"CH",
    "sg:address":"Schleusenweg 1a",
    "sg:city":"Biel/bienne",
    "sg:orig_category":"Zahntechnische Laboratorien",
    "sg:phone":"+41 21 944 31 62",
    "sg:postcode":"2502",
    "sg:province":"Bern",
    "wof:name":"Pierre Nicole Laboratoire Dentaire",
    "wof:placetype":"venue"
},
  "geometry": {"coordinates":[6.8552641869,46.4550933838],"type":"Point"}
}