{
  "type": "Feature",
  "properties": {
    "iso:country":"CH",
    "sg:address":"St\u00e4dtli 14",
    "sg:city":"Wiedlisbach",
    "sg:orig_category":"Offsetdruck Schnelldruck U Kopierservice",
    "sg:phone":"+41 27 932 33 22",
    "sg:postcode":"4537",
    "sg:province":"Bern",
    "wof:name":"Druckerei Mutter Ag",
    "wof:placetype":"venue"
},
  "geometry": {"coordinates":[7.7464680672,46.3153152466],"type":"Point"}
}