{
  "type": "Feature",
  "properties": {
    "iso:country":"CH",
    "sg:address":"Bruggweg 3",
    "sg:city":"Frenkendorf",
    "sg:orig_category":"Maler U Glasergewerbe Tapeziererei",
    "sg:phone":"+41 61 901 76 20",
    "sg:postcode":"4402",
    "sg:province":"Basel-Landschaft",
    "wof:name":"G. Branca & Sohn Ag Malergesch\u00e4ft",
    "wof:placetype":"venue"
},
  "geometry": {"coordinates":[7.7180762291,47.5039901733],"type":"Point"}
}