{
  "type": "Feature",
  "properties": {
    "iso:country":"CH",
    "sg:address":"Innerer Hof 2",
    "sg:city":"Klosters",
    "sg:orig_category":"W\u00e4scherei U chemische Reinigung",
    "sg:phone":"+41 81 422 44 40",
    "sg:postcode":"7250",
    "sg:province":"Graubunden",
    "wof:name":"Fl\u00fctsch Textilreinigungs Ag",
    "wof:placetype":"venue"
},
  "geometry": {"coordinates":[9.8800611496,46.8724555969],"type":"Point"}
}