{
  "type": "Feature",
  "properties": {
    "iso:country":"CH",
    "sg:address":"Schulstrasse 24",
    "sg:city":"Birsfelden",
    "sg:orig_category":"Politische Parteien Evangelische Volkspartei",
    "sg:phone":"+41 61 311 37 24",
    "sg:postcode":"4127",
    "sg:province":"Basel-Landschaft",
    "wof:name":"Evp Ortspartei Birsfelden",
    "wof:placetype":"venue"
},
  "geometry": {"coordinates":[7.6244540215,47.5542678833],"type":"Point"}
}