{
  "type": "Feature",
  "properties": {
    "iso:country":"CH",
    "sg:address":"Pf\u00e4ndwiesenstrasse 15",
    "sg:city":"Opfikon",
    "sg:orig_category":"Reinigungsgewerbe",
    "sg:phone":"+41 18108276",
    "sg:postcode":"8152",
    "sg:province":"Z\u00fcrich",
    "wof:name":"Luis Ti Reinigung Yanez L. + Co",
    "wof:placetype":"venue"
},
  "geometry": {"coordinates":[8.5734863281,47.4334144592],"type":"Point"}
}