{
  "type": "Feature",
  "properties": {
    "iso:country":"CH",
    "sg:address":"Im Rebh\u00fcgel 52",
    "sg:city":"Eggenwil",
    "sg:orig_category":"Fahrschulen, Flugschulen",
    "sg:phone":"+41 56 631 61 53",
    "sg:postcode":"5445",
    "sg:province":"Aargau",
    "wof:name":"Ren\u00e9 Altschul Autofahrschule",
    "wof:placetype":"venue"
},
  "geometry": {"coordinates":[8.3373479843,47.3727302551],"type":"Point"}
}