{
  "type": "Feature",
  "properties": {
    "iso:country":"CH",
    "sg:address":"Sabelmattweg 9",
    "sg:city":"Nunningen",
    "sg:orig_category":"Zimmerei, Dachdeckerei, Bauspenglerei U Abdichtung Zimmerei, Ingenieurholzbau",
    "sg:phone":"+41 61 791 01 28",
    "sg:postcode":"4208",
    "sg:province":"Solothurn",
    "wof:name":"H\u00e4nggi Josef",
    "wof:placetype":"venue"
},
  "geometry": {"coordinates":[7.6096777916,47.3569984436],"type":"Point"}
}