{
  "type": "Feature",
  "properties": {
    "iso:country":"CH",
    "sg:address":"Friedensstrasse 20",
    "sg:city":"Liestal",
    "sg:orig_category":"Maturit\u00e4tsschulen, Lehrerseminarien",
    "sg:phone":"+41 61 921 22 80",
    "sg:postcode":"4410",
    "sg:province":"Basel-Landschaft",
    "wof:name":"Gymnasium Rektorat & Sekretariat",
    "wof:placetype":"venue"
},
  "geometry": {"coordinates":[7.7246890068,47.4827728271],"type":"Point"}
}