{
  "type": "Feature",
  "properties": {
    "iso:country":"CH",
    "sg:address":"Baslerstrasse 50",
    "sg:city":"Binningen",
    "sg:orig_category":"Fussboden, Fliesen U Plattenlegerei, Tapeziererei",
    "sg:postcode":"4102",
    "sg:province":"Basel-Landschaft",
    "wof:name":"Marti, Otto",
    "wof:placetype":"venue"
},
  "geometry": {"coordinates":[7.6989850998,47.2085762024],"type":"Point"}
}