{
  "type": "Feature",
  "properties": {
    "iso:country":"CH",
    "sg:address":"3157",
    "sg:city":"Milken",
    "sg:classifiers":[
        {
            "category":"Government",
            "subcategory":"Post Office",
            "type":"Public Place"
        }
    ],
    "sg:phone":"+41 31 731 01 07",
    "sg:postcode":"3157",
    "sg:province":"Bern",
    "sg:tags":[
        "die",
        "poststellen"
    ],
    "wof:name":"Die Post",
    "wof:placetype":"venue"
},
  "geometry": {"coordinates":[7.3591098785,46.7930908203],"type":"Point"}
}