{
  "type": "Feature",
  "properties": {
    "iso:country":"CH",
    "sg:address":"Sch\u00f6ntal 16",
    "sg:city":"Zumikon",
    "sg:orig_category":"Sonstiger Grosshandel",
    "sg:phone":"+41 12149820",
    "sg:postcode":"8126",
    "sg:province":"Z\u00fcrich",
    "wof:name":"Freetimex Ag Import-export",
    "wof:placetype":"venue"
},
  "geometry": {"coordinates":[8.6131801605,47.3318595886],"type":"Point"}
}