{
  "type": "Feature",
  "properties": {
    "iso:country":"CH",
    "sg:address":"Chemin Du Vieux-moulin 61b",
    "sg:city":"Chavornay",
    "sg:orig_category":"Dienstleistungen von Beteiligungsgesellschaften",
    "sg:phone":"+41 19947264",
    "sg:postcode":"1373",
    "sg:province":"Vaud",
    "wof:name":"Ob+a Dietschi Organisation Beratung + Administration Gmbh",
    "wof:placetype":"venue"
},
  "geometry": {"coordinates":[8.6900548935,47.3005561829],"type":"Point"}
}