{
  "type": "Feature",
  "properties": {
    "iso:country":"CH",
    "sg:address":"Lyssstr. 2",
    "sg:city":"Dotzigen",
    "sg:orig_category":"Detailhandel mit Fleisch U Fleischwaren",
    "sg:phone":"+41 79 220 31 08",
    "sg:postcode":"3293",
    "sg:province":"Bern",
    "wof:name":"Dorfmetzg Bumann Marco",
    "wof:placetype":"venue"
},
  "geometry": {"coordinates":[7.933672905,46.1117172241],"type":"Point"}
}