{
  "type": "Feature",
  "properties": {
    "iso:country":"CH",
    "sg:address":"Dorfstrasse 12",
    "sg:city":"K\u00f6niz",
    "sg:orig_category":"Grosshandel mit Getr\u00e4nken",
    "sg:postcode":"3098",
    "sg:province":"Bern",
    "wof:name":"Rita Krebs Weinperle",
    "wof:placetype":"venue"
},
  "geometry": {"coordinates":[7.410900116,46.920791626],"type":"Point"}
}