{
  "type": "Feature",
  "properties": {
    "addr:full":"Mont\u00e9zillon Rochefort 2203",
    "addr:postcode":"2203",
    "iso:country":"CH",
    "sg:address":"Mont\u00e9zillon",
    "sg:city":"Rochefort",
    "sg:orig_category":"Architektur U Ingenieurb\u00fcros",
    "sg:phone":"+41 32 731 53 53",
    "sg:postcode":"2203",
    "wof:name":"Matthey B. Ing\u00e9nieurs-conseils Sa.",
    "wof:placetype":"venue"
},
  "geometry": {"coordinates":[6.83694,46.986431],"type":"Point"}
}