{
  "type": "Feature",
  "properties": {
    "iso:country":"CH",
    "sg:address":"S\u00fcdstrasse 86",
    "sg:city":"Z\u00fcrich",
    "sg:orig_category":"Politische Parteien FDP Vereine Frauen",
    "sg:phone":"+41 14228867",
    "sg:postcode":"8008",
    "sg:province":"Z\u00fcrich",
    "wof:name":"Fdp Frauen Der Stadt Z\u00fcrich",
    "wof:placetype":"venue"
},
  "geometry": {"coordinates":[8.5664377213,47.3514671326],"type":"Point"}
}