{
  "type": "Feature",
  "properties": {
    "iso:country":"CH",
    "sg:address":"Ruostelstrasse 30 8835 Feusisberg. Postfach 66",
    "sg:city":"Feusisberg",
    "sg:orig_category":"Erbringung von Dienstleistungen f\u00fcr Unternehmen Markt U Meinungsforschung",
    "sg:phone":"+41 41 249 98 68",
    "sg:postcode":"8835",
    "sg:province":"Schwyz",
    "wof:name":"Suxess - The Creative Company",
    "wof:placetype":"venue"
},
  "geometry": {"coordinates":[8.2992229462,47.051197052],"type":"Point"}
}