{
  "type": "Feature",
  "properties": {
    "iso:country":"CH",
    "sg:address":"Im Muchried 10",
    "sg:city":"Wettswil",
    "sg:orig_category":"Wirtschaftspr\u00fcfung, Steuerberatung U Treuhand",
    "sg:postcode":"8907",
    "sg:province":"Z\u00fcrich",
    "wof:name":"B&b Service Gmbh",
    "wof:placetype":"venue"
},
  "geometry": {"coordinates":[8.4747104645,47.3282814026],"type":"Point"}
}