{
  "type": "Feature",
  "properties": {
    "iso:country":"CH",
    "sg:address":"Im G\u00e4ssli 4.",
    "sg:city":"Hochwald",
    "sg:orig_category":"Architektur U Ingenieurb\u00fcros",
    "sg:postcode":"4146",
    "sg:province":"Solothurn",
    "wof:name":"Hartmann Karl H. Ingenieurb\u00fcro F\u00fcr Hoch Und Tiefbau",
    "wof:placetype":"venue"
},
  "geometry": {"coordinates":[7.641714,47.458134],"type":"Point"}
}