{
  "type": "Feature",
  "properties": {
    "iso:country":"CH",
    "sg:address":"Route Du Barrage 70",
    "sg:city":"Rossens",
    "sg:classifiers":[
        {
            "category":"Transit Center",
            "subcategory":"Freight",
            "type":"Transportation"
        }
    ],
    "sg:phone":"+41 26 411 14 14",
    "sg:postcode":"1728",
    "sg:province":"Fribourg",
    "sg:tags":[
        "load",
        "cell",
        "dynamometers"
    ],
    "wof:name":"Reznicek & Hlach S.a.",
    "wof:placetype":"venue"
},
  "geometry": {"coordinates":[7.1014771461,46.7198066711],"type":"Point"}
}