{
  "type": "Feature",
  "properties": {
    "iso:country":"CH",
    "sg:address":"Tramstrasse 107",
    "sg:city":"Suhr",
    "sg:orig_category":"Sanit\u00e4r, Heizungs U L\u00fcftungsinstallation Sanit\u00e4rinstallation",
    "sg:phone":"+41 62 824 10 27",
    "sg:postcode":"5034",
    "sg:province":"Aargau",
    "wof:name":"Stofer R. Gmbh",
    "wof:placetype":"venue"
},
  "geometry": {"coordinates":[8.0671977997,47.3864440918],"type":"Point"}
}