{
  "type": "Feature",
  "properties": {
    "iso:country":"CH",
    "sg:address":"Sch\u00fc\u00fcrlimattstrasse 9",
    "sg:city":"Port",
    "sg:orig_category":"Architektur U Ingenieurb\u00fcros Architekturb\u00fcros",
    "sg:phone":"+41 32 331 22 11",
    "sg:postcode":"2562",
    "sg:province":"Bern",
    "wof:name":"Travaglini Marco Architekt Htl",
    "wof:placetype":"venue"
},
  "geometry": {"coordinates":[7.24749,47.115341],"type":"Point"}
}