{
  "type": "Feature",
  "properties": {
    "iso:country":"CH",
    "sg:address":"Centralstrasse 32 6210 Sursee. Postfach 207",
    "sg:city":"Sursee",
    "sg:orig_category":"Arztpraxen",
    "sg:phone":"+41 41 921 28 58",
    "sg:postcode":"6210",
    "sg:province":"Luzern",
    "wof:name":"Dr.med.hansjakob Roelli Spezialarzt Fmh",
    "wof:placetype":"venue"
},
  "geometry": {"coordinates":[8.101137,47.170353],"type":"Point"}
}