{
  "type": "Feature",
  "properties": {
    "iso:country":"CH",
    "sg:address":"Seehaldenweg 20",
    "sg:city":"Tenniken",
    "sg:orig_category":"Handelsvermittlung Wirtschaftspr\u00fcfung, Steuerberatung U Treuhand",
    "sg:postcode":"4456",
    "sg:province":"Basel-Landschaft",
    "wof:name":"W&f Consilium Gmbh Unternehmensdiesntleistungen",
    "wof:placetype":"venue"
},
  "geometry": {"coordinates":[7.8107728958,47.439453125],"type":"Point"}
}