{
  "type": "Feature",
  "properties": {
    "iso:country":"CH",
    "sg:address":"Vechigen",
    "sg:city":"Boll",
    "sg:orig_category":"Herstellung von Futtermitteln f\u00fcr Nutztiere Mahl U Sch\u00e4lm\u00fchlen",
    "sg:phone":"+41 31 839 24 35",
    "sg:postcode":"3067",
    "sg:province":"Bern",
    "wof:name":"Gottfried Schindler M\u00fchle",
    "wof:placetype":"venue"
},
  "geometry": {"coordinates":[7.5487799644,46.9543113708],"type":"Point"}
}