{
  "type": "Feature",
  "properties": {
    "addr:full":"Sack Wernetshausen 8340 Girenbad B. Hinwil. Postfach Wernetshausen Z\u00fcrich 8342",
    "addr:postcode":"8340 girenbad;postfach;8342",
    "addr:street":"Hinwil.",
    "iso:country":"CH",
    "sg:address":"Sack Wernetshausen 8340 Girenbad B. Hinwil. Postfach",
    "sg:city":"Wernetshausen",
    "sg:orig_category":"Architektur U Ingenieurb\u00fcros",
    "sg:phone":"+41 31 950 45 45",
    "sg:postcode":"8342",
    "sg:province":"Z\u00fcrich",
    "wof:name":"Ramseier + Stucki, Architekten Ag",
    "wof:placetype":"venue"
},
  "geometry": {"coordinates":[7.483871,46.933208],"type":"Point"}
}