{
  "type": "Feature",
  "properties": {
    "iso:country":"CH",
    "sg:address":"L\u00e4rchenstrasse 14",
    "sg:city":"Liestal",
    "sg:orig_category":"Vorschulen, Kinderg\u00e4rten",
    "sg:phone":"+41 61 901 27 18",
    "sg:postcode":"4410",
    "sg:province":"Basel-Landschaft",
    "wof:name":"Kindergarten Radacker 3",
    "wof:placetype":"venue"
},
  "geometry": {"coordinates":[7.7231879234,47.4929504395],"type":"Point"}
}