{
  "type": "Feature",
  "properties": {
    "iso:country":"CH",
    "sg:address":"Guschstrasse 2",
    "sg:city":"Uster",
    "sg:orig_category":"Mechanische Werkst\u00e4tten",
    "sg:phone":"+41 19404800",
    "sg:postcode":"8610",
    "sg:province":"Z\u00fcrich",
    "wof:name":"Wilhelm Schiegg Mechanische Werkst\u00e4tte",
    "wof:placetype":"venue"
},
  "geometry": {"coordinates":[8.7246799469,47.345539093],"type":"Point"}
}