{
  "type": "Feature",
  "properties": {
    "iso:country":"CH",
    "sg:address":"Dorfstrasse 57",
    "sg:city":"Dintikon",
    "sg:classifiers":[
        {
            "category":"Restaurant",
            "type":"Food & Drink"
        }
    ],
    "sg:phone":"+41 56 624 12 21",
    "sg:postcode":"5606",
    "sg:province":"Aargau",
    "wof:name":"Gasthaus Zum B\u00e4ren",
    "wof:placetype":"venue"
},
  "geometry": {"coordinates":[8.2299146652,47.3680305481],"type":"Point"}
}