{
  "type": "Feature",
  "properties": {
    "iso:country":"CH",
    "sg:address":"Buacherweg 31b",
    "sg:city":"Niederrohrdorf",
    "sg:orig_category":"Non-Classified Establishments",
    "sg:phone":"+41 56 496 54 66",
    "sg:postcode":"5443",
    "sg:province":"Aargau",
    "wof:name":"Flexjoint Gmbh",
    "wof:placetype":"venue"
},
  "geometry": {"coordinates":[8.3095531464,47.4190864563],"type":"Point"}
}