{
  "type": "Feature",
  "properties": {
    "iso:country":"CH",
    "sg:address":"Platz 16 9100 Herisau. Postfach 1559",
    "sg:city":"Herisau",
    "sg:orig_category":"Detailhandel mit Brillen U anderen Sehhilfen Fachdetailhandel in Verkaufsr\u00e4umen",
    "sg:phone":"+41 71 351 11 85",
    "sg:postcode":"9102",
    "sg:province":"Appenzell Ausserrhoden",
    "wof:name":"W\u00fcrsch Optik",
    "wof:placetype":"venue"
},
  "geometry": {"coordinates":[9.27911,47.385651],"type":"Point"}
}