{
  "type": "Feature",
  "properties": {
    "iso:country":"CH",
    "sg:address":"Stampfenbachstrasse 24 8001 Z\u00fcrich. Postfach",
    "sg:city":"Z\u00fcrich",
    "sg:orig_category":"Detailhandel mit Spielwaren Sonstiger Detailhandel mit Metallwaren, Anstrichmitteln, Glaswaren, Bau ",
    "sg:phone":"+41 12615791",
    "sg:postcode":"8035",
    "sg:province":"Z\u00fcrich",
    "wof:name":"\u00abhobby\u00bb Jost P., Inhaber Sp\u00fchler-angst K. & M. Techn. Spielwaren",
    "wof:placetype":"venue"
},
  "geometry": {"coordinates":[8.5438079834,47.3784599304],"type":"Point"}
}