{
  "type": "Feature",
  "properties": {
    "iso:country":"CH",
    "sg:address":"Route De Fribourg 77",
    "sg:city":"Posieux",
    "sg:orig_category":"Nationale Postdienste",
    "sg:phone":"+41 26 411 11 61",
    "sg:postcode":"1725",
    "sg:province":"Fribourg",
    "wof:name":"La Poste Suisse",
    "wof:placetype":"venue"
},
  "geometry": {"coordinates":[7.095459938,46.7608032227],"type":"Point"}
}