{
  "type": "Feature",
  "properties": {
    "iso:country":"CH",
    "sg:address":"Impasse Champ-colin 3",
    "sg:city":"Nyon",
    "sg:orig_category":"Offsetdruck",
    "sg:phone":"+41 22 361 33 10",
    "sg:postcode":"1260",
    "sg:province":"Vaud",
    "wof:name":"Imprimerie Lanz Cie",
    "wof:placetype":"venue"
},
  "geometry": {"coordinates":[6.2186098099,46.3849411011],"type":"Point"}
}