{
  "type": "Feature",
  "properties": {
    "iso:country":"CH",
    "sg:address":"Oltnerstrasse 46",
    "sg:city":"Egerkingen",
    "sg:orig_category":"Instandhaltung U Reparatur von Automobilen",
    "sg:phone":"+41 62 388 80 80",
    "sg:postcode":"4622",
    "sg:province":"Solothurn",
    "wof:name":"Garage Reinhart",
    "wof:placetype":"venue"
},
  "geometry": {"coordinates":[7.8047399521,47.3231620789],"type":"Point"}
}