{
  "type": "Feature",
  "properties": {
    "addr:full":"Rue Pierre-jolissaint 36 2610 St-imier. Postfach St-imier Bern 2610",
    "addr:housenumber":"36",
    "addr:postcode":"2610;2610",
    "addr:street":"Rue Pierre-Jolissaint;Postfach",
    "iso:country":"CH",
    "sg:address":"Rue Pierre-jolissaint 36 2610 St-imier. Postfach",
    "sg:city":"St-imier",
    "sg:orig_category":"Advokaturb\u00fcros",
    "sg:phone":"+41 17256666",
    "sg:postcode":"2610",
    "sg:province":"Bern",
    "wof:name":"St\u00fcnzi & Weber Advokaturb\u00fcro",
    "wof:placetype":"venue"
},
  "geometry": {"coordinates":[8.599345,47.259872],"type":"Point"}
}