{
  "type": "Feature",
  "properties": {
    "iso:country":"CH",
    "sg:address":"Sch\u00fctzengasse 19a",
    "sg:city":"Biel/bienne",
    "sg:orig_category":"Physiotherapie",
    "sg:phone":"+41 32 322 45 88",
    "sg:postcode":"2502",
    "sg:province":"Bern",
    "wof:name":"Christian Schl\u00e4ppi Physiotherapie",
    "wof:placetype":"venue"
},
  "geometry": {"coordinates":[7.2471828461,47.1439361572],"type":"Point"}
}