{
  "type": "Feature",
  "properties": {
    "iso:country":"CH",
    "sg:address":"Chemin Des Epinoux 4",
    "sg:city":"Mont-sur-lausanne",
    "sg:orig_category":"Public-Relations-Agenturen",
    "sg:phone":"+41 21 652 17 96",
    "sg:postcode":"1052",
    "sg:province":"Vaud",
    "wof:name":"Pierre Haenggi Coditra",
    "wof:placetype":"venue"
},
  "geometry": {"coordinates":[6.6469888687,46.5482368469],"type":"Point"}
}