{
  "type": "Feature",
  "properties": {
    "iso:country":"CH",
    "sg:address":"Kapfstrasse 2",
    "sg:city":"Eichberg",
    "sg:orig_category":"RESTAURANTS: TEA-ROOMS",
    "sg:phone":"+41 71 755 15 82",
    "sg:postcode":"9453",
    "sg:province":"St. Gallen",
    "wof:name":"Restaurant Sonne Schiesser Silvia",
    "wof:placetype":"venue"
},
  "geometry": {"coordinates":[9.5260038376,47.3453407288],"type":"Point"}
}