{
  "type": "Feature",
  "properties": {
    "iso:country":"CH",
    "sg:address":"Cantonale Via 13",
    "sg:city":"Lugano",
    "sg:orig_category":"Maler U Glasergewerbe",
    "sg:postcode":"6900",
    "sg:province":"Ticino",
    "wof:name":"Taddei F.lli - Succ. Di Arturo Genazzini",
    "wof:placetype":"venue"
},
  "geometry": {"coordinates":[8.9501237869,46.0081596375],"type":"Point"}
}