{
  "type": "Feature",
  "properties": {
    "iso:country":"CH",
    "sg:address":"R\u00f6merstrasse 205 8404 Oberwinterthur. Postfach",
    "sg:city":"Fehraltorf",
    "sg:orig_category":"Fachdetailhandel in Verkaufsr\u00e4umen",
    "sg:postcode":"8320",
    "sg:province":"Z\u00fcrich",
    "wof:name":"Lavague Hydrogear Laurent & R\u00fcdis\u00fcli",
    "wof:placetype":"venue"
},
  "geometry": {"coordinates":[8.7564764023,47.5084342957],"type":"Point"}
}