{
  "type": "Feature",
  "properties": {
    "iso:country":"CH",
    "sg:address":"1510",
    "sg:city":"Moudon",
    "sg:orig_category":"Verwertung von Milch",
    "sg:postcode":"1510",
    "sg:province":"Vaud",
    "wof:name":"Soci\u00e9t\u00e9 De Laiterie De Moudon",
    "wof:placetype":"venue"
},
  "geometry": {"coordinates":[6.8003668785,46.6674957275],"type":"Point"}
}