{
  "type": "Feature",
  "properties": {
    "iso:country":"CH",
    "sg:address":"Cond\u00e9mines Rue Des 21",
    "sg:city":"Yverdon-les-bains",
    "sg:orig_category":"Herstellung von Konstruktionsteilen, Fertigbauteilen U Ausbauelementen aus Holz",
    "sg:phone":"+41 24 426 21 21",
    "sg:postcode":"1400",
    "sg:province":"Vaud",
    "wof:name":"Independservice, Ch\u00e9del Christian",
    "wof:placetype":"venue"
},
  "geometry": {"coordinates":[6.652291,46.76672],"type":"Point"}
}