{
  "type": "Feature",
  "properties": {
    "iso:country":"CH",
    "sg:address":"Lindenquai 4",
    "sg:city":"Chur",
    "sg:orig_category":"Architektur U Ingenieurb\u00fcros",
    "sg:phone":"+41 81 250 72 50",
    "sg:postcode":"7000",
    "sg:province":"Graubunden",
    "wof:name":"Fontana Angelo Bauleitungen Gmbh",
    "wof:placetype":"venue"
},
  "geometry": {"coordinates":[9.529533,46.847523],"type":"Point"}
}