{
  "type": "Feature",
  "properties": {
    "iso:country":"CH",
    "sg:address":"H\u00f6hgstrasse 19",
    "sg:city":"Oberhelfenschwil",
    "sg:orig_category":"Architektur U Ingenieurb\u00fcros Architekturb\u00fcros",
    "sg:phone":"+41 71 374 21 31",
    "sg:postcode":"9621",
    "sg:province":"St. Gallen",
    "wof:name":"Fredy Kull Ag Architekturb\u00fcro",
    "wof:placetype":"venue"
},
  "geometry": {"coordinates":[9.105577,47.358665],"type":"Point"}
}