{
  "type": "Feature",
  "properties": {
    "iso:country":"CH",
    "sg:address":"Langelenstrasse 28 5606 Dintikon. Postfach 34",
    "sg:city":"Dintikon",
    "sg:orig_category":"Bauschreinerei Schiffs U Bootsbau",
    "sg:phone":"+41 56 624 26 36",
    "sg:postcode":"5606",
    "sg:province":"Aargau",
    "wof:name":"Siegfried Meier Schreinerei Und Bootsbau, Inhaber Rosa Meier",
    "wof:placetype":"venue"
},
  "geometry": {"coordinates":[8.232165,47.366169],"type":"Point"}
}