{
  "type": "Feature",
  "properties": {
    "iso:country":"CH",
    "sg:address":"Rue Des Tilleuls 1",
    "sg:city":"Develier",
    "sg:orig_category":"Allgemeiner Hochbau",
    "sg:phone":"+41 32 422 44 55",
    "sg:postcode":"2802",
    "sg:province":"Jura",
    "wof:name":"Auguste Zamboni Entreprise De B\u00e2timent",
    "wof:placetype":"venue"
},
  "geometry": {"coordinates":[7.291154,47.356606],"type":"Point"}
}