{
  "type": "Feature",
  "properties": {
    "addr:full":"Les Pl\u00e9iades 1807 Blonay. Postfach Blonay Vaud 1807",
    "addr:postcode":"1807 blonay. postfach blonay;1807",
    "addr:street":"Ple\u0301Iades",
    "iso:country":"CH",
    "sg:address":"Les Pl\u00e9iades 1807 Blonay. Postfach",
    "sg:city":"Blonay",
    "sg:orig_category":"Allgemeiner Hoch U Tiefbau",
    "sg:postcode":"1807",
    "sg:province":"Vaud",
    "wof:name":"Membrez Laurent Sa, Succursale De Renens Travaux De Construction, G\u00e9nie Civil, Voies Ferr\u00e9es",
    "wof:placetype":"venue"
},
  "geometry": {"coordinates":[6.57939,46.539082],"type":"Point"}
}