{
  "type": "Feature",
  "properties": {
    "iso:country":"CH",
    "sg:address":"Gerechtigkeitsgasse 50",
    "sg:city":"Bern",
    "sg:classifiers":[
        {
            "category":"Bars & Pubs",
            "type":"Food & Drink"
        }
    ],
    "sg:phone":"+41 31 312 22 01",
    "sg:postcode":"3011",
    "sg:province":"Bern",
    "wof:name":"Different-bar",
    "wof:placetype":"venue"
},
  "geometry": {"coordinates":[7.454093,46.948318],"type":"Point"}
}