{
  "type": "Feature",
  "properties": {
    "iso:country":"CH",
    "sg:address":"Brahmsstrasse 10 8003 Z\u00fcrich. Postfach",
    "sg:city":"Z\u00fcrich",
    "sg:orig_category":"Non-Classified Establishments",
    "sg:phone":"+41 14913567",
    "sg:postcode":"8001",
    "sg:province":"Z\u00fcrich",
    "wof:name":"Trieloff Kommunikation Kommunikationsberatung, Projektleitung",
    "wof:placetype":"venue"
},
  "geometry": {"coordinates":[8.5076055527,47.3783874512],"type":"Point"}
}