{
  "type": "Feature",
  "properties": {
    "iso:country":"CH",
    "sg:address":"Anton Graff-strasse 71",
    "sg:city":"Winterthur",
    "sg:orig_category":"Wohnheime",
    "sg:phone":"+41 52 203 22 10",
    "sg:postcode":"8400",
    "sg:province":"Z\u00fcrich",
    "wof:name":"W\u00f6lfflin-stiftung",
    "wof:placetype":"venue"
},
  "geometry": {"coordinates":[8.7130155563,47.499080658],"type":"Point"}
}