{
  "type": "Feature",
  "properties": {
    "iso:country":"CH",
    "sg:address":"Bahnhofplatz 2 6003 Luzern. Postfach 4856",
    "sg:city":"Luzern",
    "sg:orig_category":"Sonstige Hilfs U Nebent\u00e4tigkeiten f\u00fcr den Landverkehr",
    "sg:postcode":"6002",
    "sg:province":"Luzern",
    "wof:name":"Tiefgarage Bahnhofplatz Ag Unterirdische Parkgarage Mit Nebenanlagen Auf Dem Bahnhofplatz Usw",
    "wof:placetype":"venue"
},
  "geometry": {"coordinates":[8.3091011047,47.0504302979],"type":"Point"}
}