{
  "type": "Feature",
  "properties": {
    "iso:country":"CH",
    "sg:address":"J\u00e4gerweg 5",
    "sg:city":"Riggisberg",
    "sg:orig_category":"Bauschreinerei Erbringung von sonstigen Dienstleistungen f\u00fcr Unternehmen",
    "sg:phone":"+41 31 809 27 30",
    "sg:postcode":"3132",
    "sg:province":"Bern",
    "wof:name":"Kurt Schwendimann Modellbau-atelier",
    "wof:placetype":"venue"
},
  "geometry": {"coordinates":[7.483044,46.809956],"type":"Point"}
}