{
  "type": "Feature",
  "properties": {
    "iso:country":"CH",
    "sg:address":"Bifangstrasse 35",
    "sg:city":"Neuendorf",
    "sg:orig_category":"Instandhaltung U Reparatur von Automobilen Mechanische Werkst\u00e4tten",
    "sg:phone":"+41 62 398 25 81",
    "sg:postcode":"4623",
    "sg:province":"Solothurn",
    "wof:name":"Paul Zeltner-strub",
    "wof:placetype":"venue"
},
  "geometry": {"coordinates":[7.7958798409,47.2999687195],"type":"Point"}
}