{
  "type": "Feature",
  "properties": {
    "addr:full":"Landstrasse 91 9495 Triesen. Postfach 329 Triesen 9495",
    "addr:housenumber":"91;329",
    "addr:postcode":"9495 triesen.;9495",
    "addr:street":"Landstrasse;Postfach",
    "iso:country":"CH",
    "sg:address":"Landstrasse 91 9495 Triesen. Postfach 329",
    "sg:city":"Triesen",
    "sg:orig_category":"Detailhandel mit Brot, Back U S\u00fcsswaren",
    "sg:phone":"+423 392 37 27",
    "sg:postcode":"9495",
    "wof:name":"Dietmar Heeb B\u00e4ckerei-konditorei",
    "wof:placetype":"venue"
},
  "geometry": {"coordinates":[9.524029,47.117157],"type":"Point"}
}