{
  "type": "Feature",
  "properties": {
    "iso:country":"CH",
    "sg:address":"Capannone Zucchetti",
    "sg:city":"Bironico",
    "sg:orig_category":"Technische, physikalische U chemische Untersuchung",
    "sg:postcode":"6804",
    "sg:province":"Ticino",
    "wof:name":"Gemmalux Sa",
    "wof:placetype":"venue"
},
  "geometry": {"coordinates":[8.9349536896,46.1139526367],"type":"Point"}
}