{
  "type": "Feature",
  "properties": {
    "iso:country":"CH",
    "sg:address":"Industriestrasse 9",
    "sg:city":"Risch",
    "sg:orig_category":"Kauf U Verkauf von Immobilien auf eigene Rechnung",
    "sg:postcode":"6343",
    "sg:province":"Zug",
    "wof:name":"Stuber Immobilien Ag",
    "wof:placetype":"venue"
},
  "geometry": {"coordinates":[8.4308996201,47.1510887146],"type":"Point"}
}