{
  "type": "Feature",
  "properties": {
    "iso:country":"CH",
    "sg:address":"Reussblickstrasse 6",
    "sg:city":"Zufikon",
    "sg:orig_category":"Datenverarbeitungsdienste Softwareentwicklung U beratung",
    "sg:phone":"+41 56 633 83 65",
    "sg:postcode":"5621",
    "sg:province":"Aargau",
    "wof:name":"Kurt Wyss Informatik Gmbh",
    "wof:placetype":"venue"
},
  "geometry": {"coordinates":[8.352668,47.355736],"type":"Point"}
}