{
  "type": "Feature",
  "properties": {
    "iso:country":"CH",
    "sg:address":"Haldenweid 26",
    "sg:city":"Schenkon",
    "sg:orig_category":"Fahrschulen, Flugschulen",
    "sg:phone":"+41 79 300 93 35",
    "sg:postcode":"6214",
    "sg:province":"Luzern",
    "wof:name":"Kurt Brunner Autofahrschule",
    "wof:placetype":"venue"
},
  "geometry": {"coordinates":[8.2834300995,47.347114563],"type":"Point"}
}