{
  "type": "Feature",
  "properties": {
    "iso:country":"CH",
    "sg:address":"Grand-rue 1",
    "sg:city":"St-blaise",
    "sg:orig_category":"Detailhandel mit elektrischen Haushaltsger\u00e4ten Elektroinstallation",
    "sg:postcode":"2072",
    "sg:province":"Neuch\u00e2tel",
    "wof:name":"Ronelli Communication Gmbh Edv Elektro Telefon",
    "wof:placetype":"venue"
},
  "geometry": {"coordinates":[8.2080078125,47.4647674561],"type":"Point"}
}