{
  "type": "Feature",
  "properties": {
    "iso:country":"CH",
    "sg:address":"Spychermattstrasse 18a",
    "sg:city":"Ammannsegg",
    "sg:orig_category":"Grosshandel mit Erzen U Metallen",
    "sg:phone":"+41 32 677 23 24",
    "sg:postcode":"4573",
    "sg:province":"Solothurn",
    "wof:name":"Indumet Sa",
    "wof:placetype":"venue"
},
  "geometry": {"coordinates":[7.5338058472,47.1719093323],"type":"Point"}
}