{
  "type": "Feature",
  "properties": {
    "iso:country":"CH",
    "sg:address":"Wychelstrasse 7 3800 Matten B. Interl. Postfach 517",
    "sg:city":"Interlaken",
    "sg:orig_category":"Landesverteidigung",
    "sg:phone":"+41 33 826 63 11",
    "sg:postcode":"3800",
    "sg:province":"Bern",
    "wof:name":"Eidg. Zeughaus Interlaken",
    "wof:placetype":"venue"
},
  "geometry": {"coordinates":[7.8595619202,46.6813774109],"type":"Point"}
}