{
  "type": "Feature",
  "properties": {
    "iso:country":"CH",
    "sg:address":"Chamerstrasse 115",
    "sg:city":"Zug",
    "sg:orig_category":"Finanzierungsinstitutionen",
    "sg:postcode":"6300",
    "sg:province":"Zug",
    "wof:name":"Rvt Finanz Ag Dienstleistungen Auf Dem Gebiet Der Finanzplanung, Verm\u00f6gensverwaltung Usw.",
    "wof:placetype":"venue"
},
  "geometry": {"coordinates":[9.5621986389,47.3128242493],"type":"Point"}
}