{
  "type": "Feature",
  "properties": {
    "iso:country":"CH",
    "sg:address":"Halles Place Des 13",
    "sg:city":"Neuch\u00e2tel",
    "sg:orig_category":"Herstellung von Konstruktionsteilen, Fertigbauteilen U Ausbauelementen aus Holz",
    "sg:postcode":"2000",
    "sg:province":"Neuch\u00e2tel",
    "wof:name":"Jeanneret Christian",
    "wof:placetype":"venue"
},
  "geometry": {"coordinates":[6.9310851097,46.9903335571],"type":"Point"}
}