{
  "type": "Feature",
  "properties": {
    "iso:country":"CH",
    "sg:address":"6803",
    "sg:city":"Camignolo",
    "sg:orig_category":"Herstellung von Konstruktionsteilen, Fertigbauteilen U Ausbauelementen aus Holz",
    "sg:phone":"+41 91 946 15 03",
    "sg:postcode":"6803",
    "sg:province":"Ticino",
    "wof:name":"Carlo Soldini",
    "wof:placetype":"venue"
},
  "geometry": {"coordinates":[8.9504499435,46.1043701172],"type":"Point"}
}