{
  "type": "Feature",
  "properties": {
    "iso:country":"CH",
    "sg:address":"Lance Avenue Eug\u00e8ne 72 1212 Grand-lancy. Postfach",
    "sg:city":"Arare",
    "sg:orig_category":"Datenverarbeitungsdienste",
    "sg:phone":"+41 22 782 30 31",
    "sg:postcode":"1212",
    "sg:province":"Gen\u00e8ve",
    "wof:name":"Gpi Gestion De Production Par Informatique Sa",
    "wof:placetype":"venue"
},
  "geometry": {"coordinates":[6.066571,46.221989],"type":"Point"}
}