{
  "type": "Feature",
  "properties": {
    "iso:country":"CH",
    "sg:address":"Riedmatt 28a 6303 Zug. Postfach 3229",
    "sg:city":"Zug",
    "sg:orig_category":"Gesundheitswesen",
    "sg:phone":"+41 41 712 23 33",
    "sg:postcode":"6300",
    "sg:province":"Zug",
    "wof:name":"Abc Beratung Ag",
    "wof:placetype":"venue"
},
  "geometry": {"coordinates":[8.491484642,47.1841468811],"type":"Point"}
}