{
  "type": "Feature",
  "properties": {
    "iso:country":"CH",
    "sg:address":"Effingerstrasse 29 3008 Bern. Postfach 6336",
    "sg:city":"Bern",
    "sg:orig_category":"Arbeitnehmerverb\u00e4nde Druck ohne Zeitungsdruck",
    "sg:postcode":"3001",
    "sg:province":"Bern",
    "wof:name":"Comedia",
    "wof:placetype":"venue"
},
  "geometry": {"coordinates":[7.42176,46.944649],"type":"Point"}
}