{
  "type": "Feature",
  "properties": {
    "iso:country":"CH",
    "sg:address":"Rigistrasse 164",
    "sg:city":"Baar",
    "sg:orig_category":"Wirtschaftspr\u00fcfung, Steuerberatung U Treuhand",
    "sg:phone":"+41 41 760 94 64",
    "sg:postcode":"6340",
    "sg:province":"Zug",
    "wof:name":"Wallach Corinne Buchhaltungs-& Treuhandservice",
    "wof:placetype":"venue"
},
  "geometry": {"coordinates":[8.5305099487,47.1919517517],"type":"Point"}
}