{
  "type": "Feature",
  "properties": {
    "iso:country":"CH",
    "sg:address":"Baumackerstrasse 53",
    "sg:city":"Z\u00fcrich",
    "sg:orig_category":"Fotografische Ateliers",
    "sg:phone":"+41 13124851",
    "sg:postcode":"8050",
    "sg:province":"Z\u00fcrich",
    "wof:name":"Arthur Roffler Foto-grafik",
    "wof:placetype":"venue"
},
  "geometry": {"coordinates":[8.5420293808,47.4095153809],"type":"Point"}
}