{
  "type": "Feature",
  "properties": {
    "iso:country":"CH",
    "sg:address":"Hopfern",
    "sg:city":"Heimisbach",
    "sg:orig_category":"Hoch U Tiefbau",
    "sg:phone":"+41 34 431 14 69",
    "sg:postcode":"3453",
    "sg:province":"Bern",
    "wof:name":"Gebr. Frank Ag Baugesch\u00e4ft",
    "wof:placetype":"venue"
},
  "geometry": {"coordinates":[7.7603111267,47.011756897],"type":"Point"}
}