{
  "type": "Feature",
  "properties": {
    "iso:country":"CH",
    "sg:address":"Kaiserstrasse 7a",
    "sg:city":"Rheinfelden",
    "sg:orig_category":"Detailhandel mit Damenbekleidung Herstellung von konfektionierten Textilwaren ohne Bekleidung",
    "sg:phone":"+41 61 833 09 00",
    "sg:postcode":"4310",
    "sg:province":"Aargau",
    "wof:name":"Seduzione, Pl\u00fcer Sandra",
    "wof:placetype":"venue"
},
  "geometry": {"coordinates":[7.7941589355,47.5523300171],"type":"Point"}
}