{
  "type": "Feature",
  "properties": {
    "iso:country":"CH",
    "sg:address":"Grenzweg 1 3097 Liebefeld. Postfach",
    "sg:city":"Liebefeld",
    "sg:orig_category":"Verwaltung von Immobilien",
    "sg:phone":"+41 31 972 21 28",
    "sg:postcode":"3097",
    "sg:province":"Bern",
    "wof:name":"Mgl M\u00f6ssinger Gurtner Liechti Immobilien-verwaltungs Ag",
    "wof:placetype":"venue"
},
  "geometry": {"coordinates":[7.4230108261,46.9339065552],"type":"Point"}
}