{
  "type": "Feature",
  "properties": {
    "iso:country":"CH",
    "sg:address":"Riethofstrasse 1",
    "sg:city":"Hettlingen",
    "sg:classifiers":[
        {
            "category":"Transit Center",
            "subcategory":"Freight",
            "type":"Transportation"
        }
    ],
    "sg:phone":"+41 52 304 10 11",
    "sg:postcode":"8442",
    "sg:province":"Z\u00fcrich",
    "sg:tags":[
        "eye",
        "cosmetic"
    ],
    "wof:name":"Novartis Ophthalmics Ag",
    "wof:placetype":"venue"
},
  "geometry": {"coordinates":[8.692614,47.544647],"type":"Point"}
}