{
  "type": "Feature",
  "properties": {
    "iso:country":"CH",
    "sg:address":"Chasa Du Parc",
    "sg:city":"Scuol",
    "sg:orig_category":"Sonstige Institutionen des Sozialwesens ohne Beherbergung",
    "sg:phone":"+41 81 750 08 40",
    "sg:postcode":"7550",
    "sg:province":"Graubunden",
    "wof:name":"Soziale Dienste Werdenberg",
    "wof:placetype":"venue"
},
  "geometry": {"coordinates":[9.4730548859,47.1687545776],"type":"Point"}
}