{
  "type": "Feature",
  "properties": {
    "iso:country":"CH",
    "sg:address":"Avenue Dapples 54",
    "sg:city":"Lausanne",
    "sg:orig_category":"Grafikateliers, Design",
    "sg:phone":"+41 21 614 60 20",
    "sg:postcode":"1006",
    "sg:province":"Vaud",
    "wof:name":"Olivier Schrago D\u00e9b\u00e8n-blanc",
    "wof:placetype":"venue"
},
  "geometry": {"coordinates":[6.6261591911,46.5150756836],"type":"Point"}
}