{
  "type": "Feature",
  "properties": {
    "iso:country":"CH",
    "sg:address":"Bubentalstrasse 7",
    "sg:city":"Wallisellen",
    "sg:orig_category":"RESTAURANTS: TEA-ROOMS",
    "sg:phone":"+41 18304327",
    "sg:postcode":"8304",
    "sg:province":"Z\u00fcrich",
    "wof:name":"China Restaurant Pak Lok Haus, C. F. Chung",
    "wof:placetype":"venue"
},
  "geometry": {"coordinates":[8.6001377106,47.4140892029],"type":"Point"}
}