{
  "type": "Feature",
  "properties": {
    "iso:country":"CH",
    "sg:address":"Grenzhof",
    "sg:city":"Freienwil",
    "sg:orig_category":"Sonstiger Grosshandel",
    "sg:postcode":"5423",
    "sg:province":"Aargau",
    "wof:name":"K. + S. Burger-koch",
    "wof:placetype":"venue"
},
  "geometry": {"coordinates":[8.3309259415,47.5095252991],"type":"Point"}
}