{
  "type": "Feature",
  "properties": {
    "iso:country":"CH",
    "sg:address":"Br\u00fcggackerstrasse 34",
    "sg:city":"Jegenstorf",
    "sg:orig_category":"Primarschulen",
    "sg:phone":"+41 31 761 24 75",
    "sg:postcode":"3303",
    "sg:province":"Bern",
    "wof:name":"Primarschule Gyrisberg",
    "wof:placetype":"venue"
},
  "geometry": {"coordinates":[7.5128479004,47.0510749817],"type":"Point"}
}