{
  "type": "Feature",
  "properties": {
    "addr:full":"Bollstrasse 1 Fislisbach Aargau 5442",
    "addr:housenumber":"1",
    "addr:postcode":"5442",
    "addr:street":"Bollstrasse",
    "iso:country":"CH",
    "sg:address":"Bollstrasse 1",
    "sg:city":"Fislisbach",
    "sg:orig_category":"Arztpraxen",
    "sg:phone":"+41 55 251 40 20",
    "sg:postcode":"5442",
    "sg:province":"Aargau",
    "wof:name":"Dr.med.christoph Zeller Arzt F.allgemeine Medizin Fmh",
    "wof:placetype":"venue"
},
  "geometry": {"coordinates":[8.84404,47.257511],"type":"Point"}
}