{
  "type": "Feature",
  "properties": {
    "iso:country":"CH",
    "sg:address":"Margarethenstrasse 7a 4450 Sissach. Postfach",
    "sg:city":"Sissach",
    "sg:orig_category":"Grosshandel mit pharmazeutischen Erzeugnissen, medizinischen U orthop\u00e4dischen Artikeln",
    "sg:phone":"+41 79 208 44 08",
    "sg:postcode":"4450",
    "sg:province":"Basel-Landschaft",
    "wof:name":"Wk Praxiseinrichtungen Gmbh",
    "wof:placetype":"venue"
},
  "geometry": {"coordinates":[8.2011947632,47.275062561],"type":"Point"}
}