{
  "type": "Feature",
  "properties": {
    "iso:country":"CH",
    "sg:address":"Allmend 5",
    "sg:city":"Gelterkinden",
    "sg:orig_category":"Arztpraxen",
    "sg:phone":"+41 61 981 14 44",
    "sg:postcode":"4460",
    "sg:province":"Basel-Landschaft",
    "wof:name":"Dr.med.markus Sch\u00f6nenberg Arzt F.allgemeine Medizin Fmh",
    "wof:placetype":"venue"
},
  "geometry": {"coordinates":[7.85144,47.464764],"type":"Point"}
}