{
  "type": "Feature",
  "properties": {
    "iso:country":"CH",
    "sg:address":"R\u00fcttimattstrasse 5 4557 Horriwil. Postfach 15",
    "sg:city":"Horriwil",
    "sg:orig_category":"Bauspenglerei Zimmerei, Dachdeckerei, Bauspenglerei U Abdichtung",
    "sg:phone":"+41 79 209 33 30",
    "sg:postcode":"4557",
    "sg:province":"Solothurn",
    "wof:name":"Schreier A. Ag",
    "wof:placetype":"venue"
},
  "geometry": {"coordinates":[7.624588,47.182281],"type":"Point"}
}