{
  "type": "Feature",
  "properties": {
    "iso:country":"CH",
    "sg:address":"Bahnhofplatz 65",
    "sg:city":"Frauenfeld",
    "sg:orig_category":"Unclassifiable Establishments",
    "sg:phone":"+41 56 631 14 25",
    "sg:postcode":"8500",
    "sg:province":"Thurgau",
    "wof:name":"Bioladen Salvia, Trutmann Carmen Und Kammermann Gisela Biologische Und \u00f6kologische Produkte; Erwerb, Verkauf Und F\u00f6rderung",
    "wof:placetype":"venue"
},
  "geometry": {"coordinates":[8.3433647156,47.3509483337],"type":"Point"}
}