{
  "type": "Feature",
  "properties": {
    "iso:country":"CH",
    "sg:address":"Schweizergasse 43",
    "sg:city":"Basel",
    "sg:orig_category":"Grosshandel mit B\u00fcromaschinen Grosshandel mit sonstigen Halbwaren",
    "sg:phone":"+41 31 311 89 89",
    "sg:postcode":"4000",
    "sg:province":"Basel-Stadt",
    "wof:name":"Jenex Ag",
    "wof:placetype":"venue"
},
  "geometry": {"coordinates":[7.576406002,47.5499153137],"type":"Point"}
}