{
  "type": "Feature",
  "properties": {
    "iso:country":"CH",
    "sg:address":"Hirschenplatz 1",
    "sg:city":"Bischofszell",
    "sg:orig_category":"Detailhandel mit Fleisch U Fleischwaren",
    "sg:phone":"+41 71 422 15 52",
    "sg:postcode":"9220",
    "sg:province":"Thurgau",
    "wof:name":"Metzgermeisterver.bischofszell & Umgebung Herrn Karl Hobi",
    "wof:placetype":"venue"
},
  "geometry": {"coordinates":[9.2390594482,47.4943275452],"type":"Point"}
}