{
  "type": "Feature",
  "properties": {
    "iso:country":"CH",
    "sg:address":"Oberer Saltinadamm 4 Glis 3902 Glis. Postfach",
    "sg:city":"Glis",
    "sg:orig_category":"Sonstiger Grosshandel",
    "sg:postcode":"3902",
    "sg:province":"Valais",
    "wof:name":"Intertradex Ag",
    "wof:placetype":"venue"
},
  "geometry": {"coordinates":[7.9776821136,46.3108596802],"type":"Point"}
}