{
  "type": "Feature",
  "properties": {
    "iso:country":"CH",
    "sg:address":"Piazza Franscini",
    "sg:city":"Faido",
    "sg:orig_category":"Reiseb\u00fcros U Reiseveranstalter",
    "sg:postcode":"6760",
    "sg:province":"Ticino",
    "wof:name":"Benitour Viaggi Sa Succursale Di Faido",
    "wof:placetype":"venue"
},
  "geometry": {"coordinates":[8.8006372452,46.4784355164],"type":"Point"}
}