{
  "type": "Feature",
  "properties": {
    "iso:country":"CH",
    "sg:address":"Gwattstrasse 56",
    "sg:city":"Thun",
    "sg:orig_category":"Autogaragen",
    "sg:phone":"+41 18503345",
    "sg:postcode":"3604",
    "sg:province":"Bern",
    "wof:name":"Otto B\u00fcchi Autoreparaturwekst\u00e4tte",
    "wof:placetype":"venue"
},
  "geometry": {"coordinates":[8.505891,47.474724],"type":"Point"}
}