{
  "type": "Feature",
  "properties": {
    "iso:country":"CH",
    "sg:address":"Avenue Du Casino 45",
    "sg:city":"Montreux",
    "sg:orig_category":"Vermittlung von Immobilien Verwaltung von Immobilien",
    "sg:phone":"+41 21 961 15 15",
    "sg:postcode":"1820",
    "sg:province":"Vaud",
    "wof:name":"Groupe Geco Sa Agence Immobili\u00e8re",
    "wof:placetype":"venue"
},
  "geometry": {"coordinates":[6.9113311768,46.4305458069],"type":"Point"}
}