{
  "type": "Feature",
  "properties": {
    "iso:country":"CH",
    "sg:address":"Rue Des Lilas 5",
    "sg:city":"Gen\u00e8ve",
    "sg:orig_category":"Non-Classified Establishments",
    "sg:postcode":"1202",
    "sg:province":"Gen\u00e8ve",
    "wof:name":"David Cherix October Agence D' Artistes",
    "wof:placetype":"venue"
},
  "geometry": {"coordinates":[6.1308641434,46.2118759155],"type":"Point"}
}