{
  "type": "Feature",
  "properties": {
    "iso:country":"CH",
    "sg:address":"Signy-centre",
    "sg:city":"Grens",
    "sg:orig_category":"Rechtsberatung",
    "sg:phone":"+41 21 621 60 00",
    "sg:postcode":"1274",
    "sg:province":"Vaud",
    "wof:name":"Meridian Management Sa",
    "wof:placetype":"venue"
},
  "geometry": {"coordinates":[6.1920938492,46.3949508667],"type":"Point"}
}