{
  "type": "Feature",
  "properties": {
    "iso:country":"CH",
    "sg:address":"In Der Luberzen 40",
    "sg:city":"Urdorf",
    "sg:orig_category":"Unternehmensberatung",
    "sg:phone":"+41 17152155",
    "sg:postcode":"8902",
    "sg:province":"Z\u00fcrich",
    "wof:name":"Iten & M\u00fcller",
    "wof:placetype":"venue"
},
  "geometry": {"coordinates":[8.5449829102,47.3223114014],"type":"Point"}
}