{
  "type": "Feature",
  "properties": {
    "iso:country":"CH",
    "sg:address":"Avenue Tronchet 34",
    "sg:city":"Th\u00f4nex",
    "sg:orig_category":"Rolladen- and Storenmontage",
    "sg:phone":"+41 55 451 04 40",
    "sg:postcode":"1226",
    "sg:province":"Gen\u00e8ve",
    "wof:name":"Crb Bertulli Gmbh",
    "wof:placetype":"venue"
},
  "geometry": {"coordinates":[8.8549194336,47.1925239563],"type":"Point"}
}