{
  "type": "Feature",
  "properties": {
    "iso:country":"CH",
    "sg:address":"Archivgasse 8",
    "sg:city":"Schwyz",
    "sg:orig_category":"Gesundheitswesen",
    "sg:postcode":"6430",
    "sg:province":"Schwyz",
    "wof:name":"Hendrikx Olivier",
    "wof:placetype":"venue"
},
  "geometry": {"coordinates":[8.6532297134,47.0203552246],"type":"Point"}
}