{
  "type": "Feature",
  "properties": {
    "addr:full":"Freie Strasse 82 Basel Basel-Stadt 4051",
    "addr:housenumber":"82",
    "addr:postcode":"4051",
    "addr:street":"Freie Strasse",
    "iso:country":"CH",
    "sg:address":"Freie Strasse 82",
    "sg:city":"Basel",
    "sg:orig_category":"Detailhandel mit Brot, Back U S\u00fcsswaren Herstellung von Kakao, Schokoladeerzeugnissen U Zuckerwaren",
    "sg:phone":"+41 61 271 12 77",
    "sg:postcode":"4051",
    "sg:province":"Basel-Stadt",
    "wof:name":"T. Pellmont, Inhaberin Simone Frey-pellmont",
    "wof:placetype":"venue"
},
  "geometry": {"coordinates":[7.591325,47.554413],"type":"Point"}
}