{
  "type": "Feature",
  "properties": {
    "iso:country":"CH",
    "sg:address":"Klarastrasse 8",
    "sg:city":"Arbon",
    "sg:orig_category":"Erbringung von Dienstleistungen f\u00fcr Unternehmen",
    "sg:phone":"+41 71 446 77 84",
    "sg:postcode":"9320",
    "sg:province":"Thurgau",
    "wof:name":"Erich Kast Transliftmulden-service",
    "wof:placetype":"venue"
},
  "geometry": {"coordinates":[9.4303312302,47.5104484558],"type":"Point"}
}