{
  "type": "Feature",
  "properties": {
    "iso:country":"CH",
    "sg:address":"Maiholzstrasse 55",
    "sg:city":"Frauenfeld",
    "sg:orig_category":"Druck ohne Zeitungsdruck Offsetdruck",
    "sg:phone":"+41 52 720 79 62",
    "sg:postcode":"8500",
    "sg:province":"Thurgau",
    "wof:name":"Enzler-druck",
    "wof:placetype":"venue"
},
  "geometry": {"coordinates":[8.8823747635,47.5617294312],"type":"Point"}
}