{
  "type": "Feature",
  "properties": {
    "iso:country":"CH",
    "sg:address":"Ohne Dom.",
    "sg:city":"Glarus",
    "sg:orig_category":"Non-Classified Establishments",
    "sg:phone":"+41 61 713 26 66",
    "sg:postcode":"8750",
    "sg:province":"Glarus",
    "wof:name":"Aaa Services P. Aebi",
    "wof:placetype":"venue"
},
  "geometry": {"coordinates":[7.5501050949,47.5111999512],"type":"Point"}
}