{
  "type": "Feature",
  "properties": {
    "iso:country":"CH",
    "sg:address":"1976",
    "sg:city":"Aven",
    "sg:orig_category":"Innendekorationsateliers",
    "sg:phone":"+41 79 445 09 55",
    "sg:postcode":"1976",
    "sg:province":"Valais",
    "wof:name":"Gerhard & Jeanette Gerber Polster Atelier",
    "wof:placetype":"venue"
},
  "geometry": {"coordinates":[7.8196492195,47.2426223755],"type":"Point"}
}