{
  "type": "Feature",
  "properties": {
    "iso:country":"CH",
    "sg:address":"Schulweg 7 3700 Spiez. Postfach",
    "sg:city":"Spiez",
    "sg:orig_category":"Reinigungsgewerbe",
    "sg:phone":"+41 33 654 65 87",
    "sg:postcode":"3700",
    "sg:province":"Bern",
    "wof:name":"Maurer-faust Paul Kaminfegergesch\u00e4ft. Feuerungskontrollen Usw",
    "wof:placetype":"venue"
},
  "geometry": {"coordinates":[7.6694121361,46.6914558411],"type":"Point"}
}