{
  "type": "Feature",
  "properties": {
    "iso:country":"CH",
    "sg:address":"Alte M\u00fchlackerstrasse 25",
    "sg:city":"Z\u00fcrich",
    "sg:orig_category":"Gartenbau",
    "sg:phone":"+41 13717766",
    "sg:postcode":"8046",
    "sg:province":"Z\u00fcrich",
    "wof:name":"Reiss & Reber Garten Und Landschaftsbau Ag",
    "wof:placetype":"venue"
},
  "geometry": {"coordinates":[8.5060949326,47.4240722656],"type":"Point"}
}