{
  "type": "Feature",
  "properties": {
    "iso:country":"CH",
    "sg:address":"Brunnackerstrasse 3",
    "sg:city":"Uster",
    "sg:orig_category":"Unternehmensberatung",
    "sg:postcode":"8610",
    "sg:province":"Z\u00fcrich",
    "wof:name":"E-simul Sa",
    "wof:placetype":"venue"
},
  "geometry": {"coordinates":[6.5614647865,46.5183067322],"type":"Point"}
}