{
  "type": "Feature",
  "properties": {
    "iso:country":"CH",
    "sg:address":"Pfosigart 17",
    "sg:city":"Besenb\u00fcren",
    "sg:orig_category":"Vereine Diverse",
    "sg:phone":"+41 56 666 36 80",
    "sg:postcode":"5627",
    "sg:province":"Aargau",
    "wof:name":"Schweiz.marketing Club",
    "wof:placetype":"venue"
},
  "geometry": {"coordinates":[8.3477687836,47.3115005493],"type":"Point"}
}