{
  "type": "Feature",
  "properties": {
    "iso:country":"CH",
    "sg:address":"Renggerstrasse 3",
    "sg:city":"Z\u00fcrich",
    "sg:orig_category":"Unternehmensberatung",
    "sg:phone":"+41 41 729 52 20",
    "sg:postcode":"8038",
    "sg:province":"Z\u00fcrich",
    "wof:name":"A.t.kearney (international) Ag Unternehmensberatung",
    "wof:placetype":"venue"
},
  "geometry": {"coordinates":[8.5320692062,47.3470497131],"type":"Point"}
}