{
  "type": "Feature",
  "properties": {
    "addr:full":"Oberfeldstrasse 19 Root Luzern 6037",
    "addr:housenumber":"19",
    "addr:postcode":"6037",
    "addr:street":"Oberfeldstrasse",
    "iso:country":"CH",
    "sg:address":"Oberfeldstrasse 19",
    "sg:city":"Root",
    "sg:classifiers":[
        {
            "category":"Utilities",
            "subcategory":"Cable",
            "type":"Services"
        }
    ],
    "sg:phone":"+41 41 455 50 70",
    "sg:postcode":"6037",
    "sg:province":"Luzern",
    "sg:tags":[
        "ready",
        "use",
        "cables",
        "finished"
    ],
    "wof:name":"El Kabel Ag",
    "wof:placetype":"venue"
},
  "geometry": {"coordinates":[8.38592,47.109619],"type":"Point"}
}