{
  "type": "Feature",
  "properties": {
    "iso:country":"CH",
    "sg:address":"Herrengasse 15",
    "sg:city":"Schwyz",
    "sg:orig_category":"Bijouterien Gold- and Silberschmuck Detailhandel",
    "sg:phone":"+41 32 913 41 42",
    "sg:postcode":"6430",
    "sg:province":"Schwyz",
    "wof:name":"Mayer-stehlin Sa Bijouterie",
    "wof:placetype":"venue"
},
  "geometry": {"coordinates":[6.8259,47.100143],"type":"Point"}
}