{
  "type": "Feature",
  "properties": {
    "iso:country":"CH",
    "sg:address":"Seestrasse 202 8810 Horgen. Postfach 124",
    "sg:city":"Horgen",
    "sg:orig_category":"Grosshandel mit elektrischen Haushaltsger\u00e4ten, Radio U Fernsehger\u00e4ten",
    "sg:phone":"+41 17253710",
    "sg:postcode":"8810",
    "sg:province":"Z\u00fcrich",
    "wof:name":"Sciamanna N. Ag Industrie-vertretungen",
    "wof:placetype":"venue"
},
  "geometry": {"coordinates":[8.6024541855,47.2590866089],"type":"Point"}
}