{
  "type": "Feature",
  "properties": {
    "iso:country":"CH",
    "sg:address":"Baarerstrasse 98",
    "sg:city":"Zug",
    "sg:orig_category":"Unclassifiable Establishments",
    "sg:phone":"+41 22 369 90 30",
    "sg:postcode":"6300",
    "sg:province":"Zug",
    "wof:name":"Tks - Teknosoft S.a.",
    "wof:placetype":"venue"
},
  "geometry": {"coordinates":[6.2428998947,46.4983406067],"type":"Point"}
}