{
  "type": "Feature",
  "properties": {
    "iso:country":"CH",
    "sg:address":"H\u00f6henweg 301",
    "sg:city":"Berikon",
    "sg:orig_category":"Sonstiger Grosshandel",
    "sg:phone":"+41 56 631 28 31",
    "sg:postcode":"8965",
    "sg:province":"Aargau",
    "wof:name":"Promos Handel Und Dienstleistungen Lazarevic Milica",
    "wof:placetype":"venue"
},
  "geometry": {"coordinates":[8.3605098724,47.3597297668],"type":"Point"}
}