{
  "type": "Feature",
  "properties": {
    "iso:country":"CH",
    "sg:address":"L\u00e4ndliweg 9a",
    "sg:city":"Baden",
    "sg:orig_category":"Unternehmensberatung",
    "sg:phone":"+41 56 221 83 33",
    "sg:postcode":"5400",
    "sg:province":"Aargau",
    "wof:name":"Pozzi + Partner Ag",
    "wof:placetype":"venue"
},
  "geometry": {"coordinates":[8.3076324463,47.4693260193],"type":"Point"}
}