{
  "type": "Feature",
  "properties": {
    "iso:country":"CH",
    "sg:address":"Gellertstrasse 144 4000 Basel. Postfach",
    "sg:city":"Basel",
    "sg:orig_category":"Wohnheime",
    "sg:phone":"+41 61 315 21 21",
    "sg:postcode":"4052",
    "sg:province":"Basel-Stadt",
    "wof:name":"Diakonat Bethesda",
    "wof:placetype":"venue"
},
  "geometry": {"coordinates":[7.6171131134,47.548210144],"type":"Point"}
}