{
  "type": "Feature",
  "properties": {
    "iso:country":"CH",
    "sg:address":"Pf\u00e4ffikerstrasse 119",
    "sg:city":"Gutenswil",
    "sg:orig_category":"Instandhaltung U Reparatur von Automobilen",
    "sg:postcode":"8605",
    "sg:province":"Z\u00fcrich",
    "wof:name":"Keller, Alfred, Autogarage.",
    "wof:placetype":"venue"
},
  "geometry": {"coordinates":[8.7180452347,47.3853263855],"type":"Point"}
}