{
  "type": "Feature",
  "properties": {
    "addr:full":"Sch\u00fctzenhausweg 3a Breitenbach Solothurn 4226",
    "addr:housenumber":"3a",
    "addr:postcode":"4226",
    "addr:street":"Schuetzenhausweg",
    "iso:country":"CH",
    "sg:address":"Sch\u00fctzenhausweg 3a",
    "sg:city":"Breitenbach",
    "sg:orig_category":"Advokaturb\u00fcros Notariate",
    "sg:phone":"+41 61 206 45 45",
    "sg:postcode":"4226",
    "sg:province":"Solothurn",
    "wof:name":"Bernhard Simonetti Advokatur-& Notariatsb\u00fcro",
    "wof:placetype":"venue"
},
  "geometry": {"coordinates":[7.552687,47.408379],"type":"Point"}
}