{
  "type": "Feature",
  "properties": {
    "iso:country":"CH",
    "sg:address":"R\u00f6merstrasse 77",
    "sg:city":"Winterthur",
    "sg:orig_category":"Detailhandel mit Antiquit\u00e4ten",
    "sg:phone":"+41 52 242 67 49",
    "sg:postcode":"8404",
    "sg:province":"Z\u00fcrich",
    "wof:name":"Giuseppe Bruni Antiquit\u00e4tenh\u00e4ndler",
    "wof:placetype":"venue"
},
  "geometry": {"coordinates":[8.746991,47.501514],"type":"Point"}
}