{
  "type": "Feature",
  "properties": {
    "iso:country":"CH",
    "sg:address":"Unterm\u00fchlestrasse 26",
    "sg:city":"Cham",
    "sg:orig_category":"Grosshandel mit sonstigen Maschinen U Ausr\u00fcstungen f\u00fcr Industrie, Handel U Schiffahrt Herstellung vo",
    "sg:phone":"+41 55 451 75 75",
    "sg:postcode":"6330",
    "sg:province":"Zug",
    "wof:name":"Ensigma Gmbh",
    "wof:placetype":"venue"
},
  "geometry": {"coordinates":[8.8595733643,47.1925392151],"type":"Point"}
}