{
  "type": "Feature",
  "properties": {
    "iso:country":"CH",
    "sg:address":"Int I Boll",
    "sg:city":"Claro",
    "sg:orig_category":"Zimmerei, Dachdeckerei, Bauspenglerei U Abdichtung",
    "sg:phone":"+41 91 858 20 19",
    "sg:postcode":"6702",
    "sg:province":"Ticino",
    "wof:name":"Korell Sa",
    "wof:placetype":"venue"
},
  "geometry": {"coordinates":[9.0303602219,46.2479667664],"type":"Point"}
}