{
  "type": "Feature",
  "properties": {
    "iso:country":"CH",
    "sg:address":"Via Alla Chiesa 5",
    "sg:city":"Viganello",
    "sg:orig_category":"Vereine Musik/Blasmusik",
    "sg:phone":"+41 91 971 60 76",
    "sg:postcode":"6962",
    "sg:province":"Ticino",
    "wof:name":"Corale Santa Teresa",
    "wof:placetype":"venue"
},
  "geometry": {"coordinates":[8.9665880203,46.0110168457],"type":"Point"}
}