{
  "type": "Feature",
  "properties": {
    "iso:country":"CH",
    "sg:address":"Lochgasse 13a 5722 Gr\u00e4nichen. Postfach",
    "sg:city":"Gr\u00e4nichen",
    "sg:orig_category":"Unternehmensberatung",
    "sg:phone":"+41 62 842 90 60",
    "sg:postcode":"5722",
    "sg:province":"Aargau",
    "wof:name":"Propart Unternehmensberatung Heiner Utz",
    "wof:placetype":"venue"
},
  "geometry": {"coordinates":[8.0978441238,47.3579940796],"type":"Point"}
}