{
  "type": "Feature",
  "properties": {
    "iso:country":"CH",
    "sg:address":"Hardturmstrasse 3 8005 Z\u00fcrich. Postfach 756",
    "sg:city":"Z\u00fcrich",
    "sg:orig_category":"Sonstige mit der Informatik verbundene T\u00e4tigkeiten",
    "sg:postcode":"8037",
    "sg:province":"Z\u00fcrich",
    "wof:name":"Bluewin Ag",
    "wof:placetype":"venue"
},
  "geometry": {"coordinates":[8.5206851959,47.3909873962],"type":"Point"}
}