{
  "type": "Feature",
  "properties": {
    "iso:country":"CH",
    "sg:address":"Avenue G\u00e9n\u00e9ral-guisan 39",
    "sg:city":"Pully",
    "sg:orig_category":"Reiseb\u00fcros U Reiseveranstalter",
    "sg:postcode":"1009",
    "sg:province":"Vaud",
    "wof:name":"Gts Reisen Weixler & Weixler",
    "wof:placetype":"venue"
},
  "geometry": {"coordinates":[9.8754692078,46.882598877],"type":"Point"}
}