{
  "type": "Feature",
  "properties": {
    "iso:country":"CH",
    "sg:address":"Segantinistrasse 11 7000 Chur. Postfach 322",
    "sg:city":"Chur",
    "sg:orig_category":"Grosshandel mit Wein U Spirituosen",
    "sg:phone":"+41 81 250 37 77",
    "sg:postcode":"7001",
    "sg:province":"Graubunden",
    "wof:name":"Troxler Weine Ag",
    "wof:placetype":"venue"
},
  "geometry": {"coordinates":[9.5219135284,46.8529663086],"type":"Point"}
}