{
  "type": "Feature",
  "properties": {
    "iso:country":"CH",
    "sg:address":"Hauptstrasse 7",
    "sg:city":"Unterkulm",
    "sg:orig_category":"Bauschreinerei Herstellung von Konstruktionsteilen, Fertigbauteilen U Ausbauelementen aus Holz",
    "sg:phone":"+41 62 776 11 29",
    "sg:postcode":"5726",
    "sg:province":"Aargau",
    "wof:name":"W. W\u00e4lti Ag",
    "wof:placetype":"venue"
},
  "geometry": {"coordinates":[8.115839,47.308498],"type":"Point"}
}