{
  "type": "Feature",
  "properties": {
    "iso:country":"CH",
    "sg:address":"Schaffhauserstrasse 479",
    "sg:city":"Z\u00fcrich",
    "sg:orig_category":"Zahnarztpraxen",
    "sg:phone":"+41 13025035",
    "sg:postcode":"8052",
    "sg:province":"Z\u00fcrich",
    "wof:name":"Dr. Med. Dent. Zsolt Magyar Zahnarzt",
    "wof:placetype":"venue"
},
  "geometry": {"coordinates":[8.5487823486,47.4205322266],"type":"Point"}
}