{
  "type": "Feature",
  "properties": {
    "iso:country":"CH",
    "sg:address":"Florastrasse 10",
    "sg:city":"Adliswil",
    "sg:orig_category":"RESTAURANTS: TEA-ROOMS",
    "sg:phone":"+41 17103000",
    "sg:postcode":"8134",
    "sg:province":"Z\u00fcrich",
    "wof:name":"Vait Gmbh",
    "wof:placetype":"venue"
},
  "geometry": {"coordinates":[8.524271965,47.3120079041],"type":"Point"}
}