{
  "type": "Feature",
  "properties": {
    "iso:country":"CH",
    "sg:address":"Neum\u00fchlequai 12 8001 Z\u00fcrich. Postfach",
    "sg:city":"Z\u00fcrich",
    "sg:orig_category":"Interessenvertretungen",
    "sg:postcode":"8001",
    "sg:province":"Z\u00fcrich",
    "wof:name":"Vereinigung Exportierender Elektrizit\u00e4ts-unternehmen Wahrung Der Interessen Der Vereinsmitglieder Usw.",
    "wof:placetype":"venue"
},
  "geometry": {"coordinates":[8.5427017212,47.3786239624],"type":"Point"}
}