{
  "type": "Feature",
  "properties": {
    "iso:country":"CH",
    "sg:address":"Grand-places 1 1700 Fribourg. Postfach",
    "sg:city":"Fribourg",
    "sg:orig_category":"Wirtschaftspr\u00fcfung, Steuerberatung U Treuhand",
    "sg:phone":"+41 26 322 17 29",
    "sg:postcode":"1701",
    "sg:province":"Fribourg",
    "wof:name":"Comptabilit\u00e9 Et Gestion Sa Fribourg",
    "wof:placetype":"venue"
},
  "geometry": {"coordinates":[7.1545848846,46.8032188416],"type":"Point"}
}