{
  "type": "Feature",
  "properties": {
    "iso:country":"CH",
    "sg:address":"Mahrenstrasse 121",
    "sg:city":"Lostorf",
    "sg:classifiers":[
        {
            "category":"Insurance",
            "subcategory":"Insurance Agent",
            "type":"Services"
        }
    ],
    "sg:phone":"+41 62 298 04 51",
    "sg:postcode":"4654",
    "sg:province":"Solothurn",
    "sg:tags":[
        "versicherungsagenturen",
        "-broker"
    ],
    "wof:name":"Philipp Graber Helvetia-patria Versicherung",
    "wof:placetype":"venue"
},
  "geometry": {"coordinates":[7.9219179153,47.3813667297],"type":"Point"}
}