{
  "type": "Feature",
  "properties": {
    "iso:country":"CH",
    "sg:address":"Rue De La Mairie 6",
    "sg:city":"Gen\u00e8ve",
    "sg:orig_category":"Detailhandel mit Antiquit\u00e4ten Detailhandel mit M\u00f6beln",
    "sg:phone":"+41 81 302 38 30",
    "sg:postcode":"1207",
    "sg:province":"Gen\u00e8ve",
    "wof:name":"Walter Balsiger Antiquit\u00e4ten & Stilm\u00f6bel",
    "wof:placetype":"venue"
},
  "geometry": {"coordinates":[9.502579,47.005249],"type":"Point"}
}