{
  "type": "Feature",
  "properties": {
    "iso:country":"CH",
    "sg:address":"Engehaldenstrasse 131",
    "sg:city":"Bern",
    "sg:orig_category":"Non-Classified Establishments",
    "sg:postcode":"3012",
    "sg:province":"Bern",
    "wof:name":"Neueret Weggenossenschaft",
    "wof:placetype":"venue"
},
  "geometry": {"coordinates":[7.2839550972,46.4762382507],"type":"Point"}
}