{
  "type": "Feature",
  "properties": {
    "iso:country":"CH",
    "sg:address":"Welbrigstrasse 4 A",
    "sg:city":"Geroldswil",
    "sg:orig_category":"Erbringung von Dienstleistungen f\u00fcr Unternehmen",
    "sg:phone":"+41 17484630",
    "sg:postcode":"8954",
    "sg:province":"Z\u00fcrich",
    "wof:name":"Dtp Computer-grafik Margrit Leuenberger",
    "wof:placetype":"venue"
},
  "geometry": {"coordinates":[8.4187297821,47.4190368652],"type":"Point"}
}