{
  "type": "Feature",
  "properties": {
    "iso:country":"CH",
    "sg:address":"Thalstrasse 12",
    "sg:city":"Heiden",
    "sg:orig_category":"Herstellung von sonstigen elektrischen Ausr\u00fcstungen",
    "sg:phone":"+41 71 891 63 26",
    "sg:postcode":"9410",
    "sg:province":"Appenzell Ausserrhoden",
    "wof:name":"Univex Michael Schulz",
    "wof:placetype":"venue"
},
  "geometry": {"coordinates":[9.5365858078,47.4499664307],"type":"Point"}
}