{
  "type": "Feature",
  "properties": {
    "iso:country":"CH",
    "sg:address":"Ruelle Proz-des-mayes",
    "sg:city":"Ardon",
    "sg:orig_category":"Maurerarbeiten Sonstiger spezialisierter Hoch U Tiefbau",
    "sg:phone":"+41 27 306 15 27",
    "sg:postcode":"1957",
    "sg:province":"Valais",
    "wof:name":"B\u00e9rard Dominique",
    "wof:placetype":"venue"
},
  "geometry": {"coordinates":[7.2545452118,46.2093849182],"type":"Point"}
}