{
  "type": "Feature",
  "properties": {
    "iso:country":"CH",
    "sg:address":"Z\u00fcrichbergstrasse 38",
    "sg:city":"Z\u00fcrich",
    "sg:orig_category":"Interessenvertretungen",
    "sg:postcode":"8044",
    "sg:province":"Z\u00fcrich",
    "wof:name":"Georg Fient, 1845 - 1915, Alt Kanzleidirektor Des Standes Graub\u00fcnden",
    "wof:placetype":"venue"
},
  "geometry": {"coordinates":[9.8291378021,46.9735374451],"type":"Point"}
}