{
  "type": "Feature",
  "properties": {
    "iso:country":"CH",
    "sg:address":"Industriestrasse 19",
    "sg:city":"Gr\u00e4nichen",
    "sg:orig_category":"Zimmerei, Dachdeckerei, Bauspenglerei U Abdichtung",
    "sg:phone":"+41 62 842 63 58",
    "sg:postcode":"5722",
    "sg:province":"Aargau",
    "wof:name":"Brechb\u00fchl Holzbau Gmbh",
    "wof:placetype":"venue"
},
  "geometry": {"coordinates":[8.1072750092,47.3508415222],"type":"Point"}
}