{
  "type": "Feature",
  "properties": {
    "iso:country":"CH",
    "sg:address":"S. Clau Sura Via 20",
    "sg:city":"Ilanz",
    "sg:orig_category":"Pensionskassen",
    "sg:phone":"+41 81 925 25 16",
    "sg:postcode":"7130",
    "sg:province":"Graubunden",
    "wof:name":"Personalf\u00fcrsorgestiftung Der Firma Collenberg Ilanz Ag",
    "wof:placetype":"venue"
},
  "geometry": {"coordinates":[9.2032766342,46.7760925293],"type":"Point"}
}