{
  "type": "Feature",
  "properties": {
    "iso:country":"CH",
    "sg:address":"Herrengasse",
    "sg:city":"Steinen",
    "sg:orig_category":"Kalb U Schweine-M\u00e4sterei U Zucht",
    "sg:phone":"+41 41 832 17 87",
    "sg:postcode":"6422",
    "sg:province":"Schwyz",
    "wof:name":"Annen-fuchs Franz",
    "wof:placetype":"venue"
},
  "geometry": {"coordinates":[8.6117172241,47.049369812],"type":"Point"}
}