{
  "type": "Feature",
  "properties": {
    "addr:full":"Aquasanastrasse 8 7000 Chur. Postfach Chur Graubunden 7002",
    "addr:housenumber":"8",
    "addr:postcode":"7000;postfach;7002",
    "addr:street":"Aquasanastrasse",
    "iso:country":"CH",
    "sg:address":"Aquasanastrasse 8 7000 Chur. Postfach",
    "sg:city":"Chur",
    "sg:orig_category":"Advokaturb\u00fcros Notariate",
    "sg:phone":"+41 81 911 31 49",
    "sg:postcode":"7002",
    "sg:province":"Graubunden",
    "wof:name":"Pajarola Sch\u00e4fer & R\u00e4ber Advokatur- & Notariatsb\u00fcro",
    "wof:placetype":"venue"
},
  "geometry": {"coordinates":[9.285231,46.836693],"type":"Point"}
}