{
  "type": "Feature",
  "properties": {
    "iso:country":"CH",
    "sg:address":"Egerta 37 9496 Balzers. Postfach 29",
    "sg:city":"Balzers",
    "sg:orig_category":"Allgemeiner Hochbau Strassenbau",
    "sg:phone":"+423 384 12 20",
    "sg:postcode":"9496",
    "wof:name":"Edy Brunhart Hoch-& Tiefbau",
    "wof:placetype":"venue"
},
  "geometry": {"coordinates":[9.508059,47.071507],"type":"Point"}
}