{
  "type": "Feature",
  "properties": {
    "iso:country":"CH",
    "sg:address":"Conf\u00e9d\u00e9ration Rue De La 3 1204 Gen\u00e8ve. Postfach",
    "sg:city":"Gen\u00e8ve",
    "sg:orig_category":"Interessenvertretungen",
    "sg:postcode":"1204",
    "sg:province":"Gen\u00e8ve",
    "wof:name":"Soci\u00e9t\u00e9 De Temp\u00e9rance, La Croix-bleue, De La Chaux-de-fonds",
    "wof:placetype":"venue"
},
  "geometry": {"coordinates":[6.8299341202,47.1097831726],"type":"Point"}
}