{
  "type": "Feature",
  "properties": {
    "addr:full":"Bernstrasse 61 Rothrist Aargau 4852",
    "addr:housenumber":"61",
    "addr:postcode":"4852",
    "addr:street":"Bernstrasse",
    "iso:country":"CH",
    "sg:address":"Bernstrasse 61",
    "sg:city":"Rothrist",
    "sg:orig_category":"Detailhandel mit Brot, Back U S\u00fcsswaren",
    "sg:phone":"+41 62 794 10 39",
    "sg:postcode":"4852",
    "sg:province":"Aargau",
    "wof:name":"Ren\u00e9 W\u00e4lchli B\u00e4ckerei-konditorei",
    "wof:placetype":"venue"
},
  "geometry": {"coordinates":[7.898364,47.305023],"type":"Point"}
}