{
  "type": "Feature",
  "properties": {
    "iso:country":"CH",
    "sg:address":"Zentrumplatz 1",
    "sg:city":"Unterkulm",
    "sg:orig_category":"Polizei",
    "sg:phone":"+41 62 873 12 10",
    "sg:postcode":"5726",
    "sg:province":"Aargau",
    "wof:name":"Kantonspolizei",
    "wof:placetype":"venue"
},
  "geometry": {"coordinates":[7.9476408958,47.5428848267],"type":"Point"}
}