{
  "type": "Feature",
  "properties": {
    "iso:country":"CH",
    "sg:address":"Menznauerstrasse 7",
    "sg:city":"Willisau",
    "sg:classifiers":[
        {
            "category":"Restaurant",
            "type":"Food & Drink"
        }
    ],
    "sg:phone":"+41 41 970 27 70",
    "sg:postcode":"6130",
    "sg:province":"Luzern",
    "wof:name":"Restaurant Eines\u00e4chzg 30",
    "wof:placetype":"venue"
},
  "geometry": {"coordinates":[7.9981608391,47.1201095581],"type":"Point"}
}