{
  "type": "Feature",
  "properties": {
    "iso:country":"CH",
    "sg:address":"Feldegg 3",
    "sg:city":"Lyss",
    "sg:orig_category":"Herstellung von Werkzeugmaschinen",
    "sg:postcode":"3250",
    "sg:province":"Bern",
    "wof:name":"Groove Engineering, U. Gisiger",
    "wof:placetype":"venue"
},
  "geometry": {"coordinates":[7.3001799583,47.0692481995],"type":"Point"}
}