{
  "type": "Feature",
  "properties": {
    "iso:country":"CH",
    "sg:address":"Riedbrugg 6218 Ettiswil. Postfach",
    "sg:city":"Ettiswil",
    "sg:orig_category":"Herstellung von Landwirtschaftstraktoren Herstellung von sonstigen landwirtschaftlichen Maschinen",
    "sg:phone":"+41 41 980 30 66",
    "sg:postcode":"6218",
    "sg:province":"Luzern",
    "wof:name":"Walter Meyer Traktoren & Landmaschinen",
    "wof:placetype":"venue"
},
  "geometry": {"coordinates":[8.0240745544,47.1499443054],"type":"Point"}
}