{
  "type": "Feature",
  "properties": {
    "addr:full":"Majorie Rue De La 8 Sion Valais 1950",
    "addr:housenumber":"8",
    "addr:postcode":"1950",
    "addr:street":"Rue De La",
    "iso:country":"CH",
    "sg:address":"Majorie Rue De La 8",
    "sg:city":"Sion",
    "sg:orig_category":"Architektur U Ingenieurb\u00fcros",
    "sg:phone":"+41 27 322 60 11",
    "sg:postcode":"1950",
    "sg:province":"Valais",
    "wof:name":"Gestion De L'environnement, Mooser M.",
    "wof:placetype":"venue"
},
  "geometry": {"coordinates":[7.358857,46.228092],"type":"Point"}
}