{
  "type": "Feature",
  "properties": {
    "iso:country":"CH",
    "sg:address":"Mattenweg 30",
    "sg:city":"Flawil",
    "sg:orig_category":"Landwirtschaftliche Schulen",
    "sg:phone":"+41 71 393 51 31",
    "sg:postcode":"9230",
    "sg:province":"St. Gallen",
    "wof:name":"Landwirtschaftliche Schule",
    "wof:placetype":"venue"
},
  "geometry": {"coordinates":[9.1905317307,47.4185409546],"type":"Point"}
}