{
  "type": "Feature",
  "properties": {
    "iso:country":"CH",
    "sg:address":"Rue De La Gruy\u00e9re 70",
    "sg:city":"Riaz",
    "sg:classifiers":[
        {
            "category":"Travel",
            "subcategory":"Hotels & Motels",
            "type":"Entertainment"
        }
    ],
    "sg:phone":"+41 26 912 72 97",
    "sg:postcode":"1632",
    "sg:province":"Fribourg",
    "sg:tags":[
        "hotels",
        "mit",
        "restaurant"
    ],
    "wof:name":"H\u00f4tel De La Croix-blanche",
    "wof:placetype":"venue"
},
  "geometry": {"coordinates":[7.0633068085,46.6424217224],"type":"Point"}
}