{
  "type": "Feature",
  "properties": {
    "iso:country":"CH",
    "sg:address":"R\u00fctistrasse 9",
    "sg:city":"Euthal",
    "sg:orig_category":"Abwasserreinigung",
    "sg:phone":"+41 55 412 53 66",
    "sg:postcode":"8844",
    "sg:province":"Schwyz",
    "wof:name":"Abwasserverband Oberes Sihltal",
    "wof:placetype":"venue"
},
  "geometry": {"coordinates":[8.813115,47.097206],"type":"Point"}
}