{
  "type": "Feature",
  "properties": {
    "iso:country":"CH",
    "sg:address":"Aarestrasse 28 3600 Thun. Postfach 1393",
    "sg:city":"Thun",
    "sg:orig_category":"Notariate",
    "sg:phone":"+41 33 222 91 33",
    "sg:postcode":"3601",
    "sg:province":"Bern",
    "wof:name":"Beat Steiner Notariatsb\u00fcro",
    "wof:placetype":"venue"
},
  "geometry": {"coordinates":[7.6269102097,46.7575302124],"type":"Point"}
}