{
  "type": "Feature",
  "properties": {
    "addr:full":"Adelbodenstrasse 21 Frutigen Bern 3714",
    "addr:housenumber":"21",
    "addr:postcode":"3714",
    "addr:street":"Adelbodenstrasse",
    "iso:country":"CH",
    "sg:address":"Adelbodenstrasse 21",
    "sg:city":"Frutigen",
    "sg:orig_category":"Arztpraxen",
    "sg:phone":"+41 33 671 28 28",
    "sg:postcode":"3714",
    "sg:province":"Bern",
    "wof:name":"Dr.med.hermann Christen Arzt F.allgemeine Medizin Fmh",
    "wof:placetype":"venue"
},
  "geometry": {"coordinates":[7.641602,46.584785],"type":"Point"}
}