{
  "type": "Feature",
  "properties": {
    "iso:country":"CH",
    "sg:address":"Bogenstrasse 1",
    "sg:city":"Berneck",
    "sg:orig_category":"Kauf U Verkauf von Immobilien auf eigene Rechnung",
    "sg:postcode":"9442",
    "sg:province":"St. Gallen",
    "wof:name":"Berimca Ag",
    "wof:placetype":"venue"
},
  "geometry": {"coordinates":[8.7890787125,47.2009925842],"type":"Point"}
}