{
  "type": "Feature",
  "properties": {
    "iso:country":"CH",
    "sg:address":"Oberer Aareweg 4",
    "sg:city":"Lyss",
    "sg:orig_category":"Electroforming",
    "sg:phone":"+41 32 753 13 53",
    "sg:postcode":"3250",
    "sg:province":"Bern",
    "wof:name":"Novasort S.a.",
    "wof:placetype":"venue"
},
  "geometry": {"coordinates":[6.8103709221,47.0867652893],"type":"Point"}
}