{
  "type": "Feature",
  "properties": {
    "iso:country":"CH",
    "sg:address":"Rue Des Voisins 23",
    "sg:city":"Gen\u00e8ve",
    "sg:orig_category":"Vereine Gesang",
    "sg:phone":"+41 22 781 23 88",
    "sg:postcode":"1205",
    "sg:province":"Gen\u00e8ve",
    "wof:name":"Chorale Catholique St-fran\u00e7ois",
    "wof:placetype":"venue"
},
  "geometry": {"coordinates":[6.1448068619,46.1945152283],"type":"Point"}
}