{
  "type": "Feature",
  "properties": {
    "iso:country":"CH",
    "sg:address":"Grindelstrasse 5",
    "sg:city":"Wallisellen",
    "sg:orig_category":"Unternehmensberatung Wirtschaftspr\u00fcfung, Steuerberatung U Treuhand",
    "sg:phone":"+41 19722505",
    "sg:postcode":"8304",
    "sg:province":"Z\u00fcrich",
    "wof:name":"Wpb Beratungen, P\u00f6tschacher Wolfgang",
    "wof:placetype":"venue"
},
  "geometry": {"coordinates":[8.7870121002,47.3085975647],"type":"Point"}
}