{
  "type": "Feature",
  "properties": {
    "iso:country":"CH",
    "sg:address":"Champs Du Pont",
    "sg:city":"Mathod",
    "sg:orig_category":"Allgemeiner Hoch U Tiefbau",
    "sg:postcode":"1438",
    "sg:province":"Vaud",
    "wof:name":"Massonnet Et Naguel Massona",
    "wof:placetype":"venue"
},
  "geometry": {"coordinates":[6.56249,46.764568],"type":"Point"}
}