{
  "type": "Feature",
  "properties": {
    "iso:country":"CH",
    "sg:address":"Krebsenbachweg 1",
    "sg:city":"Pfeffingen",
    "sg:orig_category":"Softwareentwicklung U beratung",
    "sg:phone":"+41 61 756 96 05",
    "sg:postcode":"4148",
    "sg:province":"Basel-Landschaft",
    "wof:name":"Soft World S\u00e0rl",
    "wof:placetype":"venue"
},
  "geometry": {"coordinates":[7.590485096,47.458896637],"type":"Point"}
}