{
  "type": "Feature",
  "properties": {
    "iso:country":"CH",
    "sg:address":"Burgstrasse 69",
    "sg:city":"Uster",
    "sg:orig_category":"Sportvereine Sch\u00fctzen",
    "sg:postcode":"8610",
    "sg:province":"Z\u00fcrich",
    "wof:name":"Arbeiterschiessverein",
    "wof:placetype":"venue"
},
  "geometry": {"coordinates":[8.7252597809,47.3414878845],"type":"Point"}
}