{
  "type": "Feature",
  "properties": {
    "iso:country":"CH",
    "sg:address":"Bons Rue J.-l.-de- 5 1006 Lausanne. Postfach",
    "sg:city":"Lausanne",
    "sg:orig_category":"Finanzierungsinstitutionen",
    "sg:postcode":"1006",
    "sg:province":"Vaud",
    "wof:name":"Ihg Verwaltungs-aktiengesellschaft",
    "wof:placetype":"venue"
},
  "geometry": {"coordinates":[8.3125095367,46.9867897034],"type":"Point"}
}