{
  "type": "Feature",
  "properties": {
    "iso:country":"CH",
    "sg:address":"Route Des Rottes",
    "sg:city":"Conthey",
    "sg:orig_category":"Tankstellen",
    "sg:phone":"+41 27 346 15 02",
    "sg:postcode":"1964",
    "sg:province":"Valais",
    "wof:name":"Broccard, Jean-marc",
    "wof:placetype":"venue"
},
  "geometry": {"coordinates":[7.3045201302,46.2233695984],"type":"Point"}
}