{
  "type": "Feature",
  "properties": {
    "iso:country":"CH",
    "sg:address":"Lindehofweg 1 8460 Marthalen. Postfach",
    "sg:city":"Marthalen",
    "sg:orig_category":"Herstellung von Betonerzeugnissen f\u00fcr den Bau",
    "sg:postcode":"8460",
    "sg:province":"Z\u00fcrich",
    "wof:name":"W & L Holz Und Bauelemente Gmbh",
    "wof:placetype":"venue"
},
  "geometry": {"coordinates":[8.6488208771,47.6233787537],"type":"Point"}
}