{
  "type": "Feature",
  "properties": {
    "iso:country":"CH",
    "sg:address":"Bahnweg 38",
    "sg:city":"Sargans",
    "sg:orig_category":"Maler U Glasergewerbe Malerei",
    "sg:phone":"+41 81 720 40 30",
    "sg:postcode":"7320",
    "sg:province":"St. Gallen",
    "wof:name":"Hutter",
    "wof:placetype":"venue"
},
  "geometry": {"coordinates":[9.4346551895,47.0485153198],"type":"Point"}
}