{
  "type": "Feature",
  "properties": {
    "iso:country":"CH",
    "sg:address":"Gotthardstrasse 18 - Golda",
    "sg:city":"Arth",
    "sg:classifiers":[
        {
            "category":"Travel",
            "subcategory":"Hotels & Motels",
            "type":"Entertainment"
        }
    ],
    "sg:postcode":"6415",
    "sg:province":"Schwyz",
    "sg:tags":[
        "hotels",
        "mit",
        "restaurant"
    ],
    "wof:name":"Niederberger-portmann Anna Wwe",
    "wof:placetype":"venue"
},
  "geometry": {"coordinates":[8.639749527,46.8880310059],"type":"Point"}
}