{
  "type": "Feature",
  "properties": {
    "iso:country":"CH",
    "sg:address":"2608",
    "sg:city":"Courtelary",
    "sg:orig_category":"Landesverteidigung, Sozialversicherung \u00d6ffentliche Verwaltung",
    "sg:phone":"+41 21 925 52 86",
    "sg:postcode":"2608",
    "sg:province":"Bern",
    "wof:name":"Administration Communale Protection Civile R\u00e9gion 4",
    "wof:placetype":"venue"
},
  "geometry": {"coordinates":[6.9105057716,46.4316940308],"type":"Point"}
}