{
  "type": "Feature",
  "properties": {
    "iso:country":"CH",
    "sg:address":"Waltersmattstrasse 8",
    "sg:city":"Koppigen",
    "sg:orig_category":"Gartenbau",
    "sg:phone":"+41 34 413 10 78",
    "sg:postcode":"3425",
    "sg:province":"Bern",
    "wof:name":"Hofer T.",
    "wof:placetype":"venue"
},
  "geometry": {"coordinates":[7.6068201065,47.1305503845],"type":"Point"}
}