{
  "type": "Feature",
  "properties": {
    "iso:country":"CH",
    "sg:address":"Hauptstrasse 23",
    "sg:city":"Triboltingen",
    "sg:orig_category":"Sonstiger Fachdetailhandel in Verkaufsr\u00e4umen Versandhandel",
    "sg:phone":"+41 71 664 33 74",
    "sg:postcode":"8273",
    "sg:province":"Thurgau",
    "wof:name":"Harlacher Hans Briefmarken-versand Versandhandel Mit Frankaturbriefmarken",
    "wof:placetype":"venue"
},
  "geometry": {"coordinates":[9.1081171036,47.6619491577],"type":"Point"}
}