{
  "type": "Feature",
  "properties": {
    "iso:country":"CH",
    "sg:address":"Bodenhofstrasse 6 6005 Luzern. Postfach",
    "sg:city":"Luzern",
    "sg:orig_category":"Handels-H\u00e4user U Gesellschaften",
    "sg:postcode":"6003",
    "sg:province":"Luzern",
    "wof:name":"Sanbo Gmbh Warenhandel. Immobilien Usw",
    "wof:placetype":"venue"
},
  "geometry": {"coordinates":[8.321185112,47.0394668579],"type":"Point"}
}