{
  "type": "Feature",
  "properties": {
    "addr:full":"Rue Du Bourg 3960 Sierre Case Postale Sierre Valais 3960",
    "addr:postcode":"3960;postale;3960",
    "addr:street":"Rue Du Bourg",
    "iso:country":"CH",
    "sg:address":"Rue Du Bourg 3960 Sierre Case Postale",
    "sg:city":"Sierre",
    "sg:orig_category":"Detailhandel mit Bekleidung",
    "sg:postcode":"3960",
    "sg:province":"Valais",
    "wof:name":"Modehaus Tichelli Stoffe, Bonneterie, Mercerie, Textilwaren, Damenkonfektion, Herrenartikel Usw; Handel",
    "wof:placetype":"venue"
},
  "geometry": {"coordinates":[7.536575,46.293869],"type":"Point"}
}