{
  "type": "Feature",
  "properties": {
    "iso:country":"CH",
    "sg:address":"Rue Du Pr\u00e9-salomon 3",
    "sg:city":"Satigny",
    "sg:classifiers":[
        {
            "category":"Wholesale",
            "subcategory":"Chemicals & Plastics",
            "type":"Manufacturing & Wholesale Goods"
        }
    ],
    "sg:phone":"+41 22 341 68 80",
    "sg:postcode":"1242",
    "sg:province":"Gen\u00e8ve",
    "sg:tags":[
        "cleaning",
        "surface"
    ],
    "wof:name":"Soft Applications S.a.",
    "wof:placetype":"venue"
},
  "geometry": {"coordinates":[6.062939,46.196064],"type":"Point"}
}