{
  "type": "Feature",
  "properties": {
    "iso:country":"CH",
    "sg:address":"Lauperswilstrasse 25",
    "sg:city":"Zollbr\u00fcck",
    "sg:orig_category":"Sanit\u00e4r U Heizungsinstallation",
    "sg:phone":"+41 34 496 80 68",
    "sg:postcode":"3436",
    "sg:province":"Bern",
    "wof:name":"Armin Badertscher Heizungsbau",
    "wof:placetype":"venue"
},
  "geometry": {"coordinates":[7.7403430939,46.9717407227],"type":"Point"}
}