{
  "type": "Feature",
  "properties": {
    "iso:country":"CH",
    "sg:address":"Wiesengrundstrasse 19",
    "sg:city":"W\u00e4ngi",
    "sg:orig_category":"Elektroinstallation",
    "sg:phone":"+41 52 378 18 14",
    "sg:postcode":"9545",
    "sg:province":"Thurgau",
    "wof:name":"Elektro H\u00f6rnlimann Ag",
    "wof:placetype":"venue"
},
  "geometry": {"coordinates":[8.9522619247,47.5009880066],"type":"Point"}
}