{
  "type": "Feature",
  "properties": {
    "iso:country":"CH",
    "sg:address":"Hammerstrasse 114 4057 Basel. Postfach",
    "sg:city":"Basel",
    "sg:orig_category":"Nahrungsmittel-Industrie: Rohstoffe",
    "sg:phone":"+41 61 691 73 73",
    "sg:postcode":"4051",
    "sg:province":"Basel-Stadt",
    "wof:name":"Comestibles Espanoles, Blanco Alfredo Spanische Lebensmittelspezialit\u00e4ten; Verkauf.",
    "wof:placetype":"venue"
},
  "geometry": {"coordinates":[7.5955162048,47.5660476685],"type":"Point"}
}