{
  "type": "Feature",
  "properties": {
    "iso:country":"CH",
    "sg:address":"Via Al Chioso 30",
    "sg:city":"Lugano",
    "sg:orig_category":"Tapezierer/Dekorateure",
    "sg:phone":"+41 91 971 92 06",
    "sg:postcode":"6900",
    "sg:province":"Ticino",
    "wof:name":"Giuseppe Knupfer Tappezziere-decoratore",
    "wof:placetype":"venue"
},
  "geometry": {"coordinates":[8.9636526108,46.0091400146],"type":"Point"}
}