{
  "type": "Feature",
  "properties": {
    "iso:country":"CH",
    "sg:address":"Chemin De Bellevue 3",
    "sg:city":"Prangins",
    "sg:orig_category":"Mechanische Werkst\u00e4tten Schlossereien",
    "sg:phone":"+41 79 645 08 01",
    "sg:postcode":"1197",
    "sg:province":"Vaud",
    "wof:name":"B\u00e4rtschi Maschinenbau",
    "wof:placetype":"venue"
},
  "geometry": {"coordinates":[7.5763440132,47.4938812256],"type":"Point"}
}