{
  "type": "Feature",
  "properties": {
    "iso:country":"CH",
    "sg:address":"Chemin Du Ranty",
    "sg:city":"Assens",
    "sg:orig_category":"Fassadenbau Maurerarbeiten",
    "sg:phone":"+41 21 881 40 75",
    "sg:postcode":"1042",
    "sg:province":"Vaud",
    "wof:name":"R\u00e9novation De Fa\u00e7ades As & Sl S\u00e0rl",
    "wof:placetype":"venue"
},
  "geometry": {"coordinates":[6.6198768616,46.6131668091],"type":"Point"}
}