{
  "type": "Feature",
  "properties": {
    "iso:country":"CH",
    "sg:address":"Schwermenwaldstrasse 13",
    "sg:city":"Ittigen",
    "sg:orig_category":"Non-Classified Establishments",
    "sg:postcode":"3063",
    "sg:province":"Bern",
    "wof:name":"Telecampus Ag",
    "wof:placetype":"venue"
},
  "geometry": {"coordinates":[7.4711380005,46.968711853],"type":"Point"}
}