{
  "type": "Feature",
  "properties": {
    "iso:country":"CH",
    "sg:address":"Bahnhofstrasse 23",
    "sg:city":"B\u00e4retswil",
    "sg:orig_category":"Sportvereine Turnen Vereine Damen",
    "sg:phone":"+41 19392525",
    "sg:postcode":"8344",
    "sg:province":"Z\u00fcrich",
    "wof:name":"Damenriege Stv B\u00e4retswil",
    "wof:placetype":"venue"
},
  "geometry": {"coordinates":[8.8528604507,47.3366203308],"type":"Point"}
}