{
  "type": "Feature",
  "properties": {
    "iso:country":"CH",
    "sg:address":"Rotweg 2 8820 W\u00e4denswil. Postfach",
    "sg:city":"W\u00e4denswil",
    "sg:orig_category":"Datenverarbeitungsdienste",
    "sg:phone":"+41 16801133",
    "sg:postcode":"8820",
    "sg:province":"Z\u00fcrich",
    "wof:name":"Michael Schweizer Edv-beratung",
    "wof:placetype":"venue"
},
  "geometry": {"coordinates":[8.670074,47.22802],"type":"Point"}
}