{
  "type": "Feature",
  "properties": {
    "iso:country":"CH",
    "sg:address":"Via Stazione",
    "sg:city":"Bioggio",
    "sg:orig_category":"Grosshandel mit Tabakwaren",
    "sg:phone":"+41 91 605 16 42",
    "sg:postcode":"6934",
    "sg:province":"Ticino",
    "wof:name":"British American Tobacco Switzerland Sa",
    "wof:placetype":"venue"
},
  "geometry": {"coordinates":[8.9085445404,46.0127601624],"type":"Point"}
}