{
  "type": "Feature",
  "properties": {
    "iso:country":"CH",
    "sg:address":"Sonnenbergstrasse 27",
    "sg:city":"Uster",
    "sg:orig_category":"Mechanik",
    "sg:postcode":"8610",
    "sg:province":"Z\u00fcrich",
    "wof:name":"M\u00fcller A. Metallverarbeitung + Fassadentechnik",
    "wof:placetype":"venue"
},
  "geometry": {"coordinates":[8.1510362625,47.5610466003],"type":"Point"}
}