{
  "type": "Feature",
  "properties": {
    "iso:country":"CH",
    "sg:address":"6214",
    "sg:city":"Schenkon",
    "sg:orig_category":"Verarbeitung von Milch Verwertung von Milch",
    "sg:postcode":"6214",
    "sg:province":"Luzern",
    "wof:name":"K\u00e4sereigenossenschaft Tann-zopfenberg",
    "wof:placetype":"venue"
},
  "geometry": {"coordinates":[8.138297081,47.1724777222],"type":"Point"}
}