{
  "type": "Feature",
  "properties": {
    "iso:country":"CH",
    "sg:address":"Rainacherweg 2",
    "sg:city":"Vordemwald",
    "sg:orig_category":"Wohnheime",
    "sg:postcode":"4803",
    "sg:province":"Aargau",
    "wof:name":"Genossenschaft F\u00fcr Pflege Und Alterswohnungen",
    "wof:placetype":"venue"
},
  "geometry": {"coordinates":[7.510114193,47.4790534973],"type":"Point"}
}