{
  "type": "Feature",
  "properties": {
    "iso:country":"CH",
    "sg:address":"Via Ferri 28",
    "sg:city":"Lugano",
    "sg:orig_category":"Grosshandel mit Obst U Gem\u00fcse",
    "sg:phone":"+41 62 205 78 78",
    "sg:postcode":"6900",
    "sg:province":"Ticino",
    "wof:name":"Fralco Ag",
    "wof:placetype":"venue"
},
  "geometry": {"coordinates":[7.8667988777,47.3393096924],"type":"Point"}
}