{
  "type": "Feature",
  "properties": {
    "iso:country":"CH",
    "sg:address":"Via Pedemonte 12",
    "sg:city":"Viganello",
    "sg:orig_category":"Veterin\u00e4rwesen",
    "sg:phone":"+41 91 970 34 94",
    "sg:postcode":"6962",
    "sg:province":"Ticino",
    "wof:name":"Dott.med.vet.manuela Marenco Veterinario",
    "wof:placetype":"venue"
},
  "geometry": {"coordinates":[8.9684677124,46.0106773376],"type":"Point"}
}