{
  "type": "Feature",
  "properties": {
    "iso:country":"CH",
    "sg:address":"Viaduktstrasse 6",
    "sg:city":"Herisau",
    "sg:orig_category":"Malerei-Gipserei Stukkateurgewerbe, Gipserei U Verputzerei",
    "sg:phone":"+41 71 352 40 86",
    "sg:postcode":"9100",
    "sg:province":"Appenzell Ausserrhoden",
    "wof:name":"Gennaro Basile Gipsergesch\u00e4ft",
    "wof:placetype":"venue"
},
  "geometry": {"coordinates":[9.2721576691,47.3889312744],"type":"Point"}
}