{
  "type": "Feature",
  "properties": {
    "iso:country":"CH",
    "sg:address":"Fauggersweg 32",
    "sg:city":"Ins",
    "sg:orig_category":"Herstellung von K\u00fcchenm\u00f6beln",
    "sg:phone":"+41 32 313 31 31",
    "sg:postcode":"3232",
    "sg:province":"Bern",
    "wof:name":"K\u00fcchen + Raum Ag",
    "wof:placetype":"venue"
},
  "geometry": {"coordinates":[7.0987448692,47.0030517578],"type":"Point"}
}