{
  "type": "Feature",
  "properties": {
    "iso:country":"CH",
    "sg:address":"Via Dei Gaggini 3 6500 Bellinzona. Postfach",
    "sg:city":"Bellinzona",
    "sg:orig_category":"Allgemeiner Hoch U Tiefbau",
    "sg:postcode":"6500",
    "sg:province":"Ticino",
    "wof:name":"Bomio Demis Sa",
    "wof:placetype":"venue"
},
  "geometry": {"coordinates":[9.013226,46.191414],"type":"Point"}
}