{
  "type": "Feature",
  "properties": {
    "iso:country":"CH",
    "sg:address":"Le Petit Ch\u00e2teau",
    "sg:city":"Echandens",
    "sg:orig_category":"Unternehmensberatung",
    "sg:postcode":"1026",
    "sg:province":"Vaud",
    "wof:name":"Mcs, Mercier Consulting Services",
    "wof:placetype":"venue"
},
  "geometry": {"coordinates":[6.5420351028,46.5359382629],"type":"Point"}
}