{
  "type": "Feature",
  "properties": {
    "iso:country":"CH",
    "sg:address":"R\u00fcbackerstrasse 6",
    "sg:city":"R\u00f6schenz",
    "sg:orig_category":"Non-Classified Establishments",
    "sg:postcode":"4244",
    "sg:province":"Basel-Landschaft",
    "wof:name":"M. Meury Bauteam Gmbh",
    "wof:placetype":"venue"
},
  "geometry": {"coordinates":[7.4779047966,47.4263458252],"type":"Point"}
}