{
  "type": "Feature",
  "properties": {
    "iso:country":"CH",
    "sg:address":"Hammerstrasse 200 4057 Basel. Postfach",
    "sg:city":"Basel",
    "sg:orig_category":"Detailhandel mit elektrischen Haushalts-,Radio U Fernsehger\u00e4ten sowie Musikinstrumenten",
    "sg:phone":"+41 55 442 58 38",
    "sg:postcode":"4051",
    "sg:province":"Basel-Stadt",
    "wof:name":"H & S Vertrieb Ag",
    "wof:placetype":"venue"
},
  "geometry": {"coordinates":[6.9261350632,46.39818573],"type":"Point"}
}