{
  "type": "Feature",
  "properties": {
    "iso:country":"CH",
    "sg:address":"Hautierdoz 17",
    "sg:city":"Bionnens",
    "sg:orig_category":"Non-Classified Establishments",
    "sg:postcode":"1670",
    "sg:province":"Fribourg",
    "wof:name":"Entreprise Forestiere Pascal & Silvere Gavillet",
    "wof:placetype":"venue"
},
  "geometry": {"coordinates":[6.8359251022,46.6341934204],"type":"Point"}
}