{
  "type": "Feature",
  "properties": {
    "iso:country":"CH",
    "sg:address":"Schwendi 26",
    "sg:city":"Graben",
    "sg:orig_category":"Bau U Wohngenossenschaften",
    "sg:postcode":"3376",
    "sg:province":"Bern",
    "wof:name":"Liberale Baugen.graben C/o Tr\u00f6sch & Co",
    "wof:placetype":"venue"
},
  "geometry": {"coordinates":[7.725639,47.222919],"type":"Point"}
}