{
  "type": "Feature",
  "properties": {
    "iso:country":"CH",
    "sg:address":"Ebnetstrasse 9",
    "sg:city":"Sulgen",
    "sg:orig_category":"Politische Parteien SP",
    "sg:postcode":"8583",
    "sg:province":"Thurgau",
    "wof:name":"Sp Sulgen/kradolf-sch\u00f6nenberg",
    "wof:placetype":"venue"
},
  "geometry": {"coordinates":[9.1900920868,47.5406074524],"type":"Point"}
}