{
  "type": "Feature",
  "properties": {
    "addr:full":"Im G\u00e4ssli 13 Neunkirch Schaffhausen 8213",
    "addr:housenumber":"13",
    "addr:postcode":"8213",
    "addr:street":"Im Gaessli",
    "iso:country":"CH",
    "sg:address":"Im G\u00e4ssli 13",
    "sg:city":"Neunkirch",
    "sg:orig_category":"Autolackierereien",
    "sg:phone":"+41 52 681 12 70",
    "sg:postcode":"8213",
    "sg:province":"Schaffhausen",
    "wof:name":"Marcel Volkart Autospritzwerk",
    "wof:placetype":"venue"
},
  "geometry": {"coordinates":[8.498854,47.687008],"type":"Point"}
}