{
  "type": "Feature",
  "properties": {
    "iso:country":"CH",
    "sg:address":"Recolaine 28",
    "sg:city":"Vicques",
    "sg:orig_category":"Gymnastik U Fitnesszentren",
    "sg:postcode":"2824",
    "sg:province":"Jura",
    "wof:name":"Valfit S\u00e0rl Centre De Fitness",
    "wof:placetype":"venue"
},
  "geometry": {"coordinates":[7.4232420921,47.3505058289],"type":"Point"}
}