{
  "type": "Feature",
  "properties": {
    "iso:country":"CH",
    "sg:address":"Quai Philippe-godet 5",
    "sg:city":"Neuch\u00e2tel",
    "sg:orig_category":"Pensionskassen",
    "sg:phone":"+41 32 720 06 00",
    "sg:postcode":"2000",
    "sg:province":"Neuch\u00e2tel",
    "wof:name":"Caisse De Pensions De La Compagnie Des Transports En Commun De Neuch\u00e2tel Et Environs",
    "wof:placetype":"venue"
},
  "geometry": {"coordinates":[6.9236221313,46.9899749756],"type":"Point"}
}