{
  "type": "Feature",
  "properties": {
    "iso:country":"CH",
    "sg:address":"Via Pedemonte 34 6962 Viganello. Postfach",
    "sg:city":"Agno",
    "sg:orig_category":"Grosshandel mit Datenverarbeitungsger\u00e4ten Softwareentwicklung U beratung",
    "sg:phone":"+41 17776161",
    "sg:postcode":"6982",
    "sg:province":"Ticino",
    "wof:name":"Oral Info Gmbh",
    "wof:placetype":"venue"
},
  "geometry": {"coordinates":[8.4422187805,47.3508338928],"type":"Point"}
}