{
  "type": "Feature",
  "properties": {
    "addr:full":"Alpenstrasse 9 6300 Zug. Postfach 4352 Zug Zug 6304",
    "addr:housenumber":"9",
    "addr:postcode":"6300;4352;6304",
    "addr:street":"Alpenstrasse;Postfach;Zug",
    "iso:country":"CH",
    "sg:address":"Alpenstrasse 9 6300 Zug. Postfach 4352",
    "sg:city":"Zug",
    "sg:orig_category":"Arztpraxen",
    "sg:phone":"+41 41 726 10 10",
    "sg:postcode":"6304",
    "sg:province":"Zug",
    "wof:name":"Dr.med.agnes Huszar Spezial\u00e4rztin Fmh",
    "wof:placetype":"venue"
},
  "geometry": {"coordinates":[8.514466,47.17234],"type":"Point"}
}