{
  "type": "Feature",
  "properties": {
    "iso:country":"CH",
    "sg:address":"Z\u00fcrichstrasse 56 3360 Herzogenbuchsee. Postfach",
    "sg:city":"Herzogenbuchsee",
    "sg:orig_category":"Wirtschaftspr\u00fcfung, Steuerberatung U Treuhand",
    "sg:phone":"+41 62 961 11 62",
    "sg:postcode":"3360",
    "sg:province":"Bern",
    "wof:name":"Heinz M. Hofstetter",
    "wof:placetype":"venue"
},
  "geometry": {"coordinates":[7.710021019,47.1931152344],"type":"Point"}
}