{
  "type": "Feature",
  "properties": {
    "iso:country":"CH",
    "sg:address":"Casa Triada 6575 Vairano. Postfach",
    "sg:city":"Torricella",
    "sg:orig_category":"G\u00fcterbef\u00f6rderung im Strassenverkehr",
    "sg:phone":"+41 91 945 11 53",
    "sg:postcode":"6808",
    "sg:province":"Ticino",
    "wof:name":"Bitrans Sagl",
    "wof:placetype":"venue"
},
  "geometry": {"coordinates":[8.8021802902,46.1322441101],"type":"Point"}
}