{
  "type": "Feature",
  "properties": {
    "iso:country":"CH",
    "sg:address":"Chemin Du Moulin 21",
    "sg:city":"Bernex",
    "sg:orig_category":"Datenverarbeitungsdienste",
    "sg:phone":"+41 55 240 73 83",
    "sg:postcode":"1233",
    "sg:province":"Gen\u00e8ve",
    "wof:name":"Bachmann M. + Co",
    "wof:placetype":"venue"
},
  "geometry": {"coordinates":[8.849684,47.257874],"type":"Point"}
}