{
  "type": "Feature",
  "properties": {
    "iso:country":"CH",
    "sg:address":"Rte Des Chevaliers-de-malte 30",
    "sg:city":"Plan-les-ouates",
    "sg:orig_category":"Herstellung von Betonerzeugnissen f\u00fcr den Bau",
    "sg:phone":"+41 22 771 15 72",
    "sg:postcode":"1228",
    "sg:province":"Gen\u00e8ve",
    "wof:name":"R. Maulini & G. Gagliardi",
    "wof:placetype":"venue"
},
  "geometry": {"coordinates":[6.1210718155,46.1651268005],"type":"Point"}
}