{
  "type": "Feature",
  "properties": {
    "iso:country":"CH",
    "sg:address":"Favon Bvd Georges- 15 1204 Gen\u00e8ve. Postfach",
    "sg:city":"Gen\u00e8ve",
    "sg:orig_category":"RESTAURANTS: TEA-ROOMS",
    "sg:postcode":"1204",
    "sg:province":"Gen\u00e8ve",
    "wof:name":"Isidro Fraguas & Cie",
    "wof:placetype":"venue"
},
  "geometry": {"coordinates":[6.1404027939,46.2021369934],"type":"Point"}
}