{
  "type": "Feature",
  "properties": {
    "addr:full":"1983 Evol\u00e8ne Valais 1983",
    "addr:postcode":"1983;1983",
    "iso:country":"CH",
    "sg:address":"1983",
    "sg:city":"Evol\u00e8ne",
    "sg:orig_category":"Bauspenglerei Dachdeckerei",
    "sg:phone":"+41 27 283 15 52",
    "sg:postcode":"1983",
    "sg:province":"Valais",
    "wof:name":"Gilbert Bovier Et Fils Sanitaire-ferblanterie",
    "wof:placetype":"venue"
},
  "geometry": {"coordinates":[7.496159,46.114475],"type":"Point"}
}