{
  "type": "Feature",
  "properties": {
    "iso:country":"CH",
    "sg:address":"B\u00fcntlistrasse 3",
    "sg:city":"M\u00e4genwil",
    "sg:orig_category":"Autospenglereien",
    "sg:phone":"+41 56 624 21 26",
    "sg:postcode":"5506",
    "sg:province":"Aargau",
    "wof:name":"Kurt Blaser Carrosserie",
    "wof:placetype":"venue"
},
  "geometry": {"coordinates":[8.223136,47.411507],"type":"Point"}
}