{
  "type": "Feature",
  "properties": {
    "iso:country":"CH",
    "sg:address":"Schleusenweg 28",
    "sg:city":"Port",
    "sg:orig_category":"Oberfl\u00e4chenveredlung U W\u00e4rmebehandlung",
    "sg:phone":"+41 32 331 95 11",
    "sg:postcode":"2562",
    "sg:province":"Bern",
    "wof:name":"Hermann Egon.",
    "wof:placetype":"venue"
},
  "geometry": {"coordinates":[7.2501778603,47.1195678711],"type":"Point"}
}