{
  "type": "Feature",
  "properties": {
    "iso:country":"CH",
    "sg:address":"Hauptstrasse 22",
    "sg:city":"Menziken",
    "sg:classifiers":[
        {
            "category":"Restaurant",
            "type":"Food & Drink"
        }
    ],
    "sg:phone":"+41 62 771 26 26",
    "sg:postcode":"5737",
    "sg:province":"Aargau",
    "sg:tags":[
        "tea-rooms",
        "restaurants"
    ],
    "wof:name":"Hollywood Boulevard Caf\u00e9 Sa",
    "wof:placetype":"venue"
},
  "geometry": {"coordinates":[8.1866846085,47.2439918518],"type":"Point"}
}