{
  "type": "Feature",
  "properties": {
    "iso:country":"CH",
    "sg:address":"Paradiesrain 28",
    "sg:city":"Allschwil",
    "sg:orig_category":"Nahrungsmittel-Industrie: Rohstoffe",
    "sg:phone":"+41 61 481 14 30",
    "sg:postcode":"4123",
    "sg:province":"Basel-Landschaft",
    "wof:name":"W. Beyeler Ag",
    "wof:placetype":"venue"
},
  "geometry": {"coordinates":[7.5523529053,47.5459747314],"type":"Point"}
}