{
  "type": "Feature",
  "properties": {
    "iso:country":"CH",
    "sg:address":"Boulevard De Grancy 56 1000 Lausanne. Postfach",
    "sg:city":"Lausanne",
    "sg:orig_category":"Sonstiger Grosshandel",
    "sg:postcode":"1003",
    "sg:province":"Vaud",
    "wof:name":"Home Distribtion S\u00e0rl",
    "wof:placetype":"venue"
},
  "geometry": {"coordinates":[6.6256132126,46.5166168213],"type":"Point"}
}