{
  "type": "Feature",
  "properties": {
    "iso:country":"CH",
    "sg:address":"Rue Fran\u00e7ois-versonnex 17",
    "sg:city":"Gen\u00e8ve",
    "sg:orig_category":"Detailhandel mit Damenbekleidung",
    "sg:phone":"+41 22 736 35 52",
    "sg:postcode":"1207",
    "sg:province":"Gen\u00e8ve",
    "wof:name":"Arlette Hoegen Boutique Sc\u00e9nario",
    "wof:placetype":"venue"
},
  "geometry": {"coordinates":[6.156337,46.202877],"type":"Point"}
}