{
  "type": "Feature",
  "properties": {
    "iso:country":"CH",
    "sg:address":"Ruelle De Couvaloup 2",
    "sg:city":"Grandson",
    "sg:orig_category":"Detailhandel mit Fahrr\u00e4dern Handel mit Motorr\u00e4dern, Teilen U Zubeh\u00f6r Instandhaltung U Reparatur von ",
    "sg:phone":"+41 24 445 42 09",
    "sg:postcode":"1422",
    "sg:province":"Vaud",
    "wof:name":"Andr\u00e9 Paul V\u00e9los Motos",
    "wof:placetype":"venue"
},
  "geometry": {"coordinates":[6.645468235,46.8086891174],"type":"Point"}
}