{
  "type": "Feature",
  "properties": {
    "iso:country":"CH",
    "sg:address":"H\u00f6lzlistrasse 48",
    "sg:city":"Binningen",
    "sg:orig_category":"Zahntechnische Laboratorien",
    "sg:phone":"+41 61 421 79 13",
    "sg:postcode":"4102",
    "sg:province":"Basel-Landschaft",
    "wof:name":"Walter Wicki Zahntechnisches Labor",
    "wof:placetype":"venue"
},
  "geometry": {"coordinates":[7.5642790794,47.5356788635],"type":"Point"}
}