{
  "type": "Feature",
  "properties": {
    "iso:country":"CH",
    "sg:address":"Gelterkinderstr. 24",
    "sg:city":"Sissach",
    "sg:classifiers":[
        {
            "category":"Manufacturing",
            "subcategory":"Metals",
            "type":"Manufacturing & Wholesale Goods"
        }
    ],
    "sg:phone":"+41 61 976 44 44",
    "sg:postcode":"4450",
    "sg:province":"Basel-Landschaft",
    "sg:tags":[
        "-",
        "machine",
        "equipment",
        "engineering",
        "machinery",
        "mechanical"
    ],
    "wof:name":"Von Arx Ag",
    "wof:placetype":"venue"
},
  "geometry": {"coordinates":[7.8211188316,47.4617462158],"type":"Point"}
}