{
  "type": "Feature",
  "properties": {
    "iso:country":"CH",
    "sg:address":"Lange Gasse 15 4052 Basel. Postfach",
    "sg:city":"Basel",
    "sg:orig_category":"Herstellung von Papier, Karton U Pappe",
    "sg:postcode":"4052",
    "sg:province":"Basel-Stadt",
    "wof:name":"Friedess Invest Ag",
    "wof:placetype":"venue"
},
  "geometry": {"coordinates":[8.311507225,46.9859924316],"type":"Point"}
}