{
  "type": "Feature",
  "properties": {
    "iso:country":"CH",
    "sg:address":"Chemin De Gravernay 7",
    "sg:city":"Bussigny-lausanne",
    "sg:orig_category":"G\u00fcterbef\u00f6rderung im Strassenverkehr",
    "sg:phone":"+41 21 701 17 70",
    "sg:postcode":"1030",
    "sg:province":"Vaud",
    "wof:name":"Pierre-andr\u00e9 Bertholet Transports",
    "wof:placetype":"venue"
},
  "geometry": {"coordinates":[6.5486631393,46.5510940552],"type":"Point"}
}