{
  "type": "Feature",
  "properties": {
    "iso:country":"CH",
    "sg:address":"Hauptstrasse 14",
    "sg:city":"Heinrichswil",
    "sg:orig_category":"Allgemeiner Hochbau Strassenbau",
    "sg:phone":"+41 33 251 20 58",
    "sg:postcode":"4558",
    "sg:province":"Solothurn",
    "wof:name":"S\u00e4gesser Ag Bauunternehmen",
    "wof:placetype":"venue"
},
  "geometry": {"coordinates":[7.729933,46.75676],"type":"Point"}
}