{
  "type": "Feature",
  "properties": {
    "iso:country":"CH",
    "sg:address":"Canav\u00e9e Via 4 A",
    "sg:city":"Comano",
    "sg:orig_category":"RESTAURANTS: TEA-ROOMS",
    "sg:postcode":"6949",
    "sg:province":"Ticino",
    "wof:name":"Famceri Sagl",
    "wof:placetype":"venue"
},
  "geometry": {"coordinates":[8.9696674347,45.9001045227],"type":"Point"}
}