{
  "type": "Feature",
  "properties": {
    "iso:country":"CH",
    "sg:address":"Breitmatt 10",
    "sg:city":"Toffen",
    "sg:orig_category":"Landw. Genossenschaften Dresch",
    "sg:phone":"+41 31 819 07 06",
    "sg:postcode":"3125",
    "sg:province":"Bern",
    "wof:name":"Otto Messerli M\u00e4hdrescherei",
    "wof:placetype":"venue"
},
  "geometry": {"coordinates":[7.4938101768,46.8730354309],"type":"Point"}
}