{
  "type": "Feature",
  "properties": {
    "iso:country":"CH",
    "sg:address":"Route Principale 2",
    "sg:city":"Vicques",
    "sg:classifiers":[
        {
            "category":"Arena",
            "subcategory":"Sports Club",
            "type":"Entertainment"
        }
    ],
    "sg:phone":"+41 52 375 25 45",
    "sg:postcode":"2824",
    "sg:province":"Jura",
    "sg:tags":[
        "karate",
        "judo",
        "sportvereine"
    ],
    "wof:name":"Judo Club Nippon Z\u00fcrich",
    "wof:placetype":"venue"
},
  "geometry": {"coordinates":[9.3760499954,47.4264793396],"type":"Point"}
}