{
  "type": "Feature",
  "properties": {
    "iso:country":"CH",
    "sg:address":"Badenerstrasse 281",
    "sg:city":"Z\u00fcrich",
    "sg:classifiers":[
        {
            "category":"Professional",
            "subcategory":"Computer Services",
            "type":"Services"
        }
    ],
    "sg:postcode":"8003",
    "sg:tags":[
        "safe",
        "security",
        "inheritance",
        "legacy",
        "estate",
        "legal",
        "data-protection",
        "privacy",
        "digital-inheritance",
        "data-inheritance"
    ],
    "sg:website":"http://www.dswiss.com",
    "wof:name":"DSwiss",
    "wof:placetype":"venue"
},
  "geometry": {"coordinates":[8.5142125,47.376362],"type":"Point"}
}