{
  "type": "Feature",
  "properties": {
    "iso:country":"CH",
    "sg:address":"Hauptstrasse 190",
    "sg:city":"Orpund",
    "sg:orig_category":"Polizei",
    "sg:phone":"+41 32 355 28 38",
    "sg:postcode":"2552",
    "sg:province":"Bern",
    "wof:name":"Kantonale Polizei",
    "wof:placetype":"venue"
},
  "geometry": {"coordinates":[7.3084478378,47.1385955811],"type":"Point"}
}