{
  "type": "Feature",
  "properties": {
    "iso:country":"CH",
    "sg:address":"Z.i. Bovery B",
    "sg:city":"Collombey-le-grand",
    "sg:classifiers":[
        {
            "category":"Manufacturing",
            "subcategory":"Chemicals & Compounds",
            "type":"Manufacturing & Wholesale Goods"
        }
    ],
    "sg:phone":"+41 24 472 75 75",
    "sg:postcode":"1868",
    "sg:province":"Valais",
    "sg:tags":[
        "pharmaceutical",
        "cosmetic"
    ],
    "wof:name":"Laboratoires Cosmotec S.a.",
    "wof:placetype":"venue"
},
  "geometry": {"coordinates":[6.948092,46.280167],"type":"Point"}
}