{
  "type": "Feature",
  "properties": {
    "iso:country":"CH",
    "sg:address":"Bahnhofstrasse 1",
    "sg:city":"Interlaken",
    "sg:orig_category":"Grosshandel mit Textilien",
    "sg:phone":"+41 79 689 94 36",
    "sg:postcode":"3800",
    "sg:province":"Bern",
    "wof:name":"Hornik Fibertech",
    "wof:placetype":"venue"
},
  "geometry": {"coordinates":[8.9413003922,47.2884101868],"type":"Point"}
}