{
  "type": "Feature",
  "properties": {
    "iso:country":"CH",
    "sg:address":"Contrada Maderno 1",
    "sg:city":"Bissone",
    "sg:orig_category":"Herstellung von sonstiger Bekleidung U Bekleidungszubeh\u00f6r",
    "sg:phone":"+41 91 994 38 09",
    "sg:postcode":"6816",
    "sg:province":"Ticino",
    "wof:name":"Quadrifoglio Bimbo Moda Sa",
    "wof:placetype":"venue"
},
  "geometry": {"coordinates":[8.964805603,45.9499015808],"type":"Point"}
}