{
  "type": "Feature",
  "properties": {
    "iso:country":"CH",
    "sg:address":"Marterey Rue 15",
    "sg:city":"Lausanne",
    "sg:orig_category":"Pensionskassen",
    "sg:phone":"+41 21 348 13 13",
    "sg:postcode":"1005",
    "sg:province":"Vaud",
    "wof:name":"Fondation En Faveur Du Personnel De La Loterie Romande",
    "wof:placetype":"venue"
},
  "geometry": {"coordinates":[6.6387619972,46.5209770203],"type":"Point"}
}