{
  "type": "Feature",
  "properties": {
    "iso:country":"CH",
    "sg:address":"Agasse Rue 45 1208 Gen\u00e8ve. Postfach",
    "sg:city":"Gen\u00e8ve",
    "sg:orig_category":"Pensionskassen",
    "sg:postcode":"1208",
    "sg:province":"Gen\u00e8ve",
    "wof:name":"Fondation De Pr\u00e9voyance En Faveur Du Personnel De La Soci\u00e9t\u00e9 Firmenich Sa",
    "wof:placetype":"venue"
},
  "geometry": {"coordinates":[6.1282281876,46.1970787048],"type":"Point"}
}