{
  "type": "Feature",
  "properties": {
    "iso:country":"CH",
    "sg:address":"Rue Du Rh\u00f4ne 29 1200 Genf. Postfach",
    "sg:city":"Gen\u00e8ve",
    "sg:orig_category":"Fachdetailhandel in Verkaufsr\u00e4umen",
    "sg:postcode":"1201",
    "sg:province":"Gen\u00e8ve",
    "wof:name":"Fabrication D'horlogerie, Guy Henri-robert, Montres Musette",
    "wof:placetype":"venue"
},
  "geometry": {"coordinates":[6.8255000114,47.1090316772],"type":"Point"}
}