{
  "type": "Feature",
  "properties": {
    "iso:country":"CH",
    "sg:address":"Untere Gasse 22",
    "sg:city":"Chur",
    "sg:orig_category":"Detailhandel mit Geschenkartikeln U Souvenirs Fachdetailhandel in Verkaufsr\u00e4umen",
    "sg:phone":"+41 81 252 29 21",
    "sg:postcode":"7000",
    "sg:province":"Graubunden",
    "wof:name":"Scarnuz Ag",
    "wof:placetype":"venue"
},
  "geometry": {"coordinates":[9.5298051834,46.8486442566],"type":"Point"}
}