{
  "type": "Feature",
  "properties": {
    "iso:country":"CH",
    "sg:address":"Rain 35 5000 Aarau. Postfach",
    "sg:city":"Aarau",
    "sg:orig_category":"Reiseb\u00fcros U Reiseveranstalter",
    "sg:phone":"+41 21 311 50 40",
    "sg:postcode":"5000",
    "sg:province":"Aargau",
    "wof:name":"Nova Tours Ag",
    "wof:placetype":"venue"
},
  "geometry": {"coordinates":[6.6279129982,46.5245552063],"type":"Point"}
}