{
  "type": "Feature",
  "properties": {
    "iso:country":"CH",
    "sg:address":"Avenue De Chailly 7",
    "sg:city":"Lausanne",
    "sg:orig_category":"Detailhandel mit Tabakwaren Werbung",
    "sg:phone":"+41 22 732 45 92",
    "sg:postcode":"1012",
    "sg:province":"Vaud",
    "wof:name":"Accolade Sa",
    "wof:placetype":"venue"
},
  "geometry": {"coordinates":[6.1458778381,46.2103652954],"type":"Point"}
}