{
  "type": "Feature",
  "properties": {
    "iso:country":"CH",
    "sg:address":"Oberplattenstrasse 2",
    "sg:city":"Lichtensteig",
    "sg:classifiers":[
        {
            "category":"Shopping",
            "subcategory":"Clothing, Apparel, & Fashions",
            "type":"Retail Goods"
        }
    ],
    "sg:phone":"+41 71 988 35 12",
    "sg:postcode":"9620",
    "sg:province":"St. Gallen",
    "sg:tags":[
        "protective",
        "clothing",
        "flame-proof"
    ],
    "wof:name":"Qualytex",
    "wof:placetype":"venue"
},
  "geometry": {"coordinates":[9.085026,47.331371],"type":"Point"}
}