{
  "type": "Feature",
  "properties": {
    "iso:country":"CH",
    "sg:address":"Grand'rue 3",
    "sg:city":"Auvernier",
    "sg:orig_category":"Dauerkulturbau Rebbau",
    "sg:phone":"+41 79 213 79 58",
    "sg:postcode":"2012",
    "sg:province":"Neuch\u00e2tel",
    "wof:name":"Domaine De Montmollin E. Fils, Soci\u00e9t\u00e9 En Commandite",
    "wof:placetype":"venue"
},
  "geometry": {"coordinates":[6.86853,46.980469],"type":"Point"}
}