{
  "type": "Feature",
  "properties": {
    "addr:full":"Haulenacker 491 Matzendorf Solothurn 4713",
    "addr:housenumber":"491",
    "addr:postcode":"4713",
    "addr:street":"Haulenacker",
    "iso:country":"CH",
    "sg:address":"Haulenacker 491",
    "sg:city":"Matzendorf",
    "sg:orig_category":"Bauschreinerei Herstellung von Konstruktionsteilen, Fertigbauteilen U Ausbauelementen aus Holz",
    "sg:phone":"+41 62 394 16 26",
    "sg:postcode":"4713",
    "sg:province":"Solothurn",
    "wof:name":"Bieli Franz",
    "wof:placetype":"venue"
},
  "geometry": {"coordinates":[7.626391,47.308453],"type":"Point"}
}