{
  "type": "Feature",
  "properties": {
    "iso:country":"CH",
    "sg:address":"Via Magi 729",
    "sg:city":"Origlio",
    "sg:orig_category":"Detailhandel mit Radio U Fernsehger\u00e4ten Detailhandel mit elektrischen Haushalts-,Radio U Fernsehger\u00e4",
    "sg:phone":"+41 79 207 25 27",
    "sg:postcode":"6945",
    "sg:province":"Ticino",
    "wof:name":"Audiolight Service Di Panzeri Alessandro",
    "wof:placetype":"venue"
},
  "geometry": {"coordinates":[8.9446210861,46.0543479919],"type":"Point"}
}