{
  "type": "Feature",
  "properties": {
    "iso:country":"CH",
    "sg:address":"Laupenackerstrasse 32c",
    "sg:city":"Moosseedorf",
    "sg:orig_category":"Grosshandel mit Datenverarbeitungsger\u00e4ten",
    "sg:phone":"+41 79 420 63 66",
    "sg:postcode":"3302",
    "sg:province":"Bern",
    "wof:name":"Lienta Gmbh Druckerzubeh\u00f6r",
    "wof:placetype":"venue"
},
  "geometry": {"coordinates":[8.4598588943,47.4531097412],"type":"Point"}
}