{
  "type": "Feature",
  "properties": {
    "iso:country":"CH",
    "sg:address":"Fl\u00fcelistrasse 18",
    "sg:city":"Kerns",
    "sg:orig_category":"Dachdeckerei Zimmerei, Dachdeckerei, Bauspenglerei U Abdichtung",
    "sg:phone":"+41 41 660 71 55",
    "sg:postcode":"6064",
    "sg:province":"Obwalden",
    "wof:name":"R\u00f6thlin August, Bedachungen.",
    "wof:placetype":"venue"
},
  "geometry": {"coordinates":[8.273829,46.897625],"type":"Point"}
}