{
  "type": "Feature",
  "properties": {
    "iso:country":"CH",
    "sg:address":"Steigstrasse 4 8240 Thayngen. Postfach 34",
    "sg:city":"Thayngen",
    "sg:orig_category":"Spezieller Tiefbau Strassenbau",
    "sg:phone":"+41 52 649 41 11",
    "sg:postcode":"8240",
    "sg:province":"Schaffhausen",
    "wof:name":"Gribez Stefan Imthurn Graben-& Rohrleitungsbau",
    "wof:placetype":"venue"
},
  "geometry": {"coordinates":[8.7096157074,47.7501716614],"type":"Point"}
}