{
  "type": "Feature",
  "properties": {
    "iso:country":"CH",
    "sg:address":"Burghaldenstrasse 8",
    "sg:city":"Baden",
    "sg:orig_category":"Erwachsenenbildung U Unterricht K\u00fcnstlerische Schulen",
    "sg:phone":"+41 56 221 20 39",
    "sg:postcode":"5400",
    "sg:province":"Aargau",
    "wof:name":"Musikschule Der Region Baden",
    "wof:placetype":"venue"
},
  "geometry": {"coordinates":[8.3019151688,47.4710273743],"type":"Point"}
}