{
  "type": "Feature",
  "properties": {
    "iso:country":"CH",
    "sg:address":"Route De Neuch\u00e2tel 4bis",
    "sg:city":"Romanel-s-lausanne",
    "sg:orig_category":"Grosshandel mit Milch, Milcherzeugnissen, Eiern, Speise\u00f6len U Nahrungsfetten",
    "sg:phone":"+41 34 409 84 61",
    "sg:postcode":"1032",
    "sg:province":"Vaud",
    "wof:name":"Emmi K\u00e4se Ag Kirchberg",
    "wof:placetype":"venue"
},
  "geometry": {"coordinates":[7.757589817,46.9491271973],"type":"Point"}
}