{
  "type": "Feature",
  "properties": {
    "iso:country":"CH",
    "sg:address":"Im Schleipfenacher 8",
    "sg:city":"Maur",
    "sg:orig_category":"Non-Classified Establishments",
    "sg:phone":"+41 18261001",
    "sg:postcode":"8124",
    "sg:province":"Z\u00fcrich",
    "wof:name":"Stefan Sch\u00e4dle Dipl. Arch. Eth/sia",
    "wof:placetype":"venue"
},
  "geometry": {"coordinates":[8.6536493301,47.3325691223],"type":"Point"}
}