{
  "type": "Feature",
  "properties": {
    "iso:country":"CH",
    "sg:address":"Paradiesstrasse 24",
    "sg:city":"Schafisheim",
    "sg:orig_category":"G\u00fcterbef\u00f6rderung im Strassenverkehr",
    "sg:phone":"+41 62 891 85 10",
    "sg:postcode":"5503",
    "sg:province":"Aargau",
    "wof:name":"Geiser M. Ag, Transporte",
    "wof:placetype":"venue"
},
  "geometry": {"coordinates":[8.1402654648,47.3756332397],"type":"Point"}
}