{
  "type": "Feature",
  "properties": {
    "iso:country":"CH",
    "sg:address":"Kirchmattstrasse 12",
    "sg:city":"Steinhausen",
    "sg:orig_category":"Sportvereine Turnen",
    "sg:phone":"+41 41 740 52 22",
    "sg:postcode":"6312",
    "sg:province":"Zug",
    "wof:name":"Turnverein Menzingen",
    "wof:placetype":"venue"
},
  "geometry": {"coordinates":[8.4833307266,47.1955299377],"type":"Point"}
}