{
  "type": "Feature",
  "properties": {
    "iso:country":"CH",
    "sg:address":"Laret 38",
    "sg:city":"Pontresina",
    "sg:orig_category":"Veterin\u00e4rwesen",
    "sg:postcode":"7504",
    "sg:province":"Graubunden",
    "wof:name":"Petsana Gmbh",
    "wof:placetype":"venue"
},
  "geometry": {"coordinates":[9.3179893494,47.424949646],"type":"Point"}
}