{
  "type": "Feature",
  "properties": {
    "iso:country":"CH",
    "sg:address":"Sch\u00f6nb\u00fcelstrasse 2 9032 Engelburg. Postfach 143",
    "sg:city":"Engelburg",
    "sg:orig_category":"Detailhandel mit Blumen U Pflanzen",
    "sg:phone":"+41 71 278 17 81",
    "sg:postcode":"9032",
    "sg:province":"St. Gallen",
    "wof:name":"Esther Brunner Blumen D\u00f6rfli",
    "wof:placetype":"venue"
},
  "geometry": {"coordinates":[9.340591,47.444607],"type":"Point"}
}