{
  "type": "Feature",
  "properties": {
    "iso:country":"CH",
    "sg:address":"Gerliswilstr. 17",
    "sg:city":"Emmenbr\u00fccke",
    "sg:classifiers":[
        {
            "category":"Shopping",
            "subcategory":"Crafts & Fabrics",
            "type":"Retail Goods"
        }
    ],
    "sg:phone":"+41 71 277 13 51",
    "sg:postcode":"6021",
    "sg:province":"Luzern",
    "sg:tags":[
        "textile",
        "clothing"
    ],
    "wof:name":"Robert Halter Ag",
    "wof:placetype":"venue"
},
  "geometry": {"coordinates":[9.3380699158,47.4144668579],"type":"Point"}
}