{
  "type": "Feature",
  "properties": {
    "iso:country":"CH",
    "sg:address":"Route D'eclagnens",
    "sg:city":"Goumoens-la-ville",
    "sg:orig_category":"Vermittlung von Immobilien",
    "sg:phone":"+41 21 881 50 92",
    "sg:postcode":"1376",
    "sg:province":"Vaud",
    "wof:name":"Bernard & Danielle Buchs Agence Immobili\u00e8re",
    "wof:placetype":"venue"
},
  "geometry": {"coordinates":[6.5909199715,46.6511497498],"type":"Point"}
}