{
  "type": "Feature",
  "properties": {
    "iso:country":"CH",
    "sg:address":"Via Trevano 8",
    "sg:city":"Lugano",
    "sg:orig_category":"Architekturb\u00fcros",
    "sg:phone":"+41 91 922 77 27",
    "sg:postcode":"6900",
    "sg:province":"Ticino",
    "wof:name":"Dott.gianfranco Rossi Studio D'architettura",
    "wof:placetype":"venue"
},
  "geometry": {"coordinates":[8.955318,46.013817],"type":"Point"}
}