{
  "type": "Feature",
  "properties": {
    "iso:country":"CH",
    "sg:address":"Im Moos",
    "sg:city":"Walkringen",
    "sg:orig_category":"Autolackierereien Autospenglereien",
    "sg:phone":"+41 31 701 10 78",
    "sg:postcode":"3512",
    "sg:province":"Bern",
    "wof:name":"Andreas Jost Carrosserie & Spritzwerk",
    "wof:placetype":"venue"
},
  "geometry": {"coordinates":[7.59942,46.937454],"type":"Point"}
}