{
  "type": "Feature",
  "properties": {
    "iso:country":"CH",
    "sg:address":"Route De Sous-moulin 39 1226 Th\u00f4nex. Postfach",
    "sg:city":"Th\u00f4nex",
    "sg:orig_category":"Tankstellen",
    "sg:postcode":"1226",
    "sg:province":"Gen\u00e8ve",
    "wof:name":"Narka Sa",
    "wof:placetype":"venue"
},
  "geometry": {"coordinates":[6.1919708252,46.1895217896],"type":"Point"}
}