{
  "type": "Feature",
  "properties": {
    "iso:country":"CH",
    "sg:address":"Hauptstrasse 23",
    "sg:city":"St\u00fcsslingen",
    "sg:orig_category":"Instandhaltung U Reparatur von Automobilen",
    "sg:phone":"+41 32 351 12 10",
    "sg:postcode":"4655",
    "sg:province":"Solothurn",
    "wof:name":"Garage K\u00e4sermann, Vw, Audi, Porsche",
    "wof:placetype":"venue"
},
  "geometry": {"coordinates":[7.3742251396,47.1393737793],"type":"Point"}
}