{
  "type": "Feature",
  "properties": {
    "iso:country":"CH",
    "sg:address":"Ekkehardsteig 3",
    "sg:city":"Z\u00fcrich",
    "sg:orig_category":"Arztpraxen",
    "sg:phone":"+41 13618716",
    "sg:postcode":"8006",
    "sg:province":"Z\u00fcrich",
    "wof:name":"Dr.med.heinz Stefan Herzka Spezialarzt Fmh",
    "wof:placetype":"venue"
},
  "geometry": {"coordinates":[8.543913,47.386063],"type":"Point"}
}