{
  "type": "Feature",
  "properties": {
    "addr:full":"Casa Tschess Falera Graubunden 7153",
    "addr:postcode":"7153",
    "iso:country":"CH",
    "sg:address":"Casa Tschess",
    "sg:city":"Falera",
    "sg:orig_category":"Datenverarbeitungsdienste Sonstige mit der Informatik verbundene T\u00e4tigkeiten",
    "sg:phone":"+41 81 921 35 25",
    "sg:postcode":"7153",
    "sg:province":"Graubunden",
    "wof:name":"Z\u00f6llner Martin",
    "wof:placetype":"venue"
},
  "geometry": {"coordinates":[9.231528,46.800781],"type":"Point"}
}