{
  "type": "Feature",
  "properties": {
    "addr:full":"Oberdorf 96 Beggingen Schaffhausen 8228",
    "addr:housenumber":"96",
    "addr:postcode":"8228",
    "addr:street":"Oberdorf",
    "iso:country":"CH",
    "sg:address":"Oberdorf 96",
    "sg:city":"Beggingen",
    "sg:orig_category":"Allgemeiner Hoch U Tiefbau",
    "sg:phone":"+41 71 654 60 10",
    "sg:postcode":"8228",
    "sg:province":"Schaffhausen",
    "wof:name":"Wanzenried Bau Ag",
    "wof:placetype":"venue"
},
  "geometry": {"coordinates":[9.138185,47.566669],"type":"Point"}
}