{
  "type": "Feature",
  "properties": {
    "iso:country":"CH",
    "sg:address":"Florastrasse 28",
    "sg:city":"Uster",
    "sg:classifiers":[
        {
            "category":"Professional",
            "subcategory":"Employment Agencies",
            "type":"Services"
        }
    ],
    "sg:postcode":"8610",
    "sg:province":"Z\u00fcrich",
    "sg:tags":[
        "personal",
        "u",
        "stellenvermittlung"
    ],
    "wof:name":"Uniforce Personal, Ramel M.",
    "wof:placetype":"venue"
},
  "geometry": {"coordinates":[8.7224187851,47.3468856812],"type":"Point"}
}