{
  "type": "Feature",
  "properties": {
    "iso:country":"CH",
    "sg:address":"B\u00fcrenweg 7",
    "sg:city":"Gempen",
    "sg:orig_category":"Vermittlung U Verwaltung von Immobilien Wirtschaftspr\u00fcfung, Steuerberatung U Treuhand",
    "sg:phone":"+41 61 701 29 56",
    "sg:postcode":"4145",
    "sg:province":"Solothurn",
    "wof:name":"Meier Rudolf Treuhand",
    "wof:placetype":"venue"
},
  "geometry": {"coordinates":[7.6615858078,47.4744491577],"type":"Point"}
}