{
  "type": "Feature",
  "properties": {
    "iso:country":"CH",
    "sg:address":"Viale Stefano Franscini 8",
    "sg:city":"Lugano",
    "sg:orig_category":"Unclassifiable Establishments",
    "sg:postcode":"6900",
    "sg:province":"Ticino",
    "wof:name":"Emme Haustechnik Gmbh",
    "wof:placetype":"venue"
},
  "geometry": {"coordinates":[7.6784548759,47.0036315918],"type":"Point"}
}