{
  "type": "Feature",
  "properties": {
    "iso:country":"CH",
    "sg:address":"Quaderstrasse 17",
    "sg:city":"Chur",
    "sg:orig_category":"Fernmeldedienste",
    "sg:phone":"+41 81 641 17 37",
    "sg:postcode":"7000",
    "sg:province":"Graubunden",
    "wof:name":"Tele-r\u00e4tia Ag",
    "wof:placetype":"venue"
},
  "geometry": {"coordinates":[9.533115387,46.8525161743],"type":"Point"}
}