{
  "type": "Feature",
  "properties": {
    "iso:country":"CH",
    "sg:address":"Junkerngasse 22",
    "sg:city":"Bern",
    "sg:orig_category":"Korrespondenz U Nachrichtenb\u00fcros",
    "sg:phone":"+41 31 382 71 12",
    "sg:postcode":"3011",
    "sg:province":"Bern",
    "wof:name":"Presseb\u00fcro Baumann Journalismus, Public-relations, Kommunikation",
    "wof:placetype":"venue"
},
  "geometry": {"coordinates":[7.4545459747,46.9479675293],"type":"Point"}
}