{
  "type": "Feature",
  "properties": {
    "iso:country":"CH",
    "sg:address":"Kirchgasse 13",
    "sg:city":"Rorbas",
    "sg:classifiers":[
        {
            "category":"Restaurant",
            "type":"Food & Drink"
        }
    ],
    "sg:phone":"+41 18650247",
    "sg:postcode":"8427",
    "sg:province":"Z\u00fcrich",
    "wof:name":"Restaurant Traube",
    "wof:placetype":"venue"
},
  "geometry": {"coordinates":[8.5779953003,47.5297203064],"type":"Point"}
}