{
  "type": "Feature",
  "properties": {
    "iso:country":"CH",
    "sg:address":"Ebnetrain 8",
    "sg:city":"Meggen",
    "sg:orig_category":"Non-Classified Establishments",
    "sg:postcode":"6045",
    "sg:province":"Luzern",
    "wof:name":"Environmental Consulting Prof. Dr. Rolf-dieter Henkler",
    "wof:placetype":"venue"
},
  "geometry": {"coordinates":[8.3652057648,47.0470581055],"type":"Point"}
}