{
  "type": "Feature",
  "properties": {
    "iso:country":"CH",
    "sg:address":"Bahnhofstrasse 16",
    "sg:city":"Uster",
    "sg:orig_category":"Detailhandel mit Uhren U Schmuck Fachdetailhandel in Verkaufsr\u00e4umen",
    "sg:phone":"+41 19401647",
    "sg:postcode":"8610",
    "sg:province":"Z\u00fcrich",
    "wof:name":"Theiler Markus",
    "wof:placetype":"venue"
},
  "geometry": {"coordinates":[8.7181911469,47.3487205505],"type":"Point"}
}