{
  "type": "Feature",
  "properties": {
    "iso:country":"CH",
    "sg:address":"Sch\u00f6nenhofstrasse 13 8500 Frauenfeld. Postfach 2151",
    "sg:city":"Frauenfeld",
    "sg:orig_category":"Instandhaltung U Reparatur von Automobilen",
    "sg:phone":"+41 52 720 49 90",
    "sg:postcode":"8500",
    "sg:province":"Thurgau",
    "wof:name":"S\u00fcsstrunk Martin, Ms Automobile",
    "wof:placetype":"venue"
},
  "geometry": {"coordinates":[8.8721971512,47.5528640747],"type":"Point"}
}