{
  "type": "Feature",
  "properties": {
    "addr:full":"Chemin Forge Ollon Vaud 1867",
    "addr:postcode":"1867",
    "addr:street":"Chemin Forge",
    "iso:country":"CH",
    "sg:address":"Chemin Forge",
    "sg:city":"Ollon",
    "sg:classifiers":[
        {
            "category":"Banks & Credit Unions",
            "subcategory":"Bank",
            "type":"Services"
        }
    ],
    "sg:phone":"+41 25391131",
    "sg:postcode":"1867",
    "sg:province":"Vaud",
    "wof:name":"Banque Raiffeisen D'ollon",
    "wof:placetype":"venue"
},
  "geometry": {"coordinates":[6.995725,46.29723],"type":"Point"}
}