{
  "type": "Feature",
  "properties": {
    "iso:country":"CH",
    "sg:address":"Grand-rue 6",
    "sg:city":"Ch\u00e2telard-lutry",
    "sg:orig_category":"Elektroinstallation",
    "sg:postcode":"1095",
    "sg:province":"Vaud",
    "wof:name":"Rudaz J.-j. Electricit\u00e9-t\u00e9l\u00e9phone",
    "wof:placetype":"venue"
},
  "geometry": {"coordinates":[6.6837191582,46.5026702881],"type":"Point"}
}