{
  "type": "Feature",
  "properties": {
    "iso:country":"CH",
    "sg:address":"Steinm\u00e4ttelistrasse 24",
    "sg:city":"Meiringen",
    "sg:orig_category":"Bauschreinerei Herstellung von Konstruktionsteilen, Fertigbauteilen U Ausbauelementen aus Holz",
    "sg:postcode":"3860",
    "sg:province":"Bern",
    "wof:name":"Klein Andreas",
    "wof:placetype":"venue"
},
  "geometry": {"coordinates":[8.19436,46.725056],"type":"Point"}
}