{
  "type": "Feature",
  "properties": {
    "iso:country":"CH",
    "sg:address":"Badenerstrasse 503",
    "sg:city":"Z\u00fcrich",
    "sg:orig_category":"Erwachsenenbildung U Unterricht",
    "sg:phone":"+41 14921878",
    "sg:postcode":"8048",
    "sg:province":"Z\u00fcrich",
    "wof:name":"Musikhaus + Musikschule, H. Schweizer, Inh. Daniel Gross Musikinstrumente; Handel; Musikschule.",
    "wof:placetype":"venue"
},
  "geometry": {"coordinates":[8.5028476715,47.3813972473],"type":"Point"}
}