{
  "type": "Feature",
  "properties": {
    "iso:country":"CH",
    "sg:address":"Via Morbio 13",
    "sg:city":"Vezia",
    "sg:orig_category":"Herstellung von K\u00fcchenm\u00f6beln",
    "sg:phone":"+41 91 966 37 41",
    "sg:postcode":"6943",
    "sg:province":"Ticino",
    "wof:name":"Andrea Sch\u00fcpbach Cucine & Restauri",
    "wof:placetype":"venue"
},
  "geometry": {"coordinates":[8.936126709,46.0196495056],"type":"Point"}
}