{
  "type": "Feature",
  "properties": {
    "iso:country":"CH",
    "sg:address":"Rue De L'eglise 14",
    "sg:city":"Porrentruy",
    "sg:orig_category":"Herstellung von nachrichtentechnischen Ger\u00e4ten U Einrichtungen",
    "sg:phone":"+41 32 466 14 22",
    "sg:postcode":"2900",
    "sg:province":"Jura",
    "wof:name":"Choulat, Didier",
    "wof:placetype":"venue"
},
  "geometry": {"coordinates":[7.0757799149,47.4162750244],"type":"Point"}
}