{
  "type": "Feature",
  "properties": {
    "iso:country":"CH",
    "sg:address":"Ziegelgutstrasse 18",
    "sg:city":"Oberburg",
    "sg:orig_category":"Detailhandel mit Waren verschiedener Art in Verkaufsr\u00e4umen Fachdetailhandel mit Nahrungsmitteln, Get",
    "sg:phone":"+41 34 423 21 07",
    "sg:postcode":"3414",
    "sg:province":"Bern",
    "wof:name":"Otto's Ag",
    "wof:placetype":"venue"
},
  "geometry": {"coordinates":[7.6329798698,47.0284805298],"type":"Point"}
}