{
  "type": "Feature",
  "properties": {
    "iso:country":"CH",
    "sg:address":"Cerisiers Route Des 2 1752 Villars-sur-gl\u00e2ne Case Postale 56",
    "sg:city":"Villars-sur-gl\u00e2ne",
    "sg:orig_category":"Fachdetailhandel in Verkaufsr\u00e4umen",
    "sg:phone":"+41 26 400 02 80",
    "sg:postcode":"1752",
    "sg:province":"Fribourg",
    "wof:name":"Floraline S\u00e0rl",
    "wof:placetype":"venue"
},
  "geometry": {"coordinates":[7.115032196,46.7945899963],"type":"Point"}
}