{
  "type": "Feature",
  "properties": {
    "iso:country":"CH",
    "sg:address":"Sch\u00f6neggstrasse 5 9400 Rorschach. Postfach",
    "sg:city":"Rorschacherberg",
    "sg:orig_category":"Sonstige mit Sport verbundene T\u00e4tigkeiten",
    "sg:phone":"+41 71 855 38 52",
    "sg:postcode":"9404",
    "sg:province":"St. Gallen",
    "wof:name":"Yoga-schule Heim Rolf Gmbh",
    "wof:placetype":"venue"
},
  "geometry": {"coordinates":[9.4952001572,47.4779396057],"type":"Point"}
}