{
  "type": "Feature",
  "properties": {
    "iso:country":"CH",
    "sg:address":"Sulzbergstrasse 22",
    "sg:city":"Wettingen",
    "sg:orig_category":"Sonstige pers\u00f6nliche Dienstleistungen",
    "sg:postcode":"5430",
    "sg:province":"Aargau",
    "wof:name":"Foxroad (suisse) S\u00e0rl Biens Mobiliers, Dettes, Actions Etc.; Acquisition. Syst\u00e8mes De Software; \u00e9tude, Formation, Installation",
    "wof:placetype":"venue"
},
  "geometry": {"coordinates":[6.1414251328,46.1833114624],"type":"Point"}
}