{
  "type": "Feature",
  "properties": {
    "iso:country":"CH",
    "sg:address":"Pilatusstrasse 50 6052 Hergiswil Nw. Postfach",
    "sg:city":"Luzern",
    "sg:orig_category":"Vermietung U Verpachtung von eigenen Immobilien",
    "sg:postcode":"6003",
    "sg:province":"Luzern",
    "wof:name":"Haton Immobilien Ag Immobilien; Kauf, Verkauf, Verwaltung",
    "wof:placetype":"venue"
},
  "geometry": {"coordinates":[8.308216095,46.9925575256],"type":"Point"}
}