{
  "type": "Feature",
  "properties": {
    "iso:country":"CH",
    "sg:address":"Baumgartenstrasse 28",
    "sg:city":"Langenthal",
    "sg:orig_category":"G\u00fcterbef\u00f6rderung im Strassenverkehr",
    "sg:phone":"+41 62 922 98 66",
    "sg:postcode":"4900",
    "sg:province":"Bern",
    "wof:name":"Annemarie Oehrli Tg Langenthal Int.transporte",
    "wof:placetype":"venue"
},
  "geometry": {"coordinates":[7.7941980362,47.2036399841],"type":"Point"}
}