{
  "type": "Feature",
  "properties": {
    "iso:country":"CH",
    "sg:address":"Rue Du Nord 11",
    "sg:city":"Gland",
    "sg:orig_category":"RESTAURANTS: TEA-ROOMS",
    "sg:postcode":"1196",
    "sg:province":"Vaud",
    "wof:name":"Lude-ronchi Rose-marie",
    "wof:placetype":"venue"
},
  "geometry": {"coordinates":[6.2641391754,46.425037384],"type":"Point"}
}