{
  "type": "Feature",
  "properties": {
    "addr:full":"Monbijoustrasse 74 Bern Bern 3005",
    "addr:housenumber":"74",
    "addr:postcode":"3005",
    "addr:street":"Monbijoustrasse",
    "iso:country":"CH",
    "sg:address":"Monbijoustrasse 74",
    "sg:city":"Bern",
    "sg:orig_category":"Datenverarbeitungsdienste",
    "sg:phone":"+41 22 789 45 77",
    "sg:postcode":"3005",
    "sg:province":"Bern",
    "wof:name":"Burinfor Sa Services En Informatique",
    "wof:placetype":"venue"
},
  "geometry": {"coordinates":[6.136655,46.179714],"type":"Point"}
}