{
  "type": "Feature",
  "properties": {
    "iso:country":"CH",
    "sg:address":"Hauptstr. 16",
    "sg:city":"Riedern",
    "sg:classifiers":[
        {
            "category":"Home & Garden",
            "subcategory":"Furniture",
            "type":"Retail Goods"
        }
    ],
    "sg:phone":"+41 55 640 18 20",
    "sg:postcode":"8750",
    "sg:province":"Glarus",
    "sg:tags":[
        "wood"
    ],
    "wof:name":"Robert Bernold",
    "wof:placetype":"venue"
},
  "geometry": {"coordinates":[9.0530042648,47.0490074158],"type":"Point"}
}