{
  "type": "Feature",
  "properties": {
    "iso:country":"CH",
    "sg:address":"Rue Des Moulins 11",
    "sg:city":"Neuch\u00e2tel",
    "sg:orig_category":"Detailhandel mit Getr\u00e4nken",
    "sg:phone":"+41 32 725 32 52",
    "sg:postcode":"2000",
    "sg:province":"Neuch\u00e2tel",
    "wof:name":"Au Cep D'or, Cortina A. Vins Indig\u00e8nes Ou \u00e9trangers, Liqueurs Etc.; Achat, Vente",
    "wof:placetype":"venue"
},
  "geometry": {"coordinates":[6.9282331467,46.9920463562],"type":"Point"}
}