{
  "type": "Feature",
  "properties": {
    "iso:country":"CH",
    "sg:address":"Avenue De La Gare 24",
    "sg:city":"Martigny",
    "sg:orig_category":"Glaserei",
    "sg:phone":"+41 27 722 21 45",
    "sg:postcode":"1920",
    "sg:province":"Valais",
    "wof:name":"Gualino Vitrerie Couleurs - Encadrements",
    "wof:placetype":"venue"
},
  "geometry": {"coordinates":[7.075401,46.102997],"type":"Point"}
}