{
  "type": "Feature",
  "properties": {
    "iso:country":"CH",
    "sg:address":"Zone Artisanale Du Verney 1070 Puidoux Case Postale 3",
    "sg:city":"Puidoux",
    "sg:orig_category":"Herstellung von Bergwerks U Baumaschinen",
    "sg:phone":"+41 21 946 34 41",
    "sg:postcode":"1070",
    "sg:province":"Vaud",
    "wof:name":"Christ Ag",
    "wof:placetype":"venue"
},
  "geometry": {"coordinates":[6.7827601433,46.5020484924],"type":"Point"}
}