{
  "type": "Feature",
  "properties": {
    "iso:country":"CH",
    "sg:address":"Grabenring 6 4123 Allschwil. Postfach 101",
    "sg:city":"Allschwil",
    "sg:orig_category":"Architekturb\u00fcros",
    "sg:phone":"+41 61 481 46 46",
    "sg:postcode":"4123",
    "sg:province":"Basel-Landschaft",
    "wof:name":"Henri N\u00e4f Architekturb\u00fcro",
    "wof:placetype":"venue"
},
  "geometry": {"coordinates":[7.542987,47.553486],"type":"Point"}
}