{
  "type": "Feature",
  "properties": {
    "iso:country":"CH",
    "sg:address":"Visano Via 6",
    "sg:city":"Breganzona",
    "sg:orig_category":"Non-Classified Establishments",
    "sg:phone":"+41 91 967 14 24",
    "sg:postcode":"6932",
    "sg:province":"Ticino",
    "wof:name":"Gionic Holding Sa",
    "wof:placetype":"venue"
},
  "geometry": {"coordinates":[8.9274635315,46.0015487671],"type":"Point"}
}