{
  "type": "Feature",
  "properties": {
    "iso:country":"CH",
    "sg:address":"Beckenriederstrasse 5",
    "sg:city":"Buochs",
    "sg:orig_category":"Detailhandel mit Milcherzeugnissen U Eiern Sonstiger Fachdetailhandel mit Nahrungsmitteln, Getr\u00e4nken",
    "sg:phone":"+41 41 760 06 09",
    "sg:postcode":"6374",
    "sg:province":"Nidwalden",
    "wof:name":"Ch\u00e4s-laube R\u00f6lli Gmbh",
    "wof:placetype":"venue"
},
  "geometry": {"coordinates":[8.4211626053,46.9737586975],"type":"Point"}
}