{
  "type": "Feature",
  "properties": {
    "iso:country":"CH",
    "sg:address":"Viktoriastrasse 14 8057 Z\u00fcrich. Postfach",
    "sg:city":"Z\u00fcrich",
    "sg:orig_category":"Betrieb U technische Hilfsdienste des Kultur U Unterhaltungswesens",
    "sg:phone":"+41 13117050",
    "sg:postcode":"8057",
    "sg:province":"Z\u00fcrich",
    "wof:name":"Tcb, Lindroos Bj\u00f6rn",
    "wof:placetype":"venue"
},
  "geometry": {"coordinates":[8.550627,47.402679],"type":"Point"}
}