{
  "type": "Feature",
  "properties": {
    "iso:country":"CH",
    "sg:address":"Hauptstrasse 35",
    "sg:city":"Waldenburg",
    "sg:orig_category":"Herstellung von Schrauben, Nieten, Ketten U Federn Mechanische Werkst\u00e4tten",
    "sg:phone":"+41 32 652 95 22",
    "sg:postcode":"4437",
    "sg:province":"Basel-Landschaft",
    "wof:name":"Tschui Philippo Ag",
    "wof:placetype":"venue"
},
  "geometry": {"coordinates":[7.4036288261,47.1877288818],"type":"Point"}
}