{
  "type": "Feature",
  "properties": {
    "addr:full":"Dornacherstrasse 10 Olten Solothurn 4600",
    "addr:housenumber":"10",
    "addr:postcode":"4600",
    "addr:street":"Dornacherstrasse",
    "iso:country":"CH",
    "sg:address":"Dornacherstrasse 10",
    "sg:city":"Olten",
    "sg:orig_category":"Architektur U Ingenieurb\u00fcros",
    "sg:phone":"+41 62 212 12 88",
    "sg:postcode":"4600",
    "sg:province":"Solothurn",
    "wof:name":"Buser, Gloor Und Partner Ag",
    "wof:placetype":"venue"
},
  "geometry": {"coordinates":[7.901519,47.351746],"type":"Point"}
}