{
  "type": "Feature",
  "properties": {
    "iso:country":"CH",
    "sg:address":"Gare Avenue De La 20 1003 Lausanne. Postfach",
    "sg:city":"Lausanne",
    "sg:orig_category":"Vermietung U Verpachtung von eigenen Immobilien",
    "sg:postcode":"1003",
    "sg:province":"Vaud",
    "wof:name":"Gebau Immobilien Gmbh",
    "wof:placetype":"venue"
},
  "geometry": {"coordinates":[8.3050146103,46.9951477051],"type":"Point"}
}