{
  "type": "Feature",
  "properties": {
    "iso:country":"CH",
    "sg:address":"Via Cattori 4 6600 Locarno. Postfach",
    "sg:city":"Locarno",
    "sg:classifiers":[
        {
            "category":"Restaurant",
            "type":"Food & Drink"
        }
    ],
    "sg:phone":"+41 91 943 14 64",
    "sg:postcode":"6601",
    "sg:province":"Ticino",
    "wof:name":"Osteria Vannini",
    "wof:placetype":"venue"
},
  "geometry": {"coordinates":[9.0045003891,46.0516586304],"type":"Point"}
}