{
  "type": "Feature",
  "properties": {
    "iso:country":"CH",
    "sg:address":"Neue Jonastrasse 79",
    "sg:city":"Rapperswil",
    "sg:classifiers":[
        {
            "category":"Professional",
            "subcategory":"Computer Services",
            "type":"Services"
        }
    ],
    "sg:phone":"+41 81 422 10 06",
    "sg:postcode":"8640",
    "sg:province":"Schwyz",
    "sg:tags":[
        "development",
        "software"
    ],
    "wof:name":"C Development Ag",
    "wof:placetype":"venue"
},
  "geometry": {"coordinates":[9.8754816055,46.8837432861],"type":"Point"}
}