{
  "type": "Feature",
  "properties": {
    "iso:country":"CH",
    "sg:address":"Hardstr. 22",
    "sg:city":"Bassersdorf",
    "sg:classifiers":[
        {
            "category":"Transit Center",
            "subcategory":"Freight",
            "type":"Transportation"
        }
    ],
    "sg:phone":"+41 4118364747",
    "sg:postcode":"8303",
    "sg:province":"Z\u00fcrich",
    "sg:tags":[
        "metallurgy",
        "pipe",
        "metalworking",
        "sheet"
    ],
    "wof:name":"Emil Hitz Ag",
    "wof:placetype":"venue"
},
  "geometry": {"coordinates":[8.6237249374,47.4381141663],"type":"Point"}
}