{
  "type": "Feature",
  "properties": {
    "iso:country":"CH",
    "sg:address":"Boden",
    "sg:city":"Kiental",
    "sg:orig_category":"S\u00e4gewerke",
    "sg:phone":"+41 33 676 12 35",
    "sg:postcode":"3723",
    "sg:province":"Bern",
    "wof:name":"Stephan M\u00fcrner S\u00e4gerei",
    "wof:placetype":"venue"
},
  "geometry": {"coordinates":[7.7233409882,46.587978363],"type":"Point"}
}