{
  "type": "Feature",
  "properties": {
    "iso:country":"CH",
    "sg:address":"Unterfeldstrasse 4",
    "sg:city":"Gr\u00e4nichen",
    "sg:orig_category":"MANUFACTURERS: COMPONENTS FOR PACKAGING MACHINERY",
    "sg:phone":"+41 62 842 12 66",
    "sg:postcode":"5722",
    "sg:province":"Aargau",
    "wof:name":"Vapack",
    "wof:placetype":"venue"
},
  "geometry": {"coordinates":[8.0922117233,47.3622436523],"type":"Point"}
}