{
  "type": "Feature",
  "properties": {
    "iso:country":"CH",
    "sg:address":"Feldstrasse 46",
    "sg:city":"Herrliberg",
    "sg:orig_category":"Herstellung von M\u00fcnzen U Medaillen",
    "sg:phone":"+41 19916736",
    "sg:postcode":"8704",
    "sg:province":"Z\u00fcrich",
    "wof:name":"Unico Studentenartikel, Stephan Nyfeler",
    "wof:placetype":"venue"
},
  "geometry": {"coordinates":[8.6089801788,47.2952842712],"type":"Point"}
}