{
  "type": "Feature",
  "properties": {
    "iso:country":"CH",
    "sg:address":"Frankfurt-strasse 60 4142 M\u00fcnchenstein. Postfach",
    "sg:city":"Basel",
    "sg:orig_category":"Herstellung von Kunststoffwaren Herstellung von Rohren",
    "sg:phone":"+41 61 331 55 55",
    "sg:postcode":"4002",
    "sg:province":"Basel-Stadt",
    "wof:name":"Arfa R\u00f6hrenwerke Ag",
    "wof:placetype":"venue"
},
  "geometry": {"coordinates":[7.6081600189,47.5293502808],"type":"Point"}
}