{
  "type": "Feature",
  "properties": {
    "iso:country":"CH",
    "sg:address":"Via Vignascia",
    "sg:city":"Minusio",
    "sg:orig_category":"Bezirks, Sekundar, Realschulen, Oberstufe der Primarschulen",
    "sg:phone":"+41 91 743 71 55",
    "sg:postcode":"6648",
    "sg:province":"Ticino",
    "wof:name":"Scuola Media Di Minusio",
    "wof:placetype":"venue"
},
  "geometry": {"coordinates":[8.824202,46.176693],"type":"Point"}
}