{
  "type": "Feature",
  "properties": {
    "iso:country":"CH",
    "sg:address":"Chemin Des Bosons 1 1000 Lausanne. Postfach",
    "sg:city":"Lausanne",
    "sg:orig_category":"Sonstige mit der Informatik verbundene T\u00e4tigkeiten",
    "sg:postcode":"1002",
    "sg:province":"Vaud",
    "wof:name":"Rhodanie Syst\u00e8mes Et R\u00e9seaux S. \u00e0 R.l",
    "wof:placetype":"venue"
},
  "geometry": {"coordinates":[6.6947751045,46.5545883179],"type":"Point"}
}