{
  "type": "Feature",
  "properties": {
    "iso:country":"CH",
    "sg:address":"Eglise Rue De L' 1",
    "sg:city":"Martigny",
    "sg:orig_category":"Unclassifiable Establishments",
    "sg:postcode":"1920",
    "sg:province":"Valais",
    "wof:name":"Funfish Ag",
    "wof:placetype":"venue"
},
  "geometry": {"coordinates":[8.8675823212,47.2674026489],"type":"Point"}
}