{
  "type": "Feature",
  "properties": {
    "iso:country":"CH",
    "sg:address":"Vorstadt 13a",
    "sg:city":"Willisau",
    "sg:orig_category":"Kauf U Verkauf von Immobilien auf eigene Rechnung",
    "sg:postcode":"6130",
    "sg:province":"Luzern",
    "wof:name":"Ast Immobilien + Handels Ag",
    "wof:placetype":"venue"
},
  "geometry": {"coordinates":[7.995238781,47.1209640503],"type":"Point"}
}