{
  "type": "Feature",
  "properties": {
    "iso:country":"CH",
    "sg:address":"Dorfstr. 11",
    "sg:city":"Aesch",
    "sg:orig_category":"Erschliessung von Grundst\u00fccken",
    "sg:postcode":"8904",
    "sg:province":"Z\u00fcrich",
    "wof:name":"Eigenbaugenossenschaft Halde.",
    "wof:placetype":"venue"
},
  "geometry": {"coordinates":[8.4382486343,47.3369026184],"type":"Point"}
}