{
  "type": "Feature",
  "properties": {
    "iso:country":"CH",
    "sg:address":"Weinbergstrasse 24",
    "sg:city":"Z\u00fcrich",
    "sg:orig_category":"Sonstige Aktivit\u00e4ten der nicht-\u00e4rztlichen Medizinalberufe",
    "sg:phone":"+41 17863777",
    "sg:postcode":"8001",
    "sg:province":"Z\u00fcrich",
    "wof:name":"Dr.med.robert Pernod Akupunkturpraxis",
    "wof:placetype":"venue"
},
  "geometry": {"coordinates":[8.7341480255,47.1973953247],"type":"Point"}
}