{
  "type": "Feature",
  "properties": {
    "iso:country":"CH",
    "sg:address":"Rosenstrasse 28 3800 Interlaken. Postfach 103",
    "sg:city":"Interlaken",
    "sg:orig_category":"Sanit\u00e4r, Heizungs U L\u00fcftungsinstallation Sanit\u00e4rinstallation",
    "sg:phone":"+41 33 822 88 77",
    "sg:postcode":"3800",
    "sg:province":"Bern",
    "wof:name":"Fischer Haustechnik Ag",
    "wof:placetype":"venue"
},
  "geometry": {"coordinates":[7.8551301956,46.6836051941],"type":"Point"}
}