{
  "type": "Feature",
  "properties": {
    "iso:country":"CH",
    "sg:address":"Sch\u00f6nb\u00fchl 689",
    "sg:city":"Luzern",
    "sg:orig_category":"Vermietung U Verpachtung von eigenen Immobilien",
    "sg:phone":"+41 41 360 88 66",
    "sg:postcode":"6005",
    "sg:province":"Luzern",
    "wof:name":"Sch\u00f6nb\u00fchl Immobilien Ag Luzern",
    "wof:placetype":"venue"
},
  "geometry": {"coordinates":[8.3305263519,47.0393486023],"type":"Point"}
}