{
  "type": "Feature",
  "properties": {
    "iso:country":"CH",
    "sg:address":"Alpinitstrasse 5b",
    "sg:city":"Sarmenstorf",
    "sg:orig_category":"Kosmetikinstitute",
    "sg:phone":"+41 56 667 08 30",
    "sg:postcode":"5614",
    "sg:province":"Aargau",
    "wof:name":"Sylvia Hubschmid Kosmetikinstitut",
    "wof:placetype":"venue"
},
  "geometry": {"coordinates":[8.2482919693,47.3106498718],"type":"Point"}
}