{
  "type": "Feature",
  "properties": {
    "addr:full":"Bahnhofstr. 9 Subingen Solothurn 4553",
    "addr:housenumber":"9",
    "addr:postcode":"4553",
    "addr:street":"Bahnhofstr.",
    "iso:country":"CH",
    "sg:address":"Bahnhofstr. 9",
    "sg:city":"Subingen",
    "sg:classifiers":[
        {
            "category":"Banks & Credit Unions",
            "subcategory":"Bank",
            "type":"Services"
        }
    ],
    "sg:phone":"+41 32 614 24 57",
    "sg:postcode":"4553",
    "sg:province":"Solothurn",
    "wof:name":"Raiffeisenbank",
    "wof:placetype":"venue"
},
  "geometry": {"coordinates":[7.613579,47.194408],"type":"Point"}
}