{
  "type": "Feature",
  "properties": {
    "iso:country":"CH",
    "sg:address":"6370 Stans. Postfach 1068",
    "sg:city":"Stans",
    "sg:orig_category":"Interessenvertretungen U sonstige Vereinigungen Sportvereine",
    "sg:phone":"+41 33 244 61 61",
    "sg:postcode":"6370",
    "sg:province":"Nidwalden",
    "wof:name":"Internat.ski-verband",
    "wof:placetype":"venue"
},
  "geometry": {"coordinates":[7.6728010178,46.7296447754],"type":"Point"}
}