{
  "type": "Feature",
  "properties": {
    "iso:country":"CH",
    "sg:address":"Gartenstrasse 13 4127 Birsfelden. Postfach 163",
    "sg:city":"Birsfelden",
    "sg:orig_category":"Herstellung von Wellpapier U pappe sowie von Verpackungsmitteln aus Papier, Karton U Pappe Offsetdru",
    "sg:phone":"+41 61 312 52 79",
    "sg:postcode":"4127",
    "sg:province":"Basel-Landschaft",
    "wof:name":"S. B\u00fcrgin Druck Und Verpackungs Ag",
    "wof:placetype":"venue"
},
  "geometry": {"coordinates":[7.6214270592,47.555015564],"type":"Point"}
}