{
  "type": "Feature",
  "properties": {
    "iso:country":"CH",
    "sg:address":"Trubstrasse 1",
    "sg:city":"Trubschachen",
    "sg:classifiers":[
        {
            "category":"Restaurant",
            "type":"Food & Drink"
        }
    ],
    "sg:phone":"+41 34 495 51 08",
    "sg:postcode":"3555",
    "sg:province":"Bern",
    "wof:name":"Restaurant Zum B\u00e4ren",
    "wof:placetype":"venue"
},
  "geometry": {"coordinates":[7.8446888924,46.9234924316],"type":"Point"}
}