{
  "type": "Feature",
  "properties": {
    "addr:full":"Schulstrasse 2 Magden Aargau 4312",
    "addr:housenumber":"2",
    "addr:postcode":"4312",
    "addr:street":"Schulstrasse",
    "iso:country":"CH",
    "sg:address":"Schulstrasse 2",
    "sg:city":"Magden",
    "sg:orig_category":"B\u00e4ckereien Konditoreien",
    "sg:postcode":"4312",
    "sg:province":"Aargau",
    "wof:name":"Christoph Dennler B\u00e4ckerei-konditorei Brotlaube",
    "wof:placetype":"venue"
},
  "geometry": {"coordinates":[7.813777,47.527332],"type":"Point"}
}