{
  "type": "Feature",
  "properties": {
    "iso:country":"CH",
    "sg:address":"Gottardo Via San 58b",
    "sg:city":"Bellinzona",
    "sg:orig_category":"Kauf U Verkauf von Immobilien auf eigene Rechnung",
    "sg:postcode":"6500",
    "sg:province":"Ticino",
    "wof:name":"Si Muroman Sa",
    "wof:placetype":"venue"
},
  "geometry": {"coordinates":[9.033408165,46.2016487122],"type":"Point"}
}