{
  "type": "Feature",
  "properties": {
    "iso:country":"CH",
    "sg:address":"Badweg 5",
    "sg:city":"Biglen",
    "sg:orig_category":"Sportvereine Unihockey",
    "sg:phone":"+41 31 701 39 03",
    "sg:postcode":"3507",
    "sg:province":"Bern",
    "wof:name":"Uht Arni",
    "wof:placetype":"venue"
},
  "geometry": {"coordinates":[7.6221528053,46.9258537292],"type":"Point"}
}