{
  "type": "Feature",
  "properties": {
    "iso:country":"CH",
    "sg:address":"Alte Simplonstrasse 26",
    "sg:city":"Brig",
    "sg:orig_category":"Interessenvertretungen",
    "sg:postcode":"3900",
    "sg:province":"Valais",
    "wof:name":"Stiftung Kiwanis-club Oberwallis",
    "wof:placetype":"venue"
},
  "geometry": {"coordinates":[7.9903922081,46.3154945374],"type":"Point"}
}