{
  "type": "Feature",
  "properties": {
    "iso:country":"CH",
    "sg:address":"Bahnhofstrasse 14 3930 Visp. Postfach",
    "sg:city":"Visp",
    "sg:orig_category":"Detailhandel mit Blumen U Pflanzen Fachdetailhandel in Verkaufsr\u00e4umen",
    "sg:phone":"+41 27 934 10 82",
    "sg:postcode":"3930",
    "sg:province":"Valais",
    "wof:name":"Blumen Zenh\u00e4usern, Inhaberin Kohler Ruth",
    "wof:placetype":"venue"
},
  "geometry": {"coordinates":[7.881119,46.291679],"type":"Point"}
}