{
  "type": "Feature",
  "properties": {
    "iso:country":"CH",
    "sg:address":"Oberhusrain 43",
    "sg:city":"Kriens",
    "sg:orig_category":"Sportvereine Ballsport Basketball",
    "sg:postcode":"6010",
    "sg:province":"Luzern",
    "wof:name":"Emmen Basket",
    "wof:placetype":"venue"
},
  "geometry": {"coordinates":[8.2814302444,47.0401916504],"type":"Point"}
}