{
  "type": "Feature",
  "properties": {
    "iso:country":"CH",
    "sg:address":"Bahnhofstrasse 17 2502 Biel/bienne Case Postale 603",
    "sg:city":"Biel/bienne",
    "sg:classifiers":[
        {
            "category":"Professional",
            "subcategory":"Employment Agencies",
            "type":"Services"
        }
    ],
    "sg:phone":"+41 32 322 33 55",
    "sg:postcode":"2501",
    "sg:province":"Bern",
    "sg:tags":[
        "personal",
        "u",
        "stellenvermittlung"
    ],
    "wof:name":"Kelly Services (suisse) Sa",
    "wof:placetype":"venue"
},
  "geometry": {"coordinates":[7.2443809509,47.1351242065],"type":"Point"}
}