{
  "type": "Feature",
  "properties": {
    "iso:country":"CH",
    "sg:address":"R\u00f6merstrasse 25",
    "sg:city":"Aarau",
    "sg:orig_category":"Physiotherapie",
    "sg:phone":"+41 62 822 27 44",
    "sg:postcode":"5000",
    "sg:province":"Aargau",
    "wof:name":"Eug\u00e9nie H\u00f6fler Physiotherapie",
    "wof:placetype":"venue"
},
  "geometry": {"coordinates":[8.0561513901,47.4004135132],"type":"Point"}
}