{
  "type": "Feature",
  "properties": {
    "iso:country":"CH",
    "sg:address":"Eichtalstrasse 2",
    "sg:city":"Hombrechtikon",
    "sg:orig_category":"RESTAURANTS: TEA-ROOMS",
    "sg:phone":"+41 55 244 19 53",
    "sg:postcode":"8634",
    "sg:province":"Z\u00fcrich",
    "wof:name":"Kellerhals Martin, Restaurant Linde",
    "wof:placetype":"venue"
},
  "geometry": {"coordinates":[8.7689638138,47.2508354187],"type":"Point"}
}