{
  "type": "Feature",
  "properties": {
    "iso:country":"CH",
    "sg:address":"Steiggasse 1",
    "sg:city":"Winterthur",
    "sg:classifiers":[
        {
            "category":"Travel",
            "subcategory":"Hotels & Motels",
            "type":"Entertainment"
        }
    ],
    "sg:phone":"+41 52 213 66 44",
    "sg:postcode":"8400",
    "sg:province":"Z\u00fcrich",
    "sg:tags":[
        "hotels",
        "mit",
        "restaurant"
    ],
    "wof:name":"Gasthaus R\u00f6ssli, Ueli Hack",
    "wof:placetype":"venue"
},
  "geometry": {"coordinates":[8.7277650833,47.4978408813],"type":"Point"}
}