{
  "type": "Feature",
  "properties": {
    "iso:country":"CH",
    "sg:address":"Klosterplatz 7",
    "sg:city":"Olten",
    "sg:orig_category":"Detailhandel mit Brot, Back U S\u00fcsswaren",
    "sg:phone":"+41 62 212 26 10",
    "sg:postcode":"4600",
    "sg:province":"Solothurn",
    "wof:name":"Hans Allenspach Holzofenb\u00e4ckerei",
    "wof:placetype":"venue"
},
  "geometry": {"coordinates":[7.904367,47.350376],"type":"Point"}
}