{
  "type": "Feature",
  "properties": {
    "iso:country":"CH",
    "sg:address":"Nationalstrasse 28/30",
    "sg:city":"Kreuzlingen",
    "sg:classifiers":[
        {
            "category":"Arena",
            "subcategory":"Auto Racetrack",
            "type":"Entertainment"
        }
    ],
    "sg:phone":"+41 71 677 60 60",
    "sg:postcode":"8280",
    "sg:province":"Thurgau",
    "sg:tags":[
        "machine",
        "flanging"
    ],
    "wof:name":"Gebr\u00fcder Spiegel Ag",
    "wof:placetype":"venue"
},
  "geometry": {"coordinates":[9.169236,47.648762],"type":"Point"}
}