{
  "type": "Feature",
  "properties": {
    "iso:country":"CH",
    "sg:address":"M\u00fchleg\u00e4ssli 12",
    "sg:city":"Neuenegg",
    "sg:orig_category":"Instandhaltung U Reparatur von Automobilen",
    "sg:phone":"+41 31 741 03 58",
    "sg:postcode":"3176",
    "sg:province":"Bern",
    "wof:name":"M\u00fchlegarage Peter M\u00e4der.",
    "wof:placetype":"venue"
},
  "geometry": {"coordinates":[7.303399086,46.8936042786],"type":"Point"}
}