{
  "type": "Feature",
  "properties": {
    "iso:country":"CH",
    "sg:address":"Via Trevano 38",
    "sg:city":"Lugano",
    "sg:classifiers":[
        {
            "category":"Bars & Pubs",
            "type":"Food & Drink"
        }
    ],
    "sg:phone":"+41 91 970 30 22",
    "sg:postcode":"6900",
    "sg:province":"Ticino",
    "sg:tags":[
        "restaurant"
    ],
    "wof:name":"Snack Bar Lugano",
    "wof:placetype":"venue"
},
  "geometry": {"coordinates":[8.955399,46.016098],"type":"Point"}
}