{
  "type": "Feature",
  "properties": {
    "iso:country":"CH",
    "sg:address":"Avenue Jean-jacques Mercier 2",
    "sg:city":"Lausanne",
    "sg:orig_category":"Aktivit\u00e4ten der Generalunternehmen im Baugewerbe Allgemeiner Hoch U Tiefbau",
    "sg:phone":"+41 21 312 38 03",
    "sg:postcode":"1003",
    "sg:province":"Vaud",
    "wof:name":"D\u00e9n\u00e9riaz Sa",
    "wof:placetype":"venue"
},
  "geometry": {"coordinates":[6.62988,46.52055],"type":"Point"}
}