{
  "type": "Feature",
  "properties": {
    "iso:country":"CH",
    "sg:address":"Pelzgasse 13",
    "sg:city":"Aarau",
    "sg:orig_category":"Detailhandel mit Musikinstrumenten Detailhandel mit elektrischen Haushalts-,Radio U Fernsehger\u00e4ten s",
    "sg:phone":"+41 62 823 01 21",
    "sg:postcode":"5000",
    "sg:province":"Aargau",
    "wof:name":"A-zulauf Musikinstrumente Gmbh",
    "wof:placetype":"venue"
},
  "geometry": {"coordinates":[8.0448131561,47.392742157],"type":"Point"}
}