{
  "type": "Feature",
  "properties": {
    "iso:country":"CH",
    "sg:address":"Centralstrasse 25 6210 Sursee. Postfach 62",
    "sg:city":"Sursee",
    "sg:orig_category":"Tierarztpraxis",
    "sg:phone":"+41 41 921 72 33",
    "sg:postcode":"6210",
    "sg:province":"Luzern",
    "wof:name":"Dr. Med. Vet. J\u00f6rg Willi Tierarzt",
    "wof:placetype":"venue"
},
  "geometry": {"coordinates":[8.1032619476,47.1705856323],"type":"Point"}
}