{
  "type": "Feature",
  "properties": {
    "iso:country":"CH",
    "sg:address":"Oberdorfstrasse 23",
    "sg:city":"Wigoltingen",
    "sg:orig_category":"Herstellung von Metallerzeugnissen ohne Maschinenbau Herstellung von sonstigen Maschinen f\u00fcr unspezi",
    "sg:phone":"+41 52 763 13 45",
    "sg:postcode":"8556",
    "sg:province":"Thurgau",
    "wof:name":"Vend Ag",
    "wof:placetype":"venue"
},
  "geometry": {"coordinates":[9.035159111,47.5954017639],"type":"Point"}
}