{
  "type": "Feature",
  "properties": {
    "iso:country":"CH",
    "sg:address":"8048 Z\u00fcrich. Postfach 1858",
    "sg:city":"Z\u00fcrich",
    "sg:orig_category":"Sportvereine Ballsport Fussball",
    "sg:postcode":"8048",
    "sg:province":"Z\u00fcrich",
    "wof:name":"Bois D'amont-les Rousses",
    "wof:placetype":"venue"
},
  "geometry": {"coordinates":[6.2120537758,46.582359314],"type":"Point"}
}