{
  "type": "Feature",
  "properties": {
    "iso:country":"CH",
    "sg:address":"M\u00fclibachstrasse 38",
    "sg:city":"Richterswil",
    "sg:orig_category":"Kosmetikinstitute",
    "sg:phone":"+41 17841664",
    "sg:postcode":"8805",
    "sg:province":"Z\u00fcrich",
    "wof:name":"Gerda M\u00fcller Kosmetikinstitut",
    "wof:placetype":"venue"
},
  "geometry": {"coordinates":[8.7002706528,47.2042732239],"type":"Point"}
}