{
  "type": "Feature",
  "properties": {
    "iso:country":"CH",
    "sg:address":"P\u00fcntstrasse 83 8963 Kindhausen Ag. Postfach",
    "sg:city":"D\u00fcbendorf",
    "sg:orig_category":"Grosshandel mit Getr\u00e4nken",
    "sg:postcode":"8600",
    "sg:province":"Z\u00fcrich",
    "wof:name":"Str\u00e4uli Cape Wines Wein; Import, Handel. Dienstleistungen U. Arbeiten",
    "wof:placetype":"venue"
},
  "geometry": {"coordinates":[8.3857135773,47.3889694214],"type":"Point"}
}