{
  "type": "Feature",
  "properties": {
    "iso:country":"CH",
    "sg:address":"Sonnseite 70a",
    "sg:city":"Leimiswil",
    "sg:orig_category":"Grosshandel mit lebenden Tieren",
    "sg:phone":"+41 62 965 27 32",
    "sg:postcode":"4935",
    "sg:province":"Bern",
    "wof:name":"Reist Viehhandel",
    "wof:placetype":"venue"
},
  "geometry": {"coordinates":[7.7773737907,47.1562385559],"type":"Point"}
}