{
  "type": "Feature",
  "properties": {
    "iso:country":"CH",
    "sg:address":"Oberwilerstrasse 8918 Unterlunkhofen. Postfach",
    "sg:city":"Unterlunkhofen",
    "sg:orig_category":"RESTAURANTS: TEA-ROOMS",
    "sg:postcode":"8918",
    "sg:province":"Aargau",
    "wof:name":"Restaurant Huserhof Werder Markus",
    "wof:placetype":"venue"
},
  "geometry": {"coordinates":[8.3795671463,47.3241653442],"type":"Point"}
}