{
  "type": "Feature",
  "properties": {
    "iso:country":"CH",
    "sg:address":"Rue Jules Bellet 7",
    "sg:city":"Broc",
    "sg:orig_category":"Herstellung von Duft U K\u00f6rperpflegemitteln Herstellung von Medikamenten U sonstigen pharmazeutischen",
    "sg:phone":"+41 26 921 51 51",
    "sg:postcode":"1636",
    "sg:province":"Fribourg",
    "wof:name":"Nestl\u00e9 Suisse Sa",
    "wof:placetype":"venue"
},
  "geometry": {"coordinates":[7.1082849503,46.6069145203],"type":"Point"}
}