{
  "type": "Feature",
  "properties": {
    "iso:country":"CH",
    "sg:address":"Hobiel",
    "sg:city":"Buochs",
    "sg:orig_category":"Rechtsberatung",
    "sg:postcode":"6374",
    "sg:province":"Nidwalden",
    "wof:name":"Cemex Trademarks Worldwide Ltd",
    "wof:placetype":"venue"
},
  "geometry": {"coordinates":[7.2642469406,47.1211776733],"type":"Point"}
}