{
  "type": "Feature",
  "properties": {
    "iso:country":"CH",
    "sg:address":"Schofmattweg 665",
    "sg:city":"Leuggern",
    "sg:orig_category":"Detailhandel mit M\u00f6beln Herstellung von Sitzm\u00f6beln",
    "sg:phone":"+41 56 621 18 30",
    "sg:postcode":"5316",
    "sg:province":"Aargau",
    "wof:name":"Ld Leder-design Ag",
    "wof:placetype":"venue"
},
  "geometry": {"coordinates":[8.2780599594,47.350528717],"type":"Point"}
}