{
  "type": "Feature",
  "properties": {
    "iso:country":"CH",
    "sg:address":"R\u00e4dlibach 11",
    "sg:city":"Niederuzwil",
    "sg:orig_category":"Wirtschaftspr\u00fcfung, Steuerberatung U Treuhand",
    "sg:phone":"+41 71 951 20 30",
    "sg:postcode":"9244",
    "sg:province":"St. Gallen",
    "wof:name":"Rutz + Brun Ag Treuhand",
    "wof:placetype":"venue"
},
  "geometry": {"coordinates":[9.128613472,47.4489822388],"type":"Point"}
}