{
  "type": "Feature",
  "properties": {
    "iso:country":"CH",
    "sg:address":"Bergstrasse 67",
    "sg:city":"Dietikon",
    "sg:orig_category":"Wirtschaftspr\u00fcfung, Steuerberatung U Treuhand",
    "sg:postcode":"8953",
    "sg:province":"Z\u00fcrich",
    "wof:name":"Treuhand Und Buchhaltungsb\u00fcro Urban Meyer",
    "wof:placetype":"venue"
},
  "geometry": {"coordinates":[8.3949127197,47.4009017944],"type":"Point"}
}