{
  "type": "Feature",
  "properties": {
    "iso:country":"CH",
    "sg:address":"Winterhaldenstrasse 5",
    "sg:city":"Heimberg",
    "sg:orig_category":"Instandhaltung U Reparatur von Automobilen",
    "sg:phone":"+41 33 437 54 44",
    "sg:postcode":"3627",
    "sg:province":"Bern",
    "wof:name":"K\u00e4mpf Walter, Garage-autoelektro",
    "wof:placetype":"venue"
},
  "geometry": {"coordinates":[7.6028518677,46.7976493835],"type":"Point"}
}