{
  "type": "Feature",
  "properties": {
    "iso:country":"CH",
    "sg:address":"Seestrasse 60a",
    "sg:city":"Uster",
    "sg:orig_category":"Wirtschaftspr\u00fcfung, Steuerberatung U Treuhand",
    "sg:phone":"+41 17481094",
    "sg:postcode":"8610",
    "sg:province":"Z\u00fcrich",
    "wof:name":"Mer\u00e7ay Treuhand",
    "wof:placetype":"venue"
},
  "geometry": {"coordinates":[8.7090778351,47.3452835083],"type":"Point"}
}