{
  "type": "Feature",
  "properties": {
    "iso:country":"CH",
    "sg:address":"Ruflisbergstrasse 46",
    "sg:city":"Luzern",
    "sg:orig_category":"Sonstige Finanzierungsinstitutionen",
    "sg:phone":"+41 61 713 25 60",
    "sg:postcode":"6006",
    "sg:province":"Luzern",
    "wof:name":"Terrestre Ag",
    "wof:placetype":"venue"
},
  "geometry": {"coordinates":[7.590528965,47.4900131226],"type":"Point"}
}