{
  "type": "Feature",
  "properties": {
    "iso:country":"CH",
    "sg:address":"D\u00f6rfli",
    "sg:city":"Alpthal",
    "sg:orig_category":"Landesverteidigung, Sozialversicherung \u00d6ffentliche Verwaltung",
    "sg:phone":"+41 71 755 16 44",
    "sg:postcode":"8849",
    "sg:province":"Schwyz",
    "wof:name":"Zivilschutzstelle Alst\u00e4tten",
    "wof:placetype":"venue"
},
  "geometry": {"coordinates":[9.5409851074,47.3781814575],"type":"Point"}
}