{
  "type": "Feature",
  "properties": {
    "iso:country":"CH",
    "sg:address":"Untere Bahnhofstrasse 2",
    "sg:city":"Hinwil",
    "sg:orig_category":"Detailhandel mit Beleuchtungs U Haushaltsgegenst\u00e4nden Grosshandel mit Eisenwaren sowie Installations",
    "sg:phone":"+41 79 338 12 85",
    "sg:postcode":"8340",
    "sg:province":"Z\u00fcrich",
    "wof:name":"Windlin Eisenwaren Ag",
    "wof:placetype":"venue"
},
  "geometry": {"coordinates":[8.840903,47.303131],"type":"Point"}
}