{
  "type": "Feature",
  "properties": {
    "iso:country":"CH",
    "sg:address":"Chemin Du Champ-des-pierres",
    "sg:city":"Genolier",
    "sg:orig_category":"Reiseb\u00fcros U Reiseveranstalter",
    "sg:phone":"+41 79 203 44 82",
    "sg:postcode":"1272",
    "sg:province":"Vaud",
    "wof:name":"Caitour S\u00e0rl",
    "wof:placetype":"venue"
},
  "geometry": {"coordinates":[6.2214221954,46.4285736084],"type":"Point"}
}