{
  "type": "Feature",
  "properties": {
    "iso:country":"CH",
    "sg:address":"La Ronde-fin",
    "sg:city":"Cornaux",
    "sg:classifiers":[
        {
            "category":"Wholesale",
            "subcategory":"Auto Parts",
            "type":"Manufacturing & Wholesale Goods"
        }
    ],
    "sg:phone":"+41 32 757 38 58",
    "sg:postcode":"2087",
    "sg:province":"Neuch\u00e2tel",
    "sg:tags":[
        "machine",
        "screw"
    ],
    "wof:name":"Salem Sa",
    "wof:placetype":"venue"
},
  "geometry": {"coordinates":[7.0296621323,47.036441803],"type":"Point"}
}