{
  "type": "Feature",
  "properties": {
    "iso:country":"CH",
    "sg:address":"Eichlitten",
    "sg:city":"Gams",
    "sg:orig_category":"Wohnheime",
    "sg:phone":"+41 52 743 11 73",
    "sg:postcode":"9473",
    "sg:province":"St. Gallen",
    "wof:name":"Durchgangsheim F\u00fcr Asylbewerber",
    "wof:placetype":"venue"
},
  "geometry": {"coordinates":[8.7840995789,47.7150840759],"type":"Point"}
}