{
  "type": "Feature",
  "properties": {
    "iso:country":"CH",
    "sg:address":"H\u00fcttmatt 142 5610 Wohlen Ag. Postfach",
    "sg:city":"Schafisheim",
    "sg:orig_category":"Herstellung von Metallkonstruktionen",
    "sg:phone":"+41 56 622 32 10",
    "sg:postcode":"5503",
    "sg:province":"Aargau",
    "wof:name":"Charles Scherrer Montagen",
    "wof:placetype":"venue"
},
  "geometry": {"coordinates":[8.2780704498,47.3505363464],"type":"Point"}
}