{
  "type": "Feature",
  "properties": {
    "iso:country":"CH",
    "sg:address":"Sandackerstrasse 1",
    "sg:city":"Rheinau",
    "sg:classifiers":[
        {
            "category":"Restaurant",
            "type":"Food & Drink"
        }
    ],
    "sg:phone":"+41 52 319 12 62",
    "sg:postcode":"8462",
    "sg:province":"Z\u00fcrich",
    "wof:name":"Restaurant Hirschen",
    "wof:placetype":"venue"
},
  "geometry": {"coordinates":[8.6035966873,47.6478691101],"type":"Point"}
}