{
  "type": "Feature",
  "properties": {
    "iso:country":"CH",
    "sg:address":"Heimisbach.",
    "sg:city":"Trachselwald",
    "sg:orig_category":"Interessenvertretungen",
    "sg:phone":"+41 34 431 27 25",
    "sg:postcode":"3456",
    "sg:province":"Bern",
    "wof:name":"Simon Gfeller-stiftung",
    "wof:placetype":"venue"
},
  "geometry": {"coordinates":[7.741109848,47.0142211914],"type":"Point"}
}