{
  "type": "Feature",
  "properties": {
    "iso:country":"CH",
    "sg:address":"Village Place Du 4",
    "sg:city":"Anz\u00e8re",
    "sg:orig_category":"Herstellung von Hebezeugen U F\u00f6rdermitteln",
    "sg:phone":"+41 27 398 14 14",
    "sg:postcode":"1972",
    "sg:province":"Valais",
    "wof:name":"Sa Des Remont\u00e9es M\u00e9caniques Du Wildhorn",
    "wof:placetype":"venue"
},
  "geometry": {"coordinates":[7.4004211426,46.2969818115],"type":"Point"}
}