{
  "type": "Feature",
  "properties": {
    "iso:country":"CH",
    "sg:address":"Rue De La Tournelle 19",
    "sg:city":"Orbe",
    "sg:orig_category":"Allgemeiner Hoch U Tiefbau",
    "sg:phone":"+41 24 441 32 76",
    "sg:postcode":"1350",
    "sg:province":"Vaud",
    "wof:name":"Ferrario Marc & Cie.",
    "wof:placetype":"venue"
},
  "geometry": {"coordinates":[6.535464,46.724274],"type":"Point"}
}