{
  "type": "Feature",
  "properties": {
    "iso:country":"CH",
    "sg:address":"6805",
    "sg:city":"Mezzovico",
    "sg:orig_category":"Vermietung U Verpachtung von eigenen Immobilien",
    "sg:postcode":"6805",
    "sg:province":"Ticino",
    "wof:name":"Novadim Immobiliare Sa",
    "wof:placetype":"venue"
},
  "geometry": {"coordinates":[8.9207296371,46.0964508057],"type":"Point"}
}