{
  "type": "Feature",
  "properties": {
    "addr:full":"Hauptstrasse 19 Arbon Thurgau 9320",
    "addr:housenumber":"19",
    "addr:postcode":"9320",
    "addr:street":"Hauptstrasse",
    "iso:country":"CH",
    "sg:address":"Hauptstrasse 19",
    "sg:city":"Arbon",
    "sg:orig_category":"Datenverarbeitungsdienste Softwareentwicklung U beratung",
    "sg:phone":"+41 71 463 46 84",
    "sg:postcode":"9320",
    "sg:province":"Thurgau",
    "wof:name":"Wrischnig Marcel Informatik",
    "wof:placetype":"venue"
},
  "geometry": {"coordinates":[9.434991,47.515903],"type":"Point"}
}