{
  "type": "Feature",
  "properties": {
    "iso:country":"CH",
    "sg:address":"Veilchenweg 14",
    "sg:city":"Zurzach",
    "sg:orig_category":"Sonstige mit der Informatik verbundene T\u00e4tigkeiten",
    "sg:postcode":"5330",
    "sg:province":"Aargau",
    "wof:name":"Kris Emery Consulting",
    "wof:placetype":"venue"
},
  "geometry": {"coordinates":[8.282959938,47.5933074951],"type":"Point"}
}