{
  "type": "Feature",
  "properties": {
    "iso:country":"CH",
    "sg:address":"Roosstrasse 53",
    "sg:city":"Wollerau",
    "sg:orig_category":"Satzherstellung U Reproduktion",
    "sg:phone":"+41 17847273",
    "sg:postcode":"8832",
    "sg:province":"Schwyz",
    "wof:name":"Litho-atelier Thalmann Gmbh",
    "wof:placetype":"venue"
},
  "geometry": {"coordinates":[8.7207193375,47.1887245178],"type":"Point"}
}