{
  "type": "Feature",
  "properties": {
    "iso:country":"CH",
    "sg:address":"Rue Du Mont-noble 32",
    "sg:city":"Sierre",
    "sg:orig_category":"Malerei Stukkateurgewerbe, Gipserei U Verputzerei",
    "sg:phone":"+41 27 455 19 40",
    "sg:postcode":"3960",
    "sg:province":"Valais",
    "wof:name":"Jean-michel Rey Gypserie & Peinture",
    "wof:placetype":"venue"
},
  "geometry": {"coordinates":[7.5206661224,46.2854804993],"type":"Point"}
}