{
  "type": "Feature",
  "properties": {
    "iso:country":"CH",
    "sg:address":"Steingrubenweg 160",
    "sg:city":"Riehen",
    "sg:orig_category":"Herstellung von pharmazeutischen Grundstoffen",
    "sg:phone":"+41 61 641 53 43",
    "sg:postcode":"4125",
    "sg:province":"Basel-Stadt",
    "wof:name":"Toxconsult Pfannkuch",
    "wof:placetype":"venue"
},
  "geometry": {"coordinates":[7.6646771431,47.5883750916],"type":"Point"}
}