{
  "type": "Feature",
  "properties": {
    "iso:country":"CH",
    "sg:address":"Route Henri-dunant 1 1700 Fribourg Case Postale 4",
    "sg:city":"Fribourg",
    "sg:orig_category":"Detailhandel mit B\u00fcchern, Zeitungen, Schreib U Papeteriewaren Grosshandel mit Schreibwaren, B\u00fcchern ",
    "sg:phone":"+41 26 481 31 43",
    "sg:postcode":"1702",
    "sg:province":"Fribourg",
    "wof:name":"Books Import-export S.a.",
    "wof:placetype":"venue"
},
  "geometry": {"coordinates":[7.178499,46.804844],"type":"Point"}
}