{
  "type": "Feature",
  "properties": {
    "iso:country":"CH",
    "sg:address":"Wilhofstrasse 3",
    "sg:city":"Zollikerberg",
    "sg:orig_category":"Nationale Postdienste",
    "sg:phone":"+41 19291205",
    "sg:postcode":"8125",
    "sg:province":"Z\u00fcrich",
    "wof:name":"Die Schweizerische Post",
    "wof:placetype":"venue"
},
  "geometry": {"coordinates":[8.7213697433,47.2700805664],"type":"Point"}
}