{
  "type": "Feature",
  "properties": {
    "iso:country":"CH",
    "sg:address":"Via Camana",
    "sg:city":"Cadro",
    "sg:orig_category":"Betrieb von Sportanlagen",
    "sg:postcode":"6965",
    "sg:province":"Ticino",
    "wof:name":"Attrezzature Sportive + Tempolibero Sagl",
    "wof:placetype":"venue"
},
  "geometry": {"coordinates":[8.9842,46.045166],"type":"Point"}
}