{
  "type": "Feature",
  "properties": {
    "iso:country":"CH",
    "sg:address":"Birsigstrasse 10",
    "sg:city":"Basel",
    "sg:orig_category":"Arztpraxen",
    "sg:phone":"+41 55 246 18 55",
    "sg:postcode":"4054",
    "sg:province":"Basel-Stadt",
    "wof:name":"Dr.med.katharina Pfenninger Aerztin F.allgemeine Medizin",
    "wof:placetype":"venue"
},
  "geometry": {"coordinates":[8.9413,47.28841],"type":"Point"}
}