{
  "type": "Feature",
  "properties": {
    "iso:country":"CH",
    "sg:address":"Rue Du Canal 2",
    "sg:city":"Ste-croix",
    "sg:orig_category":"Pensionskassen",
    "sg:phone":"+41 22 771 13 97",
    "sg:postcode":"1450",
    "sg:province":"Vaud",
    "wof:name":"Fondation Lpp De Tuileries Et Briqueteries Sa Bardonnex",
    "wof:placetype":"venue"
},
  "geometry": {"coordinates":[6.1364598274,46.145401001],"type":"Point"}
}