{
  "type": "Feature",
  "properties": {
    "iso:country":"CH",
    "sg:address":"Vecchio Tram Via 22",
    "sg:city":"Davesco-soragno",
    "sg:orig_category":"Herstellung von Werkzeugen",
    "sg:postcode":"6964",
    "sg:province":"Ticino",
    "wof:name":"Tc Tools Sa",
    "wof:placetype":"venue"
},
  "geometry": {"coordinates":[8.9895296097,46.0325584412],"type":"Point"}
}