{
  "type": "Feature",
  "properties": {
    "iso:country":"CH",
    "sg:address":"Obertorweg 40",
    "sg:city":"Allschwil",
    "sg:orig_category":"Jugendorganisationen",
    "sg:phone":"+41 61 482 24 51",
    "sg:postcode":"4123",
    "sg:province":"Basel-Landschaft",
    "wof:name":"Christkath.jugendgruppe Basel",
    "wof:placetype":"venue"
},
  "geometry": {"coordinates":[7.5301442146,47.5523223877],"type":"Point"}
}