{
  "type": "Feature",
  "properties": {
    "iso:country":"CH",
    "sg:address":"Dullikerstrasse 16",
    "sg:city":"Oberg\u00f6sgen",
    "sg:orig_category":"Zimmerei, Dachdeckerei, Bauspenglerei U Abdichtung",
    "sg:phone":"+41 62 295 51 47",
    "sg:postcode":"4653",
    "sg:province":"Solothurn",
    "wof:name":"Zimmerei-innenbausbau Ramseier H.",
    "wof:placetype":"venue"
},
  "geometry": {"coordinates":[7.9534859657,47.3541297913],"type":"Point"}
}