{
  "type": "Feature",
  "properties": {
    "iso:country":"CH",
    "sg:address":"Frohmattstrasse 15",
    "sg:city":"Arbon",
    "sg:orig_category":"Fachdetailhandel in Verkaufsr\u00e4umen",
    "sg:phone":"+41 71 446 67 94",
    "sg:postcode":"9320",
    "sg:province":"Thurgau",
    "wof:name":"Hofer Fritz",
    "wof:placetype":"venue"
},
  "geometry": {"coordinates":[9.4230051041,47.5186729431],"type":"Point"}
}