{
  "type": "Feature",
  "properties": {
    "iso:country":"CH",
    "sg:address":"8452",
    "sg:city":"Adlikon",
    "sg:orig_category":"Ingenieurb\u00fcros Elektro",
    "sg:phone":"+41 81 413 75 74",
    "sg:postcode":"8452",
    "sg:province":"Z\u00fcrich",
    "wof:name":"Erwin Hassler Ingenieurb\u00fcro",
    "wof:placetype":"venue"
},
  "geometry": {"coordinates":[9.8177690506,46.7947387695],"type":"Point"}
}