{
  "type": "Feature",
  "properties": {
    "iso:country":"CH",
    "sg:address":"Stationsstrasse 22 8606 Greifensee. Postfach",
    "sg:city":"Greifensee",
    "sg:orig_category":"Vermietung U Verpachtung von eigenen Immobilien",
    "sg:postcode":"8606",
    "sg:province":"Z\u00fcrich",
    "wof:name":"Sim Immobilien, Schaffer Monika, Eidg. Dipl. Immobilien-treuh\u00e4nderin",
    "wof:placetype":"venue"
},
  "geometry": {"coordinates":[8.6809444427,47.3678474426],"type":"Point"}
}