{
  "type": "Feature",
  "properties": {
    "iso:country":"CH",
    "sg:address":"R\u00f6schenzerstrasse 2",
    "sg:city":"Basel",
    "sg:orig_category":"Vermietung U Verpachtung von eigenen Immobilien Vermittlung von Immobilien",
    "sg:phone":"+41 91 972 25 61",
    "sg:postcode":"4053",
    "sg:province":"Basel-Stadt",
    "wof:name":"Sai Immobili Sa",
    "wof:placetype":"venue"
},
  "geometry": {"coordinates":[8.9575481415,46.0152587891],"type":"Point"}
}