{
  "type": "Feature",
  "properties": {
    "iso:country":"CH",
    "sg:address":"3955",
    "sg:city":"Albinen",
    "sg:orig_category":"Herstellung von Konstruktionsteilen, Fertigbauteilen U Ausbauelementen aus Holz",
    "sg:phone":"+41 27 473 18 38",
    "sg:postcode":"3955",
    "sg:province":"Valais",
    "wof:name":"Hermann Marcel, Schreinerei Und Zimmerei",
    "wof:placetype":"venue"
},
  "geometry": {"coordinates":[7.6342549324,46.340171814],"type":"Point"}
}