{
  "type": "Feature",
  "properties": {
    "iso:country":"CH",
    "sg:address":"Avenue De Montcoisi 21",
    "sg:city":"Lausanne",
    "sg:orig_category":"Architektur U Ingenieurb\u00fcros",
    "sg:phone":"+41 21 617 78 82",
    "sg:postcode":"1006",
    "sg:province":"Vaud",
    "wof:name":"Ete Ing\u00e9nieur-conseil, Miklos Splivallo",
    "wof:placetype":"venue"
},
  "geometry": {"coordinates":[6.633742,46.513321],"type":"Point"}
}