{
  "type": "Feature",
  "properties": {
    "iso:country":"CH",
    "sg:address":"Mungnau Zollbr\u00fcck.",
    "sg:city":"Lauperswil",
    "sg:orig_category":"Mahl U Sch\u00e4lm\u00fchlen",
    "sg:postcode":"3438",
    "sg:province":"Bern",
    "wof:name":"Trocknungsbetriebe Suter Gebr. Ag",
    "wof:placetype":"venue"
},
  "geometry": {"coordinates":[8.3302698135,47.5200195312],"type":"Point"}
}