{
  "type": "Feature",
  "properties": {
    "iso:country":"CH",
    "sg:address":"Dorfstrasse 51",
    "sg:city":"Trasadingen",
    "sg:orig_category":"Sonstige Verkehrsvermittlung",
    "sg:phone":"+41 52 681 17 39",
    "sg:postcode":"8219",
    "sg:province":"Schaffhausen",
    "wof:name":"Transalpi Concept Hansj\u00f6rg B\u00fchler",
    "wof:placetype":"venue"
},
  "geometry": {"coordinates":[8.4301319122,47.6685371399],"type":"Point"}
}