{
  "type": "Feature",
  "properties": {
    "iso:country":"CH",
    "sg:address":"1485",
    "sg:city":"Nuvilly",
    "sg:classifiers":[
        {
            "category":"Travel",
            "subcategory":"Hotels & Motels",
            "type":"Entertainment"
        }
    ],
    "sg:phone":"+41 32 953 11 48",
    "sg:postcode":"1485",
    "sg:province":"Fribourg",
    "sg:tags":[
        "hotels",
        "mit",
        "restaurant"
    ],
    "wof:name":"Auberge De La Bou\u00e8ge",
    "wof:placetype":"venue"
},
  "geometry": {"coordinates":[6.9007158279,47.2114601135],"type":"Point"}
}