{
  "type": "Feature",
  "properties": {
    "iso:country":"CH",
    "sg:address":"1041",
    "sg:city":"Bottens",
    "sg:orig_category":"Autogaragen",
    "sg:phone":"+41 79 321 12 12",
    "sg:postcode":"1041",
    "sg:province":"Vaud",
    "wof:name":"Bernard Friedli Garage",
    "wof:placetype":"venue"
},
  "geometry": {"coordinates":[6.13,46.183323],"type":"Point"}
}