{
  "type": "Feature",
  "properties": {
    "iso:country":"CH",
    "sg:address":"Via Borghese 18",
    "sg:city":"Locarno",
    "sg:orig_category":"Grosshandel mit Getr\u00e4nken Grosshandel mit sonstigen Getr\u00e4nken",
    "sg:phone":"+41 91 751 39 76",
    "sg:postcode":"6600",
    "sg:province":"Ticino",
    "wof:name":"Romerio F.lli Sa",
    "wof:placetype":"venue"
},
  "geometry": {"coordinates":[8.792971611,46.1702575684],"type":"Point"}
}