{
  "type": "Feature",
  "properties": {
    "iso:country":"CH",
    "sg:address":"Nieder\u00e4mterstrasse 50",
    "sg:city":"Dulliken",
    "sg:orig_category":"Herstellung von Maschinen f\u00fcr die Nahrungsmittel, Getr\u00e4nkeherstellung U die Tabakverarbeitung Herste",
    "sg:phone":"+41 62 295 48 02",
    "sg:postcode":"4657",
    "sg:province":"Solothurn",
    "wof:name":"Koch Dulliken Ag",
    "wof:placetype":"venue"
},
  "geometry": {"coordinates":[7.9378609657,47.3540344238],"type":"Point"}
}