{
  "type": "Feature",
  "properties": {
    "iso:country":"CH",
    "sg:address":"Idaplatz 9 8003 Z\u00fcrich. Postfach",
    "sg:city":"Z\u00fcrich",
    "sg:orig_category":"Sanit\u00e4r, Heizungs U L\u00fcftungsinstallation",
    "sg:postcode":"8001",
    "sg:province":"Z\u00fcrich",
    "wof:name":"Sch\u00f6nenberger & Partner Ag Sanit\u00e4re Anlagen",
    "wof:placetype":"venue"
},
  "geometry": {"coordinates":[9.0500049591,47.4476661682],"type":"Point"}
}