{
  "type": "Feature",
  "properties": {
    "iso:country":"CH",
    "sg:address":"Route Saint Eloi 21a",
    "sg:city":"Estavayer-le-lac",
    "sg:orig_category":"Hardwareberatung",
    "sg:phone":"+41 26 663 10 10",
    "sg:postcode":"1470",
    "sg:province":"Fribourg",
    "wof:name":"Leuzinger Christine Distribution",
    "wof:placetype":"venue"
},
  "geometry": {"coordinates":[6.8551659584,46.8467636108],"type":"Point"}
}