{
  "type": "Feature",
  "properties": {
    "iso:country":"CH",
    "sg:address":"Baselstrasse 160",
    "sg:city":"Laufen",
    "sg:orig_category":"Herstellung von Kunststoffwaren Oberfl\u00e4chenveredlung U W\u00e4rmebehandlung",
    "sg:phone":"+41 61 761 75 45",
    "sg:postcode":"4242",
    "sg:province":"Basel-Landschaft",
    "wof:name":"Wimas Borer C.",
    "wof:placetype":"venue"
},
  "geometry": {"coordinates":[7.5094189644,47.4257850647],"type":"Point"}
}