{
  "type": "Feature",
  "properties": {
    "iso:country":"CH",
    "sg:address":"Staatsstrasse 153",
    "sg:city":"Rebstein",
    "sg:orig_category":"Arztpraxen",
    "sg:phone":"+41 71 777 14 44",
    "sg:postcode":"9445",
    "sg:province":"St. Gallen",
    "wof:name":"Dr.med.hansj\u00f6rg Oesch Arzt F.allgemeine Medizin Fmh",
    "wof:placetype":"venue"
},
  "geometry": {"coordinates":[9.577625,47.395798],"type":"Point"}
}