{
  "type": "Feature",
  "properties": {
    "addr:full":"Ueberlandstrasse 300 D\u00fcbendorf Z\u00fcrich 8600",
    "addr:housenumber":"300",
    "addr:postcode":"8600",
    "addr:street":"Ueberlandstrasse",
    "iso:country":"CH",
    "sg:address":"Ueberlandstrasse 300",
    "sg:city":"D\u00fcbendorf",
    "sg:orig_category":"Autolackierereien",
    "sg:phone":"+41 18218550",
    "sg:postcode":"8600",
    "sg:province":"Z\u00fcrich",
    "wof:name":"Pasquale Aurichio Autospritzwerk",
    "wof:placetype":"venue"
},
  "geometry": {"coordinates":[8.635484,47.395657],"type":"Point"}
}