{
  "type": "Feature",
  "properties": {
    "iso:country":"CH",
    "sg:address":"Ohne Domizil",
    "sg:city":"Steinhausen",
    "sg:orig_category":"Detailhandel mit Metallwaren, Anstrichmitteln, Glaswaren, Bau U Heimwerkerbedarf",
    "sg:postcode":"6312",
    "sg:province":"Zug",
    "wof:name":"Aliseo Ag",
    "wof:placetype":"venue"
},
  "geometry": {"coordinates":[8.4846382141,47.1969032288],"type":"Point"}
}