{
  "type": "Feature",
  "properties": {
    "iso:country":"CH",
    "sg:address":"Rue Dents-du-midi 17",
    "sg:city":"Collombey",
    "sg:orig_category":"Handel mit Automobilen Vermietung von Automobilen",
    "sg:phone":"+41 79 213 78 13",
    "sg:postcode":"1868",
    "sg:province":"Valais",
    "wof:name":"Roger Gailloud Garage-carrosserie",
    "wof:placetype":"venue"
},
  "geometry": {"coordinates":[6.9457411766,46.2668533325],"type":"Point"}
}