{
  "type": "Feature",
  "properties": {
    "iso:country":"CH",
    "sg:address":"R\u00fctistrasse 28",
    "sg:city":"Schlieren",
    "sg:orig_category":"Grosshandel mit B\u00fcromaschinen Grosshandel mit Datenverarbeitungsger\u00e4ten",
    "sg:phone":"+41 17311221",
    "sg:postcode":"8952",
    "sg:province":"Z\u00fcrich",
    "wof:name":"Pro-data Service Ag",
    "wof:placetype":"venue"
},
  "geometry": {"coordinates":[8.4534187317,47.4006576538],"type":"Point"}
}