{
  "type": "Feature",
  "properties": {
    "iso:country":"CH",
    "sg:address":"Baldeggstrasse",
    "sg:city":"Hochdorf",
    "sg:orig_category":"Pensionskassen",
    "sg:phone":"+41 41 910 12 15",
    "sg:postcode":"6280",
    "sg:province":"Luzern",
    "wof:name":"Personalf\u00fcrsorgestiftung Der Firma Balthasar & Co",
    "wof:placetype":"venue"
},
  "geometry": {"coordinates":[8.2841253281,47.1749267578],"type":"Point"}
}