{
  "type": "Feature",
  "properties": {
    "iso:country":"CH",
    "sg:address":"Bahnhofstrasse 65 6403 K\u00fcssnacht Am Rigi. Postfach",
    "sg:city":"Immensee",
    "sg:orig_category":"Wirtschaftspr\u00fcfung, Steuerberatung U Treuhand",
    "sg:phone":"+41 41 852 03 71",
    "sg:postcode":"6405",
    "sg:province":"Schwyz",
    "wof:name":"Abag Bautreuhand Ag",
    "wof:placetype":"venue"
},
  "geometry": {"coordinates":[8.4336595535,47.0832977295],"type":"Point"}
}