{
  "type": "Feature",
  "properties": {
    "iso:country":"CH",
    "sg:address":"Wengelacher 3812 Wilderswil. Postfach",
    "sg:city":"Wilderswil",
    "sg:orig_category":"Allgemeiner Hoch U Tiefbau",
    "sg:postcode":"3812",
    "sg:province":"Bern",
    "wof:name":"Hmv Verputz Und Gips Gmbh Verputz- U. Gipserarbeiten Usw",
    "wof:placetype":"venue"
},
  "geometry": {"coordinates":[7.857084,46.67115],"type":"Point"}
}