{
  "type": "Feature",
  "properties": {
    "iso:country":"CH",
    "sg:address":"Via Angelo Maspoli 18 6850 Mendrisio. Postfach",
    "sg:city":"Mendrisio",
    "sg:orig_category":"Unclassifiable Establishments",
    "sg:postcode":"6850",
    "sg:province":"Ticino",
    "wof:name":"Logicinvest Bv, Amsterdam, Succursale Di Mendrisio",
    "wof:placetype":"venue"
},
  "geometry": {"coordinates":[8.978729248,45.8752593994],"type":"Point"}
}