{
  "type": "Feature",
  "properties": {
    "iso:country":"CH",
    "sg:address":"Kleeg\u00e4rtenstrasse 3930 Visp. Postfach 364",
    "sg:city":"Visp",
    "sg:orig_category":"Herstellung von Fenstern U T\u00fcren aus Holz Herstellung von Konstruktionsteilen, Fertigbauteilen U Aus",
    "sg:phone":"+41 32 631 20 08",
    "sg:postcode":"3930",
    "sg:province":"Valais",
    "wof:name":"Zurlinden Schreinerei & Fensterbau",
    "wof:placetype":"venue"
},
  "geometry": {"coordinates":[7.6586279869,47.2315826416],"type":"Point"}
}