{
  "type": "Feature",
  "properties": {
    "addr:full":"Freiestrasse 58 Z\u00fcrich Z\u00fcrich 8032",
    "addr:housenumber":"58",
    "addr:postcode":"8032",
    "addr:street":"Freiestrasse",
    "iso:country":"CH",
    "sg:address":"Freiestrasse 58",
    "sg:city":"Z\u00fcrich",
    "sg:orig_category":"Betrieb U technische Hilfsdienste des Kultur U Unterhaltungswesens Tanzschulen, Tanzlehrer",
    "sg:phone":"+41 12524515",
    "sg:postcode":"8032",
    "sg:province":"Z\u00fcrich",
    "wof:name":"Kinder- & Jugendtheater Metzenthin Rosmarie",
    "wof:placetype":"venue"
},
  "geometry": {"coordinates":[8.556069,47.3689],"type":"Point"}
}