{
  "type": "Feature",
  "properties": {
    "iso:country":"CH",
    "sg:address":"Krattigstrasse 2 3700 Spiez. Postfach 408",
    "sg:city":"Spiez",
    "sg:orig_category":"Sonstiges Versicherungsgewerbe",
    "sg:phone":"+41 31 839 39 84",
    "sg:postcode":"3700",
    "sg:province":"Bern",
    "wof:name":"Reichenbach Fritz Generalagentur Der Winterthur Leben",
    "wof:placetype":"venue"
},
  "geometry": {"coordinates":[7.5731639862,46.9266929626],"type":"Point"}
}