{
  "type": "Feature",
  "properties": {
    "iso:country":"CH",
    "sg:address":"Im G\u00e4rtli 2",
    "sg:city":"Oberaach",
    "sg:orig_category":"Organisationen des Gesundheitswesen",
    "sg:phone":"+41 71 411 68 45",
    "sg:postcode":"8587",
    "sg:province":"Thurgau",
    "wof:name":"Samariterverein Amriswil",
    "wof:placetype":"venue"
},
  "geometry": {"coordinates":[9.2636842728,47.5612182617],"type":"Point"}
}