{
  "type": "Feature",
  "properties": {
    "iso:country":"CH",
    "sg:address":"Sonnmattstrasse 989",
    "sg:city":"Mogelsberg",
    "sg:orig_category":"Organisationen des Gesundheitswesen",
    "sg:phone":"+41 71 374 15 16",
    "sg:postcode":"9122",
    "sg:province":"St. Gallen",
    "wof:name":"Samariterverein",
    "wof:placetype":"venue"
},
  "geometry": {"coordinates":[9.1361398697,47.3594894409],"type":"Point"}
}