{
  "type": "Feature",
  "properties": {
    "iso:country":"CH",
    "sg:address":"Lauistrasse - Ennetb\u00fchl. 9643 Krummenau. Postfach",
    "sg:city":"Ennetb\u00fchl",
    "sg:orig_category":"Wirtschaftspr\u00fcfung, Steuerberatung U Treuhand",
    "sg:postcode":"9651",
    "sg:province":"St. Gallen",
    "wof:name":"Bosshard-marti F. Frau.",
    "wof:placetype":"venue"
},
  "geometry": {"coordinates":[9.1713256836,47.2484703064],"type":"Point"}
}