{
  "type": "Feature",
  "properties": {
    "iso:country":"CH",
    "sg:address":"Kirchgasse 174",
    "sg:city":"Staffelbach",
    "sg:orig_category":"Herstellung von Schmuck, Gold U Silberschmiedwaren Herstellung von sonstigen Metallwaren",
    "sg:phone":"+41 62 212 35 08",
    "sg:postcode":"5053",
    "sg:province":"Aargau",
    "wof:name":"Gravura Degani Ag",
    "wof:placetype":"venue"
},
  "geometry": {"coordinates":[8.0473327637,47.2831993103],"type":"Point"}
}