{
  "type": "Feature",
  "properties": {
    "iso:country":"CH",
    "sg:address":"Krongasse 10",
    "sg:city":"Luzern",
    "sg:orig_category":"Detailhandel mit Textilien Herstellung von konfektionierten Textilwaren ohne Bekleidung",
    "sg:phone":"+41 41 210 23 13",
    "sg:postcode":"6003",
    "sg:province":"Luzern",
    "wof:name":"Samina, Foro Jacques",
    "wof:placetype":"venue"
},
  "geometry": {"coordinates":[8.303694725,47.050567627],"type":"Point"}
}