{
  "type": "Feature",
  "properties": {
    "iso:country":"CH",
    "sg:address":"Bruderholzstrasse 74",
    "sg:city":"Basel",
    "sg:orig_category":"Kosmetikinstitute",
    "sg:phone":"+41 91 743 27 52",
    "sg:postcode":"4053",
    "sg:province":"Basel-Stadt",
    "wof:name":"Claudine Giovannoni Istituto Beauty & Color",
    "wof:placetype":"venue"
},
  "geometry": {"coordinates":[8.825835228,46.1846466064],"type":"Point"}
}