{
  "type": "Feature",
  "properties": {
    "iso:country":"CH",
    "sg:address":"Uerkeweg 7",
    "sg:city":"Unterentfelden",
    "sg:classifiers":[
        {
            "category":"Home & Garden",
            "subcategory":"Carpets & Floor Coverings",
            "type":"Retail Goods"
        }
    ],
    "sg:phone":"+41 62 723 59 48",
    "sg:postcode":"5035",
    "sg:province":"Aargau",
    "sg:tags":[
        "tile",
        "made",
        "roof",
        "clay"
    ],
    "wof:name":"Kazan-bedachungen",
    "wof:placetype":"venue"
},
  "geometry": {"coordinates":[8.0447692871,47.3626098633],"type":"Point"}
}