{
  "type": "Feature",
  "properties": {
    "iso:country":"CH",
    "sg:address":"Dennikofenweg 197",
    "sg:city":"Ostermundigen",
    "sg:orig_category":"Vorschulen, Kinderg\u00e4rten",
    "sg:phone":"+41 31 931 31 20",
    "sg:postcode":"3072",
    "sg:province":"Bern",
    "wof:name":"Kindergarten",
    "wof:placetype":"venue"
},
  "geometry": {"coordinates":[7.4891967773,46.9518165588],"type":"Point"}
}