{
  "type": "Feature",
  "properties": {
    "iso:country":"CH",
    "sg:address":"Rest. Seeblick 6365 Kehrsiten. Postfach",
    "sg:city":"Kehrsiten",
    "sg:orig_category":"RESTAURANTS: TEA-ROOMS",
    "sg:phone":"+41 62 771 14 61",
    "sg:postcode":"6365",
    "sg:province":"Nidwalden",
    "wof:name":"Rest. Seetal, Frau Marie-therese Gerads",
    "wof:placetype":"venue"
},
  "geometry": {"coordinates":[8.2015953064,47.2725791931],"type":"Point"}
}