{
  "type": "Feature",
  "properties": {
    "iso:country":"CH",
    "sg:address":"Aarauerstrasse 1",
    "sg:city":"Sch\u00f6ftland",
    "sg:orig_category":"Non-Classified Establishments",
    "sg:phone":"+41 62 721 57 77",
    "sg:postcode":"5040",
    "sg:province":"Aargau",
    "wof:name":"Hair And Beauty Silvana Seiwald",
    "wof:placetype":"venue"
},
  "geometry": {"coordinates":[8.0512628555,47.3103942871],"type":"Point"}
}