{
  "type": "Feature",
  "properties": {
    "iso:country":"CH",
    "sg:address":"Obstgartenstrasse 30",
    "sg:city":"Thalwil",
    "sg:orig_category":"Grosshandel mit Nahrungsmitteln, Getr\u00e4nken U Tabakwaren ohne ausgepr\u00e4gten Schwerpunkt",
    "sg:phone":"+41 17208002",
    "sg:postcode":"8800",
    "sg:province":"Z\u00fcrich",
    "wof:name":"Primo Sgouros Nikolaos Gmbh",
    "wof:placetype":"venue"
},
  "geometry": {"coordinates":[8.564707756,47.2947349548],"type":"Point"}
}