{
  "type": "Feature",
  "properties": {
    "iso:country":"CH",
    "sg:address":"Emmentalstrasse 41 3414 Oberburg. Postfach",
    "sg:city":"Oberburg",
    "sg:orig_category":"Institutionen f\u00fcr Behinderte Wohnheime",
    "sg:phone":"+41 34 426 12 12",
    "sg:postcode":"3414",
    "sg:province":"Bern",
    "wof:name":"Bewo, Behindertenwerkst\u00e4tte Oberburg",
    "wof:placetype":"venue"
},
  "geometry": {"coordinates":[7.6291480064,47.0362281799],"type":"Point"}
}