{
  "type": "Feature",
  "properties": {
    "iso:country":"CH",
    "sg:address":"Gumprechtstr. 26",
    "sg:city":"Emmetten",
    "sg:orig_category":"Unternehmensberatung",
    "sg:phone":"+41 79 333 47 49",
    "sg:postcode":"6376",
    "sg:province":"Nidwalden",
    "wof:name":"Darnoc R. Conrad",
    "wof:placetype":"venue"
},
  "geometry": {"coordinates":[8.5134887695,46.9584770203],"type":"Point"}
}