{
  "type": "Feature",
  "properties": {
    "iso:country":"CH",
    "sg:address":"Steinenvorstadt 67",
    "sg:city":"Basel",
    "sg:orig_category":"Kinos",
    "sg:phone":"+41 61 281 06 88",
    "sg:postcode":"4051",
    "sg:province":"Basel-Stadt",
    "wof:name":"Kino Eldorado 1 & 2 Walch Kinobetriebe Ag",
    "wof:placetype":"venue"
},
  "geometry": {"coordinates":[7.5882592201,47.5521469116],"type":"Point"}
}