{
  "type": "Feature",
  "properties": {
    "iso:country":"CH",
    "sg:address":"Studhaldenstrasse 37",
    "sg:city":"Luzern",
    "sg:orig_category":"Detailhandel mit Fahrr\u00e4dern",
    "sg:phone":"+41 41 361 00 32",
    "sg:postcode":"6005",
    "sg:province":"Luzern",
    "wof:name":"Veloflick Paul Gr\u00e4tzer",
    "wof:placetype":"venue"
},
  "geometry": {"coordinates":[8.3225374222,47.0358276367],"type":"Point"}
}