{
  "type": "Feature",
  "properties": {
    "iso:country":"CH",
    "sg:address":"H\u00e4rtistrasse 4 7323 Wangs. Postfach",
    "sg:city":"Wangs",
    "sg:orig_category":"Herstellung von keramischen Wand U Bodenfliesen U platten",
    "sg:postcode":"7323",
    "sg:province":"St. Gallen",
    "wof:name":"Salvetti Roberto, Hafner, Plattenleger",
    "wof:placetype":"venue"
},
  "geometry": {"coordinates":[9.4314832687,47.031665802],"type":"Point"}
}