{
  "type": "Feature",
  "properties": {
    "iso:country":"CH",
    "sg:address":"Bahnhofstrasse 23",
    "sg:city":"Dielsdorf",
    "sg:orig_category":"Arztpraxen",
    "sg:phone":"+41 18531212",
    "sg:postcode":"8157",
    "sg:province":"Z\u00fcrich",
    "wof:name":"Dr.med.hansj\u00f6rg Sulzer Spezialarzt Fmh",
    "wof:placetype":"venue"
},
  "geometry": {"coordinates":[8.457427,47.48251],"type":"Point"}
}