{
  "type": "Feature",
  "properties": {
    "iso:country":"CH",
    "sg:address":"Rotshollen 4",
    "sg:city":"Lauwil",
    "sg:orig_category":"Sportvereine Ski",
    "sg:phone":"+41 61 941 13 31",
    "sg:postcode":"4426",
    "sg:province":"Basel-Landschaft",
    "wof:name":"Skiclub Reigoldswil",
    "wof:placetype":"venue"
},
  "geometry": {"coordinates":[7.6778268814,47.3911170959],"type":"Point"}
}