{
  "type": "Feature",
  "properties": {
    "iso:country":"CH",
    "sg:address":"Genferstrasse 33",
    "sg:city":"Z\u00fcrich",
    "sg:orig_category":"Non-Classified Establishments",
    "sg:postcode":"8002",
    "sg:province":"Z\u00fcrich",
    "wof:name":"Jarox Ag",
    "wof:placetype":"venue"
},
  "geometry": {"coordinates":[8.5335073471,47.3657302856],"type":"Point"}
}