{
  "type": "Feature",
  "properties": {
    "iso:country":"CH",
    "sg:address":"8465",
    "sg:city":"Rudolfingen",
    "sg:orig_category":"Sportvereine Sch\u00fctzen",
    "sg:postcode":"8465",
    "sg:province":"Z\u00fcrich",
    "wof:name":"Schiessverein Windlach",
    "wof:placetype":"venue"
},
  "geometry": {"coordinates":[8.4587154388,47.5446166992],"type":"Point"}
}