{
  "type": "Feature",
  "properties": {
    "addr:full":"Baslerstr. 1 Oftringen Aargau 4665",
    "addr:housenumber":"1",
    "addr:postcode":"4665",
    "addr:street":"Baslerstr.",
    "iso:country":"CH",
    "sg:address":"Baslerstr. 1",
    "sg:city":"Oftringen",
    "sg:classifiers":[
        {
            "category":"Banks & Credit Unions",
            "subcategory":"Bank",
            "type":"Services"
        }
    ],
    "sg:phone":"+41 62 797 25 25",
    "sg:postcode":"4665",
    "sg:province":"Aargau",
    "wof:name":"Sparkasse Oftringen",
    "wof:placetype":"venue"
},
  "geometry": {"coordinates":[7.918853,47.312996],"type":"Point"}
}