{
  "type": "Feature",
  "properties": {
    "iso:country":"CH",
    "sg:address":"Sihlfeldstrasse 138",
    "sg:city":"Z\u00fcrich",
    "sg:orig_category":"Detailhandel mit elektrischen Haushalts-,Radio U Fernsehger\u00e4ten sowie Musikinstrumenten",
    "sg:phone":"+41 71 744 66 53",
    "sg:postcode":"8004",
    "sg:province":"Z\u00fcrich",
    "wof:name":"Prosal Ag",
    "wof:placetype":"venue"
},
  "geometry": {"coordinates":[9.6351919174,47.4310073853],"type":"Point"}
}