{
  "type": "Feature",
  "properties": {
    "iso:country":"CH",
    "sg:address":"Hotel Saanerhof",
    "sg:city":"Saanen",
    "sg:orig_category":"Maler U Glasergewerbe Malerei",
    "sg:phone":"+41 33 744 91 17",
    "sg:postcode":"3792",
    "sg:province":"Bern",
    "wof:name":"Malergesch\u00e4ft Fiedler J\u00fcrgen D.",
    "wof:placetype":"venue"
},
  "geometry": {"coordinates":[7.2599210739,46.4897918701],"type":"Point"}
}