{
  "type": "Feature",
  "properties": {
    "iso:country":"CH",
    "sg:address":"Grenzacherstrasse 87 4000 Basel. Postfach",
    "sg:city":"Basel",
    "sg:orig_category":"Erbringung von Dienstleistungen f\u00fcr Unternehmen",
    "sg:postcode":"4051",
    "sg:province":"Basel-Stadt",
    "wof:name":"Inter Messebau Cinar",
    "wof:placetype":"venue"
},
  "geometry": {"coordinates":[7.6024861336,47.5588607788],"type":"Point"}
}