{
  "type": "Feature",
  "properties": {
    "iso:country":"CH",
    "sg:address":"Rue Des Buttes 7",
    "sg:city":"Fleurier",
    "sg:classifiers":[
        {
            "category":"Arena",
            "subcategory":"Sports Club",
            "type":"Entertainment"
        }
    ],
    "sg:postcode":"2114",
    "sg:province":"Neuch\u00e2tel",
    "sg:tags":[
        "karate",
        "judo",
        "sportvereine"
    ],
    "wof:name":"Karate-club Val De Travers",
    "wof:placetype":"venue"
},
  "geometry": {"coordinates":[6.5782179832,46.9017181396],"type":"Point"}
}