{
  "type": "Feature",
  "properties": {
    "addr:full":"Austrasse 45 3176 Neuenegg. Postfach Neuenegg Bern 3176",
    "addr:housenumber":"45",
    "addr:postcode":"3176 neuenegg. postfach;3176",
    "addr:street":"Austrasse",
    "iso:country":"CH",
    "sg:address":"Austrasse 45 3176 Neuenegg. Postfach",
    "sg:city":"Neuenegg",
    "sg:orig_category":"Architektur U Ingenieurb\u00fcros",
    "sg:phone":"+41 31 741 07 76",
    "sg:postcode":"3176",
    "sg:province":"Bern",
    "wof:name":"Gasser & M\u00fcller Ag",
    "wof:placetype":"venue"
},
  "geometry": {"coordinates":[7.311054,46.894657],"type":"Point"}
}