{
  "type": "Feature",
  "properties": {
    "iso:country":"CH",
    "sg:address":"Les Collines 34",
    "sg:city":"Develier",
    "sg:orig_category":"Malerei",
    "sg:phone":"+41 32 423 01 49",
    "sg:postcode":"2802",
    "sg:province":"Jura",
    "wof:name":"Giacomo Petrillo Entreprise De Peinture",
    "wof:placetype":"venue"
},
  "geometry": {"coordinates":[7.292702198,47.3568077087],"type":"Point"}
}