{
  "type": "Feature",
  "properties": {
    "addr:full":"Berglistrasse 34 Pfyn Thurgau 8505",
    "addr:housenumber":"34",
    "addr:postcode":"8505",
    "addr:street":"Berglistrasse",
    "iso:country":"CH",
    "sg:address":"Berglistrasse 34",
    "sg:city":"Pfyn",
    "sg:orig_category":"Datenverarbeitungsdienste Softwareentwicklung U beratung",
    "sg:phone":"+41 52 765 30 01",
    "sg:postcode":"8505",
    "sg:province":"Thurgau",
    "wof:name":"N + W Informatik Gmbh",
    "wof:placetype":"venue"
},
  "geometry": {"coordinates":[8.957863,47.594196],"type":"Point"}
}