{
  "type": "Feature",
  "properties": {
    "addr:full":"Kleinfeldstrasse 67 Ipsach Bern 2563",
    "addr:housenumber":"67",
    "addr:postcode":"2563",
    "addr:street":"Kleinfeldstrasse;Bern",
    "iso:country":"CH",
    "sg:address":"Kleinfeldstrasse 67",
    "sg:city":"Ipsach",
    "sg:orig_category":"Bauschreinerei Herstellung von Konstruktionsteilen, Fertigbauteilen U Ausbauelementen aus Holz",
    "sg:phone":"+41 71 385 11 11",
    "sg:postcode":"2563",
    "sg:province":"Bern",
    "wof:name":"Moser A., Schreinerei",
    "wof:placetype":"venue"
},
  "geometry": {"coordinates":[9.25665,47.416782],"type":"Point"}
}