{
  "type": "Feature",
  "properties": {
    "iso:country":"CH",
    "sg:address":"Rheinstrasse 169",
    "sg:city":"Chur",
    "sg:orig_category":"Grosshandel mit sonstigen Nahrungsmitteln",
    "sg:postcode":"7000",
    "sg:province":"Graubunden",
    "wof:name":"Guler Christian",
    "wof:placetype":"venue"
},
  "geometry": {"coordinates":[9.5148887634,46.8612060547],"type":"Point"}
}