{
  "type": "Feature",
  "properties": {
    "iso:country":"CH",
    "sg:address":"Stadelmatte 2",
    "sg:city":"Raron",
    "sg:orig_category":"Sportvereine Ballsport Tennis",
    "sg:phone":"+41 27 934 10 43",
    "sg:postcode":"3942",
    "sg:province":"Valais",
    "wof:name":"Tennisclub Turtig",
    "wof:placetype":"venue"
},
  "geometry": {"coordinates":[7.7987852097,46.311126709],"type":"Point"}
}