{
  "type": "Feature",
  "properties": {
    "iso:country":"CH",
    "sg:address":"Zentralstrasse 19",
    "sg:city":"Dietikon",
    "sg:orig_category":"Sanit\u00e4r, Heizungs U L\u00fcftungsinstallation",
    "sg:postcode":"8953",
    "sg:province":"Z\u00fcrich",
    "wof:name":"Reinli Kurt",
    "wof:placetype":"venue"
},
  "geometry": {"coordinates":[8.396065712,47.3415985107],"type":"Point"}
}