{
  "type": "Feature",
  "properties": {
    "addr:full":"Gutstrasse 86 Z\u00fcrich Z\u00fcrich 8055",
    "addr:housenumber":"86",
    "addr:postcode":"8055",
    "addr:street":"Gutstrasse",
    "iso:country":"CH",
    "sg:address":"Gutstrasse 86",
    "sg:city":"Z\u00fcrich",
    "sg:orig_category":"Bau U Wohngenossenschaften",
    "sg:phone":"+41 14511880",
    "sg:postcode":"8055",
    "sg:province":"Z\u00fcrich",
    "wof:name":"Baugenossenschaft Im Gut",
    "wof:placetype":"venue"
},
  "geometry": {"coordinates":[8.507134,47.371655],"type":"Point"}
}