{
  "type": "Feature",
  "properties": {
    "iso:country":"CH",
    "sg:address":"Sandackerstrasse 4",
    "sg:city":"Rheinau",
    "sg:orig_category":"Religi\u00f6se Vereinigungen divers Vereine Gemeinn\u00fctzige",
    "sg:phone":"+41 52 319 37 23",
    "sg:postcode":"8462",
    "sg:province":"Z\u00fcrich",
    "wof:name":"Ref.frauenver.rheinau-ellikon",
    "wof:placetype":"venue"
},
  "geometry": {"coordinates":[8.6043872833,47.6482658386],"type":"Point"}
}