{
  "type": "Feature",
  "properties": {
    "addr:full":"Chemin De Valfaye 11 1000 Lausanne. Postfach Lausanne Vaud 1002",
    "addr:housenumber":"11",
    "addr:postcode":"1000;postfach;1002",
    "addr:street":"Chemin De Valfaye",
    "iso:country":"CH",
    "sg:address":"Chemin De Valfaye 11 1000 Lausanne. Postfach",
    "sg:city":"Lausanne",
    "sg:orig_category":"Betrieb U technische Hilfsdienste des Kultur U Unterhaltungswesens",
    "sg:postcode":"1002",
    "sg:province":"Vaud",
    "wof:name":"Comme Il Vous Plaira S\u00e0rl",
    "wof:placetype":"venue"
},
  "geometry": {"coordinates":[6.653565,46.535782],"type":"Point"}
}