{
  "type": "Feature",
  "properties": {
    "iso:country":"CH",
    "sg:address":"Kirchweg 88-90",
    "sg:city":"Glarus",
    "sg:orig_category":"Instandhaltung U Reparatur von Automobilen",
    "sg:phone":"+41 55 640 27 27",
    "sg:postcode":"8750",
    "sg:province":"Glarus",
    "wof:name":"Garage Milt Ag",
    "wof:placetype":"venue"
},
  "geometry": {"coordinates":[9.0725917816,47.0358467102],"type":"Point"}
}