{
  "type": "Feature",
  "properties": {
    "iso:country":"CH",
    "sg:address":"Im Hanfgarten",
    "sg:city":"Ottikon",
    "sg:orig_category":"Elektroinstallation Herstellung von Elektrizit\u00e4tsverteilungs U schalteinrichtungen",
    "sg:phone":"+41 19351819",
    "sg:postcode":"8626",
    "sg:province":"Z\u00fcrich",
    "wof:name":"Hestec Ag",
    "wof:placetype":"venue"
},
  "geometry": {"coordinates":[8.7776603699,47.2923126221],"type":"Point"}
}