{
  "type": "Feature",
  "properties": {
    "iso:country":"CH",
    "sg:address":"Falkensteinerstrasse 57 4053 Basel. Postfach",
    "sg:city":"Basel",
    "sg:orig_category":"Wirtschaftspr\u00fcfung, Steuerberatung U Treuhand",
    "sg:phone":"+41 61 332 00 44",
    "sg:postcode":"4051",
    "sg:province":"Basel-Stadt",
    "wof:name":"Humbel Hans Rudolf Treuhandb\u00fcro",
    "wof:placetype":"venue"
},
  "geometry": {"coordinates":[7.6011390686,47.538444519],"type":"Point"}
}