{
  "type": "Feature",
  "properties": {
    "iso:country":"CH",
    "sg:address":"Rue Du Vieux-moulin 13",
    "sg:city":"Onex",
    "sg:orig_category":"Fussreflexzonenmassage",
    "sg:phone":"+41 22 792 45 04",
    "sg:postcode":"1213",
    "sg:province":"Gen\u00e8ve",
    "wof:name":"Marguerite Borcard Massage & R\u00e9flexologie",
    "wof:placetype":"venue"
},
  "geometry": {"coordinates":[6.0991139412,46.1894187927],"type":"Point"}
}