{
  "type": "Feature",
  "properties": {
    "iso:country":"CH",
    "sg:address":"Merkurstrasse 2",
    "sg:city":"Sursee",
    "sg:orig_category":"Sonstiger Grosshandel",
    "sg:phone":"+41 41 920 32 10",
    "sg:postcode":"6210",
    "sg:province":"Luzern",
    "wof:name":"Dulin Naturprodukte Wespi & B\u00e4ttig",
    "wof:placetype":"venue"
},
  "geometry": {"coordinates":[8.1014461517,47.1674919128],"type":"Point"}
}