{
  "type": "Feature",
  "properties": {
    "iso:country":"CH",
    "sg:address":"Neufuhr",
    "sg:city":"Ballwil",
    "sg:orig_category":"Detailhandel mit Milcherzeugnissen U Eiern Verarbeitung von Milch",
    "sg:postcode":"6275",
    "sg:province":"Luzern",
    "wof:name":"Milchverwertungsgenossenschaft Arni",
    "wof:placetype":"venue"
},
  "geometry": {"coordinates":[8.4309101105,47.3179206848],"type":"Point"}
}