{
  "type": "Feature",
  "properties": {
    "iso:country":"CH",
    "sg:address":"Neugasse 18a",
    "sg:city":"Oberuzwil",
    "sg:orig_category":"Bauspenglerei Sanit\u00e4r, Heizungs U L\u00fcftungsinstallation",
    "sg:phone":"+41 71 951 23 09",
    "sg:postcode":"9242",
    "sg:province":"St. Gallen",
    "wof:name":"Rieser Hans Ag",
    "wof:placetype":"venue"
},
  "geometry": {"coordinates":[9.127536,47.430248],"type":"Point"}
}