{
  "type": "Feature",
  "properties": {
    "iso:country":"CH",
    "sg:address":"Park",
    "sg:city":"Altenrhein",
    "sg:orig_category":"Herstellung von Kunststoffwaren",
    "sg:phone":"+41 71 855 70 77",
    "sg:postcode":"9423",
    "sg:province":"St. Gallen",
    "wof:name":"Sta Strukturwerkstoffe Altenrhein Ag",
    "wof:placetype":"venue"
},
  "geometry": {"coordinates":[9.5517377853,47.4903907776],"type":"Point"}
}