{
  "type": "Feature",
  "properties": {
    "iso:country":"CH",
    "sg:address":"Regensdorferstrasse 14",
    "sg:city":"Niederhasli",
    "sg:orig_category":"Handel mit Motorr\u00e4dern, Teilen U Zubeh\u00f6r Instandhaltung U Reparatur von Motorr\u00e4dern",
    "sg:phone":"+41 32 631 19 22",
    "sg:postcode":"8155",
    "sg:province":"Z\u00fcrich",
    "wof:name":"Zuber Beat",
    "wof:placetype":"venue"
},
  "geometry": {"coordinates":[7.6506237984,47.2289390564],"type":"Point"}
}