{
  "type": "Feature",
  "properties": {
    "iso:country":"CH",
    "sg:address":"Inselspital",
    "sg:city":"Bern",
    "sg:orig_category":"Kantonalbanken",
    "sg:phone":"+41 33 748 74 44",
    "sg:postcode":"3010",
    "sg:province":"Bern",
    "wof:name":"Berner Kantonalbank Bekb/bcbe",
    "wof:placetype":"venue"
},
  "geometry": {"coordinates":[7.2839550972,46.4762382507],"type":"Point"}
}