{
  "type": "Feature",
  "properties": {
    "iso:country":"CH",
    "sg:address":"Route Des Carolins 61",
    "sg:city":"Sion",
    "sg:orig_category":"Herstellung von Metallkonstruktionen",
    "sg:phone":"+41 27 203 47 51",
    "sg:postcode":"1950",
    "sg:province":"Valais",
    "wof:name":"Ls S\u00e0rl",
    "wof:placetype":"venue"
},
  "geometry": {"coordinates":[7.3627400398,46.2214508057],"type":"Point"}
}