{
  "type": "Feature",
  "properties": {
    "iso:country":"CH",
    "sg:address":"6816",
    "sg:city":"Bissone",
    "sg:orig_category":"Finanzierungsinstitutionen",
    "sg:postcode":"6816",
    "sg:province":"Ticino",
    "wof:name":"Grimoba Ag",
    "wof:placetype":"venue"
},
  "geometry": {"coordinates":[8.9648704529,45.9505004883],"type":"Point"}
}