{
  "type": "Feature",
  "properties": {
    "iso:country":"CH",
    "sg:address":"Gotthardstrasse 67",
    "sg:city":"Basel",
    "sg:orig_category":"Unclassifiable Establishments",
    "sg:postcode":"4054",
    "sg:province":"Basel-Stadt",
    "wof:name":"Idp Internet & Desktop Publishing Heidy Stricker",
    "wof:placetype":"venue"
},
  "geometry": {"coordinates":[7.5624628067,47.5491142273],"type":"Point"}
}