{
  "type": "Feature",
  "properties": {
    "iso:country":"CH",
    "sg:address":"Mittengrabenstrasse 56",
    "sg:city":"Interlaken",
    "sg:orig_category":"Sonderschulen Wohnheime",
    "sg:phone":"+41 33 822 11 39",
    "sg:postcode":"3800",
    "sg:province":"Bern",
    "wof:name":"Rbz Regionales Behindertenzentrum Interlaken",
    "wof:placetype":"venue"
},
  "geometry": {"coordinates":[7.8718218803,46.6874084473],"type":"Point"}
}