{
  "type": "Feature",
  "properties": {
    "iso:country":"CH",
    "sg:address":"Bielstrasse 24",
    "sg:city":"Solothurn",
    "sg:classifiers":[
        {
            "category":"Education",
            "subcategory":"Vocational School",
            "type":"Public Place"
        }
    ],
    "sg:postcode":"4500",
    "sg:province":"Solothurn",
    "sg:tags":[
        "koch-",
        "haushaltschulen"
    ],
    "wof:name":"Haushaltungsschule Der Stadt Solothurn",
    "wof:placetype":"venue"
},
  "geometry": {"coordinates":[7.5310101509,47.2094497681],"type":"Point"}
}