{
  "type": "Feature",
  "properties": {
    "iso:country":"CH",
    "sg:address":"Baslerstrasse 106",
    "sg:city":"Z\u00fcrich",
    "sg:orig_category":"Kauf U Verkauf von Immobilien auf eigene Rechnung",
    "sg:postcode":"8048",
    "sg:province":"Z\u00fcrich",
    "wof:name":"Kolumban Teufen Ag",
    "wof:placetype":"venue"
},
  "geometry": {"coordinates":[9.3857593536,47.3929634094],"type":"Point"}
}