{
  "type": "Feature",
  "properties": {
    "iso:country":"CH",
    "sg:address":"Br\u00fcckenweg 6 3930 Visp. Postfach 145",
    "sg:city":"Visp",
    "sg:classifiers":[
        {
            "category":"Travel",
            "subcategory":"Hotels & Motels",
            "type":"Entertainment"
        }
    ],
    "sg:phone":"+41 27 946 34 62",
    "sg:postcode":"3930",
    "sg:province":"Valais",
    "sg:tags":[
        "hotels",
        "mit",
        "restaurant"
    ],
    "wof:name":"Hotel Garni Alba, Ruff Lea",
    "wof:placetype":"venue"
},
  "geometry": {"coordinates":[7.8800721169,46.2930450439],"type":"Point"}
}