{
  "type": "Feature",
  "properties": {
    "iso:country":"CH",
    "sg:address":"Route Provence",
    "sg:city":"Concise",
    "sg:orig_category":"Maurerarbeiten Verlegen von Fliesen U Platten",
    "sg:phone":"+41 24 434 14 24",
    "sg:postcode":"1426",
    "sg:province":"Vaud",
    "wof:name":"Jean-claude Vienet Ma\u00e7onnerie & Carrelage",
    "wof:placetype":"venue"
},
  "geometry": {"coordinates":[6.7187781334,46.8558578491],"type":"Point"}
}