{
  "type": "Feature",
  "properties": {
    "iso:country":"CH",
    "sg:address":"Ciossi Via Ai",
    "sg:city":"Losone",
    "sg:orig_category":"Architektur U Ingenieurb\u00fcros",
    "sg:phone":"+41 91 791 58 33",
    "sg:postcode":"6616",
    "sg:province":"Ticino",
    "wof:name":"Rovotech Gmbh",
    "wof:placetype":"venue"
},
  "geometry": {"coordinates":[8.761185,46.162785],"type":"Point"}
}