{
  "type": "Feature",
  "properties": {
    "iso:country":"CH",
    "sg:address":"Chemin Du Pr\u00e9 Neuf",
    "sg:city":"Yverdon-les-bains",
    "sg:orig_category":"Detailhandel mit B\u00fcchern Detailhandel mit Schreib U Papeteriewaren",
    "sg:phone":"+41 24 445 33 35",
    "sg:postcode":"1400",
    "sg:province":"Vaud",
    "wof:name":"Eric Chapuis Bureaucentre",
    "wof:placetype":"venue"
},
  "geometry": {"coordinates":[6.64142,46.778633],"type":"Point"}
}