{
  "type": "Feature",
  "properties": {
    "iso:country":"CH",
    "sg:address":"Stockbrunnenrain 2",
    "sg:city":"Allschwil",
    "sg:orig_category":"Tankstellen",
    "sg:postcode":"4123",
    "sg:province":"Basel-Landschaft",
    "wof:name":"Rohner Edwin Gmbh",
    "wof:placetype":"venue"
},
  "geometry": {"coordinates":[7.5539340973,47.5463829041],"type":"Point"}
}