{
  "type": "Feature",
  "properties": {
    "iso:country":"CH",
    "sg:address":"Gemeindestrasse 54",
    "sg:city":"Z\u00fcrich",
    "sg:orig_category":"Sonstige Kultur U Unterhaltungseinrichtungen",
    "sg:phone":"+41 12510229",
    "sg:postcode":"8032",
    "sg:province":"Z\u00fcrich",
    "wof:name":"Freizeitanlage Hottingen",
    "wof:placetype":"venue"
},
  "geometry": {"coordinates":[8.5558433533,47.3695449829],"type":"Point"}
}