{
  "type": "Feature",
  "properties": {
    "iso:country":"CH",
    "sg:address":"Fl\u00e4cke",
    "sg:city":"Berom\u00fcnster",
    "sg:classifiers":[
        {
            "category":"Banks & Credit Unions",
            "subcategory":"Bank",
            "type":"Services"
        }
    ],
    "sg:phone":"+41 41 930 37 37",
    "sg:postcode":"6215",
    "sg:province":"Luzern",
    "wof:name":"Bank In Menziken",
    "wof:placetype":"venue"
},
  "geometry": {"coordinates":[8.192506,47.206577],"type":"Point"}
}