{
  "type": "Feature",
  "properties": {
    "addr:full":"Figino Figino Ticino 6918",
    "addr:housenumber":"6918",
    "iso:country":"CH",
    "sg:address":"Figino",
    "sg:city":"Figino",
    "sg:classifiers":[
        {
            "category":"Banks & Credit Unions",
            "subcategory":"Bank",
            "type":"Services"
        }
    ],
    "sg:phone":"+41 91601734",
    "sg:postcode":"6918",
    "sg:province":"Ticino",
    "wof:name":"Rentenanstalt Swiss Life",
    "wof:placetype":"venue"
},
  "geometry": {"coordinates":[8.91063,45.952148],"type":"Point"}
}