{
  "type": "Feature",
  "properties": {
    "iso:country":"CH",
    "sg:address":"Z\u00fcrcherstrasse 178",
    "sg:city":"Frauenfeld",
    "sg:orig_category":"Non-Classified Establishments",
    "sg:postcode":"8500",
    "sg:province":"Thurgau",
    "wof:name":"Fashion Corner Ag Damenmodegesch\u00e4ft",
    "wof:placetype":"venue"
},
  "geometry": {"coordinates":[8.8979997635,47.5568008423],"type":"Point"}
}