{
  "type": "Feature",
  "properties": {
    "iso:country":"CH",
    "sg:address":"Buechstr. 37",
    "sg:city":"Jona",
    "sg:orig_category":"Engines and parts Health - equipments and instruments Leather and Shoes Leather goods Mechanical Eng",
    "sg:phone":"+41 55 225 35 35",
    "sg:postcode":"8645",
    "sg:province":"St. Gallen",
    "wof:name":"Ammeraal Beltech Ag",
    "wof:placetype":"venue"
},
  "geometry": {"coordinates":[8.8697805405,47.2277603149],"type":"Point"}
}