{
  "type": "Feature",
  "properties": {
    "iso:country":"CH",
    "sg:address":"Mitteldorfstrasse 37",
    "sg:city":"Buchs",
    "sg:classifiers":[
        {
            "category":"Professional",
            "subcategory":"Computer Services",
            "type":"Services"
        }
    ],
    "sg:phone":"+41 62 822 44 33",
    "sg:postcode":"5033",
    "sg:province":"Aargau",
    "sg:tags":[
        "development",
        "software"
    ],
    "wof:name":"Presida Treuhand Ag",
    "wof:placetype":"venue"
},
  "geometry": {"coordinates":[8.0700540543,47.3901634216],"type":"Point"}
}