{
  "type": "Feature",
  "properties": {
    "iso:country":"CH",
    "sg:address":"Rue Du Vuache 1",
    "sg:city":"Gen\u00e8ve",
    "sg:orig_category":"Advokaturb\u00fcros",
    "sg:phone":"+41 22 339 90 50",
    "sg:postcode":"1201",
    "sg:province":"Gen\u00e8ve",
    "wof:name":"Robert Simon Etude D'avocat",
    "wof:placetype":"venue"
},
  "geometry": {"coordinates":[6.137957,46.207497],"type":"Point"}
}