{
  "type": "Feature",
  "properties": {
    "iso:country":"CH",
    "sg:address":"Avenue Wendt 41",
    "sg:city":"Gen\u00e8ve",
    "sg:orig_category":"Reiseb\u00fcros U Reiseveranstalter",
    "sg:phone":"+41 79 628 79 50",
    "sg:postcode":"1203",
    "sg:province":"Gen\u00e8ve",
    "wof:name":"Lakeside Marketing Sarl",
    "wof:placetype":"venue"
},
  "geometry": {"coordinates":[6.1272678375,46.2117462158],"type":"Point"}
}