{
  "type": "Feature",
  "properties": {
    "iso:country":"CH",
    "sg:address":"Sempacherstrasse 69 8032 Z\u00fcrich. Postfach 571",
    "sg:city":"Z\u00fcrich",
    "sg:orig_category":"Public-Relations-Agenturen",
    "sg:phone":"+41 14223366",
    "sg:postcode":"8029",
    "wof:name":"M.e.s. Public Relations Ag Mireille E. Saucy",
    "wof:placetype":"venue"
},
  "geometry": {"coordinates":[8.5694417953,47.3602714539],"type":"Point"}
}