{
  "type": "Feature",
  "properties": {
    "iso:country":"CH",
    "sg:address":"M\u00e4ttenlehn",
    "sg:city":"Steinhuserberg",
    "sg:orig_category":"Vereine Gesang and Jodler",
    "sg:phone":"+41 41 490 13 84",
    "sg:postcode":"6114",
    "sg:province":"Luzern",
    "wof:name":"Jodlerklub B\u00e4rggl\u00f6ggli Steinhuserberg",
    "wof:placetype":"venue"
},
  "geometry": {"coordinates":[8.0475902557,47.042098999],"type":"Point"}
}