{
  "type": "Feature",
  "properties": {
    "iso:country":"CH",
    "sg:address":"Zollikerstrasse 147 8008 Z\u00fcrich. Postfach",
    "sg:city":"Z\u00fcrich",
    "sg:orig_category":"Informatikdienste Softwareentwicklung U beratung",
    "sg:phone":"+41 13805796",
    "sg:postcode":"8008",
    "sg:province":"Z\u00fcrich",
    "wof:name":"Itiso Gmbh Projektleitungen U. Dienstleistungen Im Zusammenhang Mit Informationstechnologie Usw",
    "wof:placetype":"venue"
},
  "geometry": {"coordinates":[8.5611810684,47.3561325073],"type":"Point"}
}