{
  "type": "Feature",
  "properties": {
    "iso:country":"CH",
    "sg:address":"M\u00fcnstergasse 17",
    "sg:city":"Z\u00fcrich",
    "sg:orig_category":"RESTAURANTS: TEA-ROOMS",
    "sg:postcode":"8001",
    "sg:province":"Z\u00fcrich",
    "wof:name":"Schwarzenbach H. + B., Teecaf\u00e9",
    "wof:placetype":"venue"
},
  "geometry": {"coordinates":[8.5439977646,47.3713417053],"type":"Point"}
}