{
  "type": "Feature",
  "properties": {
    "iso:country":"CH",
    "sg:address":"Gerbergasse 2",
    "sg:city":"Basel",
    "sg:orig_category":"Sonstige pers\u00f6nliche Dienstleistungen",
    "sg:postcode":"4001",
    "sg:province":"Basel-Stadt",
    "wof:name":"Lenz Consult Gmbh",
    "wof:placetype":"venue"
},
  "geometry": {"coordinates":[7.5878357887,47.5576019287],"type":"Point"}
}