{
  "type": "Feature",
  "properties": {
    "iso:country":"CH",
    "sg:address":"Obere Stallstrasse 91",
    "sg:city":"Thusis",
    "sg:orig_category":"Arbeitnehmerverb\u00e4nde",
    "sg:postcode":"7430",
    "sg:province":"Graubunden",
    "wof:name":"Schweiz.dachdeckermeister- Verband",
    "wof:placetype":"venue"
},
  "geometry": {"coordinates":[9.438835,46.697796],"type":"Point"}
}