{
  "type": "Feature",
  "properties": {
    "iso:country":"CH",
    "sg:address":"F\u00f6hrenstrasse 10",
    "sg:city":"Kronb\u00fchl",
    "sg:orig_category":"Politische Parteien CVP",
    "sg:phone":"+41 71 222 33 84",
    "sg:postcode":"9302",
    "wof:name":"Cvp Ortspartei Kronb\u00fchl",
    "wof:placetype":"venue"
},
  "geometry": {"coordinates":[9.3907566071,47.4559707642],"type":"Point"}
}