{
  "type": "Feature",
  "properties": {
    "iso:country":"CH",
    "sg:address":"7503",
    "sg:city":"Samedan",
    "sg:orig_category":"Allgemeiner Hoch U Tiefbau Allgemeiner Hochbau",
    "sg:phone":"+41 81 851 10 51",
    "sg:postcode":"7503",
    "sg:province":"Graubunden",
    "wof:name":"Lazzarini G. & Co Ag",
    "wof:placetype":"venue"
},
  "geometry": {"coordinates":[9.872837,46.535358],"type":"Point"}
}