{
  "type": "Feature",
  "properties": {
    "iso:country":"CH",
    "sg:address":"Oberer Graben 16",
    "sg:city":"St.gallen",
    "sg:orig_category":"Interessenvertretungen",
    "sg:phone":"+41 71 222 23 93",
    "sg:postcode":"9000",
    "sg:province":"St. Gallen",
    "wof:name":"Stiftung F\u00fcr Alters Und Hinterbliebenen-versorgung Der Angeh\u00f6rigen Europ\u00e4ischer Heilberufe.",
    "wof:placetype":"venue"
},
  "geometry": {"coordinates":[9.3736371994,47.4244003296],"type":"Point"}
}