{
  "type": "Feature",
  "properties": {
    "iso:country":"CH",
    "sg:address":"Arosastrasse 25 8008 Z\u00fcrich. Postfach",
    "sg:city":"Z\u00fcrich",
    "sg:orig_category":"Erbringung von Dienstleistungen f\u00fcr Unternehmen",
    "sg:phone":"+41 21 943 57 77",
    "sg:postcode":"8001",
    "sg:province":"Z\u00fcrich",
    "wof:name":"Mtx Cr\u00e9ation Sa",
    "wof:placetype":"venue"
},
  "geometry": {"coordinates":[6.8622179031,46.4730606079],"type":"Point"}
}