{
  "type": "Feature",
  "properties": {
    "iso:country":"CH",
    "sg:address":"Rotfluhstrasse 96",
    "sg:city":"Zollikon",
    "sg:classifiers":[
        {
            "category":"Restaurant",
            "type":"Food & Drink"
        }
    ],
    "sg:phone":"+41 13912969",
    "sg:postcode":"8702",
    "sg:province":"Z\u00fcrich",
    "wof:name":"Restaurant Zollikerstube",
    "wof:placetype":"venue"
},
  "geometry": {"coordinates":[8.576748848,47.3378295898],"type":"Point"}
}