{
  "type": "Feature",
  "properties": {
    "iso:country":"CH",
    "sg:address":"Chaletweg 6",
    "sg:city":"Oberg\u00f6sgen",
    "sg:orig_category":"Unternehmensberatung",
    "sg:postcode":"4653",
    "sg:province":"Solothurn",
    "wof:name":"Ccs Bieri",
    "wof:placetype":"venue"
},
  "geometry": {"coordinates":[8.7856559753,47.2003364563],"type":"Point"}
}