{
  "type": "Feature",
  "properties": {
    "iso:country":"CH",
    "sg:address":"Aarweg 7",
    "sg:city":"M\u00fcnsingen",
    "sg:orig_category":"Kaminfeger Sanit\u00e4r U Heizungsinstallation",
    "sg:phone":"+41 19106159",
    "sg:postcode":"3110",
    "sg:province":"Bern",
    "wof:name":"Robert Zimmermann Kaminfegergesch\u00e4ft Heizungen",
    "wof:placetype":"venue"
},
  "geometry": {"coordinates":[8.5805044174,47.3156547546],"type":"Point"}
}