{
  "type": "Feature",
  "properties": {
    "iso:country":"CH",
    "sg:address":"Hauptstrasse 3792 Saanen. Postfach",
    "sg:city":"Sch\u00f6nried",
    "sg:orig_category":"Detailhandel mit Fleisch U Fleischwaren",
    "sg:phone":"+41 32 352 00 00",
    "sg:postcode":"3778",
    "sg:province":"Bern",
    "wof:name":"Bigler Ag Fleischwaren",
    "wof:placetype":"venue"
},
  "geometry": {"coordinates":[7.3608789444,47.1358757019],"type":"Point"}
}