{
  "type": "Feature",
  "properties": {
    "addr:full":"Erde Erde Valais 1976",
    "addr:housenumber":"1976",
    "iso:country":"CH",
    "sg:address":"Erde",
    "sg:city":"Erde",
    "sg:classifiers":[
        {
            "category":"Banks & Credit Unions",
            "subcategory":"Bank",
            "type":"Services"
        }
    ],
    "sg:phone":"+41 27364422",
    "sg:postcode":"1976",
    "sg:province":"Valais",
    "wof:name":"Banque Cantonale Du Valais",
    "wof:placetype":"venue"
},
  "geometry": {"coordinates":[7.29234,46.237949],"type":"Point"}
}