{
  "type": "Feature",
  "properties": {
    "iso:country":"CH",
    "sg:address":"Route De Saint-cergue 83",
    "sg:city":"Nyon",
    "sg:classifiers":[
        {
            "category":"Travel",
            "subcategory":"Hotels & Motels",
            "type":"Entertainment"
        }
    ],
    "sg:phone":"+41 21 323 23 82",
    "sg:postcode":"1260",
    "sg:province":"Vaud",
    "sg:tags":[
        "hotels",
        "mit",
        "restaurant"
    ],
    "wof:name":"Ecobiologie.ch Sa",
    "wof:placetype":"venue"
},
  "geometry": {"coordinates":[6.230905056,46.3935127258],"type":"Point"}
}