{
  "type": "Feature",
  "properties": {
    "iso:country":"CH",
    "sg:address":"Lenzburgerstrasse 2 5702 Niederlenz. Postfach 118",
    "sg:city":"Niederlenz",
    "sg:orig_category":"Pensionskassen",
    "sg:postcode":"5702",
    "sg:province":"Aargau",
    "wof:name":"Vorsorgestiftung Der Hetex Garn Ag",
    "wof:placetype":"venue"
},
  "geometry": {"coordinates":[8.177564621,47.3990745544],"type":"Point"}
}