{
  "type": "Feature",
  "properties": {
    "iso:country":"CH",
    "sg:address":"Le Bourgeal",
    "sg:city":"Orsi\u00e8res",
    "sg:orig_category":"Detailhandel mit Brot, Back U S\u00fcsswaren",
    "sg:phone":"+41 27 783 27 27",
    "sg:postcode":"1937",
    "sg:province":"Valais",
    "wof:name":"Laurent Joris Boulangerie",
    "wof:placetype":"venue"
},
  "geometry": {"coordinates":[7.144377,46.031067],"type":"Point"}
}