{
  "type": "Feature",
  "properties": {
    "addr:full":"Gass 24 Schneisingen Aargau 5425",
    "addr:housenumber":"24",
    "addr:postcode":"5425",
    "addr:street":"Gass",
    "iso:country":"CH",
    "sg:address":"Gass 24",
    "sg:city":"Schneisingen",
    "sg:orig_category":"Datenverarbeitungsdienste Softwareentwicklung U beratung",
    "sg:postcode":"5425",
    "sg:province":"Aargau",
    "wof:name":"Ruedi Besimo Allround Informatic Services",
    "wof:placetype":"venue"
},
  "geometry": {"coordinates":[8.370172,47.521252],"type":"Point"}
}