{
  "type": "Feature",
  "properties": {
    "iso:country":"CH",
    "sg:address":"Neustadtstrasse 24",
    "sg:city":"Luzern",
    "sg:orig_category":"Sonstige mit der Informatik verbundene T\u00e4tigkeiten",
    "sg:phone":"+41 41 361 11 29",
    "sg:postcode":"6003",
    "sg:province":"Luzern",
    "wof:name":"Net.worxs Homberger Marco",
    "wof:placetype":"venue"
},
  "geometry": {"coordinates":[8.3085680008,47.0431480408],"type":"Point"}
}