{
  "type": "Feature",
  "properties": {
    "iso:country":"CH",
    "sg:address":"Z\u00fcrichstrasse 38",
    "sg:city":"Einsiedeln",
    "sg:orig_category":"Sportvereine Motorrad",
    "sg:phone":"+41 55 412 75 81",
    "sg:postcode":"8840",
    "sg:province":"Schwyz",
    "wof:name":"Motorrad-club Crowns Tc",
    "wof:placetype":"venue"
},
  "geometry": {"coordinates":[8.7443847656,47.1315841675],"type":"Point"}
}