{
  "type": "Feature",
  "properties": {
    "iso:country":"CH",
    "sg:address":"Via Rinaldo Simen 89",
    "sg:city":"Minusio",
    "sg:orig_category":"Kaminfeger",
    "sg:phone":"+41 91 743 76 23",
    "sg:postcode":"6648",
    "sg:province":"Ticino",
    "wof:name":"Kurmann Sagl Spazzacamini",
    "wof:placetype":"venue"
},
  "geometry": {"coordinates":[8.8278865814,46.1784057617],"type":"Point"}
}