{
  "type": "Feature",
  "properties": {
    "iso:country":"CH",
    "sg:address":"9107 Urn\u00e4sch. Postfach 102",
    "sg:city":"Urn\u00e4sch",
    "sg:orig_category":"Sportvereine Ballsport Fussball",
    "sg:phone":"+41 71 364 12 11",
    "sg:postcode":"9107",
    "sg:province":"Appenzell Ausserrhoden",
    "wof:name":"Fc Urn\u00e4sch",
    "wof:placetype":"venue"
},
  "geometry": {"coordinates":[9.2835702896,47.3174514771],"type":"Point"}
}