{
  "type": "Feature",
  "properties": {
    "iso:country":"CH",
    "sg:address":"Li Geri",
    "sg:city":"Campocologno",
    "sg:orig_category":"Allgemeiner Hoch U Tiefbau Hoch U Tiefbau",
    "sg:phone":"+41 79 681 62 75",
    "sg:postcode":"7744",
    "sg:province":"Graubunden",
    "wof:name":"Pianta Pasquale.",
    "wof:placetype":"venue"
},
  "geometry": {"coordinates":[10.141491,46.234035],"type":"Point"}
}