{
  "type": "Feature",
  "properties": {
    "iso:country":"CH",
    "sg:address":"Rue Des Draizes 90",
    "sg:city":"Neuch\u00e2tel",
    "sg:orig_category":"Detailhandel mit Antiquit\u00e4ten",
    "sg:phone":"+41 32 731 19 62",
    "sg:postcode":"2000",
    "sg:province":"Neuch\u00e2tel",
    "wof:name":"Laurent Richard Antiquit\u00e9s",
    "wof:placetype":"venue"
},
  "geometry": {"coordinates":[6.898686,46.988907],"type":"Point"}
}