{
  "type": "Feature",
  "properties": {
    "iso:country":"CH",
    "sg:address":"Vattagne Via Alle",
    "sg:city":"Tegna",
    "sg:orig_category":"Herstellung von sonstigen keramischen Erzeugnissen",
    "sg:phone":"+41 91 780 79 21",
    "sg:postcode":"6652",
    "sg:province":"Ticino",
    "wof:name":"Creative Tile Design Sagl",
    "wof:placetype":"venue"
},
  "geometry": {"coordinates":[8.7447624207,46.1868515015],"type":"Point"}
}