{
  "type": "Feature",
  "properties": {
    "iso:country":"CH",
    "sg:address":"Via San Martino",
    "sg:city":"Mendrisio",
    "sg:orig_category":"Grosshandel mit sonstigen Maschinen U Ausr\u00fcstungen f\u00fcr Industrie, Handel U Schiffahrt",
    "sg:phone":"+41 91 646 19 50",
    "sg:postcode":"6850",
    "sg:province":"Ticino",
    "wof:name":"Wayne Switzerland Dresser Europe Sa",
    "wof:placetype":"venue"
},
  "geometry": {"coordinates":[8.984539032,45.875793457],"type":"Point"}
}