{
  "type": "Feature",
  "properties": {
    "iso:country":"CH",
    "sg:address":"Untergasse 42 2500 Biel/bienne. Postfach",
    "sg:city":"Biel/bienne",
    "sg:orig_category":"Fachdetailhandel in Verkaufsr\u00e4umen",
    "sg:postcode":"2502",
    "sg:province":"Bern",
    "wof:name":"Art N'art, Bl\u00f6chlinger Rosemarie",
    "wof:placetype":"venue"
},
  "geometry": {"coordinates":[7.2475838661,47.1421661377],"type":"Point"}
}