{
  "type": "Feature",
  "properties": {
    "iso:country":"CH",
    "sg:address":"Gemeindekanzlei",
    "sg:city":"Sumvitg",
    "sg:orig_category":"Fernmeldedienste",
    "sg:phone":"+41 81 943 21 92",
    "sg:postcode":"7175",
    "sg:province":"Graubunden",
    "wof:name":"Genossenschaft Satellitenb\u00fcro Sumvitg",
    "wof:placetype":"venue"
},
  "geometry": {"coordinates":[8.935792923,46.7273597717],"type":"Point"}
}