{
  "type": "Feature",
  "properties": {
    "iso:country":"CH",
    "sg:address":"Ch\u00e2teau Avenue Du 49",
    "sg:city":"Prilly",
    "sg:orig_category":"Stukkateurgewerbe, Gipserei U Verputzerei",
    "sg:phone":"+41 79 210 87 86",
    "sg:postcode":"1008",
    "sg:province":"Vaud",
    "wof:name":"Monti Willy Et Michel Sa",
    "wof:placetype":"venue"
},
  "geometry": {"coordinates":[6.6061439514,46.5340614319],"type":"Point"}
}