{
  "type": "Feature",
  "properties": {
    "iso:country":"CH",
    "sg:address":"Weingasse 102",
    "sg:city":"Hilfikon",
    "sg:orig_category":"Sanit\u00e4r, Heizungs U L\u00fcftungsinstallation",
    "sg:phone":"+41 71 931 10 89",
    "sg:postcode":"5613",
    "sg:province":"Aargau",
    "wof:name":"Martin Sch\u00f6nenberger Ag Wil Bedachungen - Spenglerei",
    "wof:placetype":"venue"
},
  "geometry": {"coordinates":[9.059882164,47.4699363708],"type":"Point"}
}