{
  "type": "Feature",
  "properties": {
    "iso:country":"CH",
    "sg:address":"Hauptstrasse 302",
    "sg:city":"Brienz",
    "sg:classifiers":[
        {
            "category":"Education",
            "subcategory":"Library",
            "type":"Public Place"
        }
    ],
    "sg:phone":"+41 33 951 26 26",
    "sg:postcode":"3855",
    "sg:province":"Bern",
    "sg:tags":[
        "interior",
        "equipment",
        "archive"
    ],
    "wof:name":"Fl\u00fcck Werke Ag",
    "wof:placetype":"venue"
},
  "geometry": {"coordinates":[8.04557,46.753399],"type":"Point"}
}