{
  "type": "Feature",
  "properties": {
    "iso:country":"CH",
    "sg:address":"Bahnhofstrasse 31 8320 Fehraltorf. Postfach",
    "sg:city":"Fehraltorf",
    "sg:orig_category":"Erwachsenenbildung U Unterricht",
    "sg:phone":"+41 19543439",
    "sg:postcode":"8320",
    "sg:province":"Z\u00fcrich",
    "wof:name":"Pede Ch Simon Urs Personal Development, Verkaufstraining, Hard Und Software Training",
    "wof:placetype":"venue"
},
  "geometry": {"coordinates":[8.7511758804,47.3855819702],"type":"Point"}
}