{
  "type": "Feature",
  "properties": {
    "iso:country":"CH",
    "sg:address":"Tivoli",
    "sg:city":"Spreitenbach",
    "sg:orig_category":"Detailhandel mit M\u00f6beln Detailhandel mit Teppichen",
    "sg:phone":"+41 71 923 27 55",
    "sg:postcode":"8957",
    "sg:province":"Aargau",
    "wof:name":"Lipo-m\u00f6belposten Ag",
    "wof:placetype":"venue"
},
  "geometry": {"coordinates":[9.0532541275,47.4513130188],"type":"Point"}
}