{
  "type": "Feature",
  "properties": {
    "iso:country":"CH",
    "sg:address":"Le Vieux-cerisier Arveyes",
    "sg:city":"Villars-sur-ollon",
    "sg:orig_category":"Kinderkrippen U horte",
    "sg:postcode":"1884",
    "sg:province":"Vaud",
    "wof:name":"Roland Gysin Garderie D'enfants",
    "wof:placetype":"venue"
},
  "geometry": {"coordinates":[7.0550079346,46.2969665527],"type":"Point"}
}