{
  "type": "Feature",
  "properties": {
    "iso:country":"CH",
    "sg:address":"Route Du Ch\u00e2no 33",
    "sg:city":"Belfaux",
    "sg:orig_category":"Gaskets, Washers, Seals",
    "sg:phone":"+41 26 475 34 45",
    "sg:postcode":"1782",
    "sg:province":"Fribourg",
    "wof:name":"Variotechnik Sa",
    "wof:placetype":"venue"
},
  "geometry": {"coordinates":[7.0947642326,46.8235702515],"type":"Point"}
}