{
  "type": "Feature",
  "properties": {
    "iso:country":"CH",
    "sg:address":"6986 Curio. Postfach",
    "sg:city":"Curio",
    "sg:orig_category":"Architektur U Ingenieurb\u00fcros",
    "sg:postcode":"6986",
    "sg:province":"Ticino",
    "wof:name":"Scharpf Linus",
    "wof:placetype":"venue"
},
  "geometry": {"coordinates":[7.243018,47.274029],"type":"Point"}
}