{
  "type": "Feature",
  "properties": {
    "iso:country":"CH",
    "sg:address":"6900 Lugano. Postfach 6906 Lugano",
    "sg:city":"Caselle",
    "sg:classifiers":[
        {
            "category":"Travel",
            "subcategory":"Hotels & Motels",
            "type":"Entertainment"
        }
    ],
    "sg:postcode":"6",
    "sg:tags":[
        "hotels",
        "mit",
        "restaurant"
    ],
    "wof:name":"Loosli Christian.",
    "wof:placetype":"venue"
},
  "geometry": {"coordinates":[7.131289959,47.2574310303],"type":"Point"}
}