{
  "type": "Feature",
  "properties": {
    "addr:full":"Chemin Du Closelet 2 1006 Lausanne Case Postale 1029 Lausanne Vaud 1001",
    "addr:housenumber":"2",
    "addr:postcode":"1006;1029;1001",
    "addr:street":"Chemin Du Closelet;Postale",
    "iso:country":"CH",
    "sg:address":"Chemin Du Closelet 2 1006 Lausanne Case Postale 1029",
    "sg:city":"Lausanne",
    "sg:orig_category":"Advokaturb\u00fcros",
    "sg:phone":"+41 21 617 36 14",
    "sg:postcode":"1001",
    "sg:province":"Vaud",
    "wof:name":"Urbain Lambercy Etude D'avocat",
    "wof:placetype":"venue"
},
  "geometry": {"coordinates":[6.632329,46.514664],"type":"Point"}
}