{
  "type": "Feature",
  "properties": {
    "iso:country":"CH",
    "sg:address":"Place Du Bourg-de-four 38",
    "sg:city":"Gen\u00e8ve",
    "sg:orig_category":"Unclassifiable Establishments",
    "sg:postcode":"1200",
    "sg:province":"Gen\u00e8ve",
    "wof:name":"Editions La Joie De Lire Sa",
    "wof:placetype":"venue"
},
  "geometry": {"coordinates":[6.1482467651,46.1996040344],"type":"Point"}
}