{
  "type": "Feature",
  "properties": {
    "iso:country":"CH",
    "sg:address":"Hardaustrasse 23 8003 Z\u00fcrich. Postfach 2069",
    "sg:city":"Z\u00fcrich",
    "sg:orig_category":"Elektroinstallation",
    "sg:phone":"+41 14917171",
    "sg:postcode":"8040",
    "sg:province":"Z\u00fcrich",
    "wof:name":"Elintec Ag",
    "wof:placetype":"venue"
},
  "geometry": {"coordinates":[8.509188652,47.3771247864],"type":"Point"}
}