{
  "type": "Feature",
  "properties": {
    "iso:country":"CH",
    "sg:address":"Grossm\u00fcnsterplatz 6 8001 Z\u00fcrich. Postfach",
    "sg:city":"Z\u00fcrich",
    "sg:orig_category":"Offsetdruck",
    "sg:phone":"+41 71 740 02 22",
    "sg:postcode":"8024",
    "sg:province":"Z\u00fcrich",
    "wof:name":"Print-shop Zellweger Ag",
    "wof:placetype":"venue"
},
  "geometry": {"coordinates":[9.6377496719,47.4223709106],"type":"Point"}
}