{
  "type": "Feature",
  "properties": {
    "iso:country":"CH",
    "sg:address":"Avenue Marcelin 16",
    "sg:city":"Morges",
    "sg:orig_category":"Vereine Harmonika and Akkordeon",
    "sg:phone":"+41 21 806 19 46",
    "sg:postcode":"1110",
    "sg:province":"Vaud",
    "wof:name":"St\u00e9 D'accord\u00e9onistes",
    "wof:placetype":"venue"
},
  "geometry": {"coordinates":[6.4911937714,46.5141792297],"type":"Point"}
}