{
  "type": "Feature",
  "properties": {
    "iso:country":"CH",
    "sg:address":"Althofstrasse 3",
    "sg:city":"Neuenhof",
    "sg:orig_category":"Sonstige Kultur U Unterhaltungseinrichtungen",
    "sg:phone":"+41 56 410 01 05",
    "sg:postcode":"5432",
    "sg:province":"Aargau",
    "wof:name":"Islamisches Kulturzentrum",
    "wof:placetype":"venue"
},
  "geometry": {"coordinates":[8.3215646744,47.4550018311],"type":"Point"}
}