{
  "type": "Feature",
  "properties": {
    "iso:country":"CH",
    "sg:address":"Rue Du Coppet 12",
    "sg:city":"Monthey",
    "sg:orig_category":"Reparatur von Schuhen U Lederwaren",
    "sg:phone":"+41 24 471 69 18",
    "sg:postcode":"1870",
    "sg:province":"Valais",
    "wof:name":"Vincent Zofra Cordonnerie",
    "wof:placetype":"venue"
},
  "geometry": {"coordinates":[6.9500861168,46.2525253296],"type":"Point"}
}