{
  "type": "Feature",
  "properties": {
    "iso:country":"CH",
    "sg:address":"Oberer Moosweg 14",
    "sg:city":"Frauenfeld",
    "sg:classifiers":[
        {
            "category":"Arena",
            "subcategory":"Sports Club",
            "type":"Entertainment"
        }
    ],
    "sg:phone":"+41 21 316 89 89",
    "sg:postcode":"8500",
    "sg:province":"Thurgau",
    "sg:tags":[
        "karate",
        "judo",
        "sportvereine"
    ],
    "wof:name":"Jjjc Gend.vaud.lausanne",
    "wof:placetype":"venue"
},
  "geometry": {"coordinates":[6.6334500313,46.5194282532],"type":"Point"}
}