{
  "type": "Feature",
  "properties": {
    "iso:country":"CH",
    "sg:address":"1950",
    "sg:city":"Sion",
    "sg:orig_category":"Unclassifiable Establishments",
    "sg:postcode":"1950",
    "sg:province":"Valais",
    "wof:name":"S.i. Ski Et Soleil Sa.",
    "wof:placetype":"venue"
},
  "geometry": {"coordinates":[7.3633999825,46.2366981506],"type":"Point"}
}