{
  "type": "Feature",
  "properties": {
    "iso:country":"CH",
    "sg:address":"Alpenstrasse 58",
    "sg:city":"Zollikofen",
    "sg:orig_category":"Sonstige pers\u00f6nliche Dienstleistungen",
    "sg:phone":"+41 71 385 29 17",
    "sg:postcode":"3052",
    "sg:province":"Bern",
    "wof:name":"Pro4s & Partner Gmbh",
    "wof:placetype":"venue"
},
  "geometry": {"coordinates":[9.2477693558,47.4170532227],"type":"Point"}
}