{
  "type": "Feature",
  "properties": {
    "iso:country":"CH",
    "sg:address":"Pr\u00e9 De L'oie 9",
    "sg:city":"Yvorne",
    "sg:orig_category":"Herstellung von sonstigen Waren aus Papier, Karton U Pappe Siebdruck",
    "sg:phone":"+41 24 468 00 50",
    "sg:postcode":"1853",
    "sg:province":"Vaud",
    "wof:name":"Seridec S\u00e0rl",
    "wof:placetype":"venue"
},
  "geometry": {"coordinates":[6.9233641624,46.3436775208],"type":"Point"}
}