{
  "type": "Feature",
  "properties": {
    "iso:country":"CH",
    "sg:address":"Bahnhofstrasse 28",
    "sg:city":"Zug",
    "sg:orig_category":"Wirtschaftspr\u00fcfung, Steuerberatung U Treuhand",
    "sg:phone":"+41 55 292 19 11",
    "sg:postcode":"6300",
    "sg:province":"Zug",
    "wof:name":"Office-hand, Roman Bernhardsgr\u00fctter",
    "wof:placetype":"venue"
},
  "geometry": {"coordinates":[8.924779892,47.2391891479],"type":"Point"}
}