{
  "type": "Feature",
  "properties": {
    "iso:country":"CH",
    "sg:address":"Luzernstrasse 80",
    "sg:city":"Malters",
    "sg:orig_category":"Detailhandel mit Textilien Verlegen von Fussboden",
    "sg:phone":"+41 41 497 26 23",
    "sg:postcode":"6102",
    "sg:province":"Luzern",
    "wof:name":"Werner Brugger Lederwaren Bodenbel\u00e4ge",
    "wof:placetype":"venue"
},
  "geometry": {"coordinates":[8.1812639236,47.0365562439],"type":"Point"}
}