{
  "type": "Feature",
  "properties": {
    "iso:country":"CH",
    "sg:address":"Dorfstrasse 81",
    "sg:city":"Brittnau",
    "sg:orig_category":"Detailhandel mit Fleisch U Fleischwaren",
    "sg:phone":"+41 62 751 70 48",
    "sg:postcode":"4805",
    "sg:province":"Aargau",
    "wof:name":"Ernst Grogg Metzgerei",
    "wof:placetype":"venue"
},
  "geometry": {"coordinates":[7.9425501823,47.260219574],"type":"Point"}
}