{
  "type": "Feature",
  "properties": {
    "addr:full":"K\u00e4genstrasse 17 Reinach Basel-Landschaft 4153",
    "addr:housenumber":"17",
    "addr:postcode":"4153",
    "addr:street":"Kaegenstrasse",
    "iso:country":"CH",
    "sg:address":"K\u00e4genstrasse 17",
    "sg:city":"Reinach",
    "sg:classifiers":[
        {
            "category":"Education",
            "subcategory":"College",
            "type":"Public Place"
        }
    ],
    "sg:phone":"+41 61 716 97 60",
    "sg:postcode":"4153",
    "sg:province":"Basel-Landschaft",
    "sg:tags":[
        "additive"
    ],
    "wof:name":"Christ Chemie Ag",
    "wof:placetype":"venue"
},
  "geometry": {"coordinates":[7.598005,47.486305],"type":"Point"}
}