{
  "type": "Feature",
  "properties": {
    "iso:country":"CH",
    "sg:address":"Wiler Strasse 14",
    "sg:city":"Flawil",
    "sg:orig_category":"Detailhandel mit Blumen U Pflanzen",
    "sg:phone":"+41 31 301 95 26",
    "sg:postcode":"9230",
    "sg:province":"St. Gallen",
    "wof:name":"Blumen Ambiance Gmbh",
    "wof:placetype":"venue"
},
  "geometry": {"coordinates":[7.423288,46.974743],"type":"Point"}
}