{
  "type": "Feature",
  "properties": {
    "iso:country":"CH",
    "sg:address":"Bernstrasse 114",
    "sg:city":"Ostermundigen",
    "sg:orig_category":"Gesundheitswesen",
    "sg:phone":"+41 71 288 13 21",
    "sg:postcode":"3072",
    "sg:province":"Bern",
    "wof:name":"Fleur De Lys Dousse Energietherapien",
    "wof:placetype":"venue"
},
  "geometry": {"coordinates":[9.3164548874,47.4069252014],"type":"Point"}
}