{
  "type": "Feature",
  "properties": {
    "iso:country":"CH",
    "sg:address":"Hohlenstrasse 3",
    "sg:city":"Huttwil",
    "sg:orig_category":"Eisenbahnverkehr",
    "sg:postcode":"4950",
    "sg:province":"Bern",
    "wof:name":"Verein Vereinigte Dampf-bahnen",
    "wof:placetype":"venue"
},
  "geometry": {"coordinates":[7.8435049057,47.1159515381],"type":"Point"}
}