{
  "type": "Feature",
  "properties": {
    "iso:country":"CH",
    "sg:address":"Piazza Ambrosoli 30",
    "sg:city":"Ascona",
    "sg:orig_category":"Detailhandel mit Tabakwaren",
    "sg:phone":"+41 91 791 26 47",
    "sg:postcode":"6612",
    "sg:province":"Ticino",
    "wof:name":"Clelia Kaufmann Negozio Tabacchi",
    "wof:placetype":"venue"
},
  "geometry": {"coordinates":[8.7674198151,46.1558647156],"type":"Point"}
}