{
  "type": "Feature",
  "properties": {
    "addr:full":"Reichensteinerstrasse 18 Basel Basel-Stadt 4053",
    "addr:housenumber":"18",
    "addr:postcode":"4053",
    "addr:street":"Reichensteinerstrasse",
    "iso:country":"CH",
    "sg:address":"Reichensteinerstrasse 18",
    "sg:city":"Basel",
    "sg:orig_category":"Arztpraxen",
    "sg:phone":"+41 61 271 13 11",
    "sg:postcode":"4053",
    "sg:province":"Basel-Stadt",
    "wof:name":"Dr.med.peter Peiser Spezialarzt",
    "wof:placetype":"venue"
},
  "geometry": {"coordinates":[7.584187,47.544685],"type":"Point"}
}