{
  "type": "Feature",
  "properties": {
    "addr:full":"Juravorstadt 42 Biel/bienne Bern 2502",
    "addr:housenumber":"42",
    "addr:postcode":"2502",
    "addr:street":"Juravorstadt",
    "iso:country":"CH",
    "sg:address":"Juravorstadt 42",
    "sg:city":"Biel/bienne",
    "sg:orig_category":"Christmas Cards, Painted By Disabled Artists",
    "sg:phone":"+41 32 344 80 60",
    "sg:postcode":"2502",
    "sg:province":"Bern",
    "wof:name":"Atelier Kanal 15",
    "wof:placetype":"venue"
},
  "geometry": {"coordinates":[7.250886,47.144791],"type":"Point"}
}