{
  "type": "Feature",
  "properties": {
    "iso:country":"CH",
    "sg:address":"Rickenstrasse 25",
    "sg:city":"Gommiswald",
    "sg:orig_category":"Zahnarztpraxen",
    "sg:phone":"+41 55 280 45 66",
    "sg:postcode":"8737",
    "sg:province":"St. Gallen",
    "wof:name":"Dr. Med. Dent. J\u00f6rgen Jensen Zahnarzt",
    "wof:placetype":"venue"
},
  "geometry": {"coordinates":[9.0204648972,47.2335777283],"type":"Point"}
}