{
  "type": "Feature",
  "properties": {
    "iso:country":"CH",
    "sg:address":"Baarerstrasse 113",
    "sg:city":"Zug",
    "sg:classifiers":[
        {
            "category":"Communications",
            "subcategory":"Radio Station",
            "type":"Services"
        }
    ],
    "sg:postcode":"6300",
    "sg:province":"Zug",
    "sg:tags":[
        "fernsehanstalten",
        "u"
    ],
    "wof:name":"Be&see Gmbh",
    "wof:placetype":"venue"
},
  "geometry": {"coordinates":[8.5184078217,47.1795272827],"type":"Point"}
}