{
  "type": "Feature",
  "properties": {
    "iso:country":"CH",
    "sg:address":"Via Ronco Nuovo",
    "sg:city":"Comano",
    "sg:orig_category":"Bauschreinerei Herstellung von M\u00f6beln verschiedener Art",
    "sg:phone":"+41 91 941 11 73",
    "sg:postcode":"6949",
    "sg:province":"Ticino",
    "wof:name":"Gianbattista Rossi Falegnameria",
    "wof:placetype":"venue"
},
  "geometry": {"coordinates":[8.95151,46.03344],"type":"Point"}
}