{
  "type": "Feature",
  "properties": {
    "iso:country":"CH",
    "sg:address":"Gartenstrasse 26",
    "sg:city":"Z\u00fcrich",
    "sg:orig_category":"Wirtschaftspr\u00fcfung, Steuerberatung U Treuhand",
    "sg:phone":"+41 79 279 85 94",
    "sg:postcode":"8002",
    "sg:province":"Z\u00fcrich",
    "wof:name":"Palmy Treuhand",
    "wof:placetype":"venue"
},
  "geometry": {"coordinates":[9.714589119,46.704082489],"type":"Point"}
}