{
  "type": "Feature",
  "properties": {
    "iso:country":"CH",
    "sg:address":"Lindenstrasse 4 8810 Horgen. Postfach",
    "sg:city":"Horgen",
    "sg:orig_category":"Datenverarbeitungsdienste Unternehmensberatung",
    "sg:phone":"+41 12992128",
    "sg:postcode":"8810",
    "sg:province":"Z\u00fcrich",
    "wof:name":"Interact Consulting Ag",
    "wof:placetype":"venue"
},
  "geometry": {"coordinates":[8.599813,47.259747],"type":"Point"}
}