{
  "type": "Feature",
  "properties": {
    "iso:country":"CH",
    "sg:address":"Rue Du Coll\u00e8ge 5",
    "sg:city":"Martigny",
    "sg:orig_category":"Detailhandel mit Bekleidung Detailhandel mit Geschenkartikeln U Souvenirs",
    "sg:phone":"+41 27 722 42 49",
    "sg:postcode":"1920",
    "sg:province":"Valais",
    "wof:name":"Keren Zimmermann Boutique Bekebe",
    "wof:placetype":"venue"
},
  "geometry": {"coordinates":[7.07411,46.101307],"type":"Point"}
}