{
  "type": "Feature",
  "properties": {
    "iso:country":"CH",
    "sg:address":"Talackerstrasse 17 8152 Glattbrugg. Postfach",
    "sg:city":"Z\u00fcrich",
    "sg:orig_category":"Grosshandel mit Bekleidung Interessenvertretungen",
    "sg:phone":"+41 56 470 05 91",
    "sg:postcode":"8065",
    "sg:province":"Z\u00fcrich",
    "wof:name":"Baby Rose Genossenschaft",
    "wof:placetype":"venue"
},
  "geometry": {"coordinates":[8.2869291306,47.4561080933],"type":"Point"}
}