{
  "type": "Feature",
  "properties": {
    "iso:country":"CH",
    "sg:address":"Gotthardstrasse 149 6472 Erstfeld. Postfach 221",
    "sg:city":"Erstfeld",
    "sg:orig_category":"Maler U Glasergewerbe Malerei",
    "sg:phone":"+41 41 870 93 91",
    "sg:postcode":"6472",
    "sg:province":"Uri",
    "wof:name":"Maler Rixen Ag",
    "wof:placetype":"venue"
},
  "geometry": {"coordinates":[8.6490068436,46.8257827759],"type":"Point"}
}