{
  "type": "Feature",
  "properties": {
    "iso:country":"CH",
    "sg:address":"General Dufour-strasse 50 2502 Biel/bienne. Postfach",
    "sg:city":"Biel/bienne",
    "sg:orig_category":"Detailhandel mit Waren verschiedener Art, Hauptrichtung Nahrungsmittel Grosshandel mit Nahrungsmitte",
    "sg:phone":"+41 32 341 16 87",
    "sg:postcode":"2500",
    "sg:province":"Bern",
    "wof:name":"Asien Market Tang Chor Ly Ly Asiatische Lebensmittel U. Porzellanartikel; Handel",
    "wof:placetype":"venue"
},
  "geometry": {"coordinates":[7.2513360977,47.1414260864],"type":"Point"}
}