{
  "type": "Feature",
  "properties": {
    "iso:country":"CH",
    "sg:address":"Chantemerle Route De 58",
    "sg:city":"Granges-paccot",
    "sg:orig_category":"Pensionskassen",
    "sg:postcode":"1763",
    "sg:province":"Fribourg",
    "wof:name":"Fondation De Pr\u00e9voyance En Faveur Du Personnel De Harlequin Enterprise Sa Et Des Soci\u00e9t\u00e9s Affili\u00e9es",
    "wof:placetype":"venue"
},
  "geometry": {"coordinates":[7.140182972,46.820224762],"type":"Point"}
}