{
  "type": "Feature",
  "properties": {
    "iso:country":"CH",
    "sg:address":"B\u00fchnestrasse 14",
    "sg:city":"Fulenbach",
    "sg:orig_category":"G\u00fcterbef\u00f6rderung im Strassenverkehr",
    "sg:phone":"+41 62 926 14 62",
    "sg:postcode":"4629",
    "sg:province":"Solothurn",
    "wof:name":"Hans-ruedi Rykart Transporte",
    "wof:placetype":"venue"
},
  "geometry": {"coordinates":[7.8397531509,47.278678894],"type":"Point"}
}