{
  "type": "Feature",
  "properties": {
    "iso:country":"CH",
    "sg:address":"Ebenaustrasse 6 6048 Horw. Postfach",
    "sg:city":"Horw",
    "sg:orig_category":"Handelsvermittlung U Grosshandel mit Automobilteilen U Zubeh\u00f6r Herstellung von Automobilen",
    "sg:phone":"+41 41 340 25 25",
    "sg:postcode":"6048",
    "sg:province":"Luzern",
    "wof:name":"Agl Ag F\u00fcr Lastwagenzubeh\u00f6re",
    "wof:placetype":"venue"
},
  "geometry": {"coordinates":[8.3078527451,47.0173950195],"type":"Point"}
}