{
  "type": "Feature",
  "properties": {
    "iso:country":"CH",
    "sg:address":"Scheuermattweg 35 Uettligen 3033 Wohlen B. Bern. Postfach",
    "sg:city":"Uettligen",
    "sg:orig_category":"Betrieb von Taxis",
    "sg:postcode":"3043",
    "sg:province":"Bern",
    "wof:name":"Blue Line Private Taxi Heinrich T.",
    "wof:placetype":"venue"
},
  "geometry": {"coordinates":[7.35617,46.971165],"type":"Point"}
}