{
  "type": "Feature",
  "properties": {
    "addr:full":"Burgerstrasse 33 Thun Bern 3600",
    "addr:housenumber":"33",
    "addr:postcode":"3600",
    "addr:street":"Burgerstrasse;Bern",
    "iso:country":"CH",
    "sg:address":"Burgerstrasse 33",
    "sg:city":"Thun",
    "sg:orig_category":"Bausteine Fabrikation, Handel",
    "sg:postcode":"3600",
    "sg:province":"Bern",
    "wof:name":"Mijajlovic & Co.",
    "wof:placetype":"venue"
},
  "geometry": {"coordinates":[9.263038,47.413738],"type":"Point"}
}