{
  "type": "Feature",
  "properties": {
    "iso:country":"CH",
    "sg:address":"Thunstrasse 95 3006 Bern. Postfach",
    "sg:city":"Bern",
    "sg:orig_category":"Technische, physikalische U chemische Untersuchung Unfall U Schadenversicherung",
    "sg:phone":"+41 21 635 44 11",
    "sg:postcode":"3005",
    "sg:province":"Bern",
    "wof:name":"Eav Expertises Automobiles Et Tous V\u00e9hicules Sa",
    "wof:placetype":"venue"
},
  "geometry": {"coordinates":[6.5904998779,46.5435409546],"type":"Point"}
}