{
  "type": "Feature",
  "properties": {
    "iso:country":"CH",
    "sg:address":"Hauptstrasse 104",
    "sg:city":"Ormalingen",
    "sg:orig_category":"Sanit\u00e4r, Heizungs U L\u00fcftungsinstallation",
    "sg:phone":"+41 79 241 64 84",
    "sg:postcode":"4466",
    "sg:province":"Basel-Landschaft",
    "wof:name":"Spesan Ag",
    "wof:placetype":"venue"
},
  "geometry": {"coordinates":[7.8786292076,47.4681091309],"type":"Point"}
}