{
  "type": "Feature",
  "properties": {
    "iso:country":"CH",
    "sg:address":"1428",
    "sg:city":"Provence",
    "sg:orig_category":"Grosshandel mit lebenden Tieren",
    "sg:phone":"+41 24 434 14 62",
    "sg:postcode":"1428",
    "sg:province":"Vaud",
    "wof:name":"Roger Gaille Commerce De B\u00e9tail",
    "wof:placetype":"venue"
},
  "geometry": {"coordinates":[6.7277708054,46.8915061951],"type":"Point"}
}