{
  "type": "Feature",
  "properties": {
    "iso:country":"CH",
    "sg:address":"Tr\u00fcllikerstrasse 15",
    "sg:city":"Oerlingen",
    "sg:orig_category":"Sportvereine Velo Rad-& Motorfahrer-Bund SRB",
    "sg:phone":"+41 52 319 23 16",
    "sg:postcode":"8461",
    "sg:province":"Z\u00fcrich",
    "wof:name":"Veloclub Oerlingen",
    "wof:placetype":"venue"
},
  "geometry": {"coordinates":[8.675860405,47.6255493164],"type":"Point"}
}