{
  "type": "Feature",
  "properties": {
    "iso:country":"CH",
    "sg:address":"Feldbergstrasse 124 4057 Basel. Postfach",
    "sg:city":"Basel",
    "sg:classifiers":[
        {
            "category":"Communications",
            "subcategory":"Radio Station",
            "type":"Services"
        }
    ],
    "sg:phone":"+41 61 692 81 85",
    "sg:postcode":"4051",
    "sg:province":"Basel-Stadt",
    "sg:tags":[
        "fernsehanstalten",
        "u"
    ],
    "wof:name":"Weiss Peter Philippe Productions Agentur F. Radiowerbung Usw",
    "wof:placetype":"venue"
},
  "geometry": {"coordinates":[7.5958571434,47.5669937134],"type":"Point"}
}