{
  "type": "Feature",
  "properties": {
    "iso:country":"CH",
    "sg:address":"Schlossgasse 8 8466 Tr\u00fcllikon. Postfach",
    "sg:city":"Tr\u00fcllikon",
    "sg:orig_category":"Markt U Meinungsforschung",
    "sg:postcode":"8466",
    "sg:province":"Z\u00fcrich",
    "wof:name":"D\u00f6beli Marketing Dienstleistungen Im Bereich Marketing",
    "wof:placetype":"venue"
},
  "geometry": {"coordinates":[8.6928758621,47.6372566223],"type":"Point"}
}