{
  "type": "Feature",
  "properties": {
    "iso:country":"CH",
    "sg:address":"Schaffhauserstrasse 115",
    "sg:city":"Z\u00fcrich",
    "sg:orig_category":"Detailhandel mit Teppichen Verlegen von Fussboden",
    "sg:phone":"+41 13629994",
    "sg:postcode":"8057",
    "sg:province":"Z\u00fcrich",
    "wof:name":"Mauerhofer Wohndesign Vorh\u00e4nge & Teppiche",
    "wof:placetype":"venue"
},
  "geometry": {"coordinates":[8.5400056839,47.3959083557],"type":"Point"}
}