{
  "type": "Feature",
  "properties": {
    "iso:country":"CH",
    "sg:address":"Rue Du Centre 4",
    "sg:city":"Fontainemelon",
    "sg:orig_category":"Detailhandel mit Brot, Back U S\u00fcsswaren",
    "sg:phone":"+41 32 853 21 71",
    "sg:postcode":"2052",
    "sg:province":"Neuch\u00e2tel",
    "wof:name":"Kurt Frey Boulangerie & P\u00e2tisserie",
    "wof:placetype":"venue"
},
  "geometry": {"coordinates":[6.888939,47.056026],"type":"Point"}
}