{
  "type": "Feature",
  "properties": {
    "iso:country":"CH",
    "sg:address":"Treille Rue De La 2 2000 Neuenburg. Postfach",
    "sg:city":"Neuch\u00e2tel",
    "sg:orig_category":"Detailhandel mit Brot, Back U S\u00fcsswaren",
    "sg:postcode":"2000",
    "sg:province":"Neuch\u00e2tel",
    "wof:name":"Krois Rodriguez Et Associ\u00e9s Confiserie",
    "wof:placetype":"venue"
},
  "geometry": {"coordinates":[6.931085,46.990334],"type":"Point"}
}