{
  "type": "Feature",
  "properties": {
    "iso:country":"CH",
    "sg:address":"1797",
    "sg:city":"M\u00fcnchenwiler",
    "sg:classifiers":[
        {
            "category":"Government",
            "subcategory":"Post Office",
            "type":"Public Place"
        }
    ],
    "sg:phone":"+41 32 338 25 05",
    "sg:postcode":"1797",
    "sg:province":"Bern",
    "sg:tags":[
        "die",
        "poststellen"
    ],
    "wof:name":"Die Post",
    "wof:placetype":"venue"
},
  "geometry": {"coordinates":[7.0402498245,47.022731781],"type":"Point"}
}