{
  "type": "Feature",
  "properties": {
    "iso:country":"CH",
    "sg:address":"3098 K\u00f6niz. Postfach",
    "sg:city":"Liebefeld",
    "sg:orig_category":"Grosshandel mit Parf\u00fcmerieartikeln U K\u00f6rperpflegemitteln Grosshandel mit pharmazeutischen Erzeugniss",
    "sg:phone":"+41 31 971 55 11",
    "sg:postcode":"3097",
    "sg:province":"Bern",
    "wof:name":"Soledor Vertriebs Gmbh",
    "wof:placetype":"venue"
},
  "geometry": {"coordinates":[7.4183797836,46.9104385376],"type":"Point"}
}