{
  "type": "Feature",
  "properties": {
    "iso:country":"CH",
    "sg:address":"Scharnachtalstrasse 12 3006 Bern. Postfach",
    "sg:city":"Bern",
    "sg:orig_category":"Forschung U Entwicklung im Bereich der Naturwissenschaften",
    "sg:postcode":"3005",
    "sg:province":"Bern",
    "wof:name":"Schweizerisch-liechtensteinische Stiftung F\u00fcr Arch\u00e4ologische Forschungen Im Ausland",
    "wof:placetype":"venue"
},
  "geometry": {"coordinates":[7.4714841843,46.9361228943],"type":"Point"}
}