{
  "type": "Feature",
  "properties": {
    "iso:country":"CH",
    "sg:address":"Breitenweg 2",
    "sg:city":"Erlach",
    "sg:orig_category":"Advokaturb\u00fcros",
    "sg:phone":"+41 32 338 20 82",
    "sg:postcode":"3235",
    "sg:province":"Bern",
    "wof:name":"Peter Bosshard Advokaturb\u00fcro",
    "wof:placetype":"venue"
},
  "geometry": {"coordinates":[7.095556,47.04393],"type":"Point"}
}