{
  "type": "Feature",
  "properties": {
    "iso:country":"CH",
    "sg:address":"Habset 111",
    "sg:city":"Rehetobel",
    "sg:orig_category":"Sonstiger Detailhandel mit Waren verschiedener Art, Hauptrichtung Nichtnahrungsmittel Versandhandel",
    "sg:phone":"+41 71 223 20 40",
    "sg:postcode":"9038",
    "sg:province":"Appenzell Ausserrhoden",
    "wof:name":"Witte's Witch-store",
    "wof:placetype":"venue"
},
  "geometry": {"coordinates":[9.4833850861,47.4260749817],"type":"Point"}
}