{
  "type": "Feature",
  "properties": {
    "iso:country":"CH",
    "sg:address":"Riedstrasse 12",
    "sg:city":"Dietikon",
    "sg:orig_category":"Herstellung von sonstigen elektrischen Ausr\u00fcstungen Technische B\u00fcros Elektro",
    "sg:phone":"+41 17741616",
    "sg:postcode":"8953",
    "sg:province":"Z\u00fcrich",
    "wof:name":"Dte Designtech Engineering Schmid Valentin",
    "wof:placetype":"venue"
},
  "geometry": {"coordinates":[8.3951148987,47.4202423096],"type":"Point"}
}