{
  "type": "Feature",
  "properties": {
    "addr:full":"Haustrasse 18 Weinfelden Thurgau 8570",
    "addr:housenumber":"18",
    "addr:postcode":"8570",
    "addr:street":"Haustrasse",
    "iso:country":"CH",
    "sg:address":"Haustrasse 18",
    "sg:city":"Weinfelden",
    "sg:orig_category":"Bau U Wohngenossenschaften",
    "sg:postcode":"8570",
    "sg:province":"Thurgau",
    "wof:name":"Genossenschaft Wohnungsbau",
    "wof:placetype":"venue"
},
  "geometry": {"coordinates":[9.114569,47.568729],"type":"Point"}
}