{
  "type": "Feature",
  "properties": {
    "iso:country":"CH",
    "sg:address":"B\u00fcrenstrasse 1 2542 Pieterlen. Postfach",
    "sg:city":"Pieterlen",
    "sg:orig_category":"Kauf U Verkauf von Immobilien auf eigene Rechnung",
    "sg:postcode":"2542",
    "sg:province":"Bern",
    "wof:name":"Lauper & Cie.",
    "wof:placetype":"venue"
},
  "geometry": {"coordinates":[7.3431348801,47.1712265015],"type":"Point"}
}