{
  "type": "Feature",
  "properties": {
    "iso:country":"CH",
    "sg:address":"H\u00f6chweidstrasse 36",
    "sg:city":"Ebikon",
    "sg:orig_category":"Aktivit\u00e4ten der Krankenschwestern U Hebammen, Hauspflege Sonstiges Gesundheitswesen",
    "sg:phone":"+41 41 440 93 93",
    "sg:postcode":"6030",
    "sg:province":"Luzern",
    "wof:name":"Spitex-dienste Ebikon-dierikon Krankenpflege Krankenmobilien",
    "wof:placetype":"venue"
},
  "geometry": {"coordinates":[8.3486,47.084049],"type":"Point"}
}