{
  "type": "Feature",
  "properties": {
    "iso:country":"CH",
    "sg:address":"Bremgartnerstrasse 16 8003 Z\u00fcrich. Postfach",
    "sg:city":"Z\u00fcrich",
    "sg:orig_category":"Detailhandel mit Textilien Grosshandel mit Textilien",
    "sg:phone":"+41 14626120",
    "sg:postcode":"8036",
    "sg:province":"Z\u00fcrich",
    "wof:name":"Pifko Max Leinen- U. Baumwollgewebe, Aussteuern; Handel",
    "wof:placetype":"venue"
},
  "geometry": {"coordinates":[8.5200185776,47.3721466064],"type":"Point"}
}