{
  "type": "Feature",
  "properties": {
    "iso:country":"CH",
    "sg:address":"Avenue Du Coll\u00e8ge 1-3",
    "sg:city":"Boudry",
    "sg:orig_category":"Polizei",
    "sg:phone":"+41 21 637 21 21",
    "sg:postcode":"2017",
    "sg:province":"Neuch\u00e2tel",
    "wof:name":"Police Cantonale",
    "wof:placetype":"venue"
},
  "geometry": {"coordinates":[6.5836601257,46.5385894775],"type":"Point"}
}