{
  "type": "Feature",
  "properties": {
    "iso:country":"CH",
    "sg:address":"Schutzengelstrasse 38 6340 Baar. Postfach",
    "sg:city":"Baar",
    "sg:orig_category":"Detailhandel mit elektrischen Haushalts-,Radio U Fernsehger\u00e4ten sowie Musikinstrumenten",
    "sg:postcode":"6340",
    "sg:province":"Zug",
    "wof:name":"Dvd2.ch Marz\u00e0 Tontr\u00e4ger, Bildtr\u00e4ger, Zubeh\u00f6r; Vertrieb, Vermietung",
    "wof:placetype":"venue"
},
  "geometry": {"coordinates":[8.5367889404,47.1971588135],"type":"Point"}
}