{
  "type": "Feature",
  "properties": {
    "iso:country":"CH",
    "sg:address":"Kirchlindachstrasse 15 3052 Reichenbach B.bern. Postfach",
    "sg:city":"Zollikofen",
    "sg:orig_category":"Interessenvertretungen",
    "sg:phone":"+41 31 911 37 81",
    "sg:postcode":"3052",
    "sg:province":"Bern",
    "wof:name":"Stiftung Der Kinderfreunde Bern",
    "wof:placetype":"venue"
},
  "geometry": {"coordinates":[7.4589180946,46.9967079163],"type":"Point"}
}