{
  "type": "Feature",
  "properties": {
    "iso:country":"CH",
    "sg:address":"Kolbenacker 10",
    "sg:city":"Seebach",
    "sg:orig_category":"Detailhandel mit B\u00fcchern, Zeitungen, Schreib U Papeteriewaren",
    "sg:postcode":"8052",
    "sg:province":"Z\u00fcrich",
    "wof:name":"Slim Books Strnad B\u00fccher, Video, Audioprodukte Usw; Handel",
    "wof:placetype":"venue"
},
  "geometry": {"coordinates":[8.54024,47.422482],"type":"Point"}
}