{
  "type": "Feature",
  "properties": {
    "iso:country":"CH",
    "sg:address":"Fachstrasse 17 8942 Oberrieden. Postfach",
    "sg:city":"Oberrieden",
    "sg:classifiers":[
        {
            "category":"Restaurant",
            "type":"Food & Drink"
        }
    ],
    "sg:phone":"+41 17221455",
    "sg:postcode":"8942",
    "sg:province":"Z\u00fcrich",
    "wof:name":"Snack Bar Radi",
    "wof:placetype":"venue"
},
  "geometry": {"coordinates":[8.5782699585,47.2799186707],"type":"Point"}
}