{
  "type": "Feature",
  "properties": {
    "iso:country":"CH",
    "sg:address":"Frauenfelderstrasse 95",
    "sg:city":"Matzingen",
    "sg:orig_category":"Detailhandel mit Haustieren U zoologischem Bedarf",
    "sg:phone":"+41 52 376 11 27",
    "sg:postcode":"9548",
    "sg:province":"Thurgau",
    "wof:name":"Vogel-center Ornis Urs Keller",
    "wof:placetype":"venue"
},
  "geometry": {"coordinates":[8.9221973419,47.5268211365],"type":"Point"}
}