{
  "type": "Feature",
  "properties": {
    "iso:country":"CH",
    "sg:address":"Via Parco 1",
    "sg:city":"Bellinzona",
    "sg:orig_category":"G\u00fcterbef\u00f6rderung im Strassenverkehr",
    "sg:phone":"+41 52 232 01 35",
    "sg:postcode":"6500",
    "sg:province":"Ticino",
    "wof:name":"Giovanni Murrone Trans Murrone",
    "wof:placetype":"venue"
},
  "geometry": {"coordinates":[8.7716197968,47.5080108643],"type":"Point"}
}