{
  "type": "Feature",
  "properties": {
    "iso:country":"CH",
    "sg:address":"Limmatquai 94 8001 Z\u00fcrich. Postfach",
    "sg:city":"Unterkulm",
    "sg:orig_category":"Sonstige Weberei",
    "sg:phone":"+41 62 776 56 06",
    "sg:postcode":"5726",
    "sg:province":"Aargau",
    "wof:name":"Swiss Air-tec Ag",
    "wof:placetype":"venue"
},
  "geometry": {"coordinates":[8.543091774,47.3742027283],"type":"Point"}
}