{
  "type": "Feature",
  "properties": {
    "iso:country":"CH",
    "sg:address":"Via Ferrera 25",
    "sg:city":"Ascona",
    "sg:orig_category":"Allgemeiner Hoch U Tiefbau Allgemeiner Hochbau",
    "sg:phone":"+41 91 791 57 31",
    "sg:postcode":"6612",
    "sg:province":"Ticino",
    "wof:name":"Fb Costruzioni Sa",
    "wof:placetype":"venue"
},
  "geometry": {"coordinates":[8.777835,46.155399],"type":"Point"}
}