{
  "type": "Feature",
  "properties": {
    "iso:country":"CH",
    "sg:address":"Zentralstrasse 19",
    "sg:city":"Biel/bienne",
    "sg:orig_category":"Detailhandel mit medizinischen U orthop\u00e4dischen Artikeln",
    "sg:phone":"+41 32 323 14 73",
    "sg:postcode":"2502",
    "sg:province":"Bern",
    "wof:name":"Bleuer A., Sanitas",
    "wof:placetype":"venue"
},
  "geometry": {"coordinates":[7.244904995,47.1387138367],"type":"Point"}
}