{
  "type": "Feature",
  "properties": {
    "iso:country":"CH",
    "sg:address":"Bodenacherstrasse 16",
    "sg:city":"Wittinsburg",
    "sg:orig_category":"Non-Classified Establishments",
    "sg:postcode":"4443",
    "sg:province":"Basel-Landschaft",
    "wof:name":"Happy-green, Ries Michael",
    "wof:placetype":"venue"
},
  "geometry": {"coordinates":[7.8406591415,47.4240951538],"type":"Point"}
}