{
  "type": "Feature",
  "properties": {
    "iso:country":"CH",
    "sg:address":"Buchholzstrasse 135",
    "sg:city":"Z\u00fcrich",
    "sg:orig_category":"Unclassifiable Establishments",
    "sg:phone":"+41 13821761",
    "sg:postcode":"8053",
    "sg:province":"Z\u00fcrich",
    "wof:name":"Innendecor, De Figueiredo Goretti Architekturb\u00fcro, Bes. Inneneinrichtungen U. Dekorationsgestaltung Usw",
    "wof:placetype":"venue"
},
  "geometry": {"coordinates":[8.5901403427,47.3612365723],"type":"Point"}
}