{
  "type": "Feature",
  "properties": {
    "iso:country":"CH",
    "sg:address":"Sunnenhalden 17",
    "sg:city":"St\u00e4fa",
    "sg:orig_category":"Unternehmensberatung",
    "sg:phone":"+41 17961913",
    "sg:postcode":"8712",
    "sg:province":"Z\u00fcrich",
    "wof:name":"Arni Consulting",
    "wof:placetype":"venue"
},
  "geometry": {"coordinates":[8.7319831848,47.2434005737],"type":"Point"}
}