{
  "type": "Feature",
  "properties": {
    "iso:country":"CH",
    "sg:address":"Steinerbergstrasse 41 6410 Goldau. Postfach 171",
    "sg:city":"Goldau",
    "sg:classifiers":[
        {
            "category":"Restaurant",
            "type":"Food & Drink"
        }
    ],
    "sg:phone":"+41 41 855 30 55",
    "sg:postcode":"6410",
    "sg:province":"Schwyz",
    "wof:name":"Gasthaus Sch\u00fctzenhaus",
    "wof:placetype":"venue"
},
  "geometry": {"coordinates":[8.555565834,47.052822113],"type":"Point"}
}