{
  "type": "Feature",
  "properties": {
    "iso:country":"CH",
    "sg:address":"Swiss Holiday Park 6443 Morschach. Postfach",
    "sg:city":"Morschach",
    "sg:orig_category":"Unclassifiable Establishments",
    "sg:postcode":"6443",
    "sg:province":"Schwyz",
    "wof:name":"Kosmetikstudio Marlene, Inhaberin F\u00f6hn Antoinette",
    "wof:placetype":"venue"
},
  "geometry": {"coordinates":[8.6183691025,46.9815864563],"type":"Point"}
}