{
  "type": "Feature",
  "properties": {
    "iso:country":"CH",
    "sg:address":"Wettsteinallee 14",
    "sg:city":"Basel",
    "sg:orig_category":"Fotografische Ateliers",
    "sg:phone":"+41 61 681 27 81",
    "sg:postcode":"4058",
    "sg:province":"Basel-Stadt",
    "wof:name":"Ruedi Hofstetter Fotografisches Atelier",
    "wof:placetype":"venue"
},
  "geometry": {"coordinates":[7.5998468399,47.5597419739],"type":"Point"}
}