{
  "type": "Feature",
  "properties": {
    "iso:country":"CH",
    "sg:address":"In Lampitz\u00e4ckern 5 8305 Dietlikon. Postfach",
    "sg:city":"Dietlikon",
    "sg:orig_category":"RESTAURANTS: TEA-ROOMS",
    "sg:postcode":"8305",
    "sg:province":"Z\u00fcrich",
    "wof:name":"Restaurant Sch\u00fcrhof Staudenmann Roland",
    "wof:placetype":"venue"
},
  "geometry": {"coordinates":[8.6145353317,47.416557312],"type":"Point"}
}