{
  "type": "Feature",
  "properties": {
    "iso:country":"CH",
    "sg:address":"B\u00e4ckerweg 2",
    "sg:city":"Boniswil",
    "sg:orig_category":"Kosmetikinstitute",
    "sg:phone":"+41 62 777 35 35",
    "sg:postcode":"5706",
    "sg:province":"Aargau",
    "wof:name":"C\u00e9cile R\u00fcegg Kosmetikinstitut",
    "wof:placetype":"venue"
},
  "geometry": {"coordinates":[8.1864271164,47.3143196106],"type":"Point"}
}