{
  "type": "Feature",
  "properties": {
    "iso:country":"CH",
    "sg:address":"Schulstr. 74 7206 Igis. Postfach",
    "sg:city":"Landquart",
    "sg:orig_category":"RESTAURANTS: TEA-ROOMS",
    "sg:postcode":"7302",
    "sg:province":"Graubunden",
    "wof:name":"Michel Verena",
    "wof:placetype":"venue"
},
  "geometry": {"coordinates":[9.562494278,46.9584236145],"type":"Point"}
}