{
  "type": "Feature",
  "properties": {
    "iso:country":"CH",
    "sg:address":"Rue Des Alpes 28 1700 Fribourg Case Postale 169",
    "sg:city":"Fribourg",
    "sg:orig_category":"Architektur U Ingenieurb\u00fcros Raumplanungsb\u00fcros",
    "sg:phone":"+41 26 322 19 91",
    "sg:postcode":"1707",
    "sg:province":"Fribourg",
    "wof:name":"Artefact Urbanisme S\u00e0rl",
    "wof:placetype":"venue"
},
  "geometry": {"coordinates":[7.158696,46.805016],"type":"Point"}
}