{
  "type": "Feature",
  "properties": {
    "iso:country":"CH",
    "sg:address":"Unterdorfstrasse 7",
    "sg:city":"Birr",
    "sg:orig_category":"Hoch U Tiefbau",
    "sg:phone":"+41 56 444 80 88",
    "sg:postcode":"5242",
    "sg:province":"Aargau",
    "wof:name":"Josef Fanger Fassadenrenovationen",
    "wof:placetype":"venue"
},
  "geometry": {"coordinates":[8.2042703629,47.4375762939],"type":"Point"}
}