{
  "type": "Feature",
  "properties": {
    "addr:full":"Theaterstrasse 22 8400 Winterthur. Postfach 344 Winterthur Z\u00fcrich 8401",
    "addr:housenumber":"22;344",
    "addr:postcode":"8400;8401",
    "addr:street":"Theaterstrasse;Postfach",
    "iso:country":"CH",
    "sg:address":"Theaterstrasse 22 8400 Winterthur. Postfach 344",
    "sg:city":"Winterthur",
    "sg:orig_category":"Datenverarbeitungsdienste Unternehmensberatung",
    "sg:phone":"+41 52 264 29 29",
    "sg:postcode":"8401",
    "sg:province":"Z\u00fcrich",
    "wof:name":"Truvag Informatik Ag",
    "wof:placetype":"venue"
},
  "geometry": {"coordinates":[8.728071,47.502815],"type":"Point"}
}