{
  "type": "Feature",
  "properties": {
    "iso:country":"CH",
    "sg:address":"Avenue De Savoie 71",
    "sg:city":"Vouvry",
    "sg:orig_category":"Instandhaltung U Reparatur von Automobilen",
    "sg:phone":"+41 79 206 76 12",
    "sg:postcode":"1896",
    "sg:province":"Valais",
    "wof:name":"Antoine Cornut Garage",
    "wof:placetype":"venue"
},
  "geometry": {"coordinates":[6.8874611855,46.3469657898],"type":"Point"}
}