{
  "type": "Feature",
  "properties": {
    "iso:country":"CH",
    "sg:address":"Ch. De La Chevillarde 9",
    "sg:city":"Ch\u00eane-bougeries",
    "sg:orig_category":"Sonstiger Grosshandel",
    "sg:postcode":"1224",
    "sg:province":"Gen\u00e8ve",
    "wof:name":"Crepuscules Limited, Tortola, Geneva Branch",
    "wof:placetype":"venue"
},
  "geometry": {"coordinates":[6.174697876,46.1985473633],"type":"Point"}
}