{
  "type": "Feature",
  "properties": {
    "iso:country":"CH",
    "sg:address":"Rosenstrasse 5",
    "sg:city":"Rorschach",
    "sg:orig_category":"Non-Classified Establishments",
    "sg:phone":"+41 71 845 32 30",
    "sg:postcode":"9400",
    "sg:province":"St. Gallen",
    "wof:name":"Boden Hofer",
    "wof:placetype":"venue"
},
  "geometry": {"coordinates":[9.4863462448,47.4764480591],"type":"Point"}
}