{
  "type": "Feature",
  "properties": {
    "iso:country":"CH",
    "sg:address":"Fehrenstrasse 15 8032 Z\u00fcrich. Postfach",
    "sg:city":"Z\u00fcrich",
    "sg:orig_category":"Laboratorien chemisch",
    "sg:phone":"+41 31 633 11 11",
    "sg:postcode":"8030",
    "wof:name":"Kantonales Labor",
    "wof:placetype":"venue"
},
  "geometry": {"coordinates":[7.4272341728,46.952041626],"type":"Point"}
}