{
  "type": "Feature",
  "properties": {
    "iso:country":"CH",
    "sg:address":"6830",
    "sg:city":"Chiasso",
    "sg:orig_category":"Unclassifiable Establishments",
    "sg:postcode":"6830",
    "sg:province":"Ticino",
    "wof:name":"Fondo Di Previdenza Per Il Personale Della Weisscredit, Banca Commerciale E D'investimenti",
    "wof:placetype":"venue"
},
  "geometry": {"coordinates":[9.0249595642,45.8330001831],"type":"Point"}
}