{
  "type": "Feature",
  "properties": {
    "iso:country":"CH",
    "sg:address":"Avenue F\u00e9lix-cornu 24",
    "sg:city":"Corseaux",
    "sg:orig_category":"Herstellung von keramischen Wand U Bodenfliesen U platten Verlegen von Fliesen U Platten",
    "sg:phone":"+41 21 922 73 73",
    "sg:postcode":"1802",
    "sg:province":"Vaud",
    "wof:name":"Mario Melis Entreprise De Carrelage",
    "wof:placetype":"venue"
},
  "geometry": {"coordinates":[6.825345993,46.4719581604],"type":"Point"}
}