{
  "type": "Feature",
  "properties": {
    "iso:country":"CH",
    "sg:address":"Schellenbergstrasse 37",
    "sg:city":"Chur",
    "sg:orig_category":"Vereine Sprach",
    "sg:postcode":"7000",
    "sg:province":"Graubunden",
    "wof:name":"Sprachvereinigung Romania",
    "wof:placetype":"venue"
},
  "geometry": {"coordinates":[9.5330696106,46.8661117554],"type":"Point"}
}