{
  "type": "Feature",
  "properties": {
    "iso:country":"CH",
    "sg:address":"Langstrasse 20",
    "sg:city":"Z\u00fcrich",
    "sg:orig_category":"RESTAURANTS: TEA-ROOMS",
    "sg:postcode":"8004",
    "sg:province":"Z\u00fcrich",
    "wof:name":"Psg Restaurationsbetriebe Ag",
    "wof:placetype":"venue"
},
  "geometry": {"coordinates":[8.5249652863,47.3752365112],"type":"Point"}
}