{
  "type": "Feature",
  "properties": {
    "iso:country":"CH",
    "sg:address":"Hanegg 8810 Horgen. Postfach 12",
    "sg:city":"Horgen",
    "sg:orig_category":"Stukkateurgewerbe, Gipserei U Verputzerei",
    "sg:phone":"+41 17253839",
    "sg:postcode":"8813",
    "sg:province":"Z\u00fcrich",
    "wof:name":"Schirmer Norbert Ag",
    "wof:placetype":"venue"
},
  "geometry": {"coordinates":[8.6134586334,47.2308082581],"type":"Point"}
}