{
  "type": "Feature",
  "properties": {
    "iso:country":"CH",
    "sg:address":"Lindenstrasse 9 8307 Effretikon. Postfach",
    "sg:city":"Bietenholz",
    "sg:orig_category":"Fachdetailhandel in Verkaufsr\u00e4umen",
    "sg:postcode":"8307",
    "sg:province":"Z\u00fcrich",
    "wof:name":"Sexy Hexy Gross Und Einzelhandel Stalder Christel",
    "wof:placetype":"venue"
},
  "geometry": {"coordinates":[9.2472896576,47.414100647],"type":"Point"}
}