{
  "type": "Feature",
  "properties": {
    "iso:country":"CH",
    "sg:address":"4414",
    "sg:city":"F\u00fcllinsdorf",
    "sg:orig_category":"Bezirks, Sekundar, Realschulen, Oberstufe der Primarschulen",
    "sg:postcode":"4414",
    "sg:province":"Basel-Landschaft",
    "wof:name":"Realschule Sch\u00fctzenmatt",
    "wof:placetype":"venue"
},
  "geometry": {"coordinates":[7.59807,47.466969],"type":"Point"}
}