{
  "type": "Feature",
  "properties": {
    "iso:country":"CH",
    "sg:address":"Oberwilerstrasse 159",
    "sg:city":"Unterlunkhofen",
    "sg:orig_category":"Allgemeiner Hochbau Strassenbau",
    "sg:phone":"+41 56 634 21 28",
    "sg:postcode":"8918",
    "sg:province":"Aargau",
    "wof:name":"Emmenegger Bau Gmbh",
    "wof:placetype":"venue"
},
  "geometry": {"coordinates":[8.379382,47.324215],"type":"Point"}
}