{
  "type": "Feature",
  "properties": {
    "iso:country":"CH",
    "sg:address":"Lagerhausstrasse 37",
    "sg:city":"Ins",
    "sg:orig_category":"Grosshandel mit sonstigen Getr\u00e4nken G\u00fcterbef\u00f6rderung im Strassenverkehr",
    "sg:phone":"+41 32 313 15 28",
    "sg:postcode":"3232",
    "sg:province":"Bern",
    "wof:name":"Alex Geissler",
    "wof:placetype":"venue"
},
  "geometry": {"coordinates":[7.1073498726,46.9983978271],"type":"Point"}
}