{
  "type": "Feature",
  "properties": {
    "iso:country":"CH",
    "sg:address":"Stanserstrasse 13",
    "sg:city":"Kerns",
    "sg:orig_category":"Sonstiges Gesundheitswesen",
    "sg:phone":"+41 41 660 12 26",
    "sg:postcode":"6064",
    "sg:province":"Obwalden",
    "wof:name":"Krankenmobilienmagazin Herr Walter Abegg",
    "wof:placetype":"venue"
},
  "geometry": {"coordinates":[8.279299736,46.903339386],"type":"Point"}
}