{
  "type": "Feature",
  "properties": {
    "iso:country":"CH",
    "sg:address":"Fungkstrasse 102",
    "sg:city":"Wabern",
    "sg:orig_category":"Gartenbau",
    "sg:phone":"+41 56 441 39 92",
    "sg:postcode":"3084",
    "sg:province":"Bern",
    "wof:name":"Armin Schatzmann Gartenbau",
    "wof:placetype":"venue"
},
  "geometry": {"coordinates":[8.207783699,47.4629898071],"type":"Point"}
}