{
  "type": "Feature",
  "properties": {
    "iso:country":"CH",
    "sg:address":"7402",
    "sg:city":"Bonaduz",
    "sg:orig_category":"Detailhandel mit Brot, Back U S\u00fcsswaren",
    "sg:phone":"+41 81 641 11 06",
    "sg:postcode":"7402",
    "sg:province":"Graubunden",
    "wof:name":"Caluori-wachter Franz.",
    "wof:placetype":"venue"
},
  "geometry": {"coordinates":[9.39998,46.811337],"type":"Point"}
}