{
  "type": "Feature",
  "properties": {
    "iso:country":"CH",
    "sg:address":"Rainweg 20 8902 Urdorf. Postfach",
    "sg:city":"Urdorf",
    "sg:orig_category":"Herstellung von sonstigen elektrischen Ausr\u00fcstungen Versandhandel",
    "sg:phone":"+41 17771650",
    "sg:postcode":"8902",
    "sg:province":"Z\u00fcrich",
    "wof:name":"Heirom Gmbh Elektronische Ger\u00e4te, Zubeh\u00f6r; Handel, Vertrieb, Unterhalt Usw",
    "wof:placetype":"venue"
},
  "geometry": {"coordinates":[8.4294519424,47.3884391785],"type":"Point"}
}