{
  "type": "Feature",
  "properties": {
    "iso:country":"CH",
    "sg:address":"H\u00e4ngertstrasse 3 3114 Oberwichtrach. Postfach 154",
    "sg:city":"Oberwichtrach",
    "sg:orig_category":"Bauspenglerei Sanit\u00e4rinstallation",
    "sg:phone":"+41 62 893 18 63",
    "sg:postcode":"3114",
    "sg:province":"Bern",
    "wof:name":"Stephan Fehlmann Bauspenglerei & San.anlagen",
    "wof:placetype":"venue"
},
  "geometry": {"coordinates":[8.18375,47.413925],"type":"Point"}
}