{
  "type": "Feature",
  "properties": {
    "iso:country":"CH",
    "sg:address":"Lauenenstrasse",
    "sg:city":"Saanen",
    "sg:orig_category":"Detailhandel mit Fleisch U Fleischwaren",
    "sg:phone":"+41 19401323",
    "sg:postcode":"3792",
    "sg:province":"Bern",
    "wof:name":"Rudolf Ryffel Metzgerei",
    "wof:placetype":"venue"
},
  "geometry": {"coordinates":[8.7090778351,47.3452835083],"type":"Point"}
}