{
  "type": "Feature",
  "properties": {
    "iso:country":"CH",
    "sg:address":"Gewerbestrasse 3",
    "sg:city":"Derendingen",
    "sg:classifiers":[
        {
            "category":"Military Area",
            "subcategory":"Air Force Base",
            "type":"Public Place"
        }
    ],
    "sg:phone":"+41 32 681 33 22",
    "sg:postcode":"4552",
    "sg:province":"Solothurn",
    "sg:tags":[
        "floral",
        "foam"
    ],
    "wof:name":"Reist & Co",
    "wof:placetype":"venue"
},
  "geometry": {"coordinates":[7.5970039368,47.1972122192],"type":"Point"}
}