{
  "type": "Feature",
  "properties": {
    "iso:country":"CH",
    "sg:address":"Dorf 9651 Ennetb\u00fchl. Postfach",
    "sg:city":"Ennetb\u00fchl",
    "sg:orig_category":"Grosshandel mit Nahrungsmitteln, Getr\u00e4nken U Tabakwaren ohne ausgepr\u00e4gten Schwerpunkt",
    "sg:postcode":"9651",
    "sg:province":"St. Gallen",
    "wof:name":"Julie Lusti-naef",
    "wof:placetype":"venue"
},
  "geometry": {"coordinates":[9.2108812332,47.2407112122],"type":"Point"}
}