{
  "type": "Feature",
  "properties": {
    "iso:country":"CH",
    "sg:address":"Riehentorstrasse 17 4058 Basel. Postfach",
    "sg:city":"Basel",
    "sg:orig_category":"Kauf U Verkauf von Immobilien auf eigene Rechnung",
    "sg:postcode":"4005",
    "sg:province":"Basel-Stadt",
    "wof:name":"L. & H. Rosenmund",
    "wof:placetype":"venue"
},
  "geometry": {"coordinates":[7.5957140923,47.5594482422],"type":"Point"}
}