{
  "type": "Feature",
  "properties": {
    "iso:country":"CH",
    "sg:address":"Rehweg 2",
    "sg:city":"Wiesendangen",
    "sg:orig_category":"Detailhandel mit Brennstoffen U Heizmaterial G\u00fcterbef\u00f6rderung im Strassenverkehr",
    "sg:phone":"+41 52 337 10 25",
    "sg:postcode":"8542",
    "sg:province":"Z\u00fcrich",
    "wof:name":"Heizoel-transport Ag",
    "wof:placetype":"venue"
},
  "geometry": {"coordinates":[8.78479,47.528152],"type":"Point"}
}