{
  "type": "Feature",
  "properties": {
    "addr:full":"Hauptgasse 8 Solothurn Solothurn 4500",
    "addr:housenumber":"8",
    "addr:postcode":"4500",
    "addr:street":"Hauptgasse",
    "iso:country":"CH",
    "sg:address":"Hauptgasse 8",
    "sg:city":"Solothurn",
    "sg:orig_category":"Detailhandel mit Computern U Software Softwareentwicklung U beratung",
    "sg:postcode":"4500",
    "sg:province":"Solothurn",
    "wof:name":"Marcel Graber Internet Database Development",
    "wof:placetype":"venue"
},
  "geometry": {"coordinates":[8.437253,47.08654],"type":"Point"}
}