{
  "type": "Feature",
  "properties": {
    "addr:full":"Pr\u00e9 Rue Du 6 Yverdon-les-bains Vaud 1400",
    "addr:postcode":"1400",
    "addr:street":"Rue Du 6",
    "iso:country":"CH",
    "sg:address":"Pr\u00e9 Rue Du 6",
    "sg:city":"Yverdon-les-bains",
    "sg:orig_category":"Detailhandel mit Brot, Back U S\u00fcsswaren",
    "sg:phone":"+41 24 425 89 76",
    "sg:postcode":"1400",
    "sg:province":"Vaud",
    "wof:name":"Schwab G\u00e9rard",
    "wof:placetype":"venue"
},
  "geometry": {"coordinates":[6.64142,46.778633],"type":"Point"}
}