{
  "type": "Feature",
  "properties": {
    "iso:country":"CH",
    "sg:address":"Avenue Bella-vista 9",
    "sg:city":"Veyrier",
    "sg:orig_category":"Softwareentwicklung U beratung",
    "sg:postcode":"1255",
    "sg:province":"Gen\u00e8ve",
    "wof:name":"Royston Consulting",
    "wof:placetype":"venue"
},
  "geometry": {"coordinates":[6.1430568695,46.1691818237],"type":"Point"}
}