{
  "type": "Feature",
  "properties": {
    "iso:country":"CH",
    "sg:address":"Spalenvorstadt 33",
    "sg:city":"Basel",
    "sg:orig_category":"Handel mit Motorr\u00e4dern, Teilen U Zubeh\u00f6r Instandhaltung U Reparatur von Motorr\u00e4dern",
    "sg:postcode":"4051",
    "sg:province":"Basel-Stadt",
    "wof:name":"Rolf Blum Moto",
    "wof:placetype":"venue"
},
  "geometry": {"coordinates":[7.5820198059,47.5575447083],"type":"Point"}
}