{
  "type": "Feature",
  "properties": {
    "iso:country":"CH",
    "sg:address":"Bielstrasse 29",
    "sg:city":"Pieterlen",
    "sg:classifiers":[
        {
            "category":"Manufacturing",
            "subcategory":"Tools & Machinery",
            "type":"Manufacturing & Wholesale Goods"
        }
    ],
    "sg:phone":"+41 32 931 82 05",
    "sg:postcode":"2542",
    "sg:province":"Bern",
    "sg:tags":[
        "part",
        "turned",
        "cnc"
    ],
    "wof:name":"Savimec Sa",
    "wof:placetype":"venue"
},
  "geometry": {"coordinates":[6.761765,47.060883],"type":"Point"}
}