{
  "type": "Feature",
  "properties": {
    "iso:country":"CH",
    "sg:address":"Seestrasse 92",
    "sg:city":"R\u00fcschlikon",
    "sg:orig_category":"Fachdetailhandel in Verkaufsr\u00e4umen",
    "sg:phone":"+41 17242737",
    "sg:postcode":"8803",
    "sg:province":"Z\u00fcrich",
    "wof:name":"Dr. Phil. Robert R. Bigler, Art Consultant",
    "wof:placetype":"venue"
},
  "geometry": {"coordinates":[8.558795929,47.3049201965],"type":"Point"}
}