{
  "type": "Feature",
  "properties": {
    "iso:country":"CH",
    "sg:address":"Via Lugano 2",
    "sg:city":"Ponte Tresa",
    "sg:classifiers":[
        {
            "category":"Banks & Credit Unions",
            "subcategory":"Bank",
            "type":"Services"
        }
    ],
    "sg:phone":"+41 4191218037",
    "sg:postcode":"6988",
    "sg:province":"Ticino",
    "wof:name":"Unione Di Banche Svizzere",
    "wof:placetype":"venue"
},
  "geometry": {"coordinates":[8.859884,45.967785],"type":"Point"}
}