{
  "type": "Feature",
  "properties": {
    "iso:country":"CH",
    "sg:address":"3098 K\u00f6niz. Postfach 772",
    "sg:city":"K\u00f6niz",
    "sg:orig_category":"Sportvereine Ballsport Fussball",
    "sg:phone":"+41 31 351 04 62",
    "sg:postcode":"3098",
    "sg:province":"Bern",
    "wof:name":"Fc Lusitanos K\u00f6niz",
    "wof:placetype":"venue"
},
  "geometry": {"coordinates":[7.4183797836,46.9104385376],"type":"Point"}
}