{
  "type": "Feature",
  "properties": {
    "iso:country":"CH",
    "sg:address":"1616",
    "sg:city":"Attalens",
    "sg:orig_category":"Wasserversorgung",
    "sg:postcode":"1616",
    "sg:province":"Fribourg",
    "wof:name":"Service Des Eaux De La Commune D'attalens",
    "wof:placetype":"venue"
},
  "geometry": {"coordinates":[6.8493890762,46.5091896057],"type":"Point"}
}