{
  "type": "Feature",
  "properties": {
    "iso:country":"CH",
    "sg:address":"Avenue Victor-ruffy 3",
    "sg:city":"Lausanne",
    "sg:orig_category":"Kaminfeger",
    "sg:phone":"+41 71 333 34 70",
    "sg:postcode":"1012",
    "sg:province":"Vaud",
    "wof:name":"Erich Kast Kaminfegergesch\u00e4ft",
    "wof:placetype":"venue"
},
  "geometry": {"coordinates":[9.3928632736,47.3916130066],"type":"Point"}
}