{
  "type": "Feature",
  "properties": {
    "iso:country":"CH",
    "sg:address":"Fluhgase 156 5080 Laufenburg. Postfach",
    "sg:city":"Laufenburg",
    "sg:orig_category":"Museen",
    "sg:phone":"+41 62 874 22 43",
    "sg:postcode":"5080",
    "sg:province":"Aargau",
    "wof:name":"Museum Zum Schiff",
    "wof:placetype":"venue"
},
  "geometry": {"coordinates":[8.0618391037,47.5605430603],"type":"Point"}
}