{
  "type": "Feature",
  "properties": {
    "iso:country":"CH",
    "sg:address":"Riette Chemin Sous- 29",
    "sg:city":"Crissier",
    "sg:orig_category":"Grosshandel mit sonstigen Maschinen U Ausr\u00fcstungen f\u00fcr Industrie, Handel U Schiffahrt",
    "sg:postcode":"1023",
    "sg:province":"Vaud",
    "wof:name":"Interspark Sa",
    "wof:placetype":"venue"
},
  "geometry": {"coordinates":[6.5774769783,46.5531997681],"type":"Point"}
}