{
  "type": "Feature",
  "properties": {
    "iso:country":"CH",
    "sg:address":"Alte Landstrasse 78",
    "sg:city":"M\u00e4nnedorf",
    "sg:orig_category":"Sonstige mit der Informatik verbundene T\u00e4tigkeiten Webdesign",
    "sg:postcode":"8708",
    "sg:province":"Z\u00fcrich",
    "wof:name":"Simon Vetterli Psrc",
    "wof:placetype":"venue"
},
  "geometry": {"coordinates":[8.6848468781,47.2580108643],"type":"Point"}
}