{
  "type": "Feature",
  "properties": {
    "iso:country":"CH",
    "sg:address":"Via Carona",
    "sg:city":"Pazzallo",
    "sg:classifiers":[
        {
            "category":"Restaurant",
            "type":"Food & Drink"
        }
    ],
    "sg:phone":"+41 91 994 16 97",
    "sg:postcode":"6912",
    "sg:province":"Ticino",
    "wof:name":"Osteria Pazzallo",
    "wof:placetype":"venue"
},
  "geometry": {"coordinates":[8.9406547546,45.9809837341],"type":"Point"}
}