{
  "type": "Feature",
  "properties": {
    "iso:country":"CH",
    "sg:address":"Oberdorfstrasse 9",
    "sg:city":"Mettmenstetten",
    "sg:orig_category":"Autospenglereien",
    "sg:phone":"+41 17682022",
    "sg:postcode":"8932",
    "sg:province":"Z\u00fcrich",
    "wof:name":"Roger Baumann Carrosserie",
    "wof:placetype":"venue"
},
  "geometry": {"coordinates":[8.470593,47.246567],"type":"Point"}
}