{
  "type": "Feature",
  "properties": {
    "iso:country":"CH",
    "sg:address":"Massholderenstrasse 56",
    "sg:city":"Stallikon",
    "sg:orig_category":"Grosshandel mit Getr\u00e4nken",
    "sg:phone":"+41 17001761",
    "sg:postcode":"8143",
    "sg:province":"Z\u00fcrich",
    "wof:name":"Bumbach Rolf, Weinhandel",
    "wof:placetype":"venue"
},
  "geometry": {"coordinates":[8.4900979996,47.3387145996],"type":"Point"}
}