{
  "type": "Feature",
  "properties": {
    "iso:country":"CH",
    "sg:address":"Gerlafingenstrasse 45 4565 Recherswil. Postfach",
    "sg:city":"Recherswil",
    "sg:orig_category":"Fernmeldedienste",
    "sg:postcode":"4565",
    "sg:province":"Solothurn",
    "wof:name":"Dwtel Ag Dienstleistungen Im Bereich Der Telekommunikation Usw",
    "wof:placetype":"venue"
},
  "geometry": {"coordinates":[7.5905599594,47.1646003723],"type":"Point"}
}