{
  "type": "Feature",
  "properties": {
    "iso:country":"CH",
    "sg:address":"Bachr\u00fcti 1",
    "sg:city":"Horn",
    "sg:orig_category":"Grosshandel mit sonstigen Halbwaren Herstellung von Chemiefasern",
    "sg:phone":"+41 79 423 32 44",
    "sg:postcode":"9326",
    "sg:province":"Thurgau",
    "wof:name":"Acordis Schweiz Gmbh Chemiefasern Engros",
    "wof:placetype":"venue"
},
  "geometry": {"coordinates":[9.4570350647,47.4956817627],"type":"Point"}
}