{
  "type": "Feature",
  "properties": {
    "iso:country":"CH",
    "sg:address":"Motorenstrasse 109",
    "sg:city":"Wetzikon",
    "sg:classifiers":[
        {
            "category":"Organizations",
            "subcategory":"Political Organization",
            "type":"Services"
        }
    ],
    "sg:phone":"+41 19313888",
    "sg:postcode":"8620",
    "sg:province":"Z\u00fcrich",
    "sg:tags":[
        "heat",
        "metering",
        "system"
    ],
    "wof:name":"Imeth Ag",
    "wof:placetype":"venue"
},
  "geometry": {"coordinates":[8.7915401459,47.3322410583],"type":"Point"}
}