{
  "type": "Feature",
  "properties": {
    "iso:country":"CH",
    "sg:address":"Aarwangenstrasse 96",
    "sg:city":"Langenthal",
    "sg:classifiers":[
        {
            "category":"Home & Garden",
            "subcategory":"Building Materials",
            "type":"Retail Goods"
        }
    ],
    "sg:phone":"+41 62 922 52 30",
    "sg:postcode":"4900",
    "sg:province":"Bern",
    "sg:tags":[
        "ready-mixed",
        "fresh",
        "concrete"
    ],
    "wof:name":"Frischbeton Langenthal Ag",
    "wof:placetype":"venue"
},
  "geometry": {"coordinates":[7.7787132263,47.2238426208],"type":"Point"}
}