{
  "type": "Feature",
  "properties": {
    "iso:country":"CH",
    "sg:address":"3919",
    "sg:city":"Blatten(l\u00f6tschen)",
    "sg:orig_category":"Herstellung von Konstruktionsteilen, Fertigbauteilen U Ausbauelementen aus Holz",
    "sg:phone":"+41 41 988 24 70",
    "sg:postcode":"3919",
    "sg:province":"Valais",
    "wof:name":"Schreinerei Kammermann Erich",
    "wof:placetype":"venue"
},
  "geometry": {"coordinates":[7.9175071716,47.1279182434],"type":"Point"}
}