{
  "type": "Feature",
  "properties": {
    "iso:country":"CH",
    "sg:address":"Zurlindenstrasse 292",
    "sg:city":"Z\u00fcrich",
    "sg:orig_category":"Unclassifiable Establishments",
    "sg:postcode":"8003",
    "sg:province":"Z\u00fcrich",
    "wof:name":"Sevis Ag",
    "wof:placetype":"venue"
},
  "geometry": {"coordinates":[8.510594368,47.3772010803],"type":"Point"}
}