{
  "type": "Feature",
  "properties": {
    "iso:country":"CH",
    "sg:address":"Kirchlindachstrasse 14",
    "sg:city":"M\u00fcnchenbuchsee",
    "sg:orig_category":"Sonstige pers\u00f6nliche Dienstleistungen",
    "sg:phone":"+41 31 869 10 50",
    "sg:postcode":"3053",
    "sg:province":"Bern",
    "wof:name":"Extc Gmbh",
    "wof:placetype":"venue"
},
  "geometry": {"coordinates":[7.4419879913,47.0185623169],"type":"Point"}
}