{
  "type": "Feature",
  "properties": {
    "iso:country":"CH",
    "sg:address":"Gotthardstrasse 41",
    "sg:city":"Arth",
    "sg:orig_category":"Maler U Glasergewerbe Malerei",
    "sg:phone":"+41 79 226 26 87",
    "sg:postcode":"6415",
    "sg:province":"Schwyz",
    "wof:name":"Della Valle + Co",
    "wof:placetype":"venue"
},
  "geometry": {"coordinates":[8.5240106583,47.0618476868],"type":"Point"}
}