{
  "type": "Feature",
  "properties": {
    "iso:country":"CH",
    "sg:address":"Wylenstrasse 6",
    "sg:city":"Brunnen",
    "sg:orig_category":"Bauschreinerei Herstellung von M\u00f6beln verschiedener Art",
    "sg:phone":"+41 71 367 13 82",
    "sg:postcode":"6440",
    "sg:province":"Schwyz",
    "wof:name":"Hugener Ag, M\u00f6belbau",
    "wof:placetype":"venue"
},
  "geometry": {"coordinates":[9.342467,47.368435],"type":"Point"}
}