{
  "type": "Feature",
  "properties": {
    "iso:country":"CH",
    "sg:address":"Lindenstrasse 15 8302 Kloten. Postfach",
    "sg:city":"Kloten",
    "sg:orig_category":"Sonstiges Versicherungsgewerbe",
    "sg:phone":"+41 18042060",
    "sg:postcode":"8302",
    "sg:province":"Z\u00fcrich",
    "wof:name":"Willis Ag",
    "wof:placetype":"venue"
},
  "geometry": {"coordinates":[8.5836210251,47.448928833],"type":"Point"}
}