{
  "type": "Feature",
  "properties": {
    "addr:full":"Hohlstrasse 30 8004 Z\u00fcrich. Postfach Z\u00fcrich Z\u00fcrich 8001",
    "addr:housenumber":"30",
    "addr:postcode":"8004 zuerich. postfach;8001",
    "addr:street":"Hohlstrasse",
    "iso:country":"CH",
    "sg:address":"Hohlstrasse 30 8004 Z\u00fcrich. Postfach",
    "sg:city":"Z\u00fcrich",
    "sg:orig_category":"Detailhandel mit B\u00fcchern, Zeitungen, Schreib U Papeteriewaren",
    "sg:phone":"+41 13122565",
    "sg:postcode":"8001",
    "sg:province":"Z\u00fcrich",
    "wof:name":"Rodoni S. Italien. B\u00fccher Usw; Verkauf",
    "wof:placetype":"venue"
},
  "geometry": {"coordinates":[8.52721,47.377155],"type":"Point"}
}