{
  "type": "Feature",
  "properties": {
    "iso:country":"CH",
    "sg:address":"Cara Route De 48",
    "sg:city":"Presinge",
    "sg:orig_category":"Betrieb U technische Hilfsdienste des Kultur U Unterhaltungswesens",
    "sg:postcode":"1243",
    "sg:province":"Gen\u00e8ve",
    "wof:name":"Park Productions (the), Igor Joly & Cosmin Mustata",
    "wof:placetype":"venue"
},
  "geometry": {"coordinates":[6.25512,46.21954],"type":"Point"}
}