{
  "type": "Feature",
  "properties": {
    "iso:country":"CH",
    "sg:address":"Wiesenstrasse 29 8953 Dietikon. Postfach",
    "sg:city":"Dietikon",
    "sg:orig_category":"Unternehmensberatung",
    "sg:postcode":"8953",
    "sg:province":"Z\u00fcrich",
    "wof:name":"Abc Conseils S\u00e0rl",
    "wof:placetype":"venue"
},
  "geometry": {"coordinates":[6.9533801079,46.6943054199],"type":"Point"}
}