{
  "type": "Feature",
  "properties": {
    "iso:country":"CH",
    "sg:address":"Via Bossi 1 6900 Lugano. Postfach",
    "sg:city":"Lugano",
    "sg:orig_category":"Reiseb\u00fcros U Reiseveranstalter",
    "sg:phone":"+41 91 923 44 55",
    "sg:postcode":"6901",
    "sg:province":"Ticino",
    "wof:name":"Mivi Milleviaggi Sa",
    "wof:placetype":"venue"
},
  "geometry": {"coordinates":[8.9528503418,46.0072937012],"type":"Point"}
}