{
  "type": "Feature",
  "properties": {
    "iso:country":"CH",
    "sg:address":"Levant Rue Du 8",
    "sg:city":"Hermance",
    "sg:orig_category":"Grosshandel mit Getr\u00e4nken",
    "sg:postcode":"1248",
    "sg:province":"Gen\u00e8ve",
    "wof:name":"Cave St-vincent Sa",
    "wof:placetype":"venue"
},
  "geometry": {"coordinates":[6.2465867996,46.3010864258],"type":"Point"}
}