{
  "type": "Feature",
  "properties": {
    "iso:country":"CH",
    "sg:address":"Tilleul Place Du 9",
    "sg:city":"Bulle",
    "sg:orig_category":"Vermietung U Verpachtung von eigenen Immobilien",
    "sg:phone":"+41 71 911 64 72",
    "sg:postcode":"1630",
    "sg:province":"Fribourg",
    "wof:name":"Forrer Immobilien Ag",
    "wof:placetype":"venue"
},
  "geometry": {"coordinates":[9.0449542999,47.4725265503],"type":"Point"}
}