{
  "type": "Feature",
  "properties": {
    "iso:country":"CH",
    "sg:address":"Rue De Monthoux 42",
    "sg:city":"Gen\u00e8ve",
    "sg:classifiers":[
        {
            "category":"Restaurant",
            "type":"Food & Drink"
        }
    ],
    "sg:phone":"+41 22 731 10 11",
    "sg:postcode":"1201",
    "sg:province":"Gen\u00e8ve",
    "wof:name":"Restaurant-chinois Sui-hua",
    "wof:placetype":"venue"
},
  "geometry": {"coordinates":[6.1471128464,46.2110557556],"type":"Point"}
}