{
  "type": "Feature",
  "properties": {
    "iso:country":"CH",
    "sg:address":"Ringlerweg 4",
    "sg:city":"Tecknau",
    "sg:orig_category":"Kauf U Verkauf von Immobilien auf eigene Rechnung",
    "sg:phone":"+41 61 981 20 53",
    "sg:postcode":"4492",
    "sg:province":"Basel-Landschaft",
    "wof:name":"Zega Gmbh",
    "wof:placetype":"venue"
},
  "geometry": {"coordinates":[7.8814730644,47.4523124695],"type":"Point"}
}