{
  "type": "Feature",
  "properties": {
    "iso:country":"CH",
    "sg:address":"Schwarzackerstrasse 9",
    "sg:city":"Mels",
    "sg:orig_category":"Detailhandel mit Schuhen",
    "sg:phone":"+41 81 868 56 27",
    "sg:postcode":"8887",
    "sg:province":"St. Gallen",
    "wof:name":"Matthias Prinz Schuh-mode Tirana",
    "wof:placetype":"venue"
},
  "geometry": {"coordinates":[10.3613004684,46.9444885254],"type":"Point"}
}