{
  "type": "Feature",
  "properties": {
    "iso:country":"CH",
    "sg:address":"Wylihof 7 4542 Luterbach. Postfach",
    "sg:city":"Luterbach",
    "sg:classifiers":[
        {
            "category":"Travel",
            "subcategory":"Hotels & Motels",
            "type":"Entertainment"
        }
    ],
    "sg:phone":"+41 32 681 34 34",
    "sg:postcode":"4542",
    "sg:province":"Solothurn",
    "sg:tags":[
        "hotels",
        "mit",
        "restaurant"
    ],
    "wof:name":"Faszination Ag",
    "wof:placetype":"venue"
},
  "geometry": {"coordinates":[7.5903000832,47.2241783142],"type":"Point"}
}