{
  "type": "Feature",
  "properties": {
    "iso:country":"CH",
    "sg:address":"Bodmerstrasse 28",
    "sg:city":"Chur",
    "sg:orig_category":"Grosshandel mit Datenverarbeitungsger\u00e4ten Softwareentwicklung U beratung",
    "sg:phone":"+41 81 252 28 13",
    "sg:postcode":"7000",
    "sg:province":"Graubunden",
    "wof:name":"C & B Computer, Bracchi",
    "wof:placetype":"venue"
},
  "geometry": {"coordinates":[9.5339002609,46.8464736938],"type":"Point"}
}