{
  "type": "Feature",
  "properties": {
    "iso:country":"CH",
    "sg:address":"8115",
    "sg:city":"H\u00fcttikon",
    "sg:orig_category":"Grosshandel mit Obst U Gem\u00fcse",
    "sg:postcode":"8115",
    "sg:province":"Z\u00fcrich",
    "wof:name":"Gem\u00fcseverarbeitung Imhof Ag",
    "wof:placetype":"venue"
},
  "geometry": {"coordinates":[8.3914804459,47.4425582886],"type":"Point"}
}