{
  "type": "Feature",
  "properties": {
    "iso:country":"CH",
    "sg:address":"1997",
    "sg:city":"Haute-nendaz",
    "sg:orig_category":"Detailhandel mit Brot, Back U S\u00fcsswaren",
    "sg:phone":"+41 27 288 52 36",
    "sg:postcode":"1997",
    "sg:province":"Valais",
    "wof:name":"Michelet Herv\u00e9",
    "wof:placetype":"venue"
},
  "geometry": {"coordinates":[7.29811,46.184151],"type":"Point"}
}