{
  "type": "Feature",
  "properties": {
    "iso:country":"CH",
    "sg:address":"Champ-de-l'h\u00f4pital",
    "sg:city":"Noville",
    "sg:orig_category":"Autospenglereien",
    "sg:phone":"+41 21 960 30 83",
    "sg:postcode":"1845",
    "sg:province":"Vaud",
    "wof:name":"Auto Racing Car Roger Werren Carrosserie",
    "wof:placetype":"venue"
},
  "geometry": {"coordinates":[6.907124,46.382572],"type":"Point"}
}