{
  "type": "Feature",
  "properties": {
    "iso:country":"CH",
    "sg:address":"Heuelm\u00fcli 3",
    "sg:city":"Schafisheim",
    "sg:orig_category":"Mechanische Werkst\u00e4tten",
    "sg:phone":"+41 79 218 85 86",
    "sg:postcode":"5503",
    "sg:province":"Aargau",
    "wof:name":"Samuel Richner Mechanische Werkst\u00e4tte",
    "wof:placetype":"venue"
},
  "geometry": {"coordinates":[8.1257123947,47.3742141724],"type":"Point"}
}