{
  "type": "Feature",
  "properties": {
    "iso:country":"CH",
    "sg:address":"Silbernstr. 18",
    "sg:city":"Dietikon",
    "sg:classifiers":[
        {
            "category":"Manufacturing",
            "subcategory":"Metals",
            "type":"Manufacturing & Wholesale Goods"
        }
    ],
    "sg:phone":"+41 4117412525",
    "sg:postcode":"8953",
    "sg:province":"Z\u00fcrich",
    "sg:tags":[
        "-",
        "machine",
        "equipment",
        "engineering",
        "machinery",
        "mechanical"
    ],
    "wof:name":"Esab Ag",
    "wof:placetype":"venue"
},
  "geometry": {"coordinates":[8.3938560486,47.4180526733],"type":"Point"}
}