{
  "type": "Feature",
  "properties": {
    "iso:country":"CH",
    "sg:address":"Boulevard De P\u00e9rolles 7",
    "sg:city":"Fribourg",
    "sg:classifiers":[
        {
            "category":"Professional",
            "subcategory":"Employment Agencies",
            "type":"Services"
        }
    ],
    "sg:phone":"+41 26 323 10 12",
    "sg:postcode":"1700",
    "sg:province":"Fribourg",
    "sg:tags":[
        "personal",
        "u",
        "stellenvermittlung"
    ],
    "wof:name":"Heinz U. Fivian Conseils En Personnel",
    "wof:placetype":"venue"
},
  "geometry": {"coordinates":[7.1517372131,46.801235199],"type":"Point"}
}