{
  "type": "Feature",
  "properties": {
    "iso:country":"CH",
    "sg:address":"Via Stefano Franscini 2",
    "sg:city":"Chiasso",
    "sg:orig_category":"Wirtschaftspr\u00fcfung, Steuerberatung U Treuhand",
    "sg:phone":"+41 17156410",
    "sg:postcode":"6830",
    "sg:province":"Ticino",
    "wof:name":"Rescons Gmbh",
    "wof:placetype":"venue"
},
  "geometry": {"coordinates":[8.5421142578,47.3230247498],"type":"Point"}
}