{
  "type": "Feature",
  "properties": {
    "addr:full":"Eschikon 23 Lindau Z\u00fcrich 8315",
    "addr:housenumber":"23",
    "addr:postcode":"8315",
    "addr:street":"Eschikon",
    "iso:country":"CH",
    "sg:address":"Eschikon 23",
    "sg:city":"Lindau",
    "sg:orig_category":"Buchf\u00fchrung Softwareentwicklung U beratung",
    "sg:phone":"+41 52 355 01 10",
    "sg:postcode":"8315",
    "sg:province":"Z\u00fcrich",
    "wof:name":"Agro-treuhand Lindau Ag",
    "wof:placetype":"venue"
},
  "geometry": {"coordinates":[8.68022,47.448448],"type":"Point"}
}