{
  "type": "Feature",
  "properties": {
    "iso:country":"CH",
    "sg:address":"Place De Montbrillant 19",
    "sg:city":"Gen\u00e8ve",
    "sg:orig_category":"Reiseb\u00fcros U Reiseveranstalter",
    "sg:postcode":"1201",
    "sg:province":"Gen\u00e8ve",
    "wof:name":"Toptravel Gmbh Dienstleistungen Auf Dem Internet Im Bereich Tourismus, Bes. Reisen Usw",
    "wof:placetype":"venue"
},
  "geometry": {"coordinates":[8.6912765503,47.4566345215],"type":"Point"}
}