{
  "type": "Feature",
  "properties": {
    "addr:full":"1412 Ursins Vaud 1412",
    "addr:postcode":"1412;1412",
    "iso:country":"CH",
    "sg:address":"1412",
    "sg:city":"Ursins",
    "sg:classifiers":[
        {
            "category":"Education",
            "subcategory":"Library",
            "type":"Public Place"
        }
    ],
    "sg:postcode":"1412",
    "sg:province":"Vaud",
    "sg:tags":[
        "u",
        "bibliotheken",
        "archive"
    ],
    "wof:name":"Biblioth\u00e8que Populaire",
    "wof:placetype":"venue"
},
  "geometry": {"coordinates":[6.66331,46.73864],"type":"Point"}
}