{
  "type": "Feature",
  "properties": {
    "iso:country":"CH",
    "sg:address":"Girizstrasse 42",
    "sg:city":"Biberist",
    "sg:orig_category":"Bau U Wohngenossenschaften Erschliessung von Grundst\u00fccken",
    "sg:postcode":"4562",
    "sg:province":"Solothurn",
    "wof:name":"Wohnbaugenossenschaft \u00c4mmehus",
    "wof:placetype":"venue"
},
  "geometry": {"coordinates":[7.570046,47.187164],"type":"Point"}
}