{
  "type": "Feature",
  "properties": {
    "iso:country":"CH",
    "sg:address":"Hauptstrasse 104",
    "sg:city":"Sissach",
    "sg:orig_category":"Wirtschafts- and Arbeitgeberverb\u00e4nde",
    "sg:phone":"+41 56 441 70 22",
    "sg:postcode":"4450",
    "sg:province":"Basel-Landschaft",
    "wof:name":"Schweiz.coiffeurmeisterverband",
    "wof:placetype":"venue"
},
  "geometry": {"coordinates":[8.2084331512,47.482749939],"type":"Point"}
}