{
  "type": "Feature",
  "properties": {
    "iso:country":"CH",
    "sg:address":"9494 Schaan. Postfach 17",
    "sg:city":"Schaan",
    "sg:orig_category":"Sportvereine Ballsport Tennis",
    "sg:postcode":"9494",
    "wof:name":"Tennisclub Schaan",
    "wof:placetype":"venue"
},
  "geometry": {"coordinates":[9.5097951889,47.1668434143],"type":"Point"}
}