{
  "type": "Feature",
  "properties": {
    "iso:country":"CH",
    "sg:address":"Inselstrasse 75",
    "sg:city":"Basel",
    "sg:orig_category":"Fotografische Ateliers",
    "sg:phone":"+41 76 396 75 74",
    "sg:postcode":"4057",
    "sg:province":"Basel-Stadt",
    "wof:name":"Samuel Oppliger Fotograf",
    "wof:placetype":"venue"
},
  "geometry": {"coordinates":[7.5910468102,47.5771980286],"type":"Point"}
}