{
  "type": "Feature",
  "properties": {
    "iso:country":"CH",
    "sg:address":"Paradisstrasse",
    "sg:city":"Mettmenstetten",
    "sg:orig_category":"Wohnheime f\u00fcr Kinder U Jugendliche",
    "sg:phone":"+41 17670209",
    "sg:postcode":"8932",
    "sg:province":"Z\u00fcrich",
    "wof:name":"Kinderheim Der Heilsarmee",
    "wof:placetype":"venue"
},
  "geometry": {"coordinates":[8.4687423706,47.2493476868],"type":"Point"}
}