{
  "type": "Feature",
  "properties": {
    "iso:country":"CH",
    "sg:address":"Via Monte Boglia 21",
    "sg:city":"Lugano",
    "sg:orig_category":"Sonstige Verkehrsvermittlung",
    "sg:postcode":"6900",
    "sg:province":"Ticino",
    "wof:name":"Cavalleri, Figli Fu Antonio",
    "wof:placetype":"venue"
},
  "geometry": {"coordinates":[8.9610652924,46.0178451538],"type":"Point"}
}