{
  "type": "Feature",
  "properties": {
    "iso:country":"CH",
    "sg:address":"Via Maraini 4",
    "sg:city":"Pregassona",
    "sg:orig_category":"Detailhandel mit Bekleidung Detailhandel mit Damenbekleidung",
    "sg:phone":"+41 91 942 55 31",
    "sg:postcode":"6963",
    "sg:province":"Ticino",
    "wof:name":"Nuova Bischick Sa",
    "wof:placetype":"venue"
},
  "geometry": {"coordinates":[8.972781,46.019455],"type":"Point"}
}