{
  "type": "Feature",
  "properties": {
    "iso:country":"CH",
    "sg:address":"Franklinstrasse 41",
    "sg:city":"Z\u00fcrich",
    "sg:classifiers":[
        {
            "category":"Restaurant",
            "type":"Food & Drink"
        }
    ],
    "sg:phone":"+41 52 319 11 29",
    "sg:postcode":"8050",
    "sg:province":"Z\u00fcrich",
    "wof:name":"Restaurant Baumgarten",
    "wof:placetype":"venue"
},
  "geometry": {"coordinates":[8.655412674,47.6522903442],"type":"Point"}
}