{
  "type": "Feature",
  "properties": {
    "iso:country":"CH",
    "sg:address":"Feldbergstrasse 59",
    "sg:city":"Basel",
    "sg:orig_category":"RESTAURANTS: TEA-ROOMS",
    "sg:phone":"+41 56 441 11 08",
    "sg:postcode":"4057",
    "sg:province":"Basel-Stadt",
    "wof:name":"Rolf Irion",
    "wof:placetype":"venue"
},
  "geometry": {"coordinates":[8.2088155746,47.4819908142],"type":"Point"}
}