{
  "type": "Feature",
  "properties": {
    "iso:country":"CH",
    "sg:address":"Hauptstrasse 53b",
    "sg:city":"Niederurnen",
    "sg:orig_category":"Allgemeiner Hoch U Tiefbau",
    "sg:phone":"+41 55 610 15 58",
    "sg:postcode":"8867",
    "sg:province":"Glarus",
    "wof:name":"Staubli G.",
    "wof:placetype":"venue"
},
  "geometry": {"coordinates":[9.053674,47.122108],"type":"Point"}
}