{
  "type": "Feature",
  "properties": {
    "iso:country":"CH",
    "sg:address":"Baarerstrasse 8 6300 Zug. Postfach 452",
    "sg:city":"Zug",
    "sg:orig_category":"Grosshandel mit elektrischen Haushaltsger\u00e4ten, Radio U Fernsehger\u00e4ten",
    "sg:phone":"+41 32 725 00 00",
    "sg:postcode":"6301",
    "sg:province":"Zug",
    "wof:name":"Ecs Executive Communication Systems Neuch\u00e2tel Sa",
    "wof:placetype":"venue"
},
  "geometry": {"coordinates":[6.9280581474,46.9928359985],"type":"Point"}
}