{
  "type": "Feature",
  "properties": {
    "iso:country":"CH",
    "sg:address":"Kleinroth",
    "sg:city":"Biglen",
    "sg:orig_category":"Herstellung von sonstigen landwirtschaftlichen Maschinen Schmieden",
    "sg:phone":"+41 31 701 14 47",
    "sg:postcode":"3507",
    "sg:province":"Bern",
    "wof:name":"Pauli H.",
    "wof:placetype":"venue"
},
  "geometry": {"coordinates":[7.6391000748,46.9195594788],"type":"Point"}
}