{
  "type": "Feature",
  "properties": {
    "iso:country":"CH",
    "sg:address":"Fabrikweg 1",
    "sg:city":"Bellach",
    "sg:orig_category":"Unclassifiable Establishments",
    "sg:phone":"+41 32 617 42 42",
    "sg:postcode":"4512",
    "sg:province":"Solothurn",
    "wof:name":"Fraisa Holding Ag",
    "wof:placetype":"venue"
},
  "geometry": {"coordinates":[7.5050778389,47.2106285095],"type":"Point"}
}