{
  "type": "Feature",
  "properties": {
    "iso:country":"CH",
    "sg:address":"Bahnhofstrasse 32 4133 Pratteln. Postfach",
    "sg:city":"Pratteln",
    "sg:orig_category":"Alters U Hinterlassenenversicherung AHV, Invalidenversicherung IV, Arbeitslosenversicherung ALV",
    "sg:phone":"+41 61 826 77 77",
    "sg:postcode":"4133",
    "sg:province":"Basel-Landschaft",
    "wof:name":"Oeffentliche Arbeitslosenkasse Baselland",
    "wof:placetype":"venue"
},
  "geometry": {"coordinates":[7.691584,47.519283],"type":"Point"}
}