{
  "type": "Feature",
  "properties": {
    "iso:country":"CH",
    "sg:address":"Sonnhaldenstrasse 27",
    "sg:city":"Uster",
    "sg:orig_category":"Arztpraxen",
    "sg:phone":"+41 19409822",
    "sg:postcode":"8610",
    "sg:province":"Z\u00fcrich",
    "wof:name":"Dr.med.christiane Rufini Spezial\u00e4rztin Fmh",
    "wof:placetype":"venue"
},
  "geometry": {"coordinates":[8.732779,47.340889],"type":"Point"}
}