{
  "type": "Feature",
  "properties": {
    "iso:country":"CH",
    "sg:address":"Wehntalerstrasse 40 8157 Dielsdorf. Postfach 216",
    "sg:city":"Dielsdorf",
    "sg:orig_category":"Verwaltung der Rechtspflege, Gerichte",
    "sg:phone":"+41 800 800 800",
    "sg:postcode":"8157",
    "sg:province":"Z\u00fcrich",
    "wof:name":"Notariat & Grundbuchamt Wetzikon Zh",
    "wof:placetype":"venue"
},
  "geometry": {"coordinates":[8.800699234,47.3266487122],"type":"Point"}
}