{
  "type": "Feature",
  "properties": {
    "iso:country":"CH",
    "sg:address":"Feldeggstrasse 66",
    "sg:city":"Z\u00fcrich",
    "sg:orig_category":"Erbringung von sonstigen Dienstleistungen f\u00fcr Unterhaltung, Erholung U Freizeit",
    "sg:postcode":"8008",
    "sg:province":"Z\u00fcrich",
    "wof:name":"Perlotto Orlando",
    "wof:placetype":"venue"
},
  "geometry": {"coordinates":[6.8218688965,47.0982589722],"type":"Point"}
}