{
  "type": "Feature",
  "properties": {
    "iso:country":"CH",
    "sg:address":"1295",
    "sg:city":"Tannay",
    "sg:orig_category":"Primarschulen",
    "sg:phone":"+41 22 776 38 96",
    "sg:postcode":"1295",
    "sg:province":"Vaud",
    "wof:name":"Ecole Primaire",
    "wof:placetype":"venue"
},
  "geometry": {"coordinates":[6.1760988235,46.3089599609],"type":"Point"}
}