{
  "type": "Feature",
  "properties": {
    "iso:country":"CH",
    "sg:address":"Emserstrasse 44",
    "sg:city":"Chur",
    "sg:orig_category":"Sonderschulen Wohnheime",
    "sg:phone":"+41 81 255 13 00",
    "sg:postcode":"7000",
    "sg:province":"Graubunden",
    "wof:name":"Heim Plankis J.p.hosang'sche Stiftung",
    "wof:placetype":"venue"
},
  "geometry": {"coordinates":[9.50182724,46.8450889587],"type":"Point"}
}