{
  "type": "Feature",
  "properties": {
    "iso:country":"CH",
    "sg:address":"L'epena 149",
    "sg:city":"Vallon",
    "sg:classifiers":[
        {
            "category":"Organizations",
            "subcategory":"Labor Organization",
            "type":"Services"
        }
    ],
    "sg:phone":"+41 26 667 00 90",
    "sg:postcode":"1565",
    "sg:province":"Fribourg",
    "sg:tags":[
        "cutting",
        "laser",
        "system",
        "welding"
    ],
    "wof:name":"Reper S\u00e0rl",
    "wof:placetype":"venue"
},
  "geometry": {"coordinates":[17.4480495453,1.3454699516],"type":"Point"}
}