{
  "type": "Feature",
  "properties": {
    "iso:country":"CH",
    "sg:address":"Vorstadt 4",
    "sg:city":"Zug",
    "sg:orig_category":"Linienflugverkehr",
    "sg:phone":"+41 41 712 36 60",
    "sg:postcode":"6300",
    "sg:province":"Zug",
    "wof:name":"G5 Executive Ag",
    "wof:placetype":"venue"
},
  "geometry": {"coordinates":[8.5150194168,47.168422699],"type":"Point"}
}