{
  "type": "Feature",
  "properties": {
    "iso:country":"CH",
    "sg:address":"Avenue De Cour 51",
    "sg:city":"Lausanne",
    "sg:orig_category":"Naturheil\u00e4rzte and Heilpraktiker",
    "sg:phone":"+41 21 312 71 36",
    "sg:postcode":"1007",
    "sg:province":"Vaud",
    "wof:name":"Norbert Venard Naturopathe",
    "wof:placetype":"venue"
},
  "geometry": {"coordinates":[6.6186847687,46.5148468018],"type":"Point"}
}