{
  "type": "Feature",
  "properties": {
    "iso:country":"CH",
    "sg:address":"Bahnhofstrasse",
    "sg:city":"Raron",
    "sg:orig_category":"Elektroinstallation",
    "sg:phone":"+41 27 934 17 27",
    "sg:postcode":"3942",
    "sg:province":"Valais",
    "wof:name":"Tz Stromag, Filiale Raron",
    "wof:placetype":"venue"
},
  "geometry": {"coordinates":[7.8003549576,46.307308197],"type":"Point"}
}