{
  "type": "Feature",
  "properties": {
    "iso:country":"CH",
    "sg:address":"Neue P\u00fcntacherstrasse 11",
    "sg:city":"St\u00e4fa",
    "sg:orig_category":"Detailhandel mit Damenbekleidung",
    "sg:phone":"+41 19264600",
    "sg:postcode":"8712",
    "sg:province":"Z\u00fcrich",
    "wof:name":"Edith Hiltebrand Haute Couture",
    "wof:placetype":"venue"
},
  "geometry": {"coordinates":[8.720978,47.251911],"type":"Point"}
}