{
  "type": "Feature",
  "properties": {
    "iso:country":"CH",
    "sg:address":"Thunstrasse 35 3150 Schwarzenburg. Postfach 23",
    "sg:city":"Schwarzenburg",
    "sg:orig_category":"Autogaragen Autospenglereien",
    "sg:phone":"+41 31 731 13 23",
    "sg:postcode":"3150",
    "sg:province":"Bern",
    "wof:name":"G. & M. Corpataux Garage & Carrosserie",
    "wof:placetype":"venue"
},
  "geometry": {"coordinates":[7.349003,46.818935],"type":"Point"}
}