{
  "type": "Feature",
  "properties": {
    "iso:country":"CH",
    "sg:address":"1730",
    "sg:city":"Ecuvillens",
    "sg:orig_category":"Sportvereine Sch\u00fctzen",
    "sg:postcode":"1730",
    "sg:province":"Fribourg",
    "wof:name":"St\u00e9 De Tir De La Paroisse",
    "wof:placetype":"venue"
},
  "geometry": {"coordinates":[7.0049629211,47.2118835449],"type":"Point"}
}