{
  "type": "Feature",
  "properties": {
    "iso:country":"CH",
    "sg:address":"Herzogstrasse 2",
    "sg:city":"Bern",
    "sg:orig_category":"RESTAURANTS: TEA-ROOMS",
    "sg:postcode":"3014",
    "sg:province":"Bern",
    "wof:name":"Cafe-restaurant Palette Mumenthaler",
    "wof:placetype":"venue"
},
  "geometry": {"coordinates":[7.4563040733,46.9581336975],"type":"Point"}
}