{
  "type": "Feature",
  "properties": {
    "iso:country":"CH",
    "sg:address":"Ischmatt 68",
    "sg:city":"Thunstetten",
    "sg:orig_category":"Landw. Genossenschaften Dresch",
    "sg:phone":"+41 32 381 11 41",
    "sg:postcode":"4922",
    "sg:province":"Bern",
    "wof:name":"Hansueli Krebs M\u00e4hdrescherei",
    "wof:placetype":"venue"
},
  "geometry": {"coordinates":[7.2438988686,47.0813140869],"type":"Point"}
}