{
  "type": "Feature",
  "properties": {
    "iso:country":"CH",
    "sg:address":"Rue Des Moulins 19 1400 Yverdon-les-bains Case Postale 227",
    "sg:city":"Yverdon",
    "sg:orig_category":"Vermittlung von Immobilien Wirtschaftspr\u00fcfung, Steuerberatung U Treuhand",
    "sg:phone":"+41 21 311 12 84",
    "sg:postcode":"1401",
    "sg:province":"Vaud",
    "wof:name":"Fiduciaire Maillard Sa",
    "wof:placetype":"venue"
},
  "geometry": {"coordinates":[6.6364707947,46.5213928223],"type":"Point"}
}