{
  "type": "Feature",
  "properties": {
    "iso:country":"CH",
    "sg:address":"Linseb\u00fchlstrasse 43",
    "sg:city":"St.gallen",
    "sg:orig_category":"Fachdetailhandel in Verkaufsr\u00e4umen",
    "sg:phone":"+41 71 223 55 93",
    "sg:postcode":"9000",
    "sg:province":"St. Gallen",
    "wof:name":"Basar Sexotic, Iller G.",
    "wof:placetype":"venue"
},
  "geometry": {"coordinates":[9.3824615479,47.4248046875],"type":"Point"}
}