{
  "type": "Feature",
  "properties": {
    "iso:country":"CH",
    "sg:address":"St\u00f6ckackerstrasse 89",
    "sg:city":"Bern",
    "sg:orig_category":"Gymnastik U Fitnesszentren Saunas, Solarien, Fitnesszentren U \u00e4hnliches",
    "sg:phone":"+41 31 992 03 86",
    "sg:postcode":"3018",
    "sg:province":"Bern",
    "wof:name":"Wellness Alfa 5, Rodriguez M.",
    "wof:placetype":"venue"
},
  "geometry": {"coordinates":[7.4003190994,46.9442214966],"type":"Point"}
}