{
  "type": "Feature",
  "properties": {
    "iso:country":"CH",
    "sg:address":"Gallus\u00e4ckerstrasse 3",
    "sg:city":"M\u00f6rschwil",
    "sg:orig_category":"Politische Parteien CVP",
    "sg:phone":"+41 71 866 22 08",
    "sg:postcode":"9402",
    "sg:province":"St. Gallen",
    "wof:name":"Cvp Ortspartei M\u00f6rschwil",
    "wof:placetype":"venue"
},
  "geometry": {"coordinates":[9.4243488312,47.4702682495],"type":"Point"}
}