{
  "type": "Feature",
  "properties": {
    "iso:country":"CH",
    "sg:address":"Mainaustrasse 47 8008 Z\u00fcrich. Postfach",
    "sg:city":"Z\u00fcrich",
    "sg:orig_category":"Handels-H\u00e4user U Gesellschaften",
    "sg:postcode":"8001",
    "sg:province":"Z\u00fcrich",
    "wof:name":"Omfa Trading Ag Warenhandel Aller Art Usw.",
    "wof:placetype":"venue"
},
  "geometry": {"coordinates":[8.5527496338,47.3614120483],"type":"Point"}
}