{
  "type": "Feature",
  "properties": {
    "iso:country":"CH",
    "sg:address":"Fridlingen 9612 Dreien. Postfach",
    "sg:city":"Dreien",
    "sg:orig_category":"Verwertung von Milch",
    "sg:postcode":"9612",
    "sg:province":"St. Gallen",
    "wof:name":"K\u00e4sereigenossenschaft Dreien",
    "wof:placetype":"venue"
},
  "geometry": {"coordinates":[9.0176811218,47.3729324341],"type":"Point"}
}