{
  "type": "Feature",
  "properties": {
    "iso:country":"CH",
    "sg:address":"Baltenschwilerstrasse 37b",
    "sg:city":"Bergdietikon",
    "sg:orig_category":"Baugewerbe Schlossereien",
    "sg:phone":"+41 17404822",
    "sg:postcode":"8962",
    "sg:province":"Aargau",
    "wof:name":"Fritz H\u00e4usermann Zaunmontagen Schlosserei",
    "wof:placetype":"venue"
},
  "geometry": {"coordinates":[8.393631,47.391914],"type":"Point"}
}