{
  "type": "Feature",
  "properties": {
    "iso:country":"CH",
    "sg:address":"Finkenweg 18",
    "sg:city":"Niederbipp",
    "sg:orig_category":"Fussboden, Fliesen U Plattenlegerei, Tapeziererei",
    "sg:phone":"+41 32 633 29 59",
    "sg:postcode":"4704",
    "sg:province":"Bern",
    "wof:name":"Wand Und Bodenbel\u00e4ge Ischi Markus",
    "wof:placetype":"venue"
},
  "geometry": {"coordinates":[7.6898198128,47.2692604065],"type":"Point"}
}