{
  "type": "Feature",
  "properties": {
    "iso:country":"CH",
    "sg:address":"Neuwiesenstrasse 11",
    "sg:city":"Russikon",
    "sg:orig_category":"Holzbildhauereien and Holzschnitzereien",
    "sg:phone":"+41 19540519",
    "sg:postcode":"8332",
    "sg:province":"Z\u00fcrich",
    "wof:name":"Josef Eyer Atelier",
    "wof:placetype":"venue"
},
  "geometry": {"coordinates":[8.7761697769,47.3929214478],"type":"Point"}
}