{
  "type": "Feature",
  "properties": {
    "addr:full":"Rue Verdaine 13 Gen\u00e8ve Gen\u00e8ve 1204",
    "addr:housenumber":"13",
    "addr:postcode":"1204",
    "addr:street":"Rue Verdaine",
    "iso:country":"CH",
    "sg:address":"Rue Verdaine 13",
    "sg:city":"Gen\u00e8ve",
    "sg:orig_category":"Detailhandel mit Bekleidung Detailhandel mit Damenbekleidung",
    "sg:phone":"+41 22 311 64 60",
    "sg:postcode":"1204",
    "sg:province":"Gen\u00e8ve",
    "wof:name":"El-eini A. & Cie",
    "wof:placetype":"venue"
},
  "geometry": {"coordinates":[6.149978,46.200981],"type":"Point"}
}