{
  "type": "Feature",
  "properties": {
    "addr:full":"Hintere Vorstadt 16 Aarau Aargau 5000",
    "addr:housenumber":"16",
    "addr:postcode":"5000",
    "addr:street":"Hintere Vorstadt",
    "iso:country":"CH",
    "sg:address":"Hintere Vorstadt 16",
    "sg:city":"Aarau",
    "sg:orig_category":"Detailhandel mit Bekleidung",
    "sg:postcode":"5000",
    "sg:province":"Aargau",
    "wof:name":"Rolf Fuchs, Jeans-boutique",
    "wof:placetype":"venue"
},
  "geometry": {"coordinates":[8.045291,47.391327],"type":"Point"}
}