{
  "type": "Feature",
  "properties": {
    "addr:full":"Berne Route De 99 1010 Lausanne. Postfach Lausanne Vaud 1010",
    "addr:housenumber":"99",
    "addr:postcode":"1010;postfach;1010",
    "addr:street":"Route De",
    "iso:country":"CH",
    "sg:address":"Berne Route De 99 1010 Lausanne. Postfach",
    "sg:city":"Lausanne",
    "sg:orig_category":"Allgemeiner Hoch U Tiefbau",
    "sg:phone":"+41 18333377",
    "sg:postcode":"1010",
    "sg:province":"Vaud",
    "wof:name":"Brunner & Co Hoch Und Tiefbauunternehmung Ag, Zweigniederlassung In Wangen-br\u00fcttisellen",
    "wof:placetype":"venue"
},
  "geometry": {"coordinates":[8.645645,47.410656],"type":"Point"}
}