{
  "type": "Feature",
  "properties": {
    "iso:country":"CH",
    "sg:address":"Gibraltar Rue De 8",
    "sg:city":"Neuch\u00e2tel",
    "sg:orig_category":"K\u00fcnstlerische U schriftstellerische T\u00e4tigkeiten U Darbietungen",
    "sg:phone":"+41 38246948",
    "sg:postcode":"2000",
    "sg:province":"Neuch\u00e2tel",
    "wof:name":"A. Cornella",
    "wof:placetype":"venue"
},
  "geometry": {"coordinates":[6.9443778992,46.9970970154],"type":"Point"}
}