{
  "type": "Feature",
  "properties": {
    "iso:country":"CH",
    "sg:address":"Aie Via Delle 1a 6900 Lugano. Postfach",
    "sg:city":"Lugano",
    "sg:orig_category":"Stukkateurgewerbe, Gipserei U Verputzerei",
    "sg:phone":"+41 71 385 93 17",
    "sg:postcode":"6900",
    "sg:province":"Ticino",
    "wof:name":"Ilic Gipsergesch\u00e4ft",
    "wof:placetype":"venue"
},
  "geometry": {"coordinates":[9.2419242859,47.4156112671],"type":"Point"}
}