{
  "type": "Feature",
  "properties": {
    "iso:country":"CH",
    "sg:address":"Buechental 2c 9245 Oberb\u00fcren. Postfach",
    "sg:city":"Oberb\u00fcren",
    "sg:orig_category":"Herstellung von Karosserien U Anh\u00e4ngern",
    "sg:postcode":"9245",
    "sg:province":"St. Gallen",
    "wof:name":"Heuberger Kurt",
    "wof:placetype":"venue"
},
  "geometry": {"coordinates":[9.154214859,47.4473266602],"type":"Point"}
}