{
  "type": "Feature",
  "properties": {
    "iso:country":"CH",
    "sg:address":"Seestrasse 6 6353 Weggis. Postfach",
    "sg:city":"Weggis",
    "sg:orig_category":"Kantonalbanken",
    "sg:phone":"+41 41 206 70 70",
    "sg:postcode":"6353",
    "sg:province":"Luzern",
    "wof:name":"Luzerner Kantonalbank",
    "wof:placetype":"venue"
},
  "geometry": {"coordinates":[8.2235832214,47.131149292],"type":"Point"}
}