{
  "type": "Feature",
  "properties": {
    "iso:country":"CH",
    "sg:address":"Avenue De Beaulieu 5",
    "sg:city":"St-maurice",
    "sg:orig_category":"Vermietung U Verpachtung von eigenen Immobilien",
    "sg:postcode":"1890",
    "sg:province":"Valais",
    "wof:name":"Genilloud Dominique",
    "wof:placetype":"venue"
},
  "geometry": {"coordinates":[7.0048289299,46.2119789124],"type":"Point"}
}