{
  "type": "Feature",
  "properties": {
    "iso:country":"CH",
    "sg:address":"Route De L'industrie 25",
    "sg:city":"Courtepin",
    "sg:orig_category":"Fleischverarbeitung Verarbeitung U Konservierung von Obst U Gem\u00fcse",
    "sg:phone":"+41 26 684 91 11",
    "sg:postcode":"1784",
    "sg:province":"Fribourg",
    "wof:name":"Micarna Sa Produits Carn\u00e9s",
    "wof:placetype":"venue"
},
  "geometry": {"coordinates":[7.1208529472,46.8660240173],"type":"Point"}
}