{
  "type": "Feature",
  "properties": {
    "iso:country":"CH",
    "sg:address":"Rue D'italie 57",
    "sg:city":"Vevey",
    "sg:orig_category":"Detailhandel mit Bekleidung Detailhandel mit Geschenkartikeln U Souvenirs",
    "sg:phone":"+41 21 922 42 79",
    "sg:postcode":"1800",
    "sg:province":"Vaud",
    "wof:name":"Boutique Baraka Marie-christine Amhand",
    "wof:placetype":"venue"
},
  "geometry": {"coordinates":[6.84721,46.438438],"type":"Point"}
}