{
  "type": "Feature",
  "properties": {
    "iso:country":"CH",
    "sg:address":"Klausenstrasse 21",
    "sg:city":"Fischbach-g\u00f6slikon",
    "sg:orig_category":"Unternehmensberatung",
    "sg:postcode":"5525",
    "sg:province":"Aargau",
    "wof:name":"Wellauer & Partner",
    "wof:placetype":"venue"
},
  "geometry": {"coordinates":[8.3082685471,47.3723182678],"type":"Point"}
}