{
  "type": "Feature",
  "properties": {
    "iso:country":"CH",
    "sg:address":"Chemin De La Planchette 6",
    "sg:city":"Aigle",
    "sg:orig_category":"Installation von Heizungs, L\u00fcftungs U Klimaanlagen",
    "sg:phone":"+41 24 466 20 48",
    "sg:postcode":"1860",
    "sg:province":"Vaud",
    "wof:name":"Unifroid Sa",
    "wof:placetype":"venue"
},
  "geometry": {"coordinates":[6.9591507912,46.3202476501],"type":"Point"}
}