{
  "type": "Feature",
  "properties": {
    "iso:country":"CH",
    "sg:address":"Hochwaldstrasse 37",
    "sg:city":"Dornach",
    "sg:orig_category":"\u00dcbersetzungsb\u00fcros",
    "sg:phone":"+41 56 470 40 40",
    "sg:postcode":"4143",
    "sg:province":"Solothurn",
    "wof:name":"Arno Giovannini Linguapool \u00dcbersetzungen",
    "wof:placetype":"venue"
},
  "geometry": {"coordinates":[8.2906999588,47.4518051147],"type":"Point"}
}