{
  "type": "Feature",
  "properties": {
    "iso:country":"CH",
    "sg:address":"Dorfstrasse 46",
    "sg:city":"Signau",
    "sg:orig_category":"Detailhandel mit Schuhen",
    "sg:phone":"+41 34 497 14 81",
    "sg:postcode":"3534",
    "sg:province":"Bern",
    "wof:name":"W\u00e4lti-schuhe Inh.heiniger & Stauffer",
    "wof:placetype":"venue"
},
  "geometry": {"coordinates":[7.7259907722,46.9209289551],"type":"Point"}
}