{
  "type": "Feature",
  "properties": {
    "iso:country":"CH",
    "sg:address":"Bahnhofstrasse 24",
    "sg:city":"Schaffhausen",
    "sg:orig_category":"RESTAURANTS: TEA-ROOMS",
    "sg:phone":"+41 52 625 41 25",
    "sg:postcode":"8200",
    "sg:province":"Schaffhausen",
    "wof:name":"Sunset-bar Ballotta Andrea",
    "wof:placetype":"venue"
},
  "geometry": {"coordinates":[8.6325597763,47.697517395],"type":"Point"}
}