{
  "type": "Feature",
  "properties": {
    "iso:country":"CH",
    "sg:address":"Schulhausstrasse 5",
    "sg:city":"Wynau",
    "sg:orig_category":"Herstellung von Konstruktionsteilen, Fertigbauteilen U Ausbauelementen aus Holz",
    "sg:postcode":"4923",
    "sg:province":"Bern",
    "wof:name":"Lemp Schreinerei Zimmerei",
    "wof:placetype":"venue"
},
  "geometry": {"coordinates":[7.8145890236,47.2565689087],"type":"Point"}
}