{
  "type": "Feature",
  "properties": {
    "iso:country":"CH",
    "sg:address":"Strickstrasse 6",
    "sg:city":"Uster",
    "sg:orig_category":"Vereine Gartenbau",
    "sg:postcode":"8610",
    "sg:province":"Z\u00fcrich",
    "wof:name":"P\u00fcntenp\u00e4chterver.blindenholz",
    "wof:placetype":"venue"
},
  "geometry": {"coordinates":[8.711151123,47.3559761047],"type":"Point"}
}