{
  "type": "Feature",
  "properties": {
    "iso:country":"CH",
    "sg:address":"Anemonenweg 5",
    "sg:city":"Frutigen",
    "sg:orig_category":"Innenausbau Zimmerei, Ingenieurholzbau",
    "sg:phone":"+41 33 671 29 77",
    "sg:postcode":"3714",
    "sg:province":"Bern",
    "wof:name":"Peter Ryter Zimmerei Treppen-& Innenausbau",
    "wof:placetype":"venue"
},
  "geometry": {"coordinates":[7.6569972038,46.5883026123],"type":"Point"}
}