{
  "type": "Feature",
  "properties": {
    "iso:country":"CH",
    "sg:address":"Dorfstrasse 23",
    "sg:city":"Neuendorf",
    "sg:orig_category":"Detailhandel mit Fleisch U Fleischwaren Grosshandel mit Fleisch U Fleischwaren",
    "sg:phone":"+41 62 398 41 22",
    "sg:postcode":"4623",
    "sg:province":"Solothurn",
    "wof:name":"Viande Walter Ag",
    "wof:placetype":"venue"
},
  "geometry": {"coordinates":[7.7885231972,47.3001937866],"type":"Point"}
}