{
  "type": "Feature",
  "properties": {
    "iso:country":"CH",
    "sg:address":"Ermitagestrasse 9 4144 Arlesheim. Postfach 144",
    "sg:city":"Arlesheim",
    "sg:orig_category":"Fachdetailhandel mit pharmazeutischen Produkten",
    "sg:phone":"+41 61 701 17 00",
    "sg:postcode":"4144",
    "sg:province":"Basel-Landschaft",
    "wof:name":"Birseck-apotheke Ag",
    "wof:placetype":"venue"
},
  "geometry": {"coordinates":[7.6203660965,47.4947929382],"type":"Point"}
}