{
  "type": "Feature",
  "properties": {
    "iso:country":"CH",
    "sg:address":"Ueberlandstrasse 42",
    "sg:city":"Z\u00fcrich",
    "sg:orig_category":"Allgemeiner Hoch U Tiefbau",
    "sg:postcode":"8051",
    "sg:province":"Z\u00fcrich",
    "wof:name":"Rothacher Urs Bauunternehmung",
    "wof:placetype":"venue"
},
  "geometry": {"coordinates":[8.56637,47.407318],"type":"Point"}
}