{
  "type": "Feature",
  "properties": {
    "iso:country":"CH",
    "sg:address":"B\u00e4ndlistrasse 23 8064 Z\u00fcrich. Postfach",
    "sg:city":"Z\u00fcrich",
    "sg:orig_category":"Grosshandel mit Nahrungsmitteln, Getr\u00e4nken U Tabakwaren ohne ausgepr\u00e4gten Schwerpunkt",
    "sg:phone":"+41 62 209 57 60",
    "sg:postcode":"8064",
    "sg:province":"Z\u00fcrich",
    "wof:name":"L'id\u00e9e Food K + S Ag",
    "wof:placetype":"venue"
},
  "geometry": {"coordinates":[7.8549938202,47.3366966248],"type":"Point"}
}