{
  "type": "Feature",
  "properties": {
    "iso:country":"CH",
    "sg:address":"Hinterdorfstrasse 5",
    "sg:city":"Grafenried",
    "sg:orig_category":"Detailhandel mit Fleisch U Fleischwaren Grosshandel mit lebenden Tieren",
    "sg:phone":"+41 31 767 71 62",
    "sg:postcode":"3308",
    "sg:province":"Bern",
    "wof:name":"Uelis Metzg, Liechti Ulrich",
    "wof:placetype":"venue"
},
  "geometry": {"coordinates":[7.5103340149,47.0802574158],"type":"Point"}
}