{
  "type": "Feature",
  "properties": {
    "iso:country":"CH",
    "sg:address":"Egelbergstrasse 33",
    "sg:city":"Bern",
    "sg:orig_category":"Arztpraxen",
    "sg:phone":"+41 31 352 00 00",
    "sg:postcode":"3006",
    "sg:province":"Bern",
    "wof:name":"Dr.med.halina Marty Spezial\u00e4rztin Fmh",
    "wof:placetype":"venue"
},
  "geometry": {"coordinates":[7.466219,46.946461],"type":"Point"}
}