{
  "type": "Feature",
  "properties": {
    "addr:full":"Friedaustrasse 6 Z\u00fcrich Z\u00fcrich 8003",
    "addr:housenumber":"6",
    "addr:postcode":"8003",
    "addr:street":"Friedaustrasse",
    "iso:country":"CH",
    "sg:address":"Friedaustrasse 6",
    "sg:city":"Z\u00fcrich",
    "sg:orig_category":"Architektur U Ingenieurb\u00fcros",
    "sg:phone":"+41 52 720 98 58",
    "sg:postcode":"8003",
    "sg:province":"Z\u00fcrich",
    "wof:name":"Ipl Industriebauten Wellmann & Partner",
    "wof:placetype":"venue"
},
  "geometry": {"coordinates":[8.510281,47.376534],"type":"Point"}
}