{
  "type": "Feature",
  "properties": {
    "iso:country":"CH",
    "sg:address":"Buchenstrasse 1",
    "sg:city":"Solothurn",
    "sg:orig_category":"Wirtschaftspr\u00fcfung, Steuerberatung U Treuhand",
    "sg:postcode":"4500",
    "sg:province":"Solothurn",
    "wof:name":"Alpha Tax Gmbh",
    "wof:placetype":"venue"
},
  "geometry": {"coordinates":[7.5135197639,47.2057418823],"type":"Point"}
}