{
  "type": "Feature",
  "properties": {
    "iso:country":"CH",
    "sg:address":"Gehrenhagweg 12",
    "sg:city":"Oberehrendingen",
    "sg:orig_category":"Maler U Glasergewerbe Malerei",
    "sg:phone":"+41 56 222 32 80",
    "sg:postcode":"5422",
    "wof:name":"Kaufmann & Brunati Ag",
    "wof:placetype":"venue"
},
  "geometry": {"coordinates":[8.3448905945,47.4972457886],"type":"Point"}
}