{
  "type": "Feature",
  "properties": {
    "addr:full":"Baslerstrasse 98 Trimbach Solothurn 4632",
    "addr:housenumber":"98",
    "addr:postcode":"4632",
    "addr:street":"Baslerstrasse",
    "iso:country":"CH",
    "sg:address":"Baslerstrasse 98",
    "sg:city":"Trimbach",
    "sg:orig_category":"Architektur U Ingenieurb\u00fcros Vermittlung von Immobilien",
    "sg:phone":"+41 17881666",
    "sg:postcode":"4632",
    "sg:province":"Solothurn",
    "wof:name":"Torfeld Ag",
    "wof:placetype":"venue"
},
  "geometry": {"coordinates":[8.646795,47.200165],"type":"Point"}
}