{
  "type": "Feature",
  "properties": {
    "addr:full":"Stauffacher-quai 54/56 8004 Z\u00fcrich. Postfach Z\u00fcrich Z\u00fcrich 8021",
    "addr:housenumber":"54 / 56",
    "addr:postcode":"8004 zuerich. postfach;8021",
    "addr:street":"Stauffacher-Quai",
    "iso:country":"CH",
    "sg:address":"Stauffacher-quai 54/56 8004 Z\u00fcrich. Postfach",
    "sg:city":"Z\u00fcrich",
    "sg:orig_category":"Detailhandel mit Beleuchtungs U Haushaltsgegenst\u00e4nden Herstellung von elektrischen Lampen U Leuchten",
    "sg:phone":"+41 12915700",
    "sg:postcode":"8021",
    "sg:province":"Z\u00fcrich",
    "wof:name":"Pablo Design Ag",
    "wof:placetype":"venue"
},
  "geometry": {"coordinates":[8.52866,47.369598],"type":"Point"}
}