{
  "type": "Feature",
  "properties": {
    "iso:country":"CH",
    "sg:address":"Kappelerstrasse 10",
    "sg:city":"Frauenfeld",
    "sg:orig_category":"Non-Classified Establishments",
    "sg:postcode":"8500",
    "sg:province":"Thurgau",
    "wof:name":"Zschokke Bau Ag",
    "wof:placetype":"venue"
},
  "geometry": {"coordinates":[9.4096689224,47.4332580566],"type":"Point"}
}