{
  "type": "Feature",
  "properties": {
    "iso:country":"CH",
    "sg:address":"Centralstrasse 16 6210 Sursee. Postfach",
    "sg:city":"Sursee",
    "sg:orig_category":"Herstellung von medizinischen U chirurgischen Ger\u00e4ten sowie orthop\u00e4dischen Vorrichtungen",
    "sg:postcode":"6210",
    "sg:province":"Luzern",
    "wof:name":"Innodent Gmbh Zahntechnische Arbeiten; Herstellung, Verkauf",
    "wof:placetype":"venue"
},
  "geometry": {"coordinates":[8.1047506332,47.1712493896],"type":"Point"}
}