{
  "type": "Feature",
  "properties": {
    "addr:full":"Rosenweg 21 Langenthal Bern 4900",
    "addr:housenumber":"21",
    "addr:postcode":"4900",
    "addr:street":"Rosenweg;Bern",
    "iso:country":"CH",
    "sg:address":"Rosenweg 21",
    "sg:city":"Langenthal",
    "sg:orig_category":"Architektur U Ingenieurb\u00fcros",
    "sg:phone":"+41 62 916 40 30",
    "sg:postcode":"4900",
    "sg:province":"Bern",
    "wof:name":"Bering Ag, Zweigniederlassung Langenthal",
    "wof:placetype":"venue"
},
  "geometry": {"coordinates":[7.789218,47.216038],"type":"Point"}
}