{
  "type": "Feature",
  "properties": {
    "iso:country":"CH",
    "sg:address":"Avenue De Richelien 42",
    "sg:city":"Versoix",
    "sg:orig_category":"Sonstiger spezialisierter Hoch U Tiefbau",
    "sg:postcode":"1290",
    "sg:province":"Gen\u00e8ve",
    "wof:name":"Savoy H.",
    "wof:placetype":"venue"
},
  "geometry": {"coordinates":[5.1808700562,45.8973388672],"type":"Point"}
}