{
  "type": "Feature",
  "properties": {
    "iso:country":"CH",
    "sg:address":"Moncor Route De 21",
    "sg:city":"Villars-sur-gl\u00e2ne",
    "sg:orig_category":"Grosshandel mit Getr\u00e4nken",
    "sg:phone":"+41 19101366",
    "sg:postcode":"1752",
    "sg:province":"Fribourg",
    "wof:name":"Vitality Fruchts\u00e4fte Konrad Dubs",
    "wof:placetype":"venue"
},
  "geometry": {"coordinates":[8.5781621933,47.3262138367],"type":"Point"}
}