{
  "type": "Feature",
  "properties": {
    "iso:country":"CH",
    "sg:address":"Laibach",
    "sg:city":"Elm",
    "sg:orig_category":"Verwertung von Milch",
    "sg:postcode":"8767",
    "sg:province":"Glarus",
    "wof:name":"Verband Der Butter Und Ziegerproduzenten Des Kantons Glarus Und Umgebung",
    "wof:placetype":"venue"
},
  "geometry": {"coordinates":[9.153960228,46.9111976624],"type":"Point"}
}