{
  "type": "Feature",
  "properties": {
    "iso:country":"CH",
    "sg:address":"Generoso Via 7",
    "sg:city":"Lugano",
    "sg:orig_category":"Sonstiger Grosshandel",
    "sg:postcode":"6900",
    "sg:province":"Ticino",
    "wof:name":"H\u00e4rdi Michael",
    "wof:placetype":"venue"
},
  "geometry": {"coordinates":[8.9438495636,45.995803833],"type":"Point"}
}