{
  "type": "Feature",
  "properties": {
    "iso:country":"CH",
    "sg:address":"Route Du Grand-mont 15",
    "sg:city":"Mont-sur-lausanne",
    "sg:orig_category":"Druck ohne Zeitungsdruck",
    "sg:postcode":"1052",
    "sg:province":"Vaud",
    "wof:name":"Impresscolor, Penseyres Edmond.",
    "wof:placetype":"venue"
},
  "geometry": {"coordinates":[6.6331381798,46.5625038147],"type":"Point"}
}