{
  "type": "Feature",
  "properties": {
    "iso:country":"CH",
    "sg:address":"1038",
    "sg:city":"Bercher",
    "sg:orig_category":"Verwertung von Milch",
    "sg:postcode":"1038",
    "sg:province":"Vaud",
    "wof:name":"Soci\u00e9t\u00e9 De Laiterie De Berlens",
    "wof:placetype":"venue"
},
  "geometry": {"coordinates":[6.914659977,46.6908187866],"type":"Point"}
}