{
  "type": "Feature",
  "properties": {
    "iso:country":"CH",
    "sg:address":"R\u00e9chy",
    "sg:city":"Chalais",
    "sg:orig_category":"Vermietung U Verpachtung von eigenen Immobilien",
    "sg:postcode":"3966",
    "sg:province":"Valais",
    "wof:name":"Polagir Sa",
    "wof:placetype":"venue"
},
  "geometry": {"coordinates":[7.5023798943,46.2648582458],"type":"Point"}
}