{
  "type": "Feature",
  "properties": {
    "iso:country":"CH",
    "sg:address":"La Pr\u00e9fecture",
    "sg:city":"Bulle",
    "sg:orig_category":"Wohnheime",
    "sg:postcode":"1630",
    "sg:province":"Fribourg",
    "wof:name":"Fondation Rose Lor\u00e9tan-pasquier",
    "wof:placetype":"venue"
},
  "geometry": {"coordinates":[7.0573811531,46.6186027527],"type":"Point"}
}