{
  "type": "Feature",
  "properties": {
    "iso:country":"CH",
    "sg:address":"Pfadackerstrasse 6",
    "sg:city":"Spreitenbach",
    "sg:classifiers":[
        {
            "category":"Professional",
            "subcategory":"Advertising",
            "type":"Services"
        }
    ],
    "sg:phone":"+41 56 401 51 30",
    "sg:postcode":"8957",
    "sg:province":"Aargau",
    "sg:tags":[
        "job",
        "employment"
    ],
    "wof:name":"Human Competence Center Ag",
    "wof:placetype":"venue"
},
  "geometry": {"coordinates":[8.3703260422,47.4245185852],"type":"Point"}
}