{
  "type": "Feature",
  "properties": {
    "iso:country":"CH",
    "sg:address":"Im Zopf 116",
    "sg:city":"D\u00fcrren\u00e4sch",
    "sg:orig_category":"RESTAURANTS: TEA-ROOMS",
    "sg:postcode":"5724",
    "sg:province":"Aargau",
    "wof:name":"Kurt Walti-kaspar",
    "wof:placetype":"venue"
},
  "geometry": {"coordinates":[8.1578493118,47.3212203979],"type":"Point"}
}