{
  "type": "Feature",
  "properties": {
    "iso:country":"CH",
    "sg:address":"Rorschacherstrasse 5",
    "sg:city":"Steinach",
    "sg:orig_category":"Instandhaltung U Reparatur von Automobilen",
    "sg:postcode":"9323",
    "sg:province":"St. Gallen",
    "wof:name":"Gnos Josef, Autogarage, Nachfolger Theiler Christof",
    "wof:placetype":"venue"
},
  "geometry": {"coordinates":[8.6341514587,46.8648033142],"type":"Point"}
}