{
  "type": "Feature",
  "properties": {
    "iso:country":"CH",
    "sg:address":"1868 Collombey Case Postale 205",
    "sg:city":"Collombey",
    "sg:orig_category":"Autospenglereien",
    "sg:phone":"+41 24 472 72 66",
    "sg:postcode":"1868",
    "sg:province":"Valais",
    "wof:name":"Jean-bernard Breu Carrosserie Des Colombes",
    "wof:placetype":"venue"
},
  "geometry": {"coordinates":[6.94582,46.27047],"type":"Point"}
}