{
  "type": "Feature",
  "properties": {
    "iso:country":"CH",
    "sg:address":"Bluche",
    "sg:city":"Randogne",
    "sg:classifiers":[
        {
            "category":"Travel",
            "subcategory":"Hotels & Motels",
            "type":"Entertainment"
        }
    ],
    "sg:phone":"+41 27 481 21 48",
    "sg:postcode":"3975",
    "sg:province":"Valais",
    "sg:tags":[
        "hotels",
        "mit",
        "restaurant"
    ],
    "wof:name":"H\u00f4tel Petit-paradis",
    "wof:placetype":"venue"
},
  "geometry": {"coordinates":[7.4955601692,46.309928894],"type":"Point"}
}