{
  "type": "Feature",
  "properties": {
    "iso:country":"CH",
    "sg:address":"Frontenex Avenue De 32 1207 Gen\u00e8ve. Postfach",
    "sg:city":"Gen\u00e8ve",
    "sg:orig_category":"Unclassifiable Establishments",
    "sg:postcode":"1207",
    "sg:province":"Gen\u00e8ve",
    "wof:name":"Soci\u00e9t\u00e9 Immobili\u00e8re Familia Rh\u00f4ne D",
    "wof:placetype":"venue"
},
  "geometry": {"coordinates":[6.1588449478,46.2014694214],"type":"Point"}
}