{
  "type": "Feature",
  "properties": {
    "iso:country":"CH",
    "sg:address":"Gartenweg 12 4310 Rheinfelden. Postfach",
    "sg:city":"Rheinfelden",
    "sg:orig_category":"Zahnarztpraxen",
    "sg:phone":"+41 61 836 90 90",
    "sg:postcode":"4310",
    "sg:province":"Aargau",
    "wof:name":"Dres Med.dent. A.& M. Baltzer Zahn\u00e4rzte",
    "wof:placetype":"venue"
},
  "geometry": {"coordinates":[7.7971878052,47.5535926819],"type":"Point"}
}