{
  "type": "Feature",
  "properties": {
    "iso:country":"CH",
    "sg:address":"J\u00f6chlerweg 4",
    "sg:city":"Baar",
    "sg:orig_category":"Unclassifiable Establishments",
    "sg:postcode":"6340",
    "sg:province":"Zug",
    "wof:name":"Hensler Heizungen Ag",
    "wof:placetype":"venue"
},
  "geometry": {"coordinates":[8.5264387131,47.2003974915],"type":"Point"}
}