{
  "type": "Feature",
  "properties": {
    "iso:country":"CH",
    "sg:address":"Rue Du Vieux-port 10",
    "sg:city":"Vouvry",
    "sg:orig_category":"Herstellung von sonstigen Metallwaren Herstellung von sonstigen M\u00f6beln",
    "sg:phone":"+41 24 481 14 39",
    "sg:postcode":"1896",
    "sg:province":"Valais",
    "wof:name":"Althaus Eric",
    "wof:placetype":"venue"
},
  "geometry": {"coordinates":[6.8931450844,46.3387184143],"type":"Point"}
}