{
  "type": "Feature",
  "properties": {
    "iso:country":"CH",
    "sg:address":"Seegartenstrasse 72-74",
    "sg:city":"Horgen",
    "sg:classifiers":[
        {
            "category":"Manufacturing",
            "subcategory":"Paper Products",
            "type":"Manufacturing & Wholesale Goods"
        }
    ],
    "sg:phone":"+41 17253636",
    "sg:postcode":"8810",
    "sg:province":"Z\u00fcrich",
    "sg:tags":[
        "recycled"
    ],
    "wof:name":"Ziegler-huber Ag",
    "wof:placetype":"venue"
},
  "geometry": {"coordinates":[8.5895557404,47.2663879395],"type":"Point"}
}