{
  "type": "Feature",
  "properties": {
    "iso:country":"CH",
    "sg:address":"Sonnhaldenstrasse 1",
    "sg:city":"Olten",
    "sg:orig_category":"Erschliessung von Grundst\u00fccken",
    "sg:postcode":"4600",
    "sg:province":"Solothurn",
    "wof:name":"Wohnbaugenossenschaft Sonnhalde Olten",
    "wof:placetype":"venue"
},
  "geometry": {"coordinates":[7.9130859375,47.3500862122],"type":"Point"}
}