{
  "type": "Feature",
  "properties": {
    "iso:country":"CH",
    "sg:address":"Aecherlistrasse 18",
    "sg:city":"Kerns",
    "sg:orig_category":"Herstellung von k\u00e4lte U lufttechnischen Erzeugnissen f\u00fcr gewerbliche Zwecke",
    "sg:phone":"+41 41 660 85 37",
    "sg:postcode":"6064",
    "sg:province":"Obwalden",
    "wof:name":"M & D Beraplan Gmbh",
    "wof:placetype":"venue"
},
  "geometry": {"coordinates":[8.2944717407,46.9087486267],"type":"Point"}
}