{
  "type": "Feature",
  "properties": {
    "iso:country":"CH",
    "sg:address":"Gagiurasc Al 4 6528 Camorino. Postfach",
    "sg:city":"Camorino",
    "sg:orig_category":"Erbringung von Dienstleistungen f\u00fcr Unternehmen",
    "sg:phone":"+41 91 840 26 07",
    "sg:postcode":"6528",
    "sg:province":"Ticino",
    "wof:name":"Design Express Copy Di Casali Edy Studio Di Creazioni Grafiche E Stampa Digitale",
    "wof:placetype":"venue"
},
  "geometry": {"coordinates":[9.003865242,46.1673622131],"type":"Point"}
}