{
  "type": "Feature",
  "properties": {
    "addr:full":"Leihgasse 2 Baar Zug 6340",
    "addr:housenumber":"2",
    "addr:postcode":"6340",
    "addr:street":"Leihgasse;Zug",
    "iso:country":"CH",
    "sg:address":"Leihgasse 2",
    "sg:city":"Baar",
    "sg:orig_category":"Advokaturb\u00fcros",
    "sg:phone":"+41 55 410 21 17",
    "sg:postcode":"6340",
    "sg:province":"Zug",
    "wof:name":"Hans Rudolf Ziegler Advokaturb\u00fcro",
    "wof:placetype":"venue"
},
  "geometry": {"coordinates":[8.777162,47.200268],"type":"Point"}
}