{
  "type": "Feature",
  "properties": {
    "addr:full":"Obere Hauptgasse 20 Thun Bern 3600",
    "addr:housenumber":"20",
    "addr:postcode":"3600",
    "addr:street":"Obere Hauptgasse;Bern",
    "iso:country":"CH",
    "sg:address":"Obere Hauptgasse 20",
    "sg:city":"Thun",
    "sg:orig_category":"Hardwareberatung",
    "sg:phone":"+41 33 222 82 38",
    "sg:postcode":"3600",
    "sg:province":"Bern",
    "wof:name":"Io Computer Gmbh",
    "wof:placetype":"venue"
},
  "geometry": {"coordinates":[7.629362,46.758888],"type":"Point"}
}