{
  "type": "Feature",
  "properties": {
    "iso:country":"CH",
    "sg:address":"Chaletstrasse 5 9320 Arbon. Postfach",
    "sg:city":"Arbon",
    "sg:orig_category":"Architektur U Ingenieurb\u00fcros",
    "sg:postcode":"9320",
    "sg:province":"Thurgau",
    "wof:name":"Sas Ingenieurb\u00fcro Ag",
    "wof:placetype":"venue"
},
  "geometry": {"coordinates":[9.431979,47.51133],"type":"Point"}
}