{
  "type": "Feature",
  "properties": {
    "iso:country":"CH",
    "sg:address":"M\u00fcrtschenstrasse 5",
    "sg:city":"Tuggen",
    "sg:orig_category":"Herstellung von Metallkonstruktionen",
    "sg:phone":"+41 55 445 21 06",
    "sg:postcode":"8856",
    "sg:province":"Schwyz",
    "wof:name":"Sutter Bau-team Gmbh",
    "wof:placetype":"venue"
},
  "geometry": {"coordinates":[8.9473018646,47.2046775818],"type":"Point"}
}