{
  "type": "Feature",
  "properties": {
    "iso:country":"CH",
    "sg:address":"Kapellenstrasse 37 4052 Basel. Postfach",
    "sg:city":"Basel",
    "sg:orig_category":"Vermietung U Verpachtung von eigenen Immobilien",
    "sg:postcode":"4051",
    "sg:province":"Basel-Stadt",
    "wof:name":"Reichen Peter W. Immobilien, Versicherungsberatungen",
    "wof:placetype":"venue"
},
  "geometry": {"coordinates":[7.6024851799,47.5511322021],"type":"Point"}
}