{
  "type": "Feature",
  "properties": {
    "iso:country":"CH",
    "sg:address":"Obere Gasse 14",
    "sg:city":"Chur",
    "sg:orig_category":"Detailhandel mit Musikinstrumenten Detailhandel mit elektrischen Haushalts-,Radio U Fernsehger\u00e4ten s",
    "sg:phone":"+41 81 252 31 65",
    "sg:postcode":"7000",
    "sg:province":"Graubunden",
    "wof:name":"Fischer Manfred Musikhaus Ag",
    "wof:placetype":"venue"
},
  "geometry": {"coordinates":[9.5301885605,46.8488235474],"type":"Point"}
}