{
  "type": "Feature",
  "properties": {
    "iso:country":"CH",
    "sg:address":"Via Cantonale 16",
    "sg:city":"Lugano",
    "sg:orig_category":"Wirtschaftspr\u00fcfung, Steuerberatung U Treuhand",
    "sg:phone":"+41 91 924 96 80",
    "sg:postcode":"6900",
    "sg:province":"Ticino",
    "wof:name":"2k Data Services Sa",
    "wof:placetype":"venue"
},
  "geometry": {"coordinates":[8.9507102966,46.0086479187],"type":"Point"}
}