{
  "type": "Feature",
  "properties": {
    "iso:country":"CH",
    "sg:address":"Wolfwilstrasse 442",
    "sg:city":"Kestenholz",
    "sg:orig_category":"Leichtmetallgiesserei Mechanische Werkst\u00e4tten",
    "sg:phone":"+41 62 393 12 06",
    "sg:postcode":"4703",
    "sg:province":"Solothurn",
    "wof:name":"Studer Gebr. Ag Metallgiesserei",
    "wof:placetype":"venue"
},
  "geometry": {"coordinates":[7.7619709969,47.2788848877],"type":"Point"}
}