{
  "type": "Feature",
  "properties": {
    "iso:country":"CH",
    "sg:address":"Beim Schulhaus",
    "sg:city":"Lauterbrunnen",
    "sg:orig_category":"Sportschulen Ski-& Snowboardschulen",
    "sg:phone":"+41 33 855 32 70",
    "sg:postcode":"3822",
    "sg:province":"Bern",
    "wof:name":"Schweiz.skischule",
    "wof:placetype":"venue"
},
  "geometry": {"coordinates":[7.8920111656,46.5591201782],"type":"Point"}
}