{
  "type": "Feature",
  "properties": {
    "iso:country":"CH",
    "sg:address":"Bielstrasse 54",
    "sg:city":"Selzach",
    "sg:orig_category":"Herstellung von Sitzm\u00f6beln",
    "sg:phone":"+41 32 652 32 10",
    "sg:postcode":"2545",
    "sg:province":"Solothurn",
    "wof:name":"Ofner Polsterm\u00f6bel.",
    "wof:placetype":"venue"
},
  "geometry": {"coordinates":[7.3660211563,47.1803474426],"type":"Point"}
}