{
  "type": "Feature",
  "properties": {
    "iso:country":"CH",
    "sg:address":"Gemsenstrasse 9 8006 Z\u00fcrich. Postfach",
    "sg:city":"Z\u00fcrich",
    "sg:orig_category":"Sonstiger Grosshandel",
    "sg:postcode":"8001",
    "sg:province":"Z\u00fcrich",
    "wof:name":"Erma, Ch. Demarmels Import, Export Von Und Handel Mit Waren Aller Art: Reiseagentur Usw",
    "wof:placetype":"venue"
},
  "geometry": {"coordinates":[8.5395593643,47.3887443542],"type":"Point"}
}