{
  "type": "Feature",
  "properties": {
    "iso:country":"CH",
    "sg:address":"Rigiblick 15",
    "sg:city":"Ottenbach",
    "sg:orig_category":"Grosshandel mit Eisenwaren sowie Installationsbedarf f\u00fcr Gas, Wasser U Heizung Sanit\u00e4r, Heizungs U L",
    "sg:phone":"+41 62 291 14 45",
    "sg:postcode":"8913",
    "sg:province":"Z\u00fcrich",
    "wof:name":"Hoesch Sanit\u00e4r Ag",
    "wof:placetype":"venue"
},
  "geometry": {"coordinates":[7.9755339622,47.3593215942],"type":"Point"}
}