{
  "type": "Feature",
  "properties": {
    "iso:country":"CH",
    "sg:address":"Vorstadt 48",
    "sg:city":"Olsberg",
    "sg:orig_category":"Dienstleistungen von Beteiligungsgesellschaften",
    "sg:phone":"+41 61 283 15 25",
    "sg:postcode":"4305",
    "sg:province":"Aargau",
    "wof:name":"Forex Select Inc.",
    "wof:placetype":"venue"
},
  "geometry": {"coordinates":[7.7855110168,47.5212745667],"type":"Point"}
}