{
  "type": "Feature",
  "properties": {
    "iso:country":"CH",
    "sg:address":"Via Cantonale 55",
    "sg:city":"Castione",
    "sg:orig_category":"Malerei",
    "sg:postcode":"6532",
    "sg:province":"Ticino",
    "wof:name":"Ivan Berti Impresa Di Pittura",
    "wof:placetype":"venue"
},
  "geometry": {"coordinates":[9.0427570343,46.2287521362],"type":"Point"}
}