{
  "type": "Feature",
  "properties": {
    "iso:country":"CH",
    "sg:address":"Mittelstrasse 1",
    "sg:city":"Adliswil",
    "sg:orig_category":"Allgemeiner Hoch U Tiefbau",
    "sg:postcode":"8134",
    "sg:province":"Z\u00fcrich",
    "wof:name":"R\u00fcttimann Jacques + Michel",
    "wof:placetype":"venue"
},
  "geometry": {"coordinates":[8.525522,47.311291],"type":"Point"}
}