{
  "type": "Feature",
  "properties": {
    "iso:country":"CH",
    "sg:address":"Furkastrasse 20 3902 Glis. Postfach",
    "sg:city":"Glis",
    "sg:orig_category":"Detailhandel mit elektrischen Haushalts-,Radio U Fernsehger\u00e4ten sowie Musikinstrumenten",
    "sg:postcode":"3902",
    "sg:province":"Valais",
    "wof:name":"Hifi-high-end, Rothacher Charly",
    "wof:placetype":"venue"
},
  "geometry": {"coordinates":[7.9776821136,46.3108596802],"type":"Point"}
}