{
  "type": "Feature",
  "properties": {
    "iso:country":"CH",
    "sg:address":"Mattenweg 1",
    "sg:city":"Kleind\u00f6ttingen",
    "sg:orig_category":"Architekturb\u00fcros",
    "sg:phone":"+41 56 245 11 63",
    "sg:postcode":"5314",
    "sg:province":"Aargau",
    "wof:name":"Kurt M\u00e4rki Architekturb\u00fcro Architektur Und Bauleitungsb\u00fcro",
    "wof:placetype":"venue"
},
  "geometry": {"coordinates":[8.242476,47.568096],"type":"Point"}
}