{
  "type": "Feature",
  "properties": {
    "addr:full":"Lenzburgerstrasse 2 Niederlenz Aargau 5702",
    "addr:housenumber":"2",
    "addr:postcode":"5702",
    "addr:street":"Lenzburgerstrasse",
    "iso:country":"CH",
    "sg:address":"Lenzburgerstrasse 2",
    "sg:city":"Niederlenz",
    "sg:orig_category":"Bauschreinerei Herstellung von K\u00fcchenm\u00f6beln",
    "sg:phone":"+41 62 885 40 40",
    "sg:postcode":"5702",
    "sg:province":"Aargau",
    "wof:name":"Lang K\u00fcchen Ag",
    "wof:placetype":"venue"
},
  "geometry": {"coordinates":[8.177565,47.399075],"type":"Point"}
}