{
  "type": "Feature",
  "properties": {
    "iso:country":"CH",
    "sg:address":"3186",
    "sg:city":"D\u00fcdingen",
    "sg:orig_category":"Instandhaltung U Reparatur von Automobilen",
    "sg:phone":"+41 26 493 13 47",
    "sg:postcode":"3186",
    "sg:province":"Fribourg",
    "wof:name":"Cipri-riedo Michel",
    "wof:placetype":"venue"
},
  "geometry": {"coordinates":[7.1900749207,46.8504104614],"type":"Point"}
}