{
  "type": "Feature",
  "properties": {
    "iso:country":"CH",
    "sg:address":"Bertastrasse 18a",
    "sg:city":"Z\u00fcrich",
    "sg:orig_category":"Instandhaltung U Reparatur von Automobilen",
    "sg:phone":"+41 14512222",
    "sg:postcode":"8003",
    "sg:province":"Z\u00fcrich",
    "wof:name":"Garage Kramis Nachf. H\u00e4berli P. Und Resta M.",
    "wof:placetype":"venue"
},
  "geometry": {"coordinates":[8.5148286819,47.3748130798],"type":"Point"}
}