{
  "type": "Feature",
  "properties": {
    "addr:full":"Chemin De Villardiez 2 A Pully Vaud 1009",
    "addr:housenumber":"2 a",
    "addr:postcode":"1009",
    "addr:street":"Chemin De Villardiez",
    "iso:country":"CH",
    "sg:address":"Chemin De Villardiez 2 A",
    "sg:city":"Pully",
    "sg:orig_category":"Architekturb\u00fcros",
    "sg:phone":"+41 21 728 10 61",
    "sg:postcode":"1009",
    "sg:province":"Vaud",
    "wof:name":"Bureau D'architecture Pierre D\u00e9costerd",
    "wof:placetype":"venue"
},
  "geometry": {"coordinates":[6.662502,46.514988],"type":"Point"}
}