{
  "type": "Feature",
  "properties": {
    "iso:country":"CH",
    "sg:address":"Hauptstr. 143",
    "sg:city":"Au",
    "sg:classifiers":[
        {
            "category":"Personal",
            "subcategory":"Shoe Repair & Shine",
            "type":"Services"
        }
    ],
    "sg:phone":"+41 71 744 16 56",
    "sg:postcode":"9434",
    "sg:province":"St. Gallen",
    "sg:tags":[
        "leather"
    ],
    "wof:name":"Sowa Ag",
    "wof:placetype":"venue"
},
  "geometry": {"coordinates":[9.6357841492,47.4229431152],"type":"Point"}
}