{
  "type": "Feature",
  "properties": {
    "iso:country":"CH",
    "sg:address":"Stationsstrasse 15",
    "sg:city":"Brenzikofen",
    "sg:orig_category":"Bauschreinerei Innenausbau",
    "sg:phone":"+41 31 771 37 47",
    "sg:postcode":"3671",
    "sg:province":"Bern",
    "wof:name":"Ren\u00e9 Morgenthaler Schreinerei",
    "wof:placetype":"venue"
},
  "geometry": {"coordinates":[7.61041,46.817108],"type":"Point"}
}