{
  "type": "Feature",
  "properties": {
    "iso:country":"CH",
    "sg:address":"Rue Des Foss\u00e9s 23",
    "sg:city":"Morges",
    "sg:orig_category":"Chiropraktik",
    "sg:phone":"+41 21 802 31 31",
    "sg:postcode":"1110",
    "sg:province":"Vaud",
    "wof:name":"Christophe Wegelin Chiropraticien",
    "wof:placetype":"venue"
},
  "geometry": {"coordinates":[6.497867,46.509529],"type":"Point"}
}