{
  "type": "Feature",
  "properties": {
    "iso:country":"CH",
    "sg:address":"Murgenthalstrasse 52",
    "sg:city":"Langenthal",
    "sg:orig_category":"Grosshandel mit Holz U Baustoffen Herstellung von Bergwerks U Baumaschinen",
    "sg:phone":"+41 62 922 48 41",
    "sg:postcode":"4900",
    "sg:province":"Bern",
    "wof:name":"Kohler F.",
    "wof:placetype":"venue"
},
  "geometry": {"coordinates":[7.789493084,47.2234230042],"type":"Point"}
}