{
  "type": "Feature",
  "properties": {
    "iso:country":"CH",
    "sg:address":"Langenhagstrasse 3",
    "sg:city":"Aesch",
    "sg:orig_category":"Automatic Pipette Metering Machines",
    "sg:phone":"+41 61 756 99 77",
    "sg:postcode":"4147",
    "sg:province":"Basel-Landschaft",
    "wof:name":"Flaigg Ag",
    "wof:placetype":"venue"
},
  "geometry": {"coordinates":[7.590016,47.477158],"type":"Point"}
}