{
  "type": "Feature",
  "properties": {
    "iso:country":"CH",
    "sg:address":"Bielstrasse 8",
    "sg:city":"Grenchen",
    "sg:orig_category":"Galvanische Betriebe",
    "sg:phone":"+41 79 417 85 86",
    "sg:postcode":"2540",
    "sg:province":"Solothurn",
    "wof:name":"Eloxal Aluminiumeloxierung",
    "wof:placetype":"venue"
},
  "geometry": {"coordinates":[7.3954820633,47.1923179626],"type":"Point"}
}