{
  "type": "Feature",
  "properties": {
    "iso:country":"CH",
    "sg:address":"Rue Du Centre 8",
    "sg:city":"Crissier",
    "sg:orig_category":"Rolladen- and Storenmontage",
    "sg:phone":"+41 21 635 82 87",
    "sg:postcode":"1023",
    "sg:province":"Vaud",
    "wof:name":"Giulio Persano Stores Syst\u00e8me",
    "wof:placetype":"venue"
},
  "geometry": {"coordinates":[6.5771389008,46.5533256531],"type":"Point"}
}