{
  "type": "Feature",
  "properties": {
    "iso:country":"CH",
    "sg:address":"Eichgasse 4",
    "sg:city":"Biberstein",
    "sg:orig_category":"Herstellung von k\u00e4lte U lufttechnischen Erzeugnissen f\u00fcr gewerbliche Zwecke Installation von Heizung",
    "sg:phone":"+41 62 827 13 34",
    "sg:postcode":"5023",
    "sg:province":"Aargau",
    "wof:name":"Hauser-k\u00fchlung",
    "wof:placetype":"venue"
},
  "geometry": {"coordinates":[8.083106041,47.4142875671],"type":"Point"}
}