{
  "type": "Feature",
  "properties": {
    "iso:country":"CH",
    "sg:address":"Chalet Iris 2 3780 Gruben B. Gstaad. Postfach",
    "sg:city":"Gstaad",
    "sg:orig_category":"Unternehmensberatung",
    "sg:postcode":"3780",
    "sg:province":"Bern",
    "wof:name":"Lgb Berater, Blunschi L. Und G., Gstaad",
    "wof:placetype":"venue"
},
  "geometry": {"coordinates":[7.2839550972,46.4762382507],"type":"Point"}
}