{
  "type": "Feature",
  "properties": {
    "iso:country":"CH",
    "sg:address":"Pini Via A. 32",
    "sg:city":"Biasca",
    "sg:orig_category":"Vermietung U Verpachtung von eigenen Immobilien",
    "sg:postcode":"6710",
    "sg:province":"Ticino",
    "wof:name":"Cogeco Sviluppi Sa",
    "wof:placetype":"venue"
},
  "geometry": {"coordinates":[9.0250043869,45.8448371887],"type":"Point"}
}