{
  "type": "Feature",
  "properties": {
    "iso:country":"CH",
    "sg:address":"Via Giacomo Puccini 4b",
    "sg:city":"Chiasso",
    "sg:orig_category":"Vermittlung von Immobilien",
    "sg:phone":"+41 91 682 03 53",
    "sg:postcode":"6830",
    "sg:province":"Ticino",
    "wof:name":"Roberto Sanvido Agenzia Immobiliare",
    "wof:placetype":"venue"
},
  "geometry": {"coordinates":[9.0339078903,45.8371353149],"type":"Point"}
}