{
  "type": "Feature",
  "properties": {
    "iso:country":"CH",
    "sg:address":"G\u00f6schenenstrasse 50",
    "sg:city":"Basel",
    "sg:orig_category":"Verlegen von Fliesen U Platten",
    "sg:phone":"+41 79 691 59 92",
    "sg:postcode":"4054",
    "sg:province":"Basel-Stadt",
    "wof:name":"Ernst Meister Ofenbau & Plattenbel\u00e4ge",
    "wof:placetype":"venue"
},
  "geometry": {"coordinates":[8.7341480255,47.1973953247],"type":"Point"}
}