{
  "type": "Feature",
  "properties": {
    "iso:country":"CH",
    "sg:address":"Chemin De La Fauvette 1",
    "sg:city":"Mont-sur-rolle",
    "sg:orig_category":"Herstellung von Fenstern U T\u00fcren aus Holz Schlossereien",
    "sg:phone":"+41 79 401 68 07",
    "sg:postcode":"1185",
    "sg:province":"Vaud",
    "wof:name":"Gt M\u00e9tal Trachsel & Garzon",
    "wof:placetype":"venue"
},
  "geometry": {"coordinates":[6.3489627838,46.4635810852],"type":"Point"}
}