{
  "type": "Feature",
  "properties": {
    "iso:country":"CH",
    "sg:address":"Sumpfgasse 149.",
    "sg:city":"Etziken",
    "sg:orig_category":"Wirtschaftspr\u00fcfung, Steuerberatung U Treuhand",
    "sg:postcode":"4554",
    "sg:province":"Solothurn",
    "wof:name":"Misteli, Johann Josef, Treuhandbureau.",
    "wof:placetype":"venue"
},
  "geometry": {"coordinates":[7.6469302177,47.1937294006],"type":"Point"}
}