{
  "type": "Feature",
  "properties": {
    "addr:full":"B\u00e4chgasse 10 Nunningen Solothurn 4208",
    "addr:housenumber":"10",
    "addr:postcode":"4208",
    "addr:street":"Baechgasse",
    "iso:country":"CH",
    "sg:address":"B\u00e4chgasse 10",
    "sg:city":"Nunningen",
    "sg:orig_category":"Arbeitnehmerverb\u00e4nde",
    "sg:phone":"+41 79 667 83 63",
    "sg:postcode":"4208",
    "sg:province":"Solothurn",
    "wof:name":"Schweiz.schiedsrichter-verband",
    "wof:placetype":"venue"
},
  "geometry": {"coordinates":[7.621858,47.392895],"type":"Point"}
}