{
  "type": "Feature",
  "properties": {
    "iso:country":"CH",
    "sg:address":"Bremgartenstrasse 84 8967 Widen. Postfach",
    "sg:city":"Widen",
    "sg:orig_category":"Herstellung von Kakao, Schokoladeerzeugnissen U Zuckerwaren",
    "sg:postcode":"8967",
    "sg:province":"Aargau",
    "wof:name":"Solentaler Confiserie-spezialit\u00e4ten Gmbh",
    "wof:placetype":"venue"
},
  "geometry": {"coordinates":[8.3549451828,47.3626823425],"type":"Point"}
}