{
  "type": "Feature",
  "properties": {
    "addr:full":"Rue De La Gruy\u00e8re 68 Riaz Fribourg 1632",
    "addr:housenumber":"68",
    "addr:postcode":"1632",
    "addr:street":"Rue De La Gruye\u0300Re",
    "iso:country":"CH",
    "sg:address":"Rue De La Gruy\u00e8re 68",
    "sg:city":"Riaz",
    "sg:orig_category":"Detailhandel mit Brot, Back U S\u00fcsswaren",
    "sg:phone":"+41 26 912 83 06",
    "sg:postcode":"1632",
    "sg:province":"Fribourg",
    "wof:name":"Claude Jolliet Boulangerie",
    "wof:placetype":"venue"
},
  "geometry": {"coordinates":[7.063206,46.642334],"type":"Point"}
}