{
  "type": "Feature",
  "properties": {
    "addr:full":"Lilienstrasse 41 Allschwil Basel-Landschaft 4123",
    "addr:housenumber":"41",
    "addr:postcode":"4123",
    "addr:street":"Lilienstrasse",
    "iso:country":"CH",
    "sg:address":"Lilienstrasse 41",
    "sg:city":"Allschwil",
    "sg:orig_category":"Betrieb von Taxis",
    "sg:phone":"+41 61 482 15 41",
    "sg:postcode":"4123",
    "sg:province":"Basel-Landschaft",
    "wof:name":"Pasquale Federico Taxi",
    "wof:placetype":"venue"
},
  "geometry": {"coordinates":[7.551818,47.550598],"type":"Point"}
}