{
  "type": "Feature",
  "properties": {
    "iso:country":"CH",
    "sg:address":"Rte De Bellegarde 100 1284 Chancy. Postfach",
    "sg:city":"Chancy",
    "sg:orig_category":"Bau von Strassen, Sportanlagen U Bahnverkehrsstrecken",
    "sg:postcode":"1284",
    "sg:province":"Gen\u00e8ve",
    "wof:name":"Ernst Frey Ag",
    "wof:placetype":"venue"
},
  "geometry": {"coordinates":[7.72126,47.527882],"type":"Point"}
}