{
  "type": "Feature",
  "properties": {
    "addr:full":"Kapellenweg 2 4923 Wynau. Postfach Wynau Bern 4923",
    "addr:housenumber":"2",
    "addr:postcode":"4923;4923",
    "addr:street":"Kapellenweg;Postfach",
    "iso:country":"CH",
    "sg:address":"Kapellenweg 2 4923 Wynau. Postfach",
    "sg:city":"Wynau",
    "sg:orig_category":"Autogaragen",
    "sg:phone":"+41 62 929 20 75",
    "sg:postcode":"4923",
    "sg:province":"Bern",
    "wof:name":"Hans-rudolf Greub Garage",
    "wof:placetype":"venue"
},
  "geometry": {"coordinates":[7.822964,47.258247],"type":"Point"}
}