{
  "type": "Feature",
  "properties": {
    "iso:country":"CH",
    "sg:address":"Farbweg 11a 3400 Burgdorf. Postfach",
    "sg:city":"Burgdorf",
    "sg:classifiers":[
        {
            "category":"Restaurant",
            "type":"Food & Drink"
        }
    ],
    "sg:phone":"+41 34 423 14 34",
    "sg:postcode":"3401",
    "sg:province":"Bern",
    "wof:name":"Restaurant Warteck",
    "wof:placetype":"venue"
},
  "geometry": {"coordinates":[7.6239981651,47.059841156],"type":"Point"}
}