{
  "type": "Feature",
  "properties": {
    "iso:country":"CH",
    "sg:address":"Gerbergasse 54",
    "sg:city":"Basel",
    "sg:orig_category":"Unclassifiable Establishments",
    "sg:postcode":"4001",
    "sg:province":"Basel-Stadt",
    "wof:name":"Coiff Elle Ag Coiffeursalon",
    "wof:placetype":"venue"
},
  "geometry": {"coordinates":[7.5885310173,47.555644989],"type":"Point"}
}