{
  "type": "Feature",
  "properties": {
    "iso:country":"CH",
    "sg:address":"Rainstrasse 11",
    "sg:city":"Steinhausen",
    "sg:orig_category":"Non-Classified Establishments",
    "sg:phone":"+41 41 740 47 60",
    "sg:postcode":"6312",
    "sg:province":"Zug",
    "wof:name":"Health Consulting And Commercial Administration Gmbh",
    "wof:placetype":"venue"
},
  "geometry": {"coordinates":[8.4943199158,47.1934967041],"type":"Point"}
}