{
  "type": "Feature",
  "properties": {
    "iso:country":"CH",
    "sg:address":"Aargauerstrasse 1",
    "sg:city":"Z\u00fcrich",
    "sg:orig_category":"Grosshandel mit Obst U Gem\u00fcse",
    "sg:phone":"+41 17813030",
    "sg:postcode":"8048",
    "sg:province":"Z\u00fcrich",
    "wof:name":"Bettio S\u00f6hne Ag Comestibles S\u00fcdfr\u00fcchte",
    "wof:placetype":"venue"
},
  "geometry": {"coordinates":[8.645359993,47.2416801453],"type":"Point"}
}