{
  "type": "Feature",
  "properties": {
    "iso:country":"CH",
    "sg:address":"Unterer Rheinweg 104",
    "sg:city":"Basel",
    "sg:orig_category":"Vermittlung von Immobilien",
    "sg:phone":"+41 61 692 68 83",
    "sg:postcode":"4057",
    "sg:province":"Basel-Stadt",
    "wof:name":"Rebstock Ag",
    "wof:placetype":"venue"
},
  "geometry": {"coordinates":[7.5868377686,47.5670928955],"type":"Point"}
}