{
  "type": "Feature",
  "properties": {
    "iso:country":"CH",
    "sg:address":"Molo Via Cancelliere 10",
    "sg:city":"Bellinzona",
    "sg:orig_category":"Vermietung U Verpachtung von eigenen Immobilien",
    "sg:postcode":"6500",
    "sg:province":"Ticino",
    "wof:name":"Alfia Sa",
    "wof:placetype":"venue"
},
  "geometry": {"coordinates":[9.0268745422,46.1947021484],"type":"Point"}
}