{
  "type": "Feature",
  "properties": {
    "iso:country":"CH",
    "sg:address":"Friesenbergstrasse 110",
    "sg:city":"Z\u00fcrich",
    "sg:orig_category":"Herstellung von Gummiwaren Satzherstellung U Reproduktion",
    "sg:phone":"+41 17612111",
    "sg:postcode":"8055",
    "sg:province":"Z\u00fcrich",
    "wof:name":"Optiflex Ag",
    "wof:placetype":"venue"
},
  "geometry": {"coordinates":[8.4395618439,47.2759475708],"type":"Point"}
}