{
  "type": "Feature",
  "properties": {
    "iso:country":"CH",
    "sg:address":"Rue Du Stade 4",
    "sg:city":"Sion",
    "sg:orig_category":"Advokaturb\u00fcros Notariate",
    "sg:phone":"+41 27 203 66 77",
    "sg:postcode":"1950",
    "sg:province":"Valais",
    "wof:name":"Roger Pannatier Etude D'avocat & Notaire",
    "wof:placetype":"venue"
},
  "geometry": {"coordinates":[7.372246,46.233795],"type":"Point"}
}