{
  "type": "Feature",
  "properties": {
    "iso:country":"CH",
    "sg:address":"Limmatplatz 6 8005 Z\u00fcrich. Postfach",
    "sg:city":"Z\u00fcrich",
    "sg:orig_category":"Markt U Meinungsforschung",
    "sg:postcode":"8001",
    "sg:province":"Z\u00fcrich",
    "wof:name":"M.c.s. Gmbh",
    "wof:placetype":"venue"
},
  "geometry": {"coordinates":[-77.13302612299999,40.4769287109],"type":"Point"}
}