{
  "type": "Feature",
  "properties": {
    "iso:country":"CH",
    "sg:address":"Seem\u00e4ttlistrasse 6",
    "sg:city":"Muttenz",
    "sg:orig_category":"Vereine Vogel-& Naturschutz",
    "sg:phone":"+41 61 461 22 96",
    "sg:postcode":"4132",
    "sg:province":"Basel-Landschaft",
    "wof:name":"Ornithol.ges.bs,sekt.fringilla",
    "wof:placetype":"venue"
},
  "geometry": {"coordinates":[7.6578087807,47.5253257751],"type":"Point"}
}