{
  "type": "Feature",
  "properties": {
    "iso:country":"CH",
    "sg:address":"Lausanne Rue De 14",
    "sg:city":"Fribourg",
    "sg:orig_category":"Fachdetailhandel in Verkaufsr\u00e4umen",
    "sg:postcode":"1700",
    "sg:province":"Fribourg",
    "wof:name":"Pfister Bruno Sa",
    "wof:placetype":"venue"
},
  "geometry": {"coordinates":[7.1602320671,46.8059997559],"type":"Point"}
}