{
  "type": "Feature",
  "properties": {
    "iso:country":"CH",
    "sg:address":"Gotthardstrasse 80",
    "sg:city":"Basel",
    "sg:orig_category":"Erbringung von Dienstleistungen f\u00fcr Unternehmen",
    "sg:postcode":"4054",
    "sg:province":"Basel-Stadt",
    "wof:name":"Berger Consulting",
    "wof:placetype":"venue"
},
  "geometry": {"coordinates":[7.5625939369,47.5496253967],"type":"Point"}
}