{
  "type": "Feature",
  "properties": {
    "addr:full":"Sonnhaldenstrasse 29 Kloten Z\u00fcrich 8302",
    "addr:housenumber":"29",
    "addr:postcode":"8302",
    "addr:street":"Sonnhaldenstrasse",
    "iso:country":"CH",
    "sg:address":"Sonnhaldenstrasse 29",
    "sg:city":"Kloten",
    "sg:orig_category":"Bau U Wohngenossenschaften",
    "sg:postcode":"8302",
    "sg:province":"Z\u00fcrich",
    "wof:name":"Wohnbaugen.holberg",
    "wof:placetype":"venue"
},
  "geometry": {"coordinates":[8.574908,47.448032],"type":"Point"}
}