{
  "type": "Feature",
  "properties": {
    "iso:country":"CH",
    "sg:address":"Zeughausstrasse 25 3250 Lyss. Postfach",
    "sg:city":"Lyss",
    "sg:orig_category":"Pensionskassen",
    "sg:postcode":"3250",
    "sg:province":"Bern",
    "wof:name":"Personalf\u00fcrsorgestiftung Der Firma Arni Ag In Lyss",
    "wof:placetype":"venue"
},
  "geometry": {"coordinates":[7.3010349274,47.0747566223],"type":"Point"}
}