{
  "type": "Feature",
  "properties": {
    "iso:country":"CH",
    "sg:address":"Rue Du March\u00e9 28",
    "sg:city":"Gen\u00e8ve",
    "sg:orig_category":"Detailhandel mit Schuhen U Lederwaren Vermittlung von Immobilien",
    "sg:postcode":"1204",
    "sg:province":"Gen\u00e8ve",
    "wof:name":"Spira Daniel",
    "wof:placetype":"venue"
},
  "geometry": {"coordinates":[6.1472101212,46.2029571533],"type":"Point"}
}