{
  "type": "Feature",
  "properties": {
    "iso:country":"CH",
    "sg:address":"Dorfstrasse 9",
    "sg:city":"Niederhasli",
    "sg:orig_category":"Konkurs- and Betreibungs\u00e4mter",
    "sg:phone":"+41 18503808",
    "sg:postcode":"8155",
    "sg:province":"Z\u00fcrich",
    "wof:name":"Betreibungsamt Niederhasli",
    "wof:placetype":"venue"
},
  "geometry": {"coordinates":[8.4846305847,47.4805831909],"type":"Point"}
}