{
  "type": "Feature",
  "properties": {
    "iso:country":"CH",
    "sg:address":"Luziaweg 5",
    "sg:city":"Freienbach",
    "sg:orig_category":"Softwareentwicklung U beratung",
    "sg:phone":"+41 55 410 19 03",
    "sg:postcode":"8807",
    "sg:province":"Schwyz",
    "wof:name":"St\u00e4heli Informatik",
    "wof:placetype":"venue"
},
  "geometry": {"coordinates":[8.7634353638,47.2034225464],"type":"Point"}
}