{
  "type": "Feature",
  "properties": {
    "iso:country":"CH",
    "sg:address":"Rue De La Vidond\u00e9",
    "sg:city":"Leytron",
    "sg:orig_category":"Rebbau",
    "sg:phone":"+41 27 306 23 36",
    "sg:postcode":"1912",
    "sg:province":"Valais",
    "wof:name":"Pierre Buchard Propri\u00e9taire-encaveur",
    "wof:placetype":"venue"
},
  "geometry": {"coordinates":[7.2079148293,46.1862106323],"type":"Point"}
}