{
  "type": "Feature",
  "properties": {
    "iso:country":"CH",
    "sg:address":"Engelbergstrasse 28a",
    "sg:city":"Stans",
    "sg:orig_category":"Sonstiges Versicherungsgewerbe",
    "sg:postcode":"6370",
    "sg:province":"Nidwalden",
    "wof:name":"Christen Roger",
    "wof:placetype":"venue"
},
  "geometry": {"coordinates":[8.3688764572,46.9566726685],"type":"Point"}
}