{
  "type": "Feature",
  "properties": {
    "iso:country":"CH",
    "sg:address":"Via Motta 6 6850 Mendrisio Casella Postale",
    "sg:city":"Mendrisio",
    "sg:orig_category":"Grosshandel mit festen Brennstoffen U Mineral\u00f6lerzeugnissen",
    "sg:postcode":"6850",
    "sg:province":"Ticino",
    "wof:name":"Carbura",
    "wof:placetype":"venue"
},
  "geometry": {"coordinates":[8.2241401672,46.8130912781],"type":"Point"}
}