{
  "type": "Feature",
  "properties": {
    "iso:country":"CH",
    "sg:address":"Hofackerstrasse 16",
    "sg:city":"Br\u00fctten",
    "sg:orig_category":"Detailhandel mit Sportartikeln Fachdetailhandel in Verkaufsr\u00e4umen",
    "sg:phone":"+41 52 345 35 93",
    "sg:postcode":"8311",
    "sg:province":"Z\u00fcrich",
    "wof:name":"Weber Pro Equi Reitsportzubeh\u00f6r",
    "wof:placetype":"venue"
},
  "geometry": {"coordinates":[8.6706867218,47.4716835022],"type":"Point"}
}