{
  "type": "Feature",
  "properties": {
    "iso:country":"CH",
    "sg:address":"Chemin De La Ch\u00e8vre 6",
    "sg:city":"Yverdon-les-bains",
    "sg:orig_category":"Sanit\u00e4r U Heizungsinstallation Sanit\u00e4rinstallation",
    "sg:phone":"+41 24 425 03 83",
    "sg:postcode":"1400",
    "sg:province":"Vaud",
    "wof:name":"Alexis Ordonez Sanitaire Service",
    "wof:placetype":"venue"
},
  "geometry": {"coordinates":[6.64168787,46.7595596313],"type":"Point"}
}