{
  "type": "Feature",
  "properties": {
    "iso:country":"CH",
    "sg:address":"Buchenweg 4",
    "sg:city":"M\u00f6rigen",
    "sg:orig_category":"Vereine Damen Vereine Gesang",
    "sg:phone":"+41 32 397 14 87",
    "sg:postcode":"2572",
    "sg:province":"Bern",
    "wof:name":"Frauenchor T\u00e4uffelen",
    "wof:placetype":"venue"
},
  "geometry": {"coordinates":[7.2099847794,47.0813713074],"type":"Point"}
}