{
  "type": "Feature",
  "properties": {
    "iso:country":"CH",
    "sg:address":"Lindengutstrasse 13",
    "sg:city":"Aarburg",
    "sg:orig_category":"Zahnarztpraxen",
    "sg:phone":"+41 62 791 56 52",
    "sg:postcode":"4663",
    "sg:province":"Aargau",
    "wof:name":"Dr. Med. Dent. Stefan R\u00fcegger Zahnarzt",
    "wof:placetype":"venue"
},
  "geometry": {"coordinates":[7.9088320732,47.3176765442],"type":"Point"}
}