{
  "type": "Feature",
  "properties": {
    "iso:country":"CH",
    "sg:address":"Bernstrasse 106",
    "sg:city":"Luzern",
    "sg:orig_category":"Grosshandel mit Geschenkartikeln U Souvenirs Grosshandel mit Lederwaren U Reiseartikeln",
    "sg:phone":"+41 41 240 35 44",
    "sg:postcode":"6003",
    "sg:province":"Luzern",
    "wof:name":"Wintra Luzern, Weiss H.r.",
    "wof:placetype":"venue"
},
  "geometry": {"coordinates":[8.282910347,47.0529098511],"type":"Point"}
}