{
  "type": "Feature",
  "properties": {
    "iso:country":"CH",
    "sg:address":"Freiburgstrasse 159 3008 Bern. Postfach",
    "sg:city":"Bern",
    "sg:orig_category":"Sonstiger spezialisierter Hoch U Tiefbau",
    "sg:phone":"+41 31 381 25 91",
    "sg:postcode":"3005",
    "sg:province":"Bern",
    "wof:name":"Brand Ger\u00fcste. Bauger\u00fcste; Montage, Vermietung U. Handel.",
    "wof:placetype":"venue"
},
  "geometry": {"coordinates":[7.4057378769,46.9428253174],"type":"Point"}
}