{
  "type": "Feature",
  "properties": {
    "iso:country":"CH",
    "sg:address":"Primelweg 32",
    "sg:city":"Luzern",
    "sg:orig_category":"Detailhandel mit Radio U Fernsehger\u00e4ten",
    "sg:phone":"+41 41 360 60 80",
    "sg:postcode":"6005",
    "sg:province":"Luzern",
    "wof:name":"Hermann Portmann Radio-tv-service",
    "wof:placetype":"venue"
},
  "geometry": {"coordinates":[8.3222074509,47.0371627808],"type":"Point"}
}