{
  "type": "Feature",
  "properties": {
    "iso:country":"CH",
    "sg:address":"Hauptstrasse 20",
    "sg:city":"D\u00f6ttingen",
    "sg:orig_category":"P\u00e9dicure",
    "sg:phone":"+41 56 245 76 67",
    "sg:postcode":"5312",
    "sg:province":"Aargau",
    "wof:name":"Eveline V\u00f6geli P\u00e9dicure",
    "wof:placetype":"venue"
},
  "geometry": {"coordinates":[8.2551765442,47.5760612488],"type":"Point"}
}