{
  "type": "Feature",
  "properties": {
    "iso:country":"CH",
    "sg:address":"Rue Schaub 39",
    "sg:city":"Gen\u00e8ve",
    "sg:orig_category":"G\u00fcterbef\u00f6rderung im Strassenverkehr",
    "sg:phone":"+41 22 734 22 94",
    "sg:postcode":"1202",
    "sg:province":"Gen\u00e8ve",
    "wof:name":"M. Schuwey",
    "wof:placetype":"venue"
},
  "geometry": {"coordinates":[6.1314001083,46.2142295837],"type":"Point"}
}