{
  "type": "Feature",
  "properties": {
    "iso:country":"CH",
    "sg:address":"Rue Des Saars 131",
    "sg:city":"Neuch\u00e2tel",
    "sg:orig_category":"Grosshandel mit Wasch U Reinigungsmitteln Reinigungsgewerbe",
    "sg:phone":"+41 79 406 16 70",
    "sg:postcode":"2000",
    "sg:province":"Neuch\u00e2tel",
    "wof:name":"Cleansystem Nettoyages, Mordasini R.",
    "wof:placetype":"venue"
},
  "geometry": {"coordinates":[6.9569201469,47.0024490356],"type":"Point"}
}