{
  "type": "Feature",
  "properties": {
    "iso:country":"CH",
    "sg:address":"Felsenaustrasse 17",
    "sg:city":"Chur",
    "sg:orig_category":"Handel mit Automobilen",
    "sg:phone":"+41 81 284 56 56",
    "sg:postcode":"7000",
    "sg:province":"Graubunden",
    "wof:name":"City Cars Adank H.j.",
    "wof:placetype":"venue"
},
  "geometry": {"coordinates":[9.5159626007,46.8543395996],"type":"Point"}
}