{
  "type": "Feature",
  "properties": {
    "iso:country":"CH",
    "sg:address":"Jupiterstrasse 15",
    "sg:city":"Bern",
    "sg:classifiers":[
        {
            "category":"Restaurant",
            "type":"Food & Drink"
        }
    ],
    "sg:phone":"+41 31 941 12 12",
    "sg:postcode":"3015",
    "sg:province":"Bern",
    "wof:name":"Restaurant Rotihaus",
    "wof:placetype":"venue"
},
  "geometry": {"coordinates":[7.4811987877,46.9392929077],"type":"Point"}
}