{
  "type": "Feature",
  "properties": {
    "iso:country":"CH",
    "sg:address":"Via Giovan Battist Pioda 14 6900 Lugano. Postfach",
    "sg:city":"Lugano",
    "sg:orig_category":"Non-Classified Establishments",
    "sg:postcode":"6900",
    "sg:province":"Ticino",
    "wof:name":"Sanfral Sa",
    "wof:placetype":"venue"
},
  "geometry": {"coordinates":[8.9545717239,46.0077438354],"type":"Point"}
}