{
  "type": "Feature",
  "properties": {
    "iso:country":"CH",
    "sg:address":"Bergstr. 31",
    "sg:city":"Uerkheim",
    "sg:orig_category":"RESTAURANTS: TEA-ROOMS",
    "sg:postcode":"4813",
    "sg:province":"Aargau",
    "wof:name":"Frau M. Duss-habermacher",
    "wof:placetype":"venue"
},
  "geometry": {"coordinates":[8.025223732,47.3049888611],"type":"Point"}
}