{
  "type": "Feature",
  "properties": {
    "iso:country":"CH",
    "sg:address":"Rosengartenweg 3",
    "sg:city":"Oberrieden",
    "sg:orig_category":"Unclassifiable Establishments",
    "sg:phone":"+41 17204477",
    "sg:postcode":"8942",
    "sg:province":"Z\u00fcrich",
    "wof:name":"Cornaz Ag-holding",
    "wof:placetype":"venue"
},
  "geometry": {"coordinates":[8.5764093399,47.2813529968],"type":"Point"}
}