{
  "type": "Feature",
  "properties": {
    "iso:country":"CH",
    "sg:address":"Bennwilerstr. 8",
    "sg:city":"H\u00f6lstein",
    "sg:classifiers":[
        {
            "category":"Shopping",
            "subcategory":"Computers & Home Electronics",
            "type":"Retail Goods"
        }
    ],
    "sg:phone":"+41 61 956 90 50",
    "sg:postcode":"4434",
    "sg:province":"Basel-Landschaft",
    "sg:tags":[
        "household",
        "appliance",
        "telecommunication",
        "audio-visual"
    ],
    "wof:name":"Schweizer Ag Professionelle Videotechnik",
    "wof:placetype":"venue"
},
  "geometry": {"coordinates":[7.770086,47.422989],"type":"Point"}
}