{
  "type": "Feature",
  "properties": {
    "iso:country":"CH",
    "sg:address":"Weinberglistrasse 46a",
    "sg:city":"Luzern",
    "sg:orig_category":"Grosshandel mit Sportartikeln Rechtsberatung",
    "sg:phone":"+41 32 931 43 43",
    "sg:postcode":"6005",
    "sg:province":"Luzern",
    "wof:name":"Try-ski Sa Diffusion-ventes",
    "wof:placetype":"venue"
},
  "geometry": {"coordinates":[6.7494478226,47.0568618774],"type":"Point"}
}