{
  "type": "Feature",
  "properties": {
    "iso:country":"CH",
    "sg:address":"Freilagerstrasse 5 4142 M\u00fcnchenstein. Postfach",
    "sg:city":"Basel",
    "sg:orig_category":"Detailhandel mit M\u00f6beln U Haushaltsgegenst\u00e4nden Grosshandel mit M\u00f6beln, Wohnbedarf, Teppichen U Bode",
    "sg:phone":"+41 22 300 46 11",
    "sg:postcode":"4024",
    "sg:province":"Basel-Stadt",
    "wof:name":"Natacha Morex Asaya Mobilier D'indon\u00e9sie",
    "wof:placetype":"venue"
},
  "geometry": {"coordinates":[6.1412000656,46.1817588806],"type":"Point"}
}