{
  "type": "Feature",
  "properties": {
    "iso:country":"CH",
    "sg:address":"Aux Biolettes",
    "sg:city":"Grolley",
    "sg:orig_category":"Kosmetikinstitute",
    "sg:phone":"+41 26 475 33 50",
    "sg:postcode":"1772",
    "sg:province":"Fribourg",
    "wof:name":"Institut Art & Beaut\u00e9",
    "wof:placetype":"venue"
},
  "geometry": {"coordinates":[7.0650892258,46.8314971924],"type":"Point"}
}