{
  "type": "Feature",
  "properties": {
    "iso:country":"CH",
    "sg:address":"Olgastrasse 8 8001 Z\u00fcrich. Postfach",
    "sg:city":"Z\u00fcrich",
    "sg:orig_category":"Public-Relations-Agenturen Werbeagenturen",
    "sg:phone":"+41 12669080",
    "sg:postcode":"8024",
    "sg:province":"Z\u00fcrich",
    "wof:name":"Marcel Bernet Public Relations",
    "wof:placetype":"venue"
},
  "geometry": {"coordinates":[8.5481958389,47.3676757812],"type":"Point"}
}