{
  "type": "Feature",
  "properties": {
    "iso:country":"CH",
    "sg:address":"Corso S. Gottardo 54a 6830 Chiasso. Postfach",
    "sg:city":"Chiasso",
    "sg:orig_category":"Finanzierungsinstitutionen Unternehmensberatung",
    "sg:phone":"+41 91 690 18 34",
    "sg:postcode":"6830",
    "sg:province":"Ticino",
    "wof:name":"Pro Consult & Finance Sagl Consulenza Ed Intermediazione In Ambito Finanziario Ecc",
    "wof:placetype":"venue"
},
  "geometry": {"coordinates":[9.0283632278,45.8350944519],"type":"Point"}
}