{
  "type": "Feature",
  "properties": {
    "iso:country":"CH",
    "sg:address":"Krambr\u00fccke",
    "sg:city":"Gstaad",
    "sg:orig_category":"Malerei",
    "sg:phone":"+41 33 744 63 57",
    "sg:postcode":"3780",
    "sg:province":"Bern",
    "wof:name":"Andreas Werren Malergesch\u00e4ft",
    "wof:placetype":"venue"
},
  "geometry": {"coordinates":[7.2928872108,46.4696617126],"type":"Point"}
}