{
  "type": "Feature",
  "properties": {
    "iso:country":"CH",
    "sg:address":"Rue De Lausanne 18",
    "sg:city":"Gen\u00e8ve",
    "sg:orig_category":"Detailhandel mit Schuhen",
    "sg:phone":"+41 21 922 53 70",
    "sg:postcode":"1201",
    "sg:province":"Gen\u00e8ve",
    "wof:name":"Karl V\u00f6gele Sa",
    "wof:placetype":"venue"
},
  "geometry": {"coordinates":[5.1808700562,45.8973388672],"type":"Point"}
}