{
  "type": "Feature",
  "properties": {
    "iso:country":"CH",
    "sg:address":"Juraweg 484",
    "sg:city":"Uerkheim",
    "sg:orig_category":"Bauschreinerei Herstellung von Konstruktionsteilen, Fertigbauteilen U Ausbauelementen aus Holz",
    "sg:phone":"+41 19301793",
    "sg:postcode":"4813",
    "sg:province":"Aargau",
    "wof:name":"Schreinerei Bosshard M. Ag",
    "wof:placetype":"venue"
},
  "geometry": {"coordinates":[8.793551,47.332329],"type":"Point"}
}