{
  "type": "Feature",
  "properties": {
    "iso:country":"CH",
    "sg:address":"Via Sorengo 56",
    "sg:city":"Lugano",
    "sg:orig_category":"Detailhandel mit Pelzwaren",
    "sg:phone":"+41 91 966 57 56",
    "sg:postcode":"6900",
    "sg:province":"Ticino",
    "wof:name":"Pellicceria Sage Mary Morandi",
    "wof:placetype":"venue"
},
  "geometry": {"coordinates":[8.9407224655,46.0016441345],"type":"Point"}
}