{
  "type": "Feature",
  "properties": {
    "iso:country":"CH",
    "sg:address":"Rautistrasse 60",
    "sg:city":"Z\u00fcrich",
    "sg:orig_category":"Sonstiger Fachdetailhandel mit Nahrungsmitteln, Getr\u00e4nken U Tabak in Verkaufsr\u00e4umen",
    "sg:postcode":"8048",
    "sg:province":"Z\u00fcrich",
    "wof:name":"Verband Buttergrosshandel, Vbg",
    "wof:placetype":"venue"
},
  "geometry": {"coordinates":[8.4907550812,47.3816604614],"type":"Point"}
}