{
  "type": "Feature",
  "properties": {
    "iso:country":"CH",
    "sg:address":"Weidstrasse 48",
    "sg:city":"Meilen",
    "sg:orig_category":"Mit dem Versicherungsgewerbe verbundene T\u00e4tigkeiten",
    "sg:phone":"+41 13623331",
    "sg:postcode":"8706",
    "sg:province":"Z\u00fcrich",
    "wof:name":"Versico Versicherungsberatung, Condrau Reto",
    "wof:placetype":"venue"
},
  "geometry": {"coordinates":[8.6701574326,47.267780304],"type":"Point"}
}