{
  "type": "Feature",
  "properties": {
    "iso:country":"CH",
    "sg:address":"M\u00fchlegasse 7 4800 Zofingen. Postfach",
    "sg:city":"Zofingen",
    "sg:orig_category":"Gasversorgung",
    "sg:postcode":"4800",
    "sg:province":"Aargau",
    "wof:name":"Union Internationale De L'industrie Du Gaz",
    "wof:placetype":"venue"
},
  "geometry": {"coordinates":[5.1808700562,45.8973388672],"type":"Point"}
}