{
  "type": "Feature",
  "properties": {
    "iso:country":"CH",
    "sg:address":"Neapelstrasse 8",
    "sg:city":"M\u00fcnchenstein",
    "sg:orig_category":"Grosshandel mit elektrischen Haushaltsger\u00e4ten, Radio U Fernsehger\u00e4ten",
    "sg:phone":"+41 61 332 08 00",
    "sg:postcode":"4142",
    "sg:province":"Basel-Landschaft",
    "wof:name":"Mobo-import Ag",
    "wof:placetype":"venue"
},
  "geometry": {"coordinates":[7.6111841202,47.5325088501],"type":"Point"}
}