{
  "type": "Feature",
  "properties": {
    "iso:country":"CH",
    "sg:address":"L\u00e4ngmatt",
    "sg:city":"Eggiwil",
    "sg:orig_category":"Personenbef\u00f6rderung im Linienverkehr zu Land",
    "sg:postcode":"3537",
    "sg:province":"Bern",
    "wof:name":"Skilift Netschb\u00fcel",
    "wof:placetype":"venue"
},
  "geometry": {"coordinates":[7.7921438217,46.8784675598],"type":"Point"}
}