{
  "type": "Feature",
  "properties": {
    "iso:country":"CH",
    "sg:address":"Adelbodenstrasse 10 3714 Frutigen. Postfach",
    "sg:city":"Frutigen",
    "sg:orig_category":"Tierarztpraxis",
    "sg:phone":"+41 33 671 15 60",
    "sg:postcode":"3714",
    "sg:province":"Bern",
    "wof:name":"Dr. Med. Vet. Hans Lauener Tierarzt",
    "wof:placetype":"venue"
},
  "geometry": {"coordinates":[7.6425428391,46.5861167908],"type":"Point"}
}