{
  "type": "Feature",
  "properties": {
    "iso:country":"CH",
    "sg:address":"Limmatquai 4",
    "sg:city":"Z\u00fcrich",
    "sg:classifiers":[
        {
            "category":"Banks & Credit Unions",
            "subcategory":"Bank",
            "type":"Services"
        }
    ],
    "sg:phone":"+41 12679300",
    "sg:postcode":"8001",
    "sg:province":"Z\u00fcrich",
    "wof:name":"Banque Nationale, De Paris (suisse) Sa",
    "wof:placetype":"venue"
},
  "geometry": {"coordinates":[8.544896,47.367989],"type":"Point"}
}