{
  "type": "Feature",
  "properties": {
    "iso:country":"CH",
    "sg:address":"Rue De La Grenade 39",
    "sg:city":"Moudon",
    "sg:orig_category":"Arztpraxen",
    "sg:phone":"+41 21 905 12 05",
    "sg:postcode":"1510",
    "sg:province":"Vaud",
    "wof:name":"Dr M\u00e9d. Charles-k. Briza M\u00e9decin G\u00e9n\u00e9raliste",
    "wof:placetype":"venue"
},
  "geometry": {"coordinates":[6.79965,46.670025],"type":"Point"}
}