{
  "type": "Feature",
  "properties": {
    "iso:country":"CH",
    "sg:address":"Palmenweg 9",
    "sg:city":"T\u00e4gerwilen",
    "sg:orig_category":"Interessenvertretungen",
    "sg:phone":"+41 71 669 16 04",
    "sg:postcode":"8274",
    "sg:province":"Thurgau",
    "wof:name":"Altersrentenfonds Und B\u00fcrgerstiftung Der B\u00fcrgergemeinde T\u00e4gerwilen",
    "wof:placetype":"venue"
},
  "geometry": {"coordinates":[9.1288061142,47.6578865051],"type":"Point"}
}