{
  "type": "Feature",
  "properties": {
    "iso:country":"CH",
    "sg:address":"Holeestrasse 78",
    "sg:city":"Basel",
    "sg:classifiers":[
        {
            "category":"Government",
            "subcategory":"Post Office",
            "type":"Public Place"
        }
    ],
    "sg:phone":"+41 61 302 89 07",
    "sg:postcode":"4054",
    "sg:province":"Basel-Stadt",
    "sg:tags":[
        "caf\u00e9s",
        "tea-rooms"
    ],
    "wof:name":"Caf\u00e9 Carussell",
    "wof:placetype":"venue"
},
  "geometry": {"coordinates":[7.5703377724,47.5454330444],"type":"Point"}
}