{
  "type": "Feature",
  "properties": {
    "iso:country":"CH",
    "sg:address":"Via Cantonale 3",
    "sg:city":"Lugano",
    "sg:orig_category":"Public-Relations-Agenturen",
    "sg:phone":"+41 91 912 33 20",
    "sg:postcode":"6900",
    "sg:province":"Ticino",
    "wof:name":"Megroup Sa",
    "wof:placetype":"venue"
},
  "geometry": {"coordinates":[8.9498996735,46.0068092346],"type":"Point"}
}