{
  "type": "Feature",
  "properties": {
    "iso:country":"CH",
    "sg:address":"7175",
    "sg:city":"Sumvitg",
    "sg:orig_category":"Sportvereine Sch\u00fctzen",
    "sg:phone":"+41 81 943 14 22",
    "sg:postcode":"7175",
    "sg:province":"Graubunden",
    "wof:name":"Societad De Tir",
    "wof:placetype":"venue"
},
  "geometry": {"coordinates":[8.935792923,46.7273597717],"type":"Point"}
}