{
  "type": "Feature",
  "properties": {
    "iso:country":"CH",
    "sg:address":"Gewerbestrasse 10",
    "sg:city":"Sissach",
    "sg:orig_category":"Herstellung von Radio U Fernsehger\u00e4ten sowie phono U videotechnischen Ger\u00e4ten",
    "sg:postcode":"4450",
    "sg:province":"Basel-Landschaft",
    "wof:name":"Teletrust (schweiz)",
    "wof:placetype":"venue"
},
  "geometry": {"coordinates":[7.8033361435,47.4669570923],"type":"Point"}
}