{
  "type": "Feature",
  "properties": {
    "iso:country":"CH",
    "sg:address":"Sonnenbergweg 16",
    "sg:city":"Adliswil",
    "sg:orig_category":"Sportvereine Sch\u00fctzen",
    "sg:phone":"+41 52 383 12 52",
    "sg:postcode":"8134",
    "sg:province":"Z\u00fcrich",
    "wof:name":"Gemeindeschiessverein Zell",
    "wof:placetype":"venue"
},
  "geometry": {"coordinates":[8.8035049438,47.442817688],"type":"Point"}
}