{
  "type": "Feature",
  "properties": {
    "iso:country":"CH",
    "sg:address":"Grossmatt",
    "sg:city":"Ennetb\u00fcrgen",
    "sg:orig_category":"G\u00fcterbef\u00f6rderung im Strassenverkehr",
    "sg:phone":"+41 71 633 24 30",
    "sg:postcode":"6373",
    "sg:province":"Nidwalden",
    "wof:name":"Werner Baumann Transporte + Entsorgung",
    "wof:placetype":"venue"
},
  "geometry": {"coordinates":[9.1575670242,47.5480575562],"type":"Point"}
}