{
  "type": "Feature",
  "properties": {
    "iso:country":"CH",
    "sg:address":"Via Giorgio Bernasconi 20 6850 Mendrisio Casella Postale",
    "sg:city":"Mendrisio",
    "sg:orig_category":"Grosshandel mit Maschinen U Ausr\u00fcstungen Herstellung von Bergwerks U Baumaschinen",
    "sg:phone":"+41 91 646 66 35",
    "sg:postcode":"6850",
    "sg:province":"Ticino",
    "wof:name":"Imefco Sa",
    "wof:placetype":"venue"
},
  "geometry": {"coordinates":[8.9880838394,45.870098114],"type":"Point"}
}