{
  "type": "Feature",
  "properties": {
    "iso:country":"CH",
    "sg:address":"Orpundstrasse 24a",
    "sg:city":"Biel/bienne",
    "sg:orig_category":"Non-Classified Establishments",
    "sg:postcode":"2504",
    "sg:province":"Bern",
    "wof:name":"A.m.t. Akduman Multitalente Gmbh",
    "wof:placetype":"venue"
},
  "geometry": {"coordinates":[7.2741827965,47.1443595886],"type":"Point"}
}