{
  "type": "Feature",
  "properties": {
    "iso:country":"CH",
    "sg:address":"1064",
    "sg:city":"St-cierges",
    "sg:orig_category":"Haltung von Schweinen",
    "sg:phone":"+41 21 905 33 84",
    "sg:postcode":"1064",
    "wof:name":"Fran\u00e7ois J\u00e4ggi Porcherie",
    "wof:placetype":"venue"
},
  "geometry": {"coordinates":[6.7349619865,46.6901321411],"type":"Point"}
}