{
  "type": "Feature",
  "properties": {
    "iso:country":"CH",
    "sg:address":"Hofstrasse 7 4912 Aarwangen. Postfach",
    "sg:city":"Aarwangen",
    "sg:orig_category":"Mechanische Werkst\u00e4tten",
    "sg:phone":"+41 62 922 47 50",
    "sg:postcode":"4912",
    "sg:province":"Bern",
    "wof:name":"Paul Sch\u00fctz Pr\u00e4zisionsmechanik",
    "wof:placetype":"venue"
},
  "geometry": {"coordinates":[7.7859787941,47.2382240295],"type":"Point"}
}