{
  "type": "Feature",
  "properties": {
    "iso:country":"CH",
    "sg:address":"Austrasse 3",
    "sg:city":"Niederb\u00fcren",
    "sg:orig_category":"Architektur U Ingenieurb\u00fcros",
    "sg:phone":"+41 71 422 48 38",
    "sg:postcode":"9246",
    "sg:province":"St. Gallen",
    "wof:name":"Ingenieurb\u00fcro Waldburger P.",
    "wof:placetype":"venue"
},
  "geometry": {"coordinates":[9.203957,47.464264],"type":"Point"}
}