{
  "type": "Feature",
  "properties": {
    "iso:country":"CH",
    "sg:address":"1693",
    "sg:city":"Orsonnens",
    "sg:orig_category":"Institutionen f\u00fcr Suchtkranke",
    "sg:phone":"+41 26 653 17 53",
    "sg:postcode":"1693",
    "wof:name":"Le Radeau Centre D'accueil",
    "wof:placetype":"venue"
},
  "geometry": {"coordinates":[6.9952511787,46.7164039612],"type":"Point"}
}