{
  "type": "Feature",
  "properties": {
    "iso:country":"CH",
    "sg:address":"Sternenplatz 7",
    "sg:city":"Luzern",
    "sg:classifiers":[
        {
            "category":"Travel",
            "subcategory":"Hotels & Motels",
            "type":"Entertainment"
        }
    ],
    "sg:phone":"+41 41 410 55 50",
    "sg:postcode":"6004",
    "sg:province":"Luzern",
    "sg:tags":[
        "hotels",
        "mit",
        "restaurant"
    ],
    "wof:name":"Ruda Gmbh",
    "wof:placetype":"venue"
},
  "geometry": {"coordinates":[8.3072118759,47.053024292],"type":"Point"}
}