{
  "type": "Feature",
  "properties": {
    "iso:country":"CH",
    "sg:address":"Huobmattstrasse 12",
    "sg:city":"Meggen",
    "sg:orig_category":"Forschung U Entwicklung im Bereich der Naturwissenschaften",
    "sg:phone":"+41 41 378 00 70",
    "sg:postcode":"6045",
    "sg:province":"Luzern",
    "wof:name":"Rc Consulting, Dr. Med. M.p.h. R. Cranovsky",
    "wof:placetype":"venue"
},
  "geometry": {"coordinates":[8.3802051544,47.0505218506],"type":"Point"}
}