{
  "type": "Feature",
  "properties": {
    "iso:country":"CH",
    "sg:address":"Letziwiesstrasse 2",
    "sg:city":"L\u00fctisburg",
    "sg:orig_category":"Herstellung von Werkzeugen",
    "sg:phone":"+41 71 931 37 60",
    "sg:postcode":"9604",
    "sg:province":"St. Gallen",
    "wof:name":"Hohl Arnold Ag",
    "wof:placetype":"venue"
},
  "geometry": {"coordinates":[9.0819721222,47.3942832947],"type":"Point"}
}