{
  "type": "Feature",
  "properties": {
    "iso:country":"CH",
    "sg:address":"Dorfstrasse 13",
    "sg:city":"Oberentfelden",
    "sg:orig_category":"Detailhandel mit elektrischen Haushalts-,Radio U Fernsehger\u00e4ten sowie Musikinstrumenten",
    "sg:postcode":"5036",
    "sg:province":"Aargau",
    "wof:name":"Rihusa Service Gmbh",
    "wof:placetype":"venue"
},
  "geometry": {"coordinates":[8.046746254,47.355758667],"type":"Point"}
}