{
  "type": "Feature",
  "properties": {
    "iso:country":"CH",
    "sg:address":"R\u00fctistrasse 12",
    "sg:city":"Bonstetten",
    "sg:orig_category":"Bauschreinerei Grosshandel mit Holz U Baustoffen",
    "sg:phone":"+41 17001428",
    "sg:postcode":"8906",
    "sg:province":"Z\u00fcrich",
    "wof:name":"Regaplan Raumsysteme Gallmann Ren\u00e9",
    "wof:placetype":"venue"
},
  "geometry": {"coordinates":[8.473811,47.315754],"type":"Point"}
}