{
  "type": "Feature",
  "properties": {
    "iso:country":"CH",
    "sg:address":"Dorfstrasse 22",
    "sg:city":"Leukerbad",
    "sg:classifiers":[
        {
            "category":"Travel",
            "subcategory":"Hotels & Motels",
            "type":"Entertainment"
        }
    ],
    "sg:phone":"+41 27 470 11 06",
    "sg:postcode":"3954",
    "sg:province":"Valais",
    "sg:tags":[
        "hotels",
        "mit",
        "restaurant"
    ],
    "wof:name":"Hotel Gemmi",
    "wof:placetype":"venue"
},
  "geometry": {"coordinates":[7.6293878555,46.3802642822],"type":"Point"}
}