{
  "type": "Feature",
  "properties": {
    "iso:country":"CH",
    "sg:address":"8816 Hirzel. Postfach",
    "sg:city":"Hirzel",
    "sg:orig_category":"Sportvereine Ballsport Tennis",
    "sg:phone":"+41 17299929",
    "sg:postcode":"8816",
    "sg:province":"Z\u00fcrich",
    "wof:name":"Tennisclub Morgenthal",
    "wof:placetype":"venue"
},
  "geometry": {"coordinates":[8.6067199707,47.2151374817],"type":"Point"}
}