{
  "type": "Feature",
  "properties": {
    "iso:country":"CH",
    "sg:address":"Brunaustrasse 16 8002 Z\u00fcrich. Postfach",
    "sg:city":"Z\u00fcrich",
    "sg:orig_category":"Interessenvertretungen",
    "sg:postcode":"8002",
    "sg:province":"Z\u00fcrich",
    "wof:name":"Stiftung F\u00fcr Hochbegabte Kinder Intellektuelle Und Menschliche F\u00f6rderung Von \u00fcberdurchschnittlich Begabten Kindern",
    "wof:placetype":"venue"
},
  "geometry": {"coordinates":[8.5310678482,47.355682373],"type":"Point"}
}