{
  "type": "Feature",
  "properties": {
    "iso:country":"CH",
    "sg:address":"Av. Ritz 13",
    "sg:city":"Sion",
    "sg:orig_category":"RESTAURANTS: TEA-ROOMS",
    "sg:postcode":"1950",
    "sg:province":"Valais",
    "wof:name":"Bula Josiane",
    "wof:placetype":"venue"
},
  "geometry": {"coordinates":[7.3581748009,46.2352714539],"type":"Point"}
}