{
  "type": "Feature",
  "properties": {
    "iso:country":"CH",
    "sg:address":"Chanet Rue Du 36",
    "sg:city":"B\u00f4le",
    "sg:orig_category":"Herstellung von Maschinen f\u00fcr die Nahrungsmittel, Getr\u00e4nkeherstellung U die Tabakverarbeitung",
    "sg:postcode":"2014",
    "sg:province":"Neuch\u00e2tel",
    "wof:name":"Boulangerie Raffin S\u00e0rl",
    "wof:placetype":"venue"
},
  "geometry": {"coordinates":[6.9953799248,46.2966117859],"type":"Point"}
}