{
  "type": "Feature",
  "properties": {
    "addr:full":"Burgstrasse 28 Rickenbach-attikon Z\u00fcrich 8544",
    "addr:housenumber":"28",
    "addr:postcode":"8544",
    "addr:street":"Burgstrasse;Zuerich",
    "iso:country":"CH",
    "sg:address":"Burgstrasse 28",
    "sg:city":"Rickenbach-attikon",
    "sg:orig_category":"Allgemeiner Hoch U Tiefbau",
    "sg:phone":"+41 52 222 72 35",
    "sg:postcode":"8544",
    "sg:province":"Z\u00fcrich",
    "wof:name":"Trecek Cad",
    "wof:placetype":"venue"
},
  "geometry": {"coordinates":[8.797455,47.535873],"type":"Point"}
}