{
  "type": "Feature",
  "properties": {
    "iso:country":"CH",
    "sg:address":"Hauptstrasse 72",
    "sg:city":"Triengen",
    "sg:classifiers":[
        {
            "category":"Government",
            "subcategory":"Post Office",
            "type":"Public Place"
        }
    ],
    "sg:phone":"+41 41 933 17 37",
    "sg:postcode":"6234",
    "sg:province":"Luzern",
    "sg:tags":[
        "caf\u00e9s",
        "tea-rooms"
    ],
    "wof:name":"Caf\u00e9 Pic",
    "wof:placetype":"venue"
},
  "geometry": {"coordinates":[8.0757846832,47.2360610962],"type":"Point"}
}