{
  "type": "Feature",
  "properties": {
    "iso:country":"CH",
    "sg:address":"Sieberstrasse 16",
    "sg:city":"Z\u00fcrich",
    "sg:orig_category":"W\u00e4scherei U chemische Reinigung",
    "sg:phone":"+41 32 373 15 45",
    "sg:postcode":"8055",
    "sg:province":"Z\u00fcrich",
    "wof:name":"Lauda Sa Chem.reinigung & W\u00e4scherei",
    "wof:placetype":"venue"
},
  "geometry": {"coordinates":[7.2957959175,47.1164512634],"type":"Point"}
}