{
  "type": "Feature",
  "properties": {
    "iso:country":"CH",
    "sg:address":"Alfred-schindlerstrasse 8 6030 Ebikon. Postfach 108",
    "sg:city":"Ebikon",
    "sg:orig_category":"Verlegen von Fliesen U Platten",
    "sg:phone":"+41 41 440 33 38",
    "sg:postcode":"6031",
    "sg:province":"Luzern",
    "wof:name":"Roland Eberhard Keramische Wand-& Bodenbel\u00e4ge",
    "wof:placetype":"venue"
},
  "geometry": {"coordinates":[8.3524112701,47.0865859985],"type":"Point"}
}