{
  "type": "Feature",
  "properties": {
    "iso:country":"CH",
    "sg:address":"Hirondelles Chemin Des 1",
    "sg:city":"Orbe",
    "sg:orig_category":"Vermietung U Verpachtung von eigenen Immobilien",
    "sg:postcode":"1350",
    "sg:province":"Vaud",
    "wof:name":"R\u00f6mer Immobilien",
    "wof:placetype":"venue"
},
  "geometry": {"coordinates":[8.5350914001,47.2909317017],"type":"Point"}
}