{
  "type": "Feature",
  "properties": {
    "iso:country":"CH",
    "sg:address":"Bettlachstrasse 275",
    "sg:city":"Grenchen",
    "sg:orig_category":"Herstellung von Uhren",
    "sg:postcode":"2540",
    "sg:province":"Solothurn",
    "wof:name":"Meier W. Gmbh",
    "wof:placetype":"venue"
},
  "geometry": {"coordinates":[7.4117541313,47.1977615356],"type":"Point"}
}