{
  "type": "Feature",
  "properties": {
    "iso:country":"CH",
    "sg:address":"Bellikerstrasse 9 8965 Berikon. Postfach",
    "sg:city":"Berikon",
    "sg:orig_category":"Softwareentwicklung U beratung",
    "sg:phone":"+41 56 641 11 36",
    "sg:postcode":"8965",
    "sg:province":"Aargau",
    "wof:name":"Gm Global Media Gmbh Informatikdienstl. Usw",
    "wof:placetype":"venue"
},
  "geometry": {"coordinates":[8.3669910431,47.363079071],"type":"Point"}
}