{
  "type": "Feature",
  "properties": {
    "iso:country":"CH",
    "sg:address":"Rue Du Lac 46 1815 Clarens Case Postale 18",
    "sg:city":"Clarens",
    "sg:orig_category":"Unternehmensberatung Wirtschaftspr\u00fcfung, Steuerberatung U Treuhand",
    "sg:phone":"+41 79 231 42 32",
    "sg:postcode":"1815",
    "sg:province":"Vaud",
    "wof:name":"Gestion-service Ravessoud S\u00e0rl",
    "wof:placetype":"venue"
},
  "geometry": {"coordinates":[6.8975200653,46.4404907227],"type":"Point"}
}