{
  "type": "Feature",
  "properties": {
    "iso:country":"CH",
    "sg:address":"Dorfstrasse",
    "sg:city":"Saanen",
    "sg:orig_category":"Detailhandel mit Fleisch U Fleischwaren",
    "sg:phone":"+41 33 744 32 14",
    "sg:postcode":"3792",
    "sg:province":"Bern",
    "wof:name":"Nydegger O., Metzgerei",
    "wof:placetype":"venue"
},
  "geometry": {"coordinates":[7.2619848251,46.4898033142],"type":"Point"}
}