{
  "type": "Feature",
  "properties": {
    "iso:country":"CH",
    "sg:address":"Br\u00fcnigstrasse 48 6078 Lungern. Postfach 148",
    "sg:city":"Lungern",
    "sg:orig_category":"Detailhandel mit Geschenkartikeln U Souvenirs",
    "sg:phone":"+41 41 678 01 13",
    "sg:postcode":"6078",
    "sg:province":"Obwalden",
    "wof:name":"Anita Traub & Rosmarie Gasser Boutique Zum Bunten Ballon",
    "wof:placetype":"venue"
},
  "geometry": {"coordinates":[8.159822464,46.7869529724],"type":"Point"}
}