{
  "type": "Feature",
  "properties": {
    "iso:country":"CH",
    "sg:address":"Dubematt 1",
    "sg:city":"Rain",
    "sg:orig_category":"Sportvereine Velo Rad-& Motorfahrer-Bund SRB",
    "sg:phone":"+41 41 458 15 73",
    "sg:postcode":"6026",
    "sg:province":"Luzern",
    "wof:name":"Rad & Moto Sportv.edelw.rain",
    "wof:placetype":"venue"
},
  "geometry": {"coordinates":[8.2449064255,47.1252059937],"type":"Point"}
}