{
  "type": "Feature",
  "properties": {
    "iso:country":"CH",
    "sg:address":"Hauptstrasse 48",
    "sg:city":"B\u00e4rschwil",
    "sg:orig_category":"RESTAURANTS: TEA-ROOMS",
    "sg:postcode":"4252",
    "sg:province":"Solothurn",
    "wof:name":"Gastbar Gmbh",
    "wof:placetype":"venue"
},
  "geometry": {"coordinates":[7.473596096,47.3813285828],"type":"Point"}
}