{
  "type": "Feature",
  "properties": {
    "iso:country":"CH",
    "sg:address":"6354",
    "sg:city":"Vitznau",
    "sg:orig_category":"Sportvereine Turnen",
    "sg:phone":"+41 41 390 28 84",
    "sg:postcode":"6354",
    "sg:province":"Luzern",
    "wof:name":"Turnverein Vitznau",
    "wof:placetype":"venue"
},
  "geometry": {"coordinates":[8.4833097458,47.0103416443],"type":"Point"}
}