{
  "type": "Feature",
  "properties": {
    "iso:country":"CH",
    "sg:address":"6747",
    "sg:city":"Chironico",
    "sg:orig_category":"RESTAURANTS: TEA-ROOMS",
    "sg:phone":"+41 91 865 16 26",
    "sg:postcode":"6747",
    "sg:province":"Ticino",
    "wof:name":"Merlo Luca E Elvira",
    "wof:placetype":"venue"
},
  "geometry": {"coordinates":[8.8444948196,46.4236946106],"type":"Point"}
}