{
  "type": "Feature",
  "properties": {
    "iso:country":"CH",
    "sg:address":"Chemin De La Scierie 3 1860 Aigle. Postfach",
    "sg:city":"Aigle",
    "sg:orig_category":"Grosshandel mit B\u00fcromaschinen Grosshandel mit Datenverarbeitungsger\u00e4ten",
    "sg:phone":"+41 71 385 13 15",
    "sg:postcode":"1860",
    "sg:province":"Vaud",
    "wof:name":"Bytec Bodry Technology Gmbh Tettnang (d), Zweigniederlassung Gossau Sg",
    "wof:placetype":"venue"
},
  "geometry": {"coordinates":[9.2675943375,47.4183921814],"type":"Point"}
}