{
  "type": "Feature",
  "properties": {
    "iso:country":"CH",
    "sg:address":"Mitteldorf 1",
    "sg:city":"Kaisten",
    "sg:orig_category":"Unclassifiable Establishments",
    "sg:phone":"+41 62 874 01 63",
    "sg:postcode":"5082",
    "sg:province":"Aargau",
    "wof:name":"Erhard + Lenzin Architekten Ts Gmbh",
    "wof:placetype":"venue"
},
  "geometry": {"coordinates":[8.0452737808,47.5391845703],"type":"Point"}
}