{
  "type": "Feature",
  "properties": {
    "iso:country":"CH",
    "sg:address":"Viale Franscini 1",
    "sg:city":"Lugano",
    "sg:orig_category":"Wirtschaftspr\u00fcfung, Steuerberatung U Treuhand",
    "sg:phone":"+41 81 410 60 00",
    "sg:postcode":"6900",
    "sg:province":"Ticino",
    "wof:name":"Tremont-treuhand Ag",
    "wof:placetype":"venue"
},
  "geometry": {"coordinates":[9.8203525543,46.7928695679],"type":"Point"}
}