{
  "type": "Feature",
  "properties": {
    "iso:country":"CH",
    "sg:address":"Soubeyran Rue 12-14 1203 Gen\u00e8ve. Postfach",
    "sg:city":"Gen\u00e8ve",
    "sg:classifiers":[
        {
            "category":"Travel",
            "subcategory":"Hotels & Motels",
            "type":"Entertainment"
        }
    ],
    "sg:postcode":"1203",
    "sg:province":"Gen\u00e8ve",
    "sg:tags":[
        "hotels",
        "mit",
        "restaurant"
    ],
    "wof:name":"Jos\u00e9 Barreiro",
    "wof:placetype":"venue"
},
  "geometry": {"coordinates":[6.1233491898,46.2126312256],"type":"Point"}
}