{
  "type": "Feature",
  "properties": {
    "iso:country":"CH",
    "sg:address":"Rue Mauborget 6",
    "sg:city":"Lausanne",
    "sg:orig_category":"K\u00fcnstlerische Schulen",
    "sg:phone":"+41 21 312 93 75",
    "sg:postcode":"1003",
    "sg:province":"Vaud",
    "wof:name":"Ecole Modes & Style",
    "wof:placetype":"venue"
},
  "geometry": {"coordinates":[6.6290831566,46.5227775574],"type":"Point"}
}