{
  "type": "Feature",
  "properties": {
    "iso:country":"CH",
    "sg:address":"Rue Du Rh\u00f4ne 84",
    "sg:city":"Gen\u00e8ve",
    "sg:classifiers":[
        {
            "category":"Banks & Credit Unions",
            "subcategory":"Financial Services",
            "type":"Services"
        }
    ],
    "sg:phone":"+41 22 310 90 66",
    "sg:postcode":"1204",
    "sg:province":"Gen\u00e8ve",
    "sg:tags":[
        "banking",
        "finance",
        "insurance"
    ],
    "wof:name":"Unifinter Sa",
    "wof:placetype":"venue"
},
  "geometry": {"coordinates":[6.149868,46.203613],"type":"Point"}
}