{
  "type": "Feature",
  "properties": {
    "iso:country":"CH",
    "sg:address":"Faucigny Rue P.-a.-de- 5",
    "sg:city":"Fribourg",
    "sg:orig_category":"Reiseb\u00fcros U Reiseveranstalter",
    "sg:phone":"+41 19314000",
    "sg:postcode":"1700",
    "sg:province":"Fribourg",
    "wof:name":"Prs Ag",
    "wof:placetype":"venue"
},
  "geometry": {"coordinates":[8.7979202271,47.3224182129],"type":"Point"}
}