{
  "type": "Feature",
  "properties": {
    "iso:country":"CH",
    "sg:address":"Grenzsteinweg 3 5745 Safenwil. Postfach",
    "sg:city":"Safenwil",
    "sg:orig_category":"Grosshandel mit sonstigen Gebrauchs U Verbrauchsg\u00fctern",
    "sg:postcode":"5745",
    "sg:province":"Aargau",
    "wof:name":"Meichtry Rainer Promotions",
    "wof:placetype":"venue"
},
  "geometry": {"coordinates":[7.9785032272,47.3250045776],"type":"Point"}
}