{
  "type": "Feature",
  "properties": {
    "iso:country":"CH",
    "sg:address":"Hegibachstrasse 104 8032 Z\u00fcrich",
    "sg:city":"Zust",
    "sg:orig_category":"Fachdetailhandel in Verkaufsr\u00e4umen",
    "sg:phone":"+41 41 871 15 15",
    "sg:postcode":"32",
    "wof:name":"Th\u00fcrig Optik",
    "wof:placetype":"venue"
},
  "geometry": {"coordinates":[8.6508302689,46.8718147278],"type":"Point"}
}