{
  "type": "Feature",
  "properties": {
    "iso:country":"CH",
    "sg:address":"Bahnhofstrasse 68",
    "sg:city":"Berikon",
    "sg:orig_category":"Sonstige mit der Informatik verbundene T\u00e4tigkeiten",
    "sg:postcode":"8965",
    "sg:province":"Aargau",
    "wof:name":"Beor L. H\u00fcgli Edv Beratung & Organisation",
    "wof:placetype":"venue"
},
  "geometry": {"coordinates":[8.3704118729,47.3515548706],"type":"Point"}
}