{
  "type": "Feature",
  "properties": {
    "iso:country":"CH",
    "sg:address":"D\u00f6ltschiweg 39 8055 Z\u00fcrich. Postfach",
    "sg:city":"Z\u00fcrich",
    "sg:orig_category":"Institutionen des Sozialwesens ohne Beherbergung",
    "sg:phone":"+41 14541717",
    "sg:postcode":"8055",
    "sg:province":"Z\u00fcrich",
    "wof:name":"Swisscontact, Schweizerische Stiftung F\u00fcr Technische Entwicklungszusammenarbeit",
    "wof:placetype":"venue"
},
  "geometry": {"coordinates":[8.508231163,47.3672828674],"type":"Point"}
}