{
  "type": "Feature",
  "properties": {
    "iso:country":"CH",
    "sg:address":"Route De La T\u00e9l\u00e9cabine 4",
    "sg:city":"Haute-nendaz",
    "sg:orig_category":"Nationale Postdienste",
    "sg:phone":"+41 27 288 21 92",
    "sg:postcode":"1997",
    "sg:province":"Valais",
    "wof:name":"La Poste Suisse",
    "wof:placetype":"venue"
},
  "geometry": {"coordinates":[7.2953381538,46.1824874878],"type":"Point"}
}