{
  "type": "Feature",
  "properties": {
    "iso:country":"CH",
    "sg:address":"D\u00f6rflistrasse 69",
    "sg:city":"Z\u00fcrich",
    "sg:orig_category":"Geb\u00e4ude, Wohnungsreinigung",
    "sg:phone":"+41 13124920",
    "sg:postcode":"8050",
    "sg:province":"Z\u00fcrich",
    "wof:name":"A Bis Z Geb\u00e4udereinigungsgesch\u00e4ft, Zehnder F.a. Reinigung Von Geb\u00e4uden Und R\u00e4umlichkeiten.",
    "wof:placetype":"venue"
},
  "geometry": {"coordinates":[8.550620079,47.4077110291],"type":"Point"}
}