{
  "type": "Feature",
  "properties": {
    "addr:full":"Place Chauderon 4 Lausanne Vaud 1003",
    "addr:housenumber":"4",
    "addr:postcode":"1003",
    "addr:street":"Place Chauderon",
    "iso:country":"CH",
    "sg:address":"Place Chauderon 4",
    "sg:city":"Lausanne",
    "sg:orig_category":"Arztpraxen",
    "sg:phone":"+41 21 213 77 77",
    "sg:postcode":"1003",
    "sg:province":"Vaud",
    "wof:name":"Dr M\u00e9d. Nicolas Kocsis M\u00e9decin Sp\u00e9cialiste Fmh",
    "wof:placetype":"venue"
},
  "geometry": {"coordinates":[6.627135,46.523354],"type":"Point"}
}