{
  "type": "Feature",
  "properties": {
    "iso:country":"CH",
    "sg:address":"Feldeggstrasse 85",
    "sg:city":"Z\u00fcrich",
    "sg:orig_category":"Unclassifiable Establishments",
    "sg:phone":"+41 13879920",
    "sg:postcode":"8008",
    "sg:province":"Z\u00fcrich",
    "wof:name":"The Body Clinic Ag",
    "wof:placetype":"venue"
},
  "geometry": {"coordinates":[8.554476738,47.3623580933],"type":"Point"}
}