{
  "type": "Feature",
  "properties": {
    "iso:country":"CH",
    "sg:address":"Kirchweg 4",
    "sg:city":"Worb",
    "sg:classifiers":[
        {
            "category":"Home & Garden",
            "subcategory":"Home Furnishings",
            "type":"Retail Goods"
        }
    ],
    "sg:phone":"+41 31 839 05 55",
    "sg:postcode":"3076",
    "sg:province":"Bern",
    "sg:tags":[
        "covering",
        "furniture"
    ],
    "wof:name":"M\u00f6belfabrik Worb E. Schwaller Ag",
    "wof:placetype":"venue"
},
  "geometry": {"coordinates":[7.562224865,46.929309845],"type":"Point"}
}