{
  "type": "Feature",
  "properties": {
    "iso:country":"CH",
    "sg:address":"7545",
    "sg:city":"Guarda",
    "sg:classifiers":[
        {
            "category":"Education",
            "subcategory":"Library",
            "type":"Public Place"
        }
    ],
    "sg:phone":"+41 52 378 24 87",
    "sg:postcode":"7545",
    "sg:province":"Graubunden",
    "sg:tags":[
        "u",
        "bibliotheken",
        "archive"
    ],
    "wof:name":"Gemeindebibliothek",
    "wof:placetype":"venue"
},
  "geometry": {"coordinates":[10.15055,46.775314],"type":"Point"}
}