{
  "type": "Feature",
  "properties": {
    "iso:country":"CH",
    "sg:address":"Hauptstrasse 24",
    "sg:city":"Gerlafingen",
    "sg:orig_category":"Detailhandel mit Waren verschiedener Art, Hauptrichtung Nahrungsmittel Grosshandel mit Nahrungsmitte",
    "sg:phone":"+41 32 675 64 94",
    "sg:postcode":"4563",
    "sg:province":"Solothurn",
    "wof:name":"Badertscher-holzer R., Kolonialwaren",
    "wof:placetype":"venue"
},
  "geometry": {"coordinates":[7.5699858665,47.1709213257],"type":"Point"}
}