{
  "type": "Feature",
  "properties": {
    "addr:full":"Dorfstrasse 17 Kaiseraugst Aargau 4303",
    "addr:housenumber":"17",
    "addr:postcode":"4303",
    "addr:street":"Dorfstrasse",
    "iso:country":"CH",
    "sg:address":"Dorfstrasse 17",
    "sg:city":"Kaiseraugst",
    "sg:orig_category":"Bau\u00e4mter",
    "sg:phone":"+41 55 442 32 00",
    "sg:postcode":"4303",
    "sg:province":"Aargau",
    "wof:name":"Bauverwaltung Der Gemeinde Lachen",
    "wof:placetype":"venue"
},
  "geometry": {"coordinates":[8.850825,47.192448],"type":"Point"}
}