{
  "type": "Feature",
  "properties": {
    "iso:country":"CH",
    "sg:address":"Industriestrasse 39 5314 Kleind\u00f6ttingen. Postfach 99",
    "sg:city":"Kleind\u00f6ttingen",
    "sg:orig_category":"Herstellung von Metallerzeugnissen ohne Maschinenbau Herstellung von Rohren",
    "sg:phone":"+41 56 268 78 78",
    "sg:postcode":"5314",
    "sg:province":"Aargau",
    "wof:name":"Brugg Rohrsystem Ag, B\u00f6ttstein",
    "wof:placetype":"venue"
},
  "geometry": {"coordinates":[8.237695694,47.575969696],"type":"Point"}
}