{
  "type": "Feature",
  "properties": {
    "iso:country":"CH",
    "sg:address":"Arbonerstrasse 61c",
    "sg:city":"Amriswil",
    "sg:orig_category":"Advokaturb\u00fcros",
    "sg:phone":"+41 71 411 93 93",
    "sg:postcode":"8580",
    "sg:province":"Thurgau",
    "wof:name":"Dr.lukas Br\u00fchwiler Advokaturb\u00fcro",
    "wof:placetype":"venue"
},
  "geometry": {"coordinates":[9.30631,47.543789],"type":"Point"}
}