{
  "type": "Feature",
  "properties": {
    "iso:country":"CH",
    "sg:address":"Route De Suisse 11",
    "sg:city":"Versoix",
    "sg:orig_category":"Handel mit Motorr\u00e4dern, Teilen U Zubeh\u00f6r Instandhaltung U Reparatur von Motorr\u00e4dern",
    "sg:phone":"+41 22 755 39 51",
    "sg:postcode":"1290",
    "sg:province":"Gen\u00e8ve",
    "wof:name":"Diego Conde Crazy Bike",
    "wof:placetype":"venue"
},
  "geometry": {"coordinates":[6.1687088013,46.2751579285],"type":"Point"}
}