{
  "type": "Feature",
  "properties": {
    "iso:country":"CH",
    "sg:address":"Einkaufszentrum Glatt",
    "sg:city":"Glattzentrum",
    "sg:classifiers":[
        {
            "category":"Professional",
            "subcategory":"Employment Agencies",
            "type":"Services"
        }
    ],
    "sg:phone":"+41 32 725 13 16",
    "sg:postcode":"8301",
    "sg:province":"Z\u00fcrich",
    "sg:tags":[
        "personal",
        "u",
        "stellenvermittlung"
    ],
    "wof:name":"Adecco Ressources Humaines Sa",
    "wof:placetype":"venue"
},
  "geometry": {"coordinates":[6.9363808632,46.9942970276],"type":"Point"}
}