{
  "type": "Feature",
  "properties": {
    "iso:country":"CH",
    "sg:address":"Haltenstrasse 32",
    "sg:city":"Niederscherli",
    "sg:orig_category":"Bauschreinerei",
    "sg:phone":"+41 31 849 04 11",
    "sg:postcode":"3145",
    "sg:province":"Bern",
    "wof:name":"Rudolf Gurtner Schreinerei",
    "wof:placetype":"venue"
},
  "geometry": {"coordinates":[7.391534,46.883652],"type":"Point"}
}