{
  "type": "Feature",
  "properties": {
    "iso:country":"CH",
    "sg:address":"Pisteur Chemin 3",
    "sg:city":"Veyrier",
    "sg:orig_category":"Gartenbau",
    "sg:phone":"+41 22 784 19 18",
    "sg:postcode":"1255",
    "sg:province":"Gen\u00e8ve",
    "wof:name":"P\u00e9pini\u00e8res Bonsa\u00ef Defferrard Jean-marc",
    "wof:placetype":"venue"
},
  "geometry": {"coordinates":[6.185324192,46.1668891907],"type":"Point"}
}