{
  "type": "Feature",
  "properties": {
    "iso:country":"CH",
    "sg:address":"1733",
    "sg:city":"Treyvaux",
    "sg:orig_category":"Vereine Musik/Blasmusik",
    "sg:phone":"+41 32 912 57 50",
    "sg:postcode":"1733",
    "sg:province":"Fribourg",
    "wof:name":"St\u00e9 De Musique",
    "wof:placetype":"venue"
},
  "geometry": {"coordinates":[6.8315701485,47.1029205322],"type":"Point"}
}