{
  "type": "Feature",
  "properties": {
    "iso:country":"CH",
    "sg:address":"Feld\u00e4ckerweg 7",
    "sg:city":"W\u00e4ngi",
    "sg:orig_category":"Grosshandel mit Textilien Grosshandel mit sonstigen Konsumg\u00fctern",
    "sg:phone":"+41 22 311 59 40",
    "sg:postcode":"9545",
    "sg:province":"Thurgau",
    "wof:name":"Antercom Sa",
    "wof:placetype":"venue"
},
  "geometry": {"coordinates":[6.1507530212,46.2031135559],"type":"Point"}
}