{
  "type": "Feature",
  "properties": {
    "iso:country":"CH",
    "sg:address":"Route De Del\u00e9mont 65",
    "sg:city":"Courrendlin",
    "sg:orig_category":"Instandhaltung U Reparatur von Automobilen",
    "sg:phone":"+41 32 435 50 91",
    "sg:postcode":"2830",
    "sg:province":"Jura",
    "wof:name":"Michel Jolidon S\u00e0rl Carrosserie & Peinture",
    "wof:placetype":"venue"
},
  "geometry": {"coordinates":[7.3680372238,47.3449134827],"type":"Point"}
}