{
  "type": "Feature",
  "properties": {
    "iso:country":"CH",
    "sg:address":"Vordere Gasse 26",
    "sg:city":"Wenslingen",
    "sg:orig_category":"Malerei-Gipserei Stukkateurgewerbe, Gipserei U Verputzerei",
    "sg:phone":"+41 61 991 00 49",
    "sg:postcode":"4493",
    "sg:province":"Basel-Landschaft",
    "wof:name":"Martin Suter Gipsergesch\u00e4ft",
    "wof:placetype":"venue"
},
  "geometry": {"coordinates":[7.9109830856,47.4399871826],"type":"Point"}
}