{
  "type": "Feature",
  "properties": {
    "iso:country":"CH",
    "sg:address":"Buriet",
    "sg:city":"Thal",
    "sg:orig_category":"Herstellung von konfektionierten Textilwaren ohne Bekleidung",
    "sg:postcode":"9425",
    "sg:province":"St. Gallen",
    "wof:name":"Echantillonage Service Overney A.",
    "wof:placetype":"venue"
},
  "geometry": {"coordinates":[5.1808700562,45.8973388672],"type":"Point"}
}