{
  "type": "Feature",
  "properties": {
    "iso:country":"CH",
    "sg:address":"Corraterie Rue De La 11 1204 Gen\u00e8ve. Postfach",
    "sg:city":"Gen\u00e8ve",
    "sg:orig_category":"Interessenvertretungen",
    "sg:postcode":"1204",
    "sg:province":"Gen\u00e8ve",
    "wof:name":"Fondation La R\u00e9sidence, Le Locle Assurer L'h\u00e9bergement, La Pension Etc Aux Personnes \u00e2g\u00e9es",
    "wof:placetype":"venue"
},
  "geometry": {"coordinates":[6.7467451096,47.056476593],"type":"Point"}
}