{
  "type": "Feature",
  "properties": {
    "iso:country":"CH",
    "sg:address":"Forchstrasse 136",
    "sg:city":"Zollikerberg",
    "sg:orig_category":"Arztpraxen",
    "sg:phone":"+41 13913255",
    "sg:postcode":"8125",
    "sg:province":"Z\u00fcrich",
    "wof:name":"Dr.med.jean Pierre J. Elsig Spezialarzt Fmh",
    "wof:placetype":"venue"
},
  "geometry": {"coordinates":[8.596852,47.347111],"type":"Point"}
}