{
  "type": "Feature",
  "properties": {
    "iso:country":"CH",
    "sg:address":"Industriestrasse 651",
    "sg:city":"Eschen",
    "sg:orig_category":"Geb\u00e4ude, Wohnungsreinigung",
    "sg:phone":"+423 373 33 34",
    "sg:postcode":"9492",
    "wof:name":"Widmer Industrieservice Ag",
    "wof:placetype":"venue"
},
  "geometry": {"coordinates":[9.5348901749,47.2063140869],"type":"Point"}
}