{
  "type": "Feature",
  "properties": {
    "iso:country":"CH",
    "sg:address":"Route De Ch\u00e9rard 6 1027 Lonay. Postfach",
    "sg:city":"Lausanne",
    "sg:orig_category":"RESTAURANTS: TEA-ROOMS",
    "sg:postcode":"1003",
    "sg:province":"Vaud",
    "wof:name":"Karveyr Sa Caf\u00e9-restaurant, Bars Etc.; Achat, Vente, Exploitation",
    "wof:placetype":"venue"
},
  "geometry": {"coordinates":[6.5203652382,46.5268325806],"type":"Point"}
}