{
  "type": "Feature",
  "properties": {
    "iso:country":"CH",
    "sg:address":"Gerliswilstrasse 69",
    "sg:city":"Emmenbr\u00fccke",
    "sg:orig_category":"Public-Relations-Agenturen",
    "sg:phone":"+41 79 244 22 55",
    "sg:postcode":"6020",
    "sg:province":"Luzern",
    "wof:name":"Sepp Odermatt Public Relations",
    "wof:placetype":"venue"
},
  "geometry": {"coordinates":[8.3907699585,46.9580955505],"type":"Point"}
}