{
  "type": "Feature",
  "properties": {
    "iso:country":"CH",
    "sg:address":"6814",
    "sg:city":"Lamone",
    "sg:orig_category":"Gemeindeverwaltungen",
    "sg:phone":"+41 91 966 93 44",
    "sg:postcode":"6814",
    "sg:province":"Ticino",
    "wof:name":"Amministrazione Comunale Di Cadempino",
    "wof:placetype":"venue"
},
  "geometry": {"coordinates":[8.9324798584,46.0400886536],"type":"Point"}
}