{
  "type": "Feature",
  "properties": {
    "iso:country":"CH",
    "sg:address":"1277",
    "sg:city":"Arnex-sur-nyon",
    "sg:orig_category":"Landesverteidigung, Sozialversicherung \u00d6ffentliche Verwaltung",
    "sg:phone":"+41 22 367 14 74",
    "sg:postcode":"1277",
    "sg:province":"Vaud",
    "wof:name":"Centre De Protection Civile",
    "wof:placetype":"venue"
},
  "geometry": {"coordinates":[6.1518092155,46.3812294006],"type":"Point"}
}