{
  "type": "Feature",
  "properties": {
    "iso:country":"CH",
    "sg:address":"Ch\u00e2teau-l'ev\u00eaque Route Du 1",
    "sg:city":"Jussy",
    "sg:orig_category":"Herstellung von Automobilen",
    "sg:postcode":"1254",
    "sg:province":"Gen\u00e8ve",
    "wof:name":"Compositec, Claude B\u00fcrki",
    "wof:placetype":"venue"
},
  "geometry": {"coordinates":[6.3176307678,46.2277641296],"type":"Point"}
}