{
  "type": "Feature",
  "properties": {
    "iso:country":"CH",
    "sg:address":"1553",
    "sg:city":"Ch\u00e2tonnaye",
    "sg:orig_category":"RESTAURANTS: TEA-ROOMS",
    "sg:phone":"+41 26 658 11 19",
    "sg:postcode":"1553",
    "sg:province":"Fribourg",
    "wof:name":"Auberge De La Croix-blanche, Biselx Yvon Caf\u00e9-restaurant",
    "wof:placetype":"venue"
},
  "geometry": {"coordinates":[6.9386649132,46.7540245056],"type":"Point"}
}