{
  "type": "Feature",
  "properties": {
    "iso:country":"CH",
    "sg:address":"R\u00f6merstrasse 26",
    "sg:city":"Zeiningen",
    "sg:orig_category":"Bauschreinerei Innenausbau",
    "sg:postcode":"4314",
    "sg:province":"Aargau",
    "wof:name":"Schaffner Holzgestaltung Schreinerei-zimmerei",
    "wof:placetype":"venue"
},
  "geometry": {"coordinates":[7.876522,47.548485],"type":"Point"}
}