{
  "type": "Feature",
  "properties": {
    "iso:country":"CH",
    "sg:address":"Briggm\u00e4ttli",
    "sg:city":"L\u00fctschental",
    "sg:orig_category":"Landesverteidigung, Sozialversicherung \u00d6ffentliche Verwaltung",
    "sg:phone":"+41 34 461 16 25",
    "sg:postcode":"3816",
    "sg:province":"Bern",
    "wof:name":"Zivilschutzstelle L\u00fctzelfl\u00fch",
    "wof:placetype":"venue"
},
  "geometry": {"coordinates":[7.6784501076,47.0036315918],"type":"Point"}
}