{
  "type": "Feature",
  "properties": {
    "iso:country":"CH",
    "sg:address":"Via Cantonale 58",
    "sg:city":"Magliaso",
    "sg:orig_category":"Grosshandel mit Getr\u00e4nken Grosshandel mit Wein U Spirituosen",
    "sg:phone":"+41 26 912 70 54",
    "sg:postcode":"6983",
    "sg:province":"Ticino",
    "wof:name":"Morand Fr\u00e8res S.a.",
    "wof:placetype":"venue"
},
  "geometry": {"coordinates":[7.0663948059,46.6079711914],"type":"Point"}
}