{
  "type": "Feature",
  "properties": {
    "iso:country":"CH",
    "sg:address":"Christoffelgasse 7 3011 Bern. Postfach 6826",
    "sg:city":"Bern",
    "sg:orig_category":"Advokaturb\u00fcros",
    "sg:phone":"+41 31 311 87 08",
    "sg:postcode":"3001",
    "sg:province":"Bern",
    "wof:name":"Jacobi & Moeri Advokaturb\u00fcro",
    "wof:placetype":"venue"
},
  "geometry": {"coordinates":[7.446486,46.948647],"type":"Point"}
}