{
  "type": "Feature",
  "properties": {
    "iso:country":"CH",
    "sg:address":"Rufelistrasse 15",
    "sg:city":"H\u00fcnibach",
    "sg:orig_category":"Malerei",
    "sg:phone":"+41 33 243 17 05",
    "sg:postcode":"3626",
    "sg:province":"Bern",
    "wof:name":"Robi Koller Malergesch\u00e4ft",
    "wof:placetype":"venue"
},
  "geometry": {"coordinates":[7.645359993,46.7483901978],"type":"Point"}
}