{
  "type": "Feature",
  "properties": {
    "iso:country":"CH",
    "sg:address":"3186 D\u00fcdingen. Postfach",
    "sg:city":"D\u00fcdingen",
    "sg:orig_category":"Fernmeldedienste",
    "sg:phone":"+41 26 493 29 63",
    "sg:postcode":"3186",
    "sg:province":"Fribourg",
    "wof:name":"Rega-sense Ag",
    "wof:placetype":"venue"
},
  "geometry": {"coordinates":[7.1900749207,46.8504104614],"type":"Point"}
}