{
  "type": "Feature",
  "properties": {
    "iso:country":"CH",
    "sg:address":"Route De Suisse 370",
    "sg:city":"C\u00e9ligny",
    "sg:orig_category":"Vermietung U Verpachtung von eigenen Immobilien",
    "sg:postcode":"1298",
    "sg:province":"Gen\u00e8ve",
    "wof:name":"D P F Moser & Consorts",
    "wof:placetype":"venue"
},
  "geometry": {"coordinates":[6.2088561058,46.3513145447],"type":"Point"}
}