{
  "type": "Feature",
  "properties": {
    "iso:country":"CH",
    "sg:address":"Schmidgass 1",
    "sg:city":"Sch\u00fcpfheim",
    "sg:orig_category":"Schmieden",
    "sg:phone":"+41 41 484 12 71",
    "sg:postcode":"6170",
    "sg:province":"Luzern",
    "wof:name":"August Graf Mechanische Schmiede",
    "wof:placetype":"venue"
},
  "geometry": {"coordinates":[8.0178899765,46.9530296326],"type":"Point"}
}