{
  "type": "Feature",
  "properties": {
    "iso:country":"CH",
    "sg:address":"Voa Pricipala 22 7082 Vaz/obervaz. Postfach",
    "sg:city":"Lenzerheide/lai",
    "sg:orig_category":"Herstellung von sonstigen keramischen Erzeugnissen f\u00fcr technische Zwecke",
    "sg:postcode":"7078",
    "sg:province":"Graubunden",
    "wof:name":"Caspar Thomas",
    "wof:placetype":"venue"
},
  "geometry": {"coordinates":[9.559630394,46.7550201416],"type":"Point"}
}