{
  "type": "Feature",
  "properties": {
    "iso:country":"CH",
    "sg:address":"Route Des Moulins 1523 Granges-marnand Case Postale 68",
    "sg:city":"Granges-marnand",
    "sg:orig_category":"Herstellung von Futtermitteln f\u00fcr Nutztiere Mahl U Sch\u00e4lm\u00fchlen",
    "sg:phone":"+41 26 668 51 00",
    "sg:postcode":"1523",
    "sg:province":"Vaud",
    "wof:name":"Biomill Sa",
    "wof:placetype":"venue"
},
  "geometry": {"coordinates":[6.8828139305,46.7633323669],"type":"Point"}
}