{
  "type": "Feature",
  "properties": {
    "iso:country":"CH",
    "sg:address":"Rue Ami-lullin 3",
    "sg:city":"Gen\u00e8ve",
    "sg:orig_category":"Finanzierungsinstitutionen",
    "sg:phone":"+41 22 707 17 55",
    "sg:postcode":"1207",
    "sg:province":"Gen\u00e8ve",
    "wof:name":"Inveadco Sa",
    "wof:placetype":"venue"
},
  "geometry": {"coordinates":[6.15437603,46.2004127502],"type":"Point"}
}