{
  "type": "Feature",
  "properties": {
    "iso:country":"CH",
    "sg:address":"Milit\u00e4rstrasse 8889 Plons. Postfach",
    "sg:city":"Plons",
    "sg:orig_category":"Instandhaltung U Reparatur von Automobilen",
    "sg:postcode":"8889",
    "sg:province":"St. Gallen",
    "wof:name":"Buchli & Co",
    "wof:placetype":"venue"
},
  "geometry": {"coordinates":[9.4015245438,47.0567817688],"type":"Point"}
}