{
  "type": "Feature",
  "properties": {
    "iso:country":"CH",
    "sg:address":"Signalstrasse 48",
    "sg:city":"Rorschach",
    "sg:orig_category":"Non-Classified Establishments",
    "sg:phone":"+41 71 841 37 62",
    "sg:postcode":"9400",
    "sg:province":"St. Gallen",
    "wof:name":"Belras Ag",
    "wof:placetype":"venue"
},
  "geometry": {"coordinates":[9.49223423,47.4730415344],"type":"Point"}
}