{
  "type": "Feature",
  "properties": {
    "iso:country":"CH",
    "sg:address":"M\u00fchlegasse 11 8001 Z\u00fcrich. Postfach",
    "sg:city":"Z\u00fcrich",
    "sg:orig_category":"Sonstige Hilfs U Nebent\u00e4tigkeiten f\u00fcr die Luftfahrt",
    "sg:postcode":"8001",
    "sg:province":"Z\u00fcrich",
    "wof:name":"Air Ground Services Gesellschaft Mit Beschr\u00e4nkter Haftung, Frankfurt Am Main, Zweigniederlassung Z\u00fcrich",
    "wof:placetype":"venue"
},
  "geometry": {"coordinates":[8.543964386,47.3743553162],"type":"Point"}
}