{
  "type": "Feature",
  "properties": {
    "iso:country":"CH",
    "sg:address":"Zugerbergstrasse 44",
    "sg:city":"Zug",
    "sg:orig_category":"Pensionskassen",
    "sg:postcode":"6300",
    "sg:province":"Zug",
    "wof:name":"Personalf\u00fcrsorgestiftung Der Gebr. Hodel Ag",
    "wof:placetype":"venue"
},
  "geometry": {"coordinates":[8.5194339752,47.1571578979],"type":"Point"}
}