{
  "type": "Feature",
  "properties": {
    "iso:country":"CH",
    "sg:address":"Tellistrasse 67",
    "sg:city":"Aarau",
    "sg:orig_category":"Nationale Postdienste",
    "sg:phone":"+41 17107811",
    "sg:postcode":"5004",
    "sg:province":"Aargau",
    "wof:name":"Die Schweizerische Post Adliswil 1",
    "wof:placetype":"venue"
},
  "geometry": {"coordinates":[8.5245361328,47.313243866],"type":"Point"}
}