{
  "type": "Feature",
  "properties": {
    "iso:country":"CH",
    "sg:address":"Kirchstrasse 2",
    "sg:city":"Rehetobel",
    "sg:orig_category":"Non-Classified Establishments",
    "sg:phone":"+41 71 877 37 33",
    "sg:postcode":"9038",
    "sg:province":"Appenzell Ausserrhoden",
    "wof:name":"Lonardi & Bartoli Gmbh",
    "wof:placetype":"venue"
},
  "geometry": {"coordinates":[9.482583046,47.4267311096],"type":"Point"}
}