{
  "type": "Feature",
  "properties": {
    "iso:country":"CH",
    "sg:address":"Via Vincenzo D'alberti 4",
    "sg:city":"Chiasso",
    "sg:orig_category":"Effektenvermittlung Broker Finanzierungsinstitutionen",
    "sg:postcode":"6830",
    "sg:province":"Ticino",
    "wof:name":"Merrill Lynch International Inc., Wilmington, Geneva Branch",
    "wof:placetype":"venue"
},
  "geometry": {"coordinates":[6.1556987762,46.1962547302],"type":"Point"}
}