{
  "type": "Feature",
  "properties": {
    "iso:country":"CH",
    "sg:address":"Avant Baselgia 85",
    "sg:city":"Sent",
    "sg:classifiers":[
        {
            "category":"Restaurant",
            "type":"Food & Drink"
        }
    ],
    "sg:phone":"+41 81 864 17 34",
    "sg:postcode":"7554",
    "sg:province":"Graubunden",
    "wof:name":"Restaurant Chasa Veglia",
    "wof:placetype":"venue"
},
  "geometry": {"coordinates":[10.3360109329,46.8162269592],"type":"Point"}
}