{
  "type": "Feature",
  "properties": {
    "iso:country":"CH",
    "sg:address":"Alte Landstrasse 34",
    "sg:city":"Zollikon",
    "sg:orig_category":"Effektenverwaltung Reiseb\u00fcros U Reiseveranstalter",
    "sg:phone":"+41 19951723",
    "sg:postcode":"8702",
    "sg:province":"Z\u00fcrich",
    "wof:name":"Financial-servicers.com Gmbh",
    "wof:placetype":"venue"
},
  "geometry": {"coordinates":[8.5720815659,47.3423805237],"type":"Point"}
}