{
  "type": "Feature",
  "properties": {
    "iso:country":"CH",
    "sg:address":"Alpenstrasse 3",
    "sg:city":"Lyss",
    "sg:orig_category":"Fussreflexzonenmassage Solarien",
    "sg:phone":"+41 32 384 73 45",
    "sg:postcode":"3250",
    "sg:province":"Bern",
    "wof:name":"Lilo Kehrwand Solarium",
    "wof:placetype":"venue"
},
  "geometry": {"coordinates":[7.3103518486,47.0726776123],"type":"Point"}
}