{
  "type": "Feature",
  "properties": {
    "iso:country":"CH",
    "sg:address":"B\u00fctzbergstrasse 109",
    "sg:city":"Langenthal",
    "sg:orig_category":"Mechanik Mechanische Werkst\u00e4tten",
    "sg:phone":"+41 62 922 87 22",
    "sg:postcode":"4900",
    "sg:province":"Bern",
    "wof:name":"Weber Rolf",
    "wof:placetype":"venue"
},
  "geometry": {"coordinates":[7.7678089142,47.2177047729],"type":"Point"}
}