{
  "type": "Feature",
  "properties": {
    "iso:country":"CH",
    "sg:address":"Ey",
    "sg:city":"Lauterbrunnen",
    "sg:orig_category":"Museen",
    "sg:phone":"+41 33 855 13 88",
    "sg:postcode":"3822",
    "sg:province":"Bern",
    "wof:name":"Museum Der Talschaft Lauterbrunnen",
    "wof:placetype":"venue"
},
  "geometry": {"coordinates":[7.9100618362,46.5928077698],"type":"Point"}
}