{
  "type": "Feature",
  "properties": {
    "iso:country":"CH",
    "sg:address":"Rue Des Hirondelles 3 2500 Biel/bienne. Postfach",
    "sg:city":"Biel/bienne",
    "sg:orig_category":"Non-Classified Establishments",
    "sg:postcode":"2502",
    "sg:province":"Bern",
    "wof:name":"Mecabor, Bord P.",
    "wof:placetype":"venue"
},
  "geometry": {"coordinates":[7.2614059448,47.1481323242],"type":"Point"}
}