{
  "type": "Feature",
  "properties": {
    "iso:country":"CH",
    "sg:address":"Rovray Aubonne",
    "sg:city":"Allaman",
    "sg:orig_category":"Herstellung von Bettwaren Herstellung von konfektionierten Textilwaren ohne Bekleidung",
    "sg:phone":"+41 21 807 34 11",
    "sg:postcode":"1165",
    "sg:province":"Vaud",
    "wof:name":"Etablissement R.caillet Sa Fabrique De Matelas Elite",
    "wof:placetype":"venue"
},
  "geometry": {"coordinates":[6.4031600952,46.4779891968],"type":"Point"}
}