{
  "type": "Feature",
  "properties": {
    "addr:full":"Beau-s\u00e9jour Rue 1 1003 Lausanne. Postfach Lausanne Vaud 1003",
    "addr:housenumber":"1",
    "addr:postcode":"1003;postfach;1003",
    "addr:street":"Rue",
    "iso:country":"CH",
    "sg:address":"Beau-s\u00e9jour Rue 1 1003 Lausanne. Postfach",
    "sg:city":"Lausanne",
    "sg:orig_category":"Detailhandel mit B\u00fcchern, Zeitungen, Schreib U Papeteriewaren",
    "sg:phone":"+41 21 323 25 33",
    "sg:postcode":"1003",
    "sg:province":"Vaud",
    "wof:name":"Kercoff Mme I. Successeur Kl\u00e9ber Mme Galina Librairie",
    "wof:placetype":"venue"
},
  "geometry": {"coordinates":[6.634388,46.5182],"type":"Point"}
}