{
  "type": "Feature",
  "properties": {
    "iso:country":"CH",
    "sg:address":"Stockerstrasse 38",
    "sg:city":"Z\u00fcrich",
    "sg:orig_category":"Architektur U Ingenieurb\u00fcros",
    "sg:phone":"+41 12113431",
    "sg:postcode":"8002",
    "sg:province":"Z\u00fcrich",
    "wof:name":"Enpro, Engineering Projects And Services Gmbh",
    "wof:placetype":"venue"
},
  "geometry": {"coordinates":[8.534846,47.367607],"type":"Point"}
}