{
  "type": "Feature",
  "properties": {
    "iso:country":"CH",
    "sg:address":"Schlossplatz 1",
    "sg:city":"Aarau",
    "sg:orig_category":"Unternehmensberatung",
    "sg:phone":"+41 62 825 04 34",
    "sg:postcode":"5000",
    "sg:province":"Aargau",
    "wof:name":"Act Unternehmensberatung, Max A. Hess",
    "wof:placetype":"venue"
},
  "geometry": {"coordinates":[8.0454816818,47.3937568665],"type":"Point"}
}