{
  "type": "Feature",
  "properties": {
    "iso:country":"CH",
    "sg:address":"Neugasse 17",
    "sg:city":"Vaduz",
    "sg:orig_category":"Verm\u00f6gensverwaltung",
    "sg:phone":"+423 232 14 38",
    "sg:postcode":"9490",
    "wof:name":"Treuhand-& Verwaltungs-anstalt",
    "wof:placetype":"venue"
},
  "geometry": {"coordinates":[9.5114660263,47.1514320374],"type":"Point"}
}