{
  "type": "Feature",
  "properties": {
    "iso:country":"CH",
    "sg:address":"Lerchenweg 6",
    "sg:city":"Rheinfelden",
    "sg:orig_category":"Sportvereine Turnen Damen",
    "sg:phone":"+41 61 831 52 63",
    "sg:postcode":"4310",
    "sg:province":"Aargau",
    "wof:name":"Damenturnver.stv Rheinfelden",
    "wof:placetype":"venue"
},
  "geometry": {"coordinates":[7.7798848152,47.5503845215],"type":"Point"}
}