{
  "type": "Feature",
  "properties": {
    "iso:country":"CH",
    "sg:address":"Schr\u00e4gweg 3",
    "sg:city":"T\u00e4uffelen",
    "sg:orig_category":"Herstellung von sonstigen elektrischen Ausr\u00fcstungen",
    "sg:postcode":"2575",
    "sg:province":"Bern",
    "wof:name":"Knuchel \u00ac Signatec.",
    "wof:placetype":"venue"
},
  "geometry": {"coordinates":[7.2032279968,47.0734138489],"type":"Point"}
}