{
  "type": "Feature",
  "properties": {
    "iso:country":"CH",
    "sg:address":"Siro Via San 2",
    "sg:city":"Pregassona",
    "sg:orig_category":"Kauf U Verkauf von Immobilien auf eigene Rechnung",
    "sg:postcode":"6963",
    "sg:province":"Ticino",
    "wof:name":"Aranceto N. 1 Sa",
    "wof:placetype":"venue"
},
  "geometry": {"coordinates":[8.9732227325,46.0176048279],"type":"Point"}
}