{
  "type": "Feature",
  "properties": {
    "iso:country":"CH",
    "sg:address":"Zuchwilerstrasse 43",
    "sg:city":"Solothurn",
    "sg:orig_category":"RESTAURANTS: TEA-ROOMS",
    "sg:phone":"+41 32 622 23 11",
    "sg:postcode":"4500",
    "sg:province":"Solothurn",
    "wof:name":"Caf\u00e9 Mozart, Biberstein + Von B\u00fcren",
    "wof:placetype":"venue"
},
  "geometry": {"coordinates":[7.5438389778,47.2029457092],"type":"Point"}
}