{
  "type": "Feature",
  "properties": {
    "iso:country":"CH",
    "sg:address":"Chesa Viola",
    "sg:city":"Zuoz",
    "sg:orig_category":"Herstellung von sonstigen landwirtschaftlichen Maschinen",
    "sg:phone":"+41 81 854 14 32",
    "sg:postcode":"7524",
    "sg:province":"Graubunden",
    "wof:name":"Tonu Maschinas Agriculas E Forestelas Gmbh",
    "wof:placetype":"venue"
},
  "geometry": {"coordinates":[9.9598398209,46.6027832031],"type":"Point"}
}