{
  "type": "Feature",
  "properties": {
    "iso:country":"CH",
    "sg:address":"Sternmattweg 1",
    "sg:city":"Kriens",
    "sg:orig_category":"Herstellung von sonstigen landwirtschaftlichen Maschinen",
    "sg:phone":"+41 41 310 69 69",
    "sg:postcode":"6010",
    "sg:province":"Luzern",
    "wof:name":"Franco Fa\u00e9 Rasenm\u00e4herservice",
    "wof:placetype":"venue"
},
  "geometry": {"coordinates":[8.2974510193,47.0274620056],"type":"Point"}
}