{
  "type": "Feature",
  "properties": {
    "addr:full":"Route D'yverdon 5 Cheseaux-lausanne Vaud 1033",
    "addr:housenumber":"5",
    "addr:postcode":"1033",
    "addr:street":"Route D'Yverdon",
    "iso:country":"CH",
    "sg:address":"Route D'yverdon 5",
    "sg:city":"Cheseaux-lausanne",
    "sg:orig_category":"Arztpraxen",
    "sg:phone":"+41 21 731 46 31",
    "sg:postcode":"1033",
    "sg:province":"Vaud",
    "wof:name":"Dr M\u00e9d. Stanley Hesse M\u00e9decin G\u00e9n\u00e9raliste Fmh",
    "wof:placetype":"venue"
},
  "geometry": {"coordinates":[6.607086,46.590637],"type":"Point"}
}