{
  "type": "Feature",
  "properties": {
    "iso:country":"CH",
    "sg:address":"Hardturmstrasse 126",
    "sg:city":"Z\u00fcrich",
    "sg:orig_category":"Detailhandel mit Waren verschiedener Art, Hauptrichtung Nahrungsmittel",
    "sg:phone":"+41 14406232",
    "sg:postcode":"8005",
    "sg:province":"Z\u00fcrich",
    "wof:name":"Petros Nanopoulos Lebensmittelgesch\u00e4ft L\u00e4bis 7",
    "wof:placetype":"venue"
},
  "geometry": {"coordinates":[8.5141162872,47.3936424255],"type":"Point"}
}