{
  "type": "Feature",
  "properties": {
    "iso:country":"CH",
    "sg:address":"Zwinglistrasse 3",
    "sg:city":"Z\u00fcrich",
    "sg:orig_category":"RESTAURANTS: TEA-ROOMS",
    "sg:phone":"+41 12418011",
    "sg:postcode":"8004",
    "sg:province":"Z\u00fcrich",
    "wof:name":"Restaurant Raja Bongo, Vaghela Dhiru",
    "wof:placetype":"venue"
},
  "geometry": {"coordinates":[8.5296773911,47.3778076172],"type":"Point"}
}