{
  "type": "Feature",
  "properties": {
    "iso:country":"CH",
    "sg:address":"8730 Uznach. Postfach 357",
    "sg:city":"Uznach",
    "sg:orig_category":"Tierhaltung",
    "sg:phone":"+41 17844245",
    "sg:postcode":"8730",
    "sg:province":"St. Gallen",
    "wof:name":"Rabbit - Ch Das Ultimative Kaninchenzuchtprogramm Bodmer",
    "wof:placetype":"venue"
},
  "geometry": {"coordinates":[8.9764099121,47.2250709534],"type":"Point"}
}