{
  "type": "Feature",
  "properties": {
    "iso:country":"CH",
    "sg:address":"Hauptstrasse 22",
    "sg:city":"Br\u00fcgglen",
    "sg:orig_category":"RESTAURANTS: TEA-ROOMS",
    "sg:phone":"+41 71 385 12 33",
    "sg:postcode":"4582",
    "sg:province":"Solothurn",
    "wof:name":"W\u00fcthrich Hildegard, Rest. Weisses Sch\u00e4fli",
    "wof:placetype":"venue"
},
  "geometry": {"coordinates":[9.249707222,47.414604187],"type":"Point"}
}