{
  "type": "Feature",
  "properties": {
    "iso:country":"CH",
    "sg:address":"Montavau 205",
    "sg:city":"Enney",
    "sg:orig_category":"Forstwirtschaft ohne Dienstleistungen in der Forstwirtschaft",
    "sg:phone":"+41 79 321 17 37",
    "sg:postcode":"1667",
    "sg:province":"Fribourg",
    "wof:name":"Jcg, Entreprise Foresti\u00e8re Sa",
    "wof:placetype":"venue"
},
  "geometry": {"coordinates":[7.085624218,46.5662460327],"type":"Point"}
}