{
  "type": "Feature",
  "properties": {
    "iso:country":"CH",
    "sg:address":"Bergstrasse 75",
    "sg:city":"Rebstein",
    "sg:orig_category":"Grosshandel mit Textilien Sonstiges Textilgewerbe",
    "sg:phone":"+41 71 777 11 84",
    "sg:postcode":"9445",
    "sg:province":"St. Gallen",
    "wof:name":"Keel Textil Ag Rebstein",
    "wof:placetype":"venue"
},
  "geometry": {"coordinates":[9.5806341171,47.4009780884],"type":"Point"}
}