{
  "type": "Feature",
  "properties": {
    "iso:country":"CH",
    "sg:address":"Gewerbestrasse 6 5702 Niederlenz. Postfach",
    "sg:city":"Niederlenz",
    "sg:orig_category":"Handel mit Automobilen",
    "sg:phone":"+41 55 442 24 59",
    "sg:postcode":"5702",
    "sg:province":"Aargau",
    "wof:name":"Ibertrans Sa",
    "wof:placetype":"venue"
},
  "geometry": {"coordinates":[8.8597793579,47.2014846802],"type":"Point"}
}