{
  "type": "Feature",
  "properties": {
    "iso:country":"CH",
    "sg:address":"Wolhuserstrasse",
    "sg:city":"Ruswil",
    "sg:orig_category":"Abwasserreinigung",
    "sg:phone":"+41 41 495 19 41",
    "sg:postcode":"6017",
    "sg:province":"Luzern",
    "wof:name":"Kl\u00e4ranlage",
    "wof:placetype":"venue"
},
  "geometry": {"coordinates":[8.11787,47.081604],"type":"Point"}
}