{
  "type": "Feature",
  "properties": {
    "iso:country":"CH",
    "sg:address":"Hofm\u00e4ttli 16",
    "sg:city":"Uetendorf",
    "sg:orig_category":"Malerei",
    "sg:phone":"+41 33 345 38 26",
    "sg:postcode":"3661",
    "sg:province":"Bern",
    "wof:name":"Rolf St\u00e4heli Malergesch\u00e4ft",
    "wof:placetype":"venue"
},
  "geometry": {"coordinates":[7.5787668228,46.771156311],"type":"Point"}
}