{
  "type": "Feature",
  "properties": {
    "iso:country":"CH",
    "sg:address":"Via Fusoni 5",
    "sg:city":"Lugano",
    "sg:orig_category":"Detailhandel mit Waren verschiedener Art, Hauptrichtung Nahrungsmittel Sonstiger Fachdetailhandel mi",
    "sg:phone":"+41 91 921 08 14",
    "sg:postcode":"6900",
    "sg:province":"Ticino",
    "wof:name":"Viviane Foraboschi Alimentari L'angelo",
    "wof:placetype":"venue"
},
  "geometry": {"coordinates":[8.9588670731,46.0093231201],"type":"Point"}
}