{
  "type": "Feature",
  "properties": {
    "iso:country":"CH",
    "sg:address":"Neugasse 31",
    "sg:city":"Z\u00fcrich",
    "sg:orig_category":"Herstellung von sonstigen Gummiwaren Herstellung von sonstigen Metallwaren",
    "sg:phone":"+41 12717771",
    "sg:postcode":"8005",
    "sg:province":"Z\u00fcrich",
    "wof:name":"Form- & Fa\u00e7ontechnik Ag",
    "wof:placetype":"venue"
},
  "geometry": {"coordinates":[8.5307683945,47.3818130493],"type":"Point"}
}