{
  "type": "Feature",
  "properties": {
    "iso:country":"CH",
    "sg:address":"Rue De Lo\u00e8che 39",
    "sg:city":"Sion",
    "sg:orig_category":"Psychotherapie",
    "sg:phone":"+41 27 322 78 00",
    "sg:postcode":"1950",
    "sg:province":"Valais",
    "wof:name":"Jacqueline Nanchen Psychoth\u00e9rapie",
    "wof:placetype":"venue"
},
  "geometry": {"coordinates":[7.3649568558,46.2388687134],"type":"Point"}
}