{
  "type": "Feature",
  "properties": {
    "iso:country":"CH",
    "sg:address":"Schwarztorstrasse 11",
    "sg:city":"Bern",
    "sg:classifiers":[
        {
            "category":"Restaurant",
            "type":"Food & Drink"
        }
    ],
    "sg:phone":"+41 32 631 12 42",
    "sg:postcode":"3007",
    "sg:province":"Bern",
    "wof:name":"Restaurant Rendez-vous",
    "wof:placetype":"venue"
},
  "geometry": {"coordinates":[7.6546549797,47.2356834412],"type":"Point"}
}