{
  "type": "Feature",
  "properties": {
    "iso:country":"CH",
    "sg:address":"Erlenstrasse 31a 2555 Br\u00fcgg Be Case Postale 698",
    "sg:city":"Biel/bienne",
    "sg:orig_category":"Herstellung U Zusammensetzung von Uhren Herstellung von Uhren",
    "sg:phone":"+41 22 719 31 31",
    "sg:postcode":"2501",
    "sg:province":"Bern",
    "wof:name":"Le Petit-fils De L.u. Chopard & Cie Sa",
    "wof:placetype":"venue"
},
  "geometry": {"coordinates":[6.061526,46.226723],"type":"Point"}
}