{
  "type": "Feature",
  "properties": {
    "iso:country":"CH",
    "sg:address":"Gheidstrasse 21 5507 Mellingen. Postfach",
    "sg:city":"Mellingen",
    "sg:orig_category":"Herstellung von Karosserien U Anh\u00e4ngern",
    "sg:phone":"+41 56 491 18 64",
    "sg:postcode":"5507",
    "sg:province":"Aargau",
    "wof:name":"N\u00fcssli Fahrzeugbau Ag Aufbauten Anh\u00e4nger Auflieger",
    "wof:placetype":"venue"
},
  "geometry": {"coordinates":[8.2721529007,47.410533905],"type":"Point"}
}