{
  "type": "Feature",
  "properties": {
    "iso:country":"CH",
    "sg:address":"Erbletstrasse 8",
    "sg:city":"Villigen",
    "sg:orig_category":"Grosshandel mit sonstigen Maschinen U Ausr\u00fcstungen f\u00fcr Industrie, Handel U Schiffahrt",
    "sg:phone":"+41 56 290 20 84",
    "sg:postcode":"5234",
    "sg:province":"Aargau",
    "wof:name":"H.r. Zimmermann Ag",
    "wof:placetype":"venue"
},
  "geometry": {"coordinates":[8.2182779312,47.5234680176],"type":"Point"}
}