{
  "type": "Feature",
  "properties": {
    "iso:country":"CH",
    "sg:address":"Seevorstadt 6",
    "sg:city":"Biel",
    "sg:classifiers":[
        {
            "category":"Wholesale",
            "subcategory":"Machinery & Supplies",
            "type":"Manufacturing & Wholesale Goods"
        }
    ],
    "sg:phone":"+41 32 933 31 11",
    "sg:postcode":"2501",
    "sg:province":"Bern",
    "sg:tags":[
        "equipment",
        "equipement",
        "precision",
        "timekeeping"
    ],
    "wof:name":"Tissot Sa",
    "wof:placetype":"venue"
},
  "geometry": {"coordinates":[8.2241401672,46.8130912781],"type":"Point"}
}