{
  "type": "Feature",
  "properties": {
    "iso:country":"CH",
    "sg:address":"Niklaus-konrad-strasse 25",
    "sg:city":"Solothurn",
    "sg:orig_category":"Zahnarztpraxen",
    "sg:phone":"+41 32 622 29 52",
    "sg:postcode":"4500",
    "sg:province":"Solothurn",
    "wof:name":"Dr. Med. Dent. Ruth Gr\u00fctter Zahn\u00e4rztin",
    "wof:placetype":"venue"
},
  "geometry": {"coordinates":[7.5420098305,47.2050552368],"type":"Point"}
}