{
  "type": "Feature",
  "properties": {
    "iso:country":"CH",
    "sg:address":"Hauptstrasse 36 4127 Birsfelden. Postfach",
    "sg:city":"Birsfelden",
    "sg:orig_category":"Sonstige mit der Informatik verbundene T\u00e4tigkeiten",
    "sg:postcode":"4127",
    "sg:province":"Basel-Landschaft",
    "wof:name":"Bos Broker Offert Service Ag",
    "wof:placetype":"venue"
},
  "geometry": {"coordinates":[7.6198291779,47.554019928],"type":"Point"}
}