{
  "type": "Feature",
  "properties": {
    "iso:country":"CH",
    "sg:address":"Aarbergergasse 36",
    "sg:city":"Bern",
    "sg:orig_category":"Elektroinstallation",
    "sg:phone":"+41 41 632 60 32",
    "sg:postcode":"3011",
    "sg:province":"Bern",
    "wof:name":"Waser & Co, Elektro-telefon-radio-video-tv",
    "wof:placetype":"venue"
},
  "geometry": {"coordinates":[8.3119812012,46.9970169067],"type":"Point"}
}