{
  "type": "Feature",
  "properties": {
    "iso:country":"CH",
    "sg:address":"Hinterbachwil",
    "sg:city":"Entlebuch",
    "sg:classifiers":[
        {
            "category":"Travel",
            "subcategory":"Hotels & Motels",
            "type":"Entertainment"
        }
    ],
    "sg:phone":"+41 81 911 26 57",
    "sg:postcode":"6162",
    "sg:province":"Luzern",
    "sg:tags":[
        "hotels",
        "mit",
        "restaurant"
    ],
    "wof:name":"Hotel Porta Sut",
    "wof:placetype":"venue"
},
  "geometry": {"coordinates":[9.2852306366,46.8366928101],"type":"Point"}
}