{
  "type": "Feature",
  "properties": {
    "iso:country":"CH",
    "sg:address":"Route Du Crochet 7 1762 Givisiez Case Postale 51",
    "sg:city":"Givisiez",
    "sg:orig_category":"Architektur U Ingenieurb\u00fcros",
    "sg:postcode":"1762",
    "sg:province":"Fribourg",
    "wof:name":"Chammartin Et Spicher Sa, Succursale De Riviera-chablais Bureau D'ing\u00e9nieurs-conseils En Chauffage, Sanitaires, Ventilation Etc",
    "wof:placetype":"venue"
},
  "geometry": {"coordinates":[6.864175,46.453831],"type":"Point"}
}