{
  "type": "Feature",
  "properties": {
    "iso:country":"CH",
    "sg:address":"Oberdorfstrasse 143",
    "sg:city":"Herisau",
    "sg:orig_category":"Architektur U Ingenieurb\u00fcros",
    "sg:postcode":"9100",
    "sg:province":"Appenzell Ausserrhoden",
    "wof:name":"Ingenieurb\u00fcro K\u00fcnzler M. Planung Und Datentechnik",
    "wof:placetype":"venue"
},
  "geometry": {"coordinates":[9.293099,47.390759],"type":"Point"}
}