{
  "type": "Feature",
  "properties": {
    "iso:country":"CH",
    "sg:address":"Bahnhofstrasse 28 3114 Oberwichtrach. Postfach 214",
    "sg:city":"Wichtrach",
    "sg:orig_category":"Dachdeckerei Hobel U Holzimpr\u00e4gnierwerke",
    "sg:phone":"+41 31 781 28 48",
    "sg:postcode":"3114",
    "sg:province":"Bern",
    "wof:name":"Growe Ag",
    "wof:placetype":"venue"
},
  "geometry": {"coordinates":[7.576488,46.842506],"type":"Point"}
}