{
  "type": "Feature",
  "properties": {
    "iso:country":"CH",
    "sg:address":"Route D'echandens 26",
    "sg:city":"Lonay",
    "sg:orig_category":"Maurerarbeiten",
    "sg:phone":"+41 21 801 10 06",
    "sg:postcode":"1027",
    "sg:province":"Vaud",
    "wof:name":"Francis Fauchez Entrepreneur En B\u00e2timent",
    "wof:placetype":"venue"
},
  "geometry": {"coordinates":[6.5193300247,46.5312309265],"type":"Point"}
}