{
  "type": "Feature",
  "properties": {
    "iso:country":"CH",
    "sg:address":"Haus Montana",
    "sg:city":"M\u00fcrren",
    "sg:orig_category":"Detailhandel mit Sportartikeln",
    "sg:phone":"+41 33 855 20 88",
    "sg:postcode":"3825",
    "sg:province":"Bern",
    "wof:name":"St\u00e4ger-sport",
    "wof:placetype":"venue"
},
  "geometry": {"coordinates":[7.8951401711,46.560218811],"type":"Point"}
}