{
  "type": "Feature",
  "properties": {
    "iso:country":"CH",
    "sg:address":"Grand-pr\u00e9 Rue Du 47 1202 Gen\u00e8ve. Postfach",
    "sg:city":"Gen\u00e8ve",
    "sg:orig_category":"Detailhandel mit Brot, Back U S\u00fcsswaren",
    "sg:postcode":"1202",
    "sg:province":"Gen\u00e8ve",
    "wof:name":"Rossetto Terza Mme Antonia",
    "wof:placetype":"venue"
},
  "geometry": {"coordinates":[6.133384,46.214882],"type":"Point"}
}