{
  "type": "Feature",
  "properties": {
    "iso:country":"CH",
    "sg:address":"Friedhofplatz 3. 4500 Solothurn. Postfach",
    "sg:city":"Solothurn",
    "sg:orig_category":"Non-Classified Establishments",
    "sg:phone":"+41 32 622 25 34",
    "sg:postcode":"4500",
    "sg:province":"Solothurn",
    "wof:name":"Tr\u00fcssel Hans-ulrich",
    "wof:placetype":"venue"
},
  "geometry": {"coordinates":[7.5356712341,47.2072029114],"type":"Point"}
}