{
  "type": "Feature",
  "properties": {
    "iso:country":"CH",
    "sg:address":"Ch\u00f6renmattstrasse 2 8965 Berikon. Postfach",
    "sg:city":"Berikon",
    "sg:orig_category":"Detailhandel mit Uhren U Schmuck Herstellung von Schmuck, Gold U Silberschmiedwaren",
    "sg:phone":"+41 56 633 80 10",
    "sg:postcode":"8965",
    "sg:province":"Aargau",
    "wof:name":"Keller Thildy",
    "wof:placetype":"venue"
},
  "geometry": {"coordinates":[8.3672847748,47.3609771729],"type":"Point"}
}