{
  "type": "Feature",
  "properties": {
    "iso:country":"CH",
    "sg:address":"Eisenhofstrasse 1",
    "sg:city":"Horgen",
    "sg:orig_category":"Maler U Glasergewerbe Malerei",
    "sg:phone":"+41 17279988",
    "sg:postcode":"8810",
    "sg:province":"Z\u00fcrich",
    "wof:name":"Graum\u00fcller & Scipione Malergesch\u00e4ft",
    "wof:placetype":"venue"
},
  "geometry": {"coordinates":[8.6004695892,47.2602005005],"type":"Point"}
}