{
  "type": "Feature",
  "properties": {
    "iso:country":"CH",
    "sg:address":"Hofenstrasse 76",
    "sg:city":"M\u00e4nnedorf",
    "sg:orig_category":"Datenverarbeitungsdienste Sonstige mit der Informatik verbundene T\u00e4tigkeiten",
    "sg:phone":"+41 17901582",
    "sg:postcode":"8708",
    "sg:province":"Z\u00fcrich",
    "wof:name":"Ruedi Gisin Edv Beratungen",
    "wof:placetype":"venue"
},
  "geometry": {"coordinates":[8.6945409775,47.2576599121],"type":"Point"}
}