{
  "type": "Feature",
  "properties": {
    "iso:country":"CH",
    "sg:address":"Ausserdorf",
    "sg:city":"Mosnang",
    "sg:classifiers":[
        {
            "category":"Banks & Credit Unions",
            "subcategory":"Bank",
            "type":"Services"
        }
    ],
    "sg:phone":"+41 81 738 16 26",
    "sg:postcode":"9607",
    "sg:province":"St. Gallen",
    "wof:name":"Raiffeisenbank Murg",
    "wof:placetype":"venue"
},
  "geometry": {"coordinates":[9.216112,47.113022],"type":"Point"}
}