{
  "type": "Feature",
  "properties": {
    "iso:country":"CH",
    "sg:address":"Rathausgasse",
    "sg:city":"Lenzburg",
    "sg:orig_category":"Interessenvertretungen",
    "sg:phone":"+41 79 336 90 90",
    "sg:postcode":"5600",
    "sg:province":"Aargau",
    "wof:name":"Schloss Lenzburg",
    "wof:placetype":"venue"
},
  "geometry": {"coordinates":[8.1803846359,47.387348175],"type":"Point"}
}