{
  "type": "Feature",
  "properties": {
    "iso:country":"CH",
    "sg:address":"Neumarktstrasse 34",
    "sg:city":"Biel/bienne",
    "sg:orig_category":"Werbung",
    "sg:postcode":"2502",
    "sg:province":"Bern",
    "wof:name":"C.i.d. Gmbh",
    "wof:placetype":"venue"
},
  "geometry": {"coordinates":[7.2491688728,47.1392326355],"type":"Point"}
}