{
  "type": "Feature",
  "properties": {
    "iso:country":"CH",
    "sg:address":"Zugerstasse 50",
    "sg:city":"Baar",
    "sg:orig_category":"Erbringung von Dienstleistungen f\u00fcr Unternehmen",
    "sg:phone":"+41 71 333 21 65",
    "sg:postcode":"6340",
    "sg:province":"Zug",
    "wof:name":"Etelco Holding Ag",
    "wof:placetype":"venue"
},
  "geometry": {"coordinates":[8.5262966156,47.1947250366],"type":"Point"}
}