{
  "type": "Feature",
  "properties": {
    "iso:country":"CH",
    "sg:address":"La Tuffi\u00e8re",
    "sg:city":"Ecuvillens",
    "sg:orig_category":"Instandhaltung U Reparatur von Automobilen",
    "sg:phone":"+41 26 411 41 16",
    "sg:postcode":"1730",
    "sg:province":"Fribourg",
    "wof:name":"Vm Automobiles Van De Scheur Et Cie",
    "wof:placetype":"venue"
},
  "geometry": {"coordinates":[7.0892109871,46.7579231262],"type":"Point"}
}