{
  "type": "Feature",
  "properties": {
    "iso:country":"CH",
    "sg:address":"Rue Haute 10",
    "sg:city":"Grandson",
    "sg:orig_category":"Verwaltung von Immobilien",
    "sg:phone":"+41 21 973 12 21",
    "sg:postcode":"1422",
    "sg:province":"Vaud",
    "wof:name":"Jean Desponds R\u00e9gies De La Couronne",
    "wof:placetype":"venue"
},
  "geometry": {"coordinates":[6.8804411888,46.4498291016],"type":"Point"}
}