{
  "type": "Feature",
  "properties": {
    "iso:country":"CH",
    "sg:address":"P\u00e9pinet Rue 3 1003 Lausanne. Postfach",
    "sg:city":"Lausanne",
    "sg:orig_category":"Erbringung von Dienstleistungen f\u00fcr Unternehmen",
    "sg:phone":"+41 32 914 45 70",
    "sg:postcode":"1018",
    "sg:province":"Vaud",
    "wof:name":"Tabasco'm Bureau De Conception Graphique Et Publicitaire, Cattin & Faivre",
    "wof:placetype":"venue"
},
  "geometry": {"coordinates":[6.8270487785,47.1030044556],"type":"Point"}
}