{
  "type": "Feature",
  "properties": {
    "iso:country":"CH",
    "sg:address":"Rue Du Puits-godet 10a",
    "sg:city":"Neuch\u00e2tel",
    "sg:orig_category":"Grosshandel mit Holz U Baustoffen Herstellung von elektrischen Haushaltsger\u00e4ten",
    "sg:phone":"+41 32 729 30 30",
    "sg:postcode":"2000",
    "sg:province":"Neuch\u00e2tel",
    "wof:name":"Berosa Sa",
    "wof:placetype":"venue"
},
  "geometry": {"coordinates":[6.9133257866,46.9985961914],"type":"Point"}
}