{
  "type": "Feature",
  "properties": {
    "iso:country":"CH",
    "sg:address":"Niederweg 39",
    "sg:city":"Wettswil",
    "sg:orig_category":"Grosshandel mit B\u00fcromaschinen Grosshandel mit Datenverarbeitungsger\u00e4ten",
    "sg:phone":"+41 77785202",
    "sg:postcode":"8907",
    "sg:province":"Z\u00fcrich",
    "wof:name":"Softwink Informatik Jakob Winkler",
    "wof:placetype":"venue"
},
  "geometry": {"coordinates":[8.4760971069,47.3293190002],"type":"Point"}
}