{
  "type": "Feature",
  "properties": {
    "iso:country":"CH",
    "sg:address":"Dorfstrasse 9",
    "sg:city":"Gerzensee",
    "sg:orig_category":"RESTAURANTS: TEA-ROOMS",
    "sg:phone":"+41 31 781 14 21",
    "sg:postcode":"3115",
    "sg:province":"Bern",
    "wof:name":"Marilley-fankhauser Elisabeth Verena, Restaurant B\u00e4ren",
    "wof:placetype":"venue"
},
  "geometry": {"coordinates":[7.546631813,46.8395881653],"type":"Point"}
}