{
  "type": "Feature",
  "properties": {
    "iso:country":"CH",
    "sg:address":"Weissenburg",
    "sg:city":"D\u00e4rstetten",
    "sg:orig_category":"Verwertung von Milch",
    "sg:postcode":"3763",
    "sg:province":"Bern",
    "wof:name":"Milchverwertungsgenossenschaft Weissenburg",
    "wof:placetype":"venue"
},
  "geometry": {"coordinates":[7.4759049416,46.6686592102],"type":"Point"}
}