{
  "type": "Feature",
  "properties": {
    "iso:country":"CH",
    "sg:address":"Rondboisweg 5",
    "sg:city":"Ligerz",
    "sg:orig_category":"Rebbau",
    "sg:phone":"+41 32 315 21 26",
    "sg:postcode":"2514",
    "sg:province":"Bern",
    "wof:name":"Roger Bourquin Weinbau",
    "wof:placetype":"venue"
},
  "geometry": {"coordinates":[7.1422219276,47.092628479],"type":"Point"}
}