{
  "type": "Feature",
  "properties": {
    "iso:country":"CH",
    "sg:address":"Regensdorferstrasse 9 8049 Z\u00fcrich. Postfach",
    "sg:city":"Z\u00fcrich",
    "sg:orig_category":"Kinderg\u00e4rten, Vor U Grundschulen",
    "sg:phone":"+41 13410466",
    "sg:postcode":"8049",
    "sg:province":"Z\u00fcrich",
    "wof:name":"Kinderhaus Quelle Gmbh Tageskindergarten",
    "wof:placetype":"venue"
},
  "geometry": {"coordinates":[8.4985656738,47.4025764465],"type":"Point"}
}