{
  "type": "Feature",
  "properties": {
    "iso:country":"CH",
    "sg:address":"Bahnhofplatz 3 6370 Stans. Postfach 1243",
    "sg:city":"Stans",
    "sg:orig_category":"Verwaltung der Rechtspflege, Gerichte",
    "sg:phone":"+41 41 618 72 74",
    "sg:postcode":"6371",
    "sg:province":"Nidwalden",
    "wof:name":"Kant. Grundbuchamt & Notariat",
    "wof:placetype":"venue"
},
  "geometry": {"coordinates":[8.3670463562,46.9586791992],"type":"Point"}
}