{
  "type": "Feature",
  "properties": {
    "iso:country":"CH",
    "sg:address":"Dattenmattstrasse 21",
    "sg:city":"Kriens",
    "sg:orig_category":"Pensionskassen",
    "sg:phone":"+41 41 349 45 00",
    "sg:postcode":"6010",
    "sg:province":"Luzern",
    "wof:name":"Sealed Air Pensionskasse (bvg)",
    "wof:placetype":"venue"
},
  "geometry": {"coordinates":[8.301448822,47.0195655823],"type":"Point"}
}