{
  "type": "Feature",
  "properties": {
    "iso:country":"CH",
    "sg:address":"Bl\u00e4uistrasse 12",
    "sg:city":"Gersau",
    "sg:orig_category":"Organisationen des Gesundheitswesen",
    "sg:phone":"+41 41 828 11 85",
    "sg:postcode":"6442",
    "sg:province":"Schwyz",
    "wof:name":"Krankenpflegeverein",
    "wof:placetype":"venue"
},
  "geometry": {"coordinates":[8.5276975632,46.9943313599],"type":"Point"}
}