{
  "type": "Feature",
  "properties": {
    "iso:country":"CH",
    "sg:address":"Fabrikstrasse 7",
    "sg:city":"Herzogenbuchsee",
    "sg:orig_category":"Sonstiger spezialisierter Hoch U Tiefbau",
    "sg:phone":"+41 62 961 88 80",
    "sg:postcode":"3360",
    "sg:province":"Bern",
    "wof:name":"Christian D\u00fcbi Gmbh",
    "wof:placetype":"venue"
},
  "geometry": {"coordinates":[7.70414114,47.1886940002],"type":"Point"}
}