{
  "type": "Feature",
  "properties": {
    "iso:country":"CH",
    "sg:address":"Treitengasse 8",
    "sg:city":"M\u00fcntschemier",
    "sg:orig_category":"Gem\u00fcsebau",
    "sg:phone":"+41 32 313 18 64",
    "sg:postcode":"3225",
    "sg:province":"Bern",
    "wof:name":"Theodor L\u00f6ffel Gem\u00fcsebau",
    "wof:placetype":"venue"
},
  "geometry": {"coordinates":[7.1463098526,46.9962081909],"type":"Point"}
}