{
  "type": "Feature",
  "properties": {
    "iso:country":"CH",
    "sg:address":"Unterer Graben 21",
    "sg:city":"St.gallen",
    "sg:orig_category":"Betrieb von Taxis",
    "sg:phone":"+41 26 912 27 24",
    "sg:postcode":"9000",
    "sg:province":"St. Gallen",
    "wof:name":"A.a.a. Taxis, Savary",
    "wof:placetype":"venue"
},
  "geometry": {"coordinates":[7.066395,46.607971],"type":"Point"}
}