{
  "type": "Feature",
  "properties": {
    "iso:country":"CH",
    "sg:address":"Lienhard Rue Hermann- 54 2504 Biel/bienne. Postfach",
    "sg:city":"Biel/bienne",
    "sg:orig_category":"Erbringung von Dienstleistungen f\u00fcr Unternehmen",
    "sg:phone":"+41 32 342 15 32",
    "sg:postcode":"2504",
    "sg:province":"Bern",
    "wof:name":"S & H Design Schriften Lettres Gmbh",
    "wof:placetype":"venue"
},
  "geometry": {"coordinates":[7.2656559944,47.1526947021],"type":"Point"}
}