{
  "type": "Feature",
  "properties": {
    "iso:country":"CH",
    "sg:address":"Im Bilg",
    "sg:city":"Andelfingen",
    "sg:orig_category":"Unternehmensberatung",
    "sg:postcode":"8450",
    "sg:province":"Z\u00fcrich",
    "wof:name":"Sycolor Consulting Ag",
    "wof:placetype":"venue"
},
  "geometry": {"coordinates":[8.6870536804,47.5946846008],"type":"Point"}
}