{
  "type": "Feature",
  "properties": {
    "iso:country":"CH",
    "sg:address":"Hirschenweg 2",
    "sg:city":"Heerbrugg",
    "sg:orig_category":"Blumen U Zierpflanzenbau Detailhandel mit Blumen U Pflanzen",
    "sg:phone":"+41 71 722 32 28",
    "sg:postcode":"9435",
    "sg:province":"St. Gallen",
    "wof:name":"Blumen-m\u00fcller Ag",
    "wof:placetype":"venue"
},
  "geometry": {"coordinates":[9.631254,47.414661],"type":"Point"}
}