{
  "type": "Feature",
  "properties": {
    "iso:country":"CH",
    "sg:address":"Via Arbigo 6 6616 Losone. Postfach Caselle Postale 7002",
    "sg:city":"Losone",
    "sg:orig_category":"Detailhandel mit Zeitungen U Zeitschriften Kioske",
    "sg:phone":"+41 91 791 88 81",
    "sg:postcode":"6616",
    "sg:province":"Ticino",
    "wof:name":"Floriana Von Arx Edicola Arbigo",
    "wof:placetype":"venue"
},
  "geometry": {"coordinates":[8.7569561005,46.1707878113],"type":"Point"}
}