{
  "type": "Feature",
  "properties": {
    "iso:country":"CH",
    "sg:address":"Morgartenstrasse 2",
    "sg:city":"Bern",
    "sg:orig_category":"Vorschulen, Kinderg\u00e4rten",
    "sg:phone":"+41 31 332 64 24",
    "sg:postcode":"3014",
    "sg:province":"Bern",
    "wof:name":"Kindergarten Wankdorf I",
    "wof:placetype":"venue"
},
  "geometry": {"coordinates":[7.462375164,46.9640960693],"type":"Point"}
}