{
  "type": "Feature",
  "properties": {
    "iso:country":"CH",
    "sg:address":"Tannstrasse 17a",
    "sg:city":"Gerlafingen",
    "sg:orig_category":"Bauschreinerei Innenausbau",
    "sg:phone":"+41 79 311 76 31",
    "sg:postcode":"4563",
    "sg:province":"Solothurn",
    "wof:name":"Inbau & Plan",
    "wof:placetype":"venue"
},
  "geometry": {"coordinates":[7.586022,47.174294],"type":"Point"}
}