{
  "type": "Feature",
  "properties": {
    "iso:country":"CH",
    "sg:address":"Via Fleming 10",
    "sg:city":"Bellinzona",
    "sg:orig_category":"Detektivb\u00fcros U \u00dcberwachung",
    "sg:phone":"+41 91 825 50 23",
    "sg:postcode":"6500",
    "sg:province":"Ticino",
    "wof:name":"Agenzia Di Sicurezza Di Della Valle & Co",
    "wof:placetype":"venue"
},
  "geometry": {"coordinates":[9.019080162,46.1872367859],"type":"Point"}
}