{
  "type": "Feature",
  "properties": {
    "iso:country":"CH",
    "sg:address":"Fischmarkt 15",
    "sg:city":"Zug",
    "sg:orig_category":"Vermietung U Verpachtung von eigenen Immobilien",
    "sg:postcode":"6300",
    "sg:province":"Zug",
    "wof:name":"Fischmarkt Immobilien Ag",
    "wof:placetype":"venue"
},
  "geometry": {"coordinates":[8.5149993896,47.1661643982],"type":"Point"}
}