{
  "type": "Feature",
  "properties": {
    "iso:country":"CH",
    "sg:address":"Rue De La Gare 7 2720 Tramelan Case Postale",
    "sg:city":"Tramlingen",
    "sg:orig_category":"Pensionskassen",
    "sg:phone":"+41 21 634 13 07",
    "sg:postcode":"2720",
    "sg:province":"Bern",
    "wof:name":"Fonds De Pr\u00e9voyance En Faveur Du Personnel De La Soci\u00e9t\u00e9 Louis Pisoli Sa \u00e0 Renens",
    "wof:placetype":"venue"
},
  "geometry": {"coordinates":[6.5834240913,46.5390205383],"type":"Point"}
}