{
  "type": "Feature",
  "properties": {
    "iso:country":"CH",
    "sg:address":"Vieux-canal Chemin Du 4",
    "sg:city":"Sion",
    "sg:orig_category":"Betrieb von Taxis",
    "sg:postcode":"1950",
    "sg:province":"Valais",
    "wof:name":"Taxi Direct, Pierre Leuchter",
    "wof:placetype":"venue"
},
  "geometry": {"coordinates":[6.902648,46.982918],"type":"Point"}
}