{
  "type": "Feature",
  "properties": {
    "addr:full":"Chemin Du Repos 6 Petit-lancy Gen\u00e8ve 1213",
    "addr:housenumber":"6",
    "addr:postcode":"1213",
    "addr:street":"Chemin Du Repos",
    "iso:country":"CH",
    "sg:address":"Chemin Du Repos 6",
    "sg:city":"Petit-lancy",
    "sg:orig_category":"Arztpraxen",
    "sg:phone":"+41 22 757 34 64",
    "sg:postcode":"1213",
    "sg:province":"Gen\u00e8ve",
    "wof:name":"Dr M\u00e9d. Octavio Vilchez M\u00e9decin Sp\u00e9cialiste",
    "wof:placetype":"venue"
},
  "geometry": {"coordinates":[6.119698,46.19696],"type":"Point"}
}