{
  "type": "Feature",
  "properties": {
    "iso:country":"CH",
    "sg:address":"Plattenstrasse 11 8006 Z\u00fcrich. Postfach",
    "sg:city":"Z\u00fcrich",
    "sg:orig_category":"Universit\u00e4tsspit\u00e4ler, Spit\u00e4ler f\u00fcr allgemeine Pflege Zahnkliniken",
    "sg:phone":"+41 12696969",
    "sg:postcode":"8028",
    "wof:name":"Zahnmedizinisches Zentrum & Poliklinik",
    "wof:placetype":"venue"
},
  "geometry": {"coordinates":[8.5524940491,47.3747253418],"type":"Point"}
}