{
  "type": "Feature",
  "properties": {
    "iso:country":"CH",
    "sg:address":"Simplon Route Du 38",
    "sg:city":"Paudex",
    "sg:orig_category":"Reiseb\u00fcros U Reiseveranstalter",
    "sg:phone":"+41 21 791 42 43",
    "sg:postcode":"1094",
    "sg:province":"Vaud",
    "wof:name":"Voyages Personnalis\u00e9s, Aubert Jean-pierre",
    "wof:placetype":"venue"
},
  "geometry": {"coordinates":[6.6707677841,46.5058021545],"type":"Point"}
}