{
  "type": "Feature",
  "properties": {
    "iso:country":"CH",
    "sg:address":"R\u00fctistrasse 6",
    "sg:city":"Jona",
    "sg:orig_category":"Kongress- and Tagungshotels mit Restaurant",
    "sg:phone":"+41 34 461 15 10",
    "sg:postcode":"8645",
    "sg:province":"St. Gallen",
    "wof:name":"Gasthof Ochsen",
    "wof:placetype":"venue"
},
  "geometry": {"coordinates":[7.6849250793,47.0063858032],"type":"Point"}
}