{
  "type": "Feature",
  "properties": {
    "iso:country":"CH",
    "sg:address":"6612 Ascona. Postfach 466",
    "sg:city":"Ascona",
    "sg:orig_category":"Sportvereine Ballsport Fussball",
    "sg:phone":"+41 91 791 49 12",
    "sg:postcode":"6612",
    "sg:province":"Ticino",
    "wof:name":"As Verzaschesi",
    "wof:placetype":"venue"
},
  "geometry": {"coordinates":[8.7924995422,46.2998199463],"type":"Point"}
}