{
  "type": "Feature",
  "properties": {
    "iso:country":"CH",
    "sg:address":"Rue De L'h\u00f4tel-de-ville 16 2740 Montagne-moutier Case Postale 760",
    "sg:city":"Montagne-moutier",
    "sg:orig_category":"Reiseb\u00fcros U Reiseveranstalter",
    "sg:phone":"+41 32 493 18 24",
    "sg:postcode":"2740",
    "sg:province":"Bern",
    "wof:name":"Pro Jura, Association Jurassienne De Tourisme Et Agence De Voyages",
    "wof:placetype":"venue"
},
  "geometry": {"coordinates":[7.3704648018,47.2785072327],"type":"Point"}
}