{
  "type": "Feature",
  "properties": {
    "iso:country":"CH",
    "sg:address":"Route Mon-repos 5c",
    "sg:city":"Fribourg",
    "sg:orig_category":"Fachdetailhandel mit pharmazeutischen Produkten Sonstiger Fachdetailhandel mit Nahrungsmitteln, Getr",
    "sg:phone":"+41 26 481 53 55",
    "sg:postcode":"1700",
    "sg:province":"Fribourg",
    "wof:name":"Pharmacie-droguerie Du Levant",
    "wof:placetype":"venue"
},
  "geometry": {"coordinates":[7.1734428406,46.8089256287],"type":"Point"}
}