{
  "type": "Feature",
  "properties": {
    "iso:country":"CH",
    "sg:address":"Reinacherstrasse 129 4000 Basel. Postfach",
    "sg:city":"Basel",
    "sg:orig_category":"Herstellung von Teppichen",
    "sg:postcode":"4051",
    "sg:province":"Basel-Stadt",
    "wof:name":"Mmb Bodenbel\u00e4ge Ag",
    "wof:placetype":"venue"
},
  "geometry": {"coordinates":[7.6048340797,47.5353775024],"type":"Point"}
}