{
  "type": "Feature",
  "properties": {
    "addr:full":"Streitholzstrasse 7 Z\u00fcrich Z\u00fcrich 8057",
    "addr:housenumber":"7",
    "addr:postcode":"8057",
    "addr:street":"Streitholzstrasse",
    "iso:country":"CH",
    "sg:address":"Streitholzstrasse 7",
    "sg:city":"Z\u00fcrich",
    "sg:orig_category":"Architekturb\u00fcros",
    "sg:phone":"+41 13631825",
    "sg:postcode":"8057",
    "sg:province":"Z\u00fcrich",
    "wof:name":"Hanspeter R\u00e4ber Architekturb\u00fcro",
    "wof:placetype":"venue"
},
  "geometry": {"coordinates":[8.553064,47.398518],"type":"Point"}
}