{
  "type": "Feature",
  "properties": {
    "iso:country":"CH",
    "sg:address":"Dorf",
    "sg:city":"Boltigen",
    "sg:orig_category":"G\u00fcterbef\u00f6rderung im Strassenverkehr",
    "sg:phone":"+41 33 773 61 61",
    "sg:postcode":"3766",
    "sg:province":"Bern",
    "wof:name":"Werner Seewer Autotransporte",
    "wof:placetype":"venue"
},
  "geometry": {"coordinates":[7.3912000656,46.6292114258],"type":"Point"}
}