{
  "type": "Feature",
  "properties": {
    "iso:country":"CH",
    "sg:address":"7250",
    "sg:city":"Klosters",
    "sg:classifiers":[
        {
            "category":"Travel",
            "subcategory":"Hotels & Motels",
            "type":"Entertainment"
        }
    ],
    "sg:postcode":"7250",
    "sg:province":"Graubunden",
    "sg:tags":[
        "hotels",
        "mit",
        "restaurant"
    ],
    "wof:name":"Egon Burgener",
    "wof:placetype":"venue"
},
  "geometry": {"coordinates":[9.8801698685,46.8800392151],"type":"Point"}
}