{
  "type": "Feature",
  "properties": {
    "iso:country":"CH",
    "sg:address":"Piazza Orico 1 6500 Bellinzona. Postfach",
    "sg:city":"Bellinzona",
    "sg:orig_category":"Erwachsenenbildung U Unterricht",
    "sg:postcode":"6500",
    "sg:province":"Ticino",
    "wof:name":"English For You Sagl",
    "wof:placetype":"venue"
},
  "geometry": {"coordinates":[9.0184020996,46.1923828125],"type":"Point"}
}