{
  "type": "Feature",
  "properties": {
    "iso:country":"CH",
    "sg:address":"Rembuestrasse",
    "sg:city":"Susten",
    "sg:orig_category":"Herstellung von Teppichen Verlegen von Fussboden",
    "sg:phone":"+41 79 219 26 74",
    "sg:postcode":"3952",
    "sg:province":"Valais",
    "wof:name":"Erwin Metry Ag Unterlagsb\u00f6den",
    "wof:placetype":"venue"
},
  "geometry": {"coordinates":[7.6462550163,46.30651474],"type":"Point"}
}