{
  "type": "Feature",
  "properties": {
    "iso:country":"CH",
    "sg:address":"Chemin Des Deux-communes 12",
    "sg:city":"Th\u00f4nex",
    "sg:orig_category":"P\u00e9dicure",
    "sg:phone":"+41 22 349 02 43",
    "sg:postcode":"1226",
    "sg:province":"Gen\u00e8ve",
    "wof:name":"Chantal Emerit P\u00e9dicure",
    "wof:placetype":"venue"
},
  "geometry": {"coordinates":[6.2006001472,46.1937065125],"type":"Point"}
}