{
  "type": "Feature",
  "properties": {
    "iso:country":"CH",
    "sg:address":"Wiesenstrasse 8",
    "sg:city":"Balgach",
    "sg:orig_category":"S\u00e4ge, Hobel U Holzimpr\u00e4gnierwerke S\u00e4gewerke",
    "sg:phone":"+41 71 722 22 90",
    "sg:postcode":"9436",
    "sg:province":"St. Gallen",
    "wof:name":"Sutter S\u00e4gerei",
    "wof:placetype":"venue"
},
  "geometry": {"coordinates":[9.6036062241,47.404510498],"type":"Point"}
}