{
  "type": "Feature",
  "properties": {
    "iso:country":"CH",
    "sg:address":"Pfeffingerstrasse 47",
    "sg:city":"Basel",
    "sg:classifiers":[
        {
            "category":"Professional",
            "subcategory":"Art Services",
            "type":"Services"
        }
    ],
    "sg:phone":"+41 61 331 90 00",
    "sg:postcode":"4053",
    "sg:province":"Basel-Stadt",
    "sg:tags":[
        "homepage",
        "designing"
    ],
    "wof:name":"Agentur 2000",
    "wof:placetype":"venue"
},
  "geometry": {"coordinates":[7.5918731689,47.54429245],"type":"Point"}
}