{
  "type": "Feature",
  "properties": {
    "iso:country":"CH",
    "sg:address":"Ziegeleistrasse 8",
    "sg:city":"Frauenfeld",
    "sg:orig_category":"Zimmerei, Dachdeckerei, Bauspenglerei U Abdichtung",
    "sg:phone":"+41 52 730 05 60",
    "sg:postcode":"8500",
    "sg:province":"Thurgau",
    "wof:name":"Egloff & K\u00f6nig",
    "wof:placetype":"venue"
},
  "geometry": {"coordinates":[8.9032478333,47.5617523193],"type":"Point"}
}