{
  "type": "Feature",
  "properties": {
    "iso:country":"CH",
    "sg:address":"Via Alle Brere 6598 Tenero. Postfach",
    "sg:city":"Tenero",
    "sg:orig_category":"Reinigungsgewerbe",
    "sg:postcode":"6598",
    "sg:province":"Ticino",
    "wof:name":"Pulisan Di Pellegrini Leo Impresa Di Pulizia E Vendita Di Prodotti E Accessori Per L'igiene",
    "wof:placetype":"venue"
},
  "geometry": {"coordinates":[8.8559703827,46.1687393188],"type":"Point"}
}