{
  "type": "Feature",
  "properties": {
    "iso:country":"CH",
    "sg:address":"Place De La Palud 8",
    "sg:city":"Lausanne",
    "sg:orig_category":"Zahnarztpraxen",
    "sg:phone":"+41 21 312 21 54",
    "sg:postcode":"1003",
    "sg:province":"Vaud",
    "wof:name":"Dr M\u00e9d. Dent. Martine Cruchon M\u00e9decin-dentiste",
    "wof:placetype":"venue"
},
  "geometry": {"coordinates":[6.6324009895,46.5220413208],"type":"Point"}
}