{
  "type": "Feature",
  "properties": {
    "iso:country":"CH",
    "sg:address":"Kirschplatz 5",
    "sg:city":"Dietikon",
    "sg:classifiers":[
        {
            "category":"Professional",
            "subcategory":"Employment Agencies",
            "type":"Services"
        }
    ],
    "sg:postcode":"8953",
    "sg:province":"Z\u00fcrich",
    "sg:tags":[
        "personal",
        "u",
        "stellenvermittlung"
    ],
    "wof:name":"Adecco Human Resources Ag, Filiale Von Wohlen",
    "wof:placetype":"venue"
},
  "geometry": {"coordinates":[8.2765369415,47.3493309021],"type":"Point"}
}