{
  "type": "Feature",
  "properties": {
    "iso:country":"CH",
    "sg:address":"Rue Du Village 14",
    "sg:city":"Creux-de-genthod",
    "sg:orig_category":"Interessenvertretungen",
    "sg:postcode":"1294",
    "sg:province":"Gen\u00e8ve",
    "wof:name":"Fondation Les Corbillettes Pour L'aide Aux Handicap\u00e9s Mentaux",
    "wof:placetype":"venue"
},
  "geometry": {"coordinates":[6.1569690704,46.2634773254],"type":"Point"}
}