{
  "type": "Feature",
  "properties": {
    "iso:country":"CH",
    "sg:address":"Lessoc",
    "sg:city":"Lessoc",
    "sg:classifiers":[
        {
            "category":"Banks & Credit Unions",
            "subcategory":"Bank",
            "type":"Services"
        }
    ],
    "sg:phone":"+41 2981448",
    "sg:postcode":"1669",
    "sg:province":"Fribourg",
    "wof:name":"Banque Raiffeisen",
    "wof:placetype":"venue"
},
  "geometry": {"coordinates":[7.06147,46.504959],"type":"Point"}
}