{
  "type": "Feature",
  "properties": {
    "addr:full":"Dableten Dallenwil Nidwalden 6383",
    "addr:postcode":"6383",
    "iso:country":"CH",
    "sg:address":"Dableten",
    "sg:city":"Dallenwil",
    "sg:classifiers":[
        {
            "category":"Autos & Motor Vehicles",
            "subcategory":"Auto Supplies",
            "type":"Retail Goods"
        }
    ],
    "sg:phone":"+41 41 628 01 01",
    "sg:postcode":"6383",
    "sg:province":"Nidwalden",
    "sg:tags":[
        "automobile",
        "painting"
    ],
    "wof:name":"Niederberger Carrosserie & Fahrzeugbau",
    "wof:placetype":"venue"
},
  "geometry": {"coordinates":[8.392159,46.934395],"type":"Point"}
}