{
  "type": "Feature",
  "properties": {
    "addr:full":"Am Landsberg 9 Pf\u00e4ffikon Z\u00fcrich 8330",
    "addr:housenumber":"9",
    "addr:postcode":"8330",
    "addr:street":"Am Landsberg",
    "iso:country":"CH",
    "sg:address":"Am Landsberg 9",
    "sg:city":"Pf\u00e4ffikon",
    "sg:classifiers":[
        {
            "category":"Professional",
            "subcategory":"Engineering",
            "type":"Services"
        }
    ],
    "sg:phone":"+41 19500772",
    "sg:postcode":"8330",
    "sg:province":"Z\u00fcrich",
    "sg:tags":[
        "measurement",
        "technology",
        "automation"
    ],
    "wof:name":"Spirola Elektronik",
    "wof:placetype":"venue"
},
  "geometry": {"coordinates":[8.782165,47.37439],"type":"Point"}
}