{
  "type": "Feature",
  "properties": {
    "addr:full":"Wiesendamm 20 4057 Basel. Postfach Basel Basel-Stadt 4057",
    "addr:housenumber":"20",
    "addr:postcode":"4057;4057",
    "addr:street":"Wiesendamm;Postfach",
    "iso:country":"CH",
    "sg:address":"Wiesendamm 20 4057 Basel. Postfach",
    "sg:city":"Basel",
    "sg:orig_category":"Alters U Pflegeheime Wohnheime",
    "sg:phone":"+41 61 638 91 91",
    "sg:postcode":"4057",
    "sg:province":"Basel-Stadt",
    "wof:name":"Evangelische Stiftung Alterszentrum Wiesendamm",
    "wof:placetype":"venue"
},
  "geometry": {"coordinates":[7.592393,47.580841],"type":"Point"}
}