{
  "type": "Feature",
  "properties": {
    "iso:country":"CH",
    "sg:address":"Valleggia Via 21",
    "sg:city":"Breganzona",
    "sg:orig_category":"Elektroinstallation",
    "sg:phone":"+41 31 971 91 33",
    "sg:postcode":"6932",
    "sg:province":"Ticino",
    "wof:name":"Ffl Fluder Peter, Impresa Elettrica",
    "wof:placetype":"venue"
},
  "geometry": {"coordinates":[8.9341640472,46.0061416626],"type":"Point"}
}