{
  "type": "Feature",
  "properties": {
    "iso:country":"CH",
    "sg:address":"Birkenweg 780",
    "sg:city":"Gontenschwil",
    "sg:orig_category":"Architekturb\u00fcros",
    "sg:phone":"+41 62 773 19 14",
    "sg:postcode":"5728",
    "sg:province":"Aargau",
    "wof:name":"Herbert Bolliger Architekturb\u00fcro",
    "wof:placetype":"venue"
},
  "geometry": {"coordinates":[8.145874,47.27832],"type":"Point"}
}