{
  "type": "Feature",
  "properties": {
    "addr:full":"Im B\u00fchl Friltschen Thurgau 9504",
    "addr:postcode":"9504",
    "addr:street":"Im Buehl",
    "iso:country":"CH",
    "sg:address":"Im B\u00fchl",
    "sg:city":"Friltschen",
    "sg:orig_category":"Autogaragen",
    "sg:phone":"+41 71 655 14 32",
    "sg:postcode":"9504",
    "sg:province":"Thurgau",
    "wof:name":"Harry Balmer Autoservice",
    "wof:placetype":"venue"
},
  "geometry": {"coordinates":[9.084183,47.5396],"type":"Point"}
}