{
  "type": "Feature",
  "properties": {
    "iso:country":"CH",
    "sg:address":"3270",
    "sg:city":"Aarberg",
    "sg:orig_category":"Sonstiges Versicherungsgewerbe",
    "sg:postcode":"3270",
    "sg:province":"Bern",
    "wof:name":"Pferdeversicherungsgenossenschaft Aarberg",
    "wof:placetype":"venue"
},
  "geometry": {"coordinates":[7.2756547928,47.0425682068],"type":"Point"}
}