{
  "type": "Feature",
  "properties": {
    "iso:country":"CH",
    "sg:address":"Zelgliweg 16",
    "sg:city":"Nieder\u00f6nz",
    "sg:classifiers":[
        {
            "category":"Insurance",
            "subcategory":"Insurance Agent",
            "type":"Services"
        }
    ],
    "sg:phone":"+41 62 916 80 16",
    "sg:postcode":"3362",
    "sg:province":"Bern",
    "sg:tags":[
        "versicherungsagenturen",
        "-broker"
    ],
    "wof:name":"Elvia Versicherungen Agentur Ren\u00e9 Broder",
    "wof:placetype":"venue"
},
  "geometry": {"coordinates":[7.6919431686,47.1877098083],"type":"Point"}
}