{
  "type": "Feature",
  "properties": {
    "iso:country":"CH",
    "sg:address":"Am Rank",
    "sg:city":"Beggingen",
    "sg:orig_category":"Handelsvermittlung U Grosshandel",
    "sg:phone":"+41 52 680 18 52",
    "sg:postcode":"8228",
    "sg:province":"Schaffhausen",
    "wof:name":"Konrad Vogelsanger Landesprodukte Engros",
    "wof:placetype":"venue"
},
  "geometry": {"coordinates":[8.5380983353,47.7656593323],"type":"Point"}
}