{
  "type": "Feature",
  "properties": {
    "iso:country":"CH",
    "sg:address":"Zentrumsplatz 9",
    "sg:city":"Sch\u00f6nb\u00fchl-urtenen",
    "sg:orig_category":"W\u00e4scherei U chemische Reinigung",
    "sg:phone":"+41 31 859 45 85",
    "sg:postcode":"3322",
    "sg:province":"Bern",
    "wof:name":"Textilreinigung Suber U Glatt C. + A. Gygax",
    "wof:placetype":"venue"
},
  "geometry": {"coordinates":[7.4982118607,47.0201263428],"type":"Point"}
}