{
  "type": "Feature",
  "properties": {
    "iso:country":"CH",
    "sg:address":"Route De Lamboing",
    "sg:city":"Diesse",
    "sg:orig_category":"Herstellung von sonstigen landwirtschaftlichen Maschinen Instandhaltung U Reparatur von Automobilen",
    "sg:phone":"+41 32 315 21 61",
    "sg:postcode":"2517",
    "sg:province":"Bern",
    "wof:name":"Garage Des Rocs Sa",
    "wof:placetype":"venue"
},
  "geometry": {"coordinates":[7.1218400002,47.1143760681],"type":"Point"}
}