{
  "type": "Feature",
  "properties": {
    "iso:country":"CH",
    "sg:address":"Soodstrasse 20",
    "sg:city":"Oetwil",
    "sg:orig_category":"Buchverlag Verlagsgewerbe",
    "sg:phone":"+41 17470003",
    "sg:postcode":"8955",
    "sg:province":"Z\u00fcrich",
    "wof:name":"Sailer + Co, Mega Verlag",
    "wof:placetype":"venue"
},
  "geometry": {"coordinates":[8.40111,47.427601],"type":"Point"}
}