{
  "type": "Feature",
  "properties": {
    "iso:country":"CH",
    "sg:address":"Finkenweg 1 3303 Jegenstorf. Postfach",
    "sg:city":"Jegenstorf",
    "sg:orig_category":"Detailhandel mit elektrischen Haushalts-,Radio U Fernsehger\u00e4ten sowie Musikinstrumenten",
    "sg:phone":"+41 31 819 57 74",
    "sg:postcode":"3303",
    "sg:province":"Bern",
    "wof:name":"S\u00e4mi's Elektro Haushalt, Pf\u00e4ffli Samuel",
    "wof:placetype":"venue"
},
  "geometry": {"coordinates":[7.5077261925,47.0557785034],"type":"Point"}
}