{
  "type": "Feature",
  "properties": {
    "addr:full":"Via Balestra 18 Lugano Ticino 6900",
    "addr:housenumber":"18",
    "addr:postcode":"6900",
    "addr:street":"Via Balestra",
    "iso:country":"CH",
    "sg:address":"Via Balestra 18",
    "sg:city":"Lugano",
    "sg:classifiers":[
        {
            "category":"Banks & Credit Unions",
            "subcategory":"Bank",
            "type":"Services"
        }
    ],
    "sg:phone":"+41 91 923 54 59",
    "sg:postcode":"6900",
    "sg:province":"Ticino",
    "wof:name":"Ibz Investment Bank",
    "wof:placetype":"venue"
},
  "geometry": {"coordinates":[8.957781,46.007679],"type":"Point"}
}