{
  "type": "Feature",
  "properties": {
    "iso:country":"CH",
    "sg:address":"Weidenhofstrasse 1 9323 Steinach. Postfach 37",
    "sg:city":"Steinach",
    "sg:orig_category":"Herstellung von Werkzeugen",
    "sg:phone":"+41 71 446 38 55",
    "sg:postcode":"9323",
    "sg:province":"St. Gallen",
    "wof:name":"Manser Ag",
    "wof:placetype":"venue"
},
  "geometry": {"coordinates":[9.4445667267,47.5034179688],"type":"Point"}
}