{
  "type": "Feature",
  "properties": {
    "iso:country":"CH",
    "sg:address":"Avenue G\u00e9n\u00e9ral-guisan 46a 1009 Pully. Postfach",
    "sg:city":"Pully",
    "sg:orig_category":"Effektenvermittlung Broker",
    "sg:phone":"+41 79 202 52 44",
    "sg:postcode":"1009",
    "sg:province":"Vaud",
    "wof:name":"James Raymond & Associates Inc Agence En Bourse",
    "wof:placetype":"venue"
},
  "geometry": {"coordinates":[6.6483840942,46.5066108704],"type":"Point"}
}