{
  "type": "Feature",
  "properties": {
    "iso:country":"CH",
    "sg:address":"Leumattstrasse 31 6006 Luzern. Postfach",
    "sg:city":"Emmenbr\u00fccke",
    "sg:orig_category":"Sonstiger Grosshandel",
    "sg:phone":"+41 61 712 06 25",
    "sg:postcode":"6020",
    "sg:province":"Luzern",
    "wof:name":"Fossil Gallery Della Valle",
    "wof:placetype":"venue"
},
  "geometry": {"coordinates":[7.5898852348,47.4971427917],"type":"Point"}
}