{
  "type": "Feature",
  "properties": {
    "iso:country":"CH",
    "sg:address":"Z\u00fcrichstr. 28 8602 Wangen Zh. Postfach",
    "sg:city":"Br\u00fcttisellen",
    "sg:orig_category":"Wirtschaftspr\u00fcfung, Steuerberatung U Treuhand",
    "sg:postcode":"8306",
    "sg:province":"Z\u00fcrich",
    "wof:name":"Treuhand Und Verwaltungsb\u00fcro Margrit K\u00fcnzler-meier.",
    "wof:placetype":"venue"
},
  "geometry": {"coordinates":[8.6456451416,47.4106559753],"type":"Point"}
}