{
  "type": "Feature",
  "properties": {
    "iso:country":"CH",
    "sg:address":"Grendelstrasse 21",
    "sg:city":"Luzern",
    "sg:orig_category":"Unclassifiable Establishments",
    "sg:postcode":"6004",
    "sg:province":"Luzern",
    "wof:name":"Seltex Ag",
    "wof:placetype":"venue"
},
  "geometry": {"coordinates":[8.307056427,47.0533943176],"type":"Point"}
}