{
  "type": "Feature",
  "properties": {
    "iso:country":"CH",
    "sg:address":"1987",
    "sg:city":"H\u00e9r\u00e9mence",
    "sg:classifiers":[
        {
            "category":"Restaurant",
            "type":"Food & Drink"
        }
    ],
    "sg:phone":"+41 27 281 25 55",
    "sg:postcode":"1987",
    "sg:province":"Valais",
    "wof:name":"Caf\u00e9 Masses",
    "wof:placetype":"venue"
},
  "geometry": {"coordinates":[7.404665947,46.1833267212],"type":"Point"}
}