{
  "type": "Feature",
  "properties": {
    "iso:country":"CH",
    "sg:address":"Berthoudes Rue Des 62",
    "sg:city":"Neuch\u00e2tel",
    "sg:orig_category":"Sonstiger Grosshandel",
    "sg:phone":"+41 32 753 61 69",
    "sg:postcode":"2000",
    "sg:province":"Neuch\u00e2tel",
    "wof:name":"Saepa Weibel",
    "wof:placetype":"venue"
},
  "geometry": {"coordinates":[6.9648528099,47.0090065002],"type":"Point"}
}