{
  "type": "Feature",
  "properties": {
    "iso:country":"CH",
    "sg:address":"Asylweg 7",
    "sg:city":"Ilanz",
    "sg:orig_category":"Alters U Pflegeheime Institutionen f\u00fcr Behinderte",
    "sg:phone":"+41 71 243 32 32",
    "sg:postcode":"7130",
    "sg:province":"Graubunden",
    "wof:name":"Evang.pflegeheim Heiligkreuz",
    "wof:placetype":"venue"
},
  "geometry": {"coordinates":[9.394934,47.442017],"type":"Point"}
}