{
  "type": "Feature",
  "properties": {
    "iso:country":"CH",
    "sg:address":"Cordulaplatz 3 5400 Baden. Postfach 2136",
    "sg:city":"Baden",
    "sg:orig_category":"Wirtschaftspr\u00fcfung, Steuerberatung U Treuhand",
    "sg:phone":"+41 56 222 65 65",
    "sg:postcode":"5400",
    "sg:province":"Aargau",
    "wof:name":"M\u00fcller & Senn Treuhand Ag",
    "wof:placetype":"venue"
},
  "geometry": {"coordinates":[8.3066263199,47.4721183777],"type":"Point"}
}