{
  "type": "Feature",
  "properties": {
    "iso:country":"CH",
    "sg:address":"Zentrumstrasse 5",
    "sg:city":"Kleind\u00f6ttingen",
    "sg:orig_category":"Glaserei Grosshandel mit keramischen Erzeugnissen, Glaswaren U Reinigungsmitteln",
    "sg:phone":"+41 26 402 84 64",
    "sg:postcode":"5314",
    "sg:province":"Aargau",
    "wof:name":"Jean-louis Bulliard Sa",
    "wof:placetype":"venue"
},
  "geometry": {"coordinates":[7.120223999,46.8004188538],"type":"Point"}
}