{
  "type": "Feature",
  "properties": {
    "iso:country":"CH",
    "sg:address":"Birmensdorferstrasse 94 8003 Z\u00fcrich. Postfach",
    "sg:city":"Z\u00fcrich",
    "sg:orig_category":"Fachdetailhandel mit pharmazeutischen Produkten",
    "sg:phone":"+41 14634440",
    "sg:postcode":"8036",
    "sg:province":"Z\u00fcrich",
    "wof:name":"Elisabeth Balogh Schimmel-apotheke",
    "wof:placetype":"venue"
},
  "geometry": {"coordinates":[8.5227098465,47.3709182739],"type":"Point"}
}