{
  "type": "Feature",
  "properties": {
    "iso:country":"CH",
    "sg:address":"Affolternstrasse 15",
    "sg:city":"Regensdorf",
    "sg:orig_category":"Bauschreinerei Herstellung von Konstruktionsteilen, Fertigbauteilen U Ausbauelementen aus Holz",
    "sg:phone":"+41 18403090",
    "sg:postcode":"8105",
    "sg:province":"Z\u00fcrich",
    "wof:name":"Neeser M. + B.",
    "wof:placetype":"venue"
},
  "geometry": {"coordinates":[8.464726,47.429817],"type":"Point"}
}