{
  "type": "Feature",
  "properties": {
    "iso:country":"CH",
    "sg:address":"Rue Des Petits Epineys 3",
    "sg:city":"Martigny",
    "sg:orig_category":"Detailhandel mit Blumen U Pflanzen Fachdetailhandel in Verkaufsr\u00e4umen",
    "sg:phone":"+41 27 722 27 50",
    "sg:postcode":"1920",
    "sg:province":"Valais",
    "wof:name":"Genevi\u00e8ve Fleury Fleury-fleurs",
    "wof:placetype":"venue"
},
  "geometry": {"coordinates":[7.071514,46.100849],"type":"Point"}
}