{
  "type": "Feature",
  "properties": {
    "iso:country":"CH",
    "sg:address":"Tramstrasse 47",
    "sg:city":"Muttenz",
    "sg:orig_category":"Arztpraxen",
    "sg:phone":"+41 61 463 20 63",
    "sg:postcode":"4132",
    "sg:province":"Basel-Landschaft",
    "wof:name":"Dr.med. Roland Studer Spezialarzt Fmh",
    "wof:placetype":"venue"
},
  "geometry": {"coordinates":[7.641421,47.528526],"type":"Point"}
}