{
  "type": "Feature",
  "properties": {
    "iso:country":"CH",
    "sg:address":"Kerzersstrasse 22",
    "sg:city":"M\u00fcntschemier",
    "sg:orig_category":"Gem\u00fcsebau",
    "sg:phone":"+41 32 313 32 17",
    "sg:postcode":"3225",
    "sg:province":"Bern",
    "wof:name":"Hans Balmer Gem\u00fcsebau",
    "wof:placetype":"venue"
},
  "geometry": {"coordinates":[7.1492238045,46.9951972961],"type":"Point"}
}