{
  "type": "Feature",
  "properties": {
    "iso:country":"CH",
    "sg:address":"Rain 26",
    "sg:city":"Aarau",
    "sg:orig_category":"Detailhandel mit Damenbekleidung Detailhandel mit Herrenbekleidung",
    "sg:phone":"+41 19105559",
    "sg:postcode":"5000",
    "sg:province":"Aargau",
    "wof:name":"Day-the Style Damen-& Herrenmode",
    "wof:placetype":"venue"
},
  "geometry": {"coordinates":[8.5823364258,47.3176002502],"type":"Point"}
}