{
  "type": "Feature",
  "properties": {
    "addr:full":"Mattweg 2 Arlesheim Basel-Landschaft 4144",
    "addr:housenumber":"2",
    "addr:postcode":"4144",
    "addr:street":"Mattweg",
    "iso:country":"CH",
    "sg:address":"Mattweg 2",
    "sg:city":"Arlesheim",
    "sg:orig_category":"Detailhandel mit B\u00fcchern, Zeitungen, Schreib U Papeteriewaren Detailhandel mit Schreib U Papeteriewa",
    "sg:phone":"+41 61 701 45 20",
    "sg:postcode":"4144",
    "sg:province":"Basel-Landschaft",
    "wof:name":"Pico's Papeterie Gmbh Papeterie B\u00fcrobedarf",
    "wof:placetype":"venue"
},
  "geometry": {"coordinates":[7.619528,47.495197],"type":"Point"}
}