{
  "type": "Feature",
  "properties": {
    "iso:country":"CH",
    "sg:address":"Allschwilerstrasse 117 4055 Basel. Postfach Postfach 12",
    "sg:city":"Basel",
    "sg:orig_category":"Geb\u00e4ude, Wohnungsreinigung",
    "sg:phone":"+41 61 303 36 36",
    "sg:postcode":"4009",
    "sg:province":"Basel-Stadt",
    "wof:name":"Aborein Gmbh Geb\u00e4ude & Unterhaltsreinigung",
    "wof:placetype":"venue"
},
  "geometry": {"coordinates":[7.5668501854,47.5570869446],"type":"Point"}
}