{
  "type": "Feature",
  "properties": {
    "iso:country":"CH",
    "sg:address":"Reinacherstrasse 76",
    "sg:city":"Therwil",
    "sg:orig_category":"Softwareentwicklung U beratung",
    "sg:phone":"+41 61 721 13 93",
    "sg:postcode":"4106",
    "sg:province":"Basel-Landschaft",
    "wof:name":"Comps Assistant Melina & Co.",
    "wof:placetype":"venue"
},
  "geometry": {"coordinates":[7.5657820702,47.495891571],"type":"Point"}
}