{
  "type": "Feature",
  "properties": {
    "iso:country":"CH",
    "sg:address":"Route De Sion 1",
    "sg:city":"Sierre",
    "sg:orig_category":"Advokaturb\u00fcros Notariate",
    "sg:phone":"+41 27 455 57 47",
    "sg:postcode":"3960",
    "sg:province":"Valais",
    "wof:name":"Marcel-henri Gard Etude D'avocat & Notaire",
    "wof:placetype":"venue"
},
  "geometry": {"coordinates":[7.528131,46.291649],"type":"Point"}
}