{
  "type": "Feature",
  "properties": {
    "iso:country":"CH",
    "sg:address":"Schlossstrasse 99a 3008 Bern. Postfach",
    "sg:city":"Bern",
    "sg:orig_category":"Grosshandel mit Nahrungsmitteln, Getr\u00e4nken U Tabakwaren ohne ausgepr\u00e4gten Schwerpunkt",
    "sg:postcode":"3005",
    "sg:province":"Bern",
    "wof:name":"Tschannen, Hansrudolf. Handel M. Lebensmitteln",
    "wof:placetype":"venue"
},
  "geometry": {"coordinates":[7.4140748978,46.9439888],"type":"Point"}
}