{
  "type": "Feature",
  "properties": {
    "iso:country":"CH",
    "sg:address":"Tasberg 4",
    "sg:city":"St-ours",
    "sg:orig_category":"Herstellung von Metallkonstruktionen",
    "sg:postcode":"1717",
    "sg:province":"Fribourg",
    "wof:name":"Schaller Montagen",
    "wof:placetype":"venue"
},
  "geometry": {"coordinates":[7.2048897743,46.7954483032],"type":"Point"}
}