{
  "type": "Feature",
  "properties": {
    "addr:full":"Rebenstrasse 4 Arbon Thurgau 9320",
    "addr:housenumber":"4",
    "addr:postcode":"9320",
    "addr:street":"Rebenstrasse",
    "iso:country":"CH",
    "sg:address":"Rebenstrasse 4",
    "sg:city":"Arbon",
    "sg:orig_category":"Bezirks, Sekundar, Realschulen, Oberstufe der Primarschulen",
    "sg:phone":"+41 71 440 01 55",
    "sg:postcode":"9320",
    "sg:province":"Thurgau",
    "wof:name":"Realschule Rebenschulhaus",
    "wof:placetype":"venue"
},
  "geometry": {"coordinates":[9.433121,47.514771],"type":"Point"}
}