{
  "type": "Feature",
  "properties": {
    "iso:country":"CH",
    "sg:address":"Albricci Via Degli 7",
    "sg:city":"Chiasso",
    "sg:orig_category":"Grosshandel mit Nahrungsmitteln, Getr\u00e4nken U Tabakwaren ohne ausgepr\u00e4gten Schwerpunkt",
    "sg:postcode":"6830",
    "sg:province":"Ticino",
    "wof:name":"Escaluma Sagl",
    "wof:placetype":"venue"
},
  "geometry": {"coordinates":[9.0332317352,45.8343048096],"type":"Point"}
}