{
  "type": "Feature",
  "properties": {
    "iso:country":"CH",
    "sg:address":"Industrie Burgholz 3752 Wimmis. Postfach",
    "sg:city":"Wimmis",
    "sg:orig_category":"Herstellung von Kunststoffwaren Herstellung von Reiseartikeln, Leder U Sattlerwaren",
    "sg:phone":"+41 52 672 31 02",
    "sg:postcode":"3752",
    "sg:province":"Bern",
    "wof:name":"Tuchschmid & Merter Ag",
    "wof:placetype":"venue"
},
  "geometry": {"coordinates":[8.6046133041,47.6763458252],"type":"Point"}
}