{
  "type": "Feature",
  "properties": {
    "iso:country":"CH",
    "sg:address":"Obstgartenstrasse 25",
    "sg:city":"Thundorf",
    "sg:orig_category":"R\u00fcckgewinnung U Vorbereitung f\u00fcr die Wiederverwertung Recycling von nichtmetallischen Altmaterialien",
    "sg:phone":"+41 55 442 79 70",
    "sg:postcode":"8512",
    "sg:province":"Thurgau",
    "wof:name":"Abf Ag, Gesellschaft F\u00fcr Abfallverwertung, Biotop-management Und Fl\u00e4chenrecycling",
    "wof:placetype":"venue"
},
  "geometry": {"coordinates":[8.8567247391,47.1963386536],"type":"Point"}
}