{
  "type": "Feature",
  "properties": {
    "iso:country":"CH",
    "sg:address":"Badenerstrasse 649",
    "sg:city":"Z\u00fcrich",
    "sg:orig_category":"Grosshandel mit Erzen U Metallen Grosshandel mit Schmuck",
    "sg:phone":"+41 14320658",
    "sg:postcode":"8048",
    "sg:province":"Z\u00fcrich",
    "wof:name":"Luki Brigitte Lumor Import & Export",
    "wof:placetype":"venue"
},
  "geometry": {"coordinates":[8.489563942,47.3869056702],"type":"Point"}
}