{
  "type": "Feature",
  "properties": {
    "iso:country":"CH",
    "sg:address":"Mitteldorf 21",
    "sg:city":"Kallnach",
    "sg:orig_category":"Detailhandel mit Fleisch U Fleischwaren Verarbeitung von Milch",
    "sg:phone":"+41 32 392 14 08",
    "sg:postcode":"3283",
    "sg:province":"Bern",
    "wof:name":"Meyer Fritz",
    "wof:placetype":"venue"
},
  "geometry": {"coordinates":[7.2356262207,47.0191650391],"type":"Point"}
}