{
  "type": "Feature",
  "properties": {
    "iso:country":"CH",
    "sg:address":"S\u00e4gestrasse 39",
    "sg:city":"Dielsdorf",
    "sg:classifiers":[
        {
            "category":"Communications",
            "subcategory":"Television Station",
            "type":"Services"
        }
    ],
    "sg:phone":"+41 18533454",
    "sg:postcode":"8157",
    "sg:province":"Z\u00fcrich",
    "sg:tags":[
        "monitor"
    ],
    "wof:name":"Kaufmann B\u00fcrotechnik Ag",
    "wof:placetype":"venue"
},
  "geometry": {"coordinates":[8.4489622116,47.4825401306],"type":"Point"}
}