{
  "type": "Feature",
  "properties": {
    "addr:full":"Klingentalstrasse 4057 Basel. Postfach Basel Basel-Stadt 4057",
    "addr:postcode":"4057 basel. postfach;4057",
    "addr:street":"Klingentalstrasse",
    "iso:country":"CH",
    "sg:address":"Klingentalstrasse 4057 Basel. Postfach",
    "sg:city":"Basel",
    "sg:orig_category":"Unclassifiable Establishments",
    "sg:phone":"+41 61 691 66 50",
    "sg:postcode":"4057",
    "sg:province":"Basel-Stadt",
    "wof:name":"Druckerei Klingental Ag, Druck + Verlag.",
    "wof:placetype":"venue"
},
  "geometry": {"coordinates":[7.597565,47.5648],"type":"Point"}
}