{
  "type": "Feature",
  "properties": {
    "iso:country":"CH",
    "sg:address":"Eigenmatt 15",
    "sg:city":"Kaisten",
    "sg:orig_category":"Wirtschaftspr\u00fcfung, Steuerberatung U Treuhand",
    "sg:phone":"+41 62 874 28 28",
    "sg:postcode":"5082",
    "sg:province":"Aargau",
    "wof:name":"Treuhandb\u00fcro Della Ca D. L.",
    "wof:placetype":"venue"
},
  "geometry": {"coordinates":[8.0445327759,47.5359382629],"type":"Point"}
}