{
  "type": "Feature",
  "properties": {
    "iso:country":"CH",
    "sg:address":"Seestrasse 3",
    "sg:city":"Cham",
    "sg:orig_category":"Arztpraxen",
    "sg:phone":"+41 41 780 16 60",
    "sg:postcode":"6330",
    "sg:province":"Zug",
    "wof:name":"Dr.med.fredy Loretz Spezialarzt Fmh",
    "wof:placetype":"venue"
},
  "geometry": {"coordinates":[8.460314,47.180099],"type":"Point"}
}