{
  "type": "Feature",
  "properties": {
    "iso:country":"CH",
    "sg:address":"B\u00f6rtjihus",
    "sg:city":"Klosters",
    "sg:orig_category":"P\u00e9dicure",
    "sg:phone":"+41 19203702",
    "sg:postcode":"7250",
    "sg:province":"Graubunden",
    "wof:name":"Ruth Kr\u00e4henb\u00fchl P\u00e9dicure",
    "wof:placetype":"venue"
},
  "geometry": {"coordinates":[8.675909996,47.2667694092],"type":"Point"}
}