{
  "type": "Feature",
  "properties": {
    "iso:country":"CH",
    "sg:address":"Ziegelackerstr. 11",
    "sg:city":"Bern",
    "sg:orig_category":"Health - equipments and instruments Mechanical Engineering - machines Plastics Precision Equipment R",
    "sg:phone":"+41 52 742 01 00",
    "sg:postcode":"3027",
    "sg:province":"Bern",
    "wof:name":"Silcotech Ag",
    "wof:placetype":"venue"
},
  "geometry": {"coordinates":[8.8516578674,47.6515884399],"type":"Point"}
}