{
  "type": "Feature",
  "properties": {
    "iso:country":"CH",
    "sg:address":"Haus Don Bosco",
    "sg:city":"Zermatt",
    "sg:orig_category":"Solarien",
    "sg:phone":"+41 27 967 27 93",
    "sg:postcode":"3920",
    "sg:province":"Valais",
    "wof:name":"German Taugwalder Solarium Suomi",
    "wof:placetype":"venue"
},
  "geometry": {"coordinates":[7.7484002113,46.024143219],"type":"Point"}
}