{
  "type": "Feature",
  "properties": {
    "iso:country":"CH",
    "sg:address":"Unterdorfstrasse 19",
    "sg:city":"R\u00f6schenz",
    "sg:orig_category":"Nationale Postdienste",
    "sg:phone":"+41 71 944 15 07",
    "sg:postcode":"4244",
    "sg:province":"Basel-Landschaft",
    "wof:name":"Die Schweizerische Post",
    "wof:placetype":"venue"
},
  "geometry": {"coordinates":[9.1087656021,47.473815918],"type":"Point"}
}