{
  "type": "Feature",
  "properties": {
    "iso:country":"CH",
    "sg:address":"Le Village 5",
    "sg:city":"Bonnefontaine",
    "sg:orig_category":"Gemeindeverwaltungen",
    "sg:phone":"+41 26 413 10 41",
    "sg:postcode":"1729",
    "wof:name":"Administration Communale De Bonnefontaine",
    "wof:placetype":"venue"
},
  "geometry": {"coordinates":[7.2007398605,46.7404975891],"type":"Point"}
}