{
  "type": "Feature",
  "properties": {
    "iso:country":"CH",
    "sg:address":"Hofstrasse 72b 6300 Zug. Postfach 504",
    "sg:city":"Zug",
    "sg:classifiers":[
        {
            "category":"Professional",
            "subcategory":"Employment Agencies",
            "type":"Services"
        }
    ],
    "sg:phone":"+41 41 720 29 05",
    "sg:postcode":"6301",
    "sg:province":"Zug",
    "sg:tags":[
        "personal",
        "u",
        "stellenvermittlung"
    ],
    "wof:name":"Kley Consulting",
    "wof:placetype":"venue"
},
  "geometry": {"coordinates":[8.5139799118,47.1569480896],"type":"Point"}
}