{
  "type": "Feature",
  "properties": {
    "iso:country":"CH",
    "sg:address":"Place De La Palud 19",
    "sg:city":"Lausanne",
    "sg:classifiers":[
        {
            "category":"Travel",
            "subcategory":"Hotels & Motels",
            "type":"Entertainment"
        }
    ],
    "sg:phone":"+41 21 312 27 56",
    "sg:postcode":"1003",
    "sg:province":"Vaud",
    "sg:tags":[
        "hotels",
        "mit",
        "restaurant"
    ],
    "wof:name":"H\u00f4tel-caf\u00e9-restaurant Du Raisin Sa Restaurants, Caf\u00e9s, Bars, Tea-rooms, H\u00f4tels Etc",
    "wof:placetype":"venue"
},
  "geometry": {"coordinates":[6.6330099106,46.5219345093],"type":"Point"}
}