{
  "type": "Feature",
  "properties": {
    "iso:country":"CH",
    "sg:address":"Dr\u00f4ne",
    "sg:city":"Savi\u00e8se",
    "sg:orig_category":"Detailhandel mit M\u00f6beln",
    "sg:phone":"+41 27 395 13 25",
    "sg:postcode":"1965",
    "sg:province":"Valais",
    "wof:name":"Luyet Meubles",
    "wof:placetype":"venue"
},
  "geometry": {"coordinates":[7.3610739708,46.2553024292],"type":"Point"}
}