{
  "type": "Feature",
  "properties": {
    "iso:country":"CH",
    "sg:address":"Stutzstrasse 25",
    "sg:city":"Elgg",
    "sg:orig_category":"Allgemeiner Hoch U Tiefbau Strassenbau",
    "sg:phone":"+41 52 364 18 48",
    "sg:postcode":"8353",
    "sg:province":"Z\u00fcrich",
    "wof:name":"Lang Bauunternehmung Ag",
    "wof:placetype":"venue"
},
  "geometry": {"coordinates":[8.858686,47.500286],"type":"Point"}
}