{
  "type": "Feature",
  "properties": {
    "iso:country":"CH",
    "sg:address":"Lochm\u00fcliweg 11",
    "sg:city":"Gebenstorf",
    "sg:orig_category":"Instandhaltung U Reparatur von Automobilen",
    "sg:phone":"+41 56 223 52 88",
    "sg:postcode":"5412",
    "sg:province":"Aargau",
    "wof:name":"Ami-garage Sutter R.p.",
    "wof:placetype":"venue"
},
  "geometry": {"coordinates":[8.2430171967,47.4820365906],"type":"Point"}
}