{
  "type": "Feature",
  "properties": {
    "iso:country":"CH",
    "sg:address":"Loretto 12",
    "sg:city":"Gonten",
    "sg:orig_category":"G\u00fcterbef\u00f6rderung im Strassenverkehr",
    "sg:phone":"+41 71 794 14 06",
    "sg:postcode":"9108",
    "sg:province":"Appenzell Innerhoden",
    "wof:name":"Schnider Transport Ag",
    "wof:placetype":"venue"
},
  "geometry": {"coordinates":[9.3415336609,47.325176239],"type":"Point"}
}