{
  "type": "Feature",
  "properties": {
    "iso:country":"CH",
    "sg:address":"Landenbergstrasse 18",
    "sg:city":"Z\u00fcrich",
    "sg:orig_category":"Satzherstellung U Reproduktion",
    "sg:phone":"+41 18654496",
    "sg:postcode":"8037",
    "sg:province":"Z\u00fcrich",
    "wof:name":"Nap R.koller Film-& Viedoproduktionen",
    "wof:placetype":"venue"
},
  "geometry": {"coordinates":[8.528386116,47.392539978],"type":"Point"}
}