{
  "type": "Feature",
  "properties": {
    "iso:country":"CH",
    "sg:address":"Industriering 7",
    "sg:city":"Utzenstorf",
    "sg:orig_category":"G\u00fcterbef\u00f6rderung im Strassenverkehr R\u00fcckgewinnung U Vorbereitung f\u00fcr die Wiederverwertung Recycling",
    "sg:phone":"+41 71 282 50 82",
    "sg:postcode":"3427",
    "sg:province":"Bern",
    "wof:name":"Max M\u00fcller Ag Transporte & Entsorgung",
    "wof:placetype":"venue"
},
  "geometry": {"coordinates":[9.4249677658,47.4435958862],"type":"Point"}
}