{
  "type": "Feature",
  "properties": {
    "iso:country":"CH",
    "sg:address":"Badenerstrasse 731",
    "sg:city":"Z\u00fcrich",
    "sg:orig_category":"Grosshandel mit sonstigen Gebrauchs U Verbrauchsg\u00fctern",
    "sg:phone":"+41 14330200",
    "sg:postcode":"8048",
    "sg:province":"Z\u00fcrich",
    "wof:name":"Schenker Reklame Ag Schriften & Reklamegestaltung",
    "wof:placetype":"venue"
},
  "geometry": {"coordinates":[8.4809103012,47.3897209167],"type":"Point"}
}