{
  "type": "Feature",
  "properties": {
    "iso:country":"CH",
    "sg:address":"Carmenstrasse 52 8032 Z\u00fcrich. Postfach",
    "sg:city":"Z\u00fcrich",
    "sg:orig_category":"Markt U Meinungsforschung",
    "sg:phone":"+41 12589620",
    "sg:postcode":"8030",
    "wof:name":"Wacker Und Rosser Gmbh",
    "wof:placetype":"venue"
},
  "geometry": {"coordinates":[8.5640964508,47.3666038513],"type":"Point"}
}