{
  "type": "Feature",
  "properties": {
    "iso:country":"CH",
    "sg:address":"Chutzenweg 12",
    "sg:city":"Langendorf",
    "sg:orig_category":"Gymnastik U Fitnesszentren",
    "sg:phone":"+41 32 622 08 93",
    "sg:postcode":"4513",
    "sg:province":"Solothurn",
    "wof:name":"Brigitte Di Vito Fitness-center",
    "wof:placetype":"venue"
},
  "geometry": {"coordinates":[7.5094270706,47.2205047607],"type":"Point"}
}