{
  "type": "Feature",
  "properties": {
    "iso:country":"CH",
    "sg:address":"Johann Br\u00fcderlin-strasse 10",
    "sg:city":"Muttenz",
    "sg:orig_category":"Organisationen des Gesundheitswesen",
    "sg:phone":"+41 61 461 62 22",
    "sg:postcode":"4132",
    "sg:province":"Basel-Landschaft",
    "wof:name":"Samariterverein Muttenz",
    "wof:placetype":"venue"
},
  "geometry": {"coordinates":[7.6498970985,47.5271453857],"type":"Point"}
}