{
  "type": "Feature",
  "properties": {
    "iso:country":"CH",
    "sg:address":"Seestrasse 12a",
    "sg:city":"Uster",
    "sg:orig_category":"Elektroinstallation",
    "sg:phone":"+41 71 858 60 30",
    "sg:postcode":"8610",
    "sg:province":"Z\u00fcrich",
    "wof:name":"Ren\u00e9 Hummel Elektro/swisscom Partner",
    "wof:placetype":"venue"
},
  "geometry": {"coordinates":[9.50669384,47.4764900208],"type":"Point"}
}