{
  "type": "Feature",
  "properties": {
    "iso:country":"CH",
    "sg:address":"Route Des Cr\u00eates",
    "sg:city":"Veyras",
    "sg:orig_category":"Allgemeiner Hoch U Tiefbau Architekturb\u00fcros",
    "sg:phone":"+41 27 455 47 82",
    "sg:postcode":"3968",
    "sg:province":"Valais",
    "wof:name":"Pas Archi Services Sa",
    "wof:placetype":"venue"
},
  "geometry": {"coordinates":[7.540771,46.304073],"type":"Point"}
}