{
  "type": "Feature",
  "properties": {
    "iso:country":"CH",
    "sg:address":"Im F\u00e4rich 2",
    "sg:city":"Kirchlindach",
    "sg:orig_category":"Praxis f\u00fcr Atlaslogie",
    "sg:phone":"+41 31 829 39 37",
    "sg:postcode":"3038",
    "sg:province":"Bern",
    "wof:name":"Atlaslogie Joder",
    "wof:placetype":"venue"
},
  "geometry": {"coordinates":[7.4143028259,47.0024757385],"type":"Point"}
}