{
  "type": "Feature",
  "properties": {
    "addr:full":"6984 Pura Ticino 6984",
    "addr:housenumber":"6984",
    "addr:postcode":"6984",
    "addr:street":"Pura Ticino",
    "iso:country":"CH",
    "sg:address":"6984",
    "sg:city":"Pura",
    "sg:orig_category":"Allgemeiner Hoch U Tiefbau",
    "sg:phone":"+41 71 966 35 38",
    "sg:postcode":"6984",
    "sg:province":"Ticino",
    "wof:name":"Soro Sanierungen & Renovationen Sp\u00e4ti Roland",
    "wof:placetype":"venue"
},
  "geometry": {"coordinates":[8.994448,47.47958],"type":"Point"}
}