{
  "type": "Feature",
  "properties": {
    "iso:country":"CH",
    "sg:address":"Route De Rolle 44",
    "sg:city":"St-prex",
    "sg:orig_category":"Fuel Consumption Meters",
    "sg:phone":"+41 79 212 28 31",
    "sg:postcode":"1162",
    "sg:province":"Vaud",
    "wof:name":"Aic Systems Ag",
    "wof:placetype":"venue"
},
  "geometry": {"coordinates":[6.44562006,46.4775276184],"type":"Point"}
}