{
  "type": "Feature",
  "properties": {
    "iso:country":"CH",
    "sg:address":"4310",
    "sg:city":"Rheinfelden",
    "sg:orig_category":"Sportvereine Sch\u00fctzen Pistolen-& Gewehr",
    "sg:postcode":"4310",
    "sg:province":"Aargau",
    "wof:name":"Sch\u00fctzengesellschaft",
    "wof:placetype":"venue"
},
  "geometry": {"coordinates":[7.9498701096,47.5454216003],"type":"Point"}
}