{
  "type": "Feature",
  "properties": {
    "iso:country":"CH",
    "sg:address":"Herrengasse 30 3011 Bern. Postfach",
    "sg:city":"Bern",
    "sg:orig_category":"Detailhandel mit M\u00f6beln U Haushaltsgegenst\u00e4nden",
    "sg:phone":"+41 31 351 41 61",
    "sg:postcode":"3005",
    "sg:province":"Bern",
    "wof:name":"Max K\u00f6nig Erben Inhaber Patrick K\u00f6nig Teppiche, M\u00f6bel U Vorhangstoffe; Handel.",
    "wof:placetype":"venue"
},
  "geometry": {"coordinates":[7.4495139122,46.9472122192],"type":"Point"}
}