{
  "type": "Feature",
  "properties": {
    "iso:country":"CH",
    "sg:address":"B\u00f6sch 45",
    "sg:city":"H\u00fcnenberg",
    "sg:orig_category":"Detailhandel mit Schuhen U Lederwaren",
    "sg:phone":"+41 41 784 35 35",
    "sg:postcode":"6331",
    "sg:province":"Zug",
    "wof:name":"Kt Trading Ag",
    "wof:placetype":"venue"
},
  "geometry": {"coordinates":[8.4381799698,47.1616821289],"type":"Point"}
}