{
  "type": "Feature",
  "properties": {
    "iso:country":"CH",
    "sg:address":"Weststrasse 53",
    "sg:city":"Unter\u00e4geri",
    "sg:orig_category":"Wirtschaftspr\u00fcfung, Steuerberatung U Treuhand",
    "sg:phone":"+41 41 750 44 48",
    "sg:postcode":"6314",
    "sg:province":"Zug",
    "wof:name":"Buchhaltungs Und Dienstleistungsb\u00fcro, Cascioni Rinaldo",
    "wof:placetype":"venue"
},
  "geometry": {"coordinates":[8.5705728531,47.1371879578],"type":"Point"}
}