{
  "type": "Feature",
  "properties": {
    "iso:country":"CH",
    "sg:address":"Hauptstrasse 40 4528 Zuchwil. Postfach",
    "sg:city":"Zuchwil",
    "sg:orig_category":"Druck ohne Zeitungsdruck",
    "sg:phone":"+41 32 685 21 66",
    "sg:postcode":"4528",
    "sg:province":"Solothurn",
    "wof:name":"Buchdruckerei Fl\u00fcckiger, Inhaber R\u00f6\u00f6sli-meier Jos.",
    "wof:placetype":"venue"
},
  "geometry": {"coordinates":[7.556552887,47.2031822205],"type":"Point"}
}