{
  "type": "Feature",
  "properties": {
    "iso:country":"CH",
    "sg:address":"G\u00fcterstrasse 20",
    "sg:city":"Dietikon",
    "sg:orig_category":"G\u00fcterbef\u00f6rderung im Strassenverkehr",
    "sg:phone":"+41 17744101",
    "sg:postcode":"8953",
    "sg:province":"Z\u00fcrich",
    "wof:name":"Sch\u00e4li Transport Ag",
    "wof:placetype":"venue"
},
  "geometry": {"coordinates":[8.3938217163,47.4118728638],"type":"Point"}
}