{
  "type": "Feature",
  "properties": {
    "iso:country":"CH",
    "sg:address":"Buchental 2c",
    "sg:city":"Oberb\u00fcren",
    "sg:orig_category":"Instandhaltung U Reparatur von Automobilen",
    "sg:phone":"+41 71 951 54 45",
    "sg:postcode":"9245",
    "sg:province":"St. Gallen",
    "wof:name":"Pneu 2000 Gmbh",
    "wof:placetype":"venue"
},
  "geometry": {"coordinates":[9.154214859,47.4473266602],"type":"Point"}
}