{
  "type": "Feature",
  "properties": {
    "iso:country":"CH",
    "sg:address":"Avenue De La Gare 10",
    "sg:city":"Martigny",
    "sg:orig_category":"Spielsalons",
    "sg:phone":"+41 27 723 14 22",
    "sg:postcode":"1920",
    "sg:province":"Valais",
    "wof:name":"Billard Club-acad\u00e9mie",
    "wof:placetype":"venue"
},
  "geometry": {"coordinates":[7.0742092133,46.1022529602],"type":"Point"}
}