{
  "type": "Feature",
  "properties": {
    "iso:country":"CH",
    "sg:address":"Postgasse 27 8750 Glarus. Postfach",
    "sg:city":"Glarus",
    "sg:orig_category":"Advokaturb\u00fcros",
    "sg:phone":"+41 55 640 39 39",
    "sg:postcode":"8750",
    "sg:province":"Glarus",
    "wof:name":"Werner Marti Advokaturb\u00fcro",
    "wof:placetype":"venue"
},
  "geometry": {"coordinates":[9.067401,47.041435],"type":"Point"}
}