{
  "type": "Feature",
  "properties": {
    "iso:country":"CH",
    "sg:address":"Sennheimerstrasse 44",
    "sg:city":"Basel",
    "sg:orig_category":"Schlossereien",
    "sg:phone":"+41 61 301 70 92",
    "sg:postcode":"4054",
    "sg:province":"Basel-Stadt",
    "wof:name":"Ennio Unfer Schlosserei",
    "wof:placetype":"venue"
},
  "geometry": {"coordinates":[7.570125103,47.5541877747],"type":"Point"}
}