{
  "type": "Feature",
  "properties": {
    "iso:country":"CH",
    "sg:address":"Eichweg 4 6300 Zug. Postfach 2003",
    "sg:city":"Zug",
    "sg:orig_category":"Handelsvermittlung U Grosshandel Sonstiger Grosshandel",
    "sg:phone":"+41 41 761 17 31",
    "sg:postcode":"6302",
    "sg:province":"Zug",
    "wof:name":"Aimex Ag",
    "wof:placetype":"venue"
},
  "geometry": {"coordinates":[8.5233840942,47.1797714233],"type":"Point"}
}