{
  "type": "Feature",
  "properties": {
    "iso:country":"CH",
    "sg:address":"Rue Du Centre 18",
    "sg:city":"Gorgier",
    "sg:classifiers":[
        {
            "category":"Travel",
            "subcategory":"Hotels & Motels",
            "type":"Entertainment"
        }
    ],
    "sg:phone":"+41 79 458 11 12",
    "sg:postcode":"2023",
    "sg:province":"Neuch\u00e2tel",
    "sg:tags":[
        "hotels",
        "mit",
        "restaurant"
    ],
    "wof:name":"Braillard Blaise",
    "wof:placetype":"venue"
},
  "geometry": {"coordinates":[6.7807149887,46.902973175],"type":"Point"}
}