{
  "type": "Feature",
  "properties": {
    "iso:country":"CH",
    "sg:address":"Sch\u00fclen 6130 Willisau. Postfach",
    "sg:city":"Daiwil",
    "sg:orig_category":"Sonstiger Fachdetailhandel mit Nahrungsmitteln, Getr\u00e4nken U Tabak in Verkaufsr\u00e4umen",
    "sg:phone":"+41 41 480 31 33",
    "sg:postcode":"6126",
    "sg:province":"Luzern",
    "wof:name":"Sch\u00fclen-ch\u00e4si Ag",
    "wof:placetype":"venue"
},
  "geometry": {"coordinates":[7.997189045,47.107257843],"type":"Point"}
}