{
  "type": "Feature",
  "properties": {
    "iso:country":"CH",
    "sg:address":"Bahnhofstrasse 15 8852 Altendorf. Postfach",
    "sg:city":"Altendorf",
    "sg:orig_category":"Erwachsenenbildung U Unterricht",
    "sg:postcode":"8852",
    "sg:province":"Schwyz",
    "wof:name":"Humanagement F. Fluck",
    "wof:placetype":"venue"
},
  "geometry": {"coordinates":[8.5907030106,47.3136482239],"type":"Point"}
}