{
  "type": "Feature",
  "properties": {
    "iso:country":"CH",
    "sg:address":"Z\u00fcrichstrasse 131",
    "sg:city":"D\u00fcbendorf",
    "sg:orig_category":"Pensionskassen",
    "sg:phone":"+41 18016565",
    "sg:postcode":"8600",
    "sg:province":"Z\u00fcrich",
    "wof:name":"Wohlfahrtsfonds Der Ferrolegeringar Ag",
    "wof:placetype":"venue"
},
  "geometry": {"coordinates":[8.599439621,47.396068573],"type":"Point"}
}