{
  "type": "Feature",
  "properties": {
    "iso:country":"CH",
    "sg:address":"Matte 1110 3432 L\u00fctzelfl\u00fch-goldb. Postfach",
    "sg:city":"Ranfl\u00fch",
    "sg:orig_category":"Sonstiger spezialisierter Hoch U Tiefbau",
    "sg:postcode":"3439",
    "sg:province":"Bern",
    "wof:name":"Beck Kurt, Maurergesch\u00e4ft",
    "wof:placetype":"venue"
},
  "geometry": {"coordinates":[7.6784548759,47.0036315918],"type":"Point"}
}