{
  "type": "Feature",
  "properties": {
    "iso:country":"CH",
    "sg:address":"Tanneggerstrasse 30 8374 Dussnang. Postfach",
    "sg:city":"Dussnang",
    "sg:orig_category":"Herstellung von Pumpen U Kompressoren",
    "sg:phone":"+41 18510757",
    "sg:postcode":"8374",
    "sg:province":"Thurgau",
    "wof:name":"Werni's Gas Shop, W. Knell",
    "wof:placetype":"venue"
},
  "geometry": {"coordinates":[8.4947967529,47.4972114563],"type":"Point"}
}