{
  "type": "Feature",
  "properties": {
    "iso:country":"CH",
    "sg:address":"Schlossgasse 7",
    "sg:city":"M\u00fcnchenstein",
    "sg:orig_category":"Sonstige mit der Informatik verbundene T\u00e4tigkeiten",
    "sg:postcode":"4142",
    "sg:province":"Basel-Landschaft",
    "wof:name":"Matthias Widmer",
    "wof:placetype":"venue"
},
  "geometry": {"coordinates":[7.6211919785,47.5127487183],"type":"Point"}
}