{
  "type": "Feature",
  "properties": {
    "iso:country":"CH",
    "sg:address":"Gewerbestrasse 8",
    "sg:city":"Ibach",
    "sg:orig_category":"Bauschreinerei Detailhandel mit M\u00f6beln",
    "sg:phone":"+41 79 442 42 54",
    "sg:postcode":"6438",
    "sg:province":"Schwyz",
    "wof:name":"Othmar Von Rickenbach",
    "wof:placetype":"venue"
},
  "geometry": {"coordinates":[8.634135,47.012939],"type":"Point"}
}