{
  "type": "Feature",
  "properties": {
    "iso:country":"CH",
    "sg:address":"Rue Des P\u00eacheurs",
    "sg:city":"V\u00e9troz",
    "sg:orig_category":"Grosshandel mit Holz U Baustoffen",
    "sg:postcode":"1963",
    "sg:province":"Valais",
    "wof:name":"Vidal Antonio",
    "wof:placetype":"venue"
},
  "geometry": {"coordinates":[7.2819948196,46.2227096558],"type":"Point"}
}