{
  "type": "Feature",
  "properties": {
    "iso:country":"CH",
    "sg:address":"Via Brentani 10",
    "sg:city":"Lugano",
    "sg:orig_category":"Allgemeiner Hochbau Strassenbau",
    "sg:phone":"+41 91 793 16 01",
    "sg:postcode":"6900",
    "sg:province":"Ticino",
    "wof:name":"Forzoni Sa Impresa Di Costruzioni",
    "wof:placetype":"venue"
},
  "geometry": {"coordinates":[8.959753,46.018864],"type":"Point"}
}