{
  "type": "Feature",
  "properties": {
    "iso:country":"CH",
    "sg:address":"Rue Des Sugits 4",
    "sg:city":"Fleurier",
    "sg:orig_category":"Herstellung der Ausstattung von Uhren Herstellung von Uhren",
    "sg:phone":"+41 32 861 35 34",
    "sg:postcode":"2114",
    "sg:province":"Neuch\u00e2tel",
    "wof:name":"Sugitec Sa",
    "wof:placetype":"venue"
},
  "geometry": {"coordinates":[6.579679966,46.8995285034],"type":"Point"}
}