{
  "type": "Feature",
  "properties": {
    "iso:country":"CH",
    "sg:address":"St. Urbangasse 59",
    "sg:city":"Solothurn",
    "sg:orig_category":"Detailhandel mit Waren verschiedener Art, Hauptrichtung Nahrungsmittel Grosshandel mit Nahrungsmitte",
    "sg:phone":"+41 32 622 22 46",
    "sg:postcode":"4500",
    "sg:province":"Solothurn",
    "wof:name":"G\u00e4nterli Genossenschaft",
    "wof:placetype":"venue"
},
  "geometry": {"coordinates":[7.5365300179,47.2090263367],"type":"Point"}
}