{
  "type": "Feature",
  "properties": {
    "addr:full":"Hasenmoosstrasse 15 6023 Rothenburg. Postfach Buttisholz Luzern 6018",
    "addr:housenumber":"15",
    "addr:postcode":"6018",
    "addr:street":"Hasenmoosstrasse;6023 Rothenburg. Postfach",
    "iso:country":"CH",
    "sg:address":"Hasenmoosstrasse 15 6023 Rothenburg. Postfach",
    "sg:city":"Buttisholz",
    "sg:orig_category":"Allgemeiner Hoch U Tiefbau",
    "sg:phone":"+41 41 460 07 70",
    "sg:postcode":"6018",
    "sg:province":"Luzern",
    "wof:name":"Aregger Ag Buttisholz Zweigbetrieb Sempach",
    "wof:placetype":"venue"
},
  "geometry": {"coordinates":[8.223583,47.131149],"type":"Point"}
}