{
  "type": "Feature",
  "properties": {
    "iso:country":"CH",
    "sg:address":"Neugasse 7",
    "sg:city":"Kreuzlingen",
    "sg:orig_category":"Massagestudios",
    "sg:phone":"+41 71 672 45 58",
    "sg:postcode":"8280",
    "sg:province":"Thurgau",
    "wof:name":"Bellevue Massagen",
    "wof:placetype":"venue"
},
  "geometry": {"coordinates":[9.1694936752,47.6433677673],"type":"Point"}
}