{
  "type": "Feature",
  "properties": {
    "iso:country":"CH",
    "sg:address":"Fahrnstrasse 35 9402 M\u00f6rschwil. Postfach",
    "sg:city":"M\u00f6rschwil",
    "sg:orig_category":"Softwareentwicklung U beratung Unternehmensberatung",
    "sg:phone":"+41 19207530",
    "sg:postcode":"9402",
    "sg:province":"St. Gallen",
    "wof:name":"Innovatis Group Ag",
    "wof:placetype":"venue"
},
  "geometry": {"coordinates":[8.6811342239,47.2625961304],"type":"Point"}
}