{
  "type": "Feature",
  "properties": {
    "iso:country":"CH",
    "sg:address":"Feldeggstrasse 61",
    "sg:city":"Z\u00fcrich",
    "sg:classifiers":[
        {
            "category":"Banks & Credit Unions",
            "subcategory":"Bank",
            "type":"Services"
        }
    ],
    "sg:phone":"+41 13849100",
    "sg:postcode":"8008",
    "sg:province":"Z\u00fcrich",
    "sg:tags":[
        "services",
        "energy",
        "saving",
        "consulting"
    ],
    "wof:name":"Sutterl\u00fcti Ag",
    "wof:placetype":"venue"
},
  "geometry": {"coordinates":[8.5534801483,47.3609352112],"type":"Point"}
}