{
  "type": "Feature",
  "properties": {
    "iso:country":"CH",
    "sg:address":"Rue Des P\u00eacheurs 8",
    "sg:city":"Del\u00e9mont",
    "sg:orig_category":"Malerei",
    "sg:phone":"+41 62 822 21 81",
    "sg:postcode":"2800",
    "sg:province":"Jura",
    "wof:name":"Thomas B\u00f6ss Malergesch\u00e4ft",
    "wof:placetype":"venue"
},
  "geometry": {"coordinates":[8.0690040588,47.387550354],"type":"Point"}
}