{
  "type": "Feature",
  "properties": {
    "iso:country":"CH",
    "sg:address":"Industriestrasse 24",
    "sg:city":"Zug",
    "sg:orig_category":"Non-Classified Establishments",
    "sg:phone":"+41 41 790 53 32",
    "sg:postcode":"6300",
    "sg:province":"Zug",
    "wof:name":"Hoerbiger Holding Ag",
    "wof:placetype":"venue"
},
  "geometry": {"coordinates":[8.519452095,47.1751670837],"type":"Point"}
}