{
  "type": "Feature",
  "properties": {
    "iso:country":"CH",
    "sg:address":"Oberalpstrasse 78 4054 Basel. Postfach",
    "sg:city":"Basel",
    "sg:orig_category":"Detailhandel mit Schuhen U Lederwaren",
    "sg:phone":"+41 61 307 99 00",
    "sg:postcode":"4051",
    "sg:province":"Basel-Stadt",
    "wof:name":"Rudolf Schild Lederwaren Ag Basel Lederwaren; Herstellung U. Handel",
    "wof:placetype":"venue"
},
  "geometry": {"coordinates":[7.5639262199,47.5508270264],"type":"Point"}
}