{
  "type": "Feature",
  "properties": {
    "iso:country":"CH",
    "sg:address":"Heinrich Stutz-strasse 27",
    "sg:city":"Urdorf",
    "sg:orig_category":"Druckweiterverarbeitung",
    "sg:phone":"+41 14369010",
    "sg:postcode":"8902",
    "sg:province":"Z\u00fcrich",
    "wof:name":"Buchbinderei Scherrer Ag",
    "wof:placetype":"venue"
},
  "geometry": {"coordinates":[8.4261226654,47.3690567017],"type":"Point"}
}