{
  "type": "Feature",
  "properties": {
    "iso:country":"CH",
    "sg:address":"M\u00fchlestrasse 4 8157 Dielsdorf. Postfach 212",
    "sg:city":"Dielsdorf",
    "sg:orig_category":"Sonstige Institutionen des Sozialwesens ohne Beherbergung",
    "sg:phone":"+41 19326880",
    "sg:postcode":"8157",
    "sg:province":"Z\u00fcrich",
    "wof:name":"Beratungsstelle F\u00fcr Sucht-& Drogenfragen",
    "wof:placetype":"venue"
},
  "geometry": {"coordinates":[8.7985754013,47.3229904175],"type":"Point"}
}