{
  "type": "Feature",
  "properties": {
    "iso:country":"CH",
    "sg:address":"Pierre Rue Saint- 3",
    "sg:city":"Fribourg",
    "sg:orig_category":"Unclassifiable Establishments",
    "sg:phone":"+41 26 321 26 26",
    "sg:postcode":"1700",
    "sg:province":"Fribourg",
    "wof:name":"Floor Communications S\u00e0rl Informatiques, En Partic. Dans Les Dom. Internet Etc.; Conseils, Services, D\u00e9velopp.",
    "wof:placetype":"venue"
},
  "geometry": {"coordinates":[7.1546449661,46.8038215637],"type":"Point"}
}