{
  "type": "Feature",
  "properties": {
    "iso:country":"CH",
    "sg:address":"Place Grand-st-jean 2",
    "sg:city":"Lausanne",
    "sg:orig_category":"Detailhandel mit Bekleidung Detailhandel mit Herrenbekleidung",
    "sg:phone":"+41 21 312 24 86",
    "sg:postcode":"1003",
    "sg:province":"Vaud",
    "wof:name":"Anita Agn\u00e9us Alex & Lancelot Mode Masculine",
    "wof:placetype":"venue"
},
  "geometry": {"coordinates":[6.631182,46.521694],"type":"Point"}
}