{
  "type": "Feature",
  "properties": {
    "iso:country":"CH",
    "sg:address":"Rue De La Paix 2",
    "sg:city":"Lausanne",
    "sg:orig_category":"Unternehmensberatung",
    "sg:phone":"+41 56 622 00 54",
    "sg:postcode":"1003",
    "sg:province":"Vaud",
    "wof:name":"Swiso Gmbh",
    "wof:placetype":"venue"
},
  "geometry": {"coordinates":[8.2733926773,47.3504066467],"type":"Point"}
}