{
  "type": "Feature",
  "properties": {
    "iso:country":"CH",
    "sg:address":"Rue Centrale 27",
    "sg:city":"Lausanne",
    "sg:orig_category":"Detailhandel mit Metallwaren, Anstrichmitteln, Glaswaren, Bau U Heimwerkerbedarf Detailhandel mit Sp",
    "sg:phone":"+41 21 312 14 68",
    "sg:postcode":"1003",
    "sg:province":"Vaud",
    "wof:name":"Technic Hobby, Marchand & Carrard",
    "wof:placetype":"venue"
},
  "geometry": {"coordinates":[6.6355009079,46.5210456848],"type":"Point"}
}