{
  "type": "Feature",
  "properties": {
    "iso:country":"CH",
    "sg:address":"Heuweg",
    "sg:city":"R\u00fcedisbach",
    "sg:orig_category":"Bauschreinerei Innenausbau",
    "sg:phone":"+41 34 415 17 51",
    "sg:postcode":"3474",
    "sg:province":"Bern",
    "wof:name":"Schreinerei Widmer Hansruedi",
    "wof:placetype":"venue"
},
  "geometry": {"coordinates":[7.702974,47.119553],"type":"Point"}
}