{
  "type": "Feature",
  "properties": {
    "iso:country":"CH",
    "sg:address":"Konstanzerstrasse 37",
    "sg:city":"T\u00e4gerwilen",
    "sg:orig_category":"Softwareentwicklung U beratung",
    "sg:phone":"+41 71 669 33 69",
    "sg:postcode":"8274",
    "sg:province":"Thurgau",
    "wof:name":"1a Informatik Gmbh",
    "wof:placetype":"venue"
},
  "geometry": {"coordinates":[9.1374349594,47.660068512],"type":"Point"}
}