{
  "type": "Feature",
  "properties": {
    "iso:country":"CH",
    "sg:address":"Chemin Des Clochettes 14 1200 Genf. Postfach",
    "sg:city":"Gen\u00e8ve",
    "sg:orig_category":"Datenbanken",
    "sg:phone":"+41 61 717 88 33",
    "sg:postcode":"1201",
    "sg:province":"Gen\u00e8ve",
    "wof:name":"Probase Gmbh",
    "wof:placetype":"venue"
},
  "geometry": {"coordinates":[7.600496,47.487083],"type":"Point"}
}