{
  "type": "Feature",
  "properties": {
    "iso:country":"CH",
    "sg:address":"Rheingasse 52 4058 Basel. Postfach",
    "sg:city":"Basel",
    "sg:orig_category":"Pensionskassen",
    "sg:postcode":"4051",
    "sg:province":"Basel-Stadt",
    "wof:name":"Previfond",
    "wof:placetype":"venue"
},
  "geometry": {"coordinates":[11.2962017059,45.2679977417],"type":"Point"}
}