{
  "type": "Feature",
  "properties": {
    "iso:country":"CH",
    "sg:address":"Kirchstrasse 64",
    "sg:city":"Rorschach",
    "sg:classifiers":[
        {
            "category":"Restaurant",
            "type":"Food & Drink"
        }
    ],
    "sg:phone":"+41 52 672 53 66",
    "sg:postcode":"9400",
    "sg:province":"St. Gallen",
    "wof:name":"Restaurant Metropol",
    "wof:placetype":"venue"
},
  "geometry": {"coordinates":[8.6219062805,47.6840209961],"type":"Point"}
}