{
  "type": "Feature",
  "properties": {
    "iso:country":"CH",
    "sg:address":"Tschuppina",
    "sg:city":"Breil/brigels",
    "sg:orig_category":"RESTAURANTS: TEA-ROOMS",
    "sg:phone":"+41 81 941 22 53",
    "sg:postcode":"7165",
    "sg:province":"Graubunden",
    "wof:name":"Cavegn Daniel",
    "wof:placetype":"venue"
},
  "geometry": {"coordinates":[9.0636920929,46.7676582336],"type":"Point"}
}