{
  "type": "Feature",
  "properties": {
    "iso:country":"CH",
    "sg:address":"Rue De La Porte-neuve 9",
    "sg:city":"Sion",
    "sg:classifiers":[
        {
            "category":"Travel",
            "subcategory":"Hotels & Motels",
            "type":"Entertainment"
        }
    ],
    "sg:postcode":"1950",
    "sg:province":"Valais",
    "sg:tags":[
        "hotels",
        "mit",
        "restaurant"
    ],
    "wof:name":"Sigmund Walter",
    "wof:placetype":"venue"
},
  "geometry": {"coordinates":[7.3606858253,46.2325744629],"type":"Point"}
}