{
  "type": "Feature",
  "properties": {
    "iso:country":"CH",
    "sg:address":"Burgenrain 3",
    "sg:city":"Villnachern",
    "sg:orig_category":"Non-Classified Establishments",
    "sg:postcode":"5213",
    "sg:province":"Aargau",
    "wof:name":"Killer Tankrevisionen Gmbh",
    "wof:placetype":"venue"
},
  "geometry": {"coordinates":[8.1650667191,47.4710617065],"type":"Point"}
}