{
  "type": "Feature",
  "properties": {
    "iso:country":"CH",
    "sg:address":"Viale Cantine 30",
    "sg:city":"Mendrisio",
    "sg:classifiers":[
        {
            "category":"Restaurant",
            "type":"Food & Drink"
        }
    ],
    "sg:phone":"+41 91 646 53 12",
    "sg:postcode":"6850",
    "sg:province":"Ticino",
    "wof:name":"Grotto San Martino",
    "wof:placetype":"venue"
},
  "geometry": {"coordinates":[8.9869470596,45.879486084],"type":"Point"}
}