{
  "type": "Feature",
  "properties": {
    "iso:country":"CH",
    "sg:address":"Alte Steinhauserstrasse 1",
    "sg:city":"Cham",
    "sg:classifiers":[
        {
            "category":"Banks & Credit Unions",
            "subcategory":"Financial Services",
            "type":"Services"
        }
    ],
    "sg:phone":"+41 41 748 62 00",
    "sg:postcode":"6330",
    "sg:province":"Zug",
    "sg:tags":[
        "industry"
    ],
    "wof:name":"Abt Treuhandgesellschaft Andreas Baumann & Co",
    "wof:placetype":"venue"
},
  "geometry": {"coordinates":[8.4739131927,47.1866035461],"type":"Point"}
}