{
  "type": "Feature",
  "properties": {
    "iso:country":"CH",
    "sg:address":"Forstweg 16 3600 Thun. Postfach",
    "sg:city":"Thun",
    "sg:orig_category":"Reinigungsgewerbe",
    "sg:postcode":"3603",
    "sg:province":"Bern",
    "wof:name":"Berger Armin, Hauswartungen",
    "wof:placetype":"venue"
},
  "geometry": {"coordinates":[7.5975389481,46.7654724121],"type":"Point"}
}