{
  "type": "Feature",
  "properties": {
    "iso:country":"CH",
    "sg:address":"Plattenstrasse 27",
    "sg:city":"Glattbrugg",
    "sg:orig_category":"Vereine Gesang Vereine Gesang and Jodler",
    "sg:phone":"+41 17640194",
    "sg:postcode":"8152",
    "sg:province":"Z\u00fcrich",
    "wof:name":"Jodlerverband Nosjv",
    "wof:placetype":"venue"
},
  "geometry": {"coordinates":[8.5325202942,47.2461013794],"type":"Point"}
}