{
  "type": "Feature",
  "properties": {
    "iso:country":"CH",
    "sg:address":"H\u00f6henweg 9",
    "sg:city":"Pratteln",
    "sg:orig_category":"Sportvereine Turnen Vereine Damen",
    "sg:phone":"+41 61 821 29 46",
    "sg:postcode":"4133",
    "sg:province":"Basel-Landschaft",
    "wof:name":"Damenriege Alte Sektion",
    "wof:placetype":"venue"
},
  "geometry": {"coordinates":[7.6954088211,47.5143508911],"type":"Point"}
}