{
  "type": "Feature",
  "properties": {
    "iso:country":"CH",
    "sg:address":"Hauptstrasse 17",
    "sg:city":"D\u00f6ttingen",
    "sg:orig_category":"Detailhandel mit Waren verschiedener Art, Hauptrichtung Nahrungsmittel",
    "sg:phone":"+41 56 245 15 55",
    "sg:postcode":"5312",
    "sg:province":"Aargau",
    "wof:name":"Migros-markt",
    "wof:placetype":"venue"
},
  "geometry": {"coordinates":[8.2558927536,47.5740432739],"type":"Point"}
}