{
  "type": "Feature",
  "properties": {
    "iso:country":"CH",
    "sg:address":"Fl\u00e4cke 18 6215 Berom\u00fcnster. Postfach",
    "sg:city":"Berom\u00fcnster",
    "sg:orig_category":"RESTAURANTS: TEA-ROOMS",
    "sg:phone":"+41 79 688 54 23",
    "sg:postcode":"6215",
    "sg:province":"Luzern",
    "wof:name":"Felix Josef, Restaurant Rosengarten, Berom\u00fcnster",
    "wof:placetype":"venue"
},
  "geometry": {"coordinates":[8.1914796829,47.2064247131],"type":"Point"}
}