{
  "type": "Feature",
  "properties": {
    "iso:country":"CH",
    "sg:address":"Hauptstrasse 18",
    "sg:city":"Wimmis",
    "sg:orig_category":"Instandhaltung U Reparatur von Automobilen",
    "sg:phone":"+41 33 657 17 71",
    "sg:postcode":"3752",
    "sg:province":"Bern",
    "wof:name":"Peter Iseli",
    "wof:placetype":"venue"
},
  "geometry": {"coordinates":[7.6371622086,46.6747055054],"type":"Point"}
}