{
  "type": "Feature",
  "properties": {
    "iso:country":"CH",
    "sg:address":"4524",
    "sg:city":"G\u00fcnsberg",
    "sg:orig_category":"Landesverteidigung, Sozialversicherung \u00d6ffentliche Verwaltung",
    "sg:phone":"+41 32 637 15 34",
    "sg:postcode":"4524",
    "sg:province":"Solothurn",
    "wof:name":"Zivilschutzstelle Kammersrohr",
    "wof:placetype":"venue"
},
  "geometry": {"coordinates":[7.5764451027,47.2574691772],"type":"Point"}
}