{
  "type": "Feature",
  "properties": {
    "iso:country":"CH",
    "sg:address":"Alkerenweg 23",
    "sg:city":"Worben",
    "sg:orig_category":"Hoch U Tiefbau",
    "sg:phone":"+41 32 384 25 84",
    "sg:postcode":"3252",
    "sg:province":"Bern",
    "wof:name":"E. Hofer & Co Ag Bauunternehmung",
    "wof:placetype":"venue"
},
  "geometry": {"coordinates":[7.2862410545,47.0967292786],"type":"Point"}
}