{
  "type": "Feature",
  "properties": {
    "iso:country":"CH",
    "sg:address":"Avenue De Tourbillon 68",
    "sg:city":"Sion",
    "sg:orig_category":"Softwareentwicklung U beratung Sonstige mit der Informatik verbundene T\u00e4tigkeiten",
    "sg:phone":"+41 79 422 84 74",
    "sg:postcode":"1950",
    "sg:province":"Valais",
    "wof:name":"Computer Blitz Hitz",
    "wof:placetype":"venue"
},
  "geometry": {"coordinates":[8.0745306015,47.3861656189],"type":"Point"}
}