{
  "type": "Feature",
  "properties": {
    "iso:country":"CH",
    "sg:address":"Kaisterstrasse 3 5080 Laufenburg. Postfach",
    "sg:city":"Laufenburg",
    "sg:orig_category":"Grosshandel mit Holz U Baustoffen",
    "sg:phone":"+41 62 869 41 11",
    "sg:postcode":"5080",
    "sg:province":"Aargau",
    "wof:name":"Balteschwiler Ag",
    "wof:placetype":"venue"
},
  "geometry": {"coordinates":[8.0587644577,47.5573616028],"type":"Point"}
}