{
  "type": "Feature",
  "properties": {
    "iso:country":"CH",
    "sg:address":"Lerchenb\u00fchlstrasse 10",
    "sg:city":"Meggen",
    "sg:orig_category":"Arztpraxen",
    "sg:phone":"+41 41 377 31 93",
    "sg:postcode":"6045",
    "sg:province":"Luzern",
    "wof:name":"Dr.med.adolf Bucher Arzt F.allgemeine Medizin Fmh",
    "wof:placetype":"venue"
},
  "geometry": {"coordinates":[8.361327,47.041267],"type":"Point"}
}