{
  "type": "Feature",
  "properties": {
    "iso:country":"CH",
    "sg:address":"Weissensteinweg 9",
    "sg:city":"Meinisberg",
    "sg:orig_category":"Vermietung U Verpachtung von eigenen Immobilien Vermittlung von Immobilien",
    "sg:phone":"+41 32 378 12 03",
    "sg:postcode":"2554",
    "sg:province":"Bern",
    "wof:name":"Sar Serge A. Rubitschung Immobilien Und Anlageberatung",
    "wof:placetype":"venue"
},
  "geometry": {"coordinates":[7.346323967,47.1571159363],"type":"Point"}
}