{
  "type": "Feature",
  "properties": {
    "iso:country":"CH",
    "sg:address":"Pizol",
    "sg:city":"Wangs",
    "sg:classifiers":[
        {
            "category":"Travel",
            "subcategory":"Hotels & Motels",
            "type":"Entertainment"
        }
    ],
    "sg:phone":"+41 81 723 17 91",
    "sg:postcode":"7323",
    "sg:province":"St. Gallen",
    "sg:tags":[
        "hotels",
        "mit",
        "restaurant"
    ],
    "wof:name":"Berghaus Baschalva",
    "wof:placetype":"venue"
},
  "geometry": {"coordinates":[9.4329013824,47.0280418396],"type":"Point"}
}