{
  "type": "Feature",
  "properties": {
    "iso:country":"CH",
    "sg:address":"Bahnhofstrasse 4",
    "sg:city":"Aarau",
    "sg:orig_category":"RESTAURANTS: TEA-ROOMS",
    "sg:postcode":"5000",
    "sg:province":"Aargau",
    "wof:name":"Grognuz Fr\u00e8res",
    "wof:placetype":"venue"
},
  "geometry": {"coordinates":[6.8569989204,46.4531364441],"type":"Point"}
}