{
  "type": "Feature",
  "properties": {
    "iso:country":"CH",
    "sg:address":"Rte De S\u00e9cheron 4",
    "sg:city":"Conthey",
    "sg:classifiers":[
        {
            "category":"Professional",
            "subcategory":"Engineering",
            "type":"Services"
        }
    ],
    "sg:phone":"+41 27 345 47 00",
    "sg:postcode":"1964",
    "sg:province":"Valais",
    "sg:tags":[
        "machine",
        "-",
        "mechanical"
    ],
    "wof:name":"H. M\u00dcller Fabrique De Moules Sa",
    "wof:placetype":"venue"
},
  "geometry": {"coordinates":[7.2926988602,46.2151985168],"type":"Point"}
}