{
  "type": "Feature",
  "properties": {
    "iso:country":"CH",
    "sg:address":"Br\u00fcckfeldstrasse 26",
    "sg:city":"Bern",
    "sg:orig_category":"Sanit\u00e4r U Heizungsinstallation Sanit\u00e4r, Heizungs U L\u00fcftungsinstallation",
    "sg:phone":"+41 31 301 24 24",
    "sg:postcode":"3012",
    "sg:province":"Bern",
    "wof:name":"Rowy Heizungen Gmbh",
    "wof:placetype":"venue"
},
  "geometry": {"coordinates":[7.4355349541,46.9566879272],"type":"Point"}
}