{
  "type": "Feature",
  "properties": {
    "addr:full":"Burghaldenweg 5 Zurzach Aargau 5330",
    "addr:housenumber":"5",
    "addr:postcode":"5330",
    "addr:street":"Burghaldenweg",
    "iso:country":"CH",
    "sg:address":"Burghaldenweg 5",
    "sg:city":"Zurzach",
    "sg:orig_category":"Detailhandel mit Antiquit\u00e4ten",
    "sg:phone":"+41 17503069",
    "sg:postcode":"5330",
    "sg:province":"Aargau",
    "wof:name":"Inge Peyer Antiquit\u00e4ten Boutique",
    "wof:placetype":"venue"
},
  "geometry": {"coordinates":[8.434895,47.419304],"type":"Point"}
}