{
  "type": "Feature",
  "properties": {
    "iso:country":"CH",
    "sg:address":"St. Johanns-ring 133 4056 Basel. Postfach",
    "sg:city":"Basel",
    "sg:orig_category":"Softwareentwicklung U beratung",
    "sg:postcode":"4051",
    "sg:province":"Basel-Stadt",
    "wof:name":"Futurevents Gmbh Veranstaltungen Im Bereich Information Technology; Konzeption, Management Usw",
    "wof:placetype":"venue"
},
  "geometry": {"coordinates":[7.574693203,47.5621681213],"type":"Point"}
}