{
  "type": "Feature",
  "properties": {
    "addr:full":"Wiler Strasse 15 B\u00fctschwil St. Gallen 9606",
    "addr:housenumber":"15;st.",
    "addr:postcode":"9606",
    "addr:street":"Wiler Strasse",
    "iso:country":"CH",
    "sg:address":"Wiler Strasse 15",
    "sg:city":"B\u00fctschwil",
    "sg:orig_category":"Architektur U Ingenieurb\u00fcros Architekturb\u00fcros",
    "sg:phone":"+41 79 646 36 16",
    "sg:postcode":"9606",
    "sg:province":"St. Gallen",
    "wof:name":"Architekturb\u00fcro Raschle & Egli Ag",
    "wof:placetype":"venue"
},
  "geometry": {"coordinates":[9.075101,47.367142],"type":"Point"}
}