{
  "type": "Feature",
  "properties": {
    "iso:country":"CH",
    "sg:address":"Rue Des Alpes 15",
    "sg:city":"Martigny",
    "sg:orig_category":"Tankstellen",
    "sg:phone":"+41 19321232",
    "sg:postcode":"1920",
    "sg:province":"Valais",
    "wof:name":"Jtm Gmbh",
    "wof:placetype":"venue"
},
  "geometry": {"coordinates":[8.782169342,47.3277664185],"type":"Point"}
}