{
  "type": "Feature",
  "properties": {
    "iso:country":"CH",
    "sg:address":"Via Alla Castellana",
    "sg:city":"Pazzallo",
    "sg:classifiers":[
        {
            "category":"Restaurant",
            "type":"Food & Drink"
        }
    ],
    "sg:phone":"+41 91 682 28 78",
    "sg:postcode":"6912",
    "sg:province":"Ticino",
    "wof:name":"Mcdonald's Ristorante",
    "wof:placetype":"venue"
},
  "geometry": {"coordinates":[9.0179290771,45.8444061279],"type":"Point"}
}