{
  "type": "Feature",
  "properties": {
    "iso:country":"CH",
    "sg:address":"Stationsstrasse 7 6023 Rothenburg. Postfach 61",
    "sg:city":"Rothenburg",
    "sg:orig_category":"Arztpraxen",
    "sg:phone":"+41 41 280 99 53",
    "sg:postcode":"6023",
    "sg:province":"Luzern",
    "wof:name":"Dr.med.peter Willi Arzt F.allgemeine Medizin Fmh",
    "wof:placetype":"venue"
},
  "geometry": {"coordinates":[8.25284,47.086441],"type":"Point"}
}