{
  "type": "Feature",
  "properties": {
    "iso:country":"CH",
    "sg:address":"Flurhofstrasse 7",
    "sg:city":"Sirnach",
    "sg:orig_category":"P\u00e9dicure",
    "sg:phone":"+41 71 966 36 73",
    "sg:postcode":"8370",
    "sg:province":"Thurgau",
    "wof:name":"Vreni Ott P\u00e9dicure",
    "wof:placetype":"venue"
},
  "geometry": {"coordinates":[8.9997739792,47.4642448425],"type":"Point"}
}