{
  "type": "Feature",
  "properties": {
    "iso:country":"CH",
    "sg:address":"Sonnenweg 32 3073 G\u00fcmligen. Postfach",
    "sg:city":"G\u00fcmligen",
    "sg:orig_category":"Hardwareberatung",
    "sg:phone":"+41 56 241 05 68",
    "sg:postcode":"3073",
    "sg:province":"Bern",
    "wof:name":"As Electronics, Wicki A.",
    "wof:placetype":"venue"
},
  "geometry": {"coordinates":[8.3332490921,47.5211181641],"type":"Point"}
}