{
  "type": "Feature",
  "properties": {
    "iso:country":"CH",
    "sg:address":"Rue Du Borgeaud 1",
    "sg:city":"Gland",
    "sg:orig_category":"Vermietung U Verpachtung von eigenen Immobilien Vermittlung von Immobilien",
    "sg:phone":"+41 22 354 20 00",
    "sg:postcode":"1196",
    "sg:province":"Vaud",
    "wof:name":"Gem Immobilier S\u00e0rl",
    "wof:placetype":"venue"
},
  "geometry": {"coordinates":[6.2610821724,46.4228172302],"type":"Point"}
}