{
  "type": "Feature",
  "properties": {
    "iso:country":"CH",
    "sg:address":"Rue De L'ecluse 31",
    "sg:city":"Neuenburg",
    "sg:orig_category":"Detailhandel mit Waren verschiedener Art, Hauptrichtung Nahrungsmittel",
    "sg:phone":"+41 32 724 51 27",
    "sg:postcode":"2000",
    "sg:province":"Neuch\u00e2tel",
    "wof:name":"Ngam Food, Falaschi Tuenjai",
    "wof:placetype":"venue"
},
  "geometry": {"coordinates":[6.9255328178,46.9923934937],"type":"Point"}
}