{
  "type": "Feature",
  "properties": {
    "iso:country":"CH",
    "sg:address":"1808",
    "sg:city":"Monts-de-corsier",
    "sg:orig_category":"Haltung von Rindern",
    "sg:postcode":"1808",
    "sg:province":"Vaud",
    "wof:name":"Syndicat D'\u00e9levage Bovin Du Brassus",
    "wof:placetype":"venue"
},
  "geometry": {"coordinates":[6.2120499611,46.582359314],"type":"Point"}
}