{
  "type": "Feature",
  "properties": {
    "iso:country":"CH",
    "sg:address":"Bahnhofstrasse 26",
    "sg:city":"Wolhusen",
    "sg:orig_category":"P\u00e9dicure",
    "sg:phone":"+41 41 490 42 91",
    "sg:postcode":"6110",
    "sg:province":"Luzern",
    "wof:name":"Karin Felder P\u00e9dicure",
    "wof:placetype":"venue"
},
  "geometry": {"coordinates":[8.0751724243,47.0574073792],"type":"Point"}
}