{
  "type": "Feature",
  "properties": {
    "iso:country":"CH",
    "sg:address":"1438",
    "sg:city":"Mathod",
    "sg:orig_category":"Landw. Genossenschaften Viehzucht",
    "sg:postcode":"1438",
    "sg:province":"Vaud",
    "wof:name":"Syndicat D'\u00e9levage Bovin De La Race Tach.rouge Mathod-susc\u00e9v.",
    "wof:placetype":"venue"
},
  "geometry": {"coordinates":[6.5611200333,46.7628593445],"type":"Point"}
}