{
  "type": "Feature",
  "properties": {
    "iso:country":"CH",
    "sg:address":"Grabenring 15",
    "sg:city":"Allschwil",
    "sg:orig_category":"Abbruch U Sprenggewerbe, Erdbewegungsarbeiten",
    "sg:phone":"+41 61 481 22 77",
    "sg:postcode":"4123",
    "sg:province":"Basel-Landschaft",
    "wof:name":"Christian L\u00fcthi Cl Engineering",
    "wof:placetype":"venue"
},
  "geometry": {"coordinates":[7.541013,47.55415],"type":"Point"}
}