{
  "type": "Feature",
  "properties": {
    "iso:country":"CH",
    "sg:address":"Bleicherweg 18 8002 Z\u00fcrich. Postfach",
    "sg:city":"Z\u00fcrich",
    "sg:orig_category":"Pensionskassen",
    "sg:phone":"+41 12051111",
    "sg:postcode":"8001",
    "sg:province":"Z\u00fcrich",
    "wof:name":"Ihag Personalvorsorgestiftung Bvg",
    "wof:placetype":"venue"
},
  "geometry": {"coordinates":[8.5364265442,47.3683204651],"type":"Point"}
}