{
  "type": "Feature",
  "properties": {
    "iso:country":"CH",
    "sg:address":"Rothbergstrasse 19",
    "sg:city":"Muttenz",
    "sg:orig_category":"Pensionskassen Versicherungsagenturen and -broker",
    "sg:postcode":"4132",
    "sg:province":"Basel-Landschaft",
    "wof:name":"Pk.vista Ag",
    "wof:placetype":"venue"
},
  "geometry": {"coordinates":[7.6256971359,47.5322608948],"type":"Point"}
}