{
  "type": "Feature",
  "properties": {
    "iso:country":"CH",
    "sg:address":"Walchestrasse 2 8006 Z\u00fcrich. Postfach",
    "sg:city":"Z\u00fcrich",
    "sg:orig_category":"Gew\u00e4sserschutz\u00e4mter",
    "sg:phone":"+41 12591111",
    "sg:postcode":"8090",
    "sg:province":"Z\u00fcrich",
    "wof:name":"Awel Amt F\u00fcr Abfall Wasser Ernergie & Luft",
    "wof:placetype":"venue"
},
  "geometry": {"coordinates":[8.5421009064,47.3808631897],"type":"Point"}
}