{
  "type": "Feature",
  "properties": {
    "iso:country":"CH",
    "sg:address":"Strengelbacherstrasse 41",
    "sg:city":"Zofingen",
    "sg:orig_category":"Vermietung U Verpachtung von eigenen Immobilien",
    "sg:postcode":"4800",
    "sg:province":"Aargau",
    "wof:name":"Lurant Immobilien Ag",
    "wof:placetype":"venue"
},
  "geometry": {"coordinates":[7.9365911484,47.2821083069],"type":"Point"}
}