{
  "type": "Feature",
  "properties": {
    "iso:country":"CH",
    "sg:address":"Rue Louis-bornet 16",
    "sg:city":"Bulle",
    "sg:classifiers":[
        {
            "category":"Autos & Motor Vehicles",
            "subcategory":"Fuel & Gas Station",
            "type":"Retail Goods"
        }
    ],
    "sg:phone":"+41 26 912 46 67",
    "sg:postcode":"1630",
    "sg:province":"Fribourg",
    "sg:tags":[
        "filtration",
        "spraying",
        "air",
        "filter",
        "paint",
        "fog",
        "cabin"
    ],
    "wof:name":"Tout S.a.",
    "wof:placetype":"venue"
},
  "geometry": {"coordinates":[7.048245,46.613644],"type":"Point"}
}