{
  "type": "Feature",
  "properties": {
    "iso:country":"CH",
    "sg:address":"Weizackerstrasse 28 8400 Winterthur. Postfach",
    "sg:city":"Winterthur",
    "sg:orig_category":"Grosshandel mit Textilien",
    "sg:postcode":"8405",
    "sg:province":"Z\u00fcrich",
    "wof:name":"Tam Textilimport, M\u00fcller T.",
    "wof:placetype":"venue"
},
  "geometry": {"coordinates":[8.7669506073,47.4785690308],"type":"Point"}
}