{
  "type": "Feature",
  "properties": {
    "iso:country":"CH",
    "sg:address":"Feldacher 8",
    "sg:city":"Nebikon",
    "sg:orig_category":"Advokaturb\u00fcros",
    "sg:phone":"+41 62 756 41 43",
    "sg:postcode":"6244",
    "sg:province":"Luzern",
    "wof:name":"Marianne Imbach-arnold Advokaturb\u00fcro",
    "wof:placetype":"venue"
},
  "geometry": {"coordinates":[7.982037,47.19062],"type":"Point"}
}