{
  "type": "Feature",
  "properties": {
    "iso:country":"CH",
    "sg:address":"Poststrasse 96",
    "sg:city":"Rheinau",
    "sg:orig_category":"Sportvereine Turnen Vereine Damen",
    "sg:phone":"+41 52 319 34 85",
    "sg:postcode":"8462",
    "sg:province":"Z\u00fcrich",
    "wof:name":"Damenriege Rheinau",
    "wof:placetype":"venue"
},
  "geometry": {"coordinates":[8.6000995636,47.6388397217],"type":"Point"}
}