{
  "type": "Feature",
  "properties": {
    "iso:country":"CH",
    "sg:address":"Pilatusring 19 6048 Horw. Postfach",
    "sg:city":"Horw",
    "sg:orig_category":"Stukkateurgewerbe, Gipserei U Verputzerei",
    "sg:phone":"+41 41 340 40 24",
    "sg:postcode":"6048",
    "sg:province":"Luzern",
    "wof:name":"Pedone - Kundengipser",
    "wof:placetype":"venue"
},
  "geometry": {"coordinates":[8.3033800125,47.0131874084],"type":"Point"}
}