{
  "type": "Feature",
  "properties": {
    "iso:country":"CH",
    "sg:address":"2742",
    "sg:city":"Perrefitte",
    "sg:orig_category":"Architekturb\u00fcros",
    "sg:phone":"+41 32 493 60 50",
    "sg:postcode":"2742",
    "sg:province":"Bern",
    "wof:name":"Raymond Heyer Bureau D'architecture",
    "wof:placetype":"venue"
},
  "geometry": {"coordinates":[7.342045,47.274609],"type":"Point"}
}