{
  "type": "Feature",
  "properties": {
    "iso:country":"CH",
    "sg:address":"Trichtenhausenstrasse 24",
    "sg:city":"Z\u00fcrich",
    "sg:orig_category":"Detailhandel mit Waren verschiedener Art, Hauptrichtung Nahrungsmittel",
    "sg:phone":"+41 13812917",
    "sg:postcode":"8053",
    "sg:province":"Z\u00fcrich",
    "wof:name":"Elisabeth Baumann Lebensmittel",
    "wof:placetype":"venue"
},
  "geometry": {"coordinates":[8.5962171555,47.3578071594],"type":"Point"}
}