{
  "type": "Feature",
  "properties": {
    "addr:full":"Chemin Du Milieu 144 Martigny Valais 1920",
    "addr:housenumber":"144",
    "addr:postcode":"1920",
    "addr:street":"Chemin Du Milieu",
    "iso:country":"CH",
    "sg:address":"Chemin Du Milieu 144",
    "sg:city":"Martigny",
    "sg:orig_category":"Allgemeiner Gartenbau",
    "sg:phone":"+41 27 722 35 17",
    "sg:postcode":"1920",
    "sg:province":"Valais",
    "wof:name":"Lino Filippi Entreprise De Parcs & Jardins",
    "wof:placetype":"venue"
},
  "geometry": {"coordinates":[7.067388,46.110939],"type":"Point"}
}