{
  "type": "Feature",
  "properties": {
    "iso:country":"CH",
    "sg:address":"Entschwil",
    "sg:city":"Horboden",
    "sg:orig_category":"Allgemeiner Hoch U Tiefbau Hoch U Tiefbau",
    "sg:phone":"+41 33 684 13 71",
    "sg:postcode":"3755",
    "sg:province":"Bern",
    "wof:name":"Mawi-bau Ag",
    "wof:placetype":"venue"
},
  "geometry": {"coordinates":[7.551731,46.618881],"type":"Point"}
}