{
  "type": "Feature",
  "properties": {
    "iso:country":"CH",
    "sg:address":"Bitzistrasse 19 9125 Brunnadern. Postfach 29",
    "sg:city":"Brunnadern",
    "sg:orig_category":"Druck ohne Zeitungsdruck Offsetdruck",
    "sg:phone":"+41 19321282",
    "sg:postcode":"9125",
    "sg:province":"St. Gallen",
    "wof:name":"Druck Service Henzelmann Ag",
    "wof:placetype":"venue"
},
  "geometry": {"coordinates":[8.7873086929,47.3301544189],"type":"Point"}
}