{
  "type": "Feature",
  "properties": {
    "iso:country":"CH",
    "sg:address":"Sonnhaldeweg 32",
    "sg:city":"M\u00fcnsingen",
    "sg:orig_category":"Sonstige Institutionen des Sozialwesens ohne Beherbergung",
    "sg:phone":"+41 31 721 08 64",
    "sg:postcode":"3110",
    "sg:province":"Bern",
    "wof:name":"Ida Werfeli M\u00fctter-& V\u00e4terberatung",
    "wof:placetype":"venue"
},
  "geometry": {"coordinates":[7.5683059692,46.8791007996],"type":"Point"}
}