{
  "type": "Feature",
  "properties": {
    "iso:country":"CH",
    "sg:address":"Chemin De L'oche 4",
    "sg:city":"Borex",
    "sg:orig_category":"Erdbewegungsarbeiten Maurerarbeiten",
    "sg:phone":"+41 22 367 12 28",
    "sg:postcode":"1277",
    "sg:province":"Vaud",
    "wof:name":"Paltani Sa Ma\u00e7onnerie & B\u00e9ton Arm\u00e9",
    "wof:placetype":"venue"
},
  "geometry": {"coordinates":[6.1857600212,46.3773117065],"type":"Point"}
}