{
  "type": "Feature",
  "properties": {
    "iso:country":"CH",
    "sg:address":"St.-anna-strasse 51",
    "sg:city":"Luzern",
    "sg:orig_category":"Fotografische Ateliers",
    "sg:phone":"+41 41 370 26 23",
    "sg:postcode":"6006",
    "sg:province":"Luzern",
    "wof:name":"Dr.walter Reinert Fotografisches Atelier",
    "wof:placetype":"venue"
},
  "geometry": {"coordinates":[8.3310661316,47.0588798523],"type":"Point"}
}