{
  "type": "Feature",
  "properties": {
    "iso:country":"CH",
    "sg:address":"Bernstrasse 72",
    "sg:city":"B\u00fctzberg",
    "sg:orig_category":"Unclassifiable Establishments",
    "sg:postcode":"4922",
    "sg:province":"Bern",
    "wof:name":"Ital. Paninoteca Cadente",
    "wof:placetype":"venue"
},
  "geometry": {"coordinates":[7.7389397621,47.211555481],"type":"Point"}
}