{
  "type": "Feature",
  "properties": {
    "addr:full":"Marktplatz 17 Basel Basel-Stadt 4001",
    "addr:housenumber":"17",
    "addr:postcode":"4001",
    "addr:street":"Marktplatz",
    "iso:country":"CH",
    "sg:address":"Marktplatz 17",
    "sg:city":"Basel",
    "sg:classifiers":[
        {
            "category":"Banks & Credit Unions",
            "subcategory":"Bank",
            "type":"Services"
        }
    ],
    "sg:phone":"+41 61 261 14 70",
    "sg:postcode":"4001",
    "sg:province":"Basel-Stadt",
    "wof:name":"Swiss Bank Corporation",
    "wof:placetype":"venue"
},
  "geometry": {"coordinates":[7.587687,47.557739],"type":"Point"}
}