{
  "type": "Feature",
  "properties": {
    "addr:full":"En Baule Begnins Vaud 1268",
    "addr:housenumber":"1268",
    "iso:country":"CH",
    "sg:address":"En Baule",
    "sg:city":"Begnins",
    "sg:orig_category":"Architektur U Ingenieurb\u00fcros",
    "sg:phone":"+41 22 366 18 42",
    "sg:postcode":"1268",
    "sg:province":"Vaud",
    "wof:name":"Zaric N.",
    "wof:placetype":"venue"
},
  "geometry": {"coordinates":[6.242852,46.442856],"type":"Point"}
}