{
  "type": "Feature",
  "properties": {
    "addr:full":"Obersecki 1 Walchwil Zug 6318",
    "addr:housenumber":"1",
    "addr:postcode":"6318",
    "addr:street":"Obersecki;Zug",
    "iso:country":"CH",
    "sg:address":"Obersecki 1",
    "sg:city":"Walchwil",
    "sg:classifiers":[
        {
            "category":"Utilities",
            "subcategory":"Cable",
            "type":"Services"
        }
    ],
    "sg:phone":"+41 41 758 11 12",
    "sg:postcode":"6318",
    "sg:province":"Zug",
    "sg:tags":[
        "wire",
        "erosion",
        "cnc",
        "machining"
    ],
    "wof:name":"Adisys Ag",
    "wof:placetype":"venue"
},
  "geometry": {"coordinates":[8.519224,47.097446],"type":"Point"}
}