{
  "type": "Feature",
  "properties": {
    "iso:country":"CH",
    "sg:address":"Moosgasse 16 2562 Port. Postfach",
    "sg:city":"Port",
    "sg:orig_category":"Autogaragen",
    "sg:phone":"+41 32 331 69 69",
    "sg:postcode":"2562",
    "sg:province":"Bern",
    "wof:name":"Pietro Salvato Garage",
    "wof:placetype":"venue"
},
  "geometry": {"coordinates":[7.252517,47.118294],"type":"Point"}
}