{
  "type": "Feature",
  "properties": {
    "iso:country":"CH",
    "sg:address":"Pulverm\u00fchlestrasse 84",
    "sg:city":"Chur",
    "sg:orig_category":"Dachdeckerei Zimmerei, Dachdeckerei, Bauspenglerei U Abdichtung",
    "sg:phone":"+41 81 284 45 77",
    "sg:postcode":"7000",
    "sg:province":"Graubunden",
    "wof:name":"Studach's Hans Erben, Inhaber Studach & Frei",
    "wof:placetype":"venue"
},
  "geometry": {"coordinates":[9.507361,46.854259],"type":"Point"}
}