{
  "type": "Feature",
  "properties": {
    "iso:country":"CH",
    "sg:address":"Melchiorstrasse 13/3b 3027 Bern. Postfach",
    "sg:city":"Bern",
    "sg:orig_category":"Fachdetailhandel in Verkaufsr\u00e4umen",
    "sg:postcode":"3027",
    "sg:province":"Bern",
    "wof:name":"Casa Dell'onice, Baira Kunstgegenst\u00e4nde Aus Onyxmarmor; Handel.",
    "wof:placetype":"venue"
},
  "geometry": {"coordinates":[7.3890461922,46.9521942139],"type":"Point"}
}