{
  "type": "Feature",
  "properties": {
    "iso:country":"CH",
    "sg:address":"4142 M\u00fcnchenstein. Postfach",
    "sg:city":"M\u00fcnchenstein",
    "sg:orig_category":"Lagerh\u00e4user, G\u00fcterumschlag, Verteilzentren",
    "sg:phone":"+41 61 338 96 96",
    "sg:postcode":"4142",
    "sg:province":"Basel-Landschaft",
    "wof:name":"Basler Freilager Ag",
    "wof:placetype":"venue"
},
  "geometry": {"coordinates":[7.6197199821,47.5194015503],"type":"Point"}
}