{
  "type": "Feature",
  "properties": {
    "iso:country":"CH",
    "sg:address":"Via Orico 7",
    "sg:city":"Bellinzona",
    "sg:orig_category":"Handel mit Motorr\u00e4dern, Teilen U Zubeh\u00f6r Instandhaltung U Reparatur von Motorr\u00e4dern",
    "sg:phone":"+41 91 825 26 65",
    "sg:postcode":"6500",
    "sg:province":"Ticino",
    "wof:name":"Carlo Rivolta Negozio Cicli & Moto",
    "wof:placetype":"venue"
},
  "geometry": {"coordinates":[9.0200176239,46.1918182373],"type":"Point"}
}