{
  "type": "Feature",
  "properties": {
    "iso:country":"CH",
    "sg:address":"M\u00fcnzgasse 3",
    "sg:city":"Basel",
    "sg:orig_category":"Detailhandel mit Sportartikeln",
    "sg:phone":"+41 61 263 31 50",
    "sg:postcode":"4001",
    "sg:province":"Basel-Stadt",
    "wof:name":"Beach Mountain Ag Snowboards & Skateboard",
    "wof:placetype":"venue"
},
  "geometry": {"coordinates":[7.5872921944,47.5572128296],"type":"Point"}
}