{
  "type": "Feature",
  "properties": {
    "iso:country":"CH",
    "sg:address":"Via S. Paolo 16",
    "sg:city":"Bellinzona",
    "sg:orig_category":"Dachdeckerei Zimmerei, Ingenieurholzbau",
    "sg:phone":"+41 91 794 13 26",
    "sg:postcode":"6500",
    "sg:province":"Ticino",
    "wof:name":"Bruno Antognini Sa Carpenteria & Copertura Tetti",
    "wof:placetype":"venue"
},
  "geometry": {"coordinates":[8.803478,46.131073],"type":"Point"}
}