{
  "type": "Feature",
  "properties": {
    "iso:country":"CH",
    "sg:address":"Alpenstrasse 12",
    "sg:city":"Zug",
    "sg:orig_category":"Handels-H\u00e4user U Gesellschaften",
    "sg:postcode":"6300",
    "sg:province":"Zug",
    "wof:name":"Statim Sa",
    "wof:placetype":"venue"
},
  "geometry": {"coordinates":[7.5864248276,46.2146835327],"type":"Point"}
}