{
  "type": "Feature",
  "properties": {
    "iso:country":"CH",
    "sg:address":"Schwyzerstrasse 5",
    "sg:city":"Steinen",
    "sg:orig_category":"Instandhaltung U Reparatur von Automobilen",
    "sg:phone":"+41 41 832 13 38",
    "sg:postcode":"6422",
    "sg:province":"Schwyz",
    "wof:name":"Mettler August",
    "wof:placetype":"venue"
},
  "geometry": {"coordinates":[8.6148061752,47.0491447449],"type":"Point"}
}