{
  "type": "Feature",
  "properties": {
    "addr:full":"G\u00e4nsackerweg 20 Gipf-oberfrick Aargau 5073",
    "addr:housenumber":"20",
    "addr:postcode":"5073",
    "addr:street":"Gaensackerweg",
    "iso:country":"CH",
    "sg:address":"G\u00e4nsackerweg 20",
    "sg:city":"Gipf-oberfrick",
    "sg:orig_category":"Aktivit\u00e4ten der Krankenschwestern U Hebammen, Hauspflege Organisationen des Gesundheitswesen",
    "sg:phone":"+41 62 871 08 60",
    "sg:postcode":"5073",
    "sg:province":"Aargau",
    "wof:name":"Spitex Wwok Doroth\u00e9e Menzi-erb",
    "wof:placetype":"venue"
},
  "geometry": {"coordinates":[8.001325,47.499847],"type":"Point"}
}