{
  "type": "Feature",
  "properties": {
    "iso:country":"CH",
    "sg:address":"Zielwegli 4",
    "sg:city":"Niedererlinsbach",
    "sg:orig_category":"Allgemeiner Hoch U Tiefbau",
    "sg:phone":"+41 62 844 01 60",
    "sg:postcode":"5015",
    "sg:province":"Solothurn",
    "wof:name":"Buser Martin Baugesch\u00e4ft",
    "wof:placetype":"venue"
},
  "geometry": {"coordinates":[8.006283,47.396355],"type":"Point"}
}