{
  "type": "Feature",
  "properties": {
    "iso:country":"CH",
    "sg:address":"1618",
    "sg:city":"Ch\u00e2tel-st-denis",
    "sg:classifiers":[
        {
            "category":"Travel",
            "subcategory":"Hotels & Motels",
            "type":"Entertainment"
        }
    ],
    "sg:postcode":"1618",
    "sg:province":"Fribourg",
    "sg:tags":[
        "hotels",
        "mit",
        "restaurant"
    ],
    "wof:name":"Ancarest S\u00e0rl",
    "wof:placetype":"venue"
},
  "geometry": {"coordinates":[6.9015398026,46.5275344849],"type":"Point"}
}