{
  "type": "Feature",
  "properties": {
    "iso:country":"CH",
    "sg:address":"Auerstrasse 4",
    "sg:city":"Heerbrugg",
    "sg:orig_category":"Detailhandel mit Teppichen Verlegen von Fussboden",
    "sg:phone":"+41 71 722 17 53",
    "sg:postcode":"9435",
    "sg:province":"St. Gallen",
    "wof:name":"Fischbacher H. Indecor",
    "wof:placetype":"venue"
},
  "geometry": {"coordinates":[9.6276388168,47.4118614197],"type":"Point"}
}