{
  "type": "Feature",
  "properties": {
    "iso:country":"CH",
    "sg:address":"Kappeliweg 10/12",
    "sg:city":"Herzogenbuchsee",
    "sg:orig_category":"Erschliessung von Grundst\u00fccken",
    "sg:postcode":"3360",
    "sg:province":"Bern",
    "wof:name":"Baugenossenschaft Jurablick",
    "wof:placetype":"venue"
},
  "geometry": {"coordinates":[7.7059459686,47.1928901672],"type":"Point"}
}