{
  "type": "Feature",
  "properties": {
    "iso:country":"CH",
    "sg:address":"Mittelh\u00e4usern",
    "sg:city":"Mittelh\u00e4usern",
    "sg:classifiers":[
        {
            "category":"Banks & Credit Unions",
            "subcategory":"Bank",
            "type":"Services"
        }
    ],
    "sg:phone":"+41 31 849 11 05",
    "sg:postcode":"3147",
    "sg:province":"Bern",
    "wof:name":"Raiffeisenbank Mittelh\u00e4usern",
    "wof:placetype":"venue"
},
  "geometry": {"coordinates":[7.368507,46.876537],"type":"Point"}
}