{
  "type": "Feature",
  "properties": {
    "iso:country":"CH",
    "sg:address":"Waldeggstrasse 1 Liebefeld 3098 K\u00f6niz. Postfach",
    "sg:city":"Liebefeld",
    "sg:orig_category":"Architektur U Ingenieurb\u00fcros",
    "sg:postcode":"3097",
    "sg:province":"Bern",
    "wof:name":"Architektur + Bauleitung Hossmann Heinz",
    "wof:placetype":"venue"
},
  "geometry": {"coordinates":[7.414276,46.922874],"type":"Point"}
}