{
  "type": "Feature",
  "properties": {
    "iso:country":"CH",
    "sg:address":"7050 Arosa. Postfach 320",
    "sg:city":"Arosa",
    "sg:classifiers":[
        {
            "category":"Travel",
            "subcategory":"Hotels & Motels",
            "type":"Entertainment"
        }
    ],
    "sg:phone":"+41 81 377 18 61",
    "sg:postcode":"7050",
    "sg:province":"Graubunden",
    "sg:tags":[
        "hotels",
        "mit",
        "restaurant"
    ],
    "wof:name":"Berghotel Pr\u00e4tschli Ag Arosa",
    "wof:placetype":"venue"
},
  "geometry": {"coordinates":[9.6765518188,46.7778625488],"type":"Point"}
}