{
  "type": "Feature",
  "properties": {
    "iso:country":"CH",
    "sg:address":"6162",
    "sg:city":"Rengg",
    "sg:classifiers":[
        {
            "category":"Restaurant",
            "type":"Food & Drink"
        }
    ],
    "sg:phone":"+41 41 480 13 37",
    "sg:postcode":"6162",
    "sg:province":"Luzern",
    "wof:name":"Restaurant Rengg",
    "wof:placetype":"venue"
},
  "geometry": {"coordinates":[8.0906200409,47.0034294128],"type":"Point"}
}