{
  "type": "Feature",
  "properties": {
    "addr:full":"Lettenstrasse 1 Stettfurt Thurgau 9507",
    "addr:housenumber":"1",
    "addr:postcode":"9507",
    "addr:street":"Lettenstrasse",
    "iso:country":"CH",
    "sg:address":"Lettenstrasse 1",
    "sg:city":"Stettfurt",
    "sg:orig_category":"Architektur U Ingenieurb\u00fcros",
    "sg:phone":"+41 52 376 28 58",
    "sg:postcode":"9507",
    "sg:province":"Thurgau",
    "wof:name":"Strittmatter & Partner Ag Raumplanungsb\u00fcro",
    "wof:placetype":"venue"
},
  "geometry": {"coordinates":[8.958207,47.524326],"type":"Point"}
}