{
  "type": "Feature",
  "properties": {
    "iso:country":"CH",
    "sg:address":"Neudorfstrasse 64",
    "sg:city":"Thusis",
    "sg:orig_category":"Sonstiges Versicherungsgewerbe",
    "sg:phone":"+41 81 651 15 25",
    "sg:postcode":"7430",
    "sg:province":"Graubunden",
    "wof:name":"Vts Versicherungs Und Treuhandservice Bernhard",
    "wof:placetype":"venue"
},
  "geometry": {"coordinates":[9.4395885468,46.6969108582],"type":"Point"}
}