{
  "type": "Feature",
  "properties": {
    "iso:country":"CH",
    "sg:address":"Avenue Des Communes R\u00e9unies 68",
    "sg:city":"Grand-lancy",
    "sg:orig_category":"Detailhandel mit Waren verschiedener Art, Hauptrichtung Nahrungsmittel",
    "sg:phone":"+41 22 794 71 51",
    "sg:postcode":"1212",
    "sg:province":"Gen\u00e8ve",
    "wof:name":"Pick Pay Partenaire Magasin D'alimentation",
    "wof:placetype":"venue"
},
  "geometry": {"coordinates":[6.1228928566,46.1731262207],"type":"Point"}
}