{
  "type": "Feature",
  "properties": {
    "addr:full":"Hauptstrasse 22 Reinach Basel-Landschaft 4153",
    "addr:housenumber":"22",
    "addr:postcode":"4153",
    "addr:street":"Hauptstrasse",
    "iso:country":"CH",
    "sg:address":"Hauptstrasse 22",
    "sg:city":"Reinach",
    "sg:classifiers":[
        {
            "category":"Train Station",
            "subcategory":"Rail",
            "type":"Transportation"
        }
    ],
    "sg:phone":"+41 61 717 90 60",
    "sg:postcode":"4153",
    "sg:province":"Basel-Landschaft",
    "sg:tags":[
        "travel",
        "adventure"
    ],
    "wof:name":"Beaver Ag",
    "wof:placetype":"venue"
},
  "geometry": {"coordinates":[7.590088,47.49337],"type":"Point"}
}