{
  "type": "Feature",
  "properties": {
    "iso:country":"CH",
    "sg:address":"Route Principale 2a",
    "sg:city":"Evilard",
    "sg:orig_category":"Sportvereine Wassersport Schwimmen",
    "sg:phone":"+41 32 491 67 07",
    "sg:postcode":"2533",
    "sg:province":"Bern",
    "wof:name":"Schwimm-club Magglingen",
    "wof:placetype":"venue"
},
  "geometry": {"coordinates":[7.2444639206,47.1522064209],"type":"Point"}
}