{
  "type": "Feature",
  "properties": {
    "iso:country":"CH",
    "sg:address":"Rembuestrasse",
    "sg:city":"Susten",
    "sg:classifiers":[
        {
            "category":"Insurance",
            "subcategory":"Insurance Agent",
            "type":"Services"
        }
    ],
    "sg:phone":"+41 33 676 16 26",
    "sg:postcode":"3952",
    "sg:province":"Valais",
    "sg:tags":[
        "versicherungsagenturen",
        "-broker"
    ],
    "wof:name":"Rentenanstalt/swiss Life Agentur",
    "wof:placetype":"venue"
},
  "geometry": {"coordinates":[7.6695599556,46.6155853271],"type":"Point"}
}