{
  "type": "Feature",
  "properties": {
    "iso:country":"CH",
    "sg:address":"Wildenstrasse 10 8212 Neuhausen. Postfach 1161",
    "sg:city":"Neuhausen",
    "sg:orig_category":"Detailhandel mit Textilien Grosshandel mit Textilien",
    "sg:postcode":"8212",
    "sg:province":"Schaffhausen",
    "wof:name":"Wiedella M. Wiederkehr",
    "wof:placetype":"venue"
},
  "geometry": {"coordinates":[8.618019104,47.6810493469],"type":"Point"}
}