{
  "type": "Feature",
  "properties": {
    "iso:country":"CH",
    "sg:address":"Vevey Rue De 42 1630 Bulle. Postfach",
    "sg:city":"Bulle",
    "sg:orig_category":"Architektur U Ingenieurb\u00fcros",
    "sg:phone":"+41 26 912 13 93",
    "sg:postcode":"1630",
    "sg:province":"Fribourg",
    "wof:name":"Franca S\u00e0rl Travaux De Constructions, De G\u00e9nie-civil Etc",
    "wof:placetype":"venue"
},
  "geometry": {"coordinates":[7.057381,46.618603],"type":"Point"}
}