{
  "type": "Feature",
  "properties": {
    "iso:country":"CH",
    "sg:address":"H\u00f6schgasse 70 8008 Z\u00fcrich. Postfach",
    "sg:city":"Z\u00fcrich",
    "sg:orig_category":"Allgemeiner Hoch U Tiefbau Architektur U Ingenieurb\u00fcros",
    "sg:phone":"+41 13805670",
    "sg:postcode":"8001",
    "sg:province":"Z\u00fcrich",
    "wof:name":"Schneider Immobau Ag Liegenschaften U. Immobilien, Bes. Neubau, Umbau Usw.; Planung, Organisation",
    "wof:placetype":"venue"
},
  "geometry": {"coordinates":[8.555877,47.358006],"type":"Point"}
}