{
  "type": "Feature",
  "properties": {
    "iso:country":"CH",
    "sg:address":"Cheesturmweg 5",
    "sg:city":"H\u00e4rkingen",
    "sg:orig_category":"Politische Parteien FDP",
    "sg:phone":"+41 62 398 28 19",
    "sg:postcode":"4624",
    "sg:province":"Solothurn",
    "wof:name":"Fdp Ortspartei H\u00e4rkingen",
    "wof:placetype":"venue"
},
  "geometry": {"coordinates":[7.8156781197,47.3091506958],"type":"Point"}
}