{
  "type": "Feature",
  "properties": {
    "iso:country":"CH",
    "sg:address":"Hauptstrasse 3",
    "sg:city":"Diepflingen",
    "sg:orig_category":"Pensionskassen",
    "sg:phone":"+41 79 204 72 20",
    "sg:postcode":"4442",
    "sg:province":"Basel-Landschaft",
    "wof:name":"Personalvorsorgestiftung Der Garage Oberer Ag",
    "wof:placetype":"venue"
},
  "geometry": {"coordinates":[7.8346261978,47.4491844177],"type":"Point"}
}