{
  "type": "Feature",
  "properties": {
    "iso:country":"CH",
    "sg:address":"Promenadenstrasse 83",
    "sg:city":"Rorschach",
    "sg:orig_category":"Detailhandel mit Waren verschiedener Art, Hauptrichtung Nahrungsmittel",
    "sg:phone":"+41 71 841 47 53",
    "sg:postcode":"9400",
    "sg:province":"St. Gallen",
    "wof:name":"Migros-markt",
    "wof:placetype":"venue"
},
  "geometry": {"coordinates":[9.4951143265,47.4742126465],"type":"Point"}
}