{
  "type": "Feature",
  "properties": {
    "iso:country":"CH",
    "sg:address":"Logenstrasse 3",
    "sg:city":"Biel/bienne",
    "sg:orig_category":"RESTAURANTS: TEA-ROOMS",
    "sg:phone":"+41 32 322 83 22",
    "sg:postcode":"2502",
    "sg:province":"Bern",
    "wof:name":"Restaurant Astoria",
    "wof:placetype":"venue"
},
  "geometry": {"coordinates":[7.2497987747,47.139503479],"type":"Point"}
}