{
  "type": "Feature",
  "properties": {
    "iso:country":"CH",
    "sg:address":"Bahnhofstrasse 26 4900 Langenthal. Postfach",
    "sg:city":"Langenthal",
    "sg:orig_category":"Unternehmensberatung Wirtschaftspr\u00fcfung, Steuerberatung U Treuhand",
    "sg:phone":"+41 62 916 60 60",
    "sg:postcode":"4901",
    "sg:province":"Bern",
    "wof:name":"Gfeller + Partner Ag",
    "wof:placetype":"venue"
},
  "geometry": {"coordinates":[7.7866802216,47.2135810852],"type":"Point"}
}