{
  "type": "Feature",
  "properties": {
    "iso:country":"CH",
    "sg:address":"Obermattenstrasse 31",
    "sg:city":"R\u00fcmlang",
    "sg:orig_category":"Unclassifiable Establishments",
    "sg:postcode":"8153",
    "sg:province":"Z\u00fcrich",
    "wof:name":"Hoffer Information Engineering & Project Management",
    "wof:placetype":"venue"
},
  "geometry": {"coordinates":[8.5314807892,47.4461631775],"type":"Point"}
}