{
  "type": "Feature",
  "properties": {
    "iso:country":"CH",
    "sg:address":"Dorfstrasse 88 3715 Adelboden. Postfach 210",
    "sg:city":"Adelboden",
    "sg:classifiers":[
        {
            "category":"Travel",
            "subcategory":"Hotels & Motels",
            "type":"Entertainment"
        }
    ],
    "sg:phone":"+41 33 673 15 31",
    "sg:postcode":"3715",
    "sg:province":"Bern",
    "sg:tags":[
        "hotels",
        "mit",
        "restaurant"
    ],
    "wof:name":"Hotel Huldi & Waldhaus",
    "wof:placetype":"venue"
},
  "geometry": {"coordinates":[7.553621769,46.4888381958],"type":"Point"}
}