{
  "type": "Feature",
  "properties": {
    "addr:full":"Br\u00fchlstrasse 43 Biel/bienne Bern 2503",
    "addr:housenumber":"43",
    "addr:postcode":"2503",
    "addr:street":"Bruehlstrasse",
    "iso:country":"CH",
    "sg:address":"Br\u00fchlstrasse 43",
    "sg:city":"Biel/bienne",
    "sg:orig_category":"Chemische Reinigung",
    "sg:phone":"+41 61 711 88 20",
    "sg:postcode":"2503",
    "sg:province":"Bern",
    "wof:name":"N\u00e4f Textilreinigung Inh. B.tschudin-n\u00e4f",
    "wof:placetype":"venue"
},
  "geometry": {"coordinates":[7.589458,47.493431],"type":"Point"}
}