{
  "type": "Feature",
  "properties": {
    "iso:country":"CH",
    "sg:address":"Chalenstrasse 8a 8123 Ebmatingen. Postfach",
    "sg:city":"Ebmatingen",
    "sg:orig_category":"Erbringung von Dienstleistungen f\u00fcr Unternehmen",
    "sg:phone":"+41 84848847",
    "sg:postcode":"8123",
    "sg:province":"Z\u00fcrich",
    "wof:name":"Swiss Dienstleistungszentrum Dlc Ag",
    "wof:placetype":"venue"
},
  "geometry": {"coordinates":[8.6396837234,47.3508529663],"type":"Point"}
}