{
  "type": "Feature",
  "properties": {
    "iso:country":"CH",
    "sg:address":"Werdstrasse 322 A",
    "sg:city":"Neuendorf",
    "sg:orig_category":"Bausteine Fabrikation, Handel",
    "sg:phone":"+41 62 398 25 50",
    "sg:postcode":"4623",
    "sg:province":"Solothurn",
    "wof:name":"Behrami A. Unterlagsb\u00f6den",
    "wof:placetype":"venue"
},
  "geometry": {"coordinates":[7.799978,47.304737],"type":"Point"}
}