{
  "type": "Feature",
  "properties": {
    "iso:country":"CH",
    "sg:address":"Buchmattstrasse 45 3400 Burgdorf. Postfach",
    "sg:city":"Burgdorf",
    "sg:orig_category":"Handelsvermittlung U Grosshandel mit Automobilteilen U Zubeh\u00f6r",
    "sg:phone":"+41 31 379 81 21",
    "sg:postcode":"3401",
    "sg:province":"Bern",
    "wof:name":"Technomag Ag Autoersatzteil-service Hauptsitz Verwaltung",
    "wof:placetype":"venue"
},
  "geometry": {"coordinates":[7.4139351845,46.9412002563],"type":"Point"}
}