{
  "type": "Feature",
  "properties": {
    "iso:country":"CH",
    "sg:address":"Via Solaria 31",
    "sg:city":"Minusio",
    "sg:classifiers":[
        {
            "category":"Travel",
            "subcategory":"Hotels & Motels",
            "type":"Entertainment"
        }
    ],
    "sg:postcode":"6648",
    "sg:province":"Ticino",
    "sg:tags":[
        "hotels",
        "mit",
        "restaurant"
    ],
    "wof:name":"Pensione-ristorante-negozio Capelli & Co.",
    "wof:placetype":"venue"
},
  "geometry": {"coordinates":[10.0709266663,46.3134384155],"type":"Point"}
}