{
  "type": "Feature",
  "properties": {
    "iso:country":"CH",
    "sg:address":"Blankweg 20",
    "sg:city":"Ostermundigen",
    "sg:orig_category":"Sonstiger Grosshandel",
    "sg:phone":"+41 31 931 67 04",
    "sg:postcode":"3072",
    "sg:province":"Bern",
    "wof:name":"Mk Kwapisiewicz Marek",
    "wof:placetype":"venue"
},
  "geometry": {"coordinates":[7.4926981926,46.9572296143],"type":"Point"}
}