{
  "type": "Feature",
  "properties": {
    "iso:country":"CH",
    "sg:address":"Kirchmattstrasse 18",
    "sg:city":"Steinhausen",
    "sg:orig_category":"Softwareentwicklung U beratung",
    "sg:phone":"+41 41 741 77 86",
    "sg:postcode":"6312",
    "sg:province":"Zug",
    "wof:name":"Oz Software Services, Zanetti Odette",
    "wof:placetype":"venue"
},
  "geometry": {"coordinates":[8.4827871323,47.1953887939],"type":"Point"}
}