{
  "type": "Feature",
  "properties": {
    "iso:country":"CH",
    "sg:address":"Kasinostrasse 29",
    "sg:city":"Aarau",
    "sg:orig_category":"Zahnarztpraxen",
    "sg:phone":"+41 62 822 44 76",
    "sg:postcode":"5000",
    "sg:province":"Aargau",
    "wof:name":"Dr. Med. Dent. R\u00e9my Forster Zahnarzt",
    "wof:placetype":"venue"
},
  "geometry": {"coordinates":[8.0472040176,47.392074585],"type":"Point"}
}