{
  "type": "Feature",
  "properties": {
    "iso:country":"CH",
    "sg:address":"Blaufahnenstrasse 10",
    "sg:city":"Z\u00fcrich",
    "sg:orig_category":"Interessenvertretungen",
    "sg:phone":"+41 17812605",
    "sg:postcode":"8001",
    "sg:province":"Z\u00fcrich",
    "wof:name":"Brupbacher-isler-stiftung Familie",
    "wof:placetype":"venue"
},
  "geometry": {"coordinates":[8.6527090073,47.2407150269],"type":"Point"}
}