{
  "type": "Feature",
  "properties": {
    "iso:country":"CH",
    "sg:address":"Markircherstrasse 19 4055 Basel. Postfach",
    "sg:city":"Basel",
    "sg:orig_category":"Unclassifiable Establishments",
    "sg:phone":"+41 61 811 44 50",
    "sg:postcode":"4051",
    "sg:province":"Basel-Stadt",
    "wof:name":"Schmidt Ernst Internationale Warentransporte.",
    "wof:placetype":"venue"
},
  "geometry": {"coordinates":[7.5631389618,47.5657272339],"type":"Point"}
}