{
  "type": "Feature",
  "properties": {
    "iso:country":"CH",
    "sg:address":"Post",
    "sg:city":"Rupperswil",
    "sg:orig_category":"Nationale Postdienste",
    "sg:phone":"+41 34 493 31 04",
    "sg:postcode":"5102",
    "sg:province":"Aargau",
    "wof:name":"Die Schweizerische Post",
    "wof:placetype":"venue"
},
  "geometry": {"coordinates":[7.896791935,46.8511428833],"type":"Point"}
}