{
  "type": "Feature",
  "properties": {
    "addr:full":"Burgauerstrasse 49 Flawil St. Gallen 9230",
    "addr:housenumber":"49",
    "addr:postcode":"9230",
    "addr:street":"Burgauerstrasse",
    "iso:country":"CH",
    "sg:address":"Burgauerstrasse 49",
    "sg:city":"Flawil",
    "sg:classifiers":[
        {
            "category":"Wholesale",
            "subcategory":"Metals & Minerals",
            "type":"Manufacturing & Wholesale Goods"
        }
    ],
    "sg:phone":"+41 71 393 26 26",
    "sg:postcode":"9230",
    "sg:province":"St. Gallen",
    "sg:tags":[
        "alloy",
        "cast",
        "aluminium"
    ],
    "wof:name":"Germann Guss Ag",
    "wof:placetype":"venue"
},
  "geometry": {"coordinates":[9.20204,47.410255],"type":"Point"}
}