{
  "type": "Feature",
  "properties": {
    "iso:country":"CH",
    "sg:address":"Sportstrasse",
    "sg:city":"Niederuzwil",
    "sg:classifiers":[
        {
            "category":"Restaurant",
            "type":"Food & Drink"
        }
    ],
    "sg:phone":"+41 71 951 65 88",
    "sg:postcode":"9244",
    "sg:province":"St. Gallen",
    "wof:name":"Eisbahn-caf\u00e8 Uzehalle Restaurant",
    "wof:placetype":"venue"
},
  "geometry": {"coordinates":[9.1420040131,47.439453125],"type":"Point"}
}