{
  "type": "Feature",
  "properties": {
    "iso:country":"CH",
    "sg:address":"Weidwiesen",
    "sg:city":"Oberaach",
    "sg:orig_category":"Herstellung von Tanks U Sammelbeh\u00e4ltern aus Metall Stahl U Leichtmetallbau",
    "sg:phone":"+41 71 414 50 00",
    "sg:postcode":"8587",
    "sg:province":"Thurgau",
    "wof:name":"Gerinox Ag",
    "wof:placetype":"venue"
},
  "geometry": {"coordinates":[9.2721557617,47.5536003113],"type":"Point"}
}