{
  "type": "Feature",
  "properties": {
    "iso:country":"CH",
    "sg:address":"Via San Salvatore 13 6900 Paradiso. Postfach",
    "sg:city":"Paradiso",
    "sg:orig_category":"Herstellung von elektrischen Lampen U Leuchten",
    "sg:postcode":"6900",
    "sg:province":"Ticino",
    "wof:name":"Esedera Sa, Luxembourg, Paradiso Branch",
    "wof:placetype":"venue"
},
  "geometry": {"coordinates":[8.9454631805,45.9909362793],"type":"Point"}
}