{
  "type": "Feature",
  "properties": {
    "iso:country":"CH",
    "sg:address":"Rotbachmatte 7",
    "sg:city":"Rothenburg",
    "sg:orig_category":"Architekturb\u00fcros",
    "sg:phone":"+41 81 911 30 15",
    "sg:postcode":"6023",
    "sg:province":"Luzern",
    "wof:name":"Leo Deplazes Architekturb\u00fcro",
    "wof:placetype":"venue"
},
  "geometry": {"coordinates":[9.288318,46.826241],"type":"Point"}
}