{
  "type": "Feature",
  "properties": {
    "iso:country":"CH",
    "sg:address":"Baumackerstrasse 35 8050 Z\u00fcrich. Postfach 8050 Z\u00fcrich",
    "sg:city":"Zust",
    "sg:classifiers":[
        {
            "category":"Professional",
            "subcategory":"Employment Agencies",
            "type":"Services"
        }
    ],
    "sg:phone":"+41 13158515",
    "sg:postcode":"50",
    "sg:tags":[
        "personal",
        "u",
        "stellenvermittlung"
    ],
    "wof:name":"Allbecon Industrie-service Oerlikon Ag",
    "wof:placetype":"venue"
},
  "geometry": {"coordinates":[8.5433197021,47.4092483521],"type":"Point"}
}