{
  "type": "Feature",
  "properties": {
    "iso:country":"CH",
    "sg:address":"Campingweg 12",
    "sg:city":"Oftringen",
    "sg:orig_category":"Softwareentwicklung U beratung",
    "sg:phone":"+41 62 797 80 60",
    "sg:postcode":"4665",
    "sg:province":"Aargau",
    "wof:name":"Fsp Financial Software Products Ag",
    "wof:placetype":"venue"
},
  "geometry": {"coordinates":[7.9314470291,47.3053970337],"type":"Point"}
}