{
  "type": "Feature",
  "properties": {
    "iso:country":"CH",
    "sg:address":"Hettlingerstrasse 3",
    "sg:city":"Seuzach",
    "sg:orig_category":"Werbevermittlung",
    "sg:phone":"+41 41 311 21 11",
    "sg:postcode":"8472",
    "sg:province":"Z\u00fcrich",
    "wof:name":"Hochstrasser & Partner Werbeagentur",
    "wof:placetype":"venue"
},
  "geometry": {"coordinates":[8.3026609421,47.0415611267],"type":"Point"}
}