{
  "type": "Feature",
  "properties": {
    "iso:country":"CH",
    "sg:address":"Via San Abbondio 15 6925 Gentilino. Postfach Caselle Postale 268",
    "sg:city":"Bioggio",
    "sg:orig_category":"Herstellung von pharmazeutischen Grundstoffen",
    "sg:phone":"+41 91 604 62 73",
    "sg:postcode":"6934",
    "sg:province":"Ticino",
    "wof:name":"Hawe Neos Dental Sa",
    "wof:placetype":"venue"
},
  "geometry": {"coordinates":[8.9343700409,45.9937057495],"type":"Point"}
}