{
  "type": "Feature",
  "properties": {
    "iso:country":"CH",
    "sg:address":"Frohbergstrasse 25",
    "sg:city":"Wiesendangen",
    "sg:orig_category":"Museen",
    "sg:phone":"+41 52 337 12 51",
    "sg:postcode":"8542",
    "sg:province":"Z\u00fcrich",
    "wof:name":"Ortsmuseum Herrn J\u00fcrg Stutz",
    "wof:placetype":"venue"
},
  "geometry": {"coordinates":[8.7790136337,47.5287055969],"type":"Point"}
}