{
  "type": "Feature",
  "properties": {
    "iso:country":"CH",
    "sg:address":"Buchholzstrasse 3 8702 Zollikon. Postfach 18",
    "sg:city":"Zollikon",
    "sg:orig_category":"Grosshandel mit Schmuck Grosshandel mit Uhren",
    "sg:phone":"+41 13918954",
    "sg:postcode":"8702",
    "sg:province":"Z\u00fcrich",
    "wof:name":"Rietmann Ag",
    "wof:placetype":"venue"
},
  "geometry": {"coordinates":[8.5749835968,47.338508606],"type":"Point"}
}