{
  "type": "Feature",
  "properties": {
    "iso:country":"CH",
    "sg:address":"Julierstrasse",
    "sg:city":"Tiefencastel",
    "sg:orig_category":"Institutionen f\u00fcr Behinderte Tagesheime f\u00fcr Behinderte, gesch\u00fctzte Werkst\u00e4tten",
    "sg:phone":"+41 81 681 15 70",
    "sg:postcode":"7450",
    "sg:province":"Graubunden",
    "wof:name":"Argo B\u00fcndn.werkst\u00e4tten & Wohnheime F\u00fcr Behinderte",
    "wof:placetype":"venue"
},
  "geometry": {"coordinates":[9.5766401291,46.6592445374],"type":"Point"}
}