{
  "type": "Feature",
  "properties": {
    "iso:country":"CH",
    "sg:address":"Rue De Gare 5",
    "sg:city":"Villeret",
    "sg:orig_category":"Gesundheitswesen Unterhaltung, Kultur U Sport",
    "sg:phone":"+41 32 941 24 28",
    "sg:postcode":"2613",
    "sg:province":"Bern",
    "wof:name":"Zbinden Reto Madras Yoga-institut F\u00fcr Klassisches Yoga",
    "wof:placetype":"venue"
},
  "geometry": {"coordinates":[7.018201828,47.1588249207],"type":"Point"}
}