{
  "type": "Feature",
  "properties": {
    "iso:country":"CH",
    "sg:address":"Via Galbisio 2",
    "sg:city":"Bellinzona",
    "sg:orig_category":"Detailhandel mit Waren verschiedener Art, Hauptrichtung Nahrungsmittel",
    "sg:phone":"+41 91 825 03 01",
    "sg:postcode":"6503",
    "sg:province":"Ticino",
    "wof:name":"Coop Di Carasso",
    "wof:placetype":"venue"
},
  "geometry": {"coordinates":[9.0153121948,46.2031707764],"type":"Point"}
}