{
  "type": "Feature",
  "properties": {
    "iso:country":"CH",
    "sg:address":"Cornavin Rue De 9",
    "sg:city":"Gen\u00e8ve",
    "sg:orig_category":"Detailhandel mit Bekleidung",
    "sg:phone":"+41 22 734 75 54",
    "sg:postcode":"1201",
    "sg:province":"Gen\u00e8ve",
    "wof:name":"Dussetier Christian.",
    "wof:placetype":"venue"
},
  "geometry": {"coordinates":[6.143124,46.210506],"type":"Point"}
}