{
  "type": "Feature",
  "properties": {
    "iso:country":"CH",
    "sg:address":"Z\u00e4hringerstrasse 24 8001 Z\u00fcrich. Postfach 877",
    "sg:city":"Z\u00fcrich",
    "sg:orig_category":"Werbegrafikateliers",
    "sg:phone":"+41 12623376",
    "sg:postcode":"8025",
    "wof:name":"Rolf B. Willi Grafisches Atelier",
    "wof:placetype":"venue"
},
  "geometry": {"coordinates":[8.5448141098,47.3752250671],"type":"Point"}
}