{
  "type": "Feature",
  "properties": {
    "iso:country":"CH",
    "sg:address":"Missionsstrasse 56",
    "sg:city":"Basel",
    "sg:orig_category":"G\u00fcterbef\u00f6rderung im Strassenverkehr Handelsvermittlung U Grosshandel",
    "sg:phone":"+41 61 381 20 00",
    "sg:postcode":"4055",
    "sg:province":"Basel-Stadt",
    "wof:name":"Nyffenegger Gebr. Gmbh",
    "wof:placetype":"venue"
},
  "geometry": {"coordinates":[7.5756859779,47.5609931946],"type":"Point"}
}