{
  "type": "Feature",
  "properties": {
    "iso:country":"CH",
    "sg:address":"Lufingerstrasse 42",
    "sg:city":"Winkel",
    "sg:orig_category":"Herstellung von Hebezeugen U F\u00f6rdermitteln",
    "sg:phone":"+41 18607997",
    "sg:postcode":"8185",
    "sg:province":"Z\u00fcrich",
    "wof:name":"Leemann Kurt, Liftmontagen + Reparaturen",
    "wof:placetype":"venue"
},
  "geometry": {"coordinates":[8.5656833649,47.4798088074],"type":"Point"}
}