{
  "type": "Feature",
  "properties": {
    "iso:country":"CH",
    "sg:address":"Steinerbergstrasse 2",
    "sg:city":"Sattel",
    "sg:orig_category":"G\u00fcterbef\u00f6rderung im Strassenverkehr",
    "sg:phone":"+41 41 835 11 77",
    "sg:postcode":"6417",
    "sg:province":"Schwyz",
    "wof:name":"Josef Krienb\u00fchl Autotransporte",
    "wof:placetype":"venue"
},
  "geometry": {"coordinates":[8.6299228668,47.0791778564],"type":"Point"}
}