{
  "type": "Feature",
  "properties": {
    "iso:country":"CH",
    "sg:address":"Stationsstrasse 49 8902 Urdorf. Postfach",
    "sg:city":"Urdorf",
    "sg:orig_category":"Grosshandel mit sonstigen Maschinen U Ausr\u00fcstungen f\u00fcr Industrie, Handel U Schiffahrt",
    "sg:phone":"+41 17340566",
    "sg:postcode":"8902",
    "sg:province":"Z\u00fcrich",
    "wof:name":"Johnson Controls Systems Ag",
    "wof:placetype":"venue"
},
  "geometry": {"coordinates":[8.4336900711,47.3904304504],"type":"Point"}
}