{
  "type": "Feature",
  "properties": {
    "iso:country":"CH",
    "sg:address":"Simplon Route Du 35b",
    "sg:city":"Mayens-de-saxon",
    "sg:orig_category":"Detailhandel mit elektrischen Haushalts-,Radio U Fernsehger\u00e4ten sowie Musikinstrumenten",
    "sg:postcode":"1907",
    "sg:province":"Valais",
    "wof:name":"Ideal Casa, Lopes Da Silva Luisa",
    "wof:placetype":"venue"
},
  "geometry": {"coordinates":[7.1736750603,46.148891449],"type":"Point"}
}