{
  "type": "Feature",
  "properties": {
    "iso:country":"CH",
    "sg:address":"Moosbachweg 11",
    "sg:city":"Zug",
    "sg:orig_category":"Grosshandel mit sonstigen Halbwaren",
    "sg:phone":"+41 17812211",
    "sg:postcode":"6300",
    "sg:province":"Zug",
    "wof:name":"Cawapac Ag Cartonnagefabrik",
    "wof:placetype":"venue"
},
  "geometry": {"coordinates":[8.6493587494,47.2459144592],"type":"Point"}
}