{
  "type": "Feature",
  "properties": {
    "iso:country":"CH",
    "sg:address":"B\u00f6sbachstrasse 16",
    "sg:city":"Steffisburg",
    "sg:orig_category":"Non-Classified Establishments",
    "sg:phone":"+41 33 437 82 82",
    "sg:postcode":"3612",
    "sg:province":"Bern",
    "wof:name":"Alcomsys Gmbh Computer Systeme",
    "wof:placetype":"venue"
},
  "geometry": {"coordinates":[7.6358771324,46.7748146057],"type":"Point"}
}