{
  "type": "Feature",
  "properties": {
    "iso:country":"CH",
    "sg:address":"Lerchenfeldstrasse 12",
    "sg:city":"Wil",
    "sg:classifiers":[
        {
            "category":"Banks & Credit Unions",
            "subcategory":"Bank",
            "type":"Services"
        }
    ],
    "sg:phone":"+41 33 822 92 29",
    "sg:postcode":"9500",
    "sg:province":"St. Gallen",
    "wof:name":"Raiffeisenbank Wilderswil Gsteigwiler Saxeten",
    "wof:placetype":"venue"
},
  "geometry": {"coordinates":[7.86737,46.665119],"type":"Point"}
}