{
  "type": "Feature",
  "properties": {
    "iso:country":"CH",
    "sg:address":"Dorfstrasse 49b",
    "sg:city":"Obfelden",
    "sg:orig_category":"Allgemeiner Hoch U Tiefbau",
    "sg:phone":"+41 17614214",
    "sg:postcode":"8912",
    "sg:province":"Z\u00fcrich",
    "wof:name":"M\u00fcller Richard, Bauunternehmung",
    "wof:placetype":"venue"
},
  "geometry": {"coordinates":[8.426158,47.263168],"type":"Point"}
}