{
  "type": "Feature",
  "properties": {
    "addr:full":"1669 Albeuve Fribourg 1669",
    "addr:housenumber":"1669",
    "addr:postcode":"1669",
    "addr:street":"Albeuve Fribourg",
    "iso:country":"CH",
    "sg:address":"1669",
    "sg:city":"Albeuve",
    "sg:orig_category":"B\u00e4ckereien Konditoreien",
    "sg:phone":"+41 26 928 11 29",
    "sg:postcode":"1669",
    "sg:province":"Fribourg",
    "wof:name":"Charly & Martine Sottas Boulangerie Et P\u00e2tisserie",
    "wof:placetype":"venue"
},
  "geometry": {"coordinates":[7.05588,46.518822],"type":"Point"}
}