{
  "type": "Feature",
  "properties": {
    "iso:country":"CH",
    "sg:address":"Gottefrey",
    "sg:city":"Mayens-de-saxon",
    "sg:orig_category":"Fachdetailhandel mit pharmazeutischen Produkten",
    "sg:phone":"+41 27 744 27 17",
    "sg:postcode":"1907",
    "sg:province":"Valais",
    "wof:name":"Farmill Sa",
    "wof:placetype":"venue"
},
  "geometry": {"coordinates":[7.1738901138,46.1487731934],"type":"Point"}
}