{
  "type": "Feature",
  "properties": {
    "iso:country":"CH",
    "sg:address":"Weissenb\u00fchlweg 4-6",
    "sg:city":"Bern",
    "sg:orig_category":"Betrieb von Taxis Tankstellen",
    "sg:phone":"+41 52 383 16 90",
    "sg:postcode":"3007",
    "sg:province":"Bern",
    "wof:name":"Hansruedi Inhelder Taxi & Tankstelle",
    "wof:placetype":"venue"
},
  "geometry": {"coordinates":[8.793536,47.449909],"type":"Point"}
}