{
  "type": "Feature",
  "properties": {
    "iso:country":"CH",
    "sg:address":"Passerellenweg 17",
    "sg:city":"Biel/bienne",
    "sg:orig_category":"Tierarztpraxis",
    "sg:phone":"+41 32 365 62 82",
    "sg:postcode":"2503",
    "sg:province":"Bern",
    "wof:name":"Dr. Med. Vet. Peter Weber Tierarzt",
    "wof:placetype":"venue"
},
  "geometry": {"coordinates":[7.2581129074,47.1348724365],"type":"Point"}
}