{
  "type": "Feature",
  "properties": {
    "iso:country":"CH",
    "sg:address":"Route De Lausanne 16 1052 Mont-sur-lausanne. Postfach",
    "sg:city":"Mont-sur-lausanne",
    "sg:orig_category":"Gemeindeverwaltungen",
    "sg:phone":"+41 32 954 14 73",
    "sg:postcode":"1052",
    "sg:province":"Vaud",
    "wof:name":"Administration Communale De Le Peuchapatte",
    "wof:placetype":"venue"
},
  "geometry": {"coordinates":[6.9652261734,47.1979751587],"type":"Point"}
}