{
  "type": "Feature",
  "properties": {
    "iso:country":"CH",
    "sg:address":"Binningerstrasse 92",
    "sg:city":"Allschwil",
    "sg:orig_category":"Fotografisches Gewerbe U fotografische Laboratorien",
    "sg:phone":"+41 41 630 29 74",
    "sg:postcode":"4123",
    "sg:province":"Basel-Landschaft",
    "wof:name":"C. Kipfer",
    "wof:placetype":"venue"
},
  "geometry": {"coordinates":[8.3099946976,46.9968833923],"type":"Point"}
}