{
  "type": "Feature",
  "properties": {
    "iso:country":"CH",
    "sg:address":"Aamattweg 13",
    "sg:city":"Sarnen",
    "sg:orig_category":"Autolackierereien",
    "sg:phone":"+41 41 660 23 53",
    "sg:postcode":"6060",
    "sg:province":"Obwalden",
    "wof:name":"Hans-werner Hess Autospritzwerk",
    "wof:placetype":"venue"
},
  "geometry": {"coordinates":[8.240156,46.891205],"type":"Point"}
}