{
  "type": "Feature",
  "properties": {
    "iso:country":"CH",
    "sg:address":"Route De Gr\u00f4ne",
    "sg:city":"Bramois",
    "sg:orig_category":"Autospenglereien",
    "sg:phone":"+41 27 203 13 58",
    "sg:postcode":"1967",
    "sg:province":"Valais",
    "wof:name":"Carrosserie Des Vergers",
    "wof:placetype":"venue"
},
  "geometry": {"coordinates":[7.40268,46.230122],"type":"Point"}
}