{
  "type": "Feature",
  "properties": {
    "iso:country":"CH",
    "sg:address":"Promenade Maladaire",
    "sg:city":"Payerne",
    "sg:orig_category":"Verarbeitung U Konservierung von Obst U Gem\u00fcse",
    "sg:phone":"+41 22 342 00 85",
    "sg:postcode":"1530",
    "sg:province":"Vaud",
    "wof:name":"Eugene Gras Sa Conserves Alimentaires",
    "wof:placetype":"venue"
},
  "geometry": {"coordinates":[6.1357841492,46.1866798401],"type":"Point"}
}