{
  "type": "Feature",
  "properties": {
    "iso:country":"CH",
    "sg:address":"Allmendstrasse 25 8953 Dietikon. Postfach",
    "sg:city":"Dietikon",
    "sg:orig_category":"Non-Classified Establishments",
    "sg:postcode":"8953",
    "sg:province":"Z\u00fcrich",
    "wof:name":"Dosim Holding Sa",
    "wof:placetype":"venue"
},
  "geometry": {"coordinates":[6.1107001305,46.2323417664],"type":"Point"}
}