{
  "type": "Feature",
  "properties": {
    "iso:country":"CH",
    "sg:address":"Dorfstrasse 35 3457 Wasen Im Emmental. Postfach 198",
    "sg:city":"Sumiswald",
    "sg:orig_category":"Grosshandel mit Eisenwaren sowie Installationsbedarf f\u00fcr Gas, Wasser U Heizung Handel mit Motorr\u00e4der",
    "sg:phone":"+41 34 437 16 30",
    "sg:postcode":"3454",
    "sg:province":"Bern",
    "wof:name":"Pfister Hans, Nachfolger Pfister R. + M.",
    "wof:placetype":"venue"
},
  "geometry": {"coordinates":[7.798145771,47.043762207],"type":"Point"}
}