{
  "type": "Feature",
  "properties": {
    "iso:country":"CH",
    "sg:address":"Dorfstrasse 33a",
    "sg:city":"Baar",
    "sg:orig_category":"Mit dem Versicherungsgewerbe verbundene T\u00e4tigkeiten",
    "sg:postcode":"6340",
    "sg:province":"Zug",
    "wof:name":"Attraktivfinanz Gmbh",
    "wof:placetype":"venue"
},
  "geometry": {"coordinates":[8.5234556198,47.1934776306],"type":"Point"}
}