{
  "type": "Feature",
  "properties": {
    "iso:country":"CH",
    "sg:address":"Surentalstrasse 10",
    "sg:city":"Sursee",
    "sg:orig_category":"Informatikschulen Satzherstellung U Reproduktion",
    "sg:phone":"+41 33 951 42 82",
    "sg:postcode":"6210",
    "sg:province":"Luzern",
    "wof:name":"Desktype",
    "wof:placetype":"venue"
},
  "geometry": {"coordinates":[8.0759716034,46.754573822],"type":"Point"}
}