{
  "type": "Feature",
  "properties": {
    "iso:country":"CH",
    "sg:address":"St\u00e4dtle 2",
    "sg:city":"Vaduz",
    "sg:orig_category":"Detailhandel mit Damenbekleidung Detailhandel mit Herrenbekleidung",
    "sg:phone":"+41 79 418 17 17",
    "sg:postcode":"9490",
    "wof:name":"Brogle Sport & Mode",
    "wof:placetype":"venue"
},
  "geometry": {"coordinates":[9.5212574005,47.1410064697],"type":"Point"}
}