{
  "type": "Feature",
  "properties": {
    "iso:country":"CH",
    "sg:address":"Kirchstrasse 34",
    "sg:city":"Freienbach",
    "sg:orig_category":"RESTAURANTS: TEA-ROOMS",
    "sg:phone":"+41 34 435 12 58",
    "sg:postcode":"8807",
    "sg:province":"Schwyz",
    "wof:name":"Restaurant Zum Tannenbad",
    "wof:placetype":"venue"
},
  "geometry": {"coordinates":[7.748360157,47.0614089966],"type":"Point"}
}