{
  "type": "Feature",
  "properties": {
    "iso:country":"CH",
    "sg:address":"Moncor 2 Route De",
    "sg:city":"Villars-sur-gl\u00e2ne",
    "sg:orig_category":"Architektur U Ingenieurb\u00fcros",
    "sg:phone":"+41 21 651 25 00",
    "sg:postcode":"1752",
    "sg:province":"Fribourg",
    "wof:name":"Orraco Sa",
    "wof:placetype":"venue"
},
  "geometry": {"coordinates":[7.130429,46.795582],"type":"Point"}
}