{
  "type": "Feature",
  "properties": {
    "iso:country":"CH",
    "sg:address":"Baarerstrasse 47",
    "sg:city":"Zug",
    "sg:orig_category":"Kunsthandel Maler U Glasergewerbe",
    "sg:phone":"+41 41 711 56 18",
    "sg:postcode":"6300",
    "sg:province":"Zug",
    "wof:name":"Koller Hermann",
    "wof:placetype":"venue"
},
  "geometry": {"coordinates":[8.5168762207,47.1742706299],"type":"Point"}
}