{
  "type": "Feature",
  "properties": {
    "iso:country":"CH",
    "sg:address":"Bahnhofstrasse 27 3360 Herzogenbuchsee. Postfach 288",
    "sg:city":"Herzogenbuchsee",
    "sg:orig_category":"Grosshandel mit Milch, Milcherzeugnissen, Eiern, Speise\u00f6len U Nahrungsfetten Sonstiger Fachdetailhan",
    "sg:phone":"+41 62 961 12 52",
    "sg:postcode":"3360",
    "sg:province":"Bern",
    "wof:name":"Roethlisberger Ag",
    "wof:placetype":"venue"
},
  "geometry": {"coordinates":[7.7014298439,47.1879692078],"type":"Point"}
}