{
  "type": "Feature",
  "properties": {
    "iso:country":"CH",
    "sg:address":"Chemin De La Fontaine 2 1260 Nyon. Postfach",
    "sg:city":"Nyon",
    "sg:orig_category":"Herstellung von homogenisierten U di\u00e4tetischen Nahrungsmitteln",
    "sg:postcode":"1260",
    "sg:province":"Vaud",
    "wof:name":"R\u00fctsche Daniel",
    "wof:placetype":"venue"
},
  "geometry": {"coordinates":[6.2208580971,46.3871002197],"type":"Point"}
}