{
  "type": "Feature",
  "properties": {
    "iso:country":"CH",
    "sg:address":"Wiler Strasse 1692 9230 Flawil. Postfach",
    "sg:city":"Flawil",
    "sg:orig_category":"Herstellung von Metallkonstruktionen Treibhaus- and Wintergartenbau",
    "sg:phone":"+41 71 393 51 50",
    "sg:postcode":"9230",
    "sg:province":"St. Gallen",
    "wof:name":"Rws Metallbau + Stahlbau Gmbh Metallbau- U. Stahlbaukonstruktionen Wie T\u00fcren, Fenster, Gel\u00e4nder Usw.; Herstellung U. Montage",
    "wof:placetype":"venue"
},
  "geometry": {"coordinates":[9.1668195724,47.4171791077],"type":"Point"}
}