{
  "type": "Feature",
  "properties": {
    "iso:country":"CH",
    "sg:address":"Hubel 58",
    "sg:city":"Obersteckholz",
    "sg:orig_category":"Maurerarbeiten Verlegen von Fliesen U Platten",
    "sg:phone":"+41 62 923 17 02",
    "sg:postcode":"4924",
    "sg:province":"Bern",
    "wof:name":"Michael Kiefer Bauservice",
    "wof:placetype":"venue"
},
  "geometry": {"coordinates":[7.8212270737,47.2030601501],"type":"Point"}
}