{
  "type": "Feature",
  "properties": {
    "iso:country":"CH",
    "sg:address":"Wenkenr\u00fctistrasse 20",
    "sg:city":"Wattwil",
    "sg:orig_category":"Herstellung von \u00d6fen U Brennern Verlegen von Fliesen U Platten",
    "sg:phone":"+41 71 223 36 04",
    "sg:postcode":"9630",
    "sg:province":"St. Gallen",
    "wof:name":"Buck J. Ag, St. Gallen",
    "wof:placetype":"venue"
},
  "geometry": {"coordinates":[9.378493309,47.422706604],"type":"Point"}
}