{
  "type": "Feature",
  "properties": {
    "iso:country":"CH",
    "sg:address":"S\u00e4delstrasse 31",
    "sg:city":"Gerzensee",
    "sg:orig_category":"Non-Classified Establishments",
    "sg:postcode":"3115",
    "sg:province":"Bern",
    "wof:name":"Simona Cs Consulting",
    "wof:placetype":"venue"
},
  "geometry": {"coordinates":[7.5316710472,46.8415718079],"type":"Point"}
}