{
  "type": "Feature",
  "properties": {
    "iso:country":"CH",
    "sg:address":"Guggig\u00e4ssli 24",
    "sg:city":"Frutigen",
    "sg:classifiers":[
        {
            "category":"Insurance",
            "subcategory":"Insurance Agent",
            "type":"Services"
        }
    ],
    "sg:phone":"+41 33 671 54 84",
    "sg:postcode":"3714",
    "sg:province":"Bern",
    "sg:tags":[
        "versicherungsagenturen",
        "-broker"
    ],
    "wof:name":"Norbert Zurbriggen Versicherungs-treuhand",
    "wof:placetype":"venue"
},
  "geometry": {"coordinates":[7.6549901962,46.5812683105],"type":"Point"}
}