{
  "type": "Feature",
  "properties": {
    "iso:country":"CH",
    "sg:address":"Murtenstrasse 13",
    "sg:city":"Kerzers",
    "sg:orig_category":"Zahnarztpraxen",
    "sg:phone":"+41 31 755 66 00",
    "sg:postcode":"3210",
    "sg:province":"Fribourg",
    "wof:name":"Dr.med.dent.j\u00fcrg M. Schneiter Zahnarzt",
    "wof:placetype":"venue"
},
  "geometry": {"coordinates":[7.1945238113,46.9742393494],"type":"Point"}
}