{
  "type": "Feature",
  "properties": {
    "iso:country":"CH",
    "sg:address":"1417",
    "sg:city":"Essertines-yverdon",
    "sg:classifiers":[
        {
            "category":"Travel",
            "subcategory":"Hotels & Motels",
            "type":"Entertainment"
        }
    ],
    "sg:postcode":"1417",
    "sg:province":"Vaud",
    "sg:tags":[
        "hotels",
        "mit",
        "restaurant"
    ],
    "wof:name":"Scamuffa Pietro",
    "wof:placetype":"venue"
},
  "geometry": {"coordinates":[6.6399297714,46.7164115906],"type":"Point"}
}