{
  "type": "Feature",
  "properties": {
    "iso:country":"CH",
    "sg:address":"Strada Cantonale",
    "sg:city":"Bironico",
    "sg:orig_category":"Tankstellen",
    "sg:phone":"+41 91 946 48 77",
    "sg:postcode":"6804",
    "sg:province":"Ticino",
    "wof:name":"Bottinelli Alberto",
    "wof:placetype":"venue"
},
  "geometry": {"coordinates":[8.9310903549,46.1136741638],"type":"Point"}
}