{
  "type": "Feature",
  "properties": {
    "iso:country":"CH",
    "sg:address":"Clos-donzel 1",
    "sg:city":"Fleurier",
    "sg:orig_category":"Bauschreinerei Herstellung von Konstruktionsteilen, Fertigbauteilen U Ausbauelementen aus Holz",
    "sg:phone":"+41 32 725 52 58",
    "sg:postcode":"2114",
    "sg:province":"Neuch\u00e2tel",
    "wof:name":"Menuiserie Schray Fr\u00e8res S\u00e0rl",
    "wof:placetype":"venue"
},
  "geometry": {"coordinates":[6.935285,46.997677],"type":"Point"}
}