{
  "type": "Feature",
  "properties": {
    "iso:country":"CH",
    "sg:address":"Zwinghofstrasse 23",
    "sg:city":"Diepoldsau",
    "sg:orig_category":"Instandhaltung U Reparatur von Automobilen",
    "sg:phone":"+41 71 733 20 07",
    "sg:postcode":"9444",
    "sg:province":"St. Gallen",
    "wof:name":"Carrosserie Kiss",
    "wof:placetype":"venue"
},
  "geometry": {"coordinates":[9.6600399017,47.3907737732],"type":"Point"}
}