{
  "type": "Feature",
  "properties": {
    "iso:country":"CH",
    "sg:address":"Werkstrasse 7",
    "sg:city":"Arnegg",
    "sg:orig_category":"Datenbanken",
    "sg:postcode":"9212",
    "sg:province":"St. Gallen",
    "wof:name":"Lsr Ag",
    "wof:placetype":"venue"
},
  "geometry": {"coordinates":[9.253381,47.441757],"type":"Point"}
}