{
  "type": "Feature",
  "properties": {
    "iso:country":"CH",
    "sg:address":"Rue De Guillermaux 17",
    "sg:city":"Payerne",
    "sg:classifiers":[
        {
            "category":"Education",
            "subcategory":"Library",
            "type":"Public Place"
        }
    ],
    "sg:phone":"+41 26 660 10 06",
    "sg:postcode":"1530",
    "sg:province":"Vaud",
    "sg:tags":[
        "u",
        "bibliotheken",
        "archive"
    ],
    "wof:name":"Biblioth\u00e8que Paroissiale Catholique",
    "wof:placetype":"venue"
},
  "geometry": {"coordinates":[6.934995,46.81908],"type":"Point"}
}