{
  "type": "Feature",
  "properties": {
    "iso:country":"CH",
    "sg:address":"Birkenweg 15",
    "sg:city":"Ostermundigen",
    "sg:orig_category":"Gesundheitswesen",
    "sg:postcode":"3072",
    "sg:province":"Bern",
    "wof:name":"Torn\u00e9 Jean 'dream & Be'",
    "wof:placetype":"venue"
},
  "geometry": {"coordinates":[7.4854421616,46.947227478],"type":"Point"}
}