{
  "type": "Feature",
  "properties": {
    "iso:country":"CH",
    "sg:address":"Kreuzwegacker 1",
    "sg:city":"M\u00fcnsingen",
    "sg:orig_category":"Grosshandel mit sonstigen Gebrauchs U Verbrauchsg\u00fctern",
    "sg:phone":"+41 31 721 00 28",
    "sg:postcode":"3110",
    "sg:province":"Bern",
    "wof:name":"M-pearl Design Meier F.",
    "wof:placetype":"venue"
},
  "geometry": {"coordinates":[7.5706391335,46.8800163269],"type":"Point"}
}