{
  "type": "Feature",
  "properties": {
    "iso:country":"CH",
    "sg:address":"7235",
    "sg:city":"Fideris",
    "sg:classifiers":[
        {
            "category":"Restaurant",
            "type":"Food & Drink"
        }
    ],
    "sg:phone":"+41 81 332 13 05",
    "sg:postcode":"7235",
    "sg:province":"Graubunden",
    "wof:name":"Bergrestaurant Heuberge",
    "wof:placetype":"venue"
},
  "geometry": {"coordinates":[9.7427120209,46.9152984619],"type":"Point"}
}