{
  "type": "Feature",
  "properties": {
    "iso:country":"CH",
    "sg:address":"Subergstrasse 20",
    "sg:city":"Grossaffoltern",
    "sg:orig_category":"Fussboden, Fliesen U Plattenlegerei, Tapeziererei Verlegen von Fussboden",
    "sg:phone":"+41 32 389 16 76",
    "sg:postcode":"3257",
    "sg:province":"Bern",
    "wof:name":"Hans-rudolf Loder Kunststoffbel\u00e4ge",
    "wof:placetype":"venue"
},
  "geometry": {"coordinates":[7.3523540497,47.062877655],"type":"Point"}
}