{
  "type": "Feature",
  "properties": {
    "iso:country":"CH",
    "sg:address":"Zilfuri",
    "sg:city":"Kandersteg",
    "sg:orig_category":"Sportvereine Sch\u00fctzen",
    "sg:phone":"+41 34 445 59 44",
    "sg:postcode":"3718",
    "sg:province":"Bern",
    "wof:name":"Freisch\u00fctzen Kirchberg",
    "wof:placetype":"venue"
},
  "geometry": {"coordinates":[7.5844497681,47.0851783752],"type":"Point"}
}