{
  "type": "Feature",
  "properties": {
    "iso:country":"CH",
    "sg:address":"Im G\u00e4ssli 13",
    "sg:city":"Staufen",
    "sg:orig_category":"Non-Classified Establishments",
    "sg:postcode":"5603",
    "sg:province":"Aargau",
    "wof:name":"Frigart Gmbh",
    "wof:placetype":"venue"
},
  "geometry": {"coordinates":[8.1675806046,47.3821372986],"type":"Point"}
}