{
  "type": "Feature",
  "properties": {
    "iso:country":"CH",
    "sg:address":"Rathausgasse 32",
    "sg:city":"Lenzburg",
    "sg:orig_category":"Architektur U Ingenieurb\u00fcros Architekturb\u00fcros",
    "sg:phone":"+41 56 667 39 72",
    "sg:postcode":"5600",
    "sg:province":"Aargau",
    "wof:name":"Roland H\u00fcsser-barp Gmbh F\u00fcr Baukunst",
    "wof:placetype":"venue"
},
  "geometry": {"coordinates":[8.180714,47.387138],"type":"Point"}
}