{
  "type": "Feature",
  "properties": {
    "iso:country":"CH",
    "sg:address":"Thesenacher 12",
    "sg:city":"Zumikon",
    "sg:orig_category":"Herstellung von k\u00e4lte U lufttechnischen Erzeugnissen f\u00fcr gewerbliche Zwecke Sanit\u00e4rinstallation",
    "sg:phone":"+41 19182143",
    "sg:postcode":"8126",
    "sg:province":"Z\u00fcrich",
    "wof:name":"Ganz Installationen Ag",
    "wof:placetype":"venue"
},
  "geometry": {"coordinates":[8.6333770752,47.3271903992],"type":"Point"}
}