{
  "type": "Feature",
  "properties": {
    "iso:country":"CH",
    "sg:address":"Weierenstrasse 28",
    "sg:city":"Z\u00fcberwangen",
    "sg:orig_category":"G\u00fcterbef\u00f6rderung im Strassenverkehr",
    "sg:phone":"+41 71 944 24 09",
    "sg:postcode":"9523",
    "sg:province":"St. Gallen",
    "wof:name":"Brunner Hermann, Transporte",
    "wof:placetype":"venue"
},
  "geometry": {"coordinates":[9.1021680832,47.4642028809],"type":"Point"}
}