{
  "type": "Feature",
  "properties": {
    "iso:country":"CH",
    "sg:address":"Webergutstrasse 12",
    "sg:city":"Zollikofen",
    "sg:orig_category":"G\u00fcterbef\u00f6rderung im Strassenverkehr",
    "sg:phone":"+41 71 313 91 50",
    "sg:postcode":"3052",
    "sg:province":"Bern",
    "wof:name":"Stadler Transport Ag Autotransporte",
    "wof:placetype":"venue"
},
  "geometry": {"coordinates":[9.3160448074,47.4161949158],"type":"Point"}
}