{
  "type": "Feature",
  "properties": {
    "iso:country":"CH",
    "sg:address":"3507",
    "sg:city":"Biglen",
    "sg:classifiers":[
        {
            "category":"Education",
            "subcategory":"Vocational School",
            "type":"Public Place"
        }
    ],
    "sg:postcode":"3507",
    "sg:province":"Bern",
    "sg:tags":[
        "koch-",
        "haushaltschulen"
    ],
    "wof:name":"Haushaltungsschule",
    "wof:placetype":"venue"
},
  "geometry": {"coordinates":[7.6302599907,46.9310417175],"type":"Point"}
}