{
  "type": "Feature",
  "properties": {
    "iso:country":"CH",
    "sg:address":"Chemin De La Bergerie 8",
    "sg:city":"Cartigny",
    "sg:orig_category":"Non-Classified Establishments",
    "sg:phone":"+41 22 756 20 48",
    "sg:postcode":"1236",
    "sg:province":"Gen\u00e8ve",
    "wof:name":"Remember, Pelz",
    "wof:placetype":"venue"
},
  "geometry": {"coordinates":[6.0233998299,46.1727714539],"type":"Point"}
}