{
  "type": "Feature",
  "properties": {
    "iso:country":"CH",
    "sg:address":"Zollikerstrasse 204 8008 Z\u00fcrich. Postfach",
    "sg:city":"Z\u00fcrich",
    "sg:orig_category":"Unternehmensberatung",
    "sg:phone":"+41 61 402 00 12",
    "sg:postcode":"8001",
    "sg:province":"Z\u00fcrich",
    "wof:name":"Navicom Gmbh",
    "wof:placetype":"venue"
},
  "geometry": {"coordinates":[7.5445079803,47.511264801],"type":"Point"}
}