{
  "type": "Feature",
  "properties": {
    "iso:country":"CH",
    "sg:address":"Grande-avenue 2",
    "sg:city":"Chippis",
    "sg:orig_category":"Detailhandel mit Fleisch U Fleischwaren",
    "sg:phone":"+41 27 455 11 81",
    "sg:postcode":"3965",
    "sg:province":"Valais",
    "wof:name":"Gloor Kurt",
    "wof:placetype":"venue"
},
  "geometry": {"coordinates":[7.5410528183,46.2818489075],"type":"Point"}
}