{
  "type": "Feature",
  "properties": {
    "iso:country":"CH",
    "sg:address":"Grand-donzel Chemin Du 56 1234 Vessy. Postfach",
    "sg:city":"Vessy",
    "sg:orig_category":"Finanzierungsinstitutionen",
    "sg:postcode":"1234",
    "sg:province":"Gen\u00e8ve",
    "wof:name":"Global Care Ag Kapitalanlage An Unternehmen, Die Sich Im Sinne Einer Sozialen, \u00f6kologischen Und Wirtschaftlichen Nachhaltigkeit Einsetzen Und Ausrichten",
    "wof:placetype":"venue"
},
  "geometry": {"coordinates":[8.3101320267,46.9945487976],"type":"Point"}
}