{
  "type": "Feature",
  "properties": {
    "iso:country":"CH",
    "sg:address":"Maillefer Chemin De 35 1018 Lausanne. Postfach",
    "sg:city":"Lausanne",
    "sg:orig_category":"Saunas, Solarien, Fitnesszentren U \u00e4hnliches",
    "sg:postcode":"1018",
    "sg:province":"Vaud",
    "wof:name":"Profil, Locatelli Alexandre",
    "wof:placetype":"venue"
},
  "geometry": {"coordinates":[6.857986927,46.9656143188],"type":"Point"}
}