{
  "type": "Feature",
  "properties": {
    "iso:country":"CH",
    "sg:address":"L\u00e4ttenstrasse 4",
    "sg:city":"Schlieren",
    "sg:orig_category":"Softwareentwicklung U beratung",
    "sg:postcode":"8952",
    "sg:province":"Z\u00fcrich",
    "wof:name":"Taurasi Gmbh",
    "wof:placetype":"venue"
},
  "geometry": {"coordinates":[8.4438991547,47.4030609131],"type":"Point"}
}