{
  "type": "Feature",
  "properties": {
    "iso:country":"CH",
    "sg:address":"Peupliers Chemin Des 7",
    "sg:city":"Savigny",
    "sg:orig_category":"Handels-H\u00e4user U Gesellschaften",
    "sg:phone":"+41 21 807 10 92",
    "sg:postcode":"1073",
    "sg:province":"Vaud",
    "wof:name":"Cb Consulting & Communication Buttex Et Cie",
    "wof:placetype":"venue"
},
  "geometry": {"coordinates":[6.7320752144,46.5383605957],"type":"Point"}
}