{
  "type": "Feature",
  "properties": {
    "iso:country":"CH",
    "sg:address":"Route Du Jura 37 1700 Fribourg. Postfach",
    "sg:city":"Fribourg",
    "sg:orig_category":"Erschliessung von Grundst\u00fccken",
    "sg:postcode":"1706",
    "wof:name":"Cit\u00e9 De L'est La Chaux-de-fonds",
    "wof:placetype":"venue"
},
  "geometry": {"coordinates":[6.8282241821,47.1015625],"type":"Point"}
}