{
  "type": "Feature",
  "properties": {
    "addr:full":"Via Pretorio 7 Lugano Ticino 6900",
    "addr:housenumber":"7",
    "addr:postcode":"6900",
    "addr:street":"Via Pretorio",
    "iso:country":"CH",
    "sg:address":"Via Pretorio 7",
    "sg:city":"Lugano",
    "sg:orig_category":"Detailhandel mit Antiquit\u00e4ten Detailhandel mit Teppichen",
    "sg:phone":"+41 91 921 31 11",
    "sg:postcode":"6900",
    "sg:province":"Ticino",
    "wof:name":"Storica Sa",
    "wof:placetype":"venue"
},
  "geometry": {"coordinates":[8.951465,46.00565],"type":"Point"}
}