{
  "type": "Feature",
  "properties": {
    "iso:country":"CH",
    "sg:address":"Kasernenstrasse 83 7000 Chur. Postfach 84",
    "sg:city":"Chur",
    "sg:classifiers":[
        {
            "category":"Restaurant",
            "type":"Food & Drink"
        }
    ],
    "sg:phone":"+41 81 252 28 08",
    "sg:postcode":"7007",
    "sg:province":"Graubunden",
    "wof:name":"Restaurant Westend",
    "wof:placetype":"venue"
},
  "geometry": {"coordinates":[9.5205783844,46.8469619751],"type":"Point"}
}