{
  "type": "Feature",
  "properties": {
    "addr:full":"Luterbachstrasse Zuchwil Solothurn 4528",
    "addr:postcode":"4528",
    "addr:street":"Luterbachstrasse",
    "iso:country":"CH",
    "sg:address":"Luterbachstrasse",
    "sg:city":"Zuchwil",
    "sg:orig_category":"Abwasserreinigung",
    "sg:phone":"+41 32 685 38 49",
    "sg:postcode":"4528",
    "sg:province":"Solothurn",
    "wof:name":"Ara Emmenspitz",
    "wof:placetype":"venue"
},
  "geometry": {"coordinates":[7.5623,47.20977],"type":"Point"}
}