{
  "type": "Feature",
  "properties": {
    "iso:country":"CH",
    "sg:address":"Dorfstrasse 20 4222 Zwingen. Postfach",
    "sg:city":"Basel",
    "sg:orig_category":"Markt U Meinungsforschung",
    "sg:phone":"+41 61 321 30 12",
    "sg:postcode":"4013",
    "sg:province":"Basel-Stadt",
    "wof:name":"Mrkos Marketing",
    "wof:placetype":"venue"
},
  "geometry": {"coordinates":[7.528523922,47.4371795654],"type":"Point"}
}