{
  "type": "Feature",
  "properties": {
    "iso:country":"CH",
    "sg:address":"Via Ponte Vecchio 15",
    "sg:city":"Cademario",
    "sg:orig_category":"Non-Classified Establishments",
    "sg:phone":"+41 91 604 66 32",
    "sg:postcode":"6936",
    "sg:province":"Ticino",
    "wof:name":"Il Bel Giardino Di Parravicini Luca",
    "wof:placetype":"venue"
},
  "geometry": {"coordinates":[8.8945245743,46.0211448669],"type":"Point"}
}