{
  "type": "Feature",
  "properties": {
    "iso:country":"CH",
    "sg:address":"Hauptstrasse 27",
    "sg:city":"Tr\u00fcbbach",
    "sg:orig_category":"Dedusting Systems",
    "sg:phone":"+41 81 783 29 09",
    "sg:postcode":"9477",
    "sg:province":"St. Gallen",
    "wof:name":"Se Entstaubungs- Und Umwelttechnik Ag",
    "wof:placetype":"venue"
},
  "geometry": {"coordinates":[9.48145,47.074047],"type":"Point"}
}