{
  "type": "Feature",
  "properties": {
    "iso:country":"CH",
    "sg:address":"1657",
    "sg:city":"Abl\u00e4ndschen",
    "sg:orig_category":"Primarschulen",
    "sg:phone":"+41 26 495 15 40",
    "sg:postcode":"1657",
    "sg:province":"Bern",
    "wof:name":"Primarschule",
    "wof:placetype":"venue"
},
  "geometry": {"coordinates":[7.2608799934,46.8221817017],"type":"Point"}
}