{
  "type": "Feature",
  "properties": {
    "iso:country":"CH",
    "sg:address":"Seestrasse 233 8713 Uerikon. Postfach",
    "sg:city":"Uerikon",
    "sg:orig_category":"Markt U Meinungsforschung",
    "sg:postcode":"8713",
    "sg:province":"Z\u00fcrich",
    "wof:name":"Mss N\u00fcnlist Gmbh",
    "wof:placetype":"venue"
},
  "geometry": {"coordinates":[8.7482976913,47.234828949],"type":"Point"}
}