{
  "type": "Feature",
  "properties": {
    "iso:country":"CH",
    "sg:address":"Avenue De La Gare 24",
    "sg:city":"Monthey",
    "sg:orig_category":"Detailhandel mit Geschenkartikeln U Souvenirs Herstellung von W\u00e4sche",
    "sg:phone":"+41 24 471 78 48",
    "sg:postcode":"1870",
    "sg:province":"Valais",
    "wof:name":"Boutique P\u00e9tronie, Catherine Huon Marti",
    "wof:placetype":"venue"
},
  "geometry": {"coordinates":[6.9504208565,46.2534637451],"type":"Point"}
}