{
  "type": "Feature",
  "properties": {
    "iso:country":"CH",
    "sg:address":"Via Delta 10",
    "sg:city":"Ascona",
    "sg:orig_category":"Gartenbau",
    "sg:phone":"+41 91 791 38 80",
    "sg:postcode":"6612",
    "sg:province":"Ticino",
    "wof:name":"Georg Schuster Giardini",
    "wof:placetype":"venue"
},
  "geometry": {"coordinates":[8.7749500275,46.1644020081],"type":"Point"}
}