{
  "type": "Feature",
  "properties": {
    "iso:country":"CH",
    "sg:address":"Pont-du-centenaire Ch.du 108",
    "sg:city":"Plan-les-ouates",
    "sg:orig_category":"Rechtsberatung",
    "sg:phone":"+41 22 794 77 66",
    "sg:postcode":"1228",
    "sg:province":"Gen\u00e8ve",
    "wof:name":"Frame Sa",
    "wof:placetype":"venue"
},
  "geometry": {"coordinates":[6.108019,46.170078],"type":"Point"}
}