{
  "type": "Feature",
  "properties": {
    "addr:full":"Avenue De Champel 61 Gen\u00e8ve Gen\u00e8ve 1206",
    "addr:housenumber":"61",
    "addr:postcode":"1206",
    "addr:street":"Avenue De Champel",
    "iso:country":"CH",
    "sg:address":"Avenue De Champel 61",
    "sg:city":"Gen\u00e8ve",
    "sg:orig_category":"Architekturb\u00fcros",
    "sg:phone":"+41 22 346 96 67",
    "sg:postcode":"1206",
    "sg:province":"Gen\u00e8ve",
    "wof:name":"Georges Pino Bureau D'architecture",
    "wof:placetype":"venue"
},
  "geometry": {"coordinates":[6.152608,46.191013],"type":"Point"}
}