{
  "type": "Feature",
  "properties": {
    "addr:full":"Camuzzi Via Dei 6926 Montagnola Casella Postale 5 Montagnola Ticino 6926",
    "addr:housenumber":"5",
    "addr:postcode":"6926;6926",
    "addr:street":"Via Dei;Postale",
    "iso:country":"CH",
    "sg:address":"Camuzzi Via Dei 6926 Montagnola Casella Postale 5",
    "sg:city":"Montagnola",
    "sg:orig_category":"Architektur U Ingenieurb\u00fcros",
    "sg:phone":"+41 91 993 05 80",
    "sg:postcode":"6926",
    "sg:province":"Ticino",
    "wof:name":"C & C Exima Di Enzo Carrubba",
    "wof:placetype":"venue"
},
  "geometry": {"coordinates":[8.916906,45.981918],"type":"Point"}
}