{
  "type": "Feature",
  "properties": {
    "iso:country":"CH",
    "sg:address":"Schulstrasse 12",
    "sg:city":"Uesslingen",
    "sg:orig_category":"Softwareentwicklung U beratung",
    "sg:phone":"+41 52 746 15 91",
    "sg:postcode":"8524",
    "sg:province":"Thurgau",
    "wof:name":"Scan Trade Ag",
    "wof:placetype":"venue"
},
  "geometry": {"coordinates":[8.8290052414,47.5817871094],"type":"Point"}
}