{
  "type": "Feature",
  "properties": {
    "iso:country":"CH",
    "sg:address":"Niedergesteln",
    "sg:city":"Steg",
    "sg:classifiers":[
        {
            "category":"Building & Trades",
            "subcategory":"Locksmith",
            "type":"Services"
        }
    ],
    "sg:phone":"+41 27 934 16 56",
    "sg:postcode":"3940",
    "sg:province":"Valais",
    "sg:tags":[
        "shop",
        "assembly",
        "locksmith's"
    ],
    "wof:name":"Heinrich Brenner Ag",
    "wof:placetype":"venue"
},
  "geometry": {"coordinates":[7.7464680672,46.3153152466],"type":"Point"}
}