{
  "type": "Feature",
  "properties": {
    "iso:country":"CH",
    "sg:address":"Bois-de-bay Route Du 28",
    "sg:city":"Satigny",
    "sg:orig_category":"Herstellung von Metallkonstruktionen",
    "sg:postcode":"1242",
    "sg:province":"Gen\u00e8ve",
    "wof:name":"Oxmetal, S.m.b. Pascal Perrin",
    "wof:placetype":"venue"
},
  "geometry": {"coordinates":[6.0632400513,46.1992721558],"type":"Point"}
}