{
  "type": "Feature",
  "properties": {
    "iso:country":"CH",
    "sg:address":"Oberdorfstrasse 26",
    "sg:city":"Beckenried",
    "sg:classifiers":[
        {
            "category":"Restaurant",
            "type":"Food & Drink"
        }
    ],
    "sg:phone":"+41 41 620 13 79",
    "sg:postcode":"6375",
    "sg:province":"Nidwalden",
    "wof:name":"Restaurant Schl\u00fcssel",
    "wof:placetype":"venue"
},
  "geometry": {"coordinates":[8.4594430923,46.9680747986],"type":"Point"}
}