{
  "type": "Feature",
  "properties": {
    "addr:full":"Jurastrasse 43 Basel Basel-Stadt 4053",
    "addr:housenumber":"43",
    "addr:postcode":"4053",
    "addr:street":"Jurastrasse",
    "iso:country":"CH",
    "sg:address":"Jurastrasse 43",
    "sg:city":"Basel",
    "sg:orig_category":"Bauspenglerei Zimmerei, Dachdeckerei, Bauspenglerei U Abdichtung",
    "sg:phone":"+41 79 322 31 73",
    "sg:postcode":"4053",
    "sg:province":"Basel-Stadt",
    "wof:name":"Urs Baur Gmbh",
    "wof:placetype":"venue"
},
  "geometry": {"coordinates":[7.591517,47.541847],"type":"Point"}
}