{
  "type": "Feature",
  "properties": {
    "iso:country":"CH",
    "sg:address":"Jurastrasse 43",
    "sg:city":"Basel",
    "sg:orig_category":"Bauspenglerei Zimmerei, Dachdeckerei, Bauspenglerei U Abdichtung",
    "sg:phone":"+41 79 322 31 73",
    "sg:postcode":"4053",
    "sg:province":"Basel-Stadt",
    "wof:name":"Urs Baur Gmbh",
    "wof:placetype":"venue"
},
  "geometry": {"coordinates":[7.591517,47.541847],"type":"Point"}
}