{
  "type": "Feature",
  "properties": {
    "iso:country":"CH",
    "sg:address":"Vorderdorfstrasse",
    "sg:city":"Grabs",
    "sg:orig_category":"Psychotherapie",
    "sg:phone":"+41 81 771 48 16",
    "sg:postcode":"9472",
    "sg:province":"St. Gallen",
    "wof:name":"Irmgard Weber Psychotherapie",
    "wof:placetype":"venue"
},
  "geometry": {"coordinates":[9.4432144165,47.1822662354],"type":"Point"}
}