{
  "type": "Feature",
  "properties": {
    "iso:country":"CH",
    "sg:address":"Avenue De B\u00e9thusy 46",
    "sg:city":"Lausanne",
    "sg:orig_category":"Zahnarztpraxen",
    "sg:phone":"+41 21 323 23 77",
    "sg:postcode":"1012",
    "sg:province":"Vaud",
    "wof:name":"Dr M\u00e9d. Dent. G\u00e9rald Regamey M\u00e9decin-dentiste",
    "wof:placetype":"venue"
},
  "geometry": {"coordinates":[6.6480150223,46.5223999023],"type":"Point"}
}