{
  "type": "Feature",
  "properties": {
    "iso:country":"CH",
    "sg:address":"Unterdorfstrasse 21-23 9116 Wolfertswil. Postfach",
    "sg:city":"Wolfertswil",
    "sg:orig_category":"Herstellung von Hebezeugen U F\u00f6rdermitteln",
    "sg:postcode":"9116",
    "sg:province":"St. Gallen",
    "wof:name":"Ascensa Lift Sa",
    "wof:placetype":"venue"
},
  "geometry": {"coordinates":[9.8392496109,46.4991378784],"type":"Point"}
}