{
  "type": "Feature",
  "properties": {
    "iso:country":"CH",
    "sg:address":"Kirchweg 76",
    "sg:city":"Ennenda",
    "sg:orig_category":"Sonstiger Grosshandel",
    "sg:phone":"+41 33 654 59 84",
    "sg:postcode":"8755",
    "sg:province":"Glarus",
    "wof:name":"Web\u00dc, Werner B\u00fchlmann",
    "wof:placetype":"venue"
},
  "geometry": {"coordinates":[7.7154841423,46.651386261],"type":"Point"}
}