{
  "type": "Feature",
  "properties": {
    "iso:country":"CH",
    "sg:address":"Kyburgerhof",
    "sg:city":"Sursee",
    "sg:orig_category":"Fachdetailhandel in Verkaufsr\u00e4umen",
    "sg:postcode":"6210",
    "sg:province":"Luzern",
    "wof:name":"Hockeyshop 2000 Ghisoni Brigitte",
    "wof:placetype":"venue"
},
  "geometry": {"coordinates":[8.1037883759,47.1716117859],"type":"Point"}
}