{
  "type": "Feature",
  "properties": {
    "iso:country":"CH",
    "sg:address":"Aargauerstrasse 6",
    "sg:city":"Hitzkirch",
    "sg:orig_category":"Grosshandel mit Getr\u00e4nken",
    "sg:postcode":"6285",
    "sg:province":"Luzern",
    "wof:name":"Ithaki P. Mygiakis",
    "wof:placetype":"venue"
},
  "geometry": {"coordinates":[8.1380968094,47.4427680969],"type":"Point"}
}