{
  "type": "Feature",
  "properties": {
    "iso:country":"CH",
    "sg:address":"Hertiweg 3",
    "sg:city":"B\u00fclach",
    "sg:orig_category":"Werbeagenturen Werbegrafikateliers",
    "sg:phone":"+41 18611330",
    "sg:postcode":"8180",
    "sg:province":"Z\u00fcrich",
    "wof:name":"Thomas Heller Gestaltung & Werbung",
    "wof:placetype":"venue"
},
  "geometry": {"coordinates":[8.539024353,47.5206298828],"type":"Point"}
}