{
  "type": "Feature",
  "properties": {
    "iso:country":"CH",
    "sg:address":"Rankstrasse 19",
    "sg:city":"Endingen",
    "sg:orig_category":"Weitere Kultur U Unterhaltungseinrichtungen",
    "sg:phone":"+41 56 242 19 44",
    "sg:postcode":"5304",
    "sg:province":"Aargau",
    "wof:name":"Peter Rafal Management Management& Show-kontakt",
    "wof:placetype":"venue"
},
  "geometry": {"coordinates":[8.2881813049,47.5396881104],"type":"Point"}
}