{
  "type": "Feature",
  "properties": {
    "iso:country":"CH",
    "sg:address":"Brunnmattstrasse 69",
    "sg:city":"Bern",
    "sg:orig_category":"Organisationen des Gesundheitswesen",
    "sg:phone":"+41 31 372 13 02",
    "sg:postcode":"3007",
    "sg:province":"Bern",
    "wof:name":"Samariterverein Buebeb\u00e4rg",
    "wof:placetype":"venue"
},
  "geometry": {"coordinates":[7.4237999916,46.9409446716],"type":"Point"}
}