{
  "type": "Feature",
  "properties": {
    "iso:country":"CH",
    "sg:address":"8565",
    "sg:city":"Hugelshofen",
    "sg:classifiers":[
        {
            "category":"Restaurant",
            "type":"Food & Drink"
        }
    ],
    "sg:phone":"+41 71 699 16 24",
    "sg:postcode":"8565",
    "sg:province":"Thurgau",
    "wof:name":"Restaurant L\u00f6wen",
    "wof:placetype":"venue"
},
  "geometry": {"coordinates":[9.116230011,47.5984382629],"type":"Point"}
}