{
  "type": "Feature",
  "properties": {
    "iso:country":"CH",
    "sg:address":"Holzikerstrasse 7",
    "sg:city":"Sch\u00f6ftland",
    "sg:orig_category":"Grosshandel mit Maschinen U Ausr\u00fcstungen Herstellung von Bergwerks U Baumaschinen",
    "sg:phone":"+41 62 721 34 89",
    "sg:postcode":"5040",
    "sg:province":"Aargau",
    "wof:name":"Druckluft Tec Ag",
    "wof:placetype":"venue"
},
  "geometry": {"coordinates":[8.048204422,47.3117599487],"type":"Point"}
}