{
  "type": "Feature",
  "properties": {
    "iso:country":"CH",
    "sg:address":"Rue G. De Vergy 4",
    "sg:city":"Cernier",
    "sg:orig_category":"Zahnarztpraxen",
    "sg:phone":"+41 32 853 40 53",
    "sg:postcode":"2053",
    "sg:province":"Neuch\u00e2tel",
    "wof:name":"Dr M\u00e9d. Dent. Yvan Vuilleumier M\u00e9decin-dentiste",
    "wof:placetype":"venue"
},
  "geometry": {"coordinates":[6.8992109299,47.0579795837],"type":"Point"}
}