{
  "type": "Feature",
  "properties": {
    "iso:country":"CH",
    "sg:address":"Retraites Chemin Des 5",
    "sg:city":"Lausanne",
    "sg:orig_category":"Detektivb\u00fcros U \u00dcberwachung",
    "sg:postcode":"1004",
    "sg:province":"Vaud",
    "wof:name":"Gotthard-wache Hans Reber",
    "wof:placetype":"venue"
},
  "geometry": {"coordinates":[8.6453390121,46.8755226135],"type":"Point"}
}