{
  "type": "Feature",
  "properties": {
    "iso:country":"CH",
    "sg:address":"3792 Saanen. Postfach",
    "sg:city":"Gstaad",
    "sg:classifiers":[
        {
            "category":"Travel",
            "subcategory":"Hotels & Motels",
            "type":"Entertainment"
        }
    ],
    "sg:postcode":"3780",
    "sg:province":"Bern",
    "sg:tags":[
        "hotels",
        "mit",
        "restaurant"
    ],
    "wof:name":"Widmer Ruedi, Posthotel R\u00f6ssli",
    "wof:placetype":"venue"
},
  "geometry": {"coordinates":[7.2361397743,46.463218689],"type":"Point"}
}