{
  "type": "Feature",
  "properties": {
    "iso:country":"CH",
    "sg:address":"Sch\u00f6nmattweg 12",
    "sg:city":"Thun",
    "sg:classifiers":[
        {
            "category":"Professional",
            "subcategory":"Employment Agencies",
            "type":"Services"
        }
    ],
    "sg:phone":"+41 12603836",
    "sg:postcode":"3600",
    "sg:province":"Bern",
    "sg:tags":[
        "personal",
        "u",
        "stellenvermittlung"
    ],
    "wof:name":"Kohler Consulting",
    "wof:placetype":"venue"
},
  "geometry": {"coordinates":[7.627641201,46.749206543],"type":"Point"}
}