{
  "type": "Feature",
  "properties": {
    "iso:country":"CH",
    "sg:address":"Sonnhalde 12",
    "sg:city":"M\u00f6rigen",
    "sg:classifiers":[
        {
            "category":"Shopping",
            "subcategory":"Discount & Variety Stores",
            "type":"Retail Goods"
        }
    ],
    "sg:phone":"+41 32 397 13 43",
    "sg:postcode":"2572",
    "sg:province":"Bern",
    "sg:tags":[
        "shop",
        "locksmith's"
    ],
    "wof:name":"Werner Scholl Ag",
    "wof:placetype":"venue"
},
  "geometry": {"coordinates":[7.2158331871,47.087310791],"type":"Point"}
}