{
  "type": "Feature",
  "properties": {
    "iso:country":"CH",
    "sg:address":"Dorfstr. 238 9425 Thal. Postfach",
    "sg:city":"Altenrhein",
    "sg:orig_category":"Instandhaltung U Reparatur von Automobilen",
    "sg:postcode":"9423",
    "sg:province":"St. Gallen",
    "wof:name":"Schneider Reto",
    "wof:placetype":"venue"
},
  "geometry": {"coordinates":[9.5521602631,47.4714889526],"type":"Point"}
}