{
  "type": "Feature",
  "properties": {
    "iso:country":"CH",
    "sg:address":"Linsenackerweg 4",
    "sg:city":"Sissach",
    "sg:orig_category":"Mit dem Versicherungsgewerbe verbundene T\u00e4tigkeiten",
    "sg:phone":"+41 18846501",
    "sg:postcode":"4450",
    "sg:province":"Basel-Landschaft",
    "wof:name":"Friedmann Consulting",
    "wof:placetype":"venue"
},
  "geometry": {"coordinates":[8.4423189163,47.459072113],"type":"Point"}
}