{
  "type": "Feature",
  "properties": {
    "iso:country":"CH",
    "sg:address":"Zolliker Strasse 90",
    "sg:city":"Zollikon",
    "sg:orig_category":"Unternehmensberatung",
    "sg:phone":"+41 12624444",
    "sg:postcode":"8702",
    "sg:province":"Z\u00fcrich",
    "wof:name":"Manres Ag",
    "wof:placetype":"venue"
},
  "geometry": {"coordinates":[8.5726442337,47.3389015198],"type":"Point"}
}