{
  "type": "Feature",
  "properties": {
    "iso:country":"CH",
    "sg:address":"Im Moos",
    "sg:city":"Balsthal",
    "sg:orig_category":"Minigolfpl\u00e4tze",
    "sg:phone":"+41 56 622 97 40",
    "sg:postcode":"4710",
    "sg:province":"Solothurn",
    "wof:name":"Minigolf-club Wohlen",
    "wof:placetype":"venue"
},
  "geometry": {"coordinates":[8.2780704498,47.3505363464],"type":"Point"}
}