{
  "type": "Feature",
  "properties": {
    "iso:country":"CH",
    "sg:address":"Mettlenstrasse 16",
    "sg:city":"Turbenthal",
    "sg:orig_category":"Mechanik Mechanische Werkst\u00e4tten",
    "sg:phone":"+41 52 385 29 37",
    "sg:postcode":"8488",
    "sg:province":"Z\u00fcrich",
    "wof:name":"Wettstein Werner",
    "wof:placetype":"venue"
},
  "geometry": {"coordinates":[8.8596820831,47.4341087341],"type":"Point"}
}