{
  "type": "Feature",
  "properties": {
    "iso:country":"CH",
    "sg:address":"Freudenbergstrasse 8",
    "sg:city":"Oberuzwil",
    "sg:orig_category":"Architekturb\u00fcros",
    "sg:phone":"+41 71 951 57 86",
    "sg:postcode":"9242",
    "sg:province":"St. Gallen",
    "wof:name":"Hans Galley Architekturb\u00fcro",
    "wof:placetype":"venue"
},
  "geometry": {"coordinates":[9.124157,47.432117],"type":"Point"}
}