{
  "type": "Feature",
  "properties": {
    "iso:country":"CH",
    "sg:address":"Rain 14 5000 Aarau. Postfach",
    "sg:city":"Aarau",
    "sg:orig_category":"Reparatur von Schuhen U Lederwaren",
    "sg:phone":"+41 62 824 05 90",
    "sg:postcode":"5000",
    "sg:province":"Aargau",
    "wof:name":"Fullone Saverio Schuhreparaturen, Stempel, Drucksachen, Gravuren",
    "wof:placetype":"venue"
},
  "geometry": {"coordinates":[8.0441856384,47.3911247253],"type":"Point"}
}