{
  "type": "Feature",
  "properties": {
    "iso:country":"CH",
    "sg:address":"Ober-ifang 8",
    "sg:city":"Henggart",
    "sg:orig_category":"Sportvereine Velo Rad-& Motorfahrer-Bund SRB",
    "sg:postcode":"8444",
    "sg:province":"Z\u00fcrich",
    "wof:name":"Radrenn-club Winterthur",
    "wof:placetype":"venue"
},
  "geometry": {"coordinates":[8.6829462051,47.5674476624],"type":"Point"}
}