{
  "type": "Feature",
  "properties": {
    "iso:country":"CH",
    "sg:address":"Champel Avenue De 75-77 1206 Gen\u00e8ve Case Postale 358",
    "sg:city":"Gen\u00e8ve",
    "sg:orig_category":"Sonstiges Versicherungsgewerbe Unfall U Schadenversicherung",
    "sg:phone":"+41 31 357 91 11",
    "sg:postcode":"1206",
    "sg:province":"Gen\u00e8ve",
    "wof:name":"Visana Versicherungen Ag",
    "wof:placetype":"venue"
},
  "geometry": {"coordinates":[7.4969468117,46.9266624451],"type":"Point"}
}