{
  "type": "Feature",
  "properties": {
    "iso:country":"CH",
    "sg:address":"Industriestrasse",
    "sg:city":"Reichenburg",
    "sg:orig_category":"Instandhaltung U Reparatur von Automobilen",
    "sg:phone":"+41 55 444 16 64",
    "sg:postcode":"8864",
    "sg:province":"Schwyz",
    "wof:name":"Ivic Gmbh Garage",
    "wof:placetype":"venue"
},
  "geometry": {"coordinates":[8.9875154495,47.1703987122],"type":"Point"}
}