{
  "type": "Feature",
  "properties": {
    "iso:country":"CH",
    "sg:address":"3922",
    "sg:city":"Kalpetran",
    "sg:orig_category":"Sportvereine Eissport Eishockey",
    "sg:phone":"+41 18203812",
    "sg:postcode":"3922",
    "sg:province":"Valais",
    "wof:name":"Uni-hockey-club Jump",
    "wof:placetype":"venue"
},
  "geometry": {"coordinates":[8.6222238541,47.3997840881],"type":"Point"}
}