{
  "type": "Feature",
  "properties": {
    "iso:country":"CH",
    "sg:address":"1037",
    "sg:city":"Etagni\u00e8res",
    "sg:orig_category":"Schulpflegen",
    "sg:postcode":"1037",
    "sg:province":"Vaud",
    "wof:name":"Commission Scolaire De L'ecole Primaire",
    "wof:placetype":"venue"
},
  "geometry": {"coordinates":[6.6100001335,46.6005897522],"type":"Point"}
}