{
  "type": "Feature",
  "properties": {
    "addr:full":"3766 Boltigen Bern 3766",
    "addr:postcode":"3766;3766",
    "iso:country":"CH",
    "sg:address":"3766",
    "sg:city":"Boltigen",
    "sg:orig_category":"Bau U Wohngenossenschaften",
    "sg:postcode":"3766",
    "sg:province":"Bern",
    "wof:name":"Gen.f\u00fcr Landwirtschaftl.bauen Der Gemeinde Boltigen & Umgeb.",
    "wof:placetype":"venue"
},
  "geometry": {"coordinates":[7.390518,46.628971],"type":"Point"}
}