{
  "type": "Feature",
  "properties": {
    "iso:country":"CH",
    "sg:address":"Langr\u00fctistrasse 88",
    "sg:city":"Einsiedeln",
    "sg:orig_category":"Allgemeiner Hoch U Tiefbau Strassenbau",
    "sg:phone":"+41 55 412 36 80",
    "sg:postcode":"8840",
    "sg:province":"Schwyz",
    "wof:name":"Baugesch\u00e4ft P. Weibel Gmbh",
    "wof:placetype":"venue"
},
  "geometry": {"coordinates":[8.741908,47.120792],"type":"Point"}
}