{
  "type": "Feature",
  "properties": {
    "iso:country":"CH",
    "sg:address":"Aeschenvorstadt 48",
    "sg:city":"Basel",
    "sg:orig_category":"Kauf U Verkauf von Immobilien auf eigene Rechnung",
    "sg:postcode":"4051",
    "sg:province":"Basel-Stadt",
    "wof:name":"Duha - Duss F. Liegenschaften; Bau, Umbau U Handel",
    "wof:placetype":"venue"
},
  "geometry": {"coordinates":[9.3627548218,47.4103012085],"type":"Point"}
}