{
  "type": "Feature",
  "properties": {
    "iso:country":"CH",
    "sg:address":"Hof Bad 102",
    "sg:city":"Maisprach",
    "sg:orig_category":"Tierarztpraxis",
    "sg:phone":"+41 61 843 01 26",
    "sg:postcode":"4464",
    "sg:province":"Basel-Landschaft",
    "wof:name":"Dr.med.vet. Werner Pfister Tierarzt",
    "wof:placetype":"venue"
},
  "geometry": {"coordinates":[7.8454399109,47.5239524841],"type":"Point"}
}