{
  "type": "Feature",
  "properties": {
    "iso:country":"CH",
    "sg:address":"Landskronstrasse 37",
    "sg:city":"Basel",
    "sg:orig_category":"RESTAURANTS: TEA-ROOMS",
    "sg:phone":"+41 19100402",
    "sg:postcode":"4056",
    "sg:province":"Basel-Stadt",
    "wof:name":"Restaurant Sinfonia",
    "wof:placetype":"venue"
},
  "geometry": {"coordinates":[8.5911445618,47.3055381775],"type":"Point"}
}