{
  "type": "Feature",
  "properties": {
    "iso:country":"CH",
    "sg:address":"Bernstrasse Ost 49",
    "sg:city":"Suhr",
    "sg:orig_category":"Detailhandel mit Beleuchtungs U Haushaltsgegenst\u00e4nden Einbau von Schreinerwaren",
    "sg:phone":"+41 62 842 61 33",
    "sg:postcode":"5034",
    "sg:province":"Aargau",
    "wof:name":"Fust Ag",
    "wof:placetype":"venue"
},
  "geometry": {"coordinates":[8.08459,47.374138],"type":"Point"}
}