{
  "type": "Feature",
  "properties": {
    "iso:country":"CH",
    "sg:address":"La Levratte 4",
    "sg:city":"Nyon",
    "sg:orig_category":"Sonstige Hilfsdienste des Kultur U Unterhaltungswesens Verlag von bespielten Tontr\u00e4gern",
    "sg:phone":"+41 22 361 79 56",
    "sg:postcode":"1260",
    "sg:province":"Vaud",
    "wof:name":"E-musicomm",
    "wof:placetype":"venue"
},
  "geometry": {"coordinates":[6.2292561531,46.3868293762],"type":"Point"}
}