{
  "type": "Feature",
  "properties": {
    "iso:country":"CH",
    "sg:address":"Kasimir-pfyffer-strasse 10",
    "sg:city":"Luzern",
    "sg:orig_category":"Fotografische Ateliers",
    "sg:phone":"+41 41 240 90 42",
    "sg:postcode":"6003",
    "sg:province":"Luzern",
    "wof:name":"Margherita Delussu Fotografin",
    "wof:placetype":"venue"
},
  "geometry": {"coordinates":[8.3015556335,47.0488891602],"type":"Point"}
}