{
  "type": "Feature",
  "properties": {
    "iso:country":"CH",
    "sg:address":"Toggenburger Str. 29",
    "sg:city":"Neu St. Johann",
    "sg:classifiers":[
        {
            "category":"Banks & Credit Unions",
            "subcategory":"Bank",
            "type":"Services"
        }
    ],
    "sg:phone":"+41 71 995 50 66",
    "sg:postcode":"9652",
    "sg:province":"St. Gallen",
    "wof:name":"Raiffeisenbank Nesslau-krummenau-stein",
    "wof:placetype":"venue"
},
  "geometry": {"coordinates":[9.227033,47.19886],"type":"Point"}
}