{
  "type": "Feature",
  "properties": {
    "iso:country":"CH",
    "sg:address":"1029",
    "sg:city":"Villars-ste-croix",
    "sg:orig_category":"Detailhandel mit Haustieren U zoologischem Bedarf Fachdetailhandel in Verkaufsr\u00e4umen",
    "sg:phone":"+41 21 634 78 16",
    "sg:postcode":"1029",
    "sg:province":"Vaud",
    "wof:name":"Aquarium Center Discount, Pultau J.",
    "wof:placetype":"venue"
},
  "geometry": {"coordinates":[6.5640301704,46.5662002563],"type":"Point"}
}