{
  "type": "Feature",
  "properties": {
    "iso:country":"CH",
    "sg:address":"M\u00fclhauserstrasse 70/72",
    "sg:city":"Basel",
    "sg:orig_category":"Detailhandel mit Waren verschiedener Art, Hauptrichtung Nahrungsmittel",
    "sg:phone":"+41 61 321 70 50",
    "sg:postcode":"4056",
    "sg:province":"Basel-Stadt",
    "wof:name":"Coop Basel",
    "wof:placetype":"venue"
},
  "geometry": {"coordinates":[7.579240799,47.5683288574],"type":"Point"}
}