{
  "type": "Feature",
  "properties": {
    "iso:country":"CH",
    "sg:address":"Rue Du 23 Juin 2",
    "sg:city":"Courrendlin",
    "sg:orig_category":"Unclassifiable Establishments",
    "sg:postcode":"2830",
    "sg:province":"Jura",
    "wof:name":"Trans Com Fahrni Jean-paul",
    "wof:placetype":"venue"
},
  "geometry": {"coordinates":[7.3725252151,47.3403053284],"type":"Point"}
}