{
  "type": "Feature",
  "properties": {
    "addr:full":"Siewerdtstrasse 75 Z\u00fcrich Z\u00fcrich 8050",
    "addr:housenumber":"75",
    "addr:postcode":"8050",
    "addr:street":"Siewerdtstrasse",
    "iso:country":"CH",
    "sg:address":"Siewerdtstrasse 75",
    "sg:city":"Z\u00fcrich",
    "sg:orig_category":"Architektur U Ingenieurb\u00fcros",
    "sg:phone":"+41 13115958",
    "sg:postcode":"8050",
    "sg:province":"Z\u00fcrich",
    "wof:name":"Bmm Baumanagement Gmbh",
    "wof:placetype":"venue"
},
  "geometry": {"coordinates":[8.554939,47.412354],"type":"Point"}
}