{
  "type": "Feature",
  "properties": {
    "iso:country":"CH",
    "sg:address":"St. Gallerstr. 86",
    "sg:city":"Lachen",
    "sg:classifiers":[
        {
            "category":"Food & Beverages",
            "subcategory":"Groceries & Convenience Stores",
            "type":"Retail Goods"
        }
    ],
    "sg:phone":"+41 55 442 53 53",
    "sg:postcode":"8853",
    "sg:province":"Schwyz",
    "sg:tags":[
        "product",
        "related"
    ],
    "wof:name":"Imex Ag",
    "wof:placetype":"venue"
},
  "geometry": {"coordinates":[8.8634643555,47.193195343],"type":"Point"}
}