{
  "type": "Feature",
  "properties": {
    "iso:country":"CH",
    "sg:address":"Neuenburgstrasse 69 3236 Gampelen. Postfach",
    "sg:city":"Gampelen",
    "sg:orig_category":"RESTAURANTS: TEA-ROOMS",
    "sg:postcode":"3236",
    "sg:province":"Bern",
    "wof:name":"Anag Co Ltd, London, Zweigniederlassung Gampelen",
    "wof:placetype":"venue"
},
  "geometry": {"coordinates":[7.0460038185,47.0179252625],"type":"Point"}
}