{
  "type": "Feature",
  "properties": {
    "iso:country":"CH",
    "sg:address":"Alpes Avenue Des 6",
    "sg:city":"Monthey",
    "sg:orig_category":"Non-Classified Establishments",
    "sg:postcode":"1870",
    "sg:province":"Valais",
    "wof:name":"Gel-ar\u00f4mes Krocker Helmut",
    "wof:placetype":"venue"
},
  "geometry": {"coordinates":[6.9471468925,46.2516288757],"type":"Point"}
}