{
  "type": "Feature",
  "properties": {
    "iso:country":"CH",
    "sg:address":"Bennwilerstrasse 3 4434 H\u00f6lstein. Postfach",
    "sg:city":"H\u00f6lstein",
    "sg:orig_category":"Unclassifiable Establishments",
    "sg:phone":"+41 61 951 18 40",
    "sg:postcode":"4434",
    "sg:province":"Basel-Landschaft",
    "wof:name":"Klar Tech Haustechnikanlagen; Planung, Ausf\u00fchrung",
    "wof:placetype":"venue"
},
  "geometry": {"coordinates":[7.7697100639,47.4243965149],"type":"Point"}
}