{
  "type": "Feature",
  "properties": {
    "iso:country":"CH",
    "sg:address":"Residenza Governativa",
    "sg:city":"Bellinzona",
    "sg:orig_category":"Interessenvertretungen",
    "sg:postcode":"6500",
    "sg:province":"Ticino",
    "wof:name":"Fondazione Istituto Ricerche Solari Locarno",
    "wof:placetype":"venue"
},
  "geometry": {"coordinates":[8.7865600586,46.1752166748],"type":"Point"}
}