{
  "type": "Feature",
  "properties": {
    "iso:country":"CH",
    "sg:address":"Dolderstrasse 30 8032 Z\u00fcrich",
    "sg:city":"Zust",
    "sg:orig_category":"Werbung",
    "sg:phone":"+41 17371490",
    "sg:postcode":"32",
    "wof:name":"Lips Bernhard Und Doris, Kommunikative Dienstleistungen",
    "wof:placetype":"venue"
},
  "geometry": {"coordinates":[8.44862,47.356018],"type":"Point"}
}