{
  "type": "Feature",
  "properties": {
    "iso:country":"CH",
    "sg:address":"Rue Pierre -aeby 17",
    "sg:city":"Fribourg",
    "sg:orig_category":"Architektur U Ingenieurb\u00fcros",
    "sg:phone":"+41 26 322 13 87",
    "sg:postcode":"1700",
    "sg:province":"Fribourg",
    "wof:name":"Tuescher Urbanisme Sa",
    "wof:placetype":"venue"
},
  "geometry": {"coordinates":[7.158609,46.808502],"type":"Point"}
}