{
  "type": "Feature",
  "properties": {
    "iso:country":"CH",
    "sg:address":"Brunnackerstrasse 1",
    "sg:city":"Ramlinsburg",
    "sg:orig_category":"Unclassifiable Establishments",
    "sg:postcode":"4433",
    "sg:province":"Basel-Landschaft",
    "wof:name":"Arte Vitrum Gmbh",
    "wof:placetype":"venue"
},
  "geometry": {"coordinates":[7.7644410133,47.4491081238],"type":"Point"}
}