{
  "type": "Feature",
  "properties": {
    "iso:country":"CH",
    "sg:address":"La C\u00f4te De Pallens",
    "sg:city":"Montreux",
    "sg:orig_category":"Vereine Gesang",
    "sg:postcode":"1820",
    "sg:province":"Vaud",
    "wof:name":"Choeur D'hommes La Chorale",
    "wof:placetype":"venue"
},
  "geometry": {"coordinates":[6.904610157,47.1760635376],"type":"Point"}
}