{
  "type": "Feature",
  "properties": {
    "iso:country":"CH",
    "sg:address":"Holzikerstrasse 8",
    "sg:city":"Sch\u00f6ftland",
    "sg:orig_category":"Detailhandel mit Waren verschiedener Art, Hauptrichtung Nahrungsmittel",
    "sg:phone":"+41 81 302 30 24",
    "sg:postcode":"5040",
    "sg:province":"Aargau",
    "wof:name":"Erwin B\u00fcrge Epa-superdiscount",
    "wof:placetype":"venue"
},
  "geometry": {"coordinates":[9.4979696274,47.0085983276],"type":"Point"}
}