{
  "type": "Feature",
  "properties": {
    "iso:country":"CH",
    "sg:address":"Bahnhofstrasse 7 7250 Klosters. Postfach 293",
    "sg:city":"Klosters",
    "sg:orig_category":"Fachdetailhandel in Verkaufsr\u00e4umen",
    "sg:phone":"+41 81 422 56 54",
    "sg:postcode":"7250",
    "sg:province":"Graubunden",
    "wof:name":"D\u00e9j\u00e0 Vu Gmbh",
    "wof:placetype":"venue"
},
  "geometry": {"coordinates":[9.8815584183,46.8689422607],"type":"Point"}
}