{
  "type": "Feature",
  "properties": {
    "iso:country":"CH",
    "sg:address":"Stauffacherstrasse 178 8004 Z\u00fcrich. Postfach",
    "sg:city":"Z\u00fcrich",
    "sg:orig_category":"Detailhandel mit M\u00f6beln U Haushaltsgegenst\u00e4nden Verlegen von Fussboden",
    "sg:phone":"+41 12416187",
    "sg:postcode":"8026",
    "sg:province":"Z\u00fcrich",
    "wof:name":"Gr\u00fcebler Walter Ag, Z\u00fcrich",
    "wof:placetype":"venue"
},
  "geometry": {"coordinates":[8.5207300186,47.3783187866],"type":"Point"}
}