{
  "type": "Feature",
  "properties": {
    "iso:country":"CH",
    "sg:address":"Chemin De Sorecot 15",
    "sg:city":"Cheseaux-lausanne",
    "sg:orig_category":"Grosshandel mit chemischen Erzeugnissen Grosshandel mit festen Brennstoffen U Mineral\u00f6lerzeugnissen",
    "sg:phone":"+41 21 731 35 75",
    "sg:postcode":"1033",
    "sg:province":"Vaud",
    "wof:name":"Potrans Sa",
    "wof:placetype":"venue"
},
  "geometry": {"coordinates":[6.597058773,46.5843887329],"type":"Point"}
}