{
  "type": "Feature",
  "properties": {
    "iso:country":"CH",
    "sg:address":"Bonnstrasse 1",
    "sg:city":"D\u00fcdingen",
    "sg:orig_category":"Grosshandel mit Textilien Grosshandel mit sonstigen Konsumg\u00fctern",
    "sg:phone":"+41 26 493 43 36",
    "sg:postcode":"3186",
    "sg:province":"Fribourg",
    "wof:name":"Totem Trade Gmbh",
    "wof:placetype":"venue"
},
  "geometry": {"coordinates":[7.1883111,46.8517532349],"type":"Point"}
}