{
  "type": "Feature",
  "properties": {
    "iso:country":"CH",
    "sg:address":"Im Aegelsee 3 8103 Unterengstringen. Postfach 72",
    "sg:city":"Unterengstringen",
    "sg:orig_category":"Grosshandel mit Textilien",
    "sg:phone":"+41 22 735 48 27",
    "sg:postcode":"8103",
    "sg:province":"Z\u00fcrich",
    "wof:name":"Factag Sa",
    "wof:placetype":"venue"
},
  "geometry": {"coordinates":[6.1545119286,46.1999702454],"type":"Point"}
}