{
  "type": "Feature",
  "properties": {
    "iso:country":"CH",
    "sg:address":"Baumackerstrasse 83 8048 Z\u00fcrich. Postfach",
    "sg:city":"Z\u00fcrich",
    "sg:orig_category":"Vereine Gesang",
    "sg:postcode":"8048",
    "sg:province":"Z\u00fcrich",
    "wof:name":"Kirchenchor Heilig-kreuz",
    "wof:placetype":"venue"
},
  "geometry": {"coordinates":[8.5412397385,47.4099502563],"type":"Point"}
}