{
  "type": "Feature",
  "properties": {
    "iso:country":"CH",
    "sg:address":"Luc",
    "sg:city":"Ayent",
    "sg:orig_category":"Haltung von Gefl\u00fcgel",
    "sg:phone":"+41 27 398 44 65",
    "sg:postcode":"1966",
    "sg:province":"Valais",
    "wof:name":"Jean-luc Constantin Parc Avicole",
    "wof:placetype":"venue"
},
  "geometry": {"coordinates":[7.4180102348,46.2824897766],"type":"Point"}
}