{
  "type": "Feature",
  "properties": {
    "iso:country":"CH",
    "sg:address":"Via Cantonale Centro Galleria 3 6928 Manno. Postfach 9",
    "sg:city":"Viganello",
    "sg:orig_category":"Herstellung von sonstigen elektrischen Ausr\u00fcstungen",
    "sg:postcode":"6962",
    "sg:province":"Ticino",
    "wof:name":"Novo Quartz Sa",
    "wof:placetype":"venue"
},
  "geometry": {"coordinates":[8.919005394,46.0345535278],"type":"Point"}
}