{
  "type": "Feature",
  "properties": {
    "iso:country":"CH",
    "sg:address":"Route Du Centre 24",
    "sg:city":"Marly",
    "sg:orig_category":"Detailhandel mit elektrischen Haushalts-,Radio U Fernsehger\u00e4ten sowie Musikinstrumenten",
    "sg:phone":"+41 37461531",
    "sg:postcode":"1723",
    "sg:province":"Fribourg",
    "wof:name":"Nucifora Mario",
    "wof:placetype":"venue"
},
  "geometry": {"coordinates":[7.1521878242,46.7831039429],"type":"Point"}
}