{
  "type": "Feature",
  "properties": {
    "iso:country":"CH",
    "sg:address":"F\u00f6hrenweg 2 4127 Birsfelden. Postfach",
    "sg:city":"Birsfelden",
    "sg:orig_category":"Sonstiger Grosshandel",
    "sg:postcode":"4127",
    "sg:province":"Basel-Landschaft",
    "wof:name":"Swiatrade Ag",
    "wof:placetype":"venue"
},
  "geometry": {"coordinates":[7.6292681694,47.5497932434],"type":"Point"}
}