{
  "type": "Feature",
  "properties": {
    "addr:full":"Dorfstrasse 94 Watt Z\u00fcrich 8105",
    "addr:housenumber":"94",
    "addr:postcode":"8105",
    "addr:street":"Dorfstrasse",
    "iso:country":"CH",
    "sg:address":"Dorfstrasse 94",
    "sg:city":"Watt",
    "sg:orig_category":"Antennenbau Detailhandel mit Radio U Fernsehger\u00e4ten",
    "sg:phone":"+41 56 622 42 77",
    "sg:postcode":"8105",
    "sg:province":"Z\u00fcrich",
    "wof:name":"Sauter & Borcovec Ag Television Antennenbau",
    "wof:placetype":"venue"
},
  "geometry": {"coordinates":[8.275955,47.349693],"type":"Point"}
}