{
  "type": "Feature",
  "properties": {
    "iso:country":"CH",
    "sg:address":"L\u00e4nggasse 50 2500 Biel/bienne. Postfach",
    "sg:city":"Biel/bienne",
    "sg:orig_category":"Unclassifiable Establishments",
    "sg:postcode":"2504",
    "sg:province":"Bern",
    "wof:name":"Tr\u00f6hler Michel.",
    "wof:placetype":"venue"
},
  "geometry": {"coordinates":[7.2745428085,47.1523857117],"type":"Point"}
}