{
  "type": "Feature",
  "properties": {
    "addr:full":"Talholzstrasse 24 Bottmingen Basel-Landschaft 4103",
    "addr:housenumber":"24",
    "addr:postcode":"4103",
    "addr:street":"Talholzstrasse",
    "iso:country":"CH",
    "sg:address":"Talholzstrasse 24",
    "sg:city":"Bottmingen",
    "sg:orig_category":"Architekturb\u00fcros",
    "sg:phone":"+41 61 401 11 30",
    "sg:postcode":"4103",
    "sg:province":"Basel-Landschaft",
    "wof:name":"St\u00f6cklin & Emmenegger Architekturb\u00fcro",
    "wof:placetype":"venue"
},
  "geometry": {"coordinates":[7.572289,47.519512],"type":"Point"}
}