{
  "type": "Feature",
  "properties": {
    "iso:country":"CH",
    "sg:address":"Avenue De Corsier 19",
    "sg:city":"Vevey",
    "sg:orig_category":"Vorschulen, Kinderg\u00e4rten",
    "sg:phone":"+41 21 925 59 52",
    "sg:postcode":"1800",
    "sg:province":"Vaud",
    "wof:name":"Ecole Enfantine De L'ath\u00e9n\u00e9e",
    "wof:placetype":"venue"
},
  "geometry": {"coordinates":[6.8428301811,46.4678153992],"type":"Point"}
}