{
  "type": "Feature",
  "properties": {
    "iso:country":"CH",
    "sg:address":"Gartenweg 21 B",
    "sg:city":"Wohlenschwil",
    "sg:orig_category":"G\u00fcterbef\u00f6rderung im Strassenverkehr",
    "sg:phone":"+41 56 491 03 01",
    "sg:postcode":"5512",
    "sg:province":"Aargau",
    "wof:name":"Robert Keller Transport Gmbh",
    "wof:placetype":"venue"
},
  "geometry": {"coordinates":[8.2600603104,47.4108886719],"type":"Point"}
}