{
  "type": "Feature",
  "properties": {
    "iso:country":"CH",
    "sg:address":"Hinterm\u00e4ttlistrasse 3 5506 M\u00e4genwil. Postfach",
    "sg:city":"M\u00e4genwil",
    "sg:orig_category":"Vermietung U Verpachtung von eigenen Immobilien",
    "sg:postcode":"5506",
    "sg:province":"Aargau",
    "wof:name":"Brack Immobilien Ag",
    "wof:placetype":"venue"
},
  "geometry": {"coordinates":[8.2237968445,47.4103050232],"type":"Point"}
}