{
  "type": "Feature",
  "properties": {
    "iso:country":"CH",
    "sg:address":"Weyermannsstrasse 20 3008 Bern. Postfach",
    "sg:city":"Bern",
    "sg:orig_category":"Sonstige pers\u00f6nliche Dienstleistungen",
    "sg:phone":"+41 31 381 09 06",
    "sg:postcode":"3005",
    "sg:province":"Bern",
    "wof:name":"Isenschmid Bruno Produktionsberatung Offset, Siebdruck U. Kartonagen",
    "wof:placetype":"venue"
},
  "geometry": {"coordinates":[7.4174079895,46.9483985901],"type":"Point"}
}