{
  "type": "Feature",
  "properties": {
    "iso:country":"CH",
    "sg:address":"Les Sassels",
    "sg:city":"Ligni\u00e8res",
    "sg:orig_category":"Physiotherapie",
    "sg:phone":"+41 32 751 39 94",
    "sg:postcode":"2523",
    "sg:province":"Neuch\u00e2tel",
    "wof:name":"Denise Matti Physioth\u00e9rapie",
    "wof:placetype":"venue"
},
  "geometry": {"coordinates":[7.0503048897,47.0754013062],"type":"Point"}
}