{
  "type": "Feature",
  "properties": {
    "addr:full":"Kappelenbad 203 Wynigen Bern 3472",
    "addr:housenumber":"203",
    "addr:postcode":"3472",
    "addr:street":"Wynigen Bern",
    "iso:country":"CH",
    "sg:address":"Kappelenbad 203",
    "sg:city":"Wynigen",
    "sg:orig_category":"Bauschreinerei Herstellung von Konstruktionsteilen, Fertigbauteilen U Ausbauelementen aus Holz",
    "sg:postcode":"3472",
    "sg:province":"Bern",
    "wof:name":"Fritz Strahm",
    "wof:placetype":"venue"
},
  "geometry": {"coordinates":[7.721855,47.098583],"type":"Point"}
}