{
  "type": "Feature",
  "properties": {
    "iso:country":"CH",
    "sg:address":"4656",
    "sg:city":"Starrkirch-wil",
    "sg:orig_category":"Schulpflegen",
    "sg:postcode":"4656",
    "sg:province":"Solothurn",
    "wof:name":"Schulkommission Der Gemeinde Stein",
    "wof:placetype":"venue"
},
  "geometry": {"coordinates":[9.3437595367,47.3727684021],"type":"Point"}
}