{
  "type": "Feature",
  "properties": {
    "iso:country":"CH",
    "sg:address":"Puits Chemin Du Grand- 42",
    "sg:city":"Meyrin",
    "sg:orig_category":"Stukkateurgewerbe, Gipserei U Verputzerei",
    "sg:phone":"+41 22 785 51 90",
    "sg:postcode":"1217",
    "sg:province":"Gen\u00e8ve",
    "wof:name":"Marques Jos\u00e9",
    "wof:placetype":"venue"
},
  "geometry": {"coordinates":[6.0722160339,46.2284431458],"type":"Point"}
}