{
  "type": "Feature",
  "properties": {
    "iso:country":"CH",
    "sg:address":"Talstrasse 2",
    "sg:city":"Zollikon",
    "sg:orig_category":"Fotografisches Gewerbe U fotografische Laboratorien",
    "sg:postcode":"8702",
    "sg:province":"Z\u00fcrich",
    "wof:name":"Szenografie Hoffmann Klaus",
    "wof:placetype":"venue"
},
  "geometry": {"coordinates":[8.792345047,47.3162155151],"type":"Point"}
}