{
  "type": "Feature",
  "properties": {
    "iso:country":"CH",
    "sg:address":"Ca' Sorombela 3 6989 Purasca. Postfach",
    "sg:city":"Molinazzo",
    "sg:orig_category":"Non-Classified Establishments",
    "sg:postcode":"6995",
    "sg:province":"Ticino",
    "wof:name":"Eprotec Extrusion Technology Ag",
    "wof:placetype":"venue"
},
  "geometry": {"coordinates":[9.1468276978,47.5533103943],"type":"Point"}
}