{
  "type": "Feature",
  "properties": {
    "iso:country":"CH",
    "sg:address":"Lenkstrasse 1",
    "sg:city":"Zweisimmen",
    "sg:classifiers":[
        {
            "category":"Travel",
            "subcategory":"Hotels & Motels",
            "type":"Entertainment"
        }
    ],
    "sg:phone":"+41 33 722 18 14",
    "sg:postcode":"3770",
    "sg:province":"Bern",
    "sg:tags":[
        "hotels",
        "mit",
        "restaurant"
    ],
    "wof:name":"Hotel Bergmann",
    "wof:placetype":"venue"
},
  "geometry": {"coordinates":[7.3722162247,46.5534439087],"type":"Point"}
}