{
  "type": "Feature",
  "properties": {
    "iso:country":"CH",
    "sg:address":"Route De Romanel",
    "sg:city":"Bremblens",
    "sg:classifiers":[
        {
            "category":"Autos & Motor Vehicles",
            "subcategory":"Auto Supplies",
            "type":"Retail Goods"
        }
    ],
    "sg:phone":"+41 21 869 02 02",
    "sg:postcode":"1121",
    "sg:province":"Vaud",
    "sg:tags":[
        "automobile",
        "accessory"
    ],
    "wof:name":"Arenaz Automobiles Sa",
    "wof:placetype":"venue"
},
  "geometry": {"coordinates":[6.51576,46.546349],"type":"Point"}
}