{
  "type": "Feature",
  "properties": {
    "iso:country":"CH",
    "sg:address":"Poststrasse 19",
    "sg:city":"Herisau",
    "sg:orig_category":"Elektroinstallation Herstellung von k\u00e4lte U lufttechnischen Erzeugnissen f\u00fcr gewerbliche Zwecke",
    "sg:phone":"+41 71 351 51 71",
    "sg:postcode":"9100",
    "sg:province":"Appenzell Ausserrhoden",
    "wof:name":"Deetz Klimatechnik Ag",
    "wof:placetype":"venue"
},
  "geometry": {"coordinates":[9.2771692276,47.3838310242],"type":"Point"}
}