{
  "type": "Feature",
  "properties": {
    "iso:country":"CH",
    "sg:address":"Kaiserstrasse 34",
    "sg:city":"Rheinfelden",
    "sg:classifiers":[
        {
            "category":"Social Services",
            "subcategory":"Retirement Home",
            "type":"Services"
        }
    ],
    "sg:phone":"+41 61 831 50 72",
    "sg:postcode":"4310",
    "sg:province":"Aargau",
    "sg:tags":[
        "pflegeheime",
        "u",
        "alters"
    ],
    "wof:name":"Altersheim Kloos Der Gemeinde Rheinfelden",
    "wof:placetype":"venue"
},
  "geometry": {"coordinates":[7.787111,47.551781],"type":"Point"}
}