{
  "type": "Feature",
  "properties": {
    "iso:country":"CH",
    "sg:address":"Bahnhofstrasse 5",
    "sg:city":"Wimmis",
    "sg:orig_category":"Zahnarztpraxen",
    "sg:phone":"+41 33 657 17 77",
    "sg:postcode":"3752",
    "sg:province":"Bern",
    "wof:name":"Dr. Med. Dent. Frank Maurer Zahnarzt",
    "wof:placetype":"venue"
},
  "geometry": {"coordinates":[7.635641098,46.6750335693],"type":"Point"}
}