{
  "type": "Feature",
  "properties": {
    "iso:country":"CH",
    "sg:address":"Rosengasse 21",
    "sg:city":"Glarus",
    "sg:orig_category":"Bauschreinerei Herstellung von M\u00f6beln verschiedener Art",
    "sg:phone":"+41 79 218 18 47",
    "sg:postcode":"8750",
    "sg:province":"Glarus",
    "wof:name":"Rudolf H\u00f6sli Mech.bau-& M\u00f6belschreinerei",
    "wof:placetype":"venue"
},
  "geometry": {"coordinates":[9.070979,47.037315],"type":"Point"}
}