{
  "type": "Feature",
  "properties": {
    "iso:country":"CH",
    "sg:address":"Oristalstrasse 23",
    "sg:city":"Liestal",
    "sg:orig_category":"Grosshandel mit B\u00fcromaschinen Grosshandel mit Datenverarbeitungsger\u00e4ten",
    "sg:phone":"+41 55 210 92 29",
    "sg:postcode":"4410",
    "sg:province":"Basel-Landschaft",
    "wof:name":"Twintech Ag",
    "wof:placetype":"venue"
},
  "geometry": {"coordinates":[8.8281564713,47.22813797],"type":"Point"}
}