{
  "type": "Feature",
  "properties": {
    "iso:country":"CH",
    "sg:address":"Soodring 13a 8134 Adliswil. Postfach 1130",
    "sg:city":"Baden",
    "sg:orig_category":"Vermietung U Verpachtung von eigenen Immobilien",
    "sg:postcode":"5400",
    "sg:province":"Aargau",
    "wof:name":"Interdives-immobilien-ag",
    "wof:placetype":"venue"
},
  "geometry": {"coordinates":[8.5214357376,47.3180503845],"type":"Point"}
}