{
  "type": "Feature",
  "properties": {
    "addr:full":"Freiestrasse 39 Uster Z\u00fcrich 8610",
    "addr:housenumber":"39",
    "addr:postcode":"8610",
    "addr:street":"Freiestrasse",
    "iso:country":"CH",
    "sg:address":"Freiestrasse 39",
    "sg:city":"Uster",
    "sg:orig_category":"Allgemeiner Hoch U Tiefbau",
    "sg:postcode":"8610",
    "sg:province":"Z\u00fcrich",
    "wof:name":"Ackermann Urs Baugesch\u00e4ft.",
    "wof:placetype":"venue"
},
  "geometry": {"coordinates":[8.724903,47.347569],"type":"Point"}
}