{
  "type": "Feature",
  "properties": {
    "iso:country":"CH",
    "sg:address":"Hauptstrasse 8",
    "sg:city":"Densb\u00fcren",
    "sg:orig_category":"RESTAURANTS: TEA-ROOMS",
    "sg:postcode":"5026",
    "sg:province":"Aargau",
    "wof:name":"Gastro Rotenfluh Gmbh",
    "wof:placetype":"venue"
},
  "geometry": {"coordinates":[8.6681747437,47.0146865845],"type":"Point"}
}