{
  "type": "Feature",
  "properties": {
    "iso:country":"CH",
    "sg:address":"Pittard Avenue Eug\u00e8ne- 7 1206 Gen\u00e8ve. Postfach",
    "sg:city":"Gen\u00e8ve",
    "sg:orig_category":"Handels-H\u00e4user U Gesellschaften",
    "sg:postcode":"1206",
    "sg:province":"Gen\u00e8ve",
    "wof:name":"Maurice Andr\u00e9 Sauterel",
    "wof:placetype":"venue"
},
  "geometry": {"coordinates":[6.1617598534,46.1920013428],"type":"Point"}
}