{
  "type": "Feature",
  "properties": {
    "iso:country":"CH",
    "sg:address":"Rue St-germain 11",
    "sg:city":"Bussigny-lausanne",
    "sg:orig_category":"Physiotherapie",
    "sg:phone":"+41 21 702 26 46",
    "sg:postcode":"1030",
    "sg:province":"Vaud",
    "wof:name":"Mireille Bonvin Physioth\u00e9rapie",
    "wof:placetype":"venue"
},
  "geometry": {"coordinates":[6.5496630669,46.5503234863],"type":"Point"}
}