{
  "type": "Feature",
  "properties": {
    "addr:full":"Bella Tola Montana-vermala 3962",
    "addr:housenumber":"3962",
    "iso:country":"CH",
    "sg:address":"Bella Tola",
    "sg:city":"Montana-vermala",
    "sg:orig_category":"Detailhandel mit Bekleidung Detailhandel mit Sportartikeln",
    "sg:phone":"+41 27 481 22 88",
    "sg:postcode":"3962",
    "wof:name":"Jacques Marais Montana-sports",
    "wof:placetype":"venue"
},
  "geometry": {"coordinates":[7.492434,46.314419],"type":"Point"}
}