{
  "type": "Feature",
  "properties": {
    "iso:country":"CH",
    "sg:address":"Rathausstrasse",
    "sg:city":"Liestal",
    "sg:orig_category":"Pensionskassen",
    "sg:phone":"+41 22 809 16 16",
    "sg:postcode":"4410",
    "sg:province":"Basel-Landschaft",
    "wof:name":"Cia Caisse De Pr\u00e9voyance Du Pers.enseignant & Fonctionn.",
    "wof:placetype":"venue"
},
  "geometry": {"coordinates":[6.1345381737,46.201171875],"type":"Point"}
}