{
  "type": "Feature",
  "properties": {
    "addr:full":"Seestrasse 3 Unter\u00e4geri Zug 6314",
    "addr:housenumber":"3",
    "addr:postcode":"6314",
    "addr:street":"Seestrasse;Zug",
    "iso:country":"CH",
    "sg:address":"Seestrasse 3",
    "sg:city":"Unter\u00e4geri",
    "sg:orig_category":"Detailhandel mit Blumen U Pflanzen Fachdetailhandel in Verkaufsr\u00e4umen",
    "sg:phone":"+41 41 750 49 38",
    "sg:postcode":"6314",
    "sg:province":"Zug",
    "wof:name":"Blumen Schmid, A. Meier-schmid",
    "wof:placetype":"venue"
},
  "geometry": {"coordinates":[8.584984,47.137569],"type":"Point"}
}