{
  "type": "Feature",
  "properties": {
    "iso:country":"CH",
    "sg:address":"Emmentalerstrasse 75",
    "sg:city":"Oberburg",
    "sg:orig_category":"Maschinenbau Pulvermetallurgie Schmieden, Pressen, Stanzen U Profilwalzen von Metallen",
    "sg:phone":"+41 34 422 19 81",
    "sg:postcode":"3414",
    "sg:province":"Bern",
    "wof:name":"Fl\u00fckiger & Co Ag",
    "wof:placetype":"venue"
},
  "geometry": {"coordinates":[7.631444931,47.0344657898],"type":"Point"}
}