{
  "type": "Feature",
  "properties": {
    "iso:country":"CH",
    "sg:address":"Avenue De L'industrie 25b",
    "sg:city":"Monthey",
    "sg:orig_category":"Herstellung von sonstigen elektrischen Ausr\u00fcstungen Softwareentwicklung U beratung",
    "sg:phone":"+41 61 486 91 86",
    "sg:postcode":"1870",
    "sg:province":"Valais",
    "wof:name":"Alltronic Ag",
    "wof:placetype":"venue"
},
  "geometry": {"coordinates":[7.5427632332,47.5568885803],"type":"Point"}
}