{
  "type": "Feature",
  "properties": {
    "iso:country":"CH",
    "sg:address":"Jungfraustrasse 32",
    "sg:city":"Biberist",
    "sg:orig_category":"Mechanik",
    "sg:phone":"+41 32 672 31 24",
    "sg:postcode":"4562",
    "sg:province":"Solothurn",
    "wof:name":"Blaser Walter",
    "wof:placetype":"venue"
},
  "geometry": {"coordinates":[7.5498428345,47.1850242615],"type":"Point"}
}