{
  "type": "Feature",
  "properties": {
    "iso:country":"CH",
    "sg:address":"Bahnhofstrasse 19",
    "sg:city":"Herisau",
    "sg:orig_category":"Non-Classified Establishments",
    "sg:postcode":"9100",
    "sg:province":"Appenzell Ausserrhoden",
    "wof:name":"Listh Reworld Control Ag",
    "wof:placetype":"venue"
},
  "geometry": {"coordinates":[9.2769775391,47.3877487183],"type":"Point"}
}