{
  "type": "Feature",
  "properties": {
    "iso:country":"CH",
    "sg:address":"Via Maraini 9",
    "sg:city":"Savosa",
    "sg:orig_category":"Dachdeckerei Zimmerei, Ingenieurholzbau",
    "sg:phone":"+41 91 966 40 49",
    "sg:postcode":"6942",
    "sg:province":"Ticino",
    "wof:name":"Eredi Fu Fioravanti Genola Carpenteria & Copertura Tetti",
    "wof:placetype":"venue"
},
  "geometry": {"coordinates":[8.950526,46.018478],"type":"Point"}
}