{
  "type": "Feature",
  "properties": {
    "iso:country":"CH",
    "sg:address":"Industriestrasse 1",
    "sg:city":"Rothrist",
    "sg:orig_category":"Unclassifiable Establishments",
    "sg:postcode":"4852",
    "sg:province":"Aargau",
    "wof:name":"Auto-glas-technik Br\u00fcnisholz Gmbh",
    "wof:placetype":"venue"
},
  "geometry": {"coordinates":[7.8665118217,47.3001594543],"type":"Point"}
}