{
  "type": "Feature",
  "properties": {
    "iso:country":"CH",
    "sg:address":"6072",
    "sg:city":"Sachseln",
    "sg:orig_category":"Non-Classified Establishments",
    "sg:postcode":"6072",
    "sg:province":"Obwalden",
    "wof:name":"Delco Ag",
    "wof:placetype":"venue"
},
  "geometry": {"coordinates":[8.2388353348,46.8688735962],"type":"Point"}
}