{
  "type": "Feature",
  "properties": {
    "iso:country":"CH",
    "sg:address":"1484",
    "sg:city":"Aumont",
    "sg:orig_category":"S\u00e4gewerke",
    "sg:phone":"+41 26 665 23 65",
    "sg:postcode":"1484",
    "sg:province":"Fribourg",
    "wof:name":"Jean-claude Moret Scierie",
    "wof:placetype":"venue"
},
  "geometry": {"coordinates":[6.8496398926,46.8000106812],"type":"Point"}
}