{
  "type": "Feature",
  "properties": {
    "iso:country":"CH",
    "sg:address":"Grabenackerstrasse 23",
    "sg:city":"Oberhasli",
    "sg:orig_category":"G\u00fcterbef\u00f6rderung im Strassenverkehr",
    "sg:phone":"+41 18505150",
    "sg:postcode":"8156",
    "sg:province":"Z\u00fcrich",
    "wof:name":"Volkart & Co",
    "wof:placetype":"venue"
},
  "geometry": {"coordinates":[8.5000619888,47.465511322],"type":"Point"}
}