{
  "type": "Feature",
  "properties": {
    "iso:country":"CH",
    "sg:address":"Sch\u00f6nb\u00fchlring 37 6005 Luzern. Postfach",
    "sg:city":"Luzern",
    "sg:orig_category":"Softwareentwicklung U beratung",
    "sg:postcode":"6003",
    "sg:province":"Luzern",
    "wof:name":"Ab Computers Ronald Antony Edv, Software, Zubeh\u00f6r Usw; Verkauf",
    "wof:placetype":"venue"
},
  "geometry": {"coordinates":[8.3279695511,47.0389099121],"type":"Point"}
}