{
  "type": "Feature",
  "properties": {
    "iso:country":"CH",
    "sg:address":"Aeschengraben 9 4051 Basel. Postfach",
    "sg:city":"Basel",
    "sg:orig_category":"Unclassifiable Establishments",
    "sg:postcode":"4051",
    "sg:province":"Basel-Stadt",
    "wof:name":"Dance Hall Ag",
    "wof:placetype":"venue"
},
  "geometry": {"coordinates":[8.8225984573,47.2270393372],"type":"Point"}
}