{
  "type": "Feature",
  "properties": {
    "iso:country":"CH",
    "sg:address":"Bahnhofstrasse 20",
    "sg:city":"Dielsdorf",
    "sg:classifiers":[
        {
            "category":"Professional",
            "subcategory":"Advertising",
            "type":"Services"
        }
    ],
    "sg:phone":"+41 18540480",
    "sg:postcode":"8157",
    "sg:province":"Z\u00fcrich",
    "sg:tags":[
        "agency"
    ],
    "wof:name":"Rheingold & Partner",
    "wof:placetype":"venue"
},
  "geometry": {"coordinates":[8.455998,47.482269],"type":"Point"}
}