{
  "type": "Feature",
  "properties": {
    "iso:country":"CH",
    "sg:address":"Kornmarktgasse 1",
    "sg:city":"Luzern",
    "sg:orig_category":"Detailhandel mit Schuhen Detailhandel mit Schuhen U Lederwaren",
    "sg:postcode":"6004",
    "sg:province":"Luzern",
    "wof:name":"Nunziato Schiliro",
    "wof:placetype":"venue"
},
  "geometry": {"coordinates":[6.1432762146,46.1889343262],"type":"Point"}
}