{
  "type": "Feature",
  "properties": {
    "iso:country":"CH",
    "sg:address":"Eisselmatt 510 3155 Helgisried. Postfach",
    "sg:city":"Helgisried",
    "sg:orig_category":"Unternehmensberatung",
    "sg:postcode":"3155",
    "sg:province":"Bern",
    "wof:name":"P3 Consulting M\u00fcller J\u00fcrg",
    "wof:placetype":"venue"
},
  "geometry": {"coordinates":[7.4309921265,46.8160171509],"type":"Point"}
}