{
  "type": "Feature",
  "properties": {
    "iso:country":"CH",
    "sg:address":"Poststrasse 1",
    "sg:city":"Sarnen",
    "sg:orig_category":"Vereine Hundedressur",
    "sg:postcode":"6060",
    "sg:province":"Obwalden",
    "wof:name":"Hundesport Uster & Umgebung",
    "wof:placetype":"venue"
},
  "geometry": {"coordinates":[9.1546421051,47.5675811768],"type":"Point"}
}