{
  "type": "Feature",
  "properties": {
    "iso:country":"CH",
    "sg:address":"Chemin Du Ch\u00eane 38",
    "sg:city":"Mont-sur-lausanne",
    "sg:orig_category":"Datenverarbeitungsdienste Sonstige mit der Informatik verbundene T\u00e4tigkeiten",
    "sg:phone":"+41 21 652 63 77",
    "sg:postcode":"1052",
    "sg:province":"Vaud",
    "wof:name":"Ifc, Schwarz Ren\u00e9",
    "wof:placetype":"venue"
},
  "geometry": {"coordinates":[6.63177,46.54969],"type":"Point"}
}