{
  "type": "Feature",
  "properties": {
    "iso:country":"CH",
    "sg:address":"Langenmattstrasse 20 8617 M\u00f6nchaltorf. Postfach",
    "sg:city":"M\u00f6nchaltorf",
    "sg:orig_category":"Grosshandel mit Getreide, Saatgut U Futtermitteln",
    "sg:postcode":"8617",
    "sg:province":"Z\u00fcrich",
    "wof:name":"Rheingem\u00fcse Gmbh",
    "wof:placetype":"venue"
},
  "geometry": {"coordinates":[9.5764513016,47.3154144287],"type":"Point"}
}