{
  "type": "Feature",
  "properties": {
    "iso:country":"CH",
    "sg:address":"Fr\u00f6schenweidstrasse 10",
    "sg:city":"Winterthur",
    "sg:orig_category":"Herstellung von Elektromotoren, Generatoren U Transformatoren",
    "sg:phone":"+41 52 226 00 26",
    "sg:postcode":"8408",
    "sg:province":"Z\u00fcrich",
    "wof:name":"Elektro Design + Partner Ag Stark, Schwachstromanlagen Usw; Projektierung, Berechnung",
    "wof:placetype":"venue"
},
  "geometry": {"coordinates":[8.7644844055,47.4955062866],"type":"Point"}
}