{
  "type": "Feature",
  "properties": {
    "addr:full":"Rue De Monthoux 64 Gen\u00e8ve Gen\u00e8ve 1201",
    "addr:housenumber":"64",
    "addr:postcode":"1201",
    "addr:street":"Rue De Monthoux",
    "iso:country":"CH",
    "sg:address":"Rue De Monthoux 64",
    "sg:city":"Gen\u00e8ve",
    "sg:orig_category":"Berufliche Weiterbildung, Erwachsenenbildung Informatikschulen",
    "sg:phone":"+41 22 738 80 80",
    "sg:postcode":"1201",
    "sg:province":"Gen\u00e8ve",
    "wof:name":"Digicomp Sa",
    "wof:placetype":"venue"
},
  "geometry": {"coordinates":[6.145091,46.211723],"type":"Point"}
}