{
  "type": "Feature",
  "properties": {
    "iso:country":"CH",
    "sg:address":"Freiburgstrasse 4",
    "sg:city":"Wahlern",
    "sg:orig_category":"Architektur U Ingenieurb\u00fcros Innenarchitekturb\u00fcros",
    "sg:phone":"+41 79 302 07 87",
    "sg:postcode":"3150",
    "sg:province":"Bern",
    "wof:name":"Artiv Innenarchitektur Ag",
    "wof:placetype":"venue"
},
  "geometry": {"coordinates":[7.340353,46.818062],"type":"Point"}
}