{
  "type": "Feature",
  "properties": {
    "addr:full":"St. Johanns-ring 116 Basel Basel-Stadt 4056",
    "addr:housenumber":"116",
    "addr:postcode":"4056",
    "iso:country":"CH",
    "sg:address":"St. Johanns-ring 116",
    "sg:city":"Basel",
    "sg:orig_category":"Datenverarbeitungsdienste Sonstige mit der Informatik verbundene T\u00e4tigkeiten",
    "sg:phone":"+41 61 382 23 26",
    "sg:postcode":"4056",
    "sg:province":"Basel-Stadt",
    "wof:name":"Dpt Data Promotion Trade Ag",
    "wof:placetype":"venue"
},
  "geometry": {"coordinates":[7.575124,47.562744],"type":"Point"}
}