{
  "type": "Feature",
  "properties": {
    "iso:country":"CH",
    "sg:address":"Sand",
    "sg:city":"Matt",
    "sg:orig_category":"Vermietung U Verpachtung von eigenen Immobilien",
    "sg:postcode":"8766",
    "sg:province":"Glarus",
    "wof:name":"Caseta Ag",
    "wof:placetype":"venue"
},
  "geometry": {"coordinates":[9.1725101471,46.9570846558],"type":"Point"}
}