{
  "type": "Feature",
  "properties": {
    "iso:country":"CH",
    "sg:address":"3864",
    "sg:city":"Guttannen",
    "sg:orig_category":"Schulpflegen",
    "sg:postcode":"3864",
    "sg:province":"Bern",
    "wof:name":"Primarschulkommission Der Gemeinde Gwatt (thun)",
    "wof:placetype":"venue"
},
  "geometry": {"coordinates":[7.623691082,46.7237892151],"type":"Point"}
}