{
  "type": "Feature",
  "properties": {
    "iso:country":"CH",
    "sg:address":"Ziegelbr\u00fcckstrasse",
    "sg:city":"Niederurnen",
    "sg:orig_category":"Sonstige mit Sport verbundene T\u00e4tigkeiten",
    "sg:postcode":"8867",
    "sg:province":"Glarus",
    "wof:name":"Gest\u00fct Linth, Marianne Sch\u00e4r",
    "wof:placetype":"venue"
},
  "geometry": {"coordinates":[9.0587711334,47.131401062],"type":"Point"}
}