{
  "type": "Feature",
  "properties": {
    "iso:country":"CH",
    "sg:address":"T\u00fcrgass 11 8820 W\u00e4denswil. Postfach",
    "sg:city":"W\u00e4denswil",
    "sg:orig_category":"Softwareentwicklung U beratung",
    "sg:phone":"+41 21 694 20 90",
    "sg:postcode":"8820",
    "sg:province":"Z\u00fcrich",
    "wof:name":"Sylog Consulting Sa",
    "wof:placetype":"venue"
},
  "geometry": {"coordinates":[6.5575327873,46.510093689],"type":"Point"}
}