{
  "type": "Feature",
  "properties": {
    "iso:country":"CH",
    "sg:address":"Kasernenstrasse 43",
    "sg:city":"B\u00fclach",
    "sg:orig_category":"Kinos",
    "sg:phone":"+41 18601570",
    "sg:postcode":"8180",
    "sg:province":"Z\u00fcrich",
    "wof:name":"Stillhard-m\u00fcller L. M.",
    "wof:placetype":"venue"
},
  "geometry": {"coordinates":[8.5355062485,47.517326355],"type":"Point"}
}