{
  "type": "Feature",
  "properties": {
    "addr:full":"Rue Charles-galland 15 Gen\u00e8ve Gen\u00e8ve 1206",
    "addr:housenumber":"15",
    "addr:postcode":"1206",
    "addr:street":"Rue Charles-Galland",
    "iso:country":"CH",
    "sg:address":"Rue Charles-galland 15",
    "sg:city":"Gen\u00e8ve",
    "sg:orig_category":"Arztpraxen",
    "sg:phone":"+41 22 704 05 55",
    "sg:postcode":"1206",
    "sg:province":"Gen\u00e8ve",
    "wof:name":"Dr M\u00e9d. Francis Karim M\u00e9decin Sp\u00e9cialiste Fmh",
    "wof:placetype":"venue"
},
  "geometry": {"coordinates":[6.154413,46.197803],"type":"Point"}
}