{
  "type": "Feature",
  "properties": {
    "iso:country":"CH",
    "sg:address":"Gor Chemin Du 3",
    "sg:city":"Sugiez",
    "sg:orig_category":"Instandhaltung U Reparatur von Automobilen",
    "sg:phone":"+41 34 402 28 11",
    "sg:postcode":"1786",
    "sg:province":"Fribourg",
    "wof:name":"Carrosserie Dubach Ag",
    "wof:placetype":"venue"
},
  "geometry": {"coordinates":[7.757589817,46.9491271973],"type":"Point"}
}