{
  "type": "Feature",
  "properties": {
    "iso:country":"CH",
    "sg:address":"Gaudy-le-fort Rue 14",
    "sg:city":"Onex",
    "sg:orig_category":"RESTAURANTS: TEA-ROOMS",
    "sg:postcode":"1213",
    "sg:province":"Gen\u00e8ve",
    "wof:name":"Vuille Philippe",
    "wof:placetype":"venue"
},
  "geometry": {"coordinates":[6.1001119614,46.182056427],"type":"Point"}
}