{
  "type": "Feature",
  "properties": {
    "iso:country":"CH",
    "sg:address":"Gerlisberg",
    "sg:city":"Luzern",
    "sg:orig_category":"Bibliotheken U Archive Wohnheime",
    "sg:phone":"+41 41 370 37 43",
    "sg:postcode":"6006",
    "sg:province":"Luzern",
    "wof:name":"Kloster St.anna",
    "wof:placetype":"venue"
},
  "geometry": {"coordinates":[8.3392114639,47.0586929321],"type":"Point"}
}