{
  "type": "Feature",
  "properties": {
    "iso:country":"CH",
    "sg:address":"Ottikerstrasse 24",
    "sg:city":"Z\u00fcrich",
    "sg:classifiers":[
        {
            "category":"Communications",
            "subcategory":"Film & Video Production",
            "type":"Services"
        }
    ],
    "sg:phone":"+41 43 255 10 10",
    "sg:postcode":"8006",
    "sg:province":"Z\u00fcrich",
    "sg:tags":[
        "audio-visual"
    ],
    "wof:name":"Topic Film Ag",
    "wof:placetype":"venue"
},
  "geometry": {"coordinates":[8.545247,47.385731],"type":"Point"}
}