{
  "type": "Feature",
  "properties": {
    "iso:country":"CH",
    "sg:address":"Im G\u00e4rtli 1",
    "sg:city":"Oberaach",
    "sg:orig_category":"Grosshandel mit B\u00fcromaschinen Grosshandel mit Datenverarbeitungsger\u00e4ten",
    "sg:phone":"+41 71 411 61 21",
    "sg:postcode":"8587",
    "sg:province":"Thurgau",
    "wof:name":"Comtec Principe Gabriela",
    "wof:placetype":"venue"
},
  "geometry": {"coordinates":[9.2637586594,47.5609512329],"type":"Point"}
}