{
  "type": "Feature",
  "properties": {
    "iso:country":"CH",
    "sg:address":"6010",
    "sg:city":"Kriens",
    "sg:orig_category":"Vereine Quartier",
    "sg:phone":"+41 19107378",
    "sg:postcode":"6010",
    "sg:province":"Luzern",
    "wof:name":"Quartierverein K\u00fcsnacht-dorf",
    "wof:placetype":"venue"
},
  "geometry": {"coordinates":[8.5818166733,47.3190231323],"type":"Point"}
}