{
  "type": "Feature",
  "properties": {
    "iso:country":"CH",
    "sg:address":"Schulstrasse 11",
    "sg:city":"Thun",
    "sg:orig_category":"Drogerien Sonstiger Fachdetailhandel mit Nahrungsmitteln, Getr\u00e4nken U Tabak in Verkaufsr\u00e4umen",
    "sg:phone":"+41 33 336 88 18",
    "sg:postcode":"3604",
    "sg:province":"Bern",
    "wof:name":"H\u00fcttinger D\u00fcrrenast Drogerie",
    "wof:placetype":"venue"
},
  "geometry": {"coordinates":[7.6257429123,46.7406806946],"type":"Point"}
}