{
  "type": "Feature",
  "properties": {
    "iso:country":"CH",
    "sg:address":"Matzwil. 3271 Radelfingen. Postfach",
    "sg:city":"Detligen",
    "sg:orig_category":"Schreib U \u00dcbersetzungsb\u00fcros",
    "sg:postcode":"3036",
    "sg:province":"Bern",
    "wof:name":"Kamnarokos Stilianos.",
    "wof:placetype":"venue"
},
  "geometry": {"coordinates":[7.2787270546,46.9853210449],"type":"Point"}
}