{
  "type": "Feature",
  "properties": {
    "iso:country":"CH",
    "sg:address":"Hofwiesstrasse 17 8862 Sch\u00fcbelbach. Postfach",
    "sg:city":"Sch\u00fcbelbach",
    "sg:orig_category":"Allgemeiner Hoch U Tiefbau",
    "sg:postcode":"8862",
    "sg:province":"Schwyz",
    "wof:name":"Ivan Bau Gmbh Baugesch\u00e4ft",
    "wof:placetype":"venue"
},
  "geometry": {"coordinates":[8.927916,47.171612],"type":"Point"}
}