{
  "type": "Feature",
  "properties": {
    "iso:country":"CH",
    "sg:address":"1041",
    "sg:city":"Bettens",
    "sg:orig_category":"Grosshandel mit Getreide, Saatgut U Futtermitteln",
    "sg:phone":"+41 91 827 35 60",
    "sg:postcode":"1041",
    "sg:province":"Vaud",
    "wof:name":"Rovergrains Ag",
    "wof:placetype":"venue"
},
  "geometry": {"coordinates":[9.1283597946,46.2375984192],"type":"Point"}
}