{
  "type": "Feature",
  "properties": {
    "iso:country":"CH",
    "sg:address":"Clozza",
    "sg:city":"Scuol",
    "sg:orig_category":"Allgemeiner Hoch U Tiefbau",
    "sg:phone":"+41 81 864 11 46",
    "sg:postcode":"7550",
    "sg:province":"Graubunden",
    "wof:name":"Impraisa Denoth Sa",
    "wof:placetype":"venue"
},
  "geometry": {"coordinates":[10.304555,46.79747],"type":"Point"}
}