{
  "type": "Feature",
  "properties": {
    "iso:country":"CH",
    "sg:address":"Stadtbrunnenhaus",
    "sg:city":"Gr\u00fcningen",
    "sg:orig_category":"Reinigungsgewerbe",
    "sg:phone":"+41 71 744 39 70",
    "sg:postcode":"8627",
    "sg:province":"Z\u00fcrich",
    "wof:name":"Bichsel Karl Geb\u00e4udeunterhalt",
    "wof:placetype":"venue"
},
  "geometry": {"coordinates":[9.6435194016,47.4250984192],"type":"Point"}
}