{
  "type": "Feature",
  "properties": {
    "iso:country":"CH",
    "sg:address":"K\u00f6llikerstrasse",
    "sg:city":"Safenwil",
    "sg:orig_category":"Handel mit Motorr\u00e4dern, Teilen U Zubeh\u00f6r Instandhaltung U Reparatur von Motorr\u00e4dern",
    "sg:postcode":"5745",
    "sg:province":"Aargau",
    "wof:name":"Velos-motos Zimmerli",
    "wof:placetype":"venue"
},
  "geometry": {"coordinates":[8.0024061203,47.322593689],"type":"Point"}
}