{
  "type": "Feature",
  "properties": {
    "iso:country":"CH",
    "sg:address":"Bahnhofstrasse 13",
    "sg:city":"Effretikon",
    "sg:orig_category":"Zahnarztpraxen",
    "sg:phone":"+41 71 891 38 01",
    "sg:postcode":"8307",
    "sg:province":"Z\u00fcrich",
    "wof:name":"Dr.med.dent.franz Niedermayer Zahnarzt",
    "wof:placetype":"venue"
},
  "geometry": {"coordinates":[9.5632619858,47.4255828857],"type":"Point"}
}