{
  "type": "Feature",
  "properties": {
    "iso:country":"CH",
    "sg:address":"Weihersteig 1",
    "sg:city":"Z\u00fcrich",
    "sg:orig_category":"Vereine Z\u00fcnfte",
    "sg:postcode":"8037",
    "sg:province":"Z\u00fcrich",
    "wof:name":"Zunft Zum Weggen",
    "wof:placetype":"venue"
},
  "geometry": {"coordinates":[8.5274925232,47.3976364136],"type":"Point"}
}