{
  "type": "Feature",
  "properties": {
    "iso:country":"CH",
    "sg:address":"Schnabelgasse 6 4051 Basel. Postfach",
    "sg:city":"Basel",
    "sg:orig_category":"Grosshandel mit Bekleidung",
    "sg:phone":"+41 21 971 19 80",
    "sg:postcode":"4001",
    "sg:province":"Basel-Stadt",
    "wof:name":"Jacques Romann S\u00e0rl Importateur Pr\u00eat-\u00e0-porter",
    "wof:placetype":"venue"
},
  "geometry": {"coordinates":[6.8548531532,46.4531669617],"type":"Point"}
}