{
  "type": "Feature",
  "properties": {
    "iso:country":"CH",
    "sg:address":"9320",
    "sg:city":"Arbon",
    "sg:classifiers":[
        {
            "category":"Education",
            "subcategory":"Vocational School",
            "type":"Public Place"
        }
    ],
    "sg:phone":"+41 62 752 37 35",
    "sg:postcode":"9320",
    "sg:province":"Thurgau",
    "sg:tags":[
        "koch-",
        "haushaltschulen"
    ],
    "wof:name":"Haushaltungsschule",
    "wof:placetype":"venue"
},
  "geometry": {"coordinates":[9.4349451065,47.5160446167],"type":"Point"}
}