{
  "type": "Feature",
  "properties": {
    "iso:country":"CH",
    "sg:address":"Route De Malagny 35",
    "sg:city":"Genthod",
    "sg:classifiers":[
        {
            "category":"Travel",
            "subcategory":"Hotels & Motels",
            "type":"Entertainment"
        }
    ],
    "sg:phone":"+41 22 755 16 11",
    "sg:postcode":"1294",
    "sg:province":"Gen\u00e8ve",
    "sg:tags":[
        "pflegeheime",
        "restaurant",
        "mit",
        "u",
        "alters",
        "hotels"
    ],
    "wof:name":"Pension Mimosas Sa Pour Personnes \u00e2g\u00e9es",
    "wof:placetype":"venue"
},
  "geometry": {"coordinates":[6.158695,46.26968],"type":"Point"}
}