{
  "type": "Feature",
  "properties": {
    "iso:country":"CH",
    "sg:address":"Le Coin 21",
    "sg:city":"Orvin",
    "sg:orig_category":"Bauspenglerei Herstellung von Konstruktionsteilen, Fertigbauteilen U Ausbauelementen aus Holz",
    "sg:phone":"+41 32 358 12 37",
    "sg:postcode":"2534",
    "sg:province":"Bern",
    "wof:name":"Bertrand Grosjean Inst.sanitaires & Ferblanterie",
    "wof:placetype":"venue"
},
  "geometry": {"coordinates":[7.214869,47.159664],"type":"Point"}
}