{
  "type": "Feature",
  "properties": {
    "iso:country":"CH",
    "sg:address":"M\u00fchlegasse 12",
    "sg:city":"Olten",
    "sg:orig_category":"RESTAURANTS: TEA-ROOMS",
    "sg:phone":"+41 62 212 07 80",
    "sg:postcode":"4600",
    "sg:province":"Solothurn",
    "wof:name":"Atrest Ag",
    "wof:placetype":"venue"
},
  "geometry": {"coordinates":[7.9026889801,47.3493461609],"type":"Point"}
}