{
  "type": "Feature",
  "properties": {
    "iso:country":"CH",
    "sg:address":"Feld\u00e4ckerweg 3",
    "sg:city":"W\u00e4ngi",
    "sg:orig_category":"Vorschulen, Kinderg\u00e4rten",
    "sg:phone":"+41 52 378 19 52",
    "sg:postcode":"9545",
    "sg:province":"Thurgau",
    "wof:name":"Kindergarten Feld\u00e4ckerweg",
    "wof:placetype":"venue"
},
  "geometry": {"coordinates":[8.9476270676,47.4959182739],"type":"Point"}
}