{
  "type": "Feature",
  "properties": {
    "iso:country":"CH",
    "sg:address":"Leutschenstrasse 8",
    "sg:city":"Kirchlindach",
    "sg:orig_category":"Detailhandel mit Textilien",
    "sg:phone":"+41 31 311 68 02",
    "sg:postcode":"3038",
    "sg:province":"Bern",
    "wof:name":"Pierre K\u00fcng Bettwarengesch\u00e4ft",
    "wof:placetype":"venue"
},
  "geometry": {"coordinates":[7.4143629074,47.0023536682],"type":"Point"}
}