{
  "type": "Feature",
  "properties": {
    "iso:country":"CH",
    "sg:address":"Rue Centrale 38 1880 Bex. Postfach",
    "sg:city":"Bex",
    "sg:classifiers":[
        {
            "category":"Travel",
            "subcategory":"Hotels & Motels",
            "type":"Entertainment"
        }
    ],
    "sg:phone":"+41 24 463 21 38",
    "sg:postcode":"1880",
    "sg:province":"Vaud",
    "sg:tags":[
        "hotels",
        "mit",
        "restaurant"
    ],
    "wof:name":"H\u00f4tel \u00e0 La Grappe-d'or",
    "wof:placetype":"venue"
},
  "geometry": {"coordinates":[7.0150017738,46.2504692078],"type":"Point"}
}