{
  "type": "Feature",
  "properties": {
    "iso:country":"CH",
    "sg:address":"Dettenriederstrasse 21",
    "sg:city":"Weisslingen",
    "sg:orig_category":"Elektroinstallation",
    "sg:phone":"+41 52 384 18 36",
    "sg:postcode":"8484",
    "sg:province":"Z\u00fcrich",
    "wof:name":"Tr\u00fcmpy Arnold",
    "wof:placetype":"venue"
},
  "geometry": {"coordinates":[8.7649049759,47.4329681396],"type":"Point"}
}