{
  "type": "Feature",
  "properties": {
    "iso:country":"CH",
    "sg:address":"Geuenseestrasse 5 6210 Sursee. Postfach",
    "sg:city":"Sursee",
    "sg:orig_category":"Wirtschaftsverb\u00e4nde Industrie, Handel and Gewerbe",
    "sg:phone":"+41 41 921 30 50",
    "sg:postcode":"6210",
    "sg:province":"Luzern",
    "wof:name":"Vereinig.schweiz.bohrfirmen Zentralsekretariat",
    "wof:placetype":"venue"
},
  "geometry": {"coordinates":[8.1104516983,47.1743049622],"type":"Point"}
}