{
  "type": "Feature",
  "properties": {
    "iso:country":"CH",
    "sg:address":"Obere Vorstadt 37 5000 Aarau. Postfach",
    "sg:city":"Aarau",
    "sg:orig_category":"Elektrizit\u00e4tsversorgung Gasversorgung",
    "sg:phone":"+41 56 441 15 41",
    "sg:postcode":"5001",
    "sg:province":"Aargau",
    "wof:name":"Industrielle Betriebe Der Stadt Brugg",
    "wof:placetype":"venue"
},
  "geometry": {"coordinates":[8.2075538635,47.4850006104],"type":"Point"}
}