{
  "type": "Feature",
  "properties": {
    "iso:country":"CH",
    "sg:address":"Petite Camargue 38 1897 Bouveret. Postfach",
    "sg:city":"Bouveret",
    "sg:orig_category":"Stukkateurgewerbe, Gipserei U Verputzerei",
    "sg:phone":"+41 24 481 30 13",
    "sg:postcode":"1897",
    "sg:province":"Valais",
    "wof:name":"Dervey Gilbert",
    "wof:placetype":"venue"
},
  "geometry": {"coordinates":[6.8685569763,46.3819732666],"type":"Point"}
}