{
  "type": "Feature",
  "properties": {
    "iso:country":"CH",
    "sg:address":"Dammerkirchstrasse 63 4056 Basel. Postfach",
    "sg:city":"Basel",
    "sg:orig_category":"Unclassifiable Establishments",
    "sg:postcode":"4056",
    "sg:province":"Basel-Stadt",
    "wof:name":"Innen Aussen L\u00dcdin Einrichtungsgegenst\u00e4nde F\u00fcr Haus U. Garten; Herstellung U. Reparatur",
    "wof:placetype":"venue"
},
  "geometry": {"coordinates":[7.5663661957,47.5662345886],"type":"Point"}
}