{
  "type": "Feature",
  "properties": {
    "iso:country":"CH",
    "sg:address":"Gewerbestrasse 16",
    "sg:city":"Allschwil",
    "sg:orig_category":"Softwareentwicklung U beratung",
    "sg:phone":"+41 61 332 09 89",
    "sg:postcode":"4123",
    "sg:province":"Basel-Landschaft",
    "wof:name":"M&h Informatics Ag",
    "wof:placetype":"venue"
},
  "geometry": {"coordinates":[7.5450367928,47.5578231812],"type":"Point"}
}