{
  "type": "Feature",
  "properties": {
    "iso:country":"CH",
    "sg:address":"Zelgstrasse 43 8003 Z\u00fcrich. Postfach",
    "sg:city":"Z\u00fcrich",
    "sg:orig_category":"Markt U Meinungsforschung",
    "sg:postcode":"8001",
    "sg:province":"Z\u00fcrich",
    "wof:name":"Jauch Und Klauss, Jk Think Tank Ideen-marketing, Kommunikationshilfe, Unternehmensberatung",
    "wof:placetype":"venue"
},
  "geometry": {"coordinates":[8.520989418,47.3684921265],"type":"Point"}
}