{
  "type": "Feature",
  "properties": {
    "iso:country":"CH",
    "sg:address":"Carmenstrasse 28 8032 Z\u00fcrich 32 Zust. Postfach 8032 Z\u00fcrich",
    "sg:city":"Zust",
    "sg:classifiers":[
        {
            "category":"Professional",
            "subcategory":"Employment Agencies",
            "type":"Services"
        }
    ],
    "sg:postcode":"32",
    "sg:tags":[
        "personal",
        "u",
        "stellenvermittlung"
    ],
    "wof:name":"Jobs.ch Ag Online-stellenm\u00e4rkte; Konzeption, Entwicklung, Betrieb",
    "wof:placetype":"venue"
},
  "geometry": {"coordinates":[8.5679702759,47.3668403625],"type":"Point"}
}