{
  "type": "Feature",
  "properties": {
    "iso:country":"CH",
    "sg:address":"6252",
    "sg:city":"Dagmersellen",
    "sg:orig_category":"Vorschulen, Kinderg\u00e4rten",
    "sg:phone":"+41 71 385 86 77",
    "sg:postcode":"6252",
    "sg:province":"Luzern",
    "wof:name":"Kindergarten Chellenweiher",
    "wof:placetype":"venue"
},
  "geometry": {"coordinates":[9.2698574066,47.4176177979],"type":"Point"}
}