{
  "type": "Feature",
  "properties": {
    "iso:country":"CH",
    "sg:address":"Dorfrain 1",
    "sg:city":"Gerolfingen",
    "sg:classifiers":[
        {
            "category":"Restaurant",
            "type":"Food & Drink"
        }
    ],
    "sg:phone":"+41 32 396 11 08",
    "sg:postcode":"2575",
    "sg:province":"Bern",
    "wof:name":"Restaurant R\u00f6ssli",
    "wof:placetype":"venue"
},
  "geometry": {"coordinates":[7.2002248764,47.0695991516],"type":"Point"}
}