{
  "type": "Feature",
  "properties": {
    "iso:country":"CH",
    "sg:address":"Neudorfstrasse 10",
    "sg:city":"Reinach",
    "sg:classifiers":[
        {
            "category":"Shopping",
            "subcategory":"Books",
            "type":"Retail Goods"
        }
    ],
    "sg:phone":"+41 62 771 61 12",
    "sg:postcode":"5734",
    "sg:province":"Aargau",
    "wof:name":"Urs Zuber Ag",
    "wof:placetype":"venue"
},
  "geometry": {"coordinates":[8.184734,47.253716],"type":"Point"}
}