{
  "type": "Feature",
  "properties": {
    "iso:country":"CH",
    "sg:address":"7240",
    "sg:city":"K\u00fcblis",
    "sg:orig_category":"Schulpflegen",
    "sg:postcode":"7240",
    "sg:province":"Graubunden",
    "wof:name":"Schulrat Der Gemeinde K\u00fcblis",
    "wof:placetype":"venue"
},
  "geometry": {"coordinates":[9.7779302597,46.9144554138],"type":"Point"}
}