{
  "type": "Feature",
  "properties": {
    "iso:country":"CH",
    "sg:address":"2915",
    "sg:city":"Bure",
    "sg:classifiers":[
        {
            "category":"Restaurant",
            "type":"Food & Drink"
        }
    ],
    "sg:phone":"+41 32 466 45 18",
    "sg:postcode":"2915",
    "sg:province":"Jura",
    "wof:name":"Restaurant De L' Union",
    "wof:placetype":"venue"
},
  "geometry": {"coordinates":[7.0065431595,47.4420890808],"type":"Point"}
}