{
  "type": "Feature",
  "properties": {
    "iso:country":"CH",
    "sg:address":"Alte Freudwilerstrasse",
    "sg:city":"Wermatswil",
    "sg:orig_category":"Herstellung von \u00d6fen U Brennern",
    "sg:phone":"+41 19405109",
    "sg:postcode":"8615",
    "sg:province":"Z\u00fcrich",
    "wof:name":"Hanspeter Mamie Ofen-& Chemin\u00e9ebau",
    "wof:placetype":"venue"
},
  "geometry": {"coordinates":[8.7467126846,47.3621635437],"type":"Point"}
}