{
  "type": "Feature",
  "properties": {
    "iso:country":"CH",
    "sg:address":"Burgstr. 259 Messen 3254 Balm B. Messen. Postfach",
    "sg:city":"Brunnenthal",
    "sg:orig_category":"Maler U Glasergewerbe",
    "sg:phone":"+41 31 765 57 87",
    "sg:postcode":"3307",
    "sg:province":"Solothurn",
    "wof:name":"Spielmann Fritz",
    "wof:placetype":"venue"
},
  "geometry": {"coordinates":[7.4314031601,47.1036949158],"type":"Point"}
}