{
  "type": "Feature",
  "properties": {
    "iso:country":"CH",
    "sg:address":"B\u00fchlbrunnen",
    "sg:city":"Unter\u00e4geri",
    "sg:orig_category":"Pensionskassen",
    "sg:phone":"+41 41 750 38 51",
    "sg:postcode":"6314",
    "sg:province":"Zug",
    "wof:name":"F\u00fcrsorgestiftung Der Anton Styger",
    "wof:placetype":"venue"
},
  "geometry": {"coordinates":[8.5838346481,47.1374053955],"type":"Point"}
}