{
  "type": "Feature",
  "properties": {
    "iso:country":"CH",
    "sg:address":"Via Cantonale 7. 6900 Lugano. Postfach",
    "sg:city":"Lugano",
    "sg:classifiers":[
        {
            "category":"Travel",
            "subcategory":"Hotels & Motels",
            "type":"Entertainment"
        }
    ],
    "sg:phone":"+41 91 922 85 57",
    "sg:postcode":"6900",
    "sg:province":"Ticino",
    "sg:tags":[
        "hotels",
        "mit",
        "restaurant"
    ],
    "wof:name":"Grasso Berta",
    "wof:placetype":"venue"
},
  "geometry": {"coordinates":[8.9497928619,46.0073776245],"type":"Point"}
}