{
  "type": "Feature",
  "properties": {
    "iso:country":"CH",
    "sg:address":"Haldenstrasse 1",
    "sg:city":"Baar",
    "sg:orig_category":"Sonstiger Grosshandel",
    "sg:phone":"+41 41 769 10 40",
    "sg:postcode":"6340",
    "sg:province":"Zug",
    "wof:name":"Micrografx (europe) Ag",
    "wof:placetype":"venue"
},
  "geometry": {"coordinates":[8.5362234116,47.1954154968],"type":"Point"}
}