{
  "type": "Feature",
  "properties": {
    "iso:country":"CH",
    "sg:address":"Hirschmattstrasse 29 6003 Luzern. Postfach",
    "sg:city":"Luzern",
    "sg:orig_category":"Saunas, Solarien, Fitnesszentren U \u00e4hnliches",
    "sg:postcode":"6003",
    "sg:province":"Luzern",
    "wof:name":"Beauty Sun Portmann M.l.",
    "wof:placetype":"venue"
},
  "geometry": {"coordinates":[8.3080120087,47.0470314026],"type":"Point"}
}