{
  "type": "Feature",
  "properties": {
    "iso:country":"CH",
    "sg:address":"Burgstrasse 4",
    "sg:city":"Liestal",
    "sg:classifiers":[
        {
            "category":"Restaurant",
            "type":"Food & Drink"
        }
    ],
    "sg:phone":"+41 61 921 40 30",
    "sg:postcode":"4410",
    "sg:province":"Basel-Landschaft",
    "wof:name":"Restaurant Burg",
    "wof:placetype":"venue"
},
  "geometry": {"coordinates":[7.7356939316,47.4827423096],"type":"Point"}
}