{
  "type": "Feature",
  "properties": {
    "iso:country":"CH",
    "sg:address":"Meiersmattstrasse 58 C",
    "sg:city":"Adligenswil",
    "sg:orig_category":"Kosmetikinstitute",
    "sg:phone":"+41 41 370 78 65",
    "sg:postcode":"6043",
    "sg:province":"Luzern",
    "wof:name":"Kosmetikinstitut Tetzlaff",
    "wof:placetype":"venue"
},
  "geometry": {"coordinates":[8.3654575348,47.067527771],"type":"Point"}
}