{
  "type": "Feature",
  "properties": {
    "iso:country":"CH",
    "sg:address":"Kirchstrasse 5",
    "sg:city":"Sins",
    "sg:orig_category":"Verarbeitung von Milch Verwertung von Milch",
    "sg:postcode":"5643",
    "sg:province":"Aargau",
    "wof:name":"Milchverwertungsgenossenschaft Sins & Umgebung",
    "wof:placetype":"venue"
},
  "geometry": {"coordinates":[8.394692421,47.1945533752],"type":"Point"}
}