{
  "type": "Feature",
  "properties": {
    "iso:country":"CH",
    "sg:address":"Scheideggstrasse 63",
    "sg:city":"Z\u00fcrich",
    "sg:orig_category":"Grosshandel mit Nahrungsmitteln, Getr\u00e4nken U Tabakwaren Grosshandel mit Nahrungsmitteln, Getr\u00e4nken U",
    "sg:phone":"+41 12010393",
    "sg:postcode":"8002",
    "sg:province":"Z\u00fcrich",
    "wof:name":"Kubista Gmbh",
    "wof:placetype":"venue"
},
  "geometry": {"coordinates":[8.5295448303,47.3542404175],"type":"Point"}
}