{
  "type": "Feature",
  "properties": {
    "iso:country":"CH",
    "sg:address":"Rh\u00f4ne Rue Du 5 1920 Martigny Case Postale 336",
    "sg:city":"Martigny",
    "sg:orig_category":"Elektroinstallation",
    "sg:phone":"+41 19303600",
    "sg:postcode":"1920",
    "sg:province":"Valais",
    "wof:name":"Emil Preisig Elektrische Installationen",
    "wof:placetype":"venue"
},
  "geometry": {"coordinates":[8.8130903244,47.3299980164],"type":"Point"}
}