{
  "type": "Feature",
  "properties": {
    "iso:country":"CH",
    "sg:address":"Obergestadeckweg 19",
    "sg:city":"Liestal",
    "sg:orig_category":"F\u00fcrsorge\u00e4mter",
    "sg:phone":"+41 61 921 90 30",
    "sg:postcode":"4410",
    "sg:province":"Basel-Landschaft",
    "wof:name":"Sozialberatung Stadt Liestal",
    "wof:placetype":"venue"
},
  "geometry": {"coordinates":[7.7369260788,47.4845809937],"type":"Point"}
}