{
  "type": "Feature",
  "properties": {
    "iso:country":"CH",
    "sg:address":"Route De Lully 35 1470 Estavayer-le-lac Case Postale",
    "sg:city":"Estavayer-le-lac",
    "sg:orig_category":"Herstellung von Baubedarfsartikeln aus Kunststoff Herstellung von konfektionierten Textilwaren ohne ",
    "sg:phone":"+41 26 663 94 94",
    "sg:postcode":"1470",
    "sg:province":"Fribourg",
    "wof:name":"Lamelcolor Sa",
    "wof:placetype":"venue"
},
  "geometry": {"coordinates":[6.846853,46.841755],"type":"Point"}
}