{
  "type": "Feature",
  "properties": {
    "iso:country":"CH",
    "sg:address":"Ringstrasse 82",
    "sg:city":"Z\u00fcrich",
    "sg:orig_category":"Massagestudios",
    "sg:phone":"+41 13115272",
    "sg:postcode":"8057",
    "sg:province":"Z\u00fcrich",
    "wof:name":"Verein F\u00fcr Volksgesundheit Massagen",
    "wof:placetype":"venue"
},
  "geometry": {"coordinates":[8.5384130478,47.4063491821],"type":"Point"}
}