{
  "type": "Feature",
  "properties": {
    "addr:full":"Im Z\u00fcbli 26 8730 Uznach. Postfach Uznach St. Gallen 8730",
    "addr:housenumber":"26",
    "addr:postcode":"8730 uznach. postfach;8730",
    "addr:street":"Im Zuebli",
    "iso:country":"CH",
    "sg:address":"Im Z\u00fcbli 26 8730 Uznach. Postfach",
    "sg:city":"Uznach",
    "sg:orig_category":"Allgemeiner Hoch U Tiefbau",
    "sg:phone":"+41 55 260 33 71",
    "sg:postcode":"8730",
    "sg:province":"St. Gallen",
    "wof:name":"Bachmann Bau Ag",
    "wof:placetype":"venue"
},
  "geometry": {"coordinates":[8.868782,47.266678],"type":"Point"}
}