{
  "type": "Feature",
  "properties": {
    "iso:country":"CH",
    "sg:address":"Brombergstrasse 3",
    "sg:city":"R\u00f6schenz",
    "sg:orig_category":"Sportvereine Sch\u00fctzen",
    "sg:phone":"+41 61 761 69 86",
    "sg:postcode":"4244",
    "sg:province":"Basel-Landschaft",
    "wof:name":"Milit\u00e4rschiessverein",
    "wof:placetype":"venue"
},
  "geometry": {"coordinates":[7.47833395,47.4261169434],"type":"Point"}
}