{
  "type": "Feature",
  "properties": {
    "iso:country":"CH",
    "sg:address":"Place De La Gare 25",
    "sg:city":"Del\u00e9mont",
    "sg:orig_category":"Herstellung von Radio U Fernsehger\u00e4ten sowie phono U videotechnischen Ger\u00e4ten",
    "sg:phone":"+41 18547444",
    "sg:postcode":"2800",
    "sg:province":"Jura",
    "wof:name":"Jippii Schweiz Ag",
    "wof:placetype":"venue"
},
  "geometry": {"coordinates":[9.3726291656,47.425693512],"type":"Point"}
}