{
  "type": "Feature",
  "properties": {
    "iso:country":"CH",
    "sg:address":"Hauptstrasse 39",
    "sg:city":"D\u00f6ttingen",
    "sg:orig_category":"Architektur U Ingenieurb\u00fcros",
    "sg:phone":"+41 56 245 18 74",
    "sg:postcode":"5312",
    "sg:province":"Aargau",
    "wof:name":"Heinz Schweri Ingenieurb\u00fcro Ag Hoch Und Tiefbau",
    "wof:placetype":"venue"
},
  "geometry": {"coordinates":[8.256508,47.571865],"type":"Point"}
}