{
  "type": "Feature",
  "properties": {
    "iso:country":"CH",
    "sg:address":"Eden-roc 5",
    "sg:city":"Savigny",
    "sg:orig_category":"Herstellung von Seilerwaren",
    "sg:phone":"+41 21 784 00 50",
    "sg:postcode":"1073",
    "sg:province":"Vaud",
    "wof:name":"Marius Birchler Corderie",
    "wof:placetype":"venue"
},
  "geometry": {"coordinates":[6.7065110207,46.5447845459],"type":"Point"}
}