{
  "type": "Feature",
  "properties": {
    "iso:country":"CH",
    "sg:address":"G\u00fcterstrasse 13",
    "sg:city":"Belp",
    "sg:orig_category":"Elektrizit\u00e4tsversorgung Wasserversorgung",
    "sg:phone":"+41 32 652 23 83",
    "sg:postcode":"3123",
    "sg:province":"Bern",
    "wof:name":"Gemeindebetriebe Lengnau Elektrizit\u00e4ts-& Wasserwerk",
    "wof:placetype":"venue"
},
  "geometry": {"coordinates":[7.3662500381,47.1823806763],"type":"Point"}
}