{
  "type": "Feature",
  "properties": {
    "iso:country":"CH",
    "sg:address":"Dorfstrasse 67",
    "sg:city":"Z\u00fcrich",
    "sg:orig_category":"Architektur U Ingenieurb\u00fcros",
    "sg:phone":"+41 12777788",
    "sg:postcode":"8037",
    "sg:province":"Z\u00fcrich",
    "wof:name":"Mettler + Partner, Elektro-ingenieurb\u00fcro",
    "wof:placetype":"venue"
},
  "geometry": {"coordinates":[8.51972,47.395119],"type":"Point"}
}