{
  "type": "Feature",
  "properties": {
    "iso:country":"CH",
    "sg:address":"Hotzestrasse 65",
    "sg:city":"Z\u00fcrich",
    "sg:orig_category":"RESTAURANTS: TEA-ROOMS",
    "sg:phone":"+41 13611961",
    "sg:postcode":"8006",
    "sg:province":"Z\u00fcrich",
    "wof:name":"Restaurant China Town, Van Khuong Lam",
    "wof:placetype":"venue"
},
  "geometry": {"coordinates":[8.5390405655,47.3920440674],"type":"Point"}
}