{
  "type": "Feature",
  "properties": {
    "iso:country":"CH",
    "sg:address":"Gewerbepark",
    "sg:city":"M\u00e4genwil",
    "sg:classifiers":[
        {
            "category":"Structure",
            "subcategory":"Office Building",
            "type":"Public Place"
        }
    ],
    "sg:phone":"+41 62 889 52 11",
    "sg:postcode":"5506",
    "sg:province":"Aargau",
    "sg:tags":[
        "alarm",
        "management",
        "system"
    ],
    "wof:name":"Ascom Systec Ag",
    "wof:placetype":"venue"
},
  "geometry": {"coordinates":[8.229715,47.411442],"type":"Point"}
}