{
  "type": "Feature",
  "properties": {
    "iso:country":"CH",
    "sg:address":"Thutplatz 11",
    "sg:city":"Zofingen",
    "sg:orig_category":"Maler U Glasergewerbe Tapeziererei",
    "sg:phone":"+41 62 751 13 29",
    "sg:postcode":"4800",
    "sg:province":"Aargau",
    "wof:name":"Sutermeister Ag Maler-& Tapezierergesch\u00e4ft",
    "wof:placetype":"venue"
},
  "geometry": {"coordinates":[7.9465122223,47.2889022827],"type":"Point"}
}