{
  "type": "Feature",
  "properties": {
    "iso:country":"CH",
    "sg:address":"Hinterbergstrasse 22",
    "sg:city":"Cham",
    "sg:classifiers":[
        {
            "category":"Government",
            "subcategory":"Court House",
            "type":"Public Place"
        }
    ],
    "sg:phone":"+41 41 748 25 25",
    "sg:postcode":"6330",
    "sg:province":"Zug",
    "sg:tags":[
        "administration",
        "central"
    ],
    "wof:name":"Avery Dennison Office Products Europe Gmbh",
    "wof:placetype":"venue"
},
  "geometry": {"coordinates":[8.476251,47.186619],"type":"Point"}
}