{
  "type": "Feature",
  "properties": {
    "iso:country":"CH",
    "sg:address":"Bundesplatz 10 6300 Zug. Postfach",
    "sg:city":"Zug",
    "sg:orig_category":"Sonstiges Verlagsgewerbe",
    "sg:postcode":"6300",
    "sg:province":"Zug",
    "wof:name":"Goetz Ag, Zug",
    "wof:placetype":"venue"
},
  "geometry": {"coordinates":[8.5151939392,47.1716957092],"type":"Point"}
}