{
  "type": "Feature",
  "properties": {
    "iso:country":"CH",
    "sg:address":"Dammstrasse 5 8442 Hettlingen. Postfach",
    "sg:city":"Hettlingen",
    "sg:orig_category":"Sonstige Kurierdienste",
    "sg:phone":"+41 79 430 58 66",
    "sg:postcode":"8442",
    "sg:province":"Z\u00fcrich",
    "wof:name":"Mini Kurier, Aldo Grando",
    "wof:placetype":"venue"
},
  "geometry": {"coordinates":[8.697971344,47.5433349609],"type":"Point"}
}