{
  "type": "Feature",
  "properties": {
    "iso:country":"CH",
    "sg:address":"3317",
    "sg:city":"M\u00fclchi",
    "sg:orig_category":"Landesverteidigung, Sozialversicherung \u00d6ffentliche Verwaltung",
    "sg:phone":"+41 31 765 53 05",
    "sg:postcode":"3317",
    "sg:province":"Bern",
    "wof:name":"Zivilschutzstelle M\u00fclchi",
    "wof:placetype":"venue"
},
  "geometry": {"coordinates":[7.4771418571,47.100692749],"type":"Point"}
}