{
  "type": "Feature",
  "properties": {
    "iso:country":"CH",
    "sg:address":"Mattenstrasse 22",
    "sg:city":"M\u00e4genwil",
    "sg:orig_category":"Unclassifiable Establishments",
    "sg:postcode":"5506",
    "sg:province":"Aargau",
    "wof:name":"Aarweld Schweisstechnik Ag",
    "wof:placetype":"venue"
},
  "geometry": {"coordinates":[8.2399425507,47.4135475159],"type":"Point"}
}