{
  "type": "Feature",
  "properties": {
    "iso:country":"CH",
    "sg:address":"Bargs",
    "sg:city":"Flums",
    "sg:orig_category":"Zimmerei, Dachdeckerei, Bauspenglerei U Abdichtung",
    "sg:phone":"+41 71 994 26 55",
    "sg:postcode":"8890",
    "sg:province":"St. Gallen",
    "wof:name":"Willi B\u00f6sch, Bedachungen",
    "wof:placetype":"venue"
},
  "geometry": {"coordinates":[9.2262096405,47.201839447],"type":"Point"}
}