{
  "type": "Feature",
  "properties": {
    "iso:country":"CH",
    "sg:address":"Vordere Gasse 2 5453 Remetschwil. Postfach",
    "sg:city":"Remetschwil",
    "sg:orig_category":"Unclassifiable Establishments",
    "sg:postcode":"5453",
    "sg:province":"Aargau",
    "wof:name":"M + A Transport Gmbh",
    "wof:placetype":"venue"
},
  "geometry": {"coordinates":[8.3149251938,47.4109382629],"type":"Point"}
}