{
  "type": "Feature",
  "properties": {
    "iso:country":"CH",
    "sg:address":"Im Ahorn 20",
    "sg:city":"Zollikerberg",
    "sg:orig_category":"Vereine Damen Vereine Gesang",
    "sg:phone":"+41 13912219",
    "sg:postcode":"8125",
    "sg:province":"Z\u00fcrich",
    "wof:name":"Frauenchor Zollikon",
    "wof:placetype":"venue"
},
  "geometry": {"coordinates":[8.5981521606,47.3409881592],"type":"Point"}
}