{
  "type": "Feature",
  "properties": {
    "iso:country":"CH",
    "sg:address":"Via Casa Del Frate 9",
    "sg:city":"Losone",
    "sg:orig_category":"Herstellung von Uhren",
    "sg:postcode":"6616",
    "sg:province":"Ticino",
    "wof:name":"Muller Gerard Riparazione Orologi",
    "wof:placetype":"venue"
},
  "geometry": {"coordinates":[8.7564210892,46.174571991],"type":"Point"}
}