{
  "type": "Feature",
  "properties": {
    "iso:country":"CH",
    "sg:address":"Goliathgasse 37",
    "sg:city":"St.gallen",
    "sg:orig_category":"Gesundheitswesen",
    "sg:postcode":"9000",
    "sg:province":"St. Gallen",
    "wof:name":"Psychotherapeutische Praxis, Senin Lic.phil. Fsp F.",
    "wof:placetype":"venue"
},
  "geometry": {"coordinates":[8.6485490799,47.0231666565],"type":"Point"}
}