{
  "type": "Feature",
  "properties": {
    "iso:country":"CH",
    "sg:address":"Rue De La Vernie 11-13 1023 Crissier Case Postale 29",
    "sg:city":"Crissier",
    "sg:orig_category":"Herstellung von konfektionierten Textilwaren ohne Bekleidung Herstellung von sonstigen konfektionier",
    "sg:phone":"+41 21 635 64 84",
    "sg:postcode":"1023",
    "sg:province":"Vaud",
    "wof:name":"Remund B\u00e2ches",
    "wof:placetype":"venue"
},
  "geometry": {"coordinates":[6.5728158951,46.545753479],"type":"Point"}
}