{
  "type": "Feature",
  "properties": {
    "iso:country":"CH",
    "sg:address":"Sonnenbergstrasse 1 5408 Ennetbaden. Postfach",
    "sg:city":"Ennetbaden",
    "sg:classifiers":[
        {
            "category":"Restaurant",
            "type":"Food & Drink"
        }
    ],
    "sg:phone":"+41 56 222 28 68",
    "sg:postcode":"5408",
    "sg:province":"Aargau",
    "wof:name":"Restaurant Schief",
    "wof:placetype":"venue"
},
  "geometry": {"coordinates":[8.3141145706,47.4790153503],"type":"Point"}
}