{
  "type": "Feature",
  "properties": {
    "iso:country":"CH",
    "sg:address":"Le Berceau",
    "sg:city":"Ch\u00e2teau-d'oex",
    "sg:orig_category":"Schwimmb\u00e4der",
    "sg:phone":"+41 26 924 25 25",
    "sg:postcode":"1837",
    "wof:name":"Piscine De Ch\u00e2teau-d'oex",
    "wof:placetype":"venue"
},
  "geometry": {"coordinates":[2.877589941,46.6776504517],"type":"Point"}
}