{
  "type": "Feature",
  "properties": {
    "iso:country":"CH",
    "sg:address":"L\u00e4ttenstrasse 31",
    "sg:city":"Birr",
    "sg:orig_category":"Bauspenglerei Sanit\u00e4rinstallation U Spenglerei",
    "sg:phone":"+41 56 444 82 74",
    "sg:postcode":"5242",
    "sg:province":"Aargau",
    "wof:name":"Kurt Frey Spenglerei",
    "wof:placetype":"venue"
},
  "geometry": {"coordinates":[8.204504,47.432259],"type":"Point"}
}