{
  "type": "Feature",
  "properties": {
    "iso:country":"CH",
    "sg:address":"Kirchstrasse 10 6247 Sch\u00f6tz. Postfach",
    "sg:city":"Sch\u00f6tz",
    "sg:orig_category":"Detailhandel mit Radio U Fernsehger\u00e4ten Detailhandel mit elektrischen Haushalts-,Radio U Fernsehger\u00e4",
    "sg:phone":"+41 41 980 22 64",
    "sg:postcode":"6247",
    "sg:province":"Luzern",
    "wof:name":"Pante W. Ag",
    "wof:placetype":"venue"
},
  "geometry": {"coordinates":[7.9885058403,47.1686897278],"type":"Point"}
}