{
  "type": "Feature",
  "properties": {
    "addr:full":"Ovronnaz 1912 Dugny (leytron). Postfach Ovronnaz Valais 1911",
    "addr:postcode":"1912;1911",
    "addr:street":"Ovronnaz",
    "iso:country":"CH",
    "sg:address":"Ovronnaz 1912 Dugny (leytron). Postfach",
    "sg:city":"Ovronnaz",
    "sg:orig_category":"Allgemeinbildende weiterf\u00fchrende Schulen",
    "sg:postcode":"1911",
    "sg:province":"Valais",
    "wof:name":"Tonelli Coll\u00e8ge La Cord\u00e9e",
    "wof:placetype":"venue"
},
  "geometry": {"coordinates":[7.208645,46.186459],"type":"Point"}
}