{
  "type": "Feature",
  "properties": {
    "addr:full":"Im Tiergarten 47 Z\u00fcrich Z\u00fcrich 8055",
    "addr:housenumber":"47",
    "addr:postcode":"8055",
    "addr:street":"Im Tiergarten",
    "iso:country":"CH",
    "sg:address":"Im Tiergarten 47",
    "sg:city":"Z\u00fcrich",
    "sg:orig_category":"Allgemeiner Hoch U Tiefbau Allgemeiner Hochbau",
    "sg:phone":"+41 14513711",
    "sg:postcode":"8055",
    "sg:province":"Z\u00fcrich",
    "wof:name":"M\u00fcllo Kollektivgesellschaft, Longerich & Co",
    "wof:placetype":"venue"
},
  "geometry": {"coordinates":[8.511859,47.365147],"type":"Point"}
}