{
  "type": "Feature",
  "properties": {
    "iso:country":"CH",
    "sg:address":"Via Cantonale",
    "sg:city":"Lamone-cadempino",
    "sg:orig_category":"Druckweiterverarbeitung Offsetdruck",
    "sg:phone":"+41 71 282 21 21",
    "sg:postcode":"6814",
    "sg:province":"Ticino",
    "wof:name":"Koch Ag Grafische Anstalt",
    "wof:placetype":"venue"
},
  "geometry": {"coordinates":[9.4033842087,47.4315567017],"type":"Point"}
}