{
  "type": "Feature",
  "properties": {
    "iso:country":"CH",
    "sg:address":"Industrie B\u00e4nnli 23",
    "sg:city":"Wolfwil",
    "sg:classifiers":[
        {
            "category":"Military Area",
            "subcategory":"Air Force Base",
            "type":"Public Place"
        }
    ],
    "sg:phone":"+41 62 926 34 34",
    "sg:postcode":"4628",
    "sg:province":"Solothurn",
    "sg:tags":[
        "part",
        "deep-drawn",
        "metal"
    ],
    "wof:name":"Lanz Industrietechnik Ag",
    "wof:placetype":"venue"
},
  "geometry": {"coordinates":[7.799469,47.269878],"type":"Point"}
}