{
  "type": "Feature",
  "properties": {
    "iso:country":"CH",
    "sg:address":"Hauptstrasse 9",
    "sg:city":"Niedererlinsbach",
    "sg:classifiers":[
        {
            "category":"Restaurant",
            "type":"Food & Drink"
        }
    ],
    "sg:phone":"+41 62 844 16 98",
    "sg:postcode":"5015",
    "sg:province":"Solothurn",
    "wof:name":"Restaurant Waage",
    "wof:placetype":"venue"
},
  "geometry": {"coordinates":[8.0082149506,47.3981971741],"type":"Point"}
}