{
  "type": "Feature",
  "properties": {
    "iso:country":"CH",
    "sg:address":"Schliferweg 1",
    "sg:city":"H\u00fcntwangen",
    "sg:orig_category":"Verlegen von Fliesen U Platten",
    "sg:phone":"+41 18691559",
    "sg:postcode":"8194",
    "sg:province":"Z\u00fcrich",
    "wof:name":"Fernando Bertenghi Plattenbel\u00e4ge",
    "wof:placetype":"venue"
},
  "geometry": {"coordinates":[8.4911746979,47.5956535339],"type":"Point"}
}