{
  "type": "Feature",
  "properties": {
    "iso:country":"CH",
    "sg:address":"Am Linthli 10 Postfach 147",
    "sg:city":"N\u00e4fels",
    "sg:classifiers":[
        {
            "category":"Shopping",
            "subcategory":"Hobbies, Toys, & Games",
            "type":"Retail Goods"
        }
    ],
    "sg:phone":"+41 55 618 40 70",
    "sg:postcode":"8752",
    "sg:province":"Glarus",
    "sg:tags":[
        "product",
        "miscellaneous",
        "entertainment"
    ],
    "wof:name":"Mathis Orgelbau Ag",
    "wof:placetype":"venue"
},
  "geometry": {"coordinates":[-64.9468917847,-3.7910699844],"type":"Point"}
}