{
  "type": "Feature",
  "properties": {
    "iso:country":"CH",
    "sg:address":"Bielstrasse 26 3902 Glis. Postfach",
    "sg:city":"Glis",
    "sg:orig_category":"Druck ohne Zeitungsdruck",
    "sg:phone":"+41 27 923 27 15",
    "sg:postcode":"3902",
    "sg:province":"Valais",
    "wof:name":"K\u00f6nig Druck Ag",
    "wof:placetype":"venue"
},
  "geometry": {"coordinates":[7.9647259712,46.3086967468],"type":"Point"}
}