{
  "type": "Feature",
  "properties": {
    "iso:country":"CH",
    "sg:address":"L\u00fcssiweg 8",
    "sg:city":"Zug",
    "sg:orig_category":"Reiseb\u00fcros U Reiseveranstalter",
    "sg:postcode":"6300",
    "sg:province":"Zug",
    "wof:name":"Zentrale F\u00fcr Trekking- & Studienreisen, Hemmel",
    "wof:placetype":"venue"
},
  "geometry": {"coordinates":[8.5213117599,47.1760025024],"type":"Point"}
}