{
  "type": "Feature",
  "properties": {
    "iso:country":"CH",
    "sg:address":"Haus Alpino Oeschseite",
    "sg:city":"Zweisimmen",
    "sg:orig_category":"Allgemeiner Hoch U Tiefbau",
    "sg:phone":"+41 41 630 16 85",
    "sg:postcode":"3770",
    "sg:province":"Bern",
    "wof:name":"Gebau Ag Hergiswil",
    "wof:placetype":"venue"
},
  "geometry": {"coordinates":[8.305015,46.995148],"type":"Point"}
}