{
  "type": "Feature",
  "properties": {
    "iso:country":"CH",
    "sg:address":"1732",
    "sg:city":"Arconciel",
    "sg:orig_category":"Schulpflegen",
    "sg:phone":"+41 26 413 39 68",
    "sg:postcode":"1732",
    "sg:province":"Fribourg",
    "wof:name":"Commission Scolaire De L'ecole Primaire",
    "wof:placetype":"venue"
},
  "geometry": {"coordinates":[7.1173400879,46.7530403137],"type":"Point"}
}