{
  "type": "Feature",
  "properties": {
    "iso:country":"CH",
    "sg:address":"Husmattstrasse 7",
    "sg:city":"Steinerberg",
    "sg:orig_category":"G\u00fcterbef\u00f6rderung im Strassenverkehr",
    "sg:phone":"+41 41 832 20 44",
    "sg:postcode":"6416",
    "sg:province":"Schwyz",
    "wof:name":"Paul Schleiss Transporte",
    "wof:placetype":"venue"
},
  "geometry": {"coordinates":[8.5861368179,47.0563278198],"type":"Point"}
}