{
  "type": "Feature",
  "properties": {
    "iso:country":"CH",
    "sg:address":"Bahnhofstrasse 489",
    "sg:city":"Hallau",
    "sg:orig_category":"Gesundheitswesen Physiotherapie",
    "sg:phone":"+41 52 681 29 27",
    "sg:postcode":"8215",
    "sg:province":"Schaffhausen",
    "wof:name":"Merk Hansueli Ag",
    "wof:placetype":"venue"
},
  "geometry": {"coordinates":[8.4615306854,47.684627533],"type":"Point"}
}