{
  "type": "Feature",
  "properties": {
    "iso:country":"CH",
    "sg:address":"Chemin De La Perche 14b",
    "sg:city":"Porrentruy",
    "sg:orig_category":"Micromeasuring Devices, Measuring Tools",
    "sg:phone":"+41 32 913 64 30",
    "sg:postcode":"2900",
    "sg:province":"Jura",
    "wof:name":"Spheridur",
    "wof:placetype":"venue"
},
  "geometry": {"coordinates":[6.826288,47.091827],"type":"Point"}
}