{
  "type": "Feature",
  "properties": {
    "iso:country":"CH",
    "sg:address":"Bahnhofstrasse 21",
    "sg:city":"Zug",
    "sg:orig_category":"Unternehmensberatung",
    "sg:phone":"+41 41 725 36 36",
    "sg:postcode":"6304",
    "sg:province":"Zug",
    "wof:name":"Cpm-customized Personnel Management Ag",
    "wof:placetype":"venue"
},
  "geometry": {"coordinates":[8.5156917572,47.1697540283],"type":"Point"}
}