{
  "type": "Feature",
  "properties": {
    "iso:country":"CH",
    "sg:address":"Filiale",
    "sg:city":"Elm",
    "sg:orig_category":"Allgemeiner Hoch U Tiefbau",
    "sg:postcode":"8767",
    "sg:province":"Glarus",
    "wof:name":"Marti Balz Ag, Baugesch\u00e4ft, Zweigniederlassung.",
    "wof:placetype":"venue"
},
  "geometry": {"coordinates":[9.085695,47.00042],"type":"Point"}
}