{
  "type": "Feature",
  "properties": {
    "iso:country":"CH",
    "sg:address":"Clos Bessonnet Chemin Du 3",
    "sg:city":"Prangins",
    "sg:orig_category":"Vermietung U Verpachtung von eigenen Immobilien",
    "sg:postcode":"1197",
    "sg:province":"Vaud",
    "wof:name":"Immo-loisirs Agassis M.",
    "wof:placetype":"venue"
},
  "geometry": {"coordinates":[6.2490677834,46.3910522461],"type":"Point"}
}