{
  "type": "Feature",
  "properties": {
    "iso:country":"CH",
    "sg:address":"Letzigraben 89",
    "sg:city":"Z\u00fcrich",
    "sg:orig_category":"Detailhandel mit Metallwaren, Anstrichmitteln, Glaswaren, Bau U Heimwerkerbedarf Grosshandel mit Hol",
    "sg:phone":"+41 21 691 48 49",
    "sg:postcode":"8003",
    "sg:province":"Z\u00fcrich",
    "wof:name":"Binder Jules C. Sa, Import-export",
    "wof:placetype":"venue"
},
  "geometry": {"coordinates":[6.5587749481,46.5132713318],"type":"Point"}
}