{
  "type": "Feature",
  "properties": {
    "iso:country":"CH",
    "sg:address":"Sihlmatten 18",
    "sg:city":"Adliswil",
    "sg:orig_category":"Sonstige Hilfs U Nebent\u00e4tigkeiten f\u00fcr die Luftfahrt",
    "sg:postcode":"8134",
    "sg:province":"Z\u00fcrich",
    "wof:name":"Kingshill Aviation, Dr Konigsberger William.",
    "wof:placetype":"venue"
},
  "geometry": {"coordinates":[6.2428998947,46.4983406067],"type":"Point"}
}