{
  "type": "Feature",
  "properties": {
    "iso:country":"CH",
    "sg:address":"Via Torretta 7 6600 Locarno. Postfach",
    "sg:city":"Locarno",
    "sg:orig_category":"RESTAURANTS: TEA-ROOMS",
    "sg:postcode":"6600",
    "sg:province":"Ticino",
    "wof:name":"Trattoria Bar Da Dui E Biagio Di Ferrari Maria Duilia E Todaro Biagio",
    "wof:placetype":"venue"
},
  "geometry": {"coordinates":[8.7958259583,46.170337677],"type":"Point"}
}