{
  "type": "Feature",
  "properties": {
    "iso:country":"CH",
    "sg:address":"Lerchenberg 17",
    "sg:city":"Z\u00fcrich",
    "sg:orig_category":"Architektur U Ingenieurb\u00fcros",
    "sg:phone":"+41 13719622",
    "sg:postcode":"8046",
    "sg:province":"Z\u00fcrich",
    "wof:name":"Ernst M\u00fcller Technisches B\u00fcro",
    "wof:placetype":"venue"
},
  "geometry": {"coordinates":[8.50796,47.412544],"type":"Point"}
}