{
  "type": "Feature",
  "properties": {
    "iso:country":"CH",
    "sg:address":"Seestrasse 20 8880 Walenstadt. Postfach 41",
    "sg:city":"Walenstadt",
    "sg:classifiers":[
        {
            "category":"Travel",
            "subcategory":"Hotels & Motels",
            "type":"Entertainment"
        }
    ],
    "sg:phone":"+41 81 735 11 80",
    "sg:postcode":"8880",
    "sg:province":"St. Gallen",
    "sg:tags":[
        "hotels",
        "mit",
        "restaurant"
    ],
    "wof:name":"Hotel-restaurant L\u00f6wen Fassbind Ren\u00e9",
    "wof:placetype":"venue"
},
  "geometry": {"coordinates":[9.3136577606,47.1245803833],"type":"Point"}
}