{
  "type": "Feature",
  "properties": {
    "iso:country":"CH",
    "sg:address":"1679",
    "sg:city":"Villaraboud",
    "sg:orig_category":"Darlehenskassen U Raiffeisenbanken",
    "sg:phone":"+41 26 655 12 88",
    "sg:postcode":"1679",
    "sg:province":"Fribourg",
    "wof:name":"Banque Raiffeisen St-garin",
    "wof:placetype":"venue"
},
  "geometry": {"coordinates":[6.91316,46.660339],"type":"Point"}
}