{
  "type": "Feature",
  "properties": {
    "iso:country":"CH",
    "sg:address":"Rue Edouard-dubied 12 2108 Couvet Case Postale 171",
    "sg:city":"Couvet",
    "sg:orig_category":"Handel mit Automobilen",
    "sg:phone":"+41 17814747",
    "sg:postcode":"2108",
    "sg:province":"Neuch\u00e2tel",
    "wof:name":"Autostern W\u00e4denswil Ag",
    "wof:placetype":"venue"
},
  "geometry": {"coordinates":[8.6493587494,47.2459144592],"type":"Point"}
}