{
  "type": "Feature",
  "properties": {
    "iso:country":"CH",
    "sg:address":"Moosstrasse 9 2542 Pieterlen. Postfach 307",
    "sg:city":"Pieterlen",
    "sg:orig_category":"Herstellung von Metallerzeugnissen ohne Maschinenbau Maschinenbau",
    "sg:phone":"+41 32 376 07 30",
    "sg:postcode":"2542",
    "sg:province":"Bern",
    "wof:name":"Robert Seckler Ag Sondermaschinen Automation",
    "wof:placetype":"venue"
},
  "geometry": {"coordinates":[7.3184351921,47.1699523926],"type":"Point"}
}