{
  "type": "Feature",
  "properties": {
    "addr:full":"Kirchmattstrasse 5 Steinhausen Zug 6312",
    "addr:housenumber":"5",
    "addr:postcode":"6312",
    "addr:street":"Kirchmattstrasse;Zug",
    "iso:country":"CH",
    "sg:address":"Kirchmattstrasse 5",
    "sg:city":"Steinhausen",
    "sg:orig_category":"Bauschreinerei",
    "sg:phone":"+41 79 340 92 14",
    "sg:postcode":"6312",
    "sg:province":"Zug",
    "wof:name":"Pius Imfeld Kundenschreinerei",
    "wof:placetype":"venue"
},
  "geometry": {"coordinates":[8.483391,47.194237],"type":"Point"}
}