{
  "type": "Feature",
  "properties": {
    "iso:country":"CH",
    "sg:address":"Allmig\u00e4ssli 3703 Aeschiried. Postfach",
    "sg:city":"Aeschiried",
    "sg:orig_category":"Reiseb\u00fcros U Reiseveranstalter",
    "sg:postcode":"3703",
    "sg:province":"Bern",
    "wof:name":"Genossenschaft Weitwandern F\u00f6rderung U. Durchf\u00fchrung Von Freizeit- U. Ferienangebote Im Ber. Des Sanften Tourismus Usw.",
    "wof:placetype":"venue"
},
  "geometry": {"coordinates":[7.7276711464,46.6456298828],"type":"Point"}
}