{
  "type": "Feature",
  "properties": {
    "iso:country":"CH",
    "sg:address":"Lidostrasse 92 6314 Unter\u00e4geri. Postfach",
    "sg:city":"Unter\u00e4geri",
    "sg:orig_category":"Unternehmensberatung",
    "sg:postcode":"6314",
    "sg:province":"Zug",
    "wof:name":"Bps Gmbh",
    "wof:placetype":"venue"
},
  "geometry": {"coordinates":[8.5918893814,47.1331710815],"type":"Point"}
}