{
  "type": "Feature",
  "properties": {
    "iso:country":"CH",
    "sg:address":"Neue Hard 7 8000 Z\u00fcrich. Postfach",
    "sg:city":"Z\u00fcrich",
    "sg:orig_category":"Pensionskassen",
    "sg:postcode":"8001",
    "sg:province":"Z\u00fcrich",
    "wof:name":"Personalvorsorgestiftung Der Kuoni Reisen Holding Ag Und Der Ihr Wirtschaftlich Nahestehenden Firmen",
    "wof:placetype":"venue"
},
  "geometry": {"coordinates":[8.5204248428,47.3864784241],"type":"Point"}
}