{
  "type": "Feature",
  "properties": {
    "iso:country":"CH",
    "sg:address":"Sonnenmatt 3",
    "sg:city":"Gattikon",
    "sg:orig_category":"Malerei Tapeziererei",
    "sg:phone":"+41 17201614",
    "sg:postcode":"8136",
    "sg:province":"Z\u00fcrich",
    "wof:name":"Igema J.grolla Maler-& Tapezierergesch\u00e4ft",
    "wof:placetype":"venue"
},
  "geometry": {"coordinates":[8.5453748703,47.2838592529],"type":"Point"}
}