{
  "type": "Feature",
  "properties": {
    "iso:country":"CH",
    "sg:address":"Rue De Langallerie 1",
    "sg:city":"Lausanne",
    "sg:orig_category":"Arztpraxen",
    "sg:phone":"+41 21 213 77 77",
    "sg:postcode":"1003",
    "sg:province":"Vaud",
    "wof:name":"Dres Med. Du Pasquier & Koffi M\u00e9decins G\u00e9n\u00e9ralistes",
    "wof:placetype":"venue"
},
  "geometry": {"coordinates":[6.637418,46.520592],"type":"Point"}
}