{
  "type": "Feature",
  "properties": {
    "iso:country":"CH",
    "sg:address":"Dorfstrasse",
    "sg:city":"Mauensee",
    "sg:classifiers":[
        {
            "category":"Travel",
            "subcategory":"Hotels & Motels",
            "type":"Entertainment"
        }
    ],
    "sg:phone":"+41 41 920 32 71",
    "sg:postcode":"6216",
    "sg:province":"Luzern",
    "sg:tags":[
        "hotels",
        "mit",
        "restaurant"
    ],
    "wof:name":"Dubach Xaver Landgasthof R\u00f6ssli",
    "wof:placetype":"venue"
},
  "geometry": {"coordinates":[8.0669870377,47.1679191589],"type":"Point"}
}