{
  "type": "Feature",
  "properties": {
    "iso:country":"CH",
    "sg:address":"3920",
    "sg:city":"Zermatt",
    "sg:orig_category":"Zoll- and Grenzb\u00fcros",
    "sg:phone":"+41 62 873 33 44",
    "sg:postcode":"3920",
    "sg:province":"Valais",
    "wof:name":"Haupt- Zollamt Stein-bad S\u00e4ckingen",
    "wof:placetype":"venue"
},
  "geometry": {"coordinates":[7.9498701096,47.5454216003],"type":"Point"}
}