{
  "type": "Feature",
  "properties": {
    "iso:country":"CH",
    "sg:address":"Oberer Batterieweg 64 4059 Basel. Postfach",
    "sg:city":"Basel",
    "sg:orig_category":"Interessenvertretungen",
    "sg:postcode":"4051",
    "sg:province":"Basel-Stadt",
    "wof:name":"Stiftung Neu Thierstein Schloss Neu Thierstein; Finanz. D. Pflege, Unterhaltes Usw.",
    "wof:placetype":"venue"
},
  "geometry": {"coordinates":[7.5884752274,47.5312461853],"type":"Point"}
}