{
  "type": "Feature",
  "properties": {
    "addr:full":"Rue De La Terrassi\u00e8re 52 Gen\u00e8ve Gen\u00e8ve 1207",
    "addr:housenumber":"52",
    "addr:postcode":"1207",
    "addr:street":"Rue De La Terrassie\u0300Re",
    "iso:country":"CH",
    "sg:address":"Rue De La Terrassi\u00e8re 52",
    "sg:city":"Gen\u00e8ve",
    "sg:classifiers":[
        {
            "category":"Social Services",
            "subcategory":"Retirement Home",
            "type":"Services"
        }
    ],
    "sg:phone":"+41 22 786 24 24",
    "sg:postcode":"1207",
    "sg:province":"Gen\u00e8ve",
    "sg:tags":[
        "pflegeheime",
        "u",
        "alters"
    ],
    "wof:name":"R\u00e9sidence Villereuse Pension Pr Personnes \u00e2g\u00e9es",
    "wof:placetype":"venue"
},
  "geometry": {"coordinates":[6.15901,46.2005],"type":"Point"}
}