{
  "type": "Feature",
  "properties": {
    "iso:country":"CH",
    "sg:address":"Lac Rue Du 8",
    "sg:city":"Yverdon-les-bains",
    "sg:orig_category":"Grosshandel mit Getr\u00e4nken",
    "sg:phone":"+41 24 426 14 42",
    "sg:postcode":"1400",
    "sg:province":"Vaud",
    "wof:name":"Le S'quat \u00e0 Bi\u00e8res S\u00e0rl",
    "wof:placetype":"venue"
},
  "geometry": {"coordinates":[6.6414198875,46.7786331177],"type":"Point"}
}