{
  "type": "Feature",
  "properties": {
    "addr:full":"Casa Cioss Novaggio Ticino 6986",
    "addr:postcode":"6986",
    "iso:country":"CH",
    "sg:address":"Casa Cioss",
    "sg:city":"Novaggio",
    "sg:orig_category":"Detailhandel mit Brot, Back U S\u00fcsswaren",
    "sg:phone":"+41 22 342 04 53",
    "sg:postcode":"6986",
    "sg:province":"Ticino",
    "wof:name":"Fernando Risi Boulangerie-p\u00e2tisserie",
    "wof:placetype":"venue"
},
  "geometry": {"coordinates":[6.1383,46.188129],"type":"Point"}
}