{
  "type": "Feature",
  "properties": {
    "iso:country":"CH",
    "sg:address":"Via Centrala 9",
    "sg:city":"Ilanz",
    "sg:classifiers":[
        {
            "category":"Restaurant",
            "type":"Food & Drink"
        }
    ],
    "sg:phone":"+41 81 925 13 25",
    "sg:postcode":"7130",
    "sg:province":"Graubunden",
    "wof:name":"Ustarias Rheinkrone",
    "wof:placetype":"venue"
},
  "geometry": {"coordinates":[9.2044553757,46.7750740051],"type":"Point"}
}