{
  "type": "Feature",
  "properties": {
    "iso:country":"CH",
    "sg:address":"Via Cercera 6862 Rancate. Postfach",
    "sg:city":"Rancate",
    "sg:orig_category":"Erschliessung Kauf U Verkauf von Immobilien Kauf U Verkauf von Immobilien auf eigene Rechnung",
    "sg:phone":"+41 91 640 00 45",
    "sg:postcode":"6862",
    "sg:province":"Ticino",
    "wof:name":"Caldimora Immobiliare Sa Sett. Immobiliare; Intermediazione, Assistenza Ecc",
    "wof:placetype":"venue"
},
  "geometry": {"coordinates":[8.9734096527,45.8678894043],"type":"Point"}
}