{
  "type": "Feature",
  "properties": {
    "iso:country":"CH",
    "sg:address":"1703 Fribourg. Postfach 89",
    "sg:city":"Fribourg",
    "sg:orig_category":"Selbst\u00e4ndige bildende K\u00fcnstler",
    "sg:phone":"+41 79 634 62 03",
    "sg:postcode":"1703",
    "wof:name":"Renato K.",
    "wof:placetype":"venue"
},
  "geometry": {"coordinates":[7.1512799263,46.8025016785],"type":"Point"}
}