{
  "type": "Feature",
  "properties": {
    "iso:country":"CH",
    "sg:address":"Rue Pr\u00e9-fleuri 9",
    "sg:city":"Sion",
    "sg:orig_category":"Detailhandel mit Zeitungen U Zeitschriften Kioske",
    "sg:phone":"+41 27 323 20 70",
    "sg:postcode":"1950",
    "sg:province":"Valais",
    "wof:name":"Kiosque Auf P'tit M\u00e9tro Jean & Fran\u00e7ois Revaz",
    "wof:placetype":"venue"
},
  "geometry": {"coordinates":[7.356607914,46.2293281555],"type":"Point"}
}