{
  "type": "Feature",
  "properties": {
    "iso:country":"CH",
    "sg:address":"Stadtfallenweg 7 8400 Winterthur. Postfach",
    "sg:city":"Winterthur",
    "sg:orig_category":"Saunas, Solarien, Fitnesszentren U \u00e4hnliches",
    "sg:postcode":"8400",
    "sg:province":"Z\u00fcrich",
    "wof:name":"Konrad Christoph",
    "wof:placetype":"venue"
},
  "geometry": {"coordinates":[8.7353630066,47.4955825806],"type":"Point"}
}