{
  "type": "Feature",
  "properties": {
    "iso:country":"CH",
    "sg:address":"H\u00e4gelerstr. 25b",
    "sg:city":"Remetschwil",
    "sg:orig_category":"Detailhandel mit M\u00f6beln U Haushaltsgegenst\u00e4nden",
    "sg:phone":"+41 56 496 54 81",
    "sg:postcode":"5453",
    "sg:province":"Aargau",
    "wof:name":"Dal Pont Mario Wohn-ideen",
    "wof:placetype":"venue"
},
  "geometry": {"coordinates":[8.3289251328,47.4128494263],"type":"Point"}
}