{
  "type": "Feature",
  "properties": {
    "iso:country":"CH",
    "sg:address":"6386",
    "sg:city":"Wolfenschiessen",
    "sg:classifiers":[
        {
            "category":"Education",
            "subcategory":"Library",
            "type":"Public Place"
        }
    ],
    "sg:phone":"+41 41 628 11 40",
    "sg:postcode":"6386",
    "sg:province":"Nidwalden",
    "sg:tags":[
        "u",
        "bibliotheken",
        "archive"
    ],
    "wof:name":"Katholische Pfarrbibliothek",
    "wof:placetype":"venue"
},
  "geometry": {"coordinates":[8.395655,46.910343],"type":"Point"}
}