{
  "type": "Feature",
  "properties": {
    "addr:full":"En Fenil E Fenil-sur-corsier Vaud 1809",
    "addr:housenumber":"1809",
    "addr:street":"En",
    "iso:country":"CH",
    "sg:address":"En Fenil E",
    "sg:city":"Fenil-sur-corsier",
    "sg:orig_category":"Grosshandel mit Uhren",
    "sg:phone":"+41 21 623 27 01",
    "sg:postcode":"1809",
    "sg:province":"Vaud",
    "wof:name":"Saphir Product Sa Pierres Synth.verres De Montre",
    "wof:placetype":"venue"
},
  "geometry": {"coordinates":[6.614649,46.524864],"type":"Point"}
}