{
  "type": "Feature",
  "properties": {
    "iso:country":"CH",
    "sg:address":"Moosweg 40 3645 Gwatt (thun). Postfach 182",
    "sg:city":"Thun",
    "sg:orig_category":"Mechanik Stahl U Leichtmetallbau",
    "sg:phone":"+41 33 223 25 52",
    "sg:postcode":"3602",
    "sg:province":"Bern",
    "wof:name":"Stauffer Metallbau Ag",
    "wof:placetype":"venue"
},
  "geometry": {"coordinates":[7.6180081367,46.7231941223],"type":"Point"}
}