{
  "type": "Feature",
  "properties": {
    "iso:country":"CH",
    "sg:address":"Z\u00fcrcherstrasse 22 5210 Windisch. Postfach",
    "sg:city":"Windisch",
    "sg:orig_category":"Detailhandel mit Waren verschiedener Art, Hauptrichtung Nahrungsmittel",
    "sg:phone":"+41 24 491 21 54",
    "sg:postcode":"5210",
    "sg:province":"Aargau",
    "wof:name":"Yolande Chamorel Magasin D'alimentation",
    "wof:placetype":"venue"
},
  "geometry": {"coordinates":[7.0534849167,46.3616447449],"type":"Point"}
}