{
  "type": "Feature",
  "properties": {
    "iso:country":"CH",
    "sg:address":"Florenzstrasse 7 4023 Basel. Postfach",
    "sg:city":"Basel",
    "sg:orig_category":"Sonstiger spezialisierter Hoch U Tiefbau",
    "sg:postcode":"4023",
    "sg:province":"Basel-Landschaft",
    "wof:name":"Carbura",
    "wof:placetype":"venue"
},
  "geometry": {"coordinates":[8.2241401672,46.8130912781],"type":"Point"}
}