{
  "type": "Feature",
  "properties": {
    "iso:country":"CH",
    "sg:address":"Hauptstrasse 28 5502 Hunzenschwil. Postfach 108",
    "sg:city":"Suhr",
    "sg:orig_category":"Verwaltung von Immobilien",
    "sg:postcode":"5034",
    "sg:province":"Aargau",
    "wof:name":"A & A Liegenschaften Bigstore Ag",
    "wof:placetype":"venue"
},
  "geometry": {"coordinates":[8.1261587143,47.386756897],"type":"Point"}
}