{
  "type": "Feature",
  "properties": {
    "iso:country":"CH",
    "sg:address":"Rue Des Chavannes 12",
    "sg:city":"Neuch\u00e2tel",
    "sg:orig_category":"Detailhandel mit Antiquit\u00e4ten U Gebrauchtwaren in Verkaufsr\u00e4umen Detailhandel mit Damenbekleidung",
    "sg:phone":"+41 61 711 89 97",
    "sg:postcode":"2000",
    "sg:province":"Neuch\u00e2tel",
    "wof:name":"Kleiderkiste Sonderegger M.",
    "wof:placetype":"venue"
},
  "geometry": {"coordinates":[7.592656,47.490582],"type":"Point"}
}