{
  "type": "Feature",
  "properties": {
    "iso:country":"CH",
    "sg:address":"Gotthelfstrasse 20",
    "sg:city":"Bern",
    "sg:orig_category":"Shiatsu-Therapie",
    "sg:phone":"+41 31 333 50 74",
    "sg:postcode":"3013",
    "sg:province":"Bern",
    "wof:name":"Fritz Spengler Shiatsutherapie",
    "wof:placetype":"venue"
},
  "geometry": {"coordinates":[7.4538249969,46.9534683228],"type":"Point"}
}