{
  "type": "Feature",
  "properties": {
    "iso:country":"CH",
    "sg:address":"Entfelderstrasse 61",
    "sg:city":"Aarau",
    "sg:classifiers":[
        {
            "category":"Education",
            "subcategory":"Library",
            "type":"Public Place"
        }
    ],
    "sg:phone":"+41 62 835 35 35",
    "sg:postcode":"5000",
    "sg:province":"Aargau",
    "sg:tags":[
        "u",
        "bibliotheken",
        "archive"
    ],
    "wof:name":"Schweiz.koordinationsstelle F. Bildungsforschung / Bibliothek",
    "wof:placetype":"venue"
},
  "geometry": {"coordinates":[8.050646,47.384708],"type":"Point"}
}