{
  "type": "Feature",
  "properties": {
    "iso:country":"CH",
    "sg:address":"R\u00fcstenschwil 19",
    "sg:city":"Auw",
    "sg:orig_category":"Herstellung von Baubedarfsartikeln aus Kunststoff Stahl U Leichtmetallbau",
    "sg:phone":"+41 56 664 17 77",
    "sg:postcode":"5644",
    "sg:province":"Aargau",
    "wof:name":"K\u00e4ppeli Metallbau & Kunststoffenster",
    "wof:placetype":"venue"
},
  "geometry": {"coordinates":[8.3663682938,47.2254447937],"type":"Point"}
}