{
  "type": "Feature",
  "properties": {
    "addr:full":"Hauptstrasse Gstaad Bern 3780",
    "addr:postcode":"3780",
    "addr:street":"Hauptstrasse",
    "iso:country":"CH",
    "sg:address":"Hauptstrasse",
    "sg:city":"Gstaad",
    "sg:classifiers":[
        {
            "category":"Banks & Credit Unions",
            "subcategory":"Bank",
            "type":"Services"
        }
    ],
    "sg:phone":"+41 3041193",
    "sg:postcode":"3780",
    "sg:province":"Bern",
    "wof:name":"Schweiz. Mobiliar",
    "wof:placetype":"venue"
},
  "geometry": {"coordinates":[7.283955,46.476238],"type":"Point"}
}