{
  "type": "Feature",
  "properties": {
    "iso:country":"CH",
    "sg:address":"Chillon Avenue De 66",
    "sg:city":"Territet-veytaux",
    "sg:orig_category":"Allgemeiner Hoch U Tiefbau",
    "sg:phone":"+41 21 961 29 29",
    "sg:postcode":"1820",
    "sg:province":"Vaud",
    "wof:name":"Valentino A. Sa",
    "wof:placetype":"venue"
},
  "geometry": {"coordinates":[6.910506,46.431694],"type":"Point"}
}