{
  "type": "Feature",
  "properties": {
    "iso:country":"CH",
    "sg:address":"Kriesbachstrasse 3",
    "sg:city":"Wallisellen",
    "sg:orig_category":"Detailhandel mit M\u00f6beln U Haushaltsgegenst\u00e4nden",
    "sg:postcode":"8304",
    "sg:province":"Z\u00fcrich",
    "wof:name":"Trifora Gmbh",
    "wof:placetype":"venue"
},
  "geometry": {"coordinates":[8.6123151779,47.410194397],"type":"Point"}
}