{
  "type": "Feature",
  "properties": {
    "iso:country":"CH",
    "sg:address":"Chemin Du Verger",
    "sg:city":"Villars-le-terroir",
    "sg:orig_category":"Unclassifiable Establishments",
    "sg:phone":"+41 21 881 57 57",
    "sg:postcode":"1040",
    "sg:province":"Vaud",
    "wof:name":"Bellmont Xaver Transport De Marchandises",
    "wof:placetype":"venue"
},
  "geometry": {"coordinates":[6.6415009499,46.6570854187],"type":"Point"}
}