{
  "type": "Feature",
  "properties": {
    "iso:country":"CH",
    "sg:address":"Sagendorfstrasse 10",
    "sg:city":"Emmetten",
    "sg:orig_category":"Kunsthandel",
    "sg:phone":"+41 32 631 16 66",
    "sg:postcode":"6376",
    "sg:province":"Nidwalden",
    "wof:name":"K\u00e4thy Steinke Galerie",
    "wof:placetype":"venue"
},
  "geometry": {"coordinates":[7.6502342224,47.2303199768],"type":"Point"}
}