{
  "type": "Feature",
  "properties": {
    "iso:country":"CH",
    "sg:address":"Flurstrasse 13",
    "sg:city":"Kloten",
    "sg:orig_category":"Hochschulen U h\u00f6here Ausbildung",
    "sg:phone":"+41 18138990",
    "sg:postcode":"8302",
    "sg:province":"Z\u00fcrich",
    "wof:name":"Cicb Center Of Intercultural Competence Baumer",
    "wof:placetype":"venue"
},
  "geometry": {"coordinates":[8.5906362534,47.4534263611],"type":"Point"}
}