{
  "type": "Feature",
  "properties": {
    "iso:country":"CH",
    "sg:address":"R\u00fcbeldorf 3792 Saanen. Postfach",
    "sg:city":"Saanen",
    "sg:orig_category":"S\u00e4ge, Hobel U Holzimpr\u00e4gnierwerke S\u00e4gewerke",
    "sg:phone":"+41 33 748 12 36",
    "sg:postcode":"3792",
    "sg:province":"Bern",
    "wof:name":"H. M\u00fcller Ag, S\u00e4gerei, Hobelwerk, Holzhandlung",
    "wof:placetype":"venue"
},
  "geometry": {"coordinates":[7.2713661194,46.4807510376],"type":"Point"}
}