{
  "type": "Feature",
  "properties": {
    "iso:country":"CH",
    "sg:address":"Bernstrasse 10 3270 Aarberg. Postfach 40",
    "sg:city":"Aarberg",
    "sg:orig_category":"Bauschreinerei Herstellung von Konstruktionsteilen, Fertigbauteilen U Ausbauelementen aus Holz",
    "sg:phone":"+41 32 392 26 34",
    "sg:postcode":"3270",
    "sg:province":"Bern",
    "wof:name":"Rita Pulver Schreinerei Leiternfabrik",
    "wof:placetype":"venue"
},
  "geometry": {"coordinates":[7.281178,47.044098],"type":"Point"}
}