{
  "type": "Feature",
  "properties": {
    "iso:country":"CH",
    "sg:address":"Auf Der Halde 5",
    "sg:city":"N\u00fcrensdorf",
    "sg:orig_category":"Architektur U Ingenieurb\u00fcros",
    "sg:phone":"+41 79 355 79 92",
    "sg:postcode":"8309",
    "sg:province":"Z\u00fcrich",
    "wof:name":"Matelier Gadiag, M. Gadient",
    "wof:placetype":"venue"
},
  "geometry": {"coordinates":[8.651536,47.445324],"type":"Point"}
}