{
  "type": "Feature",
  "properties": {
    "iso:country":"CH",
    "sg:address":"Bois-murat Chemin Du 18 1066 Epalinges. Postfach",
    "sg:city":"Epalinges",
    "sg:orig_category":"Sanit\u00e4r, Heizungs U L\u00fcftungsinstallation",
    "sg:phone":"+41 21 653 65 10",
    "sg:postcode":"1066",
    "sg:province":"Vaud",
    "wof:name":"Bureau Erco, Amort A.",
    "wof:placetype":"venue"
},
  "geometry": {"coordinates":[6.6570749283,46.5455741882],"type":"Point"}
}