{
  "type": "Feature",
  "properties": {
    "addr:full":"Rubeggweg 13 Lenzburg Aargau 5600",
    "addr:housenumber":"13",
    "addr:postcode":"5600",
    "addr:street":"Rubeggweg",
    "iso:country":"CH",
    "sg:address":"Rubeggweg 13",
    "sg:city":"Lenzburg",
    "sg:orig_category":"Allgemeiner Hoch U Tiefbau",
    "sg:postcode":"5600",
    "sg:province":"Aargau",
    "wof:name":"Baugesch\u00e4ft P. Doninelli Ag Lenzburg",
    "wof:placetype":"venue"
},
  "geometry": {"coordinates":[8.178185,47.381199],"type":"Point"}
}