{
  "type": "Feature",
  "properties": {
    "iso:country":"CH",
    "sg:address":"Chemin De La Chapelle",
    "sg:city":"Misery-courtion",
    "sg:orig_category":"Sanit\u00e4r, Heizungs U L\u00fcftungsinstallation Sanit\u00e4rinstallation",
    "sg:phone":"+41 26 475 23 54",
    "sg:postcode":"1721",
    "sg:province":"Fribourg",
    "wof:name":"Francis Savarioud Installations Sanitaires",
    "wof:placetype":"venue"
},
  "geometry": {"coordinates":[7.1019039154,46.8531455994],"type":"Point"}
}