{
  "type": "Feature",
  "properties": {
    "iso:country":"CH",
    "sg:address":"Bahnhofstrasse 1",
    "sg:city":"Stettlen",
    "sg:orig_category":"Detailhandel mit Milcherzeugnissen U Eiern Sonstiger Fachdetailhandel mit Nahrungsmitteln, Getr\u00e4nken",
    "sg:phone":"+41 31 931 37 31",
    "sg:postcode":"3066",
    "sg:province":"Bern",
    "wof:name":"Ch\u00e4s Vreni Laproschuh Ag",
    "wof:placetype":"venue"
},
  "geometry": {"coordinates":[7.5240998268,46.9584083557],"type":"Point"}
}