{
  "type": "Feature",
  "properties": {
    "iso:country":"CH",
    "sg:address":"Klaraweg 1 3006 Bern. Postfach",
    "sg:city":"Bern",
    "sg:orig_category":"Ausbaugewerbe Herstellung von Maschinen f\u00fcr die Nahrungsmittel, Getr\u00e4nkeherstellung U die Tabakverar",
    "sg:phone":"+41 41 497 40 60",
    "sg:postcode":"3005",
    "sg:province":"Bern",
    "wof:name":"Trocknungstechnik Trobag",
    "wof:placetype":"venue"
},
  "geometry": {"coordinates":[8.182725,47.036816],"type":"Point"}
}