{
  "type": "Feature",
  "properties": {
    "iso:country":"CH",
    "sg:address":"B\u00f6sch 43",
    "sg:city":"H\u00fcnenberg",
    "sg:orig_category":"Unclassifiable Establishments",
    "sg:phone":"+41 41 781 16 77",
    "sg:postcode":"6331",
    "sg:province":"Zug",
    "wof:name":"Warida Verwaltungs Ag",
    "wof:placetype":"venue"
},
  "geometry": {"coordinates":[8.4376420975,47.1618881226],"type":"Point"}
}