{
  "type": "Feature",
  "properties": {
    "iso:country":"CH",
    "sg:address":"Staldenweg 74",
    "sg:city":"Berikon",
    "sg:orig_category":"Sportvereine Velo Rad-& Motorfahrer-Bund SRB",
    "sg:phone":"+41 56 633 79 35",
    "sg:postcode":"8965",
    "sg:province":"Aargau",
    "wof:name":"Veloclub Bremgarten Srb",
    "wof:placetype":"venue"
},
  "geometry": {"coordinates":[8.3755407333,47.3491859436],"type":"Point"}
}