{
  "type": "Feature",
  "properties": {
    "iso:country":"CH",
    "sg:address":"Im Roggenacher 19 8602 Wangen Zh. Postfach",
    "sg:city":"Br\u00fcttisellen",
    "sg:orig_category":"Softwareentwicklung U beratung",
    "sg:postcode":"8306",
    "sg:province":"Z\u00fcrich",
    "wof:name":"Riva Point Systems Gmbh",
    "wof:placetype":"venue"
},
  "geometry": {"coordinates":[8.859670639,47.1875686646],"type":"Point"}
}