{
  "type": "Feature",
  "properties": {
    "iso:country":"CH",
    "sg:address":"Voa Sporz 12 Lenzerheide/lai 7082 Vaz/obervaz. Postfach",
    "sg:city":"Lenzerheide/lai",
    "sg:orig_category":"Detailhandel mit Fleisch U Fleischwaren",
    "sg:postcode":"7078",
    "sg:province":"Graubunden",
    "wof:name":"Metzgerei Novalai Gmbh",
    "wof:placetype":"venue"
},
  "geometry": {"coordinates":[9.5320854187,46.6989746094],"type":"Point"}
}