{
  "type": "Feature",
  "properties": {
    "iso:country":"CH",
    "sg:address":"Schulhausstrasse 23 3800 Unterseen. Postfach",
    "sg:city":"Unterseen",
    "sg:orig_category":"Mit dem Versicherungsgewerbe verbundene T\u00e4tigkeiten",
    "sg:postcode":"3800",
    "sg:province":"Bern",
    "wof:name":"Gery Odermatt Versicherungsberatung",
    "wof:placetype":"venue"
},
  "geometry": {"coordinates":[8.7341480255,47.1973953247],"type":"Point"}
}