{
  "type": "Feature",
  "properties": {
    "iso:country":"CH",
    "sg:address":"Hauptgasse 10",
    "sg:city":"Willisau",
    "sg:classifiers":[
        {
            "category":"Restaurant",
            "type":"Food & Drink"
        }
    ],
    "sg:phone":"+41 41 970 23 32",
    "sg:postcode":"6130",
    "sg:province":"Luzern",
    "wof:name":"Pizzeria Al Cervo",
    "wof:placetype":"venue"
},
  "geometry": {"coordinates":[7.9914679527,47.1209526062],"type":"Point"}
}