{
  "type": "Feature",
  "properties": {
    "iso:country":"CH",
    "sg:address":"Herrenbergstrasse 44",
    "sg:city":"Rudolfstetten",
    "sg:orig_category":"Architektur U Ingenieurb\u00fcros Bauingenieurb\u00fcros",
    "sg:postcode":"8964",
    "sg:province":"Aargau",
    "wof:name":"Nowak Bauberatung",
    "wof:placetype":"venue"
},
  "geometry": {"coordinates":[8.379068,47.372204],"type":"Point"}
}