{
  "type": "Feature",
  "properties": {
    "iso:country":"CH",
    "sg:address":"Cl\u00e9-des-champs 18 1255 Veyrier Case Postale 44",
    "sg:city":"Veyrier",
    "sg:orig_category":"Ausbaugewerbe",
    "sg:postcode":"1255",
    "sg:province":"Gen\u00e8ve",
    "wof:name":"Sp\u00fchler B. Chemin\u00e9e\u00f6fen Kaminsysteme",
    "wof:placetype":"venue"
},
  "geometry": {"coordinates":[7.414276,46.922874],"type":"Point"}
}