{
  "type": "Feature",
  "properties": {
    "iso:country":"CH",
    "sg:address":"Clausiusstrasse 41 8006 Z\u00fcrich. Postfach",
    "sg:city":"Z\u00fcrich",
    "sg:orig_category":"Elektrizit\u00e4tsversorgung R\u00fcckgewinnung U Vorbereitung f\u00fcr die Wiederverwertung Recycling",
    "sg:phone":"+41 12610707",
    "sg:postcode":"8033",
    "sg:province":"Z\u00fcrich",
    "wof:name":"Nek Umwelttechnik Ag",
    "wof:placetype":"venue"
},
  "geometry": {"coordinates":[8.5458297729,47.3792610168],"type":"Point"}
}