{
  "type": "Feature",
  "properties": {
    "iso:country":"CH",
    "sg:address":"Apothekerstr.10",
    "sg:city":"Uster",
    "sg:orig_category":"Bildung and Forschung, Museen",
    "sg:phone":"+41 19402780",
    "sg:postcode":"8610",
    "sg:province":"Z\u00fcrich",
    "wof:name":"Heilsarmee",
    "wof:placetype":"venue"
},
  "geometry": {"coordinates":[8.714851,47.346676],"type":"Point"}
}