{
  "type": "Feature",
  "properties": {
    "addr:full":"Riedtwilstrasse 66 Wynigen Bern 3472",
    "addr:housenumber":"66",
    "addr:postcode":"3472",
    "addr:street":"Riedtwilstrasse",
    "iso:country":"CH",
    "sg:address":"Riedtwilstrasse 66",
    "sg:city":"Wynigen",
    "sg:orig_category":"Architektur U Ingenieurb\u00fcros",
    "sg:phone":"+41 71 250 13 60",
    "sg:postcode":"3472",
    "sg:province":"Bern",
    "wof:name":"Bruno K. H\u00e4nni, Ingenieurb\u00fcro F\u00fcr Hoch- + Tiefbau",
    "wof:placetype":"venue"
},
  "geometry": {"coordinates":[9.403944,47.436245],"type":"Point"}
}