{
  "type": "Feature",
  "properties": {
    "iso:country":"CH",
    "sg:address":"Kastanienweg 10",
    "sg:city":"Lupfig",
    "sg:orig_category":"Organisationen des Gesundheitswesen",
    "sg:phone":"+41 56 444 05 09",
    "sg:postcode":"5242",
    "sg:province":"Aargau",
    "wof:name":"Samariterver.eigenamt-lupfig",
    "wof:placetype":"venue"
},
  "geometry": {"coordinates":[8.2014303207,47.4392700195],"type":"Point"}
}