{
  "type": "Feature",
  "properties": {
    "iso:country":"CH",
    "sg:address":"Theilmattweg 4",
    "sg:city":"Horriwil",
    "sg:orig_category":"G\u00fcterbef\u00f6rderung im Strassenverkehr",
    "sg:phone":"+41 32 614 18 51",
    "sg:postcode":"4557",
    "sg:province":"Solothurn",
    "wof:name":"Rolf Reize Internationale Transporte Gmbh",
    "wof:placetype":"venue"
},
  "geometry": {"coordinates":[7.619122982,47.1859779358],"type":"Point"}
}