{
  "type": "Feature",
  "properties": {
    "iso:country":"CH",
    "sg:address":"Riedstrasse 14",
    "sg:city":"Dietikon",
    "sg:orig_category":"Grosshandel mit Software Softwareentwicklung U beratung",
    "sg:phone":"+41 17438000",
    "sg:postcode":"8953",
    "sg:province":"Z\u00fcrich",
    "wof:name":"Damgaard Ag",
    "wof:placetype":"venue"
},
  "geometry": {"coordinates":[8.3954296112,47.4204406738],"type":"Point"}
}