{
  "type": "Feature",
  "properties": {
    "iso:country":"CH",
    "sg:address":"Route De Frontenex 42",
    "sg:city":"Gen\u00e8ve",
    "sg:orig_category":"Wirtschaftspr\u00fcfung, Steuerberatung U Treuhand",
    "sg:phone":"+41 22 700 04 41",
    "sg:postcode":"1207",
    "sg:province":"Gen\u00e8ve",
    "wof:name":"Raymond A. F\u00e9lix Expert-comptable",
    "wof:placetype":"venue"
},
  "geometry": {"coordinates":[6.1613931656,46.2014122009],"type":"Point"}
}