{
  "type": "Feature",
  "properties": {
    "iso:country":"CH",
    "sg:address":"Dorfstr. 5",
    "sg:city":"Baar",
    "sg:classifiers":[
        {
            "category":"Travel",
            "subcategory":"Hotels & Motels",
            "type":"Entertainment"
        }
    ],
    "sg:postcode":"6340",
    "sg:province":"Zug",
    "sg:tags":[
        "hotels",
        "mit",
        "restaurant"
    ],
    "wof:name":"Landgasthof Adler, Ludy Wilmes",
    "wof:placetype":"venue"
},
  "geometry": {"coordinates":[8.5259275436,47.194229126],"type":"Point"}
}