{
  "type": "Feature",
  "properties": {
    "iso:country":"CH",
    "sg:address":"Nidstalden",
    "sg:city":"Obstalden",
    "sg:orig_category":"Non-Classified Establishments",
    "sg:postcode":"8758",
    "sg:province":"Glarus",
    "wof:name":"Catac Ag",
    "wof:placetype":"venue"
},
  "geometry": {"coordinates":[9.1517496109,47.1204414368],"type":"Point"}
}