{
  "type": "Feature",
  "properties": {
    "iso:country":"CH",
    "sg:address":"Geisshalde 458",
    "sg:city":"Waldstatt",
    "sg:classifiers":[
        {
            "category":"Restaurant",
            "type":"Food & Drink"
        }
    ],
    "sg:phone":"+41 71 351 21 15",
    "sg:postcode":"9104",
    "sg:province":"Appenzell Ausserrhoden",
    "wof:name":"Restaurant Frohe Aussicht",
    "wof:placetype":"venue"
},
  "geometry": {"coordinates":[9.2811050415,47.3606567383],"type":"Point"}
}