{
  "type": "Feature",
  "properties": {
    "iso:country":"CH",
    "sg:address":"Corso Bello 2. 6850 Mendrisio. Postfach Casa Postale 79",
    "sg:city":"Mendrisio",
    "sg:orig_category":"Wirtschaftspr\u00fcfung, Steuerberatung U Treuhand",
    "sg:postcode":"6850",
    "sg:province":"Ticino",
    "wof:name":"Studio Fiduciario Angelo Quattropani.",
    "wof:placetype":"venue"
},
  "geometry": {"coordinates":[8.9874668121,45.8695793152],"type":"Point"}
}