{
  "type": "Feature",
  "properties": {
    "iso:country":"CH",
    "sg:address":"Bahnhofstrasse 29",
    "sg:city":"Dielsdorf",
    "sg:classifiers":[
        {
            "category":"Banks & Credit Unions",
            "subcategory":"Bank",
            "type":"Services"
        }
    ],
    "sg:phone":"+41 18530223",
    "sg:postcode":"8157",
    "sg:province":"Z\u00fcrich",
    "wof:name":"Bezirkssparkasse Dielsdorf",
    "wof:placetype":"venue"
},
  "geometry": {"coordinates":[8.458485,47.482643],"type":"Point"}
}