{
  "type": "Feature",
  "properties": {
    "iso:country":"CH",
    "sg:address":"R\u00f6merstrasse 9",
    "sg:city":"Ipsach",
    "sg:orig_category":"Fussreflexzonenmassage P\u00e9dicure",
    "sg:postcode":"2563",
    "sg:province":"Bern",
    "wof:name":"Doris Zogg Fusspflege Reflexzonenmassage",
    "wof:placetype":"venue"
},
  "geometry": {"coordinates":[8.5498657227,47.3236808777],"type":"Point"}
}