{
  "type": "Feature",
  "properties": {
    "iso:country":"CH",
    "sg:address":"Br\u00fcnigstrasse 7",
    "sg:city":"Luzern",
    "sg:orig_category":"G\u00fcterbef\u00f6rderung im Strassenverkehr",
    "sg:phone":"+41 79 209 20 28",
    "sg:postcode":"6005",
    "sg:province":"Luzern",
    "wof:name":"Erwin Odermatt Transporte",
    "wof:placetype":"venue"
},
  "geometry": {"coordinates":[8.3121356964,47.0432167053],"type":"Point"}
}