{
  "type": "Feature",
  "properties": {
    "iso:country":"CH",
    "sg:address":"Unterweg 14",
    "sg:city":"B\u00fclach",
    "sg:orig_category":"Erbringung von Dienstleistungen f\u00fcr Unternehmen",
    "sg:postcode":"8180",
    "sg:province":"Z\u00fcrich",
    "wof:name":"Swxpo Ag",
    "wof:placetype":"venue"
},
  "geometry": {"coordinates":[8.5425014496,47.5223503113],"type":"Point"}
}