{
  "type": "Feature",
  "properties": {
    "iso:country":"CH",
    "sg:address":"Schulweg 3",
    "sg:city":"Koppigen",
    "sg:orig_category":"Unclassifiable Establishments",
    "sg:phone":"+41 34 413 33 33",
    "sg:postcode":"3425",
    "sg:province":"Bern",
    "wof:name":"Cannatrade.ch Ag",
    "wof:placetype":"venue"
},
  "geometry": {"coordinates":[7.6044440269,47.1336021423],"type":"Point"}
}