{
  "type": "Feature",
  "properties": {
    "iso:country":"CH",
    "sg:address":"Feldbergstrasse 3",
    "sg:city":"Basel",
    "sg:orig_category":"Unclassifiable Establishments",
    "sg:postcode":"4057",
    "sg:province":"Basel-Stadt",
    "wof:name":"Wig Hair & Products, H. Sutter",
    "wof:placetype":"venue"
},
  "geometry": {"coordinates":[7.5876331329,47.565612793],"type":"Point"}
}