{
  "type": "Feature",
  "properties": {
    "iso:country":"CH",
    "sg:address":"Buchenweidstrasse 2 4535 Hubersdorf. Postfach",
    "sg:city":"Hubersdorf",
    "sg:orig_category":"Allgemeiner Hoch U Tiefbau Hoch U Tiefbau",
    "sg:phone":"+41 32 637 23 64",
    "sg:postcode":"4535",
    "sg:province":"Solothurn",
    "wof:name":"Makos Janos",
    "wof:placetype":"venue"
},
  "geometry": {"coordinates":[7.594729,47.249405],"type":"Point"}
}