{
  "type": "Feature",
  "properties": {
    "iso:country":"CH",
    "sg:address":"Sonnenwandstrasse 7",
    "sg:city":"M\u00fchlethal",
    "sg:orig_category":"Instandhaltung U Reparatur von Automobilen",
    "sg:phone":"+41 62 752 92 02",
    "sg:postcode":"4812",
    "sg:province":"Aargau",
    "wof:name":"Arber Otto",
    "wof:placetype":"venue"
},
  "geometry": {"coordinates":[7.9723548889,47.3043327332],"type":"Point"}
}