{
  "type": "Feature",
  "properties": {
    "addr:full":"Oetlingerstrasse 10 Basel Basel-Stadt 4057",
    "addr:housenumber":"10",
    "addr:postcode":"4057",
    "addr:street":"Oetlingerstrasse",
    "iso:country":"CH",
    "sg:address":"Oetlingerstrasse 10",
    "sg:city":"Basel",
    "sg:orig_category":"Datenverarbeitungsdienste Logistikberatung",
    "sg:phone":"+41 62 291 33 04",
    "sg:postcode":"4057",
    "sg:province":"Basel-Stadt",
    "wof:name":"H + S Logistik Gmbh",
    "wof:placetype":"venue"
},
  "geometry": {"coordinates":[7.959361,47.351994],"type":"Point"}
}