{
  "type": "Feature",
  "properties": {
    "iso:country":"CH",
    "sg:address":"Am Seebach 12",
    "sg:city":"H\u00fcttwilen",
    "sg:orig_category":"Sonstiger spezialisierter Hoch U Tiefbau",
    "sg:postcode":"8536",
    "sg:province":"Thurgau",
    "wof:name":"Sterki's Ch\u00fcbelimurerei",
    "wof:placetype":"venue"
},
  "geometry": {"coordinates":[8.8686323166,47.6054496765],"type":"Point"}
}