{
  "type": "Feature",
  "properties": {
    "iso:country":"CH",
    "sg:address":"Haus No 4",
    "sg:city":"Schluein",
    "sg:orig_category":"Sanit\u00e4r, Heizungs U L\u00fcftungsinstallation Sanit\u00e4rinstallation",
    "sg:phone":"+41 55 283 12 03",
    "sg:postcode":"7151",
    "sg:province":"Graubunden",
    "wof:name":"Cereghetti Gmbh",
    "wof:placetype":"venue"
},
  "geometry": {"coordinates":[9.0085849762,47.1995277405],"type":"Point"}
}