{
  "type": "Feature",
  "properties": {
    "iso:country":"CH",
    "sg:address":"Hinterbergstrasse 23",
    "sg:city":"Walchwil",
    "sg:orig_category":"Finanzierungsinstitutionen",
    "sg:postcode":"6318",
    "sg:province":"Zug",
    "wof:name":"Weber Consulting",
    "wof:placetype":"venue"
},
  "geometry": {"coordinates":[8.5217828751,47.0968132019],"type":"Point"}
}