{
  "type": "Feature",
  "properties": {
    "iso:country":"CH",
    "sg:address":"Kirchstrasse 4",
    "sg:city":"Eich",
    "sg:orig_category":"Rechtsberatung",
    "sg:phone":"+41 41 460 15 72",
    "sg:postcode":"6205",
    "sg:province":"Luzern",
    "wof:name":"Reda-patente Ag Eich",
    "wof:placetype":"venue"
},
  "geometry": {"coordinates":[8.1654138565,47.1545982361],"type":"Point"}
}