{
  "type": "Feature",
  "properties": {
    "iso:country":"CH",
    "sg:address":"G\u00e4ssli 1",
    "sg:city":"Z\u00fcrich",
    "sg:orig_category":"Bauspenglerei Sanit\u00e4rinstallation",
    "sg:phone":"+41 12712868",
    "sg:postcode":"8049",
    "sg:province":"Z\u00fcrich",
    "wof:name":"Robert & Ueli Zimmermann Sanit\u00e4r & Spenglerei",
    "wof:placetype":"venue"
},
  "geometry": {"coordinates":[8.499827,47.402172],"type":"Point"}
}