{
  "type": "Feature",
  "properties": {
    "iso:country":"CH",
    "sg:address":"Schwadernauweg 23",
    "sg:city":"Biel/bienne",
    "sg:orig_category":"Fussreflexzonenmassage",
    "sg:phone":"+41 32 341 85 63",
    "sg:postcode":"2504",
    "sg:province":"Bern",
    "wof:name":"Lucienne Kubli Fussreflexzonentherapie",
    "wof:placetype":"venue"
},
  "geometry": {"coordinates":[7.2835822105,47.1452445984],"type":"Point"}
}