{
  "type": "Feature",
  "properties": {
    "iso:country":"CH",
    "sg:address":"Birkenweg 1",
    "sg:city":"Inkwil",
    "sg:orig_category":"Herstellung von Metallerzeugnissen ohne Maschinenbau Maschinenbau",
    "sg:phone":"+41 79 607 00 38",
    "sg:postcode":"3375",
    "sg:province":"Bern",
    "wof:name":"H. Urben Ag",
    "wof:placetype":"venue"
},
  "geometry": {"coordinates":[7.6738882065,47.1979026794],"type":"Point"}
}