{
  "type": "Feature",
  "properties": {
    "iso:country":"CH",
    "sg:address":"Mattstrasse 8500 Frauenfeld. Postfach",
    "sg:city":"Frauenfeld",
    "sg:orig_category":"R\u00fcckgewinnung U Vorbereitung f\u00fcr die Wiederverwertung Recycling R\u00fcckgewinnung U Vorbereitung f\u00fcr die",
    "sg:phone":"+41 52 722 46 60",
    "sg:postcode":"8502",
    "sg:province":"Thurgau",
    "wof:name":"R.o.m. Ag, Recycling Organischer Materialien",
    "wof:placetype":"venue"
},
  "geometry": {"coordinates":[8.8406648636,47.5656547546],"type":"Point"}
}