{
  "type": "Feature",
  "properties": {
    "iso:country":"CH",
    "sg:address":"Wassergrabe 6 6210 Sursee. Postfach",
    "sg:city":"Sursee",
    "sg:orig_category":"Grosshandel mit Datenverarbeitungsger\u00e4ten Softwareentwicklung U beratung",
    "sg:phone":"+41 41 799 59 29",
    "sg:postcode":"6210",
    "sg:province":"Luzern",
    "wof:name":"Brainconnect Ag",
    "wof:placetype":"venue"
},
  "geometry": {"coordinates":[8.1088123322,47.1839179993],"type":"Point"}
}