{
  "type": "Feature",
  "properties": {
    "iso:country":"CH",
    "sg:address":"Theilerweg 7",
    "sg:city":"Frick",
    "sg:orig_category":"Arbeitnehmerverb\u00e4nde",
    "sg:phone":"+41 62 871 13 06",
    "sg:postcode":"5070",
    "sg:province":"Aargau",
    "wof:name":"Vchp-sektion Fricktal-zurzach Pr\u00e4s.herrn Franz Haberth\u00fcr",
    "wof:placetype":"venue"
},
  "geometry": {"coordinates":[8.016136,47.504604],"type":"Point"}
}