{
  "type": "Feature",
  "properties": {
    "iso:country":"CH",
    "sg:address":"Grabmattweg 3",
    "sg:city":"Selzach",
    "sg:orig_category":"Bauschreinerei Herstellung von M\u00f6beln verschiedener Art",
    "sg:phone":"+41 32 641 29 30",
    "sg:postcode":"2545",
    "sg:province":"Solothurn",
    "wof:name":"Giuseppe & Pierluigi Sapuppo Antikschreinerei",
    "wof:placetype":"venue"
},
  "geometry": {"coordinates":[7.454049,47.201942],"type":"Point"}
}