{
  "type": "Feature",
  "properties": {
    "iso:country":"CH",
    "sg:address":"Chemin De L'eglise 6",
    "sg:city":"Echandens",
    "sg:orig_category":"Herstellung von Werkzeugen Herstellung von sonstigen Metallwaren",
    "sg:phone":"+41 91 606 23 01",
    "sg:postcode":"1026",
    "sg:province":"Vaud",
    "wof:name":"N.g.m. Manufacturing Sa",
    "wof:placetype":"venue"
},
  "geometry": {"coordinates":[8.8604135513,45.9691696167],"type":"Point"}
}