{
  "type": "Feature",
  "properties": {
    "iso:country":"CH",
    "sg:address":"Gossauerstrasse 96 9100 Herisau. Postfach",
    "sg:city":"Herisau",
    "sg:orig_category":"Unclassifiable Establishments",
    "sg:postcode":"9102",
    "sg:province":"Appenzell Ausserrhoden",
    "wof:name":"Pizza-kurier Sesch, Oroz Pizza-lieferdienst Nach Hause",
    "wof:placetype":"venue"
},
  "geometry": {"coordinates":[9.2704124451,47.3928642273],"type":"Point"}
}