{
  "type": "Feature",
  "properties": {
    "iso:country":"CH",
    "sg:address":"Ankerstrasse 8",
    "sg:city":"Rorschach",
    "sg:orig_category":"Detailhandel mit Textilien Detailhandel mit elektrischen Haushaltsger\u00e4ten",
    "sg:phone":"+41 71 841 48 76",
    "sg:postcode":"9400",
    "sg:province":"St. Gallen",
    "wof:name":"Heidi Bertschi Mercerie N\u00e4hmaschinen",
    "wof:placetype":"venue"
},
  "geometry": {"coordinates":[9.4912023544,47.4783668518],"type":"Point"}
}