{
  "type": "Feature",
  "properties": {
    "iso:country":"CH",
    "sg:address":"Sonnenhof 1",
    "sg:city":"Herisau",
    "sg:orig_category":"Arztpraxen",
    "sg:phone":"+41 71 352 44 66",
    "sg:postcode":"9100",
    "sg:province":"Appenzell Ausserrhoden",
    "wof:name":"Dr.med.heinrich Weber Spezialarzt Fmh",
    "wof:placetype":"venue"
},
  "geometry": {"coordinates":[9.281852,47.386883],"type":"Point"}
}