{
  "type": "Feature",
  "properties": {
    "iso:country":"CH",
    "sg:address":"Rheinstrasse 11",
    "sg:city":"Diepoldsau",
    "sg:orig_category":"Architektur U Ingenieurb\u00fcros",
    "sg:phone":"+41 71 733 20 60",
    "sg:postcode":"9444",
    "sg:province":"St. Gallen",
    "wof:name":"Emil Durot Planungsb\u00fcro",
    "wof:placetype":"venue"
},
  "geometry": {"coordinates":[9.662109,47.389275],"type":"Point"}
}