{
  "type": "Feature",
  "properties": {
    "iso:country":"CH",
    "sg:address":"Chemin Buvelot 6",
    "sg:city":"Morges",
    "sg:orig_category":"Architektur U Ingenieurb\u00fcros",
    "sg:phone":"+41 21 691 14 74",
    "sg:postcode":"1110",
    "sg:province":"Vaud",
    "wof:name":"Philippe P. Jacques Bureau D'ing\u00e9nieur",
    "wof:placetype":"venue"
},
  "geometry": {"coordinates":[6.557301,46.514259],"type":"Point"}
}