{
  "type": "Feature",
  "properties": {
    "addr:full":"Gewerbestrasse 3 Balzers 9496",
    "addr:housenumber":"3",
    "addr:postcode":"9496",
    "addr:street":"Gewerbestrasse",
    "iso:country":"CH",
    "sg:address":"Gewerbestrasse 3",
    "sg:city":"Balzers",
    "sg:orig_category":"Datenverarbeitungsdienste",
    "sg:phone":"+423 384 30 25",
    "sg:postcode":"9496",
    "wof:name":"Img Ag",
    "wof:placetype":"venue"
},
  "geometry": {"coordinates":[9.508248,47.076256],"type":"Point"}
}