{
  "type": "Feature",
  "properties": {
    "iso:country":"CH",
    "sg:address":"Laubisr\u00fctistrasse 24",
    "sg:city":"St\u00e4fa",
    "sg:orig_category":"Sonstiger Grosshandel",
    "sg:phone":"+41 19133010",
    "sg:postcode":"8712",
    "sg:province":"Z\u00fcrich",
    "wof:name":"Novantino Ag",
    "wof:placetype":"venue"
},
  "geometry": {"coordinates":[8.5919065475,47.3059883118],"type":"Point"}
}