{
  "type": "Feature",
  "properties": {
    "iso:country":"CH",
    "sg:address":"Chesa Sur Promulins.",
    "sg:city":"Samedan",
    "sg:orig_category":"Interessenvertretungen",
    "sg:postcode":"7503",
    "sg:province":"Graubunden",
    "wof:name":"Stiftung Pfadiheim Samedan.",
    "wof:placetype":"venue"
},
  "geometry": {"coordinates":[9.87429142,46.5351486206],"type":"Point"}
}