{
  "type": "Feature",
  "properties": {
    "iso:country":"CH",
    "sg:address":"Willi Ritschard-strasse 4",
    "sg:city":"Luterbach",
    "sg:orig_category":"Maler U Glasergewerbe",
    "sg:postcode":"4542",
    "sg:province":"Solothurn",
    "wof:name":"Scherrer M., Malergesch\u00e4ft",
    "wof:placetype":"venue"
},
  "geometry": {"coordinates":[7.5809822083,47.2157554626],"type":"Point"}
}