{
  "type": "Feature",
  "properties": {
    "iso:country":"CH",
    "sg:address":"Bahnhofstrasse 6 7130 Ilanz. Postfach",
    "sg:city":"Ilanz",
    "sg:orig_category":"Physiotherapie",
    "sg:phone":"+41 81 925 16 66",
    "sg:postcode":"7130",
    "sg:province":"Graubunden",
    "wof:name":"Doris Riedi Physiotherapie",
    "wof:placetype":"venue"
},
  "geometry": {"coordinates":[9.2052583694,46.7750816345],"type":"Point"}
}