{
  "type": "Feature",
  "properties": {
    "iso:country":"CH",
    "sg:address":"Mattr\u00fctistrasse 10",
    "sg:city":"Fislisbach",
    "sg:orig_category":"Mechanische Werkst\u00e4tten",
    "sg:phone":"+41 56 493 10 88",
    "sg:postcode":"5442",
    "sg:province":"Aargau",
    "wof:name":"Willy Baumgartner Mechanische Werkst\u00e4tte",
    "wof:placetype":"venue"
},
  "geometry": {"coordinates":[8.2956018448,47.4351348877],"type":"Point"}
}