{
  "type": "Feature",
  "properties": {
    "iso:country":"CH",
    "sg:address":"Chemin Des Aulx 18",
    "sg:city":"Plan-les-ouates",
    "sg:orig_category":"HERSTELLUNG VON GER\u00c4TEN DER ELEKTRIZIT\u00c4TSERZEUGUNG, -VERTEILUNG U.\u00c4",
    "sg:phone":"+41 22 794 53 00",
    "sg:postcode":"1228",
    "sg:province":"Gen\u00e8ve",
    "wof:name":"Autodose Sa",
    "wof:placetype":"venue"
},
  "geometry": {"coordinates":[6.1043782234,46.1676292419],"type":"Point"}
}