{
  "type": "Feature",
  "properties": {
    "iso:country":"CH",
    "sg:address":"Hohrietstrasse 2",
    "sg:city":"Rorschacherberg",
    "sg:orig_category":"Betrieb von Taxis",
    "sg:phone":"+41 18580402",
    "sg:postcode":"9404",
    "sg:province":"St. Gallen",
    "wof:name":"Perlas Davinia Gmbh",
    "wof:placetype":"venue"
},
  "geometry": {"coordinates":[9.513687,47.477146],"type":"Point"}
}