{
  "type": "Feature",
  "properties": {
    "iso:country":"CH",
    "sg:address":"Rue De La Poste 3",
    "sg:city":"Martigny",
    "sg:orig_category":"Parf\u00fcmerien U sonstiger Detailhandel mit kosmetischen Artikeln U K\u00f6rperpflegemitteln",
    "sg:phone":"+41 27 722 07 44",
    "sg:postcode":"1920",
    "sg:province":"Valais",
    "wof:name":"Impo Import Parf\u00fcmerien Ag",
    "wof:placetype":"venue"
},
  "geometry": {"coordinates":[7.0763268471,46.1033172607],"type":"Point"}
}