{
  "type": "Feature",
  "properties": {
    "iso:country":"CH",
    "sg:address":"Steinengraben 40",
    "sg:city":"Basel",
    "sg:classifiers":[
        {
            "category":"Utilities",
            "subcategory":"Telephone",
            "type":"Services"
        }
    ],
    "sg:phone":"+41 22 730 51 11",
    "sg:postcode":"4051",
    "sg:province":"Basel-Stadt",
    "sg:tags":[
        "telecommunication"
    ],
    "wof:name":"Union Internationale Des Telecommunications",
    "wof:placetype":"venue"
},
  "geometry": {"coordinates":[6.1384592056,46.2222366333],"type":"Point"}
}