{
  "type": "Feature",
  "properties": {
    "iso:country":"CH",
    "sg:address":"Schulhausstrasse 26",
    "sg:city":"Vilters",
    "sg:orig_category":"Bezirks, Sekundar, Realschulen, Oberstufe der Primarschulen",
    "sg:phone":"+41 81 756 13 21",
    "sg:postcode":"7324",
    "sg:province":"St. Gallen",
    "wof:name":"Sekundarschule",
    "wof:placetype":"venue"
},
  "geometry": {"coordinates":[9.472072,47.161186],"type":"Point"}
}