{
  "type": "Feature",
  "properties": {
    "iso:country":"CH",
    "sg:address":"Lucino Via 41a",
    "sg:city":"Breganzona",
    "sg:orig_category":"Architektur U Ingenieurb\u00fcros",
    "sg:phone":"+41 91 966 15 32",
    "sg:postcode":"6932",
    "sg:province":"Ticino",
    "wof:name":"Studio D'ingegneria Fasani G. E Bianchini S.",
    "wof:placetype":"venue"
},
  "geometry": {"coordinates":[8.932496,46.006802],"type":"Point"}
}