{
  "type": "Feature",
  "properties": {
    "iso:country":"CH",
    "sg:address":"Deutsche Strasse 172 7000 Chur. Postfach",
    "sg:city":"Chur",
    "sg:orig_category":"Handelsvermittlung U Grosshandel Sonstiger Grosshandel",
    "sg:phone":"+41 81 354 95 98",
    "sg:postcode":"7005",
    "wof:name":"Eucopro Gmbh Waren; Im- U. Export, Handel Usw",
    "wof:placetype":"venue"
},
  "geometry": {"coordinates":[9.5409593582,46.8861198425],"type":"Point"}
}