{
  "type": "Feature",
  "properties": {
    "iso:country":"CH",
    "sg:address":"Bahnhofstrasse 43",
    "sg:city":"Z\u00fcrich",
    "sg:orig_category":"Erschliessung von Grundst\u00fccken",
    "sg:phone":"+41 12118082",
    "sg:postcode":"8001",
    "sg:province":"Z\u00fcrich",
    "wof:name":"Die Liegenschafter Ag Bauten; Erstellung, Renovation. Liegenschaften Usw.; Verwaltung",
    "wof:placetype":"venue"
},
  "geometry": {"coordinates":[8.5379123688,47.3713951111],"type":"Point"}
}