{
  "type": "Feature",
  "properties": {
    "iso:country":"CH",
    "sg:address":"Bernstrasse 24",
    "sg:city":"Rothrist",
    "sg:orig_category":"Softwareentwicklung U beratung",
    "sg:phone":"+41 62 775 44 54",
    "sg:postcode":"4852",
    "sg:province":"Aargau",
    "wof:name":"Informatiq Solutions Gmbh",
    "wof:placetype":"venue"
},
  "geometry": {"coordinates":[8.6814498901,47.2673797607],"type":"Point"}
}