{
  "type": "Feature",
  "properties": {
    "iso:country":"CH",
    "sg:address":"Viale Carlo Cattaneo 25",
    "sg:city":"Lugano",
    "sg:orig_category":"Arztpraxen",
    "sg:phone":"+41 91 923 42 73",
    "sg:postcode":"6900",
    "sg:province":"Ticino",
    "wof:name":"Dott.med.hans R. Bernbach Medico Generico",
    "wof:placetype":"venue"
},
  "geometry": {"coordinates":[8.960072,46.005974],"type":"Point"}
}