{
  "type": "Feature",
  "properties": {
    "iso:country":"CH",
    "sg:address":"Neustadt 45",
    "sg:city":"Schaffhausen",
    "sg:orig_category":"Detailhandel mit B\u00fcchern Detailhandel mit Gebrauchtwaren in Verkaufsr\u00e4umen",
    "sg:phone":"+41 52 624 95 68",
    "sg:postcode":"8200",
    "sg:province":"Schaffhausen",
    "wof:name":"Ruth Heinzer Antiqua Buch-antiquariat",
    "wof:placetype":"venue"
},
  "geometry": {"coordinates":[8.632035,47.695004],"type":"Point"}
}