{
  "type": "Feature",
  "properties": {
    "iso:country":"CH",
    "sg:address":"Il Sogno",
    "sg:city":"Gordevio",
    "sg:orig_category":"Reiseb\u00fcros",
    "sg:phone":"+41 61 751 66 65",
    "sg:postcode":"6672",
    "sg:province":"Ticino",
    "wof:name":"Panorama Tours Gmbh",
    "wof:placetype":"venue"
},
  "geometry": {"coordinates":[7.5994582176,47.468536377],"type":"Point"}
}