{
  "type": "Feature",
  "properties": {
    "iso:country":"CH",
    "sg:address":"Gotthardstrasse 123 6472 Erstfeld. Postfach",
    "sg:city":"Erstfeld",
    "sg:orig_category":"RESTAURANTS: TEA-ROOMS",
    "sg:postcode":"6472",
    "sg:province":"Uri",
    "wof:name":"Rolis Caf\u00e9, Roland Herger & Co",
    "wof:placetype":"venue"
},
  "geometry": {"coordinates":[8.6498718262,46.8246688843],"type":"Point"}
}