{
  "type": "Feature",
  "properties": {
    "iso:country":"CH",
    "sg:address":"Rickenbacherstrasse 177",
    "sg:city":"Altikon",
    "sg:orig_category":"RESTAURANTS: TEA-ROOMS",
    "sg:phone":"+41 52 336 11 72",
    "sg:postcode":"8479",
    "sg:province":"Z\u00fcrich",
    "wof:name":"Restaurant Thurtal, Kupper Rolf",
    "wof:placetype":"venue"
},
  "geometry": {"coordinates":[8.7815303802,47.5721893311],"type":"Point"}
}