{
  "type": "Feature",
  "properties": {
    "iso:country":"CH",
    "sg:address":"M\u00fcnchstrasse 3",
    "sg:city":"M\u00fcnchenstein",
    "sg:orig_category":"Architektur U Ingenieurb\u00fcros Architekturb\u00fcros",
    "sg:phone":"+41 71 970 05 33",
    "sg:postcode":"4142",
    "sg:province":"Basel-Landschaft",
    "wof:name":"Haas Architektur Gmbh",
    "wof:placetype":"venue"
},
  "geometry": {"coordinates":[8.97053,47.464867],"type":"Point"}
}