{
  "type": "Feature",
  "properties": {
    "addr:full":"Hinterreutenenweg 5 Z\u00e4ziwil Bern 3532",
    "addr:housenumber":"5",
    "addr:postcode":"3532",
    "addr:street":"Hinterreutenenweg",
    "iso:country":"CH",
    "sg:address":"Hinterreutenenweg 5",
    "sg:city":"Z\u00e4ziwil",
    "sg:orig_category":"Detailhandel mit Brot, Back U S\u00fcsswaren Detailhandel mit Waren verschiedener Art, Hauptrichtung Nahr",
    "sg:phone":"+41 31 711 01 81",
    "sg:postcode":"3532",
    "sg:province":"Bern",
    "wof:name":"Hans-rudolf Niederhauser B\u00e4ckerei & Handlung",
    "wof:placetype":"venue"
},
  "geometry": {"coordinates":[7.676597,46.887329],"type":"Point"}
}