{
  "type": "Feature",
  "properties": {
    "addr:full":"Kupfergasse 16 Rheinfelden Aargau 4310",
    "addr:housenumber":"16",
    "addr:postcode":"4310",
    "addr:street":"Kupfergasse",
    "iso:country":"CH",
    "sg:address":"Kupfergasse 16",
    "sg:city":"Rheinfelden",
    "sg:orig_category":"Detailhandel mit Damenbekleidung",
    "sg:phone":"+41 61 831 41 60",
    "sg:postcode":"4310",
    "sg:province":"Aargau",
    "wof:name":"Modeva Ag",
    "wof:placetype":"venue"
},
  "geometry": {"coordinates":[7.795272,47.555256],"type":"Point"}
}