{
  "type": "Feature",
  "properties": {
    "iso:country":"CH",
    "sg:address":"Via Sonvico 9",
    "sg:city":"Porza",
    "sg:orig_category":"Gymnastikschulen Sportschulen Fern\u00f6stliche Kampfsportarten",
    "sg:phone":"+41 91 941 78 66",
    "sg:postcode":"6948",
    "sg:province":"Ticino",
    "wof:name":"Accademia Arti Marziali/danza Signora Anna Fioravera",
    "wof:placetype":"venue"
},
  "geometry": {"coordinates":[8.9626054764,46.0250549316],"type":"Point"}
}