{
  "type": "Feature",
  "properties": {
    "iso:country":"CH",
    "sg:address":"Flughafen 8302 Kloten. Postfach Postfach",
    "sg:city":"Z\u00fcrich",
    "sg:orig_category":"Autotransporte international Sonstige Verkehrsvermittlung",
    "sg:phone":"+41 18162422",
    "sg:postcode":"8058",
    "sg:province":"Z\u00fcrich",
    "wof:name":"Apextrans Ag",
    "wof:placetype":"venue"
},
  "geometry": {"coordinates":[8.569773,47.449127],"type":"Point"}
}