{
  "type": "Feature",
  "properties": {
    "iso:country":"CH",
    "sg:address":"3971",
    "sg:city":"Chermignon",
    "sg:orig_category":"Non-Classified Establishments",
    "sg:postcode":"3971",
    "sg:province":"Valais",
    "wof:name":"Si La R\u00e9serve De Chapperonnaz Sa",
    "wof:placetype":"venue"
},
  "geometry": {"coordinates":[6.8613700867,46.4520492554],"type":"Point"}
}