{
  "type": "Feature",
  "properties": {
    "iso:country":"CH",
    "sg:address":"In Den Reben 32",
    "sg:city":"Witterswil",
    "sg:orig_category":"Datenverarbeitungsdienste",
    "sg:phone":"+41 61 406 95 50",
    "sg:postcode":"4108",
    "sg:province":"Solothurn",
    "wof:name":"Panchaud Edv Beratung",
    "wof:placetype":"venue"
},
  "geometry": {"coordinates":[7.55884,47.513706],"type":"Point"}
}