{
  "type": "Feature",
  "properties": {
    "iso:country":"CH",
    "sg:address":"Waldeggstrasse 1 3097 Liebefeld. Postfach",
    "sg:city":"Liebefeld",
    "sg:orig_category":"Gesundheitswesen Medizinische Labors",
    "sg:phone":"+41 31 972 16 36",
    "sg:postcode":"3097",
    "sg:province":"Bern",
    "wof:name":"Medilab Aerztelabor Dr.w\u00e4lchli Ag",
    "wof:placetype":"venue"
},
  "geometry": {"coordinates":[7.4219880104,46.9325332642],"type":"Point"}
}