{
  "type": "Feature",
  "properties": {
    "iso:country":"CH",
    "sg:address":"Forchstrasse 1402",
    "sg:city":"Herrliberg",
    "sg:orig_category":"Unternehmensberatung",
    "sg:postcode":"8704",
    "sg:province":"Z\u00fcrich",
    "wof:name":"Hasen\u00f6hrl Consulting",
    "wof:placetype":"venue"
},
  "geometry": {"coordinates":[8.6298418045,47.2890129089],"type":"Point"}
}