{
  "type": "Feature",
  "properties": {
    "iso:country":"CH",
    "sg:address":"Steinbr\u00fcggli",
    "sg:city":"Otelfingen",
    "sg:orig_category":"Vereine Frauen Vereine Gemeinn\u00fctzige",
    "sg:phone":"+41 18442380",
    "sg:postcode":"8112",
    "sg:province":"Z\u00fcrich",
    "wof:name":"Landfrauenver.bez.dielsdorf",
    "wof:placetype":"venue"
},
  "geometry": {"coordinates":[8.3863687515,47.4791221619],"type":"Point"}
}