{
  "type": "Feature",
  "properties": {
    "iso:country":"CH",
    "sg:address":"Rue Des Vignettes 8",
    "sg:city":"Sion",
    "sg:orig_category":"Oberfl\u00e4chenveredlung U W\u00e4rmebehandlung",
    "sg:postcode":"1950",
    "sg:province":"Valais",
    "wof:name":"Milici Salvatore.",
    "wof:placetype":"venue"
},
  "geometry": {"coordinates":[7.3646478653,46.239906311],"type":"Point"}
}