{
  "type": "Feature",
  "properties": {
    "iso:country":"CH",
    "sg:address":"1277",
    "sg:city":"Borex",
    "sg:orig_category":"Grosshandel mit Textilien",
    "sg:phone":"+41 22 367 17 21",
    "sg:postcode":"1277",
    "sg:province":"Vaud",
    "wof:name":"Hartmann Diffusion Sa",
    "wof:placetype":"venue"
},
  "geometry": {"coordinates":[6.1857600212,46.3773117065],"type":"Point"}
}