{
  "type": "Feature",
  "properties": {
    "iso:country":"CH",
    "sg:address":"Quartier-neuf Rue Du 6-8 1205 Gen\u00e8ve. Postfach",
    "sg:city":"Gen\u00e8ve",
    "sg:orig_category":"Architektur U Ingenieurb\u00fcros",
    "sg:phone":"+41 22 329 79 29",
    "sg:postcode":"1205",
    "sg:province":"Gen\u00e8ve",
    "wof:name":"Architechnik S\u00e0rl",
    "wof:placetype":"venue"
},
  "geometry": {"coordinates":[6.128575,46.202068],"type":"Point"}
}