{
  "type": "Feature",
  "properties": {
    "iso:country":"CH",
    "sg:address":"Poststrasse 30 6300 Zug. Postfach 1248",
    "sg:city":"Zug",
    "sg:orig_category":"Unfall U Schadenversicherung",
    "sg:phone":"+41 41 726 84 70",
    "sg:postcode":"6301",
    "sg:province":"Zug",
    "wof:name":"Cap Rechtsschutz-versicherung Hauptsitz",
    "wof:placetype":"venue"
},
  "geometry": {"coordinates":[8.5171890259,47.1715126038],"type":"Point"}
}