{
  "type": "Feature",
  "properties": {
    "iso:country":"CH",
    "sg:address":"St\u00e4mpflistrasse 2",
    "sg:city":"Zollikofen",
    "sg:orig_category":"Sonstiger Grosshandel",
    "sg:postcode":"3052",
    "sg:province":"Bern",
    "wof:name":"Kistler-handel",
    "wof:placetype":"venue"
},
  "geometry": {"coordinates":[7.46058321,46.9991111755],"type":"Point"}
}