{
  "type": "Feature",
  "properties": {
    "iso:country":"CH",
    "sg:address":"Aspacherstrasse 56",
    "sg:city":"Neftenbach",
    "sg:orig_category":"Gartenbau",
    "sg:phone":"+41 52 315 35 28",
    "sg:postcode":"8413",
    "sg:province":"Z\u00fcrich",
    "wof:name":"C. Maraffino Gartenbau",
    "wof:placetype":"venue"
},
  "geometry": {"coordinates":[8.6725597382,47.5295753479],"type":"Point"}
}