{
  "type": "Feature",
  "properties": {
    "iso:country":"CH",
    "sg:address":"Poststrasse 6",
    "sg:city":"Chur",
    "sg:orig_category":"Fussreflexzonenmassage",
    "sg:phone":"+41 81 252 87 77",
    "sg:postcode":"7000",
    "sg:province":"Graubunden",
    "wof:name":"Rico Reich Fussreflexzonen-massage",
    "wof:placetype":"venue"
},
  "geometry": {"coordinates":[9.5319375992,46.8501243591],"type":"Point"}
}