{
  "type": "Feature",
  "properties": {
    "iso:country":"CH",
    "sg:address":"Baselstrasse 64",
    "sg:city":"Muttenz",
    "sg:orig_category":"Erbringung von Dienstleistungen f\u00fcr Unternehmen Innenarchitekturb\u00fcros",
    "sg:phone":"+41 61 461 74 94",
    "sg:postcode":"4132",
    "sg:province":"Basel-Landschaft",
    "wof:name":"Saladin Individuelle Raumgestaltung",
    "wof:placetype":"venue"
},
  "geometry": {"coordinates":[7.6378388405,47.5264091492],"type":"Point"}
}