{
  "type": "Feature",
  "properties": {
    "iso:country":"CH",
    "sg:address":"Dottikerstrasse 39",
    "sg:city":"Anglikon",
    "sg:orig_category":"Handelsvermittlung U Grosshandel R\u00fcckgewinnung U Vorbereitung f\u00fcr die Wiederverwertung Recycling",
    "sg:phone":"+41 71 744 16 62",
    "sg:postcode":"5611",
    "sg:province":"Aargau",
    "wof:name":"Josef Schiegg Industrieabf\u00e4lle-altstoffe",
    "wof:placetype":"venue"
},
  "geometry": {"coordinates":[9.6351919174,47.4310073853],"type":"Point"}
}