{
  "type": "Feature",
  "properties": {
    "addr:full":"Schneggengasse 8 Z\u00fcrich Z\u00fcrich 8001",
    "addr:housenumber":"8",
    "addr:postcode":"8001",
    "addr:street":"Schneggengasse",
    "iso:country":"CH",
    "sg:address":"Schneggengasse 8",
    "sg:city":"Z\u00fcrich",
    "sg:classifiers":[
        {
            "category":"Bars & Pubs",
            "type":"Food & Drink"
        }
    ],
    "sg:phone":"+41 12522737",
    "sg:postcode":"8001",
    "sg:province":"Z\u00fcrich",
    "sg:tags":[
        "restaurant"
    ],
    "wof:name":"Bar-restaurant Velvet",
    "wof:placetype":"venue"
},
  "geometry": {"coordinates":[8.543215,47.37228],"type":"Point"}
}