{
  "type": "Feature",
  "properties": {
    "iso:country":"CH",
    "sg:address":"Beethovenstrasse 5",
    "sg:city":"Z\u00fcrich",
    "sg:orig_category":"Arztpraxen",
    "sg:phone":"+41 12017640",
    "sg:postcode":"8002",
    "sg:province":"Z\u00fcrich",
    "wof:name":"Dr.med.willi Bischofberger Spezialarzt Fmh",
    "wof:placetype":"venue"
},
  "geometry": {"coordinates":[8.537297,47.365204],"type":"Point"}
}