{
  "type": "Feature",
  "properties": {
    "iso:country":"CH",
    "sg:address":"Cl\u00e9menty Route De 62 1260 Nyon. Postfach",
    "sg:city":"Nyon",
    "sg:orig_category":"Rechtsberatung",
    "sg:postcode":"1260",
    "sg:province":"Vaud",
    "wof:name":"Leman Consulting Sa",
    "wof:placetype":"venue"
},
  "geometry": {"coordinates":[6.2285428047,46.3815231323],"type":"Point"}
}