{
  "type": "Feature",
  "properties": {
    "iso:country":"CH",
    "sg:address":"3438",
    "sg:city":"Lauperswil",
    "sg:orig_category":"Landesverteidigung, Sozialversicherung \u00d6ffentliche Verwaltung",
    "sg:phone":"+41 34 496 81 75",
    "sg:postcode":"3438",
    "sg:province":"Bern",
    "wof:name":"Zivilschutzstelle Lauperswil",
    "wof:placetype":"venue"
},
  "geometry": {"coordinates":[7.7411308289,46.9661712646],"type":"Point"}
}