{
  "type": "Feature",
  "properties": {
    "iso:country":"CH",
    "sg:address":"L\u00e4nggasse 6",
    "sg:city":"Krauchthal",
    "sg:classifiers":[
        {
            "category":"Food & Beverages",
            "subcategory":"Specialty",
            "type":"Retail Goods"
        }
    ],
    "sg:phone":"+41 34 411 28 45",
    "sg:postcode":"3326",
    "sg:province":"Bern",
    "sg:tags":[
        "caterer"
    ],
    "wof:name":"Partyservice Chuchi-tiger",
    "wof:placetype":"venue"
},
  "geometry": {"coordinates":[7.566371,47.009762],"type":"Point"}
}