{
  "type": "Feature",
  "properties": {
    "iso:country":"CH",
    "sg:address":"Amthausquai 23 4600 Olten. Postfach",
    "sg:city":"Olten",
    "sg:orig_category":"Verwaltung der Rechtspflege, Gerichte",
    "sg:phone":"+41 41 875 22 59",
    "sg:postcode":"4603",
    "sg:province":"Solothurn",
    "wof:name":"Kantonales Grundbuchamt",
    "wof:placetype":"venue"
},
  "geometry": {"coordinates":[8.6364622116,46.8782424927],"type":"Point"}
}