{
  "type": "Feature",
  "properties": {
    "iso:country":"CH",
    "sg:address":"Luzernerstrasse 9 5040 Sch\u00f6ftland. Postfach",
    "sg:city":"Sch\u00f6ftland",
    "sg:orig_category":"Grosshandel mit Bekleidung Grosshandel mit Textilien",
    "sg:phone":"+41 62 721 01 51",
    "sg:postcode":"5040",
    "sg:province":"Aargau",
    "wof:name":"Daniels & Korff Vertriebs Ag",
    "wof:placetype":"venue"
},
  "geometry": {"coordinates":[8.0503902435,47.302696228],"type":"Point"}
}