{
  "type": "Feature",
  "properties": {
    "iso:country":"CH",
    "sg:address":"8635",
    "sg:city":"D\u00fcrnten",
    "sg:orig_category":"Verwertung von Milch",
    "sg:postcode":"8635",
    "sg:province":"Z\u00fcrich",
    "wof:name":"Milchgenossenschaft Hasenstrick",
    "wof:placetype":"venue"
},
  "geometry": {"coordinates":[8.8424081802,47.2776527405],"type":"Point"}
}