{
  "type": "Feature",
  "properties": {
    "iso:country":"CH",
    "sg:address":"Hohle Gasse 2",
    "sg:city":"Kerzers",
    "sg:orig_category":"Grosshandel mit lebenden Tieren",
    "sg:phone":"+41 31 755 71 12",
    "sg:postcode":"3210",
    "sg:province":"Fribourg",
    "wof:name":"Jordi Urs",
    "wof:placetype":"venue"
},
  "geometry": {"coordinates":[7.2001729012,46.9728507996],"type":"Point"}
}