{
  "type": "Feature",
  "properties": {
    "iso:country":"CH",
    "sg:address":"Lehenmattstrasse 202",
    "sg:city":"Basel",
    "sg:orig_category":"Fachdetailhandel in Verkaufsr\u00e4umen",
    "sg:phone":"+41 61 311 36 90",
    "sg:postcode":"4052",
    "sg:province":"Basel-Stadt",
    "wof:name":"Thommen Blumen Am H\u00f6rnli Gmbh",
    "wof:placetype":"venue"
},
  "geometry": {"coordinates":[7.6210098267,47.5496482849],"type":"Point"}
}