{
  "type": "Feature",
  "properties": {
    "iso:country":"CH",
    "sg:address":"Baslerstrasse 50",
    "sg:city":"Z\u00fcrich",
    "sg:orig_category":"Detailhandel mit Waren verschiedener Art, Hauptrichtung Nahrungsmittel",
    "sg:phone":"+41 14966600",
    "sg:postcode":"8048",
    "sg:province":"Z\u00fcrich",
    "wof:name":"Coop Letzipark",
    "wof:placetype":"venue"
},
  "geometry": {"coordinates":[8.4980716705,47.3861312866],"type":"Point"}
}