{
  "type": "Feature",
  "properties": {
    "iso:country":"CH",
    "sg:address":"Dorfstrasse 26 3714 Frutigen. Postfach",
    "sg:city":"Frutigen",
    "sg:orig_category":"Finanzierungsinstitutionen",
    "sg:phone":"+41 41 630 19 20",
    "sg:postcode":"3714",
    "sg:province":"Bern",
    "wof:name":"Avz Finanz Ag",
    "wof:placetype":"venue"
},
  "geometry": {"coordinates":[8.3104372025,46.9823074341],"type":"Point"}
}