{
  "type": "Feature",
  "properties": {
    "iso:country":"CH",
    "sg:address":"Theaterweg 1 7000 Chur. Postfach",
    "sg:city":"Chur",
    "sg:classifiers":[
        {
            "category":"Communications",
            "subcategory":"Radio Station",
            "type":"Services"
        }
    ],
    "sg:phone":"+41 81 255 75 75",
    "sg:postcode":"7002",
    "sg:province":"Graubunden",
    "sg:tags":[
        "fernsehanstalten",
        "u"
    ],
    "wof:name":"Schweizerische Radio Und Fernsehgesellschaft (srg), Zweigniederlassung Radio E Televisiun Rumantscha (rtr)",
    "wof:placetype":"venue"
},
  "geometry": {"coordinates":[9.533074379,46.8520050049],"type":"Point"}
}