{
  "type": "Feature",
  "properties": {
    "iso:country":"CH",
    "sg:address":"Kreuzlinger Strasse 142a",
    "sg:city":"Oberaach",
    "sg:orig_category":"Elektroinstallation",
    "sg:phone":"+41 71 410 00 77",
    "sg:postcode":"8587",
    "sg:province":"Thurgau",
    "wof:name":"Giger Elektro Service Gmbh",
    "wof:placetype":"venue"
},
  "geometry": {"coordinates":[9.2661647797,47.5592193604],"type":"Point"}
}