{
  "type": "Feature",
  "properties": {
    "iso:country":"CH",
    "sg:address":"Bodenackerstrasse 64 8121 Benglen. Postfach",
    "sg:city":"Benglen",
    "sg:orig_category":"Non-Classified Establishments",
    "sg:postcode":"8121",
    "sg:province":"Z\u00fcrich",
    "wof:name":"Aaa-homepage.ch Gmbh Internet-auftritte Und Pr\u00e4sentationen; Vertrieb Und Realisierung Usw",
    "wof:placetype":"venue"
},
  "geometry": {"coordinates":[8.6388292313,47.3605155945],"type":"Point"}
}