{
  "type": "Feature",
  "properties": {
    "addr:full":"Avenue Bois-de-la-chapelle 13 Onex Gen\u00e8ve 1213",
    "addr:housenumber":"13",
    "addr:postcode":"1213",
    "addr:street":"Avenue Bois-De-La-Chapelle",
    "iso:country":"CH",
    "sg:address":"Avenue Bois-de-la-chapelle 13",
    "sg:city":"Onex",
    "sg:orig_category":"Detailhandel mit Antiquit\u00e4ten",
    "sg:phone":"+41 22 793 20 06",
    "sg:postcode":"1213",
    "sg:province":"Gen\u00e8ve",
    "wof:name":"Chantal Rime Brocante",
    "wof:placetype":"venue"
},
  "geometry": {"coordinates":[6.107116,46.190742],"type":"Point"}
}