{
  "type": "Feature",
  "properties": {
    "iso:country":"CH",
    "sg:address":"Typographeng\u00e4ssli 4",
    "sg:city":"Biel/bienne",
    "sg:orig_category":"Erschliessung von Grundst\u00fccken",
    "sg:postcode":"2502",
    "sg:province":"Bern",
    "wof:name":"Progeno Preisg\u00fcnstiger, Gemeinn\u00fctzier Wohnungsbau Usw",
    "wof:placetype":"venue"
},
  "geometry": {"coordinates":[7.2435369492,47.1393127441],"type":"Point"}
}