{
  "type": "Feature",
  "properties": {
    "iso:country":"CH",
    "sg:address":"Bubenbergplatz 7 3011 Bern. Postfach 7135",
    "sg:city":"Bern",
    "sg:orig_category":"Detailhandel mit Bekleidung",
    "sg:phone":"+41 31 311 79 71",
    "sg:postcode":"3001",
    "sg:province":"Bern",
    "wof:name":"Beteiligungsgesellschaft Der Leinenweberei Bern Ag Beteiligungen",
    "wof:placetype":"venue"
},
  "geometry": {"coordinates":[7.439605,46.947315],"type":"Point"}
}