{
  "type": "Feature",
  "properties": {
    "addr:full":"Steinb\u00fchlweg 76 Allschwil Basel-Landschaft 4123",
    "addr:housenumber":"76",
    "addr:postcode":"4123",
    "addr:street":"Steinbuehlweg",
    "iso:country":"CH",
    "sg:address":"Steinb\u00fchlweg 76",
    "sg:city":"Allschwil",
    "sg:orig_category":"Allgemeiner Hoch U Tiefbau",
    "sg:postcode":"4123",
    "sg:province":"Basel-Landschaft",
    "wof:name":"Zimmermann R. S\u00e0rl",
    "wof:placetype":"venue"
},
  "geometry": {"coordinates":[6.92753,47.032436],"type":"Point"}
}