{
  "type": "Feature",
  "properties": {
    "iso:country":"CH",
    "sg:address":"Haufteilstrasse",
    "sg:city":"Schmerikon",
    "sg:orig_category":"Herstellung von Konstruktionsteilen, Fertigbauteilen U Ausbauelementen aus Holz",
    "sg:phone":"+41 55 282 24 42",
    "sg:postcode":"8716",
    "sg:province":"St. Gallen",
    "wof:name":"Zigerlig Urs",
    "wof:placetype":"venue"
},
  "geometry": {"coordinates":[8.9599599838,47.2284240723],"type":"Point"}
}