{
  "type": "Feature",
  "properties": {
    "iso:country":"CH",
    "sg:address":"Oberdorfstrasse 2",
    "sg:city":"Boppelsen",
    "sg:orig_category":"Gemeindeverwaltungen",
    "sg:phone":"+41 18442060",
    "sg:postcode":"8113",
    "sg:province":"Z\u00fcrich",
    "wof:name":"Gemeindeverwaltung Boppelsen",
    "wof:placetype":"venue"
},
  "geometry": {"coordinates":[8.4025716782,47.4706954956],"type":"Point"}
}