{
  "type": "Feature",
  "properties": {
    "iso:country":"CH",
    "sg:address":"Grand-rue 19",
    "sg:city":"Corg\u00e9mont",
    "sg:orig_category":"Detailhandel mit Milcherzeugnissen U Eiern Verarbeitung von Milch",
    "sg:postcode":"2606",
    "sg:province":"Bern",
    "wof:name":"Roger Schwab Fromagerie",
    "wof:placetype":"venue"
},
  "geometry": {"coordinates":[7.1441640854,47.1942024231],"type":"Point"}
}