{
  "type": "Feature",
  "properties": {
    "iso:country":"CH",
    "sg:address":"H\u00fcttenacherweg 18",
    "sg:city":"Kleind\u00f6ttingen",
    "sg:orig_category":"Grafikateliers, Design Siebdruck",
    "sg:phone":"+41 56 245 22 77",
    "sg:postcode":"5314",
    "sg:province":"Aargau",
    "wof:name":"Margaretha Kalt Schrift-atelier",
    "wof:placetype":"venue"
},
  "geometry": {"coordinates":[8.2499914169,47.5674781799],"type":"Point"}
}