{
  "type": "Feature",
  "properties": {
    "addr:full":"Altstetterstrasse 145 8048 Z\u00fcrich. Postfach Z\u00fcrich Z\u00fcrich 8048",
    "addr:housenumber":"145",
    "addr:postcode":"8048 zuerich. postfach;8048",
    "addr:street":"Altstetterstrasse",
    "iso:country":"CH",
    "sg:address":"Altstetterstrasse 145 8048 Z\u00fcrich. Postfach",
    "sg:city":"Z\u00fcrich",
    "sg:orig_category":"Detailhandel mit B\u00fcchern, Zeitungen, Schreib U Papeteriewaren Detailhandel mit Schreib U Papeteriewa",
    "sg:phone":"+41 14305855",
    "sg:postcode":"8048",
    "sg:province":"Z\u00fcrich",
    "wof:name":"Leporello Ag Papeterie. Papeterie, Geschenkartikel; Handel",
    "wof:placetype":"venue"
},
  "geometry": {"coordinates":[8.486906,47.388641],"type":"Point"}
}