{
  "type": "Feature",
  "properties": {
    "iso:country":"CH",
    "sg:address":"Vignette Rue De La 22/24",
    "sg:city":"Payerne",
    "sg:orig_category":"G\u00fcterbef\u00f6rderung im Strassenverkehr",
    "sg:phone":"+41 56 664 44 39",
    "sg:postcode":"1530",
    "sg:province":"Vaud",
    "wof:name":"Tobiwag Sa",
    "wof:placetype":"venue"
},
  "geometry": {"coordinates":[6.9400901794,46.8218994141],"type":"Point"}
}