{
  "type": "Feature",
  "properties": {
    "iso:country":"CH",
    "sg:address":"Gasterstrasse",
    "sg:city":"Uznach",
    "sg:orig_category":"Landw. Genossenschaften Viehzucht",
    "sg:postcode":"8730",
    "sg:province":"St. Gallen",
    "wof:name":"Braunviehzuchtgenossenschaft",
    "wof:placetype":"venue"
},
  "geometry": {"coordinates":[8.9950342178,47.223991394],"type":"Point"}
}