{
  "type": "Feature",
  "properties": {
    "iso:country":"CH",
    "sg:address":"Blumenfeldstrasse 9",
    "sg:city":"Heiden",
    "sg:orig_category":"Ger\u00fcstbau Zimmerei, Dachdeckerei, Bauspenglerei U Abdichtung",
    "sg:phone":"+41 71 891 16 53",
    "sg:postcode":"9410",
    "sg:province":"Appenzell Ausserrhoden",
    "wof:name":"Alder Bedachungen Und Ger\u00fcstbau Ag",
    "wof:placetype":"venue"
},
  "geometry": {"coordinates":[9.5311374664,47.4445381165],"type":"Point"}
}