{
  "type": "Feature",
  "properties": {
    "iso:country":"CH",
    "sg:address":"Hauptstrasse 34",
    "sg:city":"D\u00fcdingen",
    "sg:orig_category":"Detailhandel mit Computern U Software Softwareentwicklung U beratung",
    "sg:phone":"+41 26 492 90 30",
    "sg:postcode":"3186",
    "sg:province":"Fribourg",
    "wof:name":"Pc-profi Gmbh",
    "wof:placetype":"venue"
},
  "geometry": {"coordinates":[7.189676,46.848732],"type":"Point"}
}