{
  "type": "Feature",
  "properties": {
    "iso:country":"CH",
    "sg:address":"Weihermatt 748",
    "sg:city":"M\u00fcmliswil",
    "sg:orig_category":"Gesundheitswesen",
    "sg:phone":"+41 62 391 13 04",
    "sg:postcode":"4717",
    "sg:province":"Solothurn",
    "wof:name":"Aktiv-zentrum Andreas B\u00fcttler",
    "wof:placetype":"venue"
},
  "geometry": {"coordinates":[7.7098398209,47.343082428],"type":"Point"}
}