{
  "type": "Feature",
  "properties": {
    "iso:country":"CH",
    "sg:address":"Spiezbergstrasse 24a",
    "sg:city":"Spiez",
    "sg:orig_category":"Massagestudios",
    "sg:phone":"+41 33 654 41 60",
    "sg:postcode":"3700",
    "sg:province":"Bern",
    "wof:name":"Silvia Liechti Massagen",
    "wof:placetype":"venue"
},
  "geometry": {"coordinates":[7.6804771423,46.691608429],"type":"Point"}
}