{
  "type": "Feature",
  "properties": {
    "iso:country":"CH",
    "sg:address":"Rue De Montchoisy 72",
    "sg:city":"Gen\u00e8ve",
    "sg:orig_category":"Detailhandel mit Brot, Back U S\u00fcsswaren RESTAURANTS: TEA-ROOMS",
    "sg:phone":"+41 22 736 26 93",
    "sg:postcode":"1207",
    "sg:province":"Gen\u00e8ve",
    "wof:name":"Dieter Keiser",
    "wof:placetype":"venue"
},
  "geometry": {"coordinates":[6.163358,46.204815],"type":"Point"}
}