{
  "type": "Feature",
  "properties": {
    "iso:country":"CH",
    "sg:address":"Tellistrasse 67",
    "sg:city":"Aarau",
    "sg:orig_category":"Detailhandel mit B\u00fcromaschinen U einrichtungen Detailhandel mit Schreib U Papeteriewaren",
    "sg:phone":"+41 62 824 47 17",
    "sg:postcode":"5004",
    "sg:province":"Aargau",
    "wof:name":"Mc Paperland Papeterie & B\u00fcrofachmarkt",
    "wof:placetype":"venue"
},
  "geometry": {"coordinates":[8.058141,47.397804],"type":"Point"}
}