{
  "type": "Feature",
  "properties": {
    "iso:country":"CH",
    "sg:address":"Lothringerstrasse 7",
    "sg:city":"Basel",
    "sg:orig_category":"Arztpraxen",
    "sg:phone":"+41 61 701 71 71",
    "sg:postcode":"4056",
    "sg:province":"Basel-Stadt",
    "wof:name":"Dr.med.rudolf Zimmermann Spezialarzt Fmh",
    "wof:placetype":"venue"
},
  "geometry": {"coordinates":[7.616977,47.478771],"type":"Point"}
}