{
  "type": "Feature",
  "properties": {
    "iso:country":"CH",
    "sg:address":"Baarerstrasse 43",
    "sg:city":"Zug",
    "sg:orig_category":"Sonstiges Versicherungsgewerbe Versicherungsagenturen and -broker",
    "sg:phone":"+41 41 727 20 48",
    "sg:postcode":"6300",
    "sg:province":"Zug",
    "wof:name":"Alcover Ag",
    "wof:placetype":"venue"
},
  "geometry": {"coordinates":[8.516579628,47.1738433838],"type":"Point"}
}