{
  "type": "Feature",
  "properties": {
    "iso:country":"CH",
    "sg:address":"Br\u00e9sil Chemin Du 2a",
    "sg:city":"Blonay",
    "sg:orig_category":"Herstellung von Duft U K\u00f6rperpflegemitteln",
    "sg:postcode":"1807",
    "sg:province":"Vaud",
    "wof:name":"Li Cosmetic Ag",
    "wof:placetype":"venue"
},
  "geometry": {"coordinates":[7.558549881,46.9297409058],"type":"Point"}
}