{
  "type": "Feature",
  "properties": {
    "iso:country":"CH",
    "sg:address":"Ch. Des Papillons 20",
    "sg:city":"Meyrin",
    "sg:orig_category":"Unclassifiable Establishments",
    "sg:postcode":"1217",
    "sg:province":"Gen\u00e8ve",
    "wof:name":"Alg Partners Sa",
    "wof:placetype":"venue"
},
  "geometry": {"coordinates":[6.0942511559,46.2231140137],"type":"Point"}
}