{
  "type": "Feature",
  "properties": {
    "iso:country":"CH",
    "sg:address":"H\u00f6henweg 30 8222 Beringen. Postfach",
    "sg:city":"Beringen",
    "sg:orig_category":"Allgemeiner Hoch U Tiefbau",
    "sg:phone":"+41 52 685 23 27",
    "sg:postcode":"8222",
    "sg:province":"Schaffhausen",
    "wof:name":"Huber Roli Bauservice Bauservice, Um, Anbauten",
    "wof:placetype":"venue"
},
  "geometry": {"coordinates":[8.571011,47.700748],"type":"Point"}
}