{
  "type": "Feature",
  "properties": {
    "iso:country":"CH",
    "sg:address":"Bellevueweg 38",
    "sg:city":"Zug",
    "sg:orig_category":"Datenverarbeitungsdienste Softwareentwicklung U beratung",
    "sg:phone":"+41 41 630 38 33",
    "sg:postcode":"6300",
    "sg:province":"Zug",
    "wof:name":"Mi Marketing-informatik Ag Computersysteme",
    "wof:placetype":"venue"
},
  "geometry": {"coordinates":[8.51847,47.151642],"type":"Point"}
}