{
  "type": "Feature",
  "properties": {
    "iso:country":"CH",
    "sg:address":"Tuftli 3",
    "sg:city":"Grindelwald",
    "sg:classifiers":[
        {
            "category":"Travel",
            "subcategory":"Hotels & Motels",
            "type":"Entertainment"
        }
    ],
    "sg:phone":"+41 55 220 66 30",
    "sg:postcode":"3818",
    "sg:province":"Bern",
    "sg:tags":[
        "hotels",
        "mit",
        "restaurant"
    ],
    "wof:name":"Hotel Bellevue Rapperswil Ag",
    "wof:placetype":"venue"
},
  "geometry": {"coordinates":[8.8146944046,47.2261352539],"type":"Point"}
}