{
  "type": "Feature",
  "properties": {
    "iso:country":"CH",
    "sg:address":"Hintere Kirchgasse 59",
    "sg:city":"Willisau",
    "sg:orig_category":"Zimmerei, Dachdeckerei, Bauspenglerei U Abdichtung",
    "sg:phone":"+41 41 970 25 59",
    "sg:postcode":"6130",
    "sg:province":"Luzern",
    "wof:name":"Kr\u00fcgel-r\u00fcedi Adolf",
    "wof:placetype":"venue"
},
  "geometry": {"coordinates":[7.9928841591,47.1222229004],"type":"Point"}
}