{
  "type": "Feature",
  "properties": {
    "iso:country":"CH",
    "sg:address":"Gemmertshausen 7",
    "sg:city":"Romanshorn",
    "sg:classifiers":[
        {
            "category":"Manufacturing",
            "subcategory":"Wood Products",
            "type":"Manufacturing & Wholesale Goods"
        }
    ],
    "sg:phone":"+41 33 681 12 28",
    "sg:postcode":"8590",
    "sg:province":"Thurgau",
    "sg:tags":[
        "firewood"
    ],
    "wof:name":"Gehrig Ag",
    "wof:placetype":"venue"
},
  "geometry": {"coordinates":[7.5498228073,46.6592407227],"type":"Point"}
}