{
  "type": "Feature",
  "properties": {
    "iso:country":"CH",
    "sg:address":"Baselstrasse 67",
    "sg:city":"Grellingen",
    "sg:orig_category":"Handel mit Automobilen",
    "sg:phone":"+41 61 901 71 71",
    "sg:postcode":"4203",
    "sg:province":"Basel-Landschaft",
    "wof:name":"Acg Auto-center Grellingen Gmbh",
    "wof:placetype":"venue"
},
  "geometry": {"coordinates":[7.5980610847,47.4434432983],"type":"Point"}
}