{
  "type": "Feature",
  "properties": {
    "iso:country":"CH",
    "sg:address":"7130",
    "sg:city":"Ilanz",
    "sg:orig_category":"Vermietung U Verpachtung von eigenen Immobilien",
    "sg:postcode":"7130",
    "sg:province":"Graubunden",
    "wof:name":"Casa Grischa Ag",
    "wof:placetype":"venue"
},
  "geometry": {"coordinates":[9.2045469284,46.7744483948],"type":"Point"}
}