{
  "type": "Feature",
  "properties": {
    "iso:country":"CH",
    "sg:address":"1584",
    "sg:city":"Villars-le-grand",
    "sg:orig_category":"K\u00fcnstlerische U schriftstellerische T\u00e4tigkeiten U Darbietungen",
    "sg:phone":"+41 26 677 29 66",
    "sg:postcode":"1584",
    "sg:province":"Vaud",
    "wof:name":"Willommet Michel",
    "wof:placetype":"venue"
},
  "geometry": {"coordinates":[6.9950299263,46.9049911499],"type":"Point"}
}