{
  "type": "Feature",
  "properties": {
    "addr:full":"Industriestrasse 5 B\u00f6singen Fribourg 3178",
    "addr:housenumber":"5",
    "addr:postcode":"3178",
    "addr:street":"Industriestrasse;Fribourg",
    "iso:country":"CH",
    "sg:address":"Industriestrasse 5",
    "sg:city":"B\u00f6singen",
    "sg:orig_category":"Allgemeiner Gartenbau",
    "sg:postcode":"3178",
    "sg:province":"Fribourg",
    "wof:name":"Spring Art G\u00e4rten & Anlagen",
    "wof:placetype":"venue"
},
  "geometry": {"coordinates":[7.23201,46.90028],"type":"Point"}
}