{
  "type": "Feature",
  "properties": {
    "iso:country":"CH",
    "sg:address":"Nordstrasse 144 8037 Z\u00fcrich. Postfach",
    "sg:city":"Z\u00fcrich",
    "sg:orig_category":"Herstellung von Ger\u00e4ten der Elektrizit\u00e4tserzeugung, -verteilung u.\u00e4. -Herstellung von elektronischen",
    "sg:phone":"+41 13610412",
    "sg:postcode":"8042",
    "sg:province":"Z\u00fcrich",
    "wof:name":"Zitt Contronic & Cie",
    "wof:placetype":"venue"
},
  "geometry": {"coordinates":[8.5331163406,47.3910484314],"type":"Point"}
}