{
  "type": "Feature",
  "properties": {
    "iso:country":"CH",
    "sg:address":"Forchstrasse 138",
    "sg:city":"Z\u00fcrich",
    "sg:orig_category":"Erwachsenenbildung U sonstiger Unterricht Sprachschulen",
    "sg:phone":"+41 14228512",
    "sg:postcode":"8032",
    "sg:province":"Z\u00fcrich",
    "wof:name":"Oise-sprachschule Im Ausland",
    "wof:placetype":"venue"
},
  "geometry": {"coordinates":[8.5628671646,47.3604927063],"type":"Point"}
}