{
  "type": "Feature",
  "properties": {
    "iso:country":"CH",
    "sg:address":"Alte Landstrasse 116",
    "sg:city":"Zollikon",
    "sg:orig_category":"HERSTELLUNG VON GER\u00c4TEN DER ELEKTRIZIT\u00c4TSERZEUGUNG, -VERTEILUNG U.\u00c4 Herstellung von Metallerzeugniss",
    "sg:phone":"+41 13913113",
    "sg:postcode":"8702",
    "sg:province":"Z\u00fcrich",
    "wof:name":"Gutermann, Elektronische Messinstrumente",
    "wof:placetype":"venue"
},
  "geometry": {"coordinates":[8.5769720078,47.3355331421],"type":"Point"}
}