{
  "type": "Feature",
  "properties": {
    "iso:country":"CH",
    "sg:address":"Rue Du Cygne 4",
    "sg:city":"Porrentruy",
    "sg:orig_category":"Maurerarbeiten",
    "sg:phone":"+41 32 466 70 19",
    "sg:postcode":"2900",
    "sg:province":"Jura",
    "wof:name":"Antonio Silva Santos Ma\u00e7onnerie",
    "wof:placetype":"venue"
},
  "geometry": {"coordinates":[7.0760087967,47.4149017334],"type":"Point"}
}