{
  "type": "Feature",
  "properties": {
    "iso:country":"CH",
    "sg:address":"Utoquai",
    "sg:city":"Z\u00fcrich",
    "sg:orig_category":"Physiotherapie",
    "sg:phone":"+41 12018085",
    "sg:postcode":"8008",
    "sg:province":"Z\u00fcrich",
    "wof:name":"Christian Drescher Sporttherapie",
    "wof:placetype":"venue"
},
  "geometry": {"coordinates":[8.547539711,47.3621139526],"type":"Point"}
}