{
  "type": "Feature",
  "properties": {
    "iso:country":"CH",
    "sg:address":"Falcon \u00eele",
    "sg:city":"Sierre",
    "sg:orig_category":"Farben and Lacke Grosshandel Grosshandel mit chemischen Erzeugnissen",
    "sg:phone":"+41 22 734 03 20",
    "sg:postcode":"3960",
    "sg:province":"Valais",
    "wof:name":"J. J. Lucchini & Fils Sa Peintures-vernis Engros",
    "wof:placetype":"venue"
},
  "geometry": {"coordinates":[6.1333899498,46.2125396729],"type":"Point"}
}