{
  "type": "Feature",
  "properties": {
    "iso:country":"CH",
    "sg:address":"Eggr\u00fctistrasse 2",
    "sg:city":"Feldbach",
    "sg:orig_category":"Primarschulen",
    "sg:phone":"+41 55 244 14 93",
    "sg:postcode":"8714",
    "sg:province":"Z\u00fcrich",
    "wof:name":"Primarschule",
    "wof:placetype":"venue"
},
  "geometry": {"coordinates":[8.7871627808,47.2409477234],"type":"Point"}
}