{
  "type": "Feature",
  "properties": {
    "iso:country":"CH",
    "sg:address":"Rue Des Chansons 37",
    "sg:city":"Peseux",
    "sg:orig_category":"Erdbewegungsarbeiten Test U Sondierbohrungen",
    "sg:phone":"+41 32 732 25 20",
    "sg:postcode":"2034",
    "sg:province":"Neuch\u00e2tel",
    "wof:name":"Bayard Rock-profil Sa",
    "wof:placetype":"venue"
},
  "geometry": {"coordinates":[6.8981280327,46.9853515625],"type":"Point"}
}