{
  "type": "Feature",
  "properties": {
    "iso:country":"CH",
    "sg:address":"Webergasse 38",
    "sg:city":"Schaffhausen",
    "sg:orig_category":"Non-Classified Establishments",
    "sg:phone":"+41 52 625 45 83",
    "sg:postcode":"8200",
    "sg:province":"Schaffhausen",
    "wof:name":"Ristorante Sapore Di Mare Gmbh",
    "wof:placetype":"venue"
},
  "geometry": {"coordinates":[8.6353092194,47.6984672546],"type":"Point"}
}