{
  "type": "Feature",
  "properties": {
    "iso:country":"CH",
    "sg:address":"Rh\u00f4ne Rue Du 118 1204 Gen\u00e8ve. Postfach",
    "sg:city":"Gen\u00e8ve",
    "sg:orig_category":"Elektroinstallation",
    "sg:phone":"+41 27 956 14 49",
    "sg:postcode":"1204",
    "sg:province":"Gen\u00e8ve",
    "wof:name":"Gruber Martin, Elektr. Anlagen",
    "wof:placetype":"venue"
},
  "geometry": {"coordinates":[7.802011013,46.1768875122],"type":"Point"}
}