{
  "type": "Feature",
  "properties": {
    "iso:country":"CH",
    "sg:address":"R\u00f6hrlistrasse 25",
    "sg:city":"Weggis",
    "sg:orig_category":"Verarbeitung von Milch Verwertung von Milch",
    "sg:phone":"+41 62 926 02 26",
    "sg:postcode":"6353",
    "sg:province":"Luzern",
    "wof:name":"Thomas Schmitter, K\u00e4serei, 4853 Riken",
    "wof:placetype":"venue"
},
  "geometry": {"coordinates":[7.8478140831,47.2762718201],"type":"Point"}
}