{
  "type": "Feature",
  "properties": {
    "iso:country":"CH",
    "sg:address":"Rue Du Simplon 15",
    "sg:city":"Bex",
    "sg:orig_category":"Instandhaltung U Reparatur von Automobilen Vermietung von Automobilen",
    "sg:phone":"+41 24 463 22 84",
    "sg:postcode":"1880",
    "sg:province":"Vaud",
    "wof:name":"Garage Touring, Bex Sa",
    "wof:placetype":"venue"
},
  "geometry": {"coordinates":[7.007174015,46.2477416992],"type":"Point"}
}