{
  "type": "Feature",
  "properties": {
    "iso:country":"CH",
    "sg:address":"Via Riviera 18 6976 Castagnola. Postfach",
    "sg:city":"Castagnola",
    "sg:orig_category":"Vermietung U Verpachtung von eigenen Immobilien",
    "sg:postcode":"6976",
    "sg:province":"Ticino",
    "wof:name":"Villa Plafino Ag",
    "wof:placetype":"venue"
},
  "geometry": {"coordinates":[9.8328380585,46.80651474],"type":"Point"}
}