{
  "type": "Feature",
  "properties": {
    "addr:full":"Neum\u00fchlestrasse 42 Winterthur Z\u00fcrich 8406",
    "addr:housenumber":"42",
    "addr:postcode":"8406",
    "addr:street":"Neumuehlestrasse",
    "iso:country":"CH",
    "sg:address":"Neum\u00fchlestrasse 42",
    "sg:city":"Winterthur",
    "sg:orig_category":"Datenbanken Softwareentwicklung U beratung",
    "sg:phone":"+41 52 202 75 55",
    "sg:postcode":"8406",
    "sg:province":"Z\u00fcrich",
    "wof:name":"Martista Ag",
    "wof:placetype":"venue"
},
  "geometry": {"coordinates":[8.707587,47.483395],"type":"Point"}
}