{
  "type": "Feature",
  "properties": {
    "iso:country":"CH",
    "sg:address":"Gerliswilstr. 64",
    "sg:city":"Emmen",
    "sg:orig_category":"Non-Classified Establishments",
    "sg:postcode":"6032",
    "sg:province":"Luzern",
    "wof:name":"Fehr H.",
    "wof:placetype":"venue"
},
  "geometry": {"coordinates":[8.2759971619,47.0760765076],"type":"Point"}
}