{
  "type": "Feature",
  "properties": {
    "iso:country":"CH",
    "sg:address":"Rue Chantepoulet 10",
    "sg:city":"Gen\u00e8ve",
    "sg:orig_category":"Detailhandel mit M\u00f6beln U Haushaltsgegenst\u00e4nden Detailhandel mit Teppichen",
    "sg:phone":"+41 22 901 14 75",
    "sg:postcode":"1201",
    "sg:province":"Gen\u00e8ve",
    "wof:name":"Nissan Galery Sa",
    "wof:placetype":"venue"
},
  "geometry": {"coordinates":[6.1433901787,46.2084121704],"type":"Point"}
}