{
  "type": "Feature",
  "properties": {
    "iso:country":"CH",
    "sg:address":"Lufingerstrasse 19",
    "sg:city":"Winkel",
    "sg:orig_category":"Detailhandel mit Antiquit\u00e4ten Detailhandel mit Gebrauchtwaren in Verkaufsr\u00e4umen",
    "sg:phone":"+41 71 245 08 77",
    "sg:postcode":"8185",
    "sg:province":"Z\u00fcrich",
    "wof:name":"Rolf Zimmerli Rolf's Flohmarkt-shop",
    "wof:placetype":"venue"
},
  "geometry": {"coordinates":[9.3954,47.43359],"type":"Point"}
}