{
  "type": "Feature",
  "properties": {
    "addr:full":"Schulstrasse 10 Sissach Basel-Landschaft 4450",
    "addr:housenumber":"10",
    "addr:postcode":"4450",
    "addr:street":"Schulstrasse",
    "iso:country":"CH",
    "sg:address":"Schulstrasse 10",
    "sg:city":"Sissach",
    "sg:orig_category":"Detailhandel mit Beleuchtungs U Haushaltsgegenst\u00e4nden",
    "sg:phone":"+41 61 921 00 47",
    "sg:postcode":"4450",
    "sg:province":"Basel-Landschaft",
    "wof:name":"Peter Wagner Innendekoration",
    "wof:placetype":"venue"
},
  "geometry": {"coordinates":[7.809663,47.465889],"type":"Point"}
}