{
  "type": "Feature",
  "properties": {
    "iso:country":"CH",
    "sg:address":"Strada Ponte Di Valle 6964 Davesco-soragno. Postfach Caselle Postale 3361",
    "sg:city":"Lugano",
    "sg:orig_category":"Dachdeckerei Herstellung von sonstigen Metallwaren",
    "sg:phone":"+41 91 941 81 71",
    "sg:postcode":"6901",
    "sg:province":"Ticino",
    "wof:name":"Sitaf Sa Isolazioni & Coperture Tetti",
    "wof:placetype":"venue"
},
  "geometry": {"coordinates":[8.978402,46.039158],"type":"Point"}
}