{
  "type": "Feature",
  "properties": {
    "iso:country":"CH",
    "sg:address":"Romanshorner Strasse 2",
    "sg:city":"Kronb\u00fchl",
    "sg:orig_category":"Kantonalbanken",
    "sg:phone":"+41 71 761 24 24",
    "sg:postcode":"9302",
    "wof:name":"St.galler Kantonalbank",
    "wof:placetype":"venue"
},
  "geometry": {"coordinates":[9.5651578903,47.3212280273],"type":"Point"}
}