{
  "type": "Feature",
  "properties": {
    "iso:country":"CH",
    "sg:address":"Deutsche Strasse 5",
    "sg:city":"Chur",
    "sg:orig_category":"Handel mit Automobilen",
    "sg:postcode":"7000",
    "sg:province":"Graubunden",
    "wof:name":"Ineichen Autohandel",
    "wof:placetype":"venue"
},
  "geometry": {"coordinates":[9.5401802063,46.8862686157],"type":"Point"}
}