{
  "type": "Feature",
  "properties": {
    "iso:country":"CH",
    "sg:address":"Zihlstrasse 50",
    "sg:city":"Nidau",
    "sg:orig_category":"Non-Classified Establishments",
    "sg:postcode":"2560",
    "sg:province":"Bern",
    "wof:name":"Holding An Der Zihl",
    "wof:placetype":"venue"
},
  "geometry": {"coordinates":[7.2421250343,47.1245765686],"type":"Point"}
}