{
  "type": "Feature",
  "properties": {
    "iso:country":"CH",
    "sg:address":"Rue Jaquet-droz 1",
    "sg:city":"Neuch\u00e2tel",
    "sg:classifiers":[
        {
            "category":"Professional",
            "subcategory":"Research",
            "type":"Services"
        }
    ],
    "sg:phone":"+41 32 720 51 31",
    "sg:postcode":"2000",
    "sg:province":"Neuch\u00e2tel",
    "sg:tags":[
        "database"
    ],
    "wof:name":"Centredoc",
    "wof:placetype":"venue"
},
  "geometry": {"coordinates":[6.947512,46.997795],"type":"Point"}
}