{
  "type": "Feature",
  "properties": {
    "iso:country":"CH",
    "sg:address":"Falcon \u00eele",
    "sg:city":"Sierre",
    "sg:orig_category":"Farben and Lacke Grosshandel Grosshandel mit chemischen Erzeugnissen",
    "sg:phone":"+41 22 329 12 22",
    "sg:postcode":"3960",
    "sg:province":"Valais",
    "wof:name":"Jalcolor Sa",
    "wof:placetype":"venue"
},
  "geometry": {"coordinates":[6.1422371864,46.1917266846],"type":"Point"}
}