{
  "type": "Feature",
  "properties": {
    "iso:country":"CH",
    "sg:address":"T\u00fcrkheimerstrasse 8",
    "sg:city":"Basel",
    "sg:orig_category":"Grosshandel mit B\u00fcromaschinen Grosshandel mit Datenverarbeitungsger\u00e4ten",
    "sg:phone":"+41 61 303 33 88",
    "sg:postcode":"4055",
    "sg:province":"Basel-Stadt",
    "wof:name":"Yanni Computer Systems",
    "wof:placetype":"venue"
},
  "geometry": {"coordinates":[7.5746240616,47.557800293],"type":"Point"}
}