{
  "type": "Feature",
  "properties": {
    "iso:country":"CH",
    "sg:address":"Ueberlandstrasse 15",
    "sg:city":"Dietikon",
    "sg:orig_category":"Herstellung von Metallerzeugnissen ohne Maschinenbau Herstellung von elektrischen Haushaltsger\u00e4ten",
    "sg:phone":"+41 17408163",
    "sg:postcode":"8953",
    "sg:province":"Z\u00fcrich",
    "wof:name":"Heinz B\u00e4hni Bodenpflegemaschinen",
    "wof:placetype":"venue"
},
  "geometry": {"coordinates":[8.406498909,47.408203125],"type":"Point"}
}