{
  "type": "Feature",
  "properties": {
    "iso:country":"CH",
    "sg:address":"Laubstenstrasse 12",
    "sg:city":"St\u00e4fa",
    "sg:orig_category":"Autogaragen",
    "sg:phone":"+41 19262036",
    "sg:postcode":"8712",
    "sg:province":"Z\u00fcrich",
    "wof:name":"Hansruedi Ryffel Autogarage",
    "wof:placetype":"venue"
},
  "geometry": {"coordinates":[8.725171,47.246136],"type":"Point"}
}