{
  "type": "Feature",
  "properties": {
    "iso:country":"CH",
    "sg:address":"Bernstrasse 97",
    "sg:city":"Steffisburg",
    "sg:orig_category":"Sonstige pers\u00f6nliche Dienstleistungen",
    "sg:phone":"+41 33 222 70 88",
    "sg:postcode":"3613",
    "sg:province":"Bern",
    "wof:name":"Ramseier W., Ramseier R. + Schiffmann U.",
    "wof:placetype":"venue"
},
  "geometry": {"coordinates":[7.618309021,46.7705764771],"type":"Point"}
}