{
  "type": "Feature",
  "properties": {
    "iso:country":"CH",
    "sg:address":"Kornfeldstrasse 1 6210 Sursee. Postfach",
    "sg:city":"Sursee",
    "sg:orig_category":"Herstellung von Fahrr\u00e4dern",
    "sg:phone":"+41 41 921 74 75",
    "sg:postcode":"6210",
    "sg:province":"Luzern",
    "wof:name":"Tigra Bike Ag Fahrr\u00e4der, -ersatzteile, -zubeh\u00f6r; Prod., Handel",
    "wof:placetype":"venue"
},
  "geometry": {"coordinates":[8.1031122208,47.1766357422],"type":"Point"}
}