{
  "type": "Feature",
  "properties": {
    "iso:country":"CH",
    "sg:address":"Rue De Bernex 266",
    "sg:city":"Bernex",
    "sg:orig_category":"Grosshandel mit keramischen Erzeugnissen, Glaswaren U Reinigungsmitteln Verlegen von Fussboden",
    "sg:phone":"+41 22 757 63 26",
    "sg:postcode":"1233",
    "sg:province":"Gen\u00e8ve",
    "wof:name":"Paperland P.barcellini & Cie Papiers-peints Tissus",
    "wof:placetype":"venue"
},
  "geometry": {"coordinates":[6.0738749504,46.1759376526],"type":"Point"}
}