{
  "type": "Feature",
  "properties": {
    "iso:country":"CH",
    "sg:address":"Ruhbergstrasse 2 9214 Kradolf. Postfach",
    "sg:city":"Kradolf",
    "sg:orig_category":"Grosshandel mit Nahrungsmitteln, Getr\u00e4nken U Tabakwaren",
    "sg:phone":"+41 71 642 77 10",
    "sg:postcode":"9214",
    "sg:province":"Thurgau",
    "wof:name":"Cruspi Sa S\u00fcsswarenimport-& Vertrieb",
    "wof:placetype":"venue"
},
  "geometry": {"coordinates":[9.2006912231,47.5277328491],"type":"Point"}
}