{
  "type": "Feature",
  "properties": {
    "iso:country":"CH",
    "sg:address":"Mattenweg",
    "sg:city":"Sch\u00f6nb\u00fchl-urtenen",
    "sg:orig_category":"Lagerh\u00e4user, G\u00fcterumschlag, Verteilzentren",
    "sg:postcode":"3322",
    "sg:province":"Bern",
    "wof:name":"Gerber & Co",
    "wof:placetype":"venue"
},
  "geometry": {"coordinates":[7.4953417778,47.0212440491],"type":"Point"}
}