{
  "type": "Feature",
  "properties": {
    "iso:country":"CH",
    "sg:address":"Thunstrasse 9 3110 M\u00fcnsingen. Postfach 1044",
    "sg:city":"M\u00fcnsingen",
    "sg:orig_category":"Advokaturb\u00fcros Notariate",
    "sg:phone":"+41 56 441 54 00",
    "sg:postcode":"3110",
    "sg:province":"Bern",
    "wof:name":"Thut & H\u00e4nggli Advokatur- & Notariatsb\u00fcro",
    "wof:placetype":"venue"
},
  "geometry": {"coordinates":[8.207449,47.480824],"type":"Point"}
}