{
  "type": "Feature",
  "properties": {
    "iso:country":"CH",
    "sg:address":"Wydenstrasse 24",
    "sg:city":"Worb",
    "sg:orig_category":"Detailhandel mit Textilien Detailhandel mit Waren verschiedener Art, Hauptrichtung Nahrungsmittel",
    "sg:phone":"+41 31 839 14 55",
    "sg:postcode":"3076",
    "sg:province":"Bern",
    "wof:name":"Marliese L\u00fcthi Lebensmittel-calida",
    "wof:placetype":"venue"
},
  "geometry": {"coordinates":[7.5676808357,46.9264831543],"type":"Point"}
}