{
  "type": "Feature",
  "properties": {
    "iso:country":"CH",
    "sg:address":"4717",
    "sg:city":"M\u00fcmliswil",
    "sg:orig_category":"Landwirtschaftliche Genossenschaften",
    "sg:phone":"+41 62 394 12 44",
    "sg:postcode":"4717",
    "sg:province":"Solothurn",
    "wof:name":"Alpgenossenschaft Zentner",
    "wof:placetype":"venue"
},
  "geometry": {"coordinates":[7.7031598091,47.3411102295],"type":"Point"}
}