{
  "type": "Feature",
  "properties": {
    "iso:country":"CH",
    "sg:address":"Unterbiel 50",
    "sg:city":"Reigoldswil",
    "sg:orig_category":"Sportvereine Turnen Vereine Damen",
    "sg:phone":"+41 61 941 15 69",
    "sg:postcode":"4418",
    "sg:province":"Basel-Landschaft",
    "wof:name":"Damenriege",
    "wof:placetype":"venue"
},
  "geometry": {"coordinates":[7.6907548904,47.4012489319],"type":"Point"}
}