{
  "type": "Feature",
  "properties": {
    "iso:country":"CH",
    "sg:address":"Grossmatte Ost 8",
    "sg:city":"Littau",
    "sg:orig_category":"Herstellung von elektrischen Lampen U Leuchten",
    "sg:phone":"+41 41 240 42 31",
    "sg:postcode":"6014",
    "sg:province":"Luzern",
    "wof:name":"Soundhouse Ag",
    "wof:placetype":"venue"
},
  "geometry": {"coordinates":[8.2677707672,47.0489311218],"type":"Point"}
}