{
  "type": "Feature",
  "properties": {
    "iso:country":"CH",
    "sg:address":"Steinh\u00f6lzli 3097 Liebefeld. Postfach",
    "sg:city":"Liebefeld",
    "sg:orig_category":"Museen",
    "sg:phone":"+41 31 970 31 41",
    "sg:postcode":"3097",
    "sg:province":"Bern",
    "wof:name":"Hess Art Collection Ag",
    "wof:placetype":"venue"
},
  "geometry": {"coordinates":[7.4304351807,46.9324302673],"type":"Point"}
}