{
  "type": "Feature",
  "properties": {
    "iso:country":"CH",
    "sg:address":"M\u00fchlebachstrasse 5",
    "sg:city":"Stans",
    "sg:orig_category":"Gymnastik U Fitnesszentren Saunas, Solarien, Fitnesszentren U \u00e4hnliches",
    "sg:phone":"+41 41 610 70 00",
    "sg:postcode":"6370",
    "sg:province":"Nidwalden",
    "wof:name":"Panthera Lady's Gym Gmbh",
    "wof:placetype":"venue"
},
  "geometry": {"coordinates":[8.3736953735,46.956451416],"type":"Point"}
}