{
  "type": "Feature",
  "properties": {
    "iso:country":"CH",
    "sg:address":"1880",
    "sg:city":"Bex",
    "sg:orig_category":"Erschliessung von Grundst\u00fccken",
    "sg:postcode":"1880",
    "sg:province":"Vaud",
    "wof:name":"Soci\u00e9t\u00e9 Coop\u00e9rative Immobili\u00e8re \u00able Logement Pour Tous\u00bb",
    "wof:placetype":"venue"
},
  "geometry": {"coordinates":[7.0156807899,46.2502593994],"type":"Point"}
}