{
  "type": "Feature",
  "properties": {
    "iso:country":"CH",
    "sg:address":"Dornacherstrasse 377",
    "sg:city":"Basel",
    "sg:classifiers":[
        {
            "category":"Professional",
            "subcategory":"Computer Services",
            "type":"Services"
        }
    ],
    "sg:phone":"+41 52 672 42 22",
    "sg:postcode":"4053",
    "sg:province":"Basel-Stadt",
    "sg:tags":[
        "development",
        "software"
    ],
    "wof:name":"Retel Ag",
    "wof:placetype":"venue"
},
  "geometry": {"coordinates":[8.6040248871,47.6752586365],"type":"Point"}
}