{
  "type": "Feature",
  "properties": {
    "iso:country":"CH",
    "sg:address":"Rue Haldimand 15",
    "sg:city":"Lausanne",
    "sg:orig_category":"Detailhandel mit Radio U Fernsehger\u00e4ten",
    "sg:phone":"+41 21 312 86 06",
    "sg:postcode":"1003",
    "sg:province":"Vaud",
    "wof:name":"B&o T\u00e9l\u00e9-clinique Bang & Olufsen Center",
    "wof:placetype":"venue"
},
  "geometry": {"coordinates":[6.6300530434,46.5221328735],"type":"Point"}
}