{
  "type": "Feature",
  "properties": {
    "iso:country":"CH",
    "sg:address":"Mattenstrasse 33 3073 G\u00fcmligen. Postfach 37",
    "sg:city":"G\u00fcmligen",
    "sg:orig_category":"Sportvereine Turnen",
    "sg:phone":"+41 31 952 64 49",
    "sg:postcode":"3073",
    "sg:province":"Bern",
    "wof:name":"Turnverein Stv Muri-g\u00fcmligen",
    "wof:placetype":"venue"
},
  "geometry": {"coordinates":[7.5110569,46.9341773987],"type":"Point"}
}