{
  "type": "Feature",
  "properties": {
    "iso:country":"CH",
    "sg:address":"Neuhaus",
    "sg:city":"Belpberg",
    "sg:orig_category":"Fachdetailhandel in Verkaufsr\u00e4umen",
    "sg:postcode":"3124",
    "sg:province":"Bern",
    "wof:name":"Elisabeth Walther Flowerpoint",
    "wof:placetype":"venue"
},
  "geometry": {"coordinates":[7.527695179,46.8660163879],"type":"Point"}
}