{
  "type": "Feature",
  "properties": {
    "iso:country":"CH",
    "sg:address":"Neudorfstrasse 7430 Thusis. Postfach 26",
    "sg:city":"Thusis",
    "sg:classifiers":[
        {
            "category":"Restaurant",
            "type":"Food & Drink"
        }
    ],
    "sg:phone":"+41 81 651 11 61",
    "sg:postcode":"7430",
    "sg:province":"Graubunden",
    "wof:name":"Restaurant Sonne",
    "wof:placetype":"venue"
},
  "geometry": {"coordinates":[9.4395151138,46.6937904358],"type":"Point"}
}