{
  "type": "Feature",
  "properties": {
    "iso:country":"CH",
    "sg:address":"Rue Du Temple 3",
    "sg:city":"Fribourg",
    "sg:orig_category":"Detailhandel mit Geschenkartikeln U Souvenirs Grosshandel mit Textilien",
    "sg:phone":"+41 26 322 88 92",
    "sg:postcode":"1700",
    "sg:province":"Fribourg",
    "wof:name":"Outsider Sportswear Sa Boutique Tat-too",
    "wof:placetype":"venue"
},
  "geometry": {"coordinates":[7.1538820267,46.8044662476],"type":"Point"}
}