{
  "type": "Feature",
  "properties": {
    "iso:country":"CH",
    "sg:address":"Eiweg 12",
    "sg:city":"Gelterkinden",
    "sg:orig_category":"Handel mit Automobilen",
    "sg:phone":"+41 61 981 69 19",
    "sg:postcode":"4460",
    "sg:province":"Basel-Landschaft",
    "wof:name":"Surer Auto Und Ersatzteil-handel",
    "wof:placetype":"venue"
},
  "geometry": {"coordinates":[7.844274044,47.4658088684],"type":"Point"}
}