{
  "type": "Feature",
  "properties": {
    "iso:country":"CH",
    "sg:address":"Lavizzari Via 3",
    "sg:city":"Lugano",
    "sg:orig_category":"Vermietung U Verpachtung von eigenen Immobilien",
    "sg:phone":"+41 91 922 68 62",
    "sg:postcode":"6900",
    "sg:province":"Ticino",
    "wof:name":"Apagest Holding Ag",
    "wof:placetype":"venue"
},
  "geometry": {"coordinates":[8.9580106735,46.0059661865],"type":"Point"}
}