{
  "type": "Feature",
  "properties": {
    "iso:country":"CH",
    "sg:address":"Bahnhofstrasse 4",
    "sg:city":"Widnau",
    "sg:orig_category":"Kosmetikinstitute",
    "sg:phone":"+41 71 722 10 77",
    "sg:postcode":"9443",
    "sg:province":"St. Gallen",
    "wof:name":"Strauss Coiffure Gmbh",
    "wof:placetype":"venue"
},
  "geometry": {"coordinates":[9.6292648315,47.4076538086],"type":"Point"}
}