{
  "type": "Feature",
  "properties": {
    "iso:country":"CH",
    "sg:address":"Grynaustrasse 1",
    "sg:city":"Uznach",
    "sg:orig_category":"Aktivit\u00e4ten der Krankenschwestern U Hebammen, Hauspflege Organisationen des Gesundheitswesen",
    "sg:phone":"+41 55 280 31 60",
    "sg:postcode":"8730",
    "sg:province":"St. Gallen",
    "wof:name":"Spitex Gemeindekrankenpflege",
    "wof:placetype":"venue"
},
  "geometry": {"coordinates":[8.984109,47.224403],"type":"Point"}
}