{
  "type": "Feature",
  "properties": {
    "iso:country":"CH",
    "sg:address":"Jurastrasse 20 4600 Olten. Postfach",
    "sg:city":"Olten",
    "sg:orig_category":"Wirtschaftspr\u00fcfung, Steuerberatung U Treuhand",
    "sg:phone":"+41 55 442 32 01",
    "sg:postcode":"4601",
    "sg:province":"Solothurn",
    "wof:name":"Vettiger Treuhand Ag",
    "wof:placetype":"venue"
},
  "geometry": {"coordinates":[8.8636655807,47.1902389526],"type":"Point"}
}