{
  "type": "Feature",
  "properties": {
    "iso:country":"CH",
    "sg:address":"Stockerhof",
    "sg:city":"Z\u00fcrich",
    "sg:orig_category":"Kantonalbanken",
    "sg:phone":"+41 12834848",
    "sg:postcode":"8002",
    "sg:province":"Z\u00fcrich",
    "wof:name":"Basler Kantonalbank",
    "wof:placetype":"venue"
},
  "geometry": {"coordinates":[8.5338163376,47.3695068359],"type":"Point"}
}