{
  "type": "Feature",
  "properties": {
    "iso:country":"CH",
    "sg:address":"Landstrasse 12",
    "sg:city":"W\u00e4ngi",
    "sg:orig_category":"Herstellung von elektrischen Lampen U Leuchten",
    "sg:phone":"+41 56 496 69 66",
    "sg:postcode":"9545",
    "sg:province":"Thurgau",
    "wof:name":"Bld Lichtberatungen, K. Diem",
    "wof:placetype":"venue"
},
  "geometry": {"coordinates":[8.3117723465,47.4017295837],"type":"Point"}
}