{
  "type": "Feature",
  "properties": {
    "iso:country":"CH",
    "sg:address":"Rue Du Petit-ch\u00eane 28",
    "sg:city":"Lausanne",
    "sg:classifiers":[
        {
            "category":"Restaurant",
            "type":"Food & Drink"
        }
    ],
    "sg:phone":"+41 21 312 77 38",
    "sg:postcode":"1003",
    "sg:province":"Vaud",
    "wof:name":"Caf\u00e9 Paradiso",
    "wof:placetype":"venue"
},
  "geometry": {"coordinates":[6.6311979294,46.5188102722],"type":"Point"}
}