{
  "type": "Feature",
  "properties": {
    "addr:full":"Rue Mauverney 22b Gland Vaud 1196",
    "addr:housenumber":"22b",
    "addr:postcode":"1196",
    "addr:street":"Rue Mauverney",
    "iso:country":"CH",
    "sg:address":"Rue Mauverney 22b",
    "sg:city":"Gland",
    "sg:orig_category":"Arztpraxen",
    "sg:phone":"+41 22 364 00 55",
    "sg:postcode":"1196",
    "sg:province":"Vaud",
    "wof:name":"Dr M\u00e9d. Francis Perruchoud M\u00e9decin Sp\u00e9cialiste Fmh",
    "wof:placetype":"venue"
},
  "geometry": {"coordinates":[6.276158,46.417076],"type":"Point"}
}