{
  "type": "Feature",
  "properties": {
    "iso:country":"CH",
    "sg:address":"Place Du Village",
    "sg:city":"Anz\u00e8re",
    "sg:classifiers":[
        {
            "category":"Travel",
            "subcategory":"Hotels & Motels",
            "type":"Entertainment"
        }
    ],
    "sg:phone":"+41 27 399 16 16",
    "sg:postcode":"1972",
    "sg:province":"Valais",
    "sg:tags":[
        "hotels",
        "mit",
        "restaurant"
    ],
    "wof:name":"H\u00f4tel Zodiaque",
    "wof:placetype":"venue"
},
  "geometry": {"coordinates":[7.399851799,46.2983703613],"type":"Point"}
}