{
  "type": "Feature",
  "properties": {
    "iso:country":"CH",
    "sg:address":"Berninastrasse 61",
    "sg:city":"Z\u00fcrich",
    "sg:orig_category":"Unternehmensberatung",
    "sg:phone":"+41 13113877",
    "sg:postcode":"8057",
    "sg:province":"Z\u00fcrich",
    "wof:name":"Peter Bischof Managementberatung",
    "wof:placetype":"venue"
},
  "geometry": {"coordinates":[8.5446243286,47.4041900635],"type":"Point"}
}