{
  "type": "Feature",
  "properties": {
    "iso:country":"CH",
    "sg:address":"Kernstrasse 9",
    "sg:city":"Boll",
    "sg:orig_category":"Detailhandel mit Waren verschiedener Art, Hauptrichtung Nahrungsmittel",
    "sg:phone":"+41 56 664 16 89",
    "sg:postcode":"3067",
    "sg:province":"Bern",
    "wof:name":"Migros-markt",
    "wof:placetype":"venue"
},
  "geometry": {"coordinates":[8.3174819946,47.2825775146],"type":"Point"}
}