{
  "type": "Feature",
  "properties": {
    "iso:country":"CH",
    "sg:address":"Rue Des C\u00e8dres 3 1950 Sion Case Postale 950",
    "sg:city":"Sion",
    "sg:orig_category":"Reiseb\u00fcros Verkehrsverb\u00e4nde",
    "sg:phone":"+41 32 724 15 32",
    "sg:postcode":"1951",
    "sg:province":"Valais",
    "wof:name":"Touring-club Suisse Tcs Office & Agence De Voyages",
    "wof:placetype":"venue"
},
  "geometry": {"coordinates":[6.9368047714,46.9931716919],"type":"Point"}
}