{
  "type": "Feature",
  "properties": {
    "iso:country":"CH",
    "sg:address":"M\u00fcllackerstrasse 36",
    "sg:city":"Opfikon",
    "sg:orig_category":"Unclassifiable Establishments",
    "sg:postcode":"8152",
    "sg:province":"Z\u00fcrich",
    "wof:name":"Komtech Glattbrugg Ag",
    "wof:placetype":"venue"
},
  "geometry": {"coordinates":[8.5696563721,47.4363517761],"type":"Point"}
}