{
  "type": "Feature",
  "properties": {
    "iso:country":"CH",
    "sg:address":"Wiesentalstrasse 22 9242 Oberuzwil. Postfach",
    "sg:city":"Oberuzwil",
    "sg:orig_category":"Handelsvermittlung U Grosshandel",
    "sg:phone":"+41 71 952 65 56",
    "sg:postcode":"9242",
    "sg:province":"St. Gallen",
    "wof:name":"Peter Hofbauer",
    "wof:placetype":"venue"
},
  "geometry": {"coordinates":[9.1300821304,47.4321975708],"type":"Point"}
}