{
  "type": "Feature",
  "properties": {
    "iso:country":"CH",
    "sg:address":"Romont Rue De 20 1700 Fribourg. Postfach",
    "sg:city":"Freiburg",
    "sg:orig_category":"Non-Classified Establishments",
    "sg:phone":"+41 71 744 34 07",
    "sg:postcode":"1700",
    "sg:province":"Fribourg",
    "wof:name":"Nordholz Ag",
    "wof:placetype":"venue"
},
  "geometry": {"coordinates":[9.6322307587,47.4504432678],"type":"Point"}
}