{
  "type": "Feature",
  "properties": {
    "addr:full":"Route Des Ormonts Leysin Vaud 1854",
    "addr:postcode":"1854",
    "addr:street":"Route Des Ormonts",
    "iso:country":"CH",
    "sg:address":"Route Des Ormonts",
    "sg:city":"Leysin",
    "sg:classifiers":[
        {
            "category":"Bars & Pubs",
            "type":"Food & Drink"
        }
    ],
    "sg:phone":"+41 24 494 14 95",
    "sg:postcode":"1854",
    "sg:province":"Vaud",
    "wof:name":"Bar Le Braconnier",
    "wof:placetype":"venue"
},
  "geometry": {"coordinates":[7.014009,46.34211],"type":"Point"}
}