{
  "type": "Feature",
  "properties": {
    "iso:country":"CH",
    "sg:address":"Hirschengutstrasse 22",
    "sg:city":"Weesen",
    "sg:orig_category":"Institutionen f\u00fcr Behinderte",
    "sg:phone":"+41 55 616 19 14",
    "sg:postcode":"8872",
    "sg:province":"St. Gallen",
    "wof:name":"Behindertenheim St.josef",
    "wof:placetype":"venue"
},
  "geometry": {"coordinates":[9.1064805984,47.1377792358],"type":"Point"}
}