{
  "type": "Feature",
  "properties": {
    "iso:country":"CH",
    "sg:address":"Rietstrasse 35",
    "sg:city":"Glattbrugg",
    "sg:orig_category":"Interessenvertretungen",
    "sg:phone":"+41 18103343",
    "sg:postcode":"8152",
    "sg:province":"Z\u00fcrich",
    "wof:name":"Aopa-switzerland, Flugzeughalter Und Pilotenverband.",
    "wof:placetype":"venue"
},
  "geometry": {"coordinates":[8.5664997101,47.4377784729],"type":"Point"}
}