{
  "type": "Feature",
  "properties": {
    "iso:country":"CH",
    "sg:address":"Grabenstrasse 57 8500 Frauenfeld. Postfach",
    "sg:city":"Frauenfeld",
    "sg:orig_category":"RESTAURANTS: TEA-ROOMS",
    "sg:postcode":"8500",
    "sg:province":"Thurgau",
    "wof:name":"Clagi Sa",
    "wof:placetype":"venue"
},
  "geometry": {"coordinates":[8.9657831192,46.0105056763],"type":"Point"}
}