{
  "type": "Feature",
  "properties": {
    "iso:country":"CH",
    "sg:address":"Place De L'europe 7 1003 Lausanne Case Postale 3145",
    "sg:city":"Lausanne",
    "sg:orig_category":"Architektur U Ingenieurb\u00fcros",
    "sg:phone":"+41 21 310 84 10",
    "sg:postcode":"1002",
    "sg:province":"Vaud",
    "wof:name":"Kbs \u00e9tudes Ing\u00e9nieurs Conseils S.a.",
    "wof:placetype":"venue"
},
  "geometry": {"coordinates":[6.63045,46.519989],"type":"Point"}
}