{
  "type": "Feature",
  "properties": {
    "iso:country":"CH",
    "sg:address":"Via Roncaglia",
    "sg:city":"Novazzano",
    "sg:orig_category":"Herstellung von Kunststoffwaren Herstellung von Teilen U Zubeh\u00f6r f\u00fcr Automobile",
    "sg:phone":"+41 91 683 93 23",
    "sg:postcode":"6883",
    "sg:province":"Ticino",
    "wof:name":"Foggini Sa",
    "wof:placetype":"venue"
},
  "geometry": {"coordinates":[8.9951210022,45.8402671814],"type":"Point"}
}