{
  "type": "Feature",
  "properties": {
    "iso:country":"CH",
    "sg:address":"St. Gallerstrasse 79",
    "sg:city":"Winterthur",
    "sg:orig_category":"Sonstiger Grosshandel",
    "sg:phone":"+41 52 233 29 11",
    "sg:postcode":"8400",
    "sg:province":"Z\u00fcrich",
    "wof:name":"J. Caamano",
    "wof:placetype":"venue"
},
  "geometry": {"coordinates":[8.7441043854,47.4983444214],"type":"Point"}
}