{
  "type": "Feature",
  "properties": {
    "iso:country":"CH",
    "sg:address":"Reussstrasse 9",
    "sg:city":"Gisikon",
    "sg:orig_category":"Pensionskassen",
    "sg:phone":"+41 41 455 01 11",
    "sg:postcode":"6038",
    "sg:province":"Luzern",
    "wof:name":"Bvg-personalvorsorgestiftung Der Rag Reichenberger Ag Gisikon",
    "wof:placetype":"venue"
},
  "geometry": {"coordinates":[8.3981866837,47.1271362305],"type":"Point"}
}