{
  "type": "Feature",
  "properties": {
    "iso:country":"CH",
    "sg:address":"Kirchweg 3",
    "sg:city":"Waltenschwil",
    "sg:orig_category":"Vermietung U Verpachtung von eigenen Immobilien Vermittlung von Immobilien",
    "sg:phone":"+41 56 622 01 21",
    "sg:postcode":"5622",
    "sg:province":"Aargau",
    "wof:name":"K\u00e4gi & Killer",
    "wof:placetype":"venue"
},
  "geometry": {"coordinates":[8.301024437,47.3339157104],"type":"Point"}
}