{
  "type": "Feature",
  "properties": {
    "iso:country":"CH",
    "sg:address":"Rue Montsalvens 7/9",
    "sg:city":"Bulle",
    "sg:orig_category":"Detailhandel mit Brot, Back U S\u00fcsswaren",
    "sg:phone":"+41 26 919 83 93",
    "sg:postcode":"1630",
    "sg:province":"Fribourg",
    "wof:name":"Repond G. Sa Boulangerie-p\u00e2tisserie Et \u00e9picerie",
    "wof:placetype":"venue"
},
  "geometry": {"coordinates":[7.05538,46.614265],"type":"Point"}
}