{
  "type": "Feature",
  "properties": {
    "iso:country":"CH",
    "sg:address":"Lommiserstrasse 2",
    "sg:city":"W\u00e4ngi",
    "sg:orig_category":"Detailhandel mit Fleisch U Fleischwaren",
    "sg:phone":"+41 52 378 12 06",
    "sg:postcode":"9545",
    "sg:province":"Thurgau",
    "wof:name":"Metzgerei Egli Josef.",
    "wof:placetype":"venue"
},
  "geometry": {"coordinates":[8.9552202225,47.5008583069],"type":"Point"}
}