{
  "type": "Feature",
  "properties": {
    "iso:country":"CH",
    "sg:address":"Viale Sartori 3 6512 Giubiasco. Postfach",
    "sg:city":"Giubiasco",
    "sg:orig_category":"Detailhandel mit Haustieren U zoologischem Bedarf Fachdetailhandel in Verkaufsr\u00e4umen",
    "sg:phone":"+41 91 857 72 91",
    "sg:postcode":"6512",
    "sg:province":"Ticino",
    "wof:name":"Miami Aquarium Di Berchtold Daniela Vendita Pesci, Acquari Ed Accessori",
    "wof:placetype":"venue"
},
  "geometry": {"coordinates":[9.0134744644,46.1746749878],"type":"Point"}
}