{
  "type": "Feature",
  "properties": {
    "iso:country":"CH",
    "sg:address":"Hof 9620 Lichtensteig. Postfach 42",
    "sg:city":"Lichtensteig",
    "sg:orig_category":"Herstellung von Besen U B\u00fcrsten",
    "sg:phone":"+41 71 988 29 29",
    "sg:postcode":"9620",
    "sg:province":"St. Gallen",
    "wof:name":"A+b B\u00fcrsten-technik Ag",
    "wof:placetype":"venue"
},
  "geometry": {"coordinates":[9.0867376328,47.3248672485],"type":"Point"}
}