{
  "type": "Feature",
  "properties": {
    "iso:country":"CH",
    "sg:address":"Poststrasse 2 4410 Liestal. Postfach",
    "sg:city":"Liestal",
    "sg:classifiers":[
        {
            "category":"Bars & Pubs",
            "type":"Food & Drink"
        }
    ],
    "sg:phone":"+41 41 871 05 05",
    "sg:postcode":"4410",
    "sg:province":"Basel-Landschaft",
    "sg:tags":[
        "caf\u00e9s",
        "tea-rooms",
        "konditoreien"
    ],
    "wof:name":"Caf\u00e9 Central",
    "wof:placetype":"venue"
},
  "geometry": {"coordinates":[8.6443738937,46.8822174072],"type":"Point"}
}