{
  "type": "Feature",
  "properties": {
    "iso:country":"CH",
    "sg:address":"Hauptstrasse 20 8280 Kreuzlingen. Postfach",
    "sg:city":"Kreuzlingen",
    "sg:orig_category":"Instandhaltung U Reparatur von Automobilen",
    "sg:postcode":"8280",
    "sg:province":"Thurgau",
    "wof:name":"Carrosserie-spritzwerk Gremlich",
    "wof:placetype":"venue"
},
  "geometry": {"coordinates":[9.1735544205,47.652671814],"type":"Point"}
}