{
  "type": "Feature",
  "properties": {
    "iso:country":"CH",
    "sg:address":"Alfred-schindlerstrasse 25",
    "sg:city":"Ebikon",
    "sg:orig_category":"Autogaragen",
    "sg:phone":"+41 17504969",
    "sg:postcode":"6030",
    "sg:province":"Luzern",
    "wof:name":"Cartek Gmbh Garage",
    "wof:placetype":"venue"
},
  "geometry": {"coordinates":[8.440954,47.415848],"type":"Point"}
}