{
  "type": "Feature",
  "properties": {
    "iso:country":"CH",
    "sg:address":"Route D'echallens 5",
    "sg:city":"Romanel-s-lausanne",
    "sg:orig_category":"Fachdetailhandel mit pharmazeutischen Produkten",
    "sg:phone":"+41 21 646 64 28",
    "sg:postcode":"1032",
    "sg:province":"Vaud",
    "wof:name":"Pharmacie Du Bourg, Guanter Marie-th\u00e9r\u00e8se",
    "wof:placetype":"venue"
},
  "geometry": {"coordinates":[6.6049871445,46.5690307617],"type":"Point"}
}