{
  "type": "Feature",
  "properties": {
    "iso:country":"CH",
    "sg:address":"Obermoosstrasse 64",
    "sg:city":"Boll",
    "sg:orig_category":"Unternehmensberatung",
    "sg:phone":"+41 31 839 97 08",
    "sg:postcode":"3067",
    "sg:province":"Bern",
    "wof:name":"Schaer & Gerber Gmbh",
    "wof:placetype":"venue"
},
  "geometry": {"coordinates":[7.5388541222,46.9591331482],"type":"Point"}
}