{
  "type": "Feature",
  "properties": {
    "iso:country":"CH",
    "sg:address":"Rue Du Ch\u00e2teau 15 2022 Bevaix Case Postale 440",
    "sg:city":"Bevaix",
    "sg:orig_category":"Grosshandel mit Getreide, Saatgut U Futtermitteln",
    "sg:phone":"+41 79 249 04 28",
    "sg:postcode":"2022",
    "sg:province":"Neuch\u00e2tel",
    "wof:name":"Agence Agricole Dubois & Cie Sa Fourrages, Engrais Etc; Comm.",
    "wof:placetype":"venue"
},
  "geometry": {"coordinates":[6.8120670319,46.9269943237],"type":"Point"}
}