{
  "type": "Feature",
  "properties": {
    "iso:country":"CH",
    "sg:address":"Hauptstrasse 90",
    "sg:city":"Kriegstetten",
    "sg:orig_category":"Grosshandel mit Datenverarbeitungsger\u00e4ten Grosshandel mit Software",
    "sg:phone":"+41 32 631 20 51",
    "sg:postcode":"4566",
    "sg:province":"Solothurn",
    "wof:name":"Vemag Computer Ag",
    "wof:placetype":"venue"
},
  "geometry": {"coordinates":[7.6508030891,47.2314567566],"type":"Point"}
}