{
  "type": "Feature",
  "properties": {
    "iso:country":"CH",
    "sg:address":"3723",
    "sg:city":"Kiental",
    "sg:classifiers":[
        {
            "category":"Travel",
            "subcategory":"Hotels & Motels",
            "type":"Entertainment"
        }
    ],
    "sg:phone":"+41 33 676 16 46",
    "sg:postcode":"3723",
    "sg:province":"Bern",
    "sg:tags":[
        "hotels",
        "mit",
        "restaurant"
    ],
    "wof:name":"Hotel Chalet",
    "wof:placetype":"venue"
},
  "geometry": {"coordinates":[7.7233400345,46.5879707336],"type":"Point"}
}