{
  "type": "Feature",
  "properties": {
    "iso:country":"CH",
    "sg:address":"Sensemattstrasse 22",
    "sg:city":"Th\u00f6rishaus",
    "sg:orig_category":"Gasth\u00f6fe/Gasth\u00e4user mit Restaurant",
    "sg:phone":"+41 71 944 15 14",
    "sg:postcode":"3174",
    "sg:province":"Bern",
    "wof:name":"Gasthof Sternen",
    "wof:placetype":"venue"
},
  "geometry": {"coordinates":[9.1090955734,47.4736671448],"type":"Point"}
}