{
  "type": "Feature",
  "properties": {
    "iso:country":"CH",
    "sg:address":"Bruni\u00e8re Rue De La",
    "sg:city":"St-l\u00e9onard",
    "sg:orig_category":"Sanit\u00e4r, Heizungs U L\u00fcftungsinstallation",
    "sg:phone":"+41 55 225 46 10",
    "sg:postcode":"1958",
    "sg:province":"Valais",
    "wof:name":"Lengg F. Energiespar-systeme",
    "wof:placetype":"venue"
},
  "geometry": {"coordinates":[8.8291730881,47.2207374573],"type":"Point"}
}