{
  "type": "Feature",
  "properties": {
    "iso:country":"CH",
    "sg:address":"Sandstrasse 90",
    "sg:city":"Gebenstorf",
    "sg:orig_category":"Organisationen des Gesundheitswesen",
    "sg:phone":"+41 56 223 12 84",
    "sg:postcode":"5412",
    "sg:province":"Aargau",
    "wof:name":"Samariterverein",
    "wof:placetype":"venue"
},
  "geometry": {"coordinates":[8.2465639114,47.4788169861],"type":"Point"}
}