{
  "type": "Feature",
  "properties": {
    "iso:country":"CH",
    "sg:address":"Nordstrasse 19",
    "sg:city":"Z\u00fcrich",
    "sg:orig_category":"Binnenschiffahrt",
    "sg:postcode":"8006",
    "sg:province":"Z\u00fcrich",
    "wof:name":"Sc Seacharter Ltd",
    "wof:placetype":"venue"
},
  "geometry": {"coordinates":[8.538919,47.384499],"type":"Point"}
}