{
  "type": "Feature",
  "properties": {
    "addr:full":"Bernex En Combes 33 Bernex Gen\u00e8ve 1233",
    "addr:housenumber":"33",
    "addr:postcode":"1233",
    "addr:street":"Bernex",
    "iso:country":"CH",
    "sg:address":"Bernex En Combes 33",
    "sg:city":"Bernex",
    "sg:orig_category":"Datenverarbeitungsdienste",
    "sg:phone":"+41 22 757 51 92",
    "sg:postcode":"1233",
    "sg:province":"Gen\u00e8ve",
    "wof:name":"Aide Assist.informatique Pr Le D\u00e9veloppement & L'enseignement",
    "wof:placetype":"venue"
},
  "geometry": {"coordinates":[6.081485,46.178623],"type":"Point"}
}