{
  "type": "Feature",
  "properties": {
    "addr:full":"Chemin De La Chaudabronnaz 1 Morges Vaud 1110",
    "addr:housenumber":"1",
    "addr:postcode":"1110",
    "addr:street":"Chemin De La Chaudabronnaz",
    "iso:country":"CH",
    "sg:address":"Chemin De La Chaudabronnaz 1",
    "sg:city":"Morges",
    "sg:orig_category":"Architekturb\u00fcros",
    "sg:phone":"+41 21 803 20 70",
    "sg:postcode":"1110",
    "sg:province":"Vaud",
    "wof:name":"Jo\u00ebl Carrupt Bureau D'architecture",
    "wof:placetype":"venue"
},
  "geometry": {"coordinates":[6.505846,46.521111],"type":"Point"}
}