{
  "type": "Feature",
  "properties": {
    "iso:country":"CH",
    "sg:address":"Hafenstrasse 87 4127 Birsfelden. Postfach 628",
    "sg:city":"Birsfelden",
    "sg:orig_category":"Herstellung von Tanks U Sammelbeh\u00e4ltern aus Metall",
    "sg:phone":"+41 61 373 34 00",
    "sg:postcode":"4127",
    "sg:province":"Basel-Landschaft",
    "wof:name":"Peacock Container B.v., Rotterdam, Zweigniederlassung Birsfelden",
    "wof:placetype":"venue"
},
  "geometry": {"coordinates":[7.639111042,47.5547103882],"type":"Point"}
}