{
  "type": "Feature",
  "properties": {
    "iso:country":"CH",
    "sg:address":"Oberwolfhauserstrasse 9",
    "sg:city":"Wolfhausen",
    "sg:classifiers":[
        {
            "category":"Community Center",
            "subcategory":"Social",
            "type":"Public Place"
        }
    ],
    "sg:phone":"+41 55 253 63 63",
    "sg:postcode":"8633",
    "sg:province":"Z\u00fcrich",
    "sg:tags":[
        "core",
        "foam",
        "cushion",
        "made"
    ],
    "wof:name":"Foam Partner Fritz Nauer Ag",
    "wof:placetype":"venue"
},
  "geometry": {"coordinates":[8.795697,47.257267],"type":"Point"}
}