{
  "type": "Feature",
  "properties": {
    "iso:country":"CH",
    "sg:address":"Poststrasse 23",
    "sg:city":"St.gallen",
    "sg:orig_category":"Erbringung von Dienstleistungen f\u00fcr Unternehmen",
    "sg:postcode":"9000",
    "sg:province":"St. Gallen",
    "wof:name":"Mcn Millennium Communication Network Gmbh",
    "wof:placetype":"venue"
},
  "geometry": {"coordinates":[9.3718137741,47.4241065979],"type":"Point"}
}