{
  "type": "Feature",
  "properties": {
    "iso:country":"CH",
    "sg:address":"Diebold-schilling-strasse 23a",
    "sg:city":"Bettlach",
    "sg:orig_category":"Unclassifiable Establishments",
    "sg:phone":"+41 32 645 26 43",
    "sg:postcode":"2544",
    "sg:province":"Solothurn",
    "wof:name":"Etiketta, Boillat",
    "wof:placetype":"venue"
},
  "geometry": {"coordinates":[7.419462204,47.1976051331],"type":"Point"}
}