{
  "type": "Feature",
  "properties": {
    "iso:country":"CH",
    "sg:address":"Chemin De La Tourelle 2-4",
    "sg:city":"Gen\u00e8ve",
    "sg:orig_category":"Detailhandel mit Waren verschiedener Art, Hauptrichtung Nahrungsmittel",
    "sg:phone":"+41 32 751 58 48",
    "sg:postcode":"1209",
    "sg:province":"Gen\u00e8ve",
    "wof:name":"Migros",
    "wof:placetype":"venue"
},
  "geometry": {"coordinates":[7.0889310837,47.0617485046],"type":"Point"}
}