{
  "type": "Feature",
  "properties": {
    "iso:country":"CH",
    "sg:address":"Poststrasse 14a",
    "sg:city":"Jenins",
    "sg:orig_category":"Rebbau",
    "sg:phone":"+41 81 302 21 79",
    "sg:postcode":"7307",
    "sg:province":"Graubunden",
    "wof:name":"Luzi Jenny Weinbau",
    "wof:placetype":"venue"
},
  "geometry": {"coordinates":[9.5577096939,47.0004615784],"type":"Point"}
}