{
  "type": "Feature",
  "properties": {
    "iso:country":"CH",
    "sg:address":"Oberstrasse 149",
    "sg:city":"St.gallen",
    "sg:orig_category":"Strassenbau",
    "sg:phone":"+41 71 686 89 49",
    "sg:postcode":"9000",
    "sg:province":"St. Gallen",
    "wof:name":"H\u00fcppi Ag Strassen-& Tiefbau",
    "wof:placetype":"venue"
},
  "geometry": {"coordinates":[9.1986970901,47.6425857544],"type":"Point"}
}