{
  "type": "Feature",
  "properties": {
    "iso:country":"CH",
    "sg:address":"Unterdorfstrasse 10 3612 Steffisburg. Postfach",
    "sg:city":"Steffisburg",
    "sg:orig_category":"Grosshandel mit sonstigen Halbwaren",
    "sg:phone":"+41 55 241 31 95",
    "sg:postcode":"3613",
    "sg:province":"Bern",
    "wof:name":"Ipc Packaging Ag Verpackungsartikel; Fabrikation, Handel",
    "wof:placetype":"venue"
},
  "geometry": {"coordinates":[8.8465433121,47.2546615601],"type":"Point"}
}