{
  "type": "Feature",
  "properties": {
    "iso:country":"CH",
    "sg:address":"Binzstrasse 18",
    "sg:city":"Z\u00fcrich",
    "sg:orig_category":"Offsetdruck Satzherstellung U Reproduktion",
    "sg:phone":"+41 14624921",
    "sg:postcode":"8045",
    "sg:province":"Z\u00fcrich",
    "wof:name":"Von K\u00e4nel & Co Ag, Mediatechnik",
    "wof:placetype":"venue"
},
  "geometry": {"coordinates":[8.5150213242,47.3627510071],"type":"Point"}
}