{
  "type": "Feature",
  "properties": {
    "iso:country":"CH",
    "sg:address":"Route De L'alliaz",
    "sg:city":"Blonay",
    "sg:orig_category":"RESTAURANTS: TEA-ROOMS",
    "sg:phone":"+41 21 943 12 83",
    "sg:postcode":"1807",
    "sg:province":"Vaud",
    "wof:name":"Caf\u00e9 Les Foug\u00e8res",
    "wof:placetype":"venue"
},
  "geometry": {"coordinates":[6.9268097878,46.4811401367],"type":"Point"}
}