{
  "type": "Feature",
  "properties": {
    "iso:country":"CH",
    "sg:address":"Raistrasse 1",
    "sg:city":"Bergdietikon",
    "sg:orig_category":"Grosshandel mit Software",
    "sg:phone":"+41 31 378 77 87",
    "sg:postcode":"8962",
    "sg:province":"Aargau",
    "wof:name":"Superbase Developers Gmbh Softwarevertrieb",
    "wof:placetype":"venue"
},
  "geometry": {"coordinates":[7.4314570427,46.9408226013],"type":"Point"}
}