{
  "type": "Feature",
  "properties": {
    "addr:full":"Sternenhaldenstrasse 8 8712 St\u00e4fa. Postfach St\u00e4fa Z\u00fcrich 8712",
    "addr:housenumber":"8",
    "addr:postcode":"8712;8712",
    "addr:street":"Sternenhaldenstrasse;Postfach Staefa Zuerich",
    "iso:country":"CH",
    "sg:address":"Sternenhaldenstrasse 8 8712 St\u00e4fa. Postfach",
    "sg:city":"St\u00e4fa",
    "sg:orig_category":"Architektur U Ingenieurb\u00fcros",
    "sg:phone":"+41 19266622",
    "sg:postcode":"8712",
    "sg:province":"Z\u00fcrich",
    "wof:name":"Meyer Ag Elektro-ingenieur-b\u00fcro",
    "wof:placetype":"venue"
},
  "geometry": {"coordinates":[8.736983,47.235882],"type":"Point"}
}