{
  "type": "Feature",
  "properties": {
    "iso:country":"CH",
    "sg:address":"Rue P.-a.-de-faucigny 7",
    "sg:city":"Fribourg",
    "sg:orig_category":"Wohnheime f\u00fcr Kinder U Jugendliche",
    "sg:phone":"+41 26 424 46 44",
    "sg:postcode":"1700",
    "sg:province":"Fribourg",
    "wof:name":"Foyer Bel-praz Pour \u00e9tudiants",
    "wof:placetype":"venue"
},
  "geometry": {"coordinates":[7.1569890976,46.7959289551],"type":"Point"}
}