{
  "type": "Feature",
  "properties": {
    "iso:country":"CH",
    "sg:address":"Luzernstrasse 9",
    "sg:city":"Huttwil",
    "sg:orig_category":"Herstellung von Reiseartikeln, Leder U Sattlerwaren Verlegen von Fussboden",
    "sg:phone":"+41 62 962 18 54",
    "sg:postcode":"4950",
    "sg:province":"Bern",
    "wof:name":"Stephan S\u00e4gesser Innendekoration/sattlerei",
    "wof:placetype":"venue"
},
  "geometry": {"coordinates":[7.8513131142,47.1134185791],"type":"Point"}
}