{
  "type": "Feature",
  "properties": {
    "iso:country":"CH",
    "sg:address":"Mythenquai 2",
    "sg:city":"Zurich",
    "sg:classifiers":[
        {
            "category":"Banks & Credit Unions",
            "subcategory":"Financial Services",
            "type":"Services"
        }
    ],
    "sg:phone":"+41 4112052121",
    "sg:postcode":"8022",
    "sg:province":"Z\u00fcrich",
    "sg:tags":[
        "banking",
        "finance",
        "insurance"
    ],
    "wof:name":"Zurich Versicherungs - Gesellschaft",
    "wof:placetype":"venue"
},
  "geometry": {"coordinates":[8.535033,47.362377],"type":"Point"}
}