{
  "type": "Feature",
  "properties": {
    "iso:country":"CH",
    "sg:address":"Brandschenkestrasse 178",
    "sg:city":"Z\u00fcrich",
    "sg:orig_category":"Non-Classified Establishments",
    "sg:postcode":"8002",
    "sg:province":"Z\u00fcrich",
    "wof:name":"Nomor Riedless Beteiligungen Ag",
    "wof:placetype":"venue"
},
  "geometry": {"coordinates":[8.5262336731,47.3624992371],"type":"Point"}
}