{
  "type": "Feature",
  "properties": {
    "iso:country":"CH",
    "sg:address":"Schutzengelstrasse 34f",
    "sg:city":"Baar",
    "sg:orig_category":"Gesundheitswesen",
    "sg:postcode":"6340",
    "sg:province":"Zug",
    "wof:name":"Markert Christian Dr. Med., Sitz Und Liegeberatungen",
    "wof:placetype":"venue"
},
  "geometry": {"coordinates":[8.5359869003,47.1978034973],"type":"Point"}
}