{
  "type": "Feature",
  "properties": {
    "iso:country":"CH",
    "sg:address":"Wasenstrasse 9 2500 Biel/bienne. Postfach",
    "sg:city":"Biel/bienne",
    "sg:orig_category":"Wirtschaftsverb\u00e4nde Industrie, Handel and Gewerbe",
    "sg:phone":"+41 32 322 50 22",
    "sg:postcode":"2501",
    "sg:province":"Bern",
    "wof:name":"Elektroverband Biel & Umgebung",
    "wof:placetype":"venue"
},
  "geometry": {"coordinates":[7.255879879,47.1450271606],"type":"Point"}
}