{
  "type": "Feature",
  "properties": {
    "iso:country":"CH",
    "sg:address":"Bahnhofstrasse 26 8304 Wallisellen. Postfach",
    "sg:city":"Wallisellen",
    "sg:orig_category":"Pensionskassen",
    "sg:phone":"+41 62 929 14 63",
    "sg:postcode":"8304",
    "sg:province":"Z\u00fcrich",
    "wof:name":"Personalf\u00fcrsorgestiftung Der Firma Gugelmann & Cie Ag",
    "wof:placetype":"venue"
},
  "geometry": {"coordinates":[7.8092489243,47.2483177185],"type":"Point"}
}