{
  "type": "Feature",
  "properties": {
    "iso:country":"CH",
    "sg:address":"Via Patrizia 3",
    "sg:city":"Ascona",
    "sg:classifiers":[
        {
            "category":"Health Services",
            "subcategory":"Medical Lab",
            "type":"Services"
        }
    ],
    "sg:phone":"+41 91 791 02 91",
    "sg:postcode":"6612",
    "sg:province":"Ticino",
    "sg:tags":[
        "appliance",
        "system"
    ],
    "wof:name":"Comprys Sa",
    "wof:placetype":"venue"
},
  "geometry": {"coordinates":[8.7817440033,46.1532745361],"type":"Point"}
}