{
  "type": "Feature",
  "properties": {
    "iso:country":"CH",
    "sg:address":"Kalkbreitestrasse 117 8036 Z\u00fcrich. Postfach 8036",
    "sg:city":"Z\u00fcrich",
    "sg:orig_category":"Orchester, Ch\u00f6re, Musiker",
    "sg:phone":"+41 22 311 82 09",
    "sg:postcode":"8036",
    "sg:province":"Z\u00fcrich",
    "wof:name":"Musique Municipale De La Ville De Gen\u00e8ve",
    "wof:placetype":"venue"
},
  "geometry": {"coordinates":[6.1486120224,46.1977996826],"type":"Point"}
}