{
  "type": "Feature",
  "properties": {
    "iso:country":"CH",
    "sg:address":"Wilerstrasse 10",
    "sg:city":"Sirnach",
    "sg:orig_category":"K\u00fcnstlerische U schriftstellerische T\u00e4tigkeiten U Darbietungen",
    "sg:phone":"+41 71 966 22 48",
    "sg:postcode":"8370",
    "sg:province":"Thurgau",
    "wof:name":"M. & E. Pfister, Kunsthandwerk-atelier",
    "wof:placetype":"venue"
},
  "geometry": {"coordinates":[8.9990720749,47.4619102478],"type":"Point"}
}