{
  "type": "Feature",
  "properties": {
    "iso:country":"CH",
    "sg:address":"Pelikanweg 8",
    "sg:city":"Basel",
    "sg:orig_category":"Vermittlung von Immobilien Verwaltung von Immobilien",
    "sg:phone":"+41 61 281 38 69",
    "sg:postcode":"4054",
    "sg:province":"Basel-Stadt",
    "wof:name":"Rolf Haberth\u00fcr Immobilien-treuhand",
    "wof:placetype":"venue"
},
  "geometry": {"coordinates":[7.5811300278,47.5499000549],"type":"Point"}
}