{
  "type": "Feature",
  "properties": {
    "iso:country":"CH",
    "sg:address":"Gerbergasse 14",
    "sg:city":"Basel",
    "sg:orig_category":"Softwareentwicklung U beratung",
    "sg:postcode":"4001",
    "sg:province":"Basel-Stadt",
    "wof:name":"Ksf-engineering Schmitz-f\u00fcglistaller Klara",
    "wof:placetype":"venue"
},
  "geometry": {"coordinates":[8.2932138443,47.4866981506],"type":"Point"}
}