{
  "type": "Feature",
  "properties": {
    "iso:country":"CH",
    "sg:address":"Habsburgstrasse 33 8964 Rudolfstetten. Postfach",
    "sg:city":"Rudolfstetten",
    "sg:orig_category":"Unclassifiable Establishments",
    "sg:postcode":"8964",
    "sg:province":"Aargau",
    "wof:name":"Prime Gardening - Haamans Gartenpflege U. Unterhalt Usw",
    "wof:placetype":"venue"
},
  "geometry": {"coordinates":[8.3705320358,47.3623657227],"type":"Point"}
}