{
  "type": "Feature",
  "properties": {
    "addr:full":"Alpenstrasse 3 Amriswil Thurgau 8580",
    "addr:housenumber":"3",
    "addr:postcode":"8580",
    "addr:street":"Alpenstrasse",
    "iso:country":"CH",
    "sg:address":"Alpenstrasse 3",
    "sg:city":"Amriswil",
    "sg:orig_category":"Bauspenglerei Sanit\u00e4rinstallation",
    "sg:phone":"+41 71 414 07 70",
    "sg:postcode":"8580",
    "sg:province":"Thurgau",
    "wof:name":"Str\u00e4ssle Installationen Ag",
    "wof:placetype":"venue"
},
  "geometry": {"coordinates":[9.305182,47.550575],"type":"Point"}
}