{
  "type": "Feature",
  "properties": {
    "iso:country":"CH",
    "sg:address":"4802",
    "sg:city":"Strengelbach",
    "sg:orig_category":"Organisationen des Gesundheitswesen",
    "sg:phone":"+41 62 751 52 58",
    "sg:postcode":"4802",
    "sg:province":"Aargau",
    "wof:name":"Samariterverein Strengelbach",
    "wof:placetype":"venue"
},
  "geometry": {"coordinates":[7.92979002,47.2783660889],"type":"Point"}
}