{
  "type": "Feature",
  "properties": {
    "iso:country":"CH",
    "sg:address":"Hauptstrasse 35",
    "sg:city":"Ziefen",
    "sg:orig_category":"Mechanik",
    "sg:phone":"+41 61 931 35 75",
    "sg:postcode":"4417",
    "sg:province":"Basel-Landschaft",
    "wof:name":"Hs Mechanik, Sch\u00fcrch Hans",
    "wof:placetype":"venue"
},
  "geometry": {"coordinates":[7.7151169777,47.4332618713],"type":"Point"}
}