{
  "type": "Feature",
  "properties": {
    "iso:country":"CH",
    "sg:address":"Im Ifang 12",
    "sg:city":"Altenrhein",
    "sg:orig_category":"Sonstiger spezialisierter Hoch U Tiefbau Test U Sondierbohrungen",
    "sg:phone":"+41 71 855 55 42",
    "sg:postcode":"9423",
    "sg:province":"St. Gallen",
    "wof:name":"Bohrtech Ag",
    "wof:placetype":"venue"
},
  "geometry": {"coordinates":[9.5569267273,47.4917068481],"type":"Point"}
}