{
  "type": "Feature",
  "properties": {
    "iso:country":"CH",
    "sg:address":"Oetwilerstrasse 44",
    "sg:city":"Dietikon",
    "sg:orig_category":"Sonstiger Grosshandel",
    "sg:postcode":"8953",
    "sg:province":"Z\u00fcrich",
    "wof:name":"Oare Enterprises",
    "wof:placetype":"venue"
},
  "geometry": {"coordinates":[8.3981294632,47.4096603394],"type":"Point"}
}