{
  "type": "Feature",
  "properties": {
    "iso:country":"CH",
    "sg:address":"En Combes",
    "sg:city":"Luins",
    "sg:orig_category":"Fernmeldedienste",
    "sg:phone":"+41 21 824 30 61",
    "sg:postcode":"1184",
    "sg:province":"Vaud",
    "wof:name":"Sdp Communications, Samuel David Pickens",
    "wof:placetype":"venue"
},
  "geometry": {"coordinates":[6.2708721161,46.4450836182],"type":"Point"}
}