{
  "type": "Feature",
  "properties": {
    "iso:country":"CH",
    "sg:address":"Blautraubenstrasse 2 8200 Schaffhausen. Postfach 207",
    "sg:city":"Schaffhausen",
    "sg:orig_category":"Allgemeiner Hoch U Tiefbau Allgemeiner Hochbau",
    "sg:phone":"+41 32 931 20 93",
    "sg:postcode":"8206",
    "wof:name":"Bieri Et Grisoni Sa, Succursale Du Locle",
    "wof:placetype":"venue"
},
  "geometry": {"coordinates":[6.745637,47.053261],"type":"Point"}
}