{
  "type": "Feature",
  "properties": {
    "iso:country":"CH",
    "sg:address":"K\u00f6rnerstrasse 1 8004 Z\u00fcrich. Postfach",
    "sg:city":"Z\u00fcrich",
    "sg:orig_category":"Herstellung von Radio U Fernsehger\u00e4ten sowie phono U videotechnischen Ger\u00e4ten",
    "sg:phone":"+41 12916004",
    "sg:postcode":"8004",
    "sg:province":"Z\u00fcrich",
    "wof:name":"Softridge Ag Multimedia-ger\u00e4te, Videospielsysteme Usw.; Handel",
    "wof:placetype":"venue"
},
  "geometry": {"coordinates":[8.5220499039,47.3738174438],"type":"Point"}
}