{
  "type": "Feature",
  "properties": {
    "iso:country":"CH",
    "sg:address":"5742",
    "sg:city":"K\u00f6lliken",
    "sg:orig_category":"Vorschulen, Kinderg\u00e4rten",
    "sg:phone":"+41 62 723 34 65",
    "sg:postcode":"5742",
    "sg:province":"Aargau",
    "wof:name":"Kindergarten",
    "wof:placetype":"venue"
},
  "geometry": {"coordinates":[8.0244512558,47.3365325928],"type":"Point"}
}