{
  "type": "Feature",
  "properties": {
    "iso:country":"CH",
    "sg:address":"Avenue De Pratifori 39",
    "sg:city":"Sion",
    "sg:orig_category":"Arztpraxen",
    "sg:phone":"+41 27 322 25 02",
    "sg:postcode":"1950",
    "sg:province":"Valais",
    "wof:name":"Dr M\u00e9d. Jacques Joliat M\u00e9decin G\u00e9n\u00e9raliste Fmh",
    "wof:placetype":"venue"
},
  "geometry": {"coordinates":[7.353608,46.230137],"type":"Point"}
}