{
  "type": "Feature",
  "properties": {
    "iso:country":"CH",
    "sg:address":"Luzernerstrasse 9",
    "sg:city":"Rotkreuz",
    "sg:orig_category":"Detailhandel mit Geschenkartikeln U Souvenirs",
    "sg:phone":"+41 41 790 22 54",
    "sg:postcode":"6343",
    "sg:province":"Zug",
    "wof:name":"Boutique Camaro F.j.besmer",
    "wof:placetype":"venue"
},
  "geometry": {"coordinates":[8.4269342422,47.1400527954],"type":"Point"}
}