{
  "type": "Feature",
  "properties": {
    "iso:country":"CH",
    "sg:address":"Neusetzi 1",
    "sg:city":"Oberflachs",
    "sg:orig_category":"Unternehmensberatung",
    "sg:phone":"+41 62 892 27 00",
    "sg:postcode":"5108",
    "sg:province":"Aargau",
    "wof:name":"Paroste Gmbh",
    "wof:placetype":"venue"
},
  "geometry": {"coordinates":[8.1301355362,47.4431533813],"type":"Point"}
}