{
  "type": "Feature",
  "properties": {
    "iso:country":"CH",
    "sg:address":"Via La Rossa",
    "sg:city":"Rancate",
    "sg:orig_category":"Unclassifiable Establishments",
    "sg:postcode":"6862",
    "sg:province":"Ticino",
    "wof:name":"Termozeta Sa",
    "wof:placetype":"venue"
},
  "geometry": {"coordinates":[8.9721879959,45.8865013123],"type":"Point"}
}