{
  "type": "Feature",
  "properties": {
    "iso:country":"CH",
    "sg:address":"L\u00f6wenstrasse 59",
    "sg:city":"Z\u00fcrich",
    "sg:orig_category":"Advokaturb\u00fcros Inkassob\u00fcros",
    "sg:phone":"+41 55 210 65 75",
    "sg:postcode":"8001",
    "sg:province":"Z\u00fcrich",
    "wof:name":"Dr.alfons Oswald Advokatur-& Inkassob\u00fcro",
    "wof:placetype":"venue"
},
  "geometry": {"coordinates":[8.822815,47.2313],"type":"Point"}
}