{
  "type": "Feature",
  "properties": {
    "addr:full":"Chemin Des Grandes-vignes 52 1242 Satigny Case Postale 35 Satigny Gen\u00e8ve 1242",
    "addr:housenumber":"52",
    "addr:postcode":"1242;35;1242",
    "addr:street":"Chemin Des Grandes-Vignes;Postale",
    "iso:country":"CH",
    "sg:address":"Chemin Des Grandes-vignes 52 1242 Satigny Case Postale 35",
    "sg:city":"Satigny",
    "sg:orig_category":"Architektur U Ingenieurb\u00fcros Elektrizit\u00e4tsversorgung",
    "sg:phone":"+41 22 753 15 07",
    "sg:postcode":"1242",
    "sg:province":"Gen\u00e8ve",
    "wof:name":"Simon Laszlo",
    "wof:placetype":"venue"
},
  "geometry": {"coordinates":[6.033461,46.211716],"type":"Point"}
}