{
  "type": "Feature",
  "properties": {
    "iso:country":"CH",
    "sg:address":"Lehngasse 78 E 3812 Wilderswil. Postfach 129",
    "sg:city":"Wilderswil",
    "sg:orig_category":"Sonstige pers\u00f6nliche Dienstleistungen",
    "sg:phone":"+41 33 823 66 14",
    "sg:postcode":"3812",
    "sg:province":"Bern",
    "wof:name":"Bvd Werner Sch\u00e4rer",
    "wof:placetype":"venue"
},
  "geometry": {"coordinates":[7.8673701286,46.6651268005],"type":"Point"}
}