{
  "type": "Feature",
  "properties": {
    "iso:country":"CH",
    "sg:address":"Chauvet Rue Michel- 3 1208 Gen\u00e8ve. Postfach",
    "sg:city":"Gen\u00e8ve",
    "sg:orig_category":"Finanzierungsinstitutionen",
    "sg:phone":"+41 22 818 31 31",
    "sg:postcode":"1208",
    "sg:province":"Gen\u00e8ve",
    "wof:name":"Societe Financiere Privee Sa",
    "wof:placetype":"venue"
},
  "geometry": {"coordinates":[6.1497969627,46.1992416382],"type":"Point"}
}