{
  "type": "Feature",
  "properties": {
    "iso:country":"CH",
    "sg:address":"Mirasole Via 1 6500 Bellinzona Casella Postale 1766",
    "sg:city":"Bellinzona",
    "sg:orig_category":"Kantinen",
    "sg:phone":"+41 91 825 89 47",
    "sg:postcode":"6500",
    "sg:province":"Ticino",
    "wof:name":"Lentini Services Sa",
    "wof:placetype":"venue"
},
  "geometry": {"coordinates":[9.0241193771,46.1944618225],"type":"Point"}
}