{
  "type": "Feature",
  "properties": {
    "iso:country":"CH",
    "sg:address":"1934 Bagnes. Postfach",
    "sg:city":"Montagnier",
    "sg:orig_category":"Stukkateurgewerbe, Gipserei U Verputzerei",
    "sg:postcode":"1934",
    "sg:province":"Valais",
    "wof:name":"Fellay Norbert",
    "wof:placetype":"venue"
},
  "geometry": {"coordinates":[7.2124481201,46.0804595947],"type":"Point"}
}