{
  "type": "Feature",
  "properties": {
    "iso:country":"CH",
    "sg:address":"Feldstrasse 6",
    "sg:city":"Aarburg",
    "sg:orig_category":"Gesundheitswesen",
    "sg:postcode":"4663",
    "sg:province":"Aargau",
    "wof:name":"Physiotherapie Broekman G.j.",
    "wof:placetype":"venue"
},
  "geometry": {"coordinates":[7.5610690117,46.9284439087],"type":"Point"}
}