{
  "type": "Feature",
  "properties": {
    "iso:country":"CH",
    "sg:address":"Wiesenweg 4",
    "sg:city":"Bassersdorf",
    "sg:orig_category":"Dienstleistungen im Gartenbau Kauf U Verkauf von Immobilien auf eigene Rechnung",
    "sg:phone":"+41 18603519",
    "sg:postcode":"8303",
    "sg:province":"Z\u00fcrich",
    "wof:name":"Z\u00fcrich-nord Liegenschaftenservice Gmbh",
    "wof:placetype":"venue"
},
  "geometry": {"coordinates":[8.6263504028,47.4415626526],"type":"Point"}
}