{
  "type": "Feature",
  "properties": {
    "iso:country":"CH",
    "sg:address":"Ringstrasse 18",
    "sg:city":"Neuenhof",
    "sg:orig_category":"Vermietung U Verpachtung von eigenen Immobilien Vermittlung von Immobilien",
    "sg:phone":"+41 56 410 00 80",
    "sg:postcode":"5432",
    "sg:province":"Aargau",
    "wof:name":"Phibera Ag",
    "wof:placetype":"venue"
},
  "geometry": {"coordinates":[8.3290786743,47.454284668],"type":"Point"}
}