{
  "type": "Feature",
  "properties": {
    "iso:country":"CH",
    "sg:address":"2554 Meinisberg. Postfach",
    "sg:city":"Meinisberg",
    "sg:orig_category":"Sportvereine Ballsport Tennis",
    "sg:phone":"+41 32 377 20 88",
    "sg:postcode":"2554",
    "sg:province":"Bern",
    "wof:name":"Tennisclub Meinisberg",
    "wof:placetype":"venue"
},
  "geometry": {"coordinates":[7.3528800011,47.1616401672],"type":"Point"}
}