{
  "type": "Feature",
  "properties": {
    "iso:country":"CH",
    "sg:address":"Rue De Neuch\u00e2tel 17",
    "sg:city":"Peseux",
    "sg:orig_category":"Instandhaltung U Reparatur von Automobilen",
    "sg:phone":"+41 32 731 47 55",
    "sg:postcode":"2034",
    "sg:province":"Neuch\u00e2tel",
    "wof:name":"Furrer Jean-claude",
    "wof:placetype":"venue"
},
  "geometry": {"coordinates":[6.8942041397,46.9884338379],"type":"Point"}
}