{
  "type": "Feature",
  "properties": {
    "iso:country":"CH",
    "sg:address":"Route De La Plaine 2",
    "sg:city":"Chavannes-renens",
    "sg:orig_category":"Schwimmb\u00e4der",
    "sg:phone":"+41 21 691 07 91",
    "sg:postcode":"1022",
    "sg:province":"Vaud",
    "wof:name":"Coll\u00e8ge De La Plaine Piscine Couverte",
    "wof:placetype":"venue"
},
  "geometry": {"coordinates":[6.5725641251,46.5264320374],"type":"Point"}
}