{
  "type": "Feature",
  "properties": {
    "iso:country":"CH",
    "sg:address":"6614",
    "sg:city":"Brissago",
    "sg:classifiers":[
        {
            "category":"Travel",
            "subcategory":"Hotels & Motels",
            "type":"Entertainment"
        }
    ],
    "sg:postcode":"6614",
    "sg:province":"Ticino",
    "sg:tags":[
        "hotels",
        "mit",
        "restaurant"
    ],
    "wof:name":"Janko Gest Sagl",
    "wof:placetype":"venue"
},
  "geometry": {"coordinates":[8.7102975845,46.118976593],"type":"Point"}
}