{
  "type": "Feature",
  "properties": {
    "iso:country":"CH",
    "sg:address":"Mittlere Strasse 5",
    "sg:city":"Trimbach",
    "sg:orig_category":"Sonstiger Grosshandel",
    "sg:postcode":"4632",
    "sg:province":"Solothurn",
    "wof:name":"Un Iliyo Handel",
    "wof:placetype":"venue"
},
  "geometry": {"coordinates":[7.9019532204,47.3598442078],"type":"Point"}
}