{
  "type": "Feature",
  "properties": {
    "iso:country":"CH",
    "sg:address":"M\u00e4rzenb\u00fchlstrasse 2",
    "sg:city":"Oberengstringen",
    "sg:orig_category":"D\u00e4mmung gegen K\u00e4lte, W\u00e4rme, Schall U Ersch\u00fctterung",
    "sg:postcode":"8102",
    "sg:province":"Z\u00fcrich",
    "wof:name":"Thermische Isolierungen Danilovic",
    "wof:placetype":"venue"
},
  "geometry": {"coordinates":[8.4577713013,47.4114761353],"type":"Point"}
}