{
  "type": "Feature",
  "properties": {
    "iso:country":"CH",
    "sg:address":"8477",
    "sg:city":"Oberstammheim",
    "sg:orig_category":"Vereine Musik/Blasmusik",
    "sg:phone":"+41 71 636 22 83",
    "sg:postcode":"8477",
    "sg:province":"Z\u00fcrich",
    "wof:name":"Musikgesellschaft",
    "wof:placetype":"venue"
},
  "geometry": {"coordinates":[9.1668395996,47.5790901184],"type":"Point"}
}