{
  "type": "Feature",
  "properties": {
    "iso:country":"CH",
    "sg:address":"Via Rotondello",
    "sg:city":"Arbedo",
    "sg:orig_category":"G\u00fcterbef\u00f6rderung im Strassenverkehr",
    "sg:phone":"+41 91 829 10 09",
    "sg:postcode":"6517",
    "sg:province":"Ticino",
    "wof:name":"Gualtiero Dafond Autotrasporti",
    "wof:placetype":"venue"
},
  "geometry": {"coordinates":[9.0439634323,46.2156829834],"type":"Point"}
}