{
  "type": "Feature",
  "properties": {
    "iso:country":"CH",
    "sg:address":"Neumatte 10",
    "sg:city":"Kerzers",
    "sg:classifiers":[
        {
            "category":"Insurance",
            "subcategory":"Insurance Agent",
            "type":"Services"
        }
    ],
    "sg:phone":"+41 31 755 65 70",
    "sg:postcode":"3210",
    "sg:province":"Fribourg",
    "sg:tags":[
        "versicherungsagenturen",
        "-broker"
    ],
    "wof:name":"Alba Versicherungen Agentur",
    "wof:placetype":"venue"
},
  "geometry": {"coordinates":[7.1918802261,46.9722328186],"type":"Point"}
}