{
  "type": "Feature",
  "properties": {
    "iso:country":"CH",
    "sg:address":"L\u00f6wenstrasse 65 8001 Z\u00fcrich. Postfach",
    "sg:city":"Z\u00fcrich",
    "sg:orig_category":"Finanzierungsinstitutionen",
    "sg:phone":"+41 12114141",
    "sg:postcode":"8023",
    "sg:province":"Z\u00fcrich",
    "wof:name":"Rutishauser Finanz Ag",
    "wof:placetype":"venue"
},
  "geometry": {"coordinates":[8.5382270813,47.377204895],"type":"Point"}
}