{
  "type": "Feature",
  "properties": {
    "iso:country":"CH",
    "sg:address":"Garage",
    "sg:city":"Tobel",
    "sg:orig_category":"Instandhaltung U Reparatur von Automobilen",
    "sg:phone":"+41 71 917 16 11",
    "sg:postcode":"9555",
    "sg:province":"Thurgau",
    "wof:name":"Siegenthaler Hans Rudolf",
    "wof:placetype":"venue"
},
  "geometry": {"coordinates":[9.0303897858,47.5119667053],"type":"Point"}
}