{
  "type": "Feature",
  "properties": {
    "iso:country":"CH",
    "sg:address":"Bleiche 6163 Ebnet. Postfach",
    "sg:city":"Ebnet",
    "sg:orig_category":"Non-Classified Establishments",
    "sg:phone":"+41 79 439 42 02",
    "sg:postcode":"6163",
    "sg:province":"Luzern",
    "wof:name":"Egli Gartenbau Ag Sursee, Zweigniederlassung Entlebuch",
    "wof:placetype":"venue"
},
  "geometry": {"coordinates":[8.0784568787,47.0232772827],"type":"Point"}
}