{
  "type": "Feature",
  "properties": {
    "iso:country":"CH",
    "sg:address":"Dorfstrasse 18 3714 Frutigen. Postfach 59",
    "sg:city":"Frutigen",
    "sg:orig_category":"Verkehrs- and Tourismusb\u00fcros",
    "sg:phone":"+41 33 671 14 21",
    "sg:postcode":"3714",
    "sg:province":"Bern",
    "wof:name":"Verkehrsb\u00fcro",
    "wof:placetype":"venue"
},
  "geometry": {"coordinates":[7.6458101273,46.5884246826],"type":"Point"}
}