{
  "type": "Feature",
  "properties": {
    "iso:country":"CH",
    "sg:address":"Feldstrasse 19",
    "sg:city":"W\u00fcrenlos",
    "sg:orig_category":"Gartenbau",
    "sg:phone":"+41 61 711 17 29",
    "sg:postcode":"5436",
    "sg:province":"Aargau",
    "wof:name":"Josef Kunz Gartenbau",
    "wof:placetype":"venue"
},
  "geometry": {"coordinates":[7.5912809372,47.4954986572],"type":"Point"}
}