{
  "type": "Feature",
  "properties": {
    "iso:country":"CH",
    "sg:address":"St\u00e4dtchenstrasse 74a",
    "sg:city":"Sargans",
    "sg:orig_category":"Finanzierungsinstitutionen",
    "sg:postcode":"7320",
    "sg:province":"St. Gallen",
    "wof:name":"Ersanka Ag",
    "wof:placetype":"venue"
},
  "geometry": {"coordinates":[9.4344491959,47.0511283875],"type":"Point"}
}