{
  "type": "Feature",
  "properties": {
    "iso:country":"CH",
    "sg:address":"Route Des Ronquoz 122",
    "sg:city":"Sion",
    "sg:classifiers":[
        {
            "category":"Banks & Credit Unions",
            "subcategory":"Financial Services",
            "type":"Services"
        }
    ],
    "sg:phone":"+41 27 322 88 51",
    "sg:postcode":"1950",
    "sg:province":"Valais",
    "sg:tags":[
        "line",
        "electric"
    ],
    "wof:name":"Grichting Sa",
    "wof:placetype":"venue"
},
  "geometry": {"coordinates":[7.3519630432,46.2221260071],"type":"Point"}
}