{
  "type": "Feature",
  "properties": {
    "iso:country":"CH",
    "sg:address":"Avenue Victor-ruffy 42 1012 Lausanne Case Postale 94",
    "sg:city":"Lausanne",
    "sg:orig_category":"Grosshandel mit Getr\u00e4nken Handelsvermittlung von Nahrungsmitteln, Getr\u00e4nken U Tabakwaren",
    "sg:phone":"+41 22 300 31 11",
    "sg:postcode":"1012",
    "sg:province":"Vaud",
    "wof:name":"Haut Prestige Wines Sa",
    "wof:placetype":"venue"
},
  "geometry": {"coordinates":[6.1296272278,46.1830863953],"type":"Point"}
}