{
  "type": "Feature",
  "properties": {
    "iso:country":"CH",
    "sg:address":"Schulstrasse 78 8952 Schlieren. Postfach",
    "sg:city":"Schlieren",
    "sg:orig_category":"Druckgewerbe Satzherstellung U Reproduktion",
    "sg:phone":"+41 17307040",
    "sg:postcode":"8952",
    "sg:province":"Z\u00fcrich",
    "wof:name":"Sp\u00f6rri Druck Ag",
    "wof:placetype":"venue"
},
  "geometry": {"coordinates":[8.4614658356,47.396232605],"type":"Point"}
}