{
  "type": "Feature",
  "properties": {
    "iso:country":"CH",
    "sg:address":"Hinterdorfstrasse 6",
    "sg:city":"Mosnang",
    "sg:orig_category":"Verkehrs- and Tourismusb\u00fcros",
    "sg:phone":"+41 71 982 70 70",
    "sg:postcode":"9607",
    "sg:province":"St. Gallen",
    "wof:name":"Verkehrsverein",
    "wof:placetype":"venue"
},
  "geometry": {"coordinates":[9.0387983322,47.3629417419],"type":"Point"}
}