{
  "type": "Feature",
  "properties": {
    "iso:country":"CH",
    "sg:address":"Avenue Grand-st-bernard 35",
    "sg:city":"Martigny",
    "sg:orig_category":"Architektur U Ingenieurb\u00fcros",
    "sg:phone":"+41 79 431 20 34",
    "sg:postcode":"1920",
    "sg:province":"Valais",
    "wof:name":"Morier Ing\u00e9nieur-conseil/repr\u00e9sentation S\u00e0rl",
    "wof:placetype":"venue"
},
  "geometry": {"coordinates":[6.56061,46.528709],"type":"Point"}
}