{
  "type": "Feature",
  "properties": {
    "addr:full":"Route De Malagnou 52 Gen\u00e8ve Gen\u00e8ve 1208",
    "addr:housenumber":"52",
    "addr:postcode":"1208",
    "addr:street":"Route De Malagnou",
    "iso:country":"CH",
    "sg:address":"Route De Malagnou 52",
    "sg:city":"Gen\u00e8ve",
    "sg:orig_category":"Detailhandel mit Brot, Back U S\u00fcsswaren",
    "sg:phone":"+41 22 736 44 40",
    "sg:postcode":"1208",
    "sg:province":"Gen\u00e8ve",
    "wof:name":"Heinz Hochwahr Confiserie-p\u00e2tisserie",
    "wof:placetype":"venue"
},
  "geometry": {"coordinates":[6.163429,46.196503],"type":"Point"}
}