{
  "type": "Feature",
  "properties": {
    "addr:full":"Dorfstrasse 1 Weisslingen Z\u00fcrich 8484",
    "addr:housenumber":"1",
    "addr:postcode":"8484",
    "addr:street":"Dorfstrasse",
    "iso:country":"CH",
    "sg:address":"Dorfstrasse 1",
    "sg:city":"Weisslingen",
    "sg:orig_category":"Autogaragen",
    "sg:phone":"+41 52 384 11 71",
    "sg:postcode":"8484",
    "sg:province":"Z\u00fcrich",
    "wof:name":"Garage H\u00fcbscher Inh.r.amb\u00fchl",
    "wof:placetype":"venue"
},
  "geometry": {"coordinates":[8.765541,47.42934],"type":"Point"}
}