{
  "type": "Feature",
  "properties": {
    "iso:country":"CH",
    "sg:address":"Seftigenstr. 212 3098 K\u00f6niz. Postfach",
    "sg:city":"Wabern",
    "sg:orig_category":"Herstellung von Schmuck, Gold U Silberschmiedwaren",
    "sg:phone":"+41 71 333 23 28",
    "sg:postcode":"3084",
    "sg:province":"Bern",
    "wof:name":"Thalmann Goldschmied",
    "wof:placetype":"venue"
},
  "geometry": {"coordinates":[9.3621683121,47.3862419128],"type":"Point"}
}