{
  "type": "Feature",
  "properties": {
    "iso:country":"CH",
    "sg:address":"Alte Hauensteinstrasse 7",
    "sg:city":"Trimbach",
    "sg:orig_category":"Selbst\u00e4ndige bildende K\u00fcnstler",
    "sg:phone":"+41 62 293 38 61",
    "sg:postcode":"4632",
    "sg:province":"Solothurn",
    "wof:name":"Dieter D\u00fcrsteler Grabmalkunst",
    "wof:placetype":"venue"
},
  "geometry": {"coordinates":[7.8815379143,47.3678665161],"type":"Point"}
}