{
  "type": "Feature",
  "properties": {
    "iso:country":"CH",
    "sg:address":"Gerliswilstrasse",
    "sg:city":"Emmenbr\u00fccke",
    "sg:orig_category":"Fachdetailhandel in Verkaufsr\u00e4umen",
    "sg:phone":"+41 16878173",
    "sg:postcode":"6020",
    "sg:province":"Luzern",
    "wof:name":"Petplanet Ag",
    "wof:placetype":"venue"
},
  "geometry": {"coordinates":[8.2729301453,47.0805931091],"type":"Point"}
}