{
  "type": "Feature",
  "properties": {
    "iso:country":"CH",
    "sg:address":"Rue Des Flandres 1",
    "sg:city":"Neuch\u00e2tel",
    "sg:classifiers":[
        {
            "category":"Restaurant",
            "type":"Food & Drink"
        }
    ],
    "sg:phone":"+41 32 724 08 22",
    "sg:postcode":"2000",
    "sg:province":"Neuch\u00e2tel",
    "wof:name":"Caf\u00e9-pizzeria Cercle National",
    "wof:placetype":"venue"
},
  "geometry": {"coordinates":[6.9290781021,46.9904403687],"type":"Point"}
}