{
  "type": "Feature",
  "properties": {
    "iso:country":"CH",
    "sg:address":"B\u00e4listeigstrasse 2",
    "sg:city":"Eschenz",
    "sg:orig_category":"R\u00fcckgewinnung U Vorbereitung f\u00fcr die Wiederverwertung Recycling",
    "sg:phone":"+41 52 740 33 30",
    "sg:postcode":"8264",
    "sg:province":"Thurgau",
    "wof:name":"Kerler Handels Gmbh",
    "wof:placetype":"venue"
},
  "geometry": {"coordinates":[8.8640794754,47.6513252258],"type":"Point"}
}