{
  "type": "Feature",
  "properties": {
    "iso:country":"CH",
    "sg:address":"1112",
    "sg:city":"Echichens",
    "sg:orig_category":"Landesverteidigung, Sozialversicherung \u00d6ffentliche Verwaltung",
    "sg:phone":"+41 21 869 94 66",
    "sg:postcode":"1112",
    "sg:province":"Vaud",
    "wof:name":"Centre De Protection Civile",
    "wof:placetype":"venue"
},
  "geometry": {"coordinates":[6.4675898552,46.555770874],"type":"Point"}
}