{
  "type": "Feature",
  "properties": {
    "iso:country":"CH",
    "sg:address":"Faubourg Du Lac 14",
    "sg:city":"Neuenburg",
    "sg:orig_category":"Non-Classified Establishments",
    "sg:postcode":"2000",
    "sg:province":"Neuch\u00e2tel",
    "wof:name":"Casino De La Rotonde Sa",
    "wof:placetype":"venue"
},
  "geometry": {"coordinates":[6.9369277954,46.994178772],"type":"Point"}
}