{
  "type": "Feature",
  "properties": {
    "iso:country":"CH",
    "sg:address":"Affolternstrasse 5",
    "sg:city":"Hedingen",
    "sg:orig_category":"Grosshandel mit Blumen U Pflanzen",
    "sg:phone":"+41 31 951 80 48",
    "sg:postcode":"8908",
    "sg:province":"Z\u00fcrich",
    "wof:name":"Interhydro Ag",
    "wof:placetype":"venue"
},
  "geometry": {"coordinates":[7.5134057999,46.9189682007],"type":"Point"}
}