{
  "type": "Feature",
  "properties": {
    "iso:country":"CH",
    "sg:address":"Im Oberen Boden 36 8049 Z\u00fcrich. Postfach",
    "sg:city":"Z\u00fcrich",
    "sg:orig_category":"Sonstige pers\u00f6nliche Dienstleistungen Unternehmensberatung",
    "sg:phone":"+41 13402166",
    "sg:postcode":"8049",
    "sg:province":"Z\u00fcrich",
    "wof:name":"Symbion Consulting Ag Beratungen, Bes. Bewirtschaftung U. Organisation",
    "wof:placetype":"venue"
},
  "geometry": {"coordinates":[8.4815044403,47.4161453247],"type":"Point"}
}