{
  "type": "Feature",
  "properties": {
    "iso:country":"CH",
    "sg:address":"Welschd\u00f6rfli 2 7000 Chur. Postfach 7",
    "sg:city":"Chur",
    "sg:orig_category":"Berufsbildende weiterf\u00fchrende Schulen HOTELS: MIT RESTAURANT",
    "sg:phone":"+41 79 413 02 50",
    "sg:postcode":"7002",
    "sg:province":"Graubunden",
    "wof:name":"Somana Gmbh",
    "wof:placetype":"venue"
},
  "geometry": {"coordinates":[9.528955,46.847786],"type":"Point"}
}