{
  "type": "Feature",
  "properties": {
    "iso:country":"CH",
    "sg:address":"Weisse Gasse 15",
    "sg:city":"Basel",
    "sg:orig_category":"Advokaturb\u00fcros",
    "sg:phone":"+41 22 346 90 44",
    "sg:postcode":"4001",
    "sg:province":"Basel-Stadt",
    "wof:name":"Ren\u00e9 Emmenegger Etude D'avocat",
    "wof:placetype":"venue"
},
  "geometry": {"coordinates":[6.152126,46.195339],"type":"Point"}
}