{
  "type": "Feature",
  "properties": {
    "iso:country":"CH",
    "sg:address":"Duboule Chemin Mo\u00efse- 31 1209 Gen\u00e8ve. Postfach",
    "sg:city":"Gen\u00e8ve",
    "sg:orig_category":"Markt U Meinungsforschung",
    "sg:postcode":"1209",
    "sg:province":"Gen\u00e8ve",
    "wof:name":"Findico Sa",
    "wof:placetype":"venue"
},
  "geometry": {"coordinates":[6.1255102158,46.2248344421],"type":"Point"}
}