{
  "type": "Feature",
  "properties": {
    "iso:country":"CH",
    "sg:address":"Ziegelackerstrasse 11",
    "sg:city":"Bern",
    "sg:classifiers":[
        {
            "category":"Banks & Credit Unions",
            "subcategory":"Investment Brokerage",
            "type":"Services"
        }
    ],
    "sg:phone":"+41 31 992 57 44",
    "sg:postcode":"3027",
    "sg:province":"Bern",
    "sg:tags":[
        "appliance",
        "examination",
        "gynaecologist"
    ],
    "wof:name":"T. & R. T\u00fcscher Ag",
    "wof:placetype":"venue"
},
  "geometry": {"coordinates":[7.401135,46.948769],"type":"Point"}
}