{
  "type": "Feature",
  "properties": {
    "iso:country":"CH",
    "sg:address":"Via Camminata 1",
    "sg:city":"Bellinzona",
    "sg:orig_category":"Aktivit\u00e4t der Bankinstitute",
    "sg:phone":"+41 800 811 820",
    "sg:postcode":"6500",
    "sg:province":"Ticino",
    "wof:name":"Banca Migros",
    "wof:placetype":"venue"
},
  "geometry": {"coordinates":[9.022666,46.190891],"type":"Point"}
}