{
  "type": "Feature",
  "properties": {
    "iso:country":"CH",
    "sg:address":"1510 Moudon Case Postale 18",
    "sg:city":"Moudon",
    "sg:orig_category":"Sportvereine Sch\u00fctzen",
    "sg:postcode":"1510",
    "sg:province":"Vaud",
    "wof:name":"St\u00e9 De Tir Amis Du Tir",
    "wof:placetype":"venue"
},
  "geometry": {"coordinates":[6.8003668785,46.6674957275],"type":"Point"}
}