{
  "type": "Feature",
  "properties": {
    "iso:country":"CH",
    "sg:address":"Sonneckstrasse 4",
    "sg:city":"Jona",
    "sg:orig_category":"Datenverarbeitungsdienste Softwareentwicklung U beratung",
    "sg:phone":"+41 55 211 11 20",
    "sg:postcode":"8645",
    "sg:province":"St. Gallen",
    "wof:name":"Ctb Controlling Software Ag",
    "wof:placetype":"venue"
},
  "geometry": {"coordinates":[8.821352,47.242947],"type":"Point"}
}