{
  "type": "Feature",
  "properties": {
    "addr:full":"Chr\u00fcmigstrasse 16 Wimmis Bern 3752",
    "addr:housenumber":"16",
    "addr:postcode":"3752",
    "addr:street":"Chruemigstrasse;Bern",
    "iso:country":"CH",
    "sg:address":"Chr\u00fcmigstrasse 16",
    "sg:city":"Wimmis",
    "sg:orig_category":"Arztpraxen",
    "sg:phone":"+41 41 850 33 85",
    "sg:postcode":"3752",
    "sg:province":"Bern",
    "wof:name":"Dr.med.urs Kayser Arzt F.allgemeine Medizin Fmh",
    "wof:placetype":"venue"
},
  "geometry": {"coordinates":[8.438616,47.075966],"type":"Point"}
}