{
  "type": "Feature",
  "properties": {
    "iso:country":"CH",
    "sg:address":"Obere Bahnhofstrasse 13 5507 Mellingen. Postfach",
    "sg:city":"Mellingen",
    "sg:orig_category":"Finanzierungsinstitutionen",
    "sg:postcode":"5507",
    "sg:province":"Aargau",
    "wof:name":"Ms Vf Consulting & Trading Gmbh",
    "wof:placetype":"venue"
},
  "geometry": {"coordinates":[8.2721204758,47.4292144775],"type":"Point"}
}