{
  "type": "Feature",
  "properties": {
    "iso:country":"CH",
    "sg:address":"Baarerstrasse 69",
    "sg:city":"Zug",
    "sg:orig_category":"Finanzierungsinstitutionen",
    "sg:phone":"+41 79 691 65 53",
    "sg:postcode":"6300",
    "sg:province":"Zug",
    "wof:name":"Masefield Trading Ag",
    "wof:placetype":"venue"
},
  "geometry": {"coordinates":[8.5175647736,47.1766815186],"type":"Point"}
}