{
  "type": "Feature",
  "properties": {
    "iso:country":"CH",
    "sg:address":"Via Lavizzari 4",
    "sg:city":"Lugano",
    "sg:orig_category":"Grosshandel mit sonstigen Halbwaren",
    "sg:phone":"+41 91 921 02 55",
    "sg:postcode":"6900",
    "sg:province":"Ticino",
    "wof:name":"Kg Tissue Trade B.v. Amsterdam",
    "wof:placetype":"venue"
},
  "geometry": {"coordinates":[8.9583463669,46.0064620972],"type":"Point"}
}