{
  "type": "Feature",
  "properties": {
    "iso:country":"CH",
    "sg:address":"Route Cantonale 1897 Bouveret Case Postale 35",
    "sg:city":"Bouveret",
    "sg:orig_category":"Instandhaltung U Reparatur von Automobilen Tankstellen",
    "sg:phone":"+41 24 481 23 55",
    "sg:postcode":"1897",
    "sg:province":"Valais",
    "wof:name":"Garage Charly Bussien Station-service Agip",
    "wof:placetype":"venue"
},
  "geometry": {"coordinates":[6.854364872,46.3833808899],"type":"Point"}
}