{
  "type": "Feature",
  "properties": {
    "iso:country":"CH",
    "sg:address":"Buchenweg 10 5702 Niederlenz. Postfach",
    "sg:city":"Niederlenz",
    "sg:orig_category":"Vermietung U Verpachtung von eigenen Immobilien",
    "sg:phone":"+41 62 891 32 55",
    "sg:postcode":"5702",
    "sg:province":"Aargau",
    "wof:name":"W\u00fcrgler Immobilien Ag",
    "wof:placetype":"venue"
},
  "geometry": {"coordinates":[8.1839389801,47.3981781006],"type":"Point"}
}