{
  "type": "Feature",
  "properties": {
    "iso:country":"CH",
    "sg:address":"St. Alban-vorstadt 80 4052 Basel. Postfach",
    "sg:city":"Basel",
    "sg:orig_category":"Unternehmensberatung",
    "sg:postcode":"4052",
    "sg:province":"Basel-Stadt",
    "wof:name":"L\u00fcdi Markus Consulting Gmbh Beratung Im Bereich Human Resources Management Usw",
    "wof:placetype":"venue"
},
  "geometry": {"coordinates":[7.5997600555,47.5538444519],"type":"Point"}
}