{
  "type": "Feature",
  "properties": {
    "iso:country":"CH",
    "sg:address":"Bei Der Kirche",
    "sg:city":"Susten",
    "sg:orig_category":"Architekturb\u00fcros",
    "sg:phone":"+41 27 473 18 06",
    "sg:postcode":"3952",
    "sg:province":"Valais",
    "wof:name":"Paul Sewer Architekturb\u00fcro",
    "wof:placetype":"venue"
},
  "geometry": {"coordinates":[7.642022,46.311512],"type":"Point"}
}