{
  "type": "Feature",
  "properties": {
    "iso:country":"CH",
    "sg:city":"Beinwil",
    "sg:classifiers":[
        {
            "category":"Banks & Credit Unions",
            "subcategory":"Bank",
            "type":"Services"
        }
    ],
    "sg:phone":"+41 4157481671",
    "sg:postcode":"5637",
    "sg:province":"Aargau",
    "wof:name":"Raiffeisenkasse",
    "wof:placetype":"venue"
},
  "geometry": {"coordinates":[8.346536,47.23188],"type":"Point"}
}