{
  "type": "Feature",
  "properties": {
    "iso:country":"CH",
    "sg:address":"Erikoner Strasse 4",
    "sg:city":"Tobel",
    "sg:orig_category":"Mechanische Werkst\u00e4tten",
    "sg:phone":"+41 71 917 13 83",
    "sg:postcode":"9555",
    "sg:province":"Thurgau",
    "wof:name":"Franz Rupper Gmbh Mechanische Werkst\u00e4tte",
    "wof:placetype":"venue"
},
  "geometry": {"coordinates":[9.0327653885,47.5152206421],"type":"Point"}
}