{
  "type": "Feature",
  "properties": {
    "iso:country":"CH",
    "sg:address":"Seestandweg 95",
    "sg:city":"Erlach",
    "sg:orig_category":"Elektrizit\u00e4tsversorgung",
    "sg:postcode":"3235",
    "sg:province":"Bern",
    "wof:name":"Solar-genossenschaft Sonne Von St. Moritz",
    "wof:placetype":"venue"
},
  "geometry": {"coordinates":[9.8381910324,46.4970664978],"type":"Point"}
}