{
  "type": "Feature",
  "properties": {
    "iso:country":"CH",
    "sg:address":"9423 Altenrhein. Postfach 11",
    "sg:city":"Altenrhein",
    "sg:orig_category":"Abwasserreinigung",
    "sg:phone":"+41 71 858 67 67",
    "sg:postcode":"9423",
    "sg:province":"St. Gallen",
    "wof:name":"Abwasserverband Altenrhein Zentrale Kl\u00e4ranlage Am Rhein",
    "wof:placetype":"venue"
},
  "geometry": {"coordinates":[9.551738,47.490391],"type":"Point"}
}