{
  "type": "Feature",
  "properties": {
    "iso:country":"CH",
    "sg:address":"Chemin Du Petit-clos 20 1815 Clarens Case Postale 77",
    "sg:city":"Clarens",
    "sg:orig_category":"Herstellung von k\u00e4lte U lufttechnischen Erzeugnissen f\u00fcr gewerbliche Zwecke Installation von Heizung",
    "sg:phone":"+41 21 964 22 69",
    "sg:postcode":"1815",
    "sg:province":"Vaud",
    "wof:name":"Roos Ventilation Sa",
    "wof:placetype":"venue"
},
  "geometry": {"coordinates":[6.8991341591,46.4418411255],"type":"Point"}
}