{
  "type": "Feature",
  "properties": {
    "iso:country":"CH",
    "sg:address":"Chemin Des Muguets 4",
    "sg:city":"Vessy",
    "sg:orig_category":"Fussreflexzonenmassage",
    "sg:phone":"+41 22 784 19 75",
    "sg:postcode":"1234",
    "sg:province":"Gen\u00e8ve",
    "wof:name":"Ariane Mentha-dugerdil R\u00e9flexoth\u00e9rapie",
    "wof:placetype":"venue"
},
  "geometry": {"coordinates":[6.1615080833,46.1711921692],"type":"Point"}
}