{
  "type": "Feature",
  "properties": {
    "iso:country":"CH",
    "sg:address":"Ch\u00fceferistrasse 5 8320 Fehraltorf. Postfach 101",
    "sg:city":"Fehraltorf",
    "sg:orig_category":"Softwareentwicklung U beratung",
    "sg:phone":"+41 19552575",
    "sg:postcode":"8320",
    "sg:province":"Z\u00fcrich",
    "wof:name":"181818 Ag",
    "wof:placetype":"venue"
},
  "geometry": {"coordinates":[8.7535657883,47.3846054077],"type":"Point"}
}