{
  "type": "Feature",
  "properties": {
    "iso:country":"CH",
    "sg:address":"Amselweg 6",
    "sg:city":"Chur",
    "sg:orig_category":"Maler U Glasergewerbe Malerei",
    "sg:phone":"+41 81 250 34 50",
    "sg:postcode":"7000",
    "sg:province":"Graubunden",
    "wof:name":"Cores Malergesch\u00e4ft Venzin & Brazerol",
    "wof:placetype":"venue"
},
  "geometry": {"coordinates":[9.5311565399,46.8577690125],"type":"Point"}
}