{
  "type": "Feature",
  "properties": {
    "iso:country":"CH",
    "sg:address":"Talstrass 2",
    "sg:city":"Marthalen",
    "sg:orig_category":"Arztpraxen",
    "sg:phone":"+41 52 319 17 86",
    "sg:postcode":"8460",
    "sg:province":"Z\u00fcrich",
    "wof:name":"Dr.med.urs Muggli Arzt F.allgemeine Medizin Fmh",
    "wof:placetype":"venue"
},
  "geometry": {"coordinates":[8.649447,47.625843],"type":"Point"}
}