{
  "type": "Feature",
  "properties": {
    "iso:country":"CH",
    "sg:address":"Rellikonstrasse 7",
    "sg:city":"Maur",
    "sg:orig_category":"Herstellung von elektronischen Bauelementen",
    "sg:phone":"+41 19803380",
    "sg:postcode":"8124",
    "sg:province":"Z\u00fcrich",
    "wof:name":"Kern Components",
    "wof:placetype":"venue"
},
  "geometry": {"coordinates":[8.6707983017,47.3396682739],"type":"Point"}
}