{
  "type": "Feature",
  "properties": {
    "iso:country":"CH",
    "sg:address":"Sprungstrasse 13d",
    "sg:city":"Unter\u00e4geri",
    "sg:orig_category":"Allgemeiner Hoch U Tiefbau",
    "sg:phone":"+41 52 383 31 50",
    "sg:postcode":"6314",
    "sg:province":"Zug",
    "wof:name":"Hess Hans Baupraxis Ag",
    "wof:placetype":"venue"
},
  "geometry": {"coordinates":[8.832124,47.458569],"type":"Point"}
}