{
  "type": "Feature",
  "properties": {
    "iso:country":"CH",
    "sg:address":"Route De Jussy 122",
    "sg:city":"Th\u00f4nex",
    "sg:orig_category":"HERSTELLUNG VON GER\u00c4TEN DER ELEKTRIZIT\u00c4TSERZEUGUNG, -VERTEILUNG U.\u00c4 Herstellung von Metallerzeugniss",
    "sg:phone":"+41 32 343 37 11",
    "sg:postcode":"1226",
    "sg:province":"Gen\u00e8ve",
    "wof:name":"Omega Electronics Ag",
    "wof:placetype":"venue"
},
  "geometry": {"coordinates":[7.2579817772,47.1375541687],"type":"Point"}
}