{
  "type": "Feature",
  "properties": {
    "iso:country":"CH",
    "sg:address":"Rue De Cornavin 3",
    "sg:city":"Gen\u00e8ve",
    "sg:orig_category":"RESTAURANTS: TEA-ROOMS",
    "sg:phone":"+41 22 732 75 59",
    "sg:postcode":"1201",
    "sg:province":"Gen\u00e8ve",
    "wof:name":"La Nasse A Sa",
    "wof:placetype":"venue"
},
  "geometry": {"coordinates":[6.1418681145,46.2073822021],"type":"Point"}
}