{
  "type": "Feature",
  "properties": {
    "iso:country":"CH",
    "sg:address":"Bahnhofstrasse 9/9a",
    "sg:city":"Baar",
    "sg:orig_category":"Allgemeiner Hoch U Tiefbau",
    "sg:phone":"+41 41 760 67 47",
    "sg:postcode":"6340",
    "sg:province":"Zug",
    "wof:name":"Zum Eigenheim",
    "wof:placetype":"venue"
},
  "geometry": {"coordinates":[8.524498,47.195431],"type":"Point"}
}