{
  "type": "Feature",
  "properties": {
    "iso:country":"CH",
    "sg:address":"Fridlimattstrasse 9",
    "sg:city":"Binz",
    "sg:orig_category":"Datenverarbeitungsdienste Softwareentwicklung U beratung",
    "sg:phone":"+41 79 403 33 60",
    "sg:postcode":"8122",
    "sg:province":"Z\u00fcrich",
    "wof:name":"Infobase Ag",
    "wof:placetype":"venue"
},
  "geometry": {"coordinates":[8.62378,47.358025],"type":"Point"}
}