{
  "type": "Feature",
  "properties": {
    "iso:country":"CH",
    "sg:address":"Vicaire-savoyard Rue Du 12 1203 Gen\u00e8ve. Postfach",
    "sg:city":"Genf",
    "sg:orig_category":"Herstellung von Teilen U Zubeh\u00f6r f\u00fcr Automobile",
    "sg:phone":"+41 32 731 38 38",
    "sg:postcode":"1200",
    "sg:province":"Gen\u00e8ve",
    "wof:name":"Comtesse H.",
    "wof:placetype":"venue"
},
  "geometry": {"coordinates":[6.8997988701,46.98878479],"type":"Point"}
}