{
  "type": "Feature",
  "properties": {
    "iso:country":"CH",
    "sg:address":"Hauptstrasse 95",
    "sg:city":"Muotathal",
    "sg:orig_category":"G\u00fcterbef\u00f6rderung im Strassenverkehr",
    "sg:phone":"+41 41 830 15 62",
    "sg:postcode":"6436",
    "sg:province":"Schwyz",
    "wof:name":"Schelbert-imhof Paul, Transporte Und Garage",
    "wof:placetype":"venue"
},
  "geometry": {"coordinates":[8.7662773132,46.9725646973],"type":"Point"}
}