{
  "type": "Feature",
  "properties": {
    "iso:country":"CH",
    "sg:address":"Hauptstr. 56. 3252 Worben. Postfach",
    "sg:city":"Worben",
    "sg:orig_category":"Detailhandel mit Brot, Back U S\u00fcsswaren",
    "sg:phone":"+41 32 384 35 35",
    "sg:postcode":"3252",
    "sg:province":"Bern",
    "wof:name":"K\u00e4ser-m\u00f6ri Therese.",
    "wof:placetype":"venue"
},
  "geometry": {"coordinates":[7.289285,47.09605],"type":"Point"}
}