{
  "type": "Feature",
  "properties": {
    "iso:country":"CH",
    "sg:address":"Ochsengasse 1",
    "sg:city":"Gelterkinden",
    "sg:orig_category":"Reiseb\u00fcros U Reiseveranstalter",
    "sg:phone":"+41 61 981 34 44",
    "sg:postcode":"4460",
    "sg:province":"Basel-Landschaft",
    "wof:name":"Quo Vadis Reisen M\u00fcller H.r.",
    "wof:placetype":"venue"
},
  "geometry": {"coordinates":[7.8563761711,47.464466095],"type":"Point"}
}