{
  "type": "Feature",
  "properties": {
    "iso:country":"CH",
    "sg:address":"Friedrichshafnerstrasse 15",
    "sg:city":"Romanshorn",
    "sg:orig_category":"Abwasserreinigung",
    "sg:phone":"+41 71 463 31 44",
    "sg:postcode":"8590",
    "sg:province":"Thurgau",
    "wof:name":"Abwasser-verband Romanshorn Ara",
    "wof:placetype":"venue"
},
  "geometry": {"coordinates":[9.373423,47.556915],"type":"Point"}
}