{
  "type": "Feature",
  "properties": {
    "iso:country":"CH",
    "sg:address":"Champ Du Fau 1085 Vulliens Case Postale 14",
    "sg:city":"Vulliens",
    "sg:orig_category":"Sonstige mit der Informatik verbundene T\u00e4tigkeiten",
    "sg:phone":"+41 21 903 44 44",
    "sg:postcode":"1085",
    "sg:province":"Vaud",
    "wof:name":"Digicem, Philippe Mayor",
    "wof:placetype":"venue"
},
  "geometry": {"coordinates":[6.7915091515,46.6141014099],"type":"Point"}
}