{
  "type": "Feature",
  "properties": {
    "iso:country":"CH",
    "sg:address":"Via Principala 58",
    "sg:city":"Trin",
    "sg:orig_category":"Detailhandel mit Fleisch U Fleischwaren Fleischverarbeitung",
    "sg:phone":"+41 56 622 40 17",
    "sg:postcode":"7014",
    "sg:province":"Graubunden",
    "wof:name":"H. Moser Und S\u00f6hne Ag",
    "wof:placetype":"venue"
},
  "geometry": {"coordinates":[8.2782850266,47.3518447876],"type":"Point"}
}