{
  "type": "Feature",
  "properties": {
    "iso:country":"CH",
    "sg:address":"Eichenstrasse 710",
    "sg:city":"Eschen",
    "sg:orig_category":"Zahnarztpraxen",
    "sg:phone":"+41 75 373 73 91",
    "sg:postcode":"9492",
    "wof:name":"Dr. Med. Dent. Gebhard Meier Zahnarzt",
    "wof:placetype":"venue"
},
  "geometry": {"coordinates":[9.5122098923,47.2123298645],"type":"Point"}
}