{
  "type": "Feature",
  "properties": {
    "iso:country":"CH",
    "sg:address":"Rue Haldimand 9 1003 Lausanne. Postfach",
    "sg:city":"Lausanne",
    "sg:orig_category":"Parf\u00fcmerien U sonstiger Detailhandel mit kosmetischen Artikeln U K\u00f6rperpflegemitteln",
    "sg:phone":"+41 21 311 00 45",
    "sg:postcode":"1002",
    "sg:province":"Vaud",
    "wof:name":"The Body Shop Levy Ag",
    "wof:placetype":"venue"
},
  "geometry": {"coordinates":[6.6312050819,46.5224151611],"type":"Point"}
}