{
  "type": "Feature",
  "properties": {
    "iso:country":"CH",
    "sg:address":"Im Grund 15 5014 Gretzenbach. Postfach",
    "sg:city":"Gretzenbach",
    "sg:orig_category":"Druck ohne Zeitungsdruck",
    "sg:phone":"+41 62 849 67 41",
    "sg:postcode":"5014",
    "sg:province":"Solothurn",
    "wof:name":"Faes Printing Systems Ag",
    "wof:placetype":"venue"
},
  "geometry": {"coordinates":[7.9893198013,47.3577690125],"type":"Point"}
}