{
  "type": "Feature",
  "properties": {
    "iso:country":"CH",
    "sg:address":"Hirtenstalweg 2",
    "sg:city":"Richterswil",
    "sg:orig_category":"Radio U Fernsehanstalten Werbeberatung",
    "sg:phone":"+41 19237537",
    "sg:postcode":"8805",
    "sg:province":"Z\u00fcrich",
    "wof:name":"Rbr Communications Breitler Roland",
    "wof:placetype":"venue"
},
  "geometry": {"coordinates":[8.7025442123,47.2117080688],"type":"Point"}
}