{
  "type": "Feature",
  "properties": {
    "iso:country":"CH",
    "sg:address":"1914",
    "sg:city":"Is\u00e9rables",
    "sg:orig_category":"Detailhandel mit Waren verschiedener Art, Hauptrichtung Nahrungsmittel",
    "sg:phone":"+41 27 306 29 21",
    "sg:postcode":"1914",
    "sg:province":"Valais",
    "wof:name":"Soci\u00e9t\u00e9 Coop\u00e9rative De Consommation La M\u00e9nag\u00e8re Is\u00e9rables",
    "wof:placetype":"venue"
},
  "geometry": {"coordinates":[7.24518013,46.1604385376],"type":"Point"}
}