{
  "type": "Feature",
  "properties": {
    "iso:country":"CH",
    "sg:address":"Lavertezzo-piano",
    "sg:city":"Riazzino",
    "sg:orig_category":"Non-Classified Establishments",
    "sg:postcode":"6595",
    "sg:province":"Ticino",
    "wof:name":"Carlog Holding Ag",
    "wof:placetype":"venue"
},
  "geometry": {"coordinates":[9.0449714661,47.4638404846],"type":"Point"}
}