{
  "type": "Feature",
  "properties": {
    "iso:country":"CH",
    "sg:address":"Strada Ai Ronchi",
    "sg:city":"Torricella",
    "sg:orig_category":"Kosmetikinstitute",
    "sg:phone":"+41 91 945 33 76",
    "sg:postcode":"6808",
    "sg:province":"Ticino",
    "wof:name":"Laura Trezzini Istituto Di Bellezza",
    "wof:placetype":"venue"
},
  "geometry": {"coordinates":[8.9205179214,46.0628623962],"type":"Point"}
}