{
  "type": "Feature",
  "properties": {
    "iso:country":"CH",
    "sg:address":"Alte Landstrasse 81",
    "sg:city":"Gamsen",
    "sg:orig_category":"Sportvereine Alpinismus",
    "sg:phone":"+41 27 956 33 86",
    "sg:postcode":"3900",
    "sg:province":"Valais",
    "wof:name":"Sac Sekt.monte Rosa St.niklaus",
    "wof:placetype":"venue"
},
  "geometry": {"coordinates":[7.8019318581,46.1757278442],"type":"Point"}
}