{
  "type": "Feature",
  "properties": {
    "iso:country":"CH",
    "sg:address":"Freilagerstrasse 47",
    "sg:city":"Z\u00fcrich",
    "sg:orig_category":"Grosshandel mit M\u00f6beln, Wohnbedarf, Teppichen U Bodenbel\u00e4gen",
    "sg:phone":"+41 61 731 39 36",
    "sg:postcode":"8043",
    "sg:province":"Z\u00fcrich",
    "wof:name":"Alma Handels Gmbh M\u00f6bel, Antiquit\u00e4ten U. Einrichtungsgegenst\u00e4nde; Handel Usw",
    "wof:placetype":"venue"
},
  "geometry": {"coordinates":[7.5190172195,47.4759254456],"type":"Point"}
}