{
  "type": "Feature",
  "properties": {
    "iso:country":"CH",
    "sg:address":"H\u00fchnerhubelstrasse 65",
    "sg:city":"Belp",
    "sg:orig_category":"Herstellung von k\u00e4lte U lufttechnischen Erzeugnissen f\u00fcr gewerbliche Zwecke",
    "sg:postcode":"3123",
    "sg:province":"Bern",
    "wof:name":"Klimatron Gmbh K\u00e4lte, Klima- U. W\u00e4rmepumpenanlagen; Handel, Montage U. Service Usw",
    "wof:placetype":"venue"
},
  "geometry": {"coordinates":[7.6622281075,46.7621574402],"type":"Point"}
}