{
  "type": "Feature",
  "properties": {
    "iso:country":"CH",
    "sg:address":"Seuzacherstrasse 3",
    "sg:city":"Hettlingen",
    "sg:orig_category":"Malerei",
    "sg:phone":"+41 52 316 24 62",
    "sg:postcode":"8442",
    "sg:province":"Z\u00fcrich",
    "wof:name":"Werner Leuppi Malergesch\u00e4ft",
    "wof:placetype":"venue"
},
  "geometry": {"coordinates":[8.7102870941,47.5461730957],"type":"Point"}
}