{
  "type": "Feature",
  "properties": {
    "iso:country":"CH",
    "sg:address":"Dr\u00e4likon 6331 H\u00fcnenberg. Postfach",
    "sg:city":"H\u00fcnenberg",
    "sg:orig_category":"Herstellung von Baubedarfsartikeln aus Kunststoff",
    "sg:phone":"+41 71 911 27 11",
    "sg:postcode":"6331",
    "sg:province":"Zug",
    "wof:name":"Silo Ag Wil",
    "wof:placetype":"venue"
},
  "geometry": {"coordinates":[9.0349321365,47.461894989],"type":"Point"}
}