{
  "type": "Feature",
  "properties": {
    "iso:country":"CH",
    "sg:address":"Pr\u00e9-fleuri Rue De 2a",
    "sg:city":"Sitten",
    "sg:orig_category":"Unclassifiable Establishments",
    "sg:postcode":"1950",
    "sg:province":"Valais",
    "wof:name":"Linea Design Concept S\u00e0rl",
    "wof:placetype":"venue"
},
  "geometry": {"coordinates":[7.3572292328,46.2286720276],"type":"Point"}
}