{
  "type": "Feature",
  "properties": {
    "iso:country":"CH",
    "sg:address":"Vignola Via 10",
    "sg:city":"Lugano",
    "sg:orig_category":"Sonstiger Grosshandel",
    "sg:phone":"+41 91 970 15 81",
    "sg:postcode":"6900",
    "sg:province":"Ticino",
    "wof:name":"Consulenza Med Inter, Gueye A.m.",
    "wof:placetype":"venue"
},
  "geometry": {"coordinates":[8.9569740295,46.0162582397],"type":"Point"}
}