{
  "type": "Feature",
  "properties": {
    "iso:country":"CH",
    "sg:address":"Im Buck 35",
    "sg:city":"Sch\u00f6fflisdorf",
    "sg:orig_category":"Architektur U Ingenieurb\u00fcros",
    "sg:phone":"+41 18561522",
    "sg:postcode":"8165",
    "sg:province":"Z\u00fcrich",
    "wof:name":"Avolin Engineering, Buchegger A.",
    "wof:placetype":"venue"
},
  "geometry": {"coordinates":[8.41956,47.503311],"type":"Point"}
}