{
  "type": "Feature",
  "properties": {
    "iso:country":"CH",
    "sg:address":"Meierhofstrasse 18",
    "sg:city":"Triesen",
    "sg:orig_category":"Gymnastik U Fitnesszentren",
    "sg:phone":"+41 75 233 31 41",
    "sg:postcode":"9495",
    "wof:name":"Vitawell Center",
    "wof:placetype":"venue"
},
  "geometry": {"coordinates":[9.5285568237,47.1220855713],"type":"Point"}
}