{
  "type": "Feature",
  "properties": {
    "iso:country":"CH",
    "sg:address":"Davidstrasse 42",
    "sg:city":"St.gallen",
    "sg:orig_category":"Fotografisches Gewerbe U fotografische Laboratorien",
    "sg:phone":"+41 71 222 06 56",
    "sg:postcode":"9000",
    "sg:province":"St. Gallen",
    "wof:name":"Confoederatio 27 Missfeld J.",
    "wof:placetype":"venue"
},
  "geometry": {"coordinates":[9.367436409,47.4199295044],"type":"Point"}
}