{
  "type": "Feature",
  "properties": {
    "iso:country":"CH",
    "sg:address":"M\u00fcller-friedberg-strasse 37 9400 Rorschach. Postfach",
    "sg:city":"Rorschach",
    "sg:orig_category":"Reiseb\u00fcros U Reiseveranstalter",
    "sg:phone":"+41 71 855 33 63",
    "sg:postcode":"9400",
    "sg:province":"St. Gallen",
    "wof:name":"Ying Reiseb\u00fcro Gehri",
    "wof:placetype":"venue"
},
  "geometry": {"coordinates":[9.5024690628,47.4725608826],"type":"Point"}
}