{
  "type": "Feature",
  "properties": {
    "iso:country":"CH",
    "sg:address":"Solothurnstrasse 101",
    "sg:city":"Grenchen",
    "sg:orig_category":"Architektur U Ingenieurb\u00fcros",
    "sg:phone":"+41 32 653 02 35",
    "sg:postcode":"2540",
    "sg:province":"Solothurn",
    "wof:name":"B\u00e4nziger+bacchetta+fehlmann+partner Ingenieure + Planer Sia Usic",
    "wof:placetype":"venue"
},
  "geometry": {"coordinates":[7.403461,47.193665],"type":"Point"}
}