{
  "type": "Feature",
  "properties": {
    "iso:country":"CH",
    "sg:address":"Schlossbergstrasse 12 8820 W\u00e4denswil. Postfach",
    "sg:city":"W\u00e4denswil",
    "sg:orig_category":"Sonstiger Fachdetailhandel mit Nahrungsmitteln, Getr\u00e4nken U Tabak in Verkaufsr\u00e4umen",
    "sg:postcode":"8820",
    "sg:province":"Z\u00fcrich",
    "wof:name":"Ekeigwe African Foods Verkauf Von Afrikanischem Essen Und Getr\u00e4nken. Party-service",
    "wof:placetype":"venue"
},
  "geometry": {"coordinates":[8.6751127243,47.225894928],"type":"Point"}
}