{
  "type": "Feature",
  "properties": {
    "iso:country":"CH",
    "sg:address":"Chemin Des L\u00e9ch\u00e8res 3",
    "sg:city":"Meyrin",
    "sg:orig_category":"Grosshandel mit Holz U Baustoffen G\u00fcterbef\u00f6rderung im Strassenverkehr",
    "sg:phone":"+41 22 989 15 10",
    "sg:postcode":"1217",
    "sg:province":"Gen\u00e8ve",
    "wof:name":"Di Padova & Cie",
    "wof:placetype":"venue"
},
  "geometry": {"coordinates":[6.0679559708,46.2225570679],"type":"Point"}
}