{
  "type": "Feature",
  "properties": {
    "iso:country":"CH",
    "sg:address":"Universit\u00e4tstrasse 33",
    "sg:city":"Z\u00fcrich",
    "sg:orig_category":"Saunas, Solarien, Fitnesszentren U \u00e4hnliches",
    "sg:phone":"+41 12523333",
    "sg:postcode":"8006",
    "sg:province":"Z\u00fcrich",
    "wof:name":"Lady-fit Beyeler Nadine",
    "wof:placetype":"venue"
},
  "geometry": {"coordinates":[8.5479440689,47.3795127869],"type":"Point"}
}