{
  "type": "Feature",
  "properties": {
    "iso:country":"CH",
    "sg:address":"Henri Dunant-strasse 31",
    "sg:city":"Biel/bienne",
    "sg:orig_category":"Sportvereine Turnen",
    "sg:phone":"+41 32 357 12 45",
    "sg:postcode":"2504",
    "sg:province":"Bern",
    "wof:name":"Turnverein Stv Biel-b\u00f6zingen",
    "wof:placetype":"venue"
},
  "geometry": {"coordinates":[7.2764940262,47.1554489136],"type":"Point"}
}