{
  "type": "Feature",
  "properties": {
    "iso:country":"CH",
    "sg:address":"Rainweidstrasse 13c 6330 Cham. Postfach",
    "sg:city":"Cham",
    "sg:orig_category":"Unternehmensberatung",
    "sg:phone":"+41 41 780 65 33",
    "sg:postcode":"6330",
    "sg:province":"Zug",
    "wof:name":"Axina Ag",
    "wof:placetype":"venue"
},
  "geometry": {"coordinates":[8.4442558289,47.1756896973],"type":"Point"}
}