{
  "type": "Feature",
  "properties": {
    "addr:full":"Route Des Combes 15 15 1746 Prez-vers-nor\u00e9az. Postfach Freiburg Fribourg 1700",
    "addr:housenumber":"15 15",
    "addr:postcode":"1746 prez-vers-nore\u0301az. postfach;1700",
    "addr:street":"Route Des Combes",
    "iso:country":"CH",
    "sg:address":"Route Des Combes 15 15 1746 Prez-vers-nor\u00e9az. Postfach",
    "sg:city":"Freiburg",
    "sg:orig_category":"Markt U Meinungsforschung",
    "sg:phone":"+41 26 470 02 85",
    "sg:postcode":"1700",
    "sg:province":"Fribourg",
    "wof:name":"M.p.m. Marketing & Product Management Consultants S.a.",
    "wof:placetype":"venue"
},
  "geometry": {"coordinates":[7.012186,46.782688],"type":"Point"}
}