{
  "type": "Feature",
  "properties": {
    "iso:country":"CH",
    "sg:address":"H\u00e4ckligen",
    "sg:city":"Schmidigen-m\u00fchlew",
    "sg:orig_category":"Bauschreinerei",
    "sg:phone":"+41 34 435 12 75",
    "sg:postcode":"3464",
    "sg:province":"Bern",
    "wof:name":"Rosmarie Aebi Schreinerei",
    "wof:placetype":"venue"
},
  "geometry": {"coordinates":[7.7474,47.093472],"type":"Point"}
}