{
  "type": "Feature",
  "properties": {
    "iso:country":"CH",
    "sg:address":"Sihlquai 259 8005 Z\u00fcrich. Postfach",
    "sg:city":"Z\u00fcrich",
    "sg:orig_category":"Fernmeldedienste",
    "sg:phone":"+41 12733544",
    "sg:postcode":"8001",
    "sg:province":"Z\u00fcrich",
    "wof:name":"Nejadpour Comsult Telecom U. It Beratungsfirma",
    "wof:placetype":"venue"
},
  "geometry": {"coordinates":[8.5275526047,47.3889579773],"type":"Point"}
}