{
  "type": "Feature",
  "properties": {
    "iso:country":"CH",
    "sg:address":"Hauptstrasse 81 8840 Einsiedeln. Postfach 144",
    "sg:city":"Einsiedeln",
    "sg:orig_category":"Fachdetailhandel mit pharmazeutischen Produkten",
    "sg:phone":"+41 55 412 55 73",
    "sg:postcode":"8840",
    "sg:province":"Schwyz",
    "wof:name":"Roos Dr. Karl, Engel-apotheke",
    "wof:placetype":"venue"
},
  "geometry": {"coordinates":[8.7493371964,47.1269378662],"type":"Point"}
}