{
  "type": "Feature",
  "properties": {
    "iso:country":"CH",
    "sg:address":"Blattenmoosstrasse 19",
    "sg:city":"Littau",
    "sg:orig_category":"Grosshandel mit sonstigen Konsumg\u00fctern",
    "sg:phone":"+41 41 250 52 51",
    "sg:postcode":"6014",
    "sg:province":"Luzern",
    "wof:name":"G\u00fcnter Bauer Textil-agentur",
    "wof:placetype":"venue"
},
  "geometry": {"coordinates":[8.2710981369,47.049533844],"type":"Point"}
}