{
  "type": "Feature",
  "properties": {
    "iso:country":"CH",
    "sg:address":"Postpassage 5 4051 Basel. Postfach",
    "sg:city":"Basel",
    "sg:classifiers":[
        {
            "category":"Education",
            "subcategory":"Library",
            "type":"Public Place"
        }
    ],
    "sg:phone":"+41 81 413 40 70",
    "sg:postcode":"4002",
    "sg:province":"Basel-Stadt",
    "sg:tags":[
        "u",
        "bibliotheken",
        "archive"
    ],
    "wof:name":"Bibliothek Der Landschaft Davos",
    "wof:placetype":"venue"
},
  "geometry": {"coordinates":[9.829768,46.801193],"type":"Point"}
}