{
  "type": "Feature",
  "properties": {
    "iso:country":"CH",
    "sg:address":"6017",
    "sg:city":"Ruswil",
    "sg:orig_category":"Grosshandel mit lebenden Tieren",
    "sg:postcode":"6017",
    "sg:province":"Luzern",
    "wof:name":"Schweinezucht Eppishausen Ag",
    "wof:placetype":"venue"
},
  "geometry": {"coordinates":[9.1058273315,47.471118927],"type":"Point"}
}