{
  "type": "Feature",
  "properties": {
    "iso:country":"CH",
    "sg:address":"Landstrasse 91 9494 Schaan. Postfach 196",
    "sg:city":"Schaan",
    "sg:orig_category":"Detailhandel mit Radio U Fernsehger\u00e4ten Elektroinstallation",
    "sg:phone":"+41 75 232 16 12",
    "sg:postcode":"9494",
    "wof:name":"Peter Gmeiner Radio-tv Antennenbau",
    "wof:placetype":"venue"
},
  "geometry": {"coordinates":[9.5088748932,47.161655426],"type":"Point"}
}