{
  "type": "Feature",
  "properties": {
    "addr:full":"General-guisan-strasse 6300 Zug. Postfach 3337 Zug Zug 6300",
    "addr:postcode":"6300;3337;6300",
    "addr:street":"General-Guisan-Strasse;Postfach;Zug",
    "iso:country":"CH",
    "sg:address":"General-guisan-strasse 6300 Zug. Postfach 3337",
    "sg:city":"Zug",
    "sg:orig_category":"Betrieb von Sportanlagen",
    "sg:phone":"+41 41 711 63 59",
    "sg:postcode":"6300",
    "sg:province":"Zug",
    "wof:name":"Kunsteisbahn Zug Ag",
    "wof:placetype":"venue"
},
  "geometry": {"coordinates":[8.503337,47.17802],"type":"Point"}
}