{
  "type": "Feature",
  "properties": {
    "iso:country":"CH",
    "sg:address":"Bl\u00e4sistrasse 7",
    "sg:city":"Z\u00fcrich",
    "sg:orig_category":"Sonstige pers\u00f6nliche Dienstleistungen",
    "sg:phone":"+41 41 921 80 37",
    "sg:postcode":"8049",
    "sg:province":"Z\u00fcrich",
    "wof:name":"\u00abfriendship Seven\u00bb Ag",
    "wof:placetype":"venue"
},
  "geometry": {"coordinates":[8.1158456802,47.1651916504],"type":"Point"}
}