{
  "type": "Feature",
  "properties": {
    "iso:country":"CH",
    "sg:address":"Solothurnstr. 26",
    "sg:city":"Jegenstorf",
    "sg:classifiers":[
        {
            "category":"Banks & Credit Unions",
            "subcategory":"Bank",
            "type":"Services"
        }
    ],
    "sg:phone":"+41 33 972 19 21",
    "sg:postcode":"3303",
    "sg:province":"Bern",
    "wof:name":"Amtsersparniskasse Oberhasli",
    "wof:placetype":"venue"
},
  "geometry": {"coordinates":[8.190589,46.719242],"type":"Point"}
}