{
  "type": "Feature",
  "properties": {
    "iso:country":"CH",
    "sg:address":"Rampe De La Gare 1a",
    "sg:city":"Versoix",
    "sg:orig_category":"Arztpraxen",
    "sg:phone":"+41 22 779 22 41",
    "sg:postcode":"1290",
    "sg:province":"Gen\u00e8ve",
    "wof:name":"Dr M\u00e9d. Isaac Gebremichael M\u00e9decin Sp\u00e9cialiste Fmh",
    "wof:placetype":"venue"
},
  "geometry": {"coordinates":[6.167662,46.279316],"type":"Point"}
}