{
  "type": "Feature",
  "properties": {
    "iso:country":"CH",
    "sg:address":"Wankdorffeldstrasse 70",
    "sg:city":"Bern",
    "sg:orig_category":"Herstellung von konfektionierten Textilwaren ohne Bekleidung",
    "sg:postcode":"3014",
    "sg:province":"Bern",
    "wof:name":"Dp Blachenvermietungs-ag",
    "wof:placetype":"venue"
},
  "geometry": {"coordinates":[7.4624991417,46.966003418],"type":"Point"}
}