{
  "type": "Feature",
  "properties": {
    "iso:country":"CH",
    "sg:address":"Le Cras 148l",
    "sg:city":"Coeuve",
    "sg:orig_category":"Autotransporte international",
    "sg:phone":"+41 32 467 13 85",
    "sg:postcode":"2932",
    "sg:province":"Jura",
    "wof:name":"Dominique & Pascal For\u00eat For\u00eatransports",
    "wof:placetype":"venue"
},
  "geometry": {"coordinates":[7.093537,47.453468],"type":"Point"}
}