{
  "type": "Feature",
  "properties": {
    "iso:country":"CH",
    "sg:address":"Route De Begnins 14 1196 Gland Case Postale 337",
    "sg:city":"Gland",
    "sg:orig_category":"Offsetdruck",
    "sg:phone":"+41 22 364 34 28",
    "sg:postcode":"1196",
    "sg:province":"Vaud",
    "wof:name":"Pierre Richard Imprimerie",
    "wof:placetype":"venue"
},
  "geometry": {"coordinates":[6.2656369209,46.4208984375],"type":"Point"}
}