{
  "type": "Feature",
  "properties": {
    "iso:country":"CH",
    "sg:address":"D\u00e4nikerstrasse 6",
    "sg:city":"Oberg\u00f6sgen",
    "sg:orig_category":"Gem\u00fcsebau",
    "sg:phone":"+41 19100765",
    "sg:postcode":"4653",
    "sg:province":"Solothurn",
    "wof:name":"Karrer G\u00e4rtnerei Ag",
    "wof:placetype":"venue"
},
  "geometry": {"coordinates":[8.5929660797,47.3206977844],"type":"Point"}
}