{
  "type": "Feature",
  "properties": {
    "iso:country":"CH",
    "sg:address":"Alpenstr. 3",
    "sg:city":"Luzern",
    "sg:classifiers":[
        {
            "category":"Travel",
            "subcategory":"Hotels & Motels",
            "type":"Entertainment"
        }
    ],
    "sg:phone":"+41 41 418 47 47",
    "sg:postcode":"6004",
    "sg:province":"Luzern",
    "sg:tags":[
        "hotels",
        "business",
        "restaurant"
    ],
    "wof:name":"Chris D Dittli Hotel Luzernerhof",
    "wof:placetype":"venue"
},
  "geometry": {"coordinates":[8.310998,47.055134],"type":"Point"}
}