{
  "type": "Feature",
  "properties": {
    "iso:country":"CH",
    "sg:address":"Z\u00fcrcherstrasse 35",
    "sg:city":"Basel",
    "sg:orig_category":"Einzelhandel mit Automobilteilen U Zubeh\u00f6r Tankstellen",
    "sg:phone":"+41 61 312 89 63",
    "sg:postcode":"4052",
    "sg:province":"Basel-Stadt",
    "wof:name":"M\u00fcnchbach Migrol-tankstelle",
    "wof:placetype":"venue"
},
  "geometry": {"coordinates":[7.6089677811,47.5539016724],"type":"Point"}
}