{
  "type": "Feature",
  "properties": {
    "iso:country":"CH",
    "sg:address":"Wagistrasse 13",
    "sg:city":"Schlieren",
    "sg:orig_category":"W\u00e4scherei U chemische Reinigung",
    "sg:postcode":"8952",
    "sg:province":"Z\u00fcrich",
    "wof:name":"W\u00e4scherei Niederhauser",
    "wof:placetype":"venue"
},
  "geometry": {"coordinates":[7.3561701775,46.9711647034],"type":"Point"}
}