{
  "type": "Feature",
  "properties": {
    "iso:country":"CH",
    "sg:address":"Widenholzstrasse 1",
    "sg:city":"Wallisellen",
    "sg:orig_category":"Druck ohne Zeitungsdruck Herstellung von Holzstoff, Papier, Karton U Pappe",
    "sg:phone":"+41 56 622 01 02",
    "sg:postcode":"8304",
    "sg:province":"Z\u00fcrich",
    "wof:name":"Sr-siebdruck + Display Ag",
    "wof:placetype":"venue"
},
  "geometry": {"coordinates":[8.2700939178,47.3547363281],"type":"Point"}
}