{
  "type": "Feature",
  "properties": {
    "addr:full":"Stockhornweg 3e Utzenstorf Bern 3427",
    "addr:housenumber":"3e",
    "addr:postcode":"3427",
    "addr:street":"Stockhornweg",
    "iso:country":"CH",
    "sg:address":"Stockhornweg 3e",
    "sg:city":"Utzenstorf",
    "sg:orig_category":"Bauschreinerei Innenausbau",
    "sg:phone":"+41 79 426 49 53",
    "sg:postcode":"3427",
    "sg:province":"Bern",
    "wof:name":"Robert Jau Schreinerei & Innenausbau",
    "wof:placetype":"venue"
},
  "geometry": {"coordinates":[7.545346,47.124893],"type":"Point"}
}