{
  "type": "Feature",
  "properties": {
    "iso:country":"CH",
    "sg:address":"Krauerstrasse 1",
    "sg:city":"Kriens",
    "sg:orig_category":"Schwimmb\u00e4der",
    "sg:phone":"+41 41 630 13 46",
    "sg:postcode":"6010",
    "sg:province":"Luzern",
    "wof:name":"Hergiswiler Badi",
    "wof:placetype":"venue"
},
  "geometry": {"coordinates":[8.3137617111,46.9955024719],"type":"Point"}
}