{
  "type": "Feature",
  "properties": {
    "iso:country":"CH",
    "sg:address":"Herliszelgstrasse 3",
    "sg:city":"Romanshorn",
    "sg:orig_category":"Sonstiger Grosshandel",
    "sg:phone":"+41 71 686 88 88",
    "sg:postcode":"8590",
    "sg:province":"Thurgau",
    "wof:name":"Mahler Edouard Fils Fr\u00e8res Sa",
    "wof:placetype":"venue"
},
  "geometry": {"coordinates":[9.3550653458,47.5621490479],"type":"Point"}
}