{
  "type": "Feature",
  "properties": {
    "iso:country":"CH",
    "sg:address":"Zentralstrasse 55",
    "sg:city":"Neuhausen",
    "sg:orig_category":"Detailhandel mit Bekleidung",
    "sg:postcode":"8212",
    "sg:province":"Schaffhausen",
    "wof:name":"E-venture Systems Sa",
    "wof:placetype":"venue"
},
  "geometry": {"coordinates":[7.153683,46.803745],"type":"Point"}
}