{
  "type": "Feature",
  "properties": {
    "iso:country":"CH",
    "sg:address":"Z\u00fcrichstr. 112 8124 Maur. Postfach",
    "sg:city":"Ebmatingen",
    "sg:orig_category":"Grosshandel mit Getr\u00e4nken",
    "sg:postcode":"8123",
    "sg:province":"Z\u00fcrich",
    "wof:name":"Cave Gevin Frau Edelgard Hiller",
    "wof:placetype":"venue"
},
  "geometry": {"coordinates":[8.6670970917,47.340587616],"type":"Point"}
}