{
  "type": "Feature",
  "properties": {
    "iso:country":"CH",
    "sg:address":"Chemin Des Palettes 22",
    "sg:city":"Grand-lancy",
    "sg:orig_category":"Detailhandel Reparatur von Gebrauchsg\u00fctern Vermietung von Gebrauchsg\u00fctern",
    "sg:phone":"+41 22 794 45 75",
    "sg:postcode":"1212",
    "sg:province":"Gen\u00e8ve",
    "wof:name":"Open Vid\u00e9o Sa",
    "wof:placetype":"venue"
},
  "geometry": {"coordinates":[6.1185178757,46.1767158508],"type":"Point"}
}