{
  "type": "Feature",
  "properties": {
    "iso:country":"CH",
    "sg:address":"Rue Mauverney 21",
    "sg:city":"Gland",
    "sg:orig_category":"W\u00e4scherei U chemische Reinigung",
    "sg:phone":"+41 22 364 80 74",
    "sg:postcode":"1196",
    "sg:province":"Vaud",
    "wof:name":"Pressing De Mauverney, Bilardo Rosa",
    "wof:placetype":"venue"
},
  "geometry": {"coordinates":[6.2762022018,46.4175758362],"type":"Point"}
}