{
  "type": "Feature",
  "properties": {
    "iso:country":"CH",
    "sg:address":"Z\u00fcrcherstrasse 76",
    "sg:city":"Frauenfeld",
    "sg:orig_category":"Sonstiger Grosshandel",
    "sg:postcode":"8500",
    "sg:province":"Thurgau",
    "wof:name":"George Und Partner Import/export",
    "wof:placetype":"venue"
},
  "geometry": {"coordinates":[8.8869895935,47.5524711609],"type":"Point"}
}