{
  "type": "Feature",
  "properties": {
    "iso:country":"CH",
    "sg:address":"Rue De Bernex 270 1233 Bernex. Postfach",
    "sg:city":"Bernex",
    "sg:orig_category":"Wirtschaftspr\u00fcfung, Steuerberatung U Treuhand",
    "sg:postcode":"1233",
    "sg:province":"Gen\u00e8ve",
    "wof:name":"Fiduciaire De Bernex Boschetti Dino & Luca",
    "wof:placetype":"venue"
},
  "geometry": {"coordinates":[6.073636055,46.1758003235],"type":"Point"}
}