{
  "type": "Feature",
  "properties": {
    "iso:country":"CH",
    "sg:address":"Pfadackerstrasse 6",
    "sg:city":"Spreitenbach",
    "sg:orig_category":"Kauf U Verkauf von Immobilien auf eigene Rechnung Vermittlung von Immobilien",
    "sg:phone":"+41 56 402 13 22",
    "sg:postcode":"8957",
    "sg:province":"Aargau",
    "wof:name":"Intercity Verwaltungs-ag",
    "wof:placetype":"venue"
},
  "geometry": {"coordinates":[8.3703260422,47.4245185852],"type":"Point"}
}