{
  "type": "Feature",
  "properties": {
    "addr:full":"St. Johanns-vorstadt 34 4056 Basel. Postfach Basel Basel-Stadt 4004",
    "addr:housenumber":"34",
    "addr:postcode":"4056;4004",
    "addr:street":"Postfach",
    "iso:country":"CH",
    "sg:address":"St. Johanns-vorstadt 34 4056 Basel. Postfach",
    "sg:city":"Basel",
    "sg:orig_category":"Detailhandel mit Beleuchtungs U Haushaltsgegenst\u00e4nden",
    "sg:phone":"+41 33 951 12 07",
    "sg:postcode":"4004",
    "sg:province":"Basel-Stadt",
    "wof:name":"Marie Wenger Haushaltartikel",
    "wof:placetype":"venue"
},
  "geometry": {"coordinates":[8.030176,46.75444],"type":"Point"}
}