{
  "type": "Feature",
  "properties": {
    "iso:country":"CH",
    "sg:address":"Leeberenstrasse 3",
    "sg:city":"Oberstammheim",
    "sg:orig_category":"Physiotherapie",
    "sg:phone":"+41 52 745 16 48",
    "sg:postcode":"8477",
    "sg:province":"Z\u00fcrich",
    "wof:name":"Eva Haas Physiotherapie",
    "wof:placetype":"venue"
},
  "geometry": {"coordinates":[8.8028364182,47.6337928772],"type":"Point"}
}