{
  "type": "Feature",
  "properties": {
    "iso:country":"CH",
    "sg:address":"Wyler",
    "sg:city":"Innertkirchen",
    "sg:classifiers":[
        {
            "category":"Travel",
            "subcategory":"Hotels & Motels",
            "type":"Entertainment"
        }
    ],
    "sg:phone":"+41 33 971 14 27",
    "sg:postcode":"3862",
    "sg:province":"Bern",
    "sg:tags":[
        "hotels",
        "mit",
        "restaurant"
    ],
    "wof:name":"Hotel T\u00e4nnler",
    "wof:placetype":"venue"
},
  "geometry": {"coordinates":[8.2436132431,46.7077522278],"type":"Point"}
}