{
  "type": "Feature",
  "properties": {
    "iso:country":"CH",
    "sg:address":"Viktoriastrasse 30a",
    "sg:city":"Z\u00fcrich",
    "sg:orig_category":"Unclassifiable Establishments",
    "sg:postcode":"8057",
    "sg:province":"Z\u00fcrich",
    "wof:name":"Cafeteria Viktoria Gmbh",
    "wof:placetype":"venue"
},
  "geometry": {"coordinates":[8.5508241653,47.4042510986],"type":"Point"}
}