{
  "type": "Feature",
  "properties": {
    "addr:full":"S\u00e4ntisstrasse 84 W\u00e4denswil Z\u00fcrich 8820",
    "addr:housenumber":"84",
    "addr:postcode":"8820",
    "addr:street":"Saentisstrasse;Zuerich",
    "iso:country":"CH",
    "sg:address":"S\u00e4ntisstrasse 84",
    "sg:city":"W\u00e4denswil",
    "sg:orig_category":"Detailhandel mit Bekleidung",
    "sg:phone":"+41 17808303",
    "sg:postcode":"8820",
    "sg:province":"Z\u00fcrich",
    "wof:name":"Daniel Grieder Handelsagentur",
    "wof:placetype":"venue"
},
  "geometry": {"coordinates":[8.684532,47.219074],"type":"Point"}
}