{
  "type": "Feature",
  "properties": {
    "iso:country":"CH",
    "sg:address":"Route Du Cr\u00eat-de-choully 29",
    "sg:city":"Satigny",
    "sg:orig_category":"Rebbau",
    "sg:phone":"+41 22 753 11 78",
    "sg:postcode":"1242",
    "sg:province":"Gen\u00e8ve",
    "wof:name":"Jean-louis Dugerdil Viticulteur",
    "wof:placetype":"venue"
},
  "geometry": {"coordinates":[6.0287799835,46.2234840393],"type":"Point"}
}