{
  "type": "Feature",
  "properties": {
    "addr:full":"Gartenstrasse 33 Z\u00fcrich Z\u00fcrich 8002",
    "addr:housenumber":"33",
    "addr:postcode":"8002",
    "addr:street":"Gartenstrasse",
    "iso:country":"CH",
    "sg:address":"Gartenstrasse 33",
    "sg:city":"Z\u00fcrich",
    "sg:orig_category":"Advokaturb\u00fcros",
    "sg:phone":"+41 81 833 31 32",
    "sg:postcode":"8002",
    "sg:province":"Z\u00fcrich",
    "wof:name":"Dr.j\u00fcrg W. Leutenegger Advokaturb\u00fcro",
    "wof:placetype":"venue"
},
  "geometry": {"coordinates":[9.838191,46.497066],"type":"Point"}
}