{
  "type": "Feature",
  "properties": {
    "iso:country":"CH",
    "sg:address":"Blegi 14",
    "sg:city":"Rotkreuz",
    "sg:orig_category":"Herstellung von Medikamenten U sonstigen pharmazeutischen Erzeugnissen",
    "sg:postcode":"6343",
    "sg:province":"Zug",
    "wof:name":"Gmk Global Market Knowledge Ag",
    "wof:placetype":"venue"
},
  "geometry": {"coordinates":[8.4355926514,47.1474685669],"type":"Point"}
}