{
  "type": "Feature",
  "properties": {
    "addr:full":"Rosengasse 4 Schaffhausen Schaffhausen 8200",
    "addr:housenumber":"4",
    "addr:postcode":"8200",
    "addr:street":"Rosengasse",
    "iso:country":"CH",
    "sg:address":"Rosengasse 4",
    "sg:city":"Schaffhausen",
    "sg:orig_category":"Datenverarbeitungsdienste",
    "sg:phone":"+41 52 675 55 80",
    "sg:postcode":"8200",
    "sg:province":"Schaffhausen",
    "wof:name":"Multiservice Michael Schmid",
    "wof:placetype":"venue"
},
  "geometry": {"coordinates":[8.634299,47.694134],"type":"Point"}
}