{
  "type": "Feature",
  "properties": {
    "iso:country":"CH",
    "sg:address":"Murtenstrasse 200",
    "sg:city":"Bern",
    "sg:orig_category":"R\u00fcckgewinnung U Vorbereitung f\u00fcr die Wiederverwertung Recycling R\u00fcckgewinnung U Vorbereitung f\u00fcr die",
    "sg:phone":"+41 52 763 37 35",
    "sg:postcode":"3027",
    "sg:province":"Bern",
    "wof:name":"Rr Regio Recycling M\u00fcllheim Ag",
    "wof:placetype":"venue"
},
  "geometry": {"coordinates":[9.0263586044,47.6082954407],"type":"Point"}
}