{
  "type": "Feature",
  "properties": {
    "iso:country":"CH",
    "sg:address":"Reuterg\u00e4ssli",
    "sg:city":"Wangenried",
    "sg:orig_category":"Herstellung von industriellen Prozesssteuerungsanlagen",
    "sg:phone":"+41 32 631 22 38",
    "sg:postcode":"3374",
    "sg:province":"Bern",
    "wof:name":"Faltinek Hans, Mess Und Regeltechnik",
    "wof:placetype":"venue"
},
  "geometry": {"coordinates":[7.663793087,47.2164535522],"type":"Point"}
}