{
  "type": "Feature",
  "properties": {
    "iso:country":"CH",
    "sg:address":"Bahnhofstrasse 25",
    "sg:city":"Zug",
    "sg:orig_category":"Grosshandel mit sonstigen Gebrauchs U Verbrauchsg\u00fctern",
    "sg:phone":"+41 79 688 41 00",
    "sg:postcode":"6300",
    "sg:province":"Zug",
    "wof:name":"Madmi Gmbh, Magic Advertising Mirror",
    "wof:placetype":"venue"
},
  "geometry": {"coordinates":[8.5155982971,47.1701393127],"type":"Point"}
}