{
  "type": "Feature",
  "properties": {
    "iso:country":"CH",
    "sg:address":"1528",
    "sg:city":"Surpierre",
    "sg:orig_category":"Darlehenskassen U Raiffeisenbanken",
    "sg:phone":"+41 26 668 94 94",
    "sg:postcode":"1528",
    "sg:province":"Fribourg",
    "wof:name":"Banque Raiffeisen De La Broye",
    "wof:placetype":"venue"
},
  "geometry": {"coordinates":[6.85046,46.74324],"type":"Point"}
}