{
  "type": "Feature",
  "properties": {
    "iso:country":"CH",
    "sg:address":"Burgzentrum",
    "sg:city":"Thun",
    "sg:orig_category":"Detailhandel mit Haustieren U zoologischem Bedarf",
    "sg:phone":"+41 56 622 49 55",
    "sg:postcode":"3600",
    "sg:province":"Bern",
    "wof:name":"Franz Papis Zoohandlung Freiamt",
    "wof:placetype":"venue"
},
  "geometry": {"coordinates":[8.2738027573,47.3491363525],"type":"Point"}
}