{
  "type": "Feature",
  "properties": {
    "iso:country":"CH",
    "sg:address":"Unterbernau 20",
    "sg:city":"Leibstadt",
    "sg:orig_category":"Elektroinstallation",
    "sg:phone":"+41 56 247 13 40",
    "sg:postcode":"5325",
    "sg:province":"Aargau",
    "wof:name":"Meili Roger Baumontagen",
    "wof:placetype":"venue"
},
  "geometry": {"coordinates":[8.1698045731,47.5939865112],"type":"Point"}
}