{
  "type": "Feature",
  "properties": {
    "addr:full":"Baselstrasse 6 Arlesheim Basel-Landschaft 4144",
    "addr:housenumber":"6",
    "addr:postcode":"4144",
    "addr:street":"Baselstrasse",
    "iso:country":"CH",
    "sg:address":"Baselstrasse 6",
    "sg:city":"Arlesheim",
    "sg:classifiers":[
        {
            "category":"Internet Cafe",
            "subcategory":"None",
            "type":"Food & Drink"
        }
    ],
    "sg:postcode":"4144",
    "sg:province":"Basel-Landschaft",
    "sg:tags":[
        "datenverarbeitungsdienste",
        "provider"
    ],
    "wof:name":"Dataship Gmbh Internet",
    "wof:placetype":"venue"
},
  "geometry": {"coordinates":[7.62111,47.496456],"type":"Point"}
}