{
  "type": "Feature",
  "properties": {
    "iso:country":"CH",
    "sg:address":"Chemin Du Point-du-jour 2",
    "sg:city":"Vevey",
    "sg:orig_category":"Maler U Glasergewerbe Stukkateurgewerbe, Gipserei U Verputzerei",
    "sg:phone":"+41 21 922 93 91",
    "sg:postcode":"1800",
    "sg:province":"Vaud",
    "wof:name":"Pahud Jean-philippe.",
    "wof:placetype":"venue"
},
  "geometry": {"coordinates":[6.8480391502,46.4622917175],"type":"Point"}
}