{
  "type": "Feature",
  "properties": {
    "iso:country":"CH",
    "sg:address":"Fischmattstrasse 1",
    "sg:city":"Buochs",
    "sg:orig_category":"Detailhandel mit Fleisch U Fleischwaren",
    "sg:phone":"+41 41 620 11 28",
    "sg:postcode":"6374",
    "sg:province":"Nidwalden",
    "wof:name":"Metzgerei Bl\u00e4ttler Gmbh",
    "wof:placetype":"venue"
},
  "geometry": {"coordinates":[8.4200048447,46.975479126],"type":"Point"}
}