{
  "type": "Feature",
  "properties": {
    "addr:full":"Hauptstrasse 1 Hemmiken Basel-Landschaft 4465",
    "addr:housenumber":"1",
    "addr:postcode":"4465",
    "addr:street":"Hauptstrasse",
    "iso:country":"CH",
    "sg:address":"Hauptstrasse 1",
    "sg:city":"Hemmiken",
    "sg:classifiers":[
        {
            "category":"Banks & Credit Unions",
            "subcategory":"Bank",
            "type":"Services"
        }
    ],
    "sg:phone":"+41 61 981 54 52",
    "sg:postcode":"4465",
    "sg:province":"Basel-Landschaft",
    "wof:name":"Raiffeisenbank Hemmiken",
    "wof:placetype":"venue"
},
  "geometry": {"coordinates":[7.89253,47.488071],"type":"Point"}
}