{
  "type": "Feature",
  "properties": {
    "addr:full":"Kapuzinerweg 14 Luzern Luzern 6006",
    "addr:housenumber":"14",
    "addr:postcode":"6006",
    "addr:street":"Kapuzinerweg",
    "iso:country":"CH",
    "sg:address":"Kapuzinerweg 14",
    "sg:city":"Luzern",
    "sg:classifiers":[
        {
            "category":"Social Services",
            "subcategory":"Retirement Home",
            "type":"Services"
        }
    ],
    "sg:phone":"+41 41 429 29 29",
    "sg:postcode":"6006",
    "sg:province":"Luzern",
    "sg:tags":[
        "pflegeheime",
        "u",
        "alters"
    ],
    "wof:name":"Betagtenzentrum Wesemlin",
    "wof:placetype":"venue"
},
  "geometry": {"coordinates":[8.313179,47.060123],"type":"Point"}
}