{
  "type": "Feature",
  "properties": {
    "iso:country":"CH",
    "sg:address":"Zone Industrielle Le Tr\u00e9si 9b 1028 Pr\u00e9verenges Case Postale",
    "sg:city":"Pr\u00e9verenges",
    "sg:orig_category":"Grosshandel mit sonstigen Maschinen U Ausr\u00fcstungen f\u00fcr Industrie, Handel U Schiffahrt Herstellung vo",
    "sg:phone":"+41 21 801 21 77",
    "sg:postcode":"1028",
    "sg:province":"Vaud",
    "wof:name":"Fonseca Friederich Technologies S\u00e0rl Machines Pour Emboutaillage, Articles De Robinetterie Et Outils; Fabrication Et Vente",
    "wof:placetype":"venue"
},
  "geometry": {"coordinates":[6.5299391747,46.522819519],"type":"Point"}
}