{
  "type": "Feature",
  "properties": {
    "iso:country":"CH",
    "sg:address":"Im Schlossacker",
    "sg:city":"Oberneunforn",
    "sg:orig_category":"Physiotherapie",
    "sg:phone":"+41 52 745 21 75",
    "sg:postcode":"8526",
    "sg:province":"Thurgau",
    "wof:name":"Eleonore Munz Physiotherapie",
    "wof:placetype":"venue"
},
  "geometry": {"coordinates":[8.7654943466,47.6080703735],"type":"Point"}
}