{
  "type": "Feature",
  "properties": {
    "iso:country":"CH",
    "sg:address":"Geissacher 2",
    "sg:city":"Egolzwil",
    "sg:orig_category":"Satzherstellung U Reproduktion",
    "sg:postcode":"6243",
    "sg:province":"Luzern",
    "wof:name":"Amb\u00fchl Satz Und Gestaltung Gmbh",
    "wof:placetype":"venue"
},
  "geometry": {"coordinates":[8.0037994385,47.1869812012],"type":"Point"}
}