{
  "type": "Feature",
  "properties": {
    "iso:country":"CH",
    "sg:address":"1317",
    "sg:city":"Orny",
    "sg:orig_category":"Non-Classified Establishments",
    "sg:postcode":"1317",
    "sg:province":"Vaud",
    "wof:name":"Olivier Pilloud",
    "wof:placetype":"venue"
},
  "geometry": {"coordinates":[5.1808700562,45.8973388672],"type":"Point"}
}