{
  "type": "Feature",
  "properties": {
    "iso:country":"CH",
    "sg:address":"Zur L\u00e4rche",
    "sg:city":"Oberr\u00fcti",
    "sg:orig_category":"Politische Parteien FDP",
    "sg:phone":"+41 41 787 22 93",
    "sg:postcode":"5647",
    "sg:province":"Aargau",
    "wof:name":"Fdp Ortspartei Oberr\u00fcti",
    "wof:placetype":"venue"
},
  "geometry": {"coordinates":[8.3944149017,47.1654052734],"type":"Point"}
}