{
  "type": "Feature",
  "properties": {
    "iso:country":"CH",
    "sg:address":"1937",
    "sg:city":"Orsi\u00e8res",
    "sg:classifiers":[
        {
            "category":"Travel",
            "subcategory":"Hotels & Motels",
            "type":"Entertainment"
        }
    ],
    "sg:phone":"+41 21 841 11 94",
    "sg:postcode":"1937",
    "sg:province":"Valais",
    "sg:tags":[
        "hotels",
        "mit",
        "restaurant"
    ],
    "wof:name":"H\u00f4tel Terminus",
    "wof:placetype":"venue"
},
  "geometry": {"coordinates":[6.3183259964,46.6652145386],"type":"Point"}
}