{
  "type": "Feature",
  "properties": {
    "iso:country":"CH",
    "sg:address":"Kirchstrasse 16a",
    "sg:city":"Dietikon",
    "sg:orig_category":"Detektivb\u00fcros U \u00dcberwachung Technische, physikalische U chemische Untersuchung",
    "sg:phone":"+41 17423115",
    "sg:postcode":"8953",
    "sg:province":"Z\u00fcrich",
    "wof:name":"Oeko-line Gmbh",
    "wof:placetype":"venue"
},
  "geometry": {"coordinates":[8.4030570984,47.4056510925],"type":"Point"}
}