{
  "type": "Feature",
  "properties": {
    "iso:country":"CH",
    "sg:address":"Via San Salvatore 11",
    "sg:city":"Paradiso",
    "sg:orig_category":"Vermietung U Verpachtung von eigenen Immobilien",
    "sg:postcode":"6900",
    "sg:province":"Ticino",
    "wof:name":"Jobe Sa",
    "wof:placetype":"venue"
},
  "geometry": {"coordinates":[8.9454183578,45.9915084839],"type":"Point"}
}