{
  "type": "Feature",
  "properties": {
    "iso:country":"CH",
    "sg:address":"Battenhusstrasse 9",
    "sg:city":"Lustm\u00fchle",
    "sg:orig_category":"Zahnarztpraxen",
    "sg:phone":"+41 71 333 10 39",
    "sg:postcode":"9062",
    "sg:province":"Appenzell Ausserrhoden",
    "wof:name":"Dres Med.dent.s.& M. Mijatovic Zahn\u00e4rzte",
    "wof:placetype":"venue"
},
  "geometry": {"coordinates":[9.3584604263,47.3988838196],"type":"Point"}
}