{
  "type": "Feature",
  "properties": {
    "iso:country":"CH",
    "sg:address":"Grienstrasse 8",
    "sg:city":"Niederlenz",
    "sg:orig_category":"Vereine Gesang",
    "sg:phone":"+41 62 891 40 77",
    "sg:postcode":"5702",
    "sg:province":"Aargau",
    "wof:name":"C\u00e4cilienverein Lenzburg",
    "wof:placetype":"venue"
},
  "geometry": {"coordinates":[8.1734371185,47.4023170471],"type":"Point"}
}