{
  "type": "Feature",
  "properties": {
    "iso:country":"CH",
    "sg:address":"Kirchgasse 1",
    "sg:city":"Grabs",
    "sg:orig_category":"Unclassifiable Establishments",
    "sg:postcode":"9472",
    "sg:province":"St. Gallen",
    "wof:name":"Summit Bk Holding Gmbh",
    "wof:placetype":"venue"
},
  "geometry": {"coordinates":[9.4460268021,47.180847168],"type":"Point"}
}