{
  "type": "Feature",
  "properties": {
    "iso:country":"CH",
    "sg:address":"Kasernenstrasse 123",
    "sg:city":"B\u00fclach",
    "sg:classifiers":[
        {
            "category":"Restaurant",
            "type":"Food & Drink"
        }
    ],
    "sg:phone":"+41 18601319",
    "sg:postcode":"8180",
    "sg:province":"Z\u00fcrich",
    "wof:name":"Restaurant Heuschober",
    "wof:placetype":"venue"
},
  "geometry": {"coordinates":[8.5261297226,47.5130386353],"type":"Point"}
}