{
  "type": "Feature",
  "properties": {
    "iso:country":"CH",
    "sg:address":"Dorneckstrasse 48",
    "sg:city":"Dornach",
    "sg:orig_category":"Kauf U Verkauf von Immobilien auf eigene Rechnung",
    "sg:phone":"+41 79 320 23 60",
    "sg:postcode":"4143",
    "sg:province":"Solothurn",
    "wof:name":"Concept Beratungen + Verwaltungen Schnellmann Bruno",
    "wof:placetype":"venue"
},
  "geometry": {"coordinates":[7.6182980537,47.4807701111],"type":"Point"}
}