{
  "type": "Feature",
  "properties": {
    "iso:country":"CH",
    "sg:address":"Gotthardstr. 7 6430 Schwyz. Postfach",
    "sg:city":"Ibach",
    "sg:orig_category":"Instandhaltung U Reparatur von Automobilen",
    "sg:phone":"+41 71 766 12 85",
    "sg:postcode":"6438",
    "sg:province":"Schwyz",
    "wof:name":"Kobler Hans Autospritzwerk",
    "wof:placetype":"venue"
},
  "geometry": {"coordinates":[9.5393848419,47.2958068848],"type":"Point"}
}