{
  "type": "Feature",
  "properties": {
    "addr:full":"Rue De L' Industrie 7 Les Ponts De Martel Neuch\u00e2tel 2316",
    "addr:housenumber":"7",
    "addr:postcode":"2316",
    "addr:street":"Rue De L ' Industrie;Martel",
    "iso:country":"CH",
    "sg:address":"Rue De L' Industrie 7",
    "sg:city":"Les Ponts De Martel",
    "sg:classifiers":[
        {
            "category":"Banks & Credit Unions",
            "subcategory":"Bank",
            "type":"Services"
        }
    ],
    "sg:phone":"+41 32 937 12 53",
    "sg:postcode":"2316",
    "sg:province":"Neuch\u00e2tel",
    "wof:name":"Raiffeisen",
    "wof:placetype":"venue"
},
  "geometry": {"coordinates":[6.731793,46.99884],"type":"Point"}
}