{
  "type": "Feature",
  "properties": {
    "iso:country":"CH",
    "sg:address":"Seestrasse 14a 5432 Neuenhof. Postfach",
    "sg:city":"Z\u00fcrich",
    "sg:orig_category":"Softwareentwicklung U beratung",
    "sg:phone":"+41 13071600",
    "sg:postcode":"8000",
    "sg:province":"Z\u00fcrich",
    "wof:name":"Peregrine Systems Gmbh",
    "wof:placetype":"venue"
},
  "geometry": {"coordinates":[8.3241167068,47.4556694031],"type":"Point"}
}