{
  "type": "Feature",
  "properties": {
    "iso:country":"CH",
    "sg:address":"Bellevue 3792 Saanen. Postfach 159",
    "sg:city":"Saanen",
    "sg:orig_category":"Sonstige mit Sport verbundene T\u00e4tigkeiten",
    "sg:postcode":"3792",
    "sg:province":"Bern",
    "wof:name":"Ballonteam Rho, Inhaber Ebneter Sepp Heissluftballon; Bef\u00f6rderung Usw.",
    "wof:placetype":"venue"
},
  "geometry": {"coordinates":[9.3420143127,47.4037513733],"type":"Point"}
}