{
  "type": "Feature",
  "properties": {
    "iso:country":"CH",
    "sg:address":"Hofmattstrasse 35a",
    "sg:city":"Huttwil",
    "sg:orig_category":"Detailhandel mit Antiquit\u00e4ten Sonstige k\u00fcnstlerische U schriftstellerische T\u00e4tigkeiten U Darbietunge",
    "sg:phone":"+41 62 962 36 72",
    "sg:postcode":"4950",
    "sg:province":"Bern",
    "wof:name":"Thomas Sch\u00e4r Sch\u00e4r's Restaurationen",
    "wof:placetype":"venue"
},
  "geometry": {"coordinates":[7.843266,47.113419],"type":"Point"}
}