{
  "type": "Feature",
  "properties": {
    "iso:country":"CH",
    "sg:address":"Hinterdorf",
    "sg:city":"Valens",
    "sg:orig_category":"G\u00fcterbef\u00f6rderung im Strassenverkehr",
    "sg:phone":"+41 56 241 11 28",
    "sg:postcode":"7317",
    "sg:province":"St. Gallen",
    "wof:name":"Robert Loser",
    "wof:placetype":"venue"
},
  "geometry": {"coordinates":[8.327662468,47.5212860107],"type":"Point"}
}