{
  "type": "Feature",
  "properties": {
    "iso:country":"CH",
    "sg:address":"Lettenstrasse 7",
    "sg:city":"Rotkreuz",
    "sg:classifiers":[
        {
            "category":"Internet Cafe",
            "subcategory":"None",
            "type":"Food & Drink"
        }
    ],
    "sg:postcode":"6343",
    "sg:province":"Zug",
    "sg:tags":[
        "informatikdienste",
        "provider"
    ],
    "wof:name":"Beat Z'graggen 111 Internet",
    "wof:placetype":"venue"
},
  "geometry": {"coordinates":[8.4318199158,47.1470794678],"type":"Point"}
}