{
  "type": "Feature",
  "properties": {
    "iso:country":"CH",
    "sg:address":"Andresenschachen 24",
    "sg:city":"Gretzenbach",
    "sg:orig_category":"Mit Sport verbundene T\u00e4tigkeiten",
    "sg:phone":"+41 62 291 15 35",
    "sg:postcode":"5014",
    "sg:province":"Solothurn",
    "wof:name":"Ernst Keller Reitschule Kipp",
    "wof:placetype":"venue"
},
  "geometry": {"coordinates":[7.9741101265,47.3655967712],"type":"Point"}
}