{
  "type": "Feature",
  "properties": {
    "iso:country":"CH",
    "sg:address":"Bahnhofplatz 26",
    "sg:city":"Zofingen",
    "sg:orig_category":"RESTAURANTS: TEA-ROOMS",
    "sg:phone":"+41 62 751 14 07",
    "sg:postcode":"4800",
    "sg:province":"Aargau",
    "wof:name":"Bahnhof-buffet, Pizzeria Al Cuore Matto Baiocco Emidia",
    "wof:placetype":"venue"
},
  "geometry": {"coordinates":[7.9440598488,47.2883071899],"type":"Point"}
}