{
  "type": "Feature",
  "properties": {
    "iso:country":"CH",
    "sg:address":"Unterprapafier 6",
    "sg:city":"Tr\u00fcbbach",
    "sg:orig_category":"Kosmetikinstitute",
    "sg:phone":"+41 81 783 21 77",
    "sg:postcode":"9477",
    "sg:province":"St. Gallen",
    "wof:name":"Vreni Bose Kosmetikinstitut",
    "wof:placetype":"venue"
},
  "geometry": {"coordinates":[9.4783277512,47.0730705261],"type":"Point"}
}