{
  "type": "Feature",
  "properties": {
    "iso:country":"CH",
    "sg:address":"Meriedweg 17",
    "sg:city":"Niederwangen",
    "sg:classifiers":[
        {
            "category":"Government",
            "subcategory":"Post Office",
            "type":"Public Place"
        }
    ],
    "sg:phone":"+41 31 981 30 88",
    "sg:postcode":"3172",
    "sg:province":"Bern",
    "sg:tags":[
        "pipe",
        "part",
        "bent"
    ],
    "wof:name":"Schenk Metall",
    "wof:placetype":"venue"
},
  "geometry": {"coordinates":[7.372839,46.920647],"type":"Point"}
}