{
  "type": "Feature",
  "properties": {
    "iso:country":"CH",
    "sg:address":"St. Alban-vorstadt 33",
    "sg:city":"Basel",
    "sg:orig_category":"Detailhandel mit Uhren U Schmuck",
    "sg:phone":"+41 61 681 15 05",
    "sg:postcode":"4052",
    "sg:province":"Basel-Stadt",
    "wof:name":"Raphael Schicker Goldschmied Atelier",
    "wof:placetype":"venue"
},
  "geometry": {"coordinates":[7.5966858864,47.5546684265],"type":"Point"}
}