{
  "type": "Feature",
  "properties": {
    "iso:country":"CH",
    "sg:address":"Buchzopfen 9",
    "sg:city":"Lyss",
    "sg:orig_category":"Erschliessung von Grundst\u00fccken",
    "sg:postcode":"3250",
    "sg:province":"Bern",
    "wof:name":"Wohnbaugen.buchzopfen Lyss",
    "wof:placetype":"venue"
},
  "geometry": {"coordinates":[7.3031468391,47.0805244446],"type":"Point"}
}