{
  "type": "Feature",
  "properties": {
    "addr:full":"Avenue Du 1er-mars 20 Neuch\u00e2tel Neuch\u00e2tel 2000",
    "addr:housenumber":"20",
    "addr:postcode":"2000",
    "addr:street":"Avenue Du 1Er-Mars",
    "iso:country":"CH",
    "sg:address":"Avenue Du 1er-mars 20",
    "sg:city":"Neuch\u00e2tel",
    "sg:orig_category":"Architektur U Ingenieurb\u00fcros",
    "sg:phone":"+41 32 724 90 24",
    "sg:postcode":"2000",
    "sg:province":"Neuch\u00e2tel",
    "wof:name":"P Plus Petermann & Philippin",
    "wof:placetype":"venue"
},
  "geometry": {"coordinates":[6.937453,46.993534],"type":"Point"}
}