{
  "type": "Feature",
  "properties": {
    "iso:country":"CH",
    "sg:address":"Hauptstrasse 52",
    "sg:city":"Meisterschwanden",
    "sg:orig_category":"B\u00e4ckereien Konditoreien",
    "sg:phone":"+41 56 443 12 51",
    "sg:postcode":"5616",
    "sg:province":"Aargau",
    "wof:name":"Karl & Barbara Richner B\u00e4ckerei Konditorei Confiserie",
    "wof:placetype":"venue"
},
  "geometry": {"coordinates":[8.146822,47.438744],"type":"Point"}
}