{
  "type": "Feature",
  "properties": {
    "iso:country":"CH",
    "sg:address":"R\u00e9sidence Belv\u00e9d\u00e8re B5",
    "sg:city":"St-cergue",
    "sg:orig_category":"Immobilienwesen Wirtschaftspr\u00fcfung, Steuerberatung U Treuhand",
    "sg:phone":"+41 22 360 82 00",
    "sg:postcode":"1264",
    "sg:province":"Vaud",
    "wof:name":"Dynagest Sa",
    "wof:placetype":"venue"
},
  "geometry": {"coordinates":[6.1575808525,46.4464187622],"type":"Point"}
}