{
  "type": "Feature",
  "properties": {
    "iso:country":"CH",
    "sg:address":"Viale Stazione 23",
    "sg:city":"Bellinzona",
    "sg:orig_category":"Detailhandel mit Textilien",
    "sg:phone":"+41 91 825 56 52",
    "sg:postcode":"6500",
    "sg:province":"Ticino",
    "wof:name":"Celestino Macconi Sa",
    "wof:placetype":"venue"
},
  "geometry": {"coordinates":[9.0267553329,46.1941986084],"type":"Point"}
}