{
  "type": "Feature",
  "properties": {
    "iso:country":"CH",
    "sg:address":"Kanalgasse 28",
    "sg:city":"Biel/bienne",
    "sg:orig_category":"Werbeagenturen",
    "sg:phone":"+41 32 323 73 14",
    "sg:postcode":"2502",
    "sg:province":"Bern",
    "wof:name":"Ren\u00e9 Tardit Werbung",
    "wof:placetype":"venue"
},
  "geometry": {"coordinates":[7.2468218803,47.1405639648],"type":"Point"}
}