{
  "type": "Feature",
  "properties": {
    "iso:country":"CH",
    "sg:address":"4805",
    "sg:city":"Brittnau",
    "sg:orig_category":"Interessenvertretungen",
    "sg:postcode":"4805",
    "sg:province":"Aargau",
    "wof:name":"B\u00fcrgerliche Museums-stiftung Stein Am Rhein",
    "wof:placetype":"venue"
},
  "geometry": {"coordinates":[8.8598861694,47.6590652466],"type":"Point"}
}