{
  "type": "Feature",
  "properties": {
    "iso:country":"CH",
    "sg:address":"Schiltistr. 5",
    "sg:city":"Flurlingen",
    "sg:orig_category":"Herstellung von sonstigen Holzwaren",
    "sg:postcode":"8247",
    "sg:province":"Z\u00fcrich",
    "wof:name":"Von Niederh\u00e4usern Willy.",
    "wof:placetype":"venue"
},
  "geometry": {"coordinates":[8.628657341,47.6875076294],"type":"Point"}
}