{
  "type": "Feature",
  "properties": {
    "iso:country":"CH",
    "sg:address":"Zaunweg 6",
    "sg:city":"Biel/bienne",
    "sg:orig_category":"Handelsvermittlung U Grosshandel",
    "sg:phone":"+41 32 344 29 84",
    "sg:postcode":"2502",
    "sg:province":"Bern",
    "wof:name":"Ted Ag Trade Exchange Development",
    "wof:placetype":"venue"
},
  "geometry": {"coordinates":[7.2630519867,47.1461868286],"type":"Point"}
}