{
  "type": "Feature",
  "properties": {
    "iso:country":"CH",
    "sg:address":"Petit-ch\u00eane Rue Du 38",
    "sg:city":"Lausanne",
    "sg:orig_category":"Allgemeiner Hoch U Tiefbau",
    "sg:phone":"+41 21 632 89 16",
    "sg:postcode":"1003",
    "sg:province":"Vaud",
    "wof:name":"Traevil Sa",
    "wof:placetype":"venue"
},
  "geometry": {"coordinates":[6.628999,46.517796],"type":"Point"}
}