{
  "type": "Feature",
  "properties": {
    "iso:country":"CH",
    "sg:address":"Dorfstrasse 14",
    "sg:city":"Ueken",
    "sg:orig_category":"Unclassifiable Establishments",
    "sg:postcode":"5028",
    "sg:province":"Aargau",
    "wof:name":"Dr. Gaston Von Glutz Kommunikationsberatung",
    "wof:placetype":"venue"
},
  "geometry": {"coordinates":[8.0468740463,47.4841880798],"type":"Point"}
}