{
  "type": "Feature",
  "properties": {
    "iso:country":"CH",
    "sg:address":"Sagen",
    "sg:city":"Pfaffnau",
    "sg:orig_category":"Non-Classified Establishments",
    "sg:postcode":"6264",
    "sg:province":"Luzern",
    "wof:name":"Hans Schwizer Transporte & Logistik",
    "wof:placetype":"venue"
},
  "geometry": {"coordinates":[7.8928499222,47.2326812744],"type":"Point"}
}