{
  "type": "Feature",
  "properties": {
    "iso:country":"CH",
    "sg:address":"Sevogelstrasse 34",
    "sg:city":"Basel",
    "sg:orig_category":"Markt U Meinungsforschung",
    "sg:phone":"+41 61 312 97 48",
    "sg:postcode":"4052",
    "sg:province":"Basel-Stadt",
    "wof:name":"Ipm R\u00fcst",
    "wof:placetype":"venue"
},
  "geometry": {"coordinates":[7.6043839455,47.551574707],"type":"Point"}
}