{
  "type": "Feature",
  "properties": {
    "iso:country":"CH",
    "sg:address":"St. Adrianstrasse 22c",
    "sg:city":"Walchwil",
    "sg:orig_category":"Grosshandel mit Maschinen U Ausr\u00fcstungen",
    "sg:phone":"+41 41 758 24 30",
    "sg:postcode":"6318",
    "sg:province":"Zug",
    "wof:name":"Semi Supply Ag",
    "wof:placetype":"venue"
},
  "geometry": {"coordinates":[8.5233650208,47.0908889771],"type":"Point"}
}