{
  "type": "Feature",
  "properties": {
    "iso:country":"CH",
    "sg:address":"Rue Du Coll\u00e8ge 2",
    "sg:city":"Avenches",
    "sg:orig_category":"Geb\u00e4ude, Wohnungsreinigung Reinigungsgewerbe",
    "sg:phone":"+41 26 675 40 31",
    "sg:postcode":"1580",
    "sg:province":"Vaud",
    "wof:name":"Belle-fontaine, Sansonnens P.",
    "wof:placetype":"venue"
},
  "geometry": {"coordinates":[7.0408630371,46.8804550171],"type":"Point"}
}