{
  "type": "Feature",
  "properties": {
    "iso:country":"CH",
    "sg:address":"Kirchrain 25",
    "sg:city":"H\u00e4gendorf",
    "sg:orig_category":"Grosshandel mit Nahrungsmitteln, Getr\u00e4nken U Tabakwaren ohne ausgepr\u00e4gten Schwerpunkt",
    "sg:phone":"+41 62 216 12 53",
    "sg:postcode":"4614",
    "sg:province":"Solothurn",
    "wof:name":"Studer Albert.",
    "wof:placetype":"venue"
},
  "geometry": {"coordinates":[7.8446650505,47.3359527588],"type":"Point"}
}