{
  "type": "Feature",
  "properties": {
    "iso:country":"CH",
    "sg:address":"Seidengasse 43",
    "sg:city":"Meilen",
    "sg:orig_category":"Detailhandel mit Getr\u00e4nken Grosshandel mit Getr\u00e4nken",
    "sg:phone":"+41 81 416 55 10",
    "sg:postcode":"8706",
    "sg:province":"Z\u00fcrich",
    "wof:name":"Scala Vini, K\u00fcnzli Christoph",
    "wof:placetype":"venue"
},
  "geometry": {"coordinates":[9.8360099792,46.8027687073],"type":"Point"}
}