{
  "type": "Feature",
  "properties": {
    "addr:full":"Via Stazione 8/10 Muralto Ticino 6600",
    "addr:housenumber":"8 / 10",
    "addr:postcode":"6600",
    "addr:street":"Via Stazione",
    "iso:country":"CH",
    "sg:address":"Via Stazione 8/10",
    "sg:city":"Muralto",
    "sg:orig_category":"Detailhandel mit Antiquit\u00e4ten U Gebrauchtwaren in Verkaufsr\u00e4umen Tapezierer/Dekorateure",
    "sg:phone":"+41 91 743 81 42",
    "sg:postcode":"6600",
    "sg:province":"Ticino",
    "wof:name":"Arredamento D'interni Zingrich",
    "wof:placetype":"venue"
},
  "geometry": {"coordinates":[8.801773,46.173176],"type":"Point"}
}