{
  "type": "Feature",
  "properties": {
    "iso:country":"CH",
    "sg:address":"Trevano Via 2 6900 Lugano. Postfach",
    "sg:city":"Lugano",
    "sg:orig_category":"Sonstige Kultur U Unterhaltungseinrichtungen",
    "sg:postcode":"6900",
    "sg:province":"Ticino",
    "wof:name":"Cirsa Casin\u00f2 Sa Esercizio Di Grandi Giochi Ecc",
    "wof:placetype":"venue"
},
  "geometry": {"coordinates":[8.9551677704,46.0127220154],"type":"Point"}
}