{
  "type": "Feature",
  "properties": {
    "iso:country":"CH",
    "sg:address":"Stationsstrasse 16 9212 Arnegg. Postfach",
    "sg:city":"Arnegg",
    "sg:orig_category":"Herstellung von konfektionierten Textilwaren ohne Bekleidung",
    "sg:postcode":"9212",
    "sg:province":"St. Gallen",
    "wof:name":"Steiner - Ehrbar Peter Ag",
    "wof:placetype":"venue"
},
  "geometry": {"coordinates":[9.2541265488,47.4426116943],"type":"Point"}
}