{
  "type": "Feature",
  "properties": {
    "iso:country":"CH",
    "sg:address":"Hauptstrasse 23",
    "sg:city":"D\u00f6ttingen",
    "sg:orig_category":"Schreib U \u00dcbersetzungsb\u00fcros",
    "sg:phone":"+41 56 245 11 19",
    "sg:postcode":"5312",
    "sg:province":"Aargau",
    "wof:name":"Locsoft Language Management Gmbh",
    "wof:placetype":"venue"
},
  "geometry": {"coordinates":[8.2560596466,47.5730781555],"type":"Point"}
}