{
  "type": "Feature",
  "properties": {
    "iso:country":"CH",
    "sg:address":"Z\u00fcrichbergstrasse 66",
    "sg:city":"Z\u00fcrich",
    "sg:orig_category":"Unternehmensberatung Werbeberatung",
    "sg:phone":"+41 12518510",
    "sg:postcode":"8044",
    "sg:province":"Z\u00fcrich",
    "wof:name":"Communicat Andr\u00e9 Sch\u00e4ppi & Elisabeth Ernst Sch\u00e4ppi",
    "wof:placetype":"venue"
},
  "geometry": {"coordinates":[8.5597076416,47.3759803772],"type":"Point"}
}