{
  "type": "Feature",
  "properties": {
    "iso:country":"CH",
    "sg:address":"Oristalstrasse 43",
    "sg:city":"Liestal",
    "sg:orig_category":"Sportvereine Sch\u00fctzen",
    "sg:phone":"+41 61 921 13 35",
    "sg:postcode":"4410",
    "sg:province":"Basel-Landschaft",
    "wof:name":"Freisch\u00fctzen Liestal",
    "wof:placetype":"venue"
},
  "geometry": {"coordinates":[7.7309799194,47.4803543091],"type":"Point"}
}