{
  "type": "Feature",
  "properties": {
    "iso:country":"CH",
    "sg:address":"Schl\u00f6sslistrasse 8",
    "sg:city":"Biel/bienne",
    "sg:orig_category":"Detailhandel mit M\u00f6beln Detailhandel mit M\u00f6beln U Haushaltsgegenst\u00e4nden",
    "sg:phone":"+41 32 341 29 04",
    "sg:postcode":"2504",
    "sg:province":"Bern",
    "wof:name":"Int\u00e9rieur Graf J\u00fcrg",
    "wof:placetype":"venue"
},
  "geometry": {"coordinates":[7.2670178413,47.1515769958],"type":"Point"}
}