{
  "type": "Feature",
  "properties": {
    "iso:country":"CH",
    "sg:address":"La Rosi\u00e8re",
    "sg:city":"Orsi\u00e8res",
    "sg:orig_category":"Grosshandel mit lebenden Tieren",
    "sg:phone":"+41 79 347 60 21",
    "sg:postcode":"1937",
    "sg:province":"Valais",
    "wof:name":"Philippe Tornay Commerce De B\u00e9tail",
    "wof:placetype":"venue"
},
  "geometry": {"coordinates":[7.1578121185,46.0486869812],"type":"Point"}
}