{
  "type": "Feature",
  "properties": {
    "iso:country":"CH",
    "sg:address":"Seeacker 3",
    "sg:city":"Rottenschwil",
    "sg:orig_category":"Herstellung von Karosserien U Anh\u00e4ngern",
    "sg:phone":"+41 56 634 26 50",
    "sg:postcode":"8919",
    "sg:province":"Aargau",
    "wof:name":"Stadelmann Zelte Gmbh",
    "wof:placetype":"venue"
},
  "geometry": {"coordinates":[8.3650541306,47.3167572021],"type":"Point"}
}