{
  "type": "Feature",
  "properties": {
    "iso:country":"CH",
    "sg:address":"Schl\u00f6sslistrasse",
    "sg:city":"Ebikon",
    "sg:orig_category":"Primarschulen",
    "sg:phone":"+41 41 440 87 34",
    "sg:postcode":"6030",
    "sg:province":"Luzern",
    "wof:name":"Primarschule Sagen",
    "wof:placetype":"venue"
},
  "geometry": {"coordinates":[8.3367519379,47.0775527954],"type":"Point"}
}