{
  "type": "Feature",
  "properties": {
    "iso:country":"CH",
    "sg:address":"Route La Claie-aux-moines 15 1073 Savigny Case Postale 56",
    "sg:city":"Savigny",
    "sg:orig_category":"Sanit\u00e4r, Heizungs U L\u00fcftungsinstallation",
    "sg:phone":"+41 21 784 24 44",
    "sg:postcode":"1073",
    "sg:province":"Vaud",
    "wof:name":"Rlco Rossi Line Construction Sa",
    "wof:placetype":"venue"
},
  "geometry": {"coordinates":[6.7130661011,46.5415763855],"type":"Point"}
}