{
  "type": "Feature",
  "properties": {
    "iso:country":"CH",
    "sg:address":"Chemin Du Noir-bois 734 2853 Courfaivre Case Postale 89",
    "sg:city":"Courfaivre",
    "sg:orig_category":"Herstellung U Zusammensetzung von Uhren Herstellung von Uhren",
    "sg:phone":"+41 32 959 19 19",
    "sg:postcode":"2853",
    "sg:province":"Jura",
    "wof:name":"Mica Sa",
    "wof:placetype":"venue"
},
  "geometry": {"coordinates":[7.0049629211,47.2118835449],"type":"Point"}
}