{
  "type": "Feature",
  "properties": {
    "iso:country":"CH",
    "sg:address":"Casu 7164 Dardin. Postfach",
    "sg:city":"Danis",
    "sg:orig_category":"Sonstige mit der Informatik verbundene T\u00e4tigkeiten",
    "sg:postcode":"7163",
    "sg:province":"Graubunden",
    "wof:name":"Its 2000plus Gmbh",
    "wof:placetype":"venue"
},
  "geometry": {"coordinates":[9.048781395,46.7593078613],"type":"Point"}
}