{
  "type": "Feature",
  "properties": {
    "iso:country":"CH",
    "sg:address":"Dorfstrasse 20 4222 Zwingen. Postfach",
    "sg:city":"Basel",
    "sg:orig_category":"Markt U Meinungsforschung",
    "sg:phone":"+41 71 274 66 68",
    "sg:postcode":"4013",
    "sg:province":"Basel-Stadt",
    "wof:name":"Ms Marketing Strategien Ag",
    "wof:placetype":"venue"
},
  "geometry": {"coordinates":[9.3504571915,47.4141807556],"type":"Point"}
}