{
  "type": "Feature",
  "properties": {
    "iso:country":"CH",
    "sg:address":"Les An\u00e9mones",
    "sg:city":"Crans-sur-sierre",
    "sg:orig_category":"Detailhandel mit Bekleidung Detailhandel mit Geschenkartikeln U Souvenirs",
    "sg:phone":"+41 81 833 72 15",
    "sg:postcode":"3963",
    "sg:province":"Valais",
    "wof:name":"Boutique Logo Beatrice Rota",
    "wof:placetype":"venue"
},
  "geometry": {"coordinates":[9.839205,46.498726],"type":"Point"}
}