{
  "type": "Feature",
  "properties": {
    "iso:country":"CH",
    "sg:address":"8585",
    "sg:city":"Happerswil",
    "sg:classifiers":[
        {
            "category":"Restaurant",
            "type":"Food & Drink"
        }
    ],
    "sg:phone":"+41 55 412 35 58",
    "sg:postcode":"8585",
    "sg:province":"Thurgau",
    "wof:name":"Restaurant Eintracht",
    "wof:placetype":"venue"
},
  "geometry": {"coordinates":[8.7831096649,47.1618118286],"type":"Point"}
}