{
  "type": "Feature",
  "properties": {
    "iso:country":"CH",
    "sg:address":"Place De La Gare",
    "sg:city":"Aigle",
    "sg:orig_category":"Detailhandel mit B\u00fcchern, Zeitungen, Schreib U Papeteriewaren Detailhandel mit Waren verschiedener A",
    "sg:phone":"+41 24 466 20 71",
    "sg:postcode":"1860",
    "sg:province":"Vaud",
    "wof:name":"Antonio Rosselli Kiosque Fleurs & Fruits",
    "wof:placetype":"venue"
},
  "geometry": {"coordinates":[6.96471,46.316105],"type":"Point"}
}