{
  "type": "Feature",
  "properties": {
    "iso:country":"CH",
    "sg:address":"Avenue De La Gare 8",
    "sg:city":"Monthey",
    "sg:orig_category":"RESTAURANTS: TEA-ROOMS",
    "sg:phone":"+41 24 471 04 71",
    "sg:postcode":"1870",
    "sg:province":"Valais",
    "wof:name":"Caf\u00e9 Le Plic",
    "wof:placetype":"venue"
},
  "geometry": {"coordinates":[6.9482049942,46.2528457642],"type":"Point"}
}