{
  "type": "Feature",
  "properties": {
    "iso:country":"CH",
    "sg:address":"Wilerstrasse 27 8370 Sirnach. Postfach 60",
    "sg:city":"Sirnach",
    "sg:orig_category":"Detailhandel mit M\u00f6beln U Haushaltsgegenst\u00e4nden Grosshandel mit M\u00f6beln, Wohnbedarf, Teppichen U Bode",
    "sg:phone":"+41 71 966 18 18",
    "sg:postcode":"8370",
    "sg:province":"Thurgau",
    "wof:name":"Scheuch & Adler Ag",
    "wof:placetype":"venue"
},
  "geometry": {"coordinates":[9.0030298233,47.463886261],"type":"Point"}
}