{
  "type": "Feature",
  "properties": {
    "iso:country":"CH",
    "sg:address":"Champs P\u00e9nys Chemin Des 5",
    "sg:city":"Mies",
    "sg:orig_category":"Handels-H\u00e4user U Gesellschaften",
    "sg:postcode":"1295",
    "sg:province":"Vaud",
    "wof:name":"Perspective 2000 Sa",
    "wof:placetype":"venue"
},
  "geometry": {"coordinates":[6.1610488892,46.2996673584],"type":"Point"}
}