{
  "type": "Feature",
  "properties": {
    "iso:country":"CH",
    "sg:address":"Schulstrasse 72",
    "sg:city":"Eptingen",
    "sg:orig_category":"Primarschulen",
    "sg:phone":"+41 62 299 23 31",
    "sg:postcode":"4458",
    "sg:province":"Basel-Landschaft",
    "wof:name":"Primarschule",
    "wof:placetype":"venue"
},
  "geometry": {"coordinates":[7.8189711571,47.3859329224],"type":"Point"}
}