{
  "type": "Feature",
  "properties": {
    "iso:country":"CH",
    "sg:address":"Gummli",
    "sg:city":"Brienzwiler",
    "sg:orig_category":"Herstellung von sonstigen Holzwaren",
    "sg:phone":"+41 33 951 24 15",
    "sg:postcode":"3856",
    "sg:province":"Bern",
    "wof:name":"Werner Amacher",
    "wof:placetype":"venue"
},
  "geometry": {"coordinates":[8.0995225906,46.7525367737],"type":"Point"}
}