{
  "type": "Feature",
  "properties": {
    "iso:country":"CH",
    "sg:address":"Paul-robert-weg 16",
    "sg:city":"Biel/bienne",
    "sg:orig_category":"Wohnheime f\u00fcr Kinder U Jugendliche",
    "sg:phone":"+41 32 341 18 35",
    "sg:postcode":"2502",
    "sg:province":"Bern",
    "wof:name":"Kinderheim Stern Im Ried",
    "wof:placetype":"venue"
},
  "geometry": {"coordinates":[7.2581009865,47.1522521973],"type":"Point"}
}