{
  "type": "Feature",
  "properties": {
    "iso:country":"CH",
    "sg:address":"Hinterdorfweg 3",
    "sg:city":"Schleinikon",
    "sg:orig_category":"Elektroinstallation",
    "sg:phone":"+41 18857444",
    "sg:postcode":"8165",
    "sg:province":"Z\u00fcrich",
    "wof:name":"Elektro Romann",
    "wof:placetype":"venue"
},
  "geometry": {"coordinates":[8.397518158,47.4971923828],"type":"Point"}
}