{
  "type": "Feature",
  "properties": {
    "addr:full":"Piazza San Rocco Minusio Ticino 6648",
    "addr:postcode":"6648",
    "addr:street":"Piazza San Rocco",
    "iso:country":"CH",
    "sg:address":"Piazza San Rocco",
    "sg:city":"Minusio",
    "sg:classifiers":[
        {
            "category":"Bars & Pubs",
            "type":"Food & Drink"
        }
    ],
    "sg:phone":"+41 56 633 12 47",
    "sg:postcode":"6648",
    "sg:province":"Ticino",
    "wof:name":"Cross Pub",
    "wof:placetype":"venue"
},
  "geometry": {"coordinates":[8.343365,47.350948],"type":"Point"}
}