{
  "type": "Feature",
  "properties": {
    "iso:country":"CH",
    "sg:address":"Hausmatt 1",
    "sg:city":"Seftigen",
    "sg:orig_category":"Instandhaltung U Reparatur von Automobilen",
    "sg:postcode":"3662",
    "sg:province":"Bern",
    "wof:name":"Autogarage H. W\u00fcthrich",
    "wof:placetype":"venue"
},
  "geometry": {"coordinates":[7.5423121452,46.7870025635],"type":"Point"}
}