{
  "type": "Feature",
  "properties": {
    "iso:country":"CH",
    "sg:address":"Therwilerstrasse 23a",
    "sg:city":"Ettingen",
    "sg:classifiers":[
        {
            "category":"Insurance",
            "subcategory":"Insurance Agent",
            "type":"Services"
        }
    ],
    "sg:phone":"+41 61 722 06 20",
    "sg:postcode":"4107",
    "sg:province":"Basel-Landschaft",
    "sg:tags":[
        "versicherungsagenturen",
        "-broker"
    ],
    "wof:name":"Carmelo Sarleti Pax-versicherungen",
    "wof:placetype":"venue"
},
  "geometry": {"coordinates":[7.5489020348,47.4860305786],"type":"Point"}
}