{
  "type": "Feature",
  "properties": {
    "iso:country":"CH",
    "sg:address":"Schneitstrasse 66",
    "sg:city":"Ober\u00e4geri",
    "sg:orig_category":"Kauf U Verkauf von Immobilien auf eigene Rechnung Vermittlung von Immobilien",
    "sg:phone":"+41 41 750 38 47",
    "sg:postcode":"6315",
    "sg:province":"Zug",
    "wof:name":"Immobilienb\u00fcro Seemann Armin",
    "wof:placetype":"venue"
},
  "geometry": {"coordinates":[8.6039791107,47.1411399841],"type":"Point"}
}