{
  "type": "Feature",
  "properties": {
    "iso:country":"CH",
    "sg:address":"Gotschnastrasse 19",
    "sg:city":"Klosters",
    "sg:orig_category":"Personenbef\u00f6rderung im Linienverkehr zu Land",
    "sg:phone":"+41 81 410 20 60",
    "sg:postcode":"7250",
    "sg:province":"Graubunden",
    "wof:name":"Ag Luftseilbahn Klosters-gotschnagrat-parsenn",
    "wof:placetype":"venue"
},
  "geometry": {"coordinates":[9.8805589676,46.8680534363],"type":"Point"}
}