{
  "type": "Feature",
  "properties": {
    "iso:country":"CH",
    "sg:address":"Kirchweg 7",
    "sg:city":"Oberehrendingen",
    "sg:orig_category":"Allgemeiner Hoch U Tiefbau Architekturb\u00fcros",
    "sg:phone":"+41 17151244",
    "sg:postcode":"5422",
    "wof:name":"Suter Partner Architekten Ag",
    "wof:placetype":"venue"
},
  "geometry": {"coordinates":[8.544104,47.331417],"type":"Point"}
}