{
  "type": "Feature",
  "properties": {
    "iso:country":"CH",
    "sg:address":"Bureau Communal De Port-valais 1897 Bouveret. Postfach",
    "sg:city":"Bouveret",
    "sg:orig_category":"Technische, physikalische U chemische Untersuchung",
    "sg:postcode":"1897",
    "sg:province":"Valais",
    "wof:name":"Fondation Cruso\u00e9 Suisse Fondation Tenant Le Respect De L'environnement Pour Vital Aux G\u00e9n\u00e9rations Futures Etc",
    "wof:placetype":"venue"
},
  "geometry": {"coordinates":[6.8527832031,46.3853225708],"type":"Point"}
}