{
  "type": "Feature",
  "properties": {
    "addr:full":"Rue De Jargonnant 2 Geneva Gen\u00e8ve 1207",
    "addr:housenumber":"2",
    "addr:postcode":"1207",
    "addr:street":"Rue De Jargonnant",
    "iso:country":"CH",
    "sg:address":"Rue De Jargonnant 2",
    "sg:city":"Geneva",
    "sg:classifiers":[
        {
            "category":"Banks & Credit Unions",
            "subcategory":"Bank",
            "type":"Services"
        }
    ],
    "sg:postcode":"1207",
    "sg:province":"Gen\u00e8ve",
    "wof:name":"Banque Unigestion",
    "wof:placetype":"venue"
},
  "geometry": {"coordinates":[6.159794,46.201118],"type":"Point"}
}