{
  "type": "Feature",
  "properties": {
    "iso:country":"CH",
    "sg:address":"Kirchstrasse 8",
    "sg:city":"G\u00e4hwil",
    "sg:orig_category":"Stickerei",
    "sg:phone":"+41 71 274 92 92",
    "sg:postcode":"9534",
    "sg:province":"St. Gallen",
    "wof:name":"Jakob Schlaepfer Stickereien",
    "wof:placetype":"venue"
},
  "geometry": {"coordinates":[9.345773,47.412853],"type":"Point"}
}