{
  "type": "Feature",
  "properties": {
    "iso:country":"CH",
    "sg:address":"Rue Denis-de-rougement 3 2108 Couvet. Postfach",
    "sg:city":"Couvet",
    "sg:orig_category":"Herstellung von Mess U Kontrollinstrumenten U vorrichtungen",
    "sg:postcode":"2108",
    "sg:province":"Neuch\u00e2tel",
    "wof:name":"Imsa, Instruments De Mesures Scientifiques Sa. Brevets De Produits Scientifiques Plus Sp\u00e9c. D'instruments De Mesures Scientifiques, Etc.",
    "wof:placetype":"venue"
},
  "geometry": {"coordinates":[6.6319680214,46.9253158569],"type":"Point"}
}