{
  "type": "Feature",
  "properties": {
    "iso:country":"CH",
    "sg:address":"Birmensdorferstrasse 7",
    "sg:city":"Dietikon",
    "sg:orig_category":"Detailhandel mit Waren verschiedener Art, Hauptrichtung Nahrungsmittel",
    "sg:phone":"+41 17742801",
    "sg:postcode":"8953",
    "sg:province":"Z\u00fcrich",
    "wof:name":"Coop Laden Brunau",
    "wof:placetype":"venue"
},
  "geometry": {"coordinates":[8.41776371,47.398273468],"type":"Point"}
}