{
  "type": "Feature",
  "properties": {
    "iso:country":"CH",
    "sg:address":"Rue Neuve 8",
    "sg:city":"Nyon",
    "sg:orig_category":"Herstellung von Oberbekleidung",
    "sg:phone":"+41 22 361 36 61",
    "sg:postcode":"1260",
    "sg:province":"Vaud",
    "wof:name":"Griffchic, Vrolijk G.f.",
    "wof:placetype":"venue"
},
  "geometry": {"coordinates":[6.2387161255,46.3832015991],"type":"Point"}
}