{
  "type": "Feature",
  "properties": {
    "iso:country":"CH",
    "sg:address":"Sur Breuya 5",
    "sg:city":"Vicques",
    "sg:orig_category":"Maurerarbeiten",
    "sg:phone":"+41 32 435 63 51",
    "sg:postcode":"2824",
    "sg:province":"Jura",
    "wof:name":"Jean-claude Bron Entreprise De Ma\u00e7onnerie",
    "wof:placetype":"venue"
},
  "geometry": {"coordinates":[7.4051661491,47.3498191833],"type":"Point"}
}