{
  "type": "Feature",
  "properties": {
    "iso:country":"CH",
    "sg:address":"B\u00f6sch 37",
    "sg:city":"H\u00fcnenberg",
    "sg:classifiers":[
        {
            "category":"Professional",
            "subcategory":"Credit Reporting & Collection",
            "type":"Services"
        }
    ],
    "sg:phone":"+41 41 784 21 61",
    "sg:postcode":"6331",
    "sg:province":"Zug",
    "sg:tags":[
        "catalogue",
        "publishing",
        "database"
    ],
    "wof:name":"Intercable Verlag Ag",
    "wof:placetype":"venue"
},
  "geometry": {"coordinates":[8.440262,47.160385],"type":"Point"}
}