{
  "type": "Feature",
  "properties": {
    "iso:country":"CH",
    "sg:address":"Industrieplatz 8212 Neuhausen. Postfach",
    "sg:city":"Zug",
    "sg:orig_category":"Grosshandel mit sonstigen Gebrauchs U Verbrauchsg\u00fctern Herstellung von Waffen U Munition",
    "sg:phone":"+41 52 672 50 91",
    "sg:postcode":"6300",
    "sg:province":"Zug",
    "wof:name":"Sig Arms Ag",
    "wof:placetype":"venue"
},
  "geometry": {"coordinates":[8.6184167862,47.6796035767],"type":"Point"}
}