{
  "type": "Feature",
  "properties": {
    "iso:country":"CH",
    "sg:address":"Untere Chamm",
    "sg:city":"Bazenheid",
    "sg:orig_category":"Tierheime",
    "sg:phone":"+41 55 246 19 19",
    "sg:postcode":"9602",
    "sg:province":"St. Gallen",
    "wof:name":"Hundepension-laupen Zh",
    "wof:placetype":"venue"
},
  "geometry": {"coordinates":[8.9390354156,47.2693862915],"type":"Point"}
}