{
  "type": "Feature",
  "properties": {
    "iso:country":"CH",
    "sg:address":"Holeeholzweg 69",
    "sg:city":"Binningen",
    "sg:classifiers":[
        {
            "category":"Personal",
            "subcategory":"Nail Salon",
            "type":"Services"
        }
    ],
    "sg:phone":"+41 61 421 65 96",
    "sg:postcode":"4102",
    "sg:province":"Basel-Landschaft",
    "sg:tags":[
        "manicure"
    ],
    "wof:name":"Centamore Francesca Nail Design",
    "wof:placetype":"venue"
},
  "geometry": {"coordinates":[7.5533781052,47.5382614136],"type":"Point"}
}