{
  "type": "Feature",
  "properties": {
    "iso:country":"CH",
    "sg:address":"Casa Pancaldi",
    "sg:city":"Avegno",
    "sg:orig_category":"Blumen U Zierpflanzenbau Gem\u00fcsebau",
    "sg:phone":"+41 56 225 11 66",
    "sg:postcode":"6670",
    "sg:province":"Ticino",
    "wof:name":"Peter Frei Gem\u00fcse-& Blumeng\u00e4rtnerei",
    "wof:placetype":"venue"
},
  "geometry": {"coordinates":[8.241534,47.463615],"type":"Point"}
}