{
  "type": "Feature",
  "properties": {
    "iso:country":"CH",
    "sg:address":"Neumattstrasse 36",
    "sg:city":"Aarau",
    "sg:orig_category":"Handelsvermittlung U Grosshandel Handelsvermittlung U Grosshandel mit Automobilteilen U Zubeh\u00f6r",
    "sg:phone":"+41 62 834 43 10",
    "sg:postcode":"5000",
    "sg:province":"Aargau",
    "wof:name":"Derendinger Ag Autobestandteile Autozubeh\u00f6r",
    "wof:placetype":"venue"
},
  "geometry": {"coordinates":[8.0648040771,47.4024848938],"type":"Point"}
}