{
  "type": "Feature",
  "properties": {
    "iso:country":"CH",
    "sg:address":"Oey 3792 Saanen. Postfach 96",
    "sg:city":"Saanen",
    "sg:orig_category":"Malerei Stukkateurgewerbe, Gipserei U Verputzerei",
    "sg:phone":"+41 33 744 52 51",
    "sg:postcode":"3792",
    "sg:province":"Bern",
    "wof:name":"Mayor Ag Maler-& Gipsergesch\u00e4ft",
    "wof:placetype":"venue"
},
  "geometry": {"coordinates":[7.2574400902,46.4894638062],"type":"Point"}
}