{
  "type": "Feature",
  "properties": {
    "iso:country":"CH",
    "sg:address":"Grundstrasse 83",
    "sg:city":"St\u00e4fa",
    "sg:orig_category":"Kunsthandel",
    "sg:phone":"+41 12010228",
    "sg:postcode":"8712",
    "sg:province":"Z\u00fcrich",
    "wof:name":"Daniel Fabian Atel.f.kunst & Restaurierung",
    "wof:placetype":"venue"
},
  "geometry": {"coordinates":[8.7261610031,47.2451972961],"type":"Point"}
}