{
  "type": "Feature",
  "properties": {
    "iso:country":"CH",
    "sg:address":"K\u00e4sereistrasse 3",
    "sg:city":"Rothenhausen",
    "sg:orig_category":"Detailhandel mit Milcherzeugnissen U Eiern Verarbeitung von Milch",
    "sg:phone":"+41 55 246 11 17",
    "sg:postcode":"9565",
    "sg:province":"Thurgau",
    "wof:name":"Albert Neff Molkerei Spittel",
    "wof:placetype":"venue"
},
  "geometry": {"coordinates":[8.9413003922,47.2884101868],"type":"Point"}
}