{
  "type": "Feature",
  "properties": {
    "iso:country":"CH",
    "sg:address":"Prom.des Champs-fr\u00e9chets 17",
    "sg:city":"Meyrin",
    "sg:orig_category":"Grosshandel mit Textilien",
    "sg:phone":"+41 22 783 04 94",
    "sg:postcode":"1217",
    "sg:province":"Gen\u00e8ve",
    "wof:name":"Sarrasin Xavier C.",
    "wof:placetype":"venue"
},
  "geometry": {"coordinates":[6.079264164,46.2378044128],"type":"Point"}
}