{
  "type": "Feature",
  "properties": {
    "addr:full":"Neuhofstrasse 23 6340 Baar. Postfach Baar Zug 6340",
    "addr:housenumber":"23",
    "addr:postcode":"6340 baar. postfach;6340",
    "addr:street":"Neuhofstrasse;Zug",
    "iso:country":"CH",
    "sg:address":"Neuhofstrasse 23 6340 Baar. Postfach",
    "sg:city":"Baar",
    "sg:orig_category":"Fachdetailhandel mit pharmazeutischen Produkten",
    "sg:phone":"+41 41 768 43 33",
    "sg:postcode":"6340",
    "sg:province":"Zug",
    "wof:name":"Abbott Laboratories Sa",
    "wof:placetype":"venue"
},
  "geometry": {"coordinates":[8.515447,47.189373],"type":"Point"}
}