{
  "type": "Feature",
  "properties": {
    "iso:country":"CH",
    "sg:address":"Affry Rue Louis-d' 3",
    "sg:city":"Fribourg",
    "sg:orig_category":"Maler U Glasergewerbe",
    "sg:phone":"+41 26 424 21 31",
    "sg:postcode":"1700",
    "sg:province":"Fribourg",
    "wof:name":"Brandao Pinto Victor",
    "wof:placetype":"venue"
},
  "geometry": {"coordinates":[7.1746201515,46.8062400818],"type":"Point"}
}