{
  "type": "Feature",
  "properties": {
    "iso:country":"CH",
    "sg:address":"Place Du March\u00e9 3/av. Du Clo\u00ee 1",
    "sg:city":"Aigle",
    "sg:orig_category":"Non-Classified Establishments",
    "sg:phone":"+41 21 961 16 26",
    "sg:postcode":"1860",
    "sg:province":"Vaud",
    "wof:name":"Place Du Marche Sa Participations Etc",
    "wof:placetype":"venue"
},
  "geometry": {"coordinates":[6.9701099396,46.3175544739],"type":"Point"}
}