{
  "type": "Feature",
  "properties": {
    "iso:country":"CH",
    "sg:address":"Gerbestrasse 2",
    "sg:city":"Oberuzwil",
    "sg:orig_category":"Detailhandel mit Uhren U Schmuck Fachdetailhandel in Verkaufsr\u00e4umen",
    "sg:phone":"+41 71 951 63 23",
    "sg:postcode":"9242",
    "sg:province":"St. Gallen",
    "wof:name":"Peter & Brigitte K\u00fcnzel Uhren Bijouterie",
    "wof:placetype":"venue"
},
  "geometry": {"coordinates":[9.1252717972,47.4304656982],"type":"Point"}
}