{
  "type": "Feature",
  "properties": {
    "iso:country":"CH",
    "sg:address":"Dorfwisenstasse 14",
    "sg:city":"Sch\u00f6fflisdorf",
    "sg:classifiers":[
        {
            "category":"Travel",
            "subcategory":"Hotels & Motels",
            "type":"Entertainment"
        }
    ],
    "sg:phone":"+41 18720333",
    "sg:postcode":"8165",
    "sg:province":"Z\u00fcrich",
    "sg:tags":[
        "oder",
        "bar",
        "restaurant"
    ],
    "wof:name":"Restaurant Schmitted\u00f6rfli Viva-bar",
    "wof:placetype":"venue"
},
  "geometry": {"coordinates":[8.414343,47.498909],"type":"Point"}
}