{
  "type": "Feature",
  "properties": {
    "addr:full":"Affolternstrasse 123 8050 Z\u00fcrich. Postfach Z\u00fcrich 8056",
    "addr:housenumber":"123",
    "addr:postcode":"8050 zuerich. postfach;8056",
    "addr:street":"Affolternstrasse",
    "iso:country":"CH",
    "sg:address":"Affolternstrasse 123 8050 Z\u00fcrich. Postfach",
    "sg:city":"Z\u00fcrich",
    "sg:orig_category":"Architektur U Ingenieurb\u00fcros Kauf U Verkauf von Immobilien auf eigene Rechnung",
    "sg:phone":"+41 13117018",
    "sg:postcode":"8056",
    "wof:name":"Interarch Gmbh",
    "wof:placetype":"venue"
},
  "geometry": {"coordinates":[8.534068,47.410656],"type":"Point"}
}