{
  "type": "Feature",
  "properties": {
    "iso:country":"CH",
    "sg:address":"Gaissbergstrasse 62",
    "sg:city":"Kreuzlingen",
    "sg:orig_category":"Unternehmensberatung",
    "sg:phone":"+41 71 670 08 30",
    "sg:postcode":"8280",
    "sg:province":"Thurgau",
    "wof:name":"Angus Western Consulting Group Ag",
    "wof:placetype":"venue"
},
  "geometry": {"coordinates":[9.1811923981,47.6391639709],"type":"Point"}
}