{
  "type": "Feature",
  "properties": {
    "iso:country":"CH",
    "sg:address":"Steinacher Strasse 2",
    "sg:city":"T\u00fcbach",
    "sg:classifiers":[
        {
            "category":"Restaurant",
            "type":"Food & Drink"
        }
    ],
    "sg:phone":"+41 71 245 13 66",
    "sg:postcode":"9327",
    "sg:province":"St. Gallen",
    "wof:name":"Landhaus Rorschacher Strasse Restaurant",
    "wof:placetype":"venue"
},
  "geometry": {"coordinates":[9.4007539749,47.434261322],"type":"Point"}
}