{
  "type": "Feature",
  "properties": {
    "addr:full":"Bernstrasse 388 Dietikon Z\u00fcrich 8953",
    "addr:housenumber":"388",
    "addr:postcode":"8953",
    "addr:street":"Bernstrasse",
    "iso:country":"CH",
    "sg:address":"Bernstrasse 388",
    "sg:city":"Dietikon",
    "sg:classifiers":[
        {
            "category":"Organizations",
            "subcategory":"Professional Association",
            "type":"Services"
        }
    ],
    "sg:phone":"+41 17466363",
    "sg:postcode":"8953",
    "sg:province":"Z\u00fcrich",
    "sg:tags":[
        "car",
        "full-service",
        "pool"
    ],
    "wof:name":"Leaseplan (schweiz) Ag",
    "wof:placetype":"venue"
},
  "geometry": {"coordinates":[8.395272,47.383579],"type":"Point"}
}