{
  "type": "Feature",
  "properties": {
    "iso:country":"CH",
    "sg:address":"Bankplatz 4 8500 Frauenfeld. Postfach",
    "sg:city":"Frauenfeld",
    "sg:orig_category":"Elektroinstallation",
    "sg:phone":"+41 52 728 98 98",
    "sg:postcode":"8501",
    "sg:province":"Thurgau",
    "wof:name":"Habersaat Ag",
    "wof:placetype":"venue"
},
  "geometry": {"coordinates":[8.8984146118,47.5568313599],"type":"Point"}
}