{
  "type": "Feature",
  "properties": {
    "iso:country":"CH",
    "sg:address":"Rue De L' Avenir 13",
    "sg:city":"Court\u00e9telle",
    "sg:classifiers":[
        {
            "category":"Manufacturing",
            "subcategory":"Metals",
            "type":"Manufacturing & Wholesale Goods"
        }
    ],
    "sg:phone":"+41 32 421 66 88",
    "sg:postcode":"2852",
    "sg:province":"Jura",
    "sg:tags":[
        "made",
        "fa\u00e7ade",
        "panel"
    ],
    "wof:name":"Hevron S.a.",
    "wof:placetype":"venue"
},
  "geometry": {"coordinates":[7.3208031654,47.3449783325],"type":"Point"}
}