{
  "type": "Feature",
  "properties": {
    "iso:country":"CH",
    "sg:address":"Les Quartiers 1837 Ch\u00e2teau-d'oex. Postfach",
    "sg:city":"Ch\u00e2teau-d'oex",
    "sg:orig_category":"M\u00f6belschreinereien",
    "sg:postcode":"1837",
    "wof:name":"Zulauff Albert S\u00e0rl",
    "wof:placetype":"venue"
},
  "geometry": {"coordinates":[23.6287593842,42.7866783142],"type":"Point"}
}