{
  "type": "Feature",
  "properties": {
    "addr:full":"Heinrich-gujerstrasse 35 Bauma Z\u00fcrich 8494",
    "addr:housenumber":"35",
    "addr:postcode":"8494",
    "addr:street":"Heinrich-Gujerstrasse",
    "iso:country":"CH",
    "sg:address":"Heinrich-gujerstrasse 35",
    "sg:city":"Bauma",
    "sg:orig_category":"Bezirks, Sekundar, Realschulen, Oberstufe der Primarschulen",
    "sg:phone":"+41 52 386 13 85",
    "sg:postcode":"8494",
    "sg:province":"Z\u00fcrich",
    "wof:name":"Oberstufenschule",
    "wof:placetype":"venue"
},
  "geometry": {"coordinates":[8.881113,47.367523],"type":"Point"}
}