{
  "type": "Feature",
  "properties": {
    "iso:country":"CH",
    "sg:address":"Tolderhaus",
    "sg:city":"N\u00e4fels",
    "sg:orig_category":"Detailhandel mit elektrischen Haushalts, Radio U Fernsehger\u00e4ten ohne ausgepr\u00e4gten Schwerpunkt",
    "sg:phone":"+41 55 618 72 50",
    "sg:postcode":"8752",
    "sg:province":"Glarus",
    "wof:name":"Elektrizit\u00e4tswerk N\u00e4fels Verkaufsladen",
    "wof:placetype":"venue"
},
  "geometry": {"coordinates":[9.0680952072,47.1045417786],"type":"Point"}
}