{
  "type": "Feature",
  "properties": {
    "iso:country":"CH",
    "sg:address":"Oberstadt 6",
    "sg:city":"Schaffhausen",
    "sg:orig_category":"Detailhandel mit Damenbekleidung Detailhandel mit Textilien",
    "sg:phone":"+41 52 624 44 44",
    "sg:postcode":"8200",
    "sg:province":"Schaffhausen",
    "wof:name":"R\u00f6del Gmbh R/line Wolle & Damenbekleidung",
    "wof:placetype":"venue"
},
  "geometry": {"coordinates":[8.6331806183,47.6965866089],"type":"Point"}
}