{
  "type": "Feature",
  "properties": {
    "iso:country":"CH",
    "sg:address":"Lavaterstrasse 67",
    "sg:city":"Z\u00fcrich",
    "sg:orig_category":"Unclassifiable Establishments",
    "sg:postcode":"8002",
    "sg:province":"Z\u00fcrich",
    "wof:name":"Valbosco Sa",
    "wof:placetype":"venue"
},
  "geometry": {"coordinates":[8.5330934525,47.3611373901],"type":"Point"}
}