{
  "type": "Feature",
  "properties": {
    "iso:country":"CH",
    "sg:address":"Kalchmatt",
    "sg:city":"Lauperswil",
    "sg:orig_category":"Mechanik",
    "sg:phone":"+41 34 496 99 99",
    "sg:postcode":"3438",
    "sg:province":"Bern",
    "wof:name":"Aug. Schneider & Co. Ag",
    "wof:placetype":"venue"
},
  "geometry": {"coordinates":[7.739590168,46.9704589844],"type":"Point"}
}