{
  "type": "Feature",
  "properties": {
    "iso:country":"CH",
    "sg:address":"Lehnweg 2",
    "sg:city":"Schenkon",
    "sg:orig_category":"Architekturb\u00fcros",
    "sg:phone":"+41 41 459 72 00",
    "sg:postcode":"6214",
    "sg:province":"Luzern",
    "wof:name":"W. & R. Leuenberger Ag Dipl.architekten Eth/htl",
    "wof:placetype":"venue"
},
  "geometry": {"coordinates":[8.135625,47.177982],"type":"Point"}
}