{
  "type": "Feature",
  "properties": {
    "iso:country":"CH",
    "sg:address":"Feldg\u00fcetliweg 121",
    "sg:city":"Meilen",
    "sg:orig_category":"Grosshandel mit Software Sonstiger Grosshandel",
    "sg:postcode":"8706",
    "sg:province":"Z\u00fcrich",
    "wof:name":"Dmt Distribution Gebr. Bamert",
    "wof:placetype":"venue"
},
  "geometry": {"coordinates":[8.6275653839,47.2747688293],"type":"Point"}
}