{
  "type": "Feature",
  "properties": {
    "iso:country":"CH",
    "sg:address":"Weyermattstrasse 4 2560 Nidau. Postfach 271",
    "sg:city":"Nidau",
    "sg:orig_category":"Zahnarztpraxen",
    "sg:phone":"+41 32 331 04 06",
    "sg:postcode":"2560",
    "sg:province":"Bern",
    "wof:name":"Dr. Med. Dent. Ernst Enzmann Zahnarzt",
    "wof:placetype":"venue"
},
  "geometry": {"coordinates":[7.2396259308,47.1262321472],"type":"Point"}
}