{
  "type": "Feature",
  "properties": {
    "iso:country":"CH",
    "sg:address":"Gellertstrasse 2a",
    "sg:city":"Basel",
    "sg:orig_category":"Aktivit\u00e4ten der Generalunternehmen im Baugewerbe Wirtschaftspr\u00fcfung, Steuerberatung U Treuhand",
    "sg:phone":"+41 19361445",
    "sg:postcode":"4052",
    "sg:province":"Basel-Stadt",
    "wof:name":"Nova Bautreuhand Ag",
    "wof:placetype":"venue"
},
  "geometry": {"coordinates":[8.749335,47.303703],"type":"Point"}
}