{
  "type": "Feature",
  "properties": {
    "iso:country":"CH",
    "sg:address":"Haut Du Village 48",
    "sg:city":"Vermes",
    "sg:orig_category":"Detailhandel mit Waren verschiedener Art, Hauptrichtung Nahrungsmittel",
    "sg:phone":"+41 32 438 87 40",
    "sg:postcode":"2829",
    "sg:province":"Jura",
    "wof:name":"Denis Fleury Alimentation",
    "wof:placetype":"venue"
},
  "geometry": {"coordinates":[7.4754562378,47.3286094666],"type":"Point"}
}