{
  "type": "Feature",
  "properties": {
    "iso:country":"CH",
    "sg:address":"Bo\u00e9chat Rue Emile- 87",
    "sg:city":"Del\u00e9mont",
    "sg:orig_category":"Betrieb von Sportanlagen",
    "sg:phone":"+41 32 422 96 66",
    "sg:postcode":"2800",
    "sg:province":"Jura",
    "wof:name":"Centre La Crois\u00e9e Sa",
    "wof:placetype":"venue"
},
  "geometry": {"coordinates":[7.357995,47.360455],"type":"Point"}
}