{
  "type": "Feature",
  "properties": {
    "iso:country":"CH",
    "sg:address":"B\u00fchlmoos 1",
    "sg:city":"Sarmenstorf",
    "sg:classifiers":[
        {
            "category":"Wholesale",
            "subcategory":"Vending Machines",
            "type":"Manufacturing & Wholesale Goods"
        }
    ],
    "sg:phone":"+41 56 667 18 13",
    "sg:postcode":"5614",
    "sg:province":"Aargau",
    "sg:tags":[
        "energy",
        "-",
        "environment",
        "equipment",
        "engineering",
        "machinery",
        "mechanical"
    ],
    "wof:name":"Josef Muff Ag",
    "wof:placetype":"venue"
},
  "geometry": {"coordinates":[8.2449970245,47.3058700562],"type":"Point"}
}