{
  "type": "Feature",
  "properties": {
    "iso:country":"CH",
    "sg:address":"Via S. Franscini 18",
    "sg:city":"Chiasso",
    "sg:orig_category":"Unclassifiable Establishments",
    "sg:phone":"+41 91 630 17 41",
    "sg:postcode":"6830",
    "sg:province":"Ticino",
    "wof:name":"Kappakrammer Sa",
    "wof:placetype":"venue"
},
  "geometry": {"coordinates":[9.0314970016,45.8359680176],"type":"Point"}
}