{
  "type": "Feature",
  "properties": {
    "iso:country":"CH",
    "sg:address":"Ruelle Jeanhenry 6",
    "sg:city":"Marin-epagnier",
    "sg:orig_category":"Saunas Solarien",
    "sg:phone":"+41 32 753 71 87",
    "sg:postcode":"2074",
    "sg:province":"Neuch\u00e2tel",
    "wof:name":"Espace Sant\u00e9 Marin",
    "wof:placetype":"venue"
},
  "geometry": {"coordinates":[6.9997649193,47.0092353821],"type":"Point"}
}