{
  "type": "Feature",
  "properties": {
    "iso:country":"CH",
    "sg:address":"Oublis Ruelle Des 1",
    "sg:city":"Ligni\u00e8res",
    "sg:orig_category":"Herstellung von elektrischen Haushaltsger\u00e4ten",
    "sg:postcode":"2523",
    "sg:province":"Neuch\u00e2tel",
    "wof:name":"Cafi-mat S\u00e0rl",
    "wof:placetype":"venue"
},
  "geometry": {"coordinates":[7.0647997856,47.0828094482],"type":"Point"}
}