{
  "type": "Feature",
  "properties": {
    "iso:country":"CH",
    "sg:address":"Grand-rue 89",
    "sg:city":"Morges",
    "sg:orig_category":"Advokaturb\u00fcros",
    "sg:phone":"+41 22 789 50 20",
    "sg:postcode":"1110",
    "sg:province":"Vaud",
    "wof:name":"Jean-fran\u00e7ois Ducrest Etude D'avocat",
    "wof:placetype":"venue"
},
  "geometry": {"coordinates":[6.153883,46.198555],"type":"Point"}
}