{
  "type": "Feature",
  "properties": {
    "iso:country":"CH",
    "sg:address":"P\u00e4chterriedstrasse 370",
    "sg:city":"Watt",
    "sg:orig_category":"Fahrschulen, Flugschulen",
    "sg:phone":"+41 18400838",
    "sg:postcode":"8105",
    "sg:province":"Z\u00fcrich",
    "wof:name":"Bruno Hugelshofer Hugi's Fahrschule",
    "wof:placetype":"venue"
},
  "geometry": {"coordinates":[8.4722995758,47.4470481873],"type":"Point"}
}