{
  "type": "Feature",
  "properties": {
    "iso:country":"CH",
    "sg:address":"Industrie Neuhof 7",
    "sg:city":"Kirchberg",
    "sg:classifiers":[
        {
            "category":"Manufacturing",
            "subcategory":"Metals",
            "type":"Manufacturing & Wholesale Goods"
        }
    ],
    "sg:phone":"+41 34 445 11 33",
    "sg:postcode":"3422",
    "sg:province":"Bern",
    "sg:tags":[
        "made",
        "fa\u00e7ade",
        "panel"
    ],
    "wof:name":"Dial Norm Ag",
    "wof:placetype":"venue"
},
  "geometry": {"coordinates":[7.5711040497,47.0926322937],"type":"Point"}
}