{
  "type": "Feature",
  "properties": {
    "iso:country":"CH",
    "sg:address":"Poststrasse 112",
    "sg:city":"Arosa",
    "sg:classifiers":[
        {
            "category":"Government",
            "subcategory":"Post Office",
            "type":"Public Place"
        }
    ],
    "sg:phone":"+41 81 410 11 22",
    "sg:postcode":"7050",
    "sg:province":"Graubunden",
    "sg:tags":[
        "caf\u00e9s",
        "tea-rooms"
    ],
    "wof:name":"Caf\u00e9 Weber",
    "wof:placetype":"venue"
},
  "geometry": {"coordinates":[9.838388443,46.8078842163],"type":"Point"}
}