{
  "type": "Feature",
  "properties": {
    "iso:country":"CH",
    "sg:address":"Kreuzstrasse 31",
    "sg:city":"Z\u00fcrich",
    "sg:orig_category":"Verwaltung von Immobilien Wirtschaftspr\u00fcfung, Steuerberatung U Treuhand",
    "sg:phone":"+41 55 450 52 52",
    "sg:postcode":"8008",
    "sg:province":"Z\u00fcrich",
    "wof:name":"A-print Verwaltungs Und Treuhand Gmbh",
    "wof:placetype":"venue"
},
  "geometry": {"coordinates":[8.9527902603,47.1751785278],"type":"Point"}
}