{
  "type": "Feature",
  "properties": {
    "iso:country":"CH",
    "sg:address":"Fornasette Di Monteggio",
    "sg:city":"Termine",
    "sg:orig_category":"Vermietung U Verpachtung von eigenen Immobilien",
    "sg:postcode":"6998",
    "sg:province":"Ticino",
    "wof:name":"Triacca Fratelli.",
    "wof:placetype":"venue"
},
  "geometry": {"coordinates":[8.8096218109,45.9958229065],"type":"Point"}
}