{
  "type": "Feature",
  "properties": {
    "iso:country":"CH",
    "sg:address":"Zeigerg\u00e4ssli 9",
    "sg:city":"Lungern",
    "sg:classifiers":[
        {
            "category":"Community Center",
            "subcategory":"Senior",
            "type":"Public Place"
        }
    ],
    "sg:phone":"+41 41 678 12 22",
    "sg:postcode":"6078",
    "sg:province":"Obwalden",
    "sg:tags":[
        "front",
        "wood",
        "door"
    ],
    "wof:name":"Leo Gasser S\u00f6hne Ag Schreinerei K\u00fcchenbau",
    "wof:placetype":"venue"
},
  "geometry": {"coordinates":[8.1603183746,46.7844543457],"type":"Point"}
}