{
  "type": "Feature",
  "properties": {
    "iso:country":"CH",
    "sg:address":"9473",
    "sg:city":"Gams",
    "sg:classifiers":[
        {
            "category":"Restaurant",
            "type":"Food & Drink"
        }
    ],
    "sg:phone":"+41 71 977 15 10",
    "sg:postcode":"9473",
    "sg:province":"St. Gallen",
    "wof:name":"Gasthaus Kreuz",
    "wof:placetype":"venue"
},
  "geometry": {"coordinates":[8.9690742493,47.4147911072],"type":"Point"}
}