{
  "type": "Feature",
  "properties": {
    "iso:country":"CH",
    "sg:address":"Geerenweg 2",
    "sg:city":"Z\u00fcrich",
    "sg:orig_category":"Sanit\u00e4r, Heizungs U L\u00fcftungsinstallation Sanit\u00e4rinstallation",
    "sg:phone":"+41 26 912 65 44",
    "sg:postcode":"8048",
    "sg:province":"Z\u00fcrich",
    "wof:name":"Riedo Clima Sa Bulle",
    "wof:placetype":"venue"
},
  "geometry": {"coordinates":[7.0662398338,46.6239776611],"type":"Point"}
}