{
  "type": "Feature",
  "properties": {
    "iso:country":"CH",
    "sg:address":"Cordulaplatz 1",
    "sg:city":"Baden",
    "sg:orig_category":"Detailhandel mit Damenbekleidung Sonstiges Textilgewerbe",
    "sg:phone":"+41 56 222 62 57",
    "sg:postcode":"5400",
    "sg:province":"Aargau",
    "wof:name":"Modelin Sa Textilwaren - W\u00e4sche",
    "wof:placetype":"venue"
},
  "geometry": {"coordinates":[8.3066082001,47.4717941284],"type":"Point"}
}