{
  "type": "Feature",
  "properties": {
    "iso:country":"CH",
    "sg:address":"Seestrasse 89",
    "sg:city":"W\u00e4denswil",
    "sg:orig_category":"Handelsvermittlung Unternehmensberatung",
    "sg:phone":"+41 16804003",
    "sg:postcode":"8820",
    "sg:province":"Z\u00fcrich",
    "wof:name":"Reto Rahm Rahm Consulting",
    "wof:placetype":"venue"
},
  "geometry": {"coordinates":[8.6757078171,47.2275924683],"type":"Point"}
}