{
  "type": "Feature",
  "properties": {
    "iso:country":"CH",
    "sg:address":"St. Gallerstrasse 17",
    "sg:city":"M\u00f6rschwil",
    "sg:classifiers":[
        {
            "category":"Autos & Motor Vehicles",
            "subcategory":"Fuel & Gas Station",
            "type":"Retail Goods"
        }
    ],
    "sg:phone":"+41 71 866 18 12",
    "sg:postcode":"9402",
    "sg:province":"St. Gallen",
    "sg:tags":[
        "steel",
        "tube",
        "chromium"
    ],
    "wof:name":"Bl\u00fccher Gmbh",
    "wof:placetype":"venue"
},
  "geometry": {"coordinates":[9.421281,47.46693],"type":"Point"}
}