{
  "type": "Feature",
  "properties": {
    "addr:full":"Resigartenstrasse 4 Guntershausen Thurgau 8357",
    "addr:housenumber":"4",
    "addr:postcode":"8357",
    "addr:street":"Resigartenstrasse",
    "iso:country":"CH",
    "sg:address":"Resigartenstrasse 4",
    "sg:city":"Guntershausen",
    "sg:orig_category":"Architektur U Ingenieurb\u00fcros",
    "sg:phone":"+41 52 365 14 07",
    "sg:postcode":"8357",
    "sg:province":"Thurgau",
    "wof:name":"Hansj\u00fcrg Kaiser Arca Engineering",
    "wof:placetype":"venue"
},
  "geometry": {"coordinates":[8.91943,47.475491],"type":"Point"}
}