{
  "type": "Feature",
  "properties": {
    "iso:country":"CH",
    "sg:address":"Waldstrasse 12 8125 Zollikerberg. Postfach",
    "sg:city":"Zollikerberg",
    "sg:orig_category":"Vermietung U Verpachtung von eigenen Immobilien",
    "sg:phone":"+41 34 496 31 00",
    "sg:postcode":"8125",
    "sg:province":"Z\u00fcrich",
    "wof:name":"Viandor Immobilien Ag",
    "wof:placetype":"venue"
},
  "geometry": {"coordinates":[7.757589817,46.9491271973],"type":"Point"}
}