{
  "type": "Feature",
  "properties": {
    "iso:country":"CH",
    "sg:address":"Route De Vuarat",
    "sg:city":"Remaufens",
    "sg:orig_category":"Sonstiger Grosshandel Unternehmensberatung",
    "sg:phone":"+41 21 948 90 00",
    "sg:postcode":"1617",
    "sg:province":"Fribourg",
    "wof:name":"Deep Services S\u00e0rl",
    "wof:placetype":"venue"
},
  "geometry": {"coordinates":[6.8742170334,46.5226364136],"type":"Point"}
}