{
  "type": "Feature",
  "properties": {
    "iso:country":"CH",
    "sg:address":"Ch\u00e2teau Le",
    "sg:city":"Vaumarcus",
    "sg:orig_category":"Unternehmensberatung",
    "sg:phone":"+41 33 442 19 73",
    "sg:postcode":"2028",
    "sg:province":"Neuch\u00e2tel",
    "wof:name":"Cpr Pricon Gmbh Dienstleistungen Im Ber. Unternehmensberatung Usw.",
    "wof:placetype":"venue"
},
  "geometry": {"coordinates":[7.6634092331,46.7622299194],"type":"Point"}
}