{
  "type": "Feature",
  "properties": {
    "iso:country":"CH",
    "sg:address":"Piazza Muraccio 18",
    "sg:city":"Locarno",
    "sg:orig_category":"Detailhandel mit Radio U Fernsehger\u00e4ten Detailhandel mit fotografischen Artikeln",
    "sg:phone":"+41 91 751 23 30",
    "sg:postcode":"6600",
    "sg:province":"Ticino",
    "wof:name":"Interdiscount Sa",
    "wof:placetype":"venue"
},
  "geometry": {"coordinates":[8.7959604263,46.167930603],"type":"Point"}
}