{
  "type": "Feature",
  "properties": {
    "iso:country":"CH",
    "sg:address":"Rue De Gen\u00e8ve 20-22",
    "sg:city":"Ch\u00eane-bourg",
    "sg:orig_category":"Detailhandel mit Pelzwaren",
    "sg:phone":"+41 22 348 19 90",
    "sg:postcode":"1225",
    "sg:province":"Gen\u00e8ve",
    "wof:name":"George Georgianos Fourreur",
    "wof:placetype":"venue"
},
  "geometry": {"coordinates":[6.1944022179,46.1943016052],"type":"Point"}
}