{
  "type": "Feature",
  "properties": {
    "iso:country":"CH",
    "sg:address":"Fr\u00f6schenweidstrasse 8",
    "sg:city":"Winterthur",
    "sg:classifiers":[
        {
            "category":"Building & Trades",
            "subcategory":"Construction",
            "type":"Services"
        }
    ],
    "sg:phone":"+41 52 233 67 17",
    "sg:postcode":"8404",
    "sg:province":"Z\u00fcrich",
    "sg:tags":[
        "component",
        "hydraulic"
    ],
    "wof:name":"Schalcher Engineering Enerpac-hydraulik",
    "wof:placetype":"venue"
},
  "geometry": {"coordinates":[8.7646369934,47.4961357117],"type":"Point"}
}