{
  "type": "Feature",
  "properties": {
    "iso:country":"CH",
    "sg:address":"G\u00fcterstrasse 39",
    "sg:city":"Diepoldsau",
    "sg:orig_category":"Unclassifiable Establishments",
    "sg:postcode":"9444",
    "sg:province":"St. Gallen",
    "wof:name":"Vzr Verm\u00f6genszentrum Rheintal Ag",
    "wof:placetype":"venue"
},
  "geometry": {"coordinates":[9.6514911652,47.3926811218],"type":"Point"}
}