{
  "type": "Feature",
  "properties": {
    "iso:country":"CH",
    "sg:address":"Z\u00fcrcherstrasse 110 8102 Oberengstringen. Postfach",
    "sg:city":"Oberengstringen",
    "sg:orig_category":"Grossbanken",
    "sg:phone":"+41 18021133",
    "sg:postcode":"8102",
    "sg:province":"Z\u00fcrich",
    "wof:name":"Credit Suisse",
    "wof:placetype":"venue"
},
  "geometry": {"coordinates":[8.6167869568,47.3971672058],"type":"Point"}
}