{
  "type": "Feature",
  "properties": {
    "iso:country":"CH",
    "sg:address":"Renggstrasse 14",
    "sg:city":"Littau",
    "sg:orig_category":"Unclassifiable Establishments",
    "sg:postcode":"6014",
    "sg:province":"Luzern",
    "wof:name":"Mode - Moll, Inhaberin Rosmarie Moll-stritt",
    "wof:placetype":"venue"
},
  "geometry": {"coordinates":[8.2582798004,47.0484580994],"type":"Point"}
}