{
  "type": "Feature",
  "properties": {
    "iso:country":"CH",
    "sg:address":"Gersauerstrasse 78",
    "sg:city":"Brunnen",
    "sg:orig_category":"Architektur U Ingenieurb\u00fcros Hoch U Tiefbau",
    "sg:phone":"+41 41 820 01 20",
    "sg:postcode":"6440",
    "sg:province":"Schwyz",
    "wof:name":"Kaiser Bauleistungen Ag",
    "wof:placetype":"venue"
},
  "geometry": {"coordinates":[8.59542,46.999329],"type":"Point"}
}