{
  "type": "Feature",
  "properties": {
    "iso:country":"CH",
    "sg:address":"Alte Landstrasse 262",
    "sg:city":"M\u00e4nnedorf",
    "sg:orig_category":"Polizei",
    "sg:phone":"+41 19200035",
    "sg:postcode":"8708",
    "sg:province":"Z\u00fcrich",
    "wof:name":"Kantonspolizei",
    "wof:placetype":"venue"
},
  "geometry": {"coordinates":[8.6958904266,47.2530555725],"type":"Point"}
}