{
  "type": "Feature",
  "properties": {
    "iso:country":"CH",
    "sg:address":"Im Geb\u00e4ude Kulm U. Sonnenberg 6377 Seelisberg. Postfach",
    "sg:city":"Seelisberg",
    "sg:orig_category":"Interessenvertretungen",
    "sg:postcode":"6377",
    "sg:province":"Uri",
    "wof:name":"Stiftung F\u00fcr Das Hauptzentrum Des Zeitalters Der Erleuchtung",
    "wof:placetype":"venue"
},
  "geometry": {"coordinates":[8.5853796005,46.9748535156],"type":"Point"}
}