{
  "type": "Feature",
  "properties": {
    "iso:country":"CH",
    "sg:address":"Pilatusstrasse 39",
    "sg:city":"Luzern",
    "sg:orig_category":"Zahnarztpraxen",
    "sg:phone":"+41 27 952 15 88",
    "sg:postcode":"6003",
    "sg:province":"Luzern",
    "wof:name":"Dr. Med. Dent. Gerold Zumstein Zahnarzt",
    "wof:placetype":"venue"
},
  "geometry": {"coordinates":[7.8664298058,46.2315216064],"type":"Point"}
}