{
  "type": "Feature",
  "properties": {
    "iso:country":"CH",
    "sg:address":"H\u00fcniweg 7 8706 Meilen. Postfach 260",
    "sg:city":"Meilen",
    "sg:orig_category":"Herstellung von sonstigen elektrischen Ausr\u00fcstungen Sonstiger Grosshandel",
    "sg:phone":"+41 79 644 32 60",
    "sg:postcode":"8706",
    "sg:province":"Z\u00fcrich",
    "wof:name":"Willi Sch\u00e4r Ag",
    "wof:placetype":"venue"
},
  "geometry": {"coordinates":[8.6418409348,47.2697105408],"type":"Point"}
}