{
  "type": "Feature",
  "properties": {
    "iso:country":"CH",
    "sg:address":"R\u00f6schibachstrasse 55",
    "sg:city":"Z\u00fcrich",
    "sg:orig_category":"Grosshandel mit Nahrungsmitteln, Getr\u00e4nken U Tabakwaren ohne ausgepr\u00e4gten Schwerpunkt",
    "sg:postcode":"8037",
    "sg:province":"Z\u00fcrich",
    "wof:name":"T\u00fcrkischer Laden S\u00f6g\u00fct",
    "wof:placetype":"venue"
},
  "geometry": {"coordinates":[7.8714990616,47.3433189392],"type":"Point"}
}