{
  "type": "Feature",
  "properties": {
    "iso:country":"CH",
    "sg:address":"Brandschenkestrasse 41 8002 Z\u00fcrich. Postfach",
    "sg:city":"Z\u00fcrich",
    "sg:orig_category":"Aktivit\u00e4t der Bankinstitute",
    "sg:phone":"+41 22 718 90 00",
    "sg:postcode":"8039",
    "wof:name":"Rabo Robeco Bank (suisse) Sa, Succursale De Gen\u00e8ve Succursale De Gen\u00e8ve",
    "wof:placetype":"venue"
},
  "geometry": {"coordinates":[6.15481,46.202759],"type":"Point"}
}