{
  "type": "Feature",
  "properties": {
    "iso:country":"CH",
    "sg:address":"Aathalstrasse 28",
    "sg:city":"Uster",
    "sg:orig_category":"Herstellung von Konstruktionsteilen, Fertigbauteilen U Ausbauelementen aus Holz Herstellung von M\u00f6be",
    "sg:phone":"+41 62 824 00 20",
    "sg:postcode":"8610",
    "sg:province":"Z\u00fcrich",
    "wof:name":"Schreinerei Schmidli Ag",
    "wof:placetype":"venue"
},
  "geometry": {"coordinates":[8.0805301666,47.3896789551],"type":"Point"}
}