{
  "type": "Feature",
  "properties": {
    "iso:country":"CH",
    "sg:address":"Chemin De La Rionda 16",
    "sg:city":"Sugiez",
    "sg:orig_category":"Non-Classified Establishments",
    "sg:postcode":"1786",
    "sg:province":"Fribourg",
    "wof:name":"Elementar, F. Br\u00fchlmann",
    "wof:placetype":"venue"
},
  "geometry": {"coordinates":[7.1109271049,46.9645957947],"type":"Point"}
}