{
  "type": "Feature",
  "properties": {
    "iso:country":"CH",
    "sg:address":"Susenbergstrasse 31 8044 Z\u00fcrich. Postfach",
    "sg:city":"Z\u00fcrich",
    "sg:orig_category":"Unclassifiable Establishments",
    "sg:postcode":"8044",
    "sg:province":"Z\u00fcrich",
    "wof:name":"Hollywood 21 Century Film Company, Wilmington (delaware/usa), Zweigniederlassung Z\u00fcrich",
    "wof:placetype":"venue"
},
  "geometry": {"coordinates":[8.567150116,47.3784408569],"type":"Point"}
}