{
  "type": "Feature",
  "properties": {
    "iso:country":"CH",
    "sg:address":"Via Cantonale",
    "sg:city":"Mezzovico",
    "sg:classifiers":[
        {
            "category":"Home & Garden",
            "subcategory":"Mobile Homes",
            "type":"Retail Goods"
        }
    ],
    "sg:phone":"+41 91 946 14 31",
    "sg:postcode":"6805",
    "sg:province":"Ticino",
    "sg:tags":[
        "awning",
        "outdoor",
        "marquee"
    ],
    "wof:name":"E. Koller S.a.",
    "wof:placetype":"venue"
},
  "geometry": {"coordinates":[8.9198827744,46.0879859924],"type":"Point"}
}