{
  "type": "Feature",
  "properties": {
    "iso:country":"CH",
    "sg:address":"Rue De La Cassarde 22",
    "sg:city":"Neuch\u00e2tel",
    "sg:orig_category":"Kinderkrippen U horte",
    "sg:phone":"+41 32 724 11 19",
    "sg:postcode":"2000",
    "sg:province":"Neuch\u00e2tel",
    "wof:name":"H\u00f4pitaux Cadolles & Pourtal\u00e8s Cr\u00e8che",
    "wof:placetype":"venue"
},
  "geometry": {"coordinates":[6.9290919304,46.9975242615],"type":"Point"}
}