{
  "type": "Feature",
  "properties": {
    "iso:country":"CH",
    "sg:address":"Wesemlinstrasse 78 6006 Luzern. Postfach",
    "sg:city":"Luzern",
    "sg:orig_category":"Interessenvertretungen",
    "sg:postcode":"6003",
    "sg:province":"Luzern",
    "wof:name":"Stiftung Pflege Wesemlinwald-kapelle",
    "wof:placetype":"venue"
},
  "geometry": {"coordinates":[8.3192853928,47.0645332336],"type":"Point"}
}