{
  "type": "Feature",
  "properties": {
    "iso:country":"CH",
    "sg:address":"Schwizerstrasse 52",
    "sg:city":"Uster",
    "sg:orig_category":"Religi\u00f6se Vereinigungen divers",
    "sg:phone":"+41 19413324",
    "sg:postcode":"8610",
    "sg:province":"Z\u00fcrich",
    "wof:name":"Cvjm/f Uster",
    "wof:placetype":"venue"
},
  "geometry": {"coordinates":[8.7204771042,47.3386154175],"type":"Point"}
}