{
  "type": "Feature",
  "properties": {
    "iso:country":"CH",
    "sg:address":"Rue Du Commerce",
    "sg:city":"Leysin",
    "sg:orig_category":"Regelm\u00e4ssige Personenbef\u00f6rderung im Fernverkehr",
    "sg:phone":"+41 27 957 19 17",
    "sg:postcode":"1854",
    "sg:province":"Vaud",
    "wof:name":"Martin Anthamatten Postautokurse",
    "wof:placetype":"venue"
},
  "geometry": {"coordinates":[7.9573631287,46.0964317322],"type":"Point"}
}