{
  "type": "Feature",
  "properties": {
    "iso:country":"CH",
    "sg:address":"Einsiedlerstrasse 176 8810 Horgen. Postfach",
    "sg:city":"Horgen",
    "sg:orig_category":"Sonstiger Grosshandel",
    "sg:postcode":"8812",
    "sg:province":"Z\u00fcrich",
    "wof:name":"Dmp Zuber + Co",
    "wof:placetype":"venue"
},
  "geometry": {"coordinates":[8.5941438675,47.2575035095],"type":"Point"}
}