{
  "type": "Feature",
  "properties": {
    "iso:country":"CH",
    "sg:address":"Kasimir-pfyffer-strasse 12",
    "sg:city":"Luzern",
    "sg:orig_category":"Kosmetikinstitute",
    "sg:phone":"+41 41 240 21 33",
    "sg:postcode":"6003",
    "sg:province":"Luzern",
    "wof:name":"K\u00e4thy Getzmann Kosmetikinstitut",
    "wof:placetype":"venue"
},
  "geometry": {"coordinates":[8.3014440536,47.0488128662],"type":"Point"}
}