{
  "type": "Feature",
  "properties": {
    "iso:country":"CH",
    "sg:address":"Dorfstrasse 4 8037 Z\u00fcrich. Postfach 526",
    "sg:city":"Z\u00fcrich",
    "sg:orig_category":"Geb\u00e4ude, Wohnungsreinigung",
    "sg:phone":"+41 12712466",
    "sg:postcode":"8037",
    "sg:province":"Z\u00fcrich",
    "wof:name":"Gammarenax Ag Stein, Fenster, Geb\u00e4ude- U. Fassadenreinigungen Usw",
    "wof:placetype":"venue"
},
  "geometry": {"coordinates":[8.5244083405,47.3939094543],"type":"Point"}
}