{
  "type": "Feature",
  "properties": {
    "iso:country":"CH",
    "sg:address":"Neumattstrasse 16 8953 Dietikon. Postfach",
    "sg:city":"Dietikon",
    "sg:orig_category":"Herstellung von Teppichen",
    "sg:phone":"+41 76 387 27 51",
    "sg:postcode":"8953",
    "sg:province":"Z\u00fcrich",
    "wof:name":"Scharr Sadiki Abdulvait Bodenlegerarbeiten, Parkett, Teppich, Linoleum, Hartbelag",
    "wof:placetype":"venue"
},
  "geometry": {"coordinates":[8.4029951096,47.4068603516],"type":"Point"}
}