{
  "type": "Feature",
  "properties": {
    "iso:country":"CH",
    "sg:address":"Strada Cantonale Grumo",
    "sg:city":"Gravesano",
    "sg:orig_category":"Einzelhandel mit Automobilteilen U Zubeh\u00f6r",
    "sg:phone":"+41 91 605 27 66",
    "sg:postcode":"6929",
    "sg:province":"Ticino",
    "wof:name":"Antonio Pompeo Riparazione Radiatori Auto",
    "wof:placetype":"venue"
},
  "geometry": {"coordinates":[8.9177694321,46.042339325],"type":"Point"}
}