{
  "type": "Feature",
  "properties": {
    "iso:country":"CH",
    "sg:address":"Br\u00fcschstrasse 92",
    "sg:city":"M\u00e4nnedorf",
    "sg:orig_category":"Herstellung von Hebezeugen U F\u00f6rdermitteln",
    "sg:postcode":"8708",
    "sg:province":"Z\u00fcrich",
    "wof:name":"Vivacor Huder R.",
    "wof:placetype":"venue"
},
  "geometry": {"coordinates":[8.7048311234,47.2522850037],"type":"Point"}
}