{
  "type": "Feature",
  "properties": {
    "iso:country":"CH",
    "sg:address":"Z\u00fcrichstrasse 33",
    "sg:city":"Neftenbach",
    "sg:classifiers":[
        {
            "category":"Professional",
            "subcategory":"Accounting & Tax Preparation",
            "type":"Services"
        }
    ],
    "sg:phone":"+41 52 315 36 26",
    "sg:postcode":"8413",
    "sg:province":"Z\u00fcrich",
    "sg:tags":[
        "book-keeping"
    ],
    "wof:name":"Gewerbe Treuhand Und Revision Ag",
    "wof:placetype":"venue"
},
  "geometry": {"coordinates":[8.664722,47.527],"type":"Point"}
}