{
  "type": "Feature",
  "properties": {
    "iso:country":"CH",
    "sg:address":"Tumigerstrasse 62a 8606 Greifensee. Postfach",
    "sg:city":"Greifensee",
    "sg:orig_category":"Non-Classified Establishments",
    "sg:postcode":"8606",
    "sg:province":"Z\u00fcrich",
    "wof:name":"Szar Gmbh",
    "wof:placetype":"venue"
},
  "geometry": {"coordinates":[8.6862211227,47.3643074036],"type":"Point"}
}