{
  "type": "Feature",
  "properties": {
    "iso:country":"CH",
    "sg:address":"Hohfurenacker 4",
    "sg:city":"Subingen",
    "sg:orig_category":"Softwareentwicklung U beratung",
    "sg:phone":"+41 21 691 33 22",
    "sg:postcode":"4553",
    "sg:province":"Solothurn",
    "wof:name":"Ailes, Lachat B. Et Svikovsky E.",
    "wof:placetype":"venue"
},
  "geometry": {"coordinates":[6.5530490875,46.515663147],"type":"Point"}
}