{
  "type": "Feature",
  "properties": {
    "iso:country":"CH",
    "sg:address":"Gurzelenstrasse 6a 4512 Bellach. Postfach",
    "sg:city":"Bellach",
    "sg:orig_category":"Handel mit Motorr\u00e4dern, Teilen U Zubeh\u00f6r Instandhaltung U Reparatur von Motorr\u00e4dern",
    "sg:postcode":"4512",
    "sg:province":"Solothurn",
    "wof:name":"Fragano Racing",
    "wof:placetype":"venue"
},
  "geometry": {"coordinates":[8.8298959732,47.2299308777],"type":"Point"}
}