{
  "type": "Feature",
  "properties": {
    "iso:country":"CH",
    "sg:address":"Terra Di Fuori",
    "sg:city":"Avegno",
    "sg:orig_category":"Sportvereine Wassersport Segeln",
    "sg:phone":"+41 91 791 34 00",
    "sg:postcode":"6670",
    "sg:province":"Ticino",
    "wof:name":"Surf Club Ascona Scasc",
    "wof:placetype":"venue"
},
  "geometry": {"coordinates":[8.7453861237,46.2082023621],"type":"Point"}
}