{
  "type": "Feature",
  "properties": {
    "iso:country":"CH",
    "sg:address":"Hauptstrasse 63 4132 Muttenz. Postfach",
    "sg:city":"Muttenz",
    "sg:orig_category":"Mechanik",
    "sg:postcode":"4132",
    "sg:province":"Basel-Landschaft",
    "wof:name":"Sch\u00fctz Schmiede - Schlosserei Gel\u00e4nder- U. Treppenbau, Kunstschmiede, Hufbeschlag Usw",
    "wof:placetype":"venue"
},
  "geometry": {"coordinates":[7.6465201378,47.5253753662],"type":"Point"}
}