{
  "type": "Feature",
  "properties": {
    "iso:country":"CH",
    "sg:address":"Vallon Route Du 56",
    "sg:city":"Ch\u00eane-bougeries",
    "sg:orig_category":"Herstellung von Schreibwaren U B\u00fcrobedarf aus Papier, Karton U Pappe",
    "sg:phone":"+41 22 349 65 10",
    "sg:postcode":"1224",
    "sg:province":"Gen\u00e8ve",
    "wof:name":"La Carterie & Co S\u00e0rl",
    "wof:placetype":"venue"
},
  "geometry": {"coordinates":[6.1872048378,46.1979255676],"type":"Point"}
}