{
  "type": "Feature",
  "properties": {
    "iso:country":"CH",
    "sg:address":"Riedrainstrasse 2",
    "sg:city":"Safnern",
    "sg:orig_category":"Instandhaltung U Reparatur von Automobilen",
    "sg:postcode":"2553",
    "sg:province":"Bern",
    "wof:name":"Garage Habermacher Ag",
    "wof:placetype":"venue"
},
  "geometry": {"coordinates":[7.3332481384,47.1552581787],"type":"Point"}
}