{
  "type": "Feature",
  "properties": {
    "iso:country":"CH",
    "sg:address":"Bleicherweg 30",
    "sg:city":"Z\u00fcrich",
    "sg:orig_category":"Non-Classified Establishments",
    "sg:postcode":"8002",
    "sg:province":"Z\u00fcrich",
    "wof:name":"San Gmbh",
    "wof:placetype":"venue"
},
  "geometry": {"coordinates":[7.8199300766,47.2484817505],"type":"Point"}
}