{
  "type": "Feature",
  "properties": {
    "iso:country":"CH",
    "sg:address":"Roggenfarstrasse 31",
    "sg:city":"Eglisau",
    "sg:orig_category":"Architektur U Ingenieurb\u00fcros",
    "sg:phone":"+41 18673723",
    "sg:postcode":"8193",
    "sg:province":"Z\u00fcrich",
    "wof:name":"Felix Meier Gmbh",
    "wof:placetype":"venue"
},
  "geometry": {"coordinates":[8.527994,47.571129],"type":"Point"}
}