{
  "type": "Feature",
  "properties": {
    "iso:country":"CH",
    "sg:address":"Rue Du Bourg 16",
    "sg:city":"Sierre",
    "sg:orig_category":"RESTAURANTS: TEA-ROOMS",
    "sg:postcode":"3960",
    "sg:province":"Valais",
    "wof:name":"Epiey Marie-th\u00e9r\u00e8se",
    "wof:placetype":"venue"
},
  "geometry": {"coordinates":[7.5343608856,46.293346405],"type":"Point"}
}