{
  "type": "Feature",
  "properties": {
    "iso:country":"CH",
    "sg:address":"Poststrasse 16",
    "sg:city":"Zug",
    "sg:orig_category":"Sonstige mit der Informatik verbundene T\u00e4tigkeiten",
    "sg:postcode":"6300",
    "sg:province":"Zug",
    "wof:name":"S - Power Gmbh",
    "wof:placetype":"venue"
},
  "geometry": {"coordinates":[8.5167655945,47.170211792],"type":"Point"}
}