{
  "type": "Feature",
  "properties": {
    "iso:country":"CH",
    "sg:address":"3758",
    "sg:city":"Latterbach",
    "sg:orig_category":"Primarschulen",
    "sg:phone":"+41 33 681 15 24",
    "sg:postcode":"3758",
    "sg:province":"Bern",
    "wof:name":"Primarschule",
    "wof:placetype":"venue"
},
  "geometry": {"coordinates":[7.578909874,46.664188385],"type":"Point"}
}