{
  "type": "Feature",
  "properties": {
    "iso:country":"CH",
    "sg:address":"Schlehdornweg 4",
    "sg:city":"Steffisburg",
    "sg:classifiers":[
        {
            "category":"Professional",
            "subcategory":"Employment Agencies",
            "type":"Services"
        }
    ],
    "sg:phone":"+41 33 437 70 77",
    "sg:postcode":"3613",
    "sg:province":"Bern",
    "sg:tags":[
        "personal",
        "u",
        "stellenvermittlung"
    ],
    "wof:name":"Comerz Consulting Gmbh Stellenvermittlung",
    "wof:placetype":"venue"
},
  "geometry": {"coordinates":[7.6228899956,46.7668571472],"type":"Point"}
}