{
  "type": "Feature",
  "properties": {
    "iso:country":"CH",
    "sg:address":"Gehren 99",
    "sg:city":"Auswil",
    "sg:orig_category":"Architektur U Ingenieurb\u00fcros",
    "sg:phone":"+41 79 647 68 07",
    "sg:postcode":"4944",
    "sg:province":"Bern",
    "wof:name":"Gerber + Partner Architekten Ag",
    "wof:placetype":"venue"
},
  "geometry": {"coordinates":[7.828945,47.136044],"type":"Point"}
}