{
  "type": "Feature",
  "properties": {
    "iso:country":"CH",
    "sg:address":"Kastelh\u00f6he 346",
    "sg:city":"Himmelried",
    "sg:orig_category":"Werbeagenturen Werbung",
    "sg:phone":"+41 61 743 00 33",
    "sg:postcode":"4204",
    "sg:province":"Solothurn",
    "wof:name":"Oberson Werbeberatung Gmbh",
    "wof:placetype":"venue"
},
  "geometry": {"coordinates":[7.5760130882,47.4278907776],"type":"Point"}
}