{
  "type": "Feature",
  "properties": {
    "iso:country":"CH",
    "sg:address":"PSE B\u00e2timent C",
    "sg:city":"Lausanne",
    "sg:classifiers":[
        {
            "category":"Manufacturing",
            "subcategory":"Electronics",
            "type":"Manufacturing & Wholesale Goods"
        }
    ],
    "sg:postcode":"CH-1015",
    "sg:website":"http://www.beamexpress.com/",
    "wof:name":"Beam Express",
    "wof:placetype":"venue"
},
  "geometry": {"coordinates":[6.5625638,46.5177782],"type":"Point"}
}