{
  "type": "Feature",
  "properties": {
    "iso:country":"CH",
    "sg:address":"Z\u00fcrcherstrasse 131",
    "sg:city":"Oberengstringen",
    "sg:orig_category":"Reiseb\u00fcros",
    "sg:phone":"+41 17511122",
    "sg:postcode":"8102",
    "sg:province":"Z\u00fcrich",
    "wof:name":"Compact Reisen",
    "wof:placetype":"venue"
},
  "geometry": {"coordinates":[8.4615688324,47.4093666077],"type":"Point"}
}