{
  "type": "Feature",
  "properties": {
    "iso:country":"CH",
    "sg:address":"Strehlgasse 5",
    "sg:city":"Biel-benken",
    "sg:classifiers":[
        {
            "category":"Banks & Credit Unions",
            "subcategory":"Investment Brokerage",
            "type":"Services"
        }
    ],
    "sg:phone":"+41 61 721 36 96",
    "sg:postcode":"4105",
    "sg:province":"Basel-Landschaft",
    "sg:tags":[
        "brushing",
        "machine",
        "cleaning",
        "surface"
    ],
    "wof:name":"Spengler Electronic Ag",
    "wof:placetype":"venue"
},
  "geometry": {"coordinates":[7.526976,47.506065],"type":"Point"}
}