{
  "type": "Feature",
  "properties": {
    "iso:country":"CH",
    "sg:address":"Zugerstrasse",
    "sg:city":"W\u00e4denswil",
    "sg:orig_category":"Herstellung von M\u00f6beln verschiedener Art Herstellung von sonstigen Metallwaren",
    "sg:phone":"+41 17811313",
    "sg:postcode":"8820",
    "sg:province":"Z\u00fcrich",
    "wof:name":"Weiss Ernst Ag",
    "wof:placetype":"venue"
},
  "geometry": {"coordinates":[8.6411895752,47.2379302979],"type":"Point"}
}