{
  "type": "Feature",
  "properties": {
    "iso:country":"CH",
    "sg:address":"Chemin Alfred-borel 13",
    "sg:city":"Bevaix",
    "sg:orig_category":"Fachdetailhandel in Verkaufsr\u00e4umen",
    "sg:phone":"+41 32 846 16 66",
    "sg:postcode":"2022",
    "sg:province":"Neuch\u00e2tel",
    "wof:name":"Humbert-droz Francis",
    "wof:placetype":"venue"
},
  "geometry": {"coordinates":[6.8164038658,46.9227561951],"type":"Point"}
}