{
  "type": "Feature",
  "properties": {
    "iso:country":"CH",
    "sg:address":"Sebastiansgasse 8",
    "sg:city":"Brig",
    "sg:orig_category":"Sonstiger Fachdetailhandel in Verkaufsr\u00e4umen",
    "sg:phone":"+41 27 923 69 89",
    "sg:postcode":"3900",
    "sg:province":"Valais",
    "wof:name":"Paul Imhof Sammler-ecke",
    "wof:placetype":"venue"
},
  "geometry": {"coordinates":[7.9888300896,46.3166885376],"type":"Point"}
}