{
  "type": "Feature",
  "properties": {
    "iso:country":"CH",
    "sg:address":"Rue Louis-favre 7",
    "sg:city":"Boudry",
    "sg:orig_category":"Architektur U Ingenieurb\u00fcros",
    "sg:phone":"+41 32 842 57 64",
    "sg:postcode":"2017",
    "sg:province":"Neuch\u00e2tel",
    "wof:name":"Bureau Technique, Borel Ren\u00e9",
    "wof:placetype":"venue"
},
  "geometry": {"coordinates":[6.837326,46.948753],"type":"Point"}
}