{
  "type": "Feature",
  "properties": {
    "iso:country":"CH",
    "sg:address":"Wasserhaus 34",
    "sg:city":"M\u00fcnchenstein",
    "sg:orig_category":"P\u00e9dicure",
    "sg:phone":"+41 61 411 70 09",
    "sg:postcode":"4142",
    "sg:province":"Basel-Landschaft",
    "wof:name":"Ella Gr\u00f6bli P\u00e9dicure",
    "wof:placetype":"venue"
},
  "geometry": {"coordinates":[7.6194939613,47.5269775391],"type":"Point"}
}