{
  "type": "Feature",
  "properties": {
    "iso:country":"CH",
    "sg:address":"Neufeldstrasse 20",
    "sg:city":"Wettingen",
    "sg:orig_category":"Interessenvertretungen",
    "sg:phone":"+41 56 426 98 39",
    "sg:postcode":"5430",
    "sg:province":"Aargau",
    "wof:name":"Aargauischer Detaillisten-verband",
    "wof:placetype":"venue"
},
  "geometry": {"coordinates":[8.3397083282,47.4591407776],"type":"Point"}
}