{
  "type": "Feature",
  "properties": {
    "iso:country":"CH",
    "sg:address":"3979",
    "sg:city":"Gr\u00f4ne",
    "sg:orig_category":"Stukkateurgewerbe, Gipserei U Verputzerei",
    "sg:phone":"+41 27 458 12 61",
    "sg:postcode":"3979",
    "sg:province":"Valais",
    "wof:name":"Zufferey Jean-louis",
    "wof:placetype":"venue"
},
  "geometry": {"coordinates":[7.4571409225,46.2511062622],"type":"Point"}
}