{
  "type": "Feature",
  "properties": {
    "iso:country":"CH",
    "sg:address":"Hauptstrasse 591",
    "sg:city":"Oberbuchsiten",
    "sg:classifiers":[
        {
            "category":"Home & Garden",
            "subcategory":"Building Materials",
            "type":"Retail Goods"
        }
    ],
    "sg:phone":"+41 62 389 98 99",
    "sg:postcode":"4625",
    "sg:province":"Solothurn",
    "sg:tags":[
        "appraisal",
        "damage"
    ],
    "wof:name":"Imp Bautest Ag",
    "wof:placetype":"venue"
},
  "geometry": {"coordinates":[7.773408,47.313148],"type":"Point"}
}