{
  "type": "Feature",
  "properties": {
    "iso:country":"CH",
    "sg:address":"Rue Couvaloup 2",
    "sg:city":"Morges",
    "sg:orig_category":"Fachdetailhandel in Verkaufsr\u00e4umen",
    "sg:phone":"+41 21 803 16 49",
    "sg:postcode":"1110",
    "sg:province":"Vaud",
    "wof:name":"Guichard Jacqueline",
    "wof:placetype":"venue"
},
  "geometry": {"coordinates":[6.4993982315,46.5107841492],"type":"Point"}
}