{
  "type": "Feature",
  "properties": {
    "iso:country":"CH",
    "sg:address":"Bahnhofstrasse 3",
    "sg:city":"Heerbrugg",
    "sg:orig_category":"Wirtschafts- and Arbeitgeberverb\u00e4nde",
    "sg:phone":"+41 71 722 10 45",
    "sg:postcode":"9435",
    "sg:province":"St. Gallen",
    "wof:name":"Arbeitgeberverband D.rheintals Sekretariat",
    "wof:placetype":"venue"
},
  "geometry": {"coordinates":[9.6260986328,47.4101333618],"type":"Point"}
}