{
  "type": "Feature",
  "properties": {
    "iso:country":"CH",
    "sg:address":"Landis + Gyr-strasse 1 6300 Zug. Postfach",
    "sg:city":"Schaffhausen",
    "sg:orig_category":"Unclassifiable Establishments",
    "sg:phone":"+41 52 630 91 11",
    "sg:postcode":"8200",
    "sg:province":"Schaffhausen",
    "wof:name":"Cilag Holding Ag",
    "wof:placetype":"venue"
},
  "geometry": {"coordinates":[8.5122509003,47.1759338379],"type":"Point"}
}