{
  "type": "Feature",
  "properties": {
    "iso:country":"CH",
    "sg:address":"Untere Hinterlohstrasse 13",
    "sg:city":"Romanshorn",
    "sg:orig_category":"Wohnheime",
    "sg:postcode":"8590",
    "sg:province":"Thurgau",
    "wof:name":"Genossenschaft Alterssiedlung Wiesental, Andwil",
    "wof:placetype":"venue"
},
  "geometry": {"coordinates":[9.2762403488,47.4391708374],"type":"Point"}
}