{
  "type": "Feature",
  "properties": {
    "iso:country":"CH",
    "sg:address":"1148",
    "sg:city":"Mauraz",
    "sg:orig_category":"Herstellung von elektronischen Bauelementen",
    "sg:phone":"+41 21 864 32 16",
    "sg:postcode":"1148",
    "sg:province":"Vaud",
    "wof:name":"Pips Tronic Pfeiffer F.",
    "wof:placetype":"venue"
},
  "geometry": {"coordinates":[6.4208111763,46.6059188843],"type":"Point"}
}