{
  "type": "Feature",
  "properties": {
    "iso:country":"CH",
    "sg:address":"Rue Centrale 43-45 1880 Bex. Postfach",
    "sg:city":"Bex",
    "sg:orig_category":"RESTAURANTS: TEA-ROOMS",
    "sg:postcode":"1880",
    "sg:province":"Vaud",
    "wof:name":"Cafe-restaurant La Chouette S\u00e0rl",
    "wof:placetype":"venue"
},
  "geometry": {"coordinates":[7.0159568787,46.250202179],"type":"Point"}
}