{
  "type": "Feature",
  "properties": {
    "iso:country":"CH",
    "sg:address":"Rue Dancet 4 1200 Genf. Postfach",
    "sg:city":"Gen\u00e8ve",
    "sg:orig_category":"RESTAURANTS: TEA-ROOMS",
    "sg:postcode":"1205",
    "sg:province":"Gen\u00e8ve",
    "wof:name":"Puccio",
    "wof:placetype":"venue"
},
  "geometry": {"coordinates":[6.1415247917,46.1943588257],"type":"Point"}
}