{
  "type": "Feature",
  "properties": {
    "iso:country":"CH",
    "sg:address":"Obermad.",
    "sg:city":"Gadmen",
    "sg:orig_category":"S\u00e4ge, Hobel U Holzimpr\u00e4gnierwerke",
    "sg:phone":"+41 33 975 11 34",
    "sg:postcode":"3863",
    "sg:province":"Bern",
    "wof:name":"Hans K\u00fchner",
    "wof:placetype":"venue"
},
  "geometry": {"coordinates":[8.3599185944,46.7385978699],"type":"Point"}
}