{
  "type": "Feature",
  "properties": {
    "iso:country":"CH",
    "sg:address":"Bahnhofstrasse 3",
    "sg:city":"Dallenwil",
    "sg:classifiers":[
        {
            "category":"Professional",
            "subcategory":"Engineering",
            "type":"Services"
        }
    ],
    "sg:phone":"+41 41 628 10 29",
    "sg:postcode":"6383",
    "sg:province":"Nidwalden",
    "wof:name":"Franz Niederberger Ingenieurb\u00fcro",
    "wof:placetype":"venue"
},
  "geometry": {"coordinates":[8.3912553787,46.9326705933],"type":"Point"}
}