{
  "type": "Feature",
  "properties": {
    "addr:full":"Hebelstrasse 81 Basel Basel-Stadt 4056",
    "addr:housenumber":"81",
    "addr:postcode":"4056",
    "addr:street":"Hebelstrasse",
    "iso:country":"CH",
    "sg:address":"Hebelstrasse 81",
    "sg:city":"Basel",
    "sg:orig_category":"Degreasing Agents",
    "sg:phone":"+41 61 261 02 00",
    "sg:postcode":"4056",
    "sg:province":"Basel-Stadt",
    "wof:name":"Paroba-chemie",
    "wof:placetype":"venue"
},
  "geometry": {"coordinates":[7.578413,47.562248],"type":"Point"}
}