{
  "type": "Feature",
  "properties": {
    "iso:country":"CH",
    "sg:address":"3860",
    "sg:city":"Meiringen",
    "sg:orig_category":"Haltung von Rindern",
    "sg:postcode":"3860",
    "sg:province":"Bern",
    "wof:name":"Braunviehzuchtgenossenschaft Meiringen Und Umgebung",
    "wof:placetype":"venue"
},
  "geometry": {"coordinates":[8.186214447,46.7278556824],"type":"Point"}
}