{
  "type": "Feature",
  "properties": {
    "iso:country":"CH",
    "sg:address":"Rue De La Monder\u00e8che 18",
    "sg:city":"Sierre",
    "sg:orig_category":"Gymnastik U Fitnesszentren",
    "sg:phone":"+41 27 456 56 95",
    "sg:postcode":"3960",
    "sg:province":"Valais",
    "wof:name":"Robert Molnar Leader Fitness Line",
    "wof:placetype":"venue"
},
  "geometry": {"coordinates":[7.5328168869,46.2894439697],"type":"Point"}
}