{
  "type": "Feature",
  "properties": {
    "iso:country":"CH",
    "sg:address":"Bielstrasse 15",
    "sg:city":"Grenchen",
    "sg:orig_category":"Arztpraxen",
    "sg:phone":"+41 32 652 26 36",
    "sg:postcode":"2540",
    "sg:province":"Solothurn",
    "wof:name":"Dr.med.daniel Widmer Spezialarzt Fmh",
    "wof:placetype":"venue"
},
  "geometry": {"coordinates":[7.394959,47.191879],"type":"Point"}
}