{
  "type": "Feature",
  "properties": {
    "iso:country":"CH",
    "sg:address":"Neuch\u00e2tel Route De 3 1588 Cudrefin. Postfach",
    "sg:city":"Cudrefin",
    "sg:orig_category":"Detailhandel mit Bekleidung",
    "sg:phone":"+41 26 677 41 41",
    "sg:postcode":"1588",
    "sg:province":"Vaud",
    "wof:name":"Marin-mode Ltd, Londres, Succursale De Cudrefin Commerce De V\u00eatements Et Accessoires",
    "wof:placetype":"venue"
},
  "geometry": {"coordinates":[7.018711,46.956837],"type":"Point"}
}