{
  "type": "Feature",
  "properties": {
    "iso:country":"CH",
    "sg:address":"6388",
    "sg:city":"Grafenort",
    "sg:orig_category":"Sonstige Herstellung von Konstruktionsteilen, Fertigbauteilen U Ausbauelementen aus Holz S\u00e4gewerke",
    "sg:phone":"+41 55 410 11 32",
    "sg:postcode":"6388",
    "sg:province":"Obwalden",
    "wof:name":"Peter M\u00fcller Ag Schindel-& Holzwollefabrik",
    "wof:placetype":"venue"
},
  "geometry": {"coordinates":[8.776268959,47.2010726929],"type":"Point"}
}