{
  "type": "Feature",
  "properties": {
    "iso:country":"CH",
    "sg:address":"Dorfstrasse 4",
    "sg:city":"Fislisbach",
    "sg:orig_category":"Detailhandel an Verkaufsst\u00e4nden U auf M\u00e4rkten",
    "sg:phone":"+41 56 484 80 20",
    "sg:postcode":"5442",
    "sg:province":"Aargau",
    "wof:name":"Senn-kaffee Kaffeemaschinencenter",
    "wof:placetype":"venue"
},
  "geometry": {"coordinates":[8.292052,47.436382],"type":"Point"}
}