{
  "type": "Feature",
  "properties": {
    "iso:country":"CH",
    "sg:address":"Wengistrasse 16",
    "sg:city":"Solothurn",
    "sg:orig_category":"Detailhandel mit Waren verschiedener Art, Hauptrichtung Nahrungsmittel Grosshandel mit Kaffee, Tee, ",
    "sg:phone":"+41 76 372 35 36",
    "sg:postcode":"4500",
    "sg:province":"Solothurn",
    "wof:name":"Carlito-coffee-shop",
    "wof:placetype":"venue"
},
  "geometry": {"coordinates":[7.5335001945,47.2070121765],"type":"Point"}
}