{
  "type": "Feature",
  "properties": {
    "iso:country":"CH",
    "sg:address":"B\u00fchl 6",
    "sg:city":"Altb\u00fcron",
    "sg:orig_category":"Institutionen f\u00fcr Finanzierungsleasing",
    "sg:phone":"+41 62 927 62 00",
    "sg:postcode":"6147",
    "sg:province":"Luzern",
    "wof:name":"Franfinance Switzerland Ag",
    "wof:placetype":"venue"
},
  "geometry": {"coordinates":[7.8842978477,47.1816444397],"type":"Point"}
}