{
  "type": "Feature",
  "properties": {
    "addr:full":"4900 Langenthal. Postfach Langenthal Bern 4900",
    "addr:postcode":"4900;4900",
    "addr:street":"Langenthal. Postfach;Bern",
    "iso:country":"CH",
    "sg:address":"4900 Langenthal. Postfach",
    "sg:city":"Langenthal",
    "sg:orig_category":"Pensionskassen",
    "sg:phone":"+41 62 771 24 66",
    "sg:postcode":"4900",
    "sg:province":"Bern",
    "wof:name":"Personalf\u00fcrsorgestiftung Der Merz & Cie Drahtwerk Ag",
    "wof:placetype":"venue"
},
  "geometry": {"coordinates":[8.171834,47.270107],"type":"Point"}
}