{
  "type": "Feature",
  "properties": {
    "iso:country":"CH",
    "sg:address":"Rue De La Gare 9 1030 Bussigny-lausanne Case Postale 333",
    "sg:city":"Bussigny-lausanne",
    "sg:orig_category":"Detailhandel mit Milcherzeugnissen U Eiern Sonstiger Fachdetailhandel mit Nahrungsmitteln, Getr\u00e4nken",
    "sg:phone":"+41 33 676 32 23",
    "sg:postcode":"1030",
    "sg:province":"Vaud",
    "wof:name":"Peter Zurbuchen Milch-& K\u00e4sespezialit\u00e4ten",
    "wof:placetype":"venue"
},
  "geometry": {"coordinates":[7.6900019646,46.6245803833],"type":"Point"}
}