{
  "type": "Feature",
  "properties": {
    "iso:country":"CH",
    "sg:address":"Schweizergasse 14",
    "sg:city":"Z\u00fcrich",
    "sg:orig_category":"Softwareentwicklung U beratung",
    "sg:postcode":"8021",
    "sg:province":"Z\u00fcrich",
    "wof:name":"Tarimed Gmbh",
    "wof:placetype":"venue"
},
  "geometry": {"coordinates":[8.5377521515,47.3762359619],"type":"Point"}
}