{
  "type": "Feature",
  "properties": {
    "iso:country":"CH",
    "sg:address":"Lavaterstrasse 81",
    "sg:city":"Z\u00fcrich",
    "sg:orig_category":"Detektivb\u00fcros U \u00dcberwachung",
    "sg:phone":"+41 22 321 37 22",
    "sg:postcode":"8002",
    "sg:province":"Z\u00fcrich",
    "wof:name":"Acp Securite Sarl Agence De S\u00e9curit\u00e9 Et D'investigations Priv\u00e9es, Filatures Etc",
    "wof:placetype":"venue"
},
  "geometry": {"coordinates":[6.1446371078,46.1954154968],"type":"Point"}
}