{
  "type": "Feature",
  "properties": {
    "iso:country":"CH",
    "sg:address":"Dorfplatz 11",
    "sg:city":"Niederwichtrach",
    "sg:orig_category":"Detailhandel mit Brot, Back U S\u00fcsswaren",
    "sg:phone":"+41 31 781 01 41",
    "sg:postcode":"3114",
    "sg:province":"Bern",
    "wof:name":"Jorns",
    "wof:placetype":"venue"
},
  "geometry": {"coordinates":[7.57607,46.849972],"type":"Point"}
}