{
  "type": "Feature",
  "properties": {
    "iso:country":"CH",
    "sg:address":"Alterschwil",
    "sg:city":"Flawil",
    "sg:orig_category":"Interessenvertretungen",
    "sg:postcode":"9230",
    "sg:province":"St. Gallen",
    "wof:name":"Dorfkorporation Alterswil",
    "wof:placetype":"venue"
},
  "geometry": {"coordinates":[9.2034702301,47.3950195312],"type":"Point"}
}