{
  "type": "Feature",
  "properties": {
    "iso:country":"CH",
    "sg:address":"Bundesstrasse 3",
    "sg:city":"Zug",
    "sg:orig_category":"Rechtsberatung",
    "sg:phone":"+41 41 711 60 15",
    "sg:postcode":"6300",
    "sg:province":"Zug",
    "wof:name":"Istag Ag Zug",
    "wof:placetype":"venue"
},
  "geometry": {"coordinates":[8.5136566162,47.1713104248],"type":"Point"}
}