{
  "type": "Feature",
  "properties": {
    "iso:country":"CH",
    "sg:address":"Industriestrasse 13",
    "sg:city":"Nieder\u00f6nz",
    "sg:orig_category":"Herstellung von Metallerzeugnissen ohne Maschinenbau Herstellung von Pumpen U Kompressoren",
    "sg:phone":"+41 19381515",
    "sg:postcode":"3362",
    "sg:province":"Bern",
    "wof:name":"Fdc Holding Ag",
    "wof:placetype":"venue"
},
  "geometry": {"coordinates":[8.8368453979,47.3006668091],"type":"Point"}
}