{
  "type": "Feature",
  "properties": {
    "iso:country":"CH",
    "sg:address":"Axenstrasse 3",
    "sg:city":"Brunnen",
    "sg:orig_category":"Markt U Meinungsforschung",
    "sg:phone":"+41 21 691 50 72",
    "sg:postcode":"6440",
    "sg:province":"Schwyz",
    "wof:name":"Tissot Jean-pierre",
    "wof:placetype":"venue"
},
  "geometry": {"coordinates":[6.5552411079,46.5117607117],"type":"Point"}
}