{
  "type": "Feature",
  "properties": {
    "iso:country":"CH",
    "sg:address":"Le Creux 1337 Vallorbe Case Postale Case Postale",
    "sg:city":"Vallorbe",
    "sg:orig_category":"Autotransporte international G\u00fcterbef\u00f6rderung im Strassenverkehr",
    "sg:phone":"+41 21 843 12 58",
    "sg:postcode":"1337",
    "sg:province":"Vaud",
    "wof:name":"Danzas Sa",
    "wof:placetype":"venue"
},
  "geometry": {"coordinates":[6.38491,46.731441],"type":"Point"}
}