{
  "type": "Feature",
  "properties": {
    "iso:country":"CH",
    "sg:address":"5064",
    "sg:city":"Wittnau",
    "sg:orig_category":"Vorschulen, Kinderg\u00e4rten",
    "sg:phone":"+41 62 871 18 81",
    "sg:postcode":"5064",
    "sg:province":"Aargau",
    "wof:name":"Kindergarten",
    "wof:placetype":"venue"
},
  "geometry": {"coordinates":[7.9845299721,47.4830818176],"type":"Point"}
}