{
  "type": "Feature",
  "properties": {
    "iso:country":"CH",
    "sg:address":"Strassburgstrasse 11 8004 Z\u00fcrich. Postfach 915",
    "sg:city":"Z\u00fcrich",
    "sg:orig_category":"Arbeitnehmerverb\u00e4nde",
    "sg:phone":"+41 17602800",
    "sg:postcode":"8021",
    "sg:province":"Z\u00fcrich",
    "wof:name":"Gewerkschaft Bau-& Industrie Sektion Affoltern Am Albis",
    "wof:placetype":"venue"
},
  "geometry": {"coordinates":[8.441432,47.272354],"type":"Point"}
}