{
  "type": "Feature",
  "properties": {
    "iso:country":"CH",
    "sg:address":"Industriestrasse",
    "sg:city":"Kerzers",
    "sg:orig_category":"Instandhaltung U Reparatur von Automobilen",
    "sg:phone":"+41 79 333 91 19",
    "sg:postcode":"3210",
    "sg:province":"Fribourg",
    "wof:name":"Ibit Ag",
    "wof:placetype":"venue"
},
  "geometry": {"coordinates":[7.1878929138,46.9712257385],"type":"Point"}
}