{
  "type": "Feature",
  "properties": {
    "iso:country":"CH",
    "sg:address":"Grenzweg 10",
    "sg:city":"Sch\u00f6ftland",
    "sg:orig_category":"Herstellung von Bergwerks U Baumaschinen",
    "sg:phone":"+41 62 721 33 34",
    "sg:postcode":"5040",
    "sg:province":"Aargau",
    "wof:name":"Klemm Bohrtechnik Ag",
    "wof:placetype":"venue"
},
  "geometry": {"coordinates":[8.0545082092,47.3147468567],"type":"Point"}
}