{
  "type": "Feature",
  "properties": {
    "iso:country":"CH",
    "sg:address":"Burstwiesenstrasse 62",
    "sg:city":"Z\u00fcrich",
    "sg:orig_category":"Unternehmensberatung",
    "sg:phone":"+41 81 921 54 94",
    "sg:postcode":"8055",
    "sg:province":"Z\u00fcrich",
    "wof:name":"Wehrli Lic. Oec. Publ. Hansj\u00f6rg Beratung Projektmanagement Schulung",
    "wof:placetype":"venue"
},
  "geometry": {"coordinates":[9.2555236816,46.8044929504],"type":"Point"}
}