{
  "type": "Feature",
  "properties": {
    "iso:country":"CH",
    "sg:address":"Dorfstrasse 62",
    "sg:city":"Signau",
    "sg:orig_category":"Mit dem Versicherungsgewerbe verbundene T\u00e4tigkeiten",
    "sg:phone":"+41 41 630 35 84",
    "sg:postcode":"3534",
    "sg:province":"Bern",
    "wof:name":"Ynor, Norbert B\u00fcrki",
    "wof:placetype":"venue"
},
  "geometry": {"coordinates":[8.2672920227,47.0947799683],"type":"Point"}
}