{
  "type": "Feature",
  "properties": {
    "iso:country":"CH",
    "sg:address":"Baarerstrasse 69 6300 Zug. Postfach 2214",
    "sg:city":"Zug",
    "sg:orig_category":"Unternehmensberatung",
    "sg:phone":"+41 41 729 35 35",
    "sg:postcode":"6302",
    "sg:province":"Zug",
    "wof:name":"K\u00fcng & Partner Treuhand Ag",
    "wof:placetype":"venue"
},
  "geometry": {"coordinates":[8.5175647736,47.1766815186],"type":"Point"}
}