{
  "type": "Feature",
  "properties": {
    "iso:country":"CH",
    "sg:address":"Steinligasse 13",
    "sg:city":"M\u00f6hlin",
    "sg:classifiers":[
        {
            "category":"Retail",
            "subcategory":"Auto Repair",
            "type":"Services"
        }
    ],
    "sg:phone":"+41 61 853 91 67",
    "sg:postcode":"4313",
    "sg:province":"Aargau",
    "sg:tags":[
        "machine",
        "automatic",
        "welding"
    ],
    "wof:name":"Wolf & Sohn Schweisstechnik",
    "wof:placetype":"venue"
},
  "geometry": {"coordinates":[7.842551,47.567326],"type":"Point"}
}