{
  "type": "Feature",
  "properties": {
    "iso:country":"CH",
    "sg:address":"Sous-les-rennauds",
    "sg:city":"Yvorne",
    "sg:orig_category":"Rebbau",
    "sg:phone":"+41 24 466 30 24",
    "sg:postcode":"1853",
    "sg:province":"Vaud",
    "wof:name":"Francis Ansermoz P\u00e9pinieriste-viticulteur",
    "wof:placetype":"venue"
},
  "geometry": {"coordinates":[6.9555549622,46.3306732178],"type":"Point"}
}