{
  "type": "Feature",
  "properties": {
    "iso:country":"CH",
    "sg:address":"Ackerstrasse",
    "sg:city":"Uster",
    "sg:orig_category":"Vorschulen, Kinderg\u00e4rten",
    "sg:phone":"+41 19415457",
    "sg:postcode":"8610",
    "sg:province":"Z\u00fcrich",
    "wof:name":"Kindergarten",
    "wof:placetype":"venue"
},
  "geometry": {"coordinates":[8.7060880661,47.3569984436],"type":"Point"}
}