{
  "type": "Feature",
  "properties": {
    "addr:full":"Sch\u00f6nbeinstrasse 6 Basel Basel-Stadt 4056",
    "addr:housenumber":"6",
    "addr:postcode":"4056",
    "addr:street":"Schoenbeinstrasse",
    "iso:country":"CH",
    "sg:address":"Sch\u00f6nbeinstrasse 6",
    "sg:city":"Basel",
    "sg:orig_category":"Allgemeiner Gartenbau Blumen U Zierpflanzenbau",
    "sg:phone":"+41 61 267 35 19",
    "sg:postcode":"4056",
    "sg:province":"Basel-Stadt",
    "wof:name":"Botanischer Garten Der Universit\u00e4t",
    "wof:placetype":"venue"
},
  "geometry": {"coordinates":[7.581135,47.558479],"type":"Point"}
}