{
  "type": "Feature",
  "properties": {
    "iso:country":"CH",
    "sg:address":"Bahnhofstrasse 12 3900 Brig. Postfach 357",
    "sg:city":"Brig",
    "sg:orig_category":"Advokaturb\u00fcros Notariate",
    "sg:phone":"+41 27 923 61 81",
    "sg:postcode":"3900",
    "sg:province":"Valais",
    "wof:name":"Dr.bruno Imhof Advokatur-& Notariatsb\u00fcro",
    "wof:placetype":"venue"
},
  "geometry": {"coordinates":[7.987991,46.317154],"type":"Point"}
}