{
  "type": "Feature",
  "properties": {
    "iso:country":"CH",
    "sg:address":"Grynau",
    "sg:city":"Uznach",
    "sg:orig_category":"Elektrizit\u00e4tsversorgung",
    "sg:phone":"+41 55 280 26 81",
    "sg:postcode":"8730",
    "sg:province":"St. Gallen",
    "wof:name":"Nordostschweiz.kraftwerke Werkhof Grynau",
    "wof:placetype":"venue"
},
  "geometry": {"coordinates":[8.9838247299,47.224193573],"type":"Point"}
}