{
  "type": "Feature",
  "properties": {
    "iso:country":"CH",
    "sg:address":"Stegackerstrasse 6",
    "sg:city":"Winterthur",
    "sg:classifiers":[
        {
            "category":"Utilities",
            "subcategory":"Electric",
            "type":"Services"
        }
    ],
    "sg:phone":"+41 52 235 15 95",
    "sg:postcode":"8409",
    "sg:province":"Z\u00fcrich",
    "sg:tags":[
        "software",
        "electro-planning",
        "cad"
    ],
    "wof:name":"Bsk Brot Scann- Und Kopiertechnik",
    "wof:placetype":"venue"
},
  "geometry": {"coordinates":[8.770617,47.501392],"type":"Point"}
}