{
  "type": "Feature",
  "properties": {
    "iso:country":"CH",
    "sg:address":"Landstrasse 79 4313 M\u00f6hlin. Postfach",
    "sg:city":"M\u00f6hlin",
    "sg:orig_category":"Ausbaugewerbe",
    "sg:postcode":"4313",
    "sg:province":"Aargau",
    "wof:name":"Chemin\u00e9es La Fiamma Donato Di Munno.",
    "wof:placetype":"venue"
},
  "geometry": {"coordinates":[6.856064,46.96843],"type":"Point"}
}