{
  "type": "Feature",
  "properties": {
    "iso:country":"CH",
    "sg:address":"Rue St-pierre 18",
    "sg:city":"Fribourg",
    "sg:orig_category":"Effektenvermittlung Broker Finanzierungsinstitutionen",
    "sg:phone":"+41 26 347 26 00",
    "sg:postcode":"1700",
    "sg:province":"Fribourg",
    "wof:name":"Rouiller, Zurkinden Et Cie Finance Sa",
    "wof:placetype":"venue"
},
  "geometry": {"coordinates":[7.1558661461,46.8040313721],"type":"Point"}
}