{
  "type": "Feature",
  "properties": {
    "iso:country":"CH",
    "sg:address":"Ruelle De La Truite",
    "sg:city":"Noville",
    "sg:orig_category":"Hardwareberatung",
    "sg:postcode":"1845",
    "sg:province":"Vaud",
    "wof:name":"Computer Farm S\u00e0rl",
    "wof:placetype":"venue"
},
  "geometry": {"coordinates":[6.8996710777,46.3805465698],"type":"Point"}
}