{
  "type": "Feature",
  "properties": {
    "iso:country":"CH",
    "sg:address":"Fabrica Ragazzi",
    "sg:city":"Poschiavo",
    "sg:orig_category":"Blumen U Zierpflanzenbau Gem\u00fcsebau",
    "sg:phone":"+41 81 844 14 33",
    "sg:postcode":"7742",
    "sg:province":"Graubunden",
    "wof:name":"Giardineria Fondovilla Fiori & Verdura Biologica",
    "wof:placetype":"venue"
},
  "geometry": {"coordinates":[10.057185,46.322933],"type":"Point"}
}