{
  "type": "Feature",
  "properties": {
    "iso:country":"CH",
    "sg:address":"Baselstrasse 32d",
    "sg:city":"Wiedlisbach",
    "sg:orig_category":"Architektur U Ingenieurb\u00fcros Mechanische Werkst\u00e4tten",
    "sg:phone":"+41 79 643 10 37",
    "sg:postcode":"4537",
    "sg:province":"Bern",
    "wof:name":"Ggt Germann Gleit-technik Gmbh",
    "wof:placetype":"venue"
},
  "geometry": {"coordinates":[8.441568,47.081211],"type":"Point"}
}