{
  "type": "Feature",
  "properties": {
    "iso:country":"CH",
    "sg:address":"Gerliswilstrasse 53 6020 Emmenbr\u00fccke. Postfach",
    "sg:city":"Emmenbr\u00fccke",
    "sg:orig_category":"Sonstiger Fachdetailhandel mit Nahrungsmitteln, Getr\u00e4nken U Tabak in Verkaufsr\u00e4umen",
    "sg:phone":"+41 41 260 07 17",
    "sg:postcode":"6020",
    "sg:province":"Luzern",
    "wof:name":"Tant\u00e2-w\u00e2n Thai Food Shop Gmbh",
    "wof:placetype":"venue"
},
  "geometry": {"coordinates":[8.2764425278,47.0747909546],"type":"Point"}
}