{
  "type": "Feature",
  "properties": {
    "iso:country":"CH",
    "sg:address":"Weststrasse 14",
    "sg:city":"Dietikon",
    "sg:orig_category":"Architektur U Ingenieurb\u00fcros Architekturb\u00fcros",
    "sg:phone":"+41 17482535",
    "sg:postcode":"8953",
    "sg:province":"Z\u00fcrich",
    "wof:name":"Canziani Architektur Ag",
    "wof:placetype":"venue"
},
  "geometry": {"coordinates":[8.393745,47.403049],"type":"Point"}
}