{
  "type": "Feature",
  "properties": {
    "iso:country":"CH",
    "sg:address":"Avenue De B\u00e9thusy 19 1005 Lausanne. Postfach",
    "sg:city":"Lausanne",
    "sg:orig_category":"Detailhandel mit M\u00f6beln U Haushaltsgegenst\u00e4nden Detailhandel mit Teppichen",
    "sg:phone":"+41 21 647 41 17",
    "sg:postcode":"1003",
    "sg:province":"Vaud",
    "wof:name":"Gerard Tapis S\u00e0rl",
    "wof:placetype":"venue"
},
  "geometry": {"coordinates":[6.6444139481,46.5212402344],"type":"Point"}
}