{
  "type": "Feature",
  "properties": {
    "iso:country":"CH",
    "sg:address":"Aarauerstrasse 101 5015 Niedererlinsbach. Postfach",
    "sg:city":"Niedererlinsbach",
    "sg:orig_category":"Markt U Meinungsforschung Werbung",
    "sg:phone":"+41 32 724 26 66",
    "sg:postcode":"5015",
    "sg:province":"Solothurn",
    "wof:name":"Ullberg Sa",
    "wof:placetype":"venue"
},
  "geometry": {"coordinates":[6.9299740791,46.9904823303],"type":"Point"}
}