{
  "type": "Feature",
  "properties": {
    "iso:country":"CH",
    "sg:address":"Wiesengasse 5",
    "sg:city":"Schaan",
    "sg:orig_category":"Werbevermittlung",
    "sg:phone":"+423 239 70 80",
    "sg:postcode":"9494",
    "wof:name":"Kurt B\u00fchler Ag Studio F\u00fcr Werbung & Design",
    "wof:placetype":"venue"
},
  "geometry": {"coordinates":[9.5081167221,47.1636581421],"type":"Point"}
}