{
  "type": "Feature",
  "properties": {
    "iso:country":"CH",
    "sg:address":"Chemin De La Truite 4 2500 Biel/bienne. Postfach",
    "sg:city":"Biel/bienne",
    "sg:orig_category":"Stukkateurgewerbe, Gipserei U Verputzerei",
    "sg:phone":"+41 32 342 57 87",
    "sg:postcode":"2504",
    "sg:province":"Bern",
    "wof:name":"Buonpane A.",
    "wof:placetype":"venue"
},
  "geometry": {"coordinates":[7.2670221329,47.1454124451],"type":"Point"}
}