{
  "type": "Feature",
  "properties": {
    "iso:country":"CH",
    "sg:address":"Rue Des Bains 25",
    "sg:city":"Gen\u00e8ve",
    "sg:orig_category":"Elektroinstallation",
    "sg:phone":"+41 22 800 37 07",
    "sg:postcode":"1205",
    "sg:province":"Gen\u00e8ve",
    "wof:name":"Giuseppe Armeli Electro-top",
    "wof:placetype":"venue"
},
  "geometry": {"coordinates":[6.1364297867,46.1981544495],"type":"Point"}
}