{
  "type": "Feature",
  "properties": {
    "iso:country":"CH",
    "sg:address":"Hostetstrasse 4",
    "sg:city":"Berneck",
    "sg:classifiers":[
        {
            "category":"Professional",
            "subcategory":"Business Services",
            "type":"Services"
        }
    ],
    "sg:phone":"+41 71 744 70 61",
    "sg:postcode":"9442",
    "sg:province":"St. Gallen",
    "sg:tags":[
        "high-precision",
        "mechanic"
    ],
    "wof:name":"B\u00fcrki & Baumgartner Ag",
    "wof:placetype":"venue"
},
  "geometry": {"coordinates":[9.5944347382,47.4256362915],"type":"Point"}
}