{
  "type": "Feature",
  "properties": {
    "iso:country":"CH",
    "sg:address":"Rue Edouard-rod 10",
    "sg:city":"Gen\u00e8ve",
    "sg:orig_category":"Grosshandel mit sonstigen Gebrauchs U Verbrauchsg\u00fctern",
    "sg:phone":"+41 22 344 36 50",
    "sg:postcode":"1203",
    "sg:province":"Gen\u00e8ve",
    "wof:name":"Longo Sa Distributeur Agr\u00e9\u00e9 3m",
    "wof:placetype":"venue"
},
  "geometry": {"coordinates":[6.1219949722,46.2124328613],"type":"Point"}
}