{
  "type": "Feature",
  "properties": {
    "iso:country":"CH",
    "sg:address":"Gr\u00fcnweg 7",
    "sg:city":"Lyss",
    "sg:orig_category":"Malerei",
    "sg:phone":"+41 32 384 44 59",
    "sg:postcode":"3250",
    "sg:province":"Bern",
    "wof:name":"Beat J\u00f6rg Malerei & Bautenschutz",
    "wof:placetype":"venue"
},
  "geometry": {"coordinates":[7.3033227921,47.0810508728],"type":"Point"}
}