{
  "type": "Feature",
  "properties": {
    "iso:country":"CH",
    "sg:address":"Bernstrasse 2",
    "sg:city":"Berikon",
    "sg:classifiers":[
        {
            "category":"Restaurant",
            "type":"Food & Drink"
        }
    ],
    "sg:phone":"+41 32 322 72 44",
    "sg:postcode":"8965",
    "sg:province":"Aargau",
    "wof:name":"Restaurant Mylady",
    "wof:placetype":"venue"
},
  "geometry": {"coordinates":[7.2464799881,47.1381149292],"type":"Point"}
}