{
  "type": "Feature",
  "properties": {
    "iso:country":"CH",
    "sg:address":"Schwefelstrasse 14",
    "sg:city":"Vaduz",
    "sg:orig_category":"Offsetdruck Satzherstellung U Reproduktion",
    "sg:phone":"+423 232 85 90",
    "sg:postcode":"9490",
    "wof:name":"Lampert Druckzentrum Ag",
    "wof:placetype":"venue"
},
  "geometry": {"coordinates":[9.5240707397,47.1291007996],"type":"Point"}
}