{
  "type": "Feature",
  "properties": {
    "iso:country":"CH",
    "sg:address":"Jurastrasse 6",
    "sg:city":"Seltisberg",
    "sg:orig_category":"Softwareentwicklung U beratung",
    "sg:phone":"+41 61 463 25 50",
    "sg:postcode":"4411",
    "sg:province":"Basel-Landschaft",
    "wof:name":"Ingenieurb\u00fcro F\u00fcr Informatik, J. Sturm",
    "wof:placetype":"venue"
},
  "geometry": {"coordinates":[7.7221698761,47.4628791809],"type":"Point"}
}