{
  "type": "Feature",
  "properties": {
    "iso:country":"CH",
    "sg:address":"6707",
    "sg:city":"Iragna",
    "sg:orig_category":"Schulpflegen",
    "sg:postcode":"6707",
    "sg:province":"Ticino",
    "wof:name":"Delegazione Scolastica Del Comune Di Iragna",
    "wof:placetype":"venue"
},
  "geometry": {"coordinates":[8.9680175781,46.330280304],"type":"Point"}
}