{
  "type": "Feature",
  "properties": {
    "iso:country":"CH",
    "sg:address":"Via Sorengo 17",
    "sg:city":"Lugano",
    "sg:orig_category":"Kaminfeger",
    "sg:phone":"+41 17804644",
    "sg:postcode":"6900",
    "sg:province":"Ticino",
    "wof:name":"Arthur Dohner Kaminfegergesch\u00e4ft",
    "wof:placetype":"venue"
},
  "geometry": {"coordinates":[8.6568174362,47.2378997803],"type":"Point"}
}