{
  "type": "Feature",
  "properties": {
    "iso:country":"CH",
    "sg:address":"Pierre \u00e0 Mazel 25 2000 Neuch\u00e2tel Case Postale",
    "sg:city":"Neuenburg",
    "sg:orig_category":"Pensionskassen",
    "sg:postcode":"2000",
    "sg:province":"Neuch\u00e2tel",
    "wof:name":"Fonds De Pr\u00e9voyance En Faveur Du Personnel Du Garage Paul Ruckstuhl Sa",
    "wof:placetype":"venue"
},
  "geometry": {"coordinates":[6.8385210037,47.1065444946],"type":"Point"}
}