{
  "type": "Feature",
  "properties": {
    "iso:country":"CH",
    "sg:address":"Butzenstrasse 49",
    "sg:city":"Z\u00fcrich",
    "sg:orig_category":"Kinderkrippen U horte",
    "sg:phone":"+41 14881011",
    "sg:postcode":"8038",
    "sg:province":"Z\u00fcrich",
    "wof:name":"Kinderkrippe Der Stadt Z\u00fcrich Entlisberg Kinderhaus",
    "wof:placetype":"venue"
},
  "geometry": {"coordinates":[8.5241250992,47.3408355713],"type":"Point"}
}