{
  "type": "Feature",
  "properties": {
    "iso:country":"CH",
    "sg:address":"Chemin De La Cl\u00e9-des-champs 10",
    "sg:city":"Vessy",
    "sg:orig_category":"Datenverarbeitungsdienste",
    "sg:phone":"+41 22 784 25 37",
    "sg:postcode":"1234",
    "sg:province":"Gen\u00e8ve",
    "wof:name":"Gilbert Vuilleumier Serv.-conseils Informatiques",
    "wof:placetype":"venue"
},
  "geometry": {"coordinates":[6.161968,46.172939],"type":"Point"}
}