{
  "type": "Feature",
  "properties": {
    "iso:country":"CH",
    "sg:address":"N\u00f6llenstrasse 15a",
    "sg:city":"Widnau",
    "sg:orig_category":"Herstellung von Konstruktionsteilen, Fertigbauteilen U Ausbauelementen aus Holz",
    "sg:phone":"+41 71 722 02 08",
    "sg:postcode":"9443",
    "sg:province":"St. Gallen",
    "wof:name":"Mobau Gmbh",
    "wof:placetype":"venue"
},
  "geometry": {"coordinates":[9.6380195618,47.4149742126],"type":"Point"}
}