{
  "type": "Feature",
  "properties": {
    "iso:country":"CH",
    "sg:address":"Chemin De La Bruy\u00e8re 34",
    "sg:city":"Prangins",
    "sg:orig_category":"Handelsvermittlung U Grosshandel",
    "sg:phone":"+41 22 361 51 66",
    "sg:postcode":"1197",
    "sg:province":"Vaud",
    "wof:name":"Keepint Sa",
    "wof:placetype":"venue"
},
  "geometry": {"coordinates":[6.2537579536,46.3959770203],"type":"Point"}
}