{
  "type": "Feature",
  "properties": {
    "iso:country":"CH",
    "sg:address":"Zentralstrasse 11 6210 Sursee. Postfach",
    "sg:city":"Sursee",
    "sg:orig_category":"Handels-H\u00e4user U Gesellschaften",
    "sg:postcode":"6210",
    "sg:province":"Luzern",
    "wof:name":"Mindblowers Sursee Gmbh Waren; Handel, Import. Hanfproduktehandel Usw",
    "wof:placetype":"venue"
},
  "geometry": {"coordinates":[8.1099796295,47.1725082397],"type":"Point"}
}