{
  "type": "Feature",
  "properties": {
    "iso:country":"CH",
    "sg:address":"Seestrasse 4",
    "sg:city":"G\u00fcttingen",
    "sg:classifiers":[
        {
            "category":"Home & Garden",
            "subcategory":"Hardware",
            "type":"Retail Goods"
        }
    ],
    "sg:phone":"+41 71 694 50 10",
    "sg:postcode":"8594",
    "sg:province":"Thurgau",
    "sg:tags":[
        "rope",
        "wire",
        "shear",
        "cable"
    ],
    "wof:name":"Metallwarenfabrik N\u00e4geli Ag",
    "wof:placetype":"venue"
},
  "geometry": {"coordinates":[9.293576,47.60746],"type":"Point"}
}