{
  "type": "Feature",
  "properties": {
    "iso:country":"CH",
    "sg:address":"Kalchofenstrasse 20",
    "sg:city":"Hasle-r\u00fcegsau",
    "sg:orig_category":"Landesverteidigung, Sozialversicherung \u00d6ffentliche Verwaltung",
    "sg:phone":"+41 41 480 11 66",
    "sg:postcode":"3415",
    "sg:province":"Bern",
    "wof:name":"Zivilschutzstelle Hasle",
    "wof:placetype":"venue"
},
  "geometry": {"coordinates":[8.0499401093,46.9792098999],"type":"Point"}
}