{
  "type": "Feature",
  "properties": {
    "iso:country":"CH",
    "sg:address":"Bergliweg 2",
    "sg:city":"Oftringen",
    "sg:orig_category":"Sportvereine Sch\u00fctzen",
    "sg:phone":"+41 62 797 52 42",
    "sg:postcode":"4665",
    "sg:province":"Aargau",
    "wof:name":"Sch\u00fctzenges.k\u00fcngoldingen",
    "wof:placetype":"venue"
},
  "geometry": {"coordinates":[7.9503908157,47.2989120483],"type":"Point"}
}