{
  "type": "Feature",
  "properties": {
    "iso:country":"CH",
    "sg:address":"Chemin Du Funiculaire 10",
    "sg:city":"Lausanne",
    "sg:orig_category":"Dachdeckerei Zimmerei, Dachdeckerei, Bauspenglerei U Abdichtung",
    "sg:phone":"+41 79 412 66 44",
    "sg:postcode":"1006",
    "sg:province":"Vaud",
    "wof:name":"Galster Et Mottaz Sa",
    "wof:placetype":"venue"
},
  "geometry": {"coordinates":[6.626649,46.508881],"type":"Point"}
}