{
  "type": "Feature",
  "properties": {
    "iso:country":"CH",
    "sg:address":"Poststrasse",
    "sg:city":"Arosa",
    "sg:orig_category":"Konkurs- and Betreibungs\u00e4mter",
    "sg:phone":"+41 81 374 14 18",
    "sg:postcode":"7050",
    "sg:province":"Graubunden",
    "wof:name":"Betreibungs-& Konkursamt Des Kreises Schanfigg",
    "wof:placetype":"venue"
},
  "geometry": {"coordinates":[9.6651620865,46.7756080627],"type":"Point"}
}