{
  "type": "Feature",
  "properties": {
    "iso:country":"CH",
    "sg:address":"M\u00fchletalweg 14",
    "sg:city":"Olten",
    "sg:orig_category":"Architekturb\u00fcros",
    "sg:phone":"+41 61 401 00 51",
    "sg:postcode":"4600",
    "sg:province":"Solothurn",
    "wof:name":"Roland Frei Architekturb\u00fcro Sia",
    "wof:placetype":"venue"
},
  "geometry": {"coordinates":[7.564668,47.520115],"type":"Point"}
}