{
  "type": "Feature",
  "properties": {
    "iso:country":"CH",
    "sg:address":"Gryfelblatte 2",
    "sg:city":"Zermatt",
    "sg:classifiers":[
        {
            "category":"Restaurant",
            "type":"Food & Drink"
        }
    ],
    "sg:phone":"+41 27 967 11 51",
    "sg:postcode":"3920",
    "sg:province":"Valais",
    "wof:name":"Restaurant Walliserstube",
    "wof:placetype":"venue"
},
  "geometry": {"coordinates":[7.7538499832,46.0235557556],"type":"Point"}
}