{
  "type": "Feature",
  "properties": {
    "iso:country":"CH",
    "sg:address":"1353",
    "sg:city":"Bofflens",
    "sg:orig_category":"Herstellung von Hebezeugen U F\u00f6rdermitteln",
    "sg:postcode":"1353",
    "sg:province":"Vaud",
    "wof:name":"Barben S\u00e0rl",
    "wof:placetype":"venue"
},
  "geometry": {"coordinates":[7.0165948868,47.0394935608],"type":"Point"}
}