{
  "type": "Feature",
  "properties": {
    "iso:country":"CH",
    "sg:address":"Dorfstrasse 29",
    "sg:city":"Baar",
    "sg:orig_category":"Detailhandel mit Textilien",
    "sg:phone":"+41 41 761 25 44",
    "sg:postcode":"6340",
    "sg:province":"Zug",
    "wof:name":"Steinhauser-larsen Margrit.",
    "wof:placetype":"venue"
},
  "geometry": {"coordinates":[8.5240659714,47.1936607361],"type":"Point"}
}