{
  "type": "Feature",
  "properties": {
    "iso:country":"CH",
    "sg:address":"Sonnenwiesenstrasse 13",
    "sg:city":"Kreuzlingen",
    "sg:classifiers":[
        {
            "category":"Professional",
            "subcategory":"Accounting & Tax Preparation",
            "type":"Services"
        }
    ],
    "sg:phone":"+41 79 335 24 52",
    "sg:postcode":"8280",
    "sg:province":"Thurgau",
    "sg:tags":[
        "u",
        "yachtbau",
        "boot"
    ],
    "wof:name":"M\u00e4chler Marina Gmbh",
    "wof:placetype":"venue"
},
  "geometry": {"coordinates":[8.855349,47.195087],"type":"Point"}
}