{
  "type": "Feature",
  "properties": {
    "iso:country":"CH",
    "sg:address":"Bahnhofstrasse 2",
    "sg:city":"Trimmis",
    "sg:orig_category":"Sanit\u00e4r U Heizungsinstallation Sanit\u00e4rinstallation",
    "sg:phone":"+41 81 353 19 78",
    "sg:postcode":"7203",
    "sg:province":"Graubunden",
    "wof:name":"Christian Zingg Sanit\u00e4r & Heizung",
    "wof:placetype":"venue"
},
  "geometry": {"coordinates":[9.5573940277,46.9059944153],"type":"Point"}
}