{
  "type": "Feature",
  "properties": {
    "addr:full":"Paradeplatz 8 P. O. Box 1 Zurich Z\u00fcrich 8070",
    "addr:housenumber":"8;1",
    "addr:postcode":"8070",
    "addr:street":"Paradeplatz;P. O. Box",
    "iso:country":"CH",
    "sg:address":"Paradeplatz 8 P. O. Box 1",
    "sg:city":"Zurich",
    "sg:classifiers":[
        {
            "category":"Industrial Area",
            "type":"Public Place"
        }
    ],
    "sg:phone":"+41 61 274 74 74",
    "sg:postcode":"8070",
    "sg:province":"Z\u00fcrich",
    "sg:tags":[
        "large",
        "private"
    ],
    "wof:name":"Danzas Group",
    "wof:placetype":"venue"
},
  "geometry": {"coordinates":[7.59394,47.546982],"type":"Point"}
}