{
  "type": "Feature",
  "properties": {
    "iso:country":"CH",
    "sg:address":"Ritter-weg 8",
    "sg:city":"Biel/bienne",
    "sg:orig_category":"Grosshandel mit B\u00fcromaschinen Grosshandel mit Datenverarbeitungsger\u00e4ten",
    "sg:phone":"+41 32 341 99 20",
    "sg:postcode":"2502",
    "sg:province":"Bern",
    "wof:name":"Newquip Informatique Froidevaux",
    "wof:placetype":"venue"
},
  "geometry": {"coordinates":[7.252204895,47.1398124695],"type":"Point"}
}