{
  "type": "Feature",
  "properties": {
    "iso:country":"CH",
    "sg:address":"Veia Purmaglera 5",
    "sg:city":"Savognin",
    "sg:classifiers":[
        {
            "category":"Insurance",
            "subcategory":"Insurance Agent",
            "type":"Services"
        }
    ],
    "sg:phone":"+41 81 684 30 18",
    "sg:postcode":"7460",
    "sg:province":"Graubunden",
    "sg:tags":[
        "versicherungsagenturen",
        "-broker"
    ],
    "wof:name":"Winterthur-versicherungen Agentur",
    "wof:placetype":"venue"
},
  "geometry": {"coordinates":[9.6038398743,46.5966300964],"type":"Point"}
}