{
  "type": "Feature",
  "properties": {
    "iso:country":"CH",
    "sg:address":"Auf Dem Wolf 24",
    "sg:city":"Basel",
    "sg:orig_category":"Abwasserreinigung",
    "sg:phone":"+41 61 312 33 33",
    "sg:postcode":"4052",
    "sg:province":"Basel-Stadt",
    "wof:name":"Kanalreinigungs-ag Reinigungs, Entstopfungsarbeiten In Kan\u00e4len Usw, Bes. Absaugen Von Schlamm, Schmutz Durch Hydrodynamisches Durchsp\u00fclen",
    "wof:placetype":"venue"
},
  "geometry": {"coordinates":[7.615259,47.540451],"type":"Point"}
}