{
  "type": "Feature",
  "properties": {
    "iso:country":"CH",
    "sg:address":"Alfred-schindlerstrasse 2 6030 Ebikon. Postfach 216",
    "sg:city":"Ebikon",
    "sg:orig_category":"Grosshandel mit Erzen U Metallen",
    "sg:phone":"+41 41 440 43 82",
    "sg:postcode":"6031",
    "sg:province":"Luzern",
    "wof:name":"Robert K\u00fcttel Vertretungen",
    "wof:placetype":"venue"
},
  "geometry": {"coordinates":[8.3522377014,47.0860671997],"type":"Point"}
}