{
  "type": "Feature",
  "properties": {
    "iso:country":"CH",
    "sg:address":"Rosenbergweg 10c 6300 Zug. Postfach 829",
    "sg:city":"Zug",
    "sg:orig_category":"Wirtschaftspr\u00fcfung, Steuerberatung U Treuhand",
    "sg:phone":"+41 41 726 30 02",
    "sg:postcode":"6301",
    "sg:province":"Zug",
    "wof:name":"Hrc Hotel Research & Consulting Co Ltd Treuhand",
    "wof:placetype":"venue"
},
  "geometry": {"coordinates":[8.5210266113,47.1659355164],"type":"Point"}
}