{
  "type": "Feature",
  "properties": {
    "iso:country":"CH",
    "sg:address":"Baslerstrasse 42",
    "sg:city":"Oftringen",
    "sg:orig_category":"Grosshandel mit Blumen U Pflanzen Torfgewinnung U brikettherstellung",
    "sg:phone":"+41 62 789 28 00",
    "sg:postcode":"4665",
    "sg:province":"Aargau",
    "wof:name":"Intertoresa Ag",
    "wof:placetype":"venue"
},
  "geometry": {"coordinates":[7.9125127792,47.3178367615],"type":"Point"}
}