{
  "type": "Feature",
  "properties": {
    "iso:country":"CH",
    "sg:address":"Kappelenring 8/723",
    "sg:city":"Hinterkappelen",
    "sg:orig_category":"R\u00fcckgewinnung U Vorbereitung f\u00fcr die Wiederverwertung Recycling R\u00fcckgewinnung U Vorbereitung f\u00fcr die",
    "sg:phone":"+41 79 646 07 73",
    "sg:postcode":"3032",
    "sg:province":"Bern",
    "wof:name":"Cardinale Franco Alteisen + Metalle",
    "wof:placetype":"venue"
},
  "geometry": {"coordinates":[7.3782048225,46.9658470154],"type":"Point"}
}