{
  "type": "Feature",
  "properties": {
    "iso:country":"CH",
    "sg:address":"Poststrasse 8",
    "sg:city":"Lenzburg",
    "sg:orig_category":"RESTAURANTS: TEA-ROOMS",
    "sg:phone":"+41 62 891 87 98",
    "sg:postcode":"5600",
    "sg:province":"Aargau",
    "wof:name":"Restaurant Central, Dietiker Urs Peter.",
    "wof:placetype":"venue"
},
  "geometry": {"coordinates":[8.1790351868,47.3882484436],"type":"Point"}
}