{
  "type": "Feature",
  "properties": {
    "iso:country":"CH",
    "sg:address":"Ruchonnet Avenue Louis- 30 1003 Lausanne. Postfach",
    "sg:city":"Lausanne",
    "sg:orig_category":"Unclassifiable Establishments",
    "sg:postcode":"1003",
    "sg:province":"Vaud",
    "wof:name":"Montilly Sa",
    "wof:placetype":"venue"
},
  "geometry": {"coordinates":[6.9875998497,47.0987815857],"type":"Point"}
}