{
  "type": "Feature",
  "properties": {
    "iso:country":"CH",
    "sg:address":"1610",
    "sg:city":"Oron-la-ville",
    "sg:orig_category":"Primarschulen",
    "sg:phone":"+41 26 912 60 81",
    "sg:postcode":"1610",
    "sg:province":"Vaud",
    "wof:name":"Ecole Primaire",
    "wof:placetype":"venue"
},
  "geometry": {"coordinates":[6.8266248703,46.5714416504],"type":"Point"}
}