{
  "type": "Feature",
  "properties": {
    "iso:country":"CH",
    "sg:address":"Rapisau",
    "sg:city":"Appenzell",
    "sg:classifiers":[
        {
            "category":"Restaurant",
            "type":"Food & Drink"
        }
    ],
    "sg:phone":"+41 55 284 63 33",
    "sg:postcode":"9050",
    "sg:province":"Appenzell Innerhoden",
    "wof:name":"Restaurant Waldegg",
    "wof:placetype":"venue"
},
  "geometry": {"coordinates":[8.967338562,47.2448921204],"type":"Point"}
}