{
  "type": "Feature",
  "properties": {
    "iso:country":"CH",
    "sg:address":"4663",
    "sg:city":"Aarburg",
    "sg:orig_category":"Landesverteidigung, Sozialversicherung \u00d6ffentliche Verwaltung",
    "sg:phone":"+41 41 787 19 38",
    "sg:postcode":"4663",
    "sg:province":"Aargau",
    "wof:name":"Zivilschutzstelle Abtwil",
    "wof:placetype":"venue"
},
  "geometry": {"coordinates":[8.3542985916,47.1750144958],"type":"Point"}
}