{
  "type": "Feature",
  "properties": {
    "iso:country":"CH",
    "sg:address":"Morgartenstrasse 3 6000 Luzern. Postfach",
    "sg:city":"Luzern",
    "sg:classifiers":[
        {
            "category":"Professional",
            "subcategory":"Employment Agencies",
            "type":"Services"
        }
    ],
    "sg:postcode":"6003",
    "sg:province":"Luzern",
    "sg:tags":[
        "personal",
        "u",
        "stellenvermittlung"
    ],
    "wof:name":"Camp Counselors And Work Experience Ltd",
    "wof:placetype":"venue"
},
  "geometry": {"coordinates":[8.3081016541,47.0493850708],"type":"Point"}
}