{
  "type": "Feature",
  "properties": {
    "iso:country":"CH",
    "sg:address":"Unterdorf 10",
    "sg:city":"Sch\u00fcpfheim",
    "sg:orig_category":"Instandhaltung U Reparatur von Automobilen",
    "sg:phone":"+41 41 484 13 70",
    "sg:postcode":"6170",
    "sg:province":"Luzern",
    "wof:name":"Auto Felder",
    "wof:placetype":"venue"
},
  "geometry": {"coordinates":[8.018904686,46.9548988342],"type":"Point"}
}