{
  "type": "Feature",
  "properties": {
    "iso:country":"CH",
    "sg:address":"Weite Gasse 6",
    "sg:city":"Baden",
    "sg:orig_category":"Detailhandel mit Milcherzeugnissen U Eiern",
    "sg:phone":"+41 71 277 48 93",
    "sg:postcode":"5400",
    "sg:province":"Aargau",
    "wof:name":"Franz Estermann Milchprodukte",
    "wof:placetype":"venue"
},
  "geometry": {"coordinates":[9.3410539627,47.4109191895],"type":"Point"}
}