{
  "type": "Feature",
  "properties": {
    "iso:country":"CH",
    "sg:address":"Germaniastrasse 64 8006 Z\u00fcrich. Postfach",
    "sg:city":"Z\u00fcrich",
    "sg:orig_category":"Unternehmensberatung",
    "sg:postcode":"8001",
    "sg:province":"Z\u00fcrich",
    "wof:name":"Giacomo Garaventa, Unternehmens Und Managementberatung",
    "wof:placetype":"venue"
},
  "geometry": {"coordinates":[8.6681747437,47.0146865845],"type":"Point"}
}