{
  "type": "Feature",
  "properties": {
    "iso:country":"CH",
    "sg:address":"D\u00fcrntnerstrasse 24",
    "sg:city":"Hinwil",
    "sg:orig_category":"Kosmetikinstitute",
    "sg:phone":"+41 19374191",
    "sg:postcode":"8340",
    "sg:province":"Z\u00fcrich",
    "wof:name":"Ursula H\u00e4derli Kosmetik- U. Massage Praxis",
    "wof:placetype":"venue"
},
  "geometry": {"coordinates":[8.8405160904,47.2986793518],"type":"Point"}
}