{
  "type": "Feature",
  "properties": {
    "iso:country":"CH",
    "sg:address":"Niederernen",
    "sg:city":"Ernen",
    "sg:orig_category":"RESTAURANTS: TEA-ROOMS",
    "sg:phone":"+41 17133300",
    "sg:postcode":"3995",
    "sg:province":"Valais",
    "wof:name":"Restaurant Gontenbach",
    "wof:placetype":"venue"
},
  "geometry": {"coordinates":[8.5304088593,47.2999687195],"type":"Point"}
}