{
  "type": "Feature",
  "properties": {
    "iso:country":"CH",
    "sg:address":"Rue Centrale 16",
    "sg:city":"Conthey",
    "sg:orig_category":"Rebbau",
    "sg:phone":"+41 27 346 14 39",
    "sg:postcode":"1964",
    "sg:province":"Valais",
    "wof:name":"Gabrielle Demierre Viticulture",
    "wof:placetype":"venue"
},
  "geometry": {"coordinates":[7.3051919937,46.2303123474],"type":"Point"}
}