{
  "type": "Feature",
  "properties": {
    "iso:country":"CH",
    "sg:address":"Nova Via 71",
    "sg:city":"Domat/ems",
    "sg:orig_category":"Herstellung von Sportger\u00e4ten",
    "sg:postcode":"7013",
    "sg:province":"Graubunden",
    "wof:name":"Bardill's Fischereiartikel",
    "wof:placetype":"venue"
},
  "geometry": {"coordinates":[9.4507446289,46.8362884521],"type":"Point"}
}