{
  "type": "Feature",
  "properties": {
    "iso:country":"CH",
    "sg:address":"Bahnhofstrasse 49 8803 R\u00fcschlikon. Postfach Postfach",
    "sg:city":"R\u00fcschlikon",
    "sg:orig_category":"Verwaltung von Immobilien",
    "sg:phone":"+41 31 352 30 96",
    "sg:postcode":"8803",
    "sg:province":"Z\u00fcrich",
    "wof:name":"Ledermann Kurt & Sohn Liegenschaften, Verm\u00f6gensverwaltungen, Treuhandb\u00fcro",
    "wof:placetype":"venue"
},
  "geometry": {"coordinates":[7.4335150719,46.9415206909],"type":"Point"}
}