{
  "type": "Feature",
  "properties": {
    "iso:country":"CH",
    "sg:address":"Uf Em Bort",
    "sg:city":"M\u00fcrren",
    "sg:orig_category":"Wasserversorgung",
    "sg:phone":"+41 79 339 06 73",
    "sg:postcode":"3825",
    "sg:province":"Bern",
    "wof:name":"Wasserversorgungsgenossenschaft M\u00fcrren",
    "wof:placetype":"venue"
},
  "geometry": {"coordinates":[7.8951401711,46.560218811],"type":"Point"}
}