{
  "type": "Feature",
  "properties": {
    "iso:country":"CH",
    "sg:address":"Holtiweg 20",
    "sg:city":"Worb",
    "sg:orig_category":"Detailhandel mit Uhren U Schmuck",
    "sg:phone":"+41 31 839 55 73",
    "sg:postcode":"3076",
    "sg:province":"Bern",
    "wof:name":"Simon Schlegel Goldschmiede",
    "wof:placetype":"venue"
},
  "geometry": {"coordinates":[7.5469589233,46.9355545044],"type":"Point"}
}