{
  "type": "Feature",
  "properties": {
    "iso:country":"CH",
    "sg:address":"Tiefenwiesstrasse 512",
    "sg:city":"Zuzwil",
    "sg:classifiers":[
        {
            "category":"Manufacturing",
            "subcategory":"Tools & Machinery",
            "type":"Manufacturing & Wholesale Goods"
        }
    ],
    "sg:phone":"+41 71 940 03 40",
    "sg:postcode":"9524",
    "sg:province":"St. Gallen",
    "sg:tags":[
        "cutting",
        "gear"
    ],
    "wof:name":"Evolvente Ag",
    "wof:placetype":"venue"
},
  "geometry": {"coordinates":[9.0993518829,47.4807777405],"type":"Point"}
}