{
  "type": "Feature",
  "properties": {
    "iso:country":"CH",
    "sg:address":"Hauptstrasse 27",
    "sg:city":"Gempen",
    "sg:orig_category":"Gartenbau",
    "sg:phone":"+41 61 721 51 80",
    "sg:postcode":"4145",
    "sg:province":"Solothurn",
    "wof:name":"Ruesch Gartenbau Inh.p.spornitz",
    "wof:placetype":"venue"
},
  "geometry": {"coordinates":[7.658698082,47.4758300781],"type":"Point"}
}