{
  "type": "Feature",
  "properties": {
    "iso:country":"CH",
    "sg:address":"Champ-de-vaud",
    "sg:city":"Penth\u00e9r\u00e9az",
    "sg:orig_category":"Malerei Tapeziererei",
    "sg:phone":"+41 79 623 49 94",
    "sg:postcode":"1375",
    "sg:province":"Vaud",
    "wof:name":"Christian Roseng Peinture & Papiers Peints",
    "wof:placetype":"venue"
},
  "geometry": {"coordinates":[6.620953083,46.6937942505],"type":"Point"}
}