{
  "type": "Feature",
  "properties": {
    "addr:full":"Dorfstrasse 4 Sonterswil Thurgau 8564",
    "addr:housenumber":"4",
    "addr:postcode":"8564",
    "addr:street":"Dorfstrasse",
    "iso:country":"CH",
    "sg:address":"Dorfstrasse 4",
    "sg:city":"Sonterswil",
    "sg:orig_category":"Detailhandel mit Brot, Back U S\u00fcsswaren Haltung von Schweinen",
    "sg:phone":"+41 71 657 11 76",
    "sg:postcode":"8564",
    "sg:province":"Thurgau",
    "wof:name":"Lippuner A.",
    "wof:placetype":"venue"
},
  "geometry": {"coordinates":[9.078777,47.620808],"type":"Point"}
}