{
  "type": "Feature",
  "properties": {
    "iso:country":"CH",
    "sg:address":"Avenue De Vaudagne 29",
    "sg:city":"Meyrin",
    "sg:orig_category":"Reinigungsgewerbe",
    "sg:postcode":"1217",
    "sg:province":"Gen\u00e8ve",
    "wof:name":"Le Pompier Noir, Reuge D.",
    "wof:placetype":"venue"
},
  "geometry": {"coordinates":[6.0757851601,46.2335777283],"type":"Point"}
}