{
  "type": "Feature",
  "properties": {
    "iso:country":"CH",
    "sg:address":"Centrale Rue 9",
    "sg:city":"Orbe",
    "sg:orig_category":"Vermietung U Verpachtung von eigenen Immobilien",
    "sg:postcode":"1350",
    "sg:province":"Vaud",
    "wof:name":"Rue David-pierre-bourquin 21 Sa",
    "wof:placetype":"venue"
},
  "geometry": {"coordinates":[6.8296899796,47.0980262756],"type":"Point"}
}