{
  "type": "Feature",
  "properties": {
    "iso:country":"CH",
    "sg:address":"Ernastrasse 3 8004 Z\u00fcrich. Postfach",
    "sg:city":"Z\u00fcrich",
    "sg:orig_category":"Vereine Fasnacht",
    "sg:phone":"+41 12427385",
    "sg:postcode":"8026",
    "sg:province":"Z\u00fcrich",
    "wof:name":"Zwigger Gugge Z\u00fcrich",
    "wof:placetype":"venue"
},
  "geometry": {"coordinates":[8.5185184479,47.3796882629],"type":"Point"}
}