{
  "type": "Feature",
  "properties": {
    "iso:country":"CH",
    "sg:address":"Merzenbrunnenweg 11",
    "sg:city":"Thayngen",
    "sg:classifiers":[
        {
            "category":"Professional",
            "subcategory":"Printing & Photocopies",
            "type":"Services"
        }
    ],
    "sg:phone":"+41 52 649 31 31",
    "sg:postcode":"8240",
    "sg:province":"Schaffhausen",
    "sg:tags":[
        "intaglio"
    ],
    "wof:name":"Druckerei Karl Augustin Ag",
    "wof:placetype":"venue"
},
  "geometry": {"coordinates":[8.7073011398,47.7508583069],"type":"Point"}
}