{
  "type": "Feature",
  "properties": {
    "iso:country":"CH",
    "sg:address":"Rue Des Lilas 3",
    "sg:city":"Ste-croix",
    "sg:orig_category":"Wirtschaftspr\u00fcfung, Steuerberatung U Treuhand",
    "sg:phone":"+41 24 454 41 70",
    "sg:postcode":"1450",
    "sg:province":"Vaud",
    "wof:name":"Fiduciaire Butticaz",
    "wof:placetype":"venue"
},
  "geometry": {"coordinates":[6.4988470078,46.8254699707],"type":"Point"}
}