{
  "type": "Feature",
  "properties": {
    "iso:country":"CH",
    "sg:address":"Kl\u00f6pfi 163",
    "sg:city":"Birrwil",
    "sg:orig_category":"Sanit\u00e4r, Heizungs U L\u00fcftungsinstallation Sanit\u00e4rinstallation U Spenglerei",
    "sg:phone":"+41 62 772 12 12",
    "sg:postcode":"5708",
    "sg:province":"Aargau",
    "wof:name":"Rudolf Graf Ag",
    "wof:placetype":"venue"
},
  "geometry": {"coordinates":[8.1966562271,47.2970237732],"type":"Point"}
}