{
  "type": "Feature",
  "properties": {
    "iso:country":"CH",
    "sg:address":"G\u00e9n\u00e9ral Boinod Rue Du 10",
    "sg:city":"Aubonne",
    "sg:orig_category":"Herstellung von Radio U Fernsehger\u00e4ten sowie phono U videotechnischen Ger\u00e4ten",
    "sg:postcode":"1170",
    "sg:province":"Vaud",
    "wof:name":"A La Bonne Location, Fagnart",
    "wof:placetype":"venue"
},
  "geometry": {"coordinates":[6.3913731575,46.4957962036],"type":"Point"}
}