{
  "type": "Feature",
  "properties": {
    "iso:country":"CH",
    "sg:address":"Grand-rue 9",
    "sg:city":"Lucens",
    "sg:orig_category":"Detailhandel mit Fleisch U Fleischwaren",
    "sg:phone":"+41 21 906 81 70",
    "sg:postcode":"1522",
    "sg:province":"Vaud",
    "wof:name":"Jacques Bersier Boucherie",
    "wof:placetype":"venue"
},
  "geometry": {"coordinates":[6.8395171165,46.7091941833],"type":"Point"}
}