{
  "type": "Feature",
  "properties": {
    "iso:country":"CH",
    "sg:address":"Br\u00fcckenstrasse 2",
    "sg:city":"Huttwil",
    "sg:classifiers":[
        {
            "category":"Professional",
            "subcategory":"Engineering",
            "type":"Services"
        }
    ],
    "sg:phone":"+41 62 962 24 24",
    "sg:postcode":"4950",
    "sg:province":"Bern",
    "sg:tags":[
        "machine",
        "-",
        "mechanical"
    ],
    "wof:name":"H. Reinhard Ag",
    "wof:placetype":"venue"
},
  "geometry": {"coordinates":[7.8633008003,47.1147994995],"type":"Point"}
}