{
  "type": "Feature",
  "properties": {
    "iso:country":"CH",
    "sg:address":"Kosters Kau",
    "sg:city":"Appenzell",
    "sg:orig_category":"Allgemeiner Hoch U Tiefbau",
    "sg:phone":"+41 71 311 25 25",
    "sg:postcode":"9050",
    "sg:province":"Appenzell Innerhoden",
    "wof:name":"Generalunternehmung Topas Ag",
    "wof:placetype":"venue"
},
  "geometry": {"coordinates":[9.407683,47.331436],"type":"Point"}
}