{
  "type": "Feature",
  "properties": {
    "iso:country":"CH",
    "sg:address":"Benzeholzstrasse 21",
    "sg:city":"Meggen",
    "sg:orig_category":"Architekturb\u00fcros",
    "sg:phone":"+41 41 260 12 54",
    "sg:postcode":"6045",
    "sg:province":"Luzern",
    "wof:name":"Urs Bucher Architekturb\u00fcro",
    "wof:placetype":"venue"
},
  "geometry": {"coordinates":[8.28154,47.070873],"type":"Point"}
}