{
  "type": "Feature",
  "properties": {
    "iso:country":"CH",
    "sg:address":"Dorfstrasse 16",
    "sg:city":"Wuppenau",
    "sg:orig_category":"Maler U Glasergewerbe Verlegen von Fussboden",
    "sg:postcode":"9514",
    "sg:province":"Thurgau",
    "wof:name":"Samuel Wettstein",
    "wof:placetype":"venue"
},
  "geometry": {"coordinates":[7.757589817,46.9491271973],"type":"Point"}
}