{
  "type": "Feature",
  "properties": {
    "iso:country":"CH",
    "sg:address":"Grand-rue 20",
    "sg:city":"Begnins",
    "sg:orig_category":"Fachdetailhandel in Verkaufsr\u00e4umen",
    "sg:phone":"+41 21 323 55 56",
    "sg:postcode":"1268",
    "sg:province":"Vaud",
    "wof:name":"Fancello Diffusion",
    "wof:placetype":"venue"
},
  "geometry": {"coordinates":[6.2493958473,46.4410514832],"type":"Point"}
}