{
  "type": "Feature",
  "properties": {
    "iso:country":"CH",
    "sg:address":"8570",
    "sg:city":"Weinfelden",
    "sg:orig_category":"Nationale Postdienste",
    "sg:phone":"+41 71 622 66 22",
    "sg:postcode":"8570",
    "sg:province":"Thurgau",
    "wof:name":"Die Post",
    "wof:placetype":"venue"
},
  "geometry": {"coordinates":[9.1071929932,47.5660934448],"type":"Point"}
}