{
  "type": "Feature",
  "properties": {
    "iso:country":"CH",
    "sg:address":"Rue Saint-roch 21",
    "sg:city":"Lausanne",
    "sg:orig_category":"P\u00e9dicure",
    "sg:phone":"+41 21 791 44 34",
    "sg:postcode":"1004",
    "sg:province":"Vaud",
    "wof:name":"Dani\u00e8le Kammer P\u00e9dicure",
    "wof:placetype":"venue"
},
  "geometry": {"coordinates":[6.6774148941,46.5133132935],"type":"Point"}
}