{
  "type": "Feature",
  "properties": {
    "addr:full":"Villette Rue De La 34 Yverdon-les-bains Vaud 1400",
    "addr:housenumber":"34",
    "addr:postcode":"1400",
    "addr:street":"Rue De La",
    "iso:country":"CH",
    "sg:address":"Villette Rue De La 34",
    "sg:city":"Yverdon-les-bains",
    "sg:orig_category":"Architektur U Ingenieurb\u00fcros",
    "sg:phone":"+41 21 613 10 40",
    "sg:postcode":"1400",
    "sg:province":"Vaud",
    "wof:name":"Perret-gentil, Rey Et Associ\u00e9s Sa",
    "wof:placetype":"venue"
},
  "geometry": {"coordinates":[6.62925,46.513271],"type":"Point"}
}