{
  "type": "Feature",
  "properties": {
    "iso:country":"CH",
    "sg:address":"Grabenstrasse 15",
    "sg:city":"Chur",
    "sg:orig_category":"Unclassifiable Establishments",
    "sg:postcode":"7000",
    "sg:province":"Graubunden",
    "wof:name":"Altissima Holding Ag",
    "wof:placetype":"venue"
},
  "geometry": {"coordinates":[9.5321493149,46.8507995605],"type":"Point"}
}