{
  "type": "Feature",
  "properties": {
    "iso:country":"CH",
    "sg:address":"Aeschistrasse 25 3110 M\u00fcnsingen. Postfach",
    "sg:city":"M\u00fcnsingen",
    "sg:orig_category":"Maschinen-Fabrikation Maschinenbau",
    "sg:phone":"+41 31 724 44 44",
    "sg:postcode":"3110",
    "sg:province":"Bern",
    "wof:name":"Kern Technologie Und Handels Gmbh Maschinen, Apparate, Systeme; Entwicklung, Herstellung, Verkauf U. Wartung",
    "wof:placetype":"venue"
},
  "geometry": {"coordinates":[7.5605092049,46.8704833984],"type":"Point"}
}