{
  "type": "Feature",
  "properties": {
    "iso:country":"CH",
    "sg:address":"Route De St-cergue 15",
    "sg:city":"Nyon",
    "sg:orig_category":"Herstellung von K\u00fcchenm\u00f6beln Herstellung von Metallerzeugnissen ohne Maschinenbau",
    "sg:postcode":"1260",
    "sg:province":"Vaud",
    "wof:name":"C&b Diffusion Sa Cuisines & Bains",
    "wof:placetype":"venue"
},
  "geometry": {"coordinates":[6.2345438004,46.386138916],"type":"Point"}
}