{
  "type": "Feature",
  "properties": {
    "iso:country":"CH",
    "sg:address":"Lerchenweg 4",
    "sg:city":"Allschwil",
    "sg:orig_category":"Kosmetikinstitute",
    "sg:phone":"+41 61 482 00 04",
    "sg:postcode":"4123",
    "sg:province":"Basel-Landschaft",
    "wof:name":"Marlene M\u00fcller Kosmetikinstitut Marlen",
    "wof:placetype":"venue"
},
  "geometry": {"coordinates":[7.5564799309,47.5549621582],"type":"Point"}
}