{
  "type": "Feature",
  "properties": {
    "iso:country":"CH",
    "sg:address":"Naglerwiesenstrasse 76",
    "sg:city":"Z\u00fcrich",
    "sg:orig_category":"Non-Classified Establishments",
    "sg:phone":"+41 13716324",
    "sg:postcode":"8049",
    "sg:province":"Z\u00fcrich",
    "wof:name":"M\u00e4chler Johann Ag",
    "wof:placetype":"venue"
},
  "geometry": {"coordinates":[8.4813699722,47.4127883911],"type":"Point"}
}