{
  "type": "Feature",
  "properties": {
    "iso:country":"CH",
    "sg:address":"Gwattstrasse",
    "sg:city":"Freienbach",
    "sg:orig_category":"Reiseb\u00fcros U Reiseveranstalter",
    "sg:postcode":"8807",
    "sg:province":"Schwyz",
    "wof:name":"Tui Customer Service Ag",
    "wof:placetype":"venue"
},
  "geometry": {"coordinates":[8.7886457443,47.2017974854],"type":"Point"}
}