{
  "type": "Feature",
  "properties": {
    "iso:country":"CH",
    "sg:address":"Zeughausplatz 14",
    "sg:city":"Liestal",
    "sg:classifiers":[
        {
            "category":"Restaurant",
            "type":"Food & Drink"
        }
    ],
    "sg:phone":"+41 61 921 94 69",
    "sg:postcode":"4410",
    "sg:province":"Basel-Landschaft",
    "wof:name":"Restaurant Zeughaus",
    "wof:placetype":"venue"
},
  "geometry": {"coordinates":[7.7349629402,47.4852104187],"type":"Point"}
}