{
  "type": "Feature",
  "properties": {
    "iso:country":"CH",
    "sg:address":"Jordanstrasse 1",
    "sg:city":"Sarnen",
    "sg:classifiers":[
        {
            "category":"Restaurant",
            "type":"Food & Drink"
        }
    ],
    "sg:phone":"+41 19322360",
    "sg:postcode":"6060",
    "sg:province":"Obwalden",
    "wof:name":"Gasthaus Linde",
    "wof:placetype":"venue"
},
  "geometry": {"coordinates":[8.784491539,47.3117027283],"type":"Point"}
}