{
  "type": "Feature",
  "properties": {
    "iso:country":"CH",
    "sg:address":"Villars-vert Route De 18",
    "sg:city":"Villars-sur-gl\u00e2ne",
    "sg:orig_category":"Sonstiger spezialisierter Hoch U Tiefbau",
    "sg:phone":"+41 71 244 94 83",
    "sg:postcode":"1752",
    "sg:province":"Fribourg",
    "wof:name":"Pefo Gmbh",
    "wof:placetype":"venue"
},
  "geometry": {"coordinates":[9.3877658844,47.4354133606],"type":"Point"}
}