{
  "type": "Feature",
  "properties": {
    "iso:country":"CH",
    "sg:address":"Aegeristrasse 76",
    "sg:city":"Zug",
    "sg:orig_category":"Grosshandel mit sonstigen Maschinen U Ausr\u00fcstungen f\u00fcr Industrie, Handel U Schiffahrt Handelsvermitt",
    "sg:phone":"+41 22 329 54 55",
    "sg:postcode":"6300",
    "sg:province":"Zug",
    "wof:name":"Traside Sa",
    "wof:placetype":"venue"
},
  "geometry": {"coordinates":[6.1399698257,46.2024345398],"type":"Point"}
}