{
  "type": "Feature",
  "properties": {
    "iso:country":"CH",
    "sg:address":"M\u00fcnsterhof 14 8001 Z\u00fcrich. Postfach 4179",
    "sg:city":"Z\u00fcrich",
    "sg:orig_category":"Werbevermittlung",
    "sg:phone":"+41 21 633 14 50",
    "sg:postcode":"8022",
    "sg:province":"Z\u00fcrich",
    "wof:name":"Fran\u00e7ois Marti Mcc Marketing Publicit\u00e9",
    "wof:placetype":"venue"
},
  "geometry": {"coordinates":[6.5845379829,46.538230896],"type":"Point"}
}