{
  "type": "Feature",
  "properties": {
    "iso:country":"CH",
    "sg:address":"Florastrasse 19",
    "sg:city":"Basel",
    "sg:orig_category":"Unternehmensberatung",
    "sg:phone":"+41 61 686 92 92",
    "sg:postcode":"4057",
    "sg:province":"Basel-Stadt",
    "wof:name":"Artax Fide Consult Ag Unternehmensberatung, Treuhandgesch\u00e4fte Usw",
    "wof:placetype":"venue"
},
  "geometry": {"coordinates":[7.5901970863,47.5643615723],"type":"Point"}
}