{
  "type": "Feature",
  "properties": {
    "iso:country":"CH",
    "sg:address":"Chemin Du Bois-de-ban 44",
    "sg:city":"Epalinges",
    "sg:orig_category":"Herstellung von k\u00e4lte U lufttechnischen Erzeugnissen f\u00fcr gewerbliche Zwecke",
    "sg:phone":"+41 21 784 29 51",
    "sg:postcode":"1066",
    "sg:province":"Vaud",
    "wof:name":"Fontannaz S\u00e0rl Bureau Technique",
    "wof:placetype":"venue"
},
  "geometry": {"coordinates":[6.6632518768,46.5572128296],"type":"Point"}
}