{
  "type": "Feature",
  "properties": {
    "iso:country":"CH",
    "sg:address":"Rugglishueb 3",
    "sg:city":"Hauptwil",
    "sg:orig_category":"Allgemeiner Gartenbau Dienstleistungen im Gartenbau",
    "sg:phone":"+41 62 929 04 22",
    "sg:postcode":"9213",
    "sg:province":"Thurgau",
    "wof:name":"Peter Knobel Gartenpflege",
    "wof:placetype":"venue"
},
  "geometry": {"coordinates":[7.82047,47.241367],"type":"Point"}
}