{
  "type": "Feature",
  "properties": {
    "iso:country":"CH",
    "sg:address":"Route De Faoug 25",
    "sg:city":"Courgevaux",
    "sg:orig_category":"Tierarztpraxis",
    "sg:phone":"+41 26 670 56 16",
    "sg:postcode":"1796",
    "sg:province":"Fribourg",
    "wof:name":"Dr M\u00e9d.v\u00e9t. E. Strittmatter M\u00e9decin V\u00e9t\u00e9rinaire",
    "wof:placetype":"venue"
},
  "geometry": {"coordinates":[7.1088399887,46.9077835083],"type":"Point"}
}