{
  "type": "Feature",
  "properties": {
    "addr:full":"Rue Ste-claire 3 Orbe Vaud 1350",
    "addr:housenumber":"3",
    "addr:postcode":"1350",
    "addr:street":"Rue Ste-Claire",
    "iso:country":"CH",
    "sg:address":"Rue Ste-claire 3",
    "sg:city":"Orbe",
    "sg:orig_category":"Arztpraxen",
    "sg:phone":"+41 24 441 22 55",
    "sg:postcode":"1350",
    "sg:province":"Vaud",
    "wof:name":"Drs M\u00e9d. B. & M. Lasserre M\u00e9decins G\u00e9n\u00e9ralistes",
    "wof:placetype":"venue"
},
  "geometry": {"coordinates":[6.532025,46.723549],"type":"Point"}
}