{
  "type": "Feature",
  "properties": {
    "iso:country":"CH",
    "sg:address":"Tumigerstrasse 71",
    "sg:city":"Greifensee",
    "sg:orig_category":"Sonstige mit der Informatik verbundene T\u00e4tigkeiten Unternehmensberatung",
    "sg:phone":"+41 71 220 36 50",
    "sg:postcode":"8606",
    "sg:province":"Z\u00fcrich",
    "wof:name":"Rsc Suter Ren\u00e9 Consulting Betriebwirtschaftliche Beratung Und Schulung In Den Bereichen Controlling, Rechnungswesen Usw",
    "wof:placetype":"venue"
},
  "geometry": {"coordinates":[9.3776988983,47.4244041443],"type":"Point"}
}