{
  "type": "Feature",
  "properties": {
    "iso:country":"CH",
    "sg:address":"Oberer Graben 22 8400 Winterthur. Postfach",
    "sg:city":"Winterthur",
    "sg:orig_category":"Fachdetailhandel in Verkaufsr\u00e4umen",
    "sg:postcode":"8400",
    "sg:province":"Z\u00fcrich",
    "wof:name":"Schmuckatelier My Line, Gabriella Heer",
    "wof:placetype":"venue"
},
  "geometry": {"coordinates":[8.7314310074,47.4989814758],"type":"Point"}
}