{
  "type": "Feature",
  "properties": {
    "iso:country":"CH",
    "sg:address":"Bachwiesenstrasse 121 8000 Z\u00fcrich. Postfach",
    "sg:city":"Z\u00fcrich",
    "sg:orig_category":"Softwareentwicklung U beratung",
    "sg:postcode":"8047",
    "sg:province":"Z\u00fcrich",
    "wof:name":"Edv-blitzofferte Moser Kati",
    "wof:placetype":"venue"
},
  "geometry": {"coordinates":[8.4851713181,47.3774795532],"type":"Point"}
}