{
  "type": "Feature",
  "properties": {
    "iso:country":"CH",
    "sg:address":"Schartenstrasse 12",
    "sg:city":"Baden",
    "sg:orig_category":"RESTAURANTS: TEA-ROOMS",
    "sg:phone":"+41 56 221 27 70",
    "sg:postcode":"5400",
    "sg:province":"Aargau",
    "wof:name":"Restaurant Metropol, Suter B.",
    "wof:placetype":"venue"
},
  "geometry": {"coordinates":[8.317568779,47.4719429016],"type":"Point"}
}