{
  "type": "Feature",
  "properties": {
    "iso:country":"CH",
    "sg:address":"Oltnerstrasse 56",
    "sg:city":"Sch\u00f6nenwerd",
    "sg:orig_category":"Non-Classified Establishments",
    "sg:postcode":"5012",
    "sg:province":"Solothurn",
    "wof:name":"Sputnick Handels Gmbh",
    "wof:placetype":"venue"
},
  "geometry": {"coordinates":[8.0007295609,47.3692207336],"type":"Point"}
}