{
  "type": "Feature",
  "properties": {
    "iso:country":"CH",
    "sg:address":"Oberdorf 9473 Gams. Postfach",
    "sg:city":"Gams",
    "sg:orig_category":"Fachdetailhandel in Verkaufsr\u00e4umen",
    "sg:postcode":"9473",
    "sg:province":"St. Gallen",
    "wof:name":"Blumen Vogel Bernadette Gmbh",
    "wof:placetype":"venue"
},
  "geometry": {"coordinates":[9.0545148849,47.1724510193],"type":"Point"}
}