{
  "type": "Feature",
  "properties": {
    "iso:country":"CH",
    "sg:address":"Predigergasse 4",
    "sg:city":"Z\u00fcrich",
    "sg:orig_category":"Herstellung von Bekleidung U Pelzwaren Herstellung von Schuhen",
    "sg:phone":"+41 12621005",
    "sg:postcode":"8001",
    "sg:province":"Z\u00fcrich",
    "wof:name":"Acood Gmbh",
    "wof:placetype":"venue"
},
  "geometry": {"coordinates":[8.546497345,47.3730735779],"type":"Point"}
}