{
  "type": "Feature",
  "properties": {
    "iso:country":"CH",
    "sg:address":"Sturmberg\u00e4cherstrasse 11a",
    "sg:city":"Wettswil",
    "sg:orig_category":"Sportvereine Orientierungslauf",
    "sg:phone":"+41 17011573",
    "sg:postcode":"8907",
    "sg:province":"Z\u00fcrich",
    "wof:name":"Zentralschw.ol-verband Zsolv",
    "wof:placetype":"venue"
},
  "geometry": {"coordinates":[8.4725151062,47.3426551819],"type":"Point"}
}