{
  "type": "Feature",
  "properties": {
    "iso:country":"CH",
    "sg:address":"Buffet De La Gare",
    "sg:city":"Porrentruy",
    "sg:orig_category":"RESTAURANTS: TEA-ROOMS",
    "sg:postcode":"2900",
    "sg:province":"Jura",
    "wof:name":"Buffet De La Gare S\u00e0rl",
    "wof:placetype":"venue"
},
  "geometry": {"coordinates":[7.0782270432,47.4170303345],"type":"Point"}
}