{
  "type": "Feature",
  "properties": {
    "iso:country":"CH",
    "sg:address":"Rauracherstrasse 33",
    "sg:city":"Riehen",
    "sg:classifiers":[
        {
            "category":"Government",
            "subcategory":"Fire Station",
            "type":"Public Place"
        }
    ],
    "sg:phone":"+41 61 601 49 41",
    "sg:postcode":"4125",
    "sg:province":"Basel-Stadt",
    "sg:tags":[
        "control",
        "equipment",
        "ventilation",
        "air conditioning",
        "unit"
    ],
    "wof:name":"Arbogast Isolierungen Ag",
    "wof:placetype":"venue"
},
  "geometry": {"coordinates":[7.6326050758,47.5707931519],"type":"Point"}
}