{
  "type": "Feature",
  "properties": {
    "iso:country":"CH",
    "sg:address":"Ohne Domizil",
    "sg:city":"Zug",
    "sg:orig_category":"Unclassifiable Establishments",
    "sg:postcode":"6300",
    "sg:province":"Zug",
    "wof:name":"Amflex Ag",
    "wof:placetype":"venue"
},
  "geometry": {"coordinates":[8.5162153244,47.1715087891],"type":"Point"}
}