{
  "type": "Feature",
  "properties": {
    "iso:country":"CH",
    "sg:address":"S\u00e4geweg 7",
    "sg:city":"Studen",
    "sg:classifiers":[
        {
            "category":"Shopping",
            "subcategory":"Computers & Home Electronics",
            "type":"Retail Goods"
        }
    ],
    "sg:phone":"+41 32 374 76 76",
    "sg:postcode":"2557",
    "sg:province":"Bern",
    "sg:tags":[
        "equipment",
        "electrical",
        "component",
        "electric",
        "electronic"
    ],
    "wof:name":"Pepperl+fuchs Ag",
    "wof:placetype":"venue"
},
  "geometry": {"coordinates":[7.3112468719,47.1103591919],"type":"Point"}
}