{
  "type": "Feature",
  "properties": {
    "iso:country":"CH",
    "sg:address":"Rue Saint-pierre 2 1003 Lausanne Case Postale 2673",
    "sg:city":"Lausanne",
    "sg:orig_category":"Advokaturb\u00fcros",
    "sg:phone":"+41 21 312 44 66",
    "sg:postcode":"1002",
    "sg:province":"Vaud",
    "wof:name":"De Haller Laffely Magnin Colombini & Ruggiero",
    "wof:placetype":"venue"
},
  "geometry": {"coordinates":[6.636792,46.519608],"type":"Point"}
}