{
  "type": "Feature",
  "properties": {
    "addr:full":"Hirschenplatz 1 Lyss Bern 3250",
    "addr:housenumber":"1",
    "addr:postcode":"3250",
    "addr:street":"Hirschenplatz;Bern",
    "iso:country":"CH",
    "sg:address":"Hirschenplatz 1",
    "sg:city":"Lyss",
    "sg:orig_category":"Arztpraxen",
    "sg:phone":"+41 32 385 36 36",
    "sg:postcode":"3250",
    "sg:province":"Bern",
    "wof:name":"Dr.med.hans Triaca Arzt F.allgemeine Medizin Fmh",
    "wof:placetype":"venue"
},
  "geometry": {"coordinates":[7.306662,47.07436],"type":"Point"}
}