{
  "type": "Feature",
  "properties": {
    "iso:country":"CH",
    "sg:address":"Via Valtgeva 8",
    "sg:city":"Sedrun",
    "sg:classifiers":[
        {
            "category":"Restaurant",
            "type":"Food & Drink"
        }
    ],
    "sg:phone":"+41 81 949 11 47",
    "sg:postcode":"7188",
    "sg:province":"Graubunden",
    "wof:name":"Ustaria Cristal",
    "wof:placetype":"venue"
},
  "geometry": {"coordinates":[8.7687129974,46.6820526123],"type":"Point"}
}