{
  "type": "Feature",
  "properties": {
    "iso:country":"CH",
    "sg:address":"Chemin De Maisonneuve 10",
    "sg:city":"Ch\u00e2telaine",
    "sg:orig_category":"Instandhaltung U Reparatur von Automobilen Mechanische Werkst\u00e4tten",
    "sg:phone":"+41 22 797 17 87",
    "sg:postcode":"1219",
    "sg:province":"Gen\u00e8ve",
    "wof:name":"Garage Caon Et Cerato",
    "wof:placetype":"venue"
},
  "geometry": {"coordinates":[6.1128878593,46.2122154236],"type":"Point"}
}