{
  "type": "Feature",
  "properties": {
    "iso:country":"CH",
    "sg:address":"Botyre",
    "sg:city":"Ayent",
    "sg:orig_category":"Elektroinstallation",
    "sg:phone":"+41 27 398 16 16",
    "sg:postcode":"1966",
    "sg:province":"Valais",
    "wof:name":"Willy Bonvin Installations \u00e9lectriques",
    "wof:placetype":"venue"
},
  "geometry": {"coordinates":[7.4068198204,46.2767791748],"type":"Point"}
}