{
  "type": "Feature",
  "properties": {
    "iso:country":"CH",
    "sg:address":"Rue Du 23-juin 48",
    "sg:city":"Del\u00e9mont",
    "sg:orig_category":"Zahnarztpraxen",
    "sg:phone":"+41 32 422 98 28",
    "sg:postcode":"2800",
    "sg:province":"Jura",
    "wof:name":"Dr M\u00e9d.dent.joseph Furtw\u00e4ngler M\u00e9decin-dentiste",
    "wof:placetype":"venue"
},
  "geometry": {"coordinates":[7.342359066,47.3646621704],"type":"Point"}
}