{
  "type": "Feature",
  "properties": {
    "iso:country":"CH",
    "sg:address":"Gibelinstrasse 27 4500 Solothurn. Postfach",
    "sg:city":"Solothurn",
    "sg:orig_category":"Detektivb\u00fcros U \u00dcberwachung",
    "sg:phone":"+41 32 621 23 03",
    "sg:postcode":"4503",
    "sg:province":"Solothurn",
    "wof:name":"Aeby Group Ag",
    "wof:placetype":"venue"
},
  "geometry": {"coordinates":[7.5257339478,47.2082633972],"type":"Point"}
}