{
  "type": "Feature",
  "properties": {
    "iso:country":"CH",
    "sg:address":"Steinenbachg\u00e4sslein 27 4051 Basel. Postfach",
    "sg:city":"Basel",
    "sg:orig_category":"Unternehmensberatung Wirtschaftspr\u00fcfung, Steuerberatung U Treuhand",
    "sg:phone":"+41 61 283 25 55",
    "sg:postcode":"4001",
    "sg:province":"Basel-Stadt",
    "wof:name":"Stb Stadt-treuhand Basel Gmbh",
    "wof:placetype":"venue"
},
  "geometry": {"coordinates":[7.5883469582,47.5528335571],"type":"Point"}
}