{
  "type": "Feature",
  "properties": {
    "iso:country":"CH",
    "sg:address":"Zentralstrasse 122",
    "sg:city":"Wettingen",
    "sg:classifiers":[
        {
            "category":"Personal",
            "subcategory":"Piercing",
            "type":"Services"
        }
    ],
    "sg:phone":"+41 56 427 40 15",
    "sg:postcode":"5430",
    "sg:province":"Aargau",
    "sg:tags":[
        "tattoo"
    ],
    "wof:name":"Dan's Tattoo",
    "wof:placetype":"venue"
},
  "geometry": {"coordinates":[8.326338768,47.4629478455],"type":"Point"}
}