{
  "type": "Feature",
  "properties": {
    "iso:country":"CH",
    "sg:address":"Via Entadavos",
    "sg:city":"Ruschein",
    "sg:orig_category":"Zimmerei, Ingenieurholzbau",
    "sg:phone":"+41 71 761 03 14",
    "sg:postcode":"7154",
    "sg:province":"Graubunden",
    "wof:name":"Daniel Kobler Zimmerei Holzbau",
    "wof:placetype":"venue"
},
  "geometry": {"coordinates":[9.5512523651,47.3193626404],"type":"Point"}
}