{
  "type": "Feature",
  "properties": {
    "iso:country":"CH",
    "sg:address":"Engelgasse 88",
    "sg:city":"Basel",
    "sg:orig_category":"Pensionskassen",
    "sg:phone":"+41 61 311 20 32",
    "sg:postcode":"4052",
    "sg:province":"Basel-Stadt",
    "wof:name":"Karrer-stiftung",
    "wof:placetype":"venue"
},
  "geometry": {"coordinates":[7.602200985,47.5485649109],"type":"Point"}
}