{
  "type": "Feature",
  "properties": {
    "addr:full":"Pr\u00e9-fleuri Chemin De 2 1006 Lausanne. Postfach Lausanne Vaud 1006",
    "addr:housenumber":"2",
    "addr:postcode":"1006;postfach;1006",
    "addr:street":"Chemin De",
    "iso:country":"CH",
    "sg:address":"Pr\u00e9-fleuri Chemin De 2 1006 Lausanne. Postfach",
    "sg:city":"Lausanne",
    "sg:orig_category":"Architektur U Ingenieurb\u00fcros",
    "sg:postcode":"1006",
    "sg:province":"Vaud",
    "wof:name":"Dlx Ing\u00e9nierie Civile S\u00e0rl Constructions Pour Logements, Activit\u00e9s Industrielles, Agricoles Etc",
    "wof:placetype":"venue"
},
  "geometry": {"coordinates":[6.630032,46.513168],"type":"Point"}
}