{
  "type": "Feature",
  "properties": {
    "iso:country":"CH",
    "sg:address":"R\u00f6tibergstr. 2 9442 Berneck. Postfach",
    "sg:city":"Balgach",
    "sg:orig_category":"Werbung",
    "sg:phone":"+41 71727072",
    "sg:postcode":"9436",
    "sg:province":"St. Gallen",
    "wof:name":"Z\u00fcnd Werbung.",
    "wof:placetype":"venue"
},
  "geometry": {"coordinates":[9.6045675278,47.426738739],"type":"Point"}
}