{
  "type": "Feature",
  "properties": {
    "iso:country":"CH",
    "sg:address":"Chemin Des Auges 17",
    "sg:city":"Villars-sur-gl\u00e2ne",
    "sg:orig_category":"G\u00fcterbef\u00f6rderung im Strassenverkehr",
    "sg:phone":"+41 31 829 22 89",
    "sg:postcode":"1752",
    "sg:province":"Fribourg",
    "wof:name":"Gilda & Daniel Trachsel Transporte",
    "wof:placetype":"venue"
},
  "geometry": {"coordinates":[7.3578181267,46.9720344543],"type":"Point"}
}