{
  "type": "Feature",
  "properties": {
    "iso:country":"CH",
    "sg:address":"Dorfstrasse 15b",
    "sg:city":"G\u00fcmligen",
    "sg:orig_category":"Mechanische Werkst\u00e4tten",
    "sg:phone":"+41 31 951 23 55",
    "sg:postcode":"3073",
    "sg:province":"Bern",
    "wof:name":"Ueli Aeschimann Mechanische Werkstatt",
    "wof:placetype":"venue"
},
  "geometry": {"coordinates":[7.5039367676,46.9361038208],"type":"Point"}
}