{
  "type": "Feature",
  "properties": {
    "iso:country":"CH",
    "sg:address":"Hauptgasse 41",
    "sg:city":"Appenzell",
    "sg:orig_category":"Grosshandel mit festen Brennstoffen U Mineral\u00f6lerzeugnissen",
    "sg:postcode":"9050",
    "sg:province":"Appenzell Innerhoden",
    "wof:name":"Krutrade Ag",
    "wof:placetype":"venue"
},
  "geometry": {"coordinates":[9.406867981,47.3313827515],"type":"Point"}
}