{
  "type": "Feature",
  "properties": {
    "iso:country":"CH",
    "sg:address":"Seestrasse 345",
    "sg:city":"Z\u00fcrich",
    "sg:orig_category":"Haltung von Rindern",
    "sg:postcode":"8038",
    "sg:province":"Z\u00fcrich",
    "wof:name":"Sennerei-genossenschaft Champf\u00e8r",
    "wof:placetype":"venue"
},
  "geometry": {"coordinates":[9.8381910324,46.4970664978],"type":"Point"}
}