{
  "type": "Feature",
  "properties": {
    "iso:country":"CH",
    "sg:address":"Weidhofstrasse 3",
    "sg:city":"Udligenswil",
    "sg:orig_category":"Physiotherapie",
    "sg:phone":"+41 41 371 00 03",
    "sg:postcode":"6044",
    "sg:province":"Luzern",
    "wof:name":"Felix & Karin Gloor Physiotherapie",
    "wof:placetype":"venue"
},
  "geometry": {"coordinates":[8.3969287872,47.090385437],"type":"Point"}
}