{
  "type": "Feature",
  "properties": {
    "iso:country":"CH",
    "sg:address":"Abtwilerstrasse 10",
    "sg:city":"Oberr\u00fcti",
    "sg:orig_category":"Non-Classified Establishments",
    "sg:postcode":"5647",
    "sg:province":"Aargau",
    "wof:name":"Genossenschaft Alterswohnheim Weiherwies, Grub Ar",
    "wof:placetype":"venue"
},
  "geometry": {"coordinates":[9.5076847076,47.4462242126],"type":"Point"}
}