{
  "type": "Feature",
  "properties": {
    "iso:country":"CH",
    "sg:address":"Rue Du Rh\u00f4ne 84",
    "sg:city":"Gen\u00e8ve",
    "sg:orig_category":"Advokaturb\u00fcros",
    "sg:phone":"+41 79 444 05 03",
    "sg:postcode":"1204",
    "sg:province":"Gen\u00e8ve",
    "wof:name":"Gion Clopath Avocat",
    "wof:placetype":"venue"
},
  "geometry": {"coordinates":[6.149868,46.203613],"type":"Point"}
}