{
  "type": "Feature",
  "properties": {
    "iso:country":"CH",
    "sg:address":"Schwaresterstr. 2",
    "sg:city":"Hendschiken",
    "sg:classifiers":[
        {
            "category":"Professional",
            "subcategory":"Engineering",
            "type":"Services"
        }
    ],
    "sg:phone":"+41 62 891 80 00",
    "sg:postcode":"5604",
    "sg:province":"Aargau",
    "sg:tags":[
        "machine",
        "-",
        "environment",
        "equipment",
        "machinery",
        "mechanical"
    ],
    "wof:name":"Kawe Ag",
    "wof:placetype":"venue"
},
  "geometry": {"coordinates":[8.2147989273,47.3856544495],"type":"Point"}
}