{
  "type": "Feature",
  "properties": {
    "iso:country":"CH",
    "sg:address":"7405",
    "sg:city":"Rothenbrunnen",
    "sg:orig_category":"Organisationen des Gesundheitswesen",
    "sg:phone":"+41 81 655 19 72",
    "sg:postcode":"7405",
    "sg:province":"Graubunden",
    "wof:name":"Samariterverein Mittel-& Ausserdomleschg",
    "wof:placetype":"venue"
},
  "geometry": {"coordinates":[9.4209403992,46.7782783508],"type":"Point"}
}