{
  "type": "Feature",
  "properties": {
    "iso:country":"CH",
    "sg:address":"Faubourg De L'h\u00f4pital 14",
    "sg:city":"Neuch\u00e2tel",
    "sg:orig_category":"Interessenvertretungen",
    "sg:postcode":"2000",
    "sg:province":"Neuch\u00e2tel",
    "wof:name":"Fondation Suisse Pour Les M\u00e9tiers D'art Fsma Objets Pr\u00e9s. Des Qualit\u00e9s Techniques Etc.; Soutenir, Favoriser",
    "wof:placetype":"venue"
},
  "geometry": {"coordinates":[6.8299050331,47.102809906],"type":"Point"}
}