{
  "type": "Feature",
  "properties": {
    "iso:country":"CH",
    "sg:address":"Talgutstrasse 24",
    "sg:city":"Winterthur",
    "sg:orig_category":"Herstellung von Metallkonstruktionen",
    "sg:postcode":"8400",
    "sg:province":"Z\u00fcrich",
    "wof:name":"M\u00fcller P. Jules Design & Handwerk",
    "wof:placetype":"venue"
},
  "geometry": {"coordinates":[8.7439432144,47.4933242798],"type":"Point"}
}