{
  "type": "Feature",
  "properties": {
    "iso:country":"CH",
    "sg:address":"Rorschacher Strasse 63",
    "sg:city":"St.gallen",
    "sg:orig_category":"Erbringung von Dienstleistungen f\u00fcr Unternehmen",
    "sg:phone":"+41 71 243 34 81",
    "sg:postcode":"9000",
    "sg:province":"St. Gallen",
    "wof:name":"Who's Who Management Edition Ag",
    "wof:placetype":"venue"
},
  "geometry": {"coordinates":[9.3840799332,47.4274902344],"type":"Point"}
}