{
  "type": "Feature",
  "properties": {
    "iso:country":"CH",
    "sg:address":"Stationsstrasse 1",
    "sg:city":"Ennetb\u00fcrgen",
    "sg:orig_category":"Detailhandel mit Fleisch U Fleischwaren",
    "sg:postcode":"6373",
    "sg:province":"Nidwalden",
    "wof:name":"Metzgerei Schaad Martin",
    "wof:placetype":"venue"
},
  "geometry": {"coordinates":[7.5159797668,47.4756889343],"type":"Point"}
}