{
  "type": "Feature",
  "properties": {
    "iso:country":"CH",
    "sg:address":"Cr\u00eat Chemin Du 1",
    "sg:city":"Crissier",
    "sg:orig_category":"Allgemeiner Hoch U Tiefbau",
    "sg:phone":"+41 21 711 22 20",
    "sg:postcode":"1023",
    "sg:province":"Vaud",
    "wof:name":"Rusconi M. Et Cie Sa",
    "wof:placetype":"venue"
},
  "geometry": {"coordinates":[6.577477,46.5532],"type":"Point"}
}