{
  "type": "Feature",
  "properties": {
    "iso:country":"CH",
    "sg:address":"Pelli Via Ferruccio 9",
    "sg:city":"Lugano",
    "sg:orig_category":"Fachdetailhandel in Verkaufsr\u00e4umen",
    "sg:phone":"+41 91 922 09 11",
    "sg:postcode":"6900",
    "sg:province":"Ticino",
    "wof:name":"Panza Collection Sa",
    "wof:placetype":"venue"
},
  "geometry": {"coordinates":[8.9507932663,46.0079956055],"type":"Point"}
}