{
  "type": "Feature",
  "properties": {
    "iso:country":"CH",
    "sg:address":"Widenholzstrasse 6",
    "sg:city":"Wallisellen",
    "sg:orig_category":"Detailhandel mit Sportartikeln",
    "sg:phone":"+41 18310744",
    "sg:postcode":"8304",
    "sg:province":"Z\u00fcrich",
    "wof:name":"Urs Zuberb\u00fchler Ski-& Snowboard Tunning-center",
    "wof:placetype":"venue"
},
  "geometry": {"coordinates":[8.6147022247,47.4115715027],"type":"Point"}
}