{
  "type": "Feature",
  "properties": {
    "iso:country":"CH",
    "sg:address":"Sonnhaldenstrasse 2",
    "sg:city":"Uster",
    "sg:orig_category":"Vereine Gesang",
    "sg:phone":"+41 71 288 13 17",
    "sg:postcode":"8610",
    "sg:province":"Z\u00fcrich",
    "wof:name":"Chorkreis St.gallen",
    "wof:placetype":"venue"
},
  "geometry": {"coordinates":[9.4045495987,47.4477386475],"type":"Point"}
}