{
  "type": "Feature",
  "properties": {
    "iso:country":"CH",
    "sg:address":"Dorfstrasse 16",
    "sg:city":"Baar",
    "sg:orig_category":"Allgemeiner Hoch U Tiefbau Allgemeiner Hochbau",
    "sg:phone":"+41 41 767 46 22",
    "sg:postcode":"6340",
    "sg:province":"Zug",
    "wof:name":"Peikert Bau Ag",
    "wof:placetype":"venue"
},
  "geometry": {"coordinates":[8.52484,47.19421],"type":"Point"}
}