{
  "type": "Feature",
  "properties": {
    "iso:country":"CH",
    "sg:address":"Margarethenstrasse 45",
    "sg:city":"Basel",
    "sg:classifiers":[
        {
            "category":"Restaurant",
            "type":"Food & Drink"
        }
    ],
    "sg:phone":"+41 61 274 19 90",
    "sg:postcode":"4053",
    "sg:province":"Basel-Stadt",
    "sg:tags":[
        "tea-rooms",
        "restaurants"
    ],
    "wof:name":"Aida Bar Restaurant, Stingelin Benmiloud Ursula",
    "wof:placetype":"venue"
},
  "geometry": {"coordinates":[7.5842981339,47.546661377],"type":"Point"}
}