{
  "type": "Feature",
  "properties": {
    "iso:country":"CH",
    "sg:address":"Segnesstrasse 12",
    "sg:city":"Z\u00fcrich",
    "sg:orig_category":"Erwachsenenbildung U Unterricht",
    "sg:phone":"+41 12736262",
    "sg:postcode":"8048",
    "sg:province":"Z\u00fcrich",
    "wof:name":"Technical English Services Ag",
    "wof:placetype":"venue"
},
  "geometry": {"coordinates":[8.4853229523,47.3883018494],"type":"Point"}
}