{
  "type": "Feature",
  "properties": {
    "iso:country":"CH",
    "sg:address":"General Guisan-quai 22",
    "sg:city":"Z\u00fcrich",
    "sg:orig_category":"Konsulate",
    "sg:phone":"+41 12857929",
    "sg:postcode":"8002",
    "sg:province":"Z\u00fcrich",
    "wof:name":"Konsulat Der Republik Seychellen",
    "wof:placetype":"venue"
},
  "geometry": {"coordinates":[8.5370693207,47.3646812439],"type":"Point"}
}