{
  "type": "Feature",
  "properties": {
    "addr:full":"St. Gallerstrasse 17 Flawil St. Gallen 9230",
    "addr:housenumber":"17",
    "addr:postcode":"9230",
    "addr:street":"St. Gallerstrasse",
    "iso:country":"CH",
    "sg:address":"St. Gallerstrasse 17",
    "sg:city":"Flawil",
    "sg:orig_category":"Immobilien U Baugewerbe, Bauhandwerk",
    "sg:phone":"+41 71 393 32 64",
    "sg:postcode":"9230",
    "sg:province":"St. Gallen",
    "wof:name":"Baumann Bauleitungen Holz- Und Metallbau",
    "wof:placetype":"venue"
},
  "geometry": {"coordinates":[9.188285,47.412582],"type":"Point"}
}