{
  "type": "Feature",
  "properties": {
    "iso:country":"CH",
    "sg:address":"Rue Du Jura 3",
    "sg:city":"Vevey",
    "sg:orig_category":"Detailhandel mit Ton U Bildtr\u00e4gern Detailhandel mit elektrischen Haushalts-,Radio U Fernsehger\u00e4ten s",
    "sg:phone":"+41 21 922 40 03",
    "sg:postcode":"1800",
    "sg:province":"Vaud",
    "wof:name":"Vinyl Records S\u00e0rl",
    "wof:placetype":"venue"
},
  "geometry": {"coordinates":[6.8415460587,46.4663200378],"type":"Point"}
}