{
  "type": "Feature",
  "properties": {
    "iso:country":"CH",
    "sg:address":"Schneggenhubel 8",
    "sg:city":"Kerns",
    "sg:orig_category":"Unclassifiable Establishments",
    "sg:phone":"+41 41 610 45 55",
    "sg:postcode":"6064",
    "sg:province":"Obwalden",
    "wof:name":"Odermatt-zimmermann Denner Satellit Gmbh",
    "wof:placetype":"venue"
},
  "geometry": {"coordinates":[8.3736953735,46.956451416],"type":"Point"}
}