{
  "type": "Feature",
  "properties": {
    "iso:country":"CH",
    "sg:address":"Alte Gasse 16",
    "sg:city":"Volketswil",
    "sg:orig_category":"Softwareentwicklung U beratung",
    "sg:postcode":"8604",
    "sg:province":"Z\u00fcrich",
    "wof:name":"D\u00f6serich Future Informatik",
    "wof:placetype":"venue"
},
  "geometry": {"coordinates":[9.0053958893,47.487487793],"type":"Point"}
}