{
  "type": "Feature",
  "properties": {
    "iso:country":"CH",
    "sg:address":"Forchstrasse 452",
    "sg:city":"Zollikon",
    "sg:orig_category":"Sonstige pers\u00f6nliche Dienstleistungen",
    "sg:postcode":"8702",
    "sg:province":"Z\u00fcrich",
    "wof:name":"Hamberger Dienstleistungen Ag",
    "wof:placetype":"venue"
},
  "geometry": {"coordinates":[7.9618401527,46.7377815247],"type":"Point"}
}