{
  "type": "Feature",
  "properties": {
    "iso:country":"CH",
    "sg:address":"Gestenrietstrasse 2",
    "sg:city":"Effretikon",
    "sg:orig_category":"Herstellung von Ger\u00e4ten der Elektrizit\u00e4tserzeugung, -verteilung u.\u00e4. -Herstellung von sonstigen elek",
    "sg:phone":"+41 52 343 80 80",
    "sg:postcode":"8307",
    "sg:province":"Z\u00fcrich",
    "wof:name":"Walesch Electronic Eschbach Walter",
    "wof:placetype":"venue"
},
  "geometry": {"coordinates":[8.6850128174,47.429069519],"type":"Point"}
}