{
  "type": "Feature",
  "properties": {
    "iso:country":"CH",
    "sg:address":"Fin-de-praz 2a",
    "sg:city":"St-aubin-sauges",
    "sg:orig_category":"S\u00e4ge, Hobel U Holzimpr\u00e4gnierwerke",
    "sg:postcode":"2024",
    "sg:province":"Neuch\u00e2tel",
    "wof:name":"Logis-bois Cnc S\u00e0rl",
    "wof:placetype":"venue"
},
  "geometry": {"coordinates":[6.7777261734,46.8959350586],"type":"Point"}
}