{
  "type": "Feature",
  "properties": {
    "iso:country":"CH",
    "sg:address":"8585",
    "sg:city":"Mattwil",
    "sg:orig_category":"Schulpflegen",
    "sg:postcode":"8585",
    "sg:province":"Thurgau",
    "wof:name":"Primarschulkommission Mattwil-birwinken-happerswil",
    "wof:placetype":"venue"
},
  "geometry": {"coordinates":[9.2072200775,47.5780792236],"type":"Point"}
}