{
  "type": "Feature",
  "properties": {
    "iso:country":"CH",
    "sg:address":"Chemin De F\u00e9nix 92",
    "sg:city":"Ch\u00e2telard-lutry",
    "sg:orig_category":"Interessenvertretungen",
    "sg:phone":"+41 27 761 22 25",
    "sg:postcode":"1095",
    "sg:province":"Vaud",
    "wof:name":"Fondation Le Chalet",
    "wof:placetype":"venue"
},
  "geometry": {"coordinates":[7.020275116,46.1201057434],"type":"Point"}
}