{
  "type": "Feature",
  "properties": {
    "addr:full":"Birchstrasse 106 Z\u00fcrich Z\u00fcrich 8050",
    "addr:housenumber":"106",
    "addr:postcode":"8050",
    "addr:street":"Birchstrasse",
    "iso:country":"CH",
    "sg:address":"Birchstrasse 106",
    "sg:city":"Z\u00fcrich",
    "sg:orig_category":"Detailhandel mit Beleuchtungs U Haushaltsgegenst\u00e4nden Innendekorationsateliers",
    "sg:phone":"+41 13103103",
    "sg:postcode":"8050",
    "sg:province":"Z\u00fcrich",
    "wof:name":"Marcel Jung Extra Creative Factory",
    "wof:placetype":"venue"
},
  "geometry": {"coordinates":[8.537246,47.408382],"type":"Point"}
}