{
  "type": "Feature",
  "properties": {
    "iso:country":"CH",
    "sg:address":"Seestrasse 29",
    "sg:city":"Thalwil",
    "sg:orig_category":"Unclassifiable Establishments",
    "sg:phone":"+41 17211593",
    "sg:postcode":"8800",
    "sg:province":"Z\u00fcrich",
    "wof:name":"Nicoliello Com",
    "wof:placetype":"venue"
},
  "geometry": {"coordinates":[8.5765886307,47.2846107483],"type":"Point"}
}