{
  "type": "Feature",
  "properties": {
    "iso:country":"CH",
    "sg:address":"Postgasse 3",
    "sg:city":"Binningen",
    "sg:classifiers":[
        {
            "category":"Restaurant",
            "type":"Food & Drink"
        }
    ],
    "sg:phone":"+41 61 421 66 47",
    "sg:postcode":"4102",
    "sg:province":"Basel-Landschaft",
    "wof:name":"Restaurant Baselbieter",
    "wof:placetype":"venue"
},
  "geometry": {"coordinates":[7.5745620728,47.5405044556],"type":"Point"}
}