{
  "type": "Feature",
  "properties": {
    "iso:country":"CH",
    "sg:address":"Rue De Vevey 201",
    "sg:city":"Bulle",
    "sg:classifiers":[
        {
            "category":"Restaurant",
            "type":"Food & Drink"
        }
    ],
    "sg:phone":"+41 71 222 20 12",
    "sg:postcode":"1630",
    "sg:province":"Fribourg",
    "wof:name":"Caf\u00e9 Colony Club",
    "wof:placetype":"venue"
},
  "geometry": {"coordinates":[9.3743562698,47.4243774414],"type":"Point"}
}