{
  "type": "Feature",
  "properties": {
    "iso:country":"CH",
    "sg:address":"Eichenweg 4 3052 Zollikofen. Postfach",
    "sg:city":"Zollikofen",
    "sg:orig_category":"Grosshandel mit Getreide, Saatgut U Futtermitteln Grosshandel mit lebenden Tieren",
    "sg:phone":"+41 31 910 85 00",
    "sg:postcode":"3052",
    "sg:province":"Bern",
    "wof:name":"Anicom Ag Viehhandel",
    "wof:placetype":"venue"
},
  "geometry": {"coordinates":[7.4634890556,46.9967079163],"type":"Point"}
}