{
  "type": "Feature",
  "properties": {
    "iso:country":"CH",
    "sg:address":"Baumackerstrasse 24 8050 Z\u00fcrich. Postfach 9189",
    "sg:city":"Z\u00fcrich",
    "sg:orig_category":"Grosshandel mit Obst U Gem\u00fcse Grosshandel mit sonstigen Nahrungsmitteln",
    "sg:phone":"+41 13155656",
    "sg:postcode":"8050",
    "sg:province":"Z\u00fcrich",
    "wof:name":"Stutzer & Co Ag Waren, Bes. Lebensmittel; Handel Usw",
    "wof:placetype":"venue"
},
  "geometry": {"coordinates":[8.5448379517,47.4087257385],"type":"Point"}
}