{
  "type": "Feature",
  "properties": {
    "addr:full":"Neufeldweg 407 Neuendorf Solothurn 4623",
    "addr:housenumber":"407",
    "addr:postcode":"4623",
    "addr:street":"Neufeldweg",
    "iso:country":"CH",
    "sg:address":"Neufeldweg 407",
    "sg:city":"Neuendorf",
    "sg:classifiers":[
        {
            "category":"Wholesale",
            "subcategory":"Machinery & Supplies",
            "type":"Manufacturing & Wholesale Goods"
        }
    ],
    "sg:phone":"+41 62 398 22 17",
    "sg:postcode":"4623",
    "sg:province":"Solothurn",
    "sg:tags":[
        "agricultural",
        "equipment"
    ],
    "wof:name":"Franz J\u00e4ggi Traktoren U. Landmaschinen",
    "wof:placetype":"venue"
},
  "geometry": {"coordinates":[7.793028,47.304218],"type":"Point"}
}