{
  "type": "Feature",
  "properties": {
    "iso:country":"CH",
    "sg:address":"Sans Adresse",
    "sg:city":"Courgenay",
    "sg:orig_category":"Sonstiges Versicherungsgewerbe",
    "sg:postcode":"2950",
    "sg:province":"Jura",
    "wof:name":"Mir Courtage, Philippe D\u00e9boeuf",
    "wof:placetype":"venue"
},
  "geometry": {"coordinates":[7.1266851425,47.403213501],"type":"Point"}
}