{
  "type": "Feature",
  "properties": {
    "iso:country":"CH",
    "sg:address":"Milit\u00e4rstrasse 84 8004 Z\u00fcrich. Postfach",
    "sg:city":"Z\u00fcrich",
    "sg:orig_category":"Reiseb\u00fcros",
    "sg:phone":"+41 12413111",
    "sg:postcode":"8021",
    "sg:province":"Z\u00fcrich",
    "wof:name":"Intercommercial Ag Reiseunternehmen",
    "wof:placetype":"venue"
},
  "geometry": {"coordinates":[8.5295591354,47.3785591125],"type":"Point"}
}