{
  "type": "Feature",
  "properties": {
    "addr:full":"Stazione F.f.s. Lugano Ticino 6900",
    "addr:postcode":"6900",
    "iso:country":"CH",
    "sg:address":"Stazione F.f.s.",
    "sg:city":"Lugano",
    "sg:orig_category":"Bahnhofbuffets Restaurants",
    "sg:phone":"+41 91 911 34 24",
    "sg:postcode":"6900",
    "sg:province":"Ticino",
    "wof:name":"Ristorante-pizzeria Stazione Lugano-ponte Tresa",
    "wof:placetype":"venue"
},
  "geometry": {"coordinates":[8.947115,46.005356],"type":"Point"}
}