{
  "type": "Feature",
  "properties": {
    "iso:country":"CH",
    "sg:address":"Sonnmatt 66",
    "sg:city":"Mogelsberg",
    "sg:orig_category":"Detailhandel mit Metallwaren, Anstrichmitteln, Glaswaren, Bau U Heimwerkerbedarf",
    "sg:phone":"+41 71 374 15 12",
    "sg:postcode":"9122",
    "sg:province":"St. Gallen",
    "wof:name":"Motra Gmbh",
    "wof:placetype":"venue"
},
  "geometry": {"coordinates":[9.1355648041,47.3580436707],"type":"Point"}
}