{
  "type": "Feature",
  "properties": {
    "iso:country":"CH",
    "sg:address":"Grubenweg 3",
    "sg:city":"Dulliken",
    "sg:orig_category":"Grosshandel mit Textilien",
    "sg:postcode":"4657",
    "sg:province":"Solothurn",
    "wof:name":"Ageco Gmbh",
    "wof:placetype":"venue"
},
  "geometry": {"coordinates":[7.9515280724,47.3533325195],"type":"Point"}
}