{
  "type": "Feature",
  "properties": {
    "iso:country":"CH",
    "sg:address":"Coppet Route De 26",
    "sg:city":"Commugny",
    "sg:orig_category":"Unclassifiable Establishments",
    "sg:phone":"+41 22 960 96 50",
    "sg:postcode":"1291",
    "sg:province":"Vaud",
    "wof:name":"Alibi S\u00e0rl Communication - Marketing - Publicit\u00e9",
    "wof:placetype":"venue"
},
  "geometry": {"coordinates":[6.1738519669,46.3194656372],"type":"Point"}
}