{
  "type": "Feature",
  "properties": {
    "addr:full":"Bremgarten Aargau 5620",
    "addr:postcode":"5620",
    "addr:street":"Bremgarten Aargau",
    "iso:country":"CH",
    "sg:city":"Bremgarten",
    "sg:orig_category":"Freizeit, Partnerschaft",
    "sg:postcode":"5620",
    "sg:province":"Aargau",
    "wof:name":"Schachklub Mutschellen",
    "wof:placetype":"venue"
},
  "geometry": {"coordinates":[8.344453,47.35067],"type":"Point"}
}