{
  "type": "Feature",
  "properties": {
    "iso:country":"CH",
    "sg:address":"Einhardweg 1 8603 Schwerzenbach. Postfach 621",
    "sg:city":"Schwerzenbach",
    "sg:orig_category":"Softwareentwicklung U beratung",
    "sg:phone":"+41 18250588",
    "sg:postcode":"8603",
    "sg:province":"Z\u00fcrich",
    "wof:name":"Bommeli'solutions Gmbh",
    "wof:placetype":"venue"
},
  "geometry": {"coordinates":[8.6599006653,47.3820304871],"type":"Point"}
}