{
  "type": "Feature",
  "properties": {
    "iso:country":"CH",
    "sg:address":"Sch\u00e4racherstrasse 6",
    "sg:city":"Z\u00fcrich",
    "sg:orig_category":"Bauschreinerei Innenausbau",
    "sg:phone":"+41 17105710",
    "sg:postcode":"8053",
    "sg:province":"Z\u00fcrich",
    "wof:name":"Rank Gmbh",
    "wof:placetype":"venue"
},
  "geometry": {"coordinates":[8.597197,47.354465],"type":"Point"}
}