{
  "type": "Feature",
  "properties": {
    "iso:country":"CH",
    "sg:address":"Schlossstrasse 3",
    "sg:city":"Pratteln",
    "sg:orig_category":"Pensionskassen",
    "sg:postcode":"4133",
    "sg:province":"Basel-Landschaft",
    "wof:name":"Wohlfahrtsfonds Der H\u00e4ring & Co Ag",
    "wof:placetype":"venue"
},
  "geometry": {"coordinates":[7.6945090294,47.5223007202],"type":"Point"}
}