{
  "type": "Feature",
  "properties": {
    "iso:country":"CH",
    "sg:address":"Sinserstrasse 1 6330 Cham. Postfach 273",
    "sg:city":"Cham",
    "sg:orig_category":"Detailhandel mit Beleuchtungs U Haushaltsgegenst\u00e4nden Sonstiger Grosshandel",
    "sg:phone":"+41 41 780 17 17",
    "sg:postcode":"6330",
    "sg:province":"Zug",
    "wof:name":"Locher W. Ag",
    "wof:placetype":"venue"
},
  "geometry": {"coordinates":[8.458759,47.181385],"type":"Point"}
}