{
  "type": "Feature",
  "properties": {
    "iso:country":"CH",
    "sg:address":"Fl\u00e4sch",
    "sg:city":"Fl\u00e4sch",
    "sg:classifiers":[
        {
            "category":"Arena",
            "subcategory":"Horse Racetrack",
            "type":"Entertainment"
        }
    ],
    "sg:phone":"+41 81 302 45 75",
    "sg:postcode":"7306",
    "sg:province":"Graubunden",
    "sg:tags":[
        "trailer"
    ],
    "wof:name":"B\u00f6ckmann Anh\u00e4ngervertrieb",
    "wof:placetype":"venue"
},
  "geometry": {"coordinates":[9.5113401413,47.0243797302],"type":"Point"}
}