{
  "type": "Feature",
  "properties": {
    "iso:country":"CH",
    "sg:address":"Ritz Avenue 1",
    "sg:city":"Sion",
    "sg:orig_category":"Interessenvertretungen",
    "sg:phone":"+41 27 606 20 06",
    "sg:postcode":"1951",
    "sg:province":"Valais",
    "wof:name":"Fondation Pour Le D\u00e9veloppement Durable Des R\u00e9gions De Montagne",
    "wof:placetype":"venue"
},
  "geometry": {"coordinates":[7.3563141823,46.2348213196],"type":"Point"}
}