{
  "type": "Feature",
  "properties": {
    "iso:country":"CH",
    "sg:address":"Riburgstrasse 16",
    "sg:city":"Basel",
    "sg:orig_category":"Sportvereine Ballsport Handball",
    "sg:phone":"+41 61 601 02 79",
    "sg:postcode":"4058",
    "sg:province":"Basel-Stadt",
    "wof:name":"Tv Aesch",
    "wof:placetype":"venue"
},
  "geometry": {"coordinates":[7.6192450523,47.5643119812],"type":"Point"}
}