{
  "type": "Feature",
  "properties": {
    "iso:country":"CH",
    "sg:address":"R\u00f6schibachstrasse 46",
    "sg:city":"Z\u00fcrich",
    "sg:orig_category":"Detailhandel mit medizinischen U orthop\u00e4dischen Artikeln Herstellung von medizinischen U chirurgisch",
    "sg:phone":"+41 12728981",
    "sg:postcode":"8037",
    "sg:province":"Z\u00fcrich",
    "wof:name":"Orthop\u00e4die-technik H\u00e4geli W. Ag",
    "wof:placetype":"venue"
},
  "geometry": {"coordinates":[8.5257978439,47.3933486938],"type":"Point"}
}