{
  "type": "Feature",
  "properties": {
    "iso:country":"CH",
    "sg:address":"Ottostrasse 25",
    "sg:city":"Chur",
    "sg:orig_category":"Architekturb\u00fcros",
    "sg:phone":"+41 81 252 01 01",
    "sg:postcode":"7000",
    "sg:province":"Graubunden",
    "wof:name":"Jakob Ruosch Architekturb\u00fcro",
    "wof:placetype":"venue"
},
  "geometry": {"coordinates":[9.533242,46.853695],"type":"Point"}
}