{
  "type": "Feature",
  "properties": {
    "iso:country":"CH",
    "sg:address":"Romanshornerstrasse 2",
    "sg:city":"Sulgen",
    "sg:classifiers":[
        {
            "category":"Restaurant",
            "type":"Food & Drink"
        }
    ],
    "sg:phone":"+41 71 642 22 88",
    "sg:postcode":"8583",
    "sg:province":"Thurgau",
    "wof:name":"Restaurant Ochsen",
    "wof:placetype":"venue"
},
  "geometry": {"coordinates":[9.1822414398,47.5449867249],"type":"Point"}
}