{
  "type": "Feature",
  "properties": {
    "iso:country":"CH",
    "sg:address":"Fribourg Route De 11 1723 Marly Case Postale 108",
    "sg:city":"Marly",
    "sg:orig_category":"Handel mit Automobilen",
    "sg:phone":"+41 26 439 99 00",
    "sg:postcode":"1723",
    "sg:province":"Fribourg",
    "wof:name":"Emil Frey Sa Gen\u00e8ve",
    "wof:placetype":"venue"
},
  "geometry": {"coordinates":[7.1522312164,46.7794761658],"type":"Point"}
}