{
  "type": "Feature",
  "properties": {
    "iso:country":"CH",
    "sg:address":"S\u00e4ntisstrasse 11 8311 Br\u00fctten. Postfach",
    "sg:city":"Br\u00fctten",
    "sg:orig_category":"Herstellung von Konstruktionsteilen, Fertigbauteilen U Ausbauelementen aus Holz",
    "sg:postcode":"8311",
    "sg:province":"Z\u00fcrich",
    "wof:name":"Eugster Bauplanung + Bauleitung Gmbh",
    "wof:placetype":"venue"
},
  "geometry": {"coordinates":[8.6761808395,47.4748191833],"type":"Point"}
}