{
  "type": "Feature",
  "properties": {
    "iso:country":"CH",
    "sg:address":"Zielweg 8",
    "sg:city":"Flawil",
    "sg:orig_category":"Elektroinstallation",
    "sg:phone":"+41 61 481 32 00",
    "sg:postcode":"9230",
    "sg:province":"St. Gallen",
    "wof:name":"Trinkler Elektro-anlagen Ag",
    "wof:placetype":"venue"
},
  "geometry": {"coordinates":[7.5365428925,47.5513458252],"type":"Point"}
}