{
  "type": "Feature",
  "properties": {
    "iso:country":"CH",
    "sg:address":"Jakob Peter-weg 27",
    "sg:city":"Z\u00fcrich",
    "sg:orig_category":"Schreib U \u00dcbersetzungsb\u00fcros",
    "sg:phone":"+41 14829442",
    "sg:postcode":"8055",
    "sg:province":"Z\u00fcrich",
    "wof:name":"Textpunkt Robert Peterhans",
    "wof:placetype":"venue"
},
  "geometry": {"coordinates":[8.5827541351,47.3182792664],"type":"Point"}
}