{
  "type": "Feature",
  "properties": {
    "iso:country":"CH",
    "sg:address":"Sandeggstrasse 9",
    "sg:city":"M\u00e4rstetten",
    "sg:orig_category":"Detailhandel mit Milcherzeugnissen U Eiern Verarbeitung von Milch",
    "sg:phone":"+41 71 657 12 47",
    "sg:postcode":"8560",
    "sg:province":"Thurgau",
    "wof:name":"Josef Kiser K\u00e4serei",
    "wof:placetype":"venue"
},
  "geometry": {"coordinates":[9.069647789,47.5922966003],"type":"Point"}
}