{
  "type": "Feature",
  "properties": {
    "iso:country":"CH",
    "sg:address":"Steinackerstrasse 8 8902 Urdorf. Postfach",
    "sg:city":"Urdorf",
    "sg:orig_category":"Detailhandel mit Metallwaren, Anstrichmitteln, Glaswaren, Bau U Heimwerkerbedarf HERSTELLUNG VON GER",
    "sg:phone":"+41 32 913 64 30",
    "sg:postcode":"8902",
    "sg:province":"Z\u00fcrich",
    "wof:name":"Spheridur, Fr\u00e9sard Claude-alain",
    "wof:placetype":"venue"
},
  "geometry": {"coordinates":[6.8262882233,47.0918273926],"type":"Point"}
}