{
  "type": "Feature",
  "properties": {
    "iso:country":"CH",
    "sg:address":"Hirschg\u00e4sslein 21 4051 Basel. Postfach",
    "sg:city":"Basel",
    "sg:orig_category":"Sonstiges Versicherungsgewerbe",
    "sg:phone":"+41 61 205 30 00",
    "sg:postcode":"4010",
    "sg:province":"Basel-Stadt",
    "wof:name":"Geb\u00e4udeversicherung Des Kantons Basel-stadt",
    "wof:placetype":"venue"
},
  "geometry": {"coordinates":[7.5928821564,47.5507316589],"type":"Point"}
}