{
  "type": "Feature",
  "properties": {
    "iso:country":"CH",
    "sg:address":"Gstaltenrainweg 70",
    "sg:city":"Riehen",
    "sg:orig_category":"Elektroinstallation Herstellung von Elektromotoren, Generatoren U Transformatoren",
    "sg:phone":"+41 61 601 34 28",
    "sg:postcode":"4125",
    "sg:province":"Basel-Stadt",
    "wof:name":"Elektro Gempeler",
    "wof:placetype":"venue"
},
  "geometry": {"coordinates":[7.6378111839,47.5741386414],"type":"Point"}
}