{
  "type": "Feature",
  "properties": {
    "iso:country":"CH",
    "sg:address":"Poststrasse 4",
    "sg:city":"Biberist",
    "sg:orig_category":"Nationale Postdienste",
    "sg:phone":"+41 32 672 45 05",
    "sg:postcode":"4562",
    "sg:province":"Solothurn",
    "wof:name":"Die Schweizerische Post",
    "wof:placetype":"venue"
},
  "geometry": {"coordinates":[7.5626578331,47.183013916],"type":"Point"}
}