{
  "type": "Feature",
  "properties": {
    "iso:country":"CH",
    "sg:address":"Innere G\u00fcterstrasse 4",
    "sg:city":"Zug",
    "sg:orig_category":"Herstellung von Kork, Flecht U Korbwaren",
    "sg:phone":"+41 52 672 63 28",
    "sg:postcode":"6300",
    "sg:province":"Zug",
    "wof:name":"Grob-garntex Ag",
    "wof:placetype":"venue"
},
  "geometry": {"coordinates":[8.6240730286,47.6816101074],"type":"Point"}
}