{
  "type": "Feature",
  "properties": {
    "iso:country":"CH",
    "sg:address":"Hauptstrasse 35",
    "sg:city":"Koppigen",
    "sg:orig_category":"Sonstiger Grosshandel",
    "sg:postcode":"3425",
    "sg:province":"Bern",
    "wof:name":"B.s. & A. Business Services And Advisory International Sa",
    "wof:placetype":"venue"
},
  "geometry": {"coordinates":[6.7649688721,47.0632553101],"type":"Point"}
}