{
  "type": "Feature",
  "properties": {
    "iso:country":"CH",
    "sg:address":"Postgasse 21",
    "sg:city":"Glarus",
    "sg:orig_category":"Grosshandel mit sonstigen Maschinen U Ausr\u00fcstungen f\u00fcr Industrie, Handel U Schiffahrt",
    "sg:postcode":"8750",
    "sg:province":"Glarus",
    "wof:name":"Pesce Industry",
    "wof:placetype":"venue"
},
  "geometry": {"coordinates":[7.4636449814,46.2584381104],"type":"Point"}
}