{
  "type": "Feature",
  "properties": {
    "iso:country":"CH",
    "sg:address":"Mellingerstrasse 22",
    "sg:city":"Baden",
    "sg:classifiers":[
        {
            "category":"Travel",
            "subcategory":"Hotels & Motels",
            "type":"Entertainment"
        }
    ],
    "sg:phone":"+41 56 222 73 39",
    "sg:postcode":"5400",
    "sg:province":"Aargau",
    "sg:tags":[
        "hotels",
        "mit",
        "restaurant"
    ],
    "wof:name":"Fritz Wanner & Co B\u00e4ckerei - Konditorei",
    "wof:placetype":"venue"
},
  "geometry": {"coordinates":[8.3050146103,47.4711685181],"type":"Point"}
}