{
  "type": "Feature",
  "properties": {
    "iso:country":"CH",
    "sg:address":"Pfistergasse 38",
    "sg:city":"Zofingen",
    "sg:orig_category":"Pensionskassen",
    "sg:postcode":"4800",
    "sg:province":"Aargau",
    "wof:name":"Versicherungskasse Der Emil Mohr Ag",
    "wof:placetype":"venue"
},
  "geometry": {"coordinates":[8.7868356705,47.323387146],"type":"Point"}
}