{
  "type": "Feature",
  "properties": {
    "iso:country":"CH",
    "sg:address":"Chemin Des Rossignols",
    "sg:city":"Lonay",
    "sg:orig_category":"Datenverarbeitungsdienste Fernmeldedienste",
    "sg:postcode":"1027",
    "sg:province":"Vaud",
    "wof:name":"Netconcept Sa",
    "wof:placetype":"venue"
},
  "geometry": {"coordinates":[6.522595,46.52816],"type":"Point"}
}