{
  "type": "Feature",
  "properties": {
    "iso:country":"CH",
    "sg:address":"Grand-rue 16",
    "sg:city":"Fleurier",
    "sg:classifiers":[
        {
            "category":"Restaurant",
            "type":"Food & Drink"
        }
    ],
    "sg:phone":"+41 32 861 10 31",
    "sg:postcode":"2114",
    "sg:province":"Neuch\u00e2tel",
    "wof:name":"Salon De Th\u00e9 Perrenoud",
    "wof:placetype":"venue"
},
  "geometry": {"coordinates":[6.582174778,46.9023284912],"type":"Point"}
}