{
  "type": "Feature",
  "properties": {
    "iso:country":"CH",
    "sg:address":"Rue Des Ages 5",
    "sg:city":"Bulle",
    "sg:orig_category":"Architekturb\u00fcros Grosshandel mit Nahrungsmitteln, Getr\u00e4nken U Tabakwaren ohne ausgepr\u00e4gten Schwerpun",
    "sg:phone":"+41 62 771 70 01",
    "sg:postcode":"1630",
    "sg:province":"Fribourg",
    "wof:name":"Drawing Office Antonio Santoro",
    "wof:placetype":"venue"
},
  "geometry": {"coordinates":[8.174195,47.252361],"type":"Point"}
}