{
  "type": "Feature",
  "properties": {
    "iso:country":"CH",
    "sg:address":"G\u00fcterstrasse 300",
    "sg:city":"Basel",
    "sg:orig_category":"Unclassifiable Establishments",
    "sg:postcode":"4053",
    "sg:province":"Basel-Stadt",
    "wof:name":"Nv Neutrale Vorsorgeberatung Palazzo",
    "wof:placetype":"venue"
},
  "geometry": {"coordinates":[7.600897789,47.5408592224],"type":"Point"}
}