{
  "type": "Feature",
  "properties": {
    "iso:country":"CH",
    "sg:address":"Freudenbergstrasse 11",
    "sg:city":"Z\u00fcrich",
    "sg:orig_category":"Interessenvertretungen",
    "sg:phone":"+41 12527865",
    "sg:postcode":"8044",
    "sg:province":"Z\u00fcrich",
    "wof:name":"Davidson-stiftung Walter Und Louise M. Beitr\u00e4ge F. Unterhalt, Erziehung U. Ausblidung Junger Menschen, Gemeinn\u00fctzige F\u00fcrsorge Usw.",
    "wof:placetype":"venue"
},
  "geometry": {"coordinates":[8.5590953827,47.3804664612],"type":"Point"}
}