{
  "type": "Feature",
  "properties": {
    "iso:country":"CH",
    "sg:address":"Simplonstrasse 81 3900 Brig. Postfach",
    "sg:city":"Brig",
    "sg:orig_category":"Verwertung von Milch",
    "sg:postcode":"3900",
    "sg:province":"Valais",
    "wof:name":"Sennereigenossenschaft Brigerberg",
    "wof:placetype":"venue"
},
  "geometry": {"coordinates":[7.9940757751,46.3212203979],"type":"Point"}
}