{
  "type": "Feature",
  "properties": {
    "iso:country":"CH",
    "sg:address":"Promenade Du Mont-blanc 14",
    "sg:city":"Nyon",
    "sg:orig_category":"Werbung",
    "sg:postcode":"1260",
    "sg:province":"Vaud",
    "wof:name":"Sabelus Public Relations",
    "wof:placetype":"venue"
},
  "geometry": {"coordinates":[8.5568380356,47.3079071045],"type":"Point"}
}