{
  "type": "Feature",
  "properties": {
    "addr:full":"Paulstrasse 7 Uster Z\u00fcrich 8610",
    "addr:housenumber":"7",
    "addr:postcode":"8610",
    "addr:street":"Paulstrasse",
    "iso:country":"CH",
    "sg:address":"Paulstrasse 7",
    "sg:city":"Uster",
    "sg:orig_category":"Bauspenglerei Sanit\u00e4rinstallation U Spenglerei",
    "sg:phone":"+41 19405418",
    "sg:postcode":"8610",
    "sg:province":"Z\u00fcrich",
    "wof:name":"Hansj\u00f6rg Weiersm\u00fcller Comet-oelfeuerungen",
    "wof:placetype":"venue"
},
  "geometry": {"coordinates":[8.712344,47.352375],"type":"Point"}
}