{
  "type": "Feature",
  "properties": {
    "iso:country":"CH",
    "sg:address":"Sempacherstrasse 30",
    "sg:city":"Basel",
    "sg:orig_category":"Interessenvertretungen",
    "sg:phone":"+41 61 361 30 56",
    "sg:postcode":"4053",
    "sg:province":"Basel-Stadt",
    "wof:name":"Willy Ebner-stiftung",
    "wof:placetype":"venue"
},
  "geometry": {"coordinates":[7.5877380371,47.5438423157],"type":"Point"}
}