{
  "type": "Feature",
  "properties": {
    "iso:country":"CH",
    "sg:address":"Bodenmatte 3",
    "sg:city":"Oberr\u00fcti",
    "sg:orig_category":"Grosshandel mit elektrischen Haushaltsger\u00e4ten, Radio U Fernsehger\u00e4ten",
    "sg:phone":"+41 41 787 07 12",
    "sg:postcode":"5647",
    "sg:province":"Aargau",
    "wof:name":"Jb Elektro Kabelkonfektion",
    "wof:placetype":"venue"
},
  "geometry": {"coordinates":[8.3977890015,47.1663780212],"type":"Point"}
}