{
  "type": "Feature",
  "properties": {
    "iso:country":"CH",
    "sg:address":"Gass",
    "sg:city":"Eriswil",
    "sg:orig_category":"Sonstiges Versicherungsgewerbe",
    "sg:phone":"+41 31 790 31 11",
    "sg:postcode":"4952",
    "sg:province":"Bern",
    "wof:name":"Emmentalische Mobiliarversich. Bezirksagentur Paul Schneider",
    "wof:placetype":"venue"
},
  "geometry": {"coordinates":[7.848859787,47.0806503296],"type":"Point"}
}