{
  "type": "Feature",
  "properties": {
    "addr:full":"In Der Eich 7 R\u00f6schenz Basel-Landschaft 4244",
    "addr:housenumber":"7",
    "addr:postcode":"4244",
    "addr:street":"In Der Eich",
    "iso:country":"CH",
    "sg:address":"In Der Eich 7",
    "sg:city":"R\u00f6schenz",
    "sg:orig_category":"Allgemeiner Hochbau Stukkateurgewerbe, Gipserei U Verputzerei",
    "sg:phone":"+41 79 321 26 16",
    "sg:postcode":"4244",
    "sg:province":"Basel-Landschaft",
    "wof:name":"Bloch & B\u00fcrgi Gipser-& Fassadengesch\u00e4ft",
    "wof:placetype":"venue"
},
  "geometry": {"coordinates":[7.593294,47.487991],"type":"Point"}
}