{
  "type": "Feature",
  "properties": {
    "iso:country":"CH",
    "sg:address":"Murtenstrasse 28",
    "sg:city":"Kerzers",
    "sg:orig_category":"RESTAURANTS: TEA-ROOMS",
    "sg:phone":"+41 62 726 18 12",
    "sg:postcode":"3210",
    "sg:province":"Fribourg",
    "wof:name":"Restaurant Resi Brunner Daniel",
    "wof:placetype":"venue"
},
  "geometry": {"coordinates":[8.1049308777,47.2695007324],"type":"Point"}
}