{
  "type": "Feature",
  "properties": {
    "iso:country":"CH",
    "sg:address":"Baarerstrasse 94",
    "sg:city":"Zug",
    "sg:orig_category":"Sonstige mit der Informatik verbundene T\u00e4tigkeiten",
    "sg:phone":"+41 32 710 00 65",
    "sg:postcode":"6300",
    "sg:province":"Zug",
    "wof:name":"Peb Informatique Sa",
    "wof:placetype":"venue"
},
  "geometry": {"coordinates":[6.9309201241,46.9920082092],"type":"Point"}
}