{
  "type": "Feature",
  "properties": {
    "iso:country":"CH",
    "sg:address":"Sorengo Via 24",
    "sg:city":"Lugano",
    "sg:orig_category":"Sonstiger Fachdetailhandel mit Nahrungsmitteln, Getr\u00e4nken U Tabak in Verkaufsr\u00e4umen",
    "sg:postcode":"6900",
    "sg:province":"Ticino",
    "wof:name":"Mefro Sagl",
    "wof:placetype":"venue"
},
  "geometry": {"coordinates":[8.9412050247,46.0029945374],"type":"Point"}
}