{
  "type": "Feature",
  "properties": {
    "iso:country":"CH",
    "sg:address":"Allmendstrasse 7 5612 Villmergen. Postfach 65",
    "sg:city":"Villmergen",
    "sg:orig_category":"Herstellung von elektrischen Haushaltsger\u00e4ten Herstellung von k\u00e4lte U lufttechnischen Erzeugnissen f",
    "sg:phone":"+41 56 618 78 78",
    "sg:postcode":"5612",
    "sg:province":"Aargau",
    "wof:name":"Bertschinger Max Ag",
    "wof:placetype":"venue"
},
  "geometry": {"coordinates":[8.249786377,47.3558349609],"type":"Point"}
}