{
  "type": "Feature",
  "properties": {
    "iso:country":"CH",
    "sg:address":"Milchstrasse",
    "sg:city":"Seewen",
    "sg:classifiers":[
        {
            "category":"Food & Beverages",
            "subcategory":"Cheese",
            "type":"Retail Goods"
        }
    ],
    "sg:phone":"+41 41 819 82 82",
    "sg:postcode":"6423",
    "sg:province":"Schwyz",
    "wof:name":"Schauk\u00e4serei Schwyzerland",
    "wof:placetype":"venue"
},
  "geometry": {"coordinates":[8.630994,47.027496],"type":"Point"}
}