{
  "type": "Feature",
  "properties": {
    "iso:country":"CH",
    "sg:address":"Weiherstrasse 11",
    "sg:city":"Wallisellen",
    "sg:orig_category":"Wirtschaftspr\u00fcfung, Steuerberatung U Treuhand",
    "sg:phone":"+41 18312891",
    "sg:postcode":"8304",
    "sg:province":"Z\u00fcrich",
    "wof:name":"Fize Treuhand Gmbh",
    "wof:placetype":"venue"
},
  "geometry": {"coordinates":[8.5972738266,47.4176445007],"type":"Point"}
}