{
  "type": "Feature",
  "properties": {
    "iso:country":"CH",
    "sg:address":"Via Montalbano",
    "sg:city":"Gentilino",
    "sg:orig_category":"Grosshandel mit sonstigen Maschinen U Ausr\u00fcstungen f\u00fcr Industrie, Handel U Schiffahrt Herstellung vo",
    "sg:phone":"+41 91 940 62 52",
    "sg:postcode":"6925",
    "sg:province":"Ticino",
    "wof:name":"Esatroll Sa Automazione Industriale",
    "wof:placetype":"venue"
},
  "geometry": {"coordinates":[8.9373817444,45.9923591614],"type":"Point"}
}