{
  "type": "Feature",
  "properties": {
    "iso:country":"CH",
    "sg:address":"Route De Courgenay 46",
    "sg:city":"Alle",
    "sg:orig_category":"G\u00fcterbef\u00f6rderung im Strassenverkehr",
    "sg:phone":"+41 32 471 13 46",
    "sg:postcode":"2942",
    "sg:province":"Jura",
    "wof:name":"Philippe Meusy Transports",
    "wof:placetype":"venue"
},
  "geometry": {"coordinates":[7.1237688065,47.4218139648],"type":"Point"}
}