{
  "type": "Feature",
  "properties": {
    "iso:country":"CH",
    "sg:address":"M\u00fcnchhaldenstrasse 10 8008 Z\u00fcrich. Postfach 919",
    "sg:city":"Z\u00fcrich",
    "sg:orig_category":"Vermietung U Verpachtung von eigenen Immobilien Vermittlung von Immobilien",
    "sg:phone":"+41 71 911 22 11",
    "sg:postcode":"8034",
    "sg:province":"Z\u00fcrich",
    "wof:name":"Atlantis Immobilien Ag",
    "wof:placetype":"venue"
},
  "geometry": {"coordinates":[9.0328617096,47.4650878906],"type":"Point"}
}