{
  "type": "Feature",
  "properties": {
    "iso:country":"CH",
    "sg:address":"Bergstrasse 14",
    "sg:city":"Kriens",
    "sg:orig_category":"RESTAURANTS: TEA-ROOMS",
    "sg:postcode":"6010",
    "sg:province":"Luzern",
    "wof:name":"Waresta Ag",
    "wof:placetype":"venue"
},
  "geometry": {"coordinates":[8.2822303772,47.038230896],"type":"Point"}
}