{
  "type": "Feature",
  "properties": {
    "iso:country":"CH",
    "sg:address":"Br\u00fcgglisacherweg 11",
    "sg:city":"Worben",
    "sg:orig_category":"Non-Classified Establishments",
    "sg:postcode":"3252",
    "sg:province":"Bern",
    "wof:name":"K\u00fcenzi Transport",
    "wof:placetype":"venue"
},
  "geometry": {"coordinates":[7.2983551025,47.1042747498],"type":"Point"}
}