{
  "type": "Feature",
  "properties": {
    "addr:full":"Krieggasse 18 Oberburg Bern 3414",
    "addr:housenumber":"18",
    "addr:postcode":"3414",
    "addr:street":"Krieggasse",
    "iso:country":"CH",
    "sg:address":"Krieggasse 18",
    "sg:city":"Oberburg",
    "sg:orig_category":"Detailhandel mit Blumen U Pflanzen Gartenbau",
    "sg:phone":"+41 41 930 27 44",
    "sg:postcode":"3414",
    "sg:province":"Bern",
    "wof:name":"M. & M. Koch Gartenbau Gmbh",
    "wof:placetype":"venue"
},
  "geometry": {"coordinates":[8.157928,47.222466],"type":"Point"}
}