{
  "type": "Feature",
  "properties": {
    "iso:country":"CH",
    "sg:address":"Route De Florissant 51",
    "sg:city":"Gen\u00e8ve",
    "sg:orig_category":"Detailhandel mit Tabakwaren Grosshandel mit Getreide, Saatgut U Futtermitteln",
    "sg:phone":"+41 22 347 90 11",
    "sg:postcode":"1206",
    "sg:province":"Gen\u00e8ve",
    "wof:name":"Aedicula Sa",
    "wof:placetype":"venue"
},
  "geometry": {"coordinates":[6.1602568626,46.1942138672],"type":"Point"}
}