{
  "type": "Feature",
  "properties": {
    "iso:country":"CH",
    "sg:address":"Vieux-bourg",
    "sg:city":"Saillon",
    "sg:orig_category":"Non-Classified Establishments",
    "sg:phone":"+41 41 418 71 11",
    "sg:postcode":"1913",
    "sg:province":"Valais",
    "wof:name":"Ahorn Holding Sa",
    "wof:placetype":"venue"
},
  "geometry": {"coordinates":[7.185005188,46.1667404175],"type":"Point"}
}