{
  "type": "Feature",
  "properties": {
    "iso:country":"CH",
    "sg:address":"Centro L'uovo Di Manno",
    "sg:city":"Manno",
    "sg:orig_category":"Sonstige mit der Informatik verbundene T\u00e4tigkeiten",
    "sg:postcode":"6928",
    "sg:province":"Ticino",
    "wof:name":"Norman Consulting Sagl Consulenza E Programmazione Nel Settore Informatico Ecc",
    "wof:placetype":"venue"
},
  "geometry": {"coordinates":[8.9691734314,45.9125137329],"type":"Point"}
}