{
  "type": "Feature",
  "properties": {
    "iso:country":"CH",
    "sg:address":"Bodenh\u00fcsli",
    "sg:city":"Heimisbach",
    "sg:orig_category":"Erdbewegungsarbeiten",
    "sg:phone":"+41 34 431 26 20",
    "sg:postcode":"3453",
    "sg:province":"Bern",
    "wof:name":"Andreas Kramer Baggerbetrieb",
    "wof:placetype":"venue"
},
  "geometry": {"coordinates":[7.7603111267,47.011756897],"type":"Point"}
}