{
  "type": "Feature",
  "properties": {
    "iso:country":"CH",
    "sg:address":"Bullingerstrasse 45 8004 Z\u00fcrich. Postfach",
    "sg:city":"Z\u00fcrich",
    "sg:orig_category":"Sonstige pers\u00f6nliche Dienstleistungen",
    "sg:phone":"+41 14915279",
    "sg:postcode":"8004",
    "sg:province":"Z\u00fcrich",
    "wof:name":"Love For Life Gmbh",
    "wof:placetype":"venue"
},
  "geometry": {"coordinates":[8.5107755661,47.3804397583],"type":"Point"}
}