{
  "type": "Feature",
  "properties": {
    "iso:country":"CH",
    "sg:address":"Badenerstrasse 27",
    "sg:city":"Dietikon",
    "sg:orig_category":"Detailhandel Reparatur von Gebrauchsg\u00fctern Vermietung von Gebrauchsg\u00fctern",
    "sg:phone":"+41 17742921",
    "sg:postcode":"8953",
    "sg:province":"Z\u00fcrich",
    "wof:name":"Joe's Multimedia Ag",
    "wof:placetype":"venue"
},
  "geometry": {"coordinates":[8.3968276978,47.4063072205],"type":"Point"}
}