{
  "type": "Feature",
  "properties": {
    "iso:country":"CH",
    "sg:address":"Avenue De La Gare 2",
    "sg:city":"Lausanne",
    "sg:orig_category":"Detailhandel mit Textilien Sonstiges Textilgewerbe",
    "sg:phone":"+41 21 323 28 47",
    "sg:postcode":"1003",
    "sg:province":"Vaud",
    "wof:name":"Georgette Sa",
    "wof:placetype":"venue"
},
  "geometry": {"coordinates":[6.6373372078,46.5169372559],"type":"Point"}
}