{
  "type": "Feature",
  "properties": {
    "iso:country":"CH",
    "sg:address":"Rue Pierre-p\u00e9quignat 34",
    "sg:city":"Porrentruy",
    "sg:orig_category":"Detailhandel mit Bekleidung Detailhandel mit Damenbekleidung",
    "sg:phone":"+41 32 466 33 03",
    "sg:postcode":"2900",
    "sg:province":"Jura",
    "wof:name":"Boutique B\u00e9atrice, Beuret Mmes - Willemin Et Lachat - Willemin",
    "wof:placetype":"venue"
},
  "geometry": {"coordinates":[7.07399,47.41787],"type":"Point"}
}