{
  "type": "Feature",
  "properties": {
    "iso:country":"CH",
    "sg:address":"Daettikonerstr. 5",
    "sg:city":"Pfungen",
    "sg:classifiers":[
        {
            "category":"Professional",
            "subcategory":"Engineering",
            "type":"Services"
        }
    ],
    "sg:phone":"+41 52 315 25 25",
    "sg:postcode":"8422",
    "sg:province":"Z\u00fcrich",
    "sg:tags":[
        "machine",
        "-",
        "mechanical"
    ],
    "wof:name":"Prang + Partner Ag",
    "wof:placetype":"venue"
},
  "geometry": {"coordinates":[8.64220047,47.5163269043],"type":"Point"}
}