{
  "type": "Feature",
  "properties": {
    "iso:country":"CH",
    "sg:address":"Arsenalstrasse 11",
    "sg:city":"Kriens",
    "sg:orig_category":"Fotografische Ateliers Fotografisches Gewerbe U fotografische Laboratorien",
    "sg:phone":"+41 41 874 16 99",
    "sg:postcode":"6010",
    "sg:province":"Luzern",
    "wof:name":"Baumann + Fryberg",
    "wof:placetype":"venue"
},
  "geometry": {"coordinates":[8.6399059296,46.8789253235],"type":"Point"}
}