{
  "type": "Feature",
  "properties": {
    "addr:full":"Felslenaustrasse 25 7000 Chur. Postfach Chur Graubunden 7000",
    "addr:housenumber":"25",
    "addr:postcode":"7000;postfach;7000",
    "addr:street":"Felslenaustrasse",
    "iso:country":"CH",
    "sg:address":"Felslenaustrasse 25 7000 Chur. Postfach",
    "sg:city":"Chur",
    "sg:orig_category":"Allgemeiner Hoch U Tiefbau",
    "sg:postcode":"7000",
    "sg:province":"Graubunden",
    "wof:name":"Zschokke Bau Ag",
    "wof:placetype":"venue"
},
  "geometry": {"coordinates":[9.531171,46.850197],"type":"Point"}
}