{
  "type": "Feature",
  "properties": {
    "iso:country":"CH",
    "sg:address":"Casino Avenue Du 45",
    "sg:city":"Montreux",
    "sg:orig_category":"Architektur U Ingenieurb\u00fcros Geometerb\u00fcros",
    "sg:phone":"+41 24 445 40 27",
    "sg:postcode":"1820",
    "sg:province":"Vaud",
    "wof:name":"Barblan Reto",
    "wof:placetype":"venue"
},
  "geometry": {"coordinates":[6.645384,46.809299],"type":"Point"}
}