{
  "type": "Feature",
  "properties": {
    "iso:country":"CH",
    "sg:address":"Route De Pfaffenwil 10",
    "sg:city":"Marly",
    "sg:orig_category":"Unternehmensberatung Wirtschaftspr\u00fcfung, Steuerberatung U Treuhand",
    "sg:phone":"+41 26 439 92 26",
    "sg:postcode":"1723",
    "sg:province":"Fribourg",
    "wof:name":"Revigest Sa",
    "wof:placetype":"venue"
},
  "geometry": {"coordinates":[7.168241024,46.7748603821],"type":"Point"}
}