{
  "type": "Feature",
  "properties": {
    "iso:country":"CH",
    "sg:address":"Grand-rue",
    "sg:city":"Concise",
    "sg:classifiers":[
        {
            "category":"Restaurant",
            "type":"Food & Drink"
        }
    ],
    "sg:phone":"+41 24 434 11 87",
    "sg:postcode":"1426",
    "sg:province":"Vaud",
    "wof:name":"Caf\u00e9 De L' Union",
    "wof:placetype":"venue"
},
  "geometry": {"coordinates":[6.7194290161,46.851108551],"type":"Point"}
}