{
  "type": "Feature",
  "properties": {
    "iso:country":"CH",
    "sg:address":"3232 Ins. Postfach",
    "sg:city":"Ins",
    "sg:classifiers":[
        {
            "category":"Travel",
            "subcategory":"Hotels & Motels",
            "type":"Entertainment"
        }
    ],
    "sg:phone":"+41 32 313 21 02",
    "sg:postcode":"3232",
    "sg:province":"Bern",
    "sg:tags":[
        "hotels",
        "mit",
        "restaurant"
    ],
    "wof:name":"Walther R.",
    "wof:placetype":"venue"
},
  "geometry": {"coordinates":[7.1058449745,47.0058517456],"type":"Point"}
}