{
  "type": "Feature",
  "properties": {
    "iso:country":"CH",
    "sg:address":"R\u00fctistrasse 3a 5400 Baden. Postfach",
    "sg:city":"Baden",
    "sg:orig_category":"Verlagsgewerbe",
    "sg:phone":"+41 21 944 67 30",
    "sg:postcode":"5401",
    "sg:province":"Aargau",
    "wof:name":"Weltrundschau Verlag Ag Revue Mondiale",
    "wof:placetype":"venue"
},
  "geometry": {"coordinates":[6.8640780449,46.452003479],"type":"Point"}
}