{
  "type": "Feature",
  "properties": {
    "iso:country":"CH",
    "sg:address":"Via Cantonale",
    "sg:city":"Grono",
    "sg:orig_category":"Grosshandel mit Datenverarbeitungsger\u00e4ten Hardwareberatung",
    "sg:phone":"+41 91 827 34 33",
    "sg:postcode":"6537",
    "sg:province":"Graubunden",
    "wof:name":"Clemcad Sa",
    "wof:placetype":"venue"
},
  "geometry": {"coordinates":[9.1564559937,46.2529716492],"type":"Point"}
}