{
  "type": "Feature",
  "properties": {
    "iso:country":"CH",
    "sg:address":"Neuhofweg 4",
    "sg:city":"Binningen",
    "sg:orig_category":"Herstellung von medizinischen U chirurgischen Ger\u00e4ten",
    "sg:postcode":"4102",
    "sg:province":"Basel-Landschaft",
    "wof:name":"Bj\u00f6rn Wieslander Medical Research Wieslander",
    "wof:placetype":"venue"
},
  "geometry": {"coordinates":[7.5614418983,47.5365333557],"type":"Point"}
}