{
  "type": "Feature",
  "properties": {
    "iso:country":"CH",
    "sg:address":"Bahnhofstrasse 53 2500 Biel/bienne. Postfach",
    "sg:city":"Biel/bienne",
    "sg:orig_category":"Detailhandel mit Brot, Back U S\u00fcsswaren",
    "sg:phone":"+41 32 322 53 88",
    "sg:postcode":"2502",
    "sg:province":"Bern",
    "wof:name":"B\u00e4ckerei Meyer",
    "wof:placetype":"venue"
},
  "geometry": {"coordinates":[7.282683,47.123737],"type":"Point"}
}