{
  "type": "Feature",
  "properties": {
    "iso:country":"CH",
    "sg:address":"Schmiedegasse 12a",
    "sg:city":"B\u00e4tterkinden",
    "sg:orig_category":"Detailhandel mit Brot, Back U S\u00fcsswaren Detailhandel mit Waren verschiedener Art, Hauptrichtung Nahr",
    "sg:phone":"+41 75 373 13 44",
    "sg:postcode":"3315",
    "sg:province":"Bern",
    "wof:name":"M\u00fcndle Ag B\u00e4ckerei & Konditorei",
    "wof:placetype":"venue"
},
  "geometry": {"coordinates":[9.54208,47.2174],"type":"Point"}
}