{
  "type": "Feature",
  "properties": {
    "iso:country":"CH",
    "sg:address":"Fierzgasse 16",
    "sg:city":"Z\u00fcrich",
    "sg:orig_category":"Unclassifiable Establishments",
    "sg:postcode":"8005",
    "sg:province":"Z\u00fcrich",
    "wof:name":"Maler Steinauer Gmbh",
    "wof:placetype":"venue"
},
  "geometry": {"coordinates":[8.6474714279,47.4087524414],"type":"Point"}
}