{
  "type": "Feature",
  "properties": {
    "iso:country":"CH",
    "sg:address":"Rheinweg 4",
    "sg:city":"Neuhausen",
    "sg:orig_category":"Unclassifiable Establishments",
    "sg:phone":"+41 52 625 44 54",
    "sg:postcode":"8212",
    "sg:province":"Schaffhausen",
    "wof:name":"Witzig Ernst Ag",
    "wof:placetype":"venue"
},
  "geometry": {"coordinates":[8.6231718063,47.6922645569],"type":"Point"}
}