{
  "type": "Feature",
  "properties": {
    "iso:country":"CH",
    "sg:address":"Pulverm\u00fchlestrasse 20",
    "sg:city":"Chur",
    "sg:orig_category":"Herstellung von Hohlglas",
    "sg:postcode":"7000",
    "sg:province":"Graubunden",
    "wof:name":"Muja Glass Design, Niederklopfer Florian",
    "wof:placetype":"venue"
},
  "geometry": {"coordinates":[9.5166130066,46.8526725769],"type":"Point"}
}