{
  "type": "Feature",
  "properties": {
    "iso:country":"CH",
    "sg:address":"6814",
    "sg:city":"Lamone",
    "sg:orig_category":"Instandhaltung U Reparatur von Automobilen",
    "sg:phone":"+41 81 413 61 44",
    "sg:postcode":"6814",
    "sg:province":"Ticino",
    "wof:name":"Allcar's M. Pedrazzini",
    "wof:placetype":"venue"
},
  "geometry": {"coordinates":[9.8323297501,46.7963294983],"type":"Point"}
}