{
  "type": "Feature",
  "properties": {
    "iso:country":"CH",
    "sg:address":"Schillerstrasse 22",
    "sg:city":"Basel",
    "sg:orig_category":"Herstellung von Werkzeugmaschinen",
    "sg:postcode":"4053",
    "sg:province":"Basel-Stadt",
    "wof:name":"Herzig, Fr\u00e4sen Und Bohren",
    "wof:placetype":"venue"
},
  "geometry": {"coordinates":[7.5961389542,47.5434532166],"type":"Point"}
}