{
  "type": "Feature",
  "properties": {
    "iso:country":"CH",
    "sg:address":"Rue De Month\u00e9olo 30",
    "sg:city":"Monthey",
    "sg:orig_category":"Non-Classified Establishments",
    "sg:postcode":"1870",
    "sg:province":"Valais",
    "wof:name":"Alain Burri - Consulting",
    "wof:placetype":"venue"
},
  "geometry": {"coordinates":[6.579390049,46.5390815735],"type":"Point"}
}