{
  "type": "Feature",
  "properties": {
    "iso:country":"CH",
    "sg:address":"Moscia Via 4",
    "sg:city":"Ascona",
    "sg:orig_category":"Non-Classified Establishments",
    "sg:postcode":"6612",
    "sg:province":"Ticino",
    "wof:name":"Ristorante Cinese Lungolago Sagl",
    "wof:placetype":"venue"
},
  "geometry": {"coordinates":[8.7660560608,46.1547622681],"type":"Point"}
}