{
  "type": "Feature",
  "properties": {
    "iso:country":"CH",
    "sg:address":"Grand-rue 11",
    "sg:city":"Echallens",
    "sg:orig_category":"Detailhandel mit Sportartikeln",
    "sg:phone":"+41 21 881 44 81",
    "sg:postcode":"1040",
    "sg:province":"Vaud",
    "wof:name":"Sport-time Magasin Articles Sports",
    "wof:placetype":"venue"
},
  "geometry": {"coordinates":[6.6335201263,46.641292572],"type":"Point"}
}