{
  "type": "Feature",
  "properties": {
    "iso:country":"CH",
    "sg:address":"Gotthardstrasse 217",
    "sg:city":"Silenen",
    "sg:orig_category":"Gemeindeverwaltungen",
    "sg:phone":"+41 41 883 11 33",
    "sg:postcode":"6473",
    "sg:province":"Uri",
    "wof:name":"Gemeindeverwaltung Silenen",
    "wof:placetype":"venue"
},
  "geometry": {"coordinates":[8.6702814102,46.7828521729],"type":"Point"}
}