{
  "type": "Feature",
  "properties": {
    "iso:country":"CH",
    "sg:address":"Aarbergstrasse 46 2503 Biel/bienne. Postfach",
    "sg:city":"Biel/bienne",
    "sg:orig_category":"Wirtschaftsverb\u00e4nde Industrie, Handel and Gewerbe",
    "sg:phone":"+41 32 322 35 44",
    "sg:postcode":"2501",
    "sg:province":"Bern",
    "wof:name":"Baumeisterverband Biel",
    "wof:placetype":"venue"
},
  "geometry": {"coordinates":[7.2403278351,47.129901886],"type":"Point"}
}