{
  "type": "Feature",
  "properties": {
    "iso:country":"CH",
    "sg:address":"Schaffhauserstrasse 22",
    "sg:city":"Seuzach",
    "sg:orig_category":"Detailhandel mit elektrischen Haushalts, Radio U Fernsehger\u00e4ten ohne ausgepr\u00e4gten Schwerpunkt Elektr",
    "sg:phone":"+41 52 335 09 56",
    "sg:postcode":"8472",
    "sg:province":"Z\u00fcrich",
    "wof:name":"Satshop Gmbh",
    "wof:placetype":"venue"
},
  "geometry": {"coordinates":[8.7151203156,47.5247421265],"type":"Point"}
}