{
  "type": "Feature",
  "properties": {
    "iso:country":"CH",
    "sg:address":"Route De Cov\u00e9ry 24 1252 Meinier. Postfach",
    "sg:city":"Meinier",
    "sg:orig_category":"Sonstige mit der Informatik verbundene T\u00e4tigkeiten",
    "sg:phone":"+41 61 711 32 43",
    "sg:postcode":"1252",
    "sg:province":"Gen\u00e8ve",
    "wof:name":"Silberschneider H. Gmbh, It-consulting",
    "wof:placetype":"venue"
},
  "geometry": {"coordinates":[7.5826768875,47.492855072],"type":"Point"}
}