{
  "type": "Feature",
  "properties": {
    "iso:country":"CH",
    "sg:address":"Hohengasse 12 3400 Burgdorf. Postfach",
    "sg:city":"Burgdorf",
    "sg:orig_category":"RESTAURANTS: TEA-ROOMS",
    "sg:phone":"+41 34 422 81 27",
    "sg:postcode":"3400",
    "sg:province":"Bern",
    "wof:name":"Marianne Fluri",
    "wof:placetype":"venue"
},
  "geometry": {"coordinates":[7.6267309189,47.0559234619],"type":"Point"}
}