{
  "type": "Feature",
  "properties": {
    "iso:country":"CH",
    "sg:address":"Weihermattstrasse 2",
    "sg:city":"Mellingen",
    "sg:orig_category":"Softwareentwicklung U beratung",
    "sg:phone":"+41 56 491 00 60",
    "sg:postcode":"5507",
    "sg:province":"Aargau",
    "wof:name":"Beat Imbach Software Engineering",
    "wof:placetype":"venue"
},
  "geometry": {"coordinates":[8.2713003159,47.4193611145],"type":"Point"}
}