{
  "type": "Feature",
  "properties": {
    "iso:country":"CH",
    "sg:address":"De-normandie Chemin 4 1206 Gen\u00e8ve. Postfach",
    "sg:city":"Gen\u00e8ve",
    "sg:orig_category":"Fachdetailhandel mit pharmazeutischen Produkten",
    "sg:postcode":"1206",
    "sg:province":"Gen\u00e8ve",
    "wof:name":"Promogestion Sarl",
    "wof:placetype":"venue"
},
  "geometry": {"coordinates":[6.1625847816,46.1904411316],"type":"Point"}
}