{
  "type": "Feature",
  "properties": {
    "iso:country":"CH",
    "sg:address":"Kirchbergstrasse 19 3400 Burgdorf. Postfach 780",
    "sg:city":"Burgdorf",
    "sg:orig_category":"Sonstiger Grosshandel Weberei",
    "sg:phone":"+41 34 445 27 13",
    "sg:postcode":"3401",
    "sg:province":"Bern",
    "wof:name":"Schl\u00e4fli Handels Ag",
    "wof:placetype":"venue"
},
  "geometry": {"coordinates":[7.6206297874,47.061958313],"type":"Point"}
}