{
  "type": "Feature",
  "properties": {
    "iso:country":"CH",
    "sg:address":"Waldeggstrasse 17 8810 Horgen. Postfach",
    "sg:city":"Horgen",
    "sg:orig_category":"Instandhaltung U Reparatur von Automobilen",
    "sg:phone":"+41 21 691 84 25",
    "sg:postcode":"8812",
    "sg:province":"Z\u00fcrich",
    "wof:name":"Bussy Bernard",
    "wof:placetype":"venue"
},
  "geometry": {"coordinates":[6.5609869957,46.5255203247],"type":"Point"}
}