{
  "type": "Feature",
  "properties": {
    "iso:country":"CH",
    "sg:address":"St\u00e4pfetlistrasse 5 8606 N\u00e4nikon. Postfach",
    "sg:city":"N\u00e4nikon",
    "sg:orig_category":"Herstellung von Tanks U Sammelbeh\u00e4ltern aus Metall",
    "sg:postcode":"8606",
    "sg:province":"Z\u00fcrich",
    "wof:name":"Contrac Ag",
    "wof:placetype":"venue"
},
  "geometry": {"coordinates":[8.677529335,47.365234375],"type":"Point"}
}