{
  "type": "Feature",
  "properties": {
    "iso:country":"CH",
    "sg:address":"Chemin Du Parc 8",
    "sg:city":"Bussigny-lausanne",
    "sg:classifiers":[
        {
            "category":"Restaurant",
            "type":"Food & Drink"
        }
    ],
    "sg:phone":"+41 21 702 42 91",
    "sg:postcode":"1030",
    "sg:province":"Vaud",
    "wof:name":"Caf\u00e9 La Hutte",
    "wof:placetype":"venue"
},
  "geometry": {"coordinates":[6.5534148216,46.5494842529],"type":"Point"}
}