{
  "type": "Feature",
  "properties": {
    "iso:country":"CH",
    "sg:address":"Bertastrasse 99",
    "sg:city":"Z\u00fcrich",
    "sg:orig_category":"Arztpraxen",
    "sg:phone":"+41 14611844",
    "sg:postcode":"8003",
    "sg:province":"Z\u00fcrich",
    "wof:name":"Dr.med.martin David Arzt F.allgemeine Medizin Fmh",
    "wof:placetype":"venue"
},
  "geometry": {"coordinates":[8.51041,47.372101],"type":"Point"}
}