{
  "type": "Feature",
  "properties": {
    "iso:country":"CH",
    "sg:address":"Wilweg 1",
    "sg:city":"Root",
    "sg:orig_category":"Arztpraxen",
    "sg:phone":"+41 61 811 51 41",
    "sg:postcode":"6037",
    "sg:province":"Luzern",
    "wof:name":"Dr.med.josef V\u00f6gtli Arzt F.allgemeine Medizin Fmh",
    "wof:placetype":"venue"
},
  "geometry": {"coordinates":[7.707525,47.533062],"type":"Point"}
}