{
  "type": "Feature",
  "properties": {
    "iso:country":"CH",
    "sg:address":"Rue Saint-maurice 2",
    "sg:city":"Neuch\u00e2tel",
    "sg:orig_category":"Kinderkrippen U horte",
    "sg:postcode":"2000",
    "sg:province":"Neuch\u00e2tel",
    "wof:name":"Garderie D'enfants Le P'tit Sioux",
    "wof:placetype":"venue"
},
  "geometry": {"coordinates":[6.9307770729,46.991230011],"type":"Point"}
}