{
  "type": "Feature",
  "properties": {
    "iso:country":"CH",
    "sg:address":"Rellikonstrasse 7",
    "sg:city":"Maur",
    "sg:orig_category":"Satzherstellung U Reproduktion",
    "sg:phone":"+41 81 300 49 57",
    "sg:postcode":"8124",
    "sg:province":"Z\u00fcrich",
    "wof:name":"Digital Repro Atelier Gmbh",
    "wof:placetype":"venue"
},
  "geometry": {"coordinates":[9.5009698868,47.0145111084],"type":"Point"}
}