{
  "type": "Feature",
  "properties": {
    "iso:country":"CH",
    "sg:address":"Br\u00fcckenstrasse 29",
    "sg:city":"Binningen",
    "sg:orig_category":"Werbung",
    "sg:postcode":"4102",
    "sg:province":"Basel-Landschaft",
    "wof:name":"Hb Werbung & Promotion Gmbh",
    "wof:placetype":"venue"
},
  "geometry": {"coordinates":[8.2660856247,47.3506774902],"type":"Point"}
}