{
  "type": "Feature",
  "properties": {
    "iso:country":"CH",
    "sg:address":"Gummweg 99",
    "sg:city":"Steffisburg",
    "sg:orig_category":"G\u00fcterbef\u00f6rderung im Strassenverkehr",
    "sg:phone":"+41 79 449 09 40",
    "sg:postcode":"3612",
    "sg:province":"Bern",
    "wof:name":"Fr\u00e9ddy Imhof Transports",
    "wof:placetype":"venue"
},
  "geometry": {"coordinates":[6.8615231514,46.9855041504],"type":"Point"}
}