{
  "type": "Feature",
  "properties": {
    "iso:country":"CH",
    "sg:address":"Rolliweg 21",
    "sg:city":"Lengnau",
    "sg:classifiers":[
        {
            "category":"Wholesale",
            "subcategory":"Vending Machines",
            "type":"Manufacturing & Wholesale Goods"
        }
    ],
    "sg:phone":"+41 32 654 15 15",
    "sg:postcode":"2543",
    "sg:province":"Bern",
    "sg:tags":[
        "ceramic",
        "processing"
    ],
    "wof:name":"Microcut Ltd",
    "wof:placetype":"venue"
},
  "geometry": {"coordinates":[7.374379,47.178329],"type":"Point"}
}