{
  "type": "Feature",
  "properties": {
    "iso:country":"CH",
    "sg:address":"Stationsstrasse 1 8003 Z\u00fcrich. Postfach",
    "sg:city":"Z\u00fcrich",
    "sg:orig_category":"Vermittlung von Immobilien Verwaltung von Immobilien",
    "sg:phone":"+41 41 420 58 80",
    "sg:postcode":"8036",
    "sg:province":"Z\u00fcrich",
    "wof:name":"Pilatus-treuhand Ag",
    "wof:placetype":"venue"
},
  "geometry": {"coordinates":[8.3122806549,47.0575027466],"type":"Point"}
}