{
  "type": "Feature",
  "properties": {
    "iso:country":"CH",
    "sg:address":"Wangenstrasse 8",
    "sg:city":"Deitingen",
    "sg:orig_category":"Detailhandel mit Blumen U Pflanzen Gartenbau",
    "sg:phone":"+41 32 614 20 13",
    "sg:postcode":"4543",
    "sg:province":"Solothurn",
    "wof:name":"Scheuermeyer Ambisign Floristik",
    "wof:placetype":"venue"
},
  "geometry": {"coordinates":[7.620395,47.21262],"type":"Point"}
}