{
  "type": "Feature",
  "properties": {
    "iso:country":"CH",
    "sg:address":"Singenbergstrasse 8",
    "sg:city":"St.gallen",
    "sg:orig_category":"Detailhandel mit Waren verschiedener Art, Hauptrichtung Nahrungsmittel Detailhandel mit elektrischen",
    "sg:phone":"+41 24 491 21 51",
    "sg:postcode":"9000",
    "sg:province":"St. Gallen",
    "wof:name":"Roulin Ernest",
    "wof:placetype":"venue"
},
  "geometry": {"coordinates":[7.0534849167,46.3616447449],"type":"Point"}
}