{
  "type": "Feature",
  "properties": {
    "addr:full":"Heiligholzstr. 8 M\u00fcnchenstein Basel-Landschaft 4142",
    "addr:housenumber":"8",
    "addr:postcode":"4142",
    "addr:street":"Heiligholzstr.",
    "iso:country":"CH",
    "sg:address":"Heiligholzstr. 8",
    "sg:city":"M\u00fcnchenstein",
    "sg:classifiers":[
        {
            "category":"Bakery",
            "type":"Food & Drink"
        }
    ],
    "sg:phone":"+41 61 411 41 13",
    "sg:postcode":"4142",
    "sg:province":"Basel-Landschaft",
    "sg:tags":[
        "cake",
        "product",
        "related",
        "bread"
    ],
    "wof:name":"B\u00c4ckerei Gyger Ag",
    "wof:placetype":"venue"
},
  "geometry": {"coordinates":[7.615188,47.513283],"type":"Point"}
}