{
  "type": "Feature",
  "properties": {
    "iso:country":"CH",
    "sg:address":"Sur Le Cr\u00eat 2720 Tramelan Case Postale 41",
    "sg:city":"Tramelan",
    "sg:orig_category":"Herstellung von Schrauben, Nieten, Ketten U Federn Herstellung von Uhren",
    "sg:phone":"+41 32 487 50 25",
    "sg:postcode":"2720",
    "sg:province":"Bern",
    "wof:name":"Jean-pierre Cl\u00e9ment & Cie Sa",
    "wof:placetype":"venue"
},
  "geometry": {"coordinates":[7.1003022194,47.2231445312],"type":"Point"}
}