{
  "type": "Feature",
  "properties": {
    "iso:country":"CH",
    "sg:address":"Moosweg 30",
    "sg:city":"Gwatt",
    "sg:classifiers":[
        {
            "category":"Manufacturing",
            "subcategory":"Motor Vehicles & Parts",
            "type":"Manufacturing & Wholesale Goods"
        }
    ],
    "sg:phone":"+41 33 336 69 90",
    "sg:postcode":"3645",
    "sg:province":"Bern",
    "sg:tags":[
        "spare",
        "trailer",
        "accessory"
    ],
    "wof:name":"Bruno Rubi Anh\u00e4nger",
    "wof:placetype":"venue"
},
  "geometry": {"coordinates":[7.6168642044,46.7241706848],"type":"Point"}
}