{
  "type": "Feature",
  "properties": {
    "iso:country":"CH",
    "sg:address":"Bodackerstrasse 14",
    "sg:city":"Dietikon",
    "sg:orig_category":"Grosshandel mit Baumaschinen Herstellung von Bergwerks U Baumaschinen",
    "sg:phone":"+41 22 736 47 04",
    "sg:postcode":"8953",
    "sg:province":"Z\u00fcrich",
    "wof:name":"Constructil Sa",
    "wof:placetype":"venue"
},
  "geometry": {"coordinates":[8.3863143921,47.4123382568],"type":"Point"}
}