{
  "type": "Feature",
  "properties": {
    "iso:country":"CH",
    "sg:address":"Postgasse 5 9620 Lichtensteig. Postfach",
    "sg:city":"Lichtensteig",
    "sg:orig_category":"Herstellung von k\u00e4lte U lufttechnischen Erzeugnissen f\u00fcr gewerbliche Zwecke",
    "sg:postcode":"9620",
    "sg:province":"St. Gallen",
    "wof:name":"Thermolux-werk Ag",
    "wof:placetype":"venue"
},
  "geometry": {"coordinates":[9.0881519318,47.3243408203],"type":"Point"}
}