{
  "type": "Feature",
  "properties": {
    "iso:country":"CH",
    "sg:address":"Steinackerstrasse 4",
    "sg:city":"Kloten",
    "sg:orig_category":"Detailhandel mit Getr\u00e4nken Grosshandel mit Getr\u00e4nken",
    "sg:phone":"+41 18135566",
    "sg:postcode":"8302",
    "sg:province":"Z\u00fcrich",
    "wof:name":"Wych\u00e4ller Chloote Ag",
    "wof:placetype":"venue"
},
  "geometry": {"coordinates":[8.5936565399,47.4499511719],"type":"Point"}
}