{
  "type": "Feature",
  "properties": {
    "iso:country":"CH",
    "sg:address":"Sainas",
    "sg:city":"Ftan",
    "sg:orig_category":"Herstellung von Tanks U Sammelbeh\u00e4ltern aus Metall Reinigungsgewerbe",
    "sg:phone":"+41 81 756 40 46",
    "sg:postcode":"7551",
    "sg:province":"Graubunden",
    "wof:name":"R\u00fctak Ag, Buchs Sg.",
    "wof:placetype":"venue"
},
  "geometry": {"coordinates":[9.4829397202,47.1730003357],"type":"Point"}
}