{
  "type": "Feature",
  "properties": {
    "iso:country":"CH",
    "sg:address":"Wildbrunnstrasse 2",
    "sg:city":"Kaltbrunn",
    "sg:orig_category":"Handel mit Motorr\u00e4dern, Teilen U Zubeh\u00f6r Herstellung von sonstigen elektrischen Ausr\u00fcstungen Instand",
    "sg:phone":"+41 55 283 01 76",
    "sg:postcode":"8722",
    "sg:province":"St. Gallen",
    "wof:name":"Noro & H\u00fcrlimann",
    "wof:placetype":"venue"
},
  "geometry": {"coordinates":[9.0088043213,47.2171287537],"type":"Point"}
}