{
  "type": "Feature",
  "properties": {
    "iso:country":"CH",
    "sg:address":"Grand'rue 1a",
    "sg:city":"Couvet",
    "sg:orig_category":"Detailhandel mit Blumen U Pflanzen",
    "sg:phone":"+41 32 863 19 41",
    "sg:postcode":"2108",
    "sg:province":"Neuch\u00e2tel",
    "wof:name":"N'belles Fleurs",
    "wof:placetype":"venue"
},
  "geometry": {"coordinates":[6.630678,46.926178],"type":"Point"}
}