{
  "type": "Feature",
  "properties": {
    "iso:country":"CH",
    "sg:address":"Rue Montolieu 9",
    "sg:city":"Bussigny-lausanne",
    "sg:orig_category":"Haltung von Rindern",
    "sg:postcode":"1030",
    "sg:province":"Vaud",
    "wof:name":"Syndicat D'\u00e9levage De B\u00e9tail Bovin",
    "wof:placetype":"venue"
},
  "geometry": {"coordinates":[6.5557308197,46.5532264709],"type":"Point"}
}