{
  "type": "Feature",
  "properties": {
    "iso:country":"CH",
    "sg:address":"Flurweg 9 5040 Sch\u00f6ftland. Postfach",
    "sg:city":"Sch\u00f6ftland",
    "sg:orig_category":"Sonstiger Grosshandel",
    "sg:phone":"+41 62 721 56 66",
    "sg:postcode":"5040",
    "sg:province":"Aargau",
    "wof:name":"Promo Concept Strebel J\u00fcrg Warenhandel. Vermittlung Und Beratung Im Finanz Und Edv-bereich Usw",
    "wof:placetype":"venue"
},
  "geometry": {"coordinates":[8.0511198044,47.3126144409],"type":"Point"}
}