{
  "type": "Feature",
  "properties": {
    "iso:country":"CH",
    "sg:address":"Eichengasse 2",
    "sg:city":"H\u00fcnenberg",
    "sg:orig_category":"Erwachsenenbildung U Unterricht",
    "sg:phone":"+41 41 781 11 66",
    "sg:postcode":"6331",
    "sg:province":"Zug",
    "wof:name":"F & A F\u00fchrung & Absatz Ag",
    "wof:placetype":"venue"
},
  "geometry": {"coordinates":[8.4267120361,47.1754417419],"type":"Point"}
}