{
  "type": "Feature",
  "properties": {
    "iso:country":"CH",
    "sg:address":"Bachstrasse 40",
    "sg:city":"Lenzburg",
    "sg:classifiers":[
        {
            "category":"Professional",
            "subcategory":"Advertising",
            "type":"Services"
        }
    ],
    "sg:phone":"+41 62 892 93 44",
    "sg:postcode":"5600",
    "sg:province":"Aargau",
    "sg:tags":[
        "agency"
    ],
    "wof:name":"Matthias Rennhard Kommunikation",
    "wof:placetype":"venue"
},
  "geometry": {"coordinates":[8.176245,47.385113],"type":"Point"}
}