{
  "type": "Feature",
  "properties": {
    "iso:country":"CH",
    "sg:address":"Bollwerk 15 3011 Bern. Postfach",
    "sg:city":"Bern",
    "sg:orig_category":"Versicherungen Generalagenturen",
    "sg:phone":"+41 31 311 10 67",
    "sg:postcode":"3001",
    "sg:province":"Bern",
    "wof:name":"Genfer Versicherungen Gesch\u00e4ftsstelle Bern",
    "wof:placetype":"venue"
},
  "geometry": {"coordinates":[7.4406290054,46.9495391846],"type":"Point"}
}