{
  "type": "Feature",
  "properties": {
    "iso:country":"CH",
    "sg:address":"Bahnhofstrasse 21",
    "sg:city":"R\u00fcmlang",
    "sg:orig_category":"Gartenbau",
    "sg:phone":"+41 18170371",
    "sg:postcode":"8153",
    "sg:province":"Z\u00fcrich",
    "wof:name":"Hans Baumgartner Gartenbau",
    "wof:placetype":"venue"
},
  "geometry": {"coordinates":[8.5297260284,47.4529685974],"type":"Point"}
}