{
  "type": "Feature",
  "properties": {
    "iso:country":"CH",
    "sg:address":"Birmenstorferstrasse 14a",
    "sg:city":"Fislisbach",
    "sg:orig_category":"Sonstige Kultur U Unterhaltungseinrichtungen",
    "sg:postcode":"5442",
    "sg:province":"Aargau",
    "wof:name":"Rosario Gmbh",
    "wof:placetype":"venue"
},
  "geometry": {"coordinates":[8.2884988785,47.4395027161],"type":"Point"}
}