{
  "type": "Feature",
  "properties": {
    "iso:country":"CH",
    "sg:address":"Rue De La Gare 41",
    "sg:city":"Nyon",
    "sg:orig_category":"Herstellung von konfektionierten Textilwaren ohne Bekleidung",
    "sg:phone":"+41 22 361 51 21",
    "sg:postcode":"1260",
    "sg:province":"Vaud",
    "wof:name":"Proma Sa",
    "wof:placetype":"venue"
},
  "geometry": {"coordinates":[6.2360692024,46.3835601807],"type":"Point"}
}