{
  "type": "Feature",
  "properties": {
    "iso:country":"CH",
    "sg:address":"Brahmsstrasse 12 8003 Z\u00fcrich. Postfach",
    "sg:city":"Z\u00fcrich",
    "sg:orig_category":"Sonstige mit der Informatik verbundene T\u00e4tigkeiten",
    "sg:phone":"+41 14932244",
    "sg:postcode":"8040",
    "sg:province":"Z\u00fcrich",
    "wof:name":"Provox Ag Z\u00fcrich",
    "wof:placetype":"venue"
},
  "geometry": {"coordinates":[8.5075426102,47.3784713745],"type":"Point"}
}