{
  "type": "Feature",
  "properties": {
    "iso:country":"CH",
    "sg:address":"Industriestr. 176",
    "sg:city":"Spreitenbach",
    "sg:classifiers":[
        {
            "category":"Professional",
            "subcategory":"Engineering",
            "type":"Services"
        }
    ],
    "sg:phone":"+41 56 418 13 00",
    "sg:postcode":"8957",
    "sg:province":"Aargau",
    "sg:tags":[
        "machine",
        "-",
        "mechanical"
    ],
    "wof:name":"Orion Al-ko Ag",
    "wof:placetype":"venue"
},
  "geometry": {"coordinates":[8.3635349274,47.4279174805],"type":"Point"}
}