{
  "type": "Feature",
  "properties": {
    "iso:country":"CH",
    "sg:address":"Z\u00fcrichstrasse 7",
    "sg:city":"Uster",
    "sg:orig_category":"Aktivit\u00e4ten der Generalunternehmen im Baugewerbe Allgemeiner Hoch U Tiefbau",
    "sg:phone":"+41 13161414",
    "sg:postcode":"8610",
    "sg:province":"Z\u00fcrich",
    "wof:name":"Ortobau Generalunternehmung Ag",
    "wof:placetype":"venue"
},
  "geometry": {"coordinates":[8.716005,47.349121],"type":"Point"}
}