{
  "type": "Feature",
  "properties": {
    "iso:country":"CH",
    "sg:address":"Gartematt 12 8180 B\u00fclach. Postfach",
    "sg:city":"B\u00fclach",
    "sg:orig_category":"Kauf U Verkauf von Immobilien auf eigene Rechnung",
    "sg:postcode":"8180",
    "sg:province":"Z\u00fcrich",
    "wof:name":"Relag Ebert & Co",
    "wof:placetype":"venue"
},
  "geometry": {"coordinates":[8.5432186127,47.5186080933],"type":"Point"}
}