{
  "type": "Feature",
  "properties": {
    "iso:country":"CH",
    "sg:address":"Fabrikstrasse 14a 3455 Gr\u00fcnen. Postfach",
    "sg:city":"Gr\u00fcnen",
    "sg:orig_category":"Unclassifiable Establishments",
    "sg:postcode":"3455",
    "sg:province":"Bern",
    "wof:name":"Napac Ag",
    "wof:placetype":"venue"
},
  "geometry": {"coordinates":[7.7369060516,47.0232658386],"type":"Point"}
}