{
  "type": "Feature",
  "properties": {
    "iso:country":"CH",
    "sg:address":"1926",
    "sg:city":"Fully",
    "sg:orig_category":"Sonstiger Fachdetailhandel mit Nahrungsmitteln, Getr\u00e4nken U Tabak in Verkaufsr\u00e4umen",
    "sg:postcode":"1926",
    "sg:province":"Valais",
    "wof:name":"Tarr\u00e8s-nissille Anne-marie",
    "wof:placetype":"venue"
},
  "geometry": {"coordinates":[6.9177680016,46.696308136],"type":"Point"}
}