{
  "type": "Feature",
  "properties": {
    "iso:country":"CH",
    "sg:address":"Avenue De La Gare 6",
    "sg:city":"Fleurier",
    "sg:orig_category":"Handel mit Automobilteilen U Zubeh\u00f6r",
    "sg:phone":"+41 34 445 74 37",
    "sg:postcode":"2114",
    "sg:province":"Neuch\u00e2tel",
    "wof:name":"Crespi Und Reinhard Autozubeh\u00f6r",
    "wof:placetype":"venue"
},
  "geometry": {"coordinates":[7.568983078,47.0876655579],"type":"Point"}
}