{
  "type": "Feature",
  "properties": {
    "iso:country":"CH",
    "sg:address":"Alleestrasse 30",
    "sg:city":"Romanshorn",
    "sg:orig_category":"Detailhandel Reparatur von Gebrauchsg\u00fctern",
    "sg:phone":"+41 71 277 79 29",
    "sg:postcode":"8590",
    "sg:province":"Thurgau",
    "wof:name":"Erotic-markt Gerhard Wolfschl\u00e4ger",
    "wof:placetype":"venue"
},
  "geometry": {"coordinates":[9.3302078247,47.4088363647],"type":"Point"}
}