{
  "type": "Feature",
  "properties": {
    "iso:country":"CH",
    "sg:address":"Haldenstrasse 33",
    "sg:city":"Oetwil",
    "sg:orig_category":"Werbung",
    "sg:phone":"+41 17481752",
    "sg:postcode":"8955",
    "sg:province":"Z\u00fcrich",
    "wof:name":"Aida Werbeteam Rolf E. Kalt & Partner",
    "wof:placetype":"venue"
},
  "geometry": {"coordinates":[8.403752327,47.4229164124],"type":"Point"}
}