{
  "type": "Feature",
  "properties": {
    "iso:country":"CH",
    "sg:address":"Hinterfeldstrasse 9",
    "sg:city":"Laufen",
    "sg:orig_category":"Vorschulen, Kinderg\u00e4rten",
    "sg:phone":"+41 61 761 14 50",
    "sg:postcode":"4242",
    "sg:province":"Basel-Landschaft",
    "wof:name":"Kindergarten Norimatt",
    "wof:placetype":"venue"
},
  "geometry": {"coordinates":[7.49898386,47.4207038879],"type":"Point"}
}