{
  "type": "Feature",
  "properties": {
    "iso:country":"CH",
    "sg:address":"Champs-du-pont 6",
    "sg:city":"Mathod",
    "sg:orig_category":"Unclassifiable Establishments",
    "sg:postcode":"1438",
    "sg:province":"Vaud",
    "wof:name":"Natalino Pepe",
    "wof:placetype":"venue"
},
  "geometry": {"coordinates":[6.5624899864,46.7645683289],"type":"Point"}
}