{
  "type": "Feature",
  "properties": {
    "iso:country":"CH",
    "sg:address":"Opfikonstrasse 96",
    "sg:city":"Z\u00fcrich",
    "sg:orig_category":"Non-Classified Establishments",
    "sg:postcode":"8050",
    "sg:province":"Z\u00fcrich",
    "wof:name":"T\u00f6ff-bekleidung Swiss Z\u00fcrich Gmbh",
    "wof:placetype":"venue"
},
  "geometry": {"coordinates":[8.5705823898,47.4154167175],"type":"Point"}
}