{
  "type": "Feature",
  "properties": {
    "iso:country":"CH",
    "sg:address":"Quadretta",
    "sg:city":"Scharans",
    "sg:orig_category":"P\u00e9dicure",
    "sg:phone":"+41 81 651 31 02",
    "sg:postcode":"7412",
    "sg:province":"Graubunden",
    "wof:name":"Beatrice Keller P\u00e9dicure",
    "wof:placetype":"venue"
},
  "geometry": {"coordinates":[9.4590911865,46.7193412781],"type":"Point"}
}