{
  "type": "Feature",
  "properties": {
    "addr:full":"M\u00f6hrlistrasse 97 Z\u00fcrich Z\u00fcrich 8006",
    "addr:housenumber":"97",
    "addr:postcode":"8006",
    "addr:street":"Moehrlistrasse",
    "iso:country":"CH",
    "sg:address":"M\u00f6hrlistrasse 97",
    "sg:city":"Z\u00fcrich",
    "sg:orig_category":"Advokaturb\u00fcros",
    "sg:phone":"+41 71 223 52 06",
    "sg:postcode":"8006",
    "sg:province":"Z\u00fcrich",
    "wof:name":"Dr.valentin N.j. Landmann Advokaturb\u00fcro",
    "wof:placetype":"venue"
},
  "geometry": {"coordinates":[8.545981,47.392597],"type":"Point"}
}