{
  "type": "Feature",
  "properties": {
    "iso:country":"CH",
    "sg:address":"Chemin Du Forge 4",
    "sg:city":"Belfaux",
    "sg:orig_category":"Arztpraxen",
    "sg:phone":"+41 26 475 26 06",
    "sg:postcode":"1782",
    "sg:province":"Fribourg",
    "wof:name":"Dr M\u00e9d. Nicolas Dousse M\u00e9decin Sp\u00e9cialiste Fmh",
    "wof:placetype":"venue"
},
  "geometry": {"coordinates":[7.10327,46.822021],"type":"Point"}
}