{
  "type": "Feature",
  "properties": {
    "addr:full":"Bollwerk 17 3011 Bern. Postfach Bern Bern 3005",
    "addr:housenumber":"17",
    "addr:postcode":"3011;postfach;3005",
    "addr:street":"Bollwerk",
    "iso:country":"CH",
    "sg:address":"Bollwerk 17 3011 Bern. Postfach",
    "sg:city":"Bern",
    "sg:orig_category":"Betrieb U technische Hilfsdienste des Kultur U Unterhaltungswesens",
    "sg:postcode":"3005",
    "sg:province":"Bern",
    "wof:name":"Pink Produktions Baumgard & Jegerlehner Show-veranstaltungen; Organisation U. Vermittlung; Ton- U. Bildtr\u00e4ger; Produktion U. Vertrieb.",
    "wof:placetype":"venue"
},
  "geometry": {"coordinates":[7.440719,46.949677],"type":"Point"}
}