{
  "type": "Feature",
  "properties": {
    "iso:country":"CH",
    "sg:address":"4574",
    "sg:city":"Nennigkofen",
    "sg:orig_category":"Forst\u00e4mter",
    "sg:phone":"+41 32 622 39 42",
    "sg:postcode":"4574",
    "sg:province":"Solothurn",
    "wof:name":"Forstkommission",
    "wof:placetype":"venue"
},
  "geometry": {"coordinates":[7.4929361343,47.1867485046],"type":"Point"}
}