{
  "type": "Feature",
  "properties": {
    "iso:country":"CH",
    "sg:address":"Gipsstrasse 2",
    "sg:city":"Oberehrendingen",
    "sg:orig_category":"Grosshandel mit Getreide, Saatgut U Futtermitteln Grosshandel mit sonstigen Nahrungsmitteln",
    "sg:phone":"+41 56 221 71 41",
    "sg:postcode":"5422",
    "wof:name":"Anf Premium Pet Food Gmbh",
    "wof:placetype":"venue"
},
  "geometry": {"coordinates":[8.3415355682,47.4962806702],"type":"Point"}
}