{
  "type": "Feature",
  "properties": {
    "iso:country":"CH",
    "sg:address":"Zugerstrasse 74",
    "sg:city":"Baar",
    "sg:orig_category":"Interessenvertretungen",
    "sg:postcode":"6340",
    "sg:province":"Zug",
    "wof:name":"Biotop-stiftung Der Portlandcementwerk Ag Olten",
    "wof:placetype":"venue"
},
  "geometry": {"coordinates":[7.8769111633,47.3401184082],"type":"Point"}
}