{
  "type": "Feature",
  "properties": {
    "iso:country":"CH",
    "sg:address":"Route De Moutier 20",
    "sg:city":"Perrefitte",
    "sg:orig_category":"Herstellung von Fahrr\u00e4dern Herstellung von Metallerzeugnissen ohne Maschinenbau",
    "sg:phone":"+41 32 493 32 61",
    "sg:postcode":"2742",
    "sg:province":"Bern",
    "wof:name":"Rm Concept Fabrication De Cycles",
    "wof:placetype":"venue"
},
  "geometry": {"coordinates":[7.3480329514,47.2729377747],"type":"Point"}
}