{
  "type": "Feature",
  "properties": {
    "iso:country":"CH",
    "sg:address":"Bleikenstrasse 98",
    "sg:city":"Wattwil",
    "sg:classifiers":[
        {
            "category":"Shopping",
            "subcategory":"Crafts & Fabrics",
            "type":"Retail Goods"
        }
    ],
    "sg:phone":"+41 71 987 61 51",
    "sg:postcode":"9630",
    "sg:province":"St. Gallen",
    "sg:tags":[
        "packaging",
        "biological",
        "material"
    ],
    "wof:name":"Lindner Verpackungen Gmbh",
    "wof:placetype":"venue"
},
  "geometry": {"coordinates":[9.0928211212,47.2861824036],"type":"Point"}
}