{
  "type": "Feature",
  "properties": {
    "iso:country":"CH",
    "sg:address":"Hagmattstrasse 10",
    "sg:city":"Allschwil",
    "sg:orig_category":"Bauspenglerei Sanit\u00e4rinstallation",
    "sg:phone":"+41 61 361 13 46",
    "sg:postcode":"4123",
    "sg:province":"Basel-Landschaft",
    "wof:name":"Rudin Hugo Spenglerei, Kunststoffbedachungen, Sanit\u00e4r-installationen Usw",
    "wof:placetype":"venue"
},
  "geometry": {"coordinates":[7.54361,47.55666],"type":"Point"}
}