{
  "type": "Feature",
  "properties": {
    "iso:country":"CH",
    "sg:address":"Gubelstrasse 19",
    "sg:city":"Zug",
    "sg:orig_category":"Fachdetailhandel in Verkaufsr\u00e4umen Handel mit Motorr\u00e4dern, Teilen U Zubeh\u00f6r Instandhaltung U Reparat",
    "sg:phone":"+41 41 711 45 51",
    "sg:postcode":"6300",
    "sg:province":"Zug",
    "wof:name":"Gull B. + Y. Zweiradsport",
    "wof:placetype":"venue"
},
  "geometry": {"coordinates":[8.5164470673,47.1744422913],"type":"Point"}
}