{
  "type": "Feature",
  "properties": {
    "addr:full":"Rue De La Mairie 6 Gen\u00e8ve Gen\u00e8ve 1207",
    "addr:housenumber":"6",
    "addr:postcode":"1207",
    "addr:street":"Rue De La Mairie",
    "iso:country":"CH",
    "sg:address":"Rue De La Mairie 6",
    "sg:city":"Gen\u00e8ve",
    "sg:orig_category":"Detailhandel mit Antiquit\u00e4ten Detailhandel mit M\u00f6beln",
    "sg:phone":"+41 22 736 30 50",
    "sg:postcode":"1207",
    "sg:province":"Gen\u00e8ve",
    "wof:name":"V\u00e9ronique Pezzotti D\u00e9coration Meubles Antiquit\u00e9s",
    "wof:placetype":"venue"
},
  "geometry": {"coordinates":[6.157823,46.203007],"type":"Point"}
}