{
  "type": "Feature",
  "properties": {
    "addr:full":"Speerstrasse 20 Ebnat-kappel St. Gallen 9642",
    "addr:housenumber":"20;st.",
    "addr:postcode":"9642",
    "addr:street":"Speerstrasse;Ebnat-Kappel",
    "iso:country":"CH",
    "sg:address":"Speerstrasse 20",
    "sg:city":"Ebnat-kappel",
    "sg:classifiers":[
        {
            "category":"Social Services",
            "subcategory":"Retirement Home",
            "type":"Services"
        }
    ],
    "sg:phone":"+41 71 243 81 11",
    "sg:postcode":"9642",
    "sg:province":"St. Gallen",
    "sg:tags":[
        "pflegeheime",
        "u",
        "alters"
    ],
    "wof:name":"B\u00fcrgerspital",
    "wof:placetype":"venue"
},
  "geometry": {"coordinates":[9.386749,47.428436],"type":"Point"}
}