{
  "type": "Feature",
  "properties": {
    "iso:country":"CH",
    "sg:address":"Rue Des Courtils 1",
    "sg:city":"Cortaillod",
    "sg:orig_category":"Detailhandel mit Waren verschiedener Art, Hauptrichtung Nichtnahrungsmittel",
    "sg:phone":"+41 32 842 28 50",
    "sg:postcode":"2016",
    "sg:province":"Neuch\u00e2tel",
    "wof:name":"Paolini Angelo, Electrom\u00e9nager",
    "wof:placetype":"venue"
},
  "geometry": {"coordinates":[6.8456897736,46.9428710938],"type":"Point"}
}