{
  "type": "Feature",
  "properties": {
    "iso:country":"CH",
    "sg:address":"Guidino Via 9a 6900 Paradiso. Postfach",
    "sg:city":"Paradiso",
    "sg:orig_category":"Handels-H\u00e4user U Gesellschaften",
    "sg:phone":"+41 91 980 08 35",
    "sg:postcode":"6900",
    "sg:province":"Ticino",
    "wof:name":"Global Food Trade Ag, Vaduz, Succursale Di Paradiso",
    "wof:placetype":"venue"
},
  "geometry": {"coordinates":[8.9504241943,45.9880218506],"type":"Point"}
}