{
  "type": "Feature",
  "properties": {
    "addr:full":"Z\u00fcrcherstrasse 4 Siebnen Schwyz 8854",
    "addr:housenumber":"4",
    "addr:postcode":"8854",
    "addr:street":"Zuercherstrasse;Schwyz",
    "iso:country":"CH",
    "sg:address":"Z\u00fcrcherstrasse 4",
    "sg:city":"Siebnen",
    "sg:classifiers":[
        {
            "category":"Banks & Credit Unions",
            "subcategory":"Bank",
            "type":"Services"
        }
    ],
    "sg:phone":"+41 4155641361",
    "sg:postcode":"8854",
    "sg:province":"Schwyz",
    "wof:name":"Bank Linth",
    "wof:placetype":"venue"
},
  "geometry": {"coordinates":[8.896375,47.174583],"type":"Point"}
}