{
  "type": "Feature",
  "properties": {
    "iso:country":"CH",
    "sg:address":"Via Besso 43",
    "sg:city":"Lugano",
    "sg:orig_category":"Detailhandel mit Brillen U anderen Sehhilfen Fachdetailhandel in Verkaufsr\u00e4umen",
    "sg:phone":"+41 91 966 51 36",
    "sg:postcode":"6900",
    "sg:province":"Ticino",
    "wof:name":"Ottica Besso Maria Luisa Rusconi",
    "wof:placetype":"venue"
},
  "geometry": {"coordinates":[8.939359,46.009239],"type":"Point"}
}