{
  "type": "Feature",
  "properties": {
    "iso:country":"CH",
    "sg:address":"Landstrasse 62 9494 Schaan. Postfach 57",
    "sg:city":"Schaan",
    "sg:orig_category":"Detailhandel mit Damenbekleidung Detailhandel mit Herrenbekleidung",
    "sg:phone":"+423 232 17 33",
    "sg:postcode":"9494",
    "wof:name":"Luigi Faoro Ag Modehaus",
    "wof:placetype":"venue"
},
  "geometry": {"coordinates":[9.5083408356,47.1636276245],"type":"Point"}
}