{
  "type": "Feature",
  "properties": {
    "iso:country":"CH",
    "sg:address":"Kestenholzerstrasse 29",
    "sg:city":"Wolfwil",
    "sg:orig_category":"Arztpraxen",
    "sg:phone":"+41 62 926 15 33",
    "sg:postcode":"4628",
    "sg:province":"Solothurn",
    "wof:name":"Dr.med.silvan Hafner Arzt F.allgemeine Medizin Fmh",
    "wof:placetype":"venue"
},
  "geometry": {"coordinates":[7.790375,47.269264],"type":"Point"}
}