{
  "type": "Feature",
  "properties": {
    "addr:full":"Coteaux Rue Des 16 Cortaillod Neuch\u00e2tel 2016",
    "addr:postcode":"2016",
    "addr:street":"Rue Des 16;Neucha\u0302Tel",
    "iso:country":"CH",
    "sg:address":"Coteaux Rue Des 16",
    "sg:city":"Cortaillod",
    "sg:orig_category":"Detailhandel mit Brot, Back U S\u00fcsswaren",
    "sg:postcode":"2016",
    "sg:province":"Neuch\u00e2tel",
    "wof:name":"Boulangerie-p\u00e2tisserie Bourgeois",
    "wof:placetype":"venue"
},
  "geometry": {"coordinates":[6.845674,46.942272],"type":"Point"}
}