{
  "type": "Feature",
  "properties": {
    "iso:country":"CH",
    "sg:address":"Quaistrasse 3/moserstrasse",
    "sg:city":"Schaffhausen",
    "sg:orig_category":"Kauf U Verkauf von Immobilien auf eigene Rechnung",
    "sg:phone":"+41 81 416 35 35",
    "sg:postcode":"8200",
    "sg:province":"Schaffhausen",
    "wof:name":"Feriensiedlung Solaria, M\u00fcller B\u00e9atrice",
    "wof:placetype":"venue"
},
  "geometry": {"coordinates":[9.8421230316,46.8021125793],"type":"Point"}
}