{
  "type": "Feature",
  "properties": {
    "iso:country":"CH",
    "sg:address":"Alte Landstrasse 233 8708 M\u00e4nnedorf. Postfach",
    "sg:city":"M\u00e4nnedorf",
    "sg:orig_category":"Unternehmensberatung",
    "sg:phone":"+41 19203306",
    "sg:postcode":"8708",
    "sg:province":"Z\u00fcrich",
    "wof:name":"Reality Change Ag Beraten U. Coaching Von Personen Zur Pers\u00f6nlichkeitsentwicklung. Beraten U. Coaching Von Unternehmen In Den Bereichen F\u00fchrung, Strategie, Kultur Usw",
    "wof:placetype":"venue"
},
  "geometry": {"coordinates":[8.6945161819,47.2539978027],"type":"Point"}
}