{
  "type": "Feature",
  "properties": {
    "iso:country":"CH",
    "sg:address":"Avenue Communes-r\u00e9unies 8bis",
    "sg:city":"Grand-lancy",
    "sg:orig_category":"Arztpraxen",
    "sg:phone":"+41 22 794 82 00",
    "sg:postcode":"1212",
    "sg:province":"Gen\u00e8ve",
    "wof:name":"Dr M\u00e9d. Michel Bourquin M\u00e9decin Sp\u00e9cialiste Fmh",
    "wof:placetype":"venue"
},
  "geometry": {"coordinates":[6.120818,46.181763],"type":"Point"}
}