{
  "type": "Feature",
  "properties": {
    "iso:country":"CH",
    "sg:address":"Hinterofenstrasse 25",
    "sg:city":"Koblenz",
    "sg:orig_category":"Herstellung von Kunststoffwaren",
    "sg:phone":"+41 19200135",
    "sg:postcode":"5322",
    "sg:province":"Aargau",
    "wof:name":"Kunststoffwerk Und Formenbau Steiger Arthur Ag",
    "wof:placetype":"venue"
},
  "geometry": {"coordinates":[8.6854944229,47.2728919983],"type":"Point"}
}