{
  "type": "Feature",
  "properties": {
    "iso:country":"CH",
    "sg:address":"Uetlibergstrasse 354 8045 Z\u00fcrich 45 Zust. Postfach 8045 Z\u00fcrich",
    "sg:city":"Zust",
    "sg:orig_category":"Sonstige pers\u00f6nliche Dienstleistungen",
    "sg:phone":"+41 12419444",
    "sg:postcode":"45",
    "wof:name":"Jordhen Consulting Gesellschaften; Finanzierung, Verwaltung, Beratung",
    "wof:placetype":"venue"
},
  "geometry": {"coordinates":[8.5118503571,47.3567810059],"type":"Point"}
}