{
  "type": "Feature",
  "properties": {
    "iso:country":"CH",
    "sg:address":"Rue De La Favi\u00e8re 19",
    "sg:city":"Grand-savagnier",
    "sg:orig_category":"Logistikberatung",
    "sg:phone":"+41 71 747 10 00",
    "sg:postcode":"2065",
    "sg:province":"Neuch\u00e2tel",
    "wof:name":"Logistik 2000 Ag",
    "wof:placetype":"venue"
},
  "geometry": {"coordinates":[9.6429071426,47.4530143738],"type":"Point"}
}