{
  "type": "Feature",
  "properties": {
    "iso:country":"CH",
    "sg:address":"Bahnhofstrasse 31 5012 Sch\u00f6nenwerd. Postfach 110",
    "sg:city":"Sch\u00f6nenwerd",
    "sg:orig_category":"Bauspenglerei Sanit\u00e4rinstallation U Spenglerei",
    "sg:phone":"+41 62 858 50 00",
    "sg:postcode":"5012",
    "sg:province":"Solothurn",
    "wof:name":"H\u00e4feli Haustechnik Gmbh",
    "wof:placetype":"venue"
},
  "geometry": {"coordinates":[8.000339,47.370522],"type":"Point"}
}