{
  "type": "Feature",
  "properties": {
    "iso:country":"CH",
    "sg:address":"Rue Saint-randoald 12",
    "sg:city":"Del\u00e9mont",
    "sg:orig_category":"Rechtsberatung Wirtschaftspr\u00fcfung, Steuerberatung U Treuhand",
    "sg:phone":"+41 32 422 77 30",
    "sg:postcode":"2800",
    "sg:province":"Jura",
    "wof:name":"Fiduciaire Mahon S\u00e0rl",
    "wof:placetype":"venue"
},
  "geometry": {"coordinates":[7.344244957,47.355342865],"type":"Point"}
}