{
  "type": "Feature",
  "properties": {
    "iso:country":"CH",
    "sg:address":"Via Dante Alighieri 1",
    "sg:city":"Chiasso",
    "sg:orig_category":"Kinos",
    "sg:phone":"+41 91 683 63 47",
    "sg:postcode":"6830",
    "sg:province":"Ticino",
    "wof:name":"Cinema Teatro Sa",
    "wof:placetype":"venue"
},
  "geometry": {"coordinates":[9.0272607803,45.8364524841],"type":"Point"}
}