{
  "type": "Feature",
  "properties": {
    "iso:country":"CH",
    "sg:address":"Hofackerstrasse 8",
    "sg:city":"Siegershausen",
    "sg:orig_category":"Mechanische Werkst\u00e4tten",
    "sg:phone":"+41 71 699 16 78",
    "sg:postcode":"8573",
    "sg:province":"Thurgau",
    "wof:name":"Hans Rechsteiner Ag Feinmechanik",
    "wof:placetype":"venue"
},
  "geometry": {"coordinates":[9.1687335968,47.6092605591],"type":"Point"}
}