{
  "type": "Feature",
  "properties": {
    "iso:country":"CH",
    "sg:address":"Hauptstrasse 14",
    "sg:city":"M\u00f6hlin",
    "sg:orig_category":"Instandhaltung U Reparatur von Automobilen",
    "sg:phone":"+41 61 851 25 51",
    "sg:postcode":"4313",
    "sg:province":"Aargau",
    "wof:name":"Garage Guido Gasser",
    "wof:placetype":"venue"
},
  "geometry": {"coordinates":[7.8414258957,47.5629882812],"type":"Point"}
}