{
  "type": "Feature",
  "properties": {
    "iso:country":"CH",
    "sg:address":"4579",
    "sg:city":"Gossliwil",
    "sg:classifiers":[
        {
            "category":"Restaurant",
            "type":"Food & Drink"
        }
    ],
    "sg:phone":"+41 55 284 19 19",
    "sg:postcode":"4579",
    "sg:province":"Solothurn",
    "wof:name":"Restaurant Kreuz",
    "wof:placetype":"venue"
},
  "geometry": {"coordinates":[9.0125598907,47.2704696655],"type":"Point"}
}