{
  "type": "Feature",
  "properties": {
    "iso:country":"CH",
    "sg:address":"Via Calprino 3",
    "sg:city":"Paradiso",
    "sg:classifiers":[
        {
            "category":"Bars & Pubs",
            "type":"Food & Drink"
        }
    ],
    "sg:phone":"+41 91 994 61 98",
    "sg:postcode":"6900",
    "sg:province":"Ticino",
    "wof:name":"Bar Flamenco",
    "wof:placetype":"venue"
},
  "geometry": {"coordinates":[8.940391,45.989048],"type":"Point"}
}