{
  "type": "Feature",
  "properties": {
    "iso:country":"CH",
    "sg:address":"M\u00fcnchhaldenstrasse 19 8008 Z\u00fcrich. Postfach",
    "sg:city":"Z\u00fcrich",
    "sg:orig_category":"Sonstiger Grosshandel",
    "sg:phone":"+41 56 450 17 50",
    "sg:postcode":"8008",
    "sg:province":"Z\u00fcrich",
    "wof:name":"Cebo Trading Celio Boniolo",
    "wof:placetype":"venue"
},
  "geometry": {"coordinates":[8.1683244705,47.4429626465],"type":"Point"}
}