{
  "type": "Feature",
  "properties": {
    "iso:country":"CH",
    "sg:address":"Fachstrasse 33",
    "sg:city":"Oberrieden",
    "sg:orig_category":"Handelsschulen",
    "sg:phone":"+41 17200160",
    "sg:postcode":"8942",
    "sg:province":"Z\u00fcrich",
    "wof:name":"Institut F\u00fcr Handelskunde",
    "wof:placetype":"venue"
},
  "geometry": {"coordinates":[8.5795249939,47.2773704529],"type":"Point"}
}