{
  "type": "Feature",
  "properties": {
    "iso:country":"CH",
    "sg:address":"Rue De Maillefer 11",
    "sg:city":"Neuch\u00e2tel",
    "sg:orig_category":"Detailhandel mit Fleisch U Fleischwaren",
    "sg:phone":"+41 32 731 27 31",
    "sg:postcode":"2000",
    "sg:province":"Neuch\u00e2tel",
    "wof:name":"Carna-top Boucherie",
    "wof:placetype":"venue"
},
  "geometry": {"coordinates":[6.9064540863,46.9841156006],"type":"Point"}
}