{
  "type": "Feature",
  "properties": {
    "iso:country":"CH",
    "sg:address":"Ch\u00eanes Chemin Des 32",
    "sg:city":"Creux-de-genthod",
    "sg:orig_category":"Erbringung von Dienstleistungen f\u00fcr Unternehmen",
    "sg:postcode":"1294",
    "sg:province":"Gen\u00e8ve",
    "wof:name":"Webmarketing S\u00e0rl",
    "wof:placetype":"venue"
},
  "geometry": {"coordinates":[6.1555528641,46.2648391724],"type":"Point"}
}