{
  "type": "Feature",
  "properties": {
    "iso:country":"CH",
    "sg:address":"2715",
    "sg:city":"Ch\u00e2telat-monible",
    "sg:orig_category":"Mechanik Schmieden",
    "sg:phone":"+41 32 481 40 66",
    "sg:postcode":"2715",
    "sg:province":"Bern",
    "wof:name":"Streit G\u00e9rald.",
    "wof:placetype":"venue"
},
  "geometry": {"coordinates":[7.1950497627,47.2773399353],"type":"Point"}
}