{
  "type": "Feature",
  "properties": {
    "iso:country":"CH",
    "sg:address":"Lungolago Motta 60 6815 Melide. Postfach",
    "sg:city":"Melide",
    "sg:orig_category":"Verwaltung von Immobilien",
    "sg:postcode":"6815",
    "sg:province":"Ticino",
    "wof:name":"Interturistica Sa",
    "wof:placetype":"venue"
},
  "geometry": {"coordinates":[8.9408407211,45.9489936829],"type":"Point"}
}