{
  "type": "Feature",
  "properties": {
    "iso:country":"CH",
    "sg:address":"Heckenweg 24",
    "sg:city":"Thun",
    "sg:orig_category":"Sonstiger Fachdetailhandel in Verkaufsr\u00e4umen",
    "sg:phone":"+41 33 336 53 47",
    "sg:postcode":"3604",
    "sg:province":"Bern",
    "wof:name":"Susanne In\u00e4bnit Schmuck & Edelsteine",
    "wof:placetype":"venue"
},
  "geometry": {"coordinates":[7.6231460571,46.7367897034],"type":"Point"}
}