{
  "type": "Feature",
  "properties": {
    "iso:country":"CH",
    "sg:address":"Winterthurerstrasse 514",
    "sg:city":"Z\u00fcrich",
    "sg:orig_category":"Werbung",
    "sg:phone":"+41 21 646 18 55",
    "sg:postcode":"8051",
    "sg:province":"Z\u00fcrich",
    "wof:name":"Charterpub, C. Simond",
    "wof:placetype":"venue"
},
  "geometry": {"coordinates":[6.6140098572,46.5377082825],"type":"Point"}
}