{
  "type": "Feature",
  "properties": {
    "iso:country":"CH",
    "sg:address":"Waldeggstr. 34 A 3800 Interlaken. Postfach",
    "sg:city":"Interlaken",
    "sg:orig_category":"Instandhaltung U Reparatur von Automobilen",
    "sg:postcode":"3800",
    "sg:province":"Bern",
    "wof:name":"H. Oertel-balmer",
    "wof:placetype":"venue"
},
  "geometry": {"coordinates":[7.8553481102,46.6799812317],"type":"Point"}
}