{
  "type": "Feature",
  "properties": {
    "iso:country":"CH",
    "sg:address":"Lindenplatz",
    "sg:city":"Uzwil",
    "sg:orig_category":"Instandhaltung U Reparatur von Automobilen",
    "sg:phone":"+41 71 951 57 92",
    "sg:postcode":"9240",
    "sg:province":"St. Gallen",
    "wof:name":"Widmer Guido.",
    "wof:placetype":"venue"
},
  "geometry": {"coordinates":[9.135925293,47.4351463318],"type":"Point"}
}