{
  "type": "Feature",
  "properties": {
    "iso:country":"CH",
    "sg:address":"Brachenstrasse 13 9050 Appenzell. Postfach",
    "sg:city":"Appenzell",
    "sg:classifiers":[
        {
            "category":"Travel",
            "subcategory":"Hotels & Motels",
            "type":"Entertainment"
        }
    ],
    "sg:phone":"+41 71 780 03 53",
    "sg:postcode":"9050",
    "sg:province":"Appenzell Innerhoden",
    "sg:tags":[
        "hotels",
        "mit",
        "restaurant"
    ],
    "wof:name":"S\u00e4ntis Seminare + Sportmarketing, Hanspeter Rusch",
    "wof:placetype":"venue"
},
  "geometry": {"coordinates":[9.4175977707,47.3231048584],"type":"Point"}
}