{
  "type": "Feature",
  "properties": {
    "iso:country":"CH",
    "sg:address":"Les Hauts-de-nendaz",
    "sg:city":"Haute-nendaz",
    "sg:classifiers":[
        {
            "category":"Travel",
            "subcategory":"Hotels & Motels",
            "type":"Entertainment"
        }
    ],
    "sg:postcode":"1997",
    "sg:province":"Valais",
    "sg:tags":[
        "hotels",
        "mit",
        "restaurant"
    ],
    "wof:name":"Lang, Mme Marthe",
    "wof:placetype":"venue"
},
  "geometry": {"coordinates":[7.2958369255,46.1869621277],"type":"Point"}
}