{
  "type": "Feature",
  "properties": {
    "iso:country":"CH",
    "sg:address":"Winkelriedstrasse 30",
    "sg:city":"Luzern",
    "sg:orig_category":"Kinesiologie",
    "sg:phone":"+41 41 211 30 11",
    "sg:postcode":"6003",
    "sg:province":"Luzern",
    "wof:name":"Conny Steinmann Kinesiologie",
    "wof:placetype":"venue"
},
  "geometry": {"coordinates":[8.3060445786,47.0476913452],"type":"Point"}
}