{
  "type": "Feature",
  "properties": {
    "iso:country":"CH",
    "sg:address":"Abbaye De Bonmont",
    "sg:city":"Ch\u00e9serex",
    "sg:orig_category":"Interessenvertretungen",
    "sg:postcode":"1275",
    "sg:province":"Vaud",
    "wof:name":"Fondation De L'abbaye De Bonmont",
    "wof:placetype":"venue"
},
  "geometry": {"coordinates":[6.15143013,46.4055862427],"type":"Point"}
}