{
  "type": "Feature",
  "properties": {
    "iso:country":"CH",
    "sg:address":"Kohlhalden 23",
    "sg:city":"Speicher",
    "sg:orig_category":"Grosshandel mit Getr\u00e4nken",
    "sg:phone":"+41 71 344 45 35",
    "sg:postcode":"9042",
    "sg:province":"Appenzell Ausserrhoden",
    "wof:name":"Vicon Gmbh",
    "wof:placetype":"venue"
},
  "geometry": {"coordinates":[9.4479389191,47.420135498],"type":"Point"}
}