{
  "type": "Feature",
  "properties": {
    "iso:country":"CH",
    "sg:address":"7306",
    "sg:city":"Fl\u00e4sch",
    "sg:classifiers":[
        {
            "category":"Restaurant",
            "type":"Food & Drink"
        }
    ],
    "sg:phone":"+41 81 302 10 54",
    "sg:postcode":"7306",
    "sg:province":"Graubunden",
    "wof:name":"Restaurant Zur M\u00fchle",
    "wof:placetype":"venue"
},
  "geometry": {"coordinates":[9.5131196976,47.0264663696],"type":"Point"}
}