{
  "type": "Feature",
  "properties": {
    "iso:country":"CH",
    "sg:address":"Linth-escher-stra\u00dfe",
    "sg:city":"Bilten",
    "sg:classifiers":[
        {
            "category":"Banks & Credit Unions",
            "subcategory":"Bank",
            "type":"Services"
        }
    ],
    "sg:phone":"+41 4158371444",
    "sg:postcode":"8865",
    "sg:province":"Glarus",
    "wof:name":"Glarner Kantonalbank, Filiale Bilten",
    "wof:placetype":"venue"
},
  "geometry": {"coordinates":[9.027595,47.151875],"type":"Point"}
}