{
  "type": "Feature",
  "properties": {
    "iso:country":"CH",
    "sg:address":"Bahnhofstrasse 6 8752 N\u00e4fels. Postfach 34",
    "sg:city":"N\u00e4fels",
    "sg:orig_category":"Detailhandel mit Uhren U Schmuck Fachdetailhandel in Verkaufsr\u00e4umen",
    "sg:phone":"+41 55 612 19 19",
    "sg:postcode":"8752",
    "sg:province":"Glarus",
    "wof:name":"Gallati-hauser Ernst, Uhren Und Bijouterie",
    "wof:placetype":"venue"
},
  "geometry": {"coordinates":[9.0648241043,47.0993309021],"type":"Point"}
}