{
  "type": "Feature",
  "properties": {
    "iso:country":"CH",
    "sg:address":"Neudorfstrasse 70",
    "sg:city":"Thusis",
    "sg:classifiers":[
        {
            "category":"Travel",
            "subcategory":"Hotels & Motels",
            "type":"Entertainment"
        }
    ],
    "sg:postcode":"7430",
    "sg:province":"Graubunden",
    "sg:tags":[
        "hotels",
        "mit",
        "restaurant"
    ],
    "wof:name":"Viamala Hotel Klee & Stutz",
    "wof:placetype":"venue"
},
  "geometry": {"coordinates":[9.4395599365,46.6972160339],"type":"Point"}
}