{
  "type": "Feature",
  "properties": {
    "iso:country":"CH",
    "sg:address":"Murtenstrasse 10 3270 Aarberg. Postfach",
    "sg:city":"Lyss",
    "sg:orig_category":"Erschliessung von Grundst\u00fccken",
    "sg:postcode":"3250",
    "sg:province":"Bern",
    "wof:name":"Genossenschaft Geissenried",
    "wof:placetype":"venue"
},
  "geometry": {"coordinates":[7.2727279663,47.0432128906],"type":"Point"}
}