{
  "type": "Feature",
  "properties": {
    "iso:country":"CH",
    "sg:address":"Oltnerstrasse 62 5012 Sch\u00f6nenwerd. Postfach",
    "sg:city":"Sch\u00f6nenwerd",
    "sg:orig_category":"Grosshandel mit Getreide, Saatgut U Futtermitteln Werbeberatung",
    "sg:phone":"+41 62 849 07 79",
    "sg:postcode":"5012",
    "sg:province":"Solothurn",
    "wof:name":"Store Service Ag Marketing Und Vertriebsgesellschaft",
    "wof:placetype":"venue"
},
  "geometry": {"coordinates":[8.0003833771,47.3688545227],"type":"Point"}
}