{
  "type": "Feature",
  "properties": {
    "iso:country":"CH",
    "sg:address":"Soresina 6802 Rivera Casella Postale 317",
    "sg:city":"Rivera",
    "sg:orig_category":"Grosshandel mit Uhren Sonstiger Grosshandel",
    "sg:phone":"+41 91 946 31 61",
    "sg:postcode":"6802",
    "sg:province":"Ticino",
    "wof:name":"Roloa Sa.",
    "wof:placetype":"venue"
},
  "geometry": {"coordinates":[8.9231395721,46.1164894104],"type":"Point"}
}