{
  "type": "Feature",
  "properties": {
    "iso:country":"CH",
    "sg:address":"Zone Industrielle En Vannel A-b",
    "sg:city":"Bex",
    "sg:orig_category":"W\u00e4scherei U chemische Reinigung",
    "sg:phone":"+41 24 463 37 31",
    "sg:postcode":"1880",
    "sg:province":"Vaud",
    "wof:name":"Ils Inter-linge Service Sa",
    "wof:placetype":"venue"
},
  "geometry": {"coordinates":[7.0156807899,46.2502593994],"type":"Point"}
}