{
  "type": "Feature",
  "properties": {
    "iso:country":"CH",
    "sg:address":"Freistrasse 2",
    "sg:city":"Schaffhausen",
    "sg:orig_category":"Unclassifiable Establishments",
    "sg:postcode":"8200",
    "sg:province":"Schaffhausen",
    "wof:name":"Frey Hydraulik, Hydrowatt-entwicklungen",
    "wof:placetype":"venue"
},
  "geometry": {"coordinates":[8.6275100708,47.7004318237],"type":"Point"}
}