{
  "type": "Feature",
  "properties": {
    "iso:country":"CH",
    "sg:address":"Bahnhofplatz",
    "sg:city":"Frauenfeld",
    "sg:orig_category":"RESTAURANTS: TEA-ROOMS",
    "sg:phone":"+41 56 622 13 13",
    "sg:postcode":"8500",
    "sg:province":"Thurgau",
    "wof:name":"Italienisches Spezialit\u00e4tenrestaurant Wohler Central Marianne Stanig- Bachmann",
    "wof:placetype":"venue"
},
  "geometry": {"coordinates":[8.2744226456,47.3500976562],"type":"Point"}
}