{
  "type": "Feature",
  "properties": {
    "iso:country":"CH",
    "sg:address":"Sonnenrainstrasse 21",
    "sg:city":"Riedholz",
    "sg:orig_category":"Sonstiges Gesundheitswesen",
    "sg:phone":"+41 32 622 28 22",
    "sg:postcode":"4533",
    "sg:province":"Solothurn",
    "wof:name":"Krankenmobilien Frau Marguerite Marchon",
    "wof:placetype":"venue"
},
  "geometry": {"coordinates":[7.5690112114,47.2330856323],"type":"Point"}
}