{
  "type": "Feature",
  "properties": {
    "iso:country":"CH",
    "sg:address":"Chemin Du Petit-flon",
    "sg:city":"Mont-sur-lausanne",
    "sg:orig_category":"Sonstige mit Sport verbundene T\u00e4tigkeiten",
    "sg:phone":"+41 21 647 37 75",
    "sg:postcode":"1052",
    "sg:province":"Vaud",
    "wof:name":"Privatir Sa Stands De Tir Etc",
    "wof:placetype":"venue"
},
  "geometry": {"coordinates":[6.6265101433,46.5438423157],"type":"Point"}
}