{
  "type": "Feature",
  "properties": {
    "iso:country":"CH",
    "sg:address":"1968 Mase. Postfach",
    "sg:city":"Vernami\u00e8ge",
    "sg:orig_category":"Zimmerei, Dachdeckerei, Bauspenglerei U Abdichtung",
    "sg:phone":"+41 27 281 24 28",
    "sg:postcode":"1961",
    "sg:province":"Valais",
    "wof:name":"Mathieu Bernard",
    "wof:placetype":"venue"
},
  "geometry": {"coordinates":[7.4307861328,46.1938591003],"type":"Point"}
}