{
  "type": "Feature",
  "properties": {
    "iso:country":"CH",
    "sg:address":"Sch\u00fctzenweg 3",
    "sg:city":"Frauenfeld",
    "sg:orig_category":"Unclassifiable Establishments",
    "sg:postcode":"8500",
    "sg:province":"Thurgau",
    "wof:name":"Kradolfer Gmbh Gipsergesch\u00e4ft",
    "wof:placetype":"venue"
},
  "geometry": {"coordinates":[8.882932663,47.5518493652],"type":"Point"}
}