{
  "type": "Feature",
  "properties": {
    "iso:country":"CH",
    "sg:address":"Therwilerstrasse 11",
    "sg:city":"Ettingen",
    "sg:orig_category":"Non-Classified Establishments",
    "sg:postcode":"4107",
    "sg:province":"Basel-Landschaft",
    "wof:name":"Caf\u00e9 Del Sergio, Inh. Beat Reiner",
    "wof:placetype":"venue"
},
  "geometry": {"coordinates":[7.5479001999,47.4847755432],"type":"Point"}
}