{
  "type": "Feature",
  "properties": {
    "iso:country":"CH",
    "sg:address":"Route De Chatacombaz 3",
    "sg:city":"Corseaux",
    "sg:orig_category":"Vereine Gesang",
    "sg:phone":"+41 21 921 33 14",
    "sg:postcode":"1802",
    "sg:province":"Vaud",
    "wof:name":"Union Chorale De Corseaux",
    "wof:placetype":"venue"
},
  "geometry": {"coordinates":[6.8183870316,46.4717979431],"type":"Point"}
}