{
  "type": "Feature",
  "properties": {
    "iso:country":"CH",
    "sg:address":"Norastrasse 7 8004 Z\u00fcrich. Postfach 2116",
    "sg:city":"Z\u00fcrich",
    "sg:orig_category":"Grosshandel mit Holz U Baustoffen",
    "sg:phone":"+41 19303174",
    "sg:postcode":"8040",
    "sg:province":"Z\u00fcrich",
    "wof:name":"Dehusan Gmbh",
    "wof:placetype":"venue"
},
  "geometry": {"coordinates":[8.7862758636,47.3284072876],"type":"Point"}
}