{
  "type": "Feature",
  "properties": {
    "iso:country":"CH",
    "sg:address":"1993",
    "sg:city":"Veysonnaz",
    "sg:classifiers":[
        {
            "category":"Restaurant",
            "type":"Food & Drink"
        }
    ],
    "sg:phone":"+41 27 281 31 95",
    "sg:postcode":"1993",
    "sg:province":"Valais",
    "wof:name":"Restaurant Mont-rouge",
    "wof:placetype":"venue"
},
  "geometry": {"coordinates":[7.3388028145,46.1959838867],"type":"Point"}
}