{
  "type": "Feature",
  "properties": {
    "iso:country":"CH",
    "sg:address":"Talb\u00e4chliweg 19",
    "sg:city":"Z\u00fcrich",
    "sg:orig_category":"Sanit\u00e4r, Heizungs U L\u00fcftungsinstallation Sanit\u00e4rinstallation",
    "sg:phone":"+41 14317242",
    "sg:postcode":"8048",
    "sg:province":"Z\u00fcrich",
    "wof:name":"Franchi Geb\u00e4udetechnik Gmbh",
    "wof:placetype":"venue"
},
  "geometry": {"coordinates":[8.467666626,47.3898200989],"type":"Point"}
}