{
  "type": "Feature",
  "properties": {
    "iso:country":"CH",
    "sg:address":"Hasenbergstrasse 2",
    "sg:city":"Udligenswil",
    "sg:orig_category":"Detailhandel mit Metallwaren, Anstrichmitteln, Glaswaren, Bau U Heimwerkerbedarf",
    "sg:phone":"+41 41 371 12 62",
    "sg:postcode":"6044",
    "sg:province":"Luzern",
    "wof:name":"Electra Engineering Ag",
    "wof:placetype":"venue"
},
  "geometry": {"coordinates":[8.3954401016,47.091884613],"type":"Point"}
}