{
  "type": "Feature",
  "properties": {
    "iso:country":"CH",
    "sg:address":"B\u00fcrgstrasse 3 8608 Bubikon. Postfach",
    "sg:city":"Bubikon",
    "sg:orig_category":"Detailhandel mit elektrischen Haushalts-,Radio U Fernsehger\u00e4ten sowie Musikinstrumenten",
    "sg:postcode":"8608",
    "sg:province":"Z\u00fcrich",
    "wof:name":"Bisaz Curdin Livesound Pa Equipment Beschallungsanlagen; Vermietung",
    "wof:placetype":"venue"
},
  "geometry": {"coordinates":[8.8149900436,47.2667388916],"type":"Point"}
}