{
  "type": "Feature",
  "properties": {
    "iso:country":"CH",
    "sg:address":"Westbahnhofstrasse 12",
    "sg:city":"Solothurn",
    "sg:orig_category":"Unternehmensberatung",
    "sg:phone":"+41 32 625 81 91",
    "sg:postcode":"4500",
    "sg:province":"Solothurn",
    "wof:name":"Gekom Gmbh",
    "wof:placetype":"venue"
},
  "geometry": {"coordinates":[7.53358078,47.2077789307],"type":"Point"}
}