{
  "type": "Feature",
  "properties": {
    "iso:country":"CH",
    "sg:address":"Horngasse 6",
    "sg:city":"Oberrieden",
    "sg:orig_category":"Allgemeiner Hochbau Maler U Glasergewerbe",
    "sg:phone":"+41 31 301 82 89",
    "sg:postcode":"8942",
    "sg:province":"Z\u00fcrich",
    "wof:name":"Jan Pelgrim",
    "wof:placetype":"venue"
},
  "geometry": {"coordinates":[7.437851,46.973469],"type":"Point"}
}