{
  "type": "Feature",
  "properties": {
    "iso:country":"CH",
    "sg:address":"Hauptstrasse 47",
    "sg:city":"Ipsach",
    "sg:orig_category":"Instandhaltung U Reparatur von Automobilen",
    "sg:phone":"+41 32 331 88 69",
    "sg:postcode":"2563",
    "sg:province":"Bern",
    "wof:name":"Carrosserie Nostalga",
    "wof:placetype":"venue"
},
  "geometry": {"coordinates":[7.2304048538,47.1127319336],"type":"Point"}
}