{
  "type": "Feature",
  "properties": {
    "iso:country":"CH",
    "sg:address":"Rue De La Terrassi\u00e8re 35",
    "sg:city":"Gen\u00e8ve",
    "sg:orig_category":"Detailhandel mit Waren verschiedener Art, Hauptrichtung Nahrungsmittel",
    "sg:phone":"+41 22 849 86 30",
    "sg:postcode":"1207",
    "sg:province":"Gen\u00e8ve",
    "wof:name":"Coop Eaux-vives 2000",
    "wof:placetype":"venue"
},
  "geometry": {"coordinates":[6.1590099335,46.2005004883],"type":"Point"}
}