{
  "type": "Feature",
  "properties": {
    "iso:country":"CH",
    "sg:address":"Bahnhofstrasse 54",
    "sg:city":"Grenchen",
    "sg:classifiers":[
        {
            "category":"Restaurant",
            "type":"Food & Drink"
        }
    ],
    "sg:phone":"+41 32 652 33 53",
    "sg:postcode":"2540",
    "sg:province":"Solothurn",
    "wof:name":"Camkiran Nihat, Hotel-restaurant Bahnhof Hotel-restaurant Bahnhof",
    "wof:placetype":"venue"
},
  "geometry": {"coordinates":[7.3983969688,47.1888237],"type":"Point"}
}