{
  "type": "Feature",
  "properties": {
    "iso:country":"CH",
    "sg:address":"Ligschwil 38",
    "sg:city":"Urswil",
    "sg:orig_category":"Gesundheitswesen Sonstige Aktivit\u00e4ten der nicht-\u00e4rztlichen Medizinalberufe",
    "sg:phone":"+41 41 910 12 89",
    "sg:postcode":"6280",
    "sg:province":"Luzern",
    "wof:name":"Institut Geduna F\u00fcr Naturheilpraktik Und Bioenergetische Therapien Kaufmann H.r.",
    "wof:placetype":"venue"
},
  "geometry": {"coordinates":[8.2893247604,47.1669769287],"type":"Point"}
}