{
  "type": "Feature",
  "properties": {
    "iso:country":"CH",
    "sg:address":"Rue Du Vieux-coll\u00e8ge 10bis",
    "sg:city":"Gen\u00e8ve",
    "sg:orig_category":"Verm\u00f6gensverwaltung Verwaltung von Immobilien",
    "sg:phone":"+41 22 319 69 40",
    "sg:postcode":"1204",
    "sg:province":"Gen\u00e8ve",
    "wof:name":"Tg Gestion Sa",
    "wof:placetype":"venue"
},
  "geometry": {"coordinates":[6.1512579918,46.2014350891],"type":"Point"}
}