{
  "type": "Feature",
  "properties": {
    "iso:country":"CH",
    "sg:address":"Cit\u00e9 De La Rosi\u00e8re 2",
    "sg:city":"Estavayer-le-lac",
    "sg:orig_category":"Physiotherapie",
    "sg:phone":"+41 26 436 51 46",
    "sg:postcode":"1470",
    "sg:province":"Fribourg",
    "wof:name":"Jean-marie & Angela Cuennet Physioth\u00e9rapie",
    "wof:placetype":"venue"
},
  "geometry": {"coordinates":[7.162648201,46.7755470276],"type":"Point"}
}