{
  "type": "Feature",
  "properties": {
    "iso:country":"CH",
    "sg:address":"Seestrasse 14",
    "sg:city":"Thun",
    "sg:orig_category":"Detailhandel mit elektrischen Haushalts-,Radio U Fernsehger\u00e4ten sowie Musikinstrumenten",
    "sg:postcode":"3600",
    "sg:province":"Bern",
    "wof:name":"At Car Design Arn T.",
    "wof:placetype":"venue"
},
  "geometry": {"coordinates":[7.317527771,47.1007652283],"type":"Point"}
}