{
  "type": "Feature",
  "properties": {
    "iso:country":"CH",
    "sg:address":"Rue Du Levant 99",
    "sg:city":"Martigny",
    "sg:orig_category":"Grosshandel mit Wein U Spirituosen Lagerung",
    "sg:phone":"+41 27 322 12 88",
    "sg:postcode":"1920",
    "sg:province":"Valais",
    "wof:name":"Cevins Sa",
    "wof:placetype":"venue"
},
  "geometry": {"coordinates":[7.085586071,46.1017112732],"type":"Point"}
}