{
  "type": "Feature",
  "properties": {
    "iso:country":"CH",
    "sg:address":"Schachenstrasse 3",
    "sg:city":"Hochfelden",
    "sg:orig_category":"Elektroinstallation",
    "sg:phone":"+41 18609310",
    "sg:postcode":"8182",
    "sg:province":"Z\u00fcrich",
    "wof:name":"Elektro Oberholzer",
    "wof:placetype":"venue"
},
  "geometry": {"coordinates":[8.5149002075,47.5238342285],"type":"Point"}
}