{
  "type": "Feature",
  "properties": {
    "iso:country":"CH",
    "sg:address":"Bois-de-vaux Cimeti\u00e8re 3",
    "sg:city":"Lausanne",
    "sg:orig_category":"Detailhandel mit Bekleidung",
    "sg:postcode":"1007",
    "sg:province":"Vaud",
    "wof:name":"Gaudard, Christian",
    "wof:placetype":"venue"
},
  "geometry": {"coordinates":[6.6006,46.52282],"type":"Point"}
}