{
  "type": "Feature",
  "properties": {
    "addr:full":"K\u00fcrzestrasse 5 Schmerikon St. Gallen 8716",
    "addr:housenumber":"5",
    "addr:postcode":"8716",
    "addr:street":"Kuerzestrasse",
    "iso:country":"CH",
    "sg:address":"K\u00fcrzestrasse 5",
    "sg:city":"Schmerikon",
    "sg:orig_category":"Architektur U Ingenieurb\u00fcros Geometerb\u00fcros",
    "sg:phone":"+41 21 921 68 93",
    "sg:postcode":"8716",
    "sg:province":"St. Gallen",
    "wof:name":"Efa+c Ing\u00e9nieurs G\u00e9om\u00e8tres Officiels Sa",
    "wof:placetype":"venue"
},
  "geometry": {"coordinates":[6.837631,46.467785],"type":"Point"}
}