{
  "type": "Feature",
  "properties": {
    "iso:country":"CH",
    "sg:address":"8461",
    "sg:city":"Oerlingen",
    "sg:orig_category":"Sportvereine Sch\u00fctzen",
    "sg:phone":"+41 31 791 38 28",
    "sg:postcode":"8461",
    "sg:province":"Z\u00fcrich",
    "wof:name":"Feldsch\u00fctzengesellschaft",
    "wof:placetype":"venue"
},
  "geometry": {"coordinates":[8.6766395569,47.6217002869],"type":"Point"}
}