{
  "type": "Feature",
  "properties": {
    "iso:country":"CH",
    "sg:address":"Kramgasse 65",
    "sg:city":"Bern",
    "sg:orig_category":"Detailhandel mit Damenbekleidung Detailhandel mit S\u00e4uglings U Kinderbekleidung",
    "sg:phone":"+41 31 311 66 47",
    "sg:postcode":"3011",
    "sg:province":"Bern",
    "wof:name":"Urs Aeschimann Ag B\u00e9b\u00e9-haus Zur Goldenen Wiege",
    "wof:placetype":"venue"
},
  "geometry": {"coordinates":[7.4489469528,46.94789505],"type":"Point"}
}