{
  "type": "Feature",
  "properties": {
    "iso:country":"CH",
    "sg:address":"Rue Cingria 7",
    "sg:city":"Gen\u00e8ve",
    "sg:orig_category":"Grosshandel mit sonstigen Nahrungsmitteln",
    "sg:phone":"+41 22 320 58 24",
    "sg:postcode":"1205",
    "sg:province":"Gen\u00e8ve",
    "wof:name":"Tony Loria Import-export",
    "wof:placetype":"venue"
},
  "geometry": {"coordinates":[6.1460847855,46.1932258606],"type":"Point"}
}