{
  "type": "Feature",
  "properties": {
    "iso:country":"CH",
    "sg:address":"R\u00f6merstrasse 49 4153 Reinach Bl. Postfach",
    "sg:city":"Frenkendorf",
    "sg:orig_category":"Herstellung von Hebezeugen U F\u00f6rdermitteln",
    "sg:phone":"+41 61 902 11 05",
    "sg:postcode":"4402",
    "sg:province":"Basel-Landschaft",
    "wof:name":"Mdrs Gmbh Dienstleistungen Im Bereich Industriemontagen, Bes. F\u00f6rdertechnik Usw",
    "wof:placetype":"venue"
},
  "geometry": {"coordinates":[7.5964150429,47.4923057556],"type":"Point"}
}