{
  "type": "Feature",
  "properties": {
    "iso:country":"CH",
    "sg:address":"Usterstrasse 30",
    "sg:city":"D\u00fcbendorf",
    "sg:orig_category":"Detailhandel mit Brillen U anderen Sehhilfen",
    "sg:phone":"+41 18201900",
    "sg:postcode":"8600",
    "sg:province":"Z\u00fcrich",
    "wof:name":"Manfred Kaune Brillenstudio",
    "wof:placetype":"venue"
},
  "geometry": {"coordinates":[8.62109,47.396595],"type":"Point"}
}