{
  "type": "Feature",
  "properties": {
    "iso:country":"CH",
    "sg:address":"R\u00f6ssligasse 22",
    "sg:city":"Gelterkinden",
    "sg:orig_category":"Herstellung von k\u00e4lte U lufttechnischen Erzeugnissen f\u00fcr gewerbliche Zwecke Installation von Heizung",
    "sg:phone":"+41 61 981 44 08",
    "sg:postcode":"4460",
    "sg:province":"Basel-Landschaft",
    "wof:name":"Lanz Otto Ag",
    "wof:placetype":"venue"
},
  "geometry": {"coordinates":[7.8545789719,47.465133667],"type":"Point"}
}