{
  "type": "Feature",
  "properties": {
    "iso:country":"CH",
    "sg:address":"Hauptstrasse 35",
    "sg:city":"Einsiedeln",
    "sg:orig_category":"Detailhandel mit Sportartikeln Fachdetailhandel in Verkaufsr\u00e4umen",
    "sg:phone":"+41 55 412 19 80",
    "sg:postcode":"8840",
    "sg:province":"Schwyz",
    "wof:name":"Sch\u00f6nb\u00e4chler Sport",
    "wof:placetype":"venue"
},
  "geometry": {"coordinates":[8.7467594147,47.1273117065],"type":"Point"}
}