{
  "type": "Feature",
  "properties": {
    "iso:country":"CH",
    "sg:address":"Rue Des Eaux-vives 45",
    "sg:city":"Gen\u00e8ve",
    "sg:orig_category":"Detailhandel mit Blumen U Pflanzen",
    "sg:phone":"+41 22 736 35 89",
    "sg:postcode":"1207",
    "sg:province":"Gen\u00e8ve",
    "wof:name":"Minaflor Commerce De Fleurs",
    "wof:placetype":"venue"
},
  "geometry": {"coordinates":[6.15868,46.204357],"type":"Point"}
}