{
  "type": "Feature",
  "properties": {
    "iso:country":"CH",
    "sg:address":"Chemin D'orjobet 23",
    "sg:city":"Vessy",
    "sg:orig_category":"G\u00fcterbef\u00f6rderung im Strassenverkehr",
    "sg:phone":"+41 22 784 21 96",
    "sg:postcode":"1234",
    "sg:province":"Gen\u00e8ve",
    "wof:name":"Michel Dupertuis Service Voirie & Transports",
    "wof:placetype":"venue"
},
  "geometry": {"coordinates":[6.1582798958,46.1719703674],"type":"Point"}
}