{
  "type": "Feature",
  "properties": {
    "iso:country":"CH",
    "sg:address":"Stockenstrasse 37",
    "sg:city":"Rebstein",
    "sg:orig_category":"Kaminfeger",
    "sg:phone":"+41 71 777 11 61",
    "sg:postcode":"9445",
    "sg:province":"St. Gallen",
    "wof:name":"Armin Buschor Kaminfegermeister",
    "wof:placetype":"venue"
},
  "geometry": {"coordinates":[9.5901947021,47.3957023621],"type":"Point"}
}