{
  "type": "Feature",
  "properties": {
    "iso:country":"CH",
    "sg:address":"Rychenbergstrasse 310",
    "sg:city":"Stadel(winterthur)",
    "sg:orig_category":"Herstellung von Wellpapier U pappe sowie von Verpackungsmitteln aus Papier, Karton U Pappe",
    "sg:phone":"+41 34 445 61 41",
    "sg:postcode":"8404",
    "sg:province":"Z\u00fcrich",
    "wof:name":"Jwg Faltboxen Ag Verpackungen Aus Wellkarton U Karton; Produktion, Handel",
    "wof:placetype":"venue"
},
  "geometry": {"coordinates":[7.5669631958,47.0952301025],"type":"Point"}
}