{
  "type": "Feature",
  "properties": {
    "iso:country":"CH",
    "sg:address":"2906",
    "sg:city":"Chevenez",
    "sg:orig_category":"Schmieden",
    "sg:phone":"+41 32 476 63 16",
    "sg:postcode":"2906",
    "sg:province":"Jura",
    "wof:name":"Joseph Petitat Mar\u00e9chalerie",
    "wof:placetype":"venue"
},
  "geometry": {"coordinates":[6.9999499321,47.3914299011],"type":"Point"}
}