{
  "type": "Feature",
  "properties": {
    "iso:country":"CH",
    "sg:address":"Tramstrasse 7 5034 Suhr. Postfach",
    "sg:city":"Suhr",
    "sg:orig_category":"Softwareentwicklung U beratung",
    "sg:postcode":"5034",
    "sg:province":"Aargau",
    "wof:name":"Newcom Computer, Th. Roth",
    "wof:placetype":"venue"
},
  "geometry": {"coordinates":[8.1680831909,47.2733612061],"type":"Point"}
}