{
  "type": "Feature",
  "properties": {
    "iso:country":"CH",
    "sg:address":"Dorfstrasse 52",
    "sg:city":"Signau",
    "sg:orig_category":"Detailhandel mit Fleisch U Fleischwaren Grosshandel mit lebenden Tieren",
    "sg:phone":"+41 34 497 11 20",
    "sg:postcode":"3534",
    "sg:province":"Bern",
    "wof:name":"Dorfmetzg W\u00fcthrich",
    "wof:placetype":"venue"
},
  "geometry": {"coordinates":[7.7249321938,46.9204292297],"type":"Point"}
}