{
  "type": "Feature",
  "properties": {
    "iso:country":"CH",
    "sg:address":"Gare Avenue De La 22",
    "sg:city":"Vouvry",
    "sg:orig_category":"Sanit\u00e4r, Heizungs U L\u00fcftungsinstallation",
    "sg:phone":"+41 24 482 05 05",
    "sg:postcode":"1896",
    "sg:province":"Valais",
    "wof:name":"Parchet Fr\u00e8res Sa",
    "wof:placetype":"venue"
},
  "geometry": {"coordinates":[6.8908228874,46.3360748291],"type":"Point"}
}