{
  "type": "Feature",
  "properties": {
    "iso:country":"CH",
    "sg:address":"Rigiblickstrasse",
    "sg:city":"Weggis",
    "sg:orig_category":"Sonstiger Grosshandel",
    "sg:phone":"+41 79 696 13 66",
    "sg:postcode":"6353",
    "sg:province":"Luzern",
    "wof:name":"Ks Handels Ag",
    "wof:placetype":"venue"
},
  "geometry": {"coordinates":[9.5371379852,47.3786277771],"type":"Point"}
}