{
  "type": "Feature",
  "properties": {
    "iso:country":"CH",
    "sg:address":"Im D\u00f6rfli 20",
    "sg:city":"Dietikon",
    "sg:orig_category":"Politische Parteien Evangelische Volkspartei",
    "sg:phone":"+41 17410012",
    "sg:postcode":"8953",
    "sg:province":"Z\u00fcrich",
    "wof:name":"Evp Bezirkspartei Dietikon",
    "wof:placetype":"venue"
},
  "geometry": {"coordinates":[8.4049062729,47.4002914429],"type":"Point"}
}