{
  "type": "Feature",
  "properties": {
    "addr:full":"Hofstrasse 5 Weesen St. Gallen 8872",
    "addr:housenumber":"5",
    "addr:postcode":"8872",
    "addr:street":"Hofstrasse",
    "iso:country":"CH",
    "sg:address":"Hofstrasse 5",
    "sg:city":"Weesen",
    "sg:orig_category":"Datenverarbeitungsdienste Softwareentwicklung U beratung",
    "sg:postcode":"8872",
    "sg:province":"St. Gallen",
    "wof:name":"Osd.ch Gmbh",
    "wof:placetype":"venue"
},
  "geometry": {"coordinates":[9.103124,47.135094],"type":"Point"}
}