{
  "type": "Feature",
  "properties": {
    "iso:country":"CH",
    "sg:address":"Veyrot Rue De 39 1217 Meyrin. Postfach",
    "sg:city":"Meyrin",
    "sg:orig_category":"Pensionskassen",
    "sg:postcode":"1217",
    "sg:province":"Gen\u00e8ve",
    "wof:name":"Fondation Pour La Pr\u00e9voyance Internationale De Agilent Technologies",
    "wof:placetype":"venue"
},
  "geometry": {"coordinates":[6.0638680458,46.2286682129],"type":"Point"}
}