{
  "type": "Feature",
  "properties": {
    "iso:country":"CH",
    "sg:address":"Lyon-strasse 31 4053 Basel. Postfach",
    "sg:city":"Basel",
    "sg:orig_category":"Saunas, Solarien, Fitnesszentren U \u00e4hnliches",
    "sg:phone":"+41 61 331 90 91",
    "sg:postcode":"4051",
    "sg:province":"Basel-Stadt",
    "wof:name":"Lb Linea Bastos Waren, Bes. Gesundheits- Massagesessel; Im, Export, Verkauf",
    "wof:placetype":"venue"
},
  "geometry": {"coordinates":[7.6072292328,47.5346069336],"type":"Point"}
}