{
  "type": "Feature",
  "properties": {
    "iso:country":"CH",
    "sg:address":"Hagenholzstrasse 24 8302 Kloten. Postfach",
    "sg:city":"Kloten",
    "sg:orig_category":"Grosshandel mit pharmazeutischen Erzeugnissen, medizinischen U orthop\u00e4dischen Artikeln",
    "sg:postcode":"8302",
    "sg:province":"Z\u00fcrich",
    "wof:name":"Swissquality-herbs, Torricelli & Langer Kr\u00e4uter, -pr\u00e4parate Schweizerischer Herkunft \u00fcbers Internet; Verkauf",
    "wof:placetype":"venue"
},
  "geometry": {"coordinates":[8.5934009552,47.4455757141],"type":"Point"}
}