{
  "type": "Feature",
  "properties": {
    "iso:country":"CH",
    "sg:address":"Hammerstrasse",
    "sg:city":"F\u00fcllinsdorf",
    "sg:orig_category":"Detailhandel mit Waren verschiedener Art, Hauptrichtung Nahrungsmittel Sonstiger Detailhandel mit Me",
    "sg:phone":"+41 61 901 87 00",
    "sg:postcode":"4414",
    "sg:province":"Basel-Landschaft",
    "wof:name":"M-do-it-yourself Sch\u00f6nthal",
    "wof:placetype":"venue"
},
  "geometry": {"coordinates":[7.7245697975,47.4999465942],"type":"Point"}
}