{
  "type": "Feature",
  "properties": {
    "iso:country":"CH",
    "sg:address":"Hubelweg 28",
    "sg:city":"Sarnen",
    "sg:orig_category":"Herstellung von sonstigen elektrischen Ausr\u00fcstungen",
    "sg:postcode":"6060",
    "sg:province":"Obwalden",
    "wof:name":"Elprotech Gmbh",
    "wof:placetype":"venue"
},
  "geometry": {"coordinates":[8.2546100616,46.8955612183],"type":"Point"}
}