{
  "type": "Feature",
  "properties": {
    "iso:country":"CH",
    "sg:address":"Eggb\u00fchlstrasse 20",
    "sg:city":"Z\u00fcrich",
    "sg:classifiers":[
        {
            "category":"Building & Trades",
            "subcategory":"Electrical",
            "type":"Services"
        }
    ],
    "sg:phone":"+41 13053030",
    "sg:postcode":"8050",
    "sg:province":"Z\u00fcrich",
    "sg:tags":[
        "engineering",
        "construction",
        "architectural",
        "software"
    ],
    "wof:name":"Cubus Software Ag",
    "wof:placetype":"venue"
},
  "geometry": {"coordinates":[8.542979,47.41637],"type":"Point"}
}