{
  "type": "Feature",
  "properties": {
    "iso:country":"CH",
    "sg:address":"Schachenstrasse 77",
    "sg:city":"Jona",
    "sg:orig_category":"Dienstleistungen von Beteiligungsgesellschaften",
    "sg:phone":"+41 55 221 61 11",
    "sg:postcode":"8645",
    "sg:province":"St. Gallen",
    "wof:name":"Geberit Verwaltungs Ag",
    "wof:placetype":"venue"
},
  "geometry": {"coordinates":[8.8423900604,47.2252693176],"type":"Point"}
}