{
  "type": "Feature",
  "properties": {
    "iso:country":"CH",
    "sg:address":"Holeeweg 19",
    "sg:city":"Allschwil",
    "sg:orig_category":"K\u00fcnstlerische Schulen",
    "sg:phone":"+41 61 481 38 58",
    "sg:postcode":"4123",
    "sg:province":"Basel-Landschaft",
    "wof:name":"Maria Kullmann Musikschule",
    "wof:placetype":"venue"
},
  "geometry": {"coordinates":[7.5411448479,47.5475692749],"type":"Point"}
}