{
  "type": "Feature",
  "properties": {
    "iso:country":"CH",
    "sg:address":"Goffers",
    "sg:city":"R\u00fceggisberg",
    "sg:orig_category":"S\u00e4ge, Hobel U Holzimpr\u00e4gnierwerke S\u00e4gewerke",
    "sg:phone":"+41 79 667 34 63",
    "sg:postcode":"3088",
    "sg:province":"Bern",
    "wof:name":"Fritz Z\u00fcrcher",
    "wof:placetype":"venue"
},
  "geometry": {"coordinates":[7.4510750771,46.8234825134],"type":"Point"}
}