{
  "type": "Feature",
  "properties": {
    "iso:country":"CH",
    "sg:address":"Rietstrasse 11 8108 D\u00e4llikon. Postfach",
    "sg:city":"D\u00e4llikon",
    "sg:orig_category":"Unclassifiable Establishments",
    "sg:postcode":"8108",
    "sg:province":"Z\u00fcrich",
    "wof:name":"Kran-m\u00fcller Transport Gmbh Transporte, Kranarbeiten Unter Einsatz Von Lastwagenkranen",
    "wof:placetype":"venue"
},
  "geometry": {"coordinates":[8.4320430756,47.4482307434],"type":"Point"}
}