{
  "type": "Feature",
  "properties": {
    "iso:country":"CH",
    "sg:address":"Via Sorengo 6",
    "sg:city":"Lugano",
    "sg:orig_category":"Grosshandel mit sonstigen Gebrauchs U Verbrauchsg\u00fctern Grosshandel mit sonstigen Halbwaren",
    "sg:phone":"+41 91 960 17 70",
    "sg:postcode":"6900",
    "sg:province":"Ticino",
    "wof:name":"3p Pulp Paper & Packaging Ltd, Dublino, Succursale Di Lugano",
    "wof:placetype":"venue"
},
  "geometry": {"coordinates":[8.9437208176,46.0052261353],"type":"Point"}
}