{
  "type": "Feature",
  "properties": {
    "iso:country":"CH",
    "sg:address":"Haltelhusstrasse 9402 M\u00f6rschwil. Postfach 80",
    "sg:city":"M\u00f6rschwil",
    "sg:orig_category":"Grosshandel mit Blumen U Pflanzen Herstellung von Werkzeugen",
    "sg:phone":"+41 71 866 10 72",
    "sg:postcode":"9402",
    "sg:province":"St. Gallen",
    "wof:name":"Faller Ag",
    "wof:placetype":"venue"
},
  "geometry": {"coordinates":[9.4331741333,47.4580116272],"type":"Point"}
}