{
  "type": "Feature",
  "properties": {
    "iso:country":"CH",
    "sg:address":"Weiherhof 16 8604 Volketswil. Postfach",
    "sg:city":"Volketswil",
    "sg:orig_category":"Buchf\u00fchrung Wirtschaftspr\u00fcfung, Steuerberatung U Treuhand",
    "sg:phone":"+41 19972722",
    "sg:postcode":"8604",
    "sg:province":"Z\u00fcrich",
    "wof:name":"Gravis Gmbh Kundenbuchhaltungen, Administrationen. Schulungen Im Kaufm\u00e4nnischen Bereich",
    "wof:placetype":"venue"
},
  "geometry": {"coordinates":[8.698533,47.391487],"type":"Point"}
}