{
  "type": "Feature",
  "properties": {
    "iso:country":"CH",
    "sg:address":"Orpundstrasse 27",
    "sg:city":"Biel/bienne",
    "sg:orig_category":"Detailhandel mit Fleisch U Fleischwaren",
    "sg:phone":"+41 32 341 32 58",
    "sg:postcode":"2504",
    "sg:province":"Bern",
    "wof:name":"Imfeld Ren\u00e9.",
    "wof:placetype":"venue"
},
  "geometry": {"coordinates":[7.2761979103,47.1434555054],"type":"Point"}
}