{
  "type": "Feature",
  "properties": {
    "iso:country":"CH",
    "sg:address":"Am See",
    "sg:city":"Leissigen",
    "sg:orig_category":"Sportvereine Eissport Eishockey",
    "sg:phone":"+41 33 847 10 35",
    "sg:postcode":"3706",
    "sg:province":"Bern",
    "wof:name":"Eishockey-club Beatenberg",
    "wof:placetype":"venue"
},
  "geometry": {"coordinates":[7.7740898132,46.6546554565],"type":"Point"}
}