{
  "type": "Feature",
  "properties": {
    "iso:country":"CH",
    "sg:address":"Route Acacias 6",
    "sg:city":"Gen\u00e8ve",
    "sg:classifiers":[
        {
            "category":"Banks & Credit Unions",
            "subcategory":"Bank",
            "type":"Services"
        }
    ],
    "sg:postcode":"1227",
    "sg:province":"Gen\u00e8ve",
    "wof:name":"Societe Mandataire Sa",
    "wof:placetype":"venue"
},
  "geometry": {"coordinates":[6.142701,46.208359],"type":"Point"}
}