{
  "type": "Feature",
  "properties": {
    "iso:country":"CH",
    "sg:address":"Gerliswilstrasse 16",
    "sg:city":"Emmenbr\u00fccke",
    "sg:orig_category":"Arztpraxen",
    "sg:phone":"+41 41 260 11 77",
    "sg:postcode":"6020",
    "sg:province":"Luzern",
    "wof:name":"Dr.med.mario Legat Spezialarzt Fmh",
    "wof:placetype":"venue"
},
  "geometry": {"coordinates":[8.280275,47.071465],"type":"Point"}
}