{
  "type": "Feature",
  "properties": {
    "iso:country":"CH",
    "sg:address":"Rue Des C\u00e8dres 7",
    "sg:city":"Sitten",
    "sg:orig_category":"Detailhandel mit Geschenkartikeln U Souvenirs Gesundheitswesen",
    "sg:phone":"+41 27 203 23 80",
    "sg:postcode":"1950",
    "sg:province":"Valais",
    "wof:name":"Mirella Andr\u00e9",
    "wof:placetype":"venue"
},
  "geometry": {"coordinates":[7.3595228195,46.2302436829],"type":"Point"}
}