{
  "type": "Feature",
  "properties": {
    "iso:country":"CH",
    "sg:address":"Heidenhubelstrasse 22",
    "sg:city":"Solothurn",
    "sg:orig_category":"Interessenvertretungen U sonstige Vereinigungen",
    "sg:postcode":"4500",
    "sg:province":"Solothurn",
    "wof:name":"Skolv",
    "wof:placetype":"venue"
},
  "geometry": {"coordinates":[7.5218491554,47.213104248],"type":"Point"}
}