{
  "type": "Feature",
  "properties": {
    "iso:country":"CH",
    "sg:address":"Gen\u00e8ve Rue De 52 1225 Ch\u00eane-bourg. Postfach",
    "sg:city":"Gen\u00e8ve",
    "sg:orig_category":"Mit dem Versicherungsgewerbe verbundene T\u00e4tigkeiten",
    "sg:postcode":"1201",
    "sg:province":"Gen\u00e8ve",
    "wof:name":"Broker Line Sa",
    "wof:placetype":"venue"
},
  "geometry": {"coordinates":[6.1965842247,46.1937446594],"type":"Point"}
}