{
  "type": "Feature",
  "properties": {
    "iso:country":"CH",
    "sg:address":"Avenue Du Petit-senn 51",
    "sg:city":"Ch\u00eane-bourg",
    "sg:orig_category":"Blumen U Zierpflanzenbau",
    "sg:phone":"+41 22 348 73 13",
    "sg:postcode":"1225",
    "sg:province":"Gen\u00e8ve",
    "wof:name":"Otto Strahm",
    "wof:placetype":"venue"
},
  "geometry": {"coordinates":[6.197611,46.190983],"type":"Point"}
}