{
  "type": "Feature",
  "properties": {
    "iso:country":"CH",
    "sg:address":"Hauptstrasse 6 4146 Hochwald. Postfach",
    "sg:city":"Hochwald",
    "sg:orig_category":"Grosshandel mit Getr\u00e4nken Grosshandel mit Wein U Spirituosen",
    "sg:phone":"+41 55 442 36 03",
    "sg:postcode":"4146",
    "sg:province":"Solothurn",
    "wof:name":"Weinkeller 3 Kapuziner Ag",
    "wof:placetype":"venue"
},
  "geometry": {"coordinates":[8.8614835739,47.1903953552],"type":"Point"}
}