{
  "type": "Feature",
  "properties": {
    "iso:country":"CH",
    "sg:address":"Oberdorf 42",
    "sg:city":"Birrwil",
    "sg:orig_category":"Herstellung von Hebezeugen U F\u00f6rdermitteln Mechanische Werkst\u00e4tten",
    "sg:phone":"+41 62 772 16 57",
    "sg:postcode":"5708",
    "sg:province":"Aargau",
    "wof:name":"M\u00fcller Stapler Service Gmbh",
    "wof:placetype":"venue"
},
  "geometry": {"coordinates":[8.1937427521,47.2878189087],"type":"Point"}
}