{
  "type": "Feature",
  "properties": {
    "iso:country":"CH",
    "sg:address":"Reitschulstrasse 5 2500 Biel/bienne. Postfach",
    "sg:city":"Biel/bienne",
    "sg:orig_category":"Gesundheitswesen",
    "sg:postcode":"2502",
    "sg:province":"Bern",
    "wof:name":"Institut Perret Esther",
    "wof:placetype":"venue"
},
  "geometry": {"coordinates":[7.2487559319,47.140712738],"type":"Point"}
}