{
  "type": "Feature",
  "properties": {
    "iso:country":"CH",
    "sg:address":"Im L\u00e4tten 2",
    "sg:city":"Adliswil",
    "sg:orig_category":"Vereine Musik/Blasmusik",
    "sg:phone":"+41 76 335 57 16",
    "sg:postcode":"8134",
    "sg:province":"Z\u00fcrich",
    "wof:name":"Musikverein Harmonie Wollishofen",
    "wof:placetype":"venue"
},
  "geometry": {"coordinates":[8.5348520279,47.3275642395],"type":"Point"}
}