{
  "type": "Feature",
  "properties": {
    "iso:country":"CH",
    "sg:address":"Eichwaldstrasse 13 6005 Luzern. Postfach",
    "sg:city":"Luzern",
    "sg:orig_category":"Erschliessung von Grundst\u00fccken",
    "sg:phone":"+41 41 319 92 92",
    "sg:postcode":"6003",
    "sg:province":"Luzern",
    "wof:name":"Immobilien-genossenschaft Eichwald",
    "wof:placetype":"venue"
},
  "geometry": {"coordinates":[8.3009052277,47.0382766724],"type":"Point"}
}