{
  "type": "Feature",
  "properties": {
    "iso:country":"CH",
    "sg:address":"Birkenweg 5",
    "sg:city":"Stilli",
    "sg:orig_category":"Herstellung von Fenstern U T\u00fcren aus Holz Herstellung von Konstruktionsteilen, Fertigbauteilen U Aus",
    "sg:phone":"+41 56 284 14 23",
    "sg:postcode":"5233",
    "sg:province":"Aargau",
    "wof:name":"Schreinerei Siegenthaler Samuel Ag",
    "wof:placetype":"venue"
},
  "geometry": {"coordinates":[8.2320661545,47.5146484375],"type":"Point"}
}