{
  "type": "Feature",
  "properties": {
    "iso:country":"CH",
    "sg:address":"Via San Gottardo 119b 6648 Minusio. Postfach Caselle Postale 1617",
    "sg:city":"Minusio",
    "sg:orig_category":"Detailhandel mit Gebrauchtwaren in Verkaufsr\u00e4umen",
    "sg:phone":"+41 91 743 41 34",
    "sg:postcode":"6648",
    "sg:province":"Ticino",
    "wof:name":"Mercatino Brockenhaus Peter Gut",
    "wof:placetype":"venue"
},
  "geometry": {"coordinates":[8.814997673,46.1779403687],"type":"Point"}
}