{
  "type": "Feature",
  "properties": {
    "iso:country":"CH",
    "sg:address":"3401 Burgdorf. Postfach 531",
    "sg:city":"Burgdorf",
    "sg:orig_category":"Sportvereine Ballsport Fussball",
    "sg:phone":"+41 34 422 04 67",
    "sg:postcode":"3401",
    "sg:province":"Bern",
    "wof:name":"Fc Kyburg",
    "wof:placetype":"venue"
},
  "geometry": {"coordinates":[7.6269898415,47.056438446],"type":"Point"}
}