{
  "type": "Feature",
  "properties": {
    "iso:country":"CH",
    "sg:address":"Br\u00fcckfeldstrasse 19 3012 Bern. Postfach",
    "sg:city":"Bern",
    "sg:orig_category":"Buchf\u00fchrung Rechtsberatung",
    "sg:phone":"+41 31 305 66 55",
    "sg:postcode":"3005",
    "sg:province":"Bern",
    "wof:name":"Iurconsult-bern Sch\u00e4ppi Walter Rechtsberatung F\u00fcr Private Usw",
    "wof:placetype":"venue"
},
  "geometry": {"coordinates":[7.435727,46.95615],"type":"Point"}
}