{
  "type": "Feature",
  "properties": {
    "iso:country":"CH",
    "sg:address":"Hauptstr. 417",
    "sg:city":"Murgenthal",
    "sg:orig_category":"Pensionskassen",
    "sg:postcode":"4853",
    "sg:province":"Aargau",
    "wof:name":"Personalf\u00fcrsorgestiftung Der Lanz Electro Ag",
    "wof:placetype":"venue"
},
  "geometry": {"coordinates":[7.8295550346,47.2646217346],"type":"Point"}
}