{
  "type": "Feature",
  "properties": {
    "iso:country":"CH",
    "sg:address":"Zurigo Via 35",
    "sg:city":"Lugano",
    "sg:orig_category":"Fachdetailhandel mit pharmazeutischen Produkten",
    "sg:phone":"+41 91 923 15 07",
    "sg:postcode":"6900",
    "sg:province":"Ticino",
    "wof:name":"Mc Kruger & Partners Limited, Tortola (b.v.i.), Succursale Di Lugano",
    "wof:placetype":"venue"
},
  "geometry": {"coordinates":[8.9507932663,46.0102005005],"type":"Point"}
}