{
  "type": "Feature",
  "properties": {
    "iso:country":"CH",
    "sg:address":"Gartenstrasse 3",
    "sg:city":"Zug",
    "sg:orig_category":"Fachdetailhandel mit pharmazeutischen Produkten Grosshandel mit pharmazeutischen Erzeugnissen",
    "sg:phone":"+41 41 710 30 55",
    "sg:postcode":"6300",
    "sg:province":"Zug",
    "wof:name":"Coro Medica Handels Ag",
    "wof:placetype":"venue"
},
  "geometry": {"coordinates":[8.5148210526,47.1700744629],"type":"Point"}
}