{
  "type": "Feature",
  "properties": {
    "addr:full":"Via Marconi 4 6900 Lugano. Postfach Caselle Postale 3079 Lugano Ticino 6900",
    "addr:housenumber":"4",
    "addr:postcode":"6900;postale 3079;6900",
    "addr:street":"Via Marconi",
    "iso:country":"CH",
    "sg:address":"Via Marconi 4 6900 Lugano. Postfach Caselle Postale 3079",
    "sg:city":"Lugano",
    "sg:orig_category":"Advokaturb\u00fcros Notariate",
    "sg:phone":"+41 79 239 10 58",
    "sg:postcode":"6900",
    "sg:province":"Ticino",
    "wof:name":"Gianrico Moor Studio Legale & Notarile",
    "wof:placetype":"venue"
},
  "geometry": {"coordinates":[8.954682,46.003967],"type":"Point"}
}