{
  "type": "Feature",
  "properties": {
    "iso:country":"CH",
    "sg:address":"Kirch\u00e4gerten 3",
    "sg:city":"Blauen",
    "sg:classifiers":[
        {
            "category":"Professional",
            "subcategory":"Advertising",
            "type":"Services"
        }
    ],
    "sg:phone":"+41 61 761 41 41",
    "sg:postcode":"4223",
    "sg:province":"Basel-Landschaft",
    "sg:tags":[
        "information",
        "medium",
        "communication"
    ],
    "wof:name":"Schweizer Baudokumentation Docu Ag",
    "wof:placetype":"venue"
},
  "geometry": {"coordinates":[7.516187,47.452454],"type":"Point"}
}