{
  "type": "Feature",
  "properties": {
    "iso:country":"CH",
    "sg:address":"Kirchlindachstrasse 7",
    "sg:city":"Zollikofen",
    "sg:orig_category":"Gesundheitswesen",
    "sg:phone":"+41 17611946",
    "sg:postcode":"3052",
    "sg:province":"Bern",
    "wof:name":"Uf Bau 365 Gava Moreno",
    "wof:placetype":"venue"
},
  "geometry": {"coordinates":[8.4488096237,47.2799491882],"type":"Point"}
}