{
  "type": "Feature",
  "properties": {
    "iso:country":"CH",
    "sg:address":"Im Himmelrich 11 8967 Widen. Postfach",
    "sg:city":"Widen",
    "sg:orig_category":"Grosshandel mit Maschinen U Ausr\u00fcstungen Herstellung von Werkzeugmaschinen",
    "sg:phone":"+41 56 633 88 71",
    "sg:postcode":"8967",
    "sg:province":"Aargau",
    "wof:name":"Beck + Pfiffner Ag",
    "wof:placetype":"venue"
},
  "geometry": {"coordinates":[8.3636407852,47.3704185486],"type":"Point"}
}