{
  "type": "Feature",
  "properties": {
    "iso:country":"CH",
    "sg:address":"M\u00fcnsterberg 10 4051 Basel. Postfach",
    "sg:city":"Basel",
    "sg:orig_category":"Advokaturb\u00fcros",
    "sg:phone":"+41 61 272 33 58",
    "sg:postcode":"4001",
    "sg:province":"Basel-Stadt",
    "wof:name":"Alfred L. Grauwiler Advokaturb\u00fcro",
    "wof:placetype":"venue"
},
  "geometry": {"coordinates":[7.591288,47.555401],"type":"Point"}
}