{
  "type": "Feature",
  "properties": {
    "iso:country":"CH",
    "sg:address":"Kilchbergstrasse 23 8134 Adliswil. Postfach",
    "sg:city":"Adliswil",
    "sg:orig_category":"Unternehmensberatung",
    "sg:postcode":"8134",
    "sg:province":"Z\u00fcrich",
    "wof:name":"Gee Jay, Gebhart + Haas Unternehmensberatung",
    "wof:placetype":"venue"
},
  "geometry": {"coordinates":[8.5309743881,47.313331604],"type":"Point"}
}