{
  "type": "Feature",
  "properties": {
    "iso:country":"CH",
    "sg:address":"Kornackerstrasse 14",
    "sg:city":"Frenkendorf",
    "sg:orig_category":"Finanzierungsinstitutionen",
    "sg:postcode":"4402",
    "sg:province":"Basel-Landschaft",
    "wof:name":"Arbila Publicit\u00e9 Sa",
    "wof:placetype":"venue"
},
  "geometry": {"coordinates":[9.1283597946,46.2375984192],"type":"Point"}
}