{
  "type": "Feature",
  "properties": {
    "iso:country":"CH",
    "sg:address":"Gotthelfstr. 52",
    "sg:city":"Burgdorf",
    "sg:orig_category":"Softwareentwicklung U beratung",
    "sg:postcode":"3400",
    "sg:province":"Bern",
    "wof:name":"Medinfo Systems K\u00fcnzi",
    "wof:placetype":"venue"
},
  "geometry": {"coordinates":[7.6260237694,47.0598716736],"type":"Point"}
}