{
  "type": "Feature",
  "properties": {
    "iso:country":"CH",
    "sg:address":"S\u00e4ngergasse 11",
    "sg:city":"Basel",
    "sg:orig_category":"Schreib U \u00dcbersetzungsb\u00fcros",
    "sg:phone":"+41 61 301 60 01",
    "sg:postcode":"4054",
    "sg:province":"Basel-Stadt",
    "wof:name":"Ifama Gmbh",
    "wof:placetype":"venue"
},
  "geometry": {"coordinates":[7.5718407631,47.5558357239],"type":"Point"}
}