{
  "type": "Feature",
  "properties": {
    "iso:country":"CH",
    "sg:address":"Via Stazione",
    "sg:city":"Cadempino",
    "sg:orig_category":"K\u00fcnstlerische U schriftstellerische T\u00e4tigkeiten U Darbietungen Sonstige k\u00fcnstlerische U schriftstell",
    "sg:phone":"+41 91 966 00 41",
    "sg:postcode":"6814",
    "sg:province":"Ticino",
    "wof:name":"Laboratorio Di Conservazione E Restauro A. Bocchi Sagl",
    "wof:placetype":"venue"
},
  "geometry": {"coordinates":[8.9337043762,46.0380096436],"type":"Point"}
}