{
  "type": "Feature",
  "properties": {
    "iso:country":"CH",
    "sg:address":"Ringstrasse 3",
    "sg:city":"Nidau",
    "sg:classifiers":[
        {
            "category":"Manufacturing",
            "subcategory":"Building Materials",
            "type":"Manufacturing & Wholesale Goods"
        }
    ],
    "sg:phone":"+41 32 331 85 53",
    "sg:postcode":"2560",
    "sg:province":"Bern",
    "sg:tags":[
        "decoration"
    ],
    "wof:name":"Inter Gaine Sa",
    "wof:placetype":"venue"
},
  "geometry": {"coordinates":[7.24038,47.125866],"type":"Point"}
}