{
  "type": "Feature",
  "properties": {
    "iso:country":"CH",
    "sg:address":"Leishof",
    "sg:city":"Zuzgen",
    "sg:orig_category":"Verarbeitung von Milch Verwertung von Milch",
    "sg:postcode":"4315",
    "sg:province":"Aargau",
    "wof:name":"Milchgenossenschaft Zuzgen",
    "wof:placetype":"venue"
},
  "geometry": {"coordinates":[7.879090786,47.5163574219],"type":"Point"}
}