{
  "type": "Feature",
  "properties": {
    "iso:country":"CH",
    "sg:address":"Industriestrasse 11",
    "sg:city":"Rotkreuz",
    "sg:orig_category":"Herstellung von sonstigen Maschinen f\u00fcr unspezifische Verwendung",
    "sg:phone":"+41 41 790 43 64",
    "sg:postcode":"6343",
    "sg:province":"Zug",
    "wof:name":"Hugentobler + Partner Ag Kochsysteme Hg 2000",
    "wof:placetype":"venue"
},
  "geometry": {"coordinates":[8.4310493469,47.1514205933],"type":"Point"}
}