{
  "type": "Feature",
  "properties": {
    "iso:country":"CH",
    "sg:address":"Oberdorfstrasse 15",
    "sg:city":"Mettmenstetten",
    "sg:orig_category":"Non-Classified Establishments",
    "sg:postcode":"8932",
    "sg:province":"Z\u00fcrich",
    "wof:name":"Martin Maya, Tierferienheim",
    "wof:placetype":"venue"
},
  "geometry": {"coordinates":[8.4699430466,47.2470779419],"type":"Point"}
}