{
  "type": "Feature",
  "properties": {
    "iso:country":"CH",
    "sg:address":"Hauptstrasse 82",
    "sg:city":"Sissach",
    "sg:classifiers":[
        {
            "category":"Professional",
            "subcategory":"Advertising",
            "type":"Services"
        }
    ],
    "sg:phone":"+41 61 971 66 96",
    "sg:postcode":"4450",
    "sg:province":"Basel-Landschaft",
    "sg:tags":[
        "poster"
    ],
    "wof:name":"Druckh\u00fcsli Ch. Hess Ag",
    "wof:placetype":"venue"
},
  "geometry": {"coordinates":[7.810576,47.464489],"type":"Point"}
}