{
  "type": "Feature",
  "properties": {
    "iso:country":"CH",
    "sg:address":"Weingasse 17",
    "sg:city":"Jonen",
    "sg:orig_category":"Non-Classified Establishments",
    "sg:postcode":"8916",
    "sg:province":"Aargau",
    "wof:name":"Mind Toys Andi Gasser",
    "wof:placetype":"venue"
},
  "geometry": {"coordinates":[8.3980493546,47.2936325073],"type":"Point"}
}