{
  "type": "Feature",
  "properties": {
    "iso:country":"CH",
    "sg:address":"Steinackerstrasse 41",
    "sg:city":"Kloten",
    "sg:orig_category":"Saunas, Solarien, Fitnesszentren U \u00e4hnliches Spielsalons",
    "sg:phone":"+41 18141919",
    "sg:postcode":"8302",
    "sg:province":"Z\u00fcrich",
    "wof:name":"Fitness-club 22 Ag",
    "wof:placetype":"venue"
},
  "geometry": {"coordinates":[8.6017465591,47.4481086731],"type":"Point"}
}