{
  "type": "Feature",
  "properties": {
    "iso:country":"CH",
    "sg:address":"Alte Triengerstrasse 55",
    "sg:city":"Moosleerau",
    "sg:orig_category":"Grosshandel mit lebenden Tieren",
    "sg:postcode":"5054",
    "sg:province":"Aargau",
    "wof:name":"Eggerschwiler Vinz.",
    "wof:placetype":"venue"
},
  "geometry": {"coordinates":[8.1107387543,47.1598739624],"type":"Point"}
}