{
  "type": "Feature",
  "properties": {
    "iso:country":"CH",
    "sg:address":"Rigistrasse 13",
    "sg:city":"Z\u00fcrich",
    "sg:orig_category":"Erbringung von Dienstleistungen f\u00fcr Unternehmen",
    "sg:phone":"+41 13253100",
    "sg:postcode":"8006",
    "sg:province":"Z\u00fcrich",
    "wof:name":"Target Group Ag F\u00fcr Marketing Und Kommunikation",
    "wof:placetype":"venue"
},
  "geometry": {"coordinates":[8.5488910675,47.3854827881],"type":"Point"}
}