{
  "type": "Feature",
  "properties": {
    "iso:country":"CH",
    "sg:address":"Ti\u00e8chestrasse 9",
    "sg:city":"Z\u00fcrich",
    "sg:orig_category":"Architektur U Ingenieurb\u00fcros",
    "sg:phone":"+41 13686040",
    "sg:postcode":"8037",
    "sg:province":"Z\u00fcrich",
    "wof:name":"K\u00f6hli & Partner Ag Elektro-ingenieur-b\u00fcro",
    "wof:placetype":"venue"
},
  "geometry": {"coordinates":[8.532411,47.398018],"type":"Point"}
}