{
  "type": "Feature",
  "properties": {
    "iso:country":"CH",
    "sg:address":"1528",
    "sg:city":"Praratoud",
    "sg:orig_category":"Gemeindeverwaltungen",
    "sg:phone":"+41 26 413 15 19",
    "sg:postcode":"1528",
    "sg:province":"Fribourg",
    "wof:name":"Administration Communale De Praroman-le Mouret",
    "wof:placetype":"venue"
},
  "geometry": {"coordinates":[7.1809358597,46.7404670715],"type":"Point"}
}