{
  "type": "Feature",
  "properties": {
    "iso:country":"CH",
    "sg:address":"Hohlweg 1 8645 Jona. Postfach",
    "sg:city":"Jona",
    "sg:orig_category":"Wirtschaftspr\u00fcfung, Steuerberatung U Treuhand",
    "sg:postcode":"8645",
    "sg:province":"St. Gallen",
    "wof:name":"Schicker Treuhand",
    "wof:placetype":"venue"
},
  "geometry": {"coordinates":[8.8310337067,47.2221717834],"type":"Point"}
}