{
  "type": "Feature",
  "properties": {
    "iso:country":"CH",
    "sg:address":"Kraftstrasse 11",
    "sg:city":"Basel",
    "sg:orig_category":"Herstellung von Metallerzeugnissen ohne Maschinenbau Herstellung von sonstigen Maschinen f\u00fcr unspezi",
    "sg:phone":"+41 61 322 15 17",
    "sg:postcode":"4056",
    "sg:province":"Basel-Stadt",
    "wof:name":"Walmag Ag",
    "wof:placetype":"venue"
},
  "geometry": {"coordinates":[7.5774278641,47.5724868774],"type":"Point"}
}