{
  "type": "Feature",
  "properties": {
    "iso:country":"CH",
    "sg:address":"Diamantstrasse 9",
    "sg:city":"Biel/bienne",
    "sg:orig_category":"Druck ohne Zeitungsdruck Siebdruck",
    "sg:phone":"+41 32 322 81 31",
    "sg:postcode":"2503",
    "sg:province":"Bern",
    "wof:name":"Atelier Grafico Von Gunten Hans-peter",
    "wof:placetype":"venue"
},
  "geometry": {"coordinates":[7.2511301041,47.13854599],"type":"Point"}
}