{
  "type": "Feature",
  "properties": {
    "iso:country":"CH",
    "sg:address":"Riedweg 12 6045 Meggen. Postfach 42",
    "sg:city":"Meggen",
    "sg:orig_category":"Maler U Glasergewerbe Malerei",
    "sg:phone":"+41 41 377 36 47",
    "sg:postcode":"6045",
    "sg:province":"Luzern",
    "wof:name":"Von Ah Ag, Malergesch\u00e4ft, Meggen.",
    "wof:placetype":"venue"
},
  "geometry": {"coordinates":[8.3652143478,47.050819397],"type":"Point"}
}