{
  "type": "Feature",
  "properties": {
    "iso:country":"CH",
    "sg:address":"Rue De La Servette 69 1200 Genf. Postfach",
    "sg:city":"Gen\u00e8ve",
    "sg:orig_category":"Finanzierungsinstitutionen",
    "sg:postcode":"1202",
    "sg:province":"Gen\u00e8ve",
    "wof:name":"Sofigest-finances Sa",
    "wof:placetype":"venue"
},
  "geometry": {"coordinates":[6.1326870918,46.2119865417],"type":"Point"}
}