{
  "type": "Feature",
  "properties": {
    "iso:country":"CH",
    "sg:address":"Birkenrain 4 8634 Hombrechtikon. Postfach 214",
    "sg:city":"Hombrechtikon",
    "sg:orig_category":"Wirtschaftspr\u00fcfung, Steuerberatung U Treuhand",
    "sg:phone":"+41 55 244 21 21",
    "sg:postcode":"8634",
    "sg:province":"Z\u00fcrich",
    "wof:name":"Treuhand Sven M\u00fcller, Lic. \u00e8s Sc. Comm.",
    "wof:placetype":"venue"
},
  "geometry": {"coordinates":[8.7669401169,47.2505340576],"type":"Point"}
}