{
  "type": "Feature",
  "properties": {
    "iso:country":"CH",
    "sg:address":"Chemin Du Mont 7",
    "sg:city":"Grandson",
    "sg:orig_category":"Versicherungen Generalagenturen",
    "sg:phone":"+41 79 204 19 58",
    "sg:postcode":"1422",
    "sg:province":"Vaud",
    "wof:name":"Ticino Vie Assurances Agence G\u00e9n\u00e9rale",
    "wof:placetype":"venue"
},
  "geometry": {"coordinates":[6.6283941269,46.800403595],"type":"Point"}
}