{
  "type": "Feature",
  "properties": {
    "iso:country":"CH",
    "sg:address":"Hauptstrasse 15 6260 Reiden. Postfach 43",
    "sg:city":"Reiden",
    "sg:orig_category":"Grosshandel mit B\u00fcromaschinen Hardwareberatung",
    "sg:phone":"+41 62 758 30 30",
    "sg:postcode":"6260",
    "sg:province":"Luzern",
    "wof:name":"Az & Partner Ag",
    "wof:placetype":"venue"
},
  "geometry": {"coordinates":[7.9703779221,47.2418479919],"type":"Point"}
}