{
  "type": "Feature",
  "properties": {
    "iso:country":"CH",
    "sg:address":"Via Al Boschetto 2",
    "sg:city":"Lugano",
    "sg:orig_category":"Vermittlung von Immobilien",
    "sg:phone":"+41 91 994 12 31",
    "sg:postcode":"6900",
    "sg:province":"Ticino",
    "wof:name":"Immobiliare Brentino Sa",
    "wof:placetype":"venue"
},
  "geometry": {"coordinates":[8.9397125244,45.9908294678],"type":"Point"}
}