{
  "type": "Feature",
  "properties": {
    "iso:country":"CH",
    "sg:address":"Alpenquai 4",
    "sg:city":"Luzern",
    "sg:classifiers":[
        {
            "category":"Manufacturing",
            "subcategory":"Signs",
            "type":"Manufacturing & Wholesale Goods"
        }
    ],
    "sg:phone":"+41 41 360 11 55",
    "sg:postcode":"6005",
    "sg:province":"Luzern",
    "sg:tags":[
        "car",
        "lettering"
    ],
    "wof:name":"Altmann Reklame",
    "wof:placetype":"venue"
},
  "geometry": {"coordinates":[8.315883,47.046852],"type":"Point"}
}