{
  "type": "Feature",
  "properties": {
    "iso:country":"CH",
    "sg:address":"K\u00fchlhausstrasse 2 4900 Langenthal. Postfach",
    "sg:city":"Langenthal",
    "sg:orig_category":"Lagerung",
    "sg:postcode":"4901",
    "sg:province":"Bern",
    "wof:name":"Obstk\u00fchlhaus St. Margrethen Ag",
    "wof:placetype":"venue"
},
  "geometry": {"coordinates":[9.6466550827,47.45079422],"type":"Point"}
}