{
  "type": "Feature",
  "properties": {
    "iso:country":"CH",
    "sg:address":"Valle Rue De La",
    "sg:city":"Court",
    "sg:orig_category":"Unclassifiable Establishments",
    "sg:postcode":"2738",
    "sg:province":"Bern",
    "wof:name":"Gobat Pierre Henri",
    "wof:placetype":"venue"
},
  "geometry": {"coordinates":[7.3414521217,47.2410430908],"type":"Point"}
}