{
  "type": "Feature",
  "properties": {
    "iso:country":"CH",
    "sg:address":"Kirchweg 2",
    "sg:city":"Nottwil",
    "sg:orig_category":"Non-Classified Establishments",
    "sg:phone":"+41 41 937 12 28",
    "sg:postcode":"6207",
    "sg:province":"Luzern",
    "wof:name":"Bernet Gartenbau",
    "wof:placetype":"venue"
},
  "geometry": {"coordinates":[8.1391515732,47.1316795349],"type":"Point"}
}