{
  "type": "Feature",
  "properties": {
    "addr:full":"Jurastrasse 44 4900 Langenthal. Postfach Langenthal Bern 4901",
    "addr:housenumber":"44",
    "addr:postcode":"4900;postfach;4901",
    "addr:street":"Jurastrasse",
    "iso:country":"CH",
    "sg:address":"Jurastrasse 44 4900 Langenthal. Postfach",
    "sg:city":"Langenthal",
    "sg:orig_category":"Advokaturb\u00fcros Notariate",
    "sg:phone":"+41 41 410 31 30",
    "sg:postcode":"4901",
    "sg:province":"Bern",
    "wof:name":"Peter M\u00f6ri Advokatur-& Notariatsb\u00fcro",
    "wof:placetype":"venue"
},
  "geometry": {"coordinates":[8.31005,47.055447],"type":"Point"}
}