{
  "type": "Feature",
  "properties": {
    "iso:country":"CH",
    "sg:address":"Chauss\u00e9e De Treycovagnes 5 1400 Yverdon-les-bains. Postfach",
    "sg:city":"Yverdon",
    "sg:orig_category":"Autogaragen Autospenglereien",
    "sg:phone":"+41 24 445 31 34",
    "sg:postcode":"1401",
    "sg:province":"Vaud",
    "wof:name":"Carrosserie Des Moulins",
    "wof:placetype":"venue"
},
  "geometry": {"coordinates":[6.625726,46.778721],"type":"Point"}
}