{
  "type": "Feature",
  "properties": {
    "iso:country":"CH",
    "sg:address":"Moosburgstrasse 20",
    "sg:city":"Effretikon",
    "sg:orig_category":"Grosshandel mit Baumaschinen",
    "sg:phone":"+41 52 343 20 40",
    "sg:postcode":"8307",
    "sg:province":"Z\u00fcrich",
    "wof:name":"Robert Kn\u00f6pfli Ag Generalvertretung Intertractor",
    "wof:placetype":"venue"
},
  "geometry": {"coordinates":[8.6914110184,47.4211387634],"type":"Point"}
}