{
  "type": "Feature",
  "properties": {
    "iso:country":"CH",
    "sg:address":"Rue Centrale 5",
    "sg:city":"Corsier-sur-vevey",
    "sg:orig_category":"Detailhandel mit Fleisch U Fleischwaren",
    "sg:postcode":"1804",
    "sg:province":"Vaud",
    "wof:name":"Nicola Mme C.",
    "wof:placetype":"venue"
},
  "geometry": {"coordinates":[6.8421959877,46.4705314636],"type":"Point"}
}