{
  "type": "Feature",
  "properties": {
    "addr:full":"Grand-rue 5-7 Nyon Vaud 1260",
    "addr:housenumber":"5-7",
    "addr:postcode":"1260",
    "addr:street":"Grand-Rue",
    "iso:country":"CH",
    "sg:address":"Grand-rue 5-7",
    "sg:city":"Nyon",
    "sg:orig_category":"Arztpraxen",
    "sg:phone":"+41 22 362 85 77",
    "sg:postcode":"1260",
    "sg:province":"Vaud",
    "wof:name":"Dr M\u00e9d. Philippe Simon M\u00e9decin Sp\u00e9cialiste",
    "wof:placetype":"venue"
},
  "geometry": {"coordinates":[6.239016,46.382385],"type":"Point"}
}