{
  "type": "Feature",
  "properties": {
    "iso:country":"CH",
    "sg:address":"Vermont Rue De 9a 1202 Gen\u00e8ve. Postfach",
    "sg:city":"Gen\u00e8ve",
    "sg:orig_category":"Interessenvertretungen",
    "sg:postcode":"1202",
    "sg:province":"Gen\u00e8ve",
    "wof:name":"Montanarini-isler - Stiftung",
    "wof:placetype":"venue"
},
  "geometry": {"coordinates":[8.2756185532,47.3521614075],"type":"Point"}
}