{
  "type": "Feature",
  "properties": {
    "iso:country":"CH",
    "sg:address":"Baumgartenweg 2",
    "sg:city":"Siebnen",
    "sg:orig_category":"Detailhandel mit Textilien",
    "sg:phone":"+41 55 440 19 04",
    "sg:postcode":"8854",
    "sg:province":"Schwyz",
    "wof:name":"Heidy Botta Handarbeiten",
    "wof:placetype":"venue"
},
  "geometry": {"coordinates":[8.8999843597,47.1726150513],"type":"Point"}
}