{
  "type": "Feature",
  "properties": {
    "iso:country":"CH",
    "sg:address":"Wermatswilerstrasse 91",
    "sg:city":"Fehraltorf",
    "sg:orig_category":"Pensionskassen",
    "sg:postcode":"8320",
    "sg:province":"Z\u00fcrich",
    "wof:name":"Personalf\u00fcrsorgestiftung Der Gr\u00f6ber Ag",
    "wof:placetype":"venue"
},
  "geometry": {"coordinates":[8.7554883957,47.3827285767],"type":"Point"}
}