{
  "type": "Feature",
  "properties": {
    "iso:country":"CH",
    "sg:address":"Aathalstrasse 5",
    "sg:city":"Uster",
    "sg:orig_category":"Erschliessung von Grundst\u00fccken",
    "sg:postcode":"8610",
    "sg:province":"Z\u00fcrich",
    "wof:name":"Gewoba Gemeinn\u00fctzige Wohnbaugenossenschaft Abtwil-st. Josefen",
    "wof:placetype":"venue"
},
  "geometry": {"coordinates":[9.3175554276,47.4242706299],"type":"Point"}
}