{
  "type": "Feature",
  "properties": {
    "iso:country":"CH",
    "sg:address":"Kantonsstrasse 3900 Gamsen. Postfach",
    "sg:city":"Glis",
    "sg:orig_category":"Instandhaltung U Reparatur von Automobilen Tankstellen",
    "sg:phone":"+41 27 923 51 64",
    "sg:postcode":"3902",
    "sg:province":"Valais",
    "wof:name":"Auto Heldner Ag",
    "wof:placetype":"venue"
},
  "geometry": {"coordinates":[7.9593667984,46.3058013916],"type":"Point"}
}