{
  "type": "Feature",
  "properties": {
    "iso:country":"CH",
    "sg:address":"Ebnetstrasse 10",
    "sg:city":"Brunnadern",
    "sg:orig_category":"Elektroinstallation Herstellung von sonstigen elektrischen Ausr\u00fcstungen",
    "sg:phone":"+41 71 375 60 00",
    "sg:postcode":"9125",
    "sg:province":"St. Gallen",
    "wof:name":"Elektro Lieberherr Ag",
    "wof:placetype":"venue"
},
  "geometry": {"coordinates":[9.131196022,47.3365402222],"type":"Point"}
}