{
  "type": "Feature",
  "properties": {
    "iso:country":"CH",
    "sg:address":"Glarnerstrasse 14 8854 Siebnen. Postfach",
    "sg:city":"Siebnen",
    "sg:orig_category":"Detailhandel mit Schuhen U Lederwaren",
    "sg:phone":"+41 55 440 12 84",
    "sg:postcode":"8854",
    "sg:province":"Schwyz",
    "wof:name":"Elisabet Strehler-kessler",
    "wof:placetype":"venue"
},
  "geometry": {"coordinates":[8.898434639,47.1746444702],"type":"Point"}
}