{
  "type": "Feature",
  "properties": {
    "iso:country":"CH",
    "sg:address":"Bahnhofstrasse 9 3930 Visp. Postfach",
    "sg:city":"Visp",
    "sg:orig_category":"Unclassifiable Establishments",
    "sg:phone":"+41 27 946 17 27",
    "sg:postcode":"3930",
    "sg:province":"Valais",
    "wof:name":"Femina Holding Ag Visp",
    "wof:placetype":"venue"
},
  "geometry": {"coordinates":[7.8818759918,46.2931022644],"type":"Point"}
}