{
  "type": "Feature",
  "properties": {
    "iso:country":"CH",
    "sg:address":"Bergstrasse 114",
    "sg:city":"Z\u00fcrich",
    "sg:orig_category":"Architektur U Ingenieurb\u00fcros",
    "sg:phone":"+41 19948030",
    "sg:postcode":"8032",
    "sg:province":"Z\u00fcrich",
    "wof:name":"Walther Bauphysik Ag",
    "wof:placetype":"venue"
},
  "geometry": {"coordinates":[8.56398,47.368301],"type":"Point"}
}