{
  "type": "Feature",
  "properties": {
    "addr:full":"1034 Boussens Vaud 1034",
    "addr:postcode":"1034;1034",
    "iso:country":"CH",
    "sg:address":"1034",
    "sg:city":"Boussens",
    "sg:orig_category":"Bauschreinerei Herstellung von Metallkonstruktionen",
    "sg:phone":"+41 71 385 71 91",
    "sg:postcode":"1034",
    "sg:province":"Vaud",
    "wof:name":"Feba-montagen B\u00e4tschmann F.",
    "wof:placetype":"venue"
},
  "geometry": {"coordinates":[9.26851,47.416622],"type":"Point"}
}