{
  "type": "Feature",
  "properties": {
    "iso:country":"CH",
    "sg:address":"Bahnhofstr.",
    "sg:city":"Rohrbach",
    "sg:classifiers":[
        {
            "category":"Banks & Credit Unions",
            "subcategory":"Bank",
            "type":"Services"
        }
    ],
    "sg:phone":"+41 62 965 11 56",
    "sg:postcode":"4938",
    "sg:province":"Bern",
    "wof:name":"Bank In Huttwil, Agentur Rohrbach",
    "wof:placetype":"venue"
},
  "geometry": {"coordinates":[7.812375,47.135906],"type":"Point"}
}