{
  "type": "Feature",
  "properties": {
    "iso:country":"CH",
    "sg:address":"1038",
    "sg:city":"Bercher",
    "sg:orig_category":"Schulpflegen",
    "sg:postcode":"1038",
    "sg:province":"Vaud",
    "wof:name":"Commission Scolaire De L'\u00e9cole Primaire De Bercher & Rueyres",
    "wof:placetype":"venue"
},
  "geometry": {"coordinates":[6.7114901543,46.6916313171],"type":"Point"}
}