{
  "type": "Feature",
  "properties": {
    "iso:country":"CH",
    "sg:address":"Gallusstr. 1",
    "sg:city":"Kriens",
    "sg:classifiers":[
        {
            "category":"Banks & Credit Unions",
            "subcategory":"Bank",
            "type":"Services"
        }
    ],
    "sg:phone":"+41 41 320 48 80",
    "sg:postcode":"6010",
    "sg:province":"Luzern",
    "wof:name":"Raiffeisenbank Kriens",
    "wof:placetype":"venue"
},
  "geometry": {"coordinates":[8.27979,47.033703],"type":"Point"}
}