{
  "type": "Feature",
  "properties": {
    "iso:country":"CH",
    "sg:address":"Camminata Via 3",
    "sg:city":"Bellinzona",
    "sg:orig_category":"Herstellung von konfektionierten Textilwaren ohne Bekleidung",
    "sg:phone":"+41 91 826 38 33",
    "sg:postcode":"6500",
    "sg:province":"Ticino",
    "wof:name":"Intimo 2001 Di Trenta Pasticci Monique",
    "wof:placetype":"venue"
},
  "geometry": {"coordinates":[9.0226812363,46.1906929016],"type":"Point"}
}