{
  "type": "Feature",
  "properties": {
    "iso:country":"CH",
    "sg:address":"Sihleggstrasse 8834 Schindellegi. Postfach",
    "sg:city":"Schindellegi",
    "sg:orig_category":"Fachdetailhandel in Verkaufsr\u00e4umen",
    "sg:postcode":"8834",
    "sg:province":"Schwyz",
    "wof:name":"Bioplant Gmbh",
    "wof:placetype":"venue"
},
  "geometry": {"coordinates":[8.7114276886,47.1822662354],"type":"Point"}
}