{
  "type": "Feature",
  "properties": {
    "iso:country":"CH",
    "sg:address":"Abl\u00e4schstrasse 24",
    "sg:city":"Glarus",
    "sg:orig_category":"Massagestudios P\u00e9dicure",
    "sg:phone":"+41 55 640 65 32",
    "sg:postcode":"8750",
    "sg:province":"Glarus",
    "wof:name":"J\u00fcrg D\u00fcrst",
    "wof:placetype":"venue"
},
  "geometry": {"coordinates":[9.0692806244,47.0377578735],"type":"Point"}
}