{
  "type": "Feature",
  "properties": {
    "iso:country":"CH",
    "sg:address":"3086",
    "sg:city":"Englisberg",
    "sg:classifiers":[
        {
            "category":"Education",
            "subcategory":"Library",
            "type":"Public Place"
        }
    ],
    "sg:postcode":"3086",
    "sg:province":"Bern",
    "sg:tags":[
        "u",
        "bibliotheken",
        "archive"
    ],
    "wof:name":"Volksbibliothek Wald",
    "wof:placetype":"venue"
},
  "geometry": {"coordinates":[7.46891,46.897301],"type":"Point"}
}