{
  "type": "Feature",
  "properties": {
    "iso:country":"CH",
    "sg:address":"Flurstrasse 21 5623 Boswil. Postfach 20",
    "sg:city":"Boswil",
    "sg:orig_category":"Interessenvertretungen",
    "sg:phone":"+41 56 666 30 84",
    "sg:postcode":"5623",
    "sg:province":"Aargau",
    "wof:name":"Stiftung K\u00fcnstlerhaus Boswil",
    "wof:placetype":"venue"
},
  "geometry": {"coordinates":[8.3206758499,47.3035583496],"type":"Point"}
}