{
  "type": "Feature",
  "properties": {
    "iso:country":"CH",
    "sg:address":"Rue De La Poste 7",
    "sg:city":"Martigny",
    "sg:orig_category":"Chemische Reinigung",
    "sg:phone":"+41 27 722 19 17",
    "sg:postcode":"1920",
    "sg:province":"Valais",
    "wof:name":"Pressing De Pr\u00e9ville",
    "wof:placetype":"venue"
},
  "geometry": {"coordinates":[7.0771670341,46.1027832031],"type":"Point"}
}