{
  "type": "Feature",
  "properties": {
    "iso:country":"CH",
    "sg:address":"Sinneringen",
    "sg:city":"Boll",
    "sg:orig_category":"Religi\u00f6se Vereinigungen divers",
    "sg:postcode":"3067",
    "sg:province":"Bern",
    "wof:name":"Cvjm",
    "wof:placetype":"venue"
},
  "geometry": {"coordinates":[7.5616650581,46.9468002319],"type":"Point"}
}