{
  "type": "Feature",
  "properties": {
    "iso:country":"CH",
    "sg:address":"Hausen",
    "sg:city":"Ossingen",
    "sg:orig_category":"Detailhandel mit Bekleidung",
    "sg:phone":"+41 52 317 25 72",
    "sg:postcode":"8475",
    "sg:province":"Z\u00fcrich",
    "wof:name":"Vetter, Helly-hansen, Shop",
    "wof:placetype":"venue"
},
  "geometry": {"coordinates":[8.714145,47.606411],"type":"Point"}
}