{
  "type": "Feature",
  "properties": {
    "iso:country":"CH",
    "sg:address":"Obere Zelglistrasse 15",
    "sg:city":"D\u00fcbendorf",
    "sg:orig_category":"Vorschulen, Kinderg\u00e4rten",
    "sg:phone":"+41 18213233",
    "sg:postcode":"8600",
    "sg:province":"Z\u00fcrich",
    "wof:name":"Kindergarten Zelgli",
    "wof:placetype":"venue"
},
  "geometry": {"coordinates":[8.6148147583,47.3933258057],"type":"Point"}
}