{
  "type": "Feature",
  "properties": {
    "iso:country":"CH",
    "sg:address":"Rothmettlen",
    "sg:city":"Burgistein",
    "sg:orig_category":"Blumen U Zierpflanzenbau",
    "sg:phone":"+41 33 356 13 63",
    "sg:postcode":"3664",
    "sg:province":"Bern",
    "wof:name":"Rudolf Remund G\u00e4rtnerei Friedhofg\u00e4rtnerei",
    "wof:placetype":"venue"
},
  "geometry": {"coordinates":[7.512487,46.794971],"type":"Point"}
}