{
  "type": "Feature",
  "properties": {
    "iso:country":"CH",
    "sg:address":"Fabrikstrasse 24",
    "sg:city":"Bischofszell",
    "sg:orig_category":"Detailhandel mit Fahrr\u00e4dern",
    "sg:phone":"+41 71 424 22 00",
    "sg:postcode":"9220",
    "sg:province":"Thurgau",
    "wof:name":"Krapf Radsport Ag",
    "wof:placetype":"venue"
},
  "geometry": {"coordinates":[9.2362003326,47.4934959412],"type":"Point"}
}