{
  "type": "Feature",
  "properties": {
    "iso:country":"CH",
    "sg:address":"Lerchenweg 2",
    "sg:city":"Attiswil",
    "sg:classifiers":[
        {
            "category":"Banks & Credit Unions",
            "subcategory":"Bank",
            "type":"Services"
        }
    ],
    "sg:phone":"+41 4165772341",
    "sg:postcode":"4536",
    "sg:province":"Bern",
    "wof:name":"Schweiz. Mobiliar",
    "wof:placetype":"venue"
},
  "geometry": {"coordinates":[7.602825,47.246597],"type":"Point"}
}