{
  "type": "Feature",
  "properties": {
    "iso:country":"CH",
    "sg:address":"Obstgartenstrasse 61",
    "sg:city":"Regensdorf",
    "sg:orig_category":"Bauingenieurb\u00fcros allgemein",
    "sg:phone":"+41 18404030",
    "sg:postcode":"8105",
    "sg:province":"Z\u00fcrich",
    "wof:name":"Ernst Hauser Ingenieurb\u00fcro",
    "wof:placetype":"venue"
},
  "geometry": {"coordinates":[8.464798,47.428135],"type":"Point"}
}