{
  "type": "Feature",
  "properties": {
    "iso:country":"CH",
    "sg:address":"Diablerets Chalet Les 1854 Leysin. Postfach",
    "sg:city":"Leysin",
    "sg:orig_category":"Detailhandel mit Fahrr\u00e4dern Fachdetailhandel in Verkaufsr\u00e4umen",
    "sg:postcode":"1854",
    "sg:province":"Vaud",
    "wof:name":"Squirrel Sport Dealer Sollberger & Tissot Sollberger & J.f. Tissot",
    "wof:placetype":"venue"
},
  "geometry": {"coordinates":[7.0130829811,46.3435630798],"type":"Point"}
}