{
  "type": "Feature",
  "properties": {
    "iso:country":"CH",
    "sg:address":"Oberhalden",
    "sg:city":"Ottoberg",
    "sg:orig_category":"Architektur U Ingenieurb\u00fcros Sonstige technische Beratung U Planung",
    "sg:phone":"+41 71 622 11 14",
    "sg:postcode":"8561",
    "sg:province":"Thurgau",
    "wof:name":"Mettler Engineering Ag",
    "wof:placetype":"venue"
},
  "geometry": {"coordinates":[9.087653,47.586174],"type":"Point"}
}