{
  "type": "Feature",
  "properties": {
    "addr:full":"Seetalstrasse 3 Buttwil Aargau 5632",
    "addr:housenumber":"3",
    "addr:postcode":"5632",
    "addr:street":"Seetalstrasse",
    "iso:country":"CH",
    "sg:address":"Seetalstrasse 3",
    "sg:city":"Buttwil",
    "sg:orig_category":"Autospenglereien",
    "sg:phone":"+41 56 664 28 70",
    "sg:postcode":"5632",
    "sg:province":"Aargau",
    "wof:name":"Kaspar Scheuber Carrosserie",
    "wof:placetype":"venue"
},
  "geometry": {"coordinates":[8.312785,47.269665],"type":"Point"}
}