{
  "type": "Feature",
  "properties": {
    "iso:country":"CH",
    "sg:address":"Route De Sullens 9",
    "sg:city":"Penthaz",
    "sg:orig_category":"Autogaragen Handel mit Automobilen",
    "sg:postcode":"1303",
    "sg:province":"Vaud",
    "wof:name":"Garage Emery S\u00e0rl Auto Electro",
    "wof:placetype":"venue"
},
  "geometry": {"coordinates":[6.542218,46.597706],"type":"Point"}
}