{
  "type": "Feature",
  "properties": {
    "iso:country":"CH",
    "sg:address":"Balgriststrasse 55",
    "sg:city":"Z\u00fcrich",
    "sg:orig_category":"Kinderkrippen U horte",
    "sg:postcode":"8008",
    "sg:province":"Z\u00fcrich",
    "wof:name":"Hort Des Schulamtes Der Stadt Z\u00fcrich",
    "wof:placetype":"venue"
},
  "geometry": {"coordinates":[8.5777139664,47.3540687561],"type":"Point"}
}