{
  "type": "Feature",
  "properties": {
    "iso:country":"CH",
    "sg:address":"Route De La Branvaude",
    "sg:city":"Chavannes-des-bois",
    "sg:orig_category":"Wirtschaftspr\u00fcfung, Steuerberatung U Treuhand",
    "sg:phone":"+41 32 731 51 43",
    "sg:postcode":"1290",
    "sg:province":"Gen\u00e8ve",
    "wof:name":"Fiduciaire Neuhaus & Cie",
    "wof:placetype":"venue"
},
  "geometry": {"coordinates":[6.9035048485,46.982749939],"type":"Point"}
}