{
  "type": "Feature",
  "properties": {
    "iso:country":"CH",
    "sg:address":"Route De Ponthaux 43",
    "sg:city":"Grolley",
    "sg:orig_category":"Gartenbau Landschaftsplanungsb\u00fcros U Gartenarchitekturb\u00fcros",
    "sg:phone":"+41 79 435 10 42",
    "sg:postcode":"1772",
    "sg:province":"Fribourg",
    "wof:name":"Marcel Roulin Paysagiste",
    "wof:placetype":"venue"
},
  "geometry": {"coordinates":[7.0607280731,46.829826355],"type":"Point"}
}