{
  "type": "Feature",
  "properties": {
    "iso:country":"CH",
    "sg:address":"R\u00fctiweg 63",
    "sg:city":"Ostermundigen",
    "sg:orig_category":"Unternehmensberatung Wirtschaftspr\u00fcfung, Steuerberatung U Treuhand",
    "sg:phone":"+41 31 931 59 89",
    "sg:postcode":"3072",
    "sg:province":"Bern",
    "wof:name":"Mischler Werner",
    "wof:placetype":"venue"
},
  "geometry": {"coordinates":[7.5063247681,46.9575271606],"type":"Point"}
}