{
  "type": "Feature",
  "properties": {
    "iso:country":"CH",
    "sg:address":"Niederfelbenweg 31",
    "sg:city":"Zollikon",
    "sg:orig_category":"Softwareentwicklung U beratung",
    "sg:postcode":"8702",
    "sg:province":"Z\u00fcrich",
    "wof:name":"Condata S. Conrad",
    "wof:placetype":"venue"
},
  "geometry": {"coordinates":[8.5699319839,47.3447990417],"type":"Point"}
}