{
  "type": "Feature",
  "properties": {
    "iso:country":"CH",
    "sg:address":"Rheinstrasse 85",
    "sg:city":"Chur",
    "sg:orig_category":"Sonstiger Grosshandel",
    "sg:postcode":"7000",
    "sg:province":"Graubunden",
    "wof:name":"Derungs J.",
    "wof:placetype":"venue"
},
  "geometry": {"coordinates":[9.5200929642,46.856174469],"type":"Point"}
}