{
  "type": "Feature",
  "properties": {
    "iso:country":"CH",
    "sg:address":"Altgasse 82",
    "sg:city":"Baar",
    "sg:classifiers":[
        {
            "category":"Communications",
            "subcategory":"Radio Station",
            "type":"Services"
        }
    ],
    "sg:phone":"+41 41 760 24 46",
    "sg:postcode":"6340",
    "sg:province":"Zug",
    "sg:tags":[
        "fernsehanstalten",
        "u"
    ],
    "wof:name":"Tc Promotion Gmbh",
    "wof:placetype":"venue"
},
  "geometry": {"coordinates":[8.5167999268,47.1905403137],"type":"Point"}
}