{
  "type": "Feature",
  "properties": {
    "iso:country":"CH",
    "sg:address":"Heidenweg 4",
    "sg:city":"Erlach",
    "sg:orig_category":"Grosshandel mit sonstigen Nahrungsmitteln",
    "sg:postcode":"3235",
    "sg:province":"Bern",
    "wof:name":"Burkhalter Poissons Sa",
    "wof:placetype":"venue"
},
  "geometry": {"coordinates":[7.0998620987,47.0455780029],"type":"Point"}
}