{
  "type": "Feature",
  "properties": {
    "iso:country":"CH",
    "sg:address":"Hauptstrasse 33",
    "sg:city":"Pieterlen",
    "sg:orig_category":"Detailhandel mit Antiquit\u00e4ten Detailhandel mit Gebrauchtwaren in Verkaufsr\u00e4umen",
    "sg:phone":"+41 79 692 90 90",
    "sg:postcode":"2542",
    "sg:province":"Bern",
    "wof:name":"Werner Elsener Antiquit\u00e4ten Brockehuus",
    "wof:placetype":"venue"
},
  "geometry": {"coordinates":[9.193615,47.230316],"type":"Point"}
}