{
  "type": "Feature",
  "properties": {
    "iso:country":"CH",
    "sg:address":"Rischmattweg 15",
    "sg:city":"Diegten",
    "sg:orig_category":"Einzelhandel mit Automobilen Fachdetailhandel in Verkaufsr\u00e4umen",
    "sg:phone":"+41 71 912 52 06",
    "sg:postcode":"4457",
    "sg:province":"Basel-Landschaft",
    "wof:name":"Artinoos Camping-& Marineartikel",
    "wof:placetype":"venue"
},
  "geometry": {"coordinates":[7.8084278107,47.403717041],"type":"Point"}
}