{
  "type": "Feature",
  "properties": {
    "iso:country":"CH",
    "sg:address":"Cantonetto Via",
    "sg:city":"Gentilino",
    "sg:orig_category":"Fachdetailhandel in Verkaufsr\u00e4umen",
    "sg:postcode":"6925",
    "sg:province":"Ticino",
    "wof:name":"Innolink Ambient Sa",
    "wof:placetype":"venue"
},
  "geometry": {"coordinates":[8.9325428009,45.9911117554],"type":"Point"}
}