{
  "type": "Feature",
  "properties": {
    "iso:country":"CH",
    "sg:address":"Uerschhausen 8537 Nussbaumen Tg. Postfach 460",
    "sg:city":"T\u00fcbach",
    "sg:orig_category":"Unternehmensberatung",
    "sg:postcode":"9327",
    "sg:province":"St. Gallen",
    "wof:name":"Easy-netbusiness Ag",
    "wof:placetype":"venue"
},
  "geometry": {"coordinates":[8.8264408112,47.6234130859],"type":"Point"}
}