{
  "type": "Feature",
  "properties": {
    "addr:full":"Eistrasse Malters Luzern 6102",
    "addr:postcode":"6102",
    "addr:street":"Eistrasse",
    "iso:country":"CH",
    "sg:address":"Eistrasse",
    "sg:city":"Malters",
    "sg:orig_category":"Autogaragen",
    "sg:phone":"+41 41 497 17 53",
    "sg:postcode":"6102",
    "sg:province":"Luzern",
    "wof:name":"Peter Ryser Garage",
    "wof:placetype":"venue"
},
  "geometry": {"coordinates":[8.189055,47.045864],"type":"Point"}
}