{
  "type": "Feature",
  "properties": {
    "iso:country":"CH",
    "sg:address":"Tour-henri 56",
    "sg:city":"Fribourg",
    "sg:orig_category":"Herstellung von Teilen U Zubeh\u00f6r f\u00fcr Automobile",
    "sg:postcode":"1700",
    "sg:province":"Fribourg",
    "wof:name":"Pius & Bel-bahar",
    "wof:placetype":"venue"
},
  "geometry": {"coordinates":[7.1536831856,46.8037452698],"type":"Point"}
}