{
  "type": "Feature",
  "properties": {
    "iso:country":"CH",
    "sg:address":"Wannwies 172",
    "sg:city":"Maur",
    "sg:orig_category":"Gartenbau",
    "sg:phone":"+41 19800209",
    "sg:postcode":"8124",
    "sg:province":"Z\u00fcrich",
    "wof:name":"Martin Metzler Gartenbau",
    "wof:placetype":"venue"
},
  "geometry": {"coordinates":[8.66929245,47.3204879761],"type":"Point"}
}