{
  "type": "Feature",
  "properties": {
    "iso:country":"CH",
    "sg:address":"Moosholzzelg 2",
    "sg:city":"Egnach",
    "sg:orig_category":"Sportvereine Ballsport Volleyball Vereine Damen",
    "sg:phone":"+41 71 477 17 06",
    "sg:postcode":"9322",
    "sg:province":"Thurgau",
    "wof:name":"Volleyball-club Dr Neukirch",
    "wof:placetype":"venue"
},
  "geometry": {"coordinates":[9.3746576309,47.5473327637],"type":"Point"}
}