{
  "type": "Feature",
  "properties": {
    "iso:country":"CH",
    "sg:address":"Avenue Des Bains 21",
    "sg:city":"Yverdon-les-bains",
    "sg:classifiers":[
        {
            "category":"Travel",
            "subcategory":"Hotels & Motels",
            "type":"Entertainment"
        }
    ],
    "sg:phone":"+41 24 426 92 81",
    "sg:postcode":"1400",
    "sg:province":"Vaud",
    "sg:tags":[
        "hotels",
        "mit",
        "restaurant"
    ],
    "wof:name":"Motel Des Bains-yverdon Sa",
    "wof:placetype":"venue"
},
  "geometry": {"coordinates":[6.6493802071,46.773059845],"type":"Point"}
}