{
  "type": "Feature",
  "properties": {
    "iso:country":"CH",
    "sg:address":"Leutschenstrasse 18",
    "sg:city":"Freienbach",
    "sg:orig_category":"Vermietung U Verpachtung von eigenen Immobilien",
    "sg:postcode":"8807",
    "sg:province":"Schwyz",
    "wof:name":"Rebh\u00fcgel-immobilien Ag",
    "wof:placetype":"venue"
},
  "geometry": {"coordinates":[8.344452858,47.3506698608],"type":"Point"}
}