{
  "type": "Feature",
  "properties": {
    "iso:country":"CH",
    "sg:address":"Boulvard De P\u00e9rolles 9",
    "sg:city":"Fribourg",
    "sg:orig_category":"Herstellung von Werkzeugen Maschinenbau",
    "sg:phone":"+41 71 278 21 80",
    "sg:postcode":"1700",
    "sg:province":"Fribourg",
    "wof:name":"Revoc Ag",
    "wof:placetype":"venue"
},
  "geometry": {"coordinates":[9.3386125565,47.4075813293],"type":"Point"}
}