{
  "type": "Feature",
  "properties": {
    "iso:country":"CH",
    "sg:address":"Zofingerstrasse 38 4805 Brittnau. Postfach 121",
    "sg:city":"Brittnau",
    "sg:orig_category":"Instandhaltung U Reparatur von Automobilen",
    "sg:phone":"+41 22 798 20 42",
    "sg:postcode":"4805",
    "sg:province":"Aargau",
    "wof:name":"F. Salamanca Garage Du Palais",
    "wof:placetype":"venue"
},
  "geometry": {"coordinates":[6.1194357872,46.2313842773],"type":"Point"}
}