{
  "type": "Feature",
  "properties": {
    "iso:country":"CH",
    "sg:address":"1304",
    "sg:city":"Cossonay-ville",
    "sg:orig_category":"Vereine Gesang",
    "sg:phone":"+41 21 845 62 09",
    "sg:postcode":"1304",
    "sg:province":"Vaud",
    "wof:name":"St\u00e9 Choraleger Golay",
    "wof:placetype":"venue"
},
  "geometry": {"coordinates":[6.2330298424,46.6065139771],"type":"Point"}
}