{
  "type": "Feature",
  "properties": {
    "iso:country":"CH",
    "sg:address":"Auf Dem Damm 17",
    "sg:city":"St.gallen",
    "sg:orig_category":"Detailhandel mit Gebrauchtwaren in Verkaufsr\u00e4umen Drogerien",
    "sg:phone":"+41 71 223 33 48",
    "sg:postcode":"9000",
    "sg:province":"St. Gallen",
    "wof:name":"Kloster-drogerie Fehr S.",
    "wof:placetype":"venue"
},
  "geometry": {"coordinates":[9.3763999939,47.422290802],"type":"Point"}
}