{
  "type": "Feature",
  "properties": {
    "iso:country":"CH",
    "sg:address":"Buechenrain 2",
    "sg:city":"W\u00e4denswil",
    "sg:orig_category":"Architekturb\u00fcros",
    "sg:phone":"+41 17801050",
    "sg:postcode":"8820",
    "sg:province":"Z\u00fcrich",
    "wof:name":"Kurt Handschin Architekturb\u00fcro",
    "wof:placetype":"venue"
},
  "geometry": {"coordinates":[8.671508,47.22406],"type":"Point"}
}