{
  "type": "Feature",
  "properties": {
    "iso:country":"CH",
    "sg:address":"Sichelweg 17",
    "sg:city":"K\u00f6niz",
    "sg:orig_category":"Maler U Glasergewerbe",
    "sg:postcode":"3098",
    "sg:province":"Bern",
    "wof:name":"Fischer Roland, Malerbedarf.",
    "wof:placetype":"venue"
},
  "geometry": {"coordinates":[7.4162259102,46.9132843018],"type":"Point"}
}