{
  "type": "Feature",
  "properties": {
    "iso:country":"CH",
    "sg:address":"Effingerstrasse 4a 3011 Bern. Postfach",
    "sg:city":"Bern",
    "sg:orig_category":"Advokaturb\u00fcros",
    "sg:phone":"+41 62 892 94 72",
    "sg:postcode":"3001",
    "sg:province":"Bern",
    "wof:name":"Gabriela M\u00fcller Advokaturb\u00fcro",
    "wof:placetype":"venue"
},
  "geometry": {"coordinates":[8.181825,47.379684],"type":"Point"}
}