{
  "type": "Feature",
  "properties": {
    "addr:full":"Z\u00fcrichstrasse 203 Aathal-seegr\u00e4ben Z\u00fcrich 8607",
    "addr:housenumber":"203",
    "addr:postcode":"8607",
    "addr:street":"Zuerichstrasse;Zuerich",
    "iso:country":"CH",
    "sg:address":"Z\u00fcrichstrasse 203",
    "sg:city":"Aathal-seegr\u00e4ben",
    "sg:orig_category":"Bauschreinerei",
    "sg:phone":"+41 19323655",
    "sg:postcode":"8607",
    "sg:province":"Z\u00fcrich",
    "wof:name":"Peter Klopfenstein Schreinerei Im Aathal",
    "wof:placetype":"venue"
},
  "geometry": {"coordinates":[8.768485,47.335884],"type":"Point"}
}