{
  "type": "Feature",
  "properties": {
    "iso:country":"CH",
    "sg:address":"Obere Gasse 51",
    "sg:city":"Chur",
    "sg:orig_category":"Kosmetikinstitute",
    "sg:phone":"+41 81 252 18 96",
    "sg:postcode":"7000",
    "sg:province":"Graubunden",
    "wof:name":"Cordula Pompino Kosmetikinstitut",
    "wof:placetype":"venue"
},
  "geometry": {"coordinates":[9.5299415588,46.8480377197],"type":"Point"}
}