{
  "type": "Feature",
  "properties": {
    "iso:country":"CH",
    "sg:address":"Alte Landstrasse 161a",
    "sg:city":"M\u00e4nnedorf",
    "sg:orig_category":"Sonstige Vermietung U Verpachtung von eigenen Immobilien Vermittlung von Immobilien",
    "sg:postcode":"8708",
    "sg:province":"Z\u00fcrich",
    "wof:name":"Ulrich & Weber Ok-immo",
    "wof:placetype":"venue"
},
  "geometry": {"coordinates":[8.6895217896,47.256477356],"type":"Point"}
}