{
  "type": "Feature",
  "properties": {
    "iso:country":"CH",
    "sg:address":"Habsburgerstrasse 20",
    "sg:city":"Luzern",
    "sg:orig_category":"Unclassifiable Establishments",
    "sg:postcode":"6003",
    "sg:province":"Luzern",
    "wof:name":"Repartimo Ag",
    "wof:placetype":"venue"
},
  "geometry": {"coordinates":[8.3074474335,47.0471115112],"type":"Point"}
}