{
  "type": "Feature",
  "properties": {
    "iso:country":"CH",
    "sg:address":"Poststrasse 15 6300 Zug. Postfach 336",
    "sg:city":"Zug",
    "sg:orig_category":"Unternehmensberatung Wirtschaftspr\u00fcfung, Steuerberatung U Treuhand",
    "sg:phone":"+41 41 729 42 42",
    "sg:postcode":"6301",
    "sg:province":"Zug",
    "wof:name":"Refidar Moore Stephens Ag",
    "wof:placetype":"venue"
},
  "geometry": {"coordinates":[8.5161523819,47.1690673828],"type":"Point"}
}