{
  "type": "Feature",
  "properties": {
    "addr:full":"Route De L'industrie 15 Grolley Fribourg 1772",
    "addr:housenumber":"15",
    "addr:postcode":"1772",
    "addr:street":"Route De L'Industrie",
    "iso:country":"CH",
    "sg:address":"Route De L'industrie 15",
    "sg:city":"Grolley",
    "sg:orig_category":"Bauschreinerei Zimmerei, Ingenieurholzbau",
    "sg:phone":"+41 26 475 32 80",
    "sg:postcode":"1772",
    "sg:province":"Fribourg",
    "wof:name":"G\u00e9rard Tinguely Menuiserie & Charpente",
    "wof:placetype":"venue"
},
  "geometry": {"coordinates":[7.058564,46.832989],"type":"Point"}
}