{
  "type": "Feature",
  "properties": {
    "iso:country":"CH",
    "sg:address":"B\u00e4ckerstrasse 5",
    "sg:city":"Berikon",
    "sg:orig_category":"Wirtschaftspr\u00fcfung, Steuerberatung U Treuhand",
    "sg:postcode":"8965",
    "sg:province":"Aargau",
    "wof:name":"Bfk D\u00fctsch",
    "wof:placetype":"venue"
},
  "geometry": {"coordinates":[8.3708610535,47.3530006409],"type":"Point"}
}