{
  "type": "Feature",
  "properties": {
    "iso:country":"CH",
    "sg:address":"Luzernerstr. 15",
    "sg:city":"Hildisrieden",
    "sg:orig_category":"Herstellung von Konstruktionsteilen, Fertigbauteilen U Ausbauelementen aus Holz",
    "sg:phone":"+41 41 460 19 72",
    "sg:postcode":"6024",
    "sg:province":"Luzern",
    "wof:name":"M\u00fcller Werner Schreinerei",
    "wof:placetype":"venue"
},
  "geometry": {"coordinates":[8.229388237,47.1492805481],"type":"Point"}
}