{
  "type": "Feature",
  "properties": {
    "addr:full":"Obergasse 17 Winterthur Z\u00fcrich 8400",
    "addr:housenumber":"17",
    "addr:postcode":"8400",
    "addr:street":"Obergasse",
    "iso:country":"CH",
    "sg:address":"Obergasse 17",
    "sg:city":"Winterthur",
    "sg:orig_category":"Detailhandel mit Blumen U Pflanzen",
    "sg:phone":"+41 52 212 61 15",
    "sg:postcode":"8400",
    "sg:province":"Z\u00fcrich",
    "wof:name":"Werner Kl\u00e4ntschi Blumengesch\u00e4ft",
    "wof:placetype":"venue"
},
  "geometry": {"coordinates":[8.730136,47.499134],"type":"Point"}
}