{
  "type": "Feature",
  "properties": {
    "iso:country":"CH",
    "sg:address":"Fabrikstrasse 9",
    "sg:city":"Lenzburg",
    "sg:orig_category":"Maler U Glasergewerbe",
    "sg:postcode":"5600",
    "sg:province":"Aargau",
    "wof:name":"Lagler, Malergesch\u00e4ft",
    "wof:placetype":"venue"
},
  "geometry": {"coordinates":[8.7577753067,47.2063064575],"type":"Point"}
}