{
  "type": "Feature",
  "properties": {
    "iso:country":"CH",
    "sg:address":"Ch. Sous-voies 38",
    "sg:city":"Mies",
    "sg:orig_category":"Grosshandel mit Textilien",
    "sg:phone":"+41 21 869 97 37",
    "sg:postcode":"1295",
    "sg:province":"Vaud",
    "wof:name":"Henco Sa",
    "wof:placetype":"venue"
},
  "geometry": {"coordinates":[6.1744332314,46.3027763367],"type":"Point"}
}