{
  "type": "Feature",
  "properties": {
    "iso:country":"CH",
    "sg:address":"Terbinerstrasse 5a",
    "sg:city":"Visp",
    "sg:orig_category":"Sportvereine Ski",
    "sg:phone":"+41 27 946 71 35",
    "sg:postcode":"3930",
    "sg:province":"Valais",
    "wof:name":"Skiclub Ktv Oberwallis Visp",
    "wof:placetype":"venue"
},
  "geometry": {"coordinates":[7.8838171959,46.2931365967],"type":"Point"}
}