{
  "type": "Feature",
  "properties": {
    "iso:country":"CH",
    "sg:address":"Bahnhofstrasse",
    "sg:city":"Lenzburg",
    "sg:orig_category":"Softwareentwicklung U beratung",
    "sg:phone":"+41 62 891 74 75",
    "sg:postcode":"5600",
    "sg:province":"Aargau",
    "wof:name":"Qering Global Gmbh",
    "wof:placetype":"venue"
},
  "geometry": {"coordinates":[8.172949791,47.3900756836],"type":"Point"}
}