{
  "type": "Feature",
  "properties": {
    "iso:country":"CH",
    "sg:address":"Lahnhalde 7 8200 Schaffhausen. Postfach",
    "sg:city":"Schaffhausen",
    "sg:orig_category":"Unclassifiable Establishments",
    "sg:postcode":"8202",
    "sg:province":"Schaffhausen",
    "wof:name":"Riebli, Armin, Multimediaberatung",
    "wof:placetype":"venue"
},
  "geometry": {"coordinates":[8.2677850723,46.9427223206],"type":"Point"}
}