{
  "type": "Feature",
  "properties": {
    "addr:full":"Talackerstrasse 17 8152 Glattbrugg. Postfach Z\u00fcrich Z\u00fcrich 8065",
    "addr:housenumber":"17",
    "addr:postcode":"8152 glattbrugg. postfach;8065",
    "addr:street":"Talackerstrasse",
    "iso:country":"CH",
    "sg:address":"Talackerstrasse 17 8152 Glattbrugg. Postfach",
    "sg:city":"Z\u00fcrich",
    "sg:orig_category":"Detailhandel mit Bekleidung",
    "sg:phone":"+41 18292245",
    "sg:postcode":"8065",
    "sg:province":"Z\u00fcrich",
    "wof:name":"Modeagentur Kammermann Ag",
    "wof:placetype":"venue"
},
  "geometry": {"coordinates":[8.5612,47.42585],"type":"Point"}
}