{
  "type": "Feature",
  "properties": {
    "iso:country":"CH",
    "sg:address":"Frontenex Route De 51",
    "sg:city":"Gen\u00e8ve",
    "sg:orig_category":"Grosshandel mit sonstigen Gebrauchs U Verbrauchsg\u00fctern",
    "sg:postcode":"1207",
    "sg:province":"Gen\u00e8ve",
    "wof:name":"De Saga Sa",
    "wof:placetype":"venue"
},
  "geometry": {"coordinates":[6.1642308235,46.2025146484],"type":"Point"}
}