{
  "type": "Feature",
  "properties": {
    "iso:country":"CH",
    "sg:address":"M\u00fchlemattstrasse 101 5000 Aarau. Postfach",
    "sg:city":"Aarau",
    "sg:orig_category":"Finanzierungsinstitutionen",
    "sg:postcode":"5004",
    "sg:province":"Aargau",
    "wof:name":"Refinax Ag",
    "wof:placetype":"venue"
},
  "geometry": {"coordinates":[8.0492696762,47.3958396912],"type":"Point"}
}