{
  "type": "Feature",
  "properties": {
    "iso:country":"CH",
    "sg:address":"Industriestrasse 27",
    "sg:city":"Zug",
    "sg:orig_category":"Sonstige mit der Informatik verbundene T\u00e4tigkeiten",
    "sg:postcode":"6300",
    "sg:province":"Zug",
    "wof:name":"Pc-experts Thomas Weingartner",
    "wof:placetype":"venue"
},
  "geometry": {"coordinates":[8.5193052292,47.1758956909],"type":"Point"}
}