{
  "type": "Feature",
  "properties": {
    "iso:country":"CH",
    "sg:address":"Aegeristrasse 7",
    "sg:city":"Sattel",
    "sg:orig_category":"Sportschulen Ski-& Snowboardschulen",
    "sg:phone":"+41 33 733 26 23",
    "sg:postcode":"6417",
    "sg:province":"Schwyz",
    "wof:name":"Schweiz.skischule Herrn Anton H\u00e4hlen",
    "wof:placetype":"venue"
},
  "geometry": {"coordinates":[7.4413700104,46.4569587708],"type":"Point"}
}