{
  "type": "Feature",
  "properties": {
    "iso:country":"CH",
    "sg:address":"Friedrichstrasse 16",
    "sg:city":"Basel",
    "sg:orig_category":"Allgemeiner Hoch U Tiefbau",
    "sg:phone":"+41 61 301 61 52",
    "sg:postcode":"4055",
    "sg:province":"Basel-Stadt",
    "wof:name":"Aeschbacher Bauunternehmung Ag",
    "wof:placetype":"venue"
},
  "geometry": {"coordinates":[7.574775,47.55645],"type":"Point"}
}