{
  "type": "Feature",
  "properties": {
    "iso:country":"CH",
    "sg:address":"Lindenhalden",
    "sg:city":"Rengg",
    "sg:orig_category":"Verwertung von Milch",
    "sg:postcode":"6162",
    "sg:province":"Luzern",
    "wof:name":"K\u00e4sereigenossenschaft Bramegg-rengg",
    "wof:placetype":"venue"
},
  "geometry": {"coordinates":[8.0649986267,46.9928016663],"type":"Point"}
}