{
  "type": "Feature",
  "properties": {
    "iso:country":"CH",
    "sg:address":"B\u00fctschwilerstrasse 11",
    "sg:city":"Mosnang",
    "sg:orig_category":"Webereien, Webwaren",
    "sg:phone":"+41 71 983 15 15",
    "sg:postcode":"9607",
    "sg:province":"St. Gallen",
    "wof:name":"Weberei Artex Ag",
    "wof:placetype":"venue"
},
  "geometry": {"coordinates":[9.0430784225,47.3628501892],"type":"Point"}
}