{
  "type": "Feature",
  "properties": {
    "iso:country":"CH",
    "sg:address":"Via Bosia 15",
    "sg:city":"Paradiso",
    "sg:orig_category":"Zahntechnische Laboratorien",
    "sg:phone":"+41 79 240 57 22",
    "sg:postcode":"6900",
    "sg:province":"Ticino",
    "wof:name":"Riccardo Poma Laboratorio D'odontotecnico",
    "wof:placetype":"venue"
},
  "geometry": {"coordinates":[8.9473114014,45.9902496338],"type":"Point"}
}