{
  "type": "Feature",
  "properties": {
    "iso:country":"CH",
    "sg:address":"Via Serodine",
    "sg:city":"Lugano",
    "sg:orig_category":"Vermietung U Verpachtung von eigenen Immobilien",
    "sg:postcode":"6900",
    "sg:province":"Ticino",
    "wof:name":"Si Ai Ronchi Sa",
    "wof:placetype":"venue"
},
  "geometry": {"coordinates":[8.9398698807,46.0083427429],"type":"Point"}
}