{
  "type": "Feature",
  "properties": {
    "iso:country":"CH",
    "sg:address":"St\u00e4dtchenstrasse 1",
    "sg:city":"Sargans",
    "sg:orig_category":"Aktivit\u00e4ten der Krankenschwestern U Hebammen, Hauspflege",
    "sg:phone":"+41 81 723 82 34",
    "sg:postcode":"7320",
    "sg:province":"St. Gallen",
    "wof:name":"Spitex Verein",
    "wof:placetype":"venue"
},
  "geometry": {"coordinates":[9.440104,47.047901],"type":"Point"}
}