{
  "type": "Feature",
  "properties": {
    "iso:country":"CH",
    "sg:address":"Centralstrasse 33",
    "sg:city":"Sursee",
    "sg:orig_category":"Detailhandel mit Gebrauchtwaren in Verkaufsr\u00e4umen",
    "sg:phone":"+41 71 220 34 76",
    "sg:postcode":"6210",
    "sg:province":"Luzern",
    "wof:name":"J\u00fcrgen Feldmann Tr\u00f6dler & Flohmarkt",
    "wof:placetype":"venue"
},
  "geometry": {"coordinates":[9.3928098679,47.4172592163],"type":"Point"}
}