{
  "type": "Feature",
  "properties": {
    "iso:country":"CH",
    "sg:address":"Voxenweidstrasse 3",
    "sg:city":"Fulenbach",
    "sg:orig_category":"Herstellung von Metallerzeugnissen ohne Maschinenbau Herstellung von Waffen U Munition",
    "sg:phone":"+41 62 926 13 10",
    "sg:postcode":"4629",
    "sg:province":"Solothurn",
    "wof:name":"Tanner Sportwaffen Ag",
    "wof:placetype":"venue"
},
  "geometry": {"coordinates":[7.830616951,47.2704048157],"type":"Point"}
}