{
  "type": "Feature",
  "properties": {
    "iso:country":"CH",
    "sg:address":"Alpmechrain 6",
    "sg:city":"Dornach",
    "sg:classifiers":[
        {
            "category":"Home & Garden",
            "subcategory":"Carpets & Floor Coverings",
            "type":"Retail Goods"
        }
    ],
    "sg:phone":"+41 61 703 90 45",
    "sg:postcode":"4143",
    "sg:province":"Solothurn",
    "sg:tags":[
        "blind",
        "nut",
        "rivet"
    ],
    "wof:name":"Top Screw Metal Corp.",
    "wof:placetype":"venue"
},
  "geometry": {"coordinates":[7.620508,47.47522],"type":"Point"}
}