{
  "type": "Feature",
  "properties": {
    "iso:country":"CH",
    "sg:address":"2114 Fleurier Case Postale 322",
    "sg:city":"Fleurier",
    "sg:orig_category":"Politische Parteien SP",
    "sg:phone":"+41 32 853 30 94",
    "sg:postcode":"2114",
    "sg:province":"Neuch\u00e2tel",
    "wof:name":"Parti Socialiste Fontaines",
    "wof:placetype":"venue"
},
  "geometry": {"coordinates":[6.8977308273,47.0404014587],"type":"Point"}
}