{
  "type": "Feature",
  "properties": {
    "iso:country":"CH",
    "sg:address":"Maihofstrasse 8",
    "sg:city":"Luzern",
    "sg:orig_category":"Herstellung von Reiseartikeln, Leder U Sattlerwaren",
    "sg:phone":"+41 41 420 16 04",
    "sg:postcode":"6004",
    "sg:province":"Luzern",
    "wof:name":"Schaer G. Sattlerei",
    "wof:placetype":"venue"
},
  "geometry": {"coordinates":[8.309012413,47.0614967346],"type":"Point"}
}