{
  "type": "Feature",
  "properties": {
    "iso:country":"CH",
    "sg:address":"Inwilerriedstrasse 49",
    "sg:city":"Baar",
    "sg:orig_category":"Softwareentwicklung U beratung",
    "sg:phone":"+41 41 760 21 04",
    "sg:postcode":"6340",
    "sg:province":"Zug",
    "wof:name":"Ose Open Systems Engineering, G\u00fcnthardt Marc",
    "wof:placetype":"venue"
},
  "geometry": {"coordinates":[8.528968811,47.1840553284],"type":"Point"}
}