{
  "type": "Feature",
  "properties": {
    "iso:country":"CH",
    "sg:address":"Pf\u00e4ffikonerstrasse 1 8834 Schindellegi. Postfach",
    "sg:city":"Schindellegi",
    "sg:orig_category":"Kantonalbanken",
    "sg:phone":"+41 17850035",
    "sg:postcode":"8834",
    "sg:province":"Schwyz",
    "wof:name":"Schwyzer Kantonalbank",
    "wof:placetype":"venue"
},
  "geometry": {"coordinates":[8.7125654221,47.1749916077],"type":"Point"}
}