{
  "type": "Feature",
  "properties": {
    "iso:country":"CH",
    "sg:address":"Biderstrasse 22",
    "sg:city":"Bern",
    "sg:orig_category":"Primarschulen",
    "sg:postcode":"3006",
    "sg:province":"Bern",
    "wof:name":"Primarschule Biderstrasse/pav.",
    "wof:placetype":"venue"
},
  "geometry": {"coordinates":[7.4784631729,46.9589576721],"type":"Point"}
}