{
  "type": "Feature",
  "properties": {
    "iso:country":"CH",
    "sg:address":"G\u00fcterstrasse 39 9444 Diepoldsau. Postfach",
    "sg:city":"Diepoldsau",
    "sg:orig_category":"Spinnstoffaufbereitung U Spinnerei",
    "sg:phone":"+41 71 737 90 10",
    "sg:postcode":"9444",
    "sg:province":"St. Gallen",
    "wof:name":"Fein-elast Grabher Ag",
    "wof:placetype":"venue"
},
  "geometry": {"coordinates":[9.6514911652,47.3926811218],"type":"Point"}
}