{
  "type": "Feature",
  "properties": {
    "iso:country":"CH",
    "sg:address":"Lac Tanay",
    "sg:city":"Miex",
    "sg:classifiers":[
        {
            "category":"Travel",
            "subcategory":"Hotels & Motels",
            "type":"Entertainment"
        }
    ],
    "sg:phone":"+41 24 481 11 83",
    "sg:postcode":"1896",
    "sg:province":"Valais",
    "sg:tags":[
        "hotels",
        "mit",
        "restaurant"
    ],
    "wof:name":"Auberge-refuge Du Grammont",
    "wof:placetype":"venue"
},
  "geometry": {"coordinates":[6.8908228874,46.3360748291],"type":"Point"}
}