{
  "type": "Feature",
  "properties": {
    "iso:country":"CH",
    "sg:address":"3945",
    "sg:city":"Niedergampel",
    "sg:orig_category":"Darlehenskassen U Raiffeisenbanken",
    "sg:phone":"+41 27 932 48 18",
    "sg:postcode":"3945",
    "sg:province":"Valais",
    "wof:name":"Raiffeisenbank",
    "wof:placetype":"venue"
},
  "geometry": {"coordinates":[7.71353,46.312149],"type":"Point"}
}