{
  "type": "Feature",
  "properties": {
    "iso:country":"CH",
    "sg:address":"3672",
    "sg:city":"Aeschlen",
    "sg:orig_category":"Vorschulen, Kinderg\u00e4rten",
    "sg:phone":"+41 31 771 04 80",
    "sg:postcode":"3672",
    "sg:province":"Bern",
    "wof:name":"Kindergarten",
    "wof:placetype":"venue"
},
  "geometry": {"coordinates":[7.640610218,46.8364295959],"type":"Point"}
}