{
  "type": "Feature",
  "properties": {
    "iso:country":"CH",
    "sg:address":"Alte Landstrasse 28",
    "sg:city":"Thalwil",
    "sg:orig_category":"Druck ohne Zeitungsdruck",
    "sg:phone":"+41 17201477",
    "sg:postcode":"8800",
    "sg:province":"Z\u00fcrich",
    "wof:name":"Mailprint Gmbh",
    "wof:placetype":"venue"
},
  "geometry": {"coordinates":[8.5724821091,47.2835083008],"type":"Point"}
}