{
  "type": "Feature",
  "properties": {
    "iso:country":"CH",
    "sg:address":"Hauptstrasse 348",
    "sg:city":"Hallau",
    "sg:orig_category":"Architektur U Ingenieurb\u00fcros",
    "sg:phone":"+41 52 681 45 20",
    "sg:postcode":"8215",
    "sg:province":"Schaffhausen",
    "wof:name":"Ingenieurb\u00fcro Ranft Kurt",
    "wof:placetype":"venue"
},
  "geometry": {"coordinates":[8.457394,47.69659],"type":"Point"}
}