{
  "type": "Feature",
  "properties": {
    "addr:full":"Zugerstrasse 166 Unterlunkhofen Aargau 8918",
    "addr:housenumber":"166",
    "addr:postcode":"8918",
    "addr:street":"Zugerstrasse",
    "iso:country":"CH",
    "sg:address":"Zugerstrasse 166",
    "sg:city":"Unterlunkhofen",
    "sg:classifiers":[
        {
            "category":"Arena",
            "subcategory":"Auto Racetrack",
            "type":"Entertainment"
        }
    ],
    "sg:phone":"+41 41 850 77 44",
    "sg:postcode":"8918",
    "sg:province":"Aargau",
    "sg:tags":[
        "car",
        "trailer",
        "roof"
    ],
    "wof:name":"Schuler & Schl\u00f6mmer Gmbh",
    "wof:placetype":"venue"
},
  "geometry": {"coordinates":[8.441568,47.081211],"type":"Point"}
}