{
  "type": "Feature",
  "properties": {
    "iso:country":"CH",
    "sg:address":"Seestrasse 448",
    "sg:city":"Merligen",
    "sg:orig_category":"Bauschreinerei Herstellung von M\u00f6beln verschiedener Art",
    "sg:phone":"+41 33 251 13 87",
    "sg:postcode":"3658",
    "sg:province":"Bern",
    "wof:name":"Kurt Von Gunten Bau-& M\u00f6belschreinerei",
    "wof:placetype":"venue"
},
  "geometry": {"coordinates":[7.736557,46.699699],"type":"Point"}
}