{
  "type": "Feature",
  "properties": {
    "iso:country":"CH",
    "sg:address":"Techno-p\u00f4le",
    "sg:city":"Sierre",
    "sg:orig_category":"Hardwareberatung",
    "sg:postcode":"3960",
    "sg:province":"Valais",
    "wof:name":"Akts Sa",
    "wof:placetype":"venue"
},
  "geometry": {"coordinates":[7.5384831429,46.2837677002],"type":"Point"}
}