{
  "type": "Feature",
  "properties": {
    "iso:country":"CH",
    "sg:address":"Oberdorf",
    "sg:city":"Saanen",
    "sg:orig_category":"Herstellung von sonstigen keramischen Erzeugnissen",
    "sg:phone":"+41 33 744 23 02",
    "sg:postcode":"3792",
    "sg:province":"Bern",
    "wof:name":"Ek Enzian Keramik Gmbh",
    "wof:placetype":"venue"
},
  "geometry": {"coordinates":[7.2665147781,46.4884796143],"type":"Point"}
}