{
  "type": "Feature",
  "properties": {
    "addr:full":"B\u00e4chlenstrasse Oey Bern 3753",
    "addr:postcode":"3753",
    "addr:street":"Baechlenstrasse Oey Bern",
    "iso:country":"CH",
    "sg:address":"B\u00e4chlenstrasse",
    "sg:city":"Oey",
    "sg:orig_category":"Detailhandel mit Brot, Back U S\u00fcsswaren Grosshandel mit Nahrungsmitteln, Getr\u00e4nken U Tabakwaren ohne",
    "sg:phone":"+41 33 681 11 19",
    "sg:postcode":"3753",
    "sg:province":"Bern",
    "wof:name":"Bieri Oey Ag B\u00e4ckerei-konditorei",
    "wof:placetype":"venue"
},
  "geometry": {"coordinates":[7.577276,46.65836],"type":"Point"}
}