{
  "type": "Feature",
  "properties": {
    "iso:country":"CH",
    "sg:address":"Plaine Rue De La 38 1400 Yverdon-les-bains Case Postale 338",
    "sg:city":"Yverdon-les-bains",
    "sg:orig_category":"Vermietung U Verpachtung von eigenen Immobilien",
    "sg:phone":"+41 24 423 45 45",
    "sg:postcode":"1400",
    "sg:province":"Vaud",
    "wof:name":"R\u00e9gie Immobili\u00e8re Decker Charles Sa",
    "wof:placetype":"venue"
},
  "geometry": {"coordinates":[6.6414198875,46.7786331177],"type":"Point"}
}