{
  "type": "Feature",
  "properties": {
    "iso:country":"CH",
    "sg:address":"Im Langen Loh 145 4054 Basel. Postfach",
    "sg:city":"Basel",
    "sg:orig_category":"Unclassifiable Establishments",
    "sg:phone":"+41 61 302 44 35",
    "sg:postcode":"4051",
    "sg:province":"Basel-Stadt",
    "wof:name":"Rutishauser Drogerie",
    "wof:placetype":"venue"
},
  "geometry": {"coordinates":[7.5613307953,47.5517234802],"type":"Point"}
}