{
  "type": "Feature",
  "properties": {
    "iso:country":"CH",
    "sg:address":"Feld\u00e4ckerweg 7",
    "sg:city":"W\u00e4ngi",
    "sg:orig_category":"Grosshandel mit Textilien Grosshandel mit sonstigen Konsumg\u00fctern",
    "sg:phone":"+41 52 378 31 00",
    "sg:postcode":"9545",
    "sg:province":"Thurgau",
    "wof:name":"Amitex Ag",
    "wof:placetype":"venue"
},
  "geometry": {"coordinates":[8.9472494125,47.4958267212],"type":"Point"}
}