{
  "type": "Feature",
  "properties": {
    "iso:country":"CH",
    "sg:address":"5322",
    "sg:city":"Koblenz",
    "sg:orig_category":"Sportvereine Turnen Vereine Damen",
    "sg:postcode":"5322",
    "sg:province":"Aargau",
    "wof:name":"Damenturnverein",
    "wof:placetype":"venue"
},
  "geometry": {"coordinates":[8.2425298691,47.6053009033],"type":"Point"}
}