{
  "type": "Feature",
  "properties": {
    "iso:country":"CH",
    "sg:address":"Wasserwerkgasse 7 3011 Bern. Postfach",
    "sg:city":"Bern",
    "sg:classifiers":[
        {
            "category":"Restaurant",
            "type":"Food & Drink"
        }
    ],
    "sg:phone":"+41 31 312 21 22",
    "sg:postcode":"3005",
    "sg:province":"Bern",
    "sg:tags":[
        "tea-rooms",
        "restaurants"
    ],
    "wof:name":"Cin\u00e9matte Restaurant.bar Lutz Christian",
    "wof:placetype":"venue"
},
  "geometry": {"coordinates":[7.4573230743,46.9468269348],"type":"Point"}
}