{
  "type": "Feature",
  "properties": {
    "iso:country":"CH",
    "sg:address":"Hauptstrasse 178 6436 Muotathal. Postfach",
    "sg:city":"Muotathal",
    "sg:orig_category":"Non-Classified Establishments",
    "sg:postcode":"6436",
    "sg:province":"Schwyz",
    "wof:name":"F\u00f6hn-heinzer Peter Holding Ag",
    "wof:placetype":"venue"
},
  "geometry": {"coordinates":[8.7730751038,46.9727287292],"type":"Point"}
}