{
  "type": "Feature",
  "properties": {
    "iso:country":"CH",
    "sg:address":"1470 Estavayer-le-lac Case Postale 45",
    "sg:city":"Estavayer-le-lac",
    "sg:orig_category":"Aktivit\u00e4ten der Generalunternehmen im Baugewerbe",
    "sg:phone":"+41 26 663 45 63",
    "sg:postcode":"1470",
    "sg:province":"Fribourg",
    "wof:name":"Cba 2000 Sa Constructions De Villas",
    "wof:placetype":"venue"
},
  "geometry": {"coordinates":[6.848279,46.848793],"type":"Point"}
}