{
  "type": "Feature",
  "properties": {
    "iso:country":"CH",
    "sg:address":"L\u00f6wenstr. 1 1588 Cudrefin. Postfach",
    "sg:city":"Z\u00fcrich",
    "sg:orig_category":"Interessenvertretungen",
    "sg:phone":"+41 12179111",
    "sg:postcode":"8001",
    "sg:province":"Z\u00fcrich",
    "wof:name":"Fondation Schnorf J.p. La Sauge",
    "wof:placetype":"venue"
},
  "geometry": {"coordinates":[7.0185198784,46.9558601379],"type":"Point"}
}