{
  "type": "Feature",
  "properties": {
    "iso:country":"CH",
    "sg:address":"B\u00e4rengasse 21",
    "sg:city":"Zofingen",
    "sg:orig_category":"Detailhandel mit Waren verschiedener Art, Hauptrichtung Nahrungsmittel Grosshandel mit Nahrungsmitte",
    "sg:phone":"+41 62 751 67 53",
    "sg:postcode":"4800",
    "sg:province":"Aargau",
    "wof:name":"Buon Gusto Pantaleo Marcello",
    "wof:placetype":"venue"
},
  "geometry": {"coordinates":[7.9450421333,47.290599823],"type":"Point"}
}