{
  "type": "Feature",
  "properties": {
    "iso:country":"CH",
    "sg:address":"Nasi Carra Dei 1b",
    "sg:city":"Ascona",
    "sg:orig_category":"Verwaltung von Immobilien",
    "sg:postcode":"6612",
    "sg:province":"Ticino",
    "wof:name":"Nabila Sagl",
    "wof:placetype":"venue"
},
  "geometry": {"coordinates":[8.7681865692,46.1560707092],"type":"Point"}
}