{
  "type": "Feature",
  "properties": {
    "iso:country":"CH",
    "sg:address":"Hauptstrasse 992b",
    "sg:city":"Goldswil",
    "sg:orig_category":"Autolackierereien Autospenglereien",
    "sg:phone":"+41 32 351 30 30",
    "sg:postcode":"3805",
    "sg:province":"Bern",
    "wof:name":"Damiano Bozza Carrosserie & Automalerei",
    "wof:placetype":"venue"
},
  "geometry": {"coordinates":[7.360879,47.135876],"type":"Point"}
}