{
  "type": "Feature",
  "properties": {
    "iso:country":"CH",
    "sg:address":"Schmitterstrasse 7",
    "sg:city":"Diepoldsau",
    "sg:classifiers":[
        {
            "category":"Utilities",
            "subcategory":"Cable",
            "type":"Services"
        }
    ],
    "sg:phone":"+41 71 288 11 33",
    "sg:postcode":"9444",
    "sg:province":"St. Gallen",
    "sg:tags":[
        "brake",
        "vehicle"
    ],
    "wof:name":"F\u00fcrk & Zeilinger Ag",
    "wof:placetype":"venue"
},
  "geometry": {"coordinates":[9.418896,47.43848],"type":"Point"}
}