{
  "type": "Feature",
  "properties": {
    "iso:country":"CH",
    "sg:address":"R\u00e4mistrasse 2",
    "sg:city":"Z\u00fcrich",
    "sg:orig_category":"Zahnarztpraxen",
    "sg:phone":"+41 12525121",
    "sg:postcode":"8001",
    "sg:province":"Z\u00fcrich",
    "wof:name":"Dr. Med. Dent. Finn Nielsen Zahnarzt",
    "wof:placetype":"venue"
},
  "geometry": {"coordinates":[8.5455350876,47.3674926758],"type":"Point"}
}