{
  "type": "Feature",
  "properties": {
    "iso:country":"CH",
    "sg:address":"H\u00f6henstrasse 10b",
    "sg:city":"Ramlinsburg",
    "sg:orig_category":"Gesundheitswesen",
    "sg:phone":"+41 61 981 58 50",
    "sg:postcode":"4433",
    "sg:province":"Basel-Landschaft",
    "wof:name":"Balsiger Sonja, Lern Und Legasthenieberatungen",
    "wof:placetype":"venue"
},
  "geometry": {"coordinates":[7.7661838531,47.4493865967],"type":"Point"}
}