{
  "type": "Feature",
  "properties": {
    "iso:country":"CH",
    "sg:address":"Messeplatz 25 4058 Basel. Postfach 336",
    "sg:city":"Basel",
    "sg:classifiers":[
        {
            "category":"Travel",
            "subcategory":"Hotels & Motels",
            "type":"Entertainment"
        }
    ],
    "sg:phone":"+41 61 690 33 33",
    "sg:postcode":"4021",
    "sg:tags":[
        "hotels",
        "mit",
        "restaurant"
    ],
    "wof:name":"Le Plaza Basel Ag",
    "wof:placetype":"venue"
},
  "geometry": {"coordinates":[7.599293232,47.5632247925],"type":"Point"}
}