{
  "type": "Feature",
  "properties": {
    "iso:country":"CH",
    "sg:address":"Kuttelgasse 4",
    "sg:city":"Z\u00fcrich",
    "sg:orig_category":"Detailhandel mit Geschenkartikeln U Souvenirs Grosshandel mit Textilien",
    "sg:phone":"+41 33 744 11 78",
    "sg:postcode":"8001",
    "sg:province":"Z\u00fcrich",
    "wof:name":"Ernst Loertscher-graa, Nachfolger Marianne Und Daniel Loertscher",
    "wof:placetype":"venue"
},
  "geometry": {"coordinates":[7.2861051559,46.4732818604],"type":"Point"}
}