{
  "type": "Feature",
  "properties": {
    "iso:country":"CH",
    "sg:address":"Seetalstrasse 133",
    "sg:city":"Schafisheim",
    "sg:classifiers":[
        {
            "category":"Restaurant",
            "type":"Food & Drink"
        }
    ],
    "sg:phone":"+41 55 644 16 14",
    "sg:postcode":"5503",
    "sg:province":"Aargau",
    "wof:name":"Wirtschaft Zum Raben",
    "wof:placetype":"venue"
},
  "geometry": {"coordinates":[9.0657901764,46.9964103699],"type":"Point"}
}