{
  "type": "Feature",
  "properties": {
    "iso:country":"CH",
    "sg:address":"Dorfstrasse 78 3715 Adelboden. Postfach 242",
    "sg:city":"Adelboden",
    "sg:orig_category":"Sanit\u00e4rinstallation Zimmerei, Dachdeckerei, Bauspenglerei U Abdichtung",
    "sg:phone":"+41 33 673 10 53",
    "sg:postcode":"3715",
    "sg:province":"Bern",
    "wof:name":"M\u00fcller Haustechnik Gmbh",
    "wof:placetype":"venue"
},
  "geometry": {"coordinates":[7.5542712212,46.4894790649],"type":"Point"}
}