{
  "type": "Feature",
  "properties": {
    "iso:country":"CH",
    "sg:address":"Freiburgstrasse 443b 3018 Bern. Postfach 5126",
    "sg:city":"Bern",
    "sg:orig_category":"Handel mit Automobilen",
    "sg:phone":"+41 31 991 14 54",
    "sg:postcode":"3018",
    "sg:province":"Bern",
    "wof:name":"Autocentro Willy Ag, Bern",
    "wof:placetype":"venue"
},
  "geometry": {"coordinates":[7.3923392296,46.9345245361],"type":"Point"}
}