{
  "type": "Feature",
  "properties": {
    "addr:full":"Bahnhofstrasse 12 B\u00fcron Luzern 6233",
    "addr:housenumber":"12",
    "addr:postcode":"6233",
    "addr:street":"Bahnhofstrasse",
    "iso:country":"CH",
    "sg:address":"Bahnhofstrasse 12",
    "sg:city":"B\u00fcron",
    "sg:orig_category":"Darlehenskassen U Raiffeisenbanken",
    "sg:phone":"+41 41 933 23 23",
    "sg:postcode":"6233",
    "sg:province":"Luzern",
    "wof:name":"Raiffeisenbank",
    "wof:placetype":"venue"
},
  "geometry": {"coordinates":[8.093074,47.213127],"type":"Point"}
}