{
  "type": "Feature",
  "properties": {
    "iso:country":"CH",
    "sg:address":"Tomenrain 5",
    "sg:city":"Gutenswil",
    "sg:orig_category":"Sportvereine Automobil",
    "sg:phone":"+41 79 612 33 76",
    "sg:postcode":"8605",
    "sg:province":"Z\u00fcrich",
    "wof:name":"Bmw-veteranen Club Schweiz",
    "wof:placetype":"venue"
},
  "geometry": {"coordinates":[8.7153530121,47.3863677979],"type":"Point"}
}