{
  "type": "Feature",
  "properties": {
    "iso:country":"CH",
    "sg:address":"Avenue Du Midi 9 1950 Sion Case Postale 496",
    "sg:city":"Sion",
    "sg:orig_category":"Detailhandel mit Musikinstrumenten Detailhandel mit elektrischen Haushalts-,Radio U Fernsehger\u00e4ten s",
    "sg:phone":"+41 27 322 10 63",
    "sg:postcode":"1951",
    "sg:province":"Valais",
    "wof:name":"Hug Musique Sa",
    "wof:placetype":"venue"
},
  "geometry": {"coordinates":[7.3598198891,46.2311897278],"type":"Point"}
}