{
  "type": "Feature",
  "properties": {
    "iso:country":"CH",
    "sg:address":"Avenue Des Morgines 12",
    "sg:city":"Petit-lancy",
    "sg:orig_category":"Elektrischer Leitungsbau Fernmeldedienste",
    "sg:phone":"+41 21 923 31 13",
    "sg:postcode":"1213",
    "sg:province":"Gen\u00e8ve",
    "wof:name":"Fibre Lac Sa Op\u00e9rateur De T\u00e9l\u00e9communcations",
    "wof:placetype":"venue"
},
  "geometry": {"coordinates":[5.1808700562,45.8973388672],"type":"Point"}
}