{
  "type": "Feature",
  "properties": {
    "iso:country":"CH",
    "sg:address":"Industriestrasse 2",
    "sg:city":"D\u00fcdingen",
    "sg:orig_category":"Instandhaltung U Reparatur von Automobilen",
    "sg:phone":"+41 26 493 16 16",
    "sg:postcode":"3186",
    "sg:province":"Fribourg",
    "wof:name":"Garage-carrosserie Fasel Ag",
    "wof:placetype":"venue"
},
  "geometry": {"coordinates":[7.1914148331,46.8541412354],"type":"Point"}
}