{
  "type": "Feature",
  "properties": {
    "iso:country":"CH",
    "sg:address":"Rennweg 80",
    "sg:city":"Basel",
    "sg:orig_category":"Architektur U Ingenieurb\u00fcros",
    "sg:phone":"+41 61 271 14 18",
    "sg:postcode":"4052",
    "sg:province":"Basel-Stadt",
    "wof:name":"Sk Automation Ag",
    "wof:placetype":"venue"
},
  "geometry": {"coordinates":[7.609624,47.550018],"type":"Point"}
}