{
  "type": "Feature",
  "properties": {
    "addr:full":"Oetlingerstrasse 35 Basel Basel-Stadt 4057",
    "addr:housenumber":"35",
    "addr:postcode":"4057",
    "addr:street":"Oetlingerstrasse",
    "iso:country":"CH",
    "sg:address":"Oetlingerstrasse 35",
    "sg:city":"Basel",
    "sg:orig_category":"Detailhandel mit Brot, Back U S\u00fcsswaren",
    "sg:phone":"+41 61 321 46 54",
    "sg:postcode":"4057",
    "sg:province":"Basel-Stadt",
    "wof:name":"A. Wischlen Ag B\u00e4ckerei-konditorei",
    "wof:placetype":"venue"
},
  "geometry": {"coordinates":[7.588984,47.567612],"type":"Point"}
}