{
  "type": "Feature",
  "properties": {
    "iso:country":"CH",
    "sg:address":"Via Del Breggia 19",
    "sg:city":"Vacallo",
    "sg:orig_category":"Detailhandel mit Sportartikeln",
    "sg:postcode":"6833",
    "sg:province":"Ticino",
    "wof:name":"Special Board Shop Simone Tettamanti",
    "wof:placetype":"venue"
},
  "geometry": {"coordinates":[9.0348567963,45.8404579163],"type":"Point"}
}