{
  "type": "Feature",
  "properties": {
    "iso:country":"CH",
    "sg:address":"Mont-blanc Rue Du 3 1201 Gen\u00e8ve Case Postale",
    "sg:city":"Gen\u00e8ve",
    "sg:orig_category":"Non-Classified Establishments",
    "sg:phone":"+41 31 992 55 12",
    "sg:postcode":"1201",
    "sg:province":"Gen\u00e8ve",
    "wof:name":"Mtm - Matic Mato - Transport",
    "wof:placetype":"venue"
},
  "geometry": {"coordinates":[7.4003720284,46.9477424622],"type":"Point"}
}