{
  "type": "Feature",
  "properties": {
    "iso:country":"CH",
    "sg:address":"Ueberlandstrasse 18",
    "sg:city":"Z\u00fcrich",
    "sg:orig_category":"Wein Detailhandel",
    "sg:phone":"+41 13116870",
    "sg:postcode":"8051",
    "sg:province":"Z\u00fcrich",
    "wof:name":"Harald Meili Failla Mascarello Weinkeller",
    "wof:placetype":"venue"
},
  "geometry": {"coordinates":[8.5663700104,47.4073181152],"type":"Point"}
}