{
  "type": "Feature",
  "properties": {
    "iso:country":"CH",
    "sg:address":"Voa Principala 9",
    "sg:city":"Valbella",
    "sg:orig_category":"Detailhandel mit Fleisch U Fleischwaren",
    "sg:phone":"+41 81 384 72 22",
    "sg:postcode":"7077",
    "sg:province":"Graubunden",
    "wof:name":"H. Schafknecht Metzgerei",
    "wof:placetype":"venue"
},
  "geometry": {"coordinates":[9.5553817749,46.7461776733],"type":"Point"}
}