{
  "type": "Feature",
  "properties": {
    "iso:country":"CH",
    "sg:address":"Poststrasse 43",
    "sg:city":"Chur",
    "sg:orig_category":"Wirtschaftsverb\u00e4nde Gewerbeverb\u00e4nde/-vereine",
    "sg:phone":"+41 81 252 63 06",
    "sg:postcode":"7000",
    "sg:province":"Graubunden",
    "wof:name":"Handels-& Gewerbeverein",
    "wof:placetype":"venue"
},
  "geometry": {"coordinates":[9.5323724747,46.8483848572],"type":"Point"}
}