{
  "type": "Feature",
  "properties": {
    "iso:country":"CH",
    "sg:address":"R\u00fcnenbergstrasse 31",
    "sg:city":"Gelterkinden",
    "sg:classifiers":[
        {
            "category":"Bars & Pubs",
            "type":"Food & Drink"
        }
    ],
    "sg:phone":"+41 61 981 66 11",
    "sg:postcode":"4460",
    "sg:province":"Basel-Landschaft",
    "wof:name":"B\u00e4rchi's Gmbh",
    "wof:placetype":"venue"
},
  "geometry": {"coordinates":[7.860715,47.460205],"type":"Point"}
}