{
  "type": "Feature",
  "properties": {
    "iso:country":"CH",
    "sg:address":"Churfirstenstr. 21 9630 Wattwil. Postfach",
    "sg:city":"Ulisbach",
    "sg:orig_category":"Sonstiger Grosshandel",
    "sg:postcode":"9631",
    "sg:province":"St. Gallen",
    "wof:name":"Topas Tschudi Tanneke",
    "wof:placetype":"venue"
},
  "geometry": {"coordinates":[9.099738121,47.28931427],"type":"Point"}
}