{
  "type": "Feature",
  "properties": {
    "iso:country":"CH",
    "sg:address":"Terreaux Rue Des 14",
    "sg:city":"Neuenburg",
    "sg:orig_category":"Interessenvertretungen",
    "sg:phone":"+41 32 725 72 57",
    "sg:postcode":"2000",
    "sg:province":"Neuch\u00e2tel",
    "wof:name":"Centre Suisse De Cartographie De La Faune (cscf)",
    "wof:placetype":"venue"
},
  "geometry": {"coordinates":[6.9302611351,46.9927368164],"type":"Point"}
}