{
  "type": "Feature",
  "properties": {
    "iso:country":"CH",
    "sg:address":"Haldenweg 31",
    "sg:city":"Triesen",
    "sg:orig_category":"Verlegen von Fliesen U Platten",
    "sg:phone":"+423 392 30 90",
    "sg:postcode":"9495",
    "wof:name":"Peter Lageder Plattenbel\u00e4ge",
    "wof:placetype":"venue"
},
  "geometry": {"coordinates":[9.5272884369,47.1150016785],"type":"Point"}
}