{
  "type": "Feature",
  "properties": {
    "iso:country":"CH",
    "sg:address":"Etzelweidstrasse 36",
    "sg:city":"Schindellegi",
    "sg:orig_category":"Sportvereine Schwingen",
    "sg:phone":"+41 41 830 18 49",
    "sg:postcode":"8834",
    "sg:province":"Schwyz",
    "wof:name":"Schwingklub Muotathal",
    "wof:placetype":"venue"
},
  "geometry": {"coordinates":[8.7115955353,46.9886245728],"type":"Point"}
}