{
  "type": "Feature",
  "properties": {
    "iso:country":"CH",
    "sg:address":"Haslen",
    "sg:city":"Oberb\u00fcren",
    "sg:orig_category":"Sonstiger Fachdetailhandel mit Nahrungsmitteln, Getr\u00e4nken U Tabak in Verkaufsr\u00e4umen",
    "sg:postcode":"9245",
    "sg:province":"St. Gallen",
    "wof:name":"Nikfer K\u00e4se Gmbh",
    "wof:placetype":"venue"
},
  "geometry": {"coordinates":[9.1547203064,47.4464645386],"type":"Point"}
}