{
  "type": "Feature",
  "properties": {
    "iso:country":"CH",
    "sg:address":"Bd Du Pont-d'arve 2. 1200 Genf Case Postale",
    "sg:city":"Genf",
    "sg:orig_category":"Detailhandel mit Waren verschiedener Art, Hauptrichtung Nahrungsmittel",
    "sg:postcode":"1200",
    "sg:province":"Gen\u00e8ve",
    "wof:name":"Vente Directe Maisonneuve J. & M.",
    "wof:placetype":"venue"
},
  "geometry": {"coordinates":[6.1900620461,46.1969070435],"type":"Point"}
}