{
  "type": "Feature",
  "properties": {
    "iso:country":"CH",
    "sg:address":"Baarerstrasse 8 6300 Zug. Postfach 244",
    "sg:city":"Zug",
    "sg:orig_category":"Unternehmensberatung Wirtschaftspr\u00fcfung, Steuerberatung U Treuhand",
    "sg:phone":"+41 79 333 46 55",
    "sg:postcode":"6301",
    "sg:province":"Zug",
    "wof:name":"Onyx Trust Services Ag",
    "wof:placetype":"venue"
},
  "geometry": {"coordinates":[8.5163869858,47.1713981628],"type":"Point"}
}