{
  "type": "Feature",
  "properties": {
    "iso:country":"CH",
    "sg:address":"Buhaldeweg 5",
    "sg:city":"Suhr",
    "sg:orig_category":"Detailhandel mit Beleuchtungs U Haushaltsgegenst\u00e4nden",
    "sg:phone":"+41 33 733 33 22",
    "sg:postcode":"5034",
    "sg:province":"Aargau",
    "wof:name":"Hanspeter Rechsteiner Eisenwaren Haushaltartikel",
    "wof:placetype":"venue"
},
  "geometry": {"coordinates":[7.444594,46.457825],"type":"Point"}
}