{
  "type": "Feature",
  "properties": {
    "iso:country":"CH",
    "sg:address":"Dorfstrasse 42",
    "sg:city":"Brittnau",
    "sg:classifiers":[
        {
            "category":"Professional",
            "subcategory":"Employment Agencies",
            "type":"Services"
        }
    ],
    "sg:postcode":"4805",
    "sg:province":"Aargau",
    "sg:tags":[
        "personal",
        "u",
        "stellenvermittlung"
    ],
    "wof:name":"Schneeberger Guido Akkordunternehmung",
    "wof:placetype":"venue"
},
  "geometry": {"coordinates":[7.943488121,47.2606086731],"type":"Point"}
}