{
  "type": "Feature",
  "properties": {
    "iso:country":"CH",
    "sg:address":"Chorgasse 4 4800 Zofingen. Postfach",
    "sg:city":"Zofingen",
    "sg:orig_category":"Allgemeiner Hoch U Tiefbau Allgemeiner Hochbau",
    "sg:phone":"+41 62 746 08 08",
    "sg:postcode":"4800",
    "sg:province":"Aargau",
    "wof:name":"Meier Und J\u00e4ggi Ag Bauunternehmung",
    "wof:placetype":"venue"
},
  "geometry": {"coordinates":[7.945652,47.28875],"type":"Point"}
}