{
  "type": "Feature",
  "properties": {
    "iso:country":"CH",
    "sg:address":"Route De Florissant 51",
    "sg:city":"Gen\u00e8ve",
    "sg:orig_category":"Konsulate",
    "sg:phone":"+41 22 734 93 40",
    "sg:postcode":"1206",
    "sg:province":"Gen\u00e8ve",
    "wof:name":"Consulat G\u00e9n\u00e9ral De Sri Lanka",
    "wof:placetype":"venue"
},
  "geometry": {"coordinates":[6.1301689148,46.2225151062],"type":"Point"}
}