{
  "type": "Feature",
  "properties": {
    "iso:country":"CH",
    "sg:address":"Hauptstrasse 39",
    "sg:city":"Kreuzlingen",
    "sg:orig_category":"Advokaturb\u00fcros",
    "sg:phone":"+41 71 678 10 10",
    "sg:postcode":"8280",
    "sg:province":"Thurgau",
    "wof:name":"Lindt Oberh\u00e4nsli Zollikofer & R\u00fcedi",
    "wof:placetype":"venue"
},
  "geometry": {"coordinates":[9.174669,47.650288],"type":"Point"}
}