{
  "type": "Feature",
  "properties": {
    "iso:country":"CH",
    "sg:address":"Aavorstadt 40 5600 Lenzburg. Postfach",
    "sg:city":"Lenzburg",
    "sg:orig_category":"Herstellung von Werkzeugen",
    "sg:postcode":"5600",
    "sg:province":"Aargau",
    "wof:name":"A. Schulthess",
    "wof:placetype":"venue"
},
  "geometry": {"coordinates":[7.5645999908,46.9250717163],"type":"Point"}
}