{
  "type": "Feature",
  "properties": {
    "iso:country":"CH",
    "sg:address":"Gasterstrasse 66",
    "sg:city":"Kaltbrunn",
    "sg:orig_category":"Handels-H\u00e4user U Gesellschaften",
    "sg:postcode":"8722",
    "sg:province":"St. Gallen",
    "wof:name":"Th\u00fclner Sa",
    "wof:placetype":"venue"
},
  "geometry": {"coordinates":[9.1906442642,46.4630699158],"type":"Point"}
}