{
  "type": "Feature",
  "properties": {
    "iso:country":"CH",
    "sg:address":"Les Places",
    "sg:city":"Tramelan",
    "sg:classifiers":[
        {
            "category":"Restaurant",
            "type":"Food & Drink"
        }
    ],
    "sg:phone":"+41 32 487 44 67",
    "sg:postcode":"2720",
    "sg:province":"Bern",
    "wof:name":"Restaurant Bellevue",
    "wof:placetype":"venue"
},
  "geometry": {"coordinates":[7.1467652321,47.2409248352],"type":"Point"}
}