{
  "type": "Feature",
  "properties": {
    "iso:country":"CH",
    "sg:address":"6928",
    "sg:city":"Manno",
    "sg:orig_category":"Chemische Industrie",
    "sg:phone":"+41 91 605 34 31",
    "sg:postcode":"6928",
    "sg:province":"Ticino",
    "wof:name":"Schoch Max Sa Prodotti Techno-chimici",
    "wof:placetype":"venue"
},
  "geometry": {"coordinates":[8.92017,46.029839],"type":"Point"}
}