{
  "type": "Feature",
  "properties": {
    "iso:country":"CH",
    "sg:address":"Neuengass-passage 3",
    "sg:city":"Bern",
    "sg:orig_category":"Herstellung von sonstigen Metallwaren Reparatur von Schuhen U Lederwaren",
    "sg:phone":"+41 17619347",
    "sg:postcode":"3011",
    "sg:province":"Bern",
    "wof:name":"Vincenzo Marinaccio Schuh-& Schl\u00fcsselservice",
    "wof:placetype":"venue"
},
  "geometry": {"coordinates":[8.4512405396,47.2764511108],"type":"Point"}
}