{
  "type": "Feature",
  "properties": {
    "iso:country":"CH",
    "sg:address":"Dammstrasse 36",
    "sg:city":"M\u00fcnchenstein",
    "sg:orig_category":"Herstellung von Teilen U Zubeh\u00f6r f\u00fcr Automobile",
    "sg:phone":"+41 61 411 10 20",
    "sg:postcode":"4142",
    "sg:province":"Basel-Landschaft",
    "wof:name":"Beer Movement Design",
    "wof:placetype":"venue"
},
  "geometry": {"coordinates":[7.6139960289,47.5256156921],"type":"Point"}
}