{
  "type": "Feature",
  "properties": {
    "iso:country":"CH",
    "sg:address":"Kirchstrasse 4",
    "sg:city":"Bonaduz",
    "sg:orig_category":"Grosshandel mit B\u00fcromaschinen Grosshandel mit Datenverarbeitungsger\u00e4ten",
    "sg:phone":"+41 81 630 21 11",
    "sg:postcode":"7402",
    "sg:province":"Graubunden",
    "wof:name":"Werth Informatik Ag",
    "wof:placetype":"venue"
},
  "geometry": {"coordinates":[9.4006061554,46.8116264343],"type":"Point"}
}