{
  "type": "Feature",
  "properties": {
    "iso:country":"CH",
    "sg:address":"Morgenstrasse 12",
    "sg:city":"Steckborn",
    "sg:orig_category":"Arztpraxen",
    "sg:phone":"+41 52 761 20 66",
    "sg:postcode":"8266",
    "sg:province":"Thurgau",
    "wof:name":"Dr.med. Martin Haas Arzt F\u00fcr Allgemeine Medizin",
    "wof:placetype":"venue"
},
  "geometry": {"coordinates":[8.986129,47.666904],"type":"Point"}
}