{
  "type": "Feature",
  "properties": {
    "iso:country":"CH",
    "sg:address":"Neue Winterthurerstrasse 26",
    "sg:city":"Wallisellen",
    "sg:orig_category":"Vermietung U Verpachtung von eigenen Immobilien",
    "sg:postcode":"8304",
    "sg:province":"Z\u00fcrich",
    "wof:name":"Remerie Immobilien Ag",
    "wof:placetype":"venue"
},
  "geometry": {"coordinates":[8.6078386307,47.4107322693],"type":"Point"}
}