{
  "type": "Feature",
  "properties": {
    "iso:country":"CH",
    "sg:address":"Untere Blumenrainstrasse 17",
    "sg:city":"Appenzell",
    "sg:orig_category":"Arztpraxen",
    "sg:phone":"+41 71 787 41 41",
    "sg:postcode":"9050",
    "sg:province":"Appenzell Innerhoden",
    "wof:name":"Dr.med.kurt Ebneter Arzt F.allgemeine Medizin Fmh",
    "wof:placetype":"venue"
},
  "geometry": {"coordinates":[9.415629,47.331097],"type":"Point"}
}