{
  "type": "Feature",
  "properties": {
    "iso:country":"CH",
    "sg:address":"Rue De Lausanne 25",
    "sg:city":"Vevey",
    "sg:orig_category":"Versicherungen Hauptagenturen",
    "sg:phone":"+41 21 921 75 60",
    "sg:postcode":"1800",
    "sg:province":"Vaud",
    "wof:name":"Winterthur Vie Assurances Bureau Pr Est Vaudois",
    "wof:placetype":"venue"
},
  "geometry": {"coordinates":[6.8428258896,46.4617462158],"type":"Point"}
}