{
  "type": "Feature",
  "properties": {
    "iso:country":"CH",
    "sg:address":"Rugenparkstrasse 47",
    "sg:city":"Interlaken",
    "sg:orig_category":"Geb\u00e4ude, Wohnungsreinigung Reinigungsgewerbe",
    "sg:phone":"+41 33 823 13 45",
    "sg:postcode":"3800",
    "sg:province":"Bern",
    "wof:name":"H\u00e4berli Service",
    "wof:placetype":"venue"
},
  "geometry": {"coordinates":[7.8512678146,46.6779174805],"type":"Point"}
}