{
  "type": "Feature",
  "properties": {
    "iso:country":"CH",
    "sg:address":"Chemin De La Villaire 4b",
    "sg:city":"Echallens",
    "sg:orig_category":"Physiotherapie",
    "sg:phone":"+41 21 881 50 01",
    "sg:postcode":"1040",
    "sg:province":"Vaud",
    "wof:name":"Yves Fasnacht Physioth\u00e9rapie",
    "wof:placetype":"venue"
},
  "geometry": {"coordinates":[6.6308932304,46.6405448914],"type":"Point"}
}