{
  "type": "Feature",
  "properties": {
    "iso:country":"CH",
    "sg:address":"Chalet Les Sept Nains",
    "sg:city":"Champ\u00e9ry",
    "sg:orig_category":"Sonstige pers\u00f6nliche Dienstleistungen",
    "sg:phone":"+41 24 471 56 31",
    "sg:postcode":"1874",
    "sg:province":"Valais",
    "wof:name":"Altitude Travaux Acrobatiques S\u00e0rl",
    "wof:placetype":"venue"
},
  "geometry": {"coordinates":[6.8706860542,46.1794052124],"type":"Point"}
}