{
  "type": "Feature",
  "properties": {
    "iso:country":"CH",
    "sg:address":"Buissons Chemin Des 8",
    "sg:city":"Saignel\u00e9gier",
    "sg:orig_category":"Herstellung von Bier",
    "sg:postcode":"2350",
    "sg:province":"Jura",
    "wof:name":"Rebetez J\u00e9r\u00f4me",
    "wof:placetype":"venue"
},
  "geometry": {"coordinates":[6.9954299927,47.2558517456],"type":"Point"}
}