{
  "type": "Feature",
  "properties": {
    "iso:country":"CH",
    "sg:address":"Riedtlistrasse 15a",
    "sg:city":"Z\u00fcrich",
    "sg:orig_category":"Hochschulen U h\u00f6here Ausbildung -\u00dcbersetzungsb\u00fcros",
    "sg:phone":"+41 13813109",
    "sg:postcode":"8006",
    "sg:province":"Z\u00fcrich",
    "wof:name":"Rent A Voice Gmbh",
    "wof:placetype":"venue"
},
  "geometry": {"coordinates":[8.540772438,47.3900260925],"type":"Point"}
}