{
  "type": "Feature",
  "properties": {
    "iso:country":"CH",
    "sg:address":"Spitalgasse 2",
    "sg:city":"Bern",
    "sg:orig_category":"Non-Classified Establishments",
    "sg:postcode":"3011",
    "sg:province":"Bern",
    "wof:name":"Pepsico Beverages Switzerland Gmbh",
    "wof:placetype":"venue"
},
  "geometry": {"coordinates":[7.4433879852,46.9482688904],"type":"Point"}
}