{
  "type": "Feature",
  "properties": {
    "iso:country":"CH",
    "sg:address":"Grundstrasse 12",
    "sg:city":"B\u00e4retswil",
    "sg:orig_category":"Sportvereine Renn-& Reitsport",
    "sg:postcode":"8344",
    "sg:province":"Z\u00fcrich",
    "wof:name":"Reitverein Wetzikon & Umgebung",
    "wof:placetype":"venue"
},
  "geometry": {"coordinates":[8.8534641266,47.3382644653],"type":"Point"}
}