{
  "type": "Feature",
  "properties": {
    "iso:country":"CH",
    "sg:address":"Rue De La Fleur-de-lys 26",
    "sg:city":"Marin-epagnier",
    "sg:orig_category":"Herstellung von sonstiger Bekleidung U Bekleidungszubeh\u00f6r Sonstiger Fachdetailhandel in Verkaufsr\u00e4um",
    "sg:phone":"+41 32 753 81 41",
    "sg:postcode":"2074",
    "sg:province":"Neuch\u00e2tel",
    "wof:name":"Claude & Gabrielle Jeannet La Maison Du B\u00e9b\u00e9",
    "wof:placetype":"venue"
},
  "geometry": {"coordinates":[7.0062298775,47.0124397278],"type":"Point"}
}