{
  "type": "Feature",
  "properties": {
    "iso:country":"CH",
    "sg:address":"Laurenzenvorstadt 21",
    "sg:city":"Aarau",
    "sg:orig_category":"Werbung",
    "sg:phone":"+41 62 823 28 21",
    "sg:postcode":"5000",
    "sg:province":"Aargau",
    "wof:name":"Baldinger & Baldinger Ag",
    "wof:placetype":"venue"
},
  "geometry": {"coordinates":[8.0478639603,47.3940086365],"type":"Point"}
}