{
  "type": "Feature",
  "properties": {
    "iso:country":"CH",
    "sg:address":"4 place du Bourg-De-Four",
    "sg:city":"Geneva",
    "sg:classifiers":[
        {
            "category":"Professional",
            "subcategory":"Management & Consulting",
            "type":"Services"
        }
    ],
    "sg:postcode":"CH-1204",
    "sg:tags":[
        "innovation",
        "incremental-innovation",
        "digital-marketing",
        "online-commerce",
        "behavioral-intelligence"
    ],
    "sg:website":"http://www.openwt.com",
    "wof:name":"Open Web Technology",
    "wof:placetype":"venue"
},
  "geometry": {"coordinates":[6.1382324,46.1986292],"type":"Point"}
}