{
  "type": "Feature",
  "properties": {
    "addr:full":"Mingerstrasse 12 3014 Bern. Postfach Bern Bern 3014",
    "addr:housenumber":"12",
    "addr:postcode":"3014;postfach;3014",
    "addr:street":"Mingerstrasse",
    "iso:country":"CH",
    "sg:address":"Mingerstrasse 12 3014 Bern. Postfach",
    "sg:city":"Bern",
    "sg:orig_category":"Betrieb von Sportanlagen",
    "sg:phone":"+41 31 332 49 33",
    "sg:postcode":"3014",
    "sg:province":"Bern",
    "wof:name":"Sportbetriebe Bern Ag Sportanlagen Bes. Kunsteisbahnen",
    "wof:placetype":"venue"
},
  "geometry": {"coordinates":[7.46786,46.958881],"type":"Point"}
}