{
  "type": "Feature",
  "properties": {
    "iso:country":"CH",
    "sg:address":"Lindauring 23",
    "sg:city":"Rothenburg",
    "sg:orig_category":"Kosmetikinstitute",
    "sg:phone":"+41 41 280 53 14",
    "sg:postcode":"6023",
    "sg:province":"Luzern",
    "wof:name":"Thildy M\u00fcller Kosmetikinstitut",
    "wof:placetype":"venue"
},
  "geometry": {"coordinates":[8.2667131424,47.1001091003],"type":"Point"}
}