{
  "type": "Feature",
  "properties": {
    "iso:country":"CH",
    "sg:address":"1121",
    "sg:city":"Bremblens",
    "sg:orig_category":"Dienstleistungen im landwirtschaftlichen Pflanzen U Gartenbau",
    "sg:postcode":"1121",
    "sg:province":"Vaud",
    "wof:name":"Battoir \u00e0 Grains De Bremblens-romanel",
    "wof:placetype":"venue"
},
  "geometry": {"coordinates":[6.5181498528,46.5501213074],"type":"Point"}
}