{
  "type": "Feature",
  "properties": {
    "iso:country":"CH",
    "sg:address":"Sch\u00fctzenstrasse 14 8304 Wallisellen. Postfach",
    "sg:city":"Wallisellen",
    "sg:orig_category":"Grosshandel mit Holz U Baustoffen Herstellung von Betonerzeugnissen f\u00fcr den Bau",
    "sg:phone":"+41 22 793 69 01",
    "sg:postcode":"8304",
    "sg:province":"Z\u00fcrich",
    "wof:name":"Breco-el\u00e9ments De Construction Sa, Lancy",
    "wof:placetype":"venue"
},
  "geometry": {"coordinates":[6.1113610268,46.1927604675],"type":"Point"}
}