{
  "type": "Feature",
  "properties": {
    "iso:country":"CH",
    "sg:address":"Pumpwerkstrasse 5",
    "sg:city":"Adliswil",
    "sg:orig_category":"K\u00fcnstlerische U schriftstellerische T\u00e4tigkeiten U Darbietungen",
    "sg:postcode":"8134",
    "sg:province":"Z\u00fcrich",
    "wof:name":"Gem\u00e4lde-restaurationen, Wittke Joachim",
    "wof:placetype":"venue"
},
  "geometry": {"coordinates":[8.5231513977,47.3178634644],"type":"Point"}
}