{
  "type": "Feature",
  "properties": {
    "iso:country":"CH",
    "sg:address":"Constant Av. Benjamin- 2 1003 Lausanne. Postfach",
    "sg:city":"Lausanne",
    "sg:orig_category":"Interessenvertretungen",
    "sg:postcode":"1003",
    "sg:province":"Vaud",
    "wof:name":"Fondation Pallium Promouvoir Les Soins Palliatifs Oncologiques Dans Le Cadre Le Cadre D'une Prise En Charge Globale Ou Partielle En Structure Priv\u00e9e",
    "wof:placetype":"venue"
},
  "geometry": {"coordinates":[6.6373381615,46.5192108154],"type":"Point"}
}