{
  "type": "Feature",
  "properties": {
    "iso:country":"CH",
    "sg:address":"Rosengartenstrasse 4 8037 Z\u00fcrich. Postfach",
    "sg:city":"Z\u00fcrich",
    "sg:orig_category":"Instandhaltung U Reparatur von Automobilen",
    "sg:phone":"+41 12720214",
    "sg:postcode":"8037",
    "sg:province":"Z\u00fcrich",
    "wof:name":"Peter Hauptlin Ag",
    "wof:placetype":"venue"
},
  "geometry": {"coordinates":[8.5249099731,47.3938407898],"type":"Point"}
}