{
  "type": "Feature",
  "properties": {
    "iso:country":"CH",
    "sg:address":"Elisabethenstrasse 10",
    "sg:city":"Bern",
    "sg:orig_category":"Non-Classified Establishments",
    "sg:phone":"+41 31 331 15 25",
    "sg:postcode":"3014",
    "sg:province":"Bern",
    "wof:name":"Comm-trade.com Gmbh",
    "wof:placetype":"venue"
},
  "geometry": {"coordinates":[7.4533319473,46.9593544006],"type":"Point"}
}