{
  "type": "Feature",
  "properties": {
    "iso:country":"CH",
    "sg:address":"Grubenstrasse 15",
    "sg:city":"Frick",
    "sg:orig_category":"Sonstige Aktivit\u00e4ten der nicht-\u00e4rztlichen Medizinalberufe",
    "sg:phone":"+41 19103938",
    "sg:postcode":"5070",
    "sg:province":"Aargau",
    "wof:name":"Beatrice Rinderknecht Polarity",
    "wof:placetype":"venue"
},
  "geometry": {"coordinates":[8.5819864273,47.3185119629],"type":"Point"}
}