{
  "type": "Feature",
  "properties": {
    "addr:full":"Gotthardstrasse 62 6438 Ibach. Postfach Ibach Schwyz 6438",
    "addr:housenumber":"62",
    "addr:postcode":"6438;postfach;6438",
    "addr:street":"Gotthardstrasse",
    "iso:country":"CH",
    "sg:address":"Gotthardstrasse 62 6438 Ibach. Postfach",
    "sg:city":"Ibach",
    "sg:orig_category":"Architektur U Ingenieurb\u00fcros",
    "sg:postcode":"6438",
    "sg:province":"Schwyz",
    "wof:name":"Scepan Ag",
    "wof:placetype":"venue"
},
  "geometry": {"coordinates":[8.643665,47.010662],"type":"Point"}
}