{
  "type": "Feature",
  "properties": {
    "iso:country":"CH",
    "sg:address":"Route D'hermance 106",
    "sg:city":"Collonge-bellerive",
    "sg:orig_category":"Herstellung von Duft U K\u00f6rperpflegemitteln Parf\u00fcmerien U sonstiger Detailhandel mit kosmetischen Art",
    "sg:phone":"+41 21 944 30 15",
    "sg:postcode":"1245",
    "sg:province":"Gen\u00e8ve",
    "wof:name":"Karin Berner Environ Cosmeceutics",
    "wof:placetype":"venue"
},
  "geometry": {"coordinates":[6.8635368347,46.459526062],"type":"Point"}
}