{
  "type": "Feature",
  "properties": {
    "iso:country":"CH",
    "sg:address":"Sentier Des Vignes 9",
    "sg:city":"Sierre",
    "sg:orig_category":"Wirtschaftspr\u00fcfung, Steuerberatung U Treuhand",
    "sg:phone":"+41 27 456 32 30",
    "sg:postcode":"3960",
    "sg:province":"Valais",
    "wof:name":"M\u00fcller Dr. & Partner Treuhand Und Consulting Ag, Steuer, Unternehmens, Anlageberatung",
    "wof:placetype":"venue"
},
  "geometry": {"coordinates":[7.5319390297,46.2978286743],"type":"Point"}
}