{
  "type": "Feature",
  "properties": {
    "iso:country":"CH",
    "sg:address":"Plantzettes",
    "sg:city":"Sierre",
    "sg:orig_category":"Non-Classified Establishments",
    "sg:postcode":"3960",
    "sg:province":"Valais",
    "wof:name":"Si Wimpel Sa",
    "wof:placetype":"venue"
},
  "geometry": {"coordinates":[7.5386247635,46.2878913879],"type":"Point"}
}