{
  "type": "Feature",
  "properties": {
    "iso:country":"CH",
    "sg:address":"Freie Strasse 29 4001 Basel. Postfach",
    "sg:city":"Basel",
    "sg:orig_category":"Detailhandel mit Geschenkartikeln U Souvenirs",
    "sg:phone":"+41 81 933 10 34",
    "sg:postcode":"4001",
    "sg:province":"Basel-Stadt",
    "wof:name":"Gschenk-l\u00e4deli Pia Schindler",
    "wof:placetype":"venue"
},
  "geometry": {"coordinates":[9.1225099564,46.7561416626],"type":"Point"}
}