{
  "type": "Feature",
  "properties": {
    "iso:country":"CH",
    "sg:address":"Rue Jean-pierre Riat 59",
    "sg:city":"Chevenez",
    "sg:orig_category":"Polizei",
    "sg:phone":"+41 71 994 18 53",
    "sg:postcode":"2906",
    "sg:province":"Jura",
    "wof:name":"Kantonale Polizei Polizeistation",
    "wof:placetype":"venue"
},
  "geometry": {"coordinates":[9.1956663132,47.229511261],"type":"Point"}
}