{
  "type": "Feature",
  "properties": {
    "iso:country":"CH",
    "sg:address":"Hauptstrasse 44",
    "sg:city":"Rietheim",
    "sg:orig_category":"Erwachsenenbildung U Unterricht",
    "sg:phone":"+41 56 250 60 00",
    "sg:postcode":"5323",
    "sg:province":"Aargau",
    "wof:name":"Smg Siegrist's Magic Globe Zauberschule Zentralschweiz",
    "wof:placetype":"venue"
},
  "geometry": {"coordinates":[8.2756309509,47.6020736694],"type":"Point"}
}