{
  "type": "Feature",
  "properties": {
    "iso:country":"CH",
    "sg:address":"Limmatstrasse 118",
    "sg:city":"Z\u00fcrich",
    "sg:orig_category":"Sonstige Kultur U Unterhaltungseinrichtungen",
    "sg:phone":"+41 14481515",
    "sg:postcode":"8005",
    "sg:province":"Z\u00fcrich",
    "wof:name":"X-tra Limmathaus",
    "wof:placetype":"venue"
},
  "geometry": {"coordinates":[8.5325059891,47.3841629028],"type":"Point"}
}