{
  "type": "Feature",
  "properties": {
    "addr:full":"Hauptstrasse 53 Speicher Appenzell Ausserrhoden 9042",
    "addr:housenumber":"53",
    "addr:postcode":"9042",
    "addr:street":"Hauptstrasse;Ausserrhoden",
    "iso:country":"CH",
    "sg:address":"Hauptstrasse 53",
    "sg:city":"Speicher",
    "sg:orig_category":"Allgemeiner Hoch U Tiefbau",
    "sg:postcode":"9042",
    "sg:province":"Appenzell Ausserrhoden",
    "wof:name":"Stutz & Rudorf Ag",
    "wof:placetype":"venue"
},
  "geometry": {"coordinates":[9.247288,47.420986],"type":"Point"}
}