{
  "type": "Feature",
  "properties": {
    "iso:country":"CH",
    "sg:address":"Avenue Louis-ruchonnet 4",
    "sg:city":"Lausanne",
    "sg:orig_category":"Sprachschulen",
    "sg:phone":"+41 21 312 83 52",
    "sg:postcode":"1003",
    "sg:province":"Vaud",
    "wof:name":"Ecole Language Links",
    "wof:placetype":"venue"
},
  "geometry": {"coordinates":[6.6274809837,46.5180511475],"type":"Point"}
}