{
  "type": "Feature",
  "properties": {
    "iso:country":"CH",
    "sg:address":"Avenue Des Platanes 19 3960 Sierre Case Postale 622",
    "sg:city":"Sierre",
    "sg:orig_category":"Allgemeiner Hoch U Tiefbau Allgemeiner Hochbau",
    "sg:phone":"+41 27 455 13 38",
    "sg:postcode":"3960",
    "sg:province":"Valais",
    "wof:name":"Valentini Et Fils, Franco.",
    "wof:placetype":"venue"
},
  "geometry": {"coordinates":[7.529162,46.289349],"type":"Point"}
}