{
  "type": "Feature",
  "properties": {
    "iso:country":"CH",
    "sg:address":"A\u00e9roport Civil",
    "sg:city":"Sion",
    "sg:orig_category":"Interessenvertretungen",
    "sg:phone":"+41 27 323 66 77",
    "sg:postcode":"1950",
    "sg:province":"Valais",
    "wof:name":"Association Des Usagers De L'a\u00e9roport De Sion",
    "wof:placetype":"venue"
},
  "geometry": {"coordinates":[7.3413538933,46.2236862183],"type":"Point"}
}