{
  "type": "Feature",
  "properties": {
    "addr:full":"Bleicherweg 33 Z\u00fcrich Z\u00fcrich 8002",
    "addr:housenumber":"33",
    "addr:postcode":"8002",
    "addr:street":"Bleicherweg",
    "iso:country":"CH",
    "sg:address":"Bleicherweg 33",
    "sg:city":"Z\u00fcrich",
    "sg:classifiers":[
        {
            "category":"Manufacturing",
            "subcategory":"Chemicals & Compounds",
            "type":"Manufacturing & Wholesale Goods"
        }
    ],
    "sg:phone":"+41 4112091511",
    "sg:postcode":"8002",
    "sg:province":"Z\u00fcrich",
    "sg:tags":[
        "pharmaceutical",
        "chemistry",
        "-",
        "by-product"
    ],
    "wof:name":"Nitrex Ag",
    "wof:placetype":"venue"
},
  "geometry": {"coordinates":[8.533664,47.366837],"type":"Point"}
}