{
  "type": "Feature",
  "properties": {
    "iso:country":"CH",
    "sg:address":"Morgentalstrasse 30",
    "sg:city":"Z\u00fcrich",
    "sg:orig_category":"Vereine Vaterl\u00e4ndische",
    "sg:phone":"+41 71 311 20 96",
    "sg:postcode":"8038",
    "sg:province":"Z\u00fcrich",
    "wof:name":"Albanischer Kulturverein Drini",
    "wof:placetype":"venue"
},
  "geometry": {"coordinates":[9.3009796143,47.4015464783],"type":"Point"}
}