{
  "type": "Feature",
  "properties": {
    "iso:country":"CH",
    "sg:address":"Ampfleteweg 4",
    "sg:city":"Villigen",
    "sg:orig_category":"Maschinen-Fabrikation",
    "sg:postcode":"5234",
    "sg:province":"Aargau",
    "wof:name":"Diversitech Gmbh",
    "wof:placetype":"venue"
},
  "geometry": {"coordinates":[8.2132349014,47.521697998],"type":"Point"}
}