{
  "type": "Feature",
  "properties": {
    "iso:country":"CH",
    "sg:address":"Dornacherstrasse 56",
    "sg:city":"Basel",
    "sg:orig_category":"Reiseb\u00fcros Reiseb\u00fcros U Reiseveranstalter",
    "sg:phone":"+41 71 222 98 79",
    "sg:postcode":"4053",
    "sg:province":"Basel-Stadt",
    "wof:name":"Triangle Travel B\u00fcrgin",
    "wof:placetype":"venue"
},
  "geometry": {"coordinates":[7.5865578651,47.5442695618],"type":"Point"}
}