{
  "type": "Feature",
  "properties": {
    "iso:country":"CH",
    "sg:address":"Zeunerstrasse 9 8037 Z\u00fcrich. Postfach",
    "sg:city":"Z\u00fcrich",
    "sg:orig_category":"Unternehmensberatung",
    "sg:postcode":"8037",
    "sg:province":"Z\u00fcrich",
    "wof:name":"M+s Management Und Search Imv Ag Unternehmensberatung, Einzelberatung, Partnersuche",
    "wof:placetype":"venue"
},
  "geometry": {"coordinates":[8.5270452499,47.392578125],"type":"Point"}
}