{
  "type": "Feature",
  "properties": {
    "iso:country":"CH",
    "sg:address":"Haldenweg 9",
    "sg:city":"Egolzwil",
    "sg:orig_category":"Detailhandel mit Damenbekleidung Herstellung von konfektionierten Textilwaren ohne Bekleidung",
    "sg:phone":"+41 41 980 26 30",
    "sg:postcode":"6243",
    "sg:province":"Luzern",
    "wof:name":"Couture Egli Lisbeth & Co.",
    "wof:placetype":"venue"
},
  "geometry": {"coordinates":[8.0104637146,47.1861572266],"type":"Point"}
}