{
  "type": "Feature",
  "properties": {
    "iso:country":"CH",
    "sg:address":"Zweigenweg 7",
    "sg:city":"Wahlen",
    "sg:orig_category":"Bolts, Galvanized",
    "sg:phone":"+41 61 761 69 91",
    "sg:postcode":"4246",
    "sg:province":"Basel-Landschaft",
    "wof:name":"Hagal Galvanik",
    "wof:placetype":"venue"
},
  "geometry": {"coordinates":[7.516521,47.399845],"type":"Point"}
}