{
  "type": "Feature",
  "properties": {
    "iso:country":"CH",
    "sg:address":"Hinterwies 42",
    "sg:city":"Speicher",
    "sg:orig_category":"Sonstiger Grosshandel",
    "sg:phone":"+41 71 344 20 11",
    "sg:postcode":"9042",
    "sg:province":"Appenzell Ausserrhoden",
    "wof:name":"3sixty Petroleum Services Gmbh (ps360)",
    "wof:placetype":"venue"
},
  "geometry": {"coordinates":[9.4358139038,47.4169044495],"type":"Point"}
}