{
  "type": "Feature",
  "properties": {
    "iso:country":"CH",
    "sg:address":"1957",
    "sg:city":"Ardon",
    "sg:orig_category":"Elektrizit\u00e4tsversorgung",
    "sg:phone":"+41 27 324 06 12",
    "sg:postcode":"1957",
    "sg:province":"Valais",
    "wof:name":"Lizerne & Morge Sa Centrale \u00e9lectrique",
    "wof:placetype":"venue"
},
  "geometry": {"coordinates":[7.2555451393,46.2083091736],"type":"Point"}
}