{
  "type": "Feature",
  "properties": {
    "iso:country":"CH",
    "sg:address":"Balmbergstrasse 2",
    "sg:city":"Biberist",
    "sg:orig_category":"Unclassifiable Establishments",
    "sg:postcode":"4562",
    "sg:province":"Solothurn",
    "wof:name":"Heri Engineering Ind'steuerungen Hw-sw Entw.",
    "wof:placetype":"venue"
},
  "geometry": {"coordinates":[7.5558300018,47.1914291382],"type":"Point"}
}