{
  "type": "Feature",
  "properties": {
    "iso:country":"CH",
    "sg:address":"Wildbachstrasse 42",
    "sg:city":"Z\u00fcrich",
    "sg:orig_category":"Druckweiterverarbeitung",
    "sg:phone":"+41 14221729",
    "sg:postcode":"8008",
    "sg:province":"Z\u00fcrich",
    "wof:name":"Hanspeter Veil Buchbinderei & Einrahmungen",
    "wof:placetype":"venue"
},
  "geometry": {"coordinates":[8.5571393967,47.3566703796],"type":"Point"}
}