{
  "type": "Feature",
  "properties": {
    "iso:country":"CH",
    "sg:address":"Obere Wallisellerstrasse 16",
    "sg:city":"Opfikon",
    "sg:orig_category":"Vereine Diverse",
    "sg:phone":"+41 18101367",
    "sg:postcode":"8152",
    "sg:province":"Z\u00fcrich",
    "wof:name":"Verein Freizeit-aktion",
    "wof:placetype":"venue"
},
  "geometry": {"coordinates":[8.5777606964,47.430896759],"type":"Point"}
}