{
  "type": "Feature",
  "properties": {
    "iso:country":"CH",
    "sg:address":"4936",
    "sg:city":"Kleindietwil",
    "sg:orig_category":"Kantonalbanken",
    "sg:phone":"+41 62 965 45 80",
    "sg:postcode":"4936",
    "sg:province":"Bern",
    "wof:name":"Berner Kantonalbank Bekb/bcbe",
    "wof:placetype":"venue"
},
  "geometry": {"coordinates":[7.7905201912,47.1418495178],"type":"Point"}
}