{
  "type": "Feature",
  "properties": {
    "iso:country":"CH",
    "sg:address":"Route De Saillon 140",
    "sg:city":"Fully",
    "sg:orig_category":"Sportvereine Velo Rad-& Motorfahrer-Bund SRB",
    "sg:postcode":"1926",
    "sg:province":"Valais",
    "wof:name":"V\u00e9lo-club Franc-coureurs",
    "wof:placetype":"venue"
},
  "geometry": {"coordinates":[6.8398399353,47.11510849],"type":"Point"}
}