{
  "type": "Feature",
  "properties": {
    "iso:country":"CH",
    "sg:address":"Bahnhofstrasse 28",
    "sg:city":"Baden",
    "sg:classifiers":[
        {
            "category":"Professional",
            "subcategory":"Computer Services",
            "type":"Services"
        }
    ],
    "sg:postcode":"CH-5401",
    "sg:website":"http://www.bbp.ch",
    "wof:name":"BBP AG",
    "wof:placetype":"venue"
},
  "geometry": {"coordinates":[8.3076951,47.4757821],"type":"Point"}
}