{
  "type": "Feature",
  "properties": {
    "iso:country":"CH",
    "sg:address":"B\u00fchlacherstrasse 8",
    "sg:city":"Jonen",
    "sg:orig_category":"Unclassifiable Establishments",
    "sg:postcode":"8916",
    "sg:province":"Aargau",
    "wof:name":"Localhost Technologies Eyb Philip",
    "wof:placetype":"venue"
},
  "geometry": {"coordinates":[8.394952774,47.2984580994],"type":"Point"}
}