{
  "type": "Feature",
  "properties": {
    "iso:country":"CH",
    "sg:address":"Seebahnstrasse 157",
    "sg:city":"Z\u00fcrich",
    "sg:orig_category":"Unclassifiable Establishments",
    "sg:postcode":"8003",
    "sg:province":"Z\u00fcrich",
    "wof:name":"Marienhof Gmbh",
    "wof:placetype":"venue"
},
  "geometry": {"coordinates":[8.5185461044,47.3749732971],"type":"Point"}
}