{
  "type": "Feature",
  "properties": {
    "iso:country":"CH",
    "sg:address":"Fl\u00f6hrebenstrasse 6 8952 Schlieren. Postfach",
    "sg:city":"Z\u00fcrich",
    "sg:orig_category":"Allgemeiner Hoch U Tiefbau",
    "sg:postcode":"8048",
    "sg:province":"Z\u00fcrich",
    "wof:name":"Forest Baudienstleistungen Gmbh Baudienstleistungen. Tempor\u00e4rpersonal; Vermietung. Im, Export",
    "wof:placetype":"venue"
},
  "geometry": {"coordinates":[8.462141,47.396465],"type":"Point"}
}