{
  "type": "Feature",
  "properties": {
    "iso:country":"CH",
    "sg:address":"Comercialstrasse 20",
    "sg:city":"Chur",
    "sg:orig_category":"Freizeit, B\u00fccher U Comics",
    "sg:phone":"+41 81 250 48 50",
    "sg:postcode":"7000",
    "sg:province":"Graubunden",
    "wof:name":"Buchhandlung Conradi",
    "wof:placetype":"venue"
},
  "geometry": {"coordinates":[9.509887,46.847504],"type":"Point"}
}