{
  "type": "Feature",
  "properties": {
    "iso:country":"CH",
    "sg:address":"Dornacherstrasse 88",
    "sg:city":"Basel",
    "sg:orig_category":"Sonstiger Grosshandel",
    "sg:postcode":"4053",
    "sg:province":"Basel-Stadt",
    "wof:name":"Trading Enterprises W. Gygax",
    "wof:placetype":"venue"
},
  "geometry": {"coordinates":[7.5876870155,47.5438652039],"type":"Point"}
}