{
  "type": "Feature",
  "properties": {
    "iso:country":"CH",
    "sg:address":"Bretzwilerstrasse 9",
    "sg:city":"Nunningen",
    "sg:orig_category":"Arztpraxen",
    "sg:phone":"+41 61 791 92 11",
    "sg:postcode":"4208",
    "sg:province":"Solothurn",
    "wof:name":"Dr.med.gerhard Ernst Arzt F\u00fcr Allgemeine Medizin",
    "wof:placetype":"venue"
},
  "geometry": {"coordinates":[7.620764,47.393806],"type":"Point"}
}