{
  "type": "Feature",
  "properties": {
    "iso:country":"CH",
    "sg:address":"Oberlandstrasse 4",
    "sg:city":"K\u00fcnten",
    "sg:orig_category":"Detailhandel mit Radio U Fernsehger\u00e4ten Herstellung von Radio U Fernsehger\u00e4ten sowie phono U videote",
    "sg:phone":"+41 56 496 30 00",
    "sg:postcode":"5444",
    "sg:province":"Aargau",
    "wof:name":"Hifi Heusler",
    "wof:placetype":"venue"
},
  "geometry": {"coordinates":[8.3343238831,47.3898239136],"type":"Point"}
}