{
  "type": "Feature",
  "properties": {
    "iso:country":"CH",
    "sg:address":"Salomon Landolt-strasse 3",
    "sg:city":"Andelfingen",
    "sg:orig_category":"Fachdetailhandel in Verkaufsr\u00e4umen",
    "sg:phone":"+41 21 866 02 60",
    "sg:postcode":"8450",
    "sg:province":"Z\u00fcrich",
    "wof:name":"Pittet Fran\u00e7ois Fleurs Commerce De Fleurs Et D'une Bouqueterie",
    "wof:placetype":"venue"
},
  "geometry": {"coordinates":[6.5128378868,46.6583976746],"type":"Point"}
}