{
  "type": "Feature",
  "properties": {
    "iso:country":"CH",
    "sg:address":"Monbijoustrasse 3011 Bern. Postfach",
    "sg:city":"Bern",
    "sg:orig_category":"Pensionskassen",
    "sg:postcode":"3011",
    "sg:province":"Bern",
    "wof:name":"Dr. Albert Wander-fonds",
    "wof:placetype":"venue"
},
  "geometry": {"coordinates":[7.4367351532,46.9450759888],"type":"Point"}
}