{
  "type": "Feature",
  "properties": {
    "iso:country":"CH",
    "sg:address":"Lenzburgerstrasse 2",
    "sg:city":"Niederlenz",
    "sg:orig_category":"Markt U Meinungsforschung",
    "sg:phone":"+41 77592018",
    "sg:postcode":"5702",
    "sg:province":"Aargau",
    "wof:name":"Csv Ag",
    "wof:placetype":"venue"
},
  "geometry": {"coordinates":[8.177564621,47.3990745544],"type":"Point"}
}