{
  "type": "Feature",
  "properties": {
    "iso:country":"CH",
    "sg:address":"1536 Combremont-petit. Postfach 1",
    "sg:city":"Combremont-petit",
    "sg:orig_category":"Sportvereine Ballsport Fussball",
    "sg:phone":"+41 22 771 26 71",
    "sg:postcode":"1536",
    "sg:province":"Vaud",
    "wof:name":"Fc Compesi\u00e8res",
    "wof:placetype":"venue"
},
  "geometry": {"coordinates":[6.1364598274,46.145401001],"type":"Point"}
}