{
  "type": "Feature",
  "properties": {
    "iso:country":"CH",
    "sg:address":"Zugerstrasse 74",
    "sg:city":"Baar",
    "sg:orig_category":"Sonstiger Grosshandel",
    "sg:phone":"+41 41 767 70 58",
    "sg:postcode":"6340",
    "sg:province":"Zug",
    "wof:name":"Monopan Ag",
    "wof:placetype":"venue"
},
  "geometry": {"coordinates":[8.5197763443,47.1836051941],"type":"Point"}
}