{
  "type": "Feature",
  "properties": {
    "iso:country":"CH",
    "sg:address":"Kupfergasse 6 4310 Rheinfelden. Postfach",
    "sg:city":"Rheinfelden",
    "sg:orig_category":"Sonstiger Fachdetailhandel in Verkaufsr\u00e4umen",
    "sg:phone":"+41 61 831 35 70",
    "sg:postcode":"4310",
    "sg:province":"Aargau",
    "wof:name":"Jean-louis Mehlin B\u00fcchsenmacherei",
    "wof:placetype":"venue"
},
  "geometry": {"coordinates":[7.7948088646,47.5551948547],"type":"Point"}
}