{
  "type": "Feature",
  "properties": {
    "iso:country":"CH",
    "sg:address":"Chemin Du Courtil 4",
    "sg:city":"Prilly",
    "sg:orig_category":"G\u00fcterbef\u00f6rderung im Strassenverkehr",
    "sg:phone":"+41 79 427 83 11",
    "sg:postcode":"1008",
    "sg:province":"Vaud",
    "wof:name":"Goumaz Armand",
    "wof:placetype":"venue"
},
  "geometry": {"coordinates":[7.0379500389,46.7550582886],"type":"Point"}
}