{
  "type": "Feature",
  "properties": {
    "iso:country":"CH",
    "sg:address":"Neunbrunnenstrasse 180 8046 Z\u00fcrich. Postfach 165",
    "sg:city":"Z\u00fcrich",
    "sg:orig_category":"Herstellung von Mess U Kontrollinstrumenten U vorrichtungen",
    "sg:phone":"+41 52 232 53 94",
    "sg:postcode":"8046",
    "sg:province":"Z\u00fcrich",
    "wof:name":"Towa, Tomaschett, Waagen Und Maschinen",
    "wof:placetype":"venue"
},
  "geometry": {"coordinates":[8.7607221603,47.4835586548],"type":"Point"}
}