{
  "type": "Feature",
  "properties": {
    "iso:country":"CH",
    "sg:address":"Rue Cheneau-de-bourg 2",
    "sg:city":"Lausanne",
    "sg:orig_category":"RESTAURANTS: TEA-ROOMS",
    "sg:phone":"+41 21 311 83 73",
    "sg:postcode":"1003",
    "sg:province":"Vaud",
    "wof:name":"Byblos, Rodriguez J. Restaurant Et Pub",
    "wof:placetype":"venue"
},
  "geometry": {"coordinates":[6.6361980438,46.520816803],"type":"Point"}
}