{
  "type": "Feature",
  "properties": {
    "iso:country":"CH",
    "sg:address":"Sulgeneckstrasse 70 3005 Bern. Postfach",
    "sg:city":"Bern",
    "sg:orig_category":"Fachdetailhandel in Verkaufsr\u00e4umen Kunsthandel",
    "sg:phone":"+41 31 371 38 66",
    "sg:postcode":"3005",
    "sg:province":"Bern",
    "wof:name":"Tom Men's Gmbh",
    "wof:placetype":"venue"
},
  "geometry": {"coordinates":[7.4408941269,46.940700531],"type":"Point"}
}