{
  "type": "Feature",
  "properties": {
    "iso:country":"CH",
    "sg:address":"Industriestrasse 5",
    "sg:city":"Neuenhof",
    "sg:orig_category":"Herstellung von Elektrizit\u00e4tsverteilungs U schalteinrichtungen",
    "sg:phone":"+41 56 410 06 66",
    "sg:postcode":"5432",
    "sg:province":"Aargau",
    "wof:name":"Brunner Dr. & Partner Ag",
    "wof:placetype":"venue"
},
  "geometry": {"coordinates":[8.3258733749,47.4557914734],"type":"Point"}
}