{
  "type": "Feature",
  "properties": {
    "iso:country":"CH",
    "sg:address":"In Den Matten 12",
    "sg:city":"Diegten",
    "sg:orig_category":"Herstellung von Konstruktionsteilen, Fertigbauteilen U Ausbauelementen aus Holz",
    "sg:postcode":"4457",
    "sg:province":"Basel-Landschaft",
    "wof:name":"Multimontages, Christian Mathon",
    "wof:placetype":"venue"
},
  "geometry": {"coordinates":[6.6947751045,46.5545883179],"type":"Point"}
}