{
  "type": "Feature",
  "properties": {
    "iso:country":"CH",
    "sg:address":"Allmendstrasse 6",
    "sg:city":"Sursee",
    "sg:orig_category":"Grosshandel mit sonstigen Maschinen U Ausr\u00fcstungen f\u00fcr Industrie, Handel U Schiffahrt Handelsvermitt",
    "sg:phone":"+41 19346010",
    "sg:postcode":"6210",
    "sg:province":"Luzern",
    "wof:name":"Stamm Industrieprodukte Ag",
    "wof:placetype":"venue"
},
  "geometry": {"coordinates":[8.7701759338,47.3695144653],"type":"Point"}
}