{
  "type": "Feature",
  "properties": {
    "iso:country":"CH",
    "sg:address":"Freiestrasse 3 8800 Thalwil. Postfach",
    "sg:city":"Thalwil",
    "sg:orig_category":"Softwareentwicklung U beratung",
    "sg:postcode":"8800",
    "sg:province":"Z\u00fcrich",
    "wof:name":"Proessentia Gmbh",
    "wof:placetype":"venue"
},
  "geometry": {"coordinates":[8.5632791519,47.292301178],"type":"Point"}
}