{
  "type": "Feature",
  "properties": {
    "iso:country":"CH",
    "sg:address":"Ahornweg 2 3012 Bern. Postfach",
    "sg:city":"Bern",
    "sg:orig_category":"Vermietung U Verpachtung von eigenen Immobilien",
    "sg:phone":"+41 31 991 88 11",
    "sg:postcode":"3027",
    "sg:province":"Bern",
    "wof:name":"Zentrum Ag Bern",
    "wof:placetype":"venue"
},
  "geometry": {"coordinates":[7.4347820282,46.953956604],"type":"Point"}
}