{
  "type": "Feature",
  "properties": {
    "iso:country":"CH",
    "sg:address":"Via Alla Campagna 18",
    "sg:city":"Lugano",
    "sg:orig_category":"Physiotherapie",
    "sg:phone":"+41 91 972 38 71",
    "sg:postcode":"6900",
    "sg:province":"Ticino",
    "wof:name":"Luana Campana Fisioterapia",
    "wof:placetype":"venue"
},
  "geometry": {"coordinates":[8.9578504562,46.0164108276],"type":"Point"}
}