{
  "type": "Feature",
  "properties": {
    "addr:full":"Gasstrasse 1 4056 Basel. Postfach Basel Basel-Stadt 4013",
    "addr:housenumber":"1",
    "addr:postcode":"4056;4013",
    "addr:street":"Gasstrasse;Postfach",
    "iso:country":"CH",
    "sg:address":"Gasstrasse 1 4056 Basel. Postfach",
    "sg:city":"Basel",
    "sg:orig_category":"Arztpraxen",
    "sg:phone":"+41 61 321 44 10",
    "sg:postcode":"4013",
    "sg:province":"Basel-Stadt",
    "wof:name":"Dr.med.kurt Rohner Arzt F.allgemeine Medizin Fmh",
    "wof:placetype":"venue"
},
  "geometry": {"coordinates":[7.57765,47.570492],"type":"Point"}
}