{
  "type": "Feature",
  "properties": {
    "iso:country":"CH",
    "sg:address":"Sodweg 4a",
    "sg:city":"Ibach",
    "sg:orig_category":"Hom\u00f6opathie Naturheil\u00e4rzte and Heilpraktiker",
    "sg:postcode":"6438",
    "sg:province":"Schwyz",
    "wof:name":"Karin Imlig Naturheilpraxis & Hom\u00f6opathie",
    "wof:placetype":"venue"
},
  "geometry": {"coordinates":[8.6451864243,47.0127792358],"type":"Point"}
}