{
  "type": "Feature",
  "properties": {
    "iso:country":"CH",
    "sg:address":"Marktstrasse 12",
    "sg:city":"Kreuzlingen",
    "sg:orig_category":"Vorschulen, Kinderg\u00e4rten",
    "sg:phone":"+41 71 672 31 01",
    "sg:postcode":"8280",
    "sg:province":"Thurgau",
    "wof:name":"Kindergarten Wehrli",
    "wof:placetype":"venue"
},
  "geometry": {"coordinates":[9.1719007492,47.648563385],"type":"Point"}
}