{
  "type": "Feature",
  "properties": {
    "iso:country":"CH",
    "sg:address":"Abernstrasse 38",
    "sg:city":"D\u00fcrnten",
    "sg:orig_category":"Unternehmensberatung",
    "sg:phone":"+41 55 241 10 68",
    "sg:postcode":"8635",
    "sg:province":"Z\u00fcrich",
    "wof:name":"Alfred Wirch Consulting",
    "wof:placetype":"venue"
},
  "geometry": {"coordinates":[8.8547315598,47.2670936584],"type":"Point"}
}