{
  "type": "Feature",
  "properties": {
    "iso:country":"CH",
    "sg:address":"Sch\u00f6neggstrasse 21",
    "sg:city":"Z\u00fcrich",
    "sg:orig_category":"Detailhandel mit Waren verschiedener Art, Hauptrichtung Nahrungsmittel Grosshandel mit Nahrungsmitte",
    "sg:phone":"+41 56 266 56 56",
    "sg:postcode":"8004",
    "sg:province":"Z\u00fcrich",
    "wof:name":"Vivosan Ag",
    "wof:placetype":"venue"
},
  "geometry": {"coordinates":[8.3146429062,47.5292358398],"type":"Point"}
}