{
  "type": "Feature",
  "properties": {
    "iso:country":"CH",
    "sg:address":"Fellenbergstrasse 289a",
    "sg:city":"Z\u00fcrich",
    "sg:orig_category":"Autogaragen Einzelhandel mit Automobilteilen U Zubeh\u00f6r",
    "sg:phone":"+41 14914400",
    "sg:postcode":"8047",
    "sg:province":"Z\u00fcrich",
    "wof:name":"Ren\u00e9 Resegatti Garage",
    "wof:placetype":"venue"
},
  "geometry": {"coordinates":[8.490612,47.375187],"type":"Point"}
}