{
  "type": "Feature",
  "properties": {
    "iso:country":"CH",
    "sg:address":"Baselmattweg 129",
    "sg:city":"Allschwil",
    "sg:orig_category":"Aktivit\u00e4ten der Krankenschwestern U Hebammen, Hauspflege Organisationen des Gesundheitswesen",
    "sg:phone":"+41 61 481 95 15",
    "sg:postcode":"4123",
    "sg:province":"Basel-Landschaft",
    "wof:name":"Kranken-& Hauspflegeverein Allschwil-sch\u00f6nenbuch",
    "wof:placetype":"venue"
},
  "geometry": {"coordinates":[7.551498,47.556805],"type":"Point"}
}