{
  "type": "Feature",
  "properties": {
    "iso:country":"CH",
    "sg:address":"B\u00fcrglistrasse 35",
    "sg:city":"Winterthur",
    "sg:orig_category":"Handels-H\u00e4user U Gesellschaften",
    "sg:postcode":"8400",
    "sg:province":"Z\u00fcrich",
    "wof:name":"Vbh Vermittlungsb\u00fcro F\u00fcr Handelsbeziehungen Mohmad",
    "wof:placetype":"venue"
},
  "geometry": {"coordinates":[8.7133655548,47.5058631897],"type":"Point"}
}