{
  "type": "Feature",
  "properties": {
    "iso:country":"CH",
    "sg:address":"Staatsstrasse 86",
    "sg:city":"Rebstein",
    "sg:orig_category":"Detailhandel mit medizinischen U orthop\u00e4dischen Artikeln Herstellung von medizinischen U chirurgisch",
    "sg:phone":"+41 71 777 66 30",
    "sg:postcode":"9445",
    "sg:province":"St. Gallen",
    "wof:name":"Fussorthop\u00e4die Hans L\u00fcchinger Gmbh",
    "wof:placetype":"venue"
},
  "geometry": {"coordinates":[9.5847110748,47.3989181519],"type":"Point"}
}