{
  "type": "Feature",
  "properties": {
    "iso:country":"CH",
    "sg:address":"Friesstrasse 41 8000 Z\u00fcrich. Postfach 8050 Z\u00fcrich",
    "sg:city":"Zust",
    "sg:orig_category":"D\u00e4mmung gegen K\u00e4lte, W\u00e4rme, Schall U Ersch\u00fctterung",
    "sg:phone":"+41 13013345",
    "sg:postcode":"50",
    "wof:name":"Ibb Institut F\u00fcr Bautenschutz Und Bausanierung Gmbh",
    "wof:placetype":"venue"
},
  "geometry": {"coordinates":[8.4809503555,47.3614616394],"type":"Point"}
}