{
  "type": "Feature",
  "properties": {
    "iso:country":"CH",
    "sg:address":"Industriestrasse 26",
    "sg:city":"Aarwangen",
    "sg:orig_category":"Herstellung von Fenstern U T\u00fcren aus Holz Herstellung von Konstruktionsteilen, Fertigbauteilen U Aus",
    "sg:phone":"+41 62 919 82 62",
    "sg:postcode":"4912",
    "sg:province":"Bern",
    "wof:name":"S\u00e4gesser Fensterfabrik Ag",
    "wof:placetype":"venue"
},
  "geometry": {"coordinates":[7.7723789215,47.2298965454],"type":"Point"}
}