{
  "type": "Feature",
  "properties": {
    "addr:full":"Kirschenweg 6 Schaffhausen Schaffhausen 8200",
    "addr:housenumber":"6",
    "addr:postcode":"8200",
    "addr:street":"Kirschenweg",
    "iso:country":"CH",
    "sg:address":"Kirschenweg 6",
    "sg:city":"Schaffhausen",
    "sg:orig_category":"Bauschreinerei Herstellung von M\u00f6beln verschiedener Art",
    "sg:phone":"+41 52 625 18 90",
    "sg:postcode":"8200",
    "sg:province":"Schaffhausen",
    "wof:name":"Martin Schlatter Bau-& M\u00f6belschreinerei Ihr Schreiner",
    "wof:placetype":"venue"
},
  "geometry": {"coordinates":[8.651075,47.702206],"type":"Point"}
}