{
  "type": "Feature",
  "properties": {
    "addr:full":"Victor Von Bruns-strasse 11 Neuhausen Schaffhausen 8212",
    "addr:housenumber":"11",
    "addr:postcode":"8212",
    "addr:street":"Victor Von Bruns-Strasse",
    "iso:country":"CH",
    "sg:address":"Victor Von Bruns-strasse 11",
    "sg:city":"Neuhausen",
    "sg:orig_category":"Architektur U Ingenieurb\u00fcros",
    "sg:postcode":"8212",
    "sg:province":"Schaffhausen",
    "wof:name":"Vuko Konstruktionsb\u00fcro Gmbh",
    "wof:placetype":"venue"
},
  "geometry": {"coordinates":[8.625661,47.679596],"type":"Point"}
}