{
  "type": "Feature",
  "properties": {
    "iso:country":"CH",
    "sg:address":"Bahnhofstrasse 7 6300 Zug. Postfach 1225",
    "sg:city":"Zug",
    "sg:orig_category":"Rechtsberatung",
    "sg:phone":"+41 12121064",
    "sg:postcode":"6301",
    "sg:province":"Zug",
    "wof:name":"Wyer & Partner",
    "wof:placetype":"venue"
},
  "geometry": {"coordinates":[8.5155220032,47.168586731],"type":"Point"}
}