{
  "type": "Feature",
  "properties": {
    "iso:country":"CH",
    "sg:address":"F\u00fcrst Franz Josef Strasse 22",
    "sg:city":"Vaduz",
    "sg:orig_category":"Tierarztpraxis",
    "sg:phone":"+41 71 244 81 10",
    "sg:postcode":"9490",
    "wof:name":"Dr.med.vet.dieter Fleischer Tierarztpraxis Am Rosenberg",
    "wof:placetype":"venue"
},
  "geometry": {"coordinates":[9.384803772,47.438129425],"type":"Point"}
}