{
  "type": "Feature",
  "properties": {
    "iso:country":"CH",
    "sg:address":"Z\u00fcrichstrasse 31",
    "sg:city":"Adliswil",
    "sg:orig_category":"Allgemeiner Gartenbau Dienstleistungen im Gartenbau",
    "sg:phone":"+41 17105134",
    "sg:postcode":"8134",
    "sg:province":"Z\u00fcrich",
    "wof:name":"Ren\u00e9 & Agnes Z\u00fcnd Gartenbau",
    "wof:placetype":"venue"
},
  "geometry": {"coordinates":[8.52875,47.314335],"type":"Point"}
}