{
  "type": "Feature",
  "properties": {
    "iso:country":"CH",
    "sg:address":"Furthof 8820 W\u00e4denswil. Postfach",
    "sg:city":"W\u00e4denswil",
    "sg:orig_category":"Unclassifiable Establishments",
    "sg:postcode":"8820",
    "sg:province":"Z\u00fcrich",
    "wof:name":"Ritter's Jackie Hundehort Und Hundeschule",
    "wof:placetype":"venue"
},
  "geometry": {"coordinates":[8.6605730057,47.2218284607],"type":"Point"}
}