{
  "type": "Feature",
  "properties": {
    "iso:country":"CH",
    "sg:address":"Tellistrasse 27",
    "sg:city":"Aarau",
    "sg:orig_category":"Vermietung U Verpachtung von eigenen Immobilien",
    "sg:postcode":"5000",
    "sg:province":"Aargau",
    "wof:name":"Urs V. De Maddalena, Lic.iur., Gesch\u00e4ftsagentur",
    "wof:placetype":"venue"
},
  "geometry": {"coordinates":[8.0529298782,47.3960533142],"type":"Point"}
}