{
  "type": "Feature",
  "properties": {
    "iso:country":"CH",
    "sg:address":"1721",
    "sg:city":"Corm\u00e9rod",
    "sg:classifiers":[
        {
            "category":"Restaurant",
            "type":"Food & Drink"
        }
    ],
    "sg:phone":"+41 26 684 11 07",
    "sg:postcode":"1721",
    "sg:province":"Fribourg",
    "wof:name":"Restaurant Agricole",
    "wof:placetype":"venue"
},
  "geometry": {"coordinates":[7.0656499863,46.8526954651],"type":"Point"}
}