{
  "type": "Feature",
  "properties": {
    "iso:country":"CH",
    "sg:address":"Fourmi Chemin De La 22 1010 Lausanne. Postfach",
    "sg:city":"Lausanne",
    "sg:orig_category":"Herstellung von Radio U Fernsehger\u00e4ten sowie phono U videotechnischen Ger\u00e4ten",
    "sg:phone":"+41 21 652 30 43",
    "sg:postcode":"1010",
    "sg:province":"Vaud",
    "wof:name":"Electro Accoustique Syst\u00e8me, Kohler Fred. Conception, Vente Et Mise En Place De Syst\u00e8mes \u00e9lectro-accoustiques, Appareils De Sonorisation, Etc.",
    "wof:placetype":"venue"
},
  "geometry": {"coordinates":[6.6557598114,46.535900116],"type":"Point"}
}