{
  "type": "Feature",
  "properties": {
    "iso:country":"CH",
    "sg:address":"Obmoos 4",
    "sg:city":"Zug",
    "sg:orig_category":"Wohnheime",
    "sg:phone":"+41 41 811 72 04",
    "sg:postcode":"6300",
    "sg:province":"Zug",
    "wof:name":"Ph\u00f6nix Haus B\u00e4ttigmatte",
    "wof:placetype":"venue"
},
  "geometry": {"coordinates":[8.6298341751,47.0271072388],"type":"Point"}
}