{
  "type": "Feature",
  "properties": {
    "iso:country":"CH",
    "sg:address":"Z.i. La Chaux",
    "sg:city":"Orges",
    "sg:orig_category":"Kauf U Verkauf von Immobilien auf eigene Rechnung",
    "sg:phone":"+41 24 445 63 02",
    "sg:postcode":"1430",
    "sg:province":"Vaud",
    "wof:name":"Arc Concept S.\u00e0 R.l.",
    "wof:placetype":"venue"
},
  "geometry": {"coordinates":[6.5868592262,46.8078918457],"type":"Point"}
}