{
  "type": "Feature",
  "properties": {
    "iso:country":"CH",
    "sg:address":"Zenrum Bahnhof",
    "sg:city":"Lax",
    "sg:orig_category":"Gemeindeverwaltungen",
    "sg:phone":"+41 27 971 24 44",
    "sg:postcode":"3994",
    "sg:province":"Valais",
    "wof:name":"Gemeindeverwaltung Lax",
    "wof:placetype":"venue"
},
  "geometry": {"coordinates":[8.1170253754,46.3876533508],"type":"Point"}
}