{
  "type": "Feature",
  "properties": {
    "iso:country":"CH",
    "sg:address":"Eichmatt",
    "sg:city":"Hedingen",
    "sg:orig_category":"Interessenvertretungen",
    "sg:postcode":"8908",
    "sg:province":"Z\u00fcrich",
    "wof:name":"Peter Berta Stiftung",
    "wof:placetype":"venue"
},
  "geometry": {"coordinates":[8.4433479309,47.3120002747],"type":"Point"}
}