{
  "type": "Feature",
  "properties": {
    "iso:country":"CH",
    "sg:address":"Geyisriedweg 63",
    "sg:city":"Biel/bienne",
    "sg:orig_category":"Gesundheitswesen",
    "sg:phone":"+41 32 341 80 21",
    "sg:postcode":"2504",
    "sg:province":"Bern",
    "wof:name":"Vitality, Therese M. Favrod",
    "wof:placetype":"venue"
},
  "geometry": {"coordinates":[7.2802419662,47.1461486816],"type":"Point"}
}