{
  "type": "Feature",
  "properties": {
    "iso:country":"CH",
    "sg:address":"F\u00fcrstenlandstrasse 31",
    "sg:city":"St.gallen",
    "sg:orig_category":"Autogaragen",
    "sg:phone":"+41 71 277 25 55",
    "sg:postcode":"9000",
    "sg:province":"St. Gallen",
    "wof:name":"Rolf Aeberhard F\u00fcrstenlandgarage",
    "wof:placetype":"venue"
},
  "geometry": {"coordinates":[9.351117,47.414356],"type":"Point"}
}