{
  "type": "Feature",
  "properties": {
    "iso:country":"CH",
    "sg:address":"Talackerstrasse 17",
    "sg:city":"Glattbrugg",
    "sg:classifiers":[
        {
            "category":"Shopping",
            "subcategory":"Clothing, Apparel, & Fashions",
            "type":"Retail Goods"
        }
    ],
    "sg:phone":"+41 81 410 10 20",
    "sg:postcode":"8152",
    "sg:province":"Z\u00fcrich",
    "sg:tags":[
        "clothing",
        "fitness"
    ],
    "wof:name":"Swiss Alp Fantasy Ag",
    "wof:placetype":"venue"
},
  "geometry": {"coordinates":[9.8360099792,46.8027687073],"type":"Point"}
}