{
  "type": "Feature",
  "properties": {
    "iso:country":"CH",
    "sg:address":"Kirchb\u00fchl 3818 Grindelwald. Postfach 44",
    "sg:city":"Grindelwald",
    "sg:orig_category":"RESTAURANTS: TEA-ROOMS",
    "sg:phone":"+41 33 853 35 53",
    "sg:postcode":"3818",
    "sg:province":"Bern",
    "wof:name":"Chr. Brawand-imboden",
    "wof:placetype":"venue"
},
  "geometry": {"coordinates":[8.0480394363,46.6276016235],"type":"Point"}
}