{
  "type": "Feature",
  "properties": {
    "iso:country":"CH",
    "sg:address":"Scheuchzerstrasse 163",
    "sg:city":"Z\u00fcrich",
    "sg:orig_category":"Schreib U \u00dcbersetzungsb\u00fcros",
    "sg:phone":"+41 13622233",
    "sg:postcode":"8057",
    "sg:province":"Z\u00fcrich",
    "wof:name":"Lingua Consult Ag",
    "wof:placetype":"venue"
},
  "geometry": {"coordinates":[8.5413208008,47.3928642273],"type":"Point"}
}