{
  "type": "Feature",
  "properties": {
    "iso:country":"CH",
    "sg:address":"Guisan Via Generale 17",
    "sg:city":"Chiasso",
    "sg:orig_category":"Kinderg\u00e4rten, Vor U Grundschulen",
    "sg:phone":"+41 91 682 58 58",
    "sg:postcode":"6830",
    "sg:province":"Ticino",
    "wof:name":"Lilliput Sagl",
    "wof:placetype":"venue"
},
  "geometry": {"coordinates":[9.0218629837,45.8328552246],"type":"Point"}
}