{
  "type": "Feature",
  "properties": {
    "iso:country":"CH",
    "sg:address":"Bahnhofstrasse 5 3920 Zermatt. Postfach 154",
    "sg:city":"Zermatt",
    "sg:orig_category":"HOTELS: MIT RESTAURANT Kongress- and Tagungshotels mit Restaurant",
    "sg:phone":"+41 81 413 26 26",
    "sg:postcode":"3920",
    "sg:province":"Valais",
    "wof:name":"Hotel Schweizerhof",
    "wof:placetype":"venue"
},
  "geometry": {"coordinates":[9.8214817047,46.7947883606],"type":"Point"}
}