{
  "type": "Feature",
  "properties": {
    "iso:country":"CH",
    "sg:address":"Industriestrasse 19",
    "sg:city":"Trimbach",
    "sg:orig_category":"Datenverarbeitungsdienste G\u00fcterbef\u00f6rderung im Strassenverkehr",
    "sg:phone":"+41 62 293 50 30",
    "sg:postcode":"4632",
    "sg:province":"Solothurn",
    "wof:name":"Borner Logistik Ag",
    "wof:placetype":"venue"
},
  "geometry": {"coordinates":[7.90683,47.35891],"type":"Point"}
}