{
  "type": "Feature",
  "properties": {
    "iso:country":"CH",
    "sg:address":"6056 K\u00e4giswil. Postfach",
    "sg:city":"K\u00e4giswil",
    "sg:orig_category":"Instandhaltung U Reparatur von Automobilen",
    "sg:postcode":"6056",
    "sg:province":"Obwalden",
    "wof:name":"Garage Beeler Ag",
    "wof:placetype":"venue"
},
  "geometry": {"coordinates":[8.2627096176,46.9216499329],"type":"Point"}
}