{
  "type": "Feature",
  "properties": {
    "iso:country":"CH",
    "sg:address":"Grand-rue 65",
    "sg:city":"Ch\u00e2tel-st-denis",
    "sg:orig_category":"Technische B\u00fcros Heizung, L\u00fcftung, Klima Technische B\u00fcros Sanit\u00e4r",
    "sg:phone":"+41 41 497 20 02",
    "sg:postcode":"1618",
    "sg:province":"Fribourg",
    "wof:name":"Josef Roth Technisches B\u00fcro",
    "wof:placetype":"venue"
},
  "geometry": {"coordinates":[8.1827249527,47.0368156433],"type":"Point"}
}