{
  "type": "Feature",
  "properties": {
    "iso:country":"CH",
    "sg:address":"Tann\u00e4gertenstrasse 18",
    "sg:city":"D\u00fcrnten",
    "sg:orig_category":"Vereine Damen Vereine Gesang",
    "sg:phone":"+41 55 241 16 91",
    "sg:postcode":"8635",
    "sg:province":"Z\u00fcrich",
    "wof:name":"Frauenchor D\u00fcrnten",
    "wof:placetype":"venue"
},
  "geometry": {"coordinates":[8.8381948471,47.2770957947],"type":"Point"}
}