{
  "type": "Feature",
  "properties": {
    "iso:country":"CH",
    "sg:address":"Riedhofstrasse 354",
    "sg:city":"Z\u00fcrich",
    "sg:orig_category":"Softwareentwicklung U beratung",
    "sg:postcode":"8049",
    "sg:province":"Z\u00fcrich",
    "wof:name":"Win-soft, Service For X - Winteler Thomas",
    "wof:placetype":"venue"
},
  "geometry": {"coordinates":[9.0412321091,47.4601135254],"type":"Point"}
}