{
  "type": "Feature",
  "properties": {
    "iso:country":"CH",
    "sg:address":"Rue Voltaire 12",
    "sg:city":"Gen\u00e8ve",
    "sg:orig_category":"Detailhandel mit Musikinstrumenten Detailhandel mit elektrischen Haushalts-,Radio U Fernsehger\u00e4ten s",
    "sg:phone":"+41 61 711 41 49",
    "sg:postcode":"1201",
    "sg:province":"Gen\u00e8ve",
    "wof:name":"Music Drive Baier D.",
    "wof:placetype":"venue"
},
  "geometry": {"coordinates":[7.5922088623,47.4950904846],"type":"Point"}
}