{
  "type": "Feature",
  "properties": {
    "iso:country":"CH",
    "sg:address":"Zugerstrasse 74",
    "sg:city":"Baar",
    "sg:classifiers":[
        {
            "category":"Banks & Credit Unions",
            "subcategory":"Investment Brokerage",
            "type":"Services"
        }
    ],
    "sg:phone":"+41 41 767 70 68",
    "sg:postcode":"6340",
    "sg:province":"Zug",
    "sg:tags":[
        "sound",
        "absorber",
        "personnel",
        "energy",
        "protection",
        "insulation"
    ],
    "wof:name":"Tubus Bauer Ag",
    "wof:placetype":"venue"
},
  "geometry": {"coordinates":[8.5197763443,47.1836051941],"type":"Point"}
}