{
  "type": "Feature",
  "properties": {
    "iso:country":"CH",
    "sg:address":"Rue Du Xxxi-d\u00e9cembre 59 1200 Genf. Postfach",
    "sg:city":"Gen\u00e8ve",
    "sg:orig_category":"RESTAURANTS: TEA-ROOMS",
    "sg:postcode":"1207",
    "sg:province":"Gen\u00e8ve",
    "wof:name":"Gomes Amaral Huber R. Et De Azevedo Oliveira J.",
    "wof:placetype":"venue"
},
  "geometry": {"coordinates":[6.1617379189,46.2017974854],"type":"Point"}
}