{
  "type": "Feature",
  "properties": {
    "iso:country":"CH",
    "sg:address":"Place Du Port 3",
    "sg:city":"Lausanne",
    "sg:orig_category":"RESTAURANTS: TEA-ROOMS",
    "sg:phone":"+41 22 798 10 11",
    "sg:postcode":"1000",
    "sg:province":"Vaud",
    "wof:name":"Suter Patrick Et Suter Jacqueline",
    "wof:placetype":"venue"
},
  "geometry": {"coordinates":[6.1188597679,46.2309913635],"type":"Point"}
}