{
  "type": "Feature",
  "properties": {
    "iso:country":"CH",
    "sg:address":"Eschenrain 7",
    "sg:city":"Steinhausen",
    "sg:orig_category":"Grosshandel mit Textilien",
    "sg:postcode":"6312",
    "sg:province":"Zug",
    "wof:name":"Urgentum Ag",
    "wof:placetype":"venue"
},
  "geometry": {"coordinates":[8.491437912,47.1971626282],"type":"Point"}
}