{
  "type": "Feature",
  "properties": {
    "iso:country":"CH",
    "sg:address":"Gerenstrasse 11",
    "sg:city":"Urn\u00e4sch",
    "sg:orig_category":"Sonstiger Grosshandel",
    "sg:phone":"+41 71 364 15 88",
    "sg:postcode":"9107",
    "sg:province":"Appenzell Ausserrhoden",
    "wof:name":"Popp, Handelsgesch\u00e4ft",
    "wof:placetype":"venue"
},
  "geometry": {"coordinates":[9.2757568359,47.3113670349],"type":"Point"}
}