{
  "type": "Feature",
  "properties": {
    "iso:country":"CH",
    "sg:address":"6776",
    "sg:city":"Piotta",
    "sg:orig_category":"Herstellung von Metallerzeugnissen ohne Maschinenbau Maschinenbau",
    "sg:phone":"+41 17619700",
    "sg:postcode":"6776",
    "sg:province":"Ticino",
    "wof:name":"Tepha R. F\u00fcllemann",
    "wof:placetype":"venue"
},
  "geometry": {"coordinates":[8.4511070251,47.2804031372],"type":"Point"}
}