{
  "type": "Feature",
  "properties": {
    "iso:country":"CH",
    "sg:address":"Weinbergstrasse 48",
    "sg:city":"Z\u00fcrich",
    "sg:classifiers":[
        {
            "category":"Communications",
            "subcategory":"Film & Video Production",
            "type":"Services"
        }
    ],
    "sg:phone":"+41 12611890",
    "sg:postcode":"8006",
    "sg:province":"Z\u00fcrich",
    "sg:tags":[
        "videofilmherstellung",
        "u"
    ],
    "wof:name":"Maya Burgdorfer Central Studio Modedesign",
    "wof:placetype":"venue"
},
  "geometry": {"coordinates":[8.5441913605,47.3806304932],"type":"Point"}
}