{
  "type": "Feature",
  "properties": {
    "iso:country":"CH",
    "sg:address":"Calendariaweg 2 6405 Immensee. Postfach",
    "sg:city":"Immensee",
    "sg:orig_category":"Sonstiges Verlagsgewerbe",
    "sg:phone":"+41 41 854 22 11",
    "sg:postcode":"6405",
    "sg:province":"Schwyz",
    "wof:name":"Calendaria Ag",
    "wof:placetype":"venue"
},
  "geometry": {"coordinates":[8.4537229538,47.094291687],"type":"Point"}
}