{
  "type": "Feature",
  "properties": {
    "iso:country":"CH",
    "sg:address":"Chemin De Pr\u00e9-clos",
    "sg:city":"Roche",
    "sg:classifiers":[
        {
            "category":"Train Station",
            "subcategory":"Rail",
            "type":"Transportation"
        }
    ],
    "sg:phone":"+41 21 960 22 51",
    "sg:postcode":"1852",
    "sg:province":"Vaud",
    "sg:tags":[
        "barrier"
    ],
    "wof:name":"Seroc Equipement Routiers Sa",
    "wof:placetype":"venue"
},
  "geometry": {"coordinates":[6.9314131737,46.3527832031],"type":"Point"}
}