{
  "type": "Feature",
  "properties": {
    "iso:country":"CH",
    "sg:address":"Via San Gottardo 21",
    "sg:city":"Bellinzona",
    "sg:orig_category":"Sanit\u00e4rinstallation",
    "sg:phone":"+41 91 825 48 75",
    "sg:postcode":"6500",
    "sg:province":"Ticino",
    "wof:name":"Giorgio Bollati Impianti Sanitari",
    "wof:placetype":"venue"
},
  "geometry": {"coordinates":[9.0300827026,46.1995201111],"type":"Point"}
}