{
  "type": "Feature",
  "properties": {
    "iso:country":"CH",
    "sg:address":"Cantonale Via 11",
    "sg:city":"Lugano",
    "sg:orig_category":"Herstellung von Seifen, Wasch U Reinigungsmitteln",
    "sg:phone":"+41 18241824",
    "sg:postcode":"6900",
    "sg:province":"Ticino",
    "wof:name":"Minatolwerke Ag",
    "wof:placetype":"venue"
},
  "geometry": {"coordinates":[8.6053600311,47.3989067078],"type":"Point"}
}