{
  "type": "Feature",
  "properties": {
    "iso:country":"CH",
    "sg:address":"Bernrainstrasse 63",
    "sg:city":"Kreuzlingen",
    "sg:orig_category":"Bauschreinerei",
    "sg:phone":"+41 71 670 08 70",
    "sg:postcode":"8280",
    "sg:province":"Thurgau",
    "wof:name":"Werner Meister Schreinerei",
    "wof:placetype":"venue"
},
  "geometry": {"coordinates":[9.1602096558,47.643951416],"type":"Point"}
}