{
  "type": "Feature",
  "properties": {
    "iso:country":"CH",
    "sg:address":"Chemin De Champ-pamont 3 1033 Cheseaux-lausanne Case Postale 78",
    "sg:city":"Cheseaux-lausanne",
    "sg:orig_category":"Grosshandel mit sonstigen Nahrungsmitteln",
    "sg:phone":"+41 22 309 40 40",
    "sg:postcode":"1033",
    "sg:province":"Vaud",
    "wof:name":"Lucas Gen\u00e8ve Sa Importation De Poissons",
    "wof:placetype":"venue"
},
  "geometry": {"coordinates":[6.1341757774,46.1815986633],"type":"Point"}
}