{
  "type": "Feature",
  "properties": {
    "iso:country":"CH",
    "sg:address":"Bahnhofstrasse 7d",
    "sg:city":"Jegenstorf",
    "sg:orig_category":"Fachdetailhandel in Verkaufsr\u00e4umen",
    "sg:phone":"+41 31 761 26 20",
    "sg:postcode":"3303",
    "sg:province":"Bern",
    "wof:name":"Sunneblueme, V\u00f6lkel N.",
    "wof:placetype":"venue"
},
  "geometry": {"coordinates":[7.5073947906,47.0481758118],"type":"Point"}
}