{
  "type": "Feature",
  "properties": {
    "iso:country":"CH",
    "sg:address":"Bahnhofstrasse 76",
    "sg:city":"Aarau",
    "sg:orig_category":"Detailhandel mit Waren verschiedener Art, Hauptrichtung Nahrungsmittel",
    "sg:phone":"+41 62 824 50 47",
    "sg:postcode":"5000",
    "sg:province":"Aargau",
    "wof:name":"Ali Gencer Suna Market",
    "wof:placetype":"venue"
},
  "geometry": {"coordinates":[8.0518140793,47.3914222717],"type":"Point"}
}