{
  "type": "Feature",
  "properties": {
    "iso:country":"CH",
    "sg:address":"Hauptstr. 192 Hinterthal.",
    "sg:city":"Muotathal",
    "sg:orig_category":"Mechanik",
    "sg:phone":"+41 41 830 14 64",
    "sg:postcode":"6436",
    "sg:province":"Schwyz",
    "wof:name":"Inderbitzin Jos.",
    "wof:placetype":"venue"
},
  "geometry": {"coordinates":[8.7582998276,46.9739761353],"type":"Point"}
}