{
  "type": "Feature",
  "properties": {
    "iso:country":"CH",
    "sg:address":"H\u00f6rnlistrasse 7 8108 D\u00e4llikon. Postfach 22",
    "sg:city":"D\u00e4llikon",
    "sg:orig_category":"Wirtschaftsverb\u00e4nde Werbung, PR, Marketing",
    "sg:phone":"+41 18440557",
    "sg:postcode":"8108",
    "sg:province":"Z\u00fcrich",
    "wof:name":"Arbeitsgemeinschaft F\u00fcr Film & Fernsehen",
    "wof:placetype":"venue"
},
  "geometry": {"coordinates":[8.4350633621,47.4378623962],"type":"Point"}
}