{
  "type": "Feature",
  "properties": {
    "iso:country":"CH",
    "sg:address":"Creusets Rue Des 5",
    "sg:city":"Sion",
    "sg:orig_category":"Druck ohne Zeitungsdruck",
    "sg:postcode":"1950",
    "sg:province":"Valais",
    "wof:name":"Pd Partnerdruck Ag",
    "wof:placetype":"venue"
},
  "geometry": {"coordinates":[9.4876050949,47.2050666809],"type":"Point"}
}