{
  "type": "Feature",
  "properties": {
    "iso:country":"CH",
    "sg:address":"Zeughausgasse 41 3011 Bern. Postfach",
    "sg:city":"Bern",
    "sg:orig_category":"Pensionskassen",
    "sg:phone":"+41 31 301 69 37",
    "sg:postcode":"3005",
    "sg:province":"Bern",
    "wof:name":"Personalf\u00fcrsorgestiftung Der Gesellschaft F\u00fcr Kongresse Und Gastronomie",
    "wof:placetype":"venue"
},
  "geometry": {"coordinates":[7.4444770813,46.9490013123],"type":"Point"}
}