{
  "type": "Feature",
  "properties": {
    "iso:country":"CH",
    "sg:address":"Turbachstrasse",
    "sg:city":"Gstaad",
    "sg:orig_category":"Zimmerei, Dachdeckerei, Bauspenglerei U Abdichtung Zimmerei, Ingenieurholzbau",
    "sg:phone":"+41 33 744 19 51",
    "sg:postcode":"3780",
    "sg:province":"Bern",
    "wof:name":"Ueli Reuteler Zimmerei & Chaletbau",
    "wof:placetype":"venue"
},
  "geometry": {"coordinates":[7.2947998047,46.4704055786],"type":"Point"}
}