{
  "type": "Feature",
  "properties": {
    "iso:country":"CH",
    "sg:address":"Reidenbach 3766 Boltigen. Postfach",
    "sg:city":"Reidenbach",
    "sg:orig_category":"Herstellung von sonstigen landwirtschaftlichen Maschinen",
    "sg:postcode":"3766",
    "sg:province":"Bern",
    "wof:name":"Hamatec, Hans Matti",
    "wof:placetype":"venue"
},
  "geometry": {"coordinates":[7.3752808571,46.6199417114],"type":"Point"}
}