{
  "type": "Feature",
  "properties": {
    "iso:country":"CH",
    "sg:address":"Klosterplatz 2 Mariastein 4115 Mariastein. Postfach",
    "sg:city":"Mariastein",
    "sg:orig_category":"Kauf U Verkauf von Immobilien auf eigene Rechnung",
    "sg:postcode":"4115",
    "sg:province":"Solothurn",
    "wof:name":"Hofgut Mariastein Ag",
    "wof:placetype":"venue"
},
  "geometry": {"coordinates":[7.4898748398,47.4764137268],"type":"Point"}
}