{
  "type": "Feature",
  "properties": {
    "iso:country":"CH",
    "sg:address":"Scheuchzerstrasse 36 8006 Z\u00fcrich. Postfach",
    "sg:city":"Z\u00fcrich",
    "sg:orig_category":"Grosshandel mit B\u00fcromaschinen Grosshandel mit Datenverarbeitungsger\u00e4ten",
    "sg:phone":"+41 13601900",
    "sg:postcode":"8033",
    "sg:province":"Z\u00fcrich",
    "wof:name":"New Voice, Z\u00fcrich, Audiotex & Voice Mail, Brigati J\u00fcrg M.",
    "wof:placetype":"venue"
},
  "geometry": {"coordinates":[8.5450763702,47.3848457336],"type":"Point"}
}