{
  "type": "Feature",
  "properties": {
    "iso:country":"CH",
    "sg:address":"Dorfstrasse 84",
    "sg:city":"Melchnau",
    "sg:orig_category":"Detailhandel mit Fleisch U Fleischwaren Grosshandel mit lebenden Tieren",
    "sg:phone":"+41 62 927 11 09",
    "sg:postcode":"4917",
    "sg:province":"Bern",
    "wof:name":"Ulrich Iff Metzgerei & Viehhandel",
    "wof:placetype":"venue"
},
  "geometry": {"coordinates":[7.8514389992,47.1819496155],"type":"Point"}
}