{
  "type": "Feature",
  "properties": {
    "iso:country":"CH",
    "sg:address":"Route De Del\u00e9mont 3",
    "sg:city":"Courrendlin",
    "sg:orig_category":"Sonstige Hilfsdienste des Kultur U Unterhaltungswesens Verlag von bespielten Tontr\u00e4gern",
    "sg:postcode":"2830",
    "sg:province":"Jura",
    "wof:name":"Patrick Champion Musifil Productions",
    "wof:placetype":"venue"
},
  "geometry": {"coordinates":[7.3716688156,47.3406791687],"type":"Point"}
}