{
  "type": "Feature",
  "properties": {
    "iso:country":"CH",
    "sg:address":"Widackerhof",
    "sg:city":"Hornussen",
    "sg:orig_category":"Politische Parteien SVP",
    "sg:phone":"+41 62 871 24 06",
    "sg:postcode":"5075",
    "sg:province":"Aargau",
    "wof:name":"Svp Ortspartei Hornussen",
    "wof:placetype":"venue"
},
  "geometry": {"coordinates":[8.0640659332,47.4877891541],"type":"Point"}
}