{
  "type": "Feature",
  "properties": {
    "iso:country":"CH",
    "sg:address":"Bubenbergplatz 15 3011 Bern. Postfach",
    "sg:city":"Bern",
    "sg:orig_category":"Detailhandel mit M\u00f6beln Innenausbau",
    "sg:phone":"+41 31 328 55 55",
    "sg:postcode":"3001",
    "sg:province":"Bern",
    "wof:name":"Anliker Langenthal Ag Bau, M\u00f6belschreinerei, Tapeziererei, Usw",
    "wof:placetype":"venue"
},
  "geometry": {"coordinates":[7.4390420914,46.9472122192],"type":"Point"}
}