{
  "type": "Feature",
  "properties": {
    "iso:country":"CH",
    "sg:address":"Buechstrasse 17",
    "sg:city":"Jona",
    "sg:orig_category":"Herstellung von Mess U Kontrollinstrumenten U vorrichtungen Mechanische Werkst\u00e4tten",
    "sg:phone":"+41 61 721 12 79",
    "sg:postcode":"8645",
    "sg:province":"St. Gallen",
    "wof:name":"Portmann Instruments Ag",
    "wof:placetype":"venue"
},
  "geometry": {"coordinates":[7.5253500938,47.5052108765],"type":"Point"}
}