{
  "type": "Feature",
  "properties": {
    "iso:country":"CH",
    "sg:address":"Casa Dell'orso",
    "sg:city":"Gordola",
    "sg:orig_category":"Architektur U Ingenieurb\u00fcros",
    "sg:postcode":"6596",
    "sg:province":"Ticino",
    "wof:name":"Tenger Hans-peter",
    "wof:placetype":"venue"
},
  "geometry": {"coordinates":[8.922647,45.00806],"type":"Point"}
}