{
  "type": "Feature",
  "properties": {
    "iso:country":"CH",
    "sg:address":"Affolterstrasse 21",
    "sg:city":"Luterbach",
    "sg:orig_category":"Instandhaltung U Reparatur von Automobilen",
    "sg:phone":"+41 32 682 40 44",
    "sg:postcode":"4542",
    "sg:province":"Solothurn",
    "wof:name":"Garage Moser Ag, Luterbach",
    "wof:placetype":"venue"
},
  "geometry": {"coordinates":[7.5923500061,47.2149429321],"type":"Point"}
}