{
  "type": "Feature",
  "properties": {
    "iso:country":"CH",
    "sg:address":"Rue De La Prairie 1",
    "sg:city":"Gland",
    "sg:orig_category":"Architektur U Ingenieurb\u00fcros",
    "sg:phone":"+41 22 364 52 40",
    "sg:postcode":"1196",
    "sg:province":"Vaud",
    "wof:name":"Pascal Aubert Bureau Technique",
    "wof:placetype":"venue"
},
  "geometry": {"coordinates":[6.274159,46.420254],"type":"Point"}
}