{
  "type": "Feature",
  "properties": {
    "iso:country":"CH",
    "sg:address":"Spitalgasse 1 4800 Zofingen. Postfach",
    "sg:city":"Zofingen",
    "sg:orig_category":"Drogerien",
    "sg:phone":"+41 62 752 25 05",
    "sg:postcode":"4800",
    "sg:province":"Aargau",
    "wof:name":"Peter M\u00fcller, Stadttor-drogerie",
    "wof:placetype":"venue"
},
  "geometry": {"coordinates":[7.9428777695,47.2916641235],"type":"Point"}
}