{
  "type": "Feature",
  "properties": {
    "iso:country":"CH",
    "sg:address":"Zugerstrasse 34",
    "sg:city":"Steinhausen",
    "sg:orig_category":"Detektivb\u00fcros U \u00dcberwachung",
    "sg:postcode":"6312",
    "sg:province":"Zug",
    "wof:name":"Bewachungs Und Sicherheitsdienst Graf",
    "wof:placetype":"venue"
},
  "geometry": {"coordinates":[8.4453458786,47.4170570374],"type":"Point"}
}