{
  "type": "Feature",
  "properties": {
    "iso:country":"CH",
    "sg:address":"Alpes Rue Des 7 1201 Gen\u00e8ve. Postfach",
    "sg:city":"Gen\u00e8ve",
    "sg:orig_category":"Wirtschaftspr\u00fcfung, Steuerberatung U Treuhand",
    "sg:postcode":"1201",
    "sg:province":"Gen\u00e8ve",
    "wof:name":"Onyx Treuhand Ag",
    "wof:placetype":"venue"
},
  "geometry": {"coordinates":[8.4369068146,47.3528442383],"type":"Point"}
}