{
  "type": "Feature",
  "properties": {
    "iso:country":"CH",
    "sg:address":"Alpenstrasse 16 6300 Zug. Postfach 4845",
    "sg:city":"Zug",
    "sg:orig_category":"Handelsvermittlung U Grosshandel",
    "sg:phone":"+41 71 890 03 03",
    "sg:postcode":"6304",
    "sg:province":"Zug",
    "wof:name":"Zwima Gmbh Warenhandel Usw",
    "wof:placetype":"venue"
},
  "geometry": {"coordinates":[9.4966526031,47.4425888062],"type":"Point"}
}