{
  "type": "Feature",
  "properties": {
    "iso:country":"CH",
    "sg:address":"Hermikonstrasse 52",
    "sg:city":"D\u00fcbendorf",
    "sg:orig_category":"Unternehmensberatung",
    "sg:phone":"+41 18200837",
    "sg:postcode":"8600",
    "sg:province":"Z\u00fcrich",
    "wof:name":"Urs Wicki Mediation",
    "wof:placetype":"venue"
},
  "geometry": {"coordinates":[8.6265935898,47.3918952942],"type":"Point"}
}