{
  "type": "Feature",
  "properties": {
    "iso:country":"CH",
    "sg:address":"Industriestr. 14",
    "sg:city":"Rothrist",
    "sg:orig_category":"Pensionskassen",
    "sg:postcode":"4852",
    "sg:province":"Aargau",
    "wof:name":"Wohlfahrtsfonds Der Rivella Ag",
    "wof:placetype":"venue"
},
  "geometry": {"coordinates":[7.8724031448,47.308506012],"type":"Point"}
}