{
  "type": "Feature",
  "properties": {
    "iso:country":"CH",
    "sg:address":"Lausanne 6 Rue De",
    "sg:city":"Bussigny-lausanne",
    "sg:orig_category":"Detailhandel mit Brot, Back U S\u00fcsswaren",
    "sg:phone":"+41 21 701 11 56",
    "sg:postcode":"1030",
    "sg:province":"Vaud",
    "wof:name":"Gerber Pascal",
    "wof:placetype":"venue"
},
  "geometry": {"coordinates":[6.551774,46.550049],"type":"Point"}
}