{
  "type": "Feature",
  "properties": {
    "iso:country":"CH",
    "sg:address":"St.gallerstrasse 43",
    "sg:city":"Kronb\u00fchl",
    "sg:orig_category":"RESTAURANTS: TEA-ROOMS",
    "sg:phone":"+41 71 298 43 40",
    "sg:postcode":"9302",
    "wof:name":"Pizzeria Testarossa Garieri S.",
    "wof:placetype":"venue"
},
  "geometry": {"coordinates":[9.3984603882,47.4556388855],"type":"Point"}
}