{
  "type": "Feature",
  "properties": {
    "iso:country":"CH",
    "sg:address":"Via Luini 22",
    "sg:city":"Locarno",
    "sg:orig_category":"Verlagsgewerbe",
    "sg:phone":"+41 21 801 51 53",
    "sg:postcode":"6600",
    "sg:province":"Ticino",
    "wof:name":"Le Quotidien De La C\u00f4te & Morges-actualit\u00e9s",
    "wof:placetype":"venue"
},
  "geometry": {"coordinates":[6.4965238571,46.5101661682],"type":"Point"}
}