{
  "type": "Feature",
  "properties": {
    "iso:country":"CH",
    "sg:address":"Rikonerstrasse 52",
    "sg:city":"Effretikon",
    "sg:classifiers":[
        {
            "category":"Restaurant",
            "type":"Food & Drink"
        }
    ],
    "sg:phone":"+41 52 343 93 60",
    "sg:postcode":"8307",
    "sg:province":"Z\u00fcrich",
    "wof:name":"Qn-restaurant",
    "wof:placetype":"venue"
},
  "geometry": {"coordinates":[8.6896591187,47.4321098328],"type":"Point"}
}