{
  "type": "Feature",
  "properties": {
    "iso:country":"CH",
    "sg:address":"Kellengasse",
    "sg:city":"Lostorf",
    "sg:orig_category":"Zahnarztpraxen",
    "sg:phone":"+41 62 298 32 08",
    "sg:postcode":"4654",
    "sg:province":"Solothurn",
    "wof:name":"Dr. Med. Dent. Bettina Holly Zahn\u00e4rztin",
    "wof:placetype":"venue"
},
  "geometry": {"coordinates":[7.9459037781,47.388217926],"type":"Point"}
}