{
  "type": "Feature",
  "properties": {
    "iso:country":"CH",
    "sg:address":"4 R St. Pierre",
    "sg:city":"Lausanne",
    "sg:classifiers":[
        {
            "category":"Manufacturing",
            "subcategory":"Metals",
            "type":"Manufacturing & Wholesale Goods"
        }
    ],
    "sg:phone":"+41 21 312 08 72",
    "sg:postcode":"1003",
    "sg:province":"Vaud",
    "sg:tags":[
        "metallurgy",
        "metalworking",
        "processing"
    ],
    "wof:name":"Fuhrer Ag",
    "wof:placetype":"venue"
},
  "geometry": {"coordinates":[6.6371030807,46.5194664001],"type":"Point"}
}