{
  "type": "Feature",
  "properties": {
    "iso:country":"CH",
    "sg:address":"Madonna Del Piano 6980 Croglio. Postfach",
    "sg:city":"Banco",
    "sg:orig_category":"Instandhaltung U Reparatur von Automobilen",
    "sg:postcode":"6981",
    "sg:province":"Ticino",
    "wof:name":"Garage Finger",
    "wof:placetype":"venue"
},
  "geometry": {"coordinates":[7.4621138573,46.7949256897],"type":"Point"}
}