{
  "type": "Feature",
  "properties": {
    "iso:country":"CH",
    "sg:address":"Viglio",
    "sg:city":"Gentilino",
    "sg:classifiers":[
        {
            "category":"Bars & Pubs",
            "type":"Food & Drink"
        }
    ],
    "sg:phone":"+41 91 994 62 69",
    "sg:postcode":"6925",
    "sg:province":"Ticino",
    "wof:name":"Piano-bar Unione Viglio",
    "wof:placetype":"venue"
},
  "geometry": {"coordinates":[8.92574,45.99408],"type":"Point"}
}