{
  "type": "Feature",
  "properties": {
    "iso:country":"CH",
    "sg:address":"Chemin Des Noyers 15",
    "sg:city":"Aigle",
    "sg:orig_category":"Grafikateliers, Design Werbung",
    "sg:phone":"+41 24 466 27 47",
    "sg:postcode":"1860",
    "sg:province":"Vaud",
    "wof:name":"Hutmacher Fr\u00e9d\u00e9ric",
    "wof:placetype":"venue"
},
  "geometry": {"coordinates":[6.9701728821,46.3200302124],"type":"Point"}
}