{
  "type": "Feature",
  "properties": {
    "iso:country":"CH",
    "sg:address":"Sch\u00f6nmattweg 9",
    "sg:city":"Belp",
    "sg:orig_category":"Herstellung von Duft U K\u00f6rperpflegemitteln",
    "sg:phone":"+41 31 819 30 42",
    "sg:postcode":"3123",
    "sg:province":"Bern",
    "wof:name":"Marketing + Vertrieb B\u00e4hler Silvia",
    "wof:placetype":"venue"
},
  "geometry": {"coordinates":[7.4978442192,46.8968276978],"type":"Point"}
}