{
  "type": "Feature",
  "properties": {
    "iso:country":"CH",
    "sg:address":"Lihn",
    "sg:city":"Filzbach",
    "sg:orig_category":"HOTELS: MIT RESTAURANT Kongress- and Tagungshotels mit Restaurant",
    "sg:phone":"+41 55 614 13 42",
    "sg:postcode":"8757",
    "sg:province":"Glarus",
    "wof:name":"Kurs Und Ferienzentrum Lihn Blaukreuz",
    "wof:placetype":"venue"
},
  "geometry": {"coordinates":[9.1266641617,47.12292099],"type":"Point"}
}