{
  "type": "Feature",
  "properties": {
    "iso:country":"CH",
    "sg:address":"Chemin Des Colombettes 3",
    "sg:city":"Savigny",
    "sg:orig_category":"Vermietung U Verpachtung von eigenen Immobilien Vermittlung von Immobilien",
    "sg:phone":"+41 21 781 21 09",
    "sg:postcode":"1073",
    "sg:province":"Vaud",
    "wof:name":"Vimmob Beatrice Virchaux Agence Immobili\u00e8re Vimmob",
    "wof:placetype":"venue"
},
  "geometry": {"coordinates":[6.7348389626,46.5390968323],"type":"Point"}
}