{
  "type": "Feature",
  "properties": {
    "iso:country":"CH",
    "sg:address":"Industrieplatz 1",
    "sg:city":"Neuhausen",
    "sg:orig_category":"Herstellung von elektronischen Bauelementen",
    "sg:phone":"+41 52 674 63 51",
    "sg:postcode":"8212",
    "sg:province":"Schaffhausen",
    "wof:name":"Thasa Ag Elektro-& Elektronikbauteile",
    "wof:placetype":"venue"
},
  "geometry": {"coordinates":[8.6186275482,47.6794319153],"type":"Point"}
}