{
  "type": "Feature",
  "properties": {
    "iso:country":"CH",
    "sg:address":"Eisweiherstrasse 30",
    "sg:city":"Winterthur",
    "sg:classifiers":[
        {
            "category":"Food & Beverages",
            "subcategory":"Specialty",
            "type":"Retail Goods"
        }
    ],
    "sg:phone":"+41 52 232 91 54",
    "sg:postcode":"8400",
    "sg:province":"Z\u00fcrich",
    "sg:tags":[
        "caterer"
    ],
    "wof:name":"Partyservice Orientalisch",
    "wof:placetype":"venue"
},
  "geometry": {"coordinates":[8.735365,47.490822],"type":"Point"}
}