{
  "type": "Feature",
  "properties": {
    "iso:country":"CH",
    "sg:address":"Ringstrasse 23 6332 Hagendorn. Postfach",
    "sg:city":"Hagendorn",
    "sg:orig_category":"Reiseb\u00fcros U Reiseveranstalter",
    "sg:postcode":"6332",
    "sg:province":"Zug",
    "wof:name":"Let's Go Travel, Owen Helena",
    "wof:placetype":"venue"
},
  "geometry": {"coordinates":[8.4368801117,47.2069206238],"type":"Point"}
}