{
  "type": "Feature",
  "properties": {
    "iso:country":"CH",
    "sg:address":"Bergweidweg 8",
    "sg:city":"Innerberg",
    "sg:orig_category":"Bauspenglerei Zimmerei, Dachdeckerei, Bauspenglerei U Abdichtung",
    "sg:phone":"+41 79 652 82 81",
    "sg:postcode":"3044",
    "sg:province":"Bern",
    "wof:name":"Spenglerei Kehrli",
    "wof:placetype":"venue"
},
  "geometry": {"coordinates":[7.30902,46.992168],"type":"Point"}
}