{
  "type": "Feature",
  "properties": {
    "iso:country":"CH",
    "sg:address":"Monte Boglia Via 6",
    "sg:city":"Lugano",
    "sg:orig_category":"Architektur U Ingenieurb\u00fcros",
    "sg:postcode":"6900",
    "sg:province":"Ticino",
    "wof:name":"Essa Servizi Sa",
    "wof:placetype":"venue"
},
  "geometry": {"coordinates":[8.958033,46.017975],"type":"Point"}
}