{
  "type": "Feature",
  "properties": {
    "iso:country":"CH",
    "sg:address":"Rue Major-davel",
    "sg:city":"Baulmes",
    "sg:orig_category":"Arztpraxen",
    "sg:phone":"+41 24 459 12 22",
    "sg:postcode":"1446",
    "sg:province":"Vaud",
    "wof:name":"Dr M\u00e9d. Claude Morier-genoud M\u00e9decin G\u00e9n\u00e9raliste Fmh",
    "wof:placetype":"venue"
},
  "geometry": {"coordinates":[6.522025,46.789181],"type":"Point"}
}