{
  "type": "Feature",
  "properties": {
    "iso:country":"CH",
    "sg:address":"Boulevard Helv\u00e9tique 16",
    "sg:city":"Gen\u00e8ve",
    "sg:orig_category":"Arztpraxen",
    "sg:phone":"+41 22 700 28 26",
    "sg:postcode":"1207",
    "sg:province":"Gen\u00e8ve",
    "wof:name":"Drs M\u00e9d. M.& M.-c. Vonlanthen M\u00e9decins Sp\u00e9cialistes Fmh",
    "wof:placetype":"venue"
},
  "geometry": {"coordinates":[6.153867,46.200085],"type":"Point"}
}