{
  "type": "Feature",
  "properties": {
    "iso:country":"CH",
    "sg:address":"Hauptstrasse 26",
    "sg:city":"Burg\u00e4schi",
    "sg:classifiers":[
        {
            "category":"Restaurant",
            "type":"Food & Drink"
        }
    ],
    "sg:phone":"+41 62 961 11 65",
    "sg:postcode":"4556",
    "sg:province":"Solothurn",
    "wof:name":"Restaurant Seeblick",
    "wof:placetype":"venue"
},
  "geometry": {"coordinates":[7.6710968018,47.171043396],"type":"Point"}
}