{
  "type": "Feature",
  "properties": {
    "iso:country":"CH",
    "sg:address":"Stelzenrebenstrasse 1",
    "sg:city":"Goldach",
    "sg:orig_category":"Unclassifiable Establishments",
    "sg:postcode":"9403",
    "sg:province":"St. Gallen",
    "wof:name":"Max Rentsch M\u00f6belschreiner Montagen Rep.",
    "wof:placetype":"venue"
},
  "geometry": {"coordinates":[9.4774923325,47.4792060852],"type":"Point"}
}