{
  "type": "Feature",
  "properties": {
    "iso:country":"CH",
    "sg:address":"6490 Andermatt. Postfach 141",
    "sg:city":"Andermatt",
    "sg:orig_category":"Sportschulen",
    "sg:phone":"+41 41 872 09 00",
    "sg:postcode":"6490",
    "sg:province":"Uri",
    "wof:name":"Bergschule Uri Sportinstitut & Schule",
    "wof:placetype":"venue"
},
  "geometry": {"coordinates":[8.5947551727,46.6329498291],"type":"Point"}
}