{
  "type": "Feature",
  "properties": {
    "iso:country":"CH",
    "sg:address":"Ritterhausstrasse 9",
    "sg:city":"Uerikon",
    "sg:orig_category":"Regionalbanken U Sparkassen",
    "sg:phone":"+41 19264444",
    "sg:postcode":"8713",
    "sg:province":"Z\u00fcrich",
    "wof:name":"Bank Linth",
    "wof:placetype":"venue"
},
  "geometry": {"coordinates":[8.7566452026,47.2360839844],"type":"Point"}
}