{
  "type": "Feature",
  "properties": {
    "iso:country":"CH",
    "sg:address":"Aecherli 6370 Stans. Postfach",
    "sg:city":"Stans",
    "sg:orig_category":"Luft U Raumfahrzeugbau",
    "sg:phone":"+41 41 619 61 11",
    "sg:postcode":"6370",
    "sg:province":"Nidwalden",
    "wof:name":"Pilatus Aircraft Service Ag",
    "wof:placetype":"venue"
},
  "geometry": {"coordinates":[8.3839883804,46.9769439697],"type":"Point"}
}