{
  "type": "Feature",
  "properties": {
    "iso:country":"CH",
    "sg:address":"Kirch\u00e4gerten 3 4223 Blauen. Postfach",
    "sg:city":"Blauen",
    "sg:orig_category":"Erbringung von Dienstleistungen f\u00fcr Unternehmen",
    "sg:phone":"+41 71 910 07 05",
    "sg:postcode":"4223",
    "sg:province":"Basel-Landschaft",
    "wof:name":"Docu-sped By Scheiwiller Document Management Systeme; Beratung U. Verkauf",
    "wof:placetype":"venue"
},
  "geometry": {"coordinates":[9.0512189865,47.4703407288],"type":"Point"}
}