{
  "type": "Feature",
  "properties": {
    "iso:country":"CH",
    "sg:address":"Chaunt Da Luf 91 7524 Zuoz. Postfach",
    "sg:city":"Zuoz",
    "sg:orig_category":"Herstellung von Metallkonstruktionen",
    "sg:phone":"+41 81 854 31 25",
    "sg:postcode":"7524",
    "sg:province":"Graubunden",
    "wof:name":"G.p. Nyfeler, Delaval-service Stall- U. Melktechnik; Einrichtungen, Service",
    "wof:placetype":"venue"
},
  "geometry": {"coordinates":[9.9584026337,46.6019058228],"type":"Point"}
}