{
  "type": "Feature",
  "properties": {
    "iso:country":"CH",
    "sg:address":"Z\u00fcrcherstrasse 96",
    "sg:city":"Altendorf",
    "sg:orig_category":"Grosshandel mit M\u00f6beln, Wohnbedarf, Teppichen U Bodenbel\u00e4gen Grosshandel mit landwirtschaftlichen Ma",
    "sg:phone":"+41 21 635 28 47",
    "sg:postcode":"8852",
    "sg:province":"Schwyz",
    "wof:name":"Green Space, Taher Claire",
    "wof:placetype":"venue"
},
  "geometry": {"coordinates":[6.5901169777,46.5324821472],"type":"Point"}
}