{
  "type": "Feature",
  "properties": {
    "iso:country":"CH",
    "sg:address":"Gotthardstr. 15 6430 Schwyz. Postfach",
    "sg:city":"Ibach",
    "sg:orig_category":"Pensionskassen",
    "sg:postcode":"6438",
    "sg:province":"Schwyz",
    "wof:name":"Personalf\u00fcrsorgestiftung Der Firma Benno M\u00fcller, Autogarage, Ibach",
    "wof:placetype":"venue"
},
  "geometry": {"coordinates":[8.6409502029,47.0184783936],"type":"Point"}
}