{
  "type": "Feature",
  "properties": {
    "iso:country":"CH",
    "sg:address":"Rue De La Coulouvreni\u00e8re 8",
    "sg:city":"Gen\u00e8ve",
    "sg:orig_category":"Herstellung U Zusammensetzung von Uhren Herstellung von Metallerzeugnissen ohne Maschinenbau",
    "sg:phone":"+41 32 953 19 50",
    "sg:postcode":"1204",
    "sg:province":"Gen\u00e8ve",
    "wof:name":"A\u00e9ro Watch Muriaux Sa",
    "wof:placetype":"venue"
},
  "geometry": {"coordinates":[6.9546117783,47.2242927551],"type":"Point"}
}