{
  "type": "Feature",
  "properties": {
    "iso:country":"CH",
    "sg:address":"Zippersh\u00e4usern 603",
    "sg:city":"Linden",
    "sg:orig_category":"Hoch U Tiefbau Verlegen von Fliesen U Platten",
    "sg:phone":"+41 31 771 08 87",
    "sg:postcode":"3673",
    "sg:province":"Bern",
    "wof:name":"Karl Moser Baugesch\u00e4ft & Plattenarbeiten",
    "wof:placetype":"venue"
},
  "geometry": {"coordinates":[7.653069973,46.845375061],"type":"Point"}
}