{
  "type": "Feature",
  "properties": {
    "iso:country":"CH",
    "sg:address":"Renggerstrasse 43",
    "sg:city":"Z\u00fcrich",
    "sg:orig_category":"Unternehmensberatung",
    "sg:phone":"+41 14819961",
    "sg:postcode":"8038",
    "sg:province":"Z\u00fcrich",
    "wof:name":"D\u00e4llenbach Dr. Alex Unternehmerberatung Kaderselektion, Unternehmensberatung, Edv-beratung",
    "wof:placetype":"venue"
},
  "geometry": {"coordinates":[8.5325508118,47.3454399109],"type":"Point"}
}