{
  "type": "Feature",
  "properties": {
    "iso:country":"CH",
    "sg:address":"Rue Horace-b.de-saussure 6 1200 Genf. Postfach",
    "sg:city":"Gen\u00e8ve",
    "sg:orig_category":"Non-Classified Establishments",
    "sg:postcode":"1204",
    "sg:province":"Gen\u00e8ve",
    "wof:name":"Icp Promotion Commerciale Sa, Gen\u00e8ve",
    "wof:placetype":"venue"
},
  "geometry": {"coordinates":[6.1423768997,46.1993293762],"type":"Point"}
}