{
  "type": "Feature",
  "properties": {
    "iso:country":"CH",
    "sg:address":"Produit",
    "sg:city":"Leytron",
    "sg:classifiers":[
        {
            "category":"Restaurant",
            "type":"Food & Drink"
        }
    ],
    "sg:phone":"+41 27 306 35 12",
    "sg:postcode":"1912",
    "sg:province":"Valais",
    "wof:name":"Caf\u00e9 Bellevue",
    "wof:placetype":"venue"
},
  "geometry": {"coordinates":[7.1934528351,46.1837348938],"type":"Point"}
}