{
  "type": "Feature",
  "properties": {
    "iso:country":"CH",
    "sg:address":"Kronenplatz 8",
    "sg:city":"Dietikon",
    "sg:orig_category":"Detailhandel mit Fleisch U Fleischwaren",
    "sg:phone":"+41 17408039",
    "sg:postcode":"8953",
    "sg:province":"Z\u00fcrich",
    "wof:name":"Fritz Brechb\u00fchl Metzgerei Wursterei",
    "wof:placetype":"venue"
},
  "geometry": {"coordinates":[8.4003047943,47.4058647156],"type":"Point"}
}