{
  "type": "Feature",
  "properties": {
    "iso:country":"CH",
    "sg:address":"Beauregard Rue De 11",
    "sg:city":"Fribourg",
    "sg:orig_category":"RESTAURANTS: TEA-ROOMS",
    "sg:postcode":"1700",
    "sg:province":"Fribourg",
    "wof:name":"Nab S\u00e0rl",
    "wof:placetype":"venue"
},
  "geometry": {"coordinates":[7.1461100578,46.802154541],"type":"Point"}
}