{
  "type": "Feature",
  "properties": {
    "iso:country":"CH",
    "sg:address":"Prom.des Champs-fr\u00e9chets 24",
    "sg:city":"Meyrin",
    "sg:orig_category":"Zahnarztpraxen",
    "sg:phone":"+41 76 397 60 21",
    "sg:postcode":"1217",
    "sg:province":"Gen\u00e8ve",
    "wof:name":"Dr M\u00e9d.dent.charles-a. Ferrero M\u00e9decin-dentiste",
    "wof:placetype":"venue"
},
  "geometry": {"coordinates":[6.0775241852,46.2370147705],"type":"Point"}
}