{
  "type": "Feature",
  "properties": {
    "iso:country":"CH",
    "sg:address":"2906 Chevenez. Postfach",
    "sg:city":"Chevenez",
    "sg:orig_category":"Sonstige pers\u00f6nliche Dienstleistungen",
    "sg:postcode":"2906",
    "sg:province":"Jura",
    "wof:name":"Sous-traitance Busch & Cie Travaux De Sous-traitance Pour Les Soci\u00e9t\u00e9s Du Groupe Etc",
    "wof:placetype":"venue"
},
  "geometry": {"coordinates":[6.9999499321,47.3914299011],"type":"Point"}
}