{
  "type": "Feature",
  "properties": {
    "iso:country":"CH",
    "sg:address":"Rheinaustrasse 8",
    "sg:city":"Sargans",
    "sg:orig_category":"Non-Classified Establishments",
    "sg:phone":"+41 81 710 44 45",
    "sg:postcode":"7320",
    "sg:province":"St. Gallen",
    "wof:name":"Pizza-kurier Fantasy Roberto-nicoletta Nunzianna",
    "wof:placetype":"venue"
},
  "geometry": {"coordinates":[9.4508686066,47.0499458313],"type":"Point"}
}