{
  "type": "Feature",
  "properties": {
    "addr:full":"Nant-d'argent Chemin Du 53 Cologny Gen\u00e8ve 1223",
    "addr:postcode":"1223",
    "addr:street":"Chemin Du 53",
    "iso:country":"CH",
    "sg:address":"Nant-d'argent Chemin Du 53",
    "sg:city":"Cologny",
    "sg:orig_category":"Binnenschiffahrt",
    "sg:phone":"+41 22 737 40 30",
    "sg:postcode":"1223",
    "sg:province":"Gen\u00e8ve",
    "wof:name":"Darya Shipping Sa",
    "wof:placetype":"venue"
},
  "geometry": {"coordinates":[6.162952,46.203648],"type":"Point"}
}