{
  "type": "Feature",
  "properties": {
    "iso:country":"CH",
    "sg:address":"Gare Avenue De La",
    "sg:city":"Montagne-moutier",
    "sg:orig_category":"RESTAURANTS: TEA-ROOMS",
    "sg:postcode":"2740",
    "sg:province":"Bern",
    "wof:name":"Wisard-sommer Andr\u00e9",
    "wof:placetype":"venue"
},
  "geometry": {"coordinates":[7.4550700188,47.285369873],"type":"Point"}
}