{
  "type": "Feature",
  "properties": {
    "iso:country":"CH",
    "sg:address":"Agnesstrasse 24 8000 Z\u00fcrich. Postfach",
    "sg:city":"Z\u00fcrich",
    "sg:orig_category":"Herstellung von Schreibwaren U B\u00fcrobedarf aus Papier, Karton U Pappe",
    "sg:phone":"+41 19475020",
    "sg:postcode":"8001",
    "sg:province":"Z\u00fcrich",
    "wof:name":"Dataform Ag",
    "wof:placetype":"venue"
},
  "geometry": {"coordinates":[8.65721035,47.3940887451],"type":"Point"}
}