{
  "type": "Feature",
  "properties": {
    "iso:country":"CH",
    "sg:address":"1626",
    "sg:city":"Rueyres-treyfayes",
    "sg:orig_category":"Detailhandel mit Waren verschiedener Art, Hauptrichtung Nahrungsmittel",
    "sg:phone":"+41 32 866 12 40",
    "sg:postcode":"1626",
    "sg:province":"Fribourg",
    "wof:name":"Fr\u00e9d\u00e9ric Matthey Alimentation Vis-\u00e0-vis",
    "wof:placetype":"venue"
},
  "geometry": {"coordinates":[6.5243558884,46.9177322388],"type":"Point"}
}