{
  "type": "Feature",
  "properties": {
    "iso:country":"CH",
    "sg:address":"Br\u00fcnigstrasse 92",
    "sg:city":"Sarnen",
    "sg:orig_category":"Bauschreinerei Innenausbau",
    "sg:phone":"+41 41 660 19 50",
    "sg:postcode":"6060",
    "sg:province":"Obwalden",
    "wof:name":"Durrer Arnold, M\u00f6bel & Innenausbau Ag",
    "wof:placetype":"venue"
},
  "geometry": {"coordinates":[8.247052,46.901581],"type":"Point"}
}