{
  "type": "Feature",
  "properties": {
    "iso:country":"CH",
    "sg:address":"K\u00fchweid",
    "sg:city":"Wiliberg",
    "sg:orig_category":"Unternehmensberatung",
    "sg:phone":"+41 62 745 99 00",
    "sg:postcode":"5058",
    "sg:province":"Aargau",
    "wof:name":"Andres Quality System Ag",
    "wof:placetype":"venue"
},
  "geometry": {"coordinates":[8.0159931183,47.2701797485],"type":"Point"}
}