{
  "type": "Feature",
  "properties": {
    "iso:country":"CH",
    "sg:address":"Route De Ch\u00eane 70",
    "sg:city":"Gen\u00e8ve",
    "sg:orig_category":"Sportvereine Sch\u00fctzen",
    "sg:phone":"+41 22 700 10 36",
    "sg:postcode":"1208",
    "sg:province":"Gen\u00e8ve",
    "wof:name":"St\u00e9 Tir Group.d.matcheurs Gen.",
    "wof:placetype":"venue"
},
  "geometry": {"coordinates":[6.1743707657,46.1995811462],"type":"Point"}
}