{
  "type": "Feature",
  "properties": {
    "iso:country":"CH",
    "sg:address":"Lamartine Rue 20",
    "sg:city":"Gen\u00e8ve",
    "sg:orig_category":"Unclassifiable Establishments",
    "sg:postcode":"1203",
    "sg:province":"Gen\u00e8ve",
    "wof:name":"Jos\u00e9 Elias Esteves",
    "wof:placetype":"venue"
},
  "geometry": {"coordinates":[7.2124481201,46.0804595947],"type":"Point"}
}