{
  "type": "Feature",
  "properties": {
    "iso:country":"CH",
    "sg:address":"1693 Orsonnens. Postfach",
    "sg:city":"Villargiroud",
    "sg:orig_category":"Zimmerei, Dachdeckerei, Bauspenglerei U Abdichtung",
    "sg:phone":"+41 24 459 19 20",
    "sg:postcode":"1694",
    "sg:province":"Fribourg",
    "wof:name":"Degiez Jean-luc",
    "wof:placetype":"venue"
},
  "geometry": {"coordinates":[6.5610051155,46.8027954102],"type":"Point"}
}