{
  "type": "Feature",
  "properties": {
    "iso:country":"CH",
    "sg:address":"Bahnhofstrasse 12",
    "sg:city":"M\u00e4nnedorf",
    "sg:orig_category":"Erschliessung von Grundst\u00fccken",
    "sg:phone":"+41 19221200",
    "sg:postcode":"8708",
    "sg:province":"Z\u00fcrich",
    "wof:name":"Baugenossenschaft Schellen M\u00e4nnedorf",
    "wof:placetype":"venue"
},
  "geometry": {"coordinates":[8.6916847229,47.2534294128],"type":"Point"}
}