{
  "type": "Feature",
  "properties": {
    "iso:country":"CH",
    "sg:address":"Baarerstrasse 22",
    "sg:city":"Zug",
    "sg:orig_category":"Architektur U Ingenieurb\u00fcros Handelsvermittlung von Holz U Baustoffen",
    "sg:postcode":"6300",
    "sg:province":"Zug",
    "wof:name":"Eduard Meier Bautreuhand Gmbh",
    "wof:placetype":"venue"
},
  "geometry": {"coordinates":[8.516957,47.17337],"type":"Point"}
}