{
  "type": "Feature",
  "properties": {
    "iso:country":"CH",
    "sg:address":"R\u00f6ssligasse 2 6003 Luzern. Postfach",
    "sg:city":"Luzern",
    "sg:orig_category":"RESTAURANTS: TEA-ROOMS",
    "sg:phone":"+41 41 410 30 14",
    "sg:postcode":"6003",
    "sg:province":"Luzern",
    "wof:name":"Wagner Peter Ag Gastronomiebetriebe; F\u00fchrung, Pacht, Erwerb",
    "wof:placetype":"venue"
},
  "geometry": {"coordinates":[8.3048667908,47.0523948669],"type":"Point"}
}