{
  "type": "Feature",
  "properties": {
    "iso:country":"CH",
    "sg:address":"Luzernerstrasse 23",
    "sg:city":"Dagmersellen",
    "sg:orig_category":"Druck ohne Zeitungsdruck Offsetdruck",
    "sg:phone":"+41 62 756 20 39",
    "sg:postcode":"6252",
    "sg:province":"Luzern",
    "wof:name":"Felder Druck Ag",
    "wof:placetype":"venue"
},
  "geometry": {"coordinates":[7.9929909706,47.2114982605],"type":"Point"}
}