{
  "type": "Feature",
  "properties": {
    "iso:country":"CH",
    "sg:address":"Hauptstrasse 17",
    "sg:city":"Sch\u00fcpfheim",
    "sg:orig_category":"Detailhandel mit Milcherzeugnissen U Eiern Verarbeitung von Milch",
    "sg:phone":"+41 41 484 21 41",
    "sg:postcode":"6170",
    "sg:province":"Luzern",
    "wof:name":"Fredy Studer K\u00e4serei",
    "wof:placetype":"venue"
},
  "geometry": {"coordinates":[8.0177736282,46.9520530701],"type":"Point"}
}