{
  "type": "Feature",
  "properties": {
    "iso:country":"CH",
    "sg:address":"M\u00e4rzenb\u00fchlstrasse 9",
    "sg:city":"Oberengstringen",
    "sg:orig_category":"Hoch U Tiefbau",
    "sg:phone":"+41 17501325",
    "sg:postcode":"8102",
    "sg:province":"Z\u00fcrich",
    "wof:name":"Vinzenz Keusch Bauunternehmung",
    "wof:placetype":"venue"
},
  "geometry": {"coordinates":[8.4574222565,47.4116439819],"type":"Point"}
}