{
  "type": "Feature",
  "properties": {
    "iso:country":"CH",
    "sg:address":"Herreng\u00e4ssli 4",
    "sg:city":"Aesch",
    "sg:orig_category":"Herstellung von industriellen Prozesssteuerungsanlagen",
    "sg:phone":"+41 17370831",
    "sg:postcode":"8904",
    "sg:province":"Z\u00fcrich",
    "wof:name":"Pivonka-binder",
    "wof:placetype":"venue"
},
  "geometry": {"coordinates":[8.4394407272,47.336391449],"type":"Point"}
}