{
  "type": "Feature",
  "properties": {
    "iso:country":"CH",
    "sg:address":"Hauptstrasse 53 6034 Inwil. Postfach",
    "sg:city":"Inwil",
    "sg:orig_category":"Erbringung von sonstigen Dienstleistungen f\u00fcr Unterhaltung, Erholung U Freizeit",
    "sg:postcode":"6034",
    "sg:province":"Luzern",
    "wof:name":"Walther E. Gmbh Hundesportartikel",
    "wof:placetype":"venue"
},
  "geometry": {"coordinates":[8.3553514481,47.1230163574],"type":"Point"}
}