{
  "type": "Feature",
  "properties": {
    "iso:country":"CH",
    "sg:address":"Ottenbacherstrasse 15-17",
    "sg:city":"Zwillikon",
    "sg:orig_category":"Interessenvertretungen Psychotherapie",
    "sg:phone":"+41 19141040",
    "sg:postcode":"8909",
    "sg:province":"Z\u00fcrich",
    "wof:name":"Jung C.g.-institut Z\u00fcrich",
    "wof:placetype":"venue"
},
  "geometry": {"coordinates":[8.5791187286,47.3156242371],"type":"Point"}
}