{
  "type": "Feature",
  "properties": {
    "iso:country":"CH",
    "sg:address":"2736",
    "sg:city":"Sorvilier",
    "sg:orig_category":"Zimmerei, Dachdeckerei, Bauspenglerei U Abdichtung",
    "sg:phone":"+41 71 931 10 16",
    "sg:postcode":"2736",
    "sg:province":"Bern",
    "wof:name":"Fehr Arnold Ag",
    "wof:placetype":"venue"
},
  "geometry": {"coordinates":[9.0621261597,47.4213905334],"type":"Point"}
}