{
  "type": "Feature",
  "properties": {
    "iso:country":"CH",
    "sg:address":"Kirchlindachstrasse 16b",
    "sg:city":"M\u00fcnchenbuchsee",
    "sg:orig_category":"Aktivit\u00e4ten der Generalunternehmen im Baugewerbe Architektur U Ingenieurb\u00fcros",
    "sg:phone":"+41 31 869 65 35",
    "sg:postcode":"3053",
    "sg:province":"Bern",
    "wof:name":"B\u00e4rtschi Christian Ag",
    "wof:placetype":"venue"
},
  "geometry": {"coordinates":[7.441879,47.018631],"type":"Point"}
}