{
  "type": "Feature",
  "properties": {
    "iso:country":"CH",
    "sg:address":"Bodenacherstr. 4b 8117 F\u00e4llanden. Postfach",
    "sg:city":"Benglen",
    "sg:orig_category":"Reiseb\u00fcros U Reiseveranstalter",
    "sg:postcode":"8121",
    "sg:province":"Z\u00fcrich",
    "wof:name":"Bahia Tours Amstalden + Amstalden",
    "wof:placetype":"venue"
},
  "geometry": {"coordinates":[8.6305551529,47.3615226746],"type":"Point"}
}