{
  "type": "Feature",
  "properties": {
    "iso:country":"CH",
    "sg:address":"Route De Malagnou 38",
    "sg:city":"Gen\u00e8ve",
    "sg:orig_category":"Grosshandel mit Kaffee, Tee, Kakao U Gew\u00fcrzen Sonstiger Grosshandel",
    "sg:phone":"+41 22 707 06 66",
    "sg:postcode":"1208",
    "sg:province":"Gen\u00e8ve",
    "wof:name":"Socadec Sa",
    "wof:placetype":"venue"
},
  "geometry": {"coordinates":[6.1608920097,46.1974372864],"type":"Point"}
}