{
  "type": "Feature",
  "properties": {
    "iso:country":"CH",
    "sg:address":"Rue Du Coq-d'inde 1",
    "sg:city":"Neuch\u00e2tel",
    "sg:orig_category":"Herstellung von Teigwaren Herstellung von sonstigen Nahrungsmitteln",
    "sg:postcode":"2000",
    "sg:province":"Neuch\u00e2tel",
    "wof:name":"Di Marco Gaetano.",
    "wof:placetype":"venue"
},
  "geometry": {"coordinates":[6.9279389381,46.9907112122],"type":"Point"}
}