{
  "type": "Feature",
  "properties": {
    "iso:country":"CH",
    "sg:address":"Bahnhofstrasse 13",
    "sg:city":"Oberr\u00fcti",
    "sg:orig_category":"Abwasserreinigung, Abfallbeseitigung U sonstige Entsorgung R\u00fcckgewinnung U Vorbereitung f\u00fcr die Wied",
    "sg:phone":"+41 41 787 05 50",
    "sg:postcode":"5647",
    "sg:province":"Aargau",
    "wof:name":"Hodel Entsorgungs Ag",
    "wof:placetype":"venue"
},
  "geometry": {"coordinates":[8.402631,47.167744],"type":"Point"}
}