{
  "type": "Feature",
  "properties": {
    "iso:country":"CH",
    "sg:address":"R\u00fctligasse 1 6003 Luzern. Postfach",
    "sg:city":"Luzern",
    "sg:orig_category":"Grosshandel mit Getr\u00e4nken",
    "sg:phone":"+41 41 240 07 78",
    "sg:postcode":"6003",
    "sg:province":"Luzern",
    "wof:name":"Schuler & Cie Ag Luzern",
    "wof:placetype":"venue"
},
  "geometry": {"coordinates":[8.3025865555,47.0501480103],"type":"Point"}
}