{
  "type": "Feature",
  "properties": {
    "iso:country":"CH",
    "sg:address":"Geissholz.",
    "sg:city":"Innertkirchen",
    "sg:orig_category":"S\u00e4ge, Hobel U Holzimpr\u00e4gnierwerke",
    "sg:postcode":"3862",
    "sg:province":"Bern",
    "wof:name":"Leuthold Max, S\u00e4gerei Und Holzhandel.",
    "wof:placetype":"venue"
},
  "geometry": {"coordinates":[8.2280960083,46.7054328918],"type":"Point"}
}