{
  "type": "Feature",
  "properties": {
    "iso:country":"CH",
    "sg:address":"Webergutstrasse 14",
    "sg:city":"Zollikofen",
    "sg:orig_category":"Innenausbau",
    "sg:phone":"+41 31 911 55 01",
    "sg:postcode":"3052",
    "sg:province":"Bern",
    "wof:name":"Spiller Ag",
    "wof:placetype":"venue"
},
  "geometry": {"coordinates":[7.4407119751,47.0027961731],"type":"Point"}
}