{
  "type": "Feature",
  "properties": {
    "addr:full":"G\u00e4uggelistrasse 2 Chur Graubunden 7000",
    "addr:housenumber":"2",
    "addr:postcode":"7000",
    "addr:street":"Gaeuggelistrasse",
    "iso:country":"CH",
    "sg:address":"G\u00e4uggelistrasse 2",
    "sg:city":"Chur",
    "sg:orig_category":"Arbeitnehmerverb\u00e4nde",
    "sg:phone":"+41 81 252 32 23",
    "sg:postcode":"7000",
    "sg:province":"Graubunden",
    "wof:name":"Gewerkschaft Bau & Industrie Sektion Graub\u00fcnden",
    "wof:placetype":"venue"
},
  "geometry": {"coordinates":[9.531432,46.850857],"type":"Point"}
}