{
  "type": "Feature",
  "properties": {
    "iso:country":"CH",
    "sg:address":"Bucheggstrasse 144",
    "sg:city":"Z\u00fcrich",
    "sg:orig_category":"Herstellung von Kunststoffwaren Herstellung von Metallerzeugnissen ohne Maschinenbau",
    "sg:phone":"+41 13616383",
    "sg:postcode":"8057",
    "sg:province":"Z\u00fcrich",
    "wof:name":"Torson Kunststofftechnik Ag",
    "wof:placetype":"venue"
},
  "geometry": {"coordinates":[8.5393600464,47.3985404968],"type":"Point"}
}