{
  "type": "Feature",
  "properties": {
    "iso:country":"CH",
    "sg:address":"Via Car\u00e0 21",
    "sg:city":"Breganzona",
    "sg:orig_category":"Non-Classified Establishments",
    "sg:postcode":"6932",
    "sg:province":"Ticino",
    "wof:name":"Ananda Film Di Tognola Jerko Victor",
    "wof:placetype":"venue"
},
  "geometry": {"coordinates":[8.922703743,46.0050888062],"type":"Point"}
}