{
  "type": "Feature",
  "properties": {
    "addr:full":"Felsenstrasse 88 St.gallen St. Gallen 9000",
    "addr:housenumber":"88",
    "addr:postcode":"9000",
    "addr:street":"Felsenstrasse",
    "iso:country":"CH",
    "sg:address":"Felsenstrasse 88",
    "sg:city":"St.gallen",
    "sg:orig_category":"Datenverarbeitungsdienste Druckweiterverarbeitung",
    "sg:phone":"+41 56 493 04 82",
    "sg:postcode":"9000",
    "sg:province":"St. Gallen",
    "wof:name":"Creative Application Pool Ag",
    "wof:placetype":"venue"
},
  "geometry": {"coordinates":[8.295399,47.446548],"type":"Point"}
}