{
  "type": "Feature",
  "properties": {
    "iso:country":"CH",
    "sg:address":"Markgr\u00e4flerstrasse 35",
    "sg:city":"Basel",
    "sg:orig_category":"Betrieb von Taxis",
    "sg:phone":"+41 61 691 04 81",
    "sg:postcode":"4057",
    "sg:province":"Basel-Stadt",
    "wof:name":"G\u00f6k Unternehmungen Gmbh",
    "wof:placetype":"venue"
},
  "geometry": {"coordinates":[7.592796,47.570168],"type":"Point"}
}