{
  "type": "Feature",
  "properties": {
    "iso:country":"CH",
    "sg:address":"Industriestrasse 59 8152 Glattbrugg. Postfach",
    "sg:city":"Horgen",
    "sg:orig_category":"Herstellung von \u00d6fen U Brennern",
    "sg:phone":"+41 17279188",
    "sg:postcode":"8810",
    "sg:province":"Z\u00fcrich",
    "wof:name":"Elcotherm Alt Ag Produkte Der W\u00e4rmeerzeugung, Bes. \u00d6l, Gasbrenner, Elektroheizungen Usw.; Vertrieb, Unterhalt",
    "wof:placetype":"venue"
},
  "geometry": {"coordinates":[8.5569200516,47.430480957],"type":"Point"}
}