{
  "type": "Feature",
  "properties": {
    "iso:country":"CH",
    "sg:address":"Via S. Gottardo",
    "sg:city":"Bellinzona",
    "sg:orig_category":"Handel mit Automobilen",
    "sg:postcode":"6500",
    "sg:province":"Ticino",
    "wof:name":"Deprati Bixio",
    "wof:placetype":"venue"
},
  "geometry": {"coordinates":[9.038359642,46.2081336975],"type":"Point"}
}