{
  "type": "Feature",
  "properties": {
    "iso:country":"CH",
    "sg:address":"Oggio",
    "sg:city":"Lopagno",
    "sg:orig_category":"Herstellung von Konstruktionsteilen, Fertigbauteilen U Ausbauelementen aus Holz",
    "sg:postcode":"6956",
    "sg:province":"Ticino",
    "wof:name":"Falegnameria Brioschi Claudio Sagl",
    "wof:placetype":"venue"
},
  "geometry": {"coordinates":[8.9768981934,46.0688018799],"type":"Point"}
}