{
  "type": "Feature",
  "properties": {
    "iso:country":"CH",
    "sg:address":"Frenkend\u00f6rferstrasse 10",
    "sg:city":"Liestal",
    "sg:orig_category":"Herstellung von sonstigen Metallwaren",
    "sg:phone":"+41 61 901 87 77",
    "sg:postcode":"4410",
    "sg:province":"Basel-Landschaft",
    "wof:name":"Reto Scheidegger Kleinschilder & Gravuren",
    "wof:placetype":"venue"
},
  "geometry": {"coordinates":[7.7225990295,47.4955863953],"type":"Point"}
}