{
  "type": "Feature",
  "properties": {
    "addr:full":"Allmend 4938 Rohrbach. Postfach 11 Rohrbach Bern 4938",
    "addr:housenumber":"11",
    "addr:postcode":"4938;4938",
    "addr:street":"Postfach",
    "iso:country":"CH",
    "sg:address":"Allmend 4938 Rohrbach. Postfach 11",
    "sg:city":"Rohrbach",
    "sg:orig_category":"Bau von Strassen, Sportanlagen U Bahnverkehrsstrecken Herstellung von k\u00e4lte U lufttechnischen Erzeug",
    "sg:phone":"+41 62 961 87 69",
    "sg:postcode":"4938",
    "sg:province":"Bern",
    "wof:name":"Servicetech Gmbh",
    "wof:placetype":"venue"
},
  "geometry": {"coordinates":[7.698985,47.208576],"type":"Point"}
}