{
  "type": "Feature",
  "properties": {
    "iso:country":"CH",
    "sg:address":"Hinterwies 58",
    "sg:city":"Speicher",
    "sg:orig_category":"Institutionen f\u00fcr Finanzierungsleasing",
    "sg:phone":"+41 71 344 20 71",
    "sg:postcode":"9042",
    "sg:province":"Appenzell Ausserrhoden",
    "wof:name":"Rema Finanz Ag",
    "wof:placetype":"venue"
},
  "geometry": {"coordinates":[9.4367036819,47.4173698425],"type":"Point"}
}