{
  "type": "Feature",
  "properties": {
    "iso:country":"CH",
    "sg:address":"Birchweg 17",
    "sg:city":"Seuzach",
    "sg:orig_category":"Datenverarbeitungsdienste Webdesign",
    "sg:phone":"+41 52 338 07 07",
    "sg:postcode":"8472",
    "sg:province":"Z\u00fcrich",
    "wof:name":"Espritnet Gmbh",
    "wof:placetype":"venue"
},
  "geometry": {"coordinates":[8.732717,47.532219],"type":"Point"}
}