{
  "type": "Feature",
  "properties": {
    "iso:country":"CH",
    "sg:address":"Poststrasse 35",
    "sg:city":"Seengen",
    "sg:orig_category":"Detailhandel mit Lederwaren U Reiseartikeln Detailhandel mit Schuhen U Lederwaren",
    "sg:postcode":"5707",
    "sg:province":"Aargau",
    "wof:name":"Martin Dubs",
    "wof:placetype":"venue"
},
  "geometry": {"coordinates":[8.2075967789,47.3234214783],"type":"Point"}
}