{
  "type": "Feature",
  "properties": {
    "iso:country":"CH",
    "sg:address":"Hauptgasse 72",
    "sg:city":"Solothurn",
    "sg:orig_category":"Veterin\u00e4r\u00e4mter",
    "sg:phone":"+41 32 627 25 27",
    "sg:postcode":"4500",
    "sg:province":"Solothurn",
    "wof:name":"Kantonales Veterin\u00e4ramt",
    "wof:placetype":"venue"
},
  "geometry": {"coordinates":[7.5399198532,47.208820343],"type":"Point"}
}