{
  "type": "Feature",
  "properties": {
    "iso:country":"CH",
    "sg:address":"Kirchmattweg 8",
    "sg:city":"Oberburg",
    "sg:orig_category":"Unternehmensberatung",
    "sg:phone":"+41 34 422 12 77",
    "sg:postcode":"3414",
    "sg:province":"Bern",
    "wof:name":"Lutz Rudolf, Oberburg",
    "wof:placetype":"venue"
},
  "geometry": {"coordinates":[7.6218972206,47.0391540527],"type":"Point"}
}