{
  "type": "Feature",
  "properties": {
    "iso:country":"CH",
    "sg:address":"Costa Di Mezzo Via 40",
    "sg:city":"Brissago",
    "sg:orig_category":"Sanit\u00e4r, Heizungs U L\u00fcftungsinstallation",
    "sg:postcode":"6614",
    "sg:province":"Ticino",
    "wof:name":"Baccal\u00e0 Igor Sagl",
    "wof:placetype":"venue"
},
  "geometry": {"coordinates":[8.7058401108,46.1189956665],"type":"Point"}
}