{
  "type": "Feature",
  "properties": {
    "iso:country":"CH",
    "sg:address":"Sandgrubenstrasse 3 8400 Winterthur. Postfach 52",
    "sg:city":"Stadel(winterthur)",
    "sg:orig_category":"Grosshandel mit Fleisch U Fleischwaren Sonstiger Grosshandel",
    "sg:phone":"+41 52 242 20 00",
    "sg:postcode":"8404",
    "sg:province":"Z\u00fcrich",
    "wof:name":"Mastai Ag",
    "wof:placetype":"venue"
},
  "geometry": {"coordinates":[8.7728099823,47.5035896301],"type":"Point"}
}