{
  "type": "Feature",
  "properties": {
    "iso:country":"CH",
    "sg:address":"Lindenstrasse 4a 8483 Kollbrunn. Postfach 56",
    "sg:city":"Kollbrunn",
    "sg:orig_category":"Wirtschaftspr\u00fcfung, Steuerberatung U Treuhand",
    "sg:phone":"+41 55 460 21 87",
    "sg:postcode":"8483",
    "sg:province":"Z\u00fcrich",
    "wof:name":"H\u00fcrlimann Walter J. Lic.oec.publ. Steuerberatungspraxis",
    "wof:placetype":"venue"
},
  "geometry": {"coordinates":[8.8962049484,47.1908302307],"type":"Point"}
}