{
  "type": "Feature",
  "properties": {
    "iso:country":"CH",
    "sg:address":"Zollstrasse 284",
    "sg:city":"Trasadingen",
    "sg:orig_category":"Grosshandel mit Textilien",
    "sg:phone":"+41 52 681 40 23",
    "sg:postcode":"8219",
    "sg:province":"Schaffhausen",
    "wof:name":"Blanca Style Ag, Zweigniederlassung Trasadingen",
    "wof:placetype":"venue"
},
  "geometry": {"coordinates":[8.4345407486,47.6644134521],"type":"Point"}
}