{
  "type": "Feature",
  "properties": {
    "iso:country":"CH",
    "sg:address":"Sternengasse 4 4051 Basel. Postfach",
    "sg:city":"Basel",
    "sg:orig_category":"Unclassifiable Establishments",
    "sg:phone":"+41 61 272 14 29",
    "sg:postcode":"4051",
    "sg:province":"Basel-Stadt",
    "wof:name":"Thordsen-pictura Verlag Ag",
    "wof:placetype":"venue"
},
  "geometry": {"coordinates":[7.5931172371,47.55235672],"type":"Point"}
}