{
  "type": "Feature",
  "properties": {
    "iso:country":"CH",
    "sg:address":"Casa Nitscholas 7019 Fidaz. Postfach",
    "sg:city":"Fidaz",
    "sg:orig_category":"Verwaltung von Immobilien",
    "sg:postcode":"7019",
    "sg:province":"Graubunden",
    "wof:name":"Immobilien Fontana Ag",
    "wof:placetype":"venue"
},
  "geometry": {"coordinates":[9.2685451508,46.846282959],"type":"Point"}
}