{
  "type": "Feature",
  "properties": {
    "iso:country":"CH",
    "sg:address":"Avenue Du Village 4 1277 Borex Case Postale 167",
    "sg:city":"Borex",
    "sg:orig_category":"Elektroinstallation",
    "sg:phone":"+41 22 367 11 40",
    "sg:postcode":"1277",
    "sg:province":"Vaud",
    "wof:name":"Philipona Sa",
    "wof:placetype":"venue"
},
  "geometry": {"coordinates":[6.1777329445,46.3789024353],"type":"Point"}
}