{
  "type": "Feature",
  "properties": {
    "iso:country":"CH",
    "sg:address":"Rue Des Terreaux 28 1350 Orbe. Postfach",
    "sg:city":"Orbe",
    "sg:orig_category":"Architektur U Ingenieurb\u00fcros",
    "sg:postcode":"1350",
    "sg:province":"Vaud",
    "wof:name":"Atelier D'architecture Duvillard P. Sa, Succursale D'orbe",
    "wof:placetype":"venue"
},
  "geometry": {"coordinates":[6.53106,46.724354],"type":"Point"}
}