{
  "type": "Feature",
  "properties": {
    "iso:country":"CH",
    "sg:address":"Tellstrasse 21",
    "sg:city":"St.gallen",
    "sg:orig_category":"Finanzierungsinstitutionen",
    "sg:phone":"+41 71 223 63 07",
    "sg:postcode":"9000",
    "sg:province":"St. Gallen",
    "wof:name":"Sch\u00fcrch Asset Management Gmbh",
    "wof:placetype":"venue"
},
  "geometry": {"coordinates":[9.3678359985,47.4242591858],"type":"Point"}
}