{
  "type": "Feature",
  "properties": {
    "iso:country":"CH",
    "sg:address":"Rue De L'industrie 17",
    "sg:city":"Yverdon-les-bains",
    "sg:orig_category":"Instandhaltung U Reparatur von Automobilen",
    "sg:phone":"+41 24 426 03 00",
    "sg:postcode":"1400",
    "sg:province":"Vaud",
    "wof:name":"Garage Pietro Barra",
    "wof:placetype":"venue"
},
  "geometry": {"coordinates":[6.6494941711,46.7809295654],"type":"Point"}
}