{
  "type": "Feature",
  "properties": {
    "iso:country":"CH",
    "sg:address":"Schachenweidstrasse 22",
    "sg:city":"Ebikon",
    "sg:orig_category":"Hoch U Tiefbau",
    "sg:phone":"+41 41 440 76 76",
    "sg:postcode":"6030",
    "sg:province":"Luzern",
    "wof:name":"Ernst Bachmann Baugesch\u00e4ft",
    "wof:placetype":"venue"
},
  "geometry": {"coordinates":[8.3350057602,47.0761833191],"type":"Point"}
}