{
  "type": "Feature",
  "properties": {
    "iso:country":"CH",
    "sg:address":"Hauptstrasse 106",
    "sg:city":"Ermatingen",
    "sg:orig_category":"Elektroinstallation",
    "sg:phone":"+41 71 664 28 88",
    "sg:postcode":"8272",
    "sg:province":"Thurgau",
    "wof:name":"Rae Regionalantenne Ermatingen Ag",
    "wof:placetype":"venue"
},
  "geometry": {"coordinates":[9.0826225281,47.6692810059],"type":"Point"}
}