{
  "type": "Feature",
  "properties": {
    "iso:country":"CH",
    "sg:address":"Z\u00fcrcherstrasse 237 8953 Dietikon. Postfach",
    "sg:city":"Dietikon",
    "sg:orig_category":"Fussboden, Fliesen U Plattenlegerei, Tapeziererei",
    "sg:postcode":"8953",
    "sg:province":"Z\u00fcrich",
    "wof:name":"Hani Plattenleger",
    "wof:placetype":"venue"
},
  "geometry": {"coordinates":[8.4283599854,47.3972969055],"type":"Point"}
}