{
  "type": "Feature",
  "properties": {
    "iso:country":"CH",
    "sg:address":"Werkstrasse 2",
    "sg:city":"Chur",
    "sg:orig_category":"Unclassifiable Establishments",
    "sg:postcode":"7000",
    "sg:province":"Graubunden",
    "wof:name":"Calandela Finanz Ag",
    "wof:placetype":"venue"
},
  "geometry": {"coordinates":[9.5267877579,46.856010437],"type":"Point"}
}