{
  "type": "Feature",
  "properties": {
    "iso:country":"CH",
    "sg:address":"M\u00e9di\u00e8res",
    "sg:city":"Verbier",
    "sg:orig_category":"Elektroinstallation",
    "sg:phone":"+41 27 771 27 49",
    "sg:postcode":"1936",
    "sg:province":"Valais",
    "wof:name":"Jean-pierre Corthay Entreprise \u00e9lectrique",
    "wof:placetype":"venue"
},
  "geometry": {"coordinates":[7.2304577827,46.0942764282],"type":"Point"}
}