{
  "type": "Feature",
  "properties": {
    "iso:country":"CH",
    "sg:address":"Paradiesstrasse 52",
    "sg:city":"Z\u00fcrich",
    "sg:orig_category":"Sportvereine Turnen Damen",
    "sg:postcode":"8038",
    "sg:province":"Z\u00fcrich",
    "wof:name":"Frauenriege Tv Wollishofen",
    "wof:placetype":"venue"
},
  "geometry": {"coordinates":[8.5259599686,47.3352813721],"type":"Point"}
}