{
  "type": "Feature",
  "properties": {
    "addr:full":"Luzernerstrasse 9a 6010 Kriens. Postfach Kriens Luzern 6010",
    "addr:housenumber":"9a",
    "addr:postcode":"6010 kriens. postfach;6010",
    "addr:street":"Luzernerstrasse",
    "iso:country":"CH",
    "sg:address":"Luzernerstrasse 9a 6010 Kriens. Postfach",
    "sg:city":"Kriens",
    "sg:orig_category":"Detailhandel mit B\u00fcchern, Zeitungen, Schreib U Papeteriewaren",
    "sg:postcode":"6010",
    "sg:province":"Luzern",
    "wof:name":"Id\u00e9e Livre, Staffelbach Buchhandlung Am Lindenplatz",
    "wof:placetype":"venue"
},
  "geometry": {"coordinates":[8.279038,47.033909],"type":"Point"}
}