{
  "type": "Feature",
  "properties": {
    "iso:country":"CH",
    "sg:address":"Oltenstrasse 31 4702 Oensingen. Postfach",
    "sg:city":"Oensingen",
    "sg:orig_category":"Allgemeiner Hoch U Tiefbau Allgemeiner Hochbau",
    "sg:phone":"+41 62 386 60 30",
    "sg:postcode":"4702",
    "sg:province":"Solothurn",
    "wof:name":"Meier + J\u00e4ggi Ag Balsthal",
    "wof:placetype":"venue"
},
  "geometry": {"coordinates":[7.729232,47.290722],"type":"Point"}
}