{
  "type": "Feature",
  "properties": {
    "iso:country":"CH",
    "sg:address":"Jurastrasse 20 4600 Olten. Postfach",
    "sg:city":"Olten",
    "sg:orig_category":"Unclassifiable Establishments",
    "sg:phone":"+41 62 213 95 90",
    "sg:postcode":"4603",
    "sg:province":"Solothurn",
    "wof:name":"Rolf B\u00fcttiker Wirtschaftsf\u00f6rderung",
    "wof:placetype":"venue"
},
  "geometry": {"coordinates":[7.9030690193,47.3530158997],"type":"Point"}
}