{
  "type": "Feature",
  "properties": {
    "iso:country":"CH",
    "sg:address":"Grand Rue 10",
    "sg:city":"Montreux",
    "sg:orig_category":"Detailhandel mit Sportartikeln Fachdetailhandel in Verkaufsr\u00e4umen",
    "sg:phone":"+41 71 744 02 74",
    "sg:postcode":"1820",
    "sg:province":"Vaud",
    "wof:name":"Uhlsport Redler Ag",
    "wof:placetype":"venue"
},
  "geometry": {"coordinates":[9.6401844025,47.4348678589],"type":"Point"}
}