{
  "type": "Feature",
  "properties": {
    "iso:country":"CH",
    "sg:address":"Ziegelh\u00fctte 6",
    "sg:city":"B\u00fclach",
    "sg:orig_category":"Maler U Glasergewerbe Malerei",
    "sg:phone":"+41 18603934",
    "sg:postcode":"8180",
    "sg:province":"Z\u00fcrich",
    "wof:name":"Zimmermann E.",
    "wof:placetype":"venue"
},
  "geometry": {"coordinates":[8.5302934647,47.5138320923],"type":"Point"}
}