{
  "type": "Feature",
  "properties": {
    "iso:country":"CH",
    "sg:address":"Brahmsstrasse 71 8003 Z\u00fcrich. Postfach",
    "sg:city":"Z\u00fcrich",
    "sg:orig_category":"Fotografische Ateliers",
    "sg:phone":"+41 14013559",
    "sg:postcode":"8040",
    "sg:province":"Z\u00fcrich",
    "wof:name":"Photo Forum Z\u00fcrich Susanne Abelin",
    "wof:placetype":"venue"
},
  "geometry": {"coordinates":[8.5039482117,47.3784294128],"type":"Point"}
}