{
  "type": "Feature",
  "properties": {
    "iso:country":"CH",
    "sg:address":"Rue Des Eussinges 10",
    "sg:city":"Ligni\u00e8res",
    "sg:orig_category":"Campingpl\u00e4tze",
    "sg:postcode":"2523",
    "sg:province":"Neuch\u00e2tel",
    "wof:name":"Fraso-ranch, Philippe Et Sylvie Geiser",
    "wof:placetype":"venue"
},
  "geometry": {"coordinates":[7.063886,47.083672],"type":"Point"}
}