{
  "type": "Feature",
  "properties": {
    "iso:country":"CH",
    "sg:address":"Quadergasse 8",
    "sg:city":"Untervaz",
    "sg:orig_category":"Detailhandel mit Waren verschiedener Art, Hauptrichtung Nahrungsmittel",
    "sg:phone":"+41 81 322 14 72",
    "sg:postcode":"7204",
    "sg:province":"Graubunden",
    "wof:name":"Lkg Untervaz",
    "wof:placetype":"venue"
},
  "geometry": {"coordinates":[9.5361785889,46.9279670715],"type":"Point"}
}