{
  "type": "Feature",
  "properties": {
    "iso:country":"CH",
    "sg:address":"Route De L'abbaye 1138 Villars-sous-yens. Postfach",
    "sg:city":"Villars-sous-yens",
    "sg:orig_category":"Fachdetailhandel in Verkaufsr\u00e4umen",
    "sg:postcode":"1138",
    "wof:name":"X-sion Gmbh Sportgesch\u00e4ft. Sport, Freizeitmode Usw.; Handel, Herstellung, Vertrieb",
    "wof:placetype":"venue"
},
  "geometry": {"coordinates":[8.7341480255,47.1973953247],"type":"Point"}
}