{
  "type": "Feature",
  "properties": {
    "iso:country":"CH",
    "sg:address":"Industrie Rue De L' 45 1630 Bulle. Postfach",
    "sg:city":"Bulle",
    "sg:orig_category":"Vermietung U Verpachtung von eigenen Immobilien",
    "sg:postcode":"1630",
    "sg:province":"Fribourg",
    "wof:name":"Mariso Bulle Sa",
    "wof:placetype":"venue"
},
  "geometry": {"coordinates":[7.0335249901,46.6226463318],"type":"Point"}
}