{
  "type": "Feature",
  "properties": {
    "iso:country":"CH",
    "sg:address":"Wiesenstrasse 13",
    "sg:city":"Rorschacherberg",
    "sg:orig_category":"Sportvereine Boccia",
    "sg:phone":"+41 71 855 52 98",
    "sg:postcode":"9404",
    "sg:province":"St. Gallen",
    "wof:name":"Boccia-club Feldm\u00fchle-primavera",
    "wof:placetype":"venue"
},
  "geometry": {"coordinates":[9.4866914749,47.4728889465],"type":"Point"}
}