{
  "type": "Feature",
  "properties": {
    "iso:country":"CH",
    "sg:address":"Route Des Abbesses 26",
    "sg:city":"Echandens",
    "sg:orig_category":"Detailhandel mit Getr\u00e4nken",
    "sg:phone":"+41 21 701 16 29",
    "sg:postcode":"1026",
    "sg:province":"Vaud",
    "wof:name":"Cave Panchaud Dominique Tavel",
    "wof:placetype":"venue"
},
  "geometry": {"coordinates":[6.5324239731,46.5317687988],"type":"Point"}
}