{
  "type": "Feature",
  "properties": {
    "iso:country":"CH",
    "sg:address":"Gasthaus Alpenrose",
    "sg:city":"Innerferrera",
    "sg:orig_category":"RESTAURANTS: TEA-ROOMS",
    "sg:phone":"+41 55 280 50 35",
    "sg:postcode":"7445",
    "sg:province":"Graubunden",
    "wof:name":"Seibel Hans-dieter Und Antoinette",
    "wof:placetype":"venue"
},
  "geometry": {"coordinates":[9.4429368973,46.5210533142],"type":"Point"}
}