{
  "type": "Feature",
  "properties": {
    "addr:full":"Rue Des Mu\u00ebses 2 Matran Fribourg 1753",
    "addr:housenumber":"2",
    "addr:postcode":"1753",
    "addr:street":"Rue Des Mue\u0308Ses",
    "iso:country":"CH",
    "sg:address":"Rue Des Mu\u00ebses 2",
    "sg:city":"Matran",
    "sg:orig_category":"Architektur U Ingenieurb\u00fcros",
    "sg:phone":"+41 26 401 02 51",
    "sg:postcode":"1753",
    "sg:province":"Fribourg",
    "wof:name":"Kleinerpreis Bei Grossglauser S\u00e0rl",
    "wof:placetype":"venue"
},
  "geometry": {"coordinates":[7.098644,46.782646],"type":"Point"}
}