{
  "type": "Feature",
  "properties": {
    "iso:country":"CH",
    "sg:address":"Via Al Chiosso 6",
    "sg:city":"Porza",
    "sg:orig_category":"G\u00fcterbef\u00f6rderung im Strassenverkehr",
    "sg:phone":"+41 91 942 41 08",
    "sg:postcode":"6948",
    "sg:province":"Ticino",
    "wof:name":"Mario Giudici Traslochi & Trasporti",
    "wof:placetype":"venue"
},
  "geometry": {"coordinates":[8.963973999,46.0270042419],"type":"Point"}
}