{
  "type": "Feature",
  "properties": {
    "iso:country":"CH",
    "sg:address":"C\u00e4cilienstrasse 21",
    "sg:city":"Bern",
    "sg:orig_category":"Erbringung von Dienstleistungen f\u00fcr Unternehmen Grafikateliers, Design",
    "sg:phone":"+41 31 372 33 30",
    "sg:postcode":"3007",
    "sg:province":"Bern",
    "wof:name":"Reklame-siegenthaler Ag",
    "wof:placetype":"venue"
},
  "geometry": {"coordinates":[7.4276227951,46.9408493042],"type":"Point"}
}