{
  "type": "Feature",
  "properties": {
    "iso:country":"CH",
    "sg:address":"Schaffhauserstrasse 272 8057 Z\u00fcrich. Postfach",
    "sg:city":"Z\u00fcrich",
    "sg:orig_category":"Architektur U Ingenieurb\u00fcros",
    "sg:postcode":"8057",
    "sg:province":"Z\u00fcrich",
    "wof:name":"Wigant Peter Bauberatungen",
    "wof:placetype":"venue"
},
  "geometry": {"coordinates":[8.52972,47.253036],"type":"Point"}
}