{
  "type": "Feature",
  "properties": {
    "iso:country":"CH",
    "sg:address":"Sch\u00f6neggstrasse 6",
    "sg:city":"Horw",
    "sg:orig_category":"Zahnarztpraxen",
    "sg:phone":"+41 41 340 11 61",
    "sg:postcode":"6048",
    "sg:province":"Luzern",
    "wof:name":"Dr.med.dent.ljubisa Ivanovic Zahnarzt",
    "wof:placetype":"venue"
},
  "geometry": {"coordinates":[8.3104705811,47.0219535828],"type":"Point"}
}