{
  "type": "Feature",
  "properties": {
    "iso:country":"CH",
    "sg:address":"Chevillarde Chemin De La 40 1208 Gen\u00e8ve. Postfach",
    "sg:city":"Gen\u00e8ve",
    "sg:orig_category":"Herstellung von Metallkonstruktionen",
    "sg:phone":"+41 55317476",
    "sg:postcode":"1208",
    "sg:province":"Gen\u00e8ve",
    "wof:name":"Alusett Ag",
    "wof:placetype":"venue"
},
  "geometry": {"coordinates":[8.7827978134,47.1985473633],"type":"Point"}
}