{
  "type": "Feature",
  "properties": {
    "iso:country":"CH",
    "sg:address":"Leonhardstrasse 6",
    "sg:city":"Z\u00fcrich",
    "sg:orig_category":"HOTELS: OHNE RESTAURANT",
    "sg:phone":"+41 12665959",
    "sg:postcode":"8001",
    "sg:province":"Z\u00fcrich",
    "wof:name":"Hotel Arc Royal Comfort Inn",
    "wof:placetype":"venue"
},
  "geometry": {"coordinates":[8.5450296402,47.3788909912],"type":"Point"}
}