{
  "type": "Feature",
  "properties": {
    "iso:country":"CH",
    "sg:address":"\u00dcberlandstrasse 101",
    "sg:city":"D\u00fcbendorf",
    "sg:orig_category":"Wirtschaftspr\u00fcfung, Steuerberatung U Treuhand",
    "sg:postcode":"8600",
    "sg:province":"Z\u00fcrich",
    "wof:name":"Vertigo Liegenschaften Ag",
    "wof:placetype":"venue"
},
  "geometry": {"coordinates":[8.607925415,47.403465271],"type":"Point"}
}