{
  "type": "Feature",
  "properties": {
    "iso:country":"CH",
    "sg:address":"Wenkenr\u00fctistrasse 20",
    "sg:city":"Wattwil",
    "sg:orig_category":"Herstellung von \u00d6fen U Brennern Verlegen von Fliesen U Platten",
    "sg:phone":"+41 71 988 37 77",
    "sg:postcode":"9630",
    "sg:province":"St. Gallen",
    "wof:name":"Bl\u00f6chliger Ag",
    "wof:placetype":"venue"
},
  "geometry": {"coordinates":[9.0799741745,47.3066444397],"type":"Point"}
}