{
  "type": "Feature",
  "properties": {
    "iso:country":"CH",
    "sg:address":"Im Sch\u00e4nzli 101",
    "sg:city":"Muttenz",
    "sg:orig_category":"Verlegen von Fliesen U Platten",
    "sg:phone":"+41 55 644 12 34",
    "sg:postcode":"4132",
    "sg:province":"Basel-Landschaft",
    "wof:name":"Hans-peter Guler Hafnerei & Plattengesch\u00e4ft",
    "wof:placetype":"venue"
},
  "geometry": {"coordinates":[9.0653114319,46.9919509888],"type":"Point"}
}