{
  "type": "Feature",
  "properties": {
    "iso:country":"CH",
    "sg:address":"Quai Jeanrenaud 3-5",
    "sg:city":"Neuch\u00e2tel",
    "sg:classifiers":[
        {
            "category":"Shopping",
            "subcategory":"Tobacco",
            "type":"Retail Goods"
        }
    ],
    "sg:phone":"+41 32 888 61 61",
    "sg:postcode":"2000",
    "sg:province":"Neuch\u00e2tel",
    "sg:tags":[
        "cigarette"
    ],
    "wof:name":"Philip Morris Products S.a.",
    "wof:placetype":"venue"
},
  "geometry": {"coordinates":[6.900245,46.980621],"type":"Point"}
}