{
  "type": "Feature",
  "properties": {
    "addr:full":"H\u00f6nggerstrasse 3 Z\u00fcrich Z\u00fcrich 8037",
    "addr:housenumber":"3",
    "addr:postcode":"8037",
    "addr:street":"Hoenggerstrasse",
    "iso:country":"CH",
    "sg:address":"H\u00f6nggerstrasse 3",
    "sg:city":"Z\u00fcrich",
    "sg:classifiers":[
        {
            "category":"Autos & Motor Vehicles",
            "subcategory":"Auto Supplies",
            "type":"Retail Goods"
        }
    ],
    "sg:phone":"+41 12715586",
    "sg:postcode":"8037",
    "sg:province":"Z\u00fcrich",
    "sg:tags":[
        "automobile",
        "accessory"
    ],
    "wof:name":"Iannotta Motorsport Garage Rudwal Ag",
    "wof:placetype":"venue"
},
  "geometry": {"coordinates":[8.527506,47.390491],"type":"Point"}
}