{
  "type": "Feature",
  "properties": {
    "iso:country":"CH",
    "sg:address":"Route Du Nant-d'avril 101",
    "sg:city":"Meyrin",
    "sg:orig_category":"Subtitling For Film And Video Productions",
    "sg:phone":"+41 22 785 55 45",
    "sg:postcode":"1217",
    "sg:province":"Gen\u00e8ve",
    "wof:name":"Titra Film S.a.",
    "wof:placetype":"venue"
},
  "geometry": {"coordinates":[6.07221,46.228439],"type":"Point"}
}