{
  "type": "Feature",
  "properties": {
    "iso:country":"CH",
    "sg:address":"Hauptstrasse 105 5074 Eiken. Postfach 13",
    "sg:city":"Eiken",
    "sg:orig_category":"Herstellung von Metallerzeugnissen ohne Maschinenbau Herstellung von k\u00e4lte U lufttechnischen Erzeugn",
    "sg:phone":"+41 62 871 55 55",
    "sg:postcode":"5074",
    "sg:province":"Aargau",
    "wof:name":"Fea Ag",
    "wof:placetype":"venue"
},
  "geometry": {"coordinates":[7.9953689575,47.52891922],"type":"Point"}
}