{
  "type": "Feature",
  "properties": {
    "iso:country":"CH",
    "sg:address":"Oberdorfstrasse 40",
    "sg:city":"Sch\u00fcpfen",
    "sg:orig_category":"Fotografische Ateliers",
    "sg:phone":"+41 31 879 15 30",
    "sg:postcode":"3054",
    "sg:province":"Bern",
    "wof:name":"Robert & Doris W\u00e4lti Fotografisches Atelier",
    "wof:placetype":"venue"
},
  "geometry": {"coordinates":[7.3759679794,47.0338439941],"type":"Point"}
}