{
  "type": "Feature",
  "properties": {
    "iso:country":"CH",
    "sg:address":"Romanshornerstrasse 90",
    "sg:city":"Kreuzlingen",
    "sg:orig_category":"Detailhandel mit Beleuchtungs U Haushaltsgegenst\u00e4nden Innendekorationsateliers",
    "sg:phone":"+41 71 688 32 12",
    "sg:postcode":"8280",
    "sg:province":"Thurgau",
    "wof:name":"Angelika Hagen Vorh\u00e4nge",
    "wof:placetype":"venue"
},
  "geometry": {"coordinates":[9.19483,47.63961],"type":"Point"}
}