{
  "type": "Feature",
  "properties": {
    "iso:country":"CH",
    "sg:address":"B\u00e4ckerstrasse 34 8004 Z\u00fcrich. Postfach",
    "sg:city":"Z\u00fcrich",
    "sg:orig_category":"Detailhandel mit Herrenbekleidung Sonstiger Grosshandel",
    "sg:phone":"+41 12981020",
    "sg:postcode":"8026",
    "sg:province":"Z\u00fcrich",
    "wof:name":"Imbach's Army And Jeans Shop Ag",
    "wof:placetype":"venue"
},
  "geometry": {"coordinates":[8.5288486481,47.374797821],"type":"Point"}
}