{
  "type": "Feature",
  "properties": {
    "iso:country":"CH",
    "sg:address":"Bahnplatz 9",
    "sg:city":"Rorschach",
    "sg:classifiers":[
        {
            "category":"Personal",
            "subcategory":"Piercing",
            "type":"Services"
        }
    ],
    "sg:phone":"+41 71 845 41 35",
    "sg:postcode":"9400",
    "sg:province":"St. Gallen",
    "sg:tags":[
        "tattoo"
    ],
    "wof:name":"Yvette's Tattoo/piercing",
    "wof:placetype":"venue"
},
  "geometry": {"coordinates":[9.4939146042,47.4783554077],"type":"Point"}
}