{
  "type": "Feature",
  "properties": {
    "iso:country":"CH",
    "sg:address":"Albisstrasse 5",
    "sg:city":"Mettmenstetten",
    "sg:orig_category":"Regionalbanken U Sparkassen",
    "sg:phone":"+41 17670011",
    "sg:postcode":"8932",
    "sg:province":"Z\u00fcrich",
    "wof:name":"Sparcassa 1816",
    "wof:placetype":"venue"
},
  "geometry": {"coordinates":[8.4635400772,47.2437286377],"type":"Point"}
}