{
  "type": "Feature",
  "properties": {
    "iso:country":"CH",
    "sg:address":"Burgiwil",
    "sg:city":"Burgistein",
    "sg:orig_category":"Verwertung von Milch",
    "sg:postcode":"3664",
    "sg:province":"Bern",
    "wof:name":"K\u00e4sereigenossenschaft Busswil B. B\u00fcren",
    "wof:placetype":"venue"
},
  "geometry": {"coordinates":[7.3292989731,47.0991363525],"type":"Point"}
}