{
  "type": "Feature",
  "properties": {
    "iso:country":"CH",
    "sg:address":"Via Livio 8",
    "sg:city":"Chiasso",
    "sg:orig_category":"Autotransporte international",
    "sg:phone":"+41 91 682 43 33",
    "sg:postcode":"6830",
    "sg:province":"Ticino",
    "wof:name":"Hans Krebser Sa Trasporti Internazionali",
    "wof:placetype":"venue"
},
  "geometry": {"coordinates":[9.029176,45.833645],"type":"Point"}
}