{
  "type": "Feature",
  "properties": {
    "iso:country":"CH",
    "sg:address":"Veia Sulada 7",
    "sg:city":"Savognin",
    "sg:orig_category":"Bauingenieurb\u00fcros Hochbau Bauingenieurb\u00fcros allgemein",
    "sg:phone":"+41 81 684 25 55",
    "sg:postcode":"7460",
    "sg:province":"Graubunden",
    "wof:name":"Guido Luzio Ingenieurb\u00fcro",
    "wof:placetype":"venue"
},
  "geometry": {"coordinates":[9.597897,46.59618],"type":"Point"}
}