{
  "type": "Feature",
  "properties": {
    "iso:country":"CH",
    "sg:address":"1669",
    "sg:city":"Albeuve",
    "sg:orig_category":"Darlehenskassen U Raiffeisenbanken",
    "sg:phone":"+41 26 919 61 11",
    "sg:postcode":"1669",
    "sg:province":"Fribourg",
    "wof:name":"Banque Raiffeisen Mol\u00e9son",
    "wof:placetype":"venue"
},
  "geometry": {"coordinates":[7.05588,46.518822],"type":"Point"}
}