{
  "type": "Feature",
  "properties": {
    "iso:country":"CH",
    "sg:address":"Haus Arelia",
    "sg:city":"Gr\u00fcsch",
    "sg:orig_category":"G\u00fcterbef\u00f6rderung im Strassenverkehr",
    "sg:phone":"+41 71 755 21 30",
    "sg:postcode":"7214",
    "sg:province":"Graubunden",
    "wof:name":"Th\u00fcr Transporte Ag",
    "wof:placetype":"venue"
},
  "geometry": {"coordinates":[9.5578517914,47.3653488159],"type":"Point"}
}