{
  "type": "Feature",
  "properties": {
    "iso:country":"CH",
    "sg:address":"Bergstrasse 38",
    "sg:city":"Dietikon",
    "sg:orig_category":"Gartenbau",
    "sg:phone":"+41 17408242",
    "sg:postcode":"8953",
    "sg:province":"Z\u00fcrich",
    "wof:name":"Ungricht A. S\u00f6hne Gartenbau Ag Garten, Landschaftsbau",
    "wof:placetype":"venue"
},
  "geometry": {"coordinates":[8.3959512711,47.4024505615],"type":"Point"}
}