{
  "type": "Feature",
  "properties": {
    "iso:country":"CH",
    "sg:address":"Rue De Rive 48",
    "sg:city":"Nyon",
    "sg:orig_category":"Grosshandel mit Schmuck Grosshandel mit Uhren",
    "sg:phone":"+41 22 362 66 11",
    "sg:postcode":"1260",
    "sg:province":"Vaud",
    "wof:name":"Maga Diffusion",
    "wof:placetype":"venue"
},
  "geometry": {"coordinates":[6.2424659729,46.3820991516],"type":"Point"}
}