{
  "type": "Feature",
  "properties": {
    "iso:country":"CH",
    "sg:address":"Grand-pont 48",
    "sg:city":"Sion",
    "sg:orig_category":"Detailhandel mit elektrischen Haushalts-,Radio U Fernsehger\u00e4ten sowie Musikinstrumenten",
    "sg:phone":"+41 27 322 52 53",
    "sg:postcode":"1950",
    "sg:province":"Valais",
    "wof:name":"Boichat Charles-henri - Valec",
    "wof:placetype":"venue"
},
  "geometry": {"coordinates":[7.3608021736,46.2355232239],"type":"Point"}
}