{
  "type": "Feature",
  "properties": {
    "iso:country":"CH",
    "sg:address":"Rue Des Moulins 8",
    "sg:city":"Neuch\u00e2tel",
    "sg:orig_category":"Kosmetikinstitute",
    "sg:phone":"+41 32 724 66 45",
    "sg:postcode":"2000",
    "sg:province":"Neuch\u00e2tel",
    "wof:name":"Antonella Corliano Institut De Beaut\u00e9 Harmony",
    "wof:placetype":"venue"
},
  "geometry": {"coordinates":[6.9286460876,46.9920806885],"type":"Point"}
}