{
  "type": "Feature",
  "properties": {
    "iso:country":"CH",
    "sg:address":"Sagendorfstrasse 16",
    "sg:city":"Emmetten",
    "sg:orig_category":"Detailhandel mit Brot, Back U S\u00fcsswaren Detailhandel mit Waren verschiedener Art, Hauptrichtung Nahr",
    "sg:phone":"+41 41 620 13 55",
    "sg:postcode":"6376",
    "sg:province":"Nidwalden",
    "wof:name":"Kaspar Leiser B\u00e4ckerei-konditorei",
    "wof:placetype":"venue"
},
  "geometry": {"coordinates":[8.525109,46.957222],"type":"Point"}
}