{
  "type": "Feature",
  "properties": {
    "iso:country":"CH",
    "sg:address":"3985 M\u00fcnster Vs. Postfach",
    "sg:city":"Fieschertal",
    "sg:orig_category":"Sonstige Hilfs U Nebent\u00e4tigkeiten f\u00fcr die Luftfahrt",
    "sg:postcode":"3984",
    "sg:province":"Valais",
    "wof:name":"Flugplatzgenossenschaft M\u00fcnster",
    "wof:placetype":"venue"
},
  "geometry": {"coordinates":[8.2618303299,46.4867591858],"type":"Point"}
}