{
  "type": "Feature",
  "properties": {
    "iso:country":"CH",
    "sg:address":"Le Coll\u00e8ge",
    "sg:city":"Servion",
    "sg:orig_category":"Maurerarbeiten Sonstiger spezialisierter Hoch U Tiefbau",
    "sg:phone":"+41 24 481 18 65",
    "sg:postcode":"1077",
    "sg:province":"Vaud",
    "wof:name":"Clerc Fernand.",
    "wof:placetype":"venue"
},
  "geometry": {"coordinates":[6.8730959892,46.3716697693],"type":"Point"}
}