{
  "type": "Feature",
  "properties": {
    "iso:country":"CH",
    "sg:address":"Niklaus-konrad-strasse 25",
    "sg:city":"Solothurn",
    "sg:orig_category":"Unclassifiable Establishments",
    "sg:postcode":"4500",
    "sg:province":"Solothurn",
    "wof:name":"Hom\u00f6opathische Beratung Ursula & Reto Inderbitzin",
    "wof:placetype":"venue"
},
  "geometry": {"coordinates":[7.5420098305,47.2050552368],"type":"Point"}
}