{
  "type": "Feature",
  "properties": {
    "iso:country":"CH",
    "sg:address":"Sunnenbachweg",
    "sg:city":"Hombrechtikon",
    "sg:orig_category":"Allgemeiner Hoch U Tiefbau Allgemeiner Hochbau",
    "sg:phone":"+41 55 244 37 92",
    "sg:postcode":"8634",
    "sg:province":"Z\u00fcrich",
    "wof:name":"M. Kundert Bauunternehmung Ag",
    "wof:placetype":"venue"
},
  "geometry": {"coordinates":[8.773009,47.246243],"type":"Point"}
}