{
  "type": "Feature",
  "properties": {
    "iso:country":"CH",
    "sg:address":"Via Campo Marzio 1",
    "sg:city":"Lugano",
    "sg:orig_category":"Herstellung von sonstigen organischen Grundstoffen U Chemikalien",
    "sg:phone":"+41 91 971 88 77",
    "sg:postcode":"6900",
    "sg:province":"Ticino",
    "wof:name":"Sanoplast Lugano Sa",
    "wof:placetype":"venue"
},
  "geometry": {"coordinates":[8.9612922668,46.0068588257],"type":"Point"}
}