{
  "type": "Feature",
  "properties": {
    "iso:country":"CH",
    "sg:address":"8522",
    "sg:city":"H\u00e4uslenen",
    "sg:classifiers":[
        {
            "category":"Restaurant",
            "type":"Food & Drink"
        }
    ],
    "sg:phone":"+41 52 721 26 03",
    "sg:postcode":"8522",
    "sg:province":"Thurgau",
    "wof:name":"Restaurant Schloss-burg",
    "wof:placetype":"venue"
},
  "geometry": {"coordinates":[8.9001302719,47.5204582214],"type":"Point"}
}