{
  "type": "Feature",
  "properties": {
    "addr:full":"St. Galler Strasse 3 Flawil St. Gallen 9230",
    "addr:housenumber":"3",
    "addr:postcode":"9230",
    "addr:street":"St. Galler Strasse",
    "iso:country":"CH",
    "sg:address":"St. Galler Strasse 3",
    "sg:city":"Flawil",
    "sg:orig_category":"Detailhandel mit Bekleidung Fachdetailhandel in Verkaufsr\u00e4umen",
    "sg:phone":"+41 81 733 13 55",
    "sg:postcode":"9230",
    "sg:province":"St. Gallen",
    "wof:name":"Gassner Sport Und Mode Ag",
    "wof:placetype":"venue"
},
  "geometry": {"coordinates":[9.285299,47.094254],"type":"Point"}
}