{
  "type": "Feature",
  "properties": {
    "iso:country":"CH",
    "sg:address":"R\u00fctmattstrasse 11 5004 Aarau. Postfach",
    "sg:city":"Aarau",
    "sg:orig_category":"Fachdetailhandel in Verkaufsr\u00e4umen",
    "sg:postcode":"5004",
    "sg:province":"Aargau",
    "wof:name":"Handelsagentur R\u00fcede M. Modeaccessoires, Geschenkart, Schreibger\u00e4te Usw; Handel",
    "wof:placetype":"venue"
},
  "geometry": {"coordinates":[8.0589132309,47.400592804],"type":"Point"}
}