{
  "type": "Feature",
  "properties": {
    "iso:country":"CH",
    "sg:address":"6825",
    "sg:city":"Capolago",
    "sg:classifiers":[
        {
            "category":"Restaurant",
            "type":"Food & Drink"
        }
    ],
    "sg:phone":"+41 91 743 29 88",
    "sg:postcode":"6825",
    "sg:province":"Ticino",
    "wof:name":"Osteria Svansec",
    "wof:placetype":"venue"
},
  "geometry": {"coordinates":[8.8300590515,46.1852149963],"type":"Point"}
}