{
  "type": "Feature",
  "properties": {
    "iso:country":"CH",
    "sg:address":"Moosegg Dorf",
    "sg:city":"Bristen",
    "sg:orig_category":"Betrieb von Taxis",
    "sg:phone":"+41 41 883 13 54",
    "sg:postcode":"6475",
    "sg:province":"Uri",
    "wof:name":"Tresch Josef",
    "wof:placetype":"venue"
},
  "geometry": {"coordinates":[8.691605,46.769054],"type":"Point"}
}