{
  "type": "Feature",
  "properties": {
    "iso:country":"CH",
    "sg:address":"Oberdorfstrasse 14b 9100 Herisau. Postfach",
    "sg:city":"Herisau",
    "sg:orig_category":"Organisationen der Wohlfahrtspflege",
    "sg:phone":"+41 71 351 15 90",
    "sg:postcode":"9102",
    "sg:province":"Appenzell Ausserrhoden",
    "wof:name":"Pro Juventute App.a.rh. Bezirkssekretariat",
    "wof:placetype":"venue"
},
  "geometry": {"coordinates":[9.2792711258,47.3851699829],"type":"Point"}
}