{
  "type": "Feature",
  "properties": {
    "iso:country":"CH",
    "sg:address":"Bernstrasse 6",
    "sg:city":"Rudolfstetten",
    "sg:classifiers":[
        {
            "category":"Professional",
            "subcategory":"Engineering",
            "type":"Services"
        }
    ],
    "sg:phone":"+41 32 967 80 50",
    "sg:postcode":"8964",
    "sg:province":"Aargau",
    "sg:tags":[
        "electronic",
        "system"
    ],
    "wof:name":"Chronofiable Sa",
    "wof:placetype":"venue"
},
  "geometry": {"coordinates":[6.8263468742,47.1074409485],"type":"Point"}
}