{
  "type": "Feature",
  "properties": {
    "iso:country":"CH",
    "sg:address":"Chemin Sous La For\u00eat 3",
    "sg:city":"Montagne-moutier",
    "sg:orig_category":"Arztpraxen",
    "sg:phone":"+41 32 493 55 02",
    "sg:postcode":"2740",
    "sg:province":"Bern",
    "wof:name":"Dr M\u00e9d. Bernhard Trost M\u00e9decin Sp\u00e9cialiste Fmh",
    "wof:placetype":"venue"
},
  "geometry": {"coordinates":[7.375695,47.281902],"type":"Point"}
}