{
  "type": "Feature",
  "properties": {
    "iso:country":"CH",
    "sg:address":"Kirchweg 19",
    "sg:city":"Binningen",
    "sg:orig_category":"Sonstige pers\u00f6nliche Dienstleistungen",
    "sg:postcode":"4102",
    "sg:province":"Basel-Landschaft",
    "wof:name":"F1-kart, E. Kalt",
    "wof:placetype":"venue"
},
  "geometry": {"coordinates":[7.577173233,47.5409622192],"type":"Point"}
}