{
  "type": "Feature",
  "properties": {
    "iso:country":"CH",
    "sg:address":"3825",
    "sg:city":"M\u00fcrren",
    "sg:orig_category":"Sessellifte and Skilifte",
    "sg:phone":"+41 41 497 10 54",
    "sg:postcode":"3825",
    "sg:province":"Bern",
    "wof:name":"Skilift Schwarzenberg Ag",
    "wof:placetype":"venue"
},
  "geometry": {"coordinates":[8.1732053757,47.0156593323],"type":"Point"}
}