{
  "type": "Feature",
  "properties": {
    "addr:full":"Hauptstrasse 107 Bubendorf Basel-Landschaft 4416",
    "addr:housenumber":"107",
    "addr:postcode":"4416",
    "addr:street":"Hauptstrasse",
    "iso:country":"CH",
    "sg:address":"Hauptstrasse 107",
    "sg:city":"Bubendorf",
    "sg:orig_category":"Bauschreinerei Herstellung von M\u00f6beln verschiedener Art",
    "sg:phone":"+41 26 418 21 78",
    "sg:postcode":"4416",
    "sg:province":"Basel-Landschaft",
    "wof:name":"Urs Aebischer Antik-m\u00f6belschreinerei",
    "wof:placetype":"venue"
},
  "geometry": {"coordinates":[7.219944,46.739483],"type":"Point"}
}