{
  "type": "Feature",
  "properties": {
    "iso:country":"CH",
    "sg:address":"Steinackerstrasse",
    "sg:city":"Buttwil",
    "sg:orig_category":"Herstellung von Karosserien U Anh\u00e4ngern",
    "sg:phone":"+41 56 664 19 30",
    "sg:postcode":"5632",
    "sg:province":"Aargau",
    "wof:name":"Chapiteau, Zeltbau - Vermietung Stefan Geissb\u00fchler",
    "wof:placetype":"venue"
},
  "geometry": {"coordinates":[8.3124008179,47.270904541],"type":"Point"}
}