{
  "type": "Feature",
  "properties": {
    "iso:country":"CH",
    "sg:address":"Drosselweg 9",
    "sg:city":"Derendingen",
    "sg:orig_category":"Herstellung von Metallkonstruktionen",
    "sg:phone":"+41 32 614 11 22",
    "sg:postcode":"4552",
    "sg:province":"Solothurn",
    "wof:name":"Stampfli J. Ag",
    "wof:placetype":"venue"
},
  "geometry": {"coordinates":[7.5916028023,47.1965637207],"type":"Point"}
}