{
  "type": "Feature",
  "properties": {
    "iso:country":"CH",
    "sg:address":"B\u00e4retstrasse 2",
    "sg:city":"Visp",
    "sg:orig_category":"Non-Classified Establishments",
    "sg:postcode":"3930",
    "sg:province":"Valais",
    "wof:name":"Kosmetikstudio Akropolis, Andenmatten Dorine",
    "wof:placetype":"venue"
},
  "geometry": {"coordinates":[7.8836660385,46.2935943604],"type":"Point"}
}