{
  "type": "Feature",
  "properties": {
    "iso:country":"CH",
    "sg:address":"Via Al Portin",
    "sg:city":"Preonzo",
    "sg:orig_category":"Handel mit Automobilen",
    "sg:phone":"+41 71 855 78 66",
    "sg:postcode":"6523",
    "sg:province":"Ticino",
    "wof:name":"Airport Automobile Marcel Speichinger",
    "wof:placetype":"venue"
},
  "geometry": {"coordinates":[9.544678688,47.4842567444],"type":"Point"}
}