{
  "type": "Feature",
  "properties": {
    "iso:country":"CH",
    "sg:address":"Hohrainlistrasse 37",
    "sg:city":"Kloten",
    "sg:orig_category":"Herstellung von elektronischen Bauelementen",
    "sg:postcode":"8302",
    "sg:province":"Z\u00fcrich",
    "wof:name":"Knespl Jitka",
    "wof:placetype":"venue"
},
  "geometry": {"coordinates":[8.582485199,47.4590606689],"type":"Point"}
}