{
  "type": "Feature",
  "properties": {
    "iso:country":"CH",
    "sg:address":"Cheminet Rue Du 37",
    "sg:city":"Yverdon-les-bains",
    "sg:orig_category":"Sanit\u00e4r, Heizungs U L\u00fcftungsinstallation",
    "sg:phone":"+41 24 445 62 47",
    "sg:postcode":"1400",
    "sg:province":"Vaud",
    "wof:name":"Sanitop, Letizia Giustino",
    "wof:placetype":"venue"
},
  "geometry": {"coordinates":[6.6295042038,46.7840690613],"type":"Point"}
}