{
  "type": "Feature",
  "properties": {
    "iso:country":"CH",
    "sg:address":"Rohrhaldenstrasse 6",
    "sg:city":"St\u00e4fa",
    "sg:orig_category":"Vereine Vogel-& Naturschutz",
    "sg:phone":"+41 19265885",
    "sg:postcode":"8712",
    "sg:province":"Z\u00fcrich",
    "wof:name":"Ornithologischer Verein St\u00e4fa",
    "wof:placetype":"venue"
},
  "geometry": {"coordinates":[8.7367963791,47.2353782654],"type":"Point"}
}