{
  "type": "Feature",
  "properties": {
    "iso:country":"CH",
    "sg:address":"Hauptstrasse 94",
    "sg:city":"Derendingen",
    "sg:orig_category":"Gem\u00fcsebau",
    "sg:phone":"+41 32 682 20 31",
    "sg:postcode":"4552",
    "sg:province":"Solothurn",
    "wof:name":"Josef Eggenschwiler Gem\u00fcsebau",
    "wof:placetype":"venue"
},
  "geometry": {"coordinates":[7.5863609314,47.1912269592],"type":"Point"}
}