{
  "type": "Feature",
  "properties": {
    "iso:country":"CH",
    "sg:address":"Ollenweg 12",
    "sg:city":"Breitenbach",
    "sg:orig_category":"Erschliessung von Grundst\u00fccken",
    "sg:postcode":"4226",
    "sg:province":"Solothurn",
    "wof:name":"Wohnbaugenossenschaft St. Fridolin",
    "wof:placetype":"venue"
},
  "geometry": {"coordinates":[7.5490989685,47.4046936035],"type":"Point"}
}