{
  "type": "Feature",
  "properties": {
    "iso:country":"CH",
    "sg:address":"Industriestr. 40",
    "sg:city":"Winterthur",
    "sg:classifiers":[
        {
            "category":"Manufacturing",
            "subcategory":"Chemicals & Compounds",
            "type":"Manufacturing & Wholesale Goods"
        }
    ],
    "sg:phone":"+41 52 234 53 00",
    "sg:postcode":"8404",
    "sg:province":"Z\u00fcrich",
    "sg:tags":[
        "pharmaceutical",
        "chemistry",
        "-",
        "by-product"
    ],
    "wof:name":"Pangas",
    "wof:placetype":"venue"
},
  "geometry": {"coordinates":[8.759048,47.497169],"type":"Point"}
}