{
  "type": "Feature",
  "properties": {
    "iso:country":"CH",
    "sg:address":"Grand-rue 45",
    "sg:city":"Fribourg",
    "sg:orig_category":"Mit dem Versicherungsgewerbe verbundene T\u00e4tigkeiten",
    "sg:postcode":"1700",
    "sg:province":"Fribourg",
    "wof:name":"Assuconseil S.a.",
    "wof:placetype":"venue"
},
  "geometry": {"coordinates":[7.1645078659,46.8054542542],"type":"Point"}
}