{
  "type": "Feature",
  "properties": {
    "iso:country":"CH",
    "sg:address":"P\u00fcntenstrasse 9",
    "sg:city":"Bachenb\u00fclach",
    "sg:orig_category":"Werbung",
    "sg:phone":"+41 18623747",
    "sg:postcode":"8184",
    "sg:province":"Z\u00fcrich",
    "wof:name":"Bts B\u00fcro Team Service Gmbh",
    "wof:placetype":"venue"
},
  "geometry": {"coordinates":[8.5476760864,47.5055427551],"type":"Point"}
}