{
  "type": "Feature",
  "properties": {
    "iso:country":"CH",
    "sg:address":"Webergasse 43",
    "sg:city":"Schaffhausen",
    "sg:orig_category":"Detailhandel mit Lederwaren U Reiseartikeln",
    "sg:phone":"+41 52 625 25 13",
    "sg:postcode":"8200",
    "sg:province":"Schaffhausen",
    "wof:name":"Aliaddin Al-maghrabi Lederkunsthandwerk",
    "wof:placetype":"venue"
},
  "geometry": {"coordinates":[8.634803772,47.698261261],"type":"Point"}
}