{
  "type": "Feature",
  "properties": {
    "iso:country":"CH",
    "sg:address":"Steiggasse",
    "sg:city":"Schlatt",
    "sg:orig_category":"Erschliessung von Grundst\u00fccken",
    "sg:postcode":"8418",
    "sg:province":"Z\u00fcrich",
    "wof:name":"Genossenschaft Sonne Hinteregg",
    "wof:placetype":"venue"
},
  "geometry": {"coordinates":[8.6900548935,47.3005561829],"type":"Point"}
}