{
  "type": "Feature",
  "properties": {
    "iso:country":"CH",
    "sg:address":"Farlifangstrasse 12",
    "sg:city":"Zumikon",
    "sg:classifiers":[
        {
            "category":"Insurance",
            "subcategory":"Insurance Agent",
            "type":"Services"
        }
    ],
    "sg:phone":"+41 19180222",
    "sg:postcode":"8126",
    "sg:province":"Z\u00fcrich",
    "sg:tags":[
        "versicherungsagenturen",
        "-broker"
    ],
    "wof:name":"Winterthur Versicherungen Agentur",
    "wof:placetype":"venue"
},
  "geometry": {"coordinates":[8.6198148727,47.3364830017],"type":"Point"}
}