{
  "type": "Feature",
  "properties": {
    "iso:country":"CH",
    "sg:address":"Lac Rue Du 27",
    "sg:city":"Yverdon-les-bains",
    "sg:orig_category":"Non-Classified Establishments",
    "sg:postcode":"1400",
    "sg:province":"Vaud",
    "wof:name":"Metamorphose Centre De Sant\u00e9 Globale S\u00e0rl",
    "wof:placetype":"venue"
},
  "geometry": {"coordinates":[6.6414198875,46.7786331177],"type":"Point"}
}