{
  "type": "Feature",
  "properties": {
    "iso:country":"CH",
    "sg:address":"Rue Jenny-enning 2",
    "sg:city":"Lausanne",
    "sg:orig_category":"Non-Classified Establishments",
    "sg:phone":"+41 55 211 14 22",
    "sg:postcode":"1000",
    "sg:province":"Vaud",
    "wof:name":"Forum Shoes & Fashion F. Pastina",
    "wof:placetype":"venue"
},
  "geometry": {"coordinates":[8.8183145523,47.2273750305],"type":"Point"}
}