{
  "type": "Feature",
  "properties": {
    "iso:country":"CH",
    "sg:address":"2608",
    "sg:city":"Courtelary",
    "sg:orig_category":"Sonstige Hilfs U Nebent\u00e4tigkeiten f\u00fcr die Luftfahrt",
    "sg:phone":"+41 32 863 15 55",
    "sg:postcode":"2608",
    "sg:province":"Bern",
    "wof:name":"A\u00e9rodrome Du Val-de-travers",
    "wof:placetype":"venue"
},
  "geometry": {"coordinates":[6.6211700439,46.9019889832],"type":"Point"}
}