{
  "type": "Feature",
  "properties": {
    "iso:country":"CH",
    "sg:address":"Chemin Cr\u00eat",
    "sg:city":"St-george",
    "sg:orig_category":"Architekturb\u00fcros",
    "sg:phone":"+41 22 368 17 87",
    "sg:postcode":"1261",
    "sg:province":"Vaud",
    "wof:name":"St\u00e9phane Grosjean Architecture",
    "wof:placetype":"venue"
},
  "geometry": {"coordinates":[6.261616,46.515434],"type":"Point"}
}