{
  "type": "Feature",
  "properties": {
    "addr:full":"Immeuble Le Rond-point Montana-vermala 3962",
    "addr:postcode":"3962",
    "addr:street":"Montana-Vermala",
    "iso:country":"CH",
    "sg:address":"Immeuble Le Rond-point",
    "sg:city":"Montana-vermala",
    "sg:orig_category":"Detailhandel mit Brot, Back U S\u00fcsswaren",
    "sg:phone":"+41 27 481 45 12",
    "sg:postcode":"3962",
    "wof:name":"Roland Stauss Sa Confiserie",
    "wof:placetype":"venue"
},
  "geometry": {"coordinates":[7.492434,46.314419],"type":"Point"}
}