{
  "type": "Feature",
  "properties": {
    "iso:country":"CH",
    "sg:address":"Chalet Le Goly",
    "sg:city":"Verbier",
    "sg:orig_category":"Unternehmensberatung",
    "sg:phone":"+41 27 771 54 52",
    "sg:postcode":"1936",
    "sg:province":"Valais",
    "wof:name":"Jan Hellman Heba Business Advice",
    "wof:placetype":"venue"
},
  "geometry": {"coordinates":[7.2229619026,46.0967292786],"type":"Point"}
}