{
  "type": "Feature",
  "properties": {
    "iso:country":"CH",
    "sg:address":"Schlossgasse 18",
    "sg:city":"Murten",
    "sg:orig_category":"Detailhandel mit Musikinstrumenten Detailhandel mit elektrischen Haushalts-,Radio U Fernsehger\u00e4ten s",
    "sg:phone":"+41 26 670 57 06",
    "sg:postcode":"3280",
    "sg:province":"Fribourg",
    "wof:name":"Musikhaus Zum R\u00fcbenloch",
    "wof:placetype":"venue"
},
  "geometry": {"coordinates":[7.1161651611,46.9278144836],"type":"Point"}
}