{
  "type": "Feature",
  "properties": {
    "iso:country":"CH",
    "sg:address":"Auer Strasse 30",
    "sg:city":"Berneck",
    "sg:orig_category":"Mechanik Mechanische Werkst\u00e4tten",
    "sg:phone":"+41 71 722 12 46",
    "sg:postcode":"9442",
    "sg:province":"St. Gallen",
    "wof:name":"Alge H. Ag",
    "wof:placetype":"venue"
},
  "geometry": {"coordinates":[9.6216068268,47.4279098511],"type":"Point"}
}