{
  "type": "Feature",
  "properties": {
    "iso:country":"CH",
    "sg:address":"Waldst\u00e4tterstrasse 6",
    "sg:city":"Luzern",
    "sg:orig_category":"Hardwareberatung",
    "sg:phone":"+41 41 210 16 56",
    "sg:postcode":"6003",
    "sg:province":"Luzern",
    "wof:name":"Cyber-shop Von Deschwanden",
    "wof:placetype":"venue"
},
  "geometry": {"coordinates":[8.307808876,47.0461235046],"type":"Point"}
}