{
  "type": "Feature",
  "properties": {
    "iso:country":"CH",
    "sg:address":"Bahnhofstrasse 8 5036 Oberentfelden. Postfach 74",
    "sg:city":"Oberentfelden",
    "sg:orig_category":"Verwaltung von Immobilien Wirtschaftspr\u00fcfung, Steuerberatung U Treuhand",
    "sg:phone":"+41 62 723 10 62",
    "sg:postcode":"5036",
    "sg:province":"Aargau",
    "wof:name":"Alru Immobilien-treuhand Ag",
    "wof:placetype":"venue"
},
  "geometry": {"coordinates":[8.0476331711,47.3563652039],"type":"Point"}
}