{
  "type": "Feature",
  "properties": {
    "iso:country":"CH",
    "sg:address":"Rufenastrasse 18",
    "sg:city":"Klosters",
    "sg:orig_category":"Sportvereine Alpinismus",
    "sg:phone":"+41 81 422 39 28",
    "sg:postcode":"7250",
    "sg:province":"Graubunden",
    "wof:name":"Sac Sektion Pr\u00e4ttigau",
    "wof:placetype":"venue"
},
  "geometry": {"coordinates":[9.883723259,46.8615760803],"type":"Point"}
}