{
  "type": "Feature",
  "properties": {
    "iso:country":"CH",
    "sg:address":"Marktgasse 28",
    "sg:city":"Bern",
    "sg:orig_category":"Kosmetikinstitute",
    "sg:phone":"+41 31 311 68 63",
    "sg:postcode":"3011",
    "sg:province":"Bern",
    "wof:name":"Juvena Ursula Meichtry Kosmetikinstitut",
    "wof:placetype":"venue"
},
  "geometry": {"coordinates":[7.4457588196,46.9479904175],"type":"Point"}
}