{
  "type": "Feature",
  "properties": {
    "iso:country":"CH",
    "sg:address":"Feldstrasse 4",
    "sg:city":"Thalwil",
    "sg:orig_category":"Non-Classified Establishments",
    "sg:postcode":"8800",
    "sg:province":"Z\u00fcrich",
    "wof:name":"Widmer Trans Gmbh",
    "wof:placetype":"venue"
},
  "geometry": {"coordinates":[9.0613527298,47.3796081543],"type":"Point"}
}