{
  "type": "Feature",
  "properties": {
    "iso:country":"CH",
    "sg:address":"Oberdorfstrasse 34",
    "sg:city":"Herisau",
    "sg:orig_category":"Detailhandel mit Radio U Fernsehger\u00e4ten Detailhandel mit elektrischen Haushalts-,Radio U Fernsehger\u00e4",
    "sg:phone":"+41 26 912 65 61",
    "sg:postcode":"9100",
    "sg:province":"Appenzell Ausserrhoden",
    "wof:name":"Radio-tv Service Copparoni Sa, \u00e0 Port-louis, Succursale De Bulle",
    "wof:placetype":"venue"
},
  "geometry": {"coordinates":[7.0587158203,46.6146965027],"type":"Point"}
}