{
  "type": "Feature",
  "properties": {
    "iso:country":"CH",
    "sg:address":"Via Povr\u00f2 8",
    "sg:city":"Massagno",
    "sg:classifiers":[
        {
            "category":"Communications",
            "subcategory":"Film & Video Production",
            "type":"Services"
        }
    ],
    "sg:phone":"+41 91 966 38 71",
    "sg:postcode":"6900",
    "sg:province":"Ticino",
    "sg:tags":[
        "videofilmherstellung",
        "u"
    ],
    "wof:name":"Pic-film Sa",
    "wof:placetype":"venue"
},
  "geometry": {"coordinates":[8.9399585724,46.014415741],"type":"Point"}
}