{
  "type": "Feature",
  "properties": {
    "iso:country":"CH",
    "sg:address":"En Lomb\u00e9ra 1261 Marchissy. Postfach",
    "sg:city":"Marchissy",
    "sg:orig_category":"Detektivb\u00fcros U \u00dcberwachung",
    "sg:phone":"+41 56 282 30 65",
    "sg:postcode":"1261",
    "sg:province":"Vaud",
    "wof:name":"Alpha Security Sicherheitsdienste Ag",
    "wof:placetype":"venue"
},
  "geometry": {"coordinates":[8.2765626907,47.4929580688],"type":"Point"}
}