{
  "type": "Feature",
  "properties": {
    "iso:country":"CH",
    "sg:address":"Mittlerestrasse 56",
    "sg:city":"Thun",
    "sg:orig_category":"Giessereiindustrie Herstellung von Metallerzeugnissen ohne Maschinenbau",
    "sg:phone":"+41 33 222 24 65",
    "sg:postcode":"3600",
    "sg:province":"Bern",
    "wof:name":"Giesserei Thun Kilchhofer Ag",
    "wof:placetype":"venue"
},
  "geometry": {"coordinates":[7.6171708107,46.7562980652],"type":"Point"}
}