{
  "type": "Feature",
  "properties": {
    "iso:country":"CH",
    "sg:address":"Riant-mont Avenue De 4",
    "sg:city":"Lausanne",
    "sg:orig_category":"Unclassifiable Establishments",
    "sg:postcode":"1004",
    "sg:province":"Vaud",
    "wof:name":"Fasolt Ag",
    "wof:placetype":"venue"
},
  "geometry": {"coordinates":[9.3852109909,47.4388961792],"type":"Point"}
}