{
  "type": "Feature",
  "properties": {
    "iso:country":"CH",
    "sg:address":"Place Du Nord 1071 Chexbres Case Postale 52",
    "sg:city":"Chexbres",
    "sg:orig_category":"Detailhandel mit Fahrr\u00e4dern Handel mit Motorr\u00e4dern, Teilen U Zubeh\u00f6r Instandhaltung U Reparatur von ",
    "sg:phone":"+41 21 946 15 10",
    "sg:postcode":"1071",
    "sg:province":"Vaud",
    "wof:name":"Claude-alain Pache V\u00e9los-motos",
    "wof:placetype":"venue"
},
  "geometry": {"coordinates":[6.776239872,46.4821128845],"type":"Point"}
}