{
  "type": "Feature",
  "properties": {
    "iso:country":"CH",
    "sg:address":"Rue De La Gare 6",
    "sg:city":"Sonceboz",
    "sg:classifiers":[
        {
            "category":"Banks & Credit Unions",
            "subcategory":"Bank",
            "type":"Services"
        }
    ],
    "sg:phone":"+41 61 286 44 00",
    "sg:postcode":"2605",
    "sg:province":"Bern",
    "wof:name":"La Roche & Co Banquiers",
    "wof:placetype":"venue"
},
  "geometry": {"coordinates":[7.58876,47.556992],"type":"Point"}
}