{
  "type": "Feature",
  "properties": {
    "iso:country":"CH",
    "sg:address":"Avenir Rue De L' 23",
    "sg:city":"Del\u00e9mont",
    "sg:orig_category":"Unclassifiable Establishments",
    "sg:postcode":"2800",
    "sg:province":"Jura",
    "wof:name":"Balton Holding Sa",
    "wof:placetype":"venue"
},
  "geometry": {"coordinates":[7.3439698219,47.3653488159],"type":"Point"}
}