{
  "type": "Feature",
  "properties": {
    "iso:country":"CH",
    "sg:address":"Steinberggasse 20",
    "sg:city":"Winterthur",
    "sg:classifiers":[
        {
            "category":"Professional",
            "subcategory":"Employment Agencies",
            "type":"Services"
        }
    ],
    "sg:phone":"+41 52 260 09 09",
    "sg:postcode":"8400",
    "sg:province":"Z\u00fcrich",
    "sg:tags":[
        "personal",
        "u",
        "stellenvermittlung"
    ],
    "wof:name":"Personalberatung Das Team Ag",
    "wof:placetype":"venue"
},
  "geometry": {"coordinates":[8.7289361954,47.49842453],"type":"Point"}
}