{
  "type": "Feature",
  "properties": {
    "iso:country":"CH",
    "sg:address":"Place Saint-fran\u00e7ois 10 1003 Lausanne. Postfach",
    "sg:city":"Lausanne",
    "sg:orig_category":"Detailhandel mit Damenbekleidung Parf\u00fcmerien U sonstiger Detailhandel mit kosmetischen Artikeln U K\u00f6",
    "sg:phone":"+41 22 310 82 22",
    "sg:postcode":"1001",
    "sg:province":"Vaud",
    "wof:name":"Brunschwig & Cie Sa Bon G\u00e9nie Les Boutiques",
    "wof:placetype":"venue"
},
  "geometry": {"coordinates":[6.1475400925,46.2030181885],"type":"Point"}
}