{
  "type": "Feature",
  "properties": {
    "addr:full":"Calandastrasse 13 Zizers Graubunden 7205",
    "addr:housenumber":"13",
    "addr:postcode":"7205",
    "addr:street":"Calandastrasse",
    "iso:country":"CH",
    "sg:address":"Calandastrasse 13",
    "sg:city":"Zizers",
    "sg:orig_category":"Architekturb\u00fcros",
    "sg:phone":"+41 81 322 95 55",
    "sg:postcode":"7205",
    "sg:province":"Graubunden",
    "wof:name":"A.c.c.a. Architektur Claudio Casutt",
    "wof:placetype":"venue"
},
  "geometry": {"coordinates":[9.561631,46.929432],"type":"Point"}
}