{
  "type": "Feature",
  "properties": {
    "iso:country":"CH",
    "sg:address":"Bahnhofstrasse 104",
    "sg:city":"Urdorf",
    "sg:orig_category":"Sportvereine Ski",
    "sg:phone":"+41 17341236",
    "sg:postcode":"8902",
    "sg:province":"Z\u00fcrich",
    "wof:name":"Skiclub Z\u00fcrich D.eisenbahner",
    "wof:placetype":"venue"
},
  "geometry": {"coordinates":[8.4229478836,47.3849601746],"type":"Point"}
}