{
  "type": "Feature",
  "properties": {
    "iso:country":"CH",
    "sg:address":"St\u00e4dtli 3",
    "sg:city":"Werdenberg",
    "sg:orig_category":"Herstellung von medizinischen U chirurgischen Ger\u00e4ten sowie orthop\u00e4dischen Vorrichtungen Zahntechnis",
    "sg:phone":"+41 81 771 30 33",
    "sg:postcode":"9470",
    "sg:province":"St. Gallen",
    "wof:name":"Gromen Dental",
    "wof:placetype":"venue"
},
  "geometry": {"coordinates":[9.4630966187,47.1681289673],"type":"Point"}
}