{
  "type": "Feature",
  "properties": {
    "iso:country":"CH",
    "sg:address":"Weidstrasse 12 8253 Diessenhofen. Postfach",
    "sg:city":"Diessenhofen",
    "sg:orig_category":"Reiseb\u00fcros U Reiseveranstalter",
    "sg:phone":"+41 52 654 18 10",
    "sg:postcode":"8253",
    "sg:province":"Thurgau",
    "wof:name":"Tourismus-schweiz.ch Gmbh",
    "wof:placetype":"venue"
},
  "geometry": {"coordinates":[8.7411079407,47.689037323],"type":"Point"}
}