{
  "type": "Feature",
  "properties": {
    "iso:country":"CH",
    "sg:address":"Champ Du Four",
    "sg:city":"Thierrens",
    "sg:orig_category":"Non-Classified Establishments",
    "sg:postcode":"1410",
    "sg:province":"Vaud",
    "wof:name":"O.m.a.g.e S\u00e0rl",
    "wof:placetype":"venue"
},
  "geometry": {"coordinates":[6.7512187958,46.7010536194],"type":"Point"}
}