{
  "type": "Feature",
  "properties": {
    "addr:full":"Strassburgstrasse 10 8004 Z\u00fcrich. Postfach Z\u00fcrich Z\u00fcrich 8026",
    "addr:housenumber":"10",
    "addr:postcode":"8004 zuerich. postfach;8026",
    "addr:street":"Strassburgstrasse",
    "iso:country":"CH",
    "sg:address":"Strassburgstrasse 10 8004 Z\u00fcrich. Postfach",
    "sg:city":"Z\u00fcrich",
    "sg:orig_category":"Detailhandel mit B\u00fcchern",
    "sg:phone":"+41 12419695",
    "sg:postcode":"8026",
    "sg:province":"Z\u00fcrich",
    "wof:name":"Analph Comicladen",
    "wof:placetype":"venue"
},
  "geometry": {"coordinates":[8.528707,47.3727],"type":"Point"}
}