{
  "type": "Feature",
  "properties": {
    "iso:country":"CH",
    "sg:address":"Solothurnstrasse 20",
    "sg:city":"Grenchen",
    "sg:orig_category":"Sonstige pers\u00f6nliche Dienstleistungen",
    "sg:postcode":"2540",
    "sg:province":"Solothurn",
    "wof:name":"Jufer & Partner Dienstleistungen",
    "wof:placetype":"venue"
},
  "geometry": {"coordinates":[7.3970651627,47.1923789978],"type":"Point"}
}