{
  "type": "Feature",
  "properties": {
    "iso:country":"CH",
    "sg:address":"Renggerstrasse 3",
    "sg:city":"Z\u00fcrich",
    "sg:classifiers":[
        {
            "category":"Structure",
            "subcategory":"Bridge",
            "type":"Public Place"
        }
    ],
    "sg:phone":"+41 14823773",
    "sg:postcode":"8038",
    "sg:province":"Z\u00fcrich",
    "sg:tags":[
        "construction"
    ],
    "wof:name":"Ingenieurb\u00fcro P. Bachmann B\u00fcro Sia F\u00fcr Bauwerkserhaltung, Hoch- /tiefbau",
    "wof:placetype":"venue"
},
  "geometry": {"coordinates":[8.532069,47.34705],"type":"Point"}
}