{
  "type": "Feature",
  "properties": {
    "iso:country":"CH",
    "sg:address":"Axenstein",
    "sg:city":"Morschach",
    "sg:orig_category":"Dienstleistungen von Beteiligungsgesellschaften Erbringung von Dienstleistungen f\u00fcr Unternehmen",
    "sg:phone":"+41 41 726 86 86",
    "sg:postcode":"6443",
    "sg:province":"Schwyz",
    "wof:name":"Rm Trust Ag",
    "wof:placetype":"venue"
},
  "geometry": {"coordinates":[8.6164798737,46.9855003357],"type":"Point"}
}