{
  "type": "Feature",
  "properties": {
    "iso:country":"CH",
    "sg:address":"Chemin De Champ-soleil 22",
    "sg:city":"Lausanne",
    "sg:classifiers":[
        {
            "category":"Building & Trades",
            "subcategory":"Construction",
            "type":"Services"
        }
    ],
    "sg:phone":"+41 21 729 60 67",
    "sg:postcode":"1012",
    "sg:province":"Vaud",
    "sg:tags":[
        "insulation",
        "heat",
        "work",
        "cold"
    ],
    "wof:name":"Bernard Schuler Isolation Thermique",
    "wof:placetype":"venue"
},
  "geometry": {"coordinates":[6.6530251503,46.5230293274],"type":"Point"}
}