{
  "type": "Feature",
  "properties": {
    "iso:country":"CH",
    "sg:address":"Via Franchino Rusca 1",
    "sg:city":"Locarno",
    "sg:orig_category":"Museen",
    "sg:phone":"+41 91 756 31 90",
    "sg:postcode":"6600",
    "sg:province":"Ticino",
    "wof:name":"Archivio Comunale",
    "wof:placetype":"venue"
},
  "geometry": {"coordinates":[8.7943334579,46.1679611206],"type":"Point"}
}