{
  "type": "Feature",
  "properties": {
    "iso:country":"CH",
    "sg:address":"Industriestrasse 20",
    "sg:city":"Arbon",
    "sg:orig_category":"Grosshandel mit Holz U Baustoffen",
    "sg:phone":"+41 71 446 74 70",
    "sg:postcode":"9320",
    "sg:province":"Thurgau",
    "wof:name":"Hg Commerciale Handelsgen. Des Schweiz. Baumeisterverband",
    "wof:placetype":"venue"
},
  "geometry": {"coordinates":[9.4155387878,47.5223045349],"type":"Point"}
}