{
  "type": "Feature",
  "properties": {
    "iso:country":"CH",
    "sg:address":"Sch\u00fctzenstrasse 6",
    "sg:city":"Herisau",
    "sg:orig_category":"Herstellung von Kakao, Schokoladeerzeugnissen U Zuckerwaren",
    "sg:phone":"+41 71 744 10 61",
    "sg:postcode":"9100",
    "sg:province":"Appenzell Ausserrhoden",
    "wof:name":"Kaiser T. Ag",
    "wof:placetype":"venue"
},
  "geometry": {"coordinates":[9.6374349594,47.4530105591],"type":"Point"}
}