{
  "type": "Feature",
  "properties": {
    "iso:country":"CH",
    "sg:address":"Wermatswilerstrasse 79",
    "sg:city":"Uster",
    "sg:orig_category":"Sportvereine Schach",
    "sg:postcode":"8610",
    "sg:province":"Z\u00fcrich",
    "wof:name":"Schachclub Uster",
    "wof:placetype":"venue"
},
  "geometry": {"coordinates":[8.7308454514,47.3557701111],"type":"Point"}
}