{
  "type": "Feature",
  "properties": {
    "iso:country":"CH",
    "sg:address":"M\u00fcntzbergstrasse 23",
    "sg:city":"Baden",
    "sg:orig_category":"Handelsvermittlung U Grosshandel Sonstiger Grosshandel",
    "sg:phone":"+41 19292995",
    "sg:postcode":"5400",
    "sg:province":"Aargau",
    "wof:name":"Luna Lai, Schweizer Hanspeter",
    "wof:placetype":"venue"
},
  "geometry": {"coordinates":[8.732085228,47.2691459656],"type":"Point"}
}