{
  "type": "Feature",
  "properties": {
    "addr:full":"Via Mezzana 31a 6616 Losone. Postfach Caselle Postale 761 Losone Ticino 6616",
    "addr:housenumber":"31a",
    "addr:postcode":"6616 losone. postfach caselle postale 761;6616",
    "addr:street":"Via Mezzana",
    "iso:country":"CH",
    "sg:address":"Via Mezzana 31a 6616 Losone. Postfach Caselle Postale 761",
    "sg:city":"Losone",
    "sg:orig_category":"Advokaturb\u00fcros Notariate",
    "sg:phone":"+41 91 791 46 26",
    "sg:postcode":"6616",
    "sg:province":"Ticino",
    "wof:name":"Salvatore Pinoja Studio Legale & Notarile",
    "wof:placetype":"venue"
},
  "geometry": {"coordinates":[8.762043,46.168121],"type":"Point"}
}