{
  "type": "Feature",
  "properties": {
    "iso:country":"CH",
    "sg:address":"1735",
    "sg:city":"Giffers",
    "sg:orig_category":"Primarschulen",
    "sg:postcode":"1735",
    "sg:province":"Fribourg",
    "wof:name":"Primarschule",
    "wof:placetype":"venue"
},
  "geometry": {"coordinates":[7.2263097763,46.7536201477],"type":"Point"}
}