{
  "type": "Feature",
  "properties": {
    "iso:country":"CH",
    "sg:address":"Altgasse 48",
    "sg:city":"Baar",
    "sg:classifiers":[
        {
            "category":"Food & Beverages",
            "subcategory":"Groceries & Convenience Stores",
            "type":"Retail Goods"
        }
    ],
    "sg:phone":"+41 41 761 65 31",
    "sg:postcode":"6340",
    "sg:province":"Zug",
    "sg:tags":[
        "product",
        "related"
    ],
    "wof:name":"Panella Frischgeb\u00c4ck Ag",
    "wof:placetype":"venue"
},
  "geometry": {"coordinates":[8.5169563293,47.1922149658],"type":"Point"}
}