{
  "type": "Feature",
  "properties": {
    "iso:country":"CH",
    "sg:address":"Rue De L'eglise-catholique 12",
    "sg:city":"Montreux",
    "sg:orig_category":"Chemische Reinigung",
    "sg:phone":"+41 19303634",
    "sg:postcode":"1820",
    "sg:province":"Vaud",
    "wof:name":"Gebr\u00fcder Stalder Ag Textilpflege",
    "wof:placetype":"venue"
},
  "geometry": {"coordinates":[8.800189,47.326958],"type":"Point"}
}