{
  "type": "Feature",
  "properties": {
    "iso:country":"CH",
    "sg:address":"Traubenweg 67",
    "sg:city":"Steffisburg",
    "sg:orig_category":"Arztpraxen",
    "sg:phone":"+41 33 221 50 30",
    "sg:postcode":"3612",
    "sg:province":"Bern",
    "wof:name":"Dr.med.bernhard Rindlisbacher Arzt F.allgemeine Medizin Fmh",
    "wof:placetype":"venue"
},
  "geometry": {"coordinates":[7.635075,46.765282],"type":"Point"}
}