{
  "type": "Feature",
  "properties": {
    "iso:country":"CH",
    "sg:address":"Rue Mi\u00e9ville 8",
    "sg:city":"Travers",
    "sg:orig_category":"Museen",
    "sg:phone":"+41 32 863 22 84",
    "sg:postcode":"2105",
    "sg:province":"Neuch\u00e2tel",
    "wof:name":"Mus\u00e9e La Banderette Monsieur Maximilien Diana",
    "wof:placetype":"venue"
},
  "geometry": {"coordinates":[6.6750187874,46.9399299622],"type":"Point"}
}