{
  "type": "Feature",
  "properties": {
    "iso:country":"CH",
    "sg:address":"Avenue De La Gare 53",
    "sg:city":"Neuch\u00e2tel",
    "sg:orig_category":"Sonstige mit der Informatik verbundene T\u00e4tigkeiten",
    "sg:phone":"+41 32 724 75 90",
    "sg:postcode":"2000",
    "sg:province":"Neuch\u00e2tel",
    "wof:name":"Infoptic, Dysli Genevi\u00e8ve",
    "wof:placetype":"venue"
},
  "geometry": {"coordinates":[6.9325761795,46.9949569702],"type":"Point"}
}