{
  "type": "Feature",
  "properties": {
    "iso:country":"CH",
    "sg:address":"Stationsstrasse 57",
    "sg:city":"Samstagern",
    "sg:orig_category":"Detailhandel mit Brot, Back U S\u00fcsswaren",
    "sg:phone":"+41 17840327",
    "sg:postcode":"8833",
    "sg:province":"Z\u00fcrich",
    "wof:name":"Gerhard Baumann B\u00e4ckerei-konditorei",
    "wof:placetype":"venue"
},
  "geometry": {"coordinates":[8.684769,47.19231],"type":"Point"}
}