{
  "type": "Feature",
  "properties": {
    "iso:country":"CH",
    "sg:address":"Rue Grenade 3",
    "sg:city":"Moudon",
    "sg:orig_category":"Detailhandel mit M\u00f6beln U Haushaltsgegenst\u00e4nden Verlegen von Fussboden",
    "sg:phone":"+41 21 905 18 67",
    "sg:postcode":"1510",
    "sg:province":"Vaud",
    "wof:name":"Chanez F.",
    "wof:placetype":"venue"
},
  "geometry": {"coordinates":[6.7973780632,46.6689758301],"type":"Point"}
}