{
  "type": "Feature",
  "properties": {
    "iso:country":"CH",
    "sg:address":"Berglistrasse 21",
    "sg:city":"Luzern",
    "sg:orig_category":"Vereine Diverse",
    "sg:phone":"+41 41 312 56 55",
    "sg:postcode":"6005",
    "sg:province":"Luzern",
    "wof:name":"Vino Club",
    "wof:placetype":"venue"
},
  "geometry": {"coordinates":[8.2983341217,47.0449485779],"type":"Point"}
}