{
  "type": "Feature",
  "properties": {
    "iso:country":"CH",
    "sg:address":"Frohsinnstrasse 11",
    "sg:city":"Dussnang",
    "sg:orig_category":"RESTAURANTS: TEA-ROOMS",
    "sg:postcode":"8374",
    "sg:province":"Thurgau",
    "wof:name":"Restaurant Sch\u00e4fli, Marcel Grom",
    "wof:placetype":"venue"
},
  "geometry": {"coordinates":[8.6300592422,47.0269699097],"type":"Point"}
}