{
  "type": "Feature",
  "properties": {
    "iso:country":"CH",
    "sg:address":"Josefstrasse 32 8005 Z\u00fcrich. Postfach 7334",
    "sg:city":"Z\u00fcrich",
    "sg:orig_category":"Politische Parteien Evangelische Volkspartei",
    "sg:phone":"+41 12727100",
    "sg:postcode":"8023",
    "sg:province":"Z\u00fcrich",
    "wof:name":"Evp Der Schweiz Evp Des Kantons Z\u00fcrich",
    "wof:placetype":"venue"
},
  "geometry": {"coordinates":[8.5335321426,47.381313324],"type":"Point"}
}