{
  "type": "Feature",
  "properties": {
    "iso:country":"CH",
    "sg:address":"Neugasse 3",
    "sg:city":"Derendingen",
    "sg:orig_category":"Elektroinstallation",
    "sg:phone":"+41 32 682 05 25",
    "sg:postcode":"4552",
    "sg:province":"Solothurn",
    "wof:name":"Elektro Stampfli",
    "wof:placetype":"venue"
},
  "geometry": {"coordinates":[7.5861282349,47.1991271973],"type":"Point"}
}