{
  "type": "Feature",
  "properties": {
    "iso:country":"CH",
    "sg:address":"Sonnenrain 2",
    "sg:city":"K\u00f6lliken",
    "sg:orig_category":"Vereine Abstinenten",
    "sg:phone":"+41 62 723 23 05",
    "sg:postcode":"5742",
    "sg:province":"Aargau",
    "wof:name":"Blaues Kreuz",
    "wof:placetype":"venue"
},
  "geometry": {"coordinates":[8.0220842361,47.3390693665],"type":"Point"}
}