{
  "type": "Feature",
  "properties": {
    "iso:country":"CH",
    "sg:address":"Chemin Des Croisettes 21",
    "sg:city":"Epalinges",
    "sg:orig_category":"Fahrschulen, Flugschulen",
    "sg:phone":"+41 21 652 79 96",
    "sg:postcode":"1066",
    "sg:province":"Vaud",
    "wof:name":"Liliane Rothen Auto-\u00e9cole",
    "wof:placetype":"venue"
},
  "geometry": {"coordinates":[6.6591968536,46.5443611145],"type":"Point"}
}