{
  "type": "Feature",
  "properties": {
    "iso:country":"CH",
    "sg:address":"Rue Du Coppet 4",
    "sg:city":"Monthey",
    "sg:orig_category":"Detailhandel mit Bekleidung Detailhandel mit Damenbekleidung",
    "sg:phone":"+41 24 472 21 13",
    "sg:postcode":"1870",
    "sg:province":"Valais",
    "wof:name":"Boutique Corolle- Antille Rose-marie",
    "wof:placetype":"venue"
},
  "geometry": {"coordinates":[6.949191,46.252258],"type":"Point"}
}