{
  "type": "Feature",
  "properties": {
    "addr:full":"Schulhausstrasse 6 Neuenegg Bern 3176",
    "addr:housenumber":"6",
    "addr:postcode":"3176",
    "addr:street":"Schulhausstrasse;Bern",
    "iso:country":"CH",
    "sg:address":"Schulhausstrasse 6",
    "sg:city":"Neuenegg",
    "sg:orig_category":"Bezirks, Sekundar, Realschulen, Oberstufe der Primarschulen",
    "sg:phone":"+41 31 741 22 82",
    "sg:postcode":"3176",
    "sg:province":"Bern",
    "wof:name":"Sekundarschule Neuenegg",
    "wof:placetype":"venue"
},
  "geometry": {"coordinates":[7.295987,46.89658],"type":"Point"}
}