{
  "type": "Feature",
  "properties": {
    "iso:country":"CH",
    "sg:address":"Neumattstrasse 29",
    "sg:city":"Aarau",
    "sg:orig_category":"Instandhaltung U Reparatur von Automobilen",
    "sg:phone":"+41 62 824 54 54",
    "sg:postcode":"5000",
    "sg:province":"Aargau",
    "wof:name":"Service Carrosserie Gmbh",
    "wof:placetype":"venue"
},
  "geometry": {"coordinates":[8.0653171539,47.4002723694],"type":"Point"}
}