{
  "type": "Feature",
  "properties": {
    "iso:country":"CH",
    "sg:address":"Promenade 57 7270 Davos Platz. Postfach",
    "sg:city":"Landquart",
    "sg:orig_category":"Wirtschaftspr\u00fcfung, Steuerberatung U Treuhand",
    "sg:postcode":"7302",
    "sg:province":"Graubunden",
    "wof:name":"Tip & Tap Gmbh",
    "wof:placetype":"venue"
},
  "geometry": {"coordinates":[8.2235832214,47.131149292],"type":"Point"}
}