{
  "type": "Feature",
  "properties": {
    "iso:country":"CH",
    "sg:address":"Rte De St-julien 126.",
    "sg:city":"Plan-les-ouates",
    "sg:orig_category":"Fachdetailhandel mit pharmazeutischen Produkten",
    "sg:phone":"+41 22 794 02 74",
    "sg:postcode":"1228",
    "sg:province":"Gen\u00e8ve",
    "wof:name":"Neri Monique.",
    "wof:placetype":"venue"
},
  "geometry": {"coordinates":[6.1192970276,46.1691970825],"type":"Point"}
}