{
  "type": "Feature",
  "properties": {
    "iso:country":"CH",
    "sg:address":"Centralstrasse 37",
    "sg:city":"Grenchen",
    "sg:orig_category":"Sonstiger Fachdetailhandel mit Nahrungsmitteln, Getr\u00e4nken U Tabak in Verkaufsr\u00e4umen",
    "sg:phone":"+41 26 913 10 30",
    "sg:postcode":"2540",
    "sg:province":"Solothurn",
    "wof:name":"Grisoni Orlando",
    "wof:placetype":"venue"
},
  "geometry": {"coordinates":[7.0663948059,46.6079711914],"type":"Point"}
}