{
  "type": "Feature",
  "properties": {
    "iso:country":"CH",
    "sg:address":"Lettenstrasse 11 6343 Rotkreuz. Postfach",
    "sg:city":"Rotkreuz",
    "sg:orig_category":"Grosshandel mit B\u00fcromaschinen Grosshandel mit Datenverarbeitungsger\u00e4ten",
    "sg:phone":"+41 41 799 10 00",
    "sg:postcode":"6343",
    "sg:province":"Zug",
    "wof:name":"Tech Data (schweiz) Ag",
    "wof:placetype":"venue"
},
  "geometry": {"coordinates":[8.4307203293,47.147518158],"type":"Point"}
}