{
  "type": "Feature",
  "properties": {
    "iso:country":"CH",
    "sg:address":"Leonhardskirchplatz 3 4001 Basel. Postfach",
    "sg:city":"Basel",
    "sg:orig_category":"Non-Classified Establishments",
    "sg:postcode":"4001",
    "sg:province":"Basel-Stadt",
    "wof:name":"Staatsanwaltschaft Basel Stadt",
    "wof:placetype":"venue"
},
  "geometry": {"coordinates":[7.5880761147,47.5552635193],"type":"Point"}
}