{
  "type": "Feature",
  "properties": {
    "iso:country":"CH",
    "sg:address":"Brisig 799",
    "sg:city":"Schwellbrunn",
    "sg:orig_category":"Instandhaltung U Reparatur von Automobilen",
    "sg:phone":"+41 71 351 33 06",
    "sg:postcode":"9103",
    "sg:province":"Appenzell Ausserrhoden",
    "wof:name":"Walter Preisig Autogarage Ag",
    "wof:placetype":"venue"
},
  "geometry": {"coordinates":[9.2638664246,47.3464584351],"type":"Point"}
}