{
  "type": "Feature",
  "properties": {
    "iso:country":"CH",
    "sg:address":"Sch\u00fctzengasse1 8001 Z\u00fcrich. Postfach Postfach",
    "sg:city":"Z\u00fcrich",
    "sg:orig_category":"Patentverwertung Unternehmensberatung",
    "sg:phone":"+41 55 221 41 04",
    "sg:postcode":"8023",
    "sg:province":"Z\u00fcrich",
    "wof:name":"Weidmann Etea Management Services Ag",
    "wof:placetype":"venue"
},
  "geometry": {"coordinates":[8.8242368698,47.2275047302],"type":"Point"}
}