{
  "type": "Feature",
  "properties": {
    "iso:country":"CH",
    "sg:address":"1097",
    "sg:city":"Riex",
    "sg:orig_category":"Verkehrs- and Tourismusb\u00fcros",
    "sg:phone":"+41 90556162",
    "sg:postcode":"1097",
    "sg:province":"Vaud",
    "wof:name":"Office Du Tourisme Neuch\u00e2telois-montagnes",
    "wof:placetype":"venue"
},
  "geometry": {"coordinates":[6.828813076,47.1023902893],"type":"Point"}
}