{
  "type": "Feature",
  "properties": {
    "iso:country":"CH",
    "sg:address":"Bahnhofstrasse 17",
    "sg:city":"Maienfeld",
    "sg:orig_category":"Hochschulen U h\u00f6here Ausbildung",
    "sg:phone":"+41 79 285 54 19",
    "sg:postcode":"7304",
    "sg:province":"Graubunden",
    "wof:name":"Ias Institut F\u00fcr Angewandte Sozialwissenschaften",
    "wof:placetype":"venue"
},
  "geometry": {"coordinates":[9.5287790298,47.0044746399],"type":"Point"}
}