{
  "type": "Feature",
  "properties": {
    "addr:full":"Via San Gottardo 59 Balerna Ticino 6828",
    "addr:housenumber":"59",
    "addr:postcode":"6828",
    "addr:street":"Via San Gottardo",
    "iso:country":"CH",
    "sg:address":"Via San Gottardo 59",
    "sg:city":"Balerna",
    "sg:classifiers":[
        {
            "category":"Banks & Credit Unions",
            "subcategory":"Bank",
            "type":"Services"
        }
    ],
    "sg:phone":"+41 4191432055",
    "sg:postcode":"6828",
    "sg:province":"Ticino",
    "wof:name":"Banca Raiffeisen, Di Balerna",
    "wof:placetype":"venue"
},
  "geometry": {"coordinates":[9.007695,45.848572],"type":"Point"}
}