{
  "type": "Feature",
  "properties": {
    "iso:country":"CH",
    "sg:address":"Zeughausstrasse 4",
    "sg:city":"Frauenfeld",
    "sg:classifiers":[
        {
            "category":"Restaurant",
            "type":"Food & Drink"
        }
    ],
    "sg:phone":"+41 52 721 45 58",
    "sg:postcode":"8500",
    "sg:province":"Thurgau",
    "wof:name":"Pizzeria Barbarossa & Trattoria Napoli",
    "wof:placetype":"venue"
},
  "geometry": {"coordinates":[8.9009389877,47.5596885681],"type":"Point"}
}