{
  "type": "Feature",
  "properties": {
    "iso:country":"CH",
    "sg:address":"Bahnhofstrasse 9 7000 Chur. Postfach",
    "sg:city":"Chur",
    "sg:orig_category":"Mit dem Versicherungsgewerbe verbundene T\u00e4tigkeiten",
    "sg:phone":"+41 81 250 54 00",
    "sg:postcode":"7000",
    "sg:province":"Graubunden",
    "wof:name":"Tscharner & Partner Dienstleistungen In Den Bereichen Versicherungs- U. Anlagewesen",
    "wof:placetype":"venue"
},
  "geometry": {"coordinates":[9.5308618546,46.8526878357],"type":"Point"}
}