{
  "type": "Feature",
  "properties": {
    "iso:country":"CH",
    "sg:address":"Dorfstrasse 40",
    "sg:city":"Matzendorf",
    "sg:classifiers":[
        {
            "category":"Banks & Credit Unions",
            "subcategory":"Bank",
            "type":"Services"
        }
    ],
    "sg:phone":"+41 52 376 11 29",
    "sg:postcode":"4713",
    "sg:province":"Solothurn",
    "wof:name":"Raiffeisenbank Matzingen",
    "wof:placetype":"venue"
},
  "geometry": {"coordinates":[8.93412,47.519981],"type":"Point"}
}