{
  "type": "Feature",
  "properties": {
    "iso:country":"CH",
    "sg:address":"Gyrenstrasse 2",
    "sg:city":"Widen",
    "sg:orig_category":"Non-Classified Establishments",
    "sg:phone":"+41 31 359 12 12",
    "sg:postcode":"8967",
    "sg:province":"Aargau",
    "wof:name":"Fmh Consulting Services Ag",
    "wof:placetype":"venue"
},
  "geometry": {"coordinates":[7.4869909286,46.9317207336],"type":"Point"}
}