{
  "type": "Feature",
  "properties": {
    "iso:country":"CH",
    "sg:address":"R\u00fctistrasse 13",
    "sg:city":"Schlieren",
    "sg:orig_category":"Erwachsenenbildung U Unterricht",
    "sg:phone":"+41 17554044",
    "sg:postcode":"8952",
    "sg:province":"Z\u00fcrich",
    "wof:name":"Swf Ag",
    "wof:placetype":"venue"
},
  "geometry": {"coordinates":[8.4525289536,47.4009437561],"type":"Point"}
}