{
  "type": "Feature",
  "properties": {
    "iso:country":"CH",
    "sg:address":"Im Spitzler 7",
    "sg:city":"Urdorf",
    "sg:orig_category":"Detailhandel mit B\u00fcchern, Zeitungen, Schreib U Papeteriewaren",
    "sg:phone":"+41 17356000",
    "sg:postcode":"8902",
    "sg:province":"Z\u00fcrich",
    "wof:name":"B\u00fcrogros Ag",
    "wof:placetype":"venue"
},
  "geometry": {"coordinates":[8.421901,47.381512],"type":"Point"}
}