{
  "type": "Feature",
  "properties": {
    "iso:country":"CH",
    "sg:address":"In Der Weid 8 8942 Oberrieden. Postfach",
    "sg:city":"Oberrieden",
    "sg:orig_category":"RESTAURANTS: TEA-ROOMS",
    "sg:phone":"+41 17210020",
    "sg:postcode":"8942",
    "sg:province":"Z\u00fcrich",
    "wof:name":"Restaurant Frohe Aussicht Keller Urs",
    "wof:placetype":"venue"
},
  "geometry": {"coordinates":[8.5770606995,47.266998291],"type":"Point"}
}