{
  "type": "Feature",
  "properties": {
    "iso:country":"CH",
    "sg:address":"Ochsenalp 7050 Arosa. Postfach",
    "sg:city":"Molinis",
    "sg:orig_category":"RESTAURANTS: TEA-ROOMS",
    "sg:postcode":"7056",
    "sg:province":"Graubunden",
    "wof:name":"V\u00f6geli Ursula",
    "wof:placetype":"venue"
},
  "geometry": {"coordinates":[9.6791057587,46.7942466736],"type":"Point"}
}