{
  "type": "Feature",
  "properties": {
    "iso:country":"CH",
    "sg:address":"Langenhagstr. 48",
    "sg:city":"Rheineck",
    "sg:classifiers":[
        {
            "category":"Professional",
            "subcategory":"Engineering",
            "type":"Services"
        }
    ],
    "sg:phone":"+41 71 886 90 80",
    "sg:postcode":"9424",
    "sg:province":"St. Gallen",
    "sg:tags":[
        "machine",
        "-",
        "environment",
        "equipment",
        "machinery",
        "mechanical"
    ],
    "wof:name":"Ewag Ag",
    "wof:placetype":"venue"
},
  "geometry": {"coordinates":[9.5850191116,47.4741516113],"type":"Point"}
}