{
  "type": "Feature",
  "properties": {
    "iso:country":"CH",
    "sg:address":"Hauptstrasse 69 5070 Frick. Postfach",
    "sg:city":"Frick",
    "sg:orig_category":"Vermietung U Verpachtung von eigenen Immobilien",
    "sg:phone":"+41 62 871 51 51",
    "sg:postcode":"5070",
    "sg:province":"Aargau",
    "wof:name":"August Benz Immobilien & Bau Ag",
    "wof:placetype":"venue"
},
  "geometry": {"coordinates":[8.0227680206,47.5065498352],"type":"Point"}
}