{
  "type": "Feature",
  "properties": {
    "iso:country":"CH",
    "sg:address":"Dorfstrasse 34",
    "sg:city":"N\u00fcrensdorf",
    "sg:orig_category":"Herstellung von sonstigen keramischen Erzeugnissen",
    "sg:phone":"+41 18366935",
    "sg:postcode":"8309",
    "sg:province":"Z\u00fcrich",
    "wof:name":"Keramik Messmer Ruth",
    "wof:placetype":"venue"
},
  "geometry": {"coordinates":[8.6336307526,47.4589042664],"type":"Point"}
}