{
  "type": "Feature",
  "properties": {
    "iso:country":"CH",
    "sg:address":"Rue Des Vieilles-forges",
    "sg:city":"Bassecourt",
    "sg:orig_category":"Autogaragen Autospenglereien",
    "sg:phone":"+41 32 426 75 70",
    "sg:postcode":"2854",
    "sg:province":"Jura",
    "wof:name":"Fabrice Houlmann Garage & Carrosserie",
    "wof:placetype":"venue"
},
  "geometry": {"coordinates":[7.24927,47.341419],"type":"Point"}
}