{
  "type": "Feature",
  "properties": {
    "iso:country":"CH",
    "sg:address":"Engelbergstrasse 10",
    "sg:city":"Oftringen",
    "sg:orig_category":"Physiotherapie",
    "sg:phone":"+41 62 797 54 04",
    "sg:postcode":"4665",
    "sg:province":"Aargau",
    "wof:name":"Heidi Andres Physiotherapie",
    "wof:placetype":"venue"
},
  "geometry": {"coordinates":[7.9402318001,47.3026809692],"type":"Point"}
}