{
  "type": "Feature",
  "properties": {
    "iso:country":"CH",
    "sg:address":"Hohenzornstrasse 2",
    "sg:city":"Frauenfeld",
    "sg:orig_category":"RESTAURANTS: TEA-ROOMS",
    "sg:phone":"+41 52 721 17 73",
    "sg:postcode":"8500",
    "sg:province":"Thurgau",
    "wof:name":"Brauhaus Sternen Ag Restaurants Usw",
    "wof:placetype":"venue"
},
  "geometry": {"coordinates":[8.900639534,47.5584182739],"type":"Point"}
}