{
  "type": "Feature",
  "properties": {
    "iso:country":"CH",
    "sg:address":"Gyrenstrasse 50",
    "sg:city":"Widen",
    "sg:orig_category":"Vereine Frauen Vereine Gemeinn\u00fctzige",
    "sg:phone":"+41 76 340 51 88",
    "sg:postcode":"8967",
    "sg:province":"Aargau",
    "wof:name":"Landfrauenverein Widen",
    "wof:placetype":"venue"
},
  "geometry": {"coordinates":[8.3507032394,47.367805481],"type":"Point"}
}