{
  "type": "Feature",
  "properties": {
    "iso:country":"CH",
    "sg:address":"Fichtenweg 1",
    "sg:city":"Birsfelden",
    "sg:orig_category":"Maler U Glasergewerbe",
    "sg:phone":"+41 61 313 10 29",
    "sg:postcode":"4127",
    "sg:province":"Basel-Landschaft",
    "wof:name":"St\u00e4hli Christian Malergesch\u00e4ft",
    "wof:placetype":"venue"
},
  "geometry": {"coordinates":[7.6296992302,47.5496673584],"type":"Point"}
}