{
  "type": "Feature",
  "properties": {
    "iso:country":"CH",
    "sg:address":"Promenade 30",
    "sg:city":"Ponts-de-martel",
    "sg:orig_category":"Abwasserreinigung, Abfallbeseitigung U sonstige Entsorgung",
    "sg:phone":"+41 56 610 05 28",
    "sg:postcode":"2316",
    "sg:province":"Neuch\u00e2tel",
    "wof:name":"H.r. Kuhn Ag Sonderabf\u00e4lle; Entsorgung. Entsorgungsanlagen; Planung, Bau Usw",
    "wof:placetype":"venue"
},
  "geometry": {"coordinates":[8.27807,47.350536],"type":"Point"}
}