{
  "type": "Feature",
  "properties": {
    "iso:country":"CH",
    "sg:address":"Sonnmattstrasse 9",
    "sg:city":"Balterswil",
    "sg:orig_category":"Maurerarbeiten",
    "sg:phone":"+41 71 971 38 33",
    "sg:postcode":"8362",
    "sg:province":"Thurgau",
    "wof:name":"Bruno Ramsperger Kundenmaurerei",
    "wof:placetype":"venue"
},
  "geometry": {"coordinates":[8.9313087463,47.4513473511],"type":"Point"}
}