{
  "type": "Feature",
  "properties": {
    "iso:country":"CH",
    "sg:address":"Schlattstrasse 17",
    "sg:city":"B\u00f6ttstein",
    "sg:orig_category":"Herstellung von konfektionierten Textilwaren ohne Bekleidung",
    "sg:postcode":"5315",
    "sg:province":"Aargau",
    "wof:name":"Versluis, Bed And Table",
    "wof:placetype":"venue"
},
  "geometry": {"coordinates":[8.4649829865,47.3639602661],"type":"Point"}
}