{
  "type": "Feature",
  "properties": {
    "iso:country":"CH",
    "sg:address":"Haltenstrasse 317",
    "sg:city":"Niederscherli",
    "sg:orig_category":"Malerei",
    "sg:phone":"+41 31 849 18 21",
    "sg:postcode":"3145",
    "sg:province":"Bern",
    "wof:name":"Ulrich Studer Malergesch\u00e4ft",
    "wof:placetype":"venue"
},
  "geometry": {"coordinates":[7.402780056,46.8849105835],"type":"Point"}
}