{
  "type": "Feature",
  "properties": {
    "iso:country":"CH",
    "sg:address":"Gasse 1081",
    "sg:city":"Urn\u00e4sch",
    "sg:orig_category":"Gartenbau",
    "sg:phone":"+41 19101171",
    "sg:postcode":"9107",
    "sg:province":"Appenzell Ausserrhoden",
    "wof:name":"Walter W\u00fcthrich Gartenunterhalt",
    "wof:placetype":"venue"
},
  "geometry": {"coordinates":[8.6035299301,47.3145103455],"type":"Point"}
}