{
  "type": "Feature",
  "properties": {
    "iso:country":"CH",
    "sg:address":"Arbachstrasse 4",
    "sg:city":"Baar",
    "sg:orig_category":"Detailhandel mit Computern U Software Softwareentwicklung U beratung",
    "sg:postcode":"6340",
    "sg:province":"Zug",
    "wof:name":"Supportworld Serves Your Eworld",
    "wof:placetype":"venue"
},
  "geometry": {"coordinates":[8.532615,47.182007],"type":"Point"}
}