{
  "type": "Feature",
  "properties": {
    "iso:country":"CH",
    "sg:address":"Bahnhofstrasse 12 3600 Thun. Postfach",
    "sg:city":"Thun",
    "sg:orig_category":"Versicherungen Generalagenturen",
    "sg:phone":"+41 41 870 00 70",
    "sg:postcode":"3601",
    "sg:province":"Bern",
    "wof:name":"Winterthur-versicherungen Generalagentur Uri",
    "wof:placetype":"venue"
},
  "geometry": {"coordinates":[8.6446094513,46.8802909851],"type":"Point"}
}