{
  "type": "Feature",
  "properties": {
    "iso:country":"CH",
    "sg:address":"Avenue Mercier De Molin 2",
    "sg:city":"Sierre",
    "sg:orig_category":"Detailhandel mit Waren verschiedener Art, Hauptrichtung Nahrungsmittel",
    "sg:postcode":"3960",
    "sg:province":"Valais",
    "wof:name":"Arnold Anika",
    "wof:placetype":"venue"
},
  "geometry": {"coordinates":[7.5285801888,46.2921409607],"type":"Point"}
}