{
  "type": "Feature",
  "properties": {
    "iso:country":"CH",
    "sg:address":"Marktgasse 11",
    "sg:city":"Weesen",
    "sg:orig_category":"Fachdetailhandel in Verkaufsr\u00e4umen",
    "sg:phone":"+41 27 957 25 05",
    "sg:postcode":"8872",
    "sg:province":"St. Gallen",
    "wof:name":"Sporthaus Anthametten & Venetz",
    "wof:placetype":"venue"
},
  "geometry": {"coordinates":[7.9573631287,46.0964317322],"type":"Point"}
}