{
  "type": "Feature",
  "properties": {
    "iso:country":"CH",
    "sg:address":"Bruggmatt 1 6130 Willisau. Postfach 80",
    "sg:city":"Willisau",
    "sg:orig_category":"Interessenvertretungen",
    "sg:phone":"+41 41 970 15 88",
    "sg:postcode":"6130",
    "sg:province":"Luzern",
    "wof:name":"Meyers Eugen Untertor-stiftung",
    "wof:placetype":"venue"
},
  "geometry": {"coordinates":[7.9928441048,47.1224403381],"type":"Point"}
}