{
  "type": "Feature",
  "properties": {
    "iso:country":"CH",
    "sg:address":"Toulettes Route Des",
    "sg:city":"Bluche-randogne",
    "sg:orig_category":"Unclassifiable Establishments",
    "sg:phone":"+41 27 480 24 55",
    "sg:postcode":"3975",
    "sg:province":"Valais",
    "wof:name":"M\u00e9trailler Jean-luc, Paysagiste",
    "wof:placetype":"venue"
},
  "geometry": {"coordinates":[7.5151138306,46.2997512817],"type":"Point"}
}