{
  "type": "Feature",
  "properties": {
    "iso:country":"CH",
    "sg:address":"Schulhausstrasse 16 8887 Mels. Postfach",
    "sg:city":"Mels",
    "sg:orig_category":"Bauspenglerei Zimmerei, Dachdeckerei, Bauspenglerei U Abdichtung",
    "sg:phone":"+41 91 648 17 91",
    "sg:postcode":"8887",
    "sg:province":"St. Gallen",
    "wof:name":"Godenzi Ivo",
    "wof:placetype":"venue"
},
  "geometry": {"coordinates":[8.975439,45.901524],"type":"Point"}
}