{
  "type": "Feature",
  "properties": {
    "iso:country":"CH",
    "sg:address":"Linde 12",
    "sg:city":"Rothenhausen",
    "sg:orig_category":"Unternehmensberatung",
    "sg:phone":"+41 71 622 15 15",
    "sg:postcode":"9565",
    "sg:province":"Thurgau",
    "wof:name":"Werren Unternehmensberatung",
    "wof:placetype":"venue"
},
  "geometry": {"coordinates":[9.0980548859,47.5500717163],"type":"Point"}
}