{
  "type": "Feature",
  "properties": {
    "iso:country":"CH",
    "sg:address":"Im Kupferschmied 14",
    "sg:city":"Aarburg",
    "sg:orig_category":"Herstellung von Duft U K\u00f6rperpflegemitteln",
    "sg:postcode":"4663",
    "sg:province":"Aargau",
    "wof:name":"Hauri-philipp Fusspflege Und Fussreflexzonen-massage",
    "wof:placetype":"venue"
},
  "geometry": {"coordinates":[7.8988471031,47.328327179],"type":"Point"}
}