{
  "type": "Feature",
  "properties": {
    "iso:country":"CH",
    "sg:address":"Adlerstrasse 19",
    "sg:city":"Magden",
    "sg:orig_category":"Sportvereine Ballsport Handball",
    "sg:phone":"+41 61 841 15 29",
    "sg:postcode":"4312",
    "sg:province":"Aargau",
    "wof:name":"Tv Magden",
    "wof:placetype":"venue"
},
  "geometry": {"coordinates":[7.8131389618,47.5261726379],"type":"Point"}
}