{
  "type": "Feature",
  "properties": {
    "iso:country":"CH",
    "sg:address":"Unterdorfstrasse 85",
    "sg:city":"Widnau",
    "sg:orig_category":"Autogaragen",
    "sg:phone":"+41 71 727 20 40",
    "sg:postcode":"9443",
    "sg:province":"St. Gallen",
    "wof:name":"Christian Jakob Ag",
    "wof:placetype":"venue"
},
  "geometry": {"coordinates":[9.634314,47.415604],"type":"Point"}
}