{
  "type": "Feature",
  "properties": {
    "iso:country":"CH",
    "sg:address":"Geerenackerstrasse 15 8044 Gockhausen. Postfach",
    "sg:city":"Gockhausen",
    "sg:classifiers":[
        {
            "category":"Professional",
            "subcategory":"Employment Agencies",
            "type":"Services"
        }
    ],
    "sg:postcode":"8044",
    "sg:province":"Z\u00fcrich",
    "sg:tags":[
        "personal",
        "u",
        "stellenvermittlung"
    ],
    "wof:name":"Egli + Partner, Hme Human Master Evolution",
    "wof:placetype":"venue"
},
  "geometry": {"coordinates":[8.6022882462,47.3807983398],"type":"Point"}
}