{
  "type": "Feature",
  "properties": {
    "iso:country":"CH",
    "sg:address":"Fluhweg 10",
    "sg:city":"Liestal",
    "sg:orig_category":"Unclassifiable Establishments",
    "sg:postcode":"4410",
    "sg:province":"Basel-Landschaft",
    "wof:name":"Frei Renato, Hafner / Plattenleger",
    "wof:placetype":"venue"
},
  "geometry": {"coordinates":[7.741519928,47.4819107056],"type":"Point"}
}