{
  "type": "Feature",
  "properties": {
    "iso:country":"CH",
    "sg:address":"Neuend\u00f6rferstrasse 1 4624 H\u00e4rkingen. Postfach",
    "sg:city":"H\u00e4rkingen",
    "sg:orig_category":"RESTAURANTS: TEA-ROOMS",
    "sg:phone":"+41 62 398 10 85",
    "sg:postcode":"4624",
    "sg:province":"Solothurn",
    "wof:name":"Ghilardelli Lorenzo Gasthaus Zum Lamm",
    "wof:placetype":"venue"
},
  "geometry": {"coordinates":[7.8142900467,47.3079185486],"type":"Point"}
}