{
  "type": "Feature",
  "properties": {
    "iso:country":"CH",
    "sg:address":"Stritenstrasse 41",
    "sg:city":"Neuenegg",
    "sg:orig_category":"Softwareentwicklung U beratung",
    "sg:phone":"+41 31 741 14 11",
    "sg:postcode":"3176",
    "sg:province":"Bern",
    "wof:name":"Com Pas Froidevaux Pascal",
    "wof:placetype":"venue"
},
  "geometry": {"coordinates":[7.3234848976,46.8951835632],"type":"Point"}
}