{
  "type": "Feature",
  "properties": {
    "iso:country":"CH",
    "sg:address":"Chemin De Val\u00e9rie 23",
    "sg:city":"Chamb\u00e9sy",
    "sg:orig_category":"P\u00e9dicure",
    "sg:phone":"+41 22 751 20 53",
    "sg:postcode":"1292",
    "sg:province":"Gen\u00e8ve",
    "wof:name":"Mich\u00e8le Kollau P\u00e9dicure",
    "wof:placetype":"venue"
},
  "geometry": {"coordinates":[6.2237911224,46.2644424438],"type":"Point"}
}