{
  "type": "Feature",
  "properties": {
    "iso:country":"CH",
    "sg:address":"Frankengasse 6",
    "sg:city":"Z\u00fcrich",
    "sg:orig_category":"Grosshandel mit Getreide, Saatgut U Futtermitteln",
    "sg:phone":"+41 22 791 00 70",
    "sg:postcode":"8001",
    "sg:province":"Z\u00fcrich",
    "wof:name":"Pms Commercial Sarl",
    "wof:placetype":"venue"
},
  "geometry": {"coordinates":[6.1268978119,46.2373313904],"type":"Point"}
}