{
  "type": "Feature",
  "properties": {
    "iso:country":"CH",
    "sg:address":"M\u00fchlegasse 12a",
    "sg:city":"Baar",
    "sg:orig_category":"HERSTELLUNG VON GER\u00c4TEN DER ELEKTRIZIT\u00c4TSERZEUGUNG, -VERTEILUNG U.\u00c4",
    "sg:phone":"+41 41 766 09 03",
    "sg:postcode":"6340",
    "sg:province":"Zug",
    "wof:name":"Group Ag Bota Manaement",
    "wof:placetype":"venue"
},
  "geometry": {"coordinates":[8.5280370712,47.1993522644],"type":"Point"}
}