{
  "type": "Feature",
  "properties": {
    "iso:country":"CH",
    "sg:address":"Vallon Du Seyon 2000 Neuenburg Case Postale",
    "sg:city":"Neuenburg",
    "sg:orig_category":"Pensionskassen",
    "sg:postcode":"2000",
    "sg:province":"Neuch\u00e2tel",
    "wof:name":"Fonds Des Oeuvres Sociales En Faveur Du Personnel De La Soci\u00e9t\u00e9 Coop\u00e9rative De Menuiserie, \u00e9b\u00e9nisterie, Travaux En B\u00e2timents",
    "wof:placetype":"venue"
},
  "geometry": {"coordinates":[6.9287309647,46.9921035767],"type":"Point"}
}