{
  "type": "Feature",
  "properties": {
    "iso:country":"CH",
    "sg:address":"Beundenweg 15a",
    "sg:city":"Pieterlen",
    "sg:orig_category":"Sportvereine Turnen Vereine Damen",
    "sg:phone":"+41 32 373 20 70",
    "sg:postcode":"2542",
    "sg:province":"Bern",
    "wof:name":"Dtv & Frauenriege Stv Br\u00fcgg",
    "wof:placetype":"venue"
},
  "geometry": {"coordinates":[7.2990369797,47.1171760559],"type":"Point"}
}