{
  "type": "Feature",
  "properties": {
    "iso:country":"CH",
    "sg:address":"Aarwangenstrasse 1",
    "sg:city":"Wynau",
    "sg:orig_category":"Gartenbau",
    "sg:phone":"+41 41 711 11 45",
    "sg:postcode":"4923",
    "sg:province":"Bern",
    "wof:name":"Stocklin Baumschulen Ag",
    "wof:placetype":"venue"
},
  "geometry": {"coordinates":[7.8079361916,47.2612686157],"type":"Point"}
}