{
  "type": "Feature",
  "properties": {
    "iso:country":"CH",
    "sg:address":"8053 Z\u00fcrich. Postfach",
    "sg:city":"Z\u00fcrich",
    "sg:orig_category":"Pensionskassen",
    "sg:phone":"+41 12257070",
    "sg:postcode":"8001",
    "sg:province":"Z\u00fcrich",
    "wof:name":"Stiftung F\u00fcr Personalf\u00fcrsorge Der Firma Kahn Siegfried Trading Ag",
    "wof:placetype":"venue"
},
  "geometry": {"coordinates":[8.5992002487,47.3622283936],"type":"Point"}
}