{
  "type": "Feature",
  "properties": {
    "iso:country":"CH",
    "sg:address":"Bleichmattstrasse 43",
    "sg:city":"Olten",
    "sg:orig_category":"Herstellung von elektrischen Lampen U Leuchten",
    "sg:phone":"+41 55 240 65 56",
    "sg:postcode":"4600",
    "sg:province":"Solothurn",
    "wof:name":"Gerwald Finsel Lampenfabrikation",
    "wof:placetype":"venue"
},
  "geometry": {"coordinates":[8.865644455,47.2656402588],"type":"Point"}
}