{
  "type": "Feature",
  "properties": {
    "iso:country":"CH",
    "sg:address":"Flawilerstrasse 52",
    "sg:city":"Oberuzwil",
    "sg:orig_category":"Kaminfeger",
    "sg:phone":"+41 71 951 35 14",
    "sg:postcode":"9242",
    "sg:province":"St. Gallen",
    "wof:name":"Willi Kn\u00f6pfel Kaminfegermeister",
    "wof:placetype":"venue"
},
  "geometry": {"coordinates":[9.1325216293,47.4272689819],"type":"Point"}
}