{
  "type": "Feature",
  "properties": {
    "iso:country":"CH",
    "sg:address":"R\u00fctimeyerstrasse 70 4054 Basel. Postfach",
    "sg:city":"Basel",
    "sg:orig_category":"Betrieb von Sportanlagen",
    "sg:postcode":"4051",
    "sg:province":"Basel-Stadt",
    "wof:name":"Bowling Sektion Baselland Amateurbowling; Organisation U. F\u00f6rderg. Usw.",
    "wof:placetype":"venue"
},
  "geometry": {"coordinates":[7.576044,47.548115],"type":"Point"}
}