{
  "type": "Feature",
  "properties": {
    "iso:country":"CH",
    "sg:address":"Hauptstrasse 10",
    "sg:city":"Erlinsbach",
    "sg:orig_category":"Unclassifiable Establishments",
    "sg:postcode":"5018",
    "sg:province":"Solothurn",
    "wof:name":"Guido Eggnauer Beschriftungen",
    "wof:placetype":"venue"
},
  "geometry": {"coordinates":[8.0070695877,47.4065284729],"type":"Point"}
}