{
  "type": "Feature",
  "properties": {
    "iso:country":"CH",
    "sg:address":"Eschfeld 9",
    "sg:city":"Knonau",
    "sg:orig_category":"Kaminfeger",
    "sg:phone":"+41 17670828",
    "sg:postcode":"8934",
    "sg:province":"Z\u00fcrich",
    "wof:name":"Paul Ammann Kaminfegergesch\u00e4ft",
    "wof:placetype":"venue"
},
  "geometry": {"coordinates":[8.4658241272,47.2191848755],"type":"Point"}
}