{
  "type": "Feature",
  "properties": {
    "iso:country":"CH",
    "sg:address":"Waserstrasse 42",
    "sg:city":"Z\u00fcrich",
    "sg:orig_category":"Sonstiges Textilgewerbe Textilgewerbe",
    "sg:phone":"+41 71 898 82 42",
    "sg:postcode":"8053",
    "sg:province":"Z\u00fcrich",
    "wof:name":"Createx Wuchner Horst Ag",
    "wof:placetype":"venue"
},
  "geometry": {"coordinates":[9.5116701126,47.4465560913],"type":"Point"}
}