{
  "type": "Feature",
  "properties": {
    "iso:country":"CH",
    "sg:address":"Casa Cigale",
    "sg:city":"Malvaglia",
    "sg:orig_category":"Elektroinstallation",
    "sg:phone":"+41 91 880 30 30",
    "sg:postcode":"6713",
    "sg:province":"Ticino",
    "wof:name":"Eloc Ag Telefon-& Schwachstromanlagen",
    "wof:placetype":"venue"
},
  "geometry": {"coordinates":[8.9850082397,46.4072380066],"type":"Point"}
}