{
  "type": "Feature",
  "properties": {
    "iso:country":"CH",
    "sg:address":"Breisacherstrasse 73",
    "sg:city":"Basel",
    "sg:classifiers":[
        {
            "category":"Restaurant",
            "type":"Food & Drink"
        }
    ],
    "sg:phone":"+41 61 692 00 60",
    "sg:postcode":"4057",
    "sg:province":"Basel-Stadt",
    "wof:name":"Restaurant Settebello",
    "wof:placetype":"venue"
},
  "geometry": {"coordinates":[7.5886149406,47.5672874451],"type":"Point"}
}