{
  "type": "Feature",
  "properties": {
    "iso:country":"CH",
    "sg:address":"Sihlbruggstrasse 6345 Neuheim. Postfach 75",
    "sg:city":"Neuheim",
    "sg:orig_category":"Gewinnung von Kies U Sand Herstellung von Transportbeton",
    "sg:phone":"+41 41 757 17 00",
    "sg:postcode":"6345",
    "sg:province":"Zug",
    "wof:name":"Sand Ag Neuheim",
    "wof:placetype":"venue"
},
  "geometry": {"coordinates":[8.579656,47.204041],"type":"Point"}
}