{
  "type": "Feature",
  "properties": {
    "iso:country":"CH",
    "sg:address":"Marktgasse 8",
    "sg:city":"Appenzell",
    "sg:orig_category":"Non-Classified Establishments",
    "sg:phone":"+41 41 630 38 26",
    "sg:postcode":"9050",
    "sg:province":"Appenzell Innerhoden",
    "wof:name":"Ci Concept Informatiksysteme Ag",
    "wof:placetype":"venue"
},
  "geometry": {"coordinates":[8.3104372025,46.9823074341],"type":"Point"}
}