{
  "type": "Feature",
  "properties": {
    "iso:country":"CH",
    "sg:address":"Gemeindekanzlei",
    "sg:city":"Oberneunforn",
    "sg:orig_category":"Landesverteidigung, Sozialversicherung \u00d6ffentliche Verwaltung",
    "sg:phone":"+41 52 745 24 75",
    "sg:postcode":"8526",
    "sg:province":"Thurgau",
    "wof:name":"Zivilschutzstelle Neunforn",
    "wof:placetype":"venue"
},
  "geometry": {"coordinates":[8.7669754028,47.6066246033],"type":"Point"}
}