{
  "type": "Feature",
  "properties": {
    "iso:country":"CH",
    "sg:address":"Grabengasse 17",
    "sg:city":"Lichtensteig",
    "sg:classifiers":[
        {
            "category":"Restaurant",
            "type":"Food & Drink"
        }
    ],
    "sg:phone":"+41 71 988 15 65",
    "sg:postcode":"9620",
    "sg:province":"St. Gallen",
    "sg:tags":[
        "tea-rooms",
        "restaurants"
    ],
    "wof:name":"Rest. Bar Ochsen, Suter-b\u00fcrge Ruth",
    "wof:placetype":"venue"
},
  "geometry": {"coordinates":[9.0882854462,47.3229064941],"type":"Point"}
}