{
  "type": "Feature",
  "properties": {
    "iso:country":"CH",
    "sg:address":"8752",
    "sg:city":"N\u00e4fels",
    "sg:orig_category":"Pensionskassen",
    "sg:postcode":"8752",
    "sg:province":"Glarus",
    "wof:name":"Personalvorsorgestiftung Der Fritz Landolt Ag",
    "wof:placetype":"venue"
},
  "geometry": {"coordinates":[9.0625753403,47.0999641418],"type":"Point"}
}