{
  "type": "Feature",
  "properties": {
    "iso:country":"CH",
    "sg:address":"Zugerstrasse 32",
    "sg:city":"Unter\u00e4geri",
    "sg:orig_category":"Fachdetailhandel mit pharmazeutischen Produkten",
    "sg:phone":"+41 81 756 38 38",
    "sg:postcode":"6314",
    "sg:province":"Zug",
    "wof:name":"Zentrums Apotheke Ag",
    "wof:placetype":"venue"
},
  "geometry": {"coordinates":[9.4725503922,47.1660575867],"type":"Point"}
}