{
  "type": "Feature",
  "properties": {
    "iso:country":"CH",
    "sg:address":"Frauenfelderstrasse 106",
    "sg:city":"Stadel(winterthur)",
    "sg:orig_category":"Zahnarztpraxen",
    "sg:phone":"+41 52 242 94 94",
    "sg:postcode":"8404",
    "sg:province":"Z\u00fcrich",
    "wof:name":"Dr. Med. Dent. Martin Heitz Praxis F\u00fcr Kieferorthop\u00e4die",
    "wof:placetype":"venue"
},
  "geometry": {"coordinates":[8.75822258,47.5065689087],"type":"Point"}
}