{
  "type": "Feature",
  "properties": {
    "iso:country":"CH",
    "sg:address":"Seidengasse 43",
    "sg:city":"Meilen",
    "sg:orig_category":"Herstellung von K\u00fcchenm\u00f6beln",
    "sg:postcode":"8706",
    "sg:province":"Z\u00fcrich",
    "wof:name":"Savardi & Rossi Sa",
    "wof:placetype":"venue"
},
  "geometry": {"coordinates":[8.6552248001,47.2667350769],"type":"Point"}
}