{
  "type": "Feature",
  "properties": {
    "iso:country":"CH",
    "sg:address":"Oberdorf 1 8554 Eschikofen. Postfach",
    "sg:city":"Eschikofen",
    "sg:orig_category":"Herstellung von sonstigen Nahrungsmitteln",
    "sg:postcode":"8554",
    "sg:province":"Thurgau",
    "wof:name":"Friedrich Meyer",
    "wof:placetype":"venue"
},
  "geometry": {"coordinates":[9.0055370331,47.5798606873],"type":"Point"}
}