{
  "type": "Feature",
  "properties": {
    "iso:country":"CH",
    "sg:address":"4204",
    "sg:city":"Himmelried",
    "sg:orig_category":"Haltung von Rindern",
    "sg:postcode":"4204",
    "sg:province":"Solothurn",
    "wof:name":"Schwarzfleckviehzuchtgenossenschaft Von Sch\u00fcpbach Und Umgebung",
    "wof:placetype":"venue"
},
  "geometry": {"coordinates":[7.7352838516,46.9267997742],"type":"Point"}
}