{
  "type": "Feature",
  "properties": {
    "iso:country":"CH",
    "sg:address":"Gotthardstrasse 76",
    "sg:city":"Schattdorf",
    "sg:classifiers":[
        {
            "category":"Restaurant",
            "type":"Food & Drink"
        }
    ],
    "sg:phone":"+41 41 870 14 29",
    "sg:postcode":"6467",
    "sg:province":"Uri",
    "wof:name":"Gasthaus St.gotthard",
    "wof:placetype":"venue"
},
  "geometry": {"coordinates":[8.6478023529,46.8619689941],"type":"Point"}
}