{
  "type": "Feature",
  "properties": {
    "iso:country":"CH",
    "sg:address":"Haus Gotthard",
    "sg:city":"Gossau",
    "sg:classifiers":[
        {
            "category":"Professional",
            "subcategory":"Computer Services",
            "type":"Services"
        }
    ],
    "sg:phone":"+41 79 219 99 58",
    "sg:postcode":"8625",
    "sg:province":"Z\u00fcrich",
    "sg:tags":[
        "development",
        "software"
    ],
    "wof:name":"Torecom Software Ag",
    "wof:placetype":"venue"
},
  "geometry": {"coordinates":[8.7609901428,47.3074913025],"type":"Point"}
}