{
  "type": "Feature",
  "properties": {
    "iso:country":"CH",
    "sg:address":"Libert\u00e9 Place De La 2",
    "sg:city":"Delsberg",
    "sg:orig_category":"Detailhandel mit Bekleidung",
    "sg:postcode":"2800",
    "sg:province":"Jura",
    "wof:name":"Polmag S\u00e0rl",
    "wof:placetype":"venue"
},
  "geometry": {"coordinates":[7.34397,47.365356],"type":"Point"}
}