{
  "type": "Feature",
  "properties": {
    "iso:country":"CH",
    "sg:address":"Alte St. Gallerstrasse 36",
    "sg:city":"R\u00e4terschen",
    "sg:classifiers":[
        {
            "category":"Restaurant",
            "type":"Food & Drink"
        }
    ],
    "sg:phone":"+41 52 363 11 68",
    "sg:postcode":"8352",
    "sg:province":"Z\u00fcrich",
    "wof:name":"Restaurant Weisses Schaf",
    "wof:placetype":"venue"
},
  "geometry": {"coordinates":[8.8023319244,47.505317688],"type":"Point"}
}