{
  "type": "Feature",
  "properties": {
    "iso:country":"CH",
    "sg:address":"Promenadestrasse 2",
    "sg:city":"Zurzach",
    "sg:orig_category":"Detailhandel mit Textilien Sonstiger Detailhandel mit Metallwaren, Anstrichmitteln, Glaswaren, Bau U",
    "sg:phone":"+41 56 249 31 71",
    "sg:postcode":"5330",
    "sg:province":"Aargau",
    "wof:name":"Bastelzentrum Wundert\u00fcte St\u00f6hr",
    "wof:placetype":"venue"
},
  "geometry": {"coordinates":[8.2953262329,47.5864028931],"type":"Point"}
}