{
  "type": "Feature",
  "properties": {
    "iso:country":"CH",
    "sg:address":"Loi Via Al",
    "sg:city":"Novazzano",
    "sg:orig_category":"Grosshandel mit Holz U Baustoffen",
    "sg:phone":"+41 91 647 41 55",
    "sg:postcode":"6883",
    "sg:province":"Ticino",
    "wof:name":"Ferrari Tiziano",
    "wof:placetype":"venue"
},
  "geometry": {"coordinates":[8.9822053909,45.8426856995],"type":"Point"}
}