{
  "type": "Feature",
  "properties": {
    "iso:country":"CH",
    "sg:address":"Arbonerstrasse 40 8590 Romanshorn. Postfach 56",
    "sg:city":"Romanshorn",
    "sg:orig_category":"Interessenvertretungen",
    "sg:postcode":"8590",
    "sg:province":"Thurgau",
    "wof:name":"Roboro-stiftung",
    "wof:placetype":"venue"
},
  "geometry": {"coordinates":[9.3676328659,47.5612335205],"type":"Point"}
}