{
  "type": "Feature",
  "properties": {
    "iso:country":"CH",
    "sg:address":"Battenhusstrasse 4 9062 Lustm\u00fchle. Postfach",
    "sg:city":"Lustm\u00fchle",
    "sg:orig_category":"Zahnarztpraxen",
    "sg:phone":"+41 71 333 23 53",
    "sg:postcode":"9062",
    "sg:province":"Appenzell Ausserrhoden",
    "wof:name":"Dr. Med. Dent. Siegfried Nigg Zahnarzt",
    "wof:placetype":"venue"
},
  "geometry": {"coordinates":[9.3584527969,47.3997764587],"type":"Point"}
}