{
  "type": "Feature",
  "properties": {
    "iso:country":"CH",
    "sg:address":"Fr\u00f6hlisberg 2",
    "sg:city":"Orpund",
    "sg:orig_category":"Vereine Vogel-& Naturschutz",
    "sg:phone":"+41 31 951 61 20",
    "sg:postcode":"2552",
    "sg:province":"Bern",
    "wof:name":"Ornithol.ver.g\u00fcmligen & Umg.",
    "wof:placetype":"venue"
},
  "geometry": {"coordinates":[7.5001192093,46.924823761],"type":"Point"}
}