{
  "type": "Feature",
  "properties": {
    "iso:country":"CH",
    "sg:address":"Route De Soleure 2 2072 St-blaise Case Postale 20",
    "sg:city":"St-blaise",
    "sg:orig_category":"Instandhaltung U Reparatur von Automobilen",
    "sg:phone":"+41 32 753 50 81",
    "sg:postcode":"2072",
    "sg:province":"Neuch\u00e2tel",
    "wof:name":"Facchinetti Claude, Garage Poids-lourds",
    "wof:placetype":"venue"
},
  "geometry": {"coordinates":[6.9920258522,47.0136032104],"type":"Point"}
}