{
  "type": "Feature",
  "properties": {
    "iso:country":"CH",
    "sg:address":"Egelseestrasse 36",
    "sg:city":"Kreuzlingen",
    "sg:classifiers":[
        {
            "category":"Personal",
            "subcategory":"Nail Salon",
            "type":"Services"
        }
    ],
    "sg:phone":"+41 71 672 58 66",
    "sg:postcode":"8280",
    "sg:province":"Thurgau",
    "sg:tags":[
        "manicure"
    ],
    "wof:name":"Natascha Stump Permanent-nagelkosmetik",
    "wof:placetype":"venue"
},
  "geometry": {"coordinates":[9.1790046692,47.6429634094],"type":"Point"}
}