{
  "type": "Feature",
  "properties": {
    "iso:country":"CH",
    "sg:address":"Kirchg\u00e4ngli 6",
    "sg:city":"Beringen",
    "sg:orig_category":"Fahrschulen, Flugschulen",
    "sg:phone":"+41 52 685 34 34",
    "sg:postcode":"8222",
    "sg:province":"Schaffhausen",
    "wof:name":"Fahr Und Theorieschule Schwyn Walter Ag",
    "wof:placetype":"venue"
},
  "geometry": {"coordinates":[8.5728406906,47.6987113953],"type":"Point"}
}