{
  "type": "Feature",
  "properties": {
    "addr:full":"Rue Pierre-pequignat 12 Pruntrut Jura 2900",
    "addr:housenumber":"12",
    "addr:postcode":"2900",
    "addr:street":"Rue Pierre-Pequignat;Jura",
    "iso:country":"CH",
    "sg:address":"Rue Pierre-pequignat 12",
    "sg:city":"Pruntrut",
    "sg:classifiers":[
        {
            "category":"Banks & Credit Unions",
            "subcategory":"Bank",
            "type":"Services"
        }
    ],
    "sg:phone":"+41 4166666441",
    "sg:postcode":"2900",
    "sg:province":"Jura",
    "wof:name":"Credit Suisse",
    "wof:placetype":"venue"
},
  "geometry": {"coordinates":[7.074698,47.417271],"type":"Point"}
}