{
  "type": "Feature",
  "properties": {
    "iso:country":"CH",
    "sg:address":"7235",
    "sg:city":"Fideris",
    "sg:orig_category":"Herstellung von Konstruktionsteilen, Fertigbauteilen U Ausbauelementen aus Holz Zimmerei, Ingenieurh",
    "sg:phone":"+41 81 332 21 13",
    "sg:postcode":"7235",
    "sg:province":"Graubunden",
    "wof:name":"Gujan & Co.",
    "wof:placetype":"venue"
},
  "geometry": {"coordinates":[9.7427120209,46.9152984619],"type":"Point"}
}