{
  "type": "Feature",
  "properties": {
    "addr:full":"Bahnhofstrasse 14 Benken St. Gallen 8717",
    "addr:housenumber":"14;st.",
    "addr:postcode":"8717",
    "addr:street":"Bahnhofstrasse;Benken",
    "iso:country":"CH",
    "sg:address":"Bahnhofstrasse 14",
    "sg:city":"Benken",
    "sg:classifiers":[
        {
            "category":"Professional",
            "subcategory":"Advertising",
            "type":"Services"
        }
    ],
    "sg:phone":"+41 55 283 37 27",
    "sg:postcode":"8717",
    "sg:province":"St. Gallen",
    "sg:tags":[
        "poster"
    ],
    "wof:name":"Druckerei Kartenverlag & Druckgrafik",
    "wof:placetype":"venue"
},
  "geometry": {"coordinates":[9.006198,47.201332],"type":"Point"}
}