{
  "type": "Feature",
  "properties": {
    "iso:country":"CH",
    "sg:address":"G\u00fcterstr. 2",
    "sg:city":"Gretzenbach",
    "sg:classifiers":[
        {
            "category":"Home & Garden",
            "subcategory":"Furniture",
            "type":"Retail Goods"
        }
    ],
    "sg:phone":"+41 62 849 43 33",
    "sg:postcode":"5014",
    "sg:province":"Solothurn",
    "sg:tags":[
        "household",
        "wood"
    ],
    "wof:name":"Hans Br\u00dcgger",
    "wof:placetype":"venue"
},
  "geometry": {"coordinates":[7.9913620949,47.3609733582],"type":"Point"}
}