{
  "type": "Feature",
  "properties": {
    "iso:country":"CH",
    "sg:address":"Barberina Via Val 6808 Torricella. Postfach",
    "sg:city":"Torricella",
    "sg:orig_category":"Erbringung von Dienstleistungen f\u00fcr Unternehmen",
    "sg:postcode":"6808",
    "sg:province":"Ticino",
    "wof:name":"Arkroom Sa",
    "wof:placetype":"venue"
},
  "geometry": {"coordinates":[8.9268951416,46.0569496155],"type":"Point"}
}