{
  "type": "Feature",
  "properties": {
    "iso:country":"CH",
    "sg:address":"Zona Industriale 4",
    "sg:city":"Rancate",
    "sg:orig_category":"Grosshandel mit Holz U Baustoffen",
    "sg:phone":"+41 91 646 49 81",
    "sg:postcode":"6862",
    "sg:province":"Ticino",
    "wof:name":"Cc Cottoceramiche Sa Pavimenti; Import., Esport., Comm. Ecc",
    "wof:placetype":"venue"
},
  "geometry": {"coordinates":[8.9681348801,45.8714981079],"type":"Point"}
}