{
  "type": "Feature",
  "properties": {
    "iso:country":"CH",
    "sg:address":"Kantonsstrasse 45",
    "sg:city":"Visp",
    "sg:orig_category":"G\u00fcterbef\u00f6rderung im Strassenverkehr",
    "sg:phone":"+41 27 945 13 50",
    "sg:postcode":"3930",
    "sg:province":"Valais",
    "wof:name":"Ernst Domig Transporte",
    "wof:placetype":"venue"
},
  "geometry": {"coordinates":[7.8920860291,46.294128418],"type":"Point"}
}