{
  "type": "Feature",
  "properties": {
    "iso:country":"CH",
    "sg:address":"Schmiedgasse 48",
    "sg:city":"Stans",
    "sg:orig_category":"Sportvereine Ballsport Squash",
    "sg:phone":"+41 71 923 93 03",
    "sg:postcode":"6370",
    "sg:province":"Nidwalden",
    "wof:name":"Squash Club Stelz",
    "wof:placetype":"venue"
},
  "geometry": {"coordinates":[9.0534296036,47.4628791809],"type":"Point"}
}