{
  "type": "Feature",
  "properties": {
    "iso:country":"CH",
    "sg:address":"Allmendstrasse 6a",
    "sg:city":"M\u00fchlethurnen",
    "sg:orig_category":"Instandhaltung U Reparatur von Automobilen",
    "sg:phone":"+41 31 809 13 18",
    "sg:postcode":"3127",
    "sg:province":"Bern",
    "wof:name":"Fritz Wyder Thurnen-garage",
    "wof:placetype":"venue"
},
  "geometry": {"coordinates":[7.5145688057,46.8159294128],"type":"Point"}
}