{
  "type": "Feature",
  "properties": {
    "iso:country":"CH",
    "sg:address":"Hubelstrasse 18",
    "sg:city":"Triengen",
    "sg:classifiers":[
        {
            "category":"Education",
            "subcategory":"Library",
            "type":"Public Place"
        }
    ],
    "sg:phone":"+41 41 933 15 32",
    "sg:postcode":"6234",
    "sg:province":"Luzern",
    "sg:tags":[
        "u",
        "bibliotheken",
        "archive"
    ],
    "wof:name":"Katholische Pfarrbibliothek",
    "wof:placetype":"venue"
},
  "geometry": {"coordinates":[8.077841,47.233921],"type":"Point"}
}