{
  "type": "Feature",
  "properties": {
    "iso:country":"CH",
    "sg:address":"R\u00f6merstrasse",
    "sg:city":"Biel/bienne",
    "sg:orig_category":"Granit",
    "sg:phone":"+41 62 293 35 71",
    "sg:postcode":"2500",
    "sg:province":"Bern",
    "wof:name":"Steinbruch Ch\u00e4nel Wisen Ag",
    "wof:placetype":"venue"
},
  "geometry": {"coordinates":[7.8959298134,47.3936080933],"type":"Point"}
}