{
  "type": "Feature",
  "properties": {
    "iso:country":"CH",
    "sg:address":"Fabrikstrasse 1",
    "sg:city":"Erlen",
    "sg:classifiers":[
        {
            "category":"Real Estate",
            "subcategory":"Real Estate Services",
            "type":"Services"
        }
    ],
    "sg:phone":"+41 71 649 22 46",
    "sg:postcode":"8586",
    "sg:province":"Thurgau",
    "sg:tags":[
        "management",
        "property",
        "software"
    ],
    "wof:name":"Cor Management Systeme Gmbh",
    "wof:placetype":"venue"
},
  "geometry": {"coordinates":[9.2177858353,47.5504112244],"type":"Point"}
}