{
  "type": "Feature",
  "properties": {
    "iso:country":"CH",
    "sg:address":"Gartenstrasse 19",
    "sg:city":"Heerbrugg",
    "sg:orig_category":"Sportvereine Turnen",
    "sg:phone":"+41 71 722 10 05",
    "sg:postcode":"9435",
    "sg:province":"St. Gallen",
    "wof:name":"Turnverein Heerbrugg",
    "wof:placetype":"venue"
},
  "geometry": {"coordinates":[9.6233720779,47.4071731567],"type":"Point"}
}