{
  "type": "Feature",
  "properties": {
    "iso:country":"CH",
    "sg:address":"Chemin De Placet 11",
    "sg:city":"Soral",
    "sg:orig_category":"Rebbau",
    "sg:phone":"+41 22 756 15 98",
    "sg:postcode":"1286",
    "sg:province":"Gen\u00e8ve",
    "wof:name":"Gilbert Dupraz Viticulteur",
    "wof:placetype":"venue"
},
  "geometry": {"coordinates":[6.045331955,46.1426773071],"type":"Point"}
}