{
  "type": "Feature",
  "properties": {
    "iso:country":"CH",
    "sg:address":"Tulpenstrasse 6",
    "sg:city":"Gerlafingen",
    "sg:orig_category":"Interessenvertretungen",
    "sg:postcode":"4563",
    "sg:province":"Solothurn",
    "wof:name":"Stiftung Oberbalmberg",
    "wof:placetype":"venue"
},
  "geometry": {"coordinates":[7.5764398575,47.1661643982],"type":"Point"}
}