{
  "type": "Feature",
  "properties": {
    "iso:country":"CH",
    "sg:address":"Rietweg",
    "sg:city":"Azmoos",
    "sg:orig_category":"Gem\u00fcsebau Grosshandel mit Obst U Gem\u00fcse",
    "sg:phone":"+41 79 682 28 05",
    "sg:postcode":"9478",
    "sg:province":"St. Gallen",
    "wof:name":"M\u00fcller Azmoos Ag, Gem\u00fcsehandel",
    "wof:placetype":"venue"
},
  "geometry": {"coordinates":[9.4812002182,47.08360672],"type":"Point"}
}