{
  "type": "Feature",
  "properties": {
    "iso:country":"CH",
    "sg:address":"Route De Pr\u00e9-bois 20",
    "sg:city":"Meyrin",
    "sg:orig_category":"Wirtschaftspr\u00fcfung, Steuerberatung U Treuhand",
    "sg:postcode":"1217",
    "sg:province":"Gen\u00e8ve",
    "wof:name":"Stg Soci\u00e9t\u00e9 Fiduciaire Suisse, Succursale De Meyrin",
    "wof:placetype":"venue"
},
  "geometry": {"coordinates":[6.1011929512,46.2245368958],"type":"Point"}
}