{
  "type": "Feature",
  "properties": {
    "iso:country":"CH",
    "sg:address":"Schweizerhausstrasse 2 6390 Engelberg. Postfach 646",
    "sg:city":"Engelberg",
    "sg:orig_category":"Ferienwohnungen, Ferienh\u00e4user HOTELS: MIT RESTAURANT",
    "sg:phone":"+41 41 637 13 32",
    "sg:postcode":"6390",
    "sg:province":"Obwalden",
    "wof:name":"Gasthaus Heimat, B\u00fctikofer Andr\u00e9",
    "wof:placetype":"venue"
},
  "geometry": {"coordinates":[8.4193725586,46.8196640015],"type":"Point"}
}