{
  "type": "Feature",
  "properties": {
    "iso:country":"CH",
    "sg:address":"Gehrenstrasse 17",
    "sg:city":"Eiken",
    "sg:orig_category":"Hoch U Tiefbau",
    "sg:phone":"+41 62 871 27 26",
    "sg:postcode":"5074",
    "sg:province":"Aargau",
    "wof:name":"Bruno Dinkel Baugesch\u00e4ft",
    "wof:placetype":"venue"
},
  "geometry": {"coordinates":[7.9838910103,47.5390548706],"type":"Point"}
}