{
  "type": "Feature",
  "properties": {
    "iso:country":"CH",
    "sg:address":"3401 Burgdorf. Postfach 817",
    "sg:city":"Burgdorf",
    "sg:orig_category":"Sportvereine Ballsport Fussball Vereine Damen",
    "sg:phone":"+41 34 422 36 11",
    "sg:postcode":"3401",
    "sg:province":"Bern",
    "wof:name":"Sc Burgdorf Abt.damen",
    "wof:placetype":"venue"
},
  "geometry": {"coordinates":[7.6269898415,47.056438446],"type":"Point"}
}