{
  "type": "Feature",
  "properties": {
    "iso:country":"CH",
    "sg:address":"Im R\u00fc\u00fcteli",
    "sg:city":"Engwang",
    "sg:orig_category":"G\u00fcterbef\u00f6rderung im Strassenverkehr",
    "sg:postcode":"8556",
    "sg:province":"Thurgau",
    "wof:name":"Adrian Zollinger Transporte",
    "wof:placetype":"venue"
},
  "geometry": {"coordinates":[9.0345516205,47.5975074768],"type":"Point"}
}