{
  "type": "Feature",
  "properties": {
    "iso:country":"CH",
    "sg:address":"Tunnelstr. 20",
    "sg:city":"Brig",
    "sg:orig_category":"RESTAURANTS: TEA-ROOMS",
    "sg:postcode":"3900",
    "sg:province":"Valais",
    "wof:name":"Restaurant Bellevue, Jordan Anton",
    "wof:placetype":"venue"
},
  "geometry": {"coordinates":[8.1194801331,46.2153892517],"type":"Point"}
}