{
  "type": "Feature",
  "properties": {
    "iso:country":"CH",
    "sg:address":"Chemin Des Selli\u00e8res 37",
    "sg:city":"A\u00efre",
    "sg:orig_category":"Stukkateurgewerbe, Gipserei U Verputzerei",
    "sg:phone":"+41 22 796 38 02",
    "sg:postcode":"1219",
    "sg:province":"Gen\u00e8ve",
    "wof:name":"Refecta Sa",
    "wof:placetype":"venue"
},
  "geometry": {"coordinates":[6.0999379158,46.1967735291],"type":"Point"}
}