{
  "type": "Feature",
  "properties": {
    "iso:country":"CH",
    "sg:address":"Mittlerestrasse 42c 3800 Unterseen. Postfach",
    "sg:city":"Unterseen",
    "sg:orig_category":"Buchf\u00fchrung Wirtschaftspr\u00fcfung, Steuerberatung U Treuhand",
    "sg:phone":"+41 71 929 57 57",
    "sg:postcode":"3800",
    "sg:province":"Bern",
    "wof:name":"Curseri Treuhand Gmbh",
    "wof:placetype":"venue"
},
  "geometry": {"coordinates":[9.040024,47.452427],"type":"Point"}
}