{
  "type": "Feature",
  "properties": {
    "addr:full":"Bahnhofstrasse 24 8803 R\u00fcschlikon. Postfach R\u00fcschlikon Z\u00fcrich 8803",
    "addr:housenumber":"24",
    "addr:postcode":"8803;8803",
    "addr:street":"Bahnhofstrasse;Postfach Rueschlikon Zuerich",
    "iso:country":"CH",
    "sg:address":"Bahnhofstrasse 24 8803 R\u00fcschlikon. Postfach",
    "sg:city":"R\u00fcschlikon",
    "sg:orig_category":"Buchverlag Verlagsgewerbe",
    "sg:phone":"+41 42325141",
    "sg:postcode":"8803",
    "sg:province":"Z\u00fcrich",
    "wof:name":"Scitec Publications Ltd",
    "wof:placetype":"venue"
},
  "geometry": {"coordinates":[8.685983,47.271645],"type":"Point"}
}