{
  "type": "Feature",
  "properties": {
    "iso:country":"CH",
    "sg:address":"Bahnhofstrasse 8750 Glarus. Postfach",
    "sg:city":"Glarus",
    "sg:orig_category":"Herstellung von Teppichen Verlegen von Fussboden",
    "sg:phone":"+41 21 634 50 13",
    "sg:postcode":"8750",
    "sg:province":"Glarus",
    "wof:name":"Weiss & Appetito Sa Renens",
    "wof:placetype":"venue"
},
  "geometry": {"coordinates":[6.5810627937,46.5379676819],"type":"Point"}
}