{
  "type": "Feature",
  "properties": {
    "iso:country":"CH",
    "sg:address":"Burgfeldermattweg 59",
    "sg:city":"Allschwil",
    "sg:orig_category":"Sportvereine Ballsport Handball",
    "sg:postcode":"4123",
    "sg:province":"Basel-Landschaft",
    "wof:name":"Hb Binningen",
    "wof:placetype":"venue"
},
  "geometry": {"coordinates":[7.541367054,47.5564804077],"type":"Point"}
}