{
  "type": "Feature",
  "properties": {
    "iso:country":"CH",
    "sg:address":"Poststrasse 11 7000 Chur. Postfach",
    "sg:city":"Chur",
    "sg:orig_category":"HOTELS: OHNE RESTAURANT",
    "sg:phone":"+41 81 868 53 33",
    "sg:postcode":"7002",
    "sg:province":"Graubunden",
    "wof:name":"Hotel Pra Garni",
    "wof:placetype":"venue"
},
  "geometry": {"coordinates":[10.3613004684,46.9444885254],"type":"Point"}
}