{
  "type": "Feature",
  "properties": {
    "iso:country":"CH",
    "sg:address":"Malojaweg 2 8048 Z\u00fcrich. Postfach",
    "sg:city":"Z\u00fcrich",
    "sg:orig_category":"Allgemeiner Hoch U Tiefbau",
    "sg:phone":"+41 14312511",
    "sg:postcode":"8048",
    "sg:province":"Z\u00fcrich",
    "wof:name":"Wilhelm Storz Ag",
    "wof:placetype":"venue"
},
  "geometry": {"coordinates":[8.479408,47.387424],"type":"Point"}
}