{
  "type": "Feature",
  "properties": {
    "iso:country":"CH",
    "sg:address":"Hasenbergstrasse 12",
    "sg:city":"Udligenswil",
    "sg:orig_category":"Wirtschaftspr\u00fcfung, Steuerberatung U Treuhand",
    "sg:phone":"+41 41 371 02 77",
    "sg:postcode":"6044",
    "sg:province":"Luzern",
    "wof:name":"Weiss J\u00fcrg Treuhand",
    "wof:placetype":"venue"
},
  "geometry": {"coordinates":[8.3935070038,47.091583252],"type":"Point"}
}