{
  "type": "Feature",
  "properties": {
    "iso:country":"CH",
    "sg:address":"Ruelle Des Oublis 1",
    "sg:city":"Ligni\u00e8res",
    "sg:orig_category":"Herstellung von elektrischen Haushaltsger\u00e4ten",
    "sg:phone":"+41 32 751 54 55",
    "sg:postcode":"2523",
    "sg:province":"Neuch\u00e2tel",
    "wof:name":"Bl\u00f6sch Michel",
    "wof:placetype":"venue"
},
  "geometry": {"coordinates":[7.0656709671,47.0836448669],"type":"Point"}
}