{
  "type": "Feature",
  "properties": {
    "iso:country":"CH",
    "sg:address":"Speicherstrasse 43",
    "sg:city":"St.gallen",
    "sg:orig_category":"Vereine Gesang",
    "sg:postcode":"9000",
    "sg:province":"St. Gallen",
    "wof:name":"M\u00e4nnerchor Rorschacherberg",
    "wof:placetype":"venue"
},
  "geometry": {"coordinates":[9.3884601593,47.4251708984],"type":"Point"}
}