{
  "type": "Feature",
  "properties": {
    "iso:country":"CH",
    "sg:address":"Via Magatti 3 6900 Lugano. Postfach",
    "sg:city":"Lugano",
    "sg:orig_category":"Ausl\u00e4ndisch beherrschte Finanzgesellschaften Dienstleistungen von Beteiligungsgesellschaften",
    "sg:phone":"+41 91 924 92 40",
    "sg:postcode":"6900",
    "sg:province":"Ticino",
    "wof:name":"Ac Private Equity Sa, Lussemburgo, Succursale Di Lugano Prestazione Di Servizi Amministrativi Ecc",
    "wof:placetype":"venue"
},
  "geometry": {"coordinates":[8.951805,46.00433],"type":"Point"}
}