{
  "type": "Feature",
  "properties": {
    "iso:country":"CH",
    "sg:address":"Trischlistrasse 8",
    "sg:city":"Rorschach",
    "sg:orig_category":"Fussboden, Fliesen U Plattenlegerei, Tapeziererei",
    "sg:postcode":"9400",
    "sg:province":"St. Gallen",
    "wof:name":"'josef Plattenleger' Rasic Jozo",
    "wof:placetype":"venue"
},
  "geometry": {"coordinates":[9.4888658524,47.4783973694],"type":"Point"}
}