{
  "type": "Feature",
  "properties": {
    "iso:country":"CH",
    "sg:address":"Au Village",
    "sg:city":"Vuadens",
    "sg:orig_category":"Unclassifiable Establishments",
    "sg:postcode":"1628",
    "sg:province":"Fribourg",
    "wof:name":"Decor Import, Alves Saraiva",
    "wof:placetype":"venue"
},
  "geometry": {"coordinates":[7.0208477974,46.6164093018],"type":"Point"}
}