{
  "type": "Feature",
  "properties": {
    "iso:country":"CH",
    "sg:address":"Les Rocailles",
    "sg:city":"H\u00e9r\u00e9mence",
    "sg:orig_category":"Sportvereine Ski",
    "sg:phone":"+41 27 281 20 27",
    "sg:postcode":"1987",
    "sg:province":"Valais",
    "wof:name":"Ski-club Heremencia",
    "wof:placetype":"venue"
},
  "geometry": {"coordinates":[7.4033498764,46.1771965027],"type":"Point"}
}