{
  "type": "Feature",
  "properties": {
    "iso:country":"CH",
    "sg:address":"Untere R\u00fcti",
    "sg:city":"Waldstatt",
    "sg:orig_category":"Pensionskassen",
    "sg:phone":"+41 71512727",
    "sg:postcode":"9104",
    "sg:province":"Appenzell Ausserrhoden",
    "wof:name":"Personalvorsorgestiftung Der Bodenmann Ag Waldstatt",
    "wof:placetype":"venue"
},
  "geometry": {"coordinates":[9.28241539,47.3536987305],"type":"Point"}
}