{
  "type": "Feature",
  "properties": {
    "iso:country":"CH",
    "sg:address":"S\u00e4listrasse 12",
    "sg:city":"Olten",
    "sg:orig_category":"Finanzierungsinstitutionen",
    "sg:postcode":"4600",
    "sg:province":"Solothurn",
    "wof:name":"Casa-crediti Ferraro",
    "wof:placetype":"venue"
},
  "geometry": {"coordinates":[7.9075350761,47.3455200195],"type":"Point"}
}