{
  "type": "Feature",
  "properties": {
    "iso:country":"CH",
    "sg:address":"1695",
    "sg:city":"Rueyres-st-laurent",
    "sg:classifiers":[
        {
            "category":"Restaurant",
            "type":"Food & Drink"
        }
    ],
    "sg:phone":"+41 26 411 11 52",
    "sg:postcode":"1695",
    "sg:province":"Fribourg",
    "wof:name":"Caf\u00e9 De L' Etoile",
    "wof:placetype":"venue"
},
  "geometry": {"coordinates":[7.033080101,46.715511322],"type":"Point"}
}