{
  "type": "Feature",
  "properties": {
    "iso:country":"CH",
    "sg:address":"Poststrasse 9 3427 Utzenstorf. Postfach",
    "sg:city":"Utzenstorf",
    "sg:orig_category":"Detailhandel mit fotografischen Artikeln Drogerien",
    "sg:postcode":"3427",
    "sg:province":"Bern",
    "wof:name":"A. Hofer",
    "wof:placetype":"venue"
},
  "geometry": {"coordinates":[7.5551600456,47.130405426],"type":"Point"}
}