{
  "type": "Feature",
  "properties": {
    "iso:country":"CH",
    "sg:address":"Grubenstrasse",
    "sg:city":"Sch\u00f6nried",
    "sg:orig_category":"Sportschulen Ski-& Snowboardschulen",
    "sg:phone":"+41 81 921 27 77",
    "sg:postcode":"3778",
    "sg:province":"Bern",
    "wof:name":"Snowboard Garage Fahrschule Snowboardschule Ssbs Skischule",
    "wof:placetype":"venue"
},
  "geometry": {"coordinates":[9.2103004456,46.8544311523],"type":"Point"}
}