{
  "type": "Feature",
  "properties": {
    "iso:country":"CH",
    "sg:address":"D\u00fcbendorfstrasse 217 8051 Z\u00fcrich. Postfach 89",
    "sg:city":"Z\u00fcrich",
    "sg:orig_category":"Druck ohne Zeitungsdruck Offsetdruck",
    "sg:phone":"+41 13212511",
    "sg:postcode":"8051",
    "sg:province":"Z\u00fcrich",
    "wof:name":"Favretto R. Ag",
    "wof:placetype":"venue"
},
  "geometry": {"coordinates":[8.5856456757,47.4005584717],"type":"Point"}
}