{
  "type": "Feature",
  "properties": {
    "iso:country":"CH",
    "sg:address":"Chemin Des Vignes 13",
    "sg:city":"Pully",
    "sg:orig_category":"Herstellung von Hebezeugen U F\u00f6rdermitteln Mechanische Werkst\u00e4tten",
    "sg:phone":"+41 21 728 88 00",
    "sg:postcode":"1009",
    "sg:province":"Vaud",
    "wof:name":"Lift-service Km Sa",
    "wof:placetype":"venue"
},
  "geometry": {"coordinates":[6.6644730568,46.5086784363],"type":"Point"}
}