{
  "type": "Feature",
  "properties": {
    "iso:country":"CH",
    "sg:address":"Im Gosten",
    "sg:city":"Unterterzen",
    "sg:orig_category":"Fischzucht, Teichwirtschaft",
    "sg:phone":"+41 81 738 17 24",
    "sg:postcode":"8882",
    "sg:province":"St. Gallen",
    "wof:name":"Erwin Walser Forellenzucht",
    "wof:placetype":"venue"
},
  "geometry": {"coordinates":[9.2564735413,47.1153793335],"type":"Point"}
}