{
  "type": "Feature",
  "properties": {
    "iso:country":"CH",
    "sg:address":"Erlachstrasse 3 8003 Z\u00fcrich. Postfach",
    "sg:city":"Z\u00fcrich",
    "sg:orig_category":"Finanzierungsinstitutionen",
    "sg:postcode":"8001",
    "sg:province":"Z\u00fcrich",
    "wof:name":"S\u00f6hner Ch. Car Consulting, Nachfolger S\u00f6hner D. Neu, Occasions-fahrzeuge; Beratung Bei Der Wahl U. Finanzierung",
    "wof:placetype":"venue"
},
  "geometry": {"coordinates":[8.5236349106,47.3689880371],"type":"Point"}
}