{
  "type": "Feature",
  "properties": {
    "iso:country":"CH",
    "sg:address":"Am Linthli 6",
    "sg:city":"N\u00e4fels",
    "sg:classifiers":[
        {
            "category":"Manufacturing",
            "subcategory":"Paper Products",
            "type":"Manufacturing & Wholesale Goods"
        }
    ],
    "sg:phone":"+41 55 618 40 00",
    "sg:postcode":"8752",
    "sg:province":"Glarus",
    "sg:tags":[
        "raw",
        "material",
        "-",
        "cardboard"
    ],
    "wof:name":"M\u00dcller Kartonagen Ag",
    "wof:placetype":"venue"
},
  "geometry": {"coordinates":[9.0685462952,47.1054916382],"type":"Point"}
}