{
  "type": "Feature",
  "properties": {
    "iso:country":"CH",
    "sg:address":"Weidenstrasse 3",
    "sg:city":"Niederg\u00f6sgen",
    "sg:orig_category":"Allgemeiner Hoch U Tiefbau",
    "sg:phone":"+41 71 385 27 79",
    "sg:postcode":"5013",
    "sg:province":"Solothurn",
    "wof:name":"Wyssen Ag",
    "wof:placetype":"venue"
},
  "geometry": {"coordinates":[9.263587,47.416309],"type":"Point"}
}