{
  "type": "Feature",
  "properties": {
    "iso:country":"CH",
    "sg:address":"Kirchstrasse 17 8274 Gottlieben. Postfach",
    "sg:city":"Gottlieben",
    "sg:orig_category":"Grosshandel mit Maschinen U Ausr\u00fcstungen",
    "sg:phone":"+41 71 666 80 30",
    "sg:postcode":"8274",
    "sg:province":"Thurgau",
    "wof:name":"Wittich Hans Service & Verkauf Gmbh Maschinen U. Apparate F. D. Kunststoffindustrie; Verkauf",
    "wof:placetype":"venue"
},
  "geometry": {"coordinates":[9.1334400177,47.664264679],"type":"Point"}
}