{
  "type": "Feature",
  "properties": {
    "iso:country":"CH",
    "sg:address":"Forchstrasse 175",
    "sg:city":"Hinteregg",
    "sg:orig_category":"Detailhandel mit Fleisch U Fleischwaren",
    "sg:phone":"+41 19841146",
    "sg:postcode":"8132",
    "sg:province":"Z\u00fcrich",
    "wof:name":"Landi-metzg Hinteregg Inhaber Karl Zehnder",
    "wof:placetype":"venue"
},
  "geometry": {"coordinates":[8.6839723587,47.3056144714],"type":"Point"}
}