{
  "type": "Feature",
  "properties": {
    "iso:country":"CH",
    "sg:address":"Molino Nuovo Piazza 15",
    "sg:city":"Lugano",
    "sg:orig_category":"Non-Classified Establishments",
    "sg:phone":"+41 91 921 14 61",
    "sg:postcode":"6900",
    "sg:province":"Ticino",
    "wof:name":"Nilortex Holding Sa",
    "wof:placetype":"venue"
},
  "geometry": {"coordinates":[8.9554157257,46.0125350952],"type":"Point"}
}