{
  "type": "Feature",
  "properties": {
    "iso:country":"CH",
    "sg:address":"Im Binz 5",
    "sg:city":"Guntershausen",
    "sg:orig_category":"Herstellung von Landwirtschaftstraktoren",
    "sg:postcode":"8357",
    "sg:province":"Thurgau",
    "wof:name":"Lehmann Ag Aadorf",
    "wof:placetype":"venue"
},
  "geometry": {"coordinates":[8.9152164459,47.4759216309],"type":"Point"}
}