{
  "type": "Feature",
  "properties": {
    "iso:country":"CH",
    "sg:address":"Hallauerstrasse 16",
    "sg:city":"Schleitheim",
    "sg:orig_category":"Detailhandel mit Uhren U Schmuck",
    "sg:phone":"+41 52 680 15 13",
    "sg:postcode":"8226",
    "sg:province":"Schaffhausen",
    "wof:name":"Adolf Kancz Goldschmiede",
    "wof:placetype":"venue"
},
  "geometry": {"coordinates":[8.4782190323,47.7457237244],"type":"Point"}
}