{
  "type": "Feature",
  "properties": {
    "iso:country":"CH",
    "sg:address":"B\u00fcrklistrasse 5",
    "sg:city":"M\u00f6hlin",
    "sg:orig_category":"Architektur U Ingenieurb\u00fcros",
    "sg:phone":"+41 34 445 11 45",
    "sg:postcode":"4313",
    "sg:province":"Aargau",
    "wof:name":"Bpu Ingenieurunternehmung Ag",
    "wof:placetype":"venue"
},
  "geometry": {"coordinates":[7.590738,47.079369],"type":"Point"}
}