{
  "type": "Feature",
  "properties": {
    "iso:country":"CH",
    "sg:address":"Cordiers Rue Des 12 1207 Gen\u00e8ve. Postfach",
    "sg:city":"Gen\u00e8ve",
    "sg:orig_category":"Handels-H\u00e4user U Gesellschaften",
    "sg:postcode":"1207",
    "sg:province":"Gen\u00e8ve",
    "wof:name":"Es Contact Constantin Jacques",
    "wof:placetype":"venue"
},
  "geometry": {"coordinates":[6.1630439758,46.2029342651],"type":"Point"}
}