{
  "type": "Feature",
  "properties": {
    "iso:country":"CH",
    "sg:address":"Av Du Crochetan 2",
    "sg:city":"Monthey",
    "sg:classifiers":[
        {
            "category":"Manufacturing",
            "subcategory":"Metals",
            "type":"Manufacturing & Wholesale Goods"
        }
    ],
    "sg:phone":"+41 24 471 88 21",
    "sg:postcode":"1870",
    "sg:province":"Valais",
    "sg:tags":[
        "metallurgy",
        "metalworking"
    ],
    "wof:name":"Carbometal Commerce Exterieur Sa",
    "wof:placetype":"venue"
},
  "geometry": {"coordinates":[6.9486250877,46.2531700134],"type":"Point"}
}