{
  "type": "Feature",
  "properties": {
    "iso:country":"CH",
    "sg:address":"Talstrasse 199",
    "sg:city":"Etzgen",
    "sg:orig_category":"Detailhandel mit M\u00f6beln U Haushaltsgegenst\u00e4nden Einbau von Schreinerwaren",
    "sg:phone":"+41 62 875 00 80",
    "sg:postcode":"5275",
    "sg:province":"Aargau",
    "wof:name":"Mobilia Etzgen Ag",
    "wof:placetype":"venue"
},
  "geometry": {"coordinates":[8.1112937927,47.5693206787],"type":"Point"}
}