{
  "type": "Feature",
  "properties": {
    "iso:country":"CH",
    "sg:address":"Luzernstrasse 2",
    "sg:city":"Neuenkirch",
    "sg:orig_category":"Non-Classified Establishments",
    "sg:phone":"+41 1370402",
    "sg:postcode":"6206",
    "sg:province":"Luzern",
    "wof:name":"Stephan Frei, Allinstall",
    "wof:placetype":"venue"
},
  "geometry": {"coordinates":[8.4487867355,47.3576049805],"type":"Point"}
}