{
  "type": "Feature",
  "properties": {
    "iso:country":"CH",
    "sg:address":"Bellerivestrasse 160",
    "sg:city":"Z\u00fcrich",
    "sg:orig_category":"Weitere Kultur U Unterhaltungseinrichtungen",
    "sg:phone":"+41 14352851",
    "sg:postcode":"8064",
    "sg:province":"Z\u00fcrich",
    "wof:name":"Chinagarten",
    "wof:placetype":"venue"
},
  "geometry": {"coordinates":[8.5530443192,47.3543434143],"type":"Point"}
}