{
  "type": "Feature",
  "properties": {
    "iso:country":"CH",
    "sg:address":"Rotbuchstrasse 72",
    "sg:city":"Z\u00fcrich",
    "sg:orig_category":"Detailhandel mit Brillen U anderen Sehhilfen",
    "sg:phone":"+41 13617457",
    "sg:postcode":"8037",
    "sg:province":"Z\u00fcrich",
    "wof:name":"Barbara Sch\u00fcrz Brillen & Kontaktlinsen",
    "wof:placetype":"venue"
},
  "geometry": {"coordinates":[8.530117,47.393364],"type":"Point"}
}