{
  "type": "Feature",
  "properties": {
    "iso:country":"CH",
    "sg:address":"Via Canton Zoc 21",
    "sg:city":"Biasca",
    "sg:orig_category":"Detailhandel mit M\u00f6beln Detailhandel mit M\u00f6beln U Haushaltsgegenst\u00e4nden",
    "sg:phone":"+41 24 471 42 32",
    "sg:postcode":"6710",
    "sg:province":"Ticino",
    "wof:name":"Trisconi Meubles",
    "wof:placetype":"venue"
},
  "geometry": {"coordinates":[6.9456748962,46.2593002319],"type":"Point"}
}