{
  "type": "Feature",
  "properties": {
    "iso:country":"CH",
    "sg:address":"Am Platz 14",
    "sg:city":"Bad Ragaz",
    "sg:classifiers":[
        {
            "category":"Banks & Credit Unions",
            "subcategory":"Bank",
            "type":"Services"
        }
    ],
    "sg:phone":"+41 81 303 47 11",
    "sg:postcode":"7310",
    "sg:province":"St. Gallen",
    "wof:name":"Credit Suisse",
    "wof:placetype":"venue"
},
  "geometry": {"coordinates":[9.500475,47.001808],"type":"Point"}
}