{
  "type": "Feature",
  "properties": {
    "iso:country":"CH",
    "sg:address":"4911",
    "sg:city":"Schwarzh\u00e4usern",
    "sg:orig_category":"Sportvereine Turnen",
    "sg:postcode":"4911",
    "sg:province":"Bern",
    "wof:name":"Turnverein",
    "wof:placetype":"venue"
},
  "geometry": {"coordinates":[7.7661499977,47.2568206787],"type":"Point"}
}