{
  "type": "Feature",
  "properties": {
    "iso:country":"CH",
    "sg:address":"Via Mastri Ligornettesi",
    "sg:city":"Ligornetto",
    "sg:orig_category":"Landwirtschaft, Jagd U damit verbundene Dienstleistungen",
    "sg:phone":"+41 91 647 21 68",
    "sg:postcode":"6853",
    "sg:province":"Ticino",
    "wof:name":"Vittorio Curti Azienda Agricola",
    "wof:placetype":"venue"
},
  "geometry": {"coordinates":[8.9509372711,45.8625640869],"type":"Point"}
}