{
  "type": "Feature",
  "properties": {
    "iso:country":"CH",
    "sg:address":"Industriestrasse 90 3902 Glis. Postfach 563",
    "sg:city":"Brig",
    "sg:orig_category":"Elektroinstallation Herstellung von Elektrizit\u00e4tsverteilungs U schalteinrichtungen",
    "sg:phone":"+41 27 923 34 00",
    "sg:postcode":"3900",
    "sg:province":"Valais",
    "wof:name":"As Aufz\u00fcge Ag",
    "wof:placetype":"venue"
},
  "geometry": {"coordinates":[7.9776821136,46.3108596802],"type":"Point"}
}