{
  "type": "Feature",
  "properties": {
    "iso:country":"CH",
    "sg:address":"Neumarktstrasse 52",
    "sg:city":"Biel/bienne",
    "sg:orig_category":"Non-Classified Establishments",
    "sg:phone":"+41 41 630 49 64",
    "sg:postcode":"2503",
    "sg:province":"Bern",
    "wof:name":"Naef Akademos Gmbh",
    "wof:placetype":"venue"
},
  "geometry": {"coordinates":[8.3074598312,46.9915618896],"type":"Point"}
}