{
  "type": "Feature",
  "properties": {
    "iso:country":"CH",
    "sg:address":"Eggenrain 2",
    "sg:city":"K\u00fcnten",
    "sg:orig_category":"Sportvereine Ballsport",
    "sg:phone":"+41 56 496 17 81",
    "sg:postcode":"5444",
    "sg:province":"Aargau",
    "wof:name":"Freunde Des Balls",
    "wof:placetype":"venue"
},
  "geometry": {"coordinates":[8.3309288025,47.3863105774],"type":"Point"}
}