{
  "type": "Feature",
  "properties": {
    "iso:country":"CH",
    "sg:address":"Talacker 41 8001 Z\u00fcrich. Postfach",
    "sg:city":"Z\u00fcrich",
    "sg:orig_category":"Sonstige Finanzierungsinstitutionen",
    "sg:phone":"+41 62 837 95 37",
    "sg:postcode":"8039",
    "wof:name":"Swisslog Management Ag",
    "wof:placetype":"venue"
},
  "geometry": {"coordinates":[8.075630188,47.3880691528],"type":"Point"}
}