{
  "type": "Feature",
  "properties": {
    "iso:country":"CH",
    "sg:address":"Lothringerstrasse 13 4056 Basel. Postfach",
    "sg:city":"Basel",
    "sg:orig_category":"Erbringung von Dienstleistungen f\u00fcr Unternehmen -\u00dcbersetzungsb\u00fcros",
    "sg:phone":"+41 878 878 940",
    "sg:postcode":"4051",
    "sg:province":"Basel-Stadt",
    "wof:name":"Steiner Dr. & Partner - Internationales Expertenb\u00fcro",
    "wof:placetype":"venue"
},
  "geometry": {"coordinates":[7.5791378021,47.5663833618],"type":"Point"}
}