{
  "type": "Feature",
  "properties": {
    "iso:country":"CH",
    "sg:address":"S\u00e9beillon Rue De 1",
    "sg:city":"Lausanne",
    "sg:orig_category":"Unclassifiable Establishments",
    "sg:postcode":"1004",
    "sg:province":"Vaud",
    "wof:name":"Etatec Ag",
    "wof:placetype":"venue"
},
  "geometry": {"coordinates":[7.2839550972,46.4762382507],"type":"Point"}
}