{
  "type": "Feature",
  "properties": {
    "iso:country":"CH",
    "sg:address":"1287",
    "sg:city":"Laconnex",
    "sg:orig_category":"Schulpflegen",
    "sg:phone":"+41 22 756 31 13",
    "sg:postcode":"1287",
    "sg:province":"Gen\u00e8ve",
    "wof:name":"Commission Scolaire De L'ecole Primaire",
    "wof:placetype":"venue"
},
  "geometry": {"coordinates":[6.034840107,46.1592712402],"type":"Point"}
}