{
  "type": "Feature",
  "properties": {
    "iso:country":"CH",
    "sg:address":"Allmendstrasse 2",
    "sg:city":"Bern",
    "sg:orig_category":"Arztpraxen",
    "sg:phone":"+41 31 332 63 39",
    "sg:postcode":"3014",
    "sg:province":"Bern",
    "wof:name":"Dr.med.hans Burgener Arzt F\u00fcr Allgemeine Medizin",
    "wof:placetype":"venue"
},
  "geometry": {"coordinates":[7.453078,46.957748],"type":"Point"}
}