{
  "type": "Feature",
  "properties": {
    "iso:country":"CH",
    "sg:address":"Gartenweg 7",
    "sg:city":"Gelterkinden",
    "sg:orig_category":"K\u00fcnstlerische Schulen",
    "sg:phone":"+41 61 981 18 77",
    "sg:postcode":"4460",
    "sg:province":"Basel-Landschaft",
    "wof:name":"Jugendmusikschule",
    "wof:placetype":"venue"
},
  "geometry": {"coordinates":[7.8572101593,47.462852478],"type":"Point"}
}