{
  "type": "Feature",
  "properties": {
    "iso:country":"CH",
    "sg:address":"General-wille-strasse 106 8706 Feldmeilen. Postfach 131",
    "sg:city":"Feldmeilen",
    "sg:orig_category":"Organisationen des Gesundheitswesen",
    "sg:phone":"+41 19236121",
    "sg:postcode":"8706",
    "sg:province":"Z\u00fcrich",
    "wof:name":"Vita Work Ag Private Haus-& Krankenpflege",
    "wof:placetype":"venue"
},
  "geometry": {"coordinates":[8.6159029007,47.2785186768],"type":"Point"}
}