{
  "type": "Feature",
  "properties": {
    "iso:country":"CH",
    "sg:address":"Rte Du Cordex",
    "sg:city":"Vich",
    "sg:orig_category":"Gesundheitswesen",
    "sg:postcode":"1267",
    "sg:province":"Vaud",
    "wof:name":"Delam S\u00e0rl",
    "wof:placetype":"venue"
},
  "geometry": {"coordinates":[6.8206748962,46.8364982605],"type":"Point"}
}