{
  "type": "Feature",
  "properties": {
    "iso:country":"CH",
    "sg:address":"Z\u00fcrcherstrasse 28",
    "sg:city":"Windisch",
    "sg:orig_category":"Grosshandel mit Erzen U Metallen Grosshandel mit elektrischen Haushaltsger\u00e4ten, Radio U Fernsehger\u00e4t",
    "sg:phone":"+41 56 441 20 80",
    "sg:postcode":"5210",
    "sg:province":"Aargau",
    "wof:name":"Agi's Metallwaren",
    "wof:placetype":"venue"
},
  "geometry": {"coordinates":[8.2174577713,47.4787788391],"type":"Point"}
}