{
  "type": "Feature",
  "properties": {
    "iso:country":"CH",
    "sg:address":"Zimmeregg 22",
    "sg:city":"Littau",
    "sg:orig_category":"Organisationen des Gesundheitswesen",
    "sg:phone":"+41 41 250 11 66",
    "sg:postcode":"6014",
    "sg:province":"Luzern",
    "wof:name":"Samariterverein Reussb\u00fchl",
    "wof:placetype":"venue"
},
  "geometry": {"coordinates":[8.2675275803,47.0528335571],"type":"Point"}
}