{
  "type": "Feature",
  "properties": {
    "iso:country":"CH",
    "sg:address":"Bernstrasse 7a",
    "sg:city":"Oftringen",
    "sg:orig_category":"Non-Classified Establishments",
    "sg:postcode":"4665",
    "sg:province":"Aargau",
    "wof:name":"Georges Feierabend",
    "wof:placetype":"venue"
},
  "geometry": {"coordinates":[7.9147000313,47.311466217],"type":"Point"}
}