{
  "type": "Feature",
  "properties": {
    "iso:country":"CH",
    "sg:address":"Schwanengasse 5",
    "sg:city":"Bern",
    "sg:orig_category":"Detailhandel mit Waren verschiedener Art, Hauptrichtung Nahrungsmittel Fachdetailhandel mit Nahrungs",
    "sg:phone":"+41 21 944 47 12",
    "sg:postcode":"3011",
    "sg:province":"Bern",
    "wof:name":"Albert Naepflin Comestibles",
    "wof:placetype":"venue"
},
  "geometry": {"coordinates":[6.8552770615,46.456993103],"type":"Point"}
}