{
  "type": "Feature",
  "properties": {
    "iso:country":"CH",
    "sg:address":"Schaffeld",
    "sg:city":"Niederh\u00fcnigen",
    "sg:orig_category":"Elektroinstallation",
    "sg:postcode":"3504",
    "sg:province":"Bern",
    "wof:name":"R\u00fcegsegger Peter",
    "wof:placetype":"venue"
},
  "geometry": {"coordinates":[7.6419639587,46.8821678162],"type":"Point"}
}