{
  "type": "Feature",
  "properties": {
    "iso:country":"CH",
    "sg:address":"Hofstrasse 18",
    "sg:city":"Ichertswil",
    "sg:orig_category":"Handel mit Motorr\u00e4dern, Teilen U Zubeh\u00f6r Instandhaltung U Reparatur von Motorr\u00e4dern",
    "sg:phone":"+41 32 677 22 54",
    "sg:postcode":"4571",
    "sg:province":"Solothurn",
    "wof:name":"Outback Motors P.kummer",
    "wof:placetype":"venue"
},
  "geometry": {"coordinates":[7.4971308708,47.1594467163],"type":"Point"}
}