{
  "type": "Feature",
  "properties": {
    "iso:country":"CH",
    "sg:address":"Avenue Du Valais 13",
    "sg:city":"Vouvry",
    "sg:orig_category":"Detailhandel mit Fleisch U Fleischwaren",
    "sg:phone":"+41 41 988 11 15",
    "sg:postcode":"1896",
    "sg:province":"Valais",
    "wof:name":"St\u00f6ckli Metzgerei",
    "wof:placetype":"venue"
},
  "geometry": {"coordinates":[7.9269361496,47.1366157532],"type":"Point"}
}