{
  "type": "Feature",
  "properties": {
    "iso:country":"CH",
    "sg:address":"Route D'a\u00efre 158 1214 Vernier. Postfach",
    "sg:city":"Vernier",
    "sg:orig_category":"Unclassifiable Establishments",
    "sg:postcode":"1214",
    "sg:province":"Gen\u00e8ve",
    "wof:name":"Oceanic Prod, Gregoire Philippe",
    "wof:placetype":"venue"
},
  "geometry": {"coordinates":[6.0804700851,46.2123413086],"type":"Point"}
}