{
  "type": "Feature",
  "properties": {
    "iso:country":"CH",
    "sg:address":"Holenstein",
    "sg:city":"Glarus",
    "sg:orig_category":"Bauspenglerei Sanit\u00e4rinstallation",
    "sg:phone":"+41 55 640 59 69",
    "sg:postcode":"8750",
    "sg:province":"Glarus",
    "wof:name":"Walter Hefti Spenglerei & Sanit\u00e4r",
    "wof:placetype":"venue"
},
  "geometry": {"coordinates":[9.076605,47.031166],"type":"Point"}
}