{
  "type": "Feature",
  "properties": {
    "iso:country":"CH",
    "sg:address":"Dorfplatz 3",
    "sg:city":"Zumikon",
    "sg:orig_category":"Detailhandel mit M\u00f6beln Verlegen von Fussboden",
    "sg:phone":"+41 81 837 05 00",
    "sg:postcode":"8126",
    "sg:province":"Z\u00fcrich",
    "wof:name":"Testa G. & Co",
    "wof:placetype":"venue"
},
  "geometry": {"coordinates":[9.8361730576,46.4885673523],"type":"Point"}
}