{
  "type": "Feature",
  "properties": {
    "iso:country":"CH",
    "sg:address":"Sternmatt 10",
    "sg:city":"Kriens",
    "sg:orig_category":"Tankstellen",
    "sg:phone":"+41 32 866 14 78",
    "sg:postcode":"6010",
    "sg:province":"Luzern",
    "wof:name":"Jacques Beyeler Station-service Shell",
    "wof:placetype":"venue"
},
  "geometry": {"coordinates":[6.4854230881,46.905254364],"type":"Point"}
}