{
  "type": "Feature",
  "properties": {
    "iso:country":"CH",
    "sg:address":"Mittlerer Kreis 29",
    "sg:city":"Therwil",
    "sg:orig_category":"Detailhandel mit Radio U Fernsehger\u00e4ten Detailhandel mit elektrischen Haushalts-,Radio U Fernsehger\u00e4",
    "sg:phone":"+41 61 721 44 44",
    "sg:postcode":"4106",
    "sg:province":"Basel-Landschaft",
    "wof:name":"Radio-television-foto B\u00fcrgi Ag",
    "wof:placetype":"venue"
},
  "geometry": {"coordinates":[7.5530982018,47.4977378845],"type":"Point"}
}