{
  "type": "Feature",
  "properties": {
    "iso:country":"CH",
    "sg:address":"G\u00e4hwiler Str. 7",
    "sg:city":"Kirchberg",
    "sg:classifiers":[
        {
            "category":"Banks & Credit Unions",
            "subcategory":"Bank",
            "type":"Services"
        }
    ],
    "sg:phone":"+41 71 931 21 31",
    "sg:postcode":"9533",
    "sg:province":"St. Gallen",
    "wof:name":"Spar- + Leihkasse, Kirchberg",
    "wof:placetype":"venue"
},
  "geometry": {"coordinates":[9.0404,47.410728],"type":"Point"}
}