{
  "type": "Feature",
  "properties": {
    "iso:country":"CH",
    "sg:address":"Casai",
    "sg:city":"Campascio",
    "sg:orig_category":"Herstellung von Medikamenten U sonstigen pharmazeutischen Erzeugnissen Herstellung von pharmazeutisc",
    "sg:phone":"+41 81 846 58 33",
    "sg:postcode":"7748",
    "sg:province":"Graubunden",
    "wof:name":"Infosint Sa",
    "wof:placetype":"venue"
},
  "geometry": {"coordinates":[10.1309347153,46.2451057434],"type":"Point"}
}