{
  "type": "Feature",
  "properties": {
    "iso:country":"CH",
    "sg:address":"Pratifori 10",
    "sg:city":"Sion",
    "sg:orig_category":"Unclassifiable Establishments",
    "sg:postcode":"1950",
    "sg:province":"Valais",
    "wof:name":"Actiforme S\u00e0rl",
    "wof:placetype":"venue"
},
  "geometry": {"coordinates":[7.5202498436,46.3162918091],"type":"Point"}
}