{
  "type": "Feature",
  "properties": {
    "iso:country":"CH",
    "sg:address":"Herblingerstrasse 62",
    "sg:city":"Schaffhausen",
    "sg:orig_category":"Non-Classified Establishments",
    "sg:postcode":"8207",
    "sg:province":"Schaffhausen",
    "wof:name":"Robert Steinemann Ingenieurb\u00fcro",
    "wof:placetype":"venue"
},
  "geometry": {"coordinates":[8.6584949493,47.7202262878],"type":"Point"}
}