{
  "type": "Feature",
  "properties": {
    "addr:full":"Thundorferstrasse 31 Frauenfeld Thurgau 8500",
    "addr:housenumber":"31",
    "addr:postcode":"8500",
    "addr:street":"Thundorferstrasse",
    "iso:country":"CH",
    "sg:address":"Thundorferstrasse 31",
    "sg:city":"Frauenfeld",
    "sg:orig_category":"Detailhandel mit Bekleidung Handelsvermittlung U Grosshandel",
    "sg:postcode":"8500",
    "sg:province":"Thurgau",
    "wof:name":"Convex Import/export Gmbh",
    "wof:placetype":"venue"
},
  "geometry": {"coordinates":[8.901027,47.554455],"type":"Point"}
}