{
  "type": "Feature",
  "properties": {
    "iso:country":"CH",
    "sg:address":"Avenue G\u00e9n\u00e9ral Jomini 20",
    "sg:city":"Payerne",
    "sg:classifiers":[
        {
            "category":"Education",
            "subcategory":"Library",
            "type":"Public Place"
        }
    ],
    "sg:phone":"+41 26 660 21 55",
    "sg:postcode":"1530",
    "sg:province":"Vaud",
    "sg:tags":[
        "u",
        "bibliotheken",
        "archive"
    ],
    "wof:name":"Biblioth\u00e8que Deutschsprachiges Ref.pfarramt",
    "wof:placetype":"venue"
},
  "geometry": {"coordinates":[6.939213,46.823368],"type":"Point"}
}