{
  "type": "Feature",
  "properties": {
    "iso:country":"CH",
    "sg:address":"Im Sihlhof 10a",
    "sg:city":"Adliswil",
    "sg:orig_category":"Fachdetailhandel in Verkaufsr\u00e4umen",
    "sg:phone":"+41 17090400",
    "sg:postcode":"8134",
    "sg:province":"Z\u00fcrich",
    "wof:name":"Sutter-hofmann Doris, Blumen",
    "wof:placetype":"venue"
},
  "geometry": {"coordinates":[8.5220451355,47.3214874268],"type":"Point"}
}