{
  "type": "Feature",
  "properties": {
    "iso:country":"CH",
    "sg:address":"Hurschli",
    "sg:city":"Dallenwil",
    "sg:orig_category":"Detailhandel mit elektrischen Haushalts-,Radio U Fernsehger\u00e4ten sowie Musikinstrumenten Schallplatte",
    "sg:phone":"+41 41 628 19 57",
    "sg:postcode":"6383",
    "sg:province":"Nidwalden",
    "wof:name":"Phono-vertriebs Gmbh",
    "wof:placetype":"venue"
},
  "geometry": {"coordinates":[8.3893842697,46.9238395691],"type":"Point"}
}