{
  "type": "Feature",
  "properties": {
    "iso:country":"CH",
    "sg:address":"6777 Quinto. Postfach",
    "sg:city":"Ambr\u00ec",
    "sg:classifiers":[
        {
            "category":"Travel",
            "subcategory":"Hotels & Motels",
            "type":"Entertainment"
        }
    ],
    "sg:postcode":"6775",
    "sg:province":"Ticino",
    "sg:tags":[
        "hotels",
        "mit",
        "restaurant"
    ],
    "wof:name":"Guscio Ilo",
    "wof:placetype":"venue"
},
  "geometry": {"coordinates":[8.713385582,46.5107307434],"type":"Point"}
}