{
  "type": "Feature",
  "properties": {
    "iso:country":"CH",
    "sg:address":"Weierweg 2",
    "sg:city":"Neudorf",
    "sg:orig_category":"Detailhandel mit Waren verschiedener Art, Hauptrichtung Nahrungsmittel",
    "sg:postcode":"6025",
    "sg:province":"Luzern",
    "wof:name":"Benjamin Kunz Spezialprodukte",
    "wof:placetype":"venue"
},
  "geometry": {"coordinates":[7.9620099068,47.1195907593],"type":"Point"}
}