{
  "type": "Feature",
  "properties": {
    "iso:country":"CH",
    "sg:address":"Rh\u00f4ne Rue Du 50 1204 Gen\u00e8ve. Postfach",
    "sg:city":"Gen\u00e8ve",
    "sg:orig_category":"Herstellung von Duft U K\u00f6rperpflegemitteln",
    "sg:postcode":"1201",
    "sg:province":"Gen\u00e8ve",
    "wof:name":"B + G Cosmetic Gmbh",
    "wof:placetype":"venue"
},
  "geometry": {"coordinates":[9.0571508408,47.4721488953],"type":"Point"}
}