{
  "type": "Feature",
  "properties": {
    "iso:country":"CH",
    "sg:address":"F\u00f6hrenweg 32 3700 Spiez. Postfach 373",
    "sg:city":"Spiez",
    "sg:orig_category":"Technische B\u00fcros Elektro",
    "sg:phone":"+41 33 654 74 42",
    "sg:postcode":"3700",
    "sg:province":"Bern",
    "wof:name":"J\u00f6rg Wiederkehr Technisches B\u00fcro",
    "wof:placetype":"venue"
},
  "geometry": {"coordinates":[7.694644928,46.6852340698],"type":"Point"}
}