{
  "type": "Feature",
  "properties": {
    "iso:country":"CH",
    "sg:address":"Bachlettenstrasse 10",
    "sg:city":"Basel",
    "sg:orig_category":"Unternehmensberatung",
    "sg:phone":"+41 61 281 99 90",
    "sg:postcode":"4054",
    "sg:province":"Basel-Stadt",
    "wof:name":"Zenfo Zentrum F\u00fcr Kommunikation & Informatik Ag",
    "wof:placetype":"venue"
},
  "geometry": {"coordinates":[7.5807228088,47.5504722595],"type":"Point"}
}