{
  "type": "Feature",
  "properties": {
    "iso:country":"CH",
    "sg:address":"Gossauerstrasse 2",
    "sg:city":"M\u00f6nchaltorf",
    "sg:classifiers":[
        {
            "category":"Restaurant",
            "type":"Food & Drink"
        }
    ],
    "sg:phone":"+41 19480148",
    "sg:postcode":"8617",
    "sg:province":"Z\u00fcrich",
    "wof:name":"Restaurant Ochsen",
    "wof:placetype":"venue"
},
  "geometry": {"coordinates":[8.7217006683,47.3097686768],"type":"Point"}
}