{
  "type": "Feature",
  "properties": {
    "iso:country":"CH",
    "sg:address":"Poststrasse 2",
    "sg:city":"Hunzenschwil",
    "sg:orig_category":"Detailhandel mit Brot, Back U S\u00fcsswaren",
    "sg:postcode":"5502",
    "sg:province":"Aargau",
    "wof:name":"Kohler + Co",
    "wof:placetype":"venue"
},
  "geometry": {"coordinates":[8.121992,47.386211],"type":"Point"}
}