{
  "type": "Feature",
  "properties": {
    "iso:country":"CH",
    "sg:address":"Zwischen Den Toren 20 5000 Aarau. Postfach",
    "sg:city":"Aarau",
    "sg:orig_category":"Detailhandel mit Bekleidung Fachdetailhandel in Verkaufsr\u00e4umen",
    "sg:phone":"+41 62 822 66 46",
    "sg:postcode":"5001",
    "sg:province":"Aargau",
    "wof:name":"H\u00e4berli Sport Ag",
    "wof:placetype":"venue"
},
  "geometry": {"coordinates":[8.04446,47.392029],"type":"Point"}
}