{
  "type": "Feature",
  "properties": {
    "iso:country":"CH",
    "sg:address":"Landstrasse 180",
    "sg:city":"Klosters",
    "sg:orig_category":"Kauf U Verkauf von Immobilien auf eigene Rechnung Vermittlung von Immobilien",
    "sg:phone":"+41 81 422 66 56",
    "sg:postcode":"7250",
    "sg:province":"Graubunden",
    "wof:name":"Pd Immobilien Gianotti Geraldine",
    "wof:placetype":"venue"
},
  "geometry": {"coordinates":[9.8832969666,46.867351532],"type":"Point"}
}