{
  "type": "Feature",
  "properties": {
    "iso:country":"CH",
    "sg:address":"Trogener Strasse 4",
    "sg:city":"Speicher",
    "sg:orig_category":"Arztpraxen",
    "sg:phone":"+41 71 344 12 18",
    "sg:postcode":"9042",
    "sg:province":"Appenzell Ausserrhoden",
    "wof:name":"Dr.med.erich Z\u00fcger Arzt F.allgemeine Medizin Fmh",
    "wof:placetype":"venue"
},
  "geometry": {"coordinates":[9.447584,47.407257],"type":"Point"}
}