{
  "type": "Feature",
  "properties": {
    "iso:country":"CH",
    "sg:address":"Amthausgasse 10",
    "sg:city":"Bern",
    "sg:orig_category":"RESTAURANTS: TEA-ROOMS",
    "sg:postcode":"3011",
    "sg:province":"Bern",
    "wof:name":"Restaurant Ermitage Hangartner U.",
    "wof:placetype":"venue"
},
  "geometry": {"coordinates":[7.4465198517,46.9474525452],"type":"Point"}
}