{
  "type": "Feature",
  "properties": {
    "iso:country":"CH",
    "sg:address":"Thunstrasse 10",
    "sg:city":"Spiez",
    "sg:orig_category":"Aktivit\u00e4ten der Krankenschwestern U Hebammen, Hauspflege",
    "sg:phone":"+41 33 654 38 78",
    "sg:postcode":"3700",
    "sg:province":"Bern",
    "wof:name":"Spitex-koordinationsstelle",
    "wof:placetype":"venue"
},
  "geometry": {"coordinates":[7.674199,46.690056],"type":"Point"}
}