{
  "type": "Feature",
  "properties": {
    "iso:country":"CH",
    "sg:address":"Aeschrain 14",
    "sg:city":"Walchwil",
    "sg:orig_category":"Softwareentwicklung U beratung",
    "sg:phone":"+41 41 759 01 11",
    "sg:postcode":"6318",
    "sg:province":"Zug",
    "wof:name":"Hemmel Consulting",
    "wof:placetype":"venue"
},
  "geometry": {"coordinates":[8.5225458145,47.0950431824],"type":"Point"}
}