{
  "type": "Feature",
  "properties": {
    "iso:country":"CH",
    "sg:address":"Baslerstrasse 101",
    "sg:city":"Allschwil",
    "sg:orig_category":"Steuer\u00e4mter",
    "sg:phone":"+41 61 486 25 25",
    "sg:postcode":"4123",
    "sg:province":"Basel-Landschaft",
    "wof:name":"Steueramt",
    "wof:placetype":"venue"
},
  "geometry": {"coordinates":[7.5448598862,47.552646637],"type":"Point"}
}