{
  "type": "Feature",
  "properties": {
    "iso:country":"CH",
    "sg:address":"Place De Coppoz 8",
    "sg:city":"Mont-sur-lausanne",
    "sg:orig_category":"Gem\u00fcsebau",
    "sg:phone":"+41 21 691 46 85",
    "sg:postcode":"1052",
    "sg:province":"Vaud",
    "wof:name":"Jean Moirandat Maraicher",
    "wof:placetype":"venue"
},
  "geometry": {"coordinates":[6.5515451431,46.5102233887],"type":"Point"}
}