{
  "type": "Feature",
  "properties": {
    "iso:country":"CH",
    "sg:address":"Via Della Scuole",
    "sg:city":"Brissago",
    "sg:orig_category":"HERSTELLUNG VON GER\u00c4TEN DER ELEKTRIZIT\u00c4TSERZEUGUNG, -VERTEILUNG U.\u00c4 Herstellung von Metallerzeugniss",
    "sg:phone":"+41 91 793 18 29",
    "sg:postcode":"6614",
    "sg:province":"Ticino",
    "wof:name":"Dechema Deutsche Gesellschaft F.chemisches Apparatewesen",
    "wof:placetype":"venue"
},
  "geometry": {"coordinates":[8.7124652863,46.1195907593],"type":"Point"}
}