{
  "type": "Feature",
  "properties": {
    "iso:country":"CH",
    "sg:address":"Via D. Alighieri 3",
    "sg:city":"Chiasso",
    "sg:orig_category":"Wirtschaftspr\u00fcfung, Steuerberatung U Treuhand",
    "sg:postcode":"6830",
    "sg:province":"Ticino",
    "wof:name":"Tasayo Audit & Consulting Sa",
    "wof:placetype":"venue"
},
  "geometry": {"coordinates":[9.026881218,45.8366012573],"type":"Point"}
}