{
  "type": "Feature",
  "properties": {
    "iso:country":"CH",
    "sg:address":"9496 Balzers. Postfach 193",
    "sg:city":"Balzers",
    "sg:orig_category":"Bezirks, Sekundar, Realschulen, Oberstufe der Primarschulen",
    "sg:phone":"+41 71 477 21 80",
    "sg:postcode":"9496",
    "wof:name":"Realschule",
    "wof:placetype":"venue"
},
  "geometry": {"coordinates":[9.3676519394,47.5294837952],"type":"Point"}
}