{
  "type": "Feature",
  "properties": {
    "iso:country":"CH",
    "sg:address":"General-dufour-strasse 38",
    "sg:city":"Biel/bienne",
    "sg:orig_category":"Zahnarztpraxen",
    "sg:phone":"+41 32 323 21 55",
    "sg:postcode":"2502",
    "sg:province":"Bern",
    "wof:name":"Dr.med.dent.jean-martin Welker Zahnarzt",
    "wof:placetype":"venue"
},
  "geometry": {"coordinates":[7.2502441406,47.1409301758],"type":"Point"}
}