{
  "type": "Feature",
  "properties": {
    "iso:country":"CH",
    "sg:address":"Route De Fribourg 45",
    "sg:city":"Courtepin",
    "sg:orig_category":"Handel mit Automobilen",
    "sg:postcode":"1784",
    "sg:province":"Fribourg",
    "wof:name":"Auto Star Center S\u00e0rl",
    "wof:placetype":"venue"
},
  "geometry": {"coordinates":[7.1245269775,46.8638000488],"type":"Point"}
}