{
  "type": "Feature",
  "properties": {
    "iso:country":"CH",
    "sg:address":"Badenerstrasse 6",
    "sg:city":"Z\u00fcrich",
    "sg:orig_category":"Fachdetailhandel mit pharmazeutischen Produkten",
    "sg:phone":"+41 32 752 35 35",
    "sg:postcode":"8001",
    "sg:province":"Z\u00fcrich",
    "wof:name":"Onde Verte, Touzeau Gildas.",
    "wof:placetype":"venue"
},
  "geometry": {"coordinates":[7.0666818619,47.0555000305],"type":"Point"}
}