{
  "type": "Feature",
  "properties": {
    "iso:country":"CH",
    "sg:address":"Grienstrasse 7 2542 Pieterlen. Postfach 203",
    "sg:city":"Pieterlen",
    "sg:orig_category":"Autogaragen",
    "sg:phone":"+41 19354585",
    "sg:postcode":"2542",
    "sg:province":"Bern",
    "wof:name":"Garage Tannenberg",
    "wof:placetype":"venue"
},
  "geometry": {"coordinates":[8.768197,47.305992],"type":"Point"}
}