{
  "type": "Feature",
  "properties": {
    "iso:country":"CH",
    "sg:address":"Industrieweg 14",
    "sg:city":"Rothrist",
    "sg:orig_category":"Mineralquellen, Herstellung von alkoholfreien Getr\u00e4nken",
    "sg:phone":"+41 62 785 43 43",
    "sg:postcode":"4852",
    "sg:province":"Aargau",
    "wof:name":"Gedis Ag",
    "wof:placetype":"venue"
},
  "geometry": {"coordinates":[7.8745141029,47.3053092957],"type":"Point"}
}