{
  "type": "Feature",
  "properties": {
    "iso:country":"CH",
    "sg:address":"Bahnhofstrasse 17",
    "sg:city":"Schaan",
    "sg:classifiers":[
        {
            "category":"Restaurant",
            "type":"Food & Drink"
        }
    ],
    "sg:phone":"+423 232 72 35",
    "sg:postcode":"9494",
    "wof:name":"Olympia Caf\u00e9 Snack",
    "wof:placetype":"venue"
},
  "geometry": {"coordinates":[9.5077323914,47.1673469543],"type":"Point"}
}