{
  "type": "Feature",
  "properties": {
    "iso:country":"CH",
    "sg:address":"Pratifori",
    "sg:city":"Sion",
    "sg:orig_category":"Detailhandel mit M\u00f6beln U Haushaltsgegenst\u00e4nden",
    "sg:phone":"+41 27 329 09 31",
    "sg:postcode":"1950",
    "sg:province":"Valais",
    "wof:name":"Eridis Sa Articles Destin\u00e9s \u00e0 L'am\u00e9lioration De L'habitat; Fabrication, Vente Et Commercialisation",
    "wof:placetype":"venue"
},
  "geometry": {"coordinates":[7.3540101051,46.2303314209],"type":"Point"}
}