{
  "type": "Feature",
  "properties": {
    "iso:country":"CH",
    "sg:address":"Landstrasse 122 5430 Wettingen. Postfach 2173",
    "sg:city":"Wettingen",
    "sg:orig_category":"Fachdetailhandel in Verkaufsr\u00e4umen Grosshandel mit Schmuck",
    "sg:phone":"+41 22 312 03 44",
    "sg:postcode":"5430",
    "sg:province":"Aargau",
    "wof:name":"Mvdb Diffusion Sa",
    "wof:placetype":"venue"
},
  "geometry": {"coordinates":[6.1531071663,46.1912918091],"type":"Point"}
}