{
  "type": "Feature",
  "properties": {
    "iso:country":"CH",
    "sg:address":"Schulgasse 165 8215 Hallau. Postfach 185",
    "sg:city":"Hallau",
    "sg:orig_category":"Mineralquellen, Herstellung von alkoholfreien Getr\u00e4nken Rebbau",
    "sg:phone":"+41 52 681 31 44",
    "sg:postcode":"8215",
    "sg:province":"Schaffhausen",
    "wof:name":"Rimuss-kellerei Rahm & Co.",
    "wof:placetype":"venue"
},
  "geometry": {"coordinates":[8.4602689743,47.6983222961],"type":"Point"}
}