{
  "type": "Feature",
  "properties": {
    "iso:country":"CH",
    "sg:address":"Chemin De Bourg-dessus 12",
    "sg:city":"Renens",
    "sg:classifiers":[
        {
            "category":"Transit Center",
            "subcategory":"Passenger",
            "type":"Transportation"
        }
    ],
    "sg:phone":"+41 21 634 09 70",
    "sg:postcode":"1020",
    "sg:province":"Vaud",
    "sg:tags":[
        "goldsmith's",
        "tool"
    ],
    "wof:name":"Huser Jean-fran\u00e7ois Bijoutil",
    "wof:placetype":"venue"
},
  "geometry": {"coordinates":[6.5948419571,46.5371704102],"type":"Point"}
}