{
  "type": "Feature",
  "properties": {
    "iso:country":"CH",
    "sg:address":"Optingenstrasse 27 3013 Bern. Postfach",
    "sg:city":"Bern",
    "sg:orig_category":"Pensionskassen",
    "sg:postcode":"3013",
    "sg:province":"Bern",
    "wof:name":"Pensionskasse Der Graphicart Internationale Ausr\u00fcstungsgesellschaft F\u00fcr Graphische Kunst Ag, In Bern",
    "wof:placetype":"venue"
},
  "geometry": {"coordinates":[7.4499330521,46.9554367065],"type":"Point"}
}