{
  "type": "Feature",
  "properties": {
    "iso:country":"CH",
    "sg:address":"Postplatz 3",
    "sg:city":"Gansingen",
    "sg:orig_category":"Detailhandel mit Waren verschiedener Art, Hauptrichtung Nahrungsmittel",
    "sg:postcode":"5272",
    "sg:province":"Aargau",
    "wof:name":"Landwirtschaftliche Konsumgenossenschaft Gansingen",
    "wof:placetype":"venue"
},
  "geometry": {"coordinates":[8.1341371536,47.5427818298],"type":"Point"}
}