{
  "type": "Feature",
  "properties": {
    "iso:country":"CH",
    "sg:address":"Bleumatthalde 10 5073 Gipf-oberfrick. Postfach",
    "sg:city":"Gipf-oberfrick",
    "sg:orig_category":"Herstellung von Futtermitteln f\u00fcr Nutztiere",
    "sg:phone":"+41 13682550",
    "sg:postcode":"5073",
    "sg:province":"Aargau",
    "wof:name":"Eichholzer Ag N\u00e4hrstoff-recycling",
    "wof:placetype":"venue"
},
  "geometry": {"coordinates":[8.006439209,47.4959602356],"type":"Point"}
}