{
  "type": "Feature",
  "properties": {
    "iso:country":"CH",
    "sg:address":"Poststrasse 32 7000 Chur. Postfach",
    "sg:city":"Chur",
    "sg:orig_category":"Herstellung von Uhren",
    "sg:postcode":"7000",
    "sg:province":"Graubunden",
    "wof:name":"Zentralverband Schweiz. Uhrmacher Sektion Graub\u00fcnden",
    "wof:placetype":"venue"
},
  "geometry": {"coordinates":[9.5318098068,46.8505783081],"type":"Point"}
}