{
  "type": "Feature",
  "properties": {
    "iso:country":"CH",
    "sg:address":"Weriweg 29",
    "sg:city":"Glis",
    "sg:orig_category":"Reiseb\u00fcros",
    "sg:phone":"+41 33 654 18 42",
    "sg:postcode":"3902",
    "sg:province":"Valais",
    "wof:name":"Markus Z\u00fcrcher Weitwandern",
    "wof:placetype":"venue"
},
  "geometry": {"coordinates":[7.6955251694,46.6565361023],"type":"Point"}
}