{
  "type": "Feature",
  "properties": {
    "iso:country":"CH",
    "sg:address":"St. Jakobs-strasse 106",
    "sg:city":"Muttenz",
    "sg:orig_category":"Unclassifiable Establishments",
    "sg:postcode":"4132",
    "sg:province":"Basel-Landschaft",
    "wof:name":"Idea Gastro Gmbh",
    "wof:placetype":"venue"
},
  "geometry": {"coordinates":[7.6336507797,47.5319519043],"type":"Point"}
}