{
  "type": "Feature",
  "properties": {
    "iso:country":"CH",
    "sg:address":"Chemin Des Addreys 6",
    "sg:city":"Ste-croix",
    "sg:orig_category":"Elektroinstallation",
    "sg:phone":"+41 24 454 27 31",
    "sg:postcode":"1450",
    "sg:province":"Vaud",
    "wof:name":"Cornuz Daniel",
    "wof:placetype":"venue"
},
  "geometry": {"coordinates":[6.5108909607,46.8210945129],"type":"Point"}
}