{
  "type": "Feature",
  "properties": {
    "iso:country":"CH",
    "sg:address":"Fraum\u00fcnsterstrasse 15 8001 Z\u00fcrich. Postfach 4139",
    "sg:city":"Z\u00fcrich",
    "sg:orig_category":"Interessenvertretungen U sonstige Vereinigungen Sonstige Institutionen des Sozialwesens ohne Beherbe",
    "sg:phone":"+41 12835005",
    "sg:postcode":"8022",
    "sg:province":"Z\u00fcrich",
    "wof:name":"Stiftung Kreatives Alter",
    "wof:placetype":"venue"
},
  "geometry": {"coordinates":[8.5408449173,47.3684196472],"type":"Point"}
}