{
  "type": "Feature",
  "properties": {
    "iso:country":"CH",
    "sg:address":"Milit\u00e4rstrasse 39",
    "sg:city":"Bern",
    "sg:orig_category":"Detailhandel mit elektrischen Haushalts-,Radio U Fernsehger\u00e4ten sowie Musikinstrumenten",
    "sg:phone":"+41 56 496 07 78",
    "sg:postcode":"3014",
    "sg:province":"Bern",
    "wof:name":"Ferob Gmbh Haushaltger\u00e4te; Handel Usw",
    "wof:placetype":"venue"
},
  "geometry": {"coordinates":[8.3095674515,47.3995933533],"type":"Point"}
}