{
  "type": "Feature",
  "properties": {
    "iso:country":"CH",
    "sg:address":"Ringstrasse 30",
    "sg:city":"Langenthal",
    "sg:orig_category":"Non-Classified Establishments",
    "sg:postcode":"4900",
    "sg:province":"Bern",
    "wof:name":"Stiftung Viktoria Frei",
    "wof:placetype":"venue"
},
  "geometry": {"coordinates":[7.7814030647,47.2124176025],"type":"Point"}
}