{
  "type": "Feature",
  "properties": {
    "iso:country":"CH",
    "sg:address":"Landstrasse 170 9494 Schaan. Postfach 473",
    "sg:city":"Schaan",
    "sg:orig_category":"Detailhandel mit Geschenkartikeln U Souvenirs Parf\u00fcmerien U sonstiger Detailhandel mit kosmetischen ",
    "sg:phone":"+423 233 22 77",
    "sg:postcode":"9494",
    "wof:name":"Vitalplus-naturprodukte Ag",
    "wof:placetype":"venue"
},
  "geometry": {"coordinates":[9.5099601746,47.1561088562],"type":"Point"}
}