{
  "type": "Feature",
  "properties": {
    "iso:country":"CH",
    "sg:address":"Les Cerisiers",
    "sg:city":"Gorgier",
    "sg:orig_category":"Schulpflegen",
    "sg:phone":"+41 32 835 33 35",
    "sg:postcode":"2023",
    "sg:province":"Neuch\u00e2tel",
    "wof:name":"Commission Scolaire De L'\u00e9cole Secondaire Du Centre Scolaire",
    "wof:placetype":"venue"
},
  "geometry": {"coordinates":[6.7763948441,46.8995552063],"type":"Point"}
}