{
  "type": "Feature",
  "properties": {
    "iso:country":"CH",
    "sg:address":"Dorfstrasse 16",
    "sg:city":"Baar",
    "sg:orig_category":"Non-Classified Establishments",
    "sg:phone":"+41 41 988 22 42",
    "sg:postcode":"6340",
    "sg:province":"Zug",
    "wof:name":"Beck Und Untern\u00e4hrer Ag",
    "wof:placetype":"venue"
},
  "geometry": {"coordinates":[7.9269800186,47.1364784241],"type":"Point"}
}