{
  "type": "Feature",
  "properties": {
    "iso:country":"CH",
    "sg:address":"Bucheggstrasse 167",
    "sg:city":"Z\u00fcrich",
    "sg:orig_category":"Sonstiger Grosshandel",
    "sg:postcode":"8057",
    "sg:province":"Z\u00fcrich",
    "wof:name":"Jaura Anjum, Importer Import V. Sportartikeln",
    "wof:placetype":"venue"
},
  "geometry": {"coordinates":[8.5421066284,47.3991203308],"type":"Point"}
}