{
  "type": "Feature",
  "properties": {
    "iso:country":"CH",
    "sg:address":"Neudorfstrasse 8",
    "sg:city":"Kriessern",
    "sg:orig_category":"Massagestudios",
    "sg:phone":"+41 71 755 12 25",
    "sg:postcode":"9451",
    "sg:province":"St. Gallen",
    "wof:name":"Jutta Wirth Massagen",
    "wof:placetype":"venue"
},
  "geometry": {"coordinates":[9.6101760864,47.3626556396],"type":"Point"}
}