{
  "type": "Feature",
  "properties": {
    "iso:country":"CH",
    "sg:address":"Staldenstrasse 49",
    "sg:city":"Siebnen",
    "sg:orig_category":"Detailhandel mit Metallwaren, Anstrichmitteln, Glaswaren, Bau U Heimwerkerbedarf Glaserei",
    "sg:phone":"+41 55 440 57 20",
    "sg:postcode":"8854",
    "sg:province":"Schwyz",
    "wof:name":"Rainer Vogt Verglasungen",
    "wof:placetype":"venue"
},
  "geometry": {"coordinates":[8.8947200775,47.1718406677],"type":"Point"}
}