{
  "type": "Feature",
  "properties": {
    "iso:country":"CH",
    "sg:address":"Fluhmattstrasse 9",
    "sg:city":"Root",
    "sg:orig_category":"Maler U Glasergewerbe Malerei",
    "sg:phone":"+41 41 450 44 19",
    "sg:postcode":"6037",
    "sg:province":"Luzern",
    "wof:name":"Felder H.",
    "wof:placetype":"venue"
},
  "geometry": {"coordinates":[8.3857469559,47.10887146],"type":"Point"}
}