{
  "type": "Feature",
  "properties": {
    "iso:country":"CH",
    "sg:address":"Aproz Route D' 6",
    "sg:city":"Sitten",
    "sg:orig_category":"Herstellung von Metallkonstruktionen",
    "sg:phone":"+41 26 912 49 61",
    "sg:postcode":"1950",
    "sg:province":"Valais",
    "wof:name":"Btm S\u00e0rl",
    "wof:placetype":"venue"
},
  "geometry": {"coordinates":[7.0576848984,46.5961875916],"type":"Point"}
}