{
  "type": "Feature",
  "properties": {
    "iso:country":"CH",
    "sg:address":"Br\u00fcnigstrasse 5",
    "sg:city":"Sachseln",
    "sg:classifiers":[
        {
            "category":"Travel",
            "subcategory":"Hotels & Motels",
            "type":"Entertainment"
        }
    ],
    "sg:phone":"+41 41 660 14 17",
    "sg:postcode":"6072",
    "sg:province":"Obwalden",
    "sg:tags":[
        "hotels",
        "mit",
        "restaurant"
    ],
    "wof:name":"Zumstein M., Hotel Belvoir",
    "wof:placetype":"venue"
},
  "geometry": {"coordinates":[8.244093895,46.8801956177],"type":"Point"}
}