{
  "type": "Feature",
  "properties": {
    "iso:country":"CH",
    "sg:address":"Hani 201 A. Postfach 1",
    "sg:city":"Reutigen",
    "sg:orig_category":"G\u00fcterbef\u00f6rderung im Strassenverkehr",
    "sg:phone":"+41 33 657 21 57",
    "sg:postcode":"3647",
    "sg:province":"Bern",
    "wof:name":"Muldenservice Oetu Reutigen Br\u00f6nnimann Ulrich",
    "wof:placetype":"venue"
},
  "geometry": {"coordinates":[40.4046211243,38.4127082825],"type":"Point"}
}