{
  "type": "Feature",
  "properties": {
    "iso:country":"CH",
    "sg:address":"Kannenfeldplatz 17",
    "sg:city":"Basel",
    "sg:orig_category":"Non-Classified Establishments",
    "sg:postcode":"4056",
    "sg:province":"Basel-Stadt",
    "wof:name":"Carola Arndt Naturheilpraxis",
    "wof:placetype":"venue"
},
  "geometry": {"coordinates":[7.573225975,47.5649604797],"type":"Point"}
}