{
  "type": "Feature",
  "properties": {
    "iso:country":"CH",
    "sg:address":"St.georgen-strasse 44",
    "sg:city":"St.gallen",
    "sg:orig_category":"Instandhaltung U Reparatur von Automobilen Tankstellen",
    "sg:phone":"+41 71 222 75 92",
    "sg:postcode":"9000",
    "sg:province":"St. Gallen",
    "wof:name":"Ebn\u00f6ther Josef, M\u00fchlegg-garage",
    "wof:placetype":"venue"
},
  "geometry": {"coordinates":[9.3797264099,47.4193229675],"type":"Point"}
}