{
  "type": "Feature",
  "properties": {
    "iso:country":"CH",
    "sg:address":"Waldeggstrasse 16",
    "sg:city":"Interlaken",
    "sg:orig_category":"Architektur U Ingenieurb\u00fcros",
    "sg:phone":"+41 31 359 40 40",
    "sg:postcode":"3800",
    "sg:province":"Bern",
    "wof:name":"Lp Ingenieure Ag",
    "wof:placetype":"venue"
},
  "geometry": {"coordinates":[7.856832,46.682095],"type":"Point"}
}