{
  "type": "Feature",
  "properties": {
    "iso:country":"CH",
    "sg:address":"Uhlandstrasse 10",
    "sg:city":"Z\u00fcrich",
    "sg:orig_category":"Detailhandel mit Textilien Innendekorationsateliers",
    "sg:phone":"+41 12714756",
    "sg:postcode":"8037",
    "sg:province":"Z\u00fcrich",
    "wof:name":"Walter Fr\u00fch Polsterwerkst\u00e4tte Bettwaren",
    "wof:placetype":"venue"
},
  "geometry": {"coordinates":[8.5285816193,47.3945159912],"type":"Point"}
}