{
  "type": "Feature",
  "properties": {
    "iso:country":"CH",
    "sg:address":"Litschstrasse 7",
    "sg:city":"Altendorf",
    "sg:orig_category":"Chemin\u00e9e- and Ofenbau",
    "sg:phone":"+41 56 282 11 74",
    "sg:postcode":"8852",
    "sg:province":"Schwyz",
    "wof:name":"Walter Huwyler Ofenbau",
    "wof:placetype":"venue"
},
  "geometry": {"coordinates":[8.297795,47.486355],"type":"Point"}
}