{
  "type": "Feature",
  "properties": {
    "iso:country":"CH",
    "sg:address":"Rauracherstrasse 135",
    "sg:city":"Riehen",
    "sg:orig_category":"Detailhandel mit Fahrr\u00e4dern Fachdetailhandel in Verkaufsr\u00e4umen",
    "sg:phone":"+41 61 601 12 90",
    "sg:postcode":"4125",
    "sg:province":"Basel-Stadt",
    "wof:name":"Wenne's Velo-lade Hoferer Werner",
    "wof:placetype":"venue"
},
  "geometry": {"coordinates":[7.63478899,47.5676651001],"type":"Point"}
}