{
  "type": "Feature",
  "properties": {
    "iso:country":"CH",
    "sg:address":"Grienstrasse 100",
    "sg:city":"Basel",
    "sg:orig_category":"Stukkateurgewerbe, Gipserei U Verputzerei",
    "sg:postcode":"4055",
    "sg:province":"Basel-Stadt",
    "wof:name":"Saracino Pasquale Gipsergesch\u00e4ft & Fassadenbau",
    "wof:placetype":"venue"
},
  "geometry": {"coordinates":[7.5652880669,47.5602912903],"type":"Point"}
}