{
  "type": "Feature",
  "properties": {
    "iso:country":"CH",
    "sg:address":"Rorschacherstrasse 130 9450 L\u00fcchingen. Postfach",
    "sg:city":"L\u00fcchingen",
    "sg:orig_category":"RESTAURANTS: TEA-ROOMS",
    "sg:postcode":"9450",
    "sg:province":"St. Gallen",
    "wof:name":"Rest. Kreuz Kostenzer",
    "wof:placetype":"venue"
},
  "geometry": {"coordinates":[8.9214897156,47.2390213013],"type":"Point"}
}