{
  "type": "Feature",
  "properties": {
    "iso:country":"CH",
    "sg:address":"Rixheimerstrasse 3",
    "sg:city":"Basel",
    "sg:orig_category":"Architekturb\u00fcros",
    "sg:phone":"+41 61 382 57 44",
    "sg:postcode":"4055",
    "sg:province":"Basel-Stadt",
    "wof:name":"Rolf D\u00fcrring Architekturb\u00fcro",
    "wof:placetype":"venue"
},
  "geometry": {"coordinates":[7.569589,47.560848],"type":"Point"}
}