{
  "type": "Feature",
  "properties": {
    "iso:country":"CH",
    "sg:address":"Bahnhofstrasse 15",
    "sg:city":"Biel/bienne",
    "sg:orig_category":"Arztpraxen",
    "sg:phone":"+41 32 323 63 30",
    "sg:postcode":"2502",
    "sg:province":"Bern",
    "wof:name":"Dr.med.antoinette Otz Spezial\u00e4rztin Fmh",
    "wof:placetype":"venue"
},
  "geometry": {"coordinates":[7.244281,47.135044],"type":"Point"}
}