{
  "type": "Feature",
  "properties": {
    "iso:country":"CH",
    "sg:address":"Avenue De Miremont 14",
    "sg:city":"Gen\u00e8ve",
    "sg:orig_category":"Finanzierungsinstitutionen",
    "sg:phone":"+41 22 347 27 34",
    "sg:postcode":"1206",
    "sg:province":"Gen\u00e8ve",
    "wof:name":"Bpi Investissements Sa",
    "wof:placetype":"venue"
},
  "geometry": {"coordinates":[6.1557011604,46.1897888184],"type":"Point"}
}