{
  "type": "Feature",
  "properties": {
    "addr:full":"In Den Matten 139 Meltingen Solothurn 4233",
    "addr:housenumber":"139",
    "addr:postcode":"4233",
    "addr:street":"In Den Matten;Solothurn",
    "iso:country":"CH",
    "sg:address":"In Den Matten 139",
    "sg:city":"Meltingen",
    "sg:orig_category":"Allgemeiner Hoch U Tiefbau",
    "sg:phone":"+41 61 791 05 06",
    "sg:postcode":"4233",
    "sg:province":"Solothurn",
    "wof:name":"Marti Ag Solothurn",
    "wof:placetype":"venue"
},
  "geometry": {"coordinates":[7.592219,47.390682],"type":"Point"}
}