{
  "type": "Feature",
  "properties": {
    "iso:country":"CH",
    "sg:address":"Dorfstrasse 28",
    "sg:city":"Ettenhausen",
    "sg:classifiers":[
        {
            "category":"Retail",
            "subcategory":"Event Space",
            "type":"Services"
        }
    ],
    "sg:phone":"+41 52 365 22 36",
    "sg:postcode":"8356",
    "sg:province":"Thurgau",
    "sg:tags":[
        "box",
        "stall"
    ],
    "wof:name":"Paul Baumgartner Ag",
    "wof:placetype":"venue"
},
  "geometry": {"coordinates":[8.901367,47.47831],"type":"Point"}
}