{
  "type": "Feature",
  "properties": {
    "iso:country":"CH",
    "sg:address":"Rue Du Pont-levis 11",
    "sg:city":"St-prex",
    "sg:orig_category":"Detailhandel mit elektrischen Haushalts-,Radio U Fernsehger\u00e4ten sowie Musikinstrumenten",
    "sg:phone":"+41 21 806 15 73",
    "sg:postcode":"1162",
    "sg:province":"Vaud",
    "wof:name":"Hutzli Electricit\u00e9 Auto Thomas Kriegers Succr",
    "wof:placetype":"venue"
},
  "geometry": {"coordinates":[6.4584889412,46.4797592163],"type":"Point"}
}