{
  "type": "Feature",
  "properties": {
    "iso:country":"CH",
    "sg:address":"Mon-loisir Avenue 7",
    "sg:city":"Lausanne",
    "sg:orig_category":"Nahrungsmittel-Industrie: Rohstoffe",
    "sg:postcode":"1006",
    "sg:province":"Vaud",
    "wof:name":"Puce Et Lacarbonara Snc",
    "wof:placetype":"venue"
},
  "geometry": {"coordinates":[6.6330089569,46.5120124817],"type":"Point"}
}