{
  "type": "Feature",
  "properties": {
    "iso:country":"CH",
    "sg:address":"Hofstrasse 2",
    "sg:city":"Sarnen",
    "sg:orig_category":"Verkehrs- and Tourismusb\u00fcros",
    "sg:phone":"+41 17151815",
    "sg:postcode":"6060",
    "sg:province":"Obwalden",
    "wof:name":"Satour S\u00fcdafrikanisches Verkehrsb\u00fcro",
    "wof:placetype":"venue"
},
  "geometry": {"coordinates":[8.5451812744,47.3314056396],"type":"Point"}
}