{
  "type": "Feature",
  "properties": {
    "addr:full":"Berglistrasse 40 Luzern Luzern 6003",
    "addr:housenumber":"40",
    "addr:postcode":"6003",
    "addr:street":"Berglistrasse",
    "iso:country":"CH",
    "sg:address":"Berglistrasse 40",
    "sg:city":"Luzern",
    "sg:orig_category":"Architektur U Ingenieurb\u00fcros Herstellung von Elektromotoren, Generatoren U Transformatoren",
    "sg:phone":"+41 41 240 94 40",
    "sg:postcode":"6003",
    "sg:province":"Luzern",
    "wof:name":"Energieprojekte Kottmann",
    "wof:placetype":"venue"
},
  "geometry": {"coordinates":[8.297039,47.047394],"type":"Point"}
}