{
  "type": "Feature",
  "properties": {
    "iso:country":"CH",
    "sg:address":"Neuengasse 38",
    "sg:city":"Bern",
    "sg:orig_category":"Vermietung U Verpachtung von eigenen Immobilien",
    "sg:postcode":"3011",
    "sg:province":"Bern",
    "wof:name":"B\u00fchlmann Th\u00e9r\u00e8se Immobilien-treuhand + Gastro Immo",
    "wof:placetype":"venue"
},
  "geometry": {"coordinates":[7.4416389465,46.9490089417],"type":"Point"}
}