{
  "type": "Feature",
  "properties": {
    "iso:country":"CH",
    "sg:address":"Sonnenstrasse 24",
    "sg:city":"Biel/bienne",
    "sg:orig_category":"Glaserei Herstellung von Glas U Glaswaren",
    "sg:phone":"+41 32 341 24 33",
    "sg:postcode":"2504",
    "sg:province":"Bern",
    "wof:name":"B\u00fcchler Glas Ag Glaserei & Glashandel",
    "wof:placetype":"venue"
},
  "geometry": {"coordinates":[7.2655119896,47.1497917175],"type":"Point"}
}