{
  "type": "Feature",
  "properties": {
    "iso:country":"CH",
    "sg:address":"Via Pobbiette 11",
    "sg:city":"Manno",
    "sg:orig_category":"Fachdetailhandel in Verkaufsr\u00e4umen",
    "sg:phone":"+41 91 993 09 24",
    "sg:postcode":"6928",
    "sg:province":"Ticino",
    "wof:name":"Smartec Sa",
    "wof:placetype":"venue"
},
  "geometry": {"coordinates":[8.9242238998,46.0319252014],"type":"Point"}
}