{
  "type": "Feature",
  "properties": {
    "iso:country":"CH",
    "sg:address":"R\u00fcderswilschachen 387",
    "sg:city":"Zollbr\u00fcck",
    "sg:orig_category":"Malerei",
    "sg:phone":"+41 34 496 56 64",
    "sg:postcode":"3436",
    "sg:province":"Bern",
    "wof:name":"Fritz Erhard Malergesch\u00e4ft",
    "wof:placetype":"venue"
},
  "geometry": {"coordinates":[7.7408971786,46.9739875793],"type":"Point"}
}