{
  "type": "Feature",
  "properties": {
    "iso:country":"CH",
    "sg:address":"Breitenstrasse 19",
    "sg:city":"Steinen",
    "sg:orig_category":"Stukkateurgewerbe, Gipserei U Verputzerei",
    "sg:phone":"+41 41 832 10 80",
    "sg:postcode":"6422",
    "sg:province":"Schwyz",
    "wof:name":"Schuler Max",
    "wof:placetype":"venue"
},
  "geometry": {"coordinates":[8.6085948944,47.0493125916],"type":"Point"}
}