{
  "type": "Feature",
  "properties": {
    "iso:country":"CH",
    "sg:address":"Route De Fey 29",
    "sg:city":"Bercher",
    "sg:orig_category":"Physiotherapie",
    "sg:phone":"+41 21 887 72 72",
    "sg:postcode":"1038",
    "sg:province":"Vaud",
    "wof:name":"Didier Estienne Physioth\u00e9rapie",
    "wof:placetype":"venue"
},
  "geometry": {"coordinates":[6.7040748596,46.6884880066],"type":"Point"}
}