{
  "type": "Feature",
  "properties": {
    "iso:country":"CH",
    "sg:address":"Bahnhofstrasse 8 8854 Siebnen. Postfach 169",
    "sg:city":"Siebnen",
    "sg:classifiers":[
        {
            "category":"Restaurant",
            "type":"Food & Drink"
        }
    ],
    "sg:phone":"+41 55 440 13 51",
    "sg:postcode":"8854",
    "sg:province":"Schwyz",
    "wof:name":"Gasthof Centralhof",
    "wof:placetype":"venue"
},
  "geometry": {"coordinates":[8.8984384537,47.175327301],"type":"Point"}
}