{
  "type": "Feature",
  "properties": {
    "iso:country":"CH",
    "sg:address":"Ruelle Des Templiers 3-5",
    "sg:city":"Gen\u00e8ve",
    "sg:orig_category":"Werbeagenturen",
    "sg:phone":"+41 22 735 02 69",
    "sg:postcode":"1207",
    "sg:province":"Gen\u00e8ve",
    "wof:name":"Pierre William Chevalley Publicit\u00e9",
    "wof:placetype":"venue"
},
  "geometry": {"coordinates":[6.1568450928,46.2007865906],"type":"Point"}
}