{
  "type": "Feature",
  "properties": {
    "iso:country":"CH",
    "sg:address":"Wabernstrasse 41",
    "sg:city":"Bern",
    "sg:orig_category":"Vermietung von Automobilen",
    "sg:phone":"+41 31 372 13 13",
    "sg:postcode":"3007",
    "sg:province":"Bern",
    "wof:name":"Avis Autovermietung Ag",
    "wof:placetype":"venue"
},
  "geometry": {"coordinates":[7.4376468658,46.9391899109],"type":"Point"}
}