{
  "type": "Feature",
  "properties": {
    "iso:country":"CH",
    "sg:address":"Pl\u00e4nkestrasse 8 2502 Biel/bienne. Postfach",
    "sg:city":"Biel/bienne",
    "sg:orig_category":"Erschliessung von Grundst\u00fccken",
    "sg:postcode":"2502",
    "sg:province":"Bern",
    "wof:name":"Wogeno Frohsinn",
    "wof:placetype":"venue"
},
  "geometry": {"coordinates":[8.4534578323,47.2788772583],"type":"Point"}
}