{
  "type": "Feature",
  "properties": {
    "iso:country":"CH",
    "sg:address":"Bahnhofstrasse 8",
    "sg:city":"Langenthal",
    "sg:orig_category":"Detailhandel mit Bekleidung Detailhandel mit Damenbekleidung",
    "sg:phone":"+41 62 922 88 88",
    "sg:postcode":"4900",
    "sg:province":"Bern",
    "wof:name":"Boutique Lord Nelson, Christine Dubach",
    "wof:placetype":"venue"
},
  "geometry": {"coordinates":[7.788665,47.212753],"type":"Point"}
}