{
  "type": "Feature",
  "properties": {
    "iso:country":"CH",
    "sg:address":"Reppischtalstrasse 18",
    "sg:city":"Aeugstertal",
    "sg:orig_category":"Detailhandel mit Fleisch U Fleischwaren",
    "sg:postcode":"8914",
    "sg:province":"Z\u00fcrich",
    "wof:name":"Steffen Metzgerei + Traiteur Ag",
    "wof:placetype":"venue"
},
  "geometry": {"coordinates":[8.4854745865,47.2676887512],"type":"Point"}
}