{
  "type": "Feature",
  "properties": {
    "iso:country":"CH",
    "sg:address":"Rebbergstrasse 58b",
    "sg:city":"Oberengstringen",
    "sg:classifiers":[
        {
            "category":"Professional",
            "subcategory":"Accounting & Tax Preparation",
            "type":"Services"
        }
    ],
    "sg:phone":"+41 17502460",
    "sg:postcode":"8102",
    "sg:province":"Z\u00fcrich",
    "sg:tags":[
        "bookkeeping"
    ],
    "wof:name":"Hans-j\u00fcrgen Mehl",
    "wof:placetype":"venue"
},
  "geometry": {"coordinates":[8.46764,47.4086],"type":"Point"}
}