{
  "type": "Feature",
  "properties": {
    "iso:country":"CH",
    "sg:address":"Rue Mercier 16",
    "sg:city":"Montagne-moutier",
    "sg:orig_category":"Non-Classified Establishments",
    "sg:postcode":"2740",
    "sg:province":"Bern",
    "wof:name":"Cort\u00e9s Raoul.",
    "wof:placetype":"venue"
},
  "geometry": {"coordinates":[7.3898258209,47.2817192078],"type":"Point"}
}