{
  "type": "Feature",
  "properties": {
    "iso:country":"CH",
    "sg:address":"7742",
    "sg:city":"Poschiavo",
    "sg:orig_category":"Allgemeiner Hoch U Tiefbau Strassenbau",
    "sg:phone":"+41 79 212 65 11",
    "sg:postcode":"7742",
    "sg:province":"Graubunden",
    "wof:name":"Schmidli Et Cie Sa",
    "wof:placetype":"venue"
},
  "geometry": {"coordinates":[6.95848,46.277584],"type":"Point"}
}