{
  "type": "Feature",
  "properties": {
    "iso:country":"CH",
    "sg:address":"1754",
    "sg:city":"Avry-sur-matran",
    "sg:orig_category":"Verbraucherm\u00e4rkte > 2500 m2",
    "sg:phone":"+41 17777141",
    "sg:postcode":"1754",
    "sg:province":"Fribourg",
    "wof:name":"Migros-genossenschaft Z\u00fcrich",
    "wof:placetype":"venue"
},
  "geometry": {"coordinates":[8.4367771149,47.3542861938],"type":"Point"}
}