{
  "type": "Feature",
  "properties": {
    "iso:country":"CH",
    "sg:address":"Obere Waidstrasse 17 8037 Z\u00fcrich. Postfach",
    "sg:city":"Z\u00fcrich",
    "sg:orig_category":"Erbringung von Dienstleistungen f\u00fcr Unternehmen",
    "sg:phone":"+41 13622300",
    "sg:postcode":"8037",
    "sg:province":"Z\u00fcrich",
    "wof:name":"Mediag Messe-dienst Ag Z\u00fcrich",
    "wof:placetype":"venue"
},
  "geometry": {"coordinates":[8.5296516418,47.3982620239],"type":"Point"}
}