{
  "type": "Feature",
  "properties": {
    "iso:country":"CH",
    "sg:address":"Brunngasse 72 3800 Matten B. Interl. Postfach",
    "sg:city":"Interlaken",
    "sg:orig_category":"Detailhandel mit Sportartikeln Fachdetailhandel in Verkaufsr\u00e4umen",
    "sg:phone":"+41 33 821 12 12",
    "sg:postcode":"3800",
    "sg:province":"Bern",
    "wof:name":"Black Diamond B\u00fchler Ueli",
    "wof:placetype":"venue"
},
  "geometry": {"coordinates":[7.8671298027,46.6789321899],"type":"Point"}
}