{
  "type": "Feature",
  "properties": {
    "iso:country":"CH",
    "sg:address":"Forrenb\u00f6hlstrasse 19",
    "sg:city":"Appenzell",
    "sg:orig_category":"Herstellung von medizinischen U chirurgischen Ger\u00e4ten sowie orthop\u00e4dischen Vorrichtungen Zahntechnis",
    "sg:phone":"+41 71 787 26 16",
    "sg:postcode":"9050",
    "sg:province":"Appenzell Innerhoden",
    "wof:name":"D'olif Dental-labor Ag",
    "wof:placetype":"venue"
},
  "geometry": {"coordinates":[9.4201068878,47.3225364685],"type":"Point"}
}