{
  "type": "Feature",
  "properties": {
    "iso:country":"CH",
    "sg:address":"Sangenstrasse 37",
    "sg:city":"Weinfelden",
    "sg:orig_category":"Diskotheken, Dancings, Night Clubs",
    "sg:phone":"+41 71 622 20 90",
    "sg:postcode":"8570",
    "sg:province":"Thurgau",
    "wof:name":"Night-club Alte M\u00fchle",
    "wof:placetype":"venue"
},
  "geometry": {"coordinates":[9.1090221405,47.5574493408],"type":"Point"}
}