{
  "type": "Feature",
  "properties": {
    "iso:country":"CH",
    "sg:address":"Grand-rue 24",
    "sg:city":"Montreux",
    "sg:orig_category":"Detailhandel mit Geschenkartikeln U Souvenirs Fachdetailhandel in Verkaufsr\u00e4umen",
    "sg:phone":"+41 21 963 40 86",
    "sg:postcode":"1820",
    "sg:province":"Vaud",
    "wof:name":"Boutique Basil, M\u00fcller E.",
    "wof:placetype":"venue"
},
  "geometry": {"coordinates":[6.9103841782,46.4328956604],"type":"Point"}
}