{
  "type": "Feature",
  "properties": {
    "iso:country":"CH",
    "sg:address":"Bahnhofstrasse 7",
    "sg:city":"Zug",
    "sg:orig_category":"Unternehmensberatung",
    "sg:phone":"+41 79 402 38 58",
    "sg:postcode":"6300",
    "sg:province":"Zug",
    "wof:name":"Groupway Gmbh",
    "wof:placetype":"venue"
},
  "geometry": {"coordinates":[8.1862077713,47.4129486084],"type":"Point"}
}