{
  "type": "Feature",
  "properties": {
    "addr:full":"Rue D'italie 1204 Geneva 6",
    "addr:postcode":"1204",
    "addr:street":"Rue D'Italie",
    "iso:country":"CH",
    "sg:address":"Rue D'italie",
    "sg:city":"1204 Geneva",
    "sg:classifiers":[
        {
            "category":"Banks & Credit Unions",
            "subcategory":"Bank",
            "type":"Services"
        }
    ],
    "sg:postcode":"6",
    "wof:name":"Brennan Limited",
    "wof:placetype":"venue"
},
  "geometry": {"coordinates":[8.53345,47.368179],"type":"Point"}
}