{
  "type": "Feature",
  "properties": {
    "iso:country":"CH",
    "sg:address":"Cattaneo Viale 17a",
    "sg:city":"Lugano",
    "sg:orig_category":"Vermietung U Verpachtung von eigenen Immobilien",
    "sg:postcode":"6900",
    "sg:province":"Ticino",
    "wof:name":"Sidef Sa",
    "wof:placetype":"venue"
},
  "geometry": {"coordinates":[8.958823204,46.0059089661],"type":"Point"}
}