{
  "type": "Feature",
  "properties": {
    "iso:country":"CH",
    "sg:address":"Haspiweg 6",
    "sg:city":"Krauchthal",
    "sg:orig_category":"Sportvereine Turnen Vereine Damen",
    "sg:postcode":"3326",
    "sg:province":"Bern",
    "wof:name":"Damenturnverein Stv Lauenen",
    "wof:placetype":"venue"
},
  "geometry": {"coordinates":[7.3220591545,46.4248275757],"type":"Point"}
}