{
  "type": "Feature",
  "properties": {
    "iso:country":"CH",
    "sg:address":"Route De Champoz",
    "sg:city":"B\u00e9vilard",
    "sg:orig_category":"Sportvereine Ballsport Tennis",
    "sg:phone":"+41 32 492 10 94",
    "sg:postcode":"2735",
    "sg:province":"Bern",
    "wof:name":"Tennis-club",
    "wof:placetype":"venue"
},
  "geometry": {"coordinates":[7.2824091911,47.2421264648],"type":"Point"}
}