{
  "type": "Feature",
  "properties": {
    "iso:country":"CH",
    "sg:address":"Hinterscheidzaun",
    "sg:city":"Eriz",
    "sg:orig_category":"Sportschulen Ski-& Snowboardschulen",
    "sg:phone":"+41 33 453 15 87",
    "sg:postcode":"3619",
    "sg:province":"Bern",
    "wof:name":"Schweiz.skischule Herrn Hans Jaun",
    "wof:placetype":"venue"
},
  "geometry": {"coordinates":[7.7775001526,46.7882156372],"type":"Point"}
}