{
  "type": "Feature",
  "properties": {
    "iso:country":"CH",
    "sg:address":"Rue Des Uttins 22",
    "sg:city":"Yverdon-les-bains",
    "sg:orig_category":"Detailhandel mit Fleisch U Fleischwaren",
    "sg:phone":"+41 24 426 14 24",
    "sg:postcode":"1400",
    "sg:province":"Vaud",
    "wof:name":"Fr\u00e9dy Buchs Boucherie-charcuterie",
    "wof:placetype":"venue"
},
  "geometry": {"coordinates":[6.6276798248,46.7851333618],"type":"Point"}
}