{
  "type": "Feature",
  "properties": {
    "iso:country":"CH",
    "sg:address":"Ruestal",
    "sg:city":"Amden",
    "sg:orig_category":"Arztpraxen",
    "sg:phone":"+41 55 611 11 10",
    "sg:postcode":"8873",
    "sg:province":"St. Gallen",
    "wof:name":"Dr.med.leo F\u00fcrer Arzt F.allgemeine Medizin Fmh",
    "wof:placetype":"venue"
},
  "geometry": {"coordinates":[9.143991,47.149647],"type":"Point"}
}