{
  "type": "Feature",
  "properties": {
    "iso:country":"CH",
    "sg:address":"Fischmarkt 10 4051 Basel. Postfach",
    "sg:city":"Basel",
    "sg:orig_category":"Kauf U Verkauf von Immobilien auf eigene Rechnung",
    "sg:phone":"+41 55 440 47 00",
    "sg:postcode":"4051",
    "sg:province":"Basel-Stadt",
    "wof:name":"Ag F\u00fcr Miet Und Eigentumswohnungen",
    "wof:placetype":"venue"
},
  "geometry": {"coordinates":[8.8964147568,47.1912956238],"type":"Point"}
}