{
  "type": "Feature",
  "properties": {
    "iso:country":"CH",
    "sg:address":"Im Schossacher 15",
    "sg:city":"D\u00fcbendorf",
    "sg:classifiers":[
        {
            "category":"Wholesale",
            "subcategory":"Medical Equipment & Supplies",
            "type":"Manufacturing & Wholesale Goods"
        }
    ],
    "sg:phone":"+41 4118216435",
    "sg:postcode":"8600",
    "sg:province":"Z\u00fcrich",
    "sg:tags":[
        "instrument",
        "health",
        "-",
        "precision"
    ],
    "wof:name":"Hess-d\u00dcbendorf",
    "wof:placetype":"venue"
},
  "geometry": {"coordinates":[8.6415748596,47.3936882019],"type":"Point"}
}