{
  "type": "Feature",
  "properties": {
    "iso:country":"CH",
    "sg:address":"Sarmenstorferstrasse 31",
    "sg:city":"Fahrwangen",
    "sg:orig_category":"Herstellung von Metallerzeugnissen ohne Maschinenbau Maschinenbau",
    "sg:phone":"+41 71 747 57 57",
    "sg:postcode":"5615",
    "sg:province":"Aargau",
    "wof:name":"Grabher Indosa-maschinenbau Ag, Au",
    "wof:placetype":"venue"
},
  "geometry": {"coordinates":[9.6402101517,47.4346046448],"type":"Point"}
}