{
  "type": "Feature",
  "properties": {
    "addr:full":"Rigistrasse 174 Baar Zug 6340",
    "addr:housenumber":"174",
    "addr:postcode":"6340",
    "addr:street":"Rigistrasse;Zug",
    "iso:country":"CH",
    "sg:address":"Rigistrasse 174",
    "sg:city":"Baar",
    "sg:orig_category":"Arztpraxen",
    "sg:phone":"+41 41 760 85 85",
    "sg:postcode":"6340",
    "sg:province":"Zug",
    "wof:name":"Dr.med.erika Scheiwiller Aerztin F.allgemeine Medizin",
    "wof:placetype":"venue"
},
  "geometry": {"coordinates":[8.53051,47.191952],"type":"Point"}
}