{
  "type": "Feature",
  "properties": {
    "iso:country":"CH",
    "sg:address":"Fisimattenweg 5",
    "sg:city":"Gr\u00e4nichen",
    "sg:orig_category":"Grosshandel mit Getreide, Saatgut U Futtermitteln",
    "sg:phone":"+41 62 842 29 68",
    "sg:postcode":"5722",
    "sg:province":"Aargau",
    "wof:name":"Fischer Max",
    "wof:placetype":"venue"
},
  "geometry": {"coordinates":[8.0878515244,47.3644828796],"type":"Point"}
}