{
  "type": "Feature",
  "properties": {
    "iso:country":"CH",
    "sg:address":"Zollweg 2 A",
    "sg:city":"Suhr",
    "sg:orig_category":"Architektur U Ingenieurb\u00fcros",
    "sg:phone":"+41 62 842 60 14",
    "sg:postcode":"5034",
    "sg:province":"Aargau",
    "wof:name":"Pl\u00fcss Ag, Architektur Und Generalunternehmung, Suhr",
    "wof:placetype":"venue"
},
  "geometry": {"coordinates":[8.067617,47.384457],"type":"Point"}
}