{
  "type": "Feature",
  "properties": {
    "addr:full":"Birsstrasse 62 Basel Basel-Stadt 4052",
    "addr:housenumber":"62",
    "addr:postcode":"4052",
    "addr:street":"Birsstrasse",
    "iso:country":"CH",
    "sg:address":"Birsstrasse 62",
    "sg:city":"Basel",
    "sg:orig_category":"Datenverarbeitungsdienste Softwareentwicklung U beratung",
    "sg:phone":"+41 61 312 31 57",
    "sg:postcode":"4052",
    "sg:province":"Basel-Stadt",
    "wof:name":"Hicon Information Consulting, Hoch S.",
    "wof:placetype":"venue"
},
  "geometry": {"coordinates":[7.621091,47.551495],"type":"Point"}
}