{
  "type": "Feature",
  "properties": {
    "iso:country":"CH",
    "sg:address":"Baarerstrasse 63 6300 Zug. Postfach",
    "sg:city":"Zug",
    "sg:orig_category":"Finanzierungsinstitutionen Verwaltung von Immobilien",
    "sg:phone":"+41 41 728 60 00",
    "sg:postcode":"6300",
    "sg:province":"Zug",
    "wof:name":"Pegasus Beratungs Und Verwaltungs Ag Uebernahme Von Beratungs Und Verwaltungsmandaten, Bes. Im Immobilienbereich Usw",
    "wof:placetype":"venue"
},
  "geometry": {"coordinates":[8.5173740387,47.1761703491],"type":"Point"}
}