{
  "type": "Feature",
  "properties": {
    "iso:country":"CH",
    "sg:address":"En Combes",
    "sg:city":"Luins",
    "sg:orig_category":"RESTAURANTS: TEA-ROOMS",
    "sg:postcode":"1184",
    "sg:province":"Vaud",
    "wof:name":"Soci\u00e9t\u00e9 Floda Sa",
    "wof:placetype":"venue"
},
  "geometry": {"coordinates":[6.2708721161,46.4450836182],"type":"Point"}
}