{
  "type": "Feature",
  "properties": {
    "iso:country":"CH",
    "sg:address":"Gurnigelstrasse 10",
    "sg:city":"Nidau",
    "sg:orig_category":"Herstellung von sonstigen elektrischen Ausr\u00fcstungen",
    "sg:postcode":"2560",
    "sg:province":"Bern",
    "wof:name":"Sergi A. Electronic",
    "wof:placetype":"venue"
},
  "geometry": {"coordinates":[7.2428941727,47.1279907227],"type":"Point"}
}