{
  "type": "Feature",
  "properties": {
    "iso:country":"CH",
    "sg:address":"Tannew\u00e4g 1 8197 Rafz. Postfach",
    "sg:city":"Z\u00fcrich",
    "sg:orig_category":"Grosshandel mit Bekleidung Herstellung von Oberbekleidung",
    "sg:phone":"+41 14502939",
    "sg:postcode":"8045",
    "sg:province":"Z\u00fcrich",
    "wof:name":"Early-bird Ag",
    "wof:placetype":"venue"
},
  "geometry": {"coordinates":[8.5386199951,47.6096496582],"type":"Point"}
}