{
  "type": "Feature",
  "properties": {
    "iso:country":"CH",
    "sg:address":"Rebberg 191",
    "sg:city":"Wohlenschwil",
    "sg:orig_category":"Pensionskassen",
    "sg:postcode":"5512",
    "sg:province":"Aargau",
    "wof:name":"Stiftung Alte M\u00fchle Wohlenschwil",
    "wof:placetype":"venue"
},
  "geometry": {"coordinates":[8.2594003677,47.4262504578],"type":"Point"}
}