{
  "type": "Feature",
  "properties": {
    "iso:country":"CH",
    "sg:address":"Schwarzenburgstrasse 3147 Mittelh\u00e4usern. Postfach",
    "sg:city":"Mittelh\u00e4usern",
    "sg:orig_category":"G\u00fcterbef\u00f6rderung im Strassenverkehr",
    "sg:phone":"+41 79 651 42 36",
    "sg:postcode":"3147",
    "sg:province":"Bern",
    "wof:name":"Pirol Ag",
    "wof:placetype":"venue"
},
  "geometry": {"coordinates":[7.3755321503,46.8791389465],"type":"Point"}
}