{
  "type": "Feature",
  "properties": {
    "iso:country":"CH",
    "sg:address":"Rue De Riddes 87",
    "sg:city":"Sion",
    "sg:orig_category":"Herstellung von k\u00e4lte U lufttechnischen Erzeugnissen f\u00fcr gewerbliche Zwecke Installation von Heizung",
    "sg:phone":"+41 27 203 38 68",
    "sg:postcode":"1950",
    "sg:province":"Valais",
    "wof:name":"Froid Et Climatisation, Conti L.",
    "wof:placetype":"venue"
},
  "geometry": {"coordinates":[7.3679361343,46.2225875854],"type":"Point"}
}