{
  "type": "Feature",
  "properties": {
    "addr:full":"Gare Avenue De La 24 Monthey Valais 1870",
    "addr:housenumber":"24",
    "addr:postcode":"1870",
    "addr:street":"Avenue De La",
    "iso:country":"CH",
    "sg:address":"Gare Avenue De La 24",
    "sg:city":"Monthey",
    "sg:orig_category":"Architektur U Ingenieurb\u00fcros",
    "sg:postcode":"1870",
    "sg:province":"Valais",
    "wof:name":"Pme-kmu - Bureau D'architecte & Associ\u00e9s Sa",
    "wof:placetype":"venue"
},
  "geometry": {"coordinates":[6.947147,46.251629],"type":"Point"}
}