{
  "type": "Feature",
  "properties": {
    "iso:country":"CH",
    "sg:address":"Berglistrasse 73d",
    "sg:city":"Wattwil",
    "sg:orig_category":"Sportvereine Ski",
    "sg:phone":"+41 71 988 65 49",
    "sg:postcode":"9630",
    "sg:province":"St. Gallen",
    "wof:name":"Skiclub Neu St.johann",
    "wof:placetype":"venue"
},
  "geometry": {"coordinates":[9.0877475739,47.3102378845],"type":"Point"}
}