{
  "type": "Feature",
  "properties": {
    "iso:country":"CH",
    "sg:address":"Oberdorfstrasse 12",
    "sg:city":"Bonstetten",
    "sg:orig_category":"Organisationen des Gesundheitswesen",
    "sg:phone":"+41 17002249",
    "sg:postcode":"8906",
    "sg:province":"Z\u00fcrich",
    "wof:name":"Samariterv.bonstetten-wettswil",
    "wof:placetype":"venue"
},
  "geometry": {"coordinates":[8.4689559937,47.3130073547],"type":"Point"}
}