{
  "type": "Feature",
  "properties": {
    "iso:country":"CH",
    "sg:address":"Weberstrasse 21",
    "sg:city":"Z\u00fcrich",
    "sg:orig_category":"Datenverarbeitungsdienste Sonstige mit der Informatik verbundene T\u00e4tigkeiten",
    "sg:phone":"+41 12959494",
    "sg:postcode":"8004",
    "sg:province":"Z\u00fcrich",
    "wof:name":"Datahand Ag",
    "wof:placetype":"venue"
},
  "geometry": {"coordinates":[8.527837,47.370972],"type":"Point"}
}