{
  "type": "Feature",
  "properties": {
    "iso:country":"CH",
    "sg:address":"Feldstrasse 25",
    "sg:city":"Urdorf",
    "sg:orig_category":"Grosshandel mit lebenden Tieren",
    "sg:postcode":"8902",
    "sg:province":"Z\u00fcrich",
    "wof:name":"Flammer-vetter Karl.",
    "wof:placetype":"venue"
},
  "geometry": {"coordinates":[8.9997148514,47.4767303467],"type":"Point"}
}