{
  "type": "Feature",
  "properties": {
    "iso:country":"CH",
    "sg:address":"Rue Du Coll\u00e8ge 2",
    "sg:city":"Ste-croix",
    "sg:orig_category":"Polizei",
    "sg:phone":"+41 27 722 20 21",
    "sg:postcode":"1450",
    "sg:province":"Vaud",
    "wof:name":"Police Cantonale",
    "wof:placetype":"venue"
},
  "geometry": {"coordinates":[7.0734558105,46.1057395935],"type":"Point"}
}