{
  "type": "Feature",
  "properties": {
    "iso:country":"CH",
    "sg:address":"H\u00f6henweg 47",
    "sg:city":"Binningen",
    "sg:orig_category":"Schreib U \u00dcbersetzungsb\u00fcros",
    "sg:phone":"+41 61 302 27 73",
    "sg:postcode":"4102",
    "sg:province":"Basel-Landschaft",
    "wof:name":"Texex, Burri Liselotte",
    "wof:placetype":"venue"
},
  "geometry": {"coordinates":[7.5677189827,47.5433921814],"type":"Point"}
}