{
  "type": "Feature",
  "properties": {
    "iso:country":"CH",
    "sg:address":"Ludetswilerstrasse 19",
    "sg:city":"Neschwil",
    "sg:classifiers":[
        {
            "category":"Restaurant",
            "type":"Food & Drink"
        }
    ],
    "sg:phone":"+41 52 384 11 36",
    "sg:postcode":"8484",
    "sg:province":"Z\u00fcrich",
    "wof:name":"Restaurant Freihof",
    "wof:placetype":"venue"
},
  "geometry": {"coordinates":[8.7889690399,47.4291534424],"type":"Point"}
}