{
  "type": "Feature",
  "properties": {
    "iso:country":"CH",
    "sg:address":"Albisstrasse 1",
    "sg:city":"Mettmenstetten",
    "sg:classifiers":[
        {
            "category":"Restaurant",
            "type":"Food & Drink"
        }
    ],
    "sg:phone":"+41 17670201",
    "sg:postcode":"8932",
    "sg:province":"Z\u00fcrich",
    "wof:name":"Restaurant Zum Weissen R\u00f6ssli",
    "wof:placetype":"venue"
},
  "geometry": {"coordinates":[8.4632902145,47.2436218262],"type":"Point"}
}