{
  "type": "Feature",
  "properties": {
    "iso:country":"CH",
    "sg:address":"Schlossgasse 2 8820 W\u00e4denswil. Postfach",
    "sg:city":"W\u00e4denswil",
    "sg:orig_category":"Grosshandel mit sonstigen Gebrauchs U Verbrauchsg\u00fctern",
    "sg:phone":"+41 17809250",
    "sg:postcode":"8820",
    "sg:province":"Z\u00fcrich",
    "wof:name":"White Dragon Gmbh Perlen, Suiseki, Steinobjekte; Verarbeitung, Handel Usw",
    "wof:placetype":"venue"
},
  "geometry": {"coordinates":[8.6779594421,47.2256584167],"type":"Point"}
}