{
  "type": "Feature",
  "properties": {
    "iso:country":"CH",
    "sg:address":"Forellenweg 34",
    "sg:city":"Tamins",
    "sg:orig_category":"Detailhandel mit Antiquit\u00e4ten U Gebrauchtwaren in Verkaufsr\u00e4umen",
    "sg:phone":"+41 81 641 26 83",
    "sg:postcode":"7015",
    "sg:province":"Graubunden",
    "wof:name":"Beeler Claudio",
    "wof:placetype":"venue"
},
  "geometry": {"coordinates":[9.411422,46.82959],"type":"Point"}
}