{
  "type": "Feature",
  "properties": {
    "iso:country":"CH",
    "sg:address":"Altstetterstrasse 153",
    "sg:city":"Z\u00fcrich",
    "sg:orig_category":"Detailhandel mit Bekleidung Detailhandel mit Textilien",
    "sg:phone":"+41 14323161",
    "sg:postcode":"8048",
    "sg:province":"Z\u00fcrich",
    "wof:name":"Joseph Rubinfeld Textilwaren",
    "wof:placetype":"venue"
},
  "geometry": {"coordinates":[8.486629,47.387245],"type":"Point"}
}