{
  "type": "Feature",
  "properties": {
    "iso:country":"CH",
    "sg:address":"Steinh\u00f6lzlistrasse 5",
    "sg:city":"Gerlafingen",
    "sg:orig_category":"Kauf U Verkauf von Immobilien auf eigene Rechnung",
    "sg:postcode":"4563",
    "sg:province":"Solothurn",
    "wof:name":"Steinlin Immobilien Gmbh",
    "wof:placetype":"venue"
},
  "geometry": {"coordinates":[9.0502166748,47.4674339294],"type":"Point"}
}