{
  "type": "Feature",
  "properties": {
    "iso:country":"CH",
    "sg:address":"L\u00e4ndliweg 2 5400 Baden. Postfach",
    "sg:city":"Baden",
    "sg:orig_category":"Polizei",
    "sg:phone":"+41 17147010",
    "sg:postcode":"5401",
    "sg:province":"Aargau",
    "wof:name":"Kantonspolizei",
    "wof:placetype":"venue"
},
  "geometry": {"coordinates":[8.5404014587,47.2887573242],"type":"Point"}
}