{
  "type": "Feature",
  "properties": {
    "iso:country":"CH",
    "sg:address":"M\u00fchledorfstrasse 15",
    "sg:city":"Niederg\u00f6sgen",
    "sg:orig_category":"Detailhandel mit Getr\u00e4nken",
    "sg:phone":"+41 62 849 35 57",
    "sg:postcode":"5013",
    "sg:province":"Solothurn",
    "wof:name":"K\u00e4thy Meier Weinhandlung",
    "wof:placetype":"venue"
},
  "geometry": {"coordinates":[7.9704499245,47.3686714172],"type":"Point"}
}