{
  "type": "Feature",
  "properties": {
    "iso:country":"CH",
    "sg:address":"Via San Gottardo 146",
    "sg:city":"Savosa",
    "sg:orig_category":"Tankstellen",
    "sg:phone":"+41 91 967 52 32",
    "sg:postcode":"6942",
    "sg:province":"Ticino",
    "wof:name":"Di Luzio Antonio Stazione Di Benzina Con Chiosco",
    "wof:placetype":"venue"
},
  "geometry": {"coordinates":[8.9410581589,46.0163764954],"type":"Point"}
}