{
  "type": "Feature",
  "properties": {
    "iso:country":"CH",
    "sg:address":"2720",
    "sg:city":"Tramlingen",
    "sg:orig_category":"Detailhandel mit Antiquit\u00e4ten Detailhandel mit Antiquit\u00e4ten U Gebrauchtwaren in Verkaufsr\u00e4umen",
    "sg:phone":"+41 56 282 52 92",
    "sg:postcode":"2720",
    "sg:province":"Bern",
    "wof:name":"Vouga E. + C.",
    "wof:placetype":"venue"
},
  "geometry": {"coordinates":[8.2745838165,47.4970741272],"type":"Point"}
}