{
  "type": "Feature",
  "properties": {
    "iso:country":"CH",
    "sg:address":"World Trade Center Avenue De 2",
    "sg:city":"Lausanne",
    "sg:orig_category":"Softwareentwicklung U beratung",
    "sg:phone":"+41 81 330 14 60",
    "sg:postcode":"1000",
    "sg:province":"Vaud",
    "wof:name":"Micropool Gmbh",
    "wof:placetype":"venue"
},
  "geometry": {"coordinates":[9.4995269775,47.006362915],"type":"Point"}
}