{
  "type": "Feature",
  "properties": {
    "iso:country":"CH",
    "sg:address":"Via Cappella 2",
    "sg:city":"Losone",
    "sg:orig_category":"Architektur U Ingenieurb\u00fcros",
    "sg:phone":"+41 91 791 51 82",
    "sg:postcode":"6616",
    "sg:province":"Ticino",
    "wof:name":"Dr. Paolo Ammann Sa Studio Di Geologia",
    "wof:placetype":"venue"
},
  "geometry": {"coordinates":[8.76034,46.166031],"type":"Point"}
}