{
  "type": "Feature",
  "properties": {
    "iso:country":"CH",
    "sg:address":"Dorfstrasse 6",
    "sg:city":"Engelberg",
    "sg:orig_category":"Museen",
    "sg:phone":"+41 41 460 07 50",
    "sg:postcode":"6390",
    "sg:province":"Obwalden",
    "wof:name":"Teddyb\u00e4r-museum Gmbh Sempach",
    "wof:placetype":"venue"
},
  "geometry": {"coordinates":[8.2235832214,47.131149292],"type":"Point"}
}