{
  "type": "Feature",
  "properties": {
    "iso:country":"CH",
    "sg:address":"Rte Nant-d'avril 107",
    "sg:city":"Meyrin",
    "sg:classifiers":[
        {
            "category":"Manufacturing",
            "subcategory":"Printing",
            "type":"Manufacturing & Wholesale Goods"
        }
    ],
    "sg:phone":"+41 22 782 14 44",
    "sg:postcode":"1217",
    "sg:province":"Gen\u00e8ve",
    "sg:tags":[
        "publishing"
    ],
    "wof:name":"Rs Reliure Service Sa",
    "wof:placetype":"venue"
},
  "geometry": {"coordinates":[6.0607328415,46.2249145508],"type":"Point"}
}