{
  "type": "Feature",
  "properties": {
    "iso:country":"CH",
    "sg:address":"Hubstrasse 31",
    "sg:city":"Rebstein",
    "sg:orig_category":"Unclassifiable Establishments",
    "sg:postcode":"9445",
    "sg:province":"St. Gallen",
    "wof:name":"Herbert Rammerstorfer Consulting",
    "wof:placetype":"venue"
},
  "geometry": {"coordinates":[9.581278801,47.4026641846],"type":"Point"}
}