{
  "type": "Feature",
  "properties": {
    "iso:country":"CH",
    "sg:address":"Rue De La Plaine 19",
    "sg:city":"Yverdon-les-bains",
    "sg:orig_category":"Satzherstellung U Reproduktion",
    "sg:phone":"+41 24 426 02 10",
    "sg:postcode":"1400",
    "sg:province":"Vaud",
    "wof:name":"Papyrus, Centlivres Edith",
    "wof:placetype":"venue"
},
  "geometry": {"coordinates":[6.6433019638,46.7778282166],"type":"Point"}
}