{
  "type": "Feature",
  "properties": {
    "iso:country":"CH",
    "sg:address":"Untere Steingrubenstrasse 19",
    "sg:city":"Solothurn",
    "sg:orig_category":"Architekturb\u00fcros",
    "sg:phone":"+41 32 622 09 54",
    "sg:postcode":"4500",
    "sg:province":"Solothurn",
    "wof:name":"Kurt Stalder Architekturb\u00fcro",
    "wof:placetype":"venue"
},
  "geometry": {"coordinates":[7.535097,47.211567],"type":"Point"}
}