{
  "type": "Feature",
  "properties": {
    "iso:country":"CH",
    "sg:address":"9043",
    "sg:city":"Trogen",
    "sg:orig_category":"Vereine Abstinenten",
    "sg:postcode":"9043",
    "sg:province":"Appenzell Ausserrhoden",
    "wof:name":"Blaues Kreuz",
    "wof:placetype":"venue"
},
  "geometry": {"coordinates":[9.4645671844,47.4079322815],"type":"Point"}
}