{
  "type": "Feature",
  "properties": {
    "iso:country":"CH",
    "sg:address":"Lindenbergstrasse 21",
    "sg:city":"H\u00fcnenberg",
    "sg:orig_category":"Kunsthandel",
    "sg:phone":"+41 41 780 65 13",
    "sg:postcode":"6331",
    "sg:province":"Zug",
    "wof:name":"Rosmarie N\u00e4pflin Galerie",
    "wof:placetype":"venue"
},
  "geometry": {"coordinates":[8.426363945,47.1796836853],"type":"Point"}
}