{
  "type": "Feature",
  "properties": {
    "iso:country":"CH",
    "sg:address":"Rue Sciob\u00e9ret",
    "sg:city":"Bulle",
    "sg:orig_category":"Detailhandel mit elektrischen Haushalts-,Radio U Fernsehger\u00e4ten sowie Musikinstrumenten",
    "sg:postcode":"1630",
    "sg:province":"Fribourg",
    "wof:name":"T\u00e9l\u00e9marc Sa",
    "wof:placetype":"venue"
},
  "geometry": {"coordinates":[7.0563287735,46.6130371094],"type":"Point"}
}