{
  "type": "Feature",
  "properties": {
    "iso:country":"CH",
    "sg:address":"Chamerstrasse 12c",
    "sg:city":"Zug",
    "sg:orig_category":"Revision Wirtschaftspr\u00fcfung, Steuerberatung U Treuhand",
    "sg:phone":"+41 79 440 32 82",
    "sg:postcode":"6300",
    "sg:province":"Zug",
    "wof:name":"Palmer Consultants Ag",
    "wof:placetype":"venue"
},
  "geometry": {"coordinates":[8.5116653442,47.1717948914],"type":"Point"}
}