{
  "type": "Feature",
  "properties": {
    "iso:country":"CH",
    "sg:address":"Dorf 49",
    "sg:city":"Walzenhausen",
    "sg:orig_category":"Wirtschaftspr\u00fcfung, Steuerberatung U Treuhand",
    "sg:phone":"+41 79 446 49 80",
    "sg:postcode":"9428",
    "sg:province":"Appenzell Ausserrhoden",
    "wof:name":"Rena Treuhand Gmbh",
    "wof:placetype":"venue"
},
  "geometry": {"coordinates":[9.6006317139,47.4505386353],"type":"Point"}
}