{
  "type": "Feature",
  "properties": {
    "iso:country":"CH",
    "sg:address":"Via Bossi 4",
    "sg:city":"Lugano",
    "sg:classifiers":[
        {
            "category":"Restaurant",
            "type":"Food & Drink"
        }
    ],
    "sg:phone":"+41 91 922 64 80",
    "sg:postcode":"6900",
    "sg:province":"Ticino",
    "wof:name":"Birreria City",
    "wof:placetype":"venue"
},
  "geometry": {"coordinates":[8.9534597397,46.0069160461],"type":"Point"}
}