{
  "type": "Feature",
  "properties": {
    "iso:country":"CH",
    "sg:address":"Via Crasta 6",
    "sg:city":"Samedan",
    "sg:orig_category":"Vermietung U Verpachtung von eigenen Immobilien",
    "sg:postcode":"7503",
    "sg:province":"Graubunden",
    "wof:name":"Verda Sa",
    "wof:placetype":"venue"
},
  "geometry": {"coordinates":[9.871427536,46.5337944031],"type":"Point"}
}