{
  "type": "Feature",
  "properties": {
    "iso:country":"CH",
    "sg:address":"Bernstrasse 181",
    "sg:city":"Rothrist",
    "sg:orig_category":"Unclassifiable Establishments",
    "sg:postcode":"4852",
    "sg:province":"Aargau",
    "wof:name":"Gr-mechanik Giovanoli & Rudolf",
    "wof:placetype":"venue"
},
  "geometry": {"coordinates":[9.4507074356,46.7033805847],"type":"Point"}
}