{
  "type": "Feature",
  "properties": {
    "iso:country":"CH",
    "sg:address":"8522",
    "sg:city":"H\u00e4uslenen",
    "sg:orig_category":"Sportvereine Sch\u00fctzen",
    "sg:phone":"+41 52 747 11 75",
    "sg:postcode":"8522",
    "sg:province":"Thurgau",
    "wof:name":"Sch\u00fctzengesellschaft",
    "wof:placetype":"venue"
},
  "geometry": {"coordinates":[8.8831300735,47.587348938],"type":"Point"}
}