{
  "type": "Feature",
  "properties": {
    "iso:country":"CH",
    "sg:address":"Gheiweg 6",
    "sg:city":"Einigen",
    "sg:orig_category":"RESTAURANTS: TEA-ROOMS",
    "sg:postcode":"3646",
    "sg:province":"Bern",
    "wof:name":"Ristorante Pizzeria Da Krebs, Bruno",
    "wof:placetype":"venue"
},
  "geometry": {"coordinates":[7.641854763,46.7110862732],"type":"Point"}
}