{
  "type": "Feature",
  "properties": {
    "iso:country":"CH",
    "sg:address":"Place Du Midi",
    "sg:city":"Estavayer-le-lac",
    "sg:orig_category":"Verkehrs- and Tourismusb\u00fcros",
    "sg:phone":"+41 26 663 12 37",
    "sg:postcode":"1470",
    "sg:province":"Fribourg",
    "wof:name":"Office Du Tourisme",
    "wof:placetype":"venue"
},
  "geometry": {"coordinates":[6.8456549644,46.8481712341],"type":"Point"}
}