{
  "type": "Feature",
  "properties": {
    "iso:country":"CH",
    "sg:address":"Am Kronenplatz Hauptgasse 67",
    "sg:city":"Solothurn",
    "sg:orig_category":"Detailhandel mit Beleuchtungs U Haushaltsgegenst\u00e4nden Detailhandel mit Radio U Fernsehger\u00e4ten",
    "sg:phone":"+41 22 301 41 42",
    "sg:postcode":"4500",
    "sg:province":"Solothurn",
    "wof:name":"Fust Sa Carouge \u00e9lectrom\u00e9nager",
    "wof:placetype":"venue"
},
  "geometry": {"coordinates":[6.143475,46.185608],"type":"Point"}
}