{
  "type": "Feature",
  "properties": {
    "iso:country":"CH",
    "sg:address":"St. Germanstrasse",
    "sg:city":"Gurmels",
    "sg:orig_category":"Detailhandel mit Brot, Back U S\u00fcsswaren",
    "sg:postcode":"3212",
    "sg:province":"Fribourg",
    "wof:name":"Dorfb\u00e4ckerei Riedo Und Defferard Ag",
    "wof:placetype":"venue"
},
  "geometry": {"coordinates":[7.173715,46.89323],"type":"Point"}
}