{
  "type": "Feature",
  "properties": {
    "iso:country":"CH",
    "sg:address":"Breitmatten",
    "sg:city":"Herbriggen",
    "sg:orig_category":"Grosshandel mit lebenden Tieren",
    "sg:phone":"+41 27 956 22 06",
    "sg:postcode":"3927",
    "sg:province":"Valais",
    "wof:name":"Erich Lengen Viehhandel",
    "wof:placetype":"venue"
},
  "geometry": {"coordinates":[7.7905101776,46.1514358521],"type":"Point"}
}