{
  "type": "Feature",
  "properties": {
    "iso:country":"CH",
    "sg:address":"Breite 13",
    "sg:city":"Merenschwand",
    "sg:orig_category":"Allgemeiner Gartenbau Landschaftsplanungsb\u00fcros U Gartenarchitekturb\u00fcros",
    "sg:phone":"+41 56 670 98 68",
    "sg:postcode":"5634",
    "sg:province":"Aargau",
    "wof:name":"Heggli Gartenbau Gmbh",
    "wof:placetype":"venue"
},
  "geometry": {"coordinates":[8.37574,47.262272],"type":"Point"}
}