{
  "type": "Feature",
  "properties": {
    "iso:country":"CH",
    "sg:address":"Loch\u00e4ckerstrasse 37 8302 Kloten. Postfach",
    "sg:city":"Z\u00fcrich",
    "sg:orig_category":"Grosshandel mit Getr\u00e4nken",
    "sg:postcode":"8049",
    "sg:province":"Z\u00fcrich",
    "wof:name":"Eicher Charles, Weinhandlung",
    "wof:placetype":"venue"
},
  "geometry": {"coordinates":[8.5914983749,47.4442367554],"type":"Point"}
}