{
  "type": "Feature",
  "properties": {
    "iso:country":"CH",
    "sg:address":"Schauburg 4b",
    "sg:city":"H\u00fcnenberg",
    "sg:classifiers":[
        {
            "category":"Professional",
            "subcategory":"Employment Agencies",
            "type":"Services"
        }
    ],
    "sg:phone":"+41 41 780 23 47",
    "sg:postcode":"6331",
    "sg:province":"Zug",
    "sg:tags":[
        "personal",
        "u",
        "stellenvermittlung"
    ],
    "wof:name":"Tempi-bureau Ohff P.",
    "wof:placetype":"venue"
},
  "geometry": {"coordinates":[8.4229736328,47.1772193909],"type":"Point"}
}