{
  "type": "Feature",
  "properties": {
    "iso:country":"CH",
    "sg:address":"Breitestrasse 28",
    "sg:city":"Zurzach",
    "sg:orig_category":"Sportvereine P\u00e9tanque",
    "sg:phone":"+41 19500707",
    "sg:postcode":"5330",
    "sg:province":"Aargau",
    "wof:name":"P\u00e9tanque-club Z\u00fcri-oberland",
    "wof:placetype":"venue"
},
  "geometry": {"coordinates":[8.781539917,47.36743927],"type":"Point"}
}