{
  "type": "Feature",
  "properties": {
    "iso:country":"CH",
    "sg:address":"Vicolo Delle Olive 23",
    "sg:city":"Ascona",
    "sg:orig_category":"Detailhandel mit Waren verschiedener Art, Hauptrichtung Nahrungsmittel",
    "sg:phone":"+41 91 791 15 76",
    "sg:postcode":"6612",
    "sg:province":"Ticino",
    "wof:name":"Giuseppe Camani",
    "wof:placetype":"venue"
},
  "geometry": {"coordinates":[8.7700061798,46.1544265747],"type":"Point"}
}