{
  "type": "Feature",
  "properties": {
    "iso:country":"CH",
    "sg:address":"M\u00fchlenstrasse 3",
    "sg:city":"Mollis",
    "sg:orig_category":"Architektur U Ingenieurb\u00fcros",
    "sg:phone":"+41 55 612 26 16",
    "sg:postcode":"8753",
    "sg:province":"Glarus",
    "wof:name":"Beglinger Gr\u00fcnplanungs Ag, Freiraumgestaltung, Garten Und Landschaftsarchitektur",
    "wof:placetype":"venue"
},
  "geometry": {"coordinates":[9.073807,47.08836],"type":"Point"}
}