{
  "type": "Feature",
  "properties": {
    "iso:country":"CH",
    "sg:address":"Bahnhofstrasse 7",
    "sg:city":"Wolhusen",
    "sg:orig_category":"Berufliche Weiterbildung, Erwachsenenbildung",
    "sg:phone":"+41 41 490 10 10",
    "sg:postcode":"6110",
    "sg:province":"Luzern",
    "wof:name":"Berufs Und Studienberatung Bezirk Wolhusen Bildungsinformationszentrum",
    "wof:placetype":"venue"
},
  "geometry": {"coordinates":[8.074283,47.058285],"type":"Point"}
}