{
  "type": "Feature",
  "properties": {
    "iso:country":"CH",
    "sg:address":"Schl\u00f6sslistrasse 48",
    "sg:city":"Ennetbaden",
    "sg:orig_category":"Reinigungsgewerbe",
    "sg:postcode":"5408",
    "sg:province":"Aargau",
    "wof:name":"Studer & Co",
    "wof:placetype":"venue"
},
  "geometry": {"coordinates":[8.3137550354,47.4769363403],"type":"Point"}
}