{
  "type": "Feature",
  "properties": {
    "iso:country":"CH",
    "sg:address":"Chemin De La Chapelle",
    "sg:city":"Misery-courtion",
    "sg:orig_category":"Erschliessung von Grundst\u00fccken",
    "sg:postcode":"1721",
    "sg:province":"Fribourg",
    "wof:name":"Habitat Coop Ssbb",
    "wof:placetype":"venue"
},
  "geometry": {"coordinates":[7.1019039154,46.8531455994],"type":"Point"}
}