{
  "type": "Feature",
  "properties": {
    "iso:country":"CH",
    "sg:address":"Rue De Moillebeau 42",
    "sg:city":"Gen\u00e8ve",
    "sg:orig_category":"Grosshandel mit B\u00fcromaschinen Grosshandel mit Datenverarbeitungsger\u00e4ten",
    "sg:phone":"+41 22 740 49 07",
    "sg:postcode":"1209",
    "sg:province":"Gen\u00e8ve",
    "wof:name":"Hi-d, Farkas",
    "wof:placetype":"venue"
},
  "geometry": {"coordinates":[6.1297497749,46.2219581604],"type":"Point"}
}