{
  "type": "Feature",
  "properties": {
    "iso:country":"CH",
    "sg:address":"T\u00f6belim\u00fclistrasse 6a",
    "sg:city":"Rheineck",
    "sg:orig_category":"Softwareentwicklung U beratung",
    "sg:postcode":"9424",
    "sg:province":"St. Gallen",
    "wof:name":"Proware Neumann",
    "wof:placetype":"venue"
},
  "geometry": {"coordinates":[9.5920028687,47.4627571106],"type":"Point"}
}