{
  "type": "Feature",
  "properties": {
    "iso:country":"CH",
    "sg:address":"Hauptstrasse",
    "sg:city":"Grindelwald",
    "sg:orig_category":"Sonstige mit Sport verbundene T\u00e4tigkeiten",
    "sg:postcode":"3818",
    "sg:province":"Bern",
    "wof:name":"Verein Schweizer Ski Und Schneesportschule Grindelwald",
    "wof:placetype":"venue"
},
  "geometry": {"coordinates":[8.0396413803,46.623500824],"type":"Point"}
}