{
  "type": "Feature",
  "properties": {
    "iso:country":"CH",
    "sg:address":"R\u00fctistrasse 2",
    "sg:city":"Baden",
    "sg:orig_category":"Technische, physikalische U chemische Untersuchung",
    "sg:postcode":"5400",
    "sg:province":"Aargau",
    "wof:name":"Treucom Holding (schweiz) Ag",
    "wof:placetype":"venue"
},
  "geometry": {"coordinates":[8.304848671,47.4752502441],"type":"Point"}
}