{
  "type": "Feature",
  "properties": {
    "iso:country":"CH",
    "sg:address":"Rudolfstrasse 19",
    "sg:city":"Winterthur",
    "sg:orig_category":"Betrieb U technische Hilfsdienste des Kultur U Unterhaltungswesens Sonstige Hilfsdienste des Kultur ",
    "sg:phone":"+41 52 213 85 00",
    "sg:postcode":"8400",
    "sg:province":"Z\u00fcrich",
    "wof:name":"Power Music Foundation, Buttauer & Ott",
    "wof:placetype":"venue"
},
  "geometry": {"coordinates":[8.723261,47.501259],"type":"Point"}
}