{
  "type": "Feature",
  "properties": {
    "iso:country":"CH",
    "sg:address":"6901 Lugano. Postfach Caselle Postale 2699",
    "sg:city":"Lugano",
    "sg:orig_category":"Sportvereine Boxen",
    "sg:postcode":"6901",
    "sg:province":"Ticino",
    "wof:name":"Atletic-club Lugano",
    "wof:placetype":"venue"
},
  "geometry": {"coordinates":[8.9555597305,46.0045394897],"type":"Point"}
}