{
  "type": "Feature",
  "properties": {
    "iso:country":"CH",
    "sg:address":"Thunstrasse 8 3510 Konolfingen. Postfach 138",
    "sg:city":"Konolfingen",
    "sg:orig_category":"Druckweiterverarbeitung Herstellung von Holzstoff, Papier, Karton U Pappe",
    "sg:phone":"+41 61 486 52 52",
    "sg:postcode":"3510",
    "sg:province":"Bern",
    "wof:name":"Karl Meyer & Co. Ag",
    "wof:placetype":"venue"
},
  "geometry": {"coordinates":[7.5471892357,47.5488204956],"type":"Point"}
}