{
  "type": "Feature",
  "properties": {
    "iso:country":"CH",
    "sg:address":"Steinhauserstrasse 51",
    "sg:city":"Zug",
    "sg:orig_category":"Non-Classified Establishments",
    "sg:phone":"+41 41 740 40 44",
    "sg:postcode":"6300",
    "sg:province":"Zug",
    "wof:name":"Swiss Lack Ag",
    "wof:placetype":"venue"
},
  "geometry": {"coordinates":[8.4930868149,47.1855430603],"type":"Point"}
}