{
  "type": "Feature",
  "properties": {
    "iso:country":"CH",
    "sg:address":"Bahnhofplatz 12",
    "sg:city":"M\u00fchlethurnen",
    "sg:orig_category":"Grosshandel mit Obst U Gem\u00fcse",
    "sg:phone":"+41 31 809 04 07",
    "sg:postcode":"3127",
    "sg:province":"Bern",
    "wof:name":"Ernst Schneider Landesprodukte Engros",
    "wof:placetype":"venue"
},
  "geometry": {"coordinates":[7.5136709213,46.8129386902],"type":"Point"}
}