{
  "type": "Feature",
  "properties": {
    "iso:country":"CH",
    "sg:address":"Falkenh\u00f6heweg 12a 3012 Bern. Postfach",
    "sg:city":"Bern",
    "sg:orig_category":"Reiseb\u00fcros U Reiseveranstalter",
    "sg:phone":"+41 31 301 11 44",
    "sg:postcode":"3005",
    "sg:province":"Bern",
    "wof:name":"Consularberatungs-service Steck Vermittlung Von Einreise-visa, Beratung Bei Einreisebestimmungen",
    "wof:placetype":"venue"
},
  "geometry": {"coordinates":[7.4338269234,46.9504089355],"type":"Point"}
}