{
  "type": "Feature",
  "properties": {
    "iso:country":"CH",
    "sg:address":"Rainweg 12",
    "sg:city":"Horgen",
    "sg:orig_category":"Bezirks, Sekundar, Realschulen, Oberstufe der Primarschulen",
    "sg:phone":"+41 17251050",
    "sg:postcode":"8810",
    "sg:province":"Z\u00fcrich",
    "wof:name":"Oberstufenschule Rainweg",
    "wof:placetype":"venue"
},
  "geometry": {"coordinates":[8.599472,47.256275],"type":"Point"}
}