{
  "type": "Feature",
  "properties": {
    "iso:country":"CH",
    "sg:address":"1445",
    "sg:city":"Vuiteboeuf",
    "sg:orig_category":"Darlehenskassen U Raiffeisenbanken",
    "sg:phone":"+41 21 907 86 24",
    "sg:postcode":"1445",
    "sg:province":"Vaud",
    "wof:name":"Banque Raiffeisen",
    "wof:placetype":"venue"
},
  "geometry": {"coordinates":[6.88147,46.581959],"type":"Point"}
}