{
  "type": "Feature",
  "properties": {
    "iso:country":"CH",
    "sg:address":"Lussy Route De 13",
    "sg:city":"St-prex",
    "sg:orig_category":"Sonstiges Versicherungsgewerbe",
    "sg:postcode":"1162",
    "sg:province":"Vaud",
    "wof:name":"Agence Corth\u00e9sy B.",
    "wof:placetype":"venue"
},
  "geometry": {"coordinates":[6.4576702118,46.4821166992],"type":"Point"}
}