{
  "type": "Feature",
  "properties": {
    "addr:full":"Muristrasse 70 Bern Bern 3006",
    "addr:housenumber":"70",
    "addr:postcode":"3006",
    "addr:street":"Muristrasse",
    "iso:country":"CH",
    "sg:address":"Muristrasse 70",
    "sg:city":"Bern",
    "sg:orig_category":"Architektur U Ingenieurb\u00fcros",
    "sg:postcode":"3006",
    "sg:province":"Bern",
    "wof:name":"Pims (projekt Informations Management System) Gmbh",
    "wof:placetype":"venue"
},
  "geometry": {"coordinates":[7.467071,46.941063],"type":"Point"}
}