{
  "type": "Feature",
  "properties": {
    "iso:country":"CH",
    "sg:address":"Zugerstrasse 25",
    "sg:city":"W\u00e4denswil",
    "sg:orig_category":"Interessenvertretungen",
    "sg:phone":"+41 17803870",
    "sg:postcode":"8820",
    "sg:province":"Z\u00fcrich",
    "wof:name":"Z\u00fcrifoti.",
    "wof:placetype":"venue"
},
  "geometry": {"coordinates":[8.6698894501,47.2295799255],"type":"Point"}
}