{
  "type": "Feature",
  "properties": {
    "iso:country":"CH",
    "sg:address":"Altweg",
    "sg:city":"Pfaffnau",
    "sg:orig_category":"Detailhandel mit Brot, Back U S\u00fcsswaren",
    "sg:phone":"+41 62 754 12 40",
    "sg:postcode":"6264",
    "sg:province":"Luzern",
    "wof:name":"Benno Schwizer B\u00e4ckerei-konditorei",
    "wof:placetype":"venue"
},
  "geometry": {"coordinates":[7.901345,47.230175],"type":"Point"}
}