{
  "type": "Feature",
  "properties": {
    "iso:country":"CH",
    "sg:address":"Saint-germain Centre 1965 Chandolin-savi\u00e8se. Postfach",
    "sg:city":"Chandolin-savi\u00e8se",
    "sg:orig_category":"Elektroinstallation",
    "sg:phone":"+41 41 240 60 50",
    "sg:postcode":"1965",
    "sg:province":"Valais",
    "wof:name":"Jomatec Matter Joe",
    "wof:placetype":"venue"
},
  "geometry": {"coordinates":[8.4588003159,47.0932502747],"type":"Point"}
}