{
  "type": "Feature",
  "properties": {
    "iso:country":"CH",
    "sg:address":"Untere Br\u00fchlstrasse 31",
    "sg:city":"Zofingen",
    "sg:orig_category":"Autogaragen",
    "sg:phone":"+41 55 246 49 59",
    "sg:postcode":"4800",
    "sg:province":"Aargau",
    "wof:name":"Team Garage Ruedi Schwengeler",
    "wof:placetype":"venue"
},
  "geometry": {"coordinates":[8.9413,47.28841],"type":"Point"}
}