{
  "type": "Feature",
  "properties": {
    "iso:country":"CH",
    "sg:address":"Sommerstrasse 6",
    "sg:city":"Gr\u00e4nichen",
    "sg:orig_category":"Blumen U Zierpflanzenbau Detailhandel mit Blumen U Pflanzen",
    "sg:phone":"+41 62 842 14 43",
    "sg:postcode":"5722",
    "sg:province":"Aargau",
    "wof:name":"St\u00f6ckli.",
    "wof:placetype":"venue"
},
  "geometry": {"coordinates":[8.096441,47.361961],"type":"Point"}
}