{
  "type": "Feature",
  "properties": {
    "iso:country":"CH",
    "sg:address":"Alte Schwarzeneggstrasse 6",
    "sg:city":"Steffisburg",
    "sg:orig_category":"Arztpraxen",
    "sg:phone":"+41 33 437 32 22",
    "sg:postcode":"3612",
    "sg:province":"Bern",
    "wof:name":"Dr.med.stefan Schacke Arzt F.allgemeine Medizin Fmh",
    "wof:placetype":"venue"
},
  "geometry": {"coordinates":[7.635157,46.781303],"type":"Point"}
}