{
  "type": "Feature",
  "properties": {
    "iso:country":"CH",
    "sg:address":"Pregny Route De 21",
    "sg:city":"Chamb\u00e9sy",
    "sg:orig_category":"Fachdetailhandel in Verkaufsr\u00e4umen",
    "sg:postcode":"1292",
    "sg:province":"Gen\u00e8ve",
    "wof:name":"Glacier Sport, Seewer Martin",
    "wof:placetype":"venue"
},
  "geometry": {"coordinates":[7.933672905,46.1117172241],"type":"Point"}
}