{
  "type": "Feature",
  "properties": {
    "iso:country":"CH",
    "sg:address":"Neuhauserstrasse 101",
    "sg:city":"Frauenfeld",
    "sg:orig_category":"Sonstige mit der Informatik verbundene T\u00e4tigkeiten",
    "sg:phone":"+41 52 722 29 61",
    "sg:postcode":"8500",
    "sg:province":"Thurgau",
    "wof:name":"Dv-peter",
    "wof:placetype":"venue"
},
  "geometry": {"coordinates":[8.9167633057,47.5523223877],"type":"Point"}
}