{
  "type": "Feature",
  "properties": {
    "iso:country":"CH",
    "sg:address":"Chemin De La Veyre D'en Haut",
    "sg:city":"St-l\u00e9gier",
    "sg:orig_category":"Handelsvermittlung U Grosshandel Herstellung von Drahtwaren",
    "sg:phone":"+41 31 839 09 66",
    "sg:postcode":"1806",
    "sg:province":"Vaud",
    "wof:name":"Kawo Aegerter",
    "wof:placetype":"venue"
},
  "geometry": {"coordinates":[7.5442538261,46.927406311],"type":"Point"}
}