{
  "type": "Feature",
  "properties": {
    "iso:country":"CH",
    "sg:address":"Hauptstrasse 1",
    "sg:city":"Binningen",
    "sg:orig_category":"Vermietung U Verpachtung von eigenen Immobilien Vermittlung von Immobilien",
    "sg:phone":"+41 91 994 52 15",
    "sg:postcode":"4102",
    "sg:province":"Basel-Landschaft",
    "wof:name":"Suvaltra Sa",
    "wof:placetype":"venue"
},
  "geometry": {"coordinates":[8.9535598755,46.0047798157],"type":"Point"}
}