{
  "type": "Feature",
  "properties": {
    "iso:country":"CH",
    "sg:address":"Schlossstrasse 6",
    "sg:city":"Oberdiessbach",
    "sg:orig_category":"Sonstige Hilfsdienste des Kultur U Unterhaltungswesens",
    "sg:phone":"+41 31 771 23 29",
    "sg:postcode":"3672",
    "sg:province":"Bern",
    "wof:name":"Creaton Felix Hochuli Tonstudio",
    "wof:placetype":"venue"
},
  "geometry": {"coordinates":[7.619166851,46.839138031],"type":"Point"}
}