{
  "type": "Feature",
  "properties": {
    "iso:country":"CH",
    "sg:address":"Industriestrasse 17",
    "sg:city":"Herisau",
    "sg:orig_category":"Pensionskassen",
    "sg:phone":"+41 71 351 30 16",
    "sg:postcode":"9100",
    "sg:province":"Appenzell Ausserrhoden",
    "wof:name":"Personalf\u00fcrsorgestiftung Josef St\u00e4dler, Glasbl\u00e4serei",
    "wof:placetype":"venue"
},
  "geometry": {"coordinates":[9.2763881683,47.3809051514],"type":"Point"}
}