{
  "type": "Feature",
  "properties": {
    "iso:country":"CH",
    "sg:address":"Rue Du Ch\u00e2teau-d'en-bas 2",
    "sg:city":"Bulle",
    "sg:orig_category":"Detailhandel mit Damenbekleidung Detailhandel mit Herrenbekleidung",
    "sg:phone":"+41 26 652 38 24",
    "sg:postcode":"1630",
    "sg:province":"Fribourg",
    "wof:name":"Charles V\u00f6gele Mode Ag",
    "wof:placetype":"venue"
},
  "geometry": {"coordinates":[6.9115872383,46.6901626587],"type":"Point"}
}