{
  "type": "Feature",
  "properties": {
    "iso:country":"CH",
    "sg:address":"Rue Du Puits 36",
    "sg:city":"St-imier",
    "sg:orig_category":"Detailhandel mit Brot, Back U S\u00fcsswaren",
    "sg:phone":"+41 32 941 43 63",
    "sg:postcode":"2610",
    "sg:province":"Bern",
    "wof:name":"Aubry Jacques",
    "wof:placetype":"venue"
},
  "geometry": {"coordinates":[7.002001,47.153305],"type":"Point"}
}