{
  "type": "Feature",
  "properties": {
    "iso:country":"CH",
    "sg:address":"Hauptstrasse 39",
    "sg:city":"Derendingen",
    "sg:orig_category":"Herstellung von Elektromotoren, Generatoren U Transformatoren",
    "sg:postcode":"4552",
    "sg:province":"Solothurn",
    "wof:name":"Klea Genossenschaft Klein-energieanlagen",
    "wof:placetype":"venue"
},
  "geometry": {"coordinates":[7.5861439705,47.1948928833],"type":"Point"}
}