{
  "type": "Feature",
  "properties": {
    "iso:country":"CH",
    "sg:address":"Langendorfstrasse 2",
    "sg:city":"Langendorf",
    "sg:orig_category":"Herstellung von Werkzeugen Mechanische Werkst\u00e4tten",
    "sg:phone":"+41 61 401 30 10",
    "sg:postcode":"4513",
    "sg:province":"Solothurn",
    "wof:name":"Gr\u00f6flin Werkzeugbau Ag",
    "wof:placetype":"venue"
},
  "geometry": {"coordinates":[7.5539569855,47.5125923157],"type":"Point"}
}