{
  "type": "Feature",
  "properties": {
    "iso:country":"CH",
    "sg:address":"7180",
    "sg:city":"Disentis/must\u00e9r",
    "sg:classifiers":[
        {
            "category":"Mining & Drilling",
            "type":"Manufacturing & Wholesale Goods"
        }
    ],
    "sg:phone":"+41 61 481 55 90",
    "sg:postcode":"7180",
    "sg:province":"Graubunden",
    "sg:tags":[
        "test",
        "sondierbohrungen",
        "u"
    ],
    "wof:name":"Bohr Ag Surselva",
    "wof:placetype":"venue"
},
  "geometry": {"coordinates":[8.8531293869,46.7046012878],"type":"Point"}
}