{
  "type": "Feature",
  "properties": {
    "iso:country":"CH",
    "sg:address":"Sch\u00f6nenhofstrasse 17 8500 Frauenfeld. Postfach",
    "sg:city":"Frauenfeld",
    "sg:orig_category":"Sonstige pers\u00f6nliche Dienstleistungen",
    "sg:postcode":"8500",
    "sg:province":"Thurgau",
    "wof:name":"Activeline Gmbh",
    "wof:placetype":"venue"
},
  "geometry": {"coordinates":[8.8709440231,47.5530815125],"type":"Point"}
}