{
  "type": "Feature",
  "properties": {
    "iso:country":"CH",
    "sg:address":"Z\u00fcrichstrasse 29",
    "sg:city":"D\u00fcbendorf",
    "sg:classifiers":[
        {
            "category":"Restaurant",
            "type":"Food & Drink"
        }
    ],
    "sg:phone":"+41 18212646",
    "sg:postcode":"8600",
    "sg:province":"Z\u00fcrich",
    "wof:name":"Topolino Plaza Caf\u00e9",
    "wof:placetype":"venue"
},
  "geometry": {"coordinates":[8.6138849258,47.3965797424],"type":"Point"}
}