{
  "type": "Feature",
  "properties": {
    "iso:country":"CH",
    "sg:address":"Obere Hauptgasse 74 3600 Thun. Postfach",
    "sg:city":"Thun",
    "sg:orig_category":"Sonstige Institutionen des Sozialwesens ohne Beherbergung",
    "sg:phone":"+41 33 222 96 22",
    "sg:postcode":"3601",
    "sg:province":"Bern",
    "wof:name":"Kantonale Erziehungsberatung Thun Oberland",
    "wof:placetype":"venue"
},
  "geometry": {"coordinates":[7.6314921379,46.7580223083],"type":"Point"}
}