{
  "type": "Feature",
  "properties": {
    "iso:country":"CH",
    "sg:address":"3997",
    "sg:city":"Bellwald",
    "sg:orig_category":"Allgemeiner Hochbau Strassenbau",
    "sg:postcode":"3997",
    "sg:province":"Valais",
    "wof:name":"Perren Baugesch\u00e4ft Ag",
    "wof:placetype":"venue"
},
  "geometry": {"coordinates":[8.158277,46.426254],"type":"Point"}
}