{
  "type": "Feature",
  "properties": {
    "iso:country":"CH",
    "sg:address":"Via Al Municipio 16",
    "sg:city":"Barbengo",
    "sg:orig_category":"Herstellung von Spielwaren",
    "sg:phone":"+41 61 701 99 30",
    "sg:postcode":"6917",
    "sg:province":"Ticino",
    "wof:name":"Atelier Anja",
    "wof:placetype":"venue"
},
  "geometry": {"coordinates":[7.6134080887,47.4781532288],"type":"Point"}
}