{
  "type": "Feature",
  "properties": {
    "iso:country":"CH",
    "sg:address":"Rue De Chamblon 6",
    "sg:city":"Yverdon-les-bains",
    "sg:orig_category":"Zahnarztpraxen",
    "sg:phone":"+41 24 425 68 84",
    "sg:postcode":"1400",
    "sg:province":"Vaud",
    "wof:name":"Dr M\u00e9d. Dent. Martine Verron M\u00e9decin-dentiste",
    "wof:placetype":"venue"
},
  "geometry": {"coordinates":[6.6338090897,46.7822647095],"type":"Point"}
}