{
  "type": "Feature",
  "properties": {
    "iso:country":"CH",
    "sg:address":"Dickenstrasse 32",
    "sg:city":"Ebnat-kappel",
    "sg:orig_category":"Sonstiges Versicherungsgewerbe",
    "sg:phone":"+41 71 913 68 90",
    "sg:postcode":"9642",
    "sg:province":"St. Gallen",
    "wof:name":"Nvc Gmbh Versicherungen",
    "wof:placetype":"venue"
},
  "geometry": {"coordinates":[9.039273262,47.4718818665],"type":"Point"}
}