{
  "type": "Feature",
  "properties": {
    "iso:country":"CH",
    "sg:address":"Avenue Du Clo\u00eetre 26 1860 Aigle Case Postale 50",
    "sg:city":"Aigle",
    "sg:orig_category":"Grosshandel mit Getr\u00e4nken Rebbau",
    "sg:phone":"+41 32 751 22 18",
    "sg:postcode":"1860",
    "sg:province":"Vaud",
    "wof:name":"Caves Du Vignoble Parata A. Sa",
    "wof:placetype":"venue"
},
  "geometry": {"coordinates":[7.0657639503,47.0564918518],"type":"Point"}
}