{
  "type": "Feature",
  "properties": {
    "iso:country":"CH",
    "sg:address":"Kilchgrundstrasse 34 3072 Ostermundigen. Postfach",
    "sg:city":"Ostermundigen",
    "sg:orig_category":"Markt U Meinungsforschung",
    "sg:phone":"+41 32 724 14 93",
    "sg:postcode":"3072",
    "sg:province":"Bern",
    "wof:name":"Jacot Jean-marc Marketing; Conseils",
    "wof:placetype":"venue"
},
  "geometry": {"coordinates":[6.9065098763,46.9884757996],"type":"Point"}
}