{
  "type": "Feature",
  "properties": {
    "iso:country":"CH",
    "sg:address":"4912",
    "sg:city":"Aarwangen",
    "sg:orig_category":"Vereine Abstinenten",
    "sg:postcode":"4912",
    "sg:province":"Bern",
    "wof:name":"Blaues Kreuz",
    "wof:placetype":"venue"
},
  "geometry": {"coordinates":[7.7689061165,47.2403030396],"type":"Point"}
}