{
  "type": "Feature",
  "properties": {
    "iso:country":"CH",
    "sg:address":"Stazione Via 6593 Cadenazzo Casella Postale 172",
    "sg:city":"Cadenazzo",
    "sg:orig_category":"Unclassifiable Establishments",
    "sg:phone":"+41 91 850 31 70",
    "sg:postcode":"6593",
    "sg:province":"Ticino",
    "wof:name":"Nadec & R. Sagl",
    "wof:placetype":"venue"
},
  "geometry": {"coordinates":[8.9523019791,46.1495780945],"type":"Point"}
}