{
  "type": "Feature",
  "properties": {
    "iso:country":"CH",
    "sg:address":"Gartenweg 2a",
    "sg:city":"Regensdorf",
    "sg:orig_category":"Herstellung von Konstruktionsteilen, Fertigbauteilen U Ausbauelementen aus Holz",
    "sg:postcode":"8105",
    "sg:province":"Z\u00fcrich",
    "wof:name":"Innenbau Crociani",
    "wof:placetype":"venue"
},
  "geometry": {"coordinates":[8.4678497314,47.4330787659],"type":"Point"}
}