{
  "type": "Feature",
  "properties": {
    "iso:country":"CH",
    "sg:address":"Fumeaux Route Des 41",
    "sg:city":"Prilly",
    "sg:orig_category":"Erzeugung U Erstbearbeitung von Kupfer",
    "sg:phone":"+41 21 624 73 21",
    "sg:postcode":"1008",
    "sg:province":"Vaud",
    "wof:name":"Hifipac Flexible Sa",
    "wof:placetype":"venue"
},
  "geometry": {"coordinates":[6.6061439514,46.5340614319],"type":"Point"}
}