{
  "type": "Feature",
  "properties": {
    "iso:country":"CH",
    "sg:address":"Rolandstrasse 15 8004 Z\u00fcrich. Postfach 4356",
    "sg:city":"Z\u00fcrich",
    "sg:orig_category":"Detailhandel mit Sportartikeln Fachdetailhandel in Verkaufsr\u00e4umen",
    "sg:phone":"+41 12415466",
    "sg:postcode":"8022",
    "sg:province":"Z\u00fcrich",
    "wof:name":"Budo-sport Ag",
    "wof:placetype":"venue"
},
  "geometry": {"coordinates":[8.526307106,47.3790931702],"type":"Point"}
}