{
  "type": "Feature",
  "properties": {
    "iso:country":"CH",
    "sg:address":"Hauptstrasse 26",
    "sg:city":"Stettfurt",
    "sg:orig_category":"Wohnheime",
    "sg:phone":"+41 52 376 12 90",
    "sg:postcode":"9507",
    "sg:province":"Thurgau",
    "wof:name":"Erholungsheim Der Bachmannschen Stiftung",
    "wof:placetype":"venue"
},
  "geometry": {"coordinates":[8.954577446,47.5240936279],"type":"Point"}
}