{
  "type": "Feature",
  "properties": {
    "iso:country":"CH",
    "sg:address":"Landstrasse 8",
    "sg:city":"Balzers",
    "sg:orig_category":"Ingenieurb\u00fcros divers",
    "sg:phone":"+43 843 030",
    "sg:postcode":"9496",
    "wof:name":"Ami Ingenieurb\u00fcro Morger Anstalt",
    "wof:placetype":"venue"
},
  "geometry": {"coordinates":[9.5109786987,47.0741081238],"type":"Point"}
}