{
  "type": "Feature",
  "properties": {
    "iso:country":"CH",
    "sg:address":"Edikerstrasse 16",
    "sg:city":"D\u00fcrnten",
    "sg:orig_category":"Buchf\u00fchrung Datenverarbeitungsdienste",
    "sg:phone":"+41 55 240 96 60",
    "sg:postcode":"8635",
    "sg:province":"Z\u00fcrich",
    "wof:name":"Urs Senn Senn Treuhand",
    "wof:placetype":"venue"
},
  "geometry": {"coordinates":[8.843226,47.281235],"type":"Point"}
}