{
  "type": "Feature",
  "properties": {
    "iso:country":"CH",
    "sg:address":"Wald",
    "sg:city":"Schangnau",
    "sg:orig_category":"Instandhaltung U Reparatur von Automobilen Mechanische Werkst\u00e4tten",
    "sg:phone":"+41 34 493 31 08",
    "sg:postcode":"6197",
    "sg:province":"Bern",
    "wof:name":"Siegenthaler + Sch\u00e4r",
    "wof:placetype":"venue"
},
  "geometry": {"coordinates":[7.8755102158,46.835521698],"type":"Point"}
}