{
  "type": "Feature",
  "properties": {
    "iso:country":"CH",
    "sg:address":"Schweielstrasse 12",
    "sg:city":"Muri",
    "sg:orig_category":"Tank Cleaning Devices And Systems",
    "sg:phone":"+41 56 664 26 28",
    "sg:postcode":"5630",
    "sg:province":"Aargau",
    "wof:name":"Hans Grob Ag",
    "wof:placetype":"venue"
},
  "geometry": {"coordinates":[8.3435974121,47.2627601624],"type":"Point"}
}