{
  "type": "Feature",
  "properties": {
    "iso:country":"CH",
    "sg:address":"Rue Du Simplon 4",
    "sg:city":"Vevey",
    "sg:orig_category":"Grosshandel mit sonstigen Maschinen U Ausr\u00fcstungen f\u00fcr Industrie, Handel U Schiffahrt Handelsvermitt",
    "sg:phone":"+41 21 921 72 33",
    "sg:postcode":"1800",
    "sg:province":"Vaud",
    "wof:name":"Jungheinrich S\u00e0rl",
    "wof:placetype":"venue"
},
  "geometry": {"coordinates":[6.8469691277,46.4591598511],"type":"Point"}
}