{
  "type": "Feature",
  "properties": {
    "iso:country":"CH",
    "sg:address":"Sp\u00e4train 32",
    "sg:city":"Muhen",
    "sg:orig_category":"Elektroinstallation",
    "sg:phone":"+41 62 723 55 48",
    "sg:postcode":"5037",
    "sg:province":"Aargau",
    "wof:name":"Topel-tec L\u00fcscher U. Onillon",
    "wof:placetype":"venue"
},
  "geometry": {"coordinates":[8.060587883,47.3283195496],"type":"Point"}
}