{
  "type": "Feature",
  "properties": {
    "iso:country":"CH",
    "sg:address":"Chemin De Marjovet B1",
    "sg:city":"Echallens",
    "sg:orig_category":"Architektur U Ingenieurb\u00fcros Strassenbau",
    "sg:phone":"+41 41 870 52 40",
    "sg:postcode":"1040",
    "sg:province":"Vaud",
    "wof:name":"Herger Toni Tiefbau Und Architekturbuero",
    "wof:placetype":"venue"
},
  "geometry": {"coordinates":[8.616725,46.879738],"type":"Point"}
}