{
  "type": "Feature",
  "properties": {
    "iso:country":"CH",
    "sg:address":"Limmattalstrasse 49",
    "sg:city":"Geroldswil",
    "sg:orig_category":"RESTAURANTS: TEA-ROOMS",
    "sg:phone":"+41 17481847",
    "sg:postcode":"8954",
    "sg:province":"Z\u00fcrich",
    "wof:name":"Restaurant Glanzenburg",
    "wof:placetype":"venue"
},
  "geometry": {"coordinates":[8.4102935791,47.4206161499],"type":"Point"}
}