{
  "type": "Feature",
  "properties": {
    "iso:country":"CH",
    "sg:address":"Blotzheimerstrasse 30",
    "sg:city":"Basel",
    "sg:orig_category":"Reiseb\u00fcros",
    "sg:phone":"+41 61 382 56 14",
    "sg:postcode":"4055",
    "sg:province":"Basel-Stadt",
    "wof:name":"Air-sea Service Furrer Reiseb\u00fcro",
    "wof:placetype":"venue"
},
  "geometry": {"coordinates":[7.5657601357,47.5615272522],"type":"Point"}
}