{
  "type": "Feature",
  "properties": {
    "iso:country":"CH",
    "sg:address":"Goldbergstrasse 7",
    "sg:city":"Bubendorf",
    "sg:classifiers":[
        {
            "category":"Insurance",
            "subcategory":"Insurance Agent",
            "type":"Services"
        }
    ],
    "sg:phone":"+41 61 931 15 28",
    "sg:postcode":"4416",
    "sg:province":"Basel-Landschaft",
    "sg:tags":[
        "versicherungsagenturen",
        "-broker"
    ],
    "wof:name":"Die Mobiliar Versicherungen & Vorsorge",
    "wof:placetype":"venue"
},
  "geometry": {"coordinates":[7.7405328751,47.4552536011],"type":"Point"}
}