{
  "type": "Feature",
  "properties": {
    "iso:country":"CH",
    "sg:address":"17-19 Rte Du Petit-moncor Cp 1136",
    "sg:city":"Fribourg",
    "sg:classifiers":[
        {
            "category":"Wholesale",
            "subcategory":"Machinery & Supplies",
            "type":"Manufacturing & Wholesale Goods"
        }
    ],
    "sg:phone":"+41 26 407 41 11",
    "sg:postcode":"1701",
    "sg:province":"Fribourg",
    "sg:tags":[
        "handling",
        "material",
        "-",
        "machine",
        "equipment",
        "engineering",
        "mechanical"
    ],
    "wof:name":"Otis",
    "wof:placetype":"venue"
},
  "geometry": {"coordinates":[7.1536831856,46.8037452698],"type":"Point"}
}