{
  "type": "Feature",
  "properties": {
    "iso:country":"CH",
    "sg:address":"Allmendstrasse 4 4512 Bellach. Postfach",
    "sg:city":"Bellach",
    "sg:orig_category":"Herstellung von Mess U Kontrollinstrumenten U vorrichtungen Mechanische Werkst\u00e4tten",
    "sg:phone":"+41 32 617 41 71",
    "sg:postcode":"4512",
    "sg:province":"Solothurn",
    "wof:name":"Kmb Feinmechanik Ag",
    "wof:placetype":"venue"
},
  "geometry": {"coordinates":[7.4991941452,47.2077407837],"type":"Point"}
}