{
  "type": "Feature",
  "properties": {
    "iso:country":"CH",
    "sg:address":"Zwislenstrasse 15",
    "sg:city":"Gais",
    "sg:orig_category":"Non-Classified Establishments",
    "sg:postcode":"9056",
    "sg:province":"Appenzell Ausserrhoden",
    "wof:name":"Auf Dem Stein Gmbh",
    "wof:placetype":"venue"
},
  "geometry": {"coordinates":[9.4533672333,47.358921051],"type":"Point"}
}