{
  "type": "Feature",
  "properties": {
    "iso:country":"CH",
    "sg:address":"Hohlstrasse 413",
    "sg:city":"Z\u00fcrich",
    "sg:orig_category":"Dachdeckerei Zimmerei, Dachdeckerei, Bauspenglerei U Abdichtung",
    "sg:phone":"+41 14011460",
    "sg:postcode":"8048",
    "sg:province":"Z\u00fcrich",
    "wof:name":"Uhlenbrock Ag Bauspenglerei & Bedachungen",
    "wof:placetype":"venue"
},
  "geometry": {"coordinates":[8.503145,47.386471],"type":"Point"}
}