{
  "type": "Feature",
  "properties": {
    "iso:country":"CH",
    "sg:address":"V\u00e9lodrome Rue Du 2 1205 Gen\u00e8ve. Postfach",
    "sg:city":"Gen\u00e8ve",
    "sg:orig_category":"Mechanik",
    "sg:postcode":"1205",
    "sg:province":"Gen\u00e8ve",
    "wof:name":"Rochat, J. Roland Rochat Succ",
    "wof:placetype":"venue"
},
  "geometry": {"coordinates":[6.1299300194,46.2004089355],"type":"Point"}
}