{
  "type": "Feature",
  "properties": {
    "iso:country":"CH",
    "sg:address":"Chemin De La Mousse 34",
    "sg:city":"Ch\u00eane-bourg",
    "sg:orig_category":"Grosshandel mit B\u00fcromaschinen Grosshandel mit Datenverarbeitungsger\u00e4ten",
    "sg:phone":"+41 22 348 51 71",
    "sg:postcode":"1225",
    "sg:province":"Gen\u00e8ve",
    "wof:name":"Selfix Sa Syst\u00e8mes D'\u00e9tiquetage",
    "wof:placetype":"venue"
},
  "geometry": {"coordinates":[6.198870182,46.1972541809],"type":"Point"}
}