{
  "type": "Feature",
  "properties": {
    "iso:country":"CH",
    "sg:address":"Seestrasse 1",
    "sg:city":"Herrliberg",
    "sg:orig_category":"Rebbau",
    "sg:phone":"+41 19153461",
    "sg:postcode":"8704",
    "sg:province":"Z\u00fcrich",
    "wof:name":"Schipfgut Weinbau Kaspar Von Meyenburg",
    "wof:placetype":"venue"
},
  "geometry": {"coordinates":[8.5991983414,47.2934837341],"type":"Point"}
}