{
  "type": "Feature",
  "properties": {
    "iso:country":"CH",
    "sg:address":"N\u00e4geligasse 13 3011 Bern. Postfach",
    "sg:city":"Bern",
    "sg:orig_category":"Vermietung U Verpachtung von eigenen Immobilien",
    "sg:postcode":"3005",
    "sg:province":"Bern",
    "wof:name":"At Sa",
    "wof:placetype":"venue"
},
  "geometry": {"coordinates":[6.1042528152,46.1490287781],"type":"Point"}
}