{
  "type": "Feature",
  "properties": {
    "iso:country":"CH",
    "sg:address":"H\u00fcnenbergstrasse 49c",
    "sg:city":"Cham",
    "sg:orig_category":"Sonstige mit der Informatik verbundene T\u00e4tigkeiten Unternehmensberatung",
    "sg:phone":"+41 41 781 16 45",
    "sg:postcode":"6330",
    "sg:province":"Zug",
    "wof:name":"Delos Consulting Gmbh",
    "wof:placetype":"venue"
},
  "geometry": {"coordinates":[8.4476242065,47.1799545288],"type":"Point"}
}