{
  "type": "Feature",
  "properties": {
    "iso:country":"CH",
    "sg:address":"Wiesentalstrasse 22",
    "sg:city":"Oberuzwil",
    "sg:orig_category":"Herstellung von Ger\u00e4ten der Elektrizit\u00e4tserzeugung, -verteilung u.\u00e4. -Herstellung von Radio U Fernse",
    "sg:phone":"+41 71 950 04 05",
    "sg:postcode":"9242",
    "sg:province":"St. Gallen",
    "wof:name":"Videotronic (schweiz) Ag",
    "wof:placetype":"venue"
},
  "geometry": {"coordinates":[9.1300821304,47.4321975708],"type":"Point"}
}