{
  "type": "Feature",
  "properties": {
    "iso:country":"CH",
    "sg:address":"Untere Waid",
    "sg:city":"M\u00f6rschwil",
    "sg:orig_category":"Maturit\u00e4tsschulen, Lehrerseminarien",
    "sg:phone":"+41 71 866 17 17",
    "sg:postcode":"9402",
    "sg:province":"St. Gallen",
    "wof:name":"Gymnasium",
    "wof:placetype":"venue"
},
  "geometry": {"coordinates":[9.4217939377,47.4532585144],"type":"Point"}
}