{
  "type": "Feature",
  "properties": {
    "iso:country":"CH",
    "sg:address":"Bernstrasse West 58",
    "sg:city":"Suhr",
    "sg:orig_category":"Handel mit Motorr\u00e4dern, Teilen U Zubeh\u00f6r Instandhaltung U Reparatur von Motorr\u00e4dern",
    "sg:phone":"+41 62 842 76 00",
    "sg:postcode":"5034",
    "sg:province":"Aargau",
    "wof:name":"Extrem-bikes Martin Ecknauer",
    "wof:placetype":"venue"
},
  "geometry": {"coordinates":[8.0792255402,47.3705406189],"type":"Point"}
}