{
  "type": "Feature",
  "properties": {
    "iso:country":"CH",
    "sg:address":"Breitweg 228",
    "sg:city":"Zetzwil",
    "sg:orig_category":"Vereine Abstinenten",
    "sg:phone":"+41 62 773 23 51",
    "sg:postcode":"5732",
    "sg:province":"Aargau",
    "wof:name":"Blaues Kreuz",
    "wof:placetype":"venue"
},
  "geometry": {"coordinates":[8.15645504,47.2839698792],"type":"Point"}
}