{
  "type": "Feature",
  "properties": {
    "iso:country":"CH",
    "sg:address":"H\u00fcnigenstrasse 3510 Konolfingen. Postfach 28",
    "sg:city":"Konolfingen",
    "sg:orig_category":"Herstellung von sonstigen Nahrungsmitteln Verarbeitung von Tee U Kaffee",
    "sg:phone":"+41 34 402 22 94",
    "sg:postcode":"3510",
    "sg:province":"Bern",
    "wof:name":"Multi-extrakt Ag",
    "wof:placetype":"venue"
},
  "geometry": {"coordinates":[7.757589817,46.9491271973],"type":"Point"}
}