{
  "type": "Feature",
  "properties": {
    "iso:country":"CH",
    "sg:address":"Oberdorfstrasse 3",
    "sg:city":"Seon",
    "sg:orig_category":"Kosmetikinstitute",
    "sg:phone":"+41 62 775 05 25",
    "sg:postcode":"5703",
    "sg:province":"Aargau",
    "wof:name":"Gisela Leumann & Luzia Iten Solarium & Kosmetik Cariderm",
    "wof:placetype":"venue"
},
  "geometry": {"coordinates":[8.1593084335,47.3456001282],"type":"Point"}
}