{
  "type": "Feature",
  "properties": {
    "iso:country":"CH",
    "sg:address":"Br\u00fcggenweid",
    "sg:city":"Gondiswil",
    "sg:orig_category":"Herstellung von M\u00f6beln S\u00e4gewerke",
    "sg:phone":"+41 26 651 96 50",
    "sg:postcode":"4955",
    "sg:province":"Bern",
    "wof:name":"Franke Romont Sa",
    "wof:placetype":"venue"
},
  "geometry": {"coordinates":[6.9533801079,46.6943054199],"type":"Point"}
}