{
  "type": "Feature",
  "properties": {
    "iso:country":"CH",
    "sg:address":"Flawiler Strasse 27",
    "sg:city":"L\u00fctisburg",
    "sg:orig_category":"Primarschulen",
    "sg:phone":"+41 71 931 25 79",
    "sg:postcode":"9604",
    "sg:province":"St. Gallen",
    "wof:name":"Primarschule Dorf",
    "wof:placetype":"venue"
},
  "geometry": {"coordinates":[9.0817718506,47.3956031799],"type":"Point"}
}