{
  "type": "Feature",
  "properties": {
    "iso:country":"CH",
    "sg:address":"Grubenstrasse 53",
    "sg:city":"Schaffhausen",
    "sg:orig_category":"RESTAURANTS: TEA-ROOMS",
    "sg:postcode":"8200",
    "sg:province":"Schaffhausen",
    "wof:name":"Leuba Heidi",
    "wof:placetype":"venue"
},
  "geometry": {"coordinates":[8.6432924271,47.70287323],"type":"Point"}
}