{
  "type": "Feature",
  "properties": {
    "iso:country":"CH",
    "sg:address":"Hohlstrasse 273",
    "sg:city":"Z\u00fcrich",
    "sg:orig_category":"Grosshandel mit Textilien",
    "sg:postcode":"8004",
    "sg:province":"Z\u00fcrich",
    "wof:name":"Chakaltaya Sagl",
    "wof:placetype":"venue"
},
  "geometry": {"coordinates":[8.9384002686,45.9265899658],"type":"Point"}
}