{
  "type": "Feature",
  "properties": {
    "iso:country":"CH",
    "sg:address":"4426",
    "sg:city":"Lauwil",
    "sg:orig_category":"Landesverteidigung, Sozialversicherung \u00d6ffentliche Verwaltung",
    "sg:phone":"+41 61 941 21 21",
    "sg:postcode":"4426",
    "sg:province":"Basel-Landschaft",
    "wof:name":"Zivilschutzstelle Lauwil",
    "wof:placetype":"venue"
},
  "geometry": {"coordinates":[7.6640000343,47.3875694275],"type":"Point"}
}