{
  "type": "Feature",
  "properties": {
    "iso:country":"CH",
    "sg:address":"Burghalden",
    "sg:city":"Herisau",
    "sg:orig_category":"Unclassifiable Establishments",
    "sg:phone":"+41 71 352 41 30",
    "sg:postcode":"9100",
    "sg:province":"Appenzell Ausserrhoden",
    "wof:name":"Bl\u00e4ttler W. Gartenbau",
    "wof:placetype":"venue"
},
  "geometry": {"coordinates":[9.2740125656,47.3921508789],"type":"Point"}
}