{
  "type": "Feature",
  "properties": {
    "iso:country":"CH",
    "sg:address":"Wilerstrasse 16",
    "sg:city":"Sirnach",
    "sg:orig_category":"Kauf U Verkauf von Immobilien auf eigene Rechnung",
    "sg:postcode":"8370",
    "sg:province":"Thurgau",
    "wof:name":"Luap Ag",
    "wof:placetype":"venue"
},
  "geometry": {"coordinates":[9.2422275543,47.3834190369],"type":"Point"}
}