{
  "type": "Feature",
  "properties": {
    "iso:country":"CH",
    "sg:address":"Brotgasse 3",
    "sg:city":"Z\u00fcrich",
    "sg:orig_category":"Non-Classified Establishments",
    "sg:postcode":"8008",
    "sg:province":"Z\u00fcrich",
    "wof:name":"Erica Jean-petit-matile Sturzenegger",
    "wof:placetype":"venue"
},
  "geometry": {"coordinates":[8.5502185822,47.3632125854],"type":"Point"}
}