{
  "type": "Feature",
  "properties": {
    "iso:country":"CH",
    "sg:address":"Grabenstrasse 6",
    "sg:city":"Thun",
    "sg:orig_category":"Herstellung von k\u00e4lte U lufttechnischen Erzeugnissen f\u00fcr gewerbliche Zwecke",
    "sg:phone":"+41 17622662",
    "sg:postcode":"3601",
    "sg:province":"Bern",
    "wof:name":"Avenco Ag",
    "wof:placetype":"venue"
},
  "geometry": {"coordinates":[8.4474697113,47.2703933716],"type":"Point"}
}