{
  "type": "Feature",
  "properties": {
    "iso:country":"CH",
    "sg:address":"Bundesplatz 14",
    "sg:city":"Zug",
    "sg:orig_category":"Non-Classified Establishments",
    "sg:postcode":"6300",
    "sg:province":"Zug",
    "wof:name":"Gcib Financial Services Ag",
    "wof:placetype":"venue"
},
  "geometry": {"coordinates":[8.7834892273,47.2015571594],"type":"Point"}
}