{
  "type": "Feature",
  "properties": {
    "iso:country":"CH",
    "sg:address":"La Ratuse",
    "sg:city":"Montagny-yverdon",
    "sg:orig_category":"Dauerkulturbau",
    "sg:postcode":"1442",
    "sg:province":"Vaud",
    "wof:name":"Blanc Pierre Et Charles Et Cie",
    "wof:placetype":"venue"
},
  "geometry": {"coordinates":[6.600573,46.788521],"type":"Point"}
}