{
  "type": "Feature",
  "properties": {
    "iso:country":"CH",
    "sg:address":"Bannholzstrasse 17 9490 Vaduz. Postfach 730",
    "sg:city":"Vaduz",
    "sg:orig_category":"Unternehmensberatung",
    "sg:phone":"+41 75 233 27 28",
    "sg:postcode":"9490",
    "wof:name":"Rampone Consulting Anstalt Buchhaltung & Unternehmensber.",
    "wof:placetype":"venue"
},
  "geometry": {"coordinates":[9.5216217041,47.1484146118],"type":"Point"}
}