{
  "type": "Feature",
  "properties": {
    "iso:country":"CH",
    "sg:address":"Hauptstrasse 29",
    "sg:city":"Giebenach",
    "sg:orig_category":"Grosshandel mit Nahrungsmitteln, Getr\u00e4nken U Tabakwaren ohne ausgepr\u00e4gten Schwerpunkt Handelsvermitt",
    "sg:phone":"+41 61 811 11 20",
    "sg:postcode":"4304",
    "sg:province":"Basel-Landschaft",
    "wof:name":"Berger-lebensmittel",
    "wof:placetype":"venue"
},
  "geometry": {"coordinates":[7.7460608482,47.5231742859],"type":"Point"}
}