{
  "type": "Feature",
  "properties": {
    "addr:full":"Bodenackerstrasse 3 Bottmingen Basel-Landschaft 4103",
    "addr:housenumber":"3",
    "addr:postcode":"4103",
    "addr:street":"Bodenackerstrasse",
    "iso:country":"CH",
    "sg:address":"Bodenackerstrasse 3",
    "sg:city":"Bottmingen",
    "sg:orig_category":"Allgemeinbildende weiterf\u00fchrende Schulen Sonstiger Unterricht",
    "sg:phone":"+41 61 361 59 90",
    "sg:postcode":"4103",
    "sg:province":"Basel-Landschaft",
    "wof:name":"Schule F\u00fcr Stil Und Moderne Umgangsformen, Isler",
    "wof:placetype":"venue"
},
  "geometry": {"coordinates":[7.583509,47.526676],"type":"Point"}
}