{
  "type": "Feature",
  "properties": {
    "addr:full":"Neuhofstrasse 4 Baar Zug 6340",
    "addr:housenumber":"4",
    "addr:postcode":"6340",
    "addr:street":"Neuhofstrasse;Zug",
    "iso:country":"CH",
    "sg:address":"Neuhofstrasse 4",
    "sg:city":"Baar",
    "sg:orig_category":"Dienstleistungen, Telekommunikation",
    "sg:postcode":"6340",
    "sg:province":"Zug",
    "wof:name":"Twister Communications Network Ag",
    "wof:placetype":"venue"
},
  "geometry": {"coordinates":[8.513691,47.190346],"type":"Point"}
}