{
  "type": "Feature",
  "properties": {
    "iso:country":"CH",
    "sg:address":"Dorfstrasse 32",
    "sg:city":"Signau",
    "sg:orig_category":"Kinos",
    "sg:phone":"+41 34 497 21 95",
    "sg:postcode":"3534",
    "sg:province":"Bern",
    "wof:name":"Kino Roxy",
    "wof:placetype":"venue"
},
  "geometry": {"coordinates":[7.7278847694,46.9223976135],"type":"Point"}
}