{
  "type": "Feature",
  "properties": {
    "iso:country":"CH",
    "sg:address":"Sonnenweg 17",
    "sg:city":"Ormalingen",
    "sg:orig_category":"Fussreflexzonenmassage P\u00e9dicure",
    "sg:phone":"+41 61 981 25 32",
    "sg:postcode":"4466",
    "sg:province":"Basel-Landschaft",
    "wof:name":"Elisabeth Buser",
    "wof:placetype":"venue"
},
  "geometry": {"coordinates":[7.8770642281,47.4708366394],"type":"Point"}
}