{
  "type": "Feature",
  "properties": {
    "iso:country":"CH",
    "sg:address":"Sihlmatten 18",
    "sg:city":"Adliswil",
    "sg:orig_category":"Sonstige Hilfs U Nebent\u00e4tigkeiten f\u00fcr die Luftfahrt",
    "sg:postcode":"8134",
    "sg:province":"Z\u00fcrich",
    "wof:name":"Kessler Daniel, Check-in",
    "wof:placetype":"venue"
},
  "geometry": {"coordinates":[8.5304346085,47.3013305664],"type":"Point"}
}