{
  "type": "Feature",
  "properties": {
    "iso:country":"CH",
    "sg:address":"Avenue De Luserna 34",
    "sg:city":"Gen\u00e8ve",
    "sg:orig_category":"Detailhandel mit Radio U Fernsehger\u00e4ten Vermietung von Gebrauchsg\u00fctern",
    "sg:phone":"+41 26 322 59 00",
    "sg:postcode":"1203",
    "sg:province":"Gen\u00e8ve",
    "wof:name":"Vid\u00e9o Champs-elys\u00e9es S\u00e0rl",
    "wof:placetype":"venue"
},
  "geometry": {"coordinates":[6.1244559288,46.2138595581],"type":"Point"}
}