{
  "type": "Feature",
  "properties": {
    "iso:country":"CH",
    "sg:address":"Bergstrasse 53",
    "sg:city":"Solothurn",
    "sg:orig_category":"Betrieb von Taxis",
    "sg:phone":"+41 32 622 22 23",
    "sg:postcode":"4500",
    "sg:province":"Solothurn",
    "wof:name":"Hammer Urs",
    "wof:placetype":"venue"
},
  "geometry": {"coordinates":[7.529411,47.219154],"type":"Point"}
}