{
  "type": "Feature",
  "properties": {
    "iso:country":"CH",
    "sg:address":"Avenue Du March\u00e9 1",
    "sg:city":"Sierre",
    "sg:orig_category":"Herstellung von homogenisierten U di\u00e4tetischen Nahrungsmitteln Sonstiger Fachdetailhandel mit Nahrun",
    "sg:phone":"+41 27 456 56 10",
    "sg:postcode":"3960",
    "sg:province":"Valais",
    "wof:name":"Boutique Harmonie Di\u00e9t\u00e9tique - Conseils - Sant\u00e9 S\u00e0rl",
    "wof:placetype":"venue"
},
  "geometry": {"coordinates":[7.5276207924,46.2917633057],"type":"Point"}
}