{
  "type": "Feature",
  "properties": {
    "iso:country":"CH",
    "sg:address":"Maison De Commune",
    "sg:city":"Bursinel",
    "sg:orig_category":"Landesverteidigung, Sozialversicherung \u00d6ffentliche Verwaltung",
    "sg:phone":"+41 21 824 11 72",
    "sg:postcode":"1195",
    "sg:province":"Vaud",
    "wof:name":"Centre De Protection Civile",
    "wof:placetype":"venue"
},
  "geometry": {"coordinates":[6.2956819534,46.4300880432],"type":"Point"}
}