{
  "type": "Feature",
  "properties": {
    "iso:country":"CH",
    "sg:address":"Bahnhofstrasse 21",
    "sg:city":"Chur",
    "sg:orig_category":"Detailhandel mit Damenbekleidung",
    "sg:phone":"+41 81 420 02 11",
    "sg:postcode":"7000",
    "sg:province":"Graubunden",
    "wof:name":"Esprit Store Bollag-guggenheim Detailhandels Ag",
    "wof:placetype":"venue"
},
  "geometry": {"coordinates":[9.820992,46.795212],"type":"Point"}
}