{
  "type": "Feature",
  "properties": {
    "iso:country":"CH",
    "sg:address":"Via Del Tiglio 1",
    "sg:city":"Locarno",
    "sg:classifiers":[
        {
            "category":"Restaurant",
            "type":"Food & Drink"
        }
    ],
    "sg:phone":"+41 91 751 89 71",
    "sg:postcode":"6605",
    "sg:province":"Ticino",
    "wof:name":"Ristorante La Montanina",
    "wof:placetype":"venue"
},
  "geometry": {"coordinates":[8.7876329422,46.1735954285],"type":"Point"}
}