{
  "type": "Feature",
  "properties": {
    "iso:country":"CH",
    "sg:address":"Via Segoma",
    "sg:city":"Capolago",
    "sg:orig_category":"Autogaragen Autospenglereien",
    "sg:phone":"+41 91 608 23 19",
    "sg:postcode":"6825",
    "sg:province":"Ticino",
    "wof:name":"Giorgio Ballinari Garage-carrozzeria",
    "wof:placetype":"venue"
},
  "geometry": {"coordinates":[8.8085,45.990734],"type":"Point"}
}