{
  "type": "Feature",
  "properties": {
    "iso:country":"CH",
    "sg:address":"Ried\u00e4ckerstrasse 2 8422 Pfungen. Postfach",
    "sg:city":"Pfungen",
    "sg:orig_category":"Handel mit Motorr\u00e4dern, Teilen U Zubeh\u00f6r Instandhaltung U Reparatur von Motorr\u00e4dern",
    "sg:postcode":"8422",
    "sg:province":"Z\u00fcrich",
    "wof:name":"Rolis Bike Stazion Hoffmann Fahrradgesch\u00e4ft",
    "wof:placetype":"venue"
},
  "geometry": {"coordinates":[8.6421775818,47.5155982971],"type":"Point"}
}