{
  "type": "Feature",
  "properties": {
    "iso:country":"CH",
    "sg:address":"Augiessenstrasse 1",
    "sg:city":"Widnau",
    "sg:orig_category":"Grosshandel mit Baumaterialien",
    "sg:phone":"+41 55 442 65 75",
    "sg:postcode":"9443",
    "sg:province":"St. Gallen",
    "wof:name":"Waba-system Vertriebs Ag",
    "wof:placetype":"venue"
},
  "geometry": {"coordinates":[8.8535680771,47.1919708252],"type":"Point"}
}