{
  "type": "Feature",
  "properties": {
    "iso:country":"CH",
    "sg:address":"Travesi\u00e8re Route",
    "sg:city":"Sion",
    "sg:orig_category":"Instandhaltung U Reparatur von Automobilen",
    "sg:phone":"+41 27 203 32 47",
    "sg:postcode":"1950",
    "sg:province":"Valais",
    "wof:name":"Garage Th\u00e9ler Walter Sa",
    "wof:placetype":"venue"
},
  "geometry": {"coordinates":[7.3759260178,46.2280082703],"type":"Point"}
}