{
  "type": "Feature",
  "properties": {
    "iso:country":"CH",
    "sg:address":"Chemin Du Belv\u00e9d\u00e8re 11",
    "sg:city":"Ste-croix",
    "sg:classifiers":[
        {
            "category":"Restaurant",
            "type":"Food & Drink"
        }
    ],
    "sg:phone":"+41 24 454 13 56",
    "sg:postcode":"1450",
    "sg:province":"Vaud",
    "wof:name":"Restaurant Les Planets",
    "wof:placetype":"venue"
},
  "geometry": {"coordinates":[6.5331802368,46.8305282593],"type":"Point"}
}