{
  "type": "Feature",
  "properties": {
    "iso:country":"CH",
    "sg:address":"Winterhaldenstrasse 26",
    "sg:city":"Heimberg",
    "sg:orig_category":"Instandhaltung U Reparatur von Automobilen",
    "sg:phone":"+41 33 437 34 54",
    "sg:postcode":"3627",
    "sg:province":"Bern",
    "wof:name":"Ad Garage W. Blatter Gmbh",
    "wof:placetype":"venue"
},
  "geometry": {"coordinates":[7.6017742157,46.7986907959],"type":"Point"}
}