{
  "type": "Feature",
  "properties": {
    "addr:full":"Grienbachstrasse 15 Zug Zug 6300",
    "addr:housenumber":"15",
    "addr:postcode":"6300",
    "addr:street":"Grienbachstrasse;Zug",
    "iso:country":"CH",
    "sg:address":"Grienbachstrasse 15",
    "sg:city":"Zug",
    "sg:orig_category":"Bauspenglerei Zimmerei, Dachdeckerei, Bauspenglerei U Abdichtung",
    "sg:phone":"+41 79 687 72 77",
    "sg:postcode":"6300",
    "sg:province":"Zug",
    "wof:name":"Adi Zollinger Spenglerei Sanit\u00e4re Anlagen",
    "wof:placetype":"venue"
},
  "geometry": {"coordinates":[8.725693,47.268127],"type":"Point"}
}