{
  "type": "Feature",
  "properties": {
    "iso:country":"CH",
    "sg:address":"Gemsle 9050 Appenzell. Postfach",
    "sg:city":"Weissbad",
    "sg:orig_category":"RESTAURANTS: TEA-ROOMS",
    "sg:phone":"+41 71 798 90 30",
    "sg:postcode":"9057",
    "sg:province":"Appenzell Innerhoden",
    "wof:name":"Killer Marcel",
    "wof:placetype":"venue"
},
  "geometry": {"coordinates":[9.4076833725,47.3314361572],"type":"Point"}
}