{
  "type": "Feature",
  "properties": {
    "iso:country":"CH",
    "sg:address":"M\u00fchleweg 14",
    "sg:city":"Langenthal",
    "sg:orig_category":"Herstellung von Radio U Fernsehger\u00e4ten sowie phono U videotechnischen Ger\u00e4ten",
    "sg:phone":"+41 62 923 96 30",
    "sg:postcode":"4900",
    "sg:province":"Bern",
    "wof:name":"P'inc. Ag",
    "wof:placetype":"venue"
},
  "geometry": {"coordinates":[7.791959,47.21331],"type":"Point"}
}