{
  "type": "Feature",
  "properties": {
    "iso:country":"CH",
    "sg:address":"Ettenriedweg 809 5316 Leuggern. Postfach",
    "sg:city":"Leuggern",
    "sg:orig_category":"Grosshandel mit Datenverarbeitungsger\u00e4ten",
    "sg:phone":"+41 56 245 74 54",
    "sg:postcode":"5316",
    "sg:province":"Aargau",
    "wof:name":"Frewa Handel Walter Frey Prod.f.d.datenverarbeitung",
    "wof:placetype":"venue"
},
  "geometry": {"coordinates":[8.2245998383,47.5858306885],"type":"Point"}
}