{
  "type": "Feature",
  "properties": {
    "iso:country":"CH",
    "sg:address":"Unterdorfstrasse 10",
    "sg:city":"Flums",
    "sg:orig_category":"Physiotherapie",
    "sg:phone":"+41 81 733 43 53",
    "sg:postcode":"8890",
    "sg:province":"St. Gallen",
    "wof:name":"Heinz Alder Physiotherapie Praxis",
    "wof:placetype":"venue"
},
  "geometry": {"coordinates":[9.3477630615,47.0911254883],"type":"Point"}
}