{
  "type": "Feature",
  "properties": {
    "iso:country":"CH",
    "sg:address":"B\u00e4renmatte 18",
    "sg:city":"H\u00f6lstein",
    "sg:orig_category":"Instandhaltung U Reparatur von Automobilen",
    "sg:phone":"+41 61 951 22 66",
    "sg:postcode":"4434",
    "sg:province":"Basel-Landschaft",
    "wof:name":"Auto Recher Ag",
    "wof:placetype":"venue"
},
  "geometry": {"coordinates":[7.7645058632,47.4405899048],"type":"Point"}
}