{
  "type": "Feature",
  "properties": {
    "iso:country":"CH",
    "sg:address":"Hauptgasse 38",
    "sg:city":"Murten",
    "sg:orig_category":"Detailhandel mit Damenbekleidung Fachdetailhandel in Verkaufsr\u00e4umen",
    "sg:phone":"+41 26 672 17 52",
    "sg:postcode":"3280",
    "sg:province":"Fribourg",
    "wof:name":"Conny's Chic Fashion",
    "wof:placetype":"venue"
},
  "geometry": {"coordinates":[7.1178498268,46.9285240173],"type":"Point"}
}