{
  "type": "Feature",
  "properties": {
    "iso:country":"CH",
    "sg:address":"Beundenweg 15a",
    "sg:city":"Pieterlen",
    "sg:orig_category":"Sportvereine Turnen Vereine Damen",
    "sg:phone":"+41 31 879 17 24",
    "sg:postcode":"2542",
    "sg:province":"Bern",
    "wof:name":"Dtv & Frauenr.stv Rapperswil",
    "wof:placetype":"venue"
},
  "geometry": {"coordinates":[7.3925199509,47.0602302551],"type":"Point"}
}