{
  "type": "Feature",
  "properties": {
    "iso:country":"CH",
    "sg:address":"Sonnhaldenweg 13",
    "sg:city":"Herisau",
    "sg:orig_category":"Grosshandel mit Fleisch U Fleischwaren Schlachten ohne Schlachten von Gefl\u00fcgel",
    "sg:postcode":"9100",
    "sg:province":"Appenzell Ausserrhoden",
    "wof:name":"Jakob Signer",
    "wof:placetype":"venue"
},
  "geometry": {"coordinates":[9.2714853287,47.3926010132],"type":"Point"}
}