{
  "type": "Feature",
  "properties": {
    "iso:country":"CH",
    "sg:address":"L\u00e9vrioux Chemin Du 16 1263 Crassier. Postfach",
    "sg:city":"Crassier",
    "sg:orig_category":"Institutionen des Sozialwesens ohne Beherbergung",
    "sg:postcode":"1263",
    "sg:province":"Vaud",
    "wof:name":"Fondation Le Cube De Verre Aide Aux Enfants Atteints D'autisme Et \u00e0 Leurs Familles",
    "wof:placetype":"venue"
},
  "geometry": {"coordinates":[6.1667180061,46.3735809326],"type":"Point"}
}