{
  "type": "Feature",
  "properties": {
    "iso:country":"CH",
    "sg:address":"Altes Schulhaus 8881 Tscherlach. Postfach 22",
    "sg:city":"Tscherlach",
    "sg:orig_category":"Elektroinstallation",
    "sg:phone":"+41 81 710 22 22",
    "sg:postcode":"8881",
    "sg:province":"St. Gallen",
    "wof:name":"Loop + G\u00f6ldi Ag",
    "wof:placetype":"venue"
},
  "geometry": {"coordinates":[9.333272934,47.1183662415],"type":"Point"}
}