{
  "type": "Feature",
  "properties": {
    "iso:country":"CH",
    "sg:address":"Predigerplatz 40",
    "sg:city":"Z\u00fcrich",
    "sg:orig_category":"Detailhandel mit Antiquit\u00e4ten U Gebrauchtwaren in Verkaufsr\u00e4umen",
    "sg:phone":"+41 12511801",
    "sg:postcode":"8001",
    "sg:province":"Z\u00fcrich",
    "wof:name":"Traktor Kult Gmbh",
    "wof:placetype":"venue"
},
  "geometry": {"coordinates":[8.545913,47.373676],"type":"Point"}
}