{
  "type": "Feature",
  "properties": {
    "iso:country":"CH",
    "sg:address":"Belpbergstrasse 12",
    "sg:city":"Belp",
    "sg:orig_category":"Versicherungen Hauptagenturen",
    "sg:phone":"+41 31 819 31 81",
    "sg:postcode":"3123",
    "sg:province":"Bern",
    "wof:name":"Emmentalische Mobiliarversich. Hauptagentur Kurt Hofmann",
    "wof:placetype":"venue"
},
  "geometry": {"coordinates":[7.5000391006,46.8889274597],"type":"Point"}
}