{
  "type": "Feature",
  "properties": {
    "iso:country":"CH",
    "sg:address":"Saint-pierre Rue 2 1003 Lausanne. Postfach",
    "sg:city":"Lausanne",
    "sg:orig_category":"Wirtschaftspr\u00fcfung, Steuerberatung U Treuhand",
    "sg:postcode":"1002",
    "sg:province":"Vaud",
    "wof:name":"Fiduciaire J. Philippoz Sa",
    "wof:placetype":"venue"
},
  "geometry": {"coordinates":[7.2086448669,46.1864585876],"type":"Point"}
}