{
  "type": "Feature",
  "properties": {
    "iso:country":"CH",
    "sg:address":"Huebwiesenstrasse 57",
    "sg:city":"Geroldswil",
    "sg:orig_category":"HERSTELLUNG VON GER\u00c4TEN DER ELEKTRIZIT\u00c4TSERZEUGUNG, -VERTEILUNG U.\u00c4 Herstellung von Metallerzeugniss",
    "sg:phone":"+41 17481333",
    "sg:postcode":"8954",
    "sg:province":"Z\u00fcrich",
    "wof:name":"Juma Control Gmbh",
    "wof:placetype":"venue"
},
  "geometry": {"coordinates":[8.4056472778,47.4227905273],"type":"Point"}
}