{
  "type": "Feature",
  "properties": {
    "iso:country":"CH",
    "sg:address":"Bahnhofplatz 12",
    "sg:city":"Z\u00fcrich",
    "sg:orig_category":"Herstellung von Maschinen f\u00fcr die Textil, Bekleidungsherstellung U die Lederverarbeitung",
    "sg:postcode":"8001",
    "sg:province":"Z\u00fcrich",
    "wof:name":"Sofitrac Ag. Textil- U. Maschinenindustrie; Fabriken Usw.",
    "wof:placetype":"venue"
},
  "geometry": {"coordinates":[8.538693428,47.3774452209],"type":"Point"}
}