{
  "type": "Feature",
  "properties": {
    "iso:country":"CH",
    "sg:address":"Kolinplatz 8",
    "sg:city":"Zug",
    "sg:orig_category":"Unternehmensberatung",
    "sg:phone":"+41 41 729 88 50",
    "sg:postcode":"6300",
    "sg:province":"Zug",
    "wof:name":"K\u00fcbler Robert P., Verkauf Und Marketing Praxis",
    "wof:placetype":"venue"
},
  "geometry": {"coordinates":[8.515206337,47.1661148071],"type":"Point"}
}