{
  "type": "Feature",
  "properties": {
    "iso:country":"CH",
    "sg:address":"Route Cantonale 103",
    "sg:city":"V\u00e9troz",
    "sg:classifiers":[
        {
            "category":"Restaurant",
            "type":"Food & Drink"
        }
    ],
    "sg:phone":"+41 27 346 12 08",
    "sg:postcode":"1963",
    "sg:province":"Valais",
    "wof:name":"Caf\u00e9 Diablerets",
    "wof:placetype":"venue"
},
  "geometry": {"coordinates":[7.2815098763,46.225605011],"type":"Point"}
}