{
  "type": "Feature",
  "properties": {
    "iso:country":"CH",
    "sg:address":"8162",
    "sg:city":"Steinmaur",
    "sg:orig_category":"Wasserversorgung",
    "sg:phone":"+41 18533696",
    "sg:postcode":"8162",
    "sg:province":"Z\u00fcrich",
    "wof:name":"Wasserversorgung Der Gemeinde Steinmaur",
    "wof:placetype":"venue"
},
  "geometry": {"coordinates":[8.4502401352,47.4946861267],"type":"Point"}
}