{
  "type": "Feature",
  "properties": {
    "iso:country":"CH",
    "sg:address":"Bahnhofstrasse",
    "sg:city":"Gampel",
    "sg:orig_category":"Grosshandel mit Parf\u00fcmerieartikeln U K\u00f6rperpflegemitteln Rechtsberatung",
    "sg:phone":"+41 27 932 55 40",
    "sg:postcode":"3945",
    "sg:province":"Valais",
    "wof:name":"Pp Science & Beauty Ag",
    "wof:placetype":"venue"
},
  "geometry": {"coordinates":[7.7447009087,46.3143196106],"type":"Point"}
}