{
  "type": "Feature",
  "properties": {
    "iso:country":"CH",
    "sg:address":"Avenue Tronchet 10 1226 Th\u00f4nex Case Postale 228",
    "sg:city":"Th\u00f4nex",
    "sg:orig_category":"Grosshandel mit B\u00fcromaschinen Grosshandel mit Datenverarbeitungsger\u00e4ten",
    "sg:phone":"+41 22 869 04 40",
    "sg:postcode":"1226",
    "sg:province":"Gen\u00e8ve",
    "wof:name":"Sage Sesam (romandie) S.a.",
    "wof:placetype":"venue"
},
  "geometry": {"coordinates":[6.2040228844,46.1938591003],"type":"Point"}
}