{
  "type": "Feature",
  "properties": {
    "iso:country":"CH",
    "sg:address":"Kaiserstuhlerstrasse 44",
    "sg:city":"Weiach",
    "sg:orig_category":"Detailhandel mit Waren verschiedener Art, Hauptrichtung Nahrungsmittel",
    "sg:phone":"+41 18582218",
    "sg:postcode":"8187",
    "sg:province":"Z\u00fcrich",
    "wof:name":"Landi Weiach-siglistorf",
    "wof:placetype":"venue"
},
  "geometry": {"coordinates":[8.428235054,47.5626449585],"type":"Point"}
}