{
  "type": "Feature",
  "properties": {
    "iso:country":"CH",
    "sg:address":"Chemin Du Verger 12",
    "sg:city":"Villars-sur-gl\u00e2ne",
    "sg:orig_category":"Elektroinstallation",
    "sg:postcode":"1752",
    "sg:province":"Fribourg",
    "wof:name":"Rima Gmbh",
    "wof:placetype":"venue"
},
  "geometry": {"coordinates":[9.0511207581,47.4669952393],"type":"Point"}
}