{
  "type": "Feature",
  "properties": {
    "iso:country":"CH",
    "sg:address":"Im Langacher 5",
    "sg:city":"Greifensee",
    "sg:orig_category":"Vereine Aquarien",
    "sg:phone":"+41 19400584",
    "sg:postcode":"8606",
    "sg:province":"Z\u00fcrich",
    "wof:name":"Aquariumverein Zh-oberland",
    "wof:placetype":"venue"
},
  "geometry": {"coordinates":[8.6850214005,47.3654136658],"type":"Point"}
}