{
  "type": "Feature",
  "properties": {
    "iso:country":"CH",
    "sg:address":"Kirchhalde 13",
    "sg:city":"Wolhusen",
    "sg:orig_category":"Sportvereine Turnen",
    "sg:phone":"+41 41 490 27 15",
    "sg:postcode":"6110",
    "sg:province":"Luzern",
    "wof:name":"Aktivriege Ktv",
    "wof:placetype":"venue"
},
  "geometry": {"coordinates":[8.0760669708,47.0580711365],"type":"Point"}
}