{
  "type": "Feature",
  "properties": {
    "iso:country":"CH",
    "sg:address":"Champ L'habitant 5a",
    "sg:city":"Champoz",
    "sg:orig_category":"Gewinnung von Kies U Sand Herstellung von Zement",
    "sg:phone":"+41 32 492 21 16",
    "sg:postcode":"2735",
    "sg:province":"Bern",
    "wof:name":"Creabeton Materiaux Ag",
    "wof:placetype":"venue"
},
  "geometry": {"coordinates":[1.5262249708,45.130191803],"type":"Point"}
}