{
  "type": "Feature",
  "properties": {
    "iso:country":"CH",
    "sg:address":"Champs-montants 12b",
    "sg:city":"Marin-centre",
    "sg:orig_category":"Erzeugung U Erstbearbeitung von Aluminium Herstellung von Metallerzeugnissen ohne Maschinenbau",
    "sg:phone":"+41 32 756 02 02",
    "sg:postcode":"2074",
    "sg:province":"Neuch\u00e2tel",
    "wof:name":"Ac Aluminium Cr\u00e9ation Sa",
    "wof:placetype":"venue"
},
  "geometry": {"coordinates":[6.999434948,47.0117378235],"type":"Point"}
}