{
  "type": "Feature",
  "properties": {
    "iso:country":"CH",
    "sg:address":"Obernauerstrasse 100",
    "sg:city":"Obernau",
    "sg:orig_category":"Herstellung von Sportger\u00e4ten Herstellung von sonstigen Fahrzeugen",
    "sg:phone":"+41 41 320 47 05",
    "sg:postcode":"6012",
    "sg:province":"Luzern",
    "wof:name":"Josef M\u00fchlebach Wagnerei & Skifabrikation",
    "wof:placetype":"venue"
},
  "geometry": {"coordinates":[8.255030632,47.0333824158],"type":"Point"}
}