{
  "type": "Feature",
  "properties": {
    "iso:country":"CH",
    "sg:address":"Rumiweg 63",
    "sg:city":"Langenthal",
    "sg:orig_category":"Schwimmb\u00e4der",
    "sg:phone":"+41 62 922 16 76",
    "sg:postcode":"4900",
    "sg:province":"Bern",
    "wof:name":"Schwimm-& Sonnenbad Langenthal",
    "wof:placetype":"venue"
},
  "geometry": {"coordinates":[7.7865920067,47.2038002014],"type":"Point"}
}