{
  "type": "Feature",
  "properties": {
    "iso:country":"CH",
    "sg:address":"Wasserweg 70",
    "sg:city":"Filisur",
    "sg:orig_category":"Bau von Sportanlagen Gartenbau",
    "sg:phone":"+41 81 384 34 00",
    "sg:postcode":"7477",
    "sg:province":"Graubunden",
    "wof:name":"Schutz Gartenbau",
    "wof:placetype":"venue"
},
  "geometry": {"coordinates":[9.687317,46.671848],"type":"Point"}
}