{
  "type": "Feature",
  "properties": {
    "iso:country":"CH",
    "sg:address":"Wyssgasse 6",
    "sg:city":"Z\u00fcrich",
    "sg:orig_category":"Gymnastik U Fitnesszentren",
    "sg:phone":"+41 12429076",
    "sg:postcode":"8004",
    "sg:province":"Z\u00fcrich",
    "wof:name":"Califor Sa Kosmetik U. Mode; Dienstleistungen U. Handel Usw.",
    "wof:placetype":"venue"
},
  "geometry": {"coordinates":[8.5256061554,47.3736419678],"type":"Point"}
}