{
  "type": "Feature",
  "properties": {
    "iso:country":"CH",
    "sg:address":"Route De Chaindon 7",
    "sg:city":"Reconvilier",
    "sg:orig_category":"Arztpraxen",
    "sg:phone":"+41 32 481 22 79",
    "sg:postcode":"2732",
    "sg:province":"Bern",
    "wof:name":"Dr M\u00e9d. Jean-charles Travaini M\u00e9decin G\u00e9n\u00e9raliste",
    "wof:placetype":"venue"
},
  "geometry": {"coordinates":[7.22,47.23502],"type":"Point"}
}