{
  "type": "Feature",
  "properties": {
    "iso:country":"CH",
    "sg:address":"Freienhofgasse 3",
    "sg:city":"Thun",
    "sg:classifiers":[
        {
            "category":"Travel",
            "subcategory":"Hotels & Motels",
            "type":"Entertainment"
        }
    ],
    "sg:postcode":"3600",
    "sg:province":"Bern",
    "sg:tags":[
        "hotels",
        "mit",
        "restaurant"
    ],
    "wof:name":"Freihof Gastro + R\u00e4geboge Weinhandlung Gmbh",
    "wof:placetype":"venue"
},
  "geometry": {"coordinates":[8.9527902603,47.1751785278],"type":"Point"}
}