{
  "type": "Feature",
  "properties": {
    "iso:country":"CH",
    "sg:address":"Rotbuchstrasse 30",
    "sg:city":"D\u00fcbendorf",
    "sg:orig_category":"Unternehmensberatung",
    "sg:postcode":"8600",
    "sg:province":"Z\u00fcrich",
    "wof:name":"Di Cintio Bruno Adminplus",
    "wof:placetype":"venue"
},
  "geometry": {"coordinates":[8.6281137466,47.4061431885],"type":"Point"}
}