{
  "type": "Feature",
  "properties": {
    "iso:country":"CH",
    "sg:address":"M\u00fcnchensteinerstrasse 6 4052 Basel. Postfach",
    "sg:city":"Basel",
    "sg:orig_category":"Fachdetailhandel in Verkaufsr\u00e4umen",
    "sg:phone":"+41 61 313 68 38",
    "sg:postcode":"4051",
    "sg:province":"Basel-Stadt",
    "wof:name":"Space Art Sch\u00e4uble D. Schmuck; Design, Herst, Vertrieb",
    "wof:placetype":"venue"
},
  "geometry": {"coordinates":[7.5979270935,47.5475006104],"type":"Point"}
}