{
  "type": "Feature",
  "properties": {
    "iso:country":"CH",
    "sg:address":"Place Du Premier-ao\u00fbt 3",
    "sg:city":"Grand-lancy",
    "sg:orig_category":"Detailhandel mit Damenbekleidung Herstellung von Radio U Fernsehger\u00e4ten sowie phono U videotechnisch",
    "sg:phone":"+41 22 794 16 44",
    "sg:postcode":"1212",
    "sg:province":"Gen\u00e8ve",
    "wof:name":"Pek Ag",
    "wof:placetype":"venue"
},
  "geometry": {"coordinates":[6.1201992035,46.1820526123],"type":"Point"}
}