{
  "type": "Feature",
  "properties": {
    "iso:country":"CH",
    "sg:address":"Am Lochenweiher 17",
    "sg:city":"Bonstetten",
    "sg:orig_category":"Fernmeldedienste",
    "sg:phone":"+41 17717101",
    "sg:postcode":"8906",
    "sg:province":"Z\u00fcrich",
    "wof:name":"Pec & Parts Grob S.",
    "wof:placetype":"venue"
},
  "geometry": {"coordinates":[8.4783773422,47.3110351562],"type":"Point"}
}