{
  "type": "Feature",
  "properties": {
    "iso:country":"CH",
    "sg:address":"Panigari Via 5 6600 Locarno. Postfach",
    "sg:city":"Locarno",
    "sg:orig_category":"Detailhandel mit M\u00f6beln U Haushaltsgegenst\u00e4nden",
    "sg:postcode":"6600",
    "sg:province":"Ticino",
    "wof:name":"De.sign Sagl Mobili D'arredamento; Acquisto, Vendita Ecc",
    "wof:placetype":"venue"
},
  "geometry": {"coordinates":[8.7943601608,46.1696777344],"type":"Point"}
}