{
  "type": "Feature",
  "properties": {
    "iso:country":"CH",
    "sg:address":"Grand'rue 11",
    "sg:city":"Rolle",
    "sg:orig_category":"Geometerb\u00fcros",
    "sg:phone":"+41 21 825 11 26",
    "sg:postcode":"1180",
    "sg:province":"Vaud",
    "wof:name":"Daniel Belotti Bureau Technique & De G\u00e9om\u00e8tre",
    "wof:placetype":"venue"
},
  "geometry": {"coordinates":[6.3382320404,46.4575157166],"type":"Point"}
}