{
  "type": "Feature",
  "properties": {
    "iso:country":"CH",
    "sg:address":"Bernstrasse 84/86",
    "sg:city":"Rudolfstetten",
    "sg:orig_category":"Einzelhandel mit Automobilteilen U Zubeh\u00f6r Herstellung von sonstigen Maschinen f\u00fcr bestimmte Verwend",
    "sg:phone":"+41 56 633 10 00",
    "sg:postcode":"8964",
    "sg:province":"Aargau",
    "wof:name":"Andex A. Anderegg & Co",
    "wof:placetype":"venue"
},
  "geometry": {"coordinates":[8.3795080185,47.3672904968],"type":"Point"}
}