{
  "type": "Feature",
  "properties": {
    "iso:country":"CH",
    "sg:address":"St. Antonsgasse 6300 Zug. Postfach",
    "sg:city":"Zug",
    "sg:orig_category":"Instandhaltung U Reparatur von Automobilen",
    "sg:postcode":"6300",
    "sg:province":"Zug",
    "wof:name":"Pit Stop Carwash Ag Betrieb V. Carwash-anlagen, Autoreinigungscentren, Tankstellen, Shops Usw",
    "wof:placetype":"venue"
},
  "geometry": {"coordinates":[8.5164451599,47.1675453186],"type":"Point"}
}