{
  "type": "Feature",
  "properties": {
    "iso:country":"CH",
    "sg:address":"Dornacherstrasse 6",
    "sg:city":"Liestal",
    "sg:orig_category":"Handels-H\u00e4user U Gesellschaften",
    "sg:postcode":"4410",
    "sg:province":"Basel-Landschaft",
    "wof:name":"Tms Trade & Marketing Services Gmbh",
    "wof:placetype":"venue"
},
  "geometry": {"coordinates":[7.7210059166,47.4823112488],"type":"Point"}
}