{
  "type": "Feature",
  "properties": {
    "iso:country":"CH",
    "sg:address":"Sch\u00f6nenfels 3",
    "sg:city":"Rothenburg",
    "sg:orig_category":"Sportvereine Ballsport Tischtennis",
    "sg:phone":"+41 31 371 62 17",
    "sg:postcode":"6023",
    "sg:province":"Luzern",
    "wof:name":"Ttc Royal Bern",
    "wof:placetype":"venue"
},
  "geometry": {"coordinates":[7.4412379265,46.9366416931],"type":"Point"}
}