{
  "type": "Feature",
  "properties": {
    "iso:country":"CH",
    "sg:address":"Petersgasse 4",
    "sg:city":"Basel",
    "sg:orig_category":"Betrieb U technische Hilfsdienste des Kultur U Unterhaltungswesens",
    "sg:phone":"+41 61 261 88 64",
    "sg:postcode":"4051",
    "sg:province":"Basel-Stadt",
    "wof:name":"Marelli Dr. V., Baragraph 4",
    "wof:placetype":"venue"
},
  "geometry": {"coordinates":[7.586464,47.560951],"type":"Point"}
}