{
  "type": "Feature",
  "properties": {
    "iso:country":"CH",
    "sg:address":"Rue Chausse-coqs 16",
    "sg:city":"Gen\u00e8ve",
    "sg:orig_category":"Arztpraxen",
    "sg:phone":"+41 22 310 01 81",
    "sg:postcode":"1204",
    "sg:province":"Gen\u00e8ve",
    "wof:name":"Dr M\u00e9d.jean-j. Burgermeister M\u00e9decin Sp\u00e9cialiste Fmh",
    "wof:placetype":"venue"
},
  "geometry": {"coordinates":[6.149076,46.199562],"type":"Point"}
}