{
  "type": "Feature",
  "properties": {
    "iso:country":"CH",
    "sg:address":"Route De Saint-julien 39",
    "sg:city":"Grand-lancy",
    "sg:orig_category":"Detailhandel mit M\u00f6beln U Haushaltsgegenst\u00e4nden",
    "sg:postcode":"1212",
    "sg:province":"Gen\u00e8ve",
    "wof:name":"Jacot Jean-claude",
    "wof:placetype":"venue"
},
  "geometry": {"coordinates":[6.130988121,46.1750907898],"type":"Point"}
}