{
  "type": "Feature",
  "properties": {
    "iso:country":"CH",
    "sg:address":"R\u00f6sslistrasse 15",
    "sg:city":"Flawil",
    "sg:orig_category":"Vermietung von Gebrauchsg\u00fctern",
    "sg:phone":"+41 71 393 58 78",
    "sg:postcode":"9230",
    "sg:province":"St. Gallen",
    "wof:name":"Thommen Show & Shock",
    "wof:placetype":"venue"
},
  "geometry": {"coordinates":[9.1875591278,47.4145851135],"type":"Point"}
}