{
  "type": "Feature",
  "properties": {
    "iso:country":"CH",
    "sg:address":"Diethelmstr.",
    "sg:city":"Stansstad",
    "sg:orig_category":"Allgemeiner Hoch U Tiefbau",
    "sg:postcode":"6362",
    "sg:province":"Nidwalden",
    "wof:name":"Proch\u00e0zka Karel",
    "wof:placetype":"venue"
},
  "geometry": {"coordinates":[8.33759,46.979527],"type":"Point"}
}