{
  "type": "Feature",
  "properties": {
    "iso:country":"CH",
    "sg:address":"Rue De L'etang 13",
    "sg:city":"Bulle",
    "sg:orig_category":"Herstellung von k\u00e4lte U lufttechnischen Erzeugnissen f\u00fcr gewerbliche Zwecke Sanit\u00e4rinstallation",
    "sg:phone":"+41 26 913 19 00",
    "sg:postcode":"1630",
    "sg:province":"Fribourg",
    "wof:name":"Polyforce Sa",
    "wof:placetype":"venue"
},
  "geometry": {"coordinates":[-75.6233596802,37.8270721436],"type":"Point"}
}