{
  "type": "Feature",
  "properties": {
    "addr:full":"Rue Des Moulins 5 Corcelles-payerne Vaud 1562",
    "addr:housenumber":"5",
    "addr:postcode":"1562",
    "addr:street":"Rue Des Moulins",
    "iso:country":"CH",
    "sg:address":"Rue Des Moulins 5",
    "sg:city":"Corcelles-payerne",
    "sg:orig_category":"Allgemeiner Hoch U Tiefbau Unterhalt U Reparatur im Hoch U Tiefbau",
    "sg:phone":"+41 79 667 13 56",
    "sg:postcode":"1562",
    "sg:province":"Vaud",
    "wof:name":"Esmoris Ramon Umbauten-renovationen",
    "wof:placetype":"venue"
},
  "geometry": {"coordinates":[6.961652,46.829849],"type":"Point"}
}