{
  "type": "Feature",
  "properties": {
    "iso:country":"CH",
    "sg:address":"Mottastrasse 5",
    "sg:city":"Bern",
    "sg:orig_category":"Ern\u00e4hrungsberatung",
    "sg:phone":"+41 31 351 00 01",
    "sg:postcode":"3005",
    "sg:province":"Bern",
    "wof:name":"Monika M\u00fcller Ern\u00e4hrungsberatung",
    "wof:placetype":"venue"
},
  "geometry": {"coordinates":[7.451772213,46.9426116943],"type":"Point"}
}