{
  "type": "Feature",
  "properties": {
    "iso:country":"CH",
    "sg:address":"Via Nosedo 16",
    "sg:city":"Massagno",
    "sg:orig_category":"Fahrschulen, Flugschulen",
    "sg:phone":"+41 91 966 08 87",
    "sg:postcode":"6900",
    "sg:province":"Ticino",
    "wof:name":"Jean Pierre Campana Autoscuola",
    "wof:placetype":"venue"
},
  "geometry": {"coordinates":[8.9405374527,46.0100631714],"type":"Point"}
}