{
  "type": "Feature",
  "properties": {
    "iso:country":"CH",
    "sg:address":"Hauptstrasse 7",
    "sg:city":"Affeltrangen",
    "sg:classifiers":[
        {
            "category":"Bars & Pubs",
            "type":"Food & Drink"
        }
    ],
    "sg:phone":"+41 71 917 12 43",
    "sg:postcode":"9556",
    "sg:province":"Thurgau",
    "wof:name":"Bar-cabaret Blauer Aff",
    "wof:placetype":"venue"
},
  "geometry": {"coordinates":[9.030098,47.527622],"type":"Point"}
}