{
  "type": "Feature",
  "properties": {
    "iso:country":"CH",
    "sg:address":"Via Cantonale",
    "sg:city":"Magliaso",
    "sg:orig_category":"Tankstellen",
    "sg:phone":"+41 91 606 60 21",
    "sg:postcode":"6983",
    "sg:province":"Ticino",
    "wof:name":"G. Realini & A. Fehmi Stazione Di Servizio Agip",
    "wof:placetype":"venue"
},
  "geometry": {"coordinates":[8.8859100342,45.9831352234],"type":"Point"}
}