{
  "type": "Feature",
  "properties": {
    "iso:country":"CH",
    "sg:address":"Gueroz",
    "sg:city":"Vernayaz",
    "sg:classifiers":[
        {
            "category":"Travel",
            "subcategory":"Hotels & Motels",
            "type":"Entertainment"
        }
    ],
    "sg:postcode":"1904",
    "sg:province":"Valais",
    "sg:tags":[
        "hotels",
        "mit",
        "restaurant"
    ],
    "wof:name":"Fontana Otto",
    "wof:placetype":"venue"
},
  "geometry": {"coordinates":[9.8128814697,46.7813949585],"type":"Point"}
}