{
  "type": "Feature",
  "properties": {
    "iso:country":"CH",
    "sg:address":"Affolterstrasse 8",
    "sg:city":"Luterbach",
    "sg:orig_category":"Instandhaltung U Reparatur von Automobilen",
    "sg:phone":"+41 32 682 25 82",
    "sg:postcode":"4542",
    "sg:province":"Solothurn",
    "wof:name":"Carrosserie Attinger Gmbh Garagen, Reparatur, Carrosseriebetriebe Usw",
    "wof:placetype":"venue"
},
  "geometry": {"coordinates":[7.5888080597,47.2149810791],"type":"Point"}
}