{
  "type": "Feature",
  "properties": {
    "iso:country":"CH",
    "sg:address":"Via San Gottardo 119 6648 Minusio. Postfach Caselle Postale 1346",
    "sg:city":"Minusio",
    "sg:orig_category":"Instandhaltung U Reparatur von Automobilen",
    "sg:phone":"+41 91 743 22 74",
    "sg:postcode":"6648",
    "sg:province":"Ticino",
    "wof:name":"Galassini Flli",
    "wof:placetype":"venue"
},
  "geometry": {"coordinates":[8.814997673,46.1779403687],"type":"Point"}
}