{
  "type": "Feature",
  "properties": {
    "iso:country":"CH",
    "sg:address":"Wingertstrasse 15",
    "sg:city":"Felsberg",
    "sg:orig_category":"Allgemeiner Hoch U Tiefbau Architekturb\u00fcros",
    "sg:phone":"+41 81 252 70 27",
    "sg:postcode":"7012",
    "sg:province":"Graubunden",
    "wof:name":"R. Sosio Ag Architekturb\u00fcro",
    "wof:placetype":"venue"
},
  "geometry": {"coordinates":[9.467282,46.844624],"type":"Point"}
}