{
  "type": "Feature",
  "properties": {
    "iso:country":"CH",
    "sg:address":"Cantonale Via 2a",
    "sg:city":"Manno",
    "sg:orig_category":"Handels-H\u00e4user U Gesellschaften",
    "sg:postcode":"6928",
    "sg:province":"Ticino",
    "wof:name":"Via Handelsagentur Bruno Men\u00e9trey",
    "wof:placetype":"venue"
},
  "geometry": {"coordinates":[8.9560079575,47.1749382019],"type":"Point"}
}