{
  "type": "Feature",
  "properties": {
    "iso:country":"CH",
    "sg:address":"Rue De Lausanne 27",
    "sg:city":"Fribourg",
    "sg:orig_category":"Verwertung von Milch",
    "sg:postcode":"1700",
    "sg:province":"Fribourg",
    "wof:name":"Pittet-rauber Pierre",
    "wof:placetype":"venue"
},
  "geometry": {"coordinates":[7.1596369743,46.8059921265],"type":"Point"}
}