{
  "type": "Feature",
  "properties": {
    "iso:country":"CH",
    "sg:address":"Anetswilerstrasse 5",
    "sg:city":"W\u00e4ngi",
    "sg:orig_category":"Grosshandel mit M\u00f6beln, Wohnbedarf, Teppichen U Bodenbel\u00e4gen Grosshandel mit keramischen Erzeugnisse",
    "sg:phone":"+41 52 378 11 88",
    "sg:postcode":"9545",
    "sg:province":"Thurgau",
    "wof:name":"Schadegg Ag",
    "wof:placetype":"venue"
},
  "geometry": {"coordinates":[8.9768886566,47.500793457],"type":"Point"}
}