{
  "type": "Feature",
  "properties": {
    "iso:country":"CH",
    "sg:address":"B\u00f6zingenstrasse 9 2502 Biel/bienne Case Postale 876",
    "sg:city":"Biel/bienne",
    "sg:orig_category":"Herstellung U Zusammensetzung von Uhren Herstellung von Uhren",
    "sg:phone":"+41 32 953 12 75",
    "sg:postcode":"2502",
    "sg:province":"Bern",
    "wof:name":"Erard Joseph Sa",
    "wof:placetype":"venue"
},
  "geometry": {"coordinates":[6.957525,47.226807],"type":"Point"}
}