{
  "type": "Feature",
  "properties": {
    "addr:full":"Kantonsstrasse 31 Geuensee Luzern 6232",
    "addr:housenumber":"31",
    "addr:postcode":"6232",
    "addr:street":"Kantonsstrasse",
    "iso:country":"CH",
    "sg:address":"Kantonsstrasse 31",
    "sg:city":"Geuensee",
    "sg:orig_category":"Aktivit\u00e4ten der Generalunternehmen im Baugewerbe Allgemeiner Hoch U Tiefbau",
    "sg:phone":"+41 79 208 48 02",
    "sg:postcode":"6232",
    "sg:province":"Luzern",
    "wof:name":"Imoventa Ag Generalunternehmung",
    "wof:placetype":"venue"
},
  "geometry": {"coordinates":[8.107683,47.199001],"type":"Point"}
}