{
  "type": "Feature",
  "properties": {
    "iso:country":"CH",
    "sg:address":"Kesselstrasse 7",
    "sg:city":"Spreitenbach",
    "sg:orig_category":"Mechanische Werkst\u00e4tten",
    "sg:phone":"+41 56 402 01 21",
    "sg:postcode":"8957",
    "sg:province":"Aargau",
    "wof:name":"Rolf Lips Lsm",
    "wof:placetype":"venue"
},
  "geometry": {"coordinates":[8.3725147247,47.4325561523],"type":"Point"}
}