{
  "type": "Feature",
  "properties": {
    "iso:country":"CH",
    "sg:address":"Allmendstrasse 27",
    "sg:city":"B\u00fclach",
    "sg:orig_category":"Handelsvermittlung U Grosshandel Sonstiger Grosshandel",
    "sg:phone":"+41 79 601 42 41",
    "sg:postcode":"8180",
    "sg:province":"Z\u00fcrich",
    "wof:name":"Zernex Ag Handel",
    "wof:placetype":"venue"
},
  "geometry": {"coordinates":[8.5417404175,47.3319320679],"type":"Point"}
}