{
  "type": "Feature",
  "properties": {
    "iso:country":"CH",
    "sg:address":"Buckstrasse 21",
    "sg:city":"W\u00e4denswil",
    "sg:orig_category":"Pensionskassen",
    "sg:phone":"+41 71 925 11 81",
    "sg:postcode":"8820",
    "sg:province":"Z\u00fcrich",
    "wof:name":"Personalf\u00fcrsorgestiftung Der Camion-transport Ag Wil Ct",
    "wof:placetype":"venue"
},
  "geometry": {"coordinates":[9.0281887054,47.4585266113],"type":"Point"}
}