{
  "type": "Feature",
  "properties": {
    "iso:country":"CH",
    "sg:address":"Buchholzstrasse 163",
    "sg:city":"Z\u00fcrich",
    "sg:orig_category":"Arztpraxen",
    "sg:phone":"+41 12696969",
    "sg:postcode":"8053",
    "sg:province":"Z\u00fcrich",
    "wof:name":"Dr.med.eduard Kaufmann Spezialarzt Fmh",
    "wof:placetype":"venue"
},
  "geometry": {"coordinates":[8.591689,47.360714],"type":"Point"}
}