{
  "type": "Feature",
  "properties": {
    "iso:country":"CH",
    "sg:address":"Bachstrasse 30",
    "sg:city":"Schleitheim",
    "sg:orig_category":"Instandhaltung U Reparatur von Automobilen",
    "sg:phone":"+41 79 447 90 52",
    "sg:postcode":"8226",
    "sg:province":"Schaffhausen",
    "wof:name":"Bachgarage Rutschmann + Co",
    "wof:placetype":"venue"
},
  "geometry": {"coordinates":[8.490447998,47.7518386841],"type":"Point"}
}