{
  "type": "Feature",
  "properties": {
    "iso:country":"CH",
    "sg:address":"Kantonsstrasse 70",
    "sg:city":"Horw",
    "sg:orig_category":"Zimmerei, Dachdeckerei, Bauspenglerei U Abdichtung",
    "sg:phone":"+41 41 340 74 21",
    "sg:postcode":"6048",
    "sg:province":"Luzern",
    "wof:name":"Schnyder Holzbau Plus Gmbh",
    "wof:placetype":"venue"
},
  "geometry": {"coordinates":[8.3106689453,47.0209197998],"type":"Point"}
}