{
  "type": "Feature",
  "properties": {
    "iso:country":"CH",
    "sg:address":"Rheinstrasse 1b",
    "sg:city":"Heerbrugg",
    "sg:orig_category":"K\u00fcnstlerische Schulen",
    "sg:phone":"+41 71 722 56 52",
    "sg:postcode":"9435",
    "sg:province":"St. Gallen",
    "wof:name":"Anneliese Kuster Musikschule",
    "wof:placetype":"venue"
},
  "geometry": {"coordinates":[9.628030777,47.4087181091],"type":"Point"}
}