{
  "type": "Feature",
  "properties": {
    "addr:full":"Wilhelm Klein-strasse 27 4056 Basel. Postfach 260 Basel Basel-Stadt 4025",
    "addr:housenumber":"27;260",
    "addr:postcode":"4056;4025",
    "addr:street":"Wilhelm Klein-Strasse;Postfach",
    "iso:country":"CH",
    "sg:address":"Wilhelm Klein-strasse 27 4056 Basel. Postfach 260",
    "sg:city":"Basel",
    "sg:classifiers":[
        {
            "category":"Education",
            "subcategory":"Library",
            "type":"Public Place"
        }
    ],
    "sg:phone":"+41 61 272 63 31",
    "sg:postcode":"4025",
    "sg:province":"Basel-Stadt",
    "sg:tags":[
        "u",
        "bibliotheken",
        "archive"
    ],
    "wof:name":"Psych.universit\u00e4tsklinik",
    "wof:placetype":"venue"
},
  "geometry": {"coordinates":[7.56595,47.571217],"type":"Point"}
}