{
  "type": "Feature",
  "properties": {
    "iso:country":"CH",
    "sg:address":"Bahnhofstrasse 27a 3800 Interlaken. Postfach 261",
    "sg:city":"Interlaken",
    "sg:orig_category":"Vereine Harmonika and Akkordeon",
    "sg:phone":"+41 32 351 28 67",
    "sg:postcode":"3800",
    "sg:province":"Bern",
    "wof:name":"Handharmonika-klub",
    "wof:placetype":"venue"
},
  "geometry": {"coordinates":[7.3718671799,47.1398963928],"type":"Point"}
}