{
  "type": "Feature",
  "properties": {
    "iso:country":"CH",
    "sg:address":"Schneisingen 8 8752 N\u00e4fels. Postfach",
    "sg:city":"N\u00e4fels",
    "sg:orig_category":"Herstellung von Teppichen",
    "sg:postcode":"8752",
    "sg:province":"Glarus",
    "wof:name":"Lamatech Spezialbodenbel\u00e4ge Landolt Marc",
    "wof:placetype":"venue"
},
  "geometry": {"coordinates":[9.056760788,47.0901107788],"type":"Point"}
}