{
  "type": "Feature",
  "properties": {
    "iso:country":"CH",
    "sg:address":"Mythenquai 20",
    "sg:city":"Z\u00fcrich",
    "sg:orig_category":"Oberfl\u00e4chenveredlung U W\u00e4rmebehandlung Verarbeitung U Veredlung von Flachglas",
    "sg:phone":"+41 61 462 00 30",
    "sg:postcode":"8002",
    "sg:province":"Z\u00fcrich",
    "wof:name":"Boglas Ag",
    "wof:placetype":"venue"
},
  "geometry": {"coordinates":[7.6390709877,47.5256538391],"type":"Point"}
}