{
  "type": "Feature",
  "properties": {
    "iso:country":"CH",
    "sg:address":"La Place",
    "sg:city":"Basse-nendaz",
    "sg:classifiers":[
        {
            "category":"Building & Trades",
            "subcategory":"Locksmith",
            "type":"Services"
        }
    ],
    "sg:phone":"+41 27 288 26 58",
    "sg:postcode":"1996",
    "sg:province":"Valais",
    "sg:tags":[
        "chimney"
    ],
    "wof:name":"Michel Glassey Carrelages Et Rev\u00eatements",
    "wof:placetype":"venue"
},
  "geometry": {"coordinates":[7.31413,46.189041],"type":"Point"}
}