{
  "type": "Feature",
  "properties": {
    "iso:country":"CH",
    "sg:address":"Schaffhauserstrasse 54",
    "sg:city":"Neuhausen",
    "sg:orig_category":"Finanzierungsinstitutionen",
    "sg:postcode":"8212",
    "sg:province":"Schaffhausen",
    "wof:name":"Zelghof Finanz Ag",
    "wof:placetype":"venue"
},
  "geometry": {"coordinates":[8.6226921082,47.6884117126],"type":"Point"}
}