{
  "type": "Feature",
  "properties": {
    "iso:country":"CH",
    "sg:address":"Seefeldstrasse 8 6374 Buochs. Postfach",
    "sg:city":"Buochs",
    "sg:orig_category":"Reinigungsgewerbe",
    "sg:postcode":"6374",
    "sg:province":"Nidwalden",
    "wof:name":"Aschwanden & H\u00f6hener Gmbh",
    "wof:placetype":"venue"
},
  "geometry": {"coordinates":[8.4222812653,46.9770126343],"type":"Point"}
}