{
  "type": "Feature",
  "properties": {
    "iso:country":"CH",
    "sg:address":"Sorengo Via 7",
    "sg:city":"Lugano",
    "sg:orig_category":"Herstellung von sonstigen Maschinen f\u00fcr unspezifische Verwendung",
    "sg:phone":"+41 62 754 10 48",
    "sg:postcode":"6900",
    "sg:province":"Ticino",
    "wof:name":"Techfit Gut",
    "wof:placetype":"venue"
},
  "geometry": {"coordinates":[7.8391251564,47.2273254395],"type":"Point"}
}