{
  "type": "Feature",
  "properties": {
    "iso:country":"CH",
    "sg:address":"Hubelweg 4",
    "sg:city":"Jens",
    "sg:orig_category":"Innenausbau Zimmerei, Dachdeckerei, Bauspenglerei U Abdichtung",
    "sg:phone":"+41 32 331 00 32",
    "sg:postcode":"2565",
    "sg:province":"Bern",
    "wof:name":"E. Kohler Holzbau/bedachungen Gmbh",
    "wof:placetype":"venue"
},
  "geometry": {"coordinates":[7.2650609016,47.0990447998],"type":"Point"}
}