{
  "type": "Feature",
  "properties": {
    "iso:country":"CH",
    "sg:address":"Tittwiesenstrasse 61",
    "sg:city":"Chur",
    "sg:classifiers":[
        {
            "category":"Brewery",
            "type":"Food & Drink"
        }
    ],
    "sg:phone":"+41 81 284 59 18",
    "sg:postcode":"7000",
    "sg:province":"Graubunden",
    "sg:tags":[
        "straw",
        "drinking"
    ],
    "wof:name":"Hotwag Gastro Ag",
    "wof:placetype":"venue"
},
  "geometry": {"coordinates":[9.5265493393,46.8585395813],"type":"Point"}
}