{
  "type": "Feature",
  "properties": {
    "iso:country":"CH",
    "sg:address":"Hofackerstrasse 48",
    "sg:city":"Muttenz",
    "sg:orig_category":"Elektrizit\u00e4tsversorgung Grosshandel mit Eisenwaren sowie Installationsbedarf f\u00fcr Gas, Wasser U Heizu",
    "sg:phone":"+41 61 462 33 33",
    "sg:postcode":"4132",
    "sg:province":"Basel-Landschaft",
    "wof:name":"Borer Ag Industrie Und Umwelttechnik",
    "wof:placetype":"venue"
},
  "geometry": {"coordinates":[7.6382770538,47.5362548828],"type":"Point"}
}