{
  "type": "Feature",
  "properties": {
    "iso:country":"CH",
    "sg:address":"R\u00f6sslistrasse 3",
    "sg:city":"N\u00e4fels",
    "sg:orig_category":"Non-Classified Establishments",
    "sg:postcode":"8752",
    "sg:province":"Glarus",
    "wof:name":"Salon Willy, W. Oswald",
    "wof:placetype":"venue"
},
  "geometry": {"coordinates":[9.0628347397,47.0983886719],"type":"Point"}
}