{
  "type": "Feature",
  "properties": {
    "iso:country":"CH",
    "sg:address":"Lochlistrasse 13",
    "sg:city":"Gachnang",
    "sg:orig_category":"Bauschreinerei Innenausbau",
    "sg:phone":"+41 52 375 19 17",
    "sg:postcode":"8547",
    "sg:province":"Thurgau",
    "wof:name":"Heinz Moor Schreinerei & Innenausbau",
    "wof:placetype":"venue"
},
  "geometry": {"coordinates":[8.855116,47.537308],"type":"Point"}
}