{
  "type": "Feature",
  "properties": {
    "iso:country":"CH",
    "sg:address":"Ruopigenh\u00f6he 9 6015 Reussb\u00fchl. Postfach",
    "sg:city":"Reussb\u00fchl",
    "sg:orig_category":"Sonstiger Grosshandel",
    "sg:phone":"+41 62 291 41 34",
    "sg:postcode":"6015",
    "sg:province":"Luzern",
    "wof:name":"Ger\u00e4te Und Warenhandel Schlachter",
    "wof:placetype":"venue"
},
  "geometry": {"coordinates":[7.9780669212,47.3529586792],"type":"Point"}
}