{
  "type": "Feature",
  "properties": {
    "iso:country":"CH",
    "sg:address":"Emil Kl\u00f6ti-strasse 21 8406 Winterthur. Postfach",
    "sg:city":"Winterthur",
    "sg:orig_category":"Baugewerbe",
    "sg:phone":"+41 52 203 77 41",
    "sg:postcode":"8406",
    "sg:province":"Z\u00fcrich",
    "wof:name":"Werner Nyffenegger Holzmontagen",
    "wof:placetype":"venue"
},
  "geometry": {"coordinates":[8.704922,47.493488],"type":"Point"}
}