{
  "type": "Feature",
  "properties": {
    "iso:country":"CH",
    "sg:address":"Neuhaltenring 12",
    "sg:city":"Ebikon",
    "sg:orig_category":"Druck ohne Zeitungsdruck Siebdruck",
    "sg:phone":"+41 81 756 57 76",
    "sg:postcode":"6030",
    "sg:province":"Luzern",
    "wof:name":"Sirek Siebdruck Und Reklamen Ag",
    "wof:placetype":"venue"
},
  "geometry": {"coordinates":[9.4828290939,47.173625946],"type":"Point"}
}