{
  "type": "Feature",
  "properties": {
    "iso:country":"CH",
    "sg:address":"3424",
    "sg:city":"Nieder\u00f6sch",
    "sg:orig_category":"Schulpflegen",
    "sg:postcode":"3424",
    "sg:province":"Bern",
    "wof:name":"Primarschulkommission Der Gemeinde Noflen",
    "wof:placetype":"venue"
},
  "geometry": {"coordinates":[7.5464100838,46.8056907654],"type":"Point"}
}