{
  "type": "Feature",
  "properties": {
    "iso:country":"CH",
    "sg:address":"Wilenhalde 2",
    "sg:city":"Herisau",
    "sg:orig_category":"Elektroinstallation",
    "sg:postcode":"9100",
    "sg:province":"Appenzell Ausserrhoden",
    "wof:name":"Meier Elektroinstallationen",
    "wof:placetype":"venue"
},
  "geometry": {"coordinates":[8.3040714264,47.3976020813],"type":"Point"}
}