{
  "type": "Feature",
  "properties": {
    "iso:country":"CH",
    "sg:address":"Via Monte Boglia 16",
    "sg:city":"Lugano",
    "sg:orig_category":"Verarbeitung U Veredlung von Flachglas",
    "sg:phone":"+41 91 971 21 01",
    "sg:postcode":"6900",
    "sg:province":"Ticino",
    "wof:name":"Biaggi Piergiorgio Gi\u00e0 Biaggi Artaria & Varallo",
    "wof:placetype":"venue"
},
  "geometry": {"coordinates":[8.9595499039,46.0177726746],"type":"Point"}
}