{
  "type": "Feature",
  "properties": {
    "addr:full":"Uttigenstrasse 62 Uetendorf Bern 3661",
    "addr:housenumber":"62",
    "addr:postcode":"3661",
    "addr:street":"Uttigenstrasse",
    "iso:country":"CH",
    "sg:address":"Uttigenstrasse 62",
    "sg:city":"Uetendorf",
    "sg:orig_category":"Autospenglereien",
    "sg:phone":"+41 33 356 17 17",
    "sg:postcode":"3661",
    "sg:province":"Bern",
    "wof:name":"Waber & Sohn Carrosserie",
    "wof:placetype":"venue"
},
  "geometry": {"coordinates":[7.590417,46.778919],"type":"Point"}
}