{
  "type": "Feature",
  "properties": {
    "iso:country":"CH",
    "sg:address":"Mettlenstrasse 10",
    "sg:city":"M\u00e4nnedorf",
    "sg:orig_category":"Sportvereine Sch\u00fctzen Pistolen-& Gewehr",
    "sg:phone":"+41 19202831",
    "sg:postcode":"8708",
    "sg:province":"Z\u00fcrich",
    "wof:name":"Pistolenschiessverein",
    "wof:placetype":"venue"
},
  "geometry": {"coordinates":[8.6984224319,47.2601165771],"type":"Point"}
}