{
  "type": "Feature",
  "properties": {
    "iso:country":"CH",
    "sg:address":"Hauptstrasse 5",
    "sg:city":"Hochdorf",
    "sg:orig_category":"Detailhandel mit Waren verschiedener Art, Hauptrichtung Nahrungsmittel",
    "sg:phone":"+41 71 242 69 30",
    "sg:postcode":"6280",
    "sg:province":"Luzern",
    "wof:name":"Migros-markt St.fiden",
    "wof:placetype":"venue"
},
  "geometry": {"coordinates":[9.3920297623,47.4354667664],"type":"Point"}
}