{
  "type": "Feature",
  "properties": {
    "iso:country":"CH",
    "sg:address":"D\u00e4hlenstrasse 37",
    "sg:city":"Grenchen",
    "sg:orig_category":"Sonstige mit der Informatik verbundene T\u00e4tigkeiten",
    "sg:postcode":"2540",
    "sg:province":"Solothurn",
    "wof:name":"Qs-system-berater, Hafner Anton",
    "wof:placetype":"venue"
},
  "geometry": {"coordinates":[7.3853259087,47.1936225891],"type":"Point"}
}