{
  "type": "Feature",
  "properties": {
    "iso:country":"CH",
    "sg:address":"Blumenhaldenweg 12",
    "sg:city":"Goldach",
    "sg:orig_category":"Druckguss-Werke",
    "sg:postcode":"9403",
    "sg:province":"St. Gallen",
    "wof:name":"Strassacker & Co Bronzen",
    "wof:placetype":"venue"
},
  "geometry": {"coordinates":[9.455452919,47.4715118408],"type":"Point"}
}