{
  "type": "Feature",
  "properties": {
    "iso:country":"CH",
    "sg:address":"3911",
    "sg:city":"Ried-brig",
    "sg:orig_category":"RESTAURANTS: TEA-ROOMS",
    "sg:postcode":"3911",
    "sg:province":"Valais",
    "wof:name":"Tscherrig Magdalena, Bergrestaurant Wasenalp",
    "wof:placetype":"venue"
},
  "geometry": {"coordinates":[8.0152349472,46.3151245117],"type":"Point"}
}