{
  "type": "Feature",
  "properties": {
    "iso:country":"CH",
    "sg:address":"Gurzelngasse 12",
    "sg:city":"Solothurn",
    "sg:orig_category":"Oberfl\u00e4chenveredlung U W\u00e4rmebehandlung",
    "sg:postcode":"4500",
    "sg:province":"Solothurn",
    "wof:name":"Poligrat-service Ag",
    "wof:placetype":"venue"
},
  "geometry": {"coordinates":[7.5366411209,47.2080459595],"type":"Point"}
}