{
  "type": "Feature",
  "properties": {
    "iso:country":"CH",
    "sg:address":"Haldenstrasse 25",
    "sg:city":"Adliswil",
    "sg:orig_category":"Architekturb\u00fcros",
    "sg:phone":"+41 81 356 09 30",
    "sg:postcode":"8134",
    "sg:province":"Z\u00fcrich",
    "wof:name":"Weber Architektur",
    "wof:placetype":"venue"
},
  "geometry": {"coordinates":[8.523372,47.308678],"type":"Point"}
}