{
  "type": "Feature",
  "properties": {
    "iso:country":"CH",
    "sg:address":"Baslerstrasse 8",
    "sg:city":"Rheinfelden",
    "sg:orig_category":"Rechtsberatung",
    "sg:postcode":"4310",
    "sg:province":"Aargau",
    "wof:name":"Ccs Inter Gmbh",
    "wof:placetype":"venue"
},
  "geometry": {"coordinates":[7.7852911949,47.5516777039],"type":"Point"}
}