{
  "type": "Feature",
  "properties": {
    "iso:country":"CH",
    "sg:address":"Hengelenweg 4",
    "sg:city":"Degersheim",
    "sg:orig_category":"RESTAURANTS: TEA-ROOMS",
    "sg:phone":"+41 71 371 14 48",
    "sg:postcode":"9113",
    "sg:province":"St. Gallen",
    "wof:name":"Minikus August.",
    "wof:placetype":"venue"
},
  "geometry": {"coordinates":[9.2062501907,47.3734512329],"type":"Point"}
}