{
  "type": "Feature",
  "properties": {
    "addr:full":"L\u00e4ngmatt 6 Murten Fribourg 3280",
    "addr:housenumber":"6",
    "addr:postcode":"3280",
    "addr:street":"Laengmatt",
    "iso:country":"CH",
    "sg:address":"L\u00e4ngmatt 6",
    "sg:city":"Murten",
    "sg:orig_category":"Bezirks, Sekundar, Realschulen, Oberstufe der Primarschulen",
    "sg:phone":"+41 62 961 49 84",
    "sg:postcode":"3280",
    "sg:province":"Fribourg",
    "wof:name":"Sekundarschule",
    "wof:placetype":"venue"
},
  "geometry": {"coordinates":[7.119535,46.930721],"type":"Point"}
}