{
  "type": "Feature",
  "properties": {
    "iso:country":"CH",
    "sg:address":"Uebersax",
    "sg:city":"Linthal",
    "sg:orig_category":"S\u00e4ge, Hobel U Holzimpr\u00e4gnierwerke S\u00e4gewerke",
    "sg:phone":"+41 55 643 38 60",
    "sg:postcode":"8783",
    "sg:province":"Glarus",
    "wof:name":"S\u00e4gerei St\u00fcssi Ag",
    "wof:placetype":"venue"
},
  "geometry": {"coordinates":[9.0037260056,46.9244880676],"type":"Point"}
}