{
  "type": "Feature",
  "properties": {
    "iso:country":"CH",
    "sg:address":"Hofmeisterstrasse 1 3006 Bern. Postfach",
    "sg:city":"Bern",
    "sg:orig_category":"Elektroinstallation",
    "sg:postcode":"3005",
    "sg:province":"Bern",
    "wof:name":"A. Clausen Elektr. Anlagen U App.; Ausf\u00fchrung, Handel",
    "wof:placetype":"venue"
},
  "geometry": {"coordinates":[7.4724678993,46.9376144409],"type":"Point"}
}