{
  "type": "Feature",
  "properties": {
    "iso:country":"CH",
    "sg:address":"Luzernstrasse 8",
    "sg:city":"Merenschwand",
    "sg:orig_category":"Physiotherapie",
    "sg:phone":"+41 56 668 21 21",
    "sg:postcode":"5634",
    "sg:province":"Aargau",
    "wof:name":"Luzia H\u00e4nni Physiotherapie Alte Bank",
    "wof:placetype":"venue"
},
  "geometry": {"coordinates":[8.3750371933,47.2588500977],"type":"Point"}
}