{
  "type": "Feature",
  "properties": {
    "iso:country":"CH",
    "sg:address":"Zetzwilerstrasse 763 5728 Gontenschwil. Postfach 18",
    "sg:city":"Gontenschwil",
    "sg:orig_category":"Grosshandel mit sonstigen Halbwaren Herstellung von Kunststoffwaren",
    "sg:phone":"+41 56 675 44 99",
    "sg:postcode":"5728",
    "sg:province":"Aargau",
    "wof:name":"Carthuplas Ag",
    "wof:placetype":"venue"
},
  "geometry": {"coordinates":[8.3174819946,47.2825775146],"type":"Point"}
}