{
  "type": "Feature",
  "properties": {
    "iso:country":"CH",
    "sg:address":"Kirchbergstrasse 8",
    "sg:city":"Aarau",
    "sg:orig_category":"Vorschulen, Kinderg\u00e4rten",
    "sg:phone":"+41 71 744 44 10",
    "sg:postcode":"5000",
    "sg:province":"Aargau",
    "wof:name":"St\u00e4dtischer Kindergarten Scheibenschachen",
    "wof:placetype":"venue"
},
  "geometry": {"coordinates":[8.0448789597,47.3981895447],"type":"Point"}
}