{
  "type": "Feature",
  "properties": {
    "iso:country":"CH",
    "sg:address":"Rotte Chemin De La 3",
    "sg:city":"Montreux",
    "sg:orig_category":"Instandhaltung U Reparatur von Automobilen",
    "sg:phone":"+41 21 981 28 79",
    "sg:postcode":"1820",
    "sg:province":"Vaud",
    "wof:name":"Garage Mc Sport, Michel Cosandey",
    "wof:placetype":"venue"
},
  "geometry": {"coordinates":[6.9105057716,46.4316940308],"type":"Point"}
}