{
  "type": "Feature",
  "properties": {
    "iso:country":"CH",
    "sg:address":"Neue Sonnenbergstrasse 7324 Vilters. Postfach",
    "sg:city":"Vilters",
    "sg:orig_category":"Sprachschulen",
    "sg:phone":"+41 81 723 13 96",
    "sg:postcode":"7324",
    "sg:province":"St. Gallen",
    "wof:name":"Regionale Sprachschule",
    "wof:placetype":"venue"
},
  "geometry": {"coordinates":[9.4482831955,47.0233001709],"type":"Point"}
}