{
  "type": "Feature",
  "properties": {
    "iso:country":"CH",
    "sg:address":"Schwarzenburgstrasse 865",
    "sg:city":"Niederscherli",
    "sg:orig_category":"Bauschreinerei",
    "sg:phone":"+41 31 849 02 44",
    "sg:postcode":"3145",
    "sg:province":"Bern",
    "wof:name":"Fritz Gfeller Schreinerei",
    "wof:placetype":"venue"
},
  "geometry": {"coordinates":[7.381327,46.882767],"type":"Point"}
}