{
  "type": "Feature",
  "properties": {
    "iso:country":"CH",
    "sg:address":"Hauptstrasse 22",
    "sg:city":"Ober\u00e4geri",
    "sg:orig_category":"RESTAURANTS: TEA-ROOMS",
    "sg:phone":"+41 41 750 64 50",
    "sg:postcode":"6315",
    "sg:province":"Zug",
    "wof:name":"Rest. Falken, Imboden I. & P.",
    "wof:placetype":"venue"
},
  "geometry": {"coordinates":[8.6113462448,47.1354255676],"type":"Point"}
}