{
  "type": "Feature",
  "properties": {
    "iso:country":"CH",
    "sg:address":"K\u00fcttigerstrasse 76",
    "sg:city":"Erlinsbach",
    "sg:orig_category":"Sonstiges Gesundheitswesen",
    "sg:phone":"+41 41 497 14 78",
    "sg:postcode":"5018",
    "sg:province":"Solothurn",
    "wof:name":"Krankenmobilien Frau Helene Von Rotz",
    "wof:placetype":"venue"
},
  "geometry": {"coordinates":[8.1866397858,47.0165405273],"type":"Point"}
}