{
  "type": "Feature",
  "properties": {
    "iso:country":"CH",
    "sg:address":"Im Dorf",
    "sg:city":"B\u00fcchslen",
    "sg:orig_category":"Gem\u00fcsebau",
    "sg:phone":"+41 31 751 17 10",
    "sg:postcode":"3215",
    "sg:province":"Fribourg",
    "wof:name":"Ulrich Christen Gem\u00fcsebau",
    "wof:placetype":"venue"
},
  "geometry": {"coordinates":[7.1804738045,46.9448051453],"type":"Point"}
}