{
  "type": "Feature",
  "properties": {
    "iso:country":"CH",
    "sg:address":"Postweg 3",
    "sg:city":"Zuchwil",
    "sg:orig_category":"Maler U Glasergewerbe",
    "sg:phone":"+41 32 685 31 37",
    "sg:postcode":"4528",
    "sg:province":"Solothurn",
    "wof:name":"Affolter Erich",
    "wof:placetype":"venue"
},
  "geometry": {"coordinates":[7.5540509224,47.2029304504],"type":"Point"}
}