{
  "type": "Feature",
  "properties": {
    "iso:country":"CH",
    "sg:address":"Gasse 10 8846 Willerzell. Postfach",
    "sg:city":"Willerzell",
    "sg:orig_category":"Detailhandel mit Metallwaren, Anstrichmitteln, Glaswaren, Bau U Heimwerkerbedarf",
    "sg:postcode":"8846",
    "sg:province":"Schwyz",
    "wof:name":"Paguna-tech Gmbh",
    "wof:placetype":"venue"
},
  "geometry": {"coordinates":[8.7961425781,47.1295433044],"type":"Point"}
}