{
  "type": "Feature",
  "properties": {
    "iso:country":"CH",
    "sg:address":"Via Monda 2",
    "sg:city":"Camorino",
    "sg:orig_category":"Erwachsenenbildung U Unterricht Handelsvermittlung U Grosshandel",
    "sg:phone":"+41 91 857 04 70",
    "sg:postcode":"6528",
    "sg:province":"Ticino",
    "wof:name":"Labor Transfer Sa",
    "wof:placetype":"venue"
},
  "geometry": {"coordinates":[8.9937438965,46.1676101685],"type":"Point"}
}