{
  "type": "Feature",
  "properties": {
    "iso:country":"CH",
    "sg:address":"Huguenin Rue Oscar- 25 2017 Boudry. Postfach",
    "sg:city":"Boudry",
    "sg:orig_category":"Sanit\u00e4r, Heizungs U L\u00fcftungsinstallation",
    "sg:postcode":"2017",
    "sg:province":"Neuch\u00e2tel",
    "wof:name":"K\u00e4slin Et Saner Sanitaire Sa Entreprise D'installations Sanitaires Etc",
    "wof:placetype":"venue"
},
  "geometry": {"coordinates":[6.8369731903,46.950050354],"type":"Point"}
}