{
  "type": "Feature",
  "properties": {
    "iso:country":"CH",
    "sg:address":"Hauptstrasse 30",
    "sg:city":"Ueken",
    "sg:orig_category":"Architektur U Ingenieurb\u00fcros Architekturb\u00fcros",
    "sg:phone":"+41 62 871 37 37",
    "sg:postcode":"5028",
    "sg:province":"Aargau",
    "wof:name":"H\u00e4gi + Partner Ag",
    "wof:placetype":"venue"
},
  "geometry": {"coordinates":[8.048032,47.485451],"type":"Point"}
}