{
  "type": "Feature",
  "properties": {
    "iso:country":"CH",
    "sg:address":"Z\u00fcrichstrasse 1",
    "sg:city":"Winkel",
    "sg:orig_category":"G\u00fcterbef\u00f6rderung im Strassenverkehr",
    "sg:phone":"+41 19323535",
    "sg:postcode":"8185",
    "sg:province":"Z\u00fcrich",
    "wof:name":"Meier Gr\u00fct J. Transporte Ag",
    "wof:placetype":"venue"
},
  "geometry": {"coordinates":[8.7565450668,47.3069381714],"type":"Point"}
}