{
  "type": "Feature",
  "properties": {
    "iso:country":"CH",
    "sg:address":"Seestrasse 24 3600 Thun. Postfach",
    "sg:city":"Thun",
    "sg:orig_category":"Installation von Heizungs, L\u00fcftungs U Klimaanlagen",
    "sg:phone":"+41 33 223 00 00",
    "sg:postcode":"3602",
    "sg:province":"Bern",
    "wof:name":"Goetz Ag K\u00fchlanlagen & W\u00e4rmepumpen",
    "wof:placetype":"venue"
},
  "geometry": {"coordinates":[7.6335639954,46.7484855652],"type":"Point"}
}