{
  "type": "Feature",
  "properties": {
    "iso:country":"CH",
    "sg:address":"Unterweg 4",
    "sg:city":"Moosseedorf",
    "sg:orig_category":"Malerei",
    "sg:phone":"+41 31 859 09 75",
    "sg:postcode":"3302",
    "sg:province":"Bern",
    "wof:name":"Hans & Eliane Berger Malergesch\u00e4ft",
    "wof:placetype":"venue"
},
  "geometry": {"coordinates":[7.4857401848,47.0138206482],"type":"Point"}
}