{
  "type": "Feature",
  "properties": {
    "iso:country":"CH",
    "sg:address":"R\u00fctistrasse",
    "sg:city":"Bubikon",
    "sg:orig_category":"Architektur U Ingenieurb\u00fcros Einbau von Schreinerwaren",
    "sg:phone":"+41 55 243 12 49",
    "sg:postcode":"8608",
    "sg:province":"Z\u00fcrich",
    "wof:name":"Max Neff",
    "wof:placetype":"venue"
},
  "geometry": {"coordinates":[8.828498,47.260624],"type":"Point"}
}