{
  "type": "Feature",
  "properties": {
    "iso:country":"CH",
    "sg:address":"Route Cantonale 116",
    "sg:city":"Grand-lancy",
    "sg:orig_category":"Instandhaltung U Reparatur von Automobilen",
    "sg:phone":"+41 31 371 07 37",
    "sg:postcode":"1212",
    "sg:province":"Gen\u00e8ve",
    "wof:name":"Garage Hadorn Ag",
    "wof:placetype":"venue"
},
  "geometry": {"coordinates":[7.4396901131,46.9406394958],"type":"Point"}
}