{
  "type": "Feature",
  "properties": {
    "iso:country":"CH",
    "sg:address":"Grubenstrasse 11",
    "sg:city":"Madetswil",
    "sg:orig_category":"G\u00fcterbef\u00f6rderung im Strassenverkehr",
    "sg:phone":"+41 19540727",
    "sg:postcode":"8322",
    "sg:province":"Z\u00fcrich",
    "wof:name":"Otto Sigrist Vip Limousine Service",
    "wof:placetype":"venue"
},
  "geometry": {"coordinates":[8.7936544418,47.413684845],"type":"Point"}
}