{
  "type": "Feature",
  "properties": {
    "iso:country":"CH",
    "sg:address":"Gerbergasse 42",
    "sg:city":"Basel",
    "sg:orig_category":"Fachdetailhandel mit pharmazeutischen, medizinischen U kosmetischen Artikeln in Verkaufsr\u00e4umen Kosme",
    "sg:phone":"+41 61 261 38 33",
    "sg:postcode":"4001",
    "sg:province":"Basel-Stadt",
    "wof:name":"Bodyzone Gmbh Kosmetik- & K\u00f6rperpflege-inst.",
    "wof:placetype":"venue"
},
  "geometry": {"coordinates":[7.5884599686,47.5561523438],"type":"Point"}
}