{
  "type": "Feature",
  "properties": {
    "iso:country":"CH",
    "sg:address":"In Der Au 6 8401 Winterthur. Postfach 638",
    "sg:city":"Winterthur",
    "sg:orig_category":"Grosshandel mit elektrischen Haushaltsger\u00e4ten Herstellung von elektrischen Lampen U Leuchten",
    "sg:phone":"+41 31 931 20 34",
    "sg:postcode":"8401",
    "sg:province":"Z\u00fcrich",
    "wof:name":"Proluma Ag",
    "wof:placetype":"venue"
},
  "geometry": {"coordinates":[7.4726228714,46.9590263367],"type":"Point"}
}