{
  "type": "Feature",
  "properties": {
    "iso:country":"CH",
    "sg:address":"Chemin De Conches 44",
    "sg:city":"Conches",
    "sg:orig_category":"Sportvereine Turnen",
    "sg:phone":"+41 22 361 04 19",
    "sg:postcode":"1231",
    "sg:province":"Gen\u00e8ve",
    "wof:name":"St\u00e9 De Gymnastique De Nyon",
    "wof:placetype":"venue"
},
  "geometry": {"coordinates":[6.2390799522,46.382358551],"type":"Point"}
}