{
  "type": "Feature",
  "properties": {
    "iso:country":"CH",
    "sg:address":"Route Des Cliniques 17",
    "sg:city":"Fribourg",
    "sg:orig_category":"F\u00fcrsorge\u00e4mter",
    "sg:phone":"+41 21 632 77 22",
    "sg:postcode":"1700",
    "sg:province":"Fribourg",
    "wof:name":"Direction De La S\u00e9curit\u00e9 Sociale",
    "wof:placetype":"venue"
},
  "geometry": {"coordinates":[6.5833587646,46.5367889404],"type":"Point"}
}