{
  "type": "Feature",
  "properties": {
    "iso:country":"CH",
    "sg:address":"Rue Arnold Winkelried 6",
    "sg:city":"Genf",
    "sg:orig_category":"RESTAURANTS: TEA-ROOMS",
    "sg:postcode":"1200",
    "sg:province":"Gen\u00e8ve",
    "wof:name":"Cafe Bar Zum St\u00e4fi, Henzen-zengaffinen Richard",
    "wof:placetype":"venue"
},
  "geometry": {"coordinates":[7.7464680672,46.3153152466],"type":"Point"}
}