{
  "type": "Feature",
  "properties": {
    "iso:country":"CH",
    "sg:address":"Wechsel 8",
    "sg:city":"Bubikon",
    "sg:orig_category":"Herstellung von Frucht U Gem\u00fcses\u00e4ften Herstellung von Obst U Fruchtweinen",
    "sg:phone":"+41 55 243 11 44",
    "sg:postcode":"8608",
    "sg:province":"Z\u00fcrich",
    "wof:name":"Albert Maurer Mosterei",
    "wof:placetype":"venue"
},
  "geometry": {"coordinates":[8.8094396591,47.2713737488],"type":"Point"}
}