{
  "type": "Feature",
  "properties": {
    "iso:country":"CH",
    "sg:address":"Via Convento 4",
    "sg:city":"Bellinzona",
    "sg:orig_category":"Detailhandel mit elektrischen Haushalts-,Radio U Fernsehger\u00e4ten sowie Musikinstrumenten Grosshandel ",
    "sg:phone":"+41 91 825 56 20",
    "sg:postcode":"6500",
    "sg:province":"Ticino",
    "wof:name":"Jura Concessionaria Sagl",
    "wof:placetype":"venue"
},
  "geometry": {"coordinates":[9.0188999176,46.1869163513],"type":"Point"}
}