{
  "type": "Feature",
  "properties": {
    "iso:country":"CH",
    "sg:address":"Gerliswilstrasse 10",
    "sg:city":"Emmenbr\u00fccke",
    "sg:orig_category":"Autogaragen",
    "sg:phone":"+41 41 260 14 55",
    "sg:postcode":"6020",
    "sg:province":"Luzern",
    "wof:name":"Michele Palermo Blitz-garage",
    "wof:placetype":"venue"
},
  "geometry": {"coordinates":[8.280601,47.070972],"type":"Point"}
}