{
  "type": "Feature",
  "properties": {
    "iso:country":"CH",
    "sg:address":"Simplon Rue Du 7 1207 Gen\u00e8ve. Postfach",
    "sg:city":"Gen\u00e8ve",
    "sg:orig_category":"Mechanik",
    "sg:postcode":"1207",
    "sg:province":"Gen\u00e8ve",
    "wof:name":"Aaa Cnc Mechanik W\u00fcthrich Mechanische Bearbeitung U. Dienstleistungen",
    "wof:placetype":"venue"
},
  "geometry": {"coordinates":[7.6784548759,47.0036315918],"type":"Point"}
}