{
  "type": "Feature",
  "properties": {
    "iso:country":"CH",
    "sg:address":"Seestrasse 8",
    "sg:city":"Walenstadt",
    "sg:orig_category":"RESTAURANTS: TEA-ROOMS",
    "sg:phone":"+41 81 735 28 73",
    "sg:postcode":"8880",
    "sg:province":"St. Gallen",
    "wof:name":"Rest. Ochsen Rolf Heiniger",
    "wof:placetype":"venue"
},
  "geometry": {"coordinates":[9.3144807816,47.1244468689],"type":"Point"}
}