{
  "type": "Feature",
  "properties": {
    "iso:country":"CH",
    "sg:address":"Schulstrasse 11",
    "sg:city":"Rheinau",
    "sg:orig_category":"Landesverteidigung, Sozialversicherung \u00d6ffentliche Verwaltung",
    "sg:phone":"+41 52 319 13 68",
    "sg:postcode":"8462",
    "sg:province":"Z\u00fcrich",
    "wof:name":"Zivilschutzstelle Rheinau",
    "wof:placetype":"venue"
},
  "geometry": {"coordinates":[8.601729393,47.6433982849],"type":"Point"}
}