{
  "type": "Feature",
  "properties": {
    "iso:country":"CH",
    "sg:address":"Via Muggina 21",
    "sg:city":"Viganello",
    "sg:orig_category":"Grosshandel mit Parf\u00fcmerieartikeln U K\u00f6rperpflegemitteln Herstellung von Duft U K\u00f6rperpflegemitteln",
    "sg:phone":"+41 62 961 75 38",
    "sg:postcode":"6962",
    "sg:province":"Ticino",
    "wof:name":"Trias Bigler & Co",
    "wof:placetype":"venue"
},
  "geometry": {"coordinates":[7.6635460854,47.1924057007],"type":"Point"}
}