{
  "type": "Feature",
  "properties": {
    "iso:country":"CH",
    "sg:address":"8965",
    "sg:city":"Berikon",
    "sg:orig_category":"Sportvereine Turnen Vereine Damen",
    "sg:phone":"+41 56 633 96 40",
    "sg:postcode":"8965",
    "sg:province":"Aargau",
    "wof:name":"Damenriege Tsv Berikon",
    "wof:placetype":"venue"
},
  "geometry": {"coordinates":[8.3731718063,47.3499565125],"type":"Point"}
}