{
  "type": "Feature",
  "properties": {
    "iso:country":"CH",
    "sg:address":"Via Giuseppe Bagutti 2 6900 Lugano. Postfach",
    "sg:city":"Lugano",
    "sg:orig_category":"Herstellung von Anstrichmitteln, Druckfarben U Kitten",
    "sg:postcode":"6900",
    "sg:province":"Ticino",
    "wof:name":"Nesa Tiziano Sagl Colori, Vernici Ecc.; Comm.",
    "wof:placetype":"venue"
},
  "geometry": {"coordinates":[8.9558820724,46.0116920471],"type":"Point"}
}