{
  "type": "Feature",
  "properties": {
    "iso:country":"CH",
    "sg:address":"Im Oberen Boden 11",
    "sg:city":"Z\u00fcrich",
    "sg:orig_category":"Dienstleistungen von Beteiligungsgesellschaften",
    "sg:postcode":"8049",
    "sg:province":"Z\u00fcrich",
    "wof:name":"Der Geistige Rat Der Baha'i Von Z\u00fcrich",
    "wof:placetype":"venue"
},
  "geometry": {"coordinates":[8.4811983109,47.4158668518],"type":"Point"}
}