{
  "type": "Feature",
  "properties": {
    "iso:country":"CH",
    "sg:address":"Benkenstrasse 15",
    "sg:city":"Therwil",
    "sg:orig_category":"Malerei-Gipserei Stukkateurgewerbe, Gipserei U Verputzerei",
    "sg:phone":"+41 61 721 28 23",
    "sg:postcode":"4106",
    "sg:province":"Basel-Landschaft",
    "wof:name":"Emil Erzer Gipsergesch\u00e4ft",
    "wof:placetype":"venue"
},
  "geometry": {"coordinates":[7.5498170853,47.4987754822],"type":"Point"}
}