{
  "type": "Feature",
  "properties": {
    "iso:country":"CH",
    "sg:address":"Wiesentalstrasse 78",
    "sg:city":"Uzwil",
    "sg:orig_category":"Detailhandel mit Fleisch U Fleischwaren",
    "sg:phone":"+41 71 951 58 42",
    "sg:postcode":"9240",
    "sg:province":"St. Gallen",
    "wof:name":"Hans Vetsch Metzgerei",
    "wof:placetype":"venue"
},
  "geometry": {"coordinates":[9.1351776123,47.4348182678],"type":"Point"}
}