{
  "type": "Feature",
  "properties": {
    "iso:country":"CH",
    "sg:address":"Ponte Tresa Via 28",
    "sg:city":"Sorengo",
    "sg:orig_category":"Vermietung U Verpachtung von eigenen Immobilien",
    "sg:postcode":"6924",
    "sg:province":"Ticino",
    "wof:name":"Imso Sa",
    "wof:placetype":"venue"
},
  "geometry": {"coordinates":[8.9349870682,45.9967346191],"type":"Point"}
}