{
  "type": "Feature",
  "properties": {
    "iso:country":"CH",
    "sg:address":"Waldhofstrasse 9",
    "sg:city":"Rheinfelden",
    "sg:orig_category":"Wirtschaftspr\u00fcfung, Steuerberatung U Treuhand",
    "sg:phone":"+41 61 811 49 91",
    "sg:postcode":"4310",
    "sg:province":"Aargau",
    "wof:name":"Bb Consult Gmbh",
    "wof:placetype":"venue"
},
  "geometry": {"coordinates":[7.7694129944,47.5477981567],"type":"Point"}
}