{
  "type": "Feature",
  "properties": {
    "iso:country":"CH",
    "sg:address":"Ch. Du Stand 1040 Echallens Case Postale",
    "sg:city":"Echallens",
    "sg:orig_category":"K\u00fcnstlerische U schriftstellerische T\u00e4tigkeiten U Darbietungen",
    "sg:phone":"+41 21 881 23 86",
    "sg:postcode":"1040",
    "sg:province":"Vaud",
    "wof:name":"Musique Et Vari\u00e9t\u00e9s Meier J. P. Agence Artistique Pour Le Placement D'orchestres Et Artistes De Vari\u00e9t\u00e9s",
    "wof:placetype":"venue"
},
  "geometry": {"coordinates":[6.6408371925,46.6393203735],"type":"Point"}
}