{
  "type": "Feature",
  "properties": {
    "iso:country":"CH",
    "sg:address":"P. Del Ponte",
    "sg:city":"Arzo",
    "sg:classifiers":[
        {
            "category":"Banks & Credit Unions",
            "subcategory":"Bank",
            "type":"Services"
        }
    ],
    "sg:phone":"+41 91 646 70 21",
    "sg:postcode":"6864",
    "sg:province":"Ticino",
    "wof:name":"Raiffeisen Di Arzo",
    "wof:placetype":"venue"
},
  "geometry": {"coordinates":[8.938705,45.875237],"type":"Point"}
}