{
  "type": "Feature",
  "properties": {
    "iso:country":"CH",
    "sg:address":"Hauptstrasse 10",
    "sg:city":"Illighausen",
    "sg:orig_category":"Herstellung von Frischmilchprodukten Sonstiger Fachdetailhandel mit Nahrungsmitteln, Getr\u00e4nken U Tab",
    "sg:phone":"+41 71 688 42 48",
    "sg:postcode":"8574",
    "sg:province":"Thurgau",
    "wof:name":"Oettli Ernst Ag",
    "wof:placetype":"venue"
},
  "geometry": {"coordinates":[9.2063903809,47.6047782898],"type":"Point"}
}