{
  "type": "Feature",
  "properties": {
    "iso:country":"CH",
    "sg:address":"Masanserstrasse 4 7000 Chur. Postfach",
    "sg:city":"Chur",
    "sg:orig_category":"Zahnkliniken",
    "sg:phone":"+41 81 254 41 11",
    "sg:postcode":"7002",
    "sg:province":"Graubunden",
    "wof:name":"Schulzahnklinik Chur",
    "wof:placetype":"venue"
},
  "geometry": {"coordinates":[9.5352468491,46.8659477234],"type":"Point"}
}