{
  "type": "Feature",
  "properties": {
    "iso:country":"CH",
    "sg:address":"Klosterplatz 14",
    "sg:city":"Mariastein",
    "sg:classifiers":[
        {
            "category":"Travel",
            "subcategory":"Hotels & Motels",
            "type":"Entertainment"
        }
    ],
    "sg:phone":"+41 61 731 10 22",
    "sg:postcode":"4115",
    "sg:province":"Solothurn",
    "sg:tags":[
        "hotels",
        "mit",
        "restaurant"
    ],
    "wof:name":"Hotel Post",
    "wof:placetype":"venue"
},
  "geometry": {"coordinates":[7.4913129807,47.476474762],"type":"Point"}
}