{
  "type": "Feature",
  "properties": {
    "iso:country":"CH",
    "sg:address":"Weissensteinstrasse 15",
    "sg:city":"Solothurn",
    "sg:orig_category":"Erschliessung von Grundst\u00fccken",
    "sg:postcode":"4500",
    "sg:province":"Solothurn",
    "wof:name":"Genossenschaft H\u00fcbeliweg",
    "wof:placetype":"venue"
},
  "geometry": {"coordinates":[7.527990818,47.2112426758],"type":"Point"}
}