{
  "type": "Feature",
  "properties": {
    "iso:country":"CH",
    "sg:address":"Place Bel-air 1",
    "sg:city":"Yverdon-les-bains",
    "sg:orig_category":"Detailhandel mit Sportartikeln Herstellung von elektrischen Ausr\u00fcstungen f\u00fcr Motoren U Fahrzeuge",
    "sg:phone":"+41 24 425 57 25",
    "sg:postcode":"1400",
    "sg:province":"Vaud",
    "wof:name":"Vallotton Sport",
    "wof:placetype":"venue"
},
  "geometry": {"coordinates":[6.6368608475,46.780544281],"type":"Point"}
}