{
  "type": "Feature",
  "properties": {
    "iso:country":"CH",
    "sg:address":"Wartstrasse 31 8400 Winterthur. Postfach",
    "sg:city":"Winterthur",
    "sg:orig_category":"Non-Classified Establishments",
    "sg:postcode":"8400",
    "sg:province":"Z\u00fcrich",
    "wof:name":"4ward-webdesign Gmbh",
    "wof:placetype":"venue"
},
  "geometry": {"coordinates":[9.0720481873,46.9925193787],"type":"Point"}
}