{
  "type": "Feature",
  "properties": {
    "iso:country":"CH",
    "sg:address":"Route De B\u00e2le 128",
    "sg:city":"Del\u00e9mont",
    "sg:orig_category":"Ger\u00fcstbau Sonstiger spezialisierter Hoch U Tiefbau",
    "sg:phone":"+41 32 422 71 71",
    "sg:postcode":"2800",
    "sg:province":"Jura",
    "wof:name":"Roth Echafaudages Sa Succursale De Del\u00e9mont",
    "wof:placetype":"venue"
},
  "geometry": {"coordinates":[7.3597769737,47.3709754944],"type":"Point"}
}