{
  "type": "Feature",
  "properties": {
    "iso:country":"CH",
    "sg:address":"7250 Klosters. Postfach 219",
    "sg:city":"Klosters",
    "sg:orig_category":"Personenbef\u00f6rderung im Linienverkehr zu Land",
    "sg:phone":"+41 81 826 54 46",
    "sg:postcode":"7250",
    "sg:province":"Graubunden",
    "wof:name":"Furtschellas-bahn Ag",
    "wof:placetype":"venue"
},
  "geometry": {"coordinates":[9.764169693,46.4287605286],"type":"Point"}
}