{
  "type": "Feature",
  "properties": {
    "iso:country":"CH",
    "sg:address":"Bois-des-arts Chemin Du 77",
    "sg:city":"Th\u00f4nex",
    "sg:orig_category":"Unclassifiable Establishments",
    "sg:phone":"+41 22 349 08 87",
    "sg:postcode":"1226",
    "sg:province":"Gen\u00e8ve",
    "wof:name":"Foschia Nathalie",
    "wof:placetype":"venue"
},
  "geometry": {"coordinates":[6.1996469498,46.1886062622],"type":"Point"}
}