{
  "type": "Feature",
  "properties": {
    "iso:country":"CH",
    "sg:address":"Muttenzerstrasse 105",
    "sg:city":"Pratteln",
    "sg:orig_category":"RESTAURANTS: TEA-ROOMS",
    "sg:postcode":"4133",
    "sg:province":"Basel-Landschaft",
    "wof:name":"Thuring Sidonie Th\u00e9r\u00e8se",
    "wof:placetype":"venue"
},
  "geometry": {"coordinates":[6.1458621025,46.1836357117],"type":"Point"}
}