{
  "type": "Feature",
  "properties": {
    "iso:country":"CH",
    "sg:address":"M\u00fchlebachstrasse 49",
    "sg:city":"Thalwil",
    "sg:orig_category":"Wirtschaftspr\u00fcfung, Steuerberatung U Treuhand",
    "sg:phone":"+41 17721035",
    "sg:postcode":"8800",
    "sg:province":"Z\u00fcrich",
    "wof:name":"Aiutaria Fiduciaire",
    "wof:placetype":"venue"
},
  "geometry": {"coordinates":[8.5660123825,47.2920722961],"type":"Point"}
}