{
  "type": "Feature",
  "properties": {
    "iso:country":"CH",
    "sg:address":"Ygrubenstrasse",
    "sg:city":"Glarus",
    "sg:orig_category":"Grosshandel mit festen Brennstoffen U Mineral\u00f6lerzeugnissen",
    "sg:phone":"+41 79 437 81 45",
    "sg:postcode":"8750",
    "sg:province":"Glarus",
    "wof:name":"Sudero Gianni",
    "wof:placetype":"venue"
},
  "geometry": {"coordinates":[8.9985790253,47.4774475098],"type":"Point"}
}