{
  "type": "Feature",
  "properties": {
    "iso:country":"CH",
    "sg:address":"Badenerstrasse 362",
    "sg:city":"Z\u00fcrich",
    "sg:orig_category":"Unternehmensberatung",
    "sg:phone":"+41 14010700",
    "sg:postcode":"8004",
    "sg:province":"Z\u00fcrich",
    "wof:name":"Isler Max, Consulting",
    "wof:placetype":"venue"
},
  "geometry": {"coordinates":[8.5095205307,47.3788375854],"type":"Point"}
}