{
  "type": "Feature",
  "properties": {
    "iso:country":"CH",
    "sg:address":"Fabrikstrasse 28 8854 Siebnen. Postfach",
    "sg:city":"Siebnen",
    "sg:orig_category":"Herstellung von Elektromotoren, Generatoren U Transformatoren",
    "sg:phone":"+41 55 440 18 21",
    "sg:postcode":"8854",
    "sg:province":"Schwyz",
    "wof:name":"Ew Wirth Ag",
    "wof:placetype":"venue"
},
  "geometry": {"coordinates":[8.8963603973,47.1754112244],"type":"Point"}
}