{
  "type": "Feature",
  "properties": {
    "iso:country":"CH",
    "sg:address":"Chailly Avenue De 7 1012 Lausanne. Postfach",
    "sg:city":"Lausanne",
    "sg:orig_category":"Vermietung von Gebrauchsg\u00fctern",
    "sg:postcode":"1003",
    "sg:province":"Vaud",
    "wof:name":"Vid\u00e9o Club Ascort",
    "wof:placetype":"venue"
},
  "geometry": {"coordinates":[3.4919900894,47.9411315918],"type":"Point"}
}