{
  "type": "Feature",
  "properties": {
    "iso:country":"CH",
    "sg:address":"Houelbachstrasse 3 6010 Kriens. Postfach",
    "sg:city":"Kriens",
    "sg:orig_category":"Vermietung U Verpachtung von eigenen Immobilien",
    "sg:postcode":"6010",
    "sg:province":"Luzern",
    "wof:name":"Waldig Bau Ag Immobilien; Kauf, Verkauf, Vermittlung, Verwaltung Usw",
    "wof:placetype":"venue"
},
  "geometry": {"coordinates":[8.270775795,47.0308876038],"type":"Point"}
}