{
  "type": "Feature",
  "properties": {
    "iso:country":"CH",
    "sg:address":"Chandolan Route De 8 1752 Villars-sur-gl\u00e2ne Case Postale 196",
    "sg:city":"Villars-sur-gl\u00e2ne",
    "sg:orig_category":"Non-Classified Establishments",
    "sg:phone":"+41 26 322 26 17",
    "sg:postcode":"1752",
    "sg:province":"Fribourg",
    "wof:name":"Van Cleef & Arpels Holdings Switzerland Sa",
    "wof:placetype":"venue"
},
  "geometry": {"coordinates":[7.1175031662,46.8008422852],"type":"Point"}
}