{
  "type": "Feature",
  "properties": {
    "iso:country":"CH",
    "sg:address":"Alte Strasse 3713 Reichenbach I. K.. Postfach",
    "sg:city":"Frutigen",
    "sg:orig_category":"Schlachten ohne Schlachten von Gefl\u00fcgel Schlachth\u00e4user",
    "sg:phone":"+41 33 676 22 16",
    "sg:postcode":"3714",
    "sg:province":"Bern",
    "wof:name":"Frutigland Fleisch Ag Schlachten Von Nutztieren, Verarbeitung Von Bankw\u00fcrdigem Fleisch Usw",
    "wof:placetype":"venue"
},
  "geometry": {"coordinates":[7.6837968826,46.6206626892],"type":"Point"}
}