{
  "type": "Feature",
  "properties": {
    "iso:country":"CH",
    "sg:address":"Via Malpensata",
    "sg:city":"Novazzano",
    "sg:orig_category":"G\u00fcterbef\u00f6rderung im Strassenverkehr",
    "sg:postcode":"6883",
    "sg:province":"Ticino",
    "wof:name":"Angelo Raetzo Ag",
    "wof:placetype":"venue"
},
  "geometry": {"coordinates":[7.2608799934,46.8221817017],"type":"Point"}
}