{
  "type": "Feature",
  "properties": {
    "iso:country":"CH",
    "sg:address":"B\u00fcrgenstockstrasse 2",
    "sg:city":"Ennetb\u00fcrgen",
    "sg:orig_category":"Weiterbildungskurse and Seminar Anbieter",
    "sg:phone":"+41 41 624 44 44",
    "sg:postcode":"6373",
    "sg:province":"Nidwalden",
    "wof:name":"Odermatt Peter Management Ag Management-seminare",
    "wof:placetype":"venue"
},
  "geometry": {"coordinates":[8.4135103226,46.985370636],"type":"Point"}
}