{
  "type": "Feature",
  "properties": {
    "iso:country":"CH",
    "sg:address":"Canevascini Via G. 19",
    "sg:city":"Locarno",
    "sg:orig_category":"G\u00fcterbef\u00f6rderung im Strassenverkehr",
    "sg:phone":"+41 14815869",
    "sg:postcode":"6600",
    "sg:province":"Ticino",
    "wof:name":"Tsd Trasporti St\u00f6pfer",
    "wof:placetype":"venue"
},
  "geometry": {"coordinates":[8.8003940582,46.1705741882],"type":"Point"}
}