{
  "type": "Feature",
  "properties": {
    "iso:country":"CH",
    "sg:address":"Industriestrasse 2 2552 Orpund. Postfach 182",
    "sg:city":"Orpund",
    "sg:orig_category":"Elektroinstallation",
    "sg:phone":"+41 32 344 01 01",
    "sg:postcode":"2552",
    "sg:province":"Bern",
    "wof:name":"Fischer Electric Ag F\u00fcr Elektrotechnische Anlagen",
    "wof:placetype":"venue"
},
  "geometry": {"coordinates":[7.2853679657,47.1416130066],"type":"Point"}
}