{
  "type": "Feature",
  "properties": {
    "iso:country":"CH",
    "sg:address":"Schawandistr. 29",
    "sg:city":"Frutigen",
    "sg:classifiers":[
        {
            "category":"Autos & Motor Vehicles",
            "subcategory":"Automobile Sales",
            "type":"Retail Goods"
        }
    ],
    "sg:phone":"+41 33 671 31 33",
    "sg:postcode":"3714",
    "sg:province":"Bern",
    "sg:tags":[
        "equipment",
        "transport"
    ],
    "wof:name":"B\u00c4rtschi Bau Ag",
    "wof:placetype":"venue"
},
  "geometry": {"coordinates":[7.6600031853,46.5918502808],"type":"Point"}
}