{
  "type": "Feature",
  "properties": {
    "iso:country":"CH",
    "sg:address":"Oberdorf",
    "sg:city":"Wilderswil",
    "sg:orig_category":"Maler U Glasergewerbe Malerei",
    "sg:phone":"+41 79 342 11 74",
    "sg:postcode":"3812",
    "sg:province":"Bern",
    "wof:name":"Pfister Martin, Malergesch\u00e4ft",
    "wof:placetype":"venue"
},
  "geometry": {"coordinates":[7.857626915,46.6645393372],"type":"Point"}
}