{
  "type": "Feature",
  "properties": {
    "iso:country":"CH",
    "sg:address":"Frauenfelderstrasse 68 8404 Oberwinterthur. Postfach 765",
    "sg:city":"Winterthur",
    "sg:orig_category":"K\u00fcnstlerische U schriftstellerische T\u00e4tigkeiten U Darbietungen",
    "sg:phone":"+41 52 222 39 60",
    "sg:postcode":"8404",
    "sg:province":"Z\u00fcrich",
    "wof:name":"Albanese Domenico, Live Music Edizioni",
    "wof:placetype":"venue"
},
  "geometry": {"coordinates":[8.7544660568,47.5046615601],"type":"Point"}
}