{
  "type": "Feature",
  "properties": {
    "iso:country":"CH",
    "sg:address":"Rue Du Valentin 56",
    "sg:city":"Yverdon-les-bains",
    "sg:orig_category":"Grosshandel mit Eisenwaren sowie Installationsbedarf f\u00fcr Gas, Wasser U Heizung Herstellung von \u00d6fen ",
    "sg:phone":"+41 24 426 27 11",
    "sg:postcode":"1400",
    "sg:province":"Vaud",
    "wof:name":"Gendroz Sa Appareils M\u00e9nagers; Commerce, R\u00e9paration",
    "wof:placetype":"venue"
},
  "geometry": {"coordinates":[6.6410899162,46.7752227783],"type":"Point"}
}