{
  "type": "Feature",
  "properties": {
    "iso:country":"CH",
    "sg:address":"Montfleury Chemin De 1",
    "sg:city":"Versoix",
    "sg:orig_category":"Kinderg\u00e4rten, Vor U Grundschulen",
    "sg:postcode":"1290",
    "sg:province":"Gen\u00e8ve",
    "wof:name":"Fondation Communale Du Grand-saconnex Pour La Petite Enfance",
    "wof:placetype":"venue"
},
  "geometry": {"coordinates":[6.1259880066,46.2352104187],"type":"Point"}
}