{
  "type": "Feature",
  "properties": {
    "iso:country":"CH",
    "sg:address":"Obere Halten",
    "sg:city":"Emmen",
    "sg:orig_category":"Gemischte Landwirtschaft",
    "sg:phone":"+41 41 280 74 43",
    "sg:postcode":"6032",
    "sg:province":"Luzern",
    "wof:name":"Genossenschaft Oberwolfisb\u00fchl",
    "wof:placetype":"venue"
},
  "geometry": {"coordinates":[8.2831707001,47.088218689],"type":"Point"}
}