{
  "type": "Feature",
  "properties": {
    "iso:country":"CH",
    "sg:address":"Sonneggstrasse 4",
    "sg:city":"Olten",
    "sg:orig_category":"Herstellung von Elektromotoren, Generatoren U Transformatoren",
    "sg:postcode":"4600",
    "sg:province":"Solothurn",
    "wof:name":"Ingenieurgemeinschaft Energietechnik Gmbh Energietechnische Anlagen; Beratung, Planung U. Ausf\u00fchrung",
    "wof:placetype":"venue"
},
  "geometry": {"coordinates":[9.3807353973,47.4299201965],"type":"Point"}
}