{
  "type": "Feature",
  "properties": {
    "iso:country":"CH",
    "sg:address":"Dorfstrasse 15",
    "sg:city":"Oberegg",
    "sg:classifiers":[
        {
            "category":"Restaurant",
            "type":"Food & Drink"
        }
    ],
    "sg:phone":"+41 71 891 19 35",
    "sg:postcode":"9413",
    "sg:province":"Appenzell Innerhoden",
    "wof:name":"Bistro S\u00e4ntis",
    "wof:placetype":"venue"
},
  "geometry": {"coordinates":[9.5518693924,47.42237854],"type":"Point"}
}