{
  "type": "Feature",
  "properties": {
    "addr:full":"Bahnhofstrasse Grenchen Solothurn 2540",
    "addr:postcode":"2540",
    "addr:street":"Bahnhofstrasse",
    "iso:country":"CH",
    "sg:address":"Bahnhofstrasse",
    "sg:city":"Grenchen",
    "sg:orig_category":"Aktivit\u00e4t der Bankinstitute",
    "sg:phone":"+41 32 654 58 58",
    "sg:postcode":"2540",
    "sg:province":"Solothurn",
    "wof:name":"Migrosbank Mmm Grenchen",
    "wof:placetype":"venue"
},
  "geometry": {"coordinates":[7.396014,47.191463],"type":"Point"}
}