{
  "type": "Feature",
  "properties": {
    "iso:country":"CH",
    "sg:address":"Alpenstrasse 12",
    "sg:city":"Zug",
    "sg:orig_category":"Non-Classified Establishments",
    "sg:postcode":"6300",
    "sg:province":"Zug",
    "wof:name":"Edfor Holding Ag",
    "wof:placetype":"venue"
},
  "geometry": {"coordinates":[8.5149440765,47.1725082397],"type":"Point"}
}