{
  "type": "Feature",
  "properties": {
    "iso:country":"CH",
    "sg:address":"Ribeliweg 2",
    "sg:city":"Wiedlisbach",
    "sg:orig_category":"Betrieb U technische Hilfsdienste des Kultur U Unterhaltungswesens",
    "sg:postcode":"4537",
    "sg:province":"Bern",
    "wof:name":"Kms Kulturmanagement Ag",
    "wof:placetype":"venue"
},
  "geometry": {"coordinates":[7.646687,47.250912],"type":"Point"}
}