{
  "type": "Feature",
  "properties": {
    "iso:country":"CH",
    "sg:address":"Bahnhofstrasse 53",
    "sg:city":"D\u00fcbendorf",
    "sg:orig_category":"Reiseb\u00fcros",
    "sg:phone":"+41 18210055",
    "sg:postcode":"8600",
    "sg:province":"Z\u00fcrich",
    "wof:name":"Imholz Reisen",
    "wof:placetype":"venue"
},
  "geometry": {"coordinates":[8.6216335297,47.3995819092],"type":"Point"}
}