{
  "type": "Feature",
  "properties": {
    "iso:country":"CH",
    "sg:address":"7173",
    "sg:city":"Surrein",
    "sg:orig_category":"Bauschreinerei Herstellung von Konstruktionsteilen, Fertigbauteilen U Ausbauelementen aus Holz",
    "sg:phone":"+41 81 943 23 66",
    "sg:postcode":"7173",
    "sg:province":"Graubunden",
    "wof:name":"Bundi Robert Sa",
    "wof:placetype":"venue"
},
  "geometry": {"coordinates":[8.95137,46.722801],"type":"Point"}
}