{
  "type": "Feature",
  "properties": {
    "iso:country":"CH",
    "sg:address":"Milit\u00e4rstrasse 84",
    "sg:city":"Z\u00fcrich",
    "sg:orig_category":"Reiseb\u00fcros U Reiseveranstalter",
    "sg:phone":"+41 12405544",
    "sg:postcode":"8004",
    "sg:province":"Z\u00fcrich",
    "wof:name":"Mondial Travel Reisen Und Veranstaltungen",
    "wof:placetype":"venue"
},
  "geometry": {"coordinates":[8.5295591354,47.3785591125],"type":"Point"}
}