{
  "type": "Feature",
  "properties": {
    "iso:country":"CH",
    "sg:address":"Horn",
    "sg:city":"Sumiswald",
    "sg:orig_category":"Verwertung von Milch",
    "sg:postcode":"3454",
    "sg:province":"Bern",
    "wof:name":"K\u00e4sereigenossenschaft Horrenbach-reust",
    "wof:placetype":"venue"
},
  "geometry": {"coordinates":[7.7515201569,46.779258728],"type":"Point"}
}