{
  "type": "Feature",
  "properties": {
    "iso:country":"CH",
    "sg:address":"Villa La Sage",
    "sg:city":"Evol\u00e8ne",
    "sg:orig_category":"RESTAURANTS: TEA-ROOMS",
    "sg:postcode":"1983",
    "sg:province":"Valais",
    "wof:name":"Maistre-forclaz, Veuve Jean",
    "wof:placetype":"venue"
},
  "geometry": {"coordinates":[7.5161571503,46.1043891907],"type":"Point"}
}