{
  "type": "Feature",
  "properties": {
    "addr:full":"Hauptstrasse 266 B\u00f6zen Aargau 5076",
    "addr:housenumber":"266",
    "addr:postcode":"5076",
    "addr:street":"Hauptstrasse",
    "iso:country":"CH",
    "sg:address":"Hauptstrasse 266",
    "sg:city":"B\u00f6zen",
    "sg:orig_category":"Abfallbeseitigung G\u00fcterbef\u00f6rderung im Strassenverkehr",
    "sg:phone":"+41 62 876 11 18",
    "sg:postcode":"5076",
    "sg:province":"Aargau",
    "wof:name":"Peter Pfister Ag Kehrichtabfuhr Kippertransport",
    "wof:placetype":"venue"
},
  "geometry": {"coordinates":[8.083139,47.495064],"type":"Point"}
}