{
  "type": "Feature",
  "properties": {
    "iso:country":"CH",
    "sg:address":"Schlossergasse 1",
    "sg:city":"Sch\u00f6tz",
    "sg:orig_category":"Detailhandel mit elektrischen Haushalts-,Radio U Fernsehger\u00e4ten sowie Musikinstrumenten",
    "sg:phone":"+41 41 980 43 66",
    "sg:postcode":"6247",
    "sg:province":"Luzern",
    "wof:name":"Im Egge Haushalts Und Eisenwaren Linggi",
    "wof:placetype":"venue"
},
  "geometry": {"coordinates":[7.987156868,47.1701469421],"type":"Point"}
}