{
  "type": "Feature",
  "properties": {
    "iso:country":"CH",
    "sg:address":"P\u00fcntstrasse 9",
    "sg:city":"Maur",
    "sg:orig_category":"Sonstige mit der Informatik verbundene T\u00e4tigkeiten",
    "sg:phone":"+41 76 399 15 87",
    "sg:postcode":"8124",
    "sg:province":"Z\u00fcrich",
    "wof:name":"Dkp Beratung D. Grond",
    "wof:placetype":"venue"
},
  "geometry": {"coordinates":[8.6886901855,47.3268814087],"type":"Point"}
}