{
  "type": "Feature",
  "properties": {
    "iso:country":"CH",
    "sg:address":"R\u00f6rswilstrasse 59 3065 Bolligen. Postfach 457",
    "sg:city":"Bolligen",
    "sg:orig_category":"Grosshandel mit sonstigen Halbwaren Grosshandel mit sonstigen Maschinen U Ausr\u00fcstungen f\u00fcr Industrie",
    "sg:phone":"+41 31 381 60 66",
    "sg:postcode":"3065",
    "sg:province":"Bern",
    "wof:name":"Mapag Maschinen Ag",
    "wof:placetype":"venue"
},
  "geometry": {"coordinates":[7.4118590355,46.9421920776],"type":"Point"}
}