{
  "type": "Feature",
  "properties": {
    "iso:country":"CH",
    "sg:address":"Chemin De La Roche 15 1091 Grandvaux. Postfach",
    "sg:city":"Grandvaux",
    "sg:orig_category":"Vermietung U Verpachtung von eigenen Immobilien",
    "sg:postcode":"1091",
    "sg:province":"Vaud",
    "wof:name":"Algima Sa",
    "wof:placetype":"venue"
},
  "geometry": {"coordinates":[6.7180228233,46.5018615723],"type":"Point"}
}