{
  "type": "Feature",
  "properties": {
    "iso:country":"CH",
    "sg:address":"Rue De Bourg 43",
    "sg:city":"Lausanne",
    "sg:orig_category":"Versicherungen Generalagenturen",
    "sg:phone":"+41 21 323 48 48",
    "sg:postcode":"1003",
    "sg:province":"Vaud",
    "wof:name":"Phenix Assurances Agence G\u00e9n\u00e9rale",
    "wof:placetype":"venue"
},
  "geometry": {"coordinates":[6.6361532211,46.5200576782],"type":"Point"}
}