{
  "type": "Feature",
  "properties": {
    "iso:country":"CH",
    "sg:address":"Pilgerweg 29 8803 R\u00fcschlikon. Postfach",
    "sg:city":"R\u00fcschlikon",
    "sg:orig_category":"Landesverteidigung, Sozialversicherung \u00d6ffentliche Verwaltung",
    "sg:phone":"+41 55 251 32 80",
    "sg:postcode":"8803",
    "sg:province":"Z\u00fcrich",
    "wof:name":"Zivilschutzstelle R\u00fcti",
    "wof:placetype":"venue"
},
  "geometry": {"coordinates":[8.8503112793,47.2565078735],"type":"Point"}
}