{
  "type": "Feature",
  "properties": {
    "iso:country":"CH",
    "sg:address":"Hochbergerstr. 15",
    "sg:city":"Basel",
    "sg:classifiers":[
        {
            "category":"Professional",
            "subcategory":"Printing & Photocopies",
            "type":"Services"
        }
    ],
    "sg:phone":"+41 61 639 10 30",
    "sg:postcode":"4002",
    "sg:province":"Basel-Stadt",
    "sg:tags":[
        "publishing"
    ],
    "wof:name":"Rittmann Ag",
    "wof:placetype":"venue"
},
  "geometry": {"coordinates":[7.5975160599,47.5763092041],"type":"Point"}
}