{
  "type": "Feature",
  "properties": {
    "iso:country":"CH",
    "sg:address":"Rue Centrale 1884 Villars-sur-ollon Case Postale 133",
    "sg:city":"Villars-sur-ollon",
    "sg:orig_category":"Personenbef\u00f6rderung im Linienverkehr zu Land",
    "sg:phone":"+41 24 492 32 92",
    "sg:postcode":"1884",
    "sg:province":"Vaud",
    "wof:name":"T\u00e9l\u00e9cabine Les Diablerets-isenau Sa",
    "wof:placetype":"venue"
},
  "geometry": {"coordinates":[7.1587119102,46.3500404358],"type":"Point"}
}