{
  "type": "Feature",
  "properties": {
    "iso:country":"CH",
    "sg:address":"F\u00f6hrenstrasse 5a",
    "sg:city":"St.gallen",
    "sg:orig_category":"Unclassifiable Establishments",
    "sg:postcode":"9000",
    "sg:province":"St. Gallen",
    "wof:name":"Yeeon - Gr\u00fcnes Atelier Marianne Schwizer",
    "wof:placetype":"venue"
},
  "geometry": {"coordinates":[9.3508558273,47.418346405],"type":"Point"}
}