{
  "type": "Feature",
  "properties": {
    "iso:country":"CH",
    "sg:address":"Rue Des Pr\u00e9s 17",
    "sg:city":"Reconvilier",
    "sg:classifiers":[
        {
            "category":"Insurance",
            "subcategory":"Insurance Agent",
            "type":"Services"
        }
    ],
    "sg:phone":"+41 79 455 66 71",
    "sg:postcode":"2732",
    "sg:province":"Bern",
    "sg:tags":[
        "versicherungsagenturen",
        "-broker"
    ],
    "wof:name":"Raymond Rohrbach Cons.en Pr\u00e9voyance Rentenanst.",
    "wof:placetype":"venue"
},
  "geometry": {"coordinates":[7.2216100693,47.2328033447],"type":"Point"}
}