{
  "type": "Feature",
  "properties": {
    "iso:country":"CH",
    "sg:address":"Manessestrasse 36",
    "sg:city":"Z\u00fcrich",
    "sg:orig_category":"Vermietung U Verpachtung von eigenen Immobilien",
    "sg:postcode":"8003",
    "sg:province":"Z\u00fcrich",
    "wof:name":"Mersini Immobilien",
    "wof:placetype":"venue"
},
  "geometry": {"coordinates":[8.523976326,47.368396759],"type":"Point"}
}