{
  "type": "Feature",
  "properties": {
    "iso:country":"CH",
    "sg:address":"Thiersteinerallee 87",
    "sg:city":"Basel",
    "sg:orig_category":"Erbringung von Dienstleistungen f\u00fcr Unternehmen",
    "sg:phone":"+41 61 332 01 86",
    "sg:postcode":"4053",
    "sg:province":"Basel-Stadt",
    "wof:name":"Karosatz Karoline Hafner",
    "wof:placetype":"venue"
},
  "geometry": {"coordinates":[7.596818924,47.5396652222],"type":"Point"}
}