{
  "type": "Feature",
  "properties": {
    "iso:country":"CH",
    "sg:address":"7228",
    "sg:city":"Schuders",
    "sg:orig_category":"Sportvereine Sch\u00fctzen",
    "sg:phone":"+41 81 641 32 88",
    "sg:postcode":"7228",
    "sg:province":"Graubunden",
    "wof:name":"Sch\u00fctzenverein",
    "wof:placetype":"venue"
},
  "geometry": {"coordinates":[9.7384500504,46.992099762],"type":"Point"}
}