{
  "type": "Feature",
  "properties": {
    "iso:country":"CH",
    "sg:address":"Am Suteracher 92",
    "sg:city":"Z\u00fcrich",
    "sg:orig_category":"Organisationen des Gesundheitswesen",
    "sg:postcode":"8048",
    "sg:province":"Z\u00fcrich",
    "wof:name":"Samariterverein Avers",
    "wof:placetype":"venue"
},
  "geometry": {"coordinates":[9.5131464005,46.4727554321],"type":"Point"}
}