{
  "type": "Feature",
  "properties": {
    "addr:full":"Route De Belfort 10 2900 Porrentruy Case Postale Porrentruy Jura 2900",
    "addr:housenumber":"10",
    "addr:postcode":"2900;2900",
    "addr:street":"Route De Belfort;Case Postale;Jura",
    "iso:country":"CH",
    "sg:address":"Route De Belfort 10 2900 Porrentruy Case Postale",
    "sg:city":"Porrentruy",
    "sg:orig_category":"Allgemeinbildende weiterf\u00fchrende Schulen Primarschulen",
    "sg:phone":"+41 21 944 53 04",
    "sg:postcode":"2900",
    "sg:province":"Jura",
    "wof:name":"Ecole Blancpain Sa",
    "wof:placetype":"venue"
},
  "geometry": {"coordinates":[6.864664,46.455116],"type":"Point"}
}