{
  "type": "Feature",
  "properties": {
    "iso:country":"CH",
    "sg:address":"Witikonerstrasse 385 8000 Z\u00fcrich. Postfach",
    "sg:city":"Z\u00fcrich",
    "sg:orig_category":"RESTAURANTS: TEA-ROOMS",
    "sg:postcode":"8053",
    "sg:province":"Z\u00fcrich",
    "wof:name":"Sfs Gastro Gmbh",
    "wof:placetype":"venue"
},
  "geometry": {"coordinates":[8.5740203857,47.3616790771],"type":"Point"}
}