{
  "type": "Feature",
  "properties": {
    "iso:country":"CH",
    "sg:address":"Im Hof 6",
    "sg:city":"Romanshorn",
    "sg:orig_category":"Handel mit Motorr\u00e4dern, Teilen U Zubeh\u00f6r Instandhaltung U Reparatur von Motorr\u00e4dern",
    "sg:phone":"+41 71 463 34 24",
    "sg:postcode":"8590",
    "sg:province":"Thurgau",
    "wof:name":"Mofa-fan-shop Ag",
    "wof:placetype":"venue"
},
  "geometry": {"coordinates":[9.3669595718,47.5577316284],"type":"Point"}
}