{
  "type": "Feature",
  "properties": {
    "iso:country":"CH",
    "sg:address":"Bahnhofstrasse 148",
    "sg:city":"M\u00f6hlin",
    "sg:orig_category":"Grosshandel mit Nahrungsmitteln, Getr\u00e4nken U Tabakwaren ohne ausgepr\u00e4gten Schwerpunkt",
    "sg:phone":"+41 61 851 09 31",
    "sg:postcode":"4313",
    "sg:province":"Aargau",
    "wof:name":"Mini Market Sena Nuhija Sefedin",
    "wof:placetype":"venue"
},
  "geometry": {"coordinates":[7.8500270844,47.5533256531],"type":"Point"}
}