{
  "type": "Feature",
  "properties": {
    "iso:country":"CH",
    "sg:address":"Henneb\u00fcelweg 24",
    "sg:city":"Trimbach",
    "sg:orig_category":"Betrieb von Sportanlagen",
    "sg:phone":"+41 62 293 00 01",
    "sg:postcode":"4632",
    "sg:province":"Solothurn",
    "wof:name":"Ga Golfing Gmbh",
    "wof:placetype":"venue"
},
  "geometry": {"coordinates":[7.893037796,47.3681602478],"type":"Point"}
}