{
  "type": "Feature",
  "properties": {
    "iso:country":"CH",
    "sg:address":"Leutenegg",
    "sg:city":"Sch\u00f6nholzerswilen",
    "sg:orig_category":"Verwertung von Milch",
    "sg:postcode":"8577",
    "sg:province":"Thurgau",
    "wof:name":"K\u00e4sereigesellschaft Nesslau",
    "wof:placetype":"venue"
},
  "geometry": {"coordinates":[9.1993598938,47.2241897583],"type":"Point"}
}