{
  "type": "Feature",
  "properties": {
    "iso:country":"CH",
    "sg:address":"Buchholzstrasse 15a 3600 Thun. Postfach",
    "sg:city":"Thun",
    "sg:orig_category":"Erschliessung von Grundst\u00fccken",
    "sg:postcode":"3604",
    "sg:province":"Bern",
    "wof:name":"Gemeinn\u00fctzige Bau Und Wohngenossenschaft Freistatt Thun (gbwg Freistatt Thun)",
    "wof:placetype":"venue"
},
  "geometry": {"coordinates":[7.6097898483,46.7300643921],"type":"Point"}
}