{
  "type": "Feature",
  "properties": {
    "iso:country":"CH",
    "sg:address":"Gerbergasse 41 4001 Basel. Postfach",
    "sg:city":"Basel",
    "sg:orig_category":"Detailhandel mit Uhren U Schmuck",
    "sg:phone":"+41 61 261 99 66",
    "sg:postcode":"4001",
    "sg:province":"Basel-Stadt",
    "wof:name":"Goldl\u00e4deli Ag",
    "wof:placetype":"venue"
},
  "geometry": {"coordinates":[7.5887169838,47.5560951233],"type":"Point"}
}