{
  "type": "Feature",
  "properties": {
    "iso:country":"CH",
    "sg:address":"Mayenfelserstrasse 46",
    "sg:city":"Pratteln",
    "sg:orig_category":"Sportvereine Ballsport Tennis",
    "sg:phone":"+41 62 291 22 73",
    "sg:postcode":"4133",
    "sg:province":"Basel-Landschaft",
    "wof:name":"Tc Ptt Aarau",
    "wof:placetype":"venue"
},
  "geometry": {"coordinates":[7.9879260063,47.3481216431],"type":"Point"}
}