{
  "type": "Feature",
  "properties": {
    "addr:full":"Casa Glix Andiast Graubunden 7159",
    "addr:housenumber":"7159",
    "iso:country":"CH",
    "sg:address":"Casa Glix",
    "sg:city":"Andiast",
    "sg:orig_category":"Allgemeiner Hoch U Tiefbau Allgemeiner Hochbau",
    "sg:phone":"+41 79 207 75 55",
    "sg:postcode":"7159",
    "sg:province":"Graubunden",
    "wof:name":"Spescha Gmbh",
    "wof:placetype":"venue"
},
  "geometry": {"coordinates":[9.11432,46.784595],"type":"Point"}
}