{
  "type": "Feature",
  "properties": {
    "iso:country":"CH",
    "sg:address":"Dorf",
    "sg:city":"Sigriswil",
    "sg:orig_category":"Reiseb\u00fcros U Reiseveranstalter",
    "sg:phone":"+41 71 630 02 31",
    "sg:postcode":"3655",
    "sg:province":"Bern",
    "wof:name":"Hans Kaufmann Touristikberatung",
    "wof:placetype":"venue"
},
  "geometry": {"coordinates":[9.1568994522,47.5465126038],"type":"Point"}
}