{
  "type": "Feature",
  "properties": {
    "iso:country":"CH",
    "sg:address":"Rorschacher Strasse 7 8424 Embrach. Postfach 194",
    "sg:city":"Embrach",
    "sg:orig_category":"Interessenvertretungen",
    "sg:phone":"+41 18653933",
    "sg:postcode":"8424",
    "sg:province":"Z\u00fcrich",
    "wof:name":"Rau'sche-dr. Medizinalstiftung",
    "wof:placetype":"venue"
},
  "geometry": {"coordinates":[8.5935716629,47.506690979],"type":"Point"}
}