{
  "type": "Feature",
  "properties": {
    "iso:country":"CH",
    "sg:address":"Kohlestrasse 12a",
    "sg:city":"Schlieren",
    "sg:orig_category":"Fotografische Ateliers",
    "sg:phone":"+41 71 244 26 24",
    "sg:postcode":"8952",
    "sg:province":"Z\u00fcrich",
    "wof:name":"Hanspeter Wagner Ag",
    "wof:placetype":"venue"
},
  "geometry": {"coordinates":[9.394194603,47.4333953857],"type":"Point"}
}