{
  "type": "Feature",
  "properties": {
    "addr:full":"Kleine Allmend 15 Sissach Basel-Landschaft 4450",
    "addr:housenumber":"15",
    "addr:postcode":"4450",
    "addr:street":"Kleine Allmend",
    "iso:country":"CH",
    "sg:address":"Kleine Allmend 15",
    "sg:city":"Sissach",
    "sg:orig_category":"Bauspenglerei Zimmerei, Dachdeckerei, Bauspenglerei U Abdichtung",
    "sg:phone":"+41 61 971 45 55",
    "sg:postcode":"4450",
    "sg:province":"Basel-Landschaft",
    "wof:name":"Julius Schaub Ag",
    "wof:placetype":"venue"
},
  "geometry": {"coordinates":[7.810259,47.467564],"type":"Point"}
}