{
  "type": "Feature",
  "properties": {
    "iso:country":"CH",
    "sg:address":"En Chotet",
    "sg:city":"Duillier",
    "sg:orig_category":"Instandhaltung U Reparatur von Automobilen",
    "sg:postcode":"1266",
    "sg:province":"Vaud",
    "wof:name":"Tecnomacchine Di Carlo Lavanzini",
    "wof:placetype":"venue"
},
  "geometry": {"coordinates":[8.9665212631,45.9541091919],"type":"Point"}
}