{
  "type": "Feature",
  "properties": {
    "iso:country":"CH",
    "sg:address":"Versamerstrasse 15",
    "sg:city":"Bonaduz",
    "sg:orig_category":"Detailhandel mit Waren verschiedener Art, Hauptrichtung Nahrungsmittel Sonstiger Grosshandel",
    "sg:phone":"+41 91 647 08 77",
    "sg:postcode":"7402",
    "sg:province":"Graubunden",
    "wof:name":"Thomaliment Sa",
    "wof:placetype":"venue"
},
  "geometry": {"coordinates":[8.937087059,45.8587913513],"type":"Point"}
}