{
  "type": "Feature",
  "properties": {
    "iso:country":"CH",
    "sg:address":"3036",
    "sg:city":"Detligen",
    "sg:orig_category":"Verarbeitung von Milch Verwertung von Milch",
    "sg:phone":"+41 71 931 11 27",
    "sg:postcode":"3036",
    "sg:province":"Bern",
    "wof:name":"K\u00e4sereigenossenschaft Dietschwil",
    "wof:placetype":"venue"
},
  "geometry": {"coordinates":[9.0401592255,47.41065979],"type":"Point"}
}