{
  "type": "Feature",
  "properties": {
    "iso:country":"CH",
    "sg:address":"Weyermattstrasse 61",
    "sg:city":"Nidau",
    "sg:orig_category":"Unternehmensberatung",
    "sg:postcode":"2560",
    "sg:province":"Bern",
    "wof:name":"Corporation For Consulting Design And Education",
    "wof:placetype":"venue"
},
  "geometry": {"coordinates":[7.2338218689,47.1254196167],"type":"Point"}
}