{
  "type": "Feature",
  "properties": {
    "iso:country":"CH",
    "sg:address":"6715",
    "sg:city":"Dongio",
    "sg:classifiers":[
        {
            "category":"Restaurant",
            "type":"Food & Drink"
        }
    ],
    "sg:phone":"+41 91 871 28 98",
    "sg:postcode":"6715",
    "sg:province":"Ticino",
    "wof:name":"Pizzeria Della Piazza Sa",
    "wof:placetype":"venue"
},
  "geometry": {"coordinates":[8.9522600174,46.4397087097],"type":"Point"}
}