{
  "type": "Feature",
  "properties": {
    "iso:country":"CH",
    "sg:address":"Kommetsr\u00fcti 65",
    "sg:city":"Wolhusen",
    "sg:orig_category":"Institutionen f\u00fcr Behinderte Tagesheime f\u00fcr Behinderte, gesch\u00fctzte Werkst\u00e4tten",
    "sg:phone":"+41 41 490 10 30",
    "sg:postcode":"6110",
    "sg:province":"Luzern",
    "wof:name":"Stiftung F.schwerbehinderte Besch\u00e4ftigungsst\u00e4tte",
    "wof:placetype":"venue"
},
  "geometry": {"coordinates":[8.0683498383,47.0544891357],"type":"Point"}
}