{
  "type": "Feature",
  "properties": {
    "addr:full":"Dorfstrasse 36 Zwingen Basel-Landschaft 4222",
    "addr:housenumber":"36",
    "addr:postcode":"4222",
    "addr:street":"Dorfstrasse",
    "iso:country":"CH",
    "sg:address":"Dorfstrasse 36",
    "sg:city":"Zwingen",
    "sg:orig_category":"Detailhandel mit Brot, Back U S\u00fcsswaren Detailhandel mit Waren verschiedener Art, Hauptrichtung Nahr",
    "sg:phone":"+41 61 761 64 21",
    "sg:postcode":"4222",
    "sg:province":"Basel-Landschaft",
    "wof:name":"Werner Anklin",
    "wof:placetype":"venue"
},
  "geometry": {"coordinates":[7.529198,47.43541],"type":"Point"}
}