{
  "type": "Feature",
  "properties": {
    "iso:country":"CH",
    "sg:address":"Bahnhofstrasse 5 6037 Root. Postfach",
    "sg:city":"Root",
    "sg:orig_category":"Detailhandel mit Blumen U Pflanzen",
    "sg:phone":"+41 41 450 12 75",
    "sg:postcode":"6037",
    "sg:province":"Luzern",
    "wof:name":"Josef Widler",
    "wof:placetype":"venue"
},
  "geometry": {"coordinates":[8.390605,47.116093],"type":"Point"}
}