{
  "type": "Feature",
  "properties": {
    "iso:country":"CH",
    "sg:address":"Gerechtigkeitsgasse 11",
    "sg:city":"Bern",
    "sg:orig_category":"Detailhandel mit Textilien Herstellung von Damen U M\u00e4dchenoberbekleidung",
    "sg:phone":"+41 31 311 02 77",
    "sg:postcode":"3011",
    "sg:province":"Bern",
    "wof:name":"Boutique Provence Charlotte Ehrlich",
    "wof:placetype":"venue"
},
  "geometry": {"coordinates":[7.4553141594,46.9484329224],"type":"Point"}
}