{
  "type": "Feature",
  "properties": {
    "iso:country":"CH",
    "sg:address":"Chemin De La Grangette",
    "sg:city":"Villars-sur-ollon",
    "sg:orig_category":"Herstellung von Teppichen Verlegen von Fussboden",
    "sg:phone":"+41 24 495 20 25",
    "sg:postcode":"1884",
    "sg:province":"Vaud",
    "wof:name":"Pignolet Michel",
    "wof:placetype":"venue"
},
  "geometry": {"coordinates":[7.0525369644,46.2959861755],"type":"Point"}
}