{
  "type": "Feature",
  "properties": {
    "iso:country":"CH",
    "sg:address":"Chemin De Ros\u00e9az 1",
    "sg:city":"Bussigny-lausanne",
    "sg:orig_category":"P\u00e9dicure",
    "sg:phone":"+41 21 701 29 09",
    "sg:postcode":"1030",
    "sg:province":"Vaud",
    "wof:name":"Claudine Regamey P\u00e9dicure",
    "wof:placetype":"venue"
},
  "geometry": {"coordinates":[6.5536208153,46.5493469238],"type":"Point"}
}