{
  "type": "Feature",
  "properties": {
    "iso:country":"CH",
    "sg:address":"Gurzelngasse 38 4500 Solothurn. Postfach",
    "sg:city":"Solothurn",
    "sg:orig_category":"Detailhandel mit Bekleidung Detailhandel mit Waren verschiedener Art, Hauptrichtung Nichtnahrungsmit",
    "sg:phone":"+41 32 622 20 44",
    "sg:postcode":"4502",
    "sg:province":"Solothurn",
    "wof:name":"Jecker Ag",
    "wof:placetype":"venue"
},
  "geometry": {"coordinates":[7.535421,47.208115],"type":"Point"}
}