{
  "type": "Feature",
  "properties": {
    "iso:country":"CH",
    "sg:address":"Torfnest",
    "sg:city":"Oberegg",
    "sg:orig_category":"Alters U Pflegeheime Institutionen f\u00fcr Behinderte",
    "sg:phone":"+41 31 740 11 11",
    "sg:postcode":"9413",
    "sg:province":"Appenzell Innerhoden",
    "wof:name":"Alters-& Krankenheim",
    "wof:placetype":"venue"
},
  "geometry": {"coordinates":[7.243912,46.909149],"type":"Point"}
}