{
  "type": "Feature",
  "properties": {
    "iso:country":"CH",
    "sg:address":"Pilatusstrasse 64",
    "sg:city":"Luzern",
    "sg:orig_category":"Sonstige mit der Informatik verbundene T\u00e4tigkeiten",
    "sg:postcode":"6003",
    "sg:province":"Luzern",
    "wof:name":"Compusource Ag",
    "wof:placetype":"venue"
},
  "geometry": {"coordinates":[8.3017101288,47.0468292236],"type":"Point"}
}