{
  "type": "Feature",
  "properties": {
    "iso:country":"CH",
    "sg:address":"Industriestrasse 26",
    "sg:city":"Volketswil",
    "sg:orig_category":"Event Arrangements, Vip Villages",
    "sg:phone":"+41 19461800",
    "sg:postcode":"8604",
    "sg:province":"Z\u00fcrich",
    "wof:name":"Artino Design Messebau Ag",
    "wof:placetype":"venue"
},
  "geometry": {"coordinates":[8.6788740158,47.3794898987],"type":"Point"}
}