{
  "type": "Feature",
  "properties": {
    "iso:country":"CH",
    "sg:address":"Waisenhausplatz",
    "sg:city":"Bern",
    "sg:orig_category":"Detailhandel mit Schuhen",
    "sg:phone":"+41 31 311 81 00",
    "sg:postcode":"3011",
    "sg:province":"Bern",
    "wof:name":"Companero Ag",
    "wof:placetype":"venue"
},
  "geometry": {"coordinates":[7.4444880486,46.9499893188],"type":"Point"}
}