{
  "type": "Feature",
  "properties": {
    "iso:country":"CH",
    "sg:address":"Via Tesserete 10",
    "sg:city":"Lugano",
    "sg:orig_category":"Handelsvermittlung U Grosshandel",
    "sg:phone":"+41 56 282 18 13",
    "sg:postcode":"6900",
    "sg:province":"Ticino",
    "wof:name":"Cimexy Import-export Cikota Miranda",
    "wof:placetype":"venue"
},
  "geometry": {"coordinates":[8.2866802216,47.4876594543],"type":"Point"}
}