{
  "type": "Feature",
  "properties": {
    "iso:country":"CH",
    "sg:address":"Blauchen 3",
    "sg:city":"Niederbipp",
    "sg:orig_category":"Haltung von Rindern",
    "sg:postcode":"4704",
    "sg:province":"Bern",
    "wof:name":"Braunviehzuchtgenossenschaft Niederbipp Und Umgebung",
    "wof:placetype":"venue"
},
  "geometry": {"coordinates":[7.6922550201,47.2706947327],"type":"Point"}
}