{
  "type": "Feature",
  "properties": {
    "iso:country":"CH",
    "sg:address":"Rotbuchstrasse 68",
    "sg:city":"Z\u00fcrich",
    "sg:orig_category":"Bauingenieurb\u00fcros allgemein",
    "sg:phone":"+41 13625015",
    "sg:postcode":"8037",
    "sg:province":"Z\u00fcrich",
    "wof:name":"Norbert Ruoss Ingenieurb\u00fcro",
    "wof:placetype":"venue"
},
  "geometry": {"coordinates":[8.530481,47.393234],"type":"Point"}
}