{
  "type": "Feature",
  "properties": {
    "iso:country":"CH",
    "sg:address":"Obergrundstrasse 69",
    "sg:city":"Luzern",
    "sg:orig_category":"Detailhandel mit Schuhen",
    "sg:phone":"+41 71 223 32 52",
    "sg:postcode":"6003",
    "sg:province":"Luzern",
    "wof:name":"Sennissimo Senn Schuhe",
    "wof:placetype":"venue"
},
  "geometry": {"coordinates":[9.3727931976,47.4228858948],"type":"Point"}
}