{
  "type": "Feature",
  "properties": {
    "iso:country":"CH",
    "sg:address":"Via Maggio",
    "sg:city":"Lugano",
    "sg:orig_category":"Kauf U Verkauf von Immobilien auf eigene Rechnung Vermietung U Verpachtung von eigenen Immobilien",
    "sg:phone":"+41 91 971 70 36",
    "sg:postcode":"6900",
    "sg:province":"Ticino",
    "wof:name":"Residenza Tamporiva Sa",
    "wof:placetype":"venue"
},
  "geometry": {"coordinates":[8.9672651291,46.0087242126],"type":"Point"}
}