{
  "type": "Feature",
  "properties": {
    "iso:country":"CH",
    "sg:address":"L\u00f6wengraben 8",
    "sg:city":"Luzern",
    "sg:orig_category":"Werbegrafikateliers",
    "sg:phone":"+41 41 410 90 04",
    "sg:postcode":"6004",
    "sg:province":"Luzern",
    "wof:name":"Christoph Helmlin Grafik Pinselschwung",
    "wof:placetype":"venue"
},
  "geometry": {"coordinates":[8.3052377701,47.0530471802],"type":"Point"}
}