{
  "type": "Feature",
  "properties": {
    "iso:country":"CH",
    "sg:address":"Avenue Henri-dunant 2",
    "sg:city":"Gen\u00e8ve",
    "sg:orig_category":"Allgemeiner Hoch U Tiefbau",
    "sg:phone":"+41 22 321 40 55",
    "sg:postcode":"1205",
    "sg:province":"Gen\u00e8ve",
    "wof:name":"Ie B\u00e2timents Industriels-engineering Sa",
    "wof:placetype":"venue"
},
  "geometry": {"coordinates":[6.142249,46.19767],"type":"Point"}
}