{
  "type": "Feature",
  "properties": {
    "addr:full":"Boschina Via 19 Pregassona Ticino 6963",
    "addr:housenumber":"19",
    "addr:postcode":"6963",
    "addr:street":"Via",
    "iso:country":"CH",
    "sg:address":"Boschina Via 19",
    "sg:city":"Pregassona",
    "sg:orig_category":"Architektur U Ingenieurb\u00fcros",
    "sg:phone":"+41 91 971 13 93",
    "sg:postcode":"6963",
    "sg:province":"Ticino",
    "wof:name":"V\u00f6geli Franco - Studio Di Architettura Sa",
    "wof:placetype":"venue"
},
  "geometry": {"coordinates":[8.96366,46.019787],"type":"Point"}
}