{
  "type": "Feature",
  "properties": {
    "iso:country":"CH",
    "sg:address":"Pioda Via 6",
    "sg:city":"Lugano",
    "sg:orig_category":"Detailhandel mit Schuhen U Lederwaren",
    "sg:postcode":"6900",
    "sg:province":"Ticino",
    "wof:name":"Vans (suisse) S\u00e0rl",
    "wof:placetype":"venue"
},
  "geometry": {"coordinates":[7.2707691193,47.1210594177],"type":"Point"}
}