{
  "type": "Feature",
  "properties": {
    "iso:country":"CH",
    "sg:address":"Amstutzweg 5",
    "sg:city":"Kriens",
    "sg:orig_category":"G\u00fcterbef\u00f6rderung im Strassenverkehr",
    "sg:phone":"+41 41 310 85 25",
    "sg:postcode":"6010",
    "sg:province":"Luzern",
    "wof:name":"S\u00fcess Umz\u00fcge & Transport Ag",
    "wof:placetype":"venue"
},
  "geometry": {"coordinates":[8.2928113937,47.0391654968],"type":"Point"}
}