{
  "type": "Feature",
  "properties": {
    "iso:country":"CH",
    "sg:address":"Gschwendstrasse",
    "sg:city":"Gersau",
    "sg:orig_category":"Grosshandel mit lebenden Tieren",
    "sg:phone":"+41 41 828 13 72",
    "sg:postcode":"6442",
    "sg:province":"Schwyz",
    "wof:name":"Karl Janser Viehhandel",
    "wof:placetype":"venue"
},
  "geometry": {"coordinates":[8.5268650055,46.9947471619],"type":"Point"}
}