{
  "type": "Feature",
  "properties": {
    "iso:country":"CH",
    "sg:address":"Route De Moutier 9",
    "sg:city":"Del\u00e9mont",
    "sg:orig_category":"Detailhandel mit Waren verschiedener Art, Hauptrichtung Nahrungsmittel Rebbau",
    "sg:phone":"+41 26 662 44 44",
    "sg:postcode":"2800",
    "sg:province":"Jura",
    "wof:name":"Acb, Agri-centre De La Broye",
    "wof:placetype":"venue"
},
  "geometry": {"coordinates":[6.8926100731,46.8147010803],"type":"Point"}
}