{
  "type": "Feature",
  "properties": {
    "iso:country":"CH",
    "sg:address":"Winkelrainweg 12",
    "sg:city":"Oberengstringen",
    "sg:orig_category":"Elektroinstallation",
    "sg:phone":"+41 17504433",
    "sg:postcode":"8102",
    "sg:province":"Z\u00fcrich",
    "wof:name":"Jakob Manfred",
    "wof:placetype":"venue"
},
  "geometry": {"coordinates":[8.4593572617,47.4095535278],"type":"Point"}
}