{
  "type": "Feature",
  "properties": {
    "iso:country":"CH",
    "sg:address":"Rue De Contamines 29",
    "sg:city":"Gen\u00e8ve",
    "sg:orig_category":"Zahnarztpraxen",
    "sg:phone":"+41 22 347 62 74",
    "sg:postcode":"1206",
    "sg:province":"Gen\u00e8ve",
    "wof:name":"Dr M\u00e9d.dent. Jean-p. Bozzoli M\u00e9decin-dentiste",
    "wof:placetype":"venue"
},
  "geometry": {"coordinates":[6.1546721458,46.1942825317],"type":"Point"}
}