{
  "type": "Feature",
  "properties": {
    "iso:country":"CH",
    "sg:address":"1255 Veyrier Case Postale 135",
    "sg:city":"Veyrier",
    "sg:orig_category":"Sportvereine Ballsport Tennis",
    "sg:phone":"+41 22 784 00 45",
    "sg:postcode":"1255",
    "sg:province":"Gen\u00e8ve",
    "wof:name":"Tennisclub Veyrier Grand-donzel",
    "wof:placetype":"venue"
},
  "geometry": {"coordinates":[6.1743302345,46.1731300354],"type":"Point"}
}