{
  "type": "Feature",
  "properties": {
    "iso:country":"CH",
    "sg:address":"Comercialstrasse 23",
    "sg:city":"Chur",
    "sg:classifiers":[
        {
            "category":"Home & Garden",
            "subcategory":"Home Furnishings",
            "type":"Retail Goods"
        }
    ],
    "sg:phone":"+41 21 845 10 10",
    "sg:postcode":"7000",
    "sg:province":"Graubunden",
    "sg:tags":[
        "desk"
    ],
    "wof:name":"J. Bodenmann S.a.",
    "wof:placetype":"venue"
},
  "geometry": {"coordinates":[6.214657,46.584084],"type":"Point"}
}