{
  "type": "Feature",
  "properties": {
    "iso:country":"CH",
    "sg:address":"La Ligni\u00e8re 15",
    "sg:city":"Malleray",
    "sg:orig_category":"Maschinenbau Mechanische Werkst\u00e4tten",
    "sg:phone":"+41 32 492 28 18",
    "sg:postcode":"2735",
    "sg:province":"Bern",
    "wof:name":"Trinita Sa Atelier De M\u00e9canique, Etc.",
    "wof:placetype":"venue"
},
  "geometry": {"coordinates":[7.2727050781,47.2373085022],"type":"Point"}
}