{
  "type": "Feature",
  "properties": {
    "iso:country":"CH",
    "sg:address":"3534",
    "sg:city":"Signau",
    "sg:orig_category":"Sportvereine Turnen Vereine Damen",
    "sg:phone":"+41 33 722 29 65",
    "sg:postcode":"3534",
    "sg:province":"Bern",
    "wof:name":"Damenturnverein Stv St.stefan",
    "wof:placetype":"venue"
},
  "geometry": {"coordinates":[7.3968400955,46.507598877],"type":"Point"}
}