{
  "type": "Feature",
  "properties": {
    "iso:country":"CH",
    "sg:address":"3048 Worblaufen. Postfach 119",
    "sg:city":"Worblaufen",
    "sg:orig_category":"Eisenbahnverkehr Schienenfahrzeugbau",
    "sg:phone":"+41 41 631 09 77",
    "sg:postcode":"3048",
    "sg:province":"Bern",
    "wof:name":"Fabryka Wagon Holding Ag",
    "wof:placetype":"venue"
},
  "geometry": {"coordinates":[8.311507225,46.9859924316],"type":"Point"}
}