{
  "type": "Feature",
  "properties": {
    "iso:country":"CH",
    "sg:address":"Bahnhofstrasse 24 8001 Z\u00fcrich. Postfach",
    "sg:city":"Z\u00fcrich",
    "sg:orig_category":"Aktivit\u00e4t der Bankinstitute",
    "sg:phone":"+41 21 320 56 21",
    "sg:postcode":"8022",
    "sg:province":"Z\u00fcrich",
    "wof:name":"Cbg Compagnie Bancaire Gen\u00e8ve",
    "wof:placetype":"venue"
},
  "geometry": {"coordinates":[6.142849,46.203693],"type":"Point"}
}