{
  "type": "Feature",
  "properties": {
    "iso:country":"CH",
    "sg:address":"Gottardo Via San 101",
    "sg:city":"Gordola",
    "sg:orig_category":"Werbung",
    "sg:phone":"+41 91 745 42 92",
    "sg:postcode":"6596",
    "sg:province":"Ticino",
    "wof:name":"Pubblistudio Sagl",
    "wof:placetype":"venue"
},
  "geometry": {"coordinates":[8.8655157089,46.1808280945],"type":"Point"}
}