{
  "type": "Feature",
  "properties": {
    "addr:full":"Industriezone Hintere R\u00fcti W\u00e4denswil Z\u00fcrich 8820",
    "addr:postcode":"8820",
    "addr:street":"Hintere Rueti Waedenswil Zuerich",
    "iso:country":"CH",
    "sg:address":"Industriezone Hintere R\u00fcti",
    "sg:city":"W\u00e4denswil",
    "sg:orig_category":"Betrieb von Sportanlagen",
    "sg:postcode":"8820",
    "sg:province":"Z\u00fcrich",
    "wof:name":"Tennispark Falkensteig Ag",
    "wof:placetype":"venue"
},
  "geometry": {"coordinates":[9.417132,47.437325],"type":"Point"}
}