{
  "type": "Feature",
  "properties": {
    "iso:country":"CH",
    "sg:address":"Allmendstrasse 6",
    "sg:city":"Bettlach",
    "sg:orig_category":"Fachdetailhandel in Verkaufsr\u00e4umen",
    "sg:postcode":"2544",
    "sg:province":"Solothurn",
    "wof:name":"Suwe-sport, Wenger Susanne",
    "wof:placetype":"venue"
},
  "geometry": {"coordinates":[7.4246168137,47.2056350708],"type":"Point"}
}