{
  "type": "Feature",
  "properties": {
    "iso:country":"CH",
    "sg:address":"Compognastrasse 7430 Thusis. Postfach",
    "sg:city":"Thusis",
    "sg:orig_category":"Interessenvertretungen",
    "sg:phone":"+41 81 651 22 33",
    "sg:postcode":"7430",
    "sg:province":"Graubunden",
    "wof:name":"Evangelisches Pflege Und Altersheim",
    "wof:placetype":"venue"
},
  "geometry": {"coordinates":[9.439997673,46.7051582336],"type":"Point"}
}