{
  "type": "Feature",
  "properties": {
    "iso:country":"CH",
    "sg:address":"Schuemacherstrasse 17",
    "sg:city":"B\u00fclach",
    "sg:classifiers":[
        {
            "category":"Insurance",
            "subcategory":"Insurance Agent",
            "type":"Services"
        }
    ],
    "sg:phone":"+41 18606117",
    "sg:postcode":"8180",
    "sg:province":"Z\u00fcrich",
    "sg:tags":[
        "versicherungsagenturen",
        "-broker"
    ],
    "wof:name":"Helvetia Patria Versicherungen Agentur",
    "wof:placetype":"venue"
},
  "geometry": {"coordinates":[8.5473165512,47.5274810791],"type":"Point"}
}