{
  "type": "Feature",
  "properties": {
    "iso:country":"CH",
    "sg:address":"Z\u00fcrichstrasse 12",
    "sg:city":"Neftenbach",
    "sg:orig_category":"Herstellung von sonstigen Fahrzeugen",
    "sg:phone":"+41 52 315 29 11",
    "sg:postcode":"8413",
    "sg:province":"Z\u00fcrich",
    "wof:name":"Alfred Fischer Wagnerei",
    "wof:placetype":"venue"
},
  "geometry": {"coordinates":[8.6658554077,47.5275268555],"type":"Point"}
}