{
  "type": "Feature",
  "properties": {
    "iso:country":"CH",
    "sg:address":"Strehlgasse 5 6430 Schwyz. Postfach 47",
    "sg:city":"Schwyz",
    "sg:orig_category":"Sonstiges Versicherungsgewerbe",
    "sg:phone":"+41 71 912 44 55",
    "sg:postcode":"6431",
    "sg:province":"Schwyz",
    "wof:name":"Allianz Versicherungen Generalagentur Georges K\u00f6lliker",
    "wof:placetype":"venue"
},
  "geometry": {"coordinates":[9.0440979004,47.4605712891],"type":"Point"}
}