{
  "type": "Feature",
  "properties": {
    "iso:country":"CH",
    "sg:address":"Rosshalde 16",
    "sg:city":"Rothenburg",
    "sg:orig_category":"Physiotherapie",
    "sg:phone":"+41 41 280 85 45",
    "sg:postcode":"6023",
    "sg:province":"Luzern",
    "wof:name":"Ruth Kaufmann Physiotherapie",
    "wof:placetype":"venue"
},
  "geometry": {"coordinates":[8.2654428482,47.102596283],"type":"Point"}
}