{
  "type": "Feature",
  "properties": {
    "iso:country":"CH",
    "sg:address":"Bierigut-strasse 18",
    "sg:city":"Thun",
    "sg:classifiers":[
        {
            "category":"Sports & Exercise",
            "subcategory":"Skate Park",
            "type":"Entertainment"
        }
    ],
    "sg:phone":"+41 33 334 24 24",
    "sg:postcode":"3608",
    "sg:province":"Bern",
    "sg:tags":[
        "equipment",
        "practice",
        "doctor's"
    ],
    "wof:name":"Strasser Ag Thun",
    "wof:placetype":"venue"
},
  "geometry": {"coordinates":[7.6009559631,46.7406387329],"type":"Point"}
}