{
  "type": "Feature",
  "properties": {
    "iso:country":"CH",
    "sg:address":"St. Johanns-vorstadt 46",
    "sg:city":"Basel",
    "sg:orig_category":"Erbringung von Dienstleistungen f\u00fcr Unternehmen",
    "sg:phone":"+41 61 261 67 57",
    "sg:postcode":"4056",
    "sg:province":"Basel-Stadt",
    "wof:name":"Vista Point Ag",
    "wof:placetype":"venue"
},
  "geometry": {"coordinates":[7.5843057632,47.5640830994],"type":"Point"}
}