{
  "type": "Feature",
  "properties": {
    "iso:country":"CH",
    "sg:address":"L'or\u00e9e Des Vignes",
    "sg:city":"Lussy-sur-morges",
    "sg:orig_category":"Non-Classified Establishments",
    "sg:postcode":"1133",
    "wof:name":"Polyglotte Verbier S.\u00e0 R.l., Succursale De Lussy-sur-morges",
    "wof:placetype":"venue"
},
  "geometry": {"coordinates":[-87.38720703120001,44.7263183594],"type":"Point"}
}