{
  "type": "Feature",
  "properties": {
    "iso:country":"CH",
    "sg:address":"Schwaresterstrasse 2",
    "sg:city":"Hendschiken",
    "sg:orig_category":"Herstellung von Elektrizit\u00e4tsverteilungs U schalteinrichtungen",
    "sg:phone":"+41 62 891 89 80",
    "sg:postcode":"5604",
    "sg:province":"Aargau",
    "wof:name":"Peter Larini Steuerungstechnik",
    "wof:placetype":"venue"
},
  "geometry": {"coordinates":[8.2147989273,47.3856544495],"type":"Point"}
}