{
  "type": "Feature",
  "properties": {
    "iso:country":"CH",
    "sg:address":"Sch\u00fctzenstrasse 9 8212 Neuhausen. Postfach",
    "sg:city":"Neuhausen",
    "sg:orig_category":"Unclassifiable Establishments",
    "sg:postcode":"8212",
    "sg:province":"Schaffhausen",
    "wof:name":"Janev - Transport",
    "wof:placetype":"venue"
},
  "geometry": {"coordinates":[8.6068296432,47.6804046631],"type":"Point"}
}