{
  "type": "Feature",
  "properties": {
    "iso:country":"CH",
    "sg:address":"1615 Bossonnens Case Postale 40",
    "sg:city":"Bossonnens",
    "sg:orig_category":"Non-Classified Establishments",
    "sg:phone":"+41 21 947 47 58",
    "sg:postcode":"1615",
    "sg:province":"Fribourg",
    "wof:name":"Lcbe Laboratoire De Contr\u00f4le B\u00e9tons, Enrob\u00e9s Et Sols Sa",
    "wof:placetype":"venue"
},
  "geometry": {"coordinates":[6.8484401703,46.529209137],"type":"Point"}
}