{
  "type": "Feature",
  "properties": {
    "addr:full":"Hertistrasse 29 Wallisellen Z\u00fcrich 8304",
    "addr:housenumber":"29",
    "addr:postcode":"8304",
    "addr:street":"Hertistrasse",
    "iso:country":"CH",
    "sg:address":"Hertistrasse 29",
    "sg:city":"Wallisellen",
    "sg:classifiers":[
        {
            "category":"Manufacturing",
            "subcategory":"Paper Products",
            "type":"Manufacturing & Wholesale Goods"
        }
    ],
    "sg:phone":"+41 18311630",
    "sg:postcode":"8304",
    "sg:province":"Z\u00fcrich",
    "sg:tags":[
        "plastics",
        "sheet",
        "laminated",
        "machine",
        "cutting",
        "cardboard"
    ],
    "wof:name":"Koelliker B\u00fcroautomation Ag",
    "wof:placetype":"venue"
},
  "geometry": {"coordinates":[8.576237,47.416195],"type":"Point"}
}