{
  "type": "Feature",
  "properties": {
    "iso:country":"CH",
    "sg:address":"Boulevard De P\u00e9rolles 30",
    "sg:city":"Fribourg",
    "sg:orig_category":"Detailhandel mit Waren verschiedener Art, Hauptrichtung Nahrungsmittel Grosshandel mit Nahrungsmitte",
    "sg:phone":"+41 33 971 21 10",
    "sg:postcode":"1700",
    "sg:province":"Fribourg",
    "wof:name":"Blatter Katharina",
    "wof:placetype":"venue"
},
  "geometry": {"coordinates":[8.1754245758,46.7503967285],"type":"Point"}
}