{
  "type": "Feature",
  "properties": {
    "addr:full":"Lerchenstrasse 1 Wangs St. Gallen 7323",
    "addr:housenumber":"1",
    "addr:postcode":"7323",
    "addr:street":"Lerchenstrasse",
    "iso:country":"CH",
    "sg:address":"Lerchenstrasse 1",
    "sg:city":"Wangs",
    "sg:orig_category":"Bauschreinerei Herstellung von Konstruktionsteilen, Fertigbauteilen U Ausbauelementen aus Holz",
    "sg:phone":"+41 81 723 30 50",
    "sg:postcode":"7323",
    "sg:province":"St. Gallen",
    "wof:name":"Thomas Marquart, Schreinerei",
    "wof:placetype":"venue"
},
  "geometry": {"coordinates":[9.431483,47.031666],"type":"Point"}
}