{
  "type": "Feature",
  "properties": {
    "iso:country":"CH",
    "sg:address":"Route De Gollion 15",
    "sg:city":"Penthalaz",
    "sg:orig_category":"Elektroinstallation",
    "sg:phone":"+41 21 861 34 27",
    "sg:postcode":"1305",
    "sg:province":"Vaud",
    "wof:name":"Albert Chaillet Sa Installations \u00e9lectriques",
    "wof:placetype":"venue"
},
  "geometry": {"coordinates":[6.5251722336,46.600189209],"type":"Point"}
}