{
  "type": "Feature",
  "properties": {
    "iso:country":"CH",
    "sg:address":"Gasparin Rue De 13",
    "sg:city":"Yverdon-les-bains",
    "sg:orig_category":"Herstellung von elektrischen Lampen U Leuchten",
    "sg:postcode":"1400",
    "sg:province":"Vaud",
    "wof:name":"Flash Sound S\u00e0rl",
    "wof:placetype":"venue"
},
  "geometry": {"coordinates":[6.646572113,46.7735671997],"type":"Point"}
}