{
  "type": "Feature",
  "properties": {
    "iso:country":"CH",
    "sg:address":"Hertensteinstrasse 41",
    "sg:city":"Z\u00fcrich",
    "sg:orig_category":"Fahrschulen, Flugschulen",
    "sg:phone":"+41 13014422",
    "sg:postcode":"8052",
    "sg:province":"Z\u00fcrich",
    "wof:name":"Billeter Fahrschule",
    "wof:placetype":"venue"
},
  "geometry": {"coordinates":[8.5434789658,47.4251747131],"type":"Point"}
}