{
  "type": "Feature",
  "properties": {
    "iso:country":"CH",
    "sg:address":"St. Jakobstrasse 54",
    "sg:city":"Z\u00fcrich",
    "sg:orig_category":"Bauschreinerei Herstellung von M\u00f6beln verschiedener Art",
    "sg:phone":"+41 33 951 24 53",
    "sg:postcode":"8004",
    "sg:province":"Z\u00fcrich",
    "wof:name":"Fritz Kienholz M\u00f6bel-& Antikschreinerei",
    "wof:placetype":"venue"
},
  "geometry": {"coordinates":[8.024194,46.759132],"type":"Point"}
}