{
  "type": "Feature",
  "properties": {
    "iso:country":"CH",
    "sg:address":"Mellingerstrasse 6 5400 Baden. Postfach",
    "sg:city":"Baden",
    "sg:orig_category":"Advokaturb\u00fcros",
    "sg:phone":"+41 56 221 75 65",
    "sg:postcode":"5401",
    "sg:province":"Aargau",
    "wof:name":"Arthur Zeller Advokaturb\u00fcro",
    "wof:placetype":"venue"
},
  "geometry": {"coordinates":[8.305408,47.471298],"type":"Point"}
}