{
  "type": "Feature",
  "properties": {
    "iso:country":"CH",
    "sg:address":"Grand-rue 59",
    "sg:city":"Morges",
    "sg:orig_category":"Reiseb\u00fcros",
    "sg:phone":"+41 22 909 79 79",
    "sg:postcode":"1110",
    "sg:province":"Vaud",
    "wof:name":"Imholz Agences Sa",
    "wof:placetype":"venue"
},
  "geometry": {"coordinates":[6.1481518745,46.2104911804],"type":"Point"}
}