{
  "type": "Feature",
  "properties": {
    "iso:country":"CH",
    "sg:address":"Pestalozzi Corso 27",
    "sg:city":"Lugano",
    "sg:orig_category":"Grosshandel mit sonstigen Gebrauchs U Verbrauchsg\u00fctern",
    "sg:postcode":"6900",
    "sg:province":"Ticino",
    "wof:name":"Daylight Trading Ltd, Dublino, Succursale Di Lugano",
    "wof:placetype":"venue"
},
  "geometry": {"coordinates":[8.9546928406,46.0059700012],"type":"Point"}
}