{
  "type": "Feature",
  "properties": {
    "iso:country":"CH",
    "sg:address":"Neustadtgasse 1a 8400 Winterthur. Postfach",
    "sg:city":"Winterthur",
    "sg:orig_category":"Herstellung von Metallkonstruktionen",
    "sg:phone":"+41 52 260 20 90",
    "sg:postcode":"8400",
    "sg:province":"Z\u00fcrich",
    "wof:name":"Pamag Montagetechnik Und Personal Winterthur Gmbh Stahlbau, Metallbau, Fassadenbau, Apparatebau, Rohrleitungsbau Usw",
    "wof:placetype":"venue"
},
  "geometry": {"coordinates":[8.7320327759,47.4983596802],"type":"Point"}
}