{
  "type": "Feature",
  "properties": {
    "iso:country":"CH",
    "sg:address":"Irchelstrasse 112",
    "sg:city":"Volken",
    "sg:orig_category":"K\u00fcnstlerische U schriftstellerische T\u00e4tigkeiten U Darbietungen",
    "sg:postcode":"8459",
    "sg:province":"Z\u00fcrich",
    "wof:name":"Atelier Andreas Franz Dipl. Restaurator Hfg/skr",
    "wof:placetype":"venue"
},
  "geometry": {"coordinates":[8.5822973251,47.3234405518],"type":"Point"}
}