{
  "type": "Feature",
  "properties": {
    "addr:full":"Carmenstrasse 12 8032 Z\u00fcrich Zust 32",
    "addr:housenumber":"12;32",
    "addr:postcode":"8032",
    "addr:street":"Carmenstrasse;Zust",
    "iso:country":"CH",
    "sg:address":"Carmenstrasse 12 8032 Z\u00fcrich",
    "sg:city":"Zust",
    "sg:orig_category":"Betrieb U technische Hilfsdienste des Kultur U Unterhaltungswesens",
    "sg:phone":"+41 79 200 14 41",
    "sg:postcode":"32",
    "wof:name":"Linie Special Ag",
    "wof:placetype":"venue"
},
  "geometry": {"coordinates":[8.635041,47.202759],"type":"Point"}
}