{
  "type": "Feature",
  "properties": {
    "iso:country":"CH",
    "sg:address":"Jurastrasse 8",
    "sg:city":"Unterentfelden",
    "sg:orig_category":"Nationale Postdienste",
    "sg:phone":"+41 62 723 66 33",
    "sg:postcode":"5035",
    "sg:province":"Aargau",
    "wof:name":"Die Schweizerische Post",
    "wof:placetype":"venue"
},
  "geometry": {"coordinates":[8.0435209274,47.3683052063],"type":"Point"}
}