{
  "type": "Feature",
  "properties": {
    "iso:country":"CH",
    "sg:address":"5605",
    "sg:city":"Dottikon",
    "sg:classifiers":[
        {
            "category":"Education",
            "subcategory":"Vocational School",
            "type":"Public Place"
        }
    ],
    "sg:postcode":"5605",
    "sg:province":"Aargau",
    "sg:tags":[
        "koch-",
        "haushaltschulen"
    ],
    "wof:name":"Haushaltungsschule",
    "wof:placetype":"venue"
},
  "geometry": {"coordinates":[8.2455596924,47.3773498535],"type":"Point"}
}