{
  "type": "Feature",
  "properties": {
    "iso:country":"CH",
    "sg:address":"Schaffhauserstr. 55",
    "sg:city":"Glattbrugg",
    "sg:classifiers":[
        {
            "category":"Professional",
            "subcategory":"Computer Services",
            "type":"Services"
        }
    ],
    "sg:phone":"+41 4118089555",
    "sg:postcode":"8152",
    "sg:province":"Z\u00fcrich",
    "sg:tags":[
        "information",
        "technology",
        "software"
    ],
    "wof:name":"Workstation Ag",
    "wof:placetype":"venue"
},
  "geometry": {"coordinates":[8.56067276,47.4303474426],"type":"Point"}
}