{
  "type": "Feature",
  "properties": {
    "iso:country":"CH",
    "sg:address":"Wabernstrasse 71",
    "sg:city":"Bern",
    "sg:orig_category":"Wohnheime",
    "sg:postcode":"3005",
    "sg:province":"Bern",
    "wof:name":"Senioren-haus R\u00f6ssli Ag",
    "wof:placetype":"venue"
},
  "geometry": {"coordinates":[7.4391078949,46.9376945496],"type":"Point"}
}