{
  "type": "Feature",
  "properties": {
    "addr:full":"Schaffhuserstrass 8 Marthalen Z\u00fcrich 8460",
    "addr:housenumber":"8",
    "addr:postcode":"8460",
    "addr:street":"Schaffhuserstrass",
    "iso:country":"CH",
    "sg:address":"Schaffhuserstrass 8",
    "sg:city":"Marthalen",
    "sg:classifiers":[
        {
            "category":"Manufacturing",
            "subcategory":"Textiles",
            "type":"Manufacturing & Wholesale Goods"
        }
    ],
    "sg:phone":"+41 52 305 45 05",
    "sg:postcode":"8460",
    "sg:province":"Z\u00fcrich",
    "sg:tags":[
        "cloth",
        "fleece",
        "made"
    ],
    "wof:name":"Toggenburger & Co Ag",
    "wof:placetype":"venue"
},
  "geometry": {"coordinates":[8.651056,47.627262],"type":"Point"}
}