{
  "type": "Feature",
  "properties": {
    "iso:country":"CH",
    "sg:address":"Industrielle Avenue 14 1227 Carouge Ge. Postfach",
    "sg:city":"Gen\u00e8ve",
    "sg:orig_category":"Fachdetailhandel in Verkaufsr\u00e4umen",
    "sg:postcode":"1201",
    "sg:province":"Gen\u00e8ve",
    "wof:name":"Leytron Consult S\u00e0rl, \u00e0 Carouge",
    "wof:placetype":"venue"
},
  "geometry": {"coordinates":[6.1344838142,46.1894760132],"type":"Point"}
}