{
  "type": "Feature",
  "properties": {
    "iso:country":"CH",
    "sg:address":"G\u00f6scheneralpstrasse",
    "sg:city":"G\u00f6schenen",
    "sg:orig_category":"Arztpraxen",
    "sg:phone":"+41 41 885 11 63",
    "sg:postcode":"6487",
    "sg:province":"Uri",
    "wof:name":"Dr.med.peter Hirzel Arzt F\u00fcr Allgemeine Medizin",
    "wof:placetype":"venue"
},
  "geometry": {"coordinates":[8.545018,46.661545],"type":"Point"}
}