{
  "type": "Feature",
  "properties": {
    "iso:country":"CH",
    "sg:address":"Oberdorfstrasse 11 6260 Reiden. Postfach",
    "sg:city":"Reiden",
    "sg:orig_category":"Herstellung von Konstruktionsteilen, Fertigbauteilen U Ausbauelementen aus Holz Innenausbau",
    "sg:phone":"+41 19751666",
    "sg:postcode":"6260",
    "sg:province":"Luzern",
    "wof:name":"Kurt Meier Gmbh",
    "wof:placetype":"venue"
},
  "geometry": {"coordinates":[8.7695713043,47.3041954041],"type":"Point"}
}