{
  "type": "Feature",
  "properties": {
    "iso:country":"CH",
    "sg:address":"Gemeinschaftszollanlage",
    "sg:city":"Kreuzlingen",
    "sg:orig_category":"Customs Agencies, Declarants",
    "sg:phone":"+41 71 677 95 00",
    "sg:postcode":"8280",
    "sg:province":"Thurgau",
    "wof:name":"Frederick & St\u00e4hli Transporte Zollagentur",
    "wof:placetype":"venue"
},
  "geometry": {"coordinates":[9.175115,47.648178],"type":"Point"}
}