{
  "type": "Feature",
  "properties": {
    "iso:country":"CH",
    "sg:address":"Schaffhauserstrasse 146",
    "sg:city":"Kloten",
    "sg:classifiers":[
        {
            "category":"Utilities",
            "subcategory":"Cable",
            "type":"Services"
        }
    ],
    "sg:phone":"+41 18131211",
    "sg:postcode":"8302",
    "sg:province":"Z\u00fcrich",
    "wof:name":"Dynawell Ag",
    "wof:placetype":"venue"
},
  "geometry": {"coordinates":[8.5805521011,47.4532241821],"type":"Point"}
}