{
  "type": "Feature",
  "properties": {
    "iso:country":"CH",
    "sg:address":"Alte Landstrasse 18",
    "sg:city":"Pieterlen",
    "sg:orig_category":"Architekturb\u00fcros",
    "sg:phone":"+41 22 320 35 22",
    "sg:postcode":"2542",
    "sg:province":"Bern",
    "wof:name":"Pietro Sartorio Bureau D'architecture",
    "wof:placetype":"venue"
},
  "geometry": {"coordinates":[6.143381,46.191788],"type":"Point"}
}