{
  "type": "Feature",
  "properties": {
    "iso:country":"CH",
    "sg:address":"Rue De Montbrillant 26",
    "sg:city":"Gen\u00e8ve",
    "sg:orig_category":"Grosshandel mit Radio U Fernsehger\u00e4ten Grosshandel mit sonstigen Gebrauchs U Verbrauchsg\u00fctern",
    "sg:phone":"+41 32 913 52 39",
    "sg:postcode":"1201",
    "sg:province":"Gen\u00e8ve",
    "wof:name":"Nido Giuseppe",
    "wof:placetype":"venue"
},
  "geometry": {"coordinates":[6.823551178,47.0992622375],"type":"Point"}
}