{
  "type": "Feature",
  "properties": {
    "iso:country":"CH",
    "sg:address":"Sonnenbergstrasse 11",
    "sg:city":"Uster",
    "sg:orig_category":"Arztpraxen",
    "sg:phone":"+41 19402185",
    "sg:postcode":"8610",
    "sg:province":"Z\u00fcrich",
    "wof:name":"Dres Med. Schriber & Peters \u00c4rzte F.allgemeine Medizin Fmh",
    "wof:placetype":"venue"
},
  "geometry": {"coordinates":[8.7052,47.35141],"type":"Point"}
}