{
  "type": "Feature",
  "properties": {
    "iso:country":"CH",
    "sg:address":"2738",
    "sg:city":"Court",
    "sg:classifiers":[
        {
            "category":"Education",
            "subcategory":"Vocational School",
            "type":"Public Place"
        }
    ],
    "sg:postcode":"2738",
    "sg:province":"Bern",
    "sg:tags":[
        "koch-",
        "haushaltschulen"
    ],
    "wof:name":"Ecole M\u00e9nag\u00e8re",
    "wof:placetype":"venue"
},
  "geometry": {"coordinates":[7.3414521217,47.2410430908],"type":"Point"}
}