{
  "type": "Feature",
  "properties": {
    "iso:country":"CH",
    "sg:address":"Allerheiligenstrasse 111",
    "sg:city":"Grenchen",
    "sg:orig_category":"Herstellung von elektronischen Bauelementen",
    "sg:postcode":"2540",
    "sg:province":"Solothurn",
    "wof:name":"Ase Beat Isenring",
    "wof:placetype":"venue"
},
  "geometry": {"coordinates":[7.3792881966,47.1960372925],"type":"Point"}
}