{
  "type": "Feature",
  "properties": {
    "iso:country":"CH",
    "sg:address":"B\u00f6sch 35 6331 H\u00fcnenberg. Postfach",
    "sg:city":"H\u00fcnenberg",
    "sg:orig_category":"Herstellung von elektronischen Bauelementen",
    "sg:postcode":"6331",
    "sg:province":"Zug",
    "wof:name":"Contrel Ict Ag",
    "wof:placetype":"venue"
},
  "geometry": {"coordinates":[8.4397125244,47.1606407166],"type":"Point"}
}