{
  "type": "Feature",
  "properties": {
    "iso:country":"CH",
    "sg:address":"Schickenstrasse 7",
    "sg:city":"Dielsdorf",
    "sg:orig_category":"Hoch U Tiefbau",
    "sg:phone":"+41 18540384",
    "sg:postcode":"8157",
    "sg:province":"Z\u00fcrich",
    "wof:name":"John Spiess Baugesch\u00e4ft",
    "wof:placetype":"venue"
},
  "geometry": {"coordinates":[8.4548015594,47.4846382141],"type":"Point"}
}