{
  "type": "Feature",
  "properties": {
    "iso:country":"CH",
    "sg:address":"Jupiterstrasse 40",
    "sg:city":"Z\u00fcrich",
    "sg:orig_category":"Wohnheime",
    "sg:phone":"+41 27 923 17 44",
    "sg:postcode":"8032",
    "sg:province":"Z\u00fcrich",
    "wof:name":"Theresianum-erholungsheim",
    "wof:placetype":"venue"
},
  "geometry": {"coordinates":[7.9855179787,46.3596801758],"type":"Point"}
}