{
  "type": "Feature",
  "properties": {
    "iso:country":"CH",
    "sg:address":"Nordstrasse 286",
    "sg:city":"Z\u00fcrich",
    "sg:orig_category":"Detailhandel mit Milcherzeugnissen U Eiern",
    "sg:phone":"+41 12735080",
    "sg:postcode":"8037",
    "sg:province":"Z\u00fcrich",
    "wof:name":"Rothacher & Partner, Ch\u00e4s Egge Lebensmittel, Bes. K\u00e4se, Milchprodukte; Handel",
    "wof:placetype":"venue"
},
  "geometry": {"coordinates":[8.5242490768,47.3953323364],"type":"Point"}
}