{
  "type": "Feature",
  "properties": {
    "iso:country":"CH",
    "sg:address":"1125",
    "sg:city":"Monnaz",
    "sg:orig_category":"Grosshandel mit lebenden Tieren",
    "sg:phone":"+41 21 801 77 43",
    "sg:postcode":"1125",
    "sg:province":"Vaud",
    "wof:name":"Chollet Olivier",
    "wof:placetype":"venue"
},
  "geometry": {"coordinates":[6.4795398712,46.5340805054],"type":"Point"}
}