{
  "type": "Feature",
  "properties": {
    "iso:country":"CH",
    "sg:address":"B\u00fctzmatt. 3127 M\u00fchlethurnen. Postfach",
    "sg:city":"M\u00fchlethurnen",
    "sg:orig_category":"Instandhaltung U Reparatur von Automobilen",
    "sg:phone":"+41 62 822 36 22",
    "sg:postcode":"3127",
    "sg:province":"Bern",
    "wof:name":"Hofer Ag",
    "wof:placetype":"venue"
},
  "geometry": {"coordinates":[8.075630188,47.3880691528],"type":"Point"}
}