{
  "type": "Feature",
  "properties": {
    "iso:country":"CH",
    "sg:address":"Pradafant 1",
    "sg:city":"Vaduz",
    "sg:orig_category":"Unternehmensberatung",
    "sg:phone":"+423 232 51 10",
    "sg:postcode":"9490",
    "wof:name":"Hsm Managementberatung Ag",
    "wof:placetype":"venue"
},
  "geometry": {"coordinates":[9.513964653,47.1446037292],"type":"Point"}
}