{
  "type": "Feature",
  "properties": {
    "iso:country":"CH",
    "sg:address":"Regensdorferstrasse 18 8108 D\u00e4llikon. Postfach 108",
    "sg:city":"D\u00e4llikon",
    "sg:orig_category":"Herstellung von Metallerzeugnissen ohne Maschinenbau Herstellung von sonstigen Maschinen f\u00fcr unspezi",
    "sg:phone":"+41 52 741 24 37",
    "sg:postcode":"8108",
    "sg:province":"Z\u00fcrich",
    "wof:name":"Otto Dietzsch",
    "wof:placetype":"venue"
},
  "geometry": {"coordinates":[8.859910965,47.6644134521],"type":"Point"}
}