{
  "type": "Feature",
  "properties": {
    "iso:country":"CH",
    "sg:address":"Allmendstrasse 6",
    "sg:city":"Sursee",
    "sg:orig_category":"Detailhandel mit B\u00fcchern, Zeitungen, Schreib U Papeteriewaren",
    "sg:postcode":"6210",
    "sg:province":"Luzern",
    "wof:name":"R\u00f6ssler Papier Ag (schweiz)",
    "wof:placetype":"venue"
},
  "geometry": {"coordinates":[8.108977,47.18042],"type":"Point"}
}