{
  "type": "Feature",
  "properties": {
    "iso:country":"CH",
    "sg:address":"Landquartstrasse 32",
    "sg:city":"Arbon",
    "sg:orig_category":"Unclassifiable Establishments",
    "sg:postcode":"9320",
    "sg:province":"Thurgau",
    "wof:name":"Tabacomat Operaiting Gmbh",
    "wof:placetype":"venue"
},
  "geometry": {"coordinates":[9.4278459549,47.5086555481],"type":"Point"}
}