{
  "type": "Feature",
  "properties": {
    "iso:country":"CH",
    "sg:address":"Corso San Gottardo 14",
    "sg:city":"Chiasso",
    "sg:orig_category":"Non-Classified Establishments",
    "sg:postcode":"6830",
    "sg:province":"Ticino",
    "wof:name":"Ferdinand Bertsch",
    "wof:placetype":"venue"
},
  "geometry": {"coordinates":[8.460401535,47.3704147339],"type":"Point"}
}