{
  "type": "Feature",
  "properties": {
    "iso:country":"CH",
    "sg:address":"Steinenbachstrasse 5 9642 Ebnat. Postfach",
    "sg:city":"Ebnat",
    "sg:orig_category":"Zimmerei, Dachdeckerei, Bauspenglerei U Abdichtung",
    "sg:phone":"+41 24 472 85 38",
    "sg:postcode":"9642",
    "sg:province":"St. Gallen",
    "wof:name":"Schmid Fr\u00e9d\u00e9ric",
    "wof:placetype":"venue"
},
  "geometry": {"coordinates":[6.945827961,46.2704734802],"type":"Point"}
}