{
  "type": "Feature",
  "properties": {
    "iso:country":"CH",
    "sg:address":"Storchenbadstrasse 15",
    "sg:city":"Grabs",
    "sg:orig_category":"Mechanische Werkst\u00e4tten Oberfl\u00e4chenreinigung Sandstrahlen",
    "sg:phone":"+41 55 250 32 55",
    "sg:postcode":"9472",
    "sg:province":"St. Gallen",
    "wof:name":"I. Barac Diz Klein-/langteilbearbeitung",
    "wof:placetype":"venue"
},
  "geometry": {"coordinates":[8.8551568985,47.2647895813],"type":"Point"}
}