{
  "type": "Feature",
  "properties": {
    "iso:country":"CH",
    "sg:address":"Orico Via 6",
    "sg:city":"Bellinzona",
    "sg:orig_category":"Softwareentwicklung U beratung",
    "sg:postcode":"6500",
    "sg:province":"Ticino",
    "wof:name":"Il Quadrifoglio Sagl",
    "wof:placetype":"venue"
},
  "geometry": {"coordinates":[9.018992424,46.1918792725],"type":"Point"}
}