{
  "type": "Feature",
  "properties": {
    "iso:country":"CH",
    "sg:address":"Kirchweg 34a 8750 Glarus. Postfach 316",
    "sg:city":"Glarus",
    "sg:orig_category":"Hardwareberatung",
    "sg:phone":"+41 55 650 22 26",
    "sg:postcode":"8750",
    "sg:province":"Glarus",
    "wof:name":"Esoft Gmbh",
    "wof:placetype":"venue"
},
  "geometry": {"coordinates":[9.0706710815,47.038269043],"type":"Point"}
}