{
  "type": "Feature",
  "properties": {
    "iso:country":"CH",
    "sg:address":"Bahnhofplatz 1",
    "sg:city":"Lenzburg",
    "sg:orig_category":"Unternehmensberatung",
    "sg:phone":"+41 79 210 42 30",
    "sg:postcode":"5600",
    "sg:province":"Aargau",
    "wof:name":"Waldmeier & Partner Risk Management Ag",
    "wof:placetype":"venue"
},
  "geometry": {"coordinates":[8.1703176498,47.3905792236],"type":"Point"}
}