{
  "type": "Feature",
  "properties": {
    "iso:country":"CH",
    "sg:address":"Hauptstrasse 47",
    "sg:city":"Unterseen",
    "sg:orig_category":"Detailhandel mit Haustieren U zoologischem Bedarf Fachdetailhandel in Verkaufsr\u00e4umen",
    "sg:phone":"+41 33 822 52 33",
    "sg:postcode":"3800",
    "sg:province":"Bern",
    "wof:name":"Zoo Harder Ag",
    "wof:placetype":"venue"
},
  "geometry": {"coordinates":[7.8489899635,46.6856498718],"type":"Point"}
}