{
  "type": "Feature",
  "properties": {
    "iso:country":"CH",
    "sg:address":"Avenue De Feuillasse 24",
    "sg:city":"Meyrin",
    "sg:orig_category":"Reparatur von Schuhen U Lederwaren Schl\u00fcsselservice",
    "sg:phone":"+41 22 785 47 60",
    "sg:postcode":"1217",
    "sg:province":"Gen\u00e8ve",
    "wof:name":"Minit Switzerland Mister Minit Schuhrep.",
    "wof:placetype":"venue"
},
  "geometry": {"coordinates":[6.0827088356,46.2315216064],"type":"Point"}
}