{
  "type": "Feature",
  "properties": {
    "iso:country":"CH",
    "sg:address":"1045",
    "sg:city":"Ogens",
    "sg:orig_category":"Gemeindeverwaltungen",
    "sg:phone":"+41 21 887 70 96",
    "sg:postcode":"1045",
    "sg:province":"Vaud",
    "wof:name":"Administration Communale De Ogens",
    "wof:placetype":"venue"
},
  "geometry": {"coordinates":[6.7248702049,46.7098083496],"type":"Point"}
}