{
  "type": "Feature",
  "properties": {
    "iso:country":"CH",
    "sg:address":"Sonnhalde 21",
    "sg:city":"Liestal",
    "sg:classifiers":[
        {
            "category":"Personal",
            "subcategory":"Nail Salon",
            "type":"Services"
        }
    ],
    "sg:phone":"+41 61 923 05 36",
    "sg:postcode":"4410",
    "sg:province":"Basel-Landschaft",
    "sg:tags":[
        "manicure"
    ],
    "wof:name":"Ruth Karlen Kosmetik Studio",
    "wof:placetype":"venue"
},
  "geometry": {"coordinates":[7.7480249405,47.4827156067],"type":"Point"}
}