{
  "type": "Feature",
  "properties": {
    "iso:country":"CH",
    "sg:address":"Allmendstrasse 18",
    "sg:city":"Thun",
    "sg:orig_category":"Landesverteidigung",
    "sg:phone":"+41 33 225 62 30",
    "sg:postcode":"3600",
    "sg:province":"Bern",
    "wof:name":"Kreiskommando",
    "wof:placetype":"venue"
},
  "geometry": {"coordinates":[7.6234278679,46.7599372864],"type":"Point"}
}