{
  "type": "Feature",
  "properties": {
    "iso:country":"CH",
    "sg:address":"Hinterm Bach 6 7000 Chur. Postfach",
    "sg:city":"Chur",
    "sg:orig_category":"Advokaturb\u00fcros",
    "sg:phone":"+41 81 253 79 60",
    "sg:postcode":"7002",
    "sg:province":"Graubunden",
    "wof:name":"Benno Burtscher Advokaturb\u00fcro",
    "wof:placetype":"venue"
},
  "geometry": {"coordinates":[9.53059,46.847309],"type":"Point"}
}