{
  "type": "Feature",
  "properties": {
    "iso:country":"CH",
    "sg:address":"4536",
    "sg:city":"Attiswil",
    "sg:orig_category":"Sportvereine Turnen Vereine Damen",
    "sg:phone":"+41 32 637 20 74",
    "sg:postcode":"4536",
    "sg:province":"Bern",
    "wof:name":"Damenturnverein",
    "wof:placetype":"venue"
},
  "geometry": {"coordinates":[7.6126790047,47.246887207],"type":"Point"}
}