{
  "type": "Feature",
  "properties": {
    "addr:full":"8124 Maur Z\u00fcrich 8124",
    "addr:postcode":"8124;8124",
    "iso:country":"CH",
    "sg:address":"8124",
    "sg:city":"Maur",
    "sg:orig_category":"Detailhandel mit B\u00fcchern, Zeitungen, Schreib U Papeteriewaren",
    "sg:postcode":"8124",
    "sg:province":"Z\u00fcrich",
    "wof:name":"Solution Consulting Mennel + Renggli",
    "wof:placetype":"venue"
},
  "geometry": {"coordinates":[8.667613,47.340317],"type":"Point"}
}