{
  "type": "Feature",
  "properties": {
    "iso:country":"CH",
    "sg:address":"Kirchmatte 3 6362 Stansstad. Postfach",
    "sg:city":"Stansstad",
    "sg:orig_category":"Verwaltung von Immobilien",
    "sg:postcode":"6362",
    "sg:province":"Nidwalden",
    "wof:name":"Gerberteam Gmbh Immobilien Und Bauberatung",
    "wof:placetype":"venue"
},
  "geometry": {"coordinates":[8.3397436142,46.9795303345],"type":"Point"}
}