{
  "type": "Feature",
  "properties": {
    "iso:country":"CH",
    "sg:address":"Lindenhubel 3",
    "sg:city":"Kerzers",
    "sg:orig_category":"Unclassifiable Establishments",
    "sg:phone":"+41 31 755 80 80",
    "sg:postcode":"3210",
    "sg:province":"Fribourg",
    "wof:name":"Hedal Ag",
    "wof:placetype":"venue"
},
  "geometry": {"coordinates":[7.2023129463,46.9784317017],"type":"Point"}
}