{
  "type": "Feature",
  "properties": {
    "iso:country":"CH",
    "sg:address":"Industriestrasse 27",
    "sg:city":"Schlieren",
    "sg:orig_category":"Instandhaltung U Reparatur von Automobilen",
    "sg:phone":"+41 17309900",
    "sg:postcode":"8952",
    "sg:province":"Z\u00fcrich",
    "wof:name":"St\u00fctzliw\u00f6sch Ag",
    "wof:placetype":"venue"
},
  "geometry": {"coordinates":[8.4531755447,47.40184021],"type":"Point"}
}