{
  "type": "Feature",
  "properties": {
    "iso:country":"CH",
    "sg:address":"Neuarlesheimerstrasse 1",
    "sg:city":"Dornach",
    "sg:orig_category":"Herstellung von sonstigen Erzeugnissen",
    "sg:phone":"+41 61 701 33 33",
    "sg:postcode":"4143",
    "sg:province":"Solothurn",
    "wof:name":"Ruetsch Michel Blumen",
    "wof:placetype":"venue"
},
  "geometry": {"coordinates":[7.6084580421,47.4885292053],"type":"Point"}
}