{
  "type": "Feature",
  "properties": {
    "iso:country":"CH",
    "sg:address":"Buechlistrasse 27",
    "sg:city":"Galgenen",
    "sg:orig_category":"Verlag von bespielten Tontr\u00e4gern",
    "sg:phone":"+41 55 440 45 70",
    "sg:postcode":"8854",
    "sg:province":"Schwyz",
    "wof:name":"Gambira Music M.gambirasio & D.del Degan",
    "wof:placetype":"venue"
},
  "geometry": {"coordinates":[8.8662643433,47.180721283],"type":"Point"}
}