{
  "type": "Feature",
  "properties": {
    "iso:country":"CH",
    "sg:address":"6025",
    "sg:city":"Neudorf",
    "sg:orig_category":"Schulpflegen",
    "sg:postcode":"6025",
    "sg:province":"Luzern",
    "wof:name":"Schulpflege Der Gemeinde Neudorf",
    "wof:placetype":"venue"
},
  "geometry": {"coordinates":[8.2092485428,47.1774597168],"type":"Point"}
}