{
  "type": "Feature",
  "properties": {
    "iso:country":"CH",
    "sg:address":"Scheibenstrasse 3 3600 Thun. Postfach",
    "sg:city":"Thun",
    "sg:orig_category":"Interessenvertretungen U sonstige Vereinigungen Organisationen der Wohlfahrtspflege",
    "sg:phone":"+41 33 222 46 87",
    "sg:postcode":"3601",
    "sg:province":"Bern",
    "wof:name":"Pro Juventute",
    "wof:placetype":"venue"
},
  "geometry": {"coordinates":[7.6251001358,46.7600402832],"type":"Point"}
}