{
  "type": "Feature",
  "properties": {
    "iso:country":"CH",
    "sg:address":"Via Castel Di Sotto",
    "sg:city":"Novazzano",
    "sg:orig_category":"Detailhandel mit Brot, Back U S\u00fcsswaren",
    "sg:phone":"+41 91 683 49 78",
    "sg:postcode":"6883",
    "sg:province":"Ticino",
    "wof:name":"Ernesto & Bruno Bortolotto Panetteria & Pasticceria",
    "wof:placetype":"venue"
},
  "geometry": {"coordinates":[8.987805,45.843555],"type":"Point"}
}