{
  "type": "Feature",
  "properties": {
    "iso:country":"CH",
    "sg:address":"Untere Bahnhofstrasse",
    "sg:city":"Frutigen",
    "sg:orig_category":"Gewinnung von Kies U Sand Herstellung von Betonerzeugnissen f\u00fcr den Bau",
    "sg:phone":"+41 33 671 25 85",
    "sg:postcode":"3714",
    "sg:province":"Bern",
    "wof:name":"Fbf Frischbeton Ag Frutigen",
    "wof:placetype":"venue"
},
  "geometry": {"coordinates":[7.6503691673,46.5901145935],"type":"Point"}
}