{
  "type": "Feature",
  "properties": {
    "iso:country":"CH",
    "sg:address":"Boulevard Des Philosophes 5",
    "sg:city":"Gen\u00e8ve",
    "sg:orig_category":"Architektur U Ingenieurb\u00fcros",
    "sg:phone":"+41 22 320 11 33",
    "sg:postcode":"1205",
    "sg:province":"Gen\u00e8ve",
    "wof:name":"Cerplata Sa",
    "wof:placetype":"venue"
},
  "geometry": {"coordinates":[6.143774,46.197689],"type":"Point"}
}