{
  "type": "Feature",
  "properties": {
    "iso:country":"CH",
    "sg:address":"General Wille-strasse 320",
    "sg:city":"Meilen",
    "sg:orig_category":"Sonstige Hilfs U Nebent\u00e4tigkeiten f\u00fcr die Schiffahrt",
    "sg:postcode":"8706",
    "sg:province":"Z\u00fcrich",
    "wof:name":"Hafengenossenschaft W\u00e4denswil",
    "wof:placetype":"venue"
},
  "geometry": {"coordinates":[8.6460790634,47.2435073853],"type":"Point"}
}