{
  "type": "Feature",
  "properties": {
    "iso:country":"CH",
    "sg:address":"Ibelweg 18a 6340 Baar. Postfach",
    "sg:city":"Baar",
    "sg:classifiers":[
        {
            "category":"Communications",
            "subcategory":"Radio Station",
            "type":"Services"
        }
    ],
    "sg:postcode":"6340",
    "sg:province":"Zug",
    "sg:tags":[
        "fernsehanstalten",
        "u"
    ],
    "wof:name":"Parx Sonic Gmbh Dienstl., Management, Beratung Usw. Im Bereich Audio, Sounddesign, Content F\u00fcr Medien Mit Schwerpunkt Internet",
    "wof:placetype":"venue"
},
  "geometry": {"coordinates":[8.5254907608,47.1805229187],"type":"Point"}
}