{
  "type": "Feature",
  "properties": {
    "iso:country":"CH",
    "sg:address":"De Castella-weg 16 3280 Greng. Postfach 1519",
    "sg:city":"Greng",
    "sg:orig_category":"Wirtschaftspr\u00fcfung, Steuerberatung U Treuhand",
    "sg:phone":"+41 26 672 97 76",
    "sg:postcode":"3280",
    "sg:province":"Fribourg",
    "wof:name":"Erka Ag",
    "wof:placetype":"venue"
},
  "geometry": {"coordinates":[7.0914301872,46.9135360718],"type":"Point"}
}