{
  "type": "Feature",
  "properties": {
    "iso:country":"CH",
    "sg:address":"St. Gallerstrasse 1 8500 Frauenfeld. Postfach",
    "sg:city":"Frauenfeld",
    "sg:orig_category":"Verwaltung der Rechtspflege, Gerichte",
    "sg:phone":"+41 52 724 25 64",
    "sg:postcode":"8501",
    "sg:province":"Thurgau",
    "wof:name":"Handels-& G\u00fcterrechts- Registeramt Des Kts Thurgau",
    "wof:placetype":"venue"
},
  "geometry": {"coordinates":[8.8986730576,47.5545005798],"type":"Point"}
}