{
  "type": "Feature",
  "properties": {
    "iso:country":"CH",
    "sg:address":"B\u00f6zbergstrasse 128",
    "sg:city":"Effingen",
    "sg:orig_category":"Grosshandel mit sonstigen Maschinen U Ausr\u00fcstungen f\u00fcr Industrie, Handel U Schiffahrt",
    "sg:phone":"+41 62 876 15 24",
    "sg:postcode":"5078",
    "sg:province":"Aargau",
    "wof:name":"Egger Christian",
    "wof:placetype":"venue"
},
  "geometry": {"coordinates":[8.1079435349,47.4873847961],"type":"Point"}
}