{
  "type": "Feature",
  "properties": {
    "iso:country":"CH",
    "sg:address":"Hohr\u00fctistrasse 22",
    "sg:city":"Kloten",
    "sg:orig_category":"Unternehmensberatung",
    "sg:phone":"+41 18134083",
    "sg:postcode":"8302",
    "sg:province":"Z\u00fcrich",
    "wof:name":"Scmc Campestrini Silvio Management Consulting",
    "wof:placetype":"venue"
},
  "geometry": {"coordinates":[8.5840110779,47.4663887024],"type":"Point"}
}