{
  "type": "Feature",
  "properties": {
    "iso:country":"CH",
    "sg:address":"Hardstrasse 18",
    "sg:city":"Bassersdorf",
    "sg:orig_category":"Chemische Industrie Herstellung von Schleifmitteln",
    "sg:phone":"+41 41 499 92 00",
    "sg:postcode":"8303",
    "sg:province":"Z\u00fcrich",
    "wof:name":"Blaser Ag Malters",
    "wof:placetype":"venue"
},
  "geometry": {"coordinates":[8.182725,47.036816],"type":"Point"}
}