{
  "type": "Feature",
  "properties": {
    "iso:country":"CH",
    "sg:address":"Schmiedgasse 11",
    "sg:city":"Zofingen",
    "sg:classifiers":[
        {
            "category":"Professional",
            "subcategory":"Employment Agencies",
            "type":"Services"
        }
    ],
    "sg:postcode":"4800",
    "sg:province":"Aargau",
    "sg:tags":[
        "personal",
        "u",
        "stellenvermittlung"
    ],
    "wof:name":"Ratu Gmbh",
    "wof:placetype":"venue"
},
  "geometry": {"coordinates":[7.946228981,47.287525177],"type":"Point"}
}