{
  "type": "Feature",
  "properties": {
    "iso:country":"CH",
    "sg:address":"Le Grand-chemin 56",
    "sg:city":"Steinhausen",
    "sg:orig_category":"Non-Classified Establishments",
    "sg:postcode":"6312",
    "sg:province":"Zug",
    "wof:name":"Sunstar Hotel Wengen****",
    "wof:placetype":"venue"
},
  "geometry": {"coordinates":[7.921599865,46.6051940918],"type":"Point"}
}