{
  "type": "Feature",
  "properties": {
    "iso:country":"CH",
    "sg:address":"Restockhalde 28",
    "sg:city":"Luzern",
    "sg:orig_category":"Wirtschaftspr\u00fcfung, Steuerberatung U Treuhand",
    "sg:postcode":"6000",
    "sg:province":"Luzern",
    "wof:name":"Rickenmann Guido Rechnungswesen Und Unternehmensberatung",
    "wof:placetype":"venue"
},
  "geometry": {"coordinates":[8.3545656204,47.0426177979],"type":"Point"}
}