{
  "type": "Feature",
  "properties": {
    "iso:country":"CH",
    "sg:address":"Rue Grenade 11",
    "sg:city":"Moudon",
    "sg:orig_category":"Detailhandel mit Bekleidung",
    "sg:phone":"+41 21 905 26 12",
    "sg:postcode":"1510",
    "sg:province":"Vaud",
    "wof:name":"Jean-claude Gobet L'habit-bleu Confection",
    "wof:placetype":"venue"
},
  "geometry": {"coordinates":[6.797865,46.669022],"type":"Point"}
}