{
  "type": "Feature",
  "properties": {
    "iso:country":"CH",
    "sg:address":"Waldeggstrasse 58a 3800 Interlaken. Postfach 89",
    "sg:city":"Interlaken",
    "sg:orig_category":"Sonstiger Grosshandel",
    "sg:postcode":"3800",
    "sg:province":"Bern",
    "wof:name":"Inter Business Service Sauter Beatrice",
    "wof:placetype":"venue"
},
  "geometry": {"coordinates":[7.8543519974,46.6794586182],"type":"Point"}
}