{
  "type": "Feature",
  "properties": {
    "iso:country":"CH",
    "sg:address":"Industrie Rue De L' 21",
    "sg:city":"Del\u00e9mont",
    "sg:orig_category":"Grosshandel mit Textilien",
    "sg:phone":"+41 32 422 07 33",
    "sg:postcode":"2800",
    "sg:province":"Jura",
    "wof:name":"Pap S\u00e0rl",
    "wof:placetype":"venue"
},
  "geometry": {"coordinates":[7.3468317986,47.3650283813],"type":"Point"}
}