{
  "type": "Feature",
  "properties": {
    "iso:country":"CH",
    "sg:address":"6672",
    "sg:city":"Gordevio",
    "sg:orig_category":"Campingpl\u00e4tze Detailhandel mit Zeitungen U Zeitschriften Kioske",
    "sg:phone":"+41 91 795 14 74",
    "sg:postcode":"6672",
    "sg:province":"Ticino",
    "wof:name":"Campeggio Tcs Bellavista",
    "wof:placetype":"venue"
},
  "geometry": {"coordinates":[8.84147,46.143795],"type":"Point"}
}