{
  "type": "Feature",
  "properties": {
    "iso:country":"CH",
    "sg:address":"1690",
    "sg:city":"Villaz-st-pierre",
    "sg:orig_category":"Schulpflegen",
    "sg:phone":"+41 26 653 21 07",
    "sg:postcode":"1690",
    "sg:province":"Fribourg",
    "wof:name":"Commission Scolaire De L'ecole Primaire",
    "wof:placetype":"venue"
},
  "geometry": {"coordinates":[6.9565711021,46.7209243774],"type":"Point"}
}