{
  "type": "Feature",
  "properties": {
    "iso:country":"CH",
    "sg:address":"Friedentalstrasse 41a",
    "sg:city":"Luzern",
    "sg:orig_category":"Elektroinstallation",
    "sg:phone":"+41 52 762 74 40",
    "sg:postcode":"6004",
    "sg:province":"Luzern",
    "wof:name":"Broger Ag",
    "wof:placetype":"venue"
},
  "geometry": {"coordinates":[9.0115089417,47.6054611206],"type":"Point"}
}