{
  "type": "Feature",
  "properties": {
    "iso:country":"CH",
    "sg:address":"Fribourg Route De 48",
    "sg:city":"Marly",
    "sg:orig_category":"Allgemeiner Hoch U Tiefbau",
    "sg:phone":"+41 26 436 12 43",
    "sg:postcode":"1723",
    "sg:province":"Fribourg",
    "wof:name":"Dousse Constructions Sa",
    "wof:placetype":"venue"
},
  "geometry": {"coordinates":[7.150828,46.78566],"type":"Point"}
}