{
  "type": "Feature",
  "properties": {
    "iso:country":"CH",
    "sg:address":"Lochmatten 35",
    "sg:city":"H\u00e4rkingen",
    "sg:classifiers":[
        {
            "category":"Insurance",
            "subcategory":"Insurance Agent",
            "type":"Services"
        }
    ],
    "sg:phone":"+41 33 765 32 13",
    "sg:postcode":"4624",
    "sg:province":"Solothurn",
    "sg:tags":[
        "versicherungsagenturen",
        "-broker"
    ],
    "wof:name":"Emmentalische Mobiliarversich. Agentur Lauenen",
    "wof:placetype":"venue"
},
  "geometry": {"coordinates":[7.3351597786,46.4200019836],"type":"Point"}
}