{
  "type": "Feature",
  "properties": {
    "iso:country":"CH",
    "sg:address":"M\u00fchlengasse 22",
    "sg:city":"Neunkirch",
    "sg:orig_category":"Massagestudios Saunas",
    "sg:phone":"+41 52 681 45 49",
    "sg:postcode":"8213",
    "sg:province":"Schaffhausen",
    "wof:name":"Ursula Tresch",
    "wof:placetype":"venue"
},
  "geometry": {"coordinates":[8.4994163513,47.6906967163],"type":"Point"}
}