{
  "type": "Feature",
  "properties": {
    "addr:full":"Via Vela 3 Chiasso Ticino 6830",
    "addr:housenumber":"3",
    "addr:postcode":"6830",
    "addr:street":"Via Vela;Ticino",
    "iso:country":"CH",
    "sg:address":"Via Vela 3",
    "sg:city":"Chiasso",
    "sg:orig_category":"Architektur U Ingenieurb\u00fcros Markt U Meinungsforschung",
    "sg:phone":"+41 56 664 27 55",
    "sg:postcode":"6830",
    "sg:province":"Ticino",
    "wof:name":"Sheltec Ag",
    "wof:placetype":"venue"
},
  "geometry": {"coordinates":[8.317482,47.282578],"type":"Point"}
}