{
  "type": "Feature",
  "properties": {
    "iso:country":"CH",
    "sg:address":"K\u00f6nizstrasse 194",
    "sg:city":"Liebefeld",
    "sg:orig_category":"Arbeitnehmerverb\u00e4nde",
    "sg:phone":"+41 31 972 21 00",
    "sg:postcode":"3097",
    "sg:province":"Bern",
    "wof:name":"Verband Schweiz.dichtstoff- Verarbeiter Vsd",
    "wof:placetype":"venue"
},
  "geometry": {"coordinates":[7.414632,46.933311],"type":"Point"}
}