{
  "type": "Feature",
  "properties": {
    "iso:country":"CH",
    "sg:address":"B\u00fcndtenweg 5",
    "sg:city":"Gelterkinden",
    "sg:orig_category":"Druck ohne Zeitungsdruck Offsetdruck",
    "sg:phone":"+41 61 981 11 14",
    "sg:postcode":"4460",
    "sg:province":"Basel-Landschaft",
    "wof:name":"Seiler Print Ag",
    "wof:placetype":"venue"
},
  "geometry": {"coordinates":[7.8585019112,47.4603843689],"type":"Point"}
}