{
  "type": "Feature",
  "properties": {
    "iso:country":"CH",
    "sg:address":"Guggisbergstrasse 2",
    "sg:city":"Schwarzenburg",
    "sg:orig_category":"Handelsvermittlung von Textilien, Bekleidung, Schuhen U Lederwaren",
    "sg:phone":"+41 61 811 77 55",
    "sg:postcode":"3150",
    "sg:province":"Bern",
    "wof:name":"4 You Modeberatung Gmbh",
    "wof:placetype":"venue"
},
  "geometry": {"coordinates":[7.5550508499,47.5083274841],"type":"Point"}
}