{
  "type": "Feature",
  "properties": {
    "iso:country":"CH",
    "sg:address":"Via Balestra 15a",
    "sg:city":"Lugano",
    "sg:orig_category":"Advokaturb\u00fcros Notariate",
    "sg:phone":"+41 91 921 30 37",
    "sg:postcode":"6900",
    "sg:province":"Ticino",
    "wof:name":"Michael Becker Studio Legale & Notarile",
    "wof:placetype":"venue"
},
  "geometry": {"coordinates":[8.955385,46.008163],"type":"Point"}
}