{
  "type": "Feature",
  "properties": {
    "iso:country":"CH",
    "sg:address":"Calandastrasse 12",
    "sg:city":"Zizers",
    "sg:orig_category":"Vermietung U Verpachtung von eigenen Immobilien",
    "sg:phone":"+41 81 322 12 29",
    "sg:postcode":"7205",
    "sg:province":"Graubunden",
    "wof:name":"Stock Peter & Co",
    "wof:placetype":"venue"
},
  "geometry": {"coordinates":[9.5614881516,46.9294281006],"type":"Point"}
}