{
  "type": "Feature",
  "properties": {
    "addr:full":"Zollstrasse 58 Z\u00fcrich Z\u00fcrich 8005",
    "addr:housenumber":"58",
    "addr:postcode":"8005",
    "addr:street":"Zollstrasse",
    "iso:country":"CH",
    "sg:address":"Zollstrasse 58",
    "sg:city":"Z\u00fcrich",
    "sg:classifiers":[
        {
            "category":"Professional",
            "subcategory":"Research",
            "type":"Services"
        }
    ],
    "sg:phone":"+41 12741333",
    "sg:postcode":"8005",
    "sg:province":"Z\u00fcrich",
    "sg:tags":[
        "database"
    ],
    "wof:name":"Thomson Corporation Switzerland Ag",
    "wof:placetype":"venue"
},
  "geometry": {"coordinates":[8.533161,47.380871],"type":"Point"}
}