{
  "type": "Feature",
  "properties": {
    "iso:country":"CH",
    "sg:address":"Comble-emine 15",
    "sg:city":"Cernier",
    "sg:orig_category":"Injection Moulded Plastic Parts For Small Series",
    "sg:phone":"+41 32 853 46 32",
    "sg:postcode":"2053",
    "sg:province":"Neuch\u00e2tel",
    "wof:name":"Pierre Bercher Sa",
    "wof:placetype":"venue"
},
  "geometry": {"coordinates":[6.9035358429,47.0576477051],"type":"Point"}
}