{
  "type": "Feature",
  "properties": {
    "iso:country":"CH",
    "sg:address":"Rue De Hollande 16",
    "sg:city":"Gen\u00e8ve",
    "sg:orig_category":"Privatbanken",
    "sg:phone":"+41 31 313 12 12",
    "sg:postcode":"1204",
    "sg:province":"Gen\u00e8ve",
    "wof:name":"Bordier Capital Sa",
    "wof:placetype":"venue"
},
  "geometry": {"coordinates":[7.4445819855,46.9492034912],"type":"Point"}
}