{
  "type": "Feature",
  "properties": {
    "iso:country":"CH",
    "sg:address":"Eschenring 5",
    "sg:city":"Zug",
    "sg:orig_category":"Herstellung von Schreibwaren U B\u00fcrobedarf aus Papier, Karton U Pappe",
    "sg:postcode":"6300",
    "sg:province":"Zug",
    "wof:name":"Papco Sa",
    "wof:placetype":"venue"
},
  "geometry": {"coordinates":[8.5180444717,47.1818389893],"type":"Point"}
}