{
  "type": "Feature",
  "properties": {
    "iso:country":"CH",
    "sg:address":"Klotenerstrasse 20",
    "sg:city":"R\u00fcmlang",
    "sg:classifiers":[
        {
            "category":"Utilities",
            "type":"Services"
        }
    ],
    "sg:phone":"+41 21 925 87 87",
    "sg:postcode":"8153",
    "sg:province":"Z\u00fcrich",
    "sg:tags":[
        "raw",
        "energy",
        "material"
    ],
    "wof:name":"Compagnie Industrielle Et Commerciale Du Gaz Sa",
    "wof:placetype":"venue"
},
  "geometry": {"coordinates":[15.0666999817,40.9967689514],"type":"Point"}
}