{
  "type": "Feature",
  "properties": {
    "iso:country":"CH",
    "sg:address":"Chemin De Gravernay 17",
    "sg:city":"Bussigny-lausanne",
    "sg:classifiers":[
        {
            "category":"Insurance",
            "subcategory":"Insurance Agent",
            "type":"Services"
        }
    ],
    "sg:phone":"+41 21 701 32 18",
    "sg:postcode":"1030",
    "sg:province":"Vaud",
    "sg:tags":[
        "versicherungsagenturen",
        "-broker"
    ],
    "wof:name":"Carlo Fazzi Assurances",
    "wof:placetype":"venue"
},
  "geometry": {"coordinates":[6.5478749275,46.5516777039],"type":"Point"}
}