{
  "type": "Feature",
  "properties": {
    "iso:country":"CH",
    "sg:address":"Sommeraustrasse 10",
    "sg:city":"Schlattingen",
    "sg:orig_category":"Einrahmungen",
    "sg:phone":"+41 52 657 52 73",
    "sg:postcode":"8255",
    "sg:province":"Thurgau",
    "wof:name":"Kerstin Amon Bilderrahmenvergoldungen",
    "wof:placetype":"venue"
},
  "geometry": {"coordinates":[8.7699747086,47.6639137268],"type":"Point"}
}