{
  "type": "Feature",
  "properties": {
    "iso:country":"CH",
    "sg:address":"Chemin Rieu 6",
    "sg:city":"Gen\u00e8ve",
    "sg:orig_category":"Architekturb\u00fcros",
    "sg:phone":"+41 22 735 29 86",
    "sg:postcode":"1208",
    "sg:province":"Gen\u00e8ve",
    "wof:name":"Thomas-philippe Fritschi Bureau D'architecture",
    "wof:placetype":"venue"
},
  "geometry": {"coordinates":[6.165531,46.195721],"type":"Point"}
}