{
  "type": "Feature",
  "properties": {
    "iso:country":"CH",
    "sg:address":"Riva Dal Garavell",
    "sg:city":"Morcote",
    "sg:orig_category":"Herstellung von keramischen Haushaltswaren U Ziergegenst\u00e4nden",
    "sg:phone":"+41 91 996 13 49",
    "sg:postcode":"6922",
    "sg:province":"Ticino",
    "wof:name":"Adriano Antonini Ceramiche Artistiche",
    "wof:placetype":"venue"
},
  "geometry": {"coordinates":[8.9194402695,45.924369812],"type":"Point"}
}