{
  "type": "Feature",
  "properties": {
    "iso:country":"CH",
    "sg:address":"Panoramaweg 4",
    "sg:city":"Othmarsingen",
    "sg:orig_category":"Ingenieurb\u00fcros Umwelttechnik and \u00d6kologie",
    "sg:phone":"+41 61 911 80 77",
    "sg:postcode":"5504",
    "sg:province":"Aargau",
    "wof:name":"Dr. Narendra Prasad Geocom",
    "wof:placetype":"venue"
},
  "geometry": {"coordinates":[7.6698288918,47.4492912292],"type":"Point"}
}