{
  "type": "Feature",
  "properties": {
    "iso:country":"CH",
    "sg:address":"Bahnhofstr. 25 8280 Kreuzlingen. Postfach",
    "sg:city":"Kreuzlingen",
    "sg:orig_category":"Fachdetailhandel in Verkaufsr\u00e4umen",
    "sg:postcode":"8280",
    "sg:province":"Thurgau",
    "wof:name":"Ditz E. Optiker",
    "wof:placetype":"venue"
},
  "geometry": {"coordinates":[9.1699781418,47.6520614624],"type":"Point"}
}