{
  "type": "Feature",
  "properties": {
    "iso:country":"CH",
    "sg:address":"Verbier 1934 Le Ch\u00e2ble Vs. Postfach",
    "sg:city":"Verbier",
    "sg:orig_category":"Detailhandel mit Bekleidung",
    "sg:postcode":"1936",
    "sg:province":"Valais",
    "wof:name":"Dereck Guy",
    "wof:placetype":"venue"
},
  "geometry": {"coordinates":[7.56338,46.929745],"type":"Point"}
}