{
  "type": "Feature",
  "properties": {
    "iso:country":"CH",
    "sg:address":"Via Ross\u00e8e 3",
    "sg:city":"Caslano",
    "sg:classifiers":[
        {
            "category":"Restaurant",
            "type":"Food & Drink"
        }
    ],
    "sg:phone":"+41 91 606 65 66",
    "sg:postcode":"6987",
    "sg:province":"Ticino",
    "wof:name":"Osteria Debarcadero",
    "wof:placetype":"venue"
},
  "geometry": {"coordinates":[8.8755178452,45.976940155],"type":"Point"}
}