{
  "type": "Feature",
  "properties": {
    "iso:country":"CH",
    "sg:address":"Im Ifang 6 8307 Effretikon. Postfach",
    "sg:city":"Tagelswangen",
    "sg:orig_category":"Finanzierungsinstitutionen Unternehmensberatung",
    "sg:phone":"+41 22 328 29 11",
    "sg:postcode":"8317",
    "sg:province":"Z\u00fcrich",
    "wof:name":"Rsi Asset Management Sa G\u00e9rance De Fortunes",
    "wof:placetype":"venue"
},
  "geometry": {"coordinates":[6.1444330215,46.194480896],"type":"Point"}
}