{
  "type": "Feature",
  "properties": {
    "iso:country":"CH",
    "sg:address":"Carmenstrasse 28 8032 Z\u00fcrich. Postfach 1724",
    "sg:city":"Z\u00fcrich",
    "sg:orig_category":"Personal U Stellenvermittlung Verlagsgewerbe",
    "sg:phone":"+41 12546969",
    "sg:postcode":"8032",
    "sg:province":"Z\u00fcrich",
    "wof:name":"Jobindex Media Ag",
    "wof:placetype":"venue"
},
  "geometry": {"coordinates":[8.5623130798,47.3684158325],"type":"Point"}
}