{
  "type": "Feature",
  "properties": {
    "addr:full":"La Bourdonnette St-oyens Vaud 1187",
    "addr:housenumber":"1187",
    "iso:country":"CH",
    "sg:address":"La Bourdonnette",
    "sg:city":"St-oyens",
    "sg:orig_category":"Bauschreinerei Zimmerei, Dachdeckerei, Bauspenglerei U Abdichtung",
    "sg:phone":"+41 21 828 22 10",
    "sg:postcode":"1187",
    "sg:province":"Vaud",
    "wof:name":"Cl\u00e9ment Charpentes Sa",
    "wof:placetype":"venue"
},
  "geometry": {"coordinates":[6.308816,46.498707],"type":"Point"}
}