{
  "type": "Feature",
  "properties": {
    "iso:country":"CH",
    "sg:address":"Aarwangenstrasse 2",
    "sg:city":"Langenthal",
    "sg:orig_category":"Warenh\u00e4user",
    "sg:phone":"+41 24 473 62 63",
    "sg:postcode":"4900",
    "sg:province":"Bern",
    "wof:name":"Manor",
    "wof:placetype":"venue"
},
  "geometry": {"coordinates":[6.9502420425,46.2580986023],"type":"Point"}
}