{
  "type": "Feature",
  "properties": {
    "iso:country":"CH",
    "sg:address":"Hauptstrasse 148",
    "sg:city":"B\u00fchler",
    "sg:orig_category":"Arztpraxen",
    "sg:phone":"+41 71 245 30 45",
    "sg:postcode":"9055",
    "sg:province":"Appenzell Ausserrhoden",
    "wof:name":"Dr.med.hans-beat Zangerl Arzt F\u00fcr Allgemeine Medizin",
    "wof:placetype":"venue"
},
  "geometry": {"coordinates":[9.390833,47.429855],"type":"Point"}
}