{
  "type": "Feature",
  "properties": {
    "iso:country":"CH",
    "sg:address":"T\u00f6distrasse 68 8812 Horgen. Postfach",
    "sg:city":"Horgen",
    "sg:orig_category":"Herstellung von Mess U Kontrollinstrumenten U vorrichtungen",
    "sg:phone":"+41 32 931 45 19",
    "sg:postcode":"8810",
    "sg:province":"Z\u00fcrich",
    "wof:name":"Huguenin O. Et Sester J.-c., My Styl",
    "wof:placetype":"venue"
},
  "geometry": {"coordinates":[6.7570548058,47.0617256165],"type":"Point"}
}