{
  "type": "Feature",
  "properties": {
    "iso:country":"CH",
    "sg:address":"1897",
    "sg:city":"Bouveret",
    "sg:orig_category":"Kinderkrippen U horte",
    "sg:postcode":"1897",
    "sg:province":"Valais",
    "wof:name":"Garderie D'enfants Communale",
    "wof:placetype":"venue"
},
  "geometry": {"coordinates":[6.8527798653,46.3853187561],"type":"Point"}
}