{
  "type": "Feature",
  "properties": {
    "iso:country":"CH",
    "sg:address":"Bachtobelstrasse 28",
    "sg:city":"Z\u00fcrich",
    "sg:orig_category":"Elektroinstallation Herstellung von sonstigen elektrischen Ausr\u00fcstungen",
    "sg:phone":"+41 14621511",
    "sg:postcode":"8045",
    "sg:province":"Z\u00fcrich",
    "wof:name":"Elektro Dittli Ag",
    "wof:placetype":"venue"
},
  "geometry": {"coordinates":[8.5159540176,47.361125946],"type":"Point"}
}