{
  "type": "Feature",
  "properties": {
    "iso:country":"CH",
    "sg:address":"Emmentalstrasse 23",
    "sg:city":"Oberburg",
    "sg:orig_category":"Detailhandel mit Brot, Back U S\u00fcsswaren",
    "sg:phone":"+41 34 422 28 28",
    "sg:postcode":"3414",
    "sg:province":"Bern",
    "wof:name":"Hans Hirschi B\u00e4ckerei-konditorei M\u00e4rki",
    "wof:placetype":"venue"
},
  "geometry": {"coordinates":[7.627553,47.037849],"type":"Point"}
}