{
  "type": "Feature",
  "properties": {
    "iso:country":"CH",
    "sg:address":"Bahnhof",
    "sg:city":"Weinfelden",
    "sg:orig_category":"Reiseb\u00fcros",
    "sg:phone":"+41 19322010",
    "sg:postcode":"8570",
    "sg:province":"Thurgau",
    "wof:name":"Sbb Reiseb\u00fcro",
    "wof:placetype":"venue"
},
  "geometry": {"coordinates":[8.8024339676,47.3280944824],"type":"Point"}
}