{
  "type": "Feature",
  "properties": {
    "iso:country":"CH",
    "sg:address":"Rue Du Simplon 3",
    "sg:city":"Lausanne",
    "sg:orig_category":"Hundesalons",
    "sg:phone":"+41 21 616 08 78",
    "sg:postcode":"1006",
    "sg:province":"Vaud",
    "wof:name":"Diane Stiner Au Bonheur Des Chiens",
    "wof:placetype":"venue"
},
  "geometry": {"coordinates":[6.6320428848,46.5153312683],"type":"Point"}
}