{
  "type": "Feature",
  "properties": {
    "iso:country":"CH",
    "sg:address":"Heizenholz 39 8049 Z\u00fcrich. Postfach",
    "sg:city":"Z\u00fcrich",
    "sg:orig_category":"Non-Classified Establishments",
    "sg:postcode":"8049",
    "sg:province":"Z\u00fcrich",
    "wof:name":"Denzler Ofen-chemin\u00e9ebau, Keramische Wand Und Bodenbel\u00e4ge",
    "wof:placetype":"venue"
},
  "geometry": {"coordinates":[8.4861345291,47.4113578796],"type":"Point"}
}