{
  "type": "Feature",
  "properties": {
    "iso:country":"CH",
    "sg:address":"Zona Industriale 3",
    "sg:city":"Quartino",
    "sg:orig_category":"M\u00f6belveredelung U restaurierung Verlegen von Fussboden",
    "sg:phone":"+41 91 795 30 93",
    "sg:postcode":"6572",
    "sg:province":"Ticino",
    "wof:name":"Bonetti Gianfranco",
    "wof:placetype":"venue"
},
  "geometry": {"coordinates":[8.8953781128,46.1506347656],"type":"Point"}
}