{
  "type": "Feature",
  "properties": {
    "iso:country":"CH",
    "sg:address":"Dorfstr. 17 8315 Lindau. Postfach",
    "sg:city":"Grafstal",
    "sg:orig_category":"Herstellung von sonstigen elektrischen Ausr\u00fcstungen",
    "sg:postcode":"8310",
    "sg:province":"Z\u00fcrich",
    "wof:name":"Frt Electronic, J\u00fcrg Schalcher",
    "wof:placetype":"venue"
},
  "geometry": {"coordinates":[8.6956148148,47.443069458],"type":"Point"}
}