{
  "type": "Feature",
  "properties": {
    "iso:country":"CH",
    "sg:address":"Fischerh\u00e4userstrasse 26",
    "sg:city":"Schaffhausen",
    "sg:orig_category":"Non-Classified Establishments",
    "sg:postcode":"8200",
    "sg:province":"Schaffhausen",
    "wof:name":"Roland Hofer, Dipl. Arch. Eth Bsa / Sia / Swb",
    "wof:placetype":"venue"
},
  "geometry": {"coordinates":[8.6433830261,47.6955757141],"type":"Point"}
}