{
  "type": "Feature",
  "properties": {
    "iso:country":"CH",
    "sg:address":"Schmittenstrasse 4",
    "sg:city":"Kreuzlingen",
    "sg:orig_category":"Erbringung von Dienstleistungen f\u00fcr Unternehmen",
    "sg:postcode":"8280",
    "sg:province":"Thurgau",
    "wof:name":"Schilling Andreas, Trend-cars-graphik",
    "wof:placetype":"venue"
},
  "geometry": {"coordinates":[9.1603841782,47.6452903748],"type":"Point"}
}