{
  "type": "Feature",
  "properties": {
    "iso:country":"CH",
    "sg:address":"Rosenmattstrasse 20",
    "sg:city":"Leuzigen",
    "sg:orig_category":"Architektur U Ingenieurb\u00fcros Architekturb\u00fcros",
    "sg:phone":"+41 32 679 22 77",
    "sg:postcode":"3297",
    "sg:province":"Bern",
    "wof:name":"Architekturb\u00fcro Gerber Andr\u00e9",
    "wof:placetype":"venue"
},
  "geometry": {"coordinates":[7.457872,47.169998],"type":"Point"}
}