{
  "type": "Feature",
  "properties": {
    "iso:country":"CH",
    "sg:address":"Schwerzistrasse 4",
    "sg:city":"Freienbach",
    "sg:orig_category":"Elektrischer Leitungsbau Rohrleitungsbau",
    "sg:phone":"+41 62 752 88 88",
    "sg:postcode":"8807",
    "sg:province":"Schwyz",
    "wof:name":"Kaspar Kabel-& Leitungsbau Ag",
    "wof:placetype":"venue"
},
  "geometry": {"coordinates":[7.9742679596,47.326210022],"type":"Point"}
}