{
  "type": "Feature",
  "properties": {
    "iso:country":"CH",
    "sg:address":"Chemin Des Clochettes 22b 1200 Gen\u00e8ve. Postfach",
    "sg:city":"Gen\u00e8ve",
    "sg:orig_category":"Wirtschaftspr\u00fcfung, Steuerberatung U Treuhand",
    "sg:postcode":"1206",
    "sg:province":"Gen\u00e8ve",
    "wof:name":"Fiduciaire Monique Nicolaidis",
    "wof:placetype":"venue"
},
  "geometry": {"coordinates":[6.1591620445,46.1890678406],"type":"Point"}
}