{
  "type": "Feature",
  "properties": {
    "iso:country":"CH",
    "sg:address":"Schmitterstrasse 31",
    "sg:city":"Diepoldsau",
    "sg:orig_category":"Handelsvermittlung U Grosshandel R\u00fcckgewinnung U Vorbereitung f\u00fcr die Wiederverwertung Recycling",
    "sg:phone":"+41 71 733 21 02",
    "sg:postcode":"9444",
    "sg:province":"St. Gallen",
    "wof:name":"Emil Kehl Gmbh",
    "wof:placetype":"venue"
},
  "geometry": {"coordinates":[9.6558856964,47.3895721436],"type":"Point"}
}