{
  "type": "Feature",
  "properties": {
    "iso:country":"CH",
    "sg:address":"Stauffacherstrasse 130a",
    "sg:city":"Bern",
    "sg:classifiers":[
        {
            "category":"Home & Garden",
            "subcategory":"Hardware",
            "type":"Retail Goods"
        }
    ],
    "sg:phone":"+41 31 332 55 51",
    "sg:postcode":"3014",
    "sg:province":"Bern",
    "sg:tags":[
        "steel",
        "stainless",
        "banister"
    ],
    "wof:name":"Werner W\u00fcthrich Schlosserei",
    "wof:placetype":"venue"
},
  "geometry": {"coordinates":[7.465429,46.968479],"type":"Point"}
}