{
  "type": "Feature",
  "properties": {
    "iso:country":"CH",
    "sg:address":"3067",
    "sg:city":"Boll",
    "sg:orig_category":"RESTAURANTS: TEA-ROOMS",
    "sg:postcode":"3067",
    "sg:province":"Bern",
    "wof:name":"Schneider Stefan Restaurant Schenkenbergerhof",
    "wof:placetype":"venue"
},
  "geometry": {"coordinates":[8.096414566,47.4363288879],"type":"Point"}
}