{
  "type": "Feature",
  "properties": {
    "iso:country":"CH",
    "sg:address":"Sch\u00f6nb\u00fcel 6215 Berom\u00fcnster. Postfach 121",
    "sg:city":"Berom\u00fcnster",
    "sg:orig_category":"Grosshandel mit B\u00fcromaschinen Grosshandel mit Geschenkartikeln U Souvenirs",
    "sg:phone":"+41 79 444 62 45",
    "sg:postcode":"6215",
    "sg:province":"Luzern",
    "wof:name":"Ravaria Rast Beat",
    "wof:placetype":"venue"
},
  "geometry": {"coordinates":[8.186085701,47.2063217163],"type":"Point"}
}