{
  "type": "Feature",
  "properties": {
    "iso:country":"CH",
    "sg:address":"1261 Marchissy Case Postale 22",
    "sg:city":"Marchissy",
    "sg:orig_category":"Sicherheitsdienste",
    "sg:phone":"+41 22 368 18 50",
    "sg:postcode":"1261",
    "sg:province":"Vaud",
    "wof:name":"Gsp,guardian & Security Partner,st\u00e9 Suisse De S\u00e9curit\u00e9",
    "wof:placetype":"venue"
},
  "geometry": {"coordinates":[6.2470231056,46.4884986877],"type":"Point"}
}