{
  "type": "Feature",
  "properties": {
    "iso:country":"CH",
    "sg:address":"Milchbuckstrasse 70",
    "sg:city":"Z\u00fcrich",
    "sg:orig_category":"Unclassifiable Establishments",
    "sg:postcode":"8057",
    "sg:province":"Z\u00fcrich",
    "wof:name":"Islamisch-kultureller Verein Ahle Beyt",
    "wof:placetype":"venue"
},
  "geometry": {"coordinates":[8.5450496674,47.3937797546],"type":"Point"}
}