{
  "type": "Feature",
  "properties": {
    "iso:country":"CH",
    "sg:address":"S\u00fcdstrasse 36",
    "sg:city":"Kriens",
    "sg:orig_category":"K\u00fcnstlerische Schulen",
    "sg:phone":"+41 41 320 57 42",
    "sg:postcode":"6010",
    "sg:province":"Luzern",
    "wof:name":"Musikschule Der Gemeinde Kriens,meiersmattschulhaus 1",
    "wof:placetype":"venue"
},
  "geometry": {"coordinates":[8.2693300247,47.0320701599],"type":"Point"}
}