{
  "type": "Feature",
  "properties": {
    "addr:full":"Im Wiesengrund 14 8700 K\u00fcsnacht Zh. Postfach Z\u00fcrich Z\u00fcrich 8001",
    "addr:housenumber":"14",
    "addr:postcode":"8700;8001",
    "addr:street":"Im Wiesengrund",
    "iso:country":"CH",
    "sg:address":"Im Wiesengrund 14 8700 K\u00fcsnacht Zh. Postfach",
    "sg:city":"Z\u00fcrich",
    "sg:orig_category":"Betrieb U technische Hilfsdienste des Kultur U Unterhaltungswesens",
    "sg:phone":"+41 14620215",
    "sg:postcode":"8001",
    "sg:province":"Z\u00fcrich",
    "wof:name":"Crescendo, Hitz Marianne K. Party-service, Veranstaltungen; Organisation",
    "wof:placetype":"venue"
},
  "geometry": {"coordinates":[8.589898,47.308613],"type":"Point"}
}