{
  "type": "Feature",
  "properties": {
    "iso:country":"CH",
    "sg:address":"Place Centrale 5",
    "sg:city":"Penthalaz",
    "sg:orig_category":"Wasserversorgung",
    "sg:phone":"+41 21 861 00 31",
    "sg:postcode":"1305",
    "sg:province":"Vaud",
    "wof:name":"Service Des Eaux De La Commune De Penthalaz",
    "wof:placetype":"venue"
},
  "geometry": {"coordinates":[6.5242218971,46.6101875305],"type":"Point"}
}