{
  "type": "Feature",
  "properties": {
    "iso:country":"CH",
    "sg:address":"Erlenweg 19",
    "sg:city":"Herzogenbuchsee",
    "sg:orig_category":"Detailhandel mit Geschenkartikeln U Souvenirs",
    "sg:phone":"+41 62 961 47 52",
    "sg:postcode":"3360",
    "sg:province":"Bern",
    "wof:name":"Ruth Weber Kunsthandwerk",
    "wof:placetype":"venue"
},
  "geometry": {"coordinates":[7.7053031921,47.1971244812],"type":"Point"}
}