{
  "type": "Feature",
  "properties": {
    "iso:country":"CH",
    "sg:address":"Ueberlandstrasse 350",
    "sg:city":"Z\u00fcrich",
    "sg:orig_category":"Kosmetikinstitute",
    "sg:phone":"+41 13223713",
    "sg:postcode":"8051",
    "sg:province":"Z\u00fcrich",
    "wof:name":"Permanent-kosmetik, M\u00fcller Kocherhans Evelyn",
    "wof:placetype":"venue"
},
  "geometry": {"coordinates":[8.5799713135,47.4085350037],"type":"Point"}
}