{
  "type": "Feature",
  "properties": {
    "iso:country":"CH",
    "sg:address":"Via Pometta 3",
    "sg:city":"Bellinzona",
    "sg:orig_category":"Grosshandel mit Obst U Gem\u00fcse",
    "sg:phone":"+41 91 821 15 15",
    "sg:postcode":"6500",
    "sg:province":"Ticino",
    "wof:name":"Frutta Banfi Sa",
    "wof:placetype":"venue"
},
  "geometry": {"coordinates":[9.0168876648,46.1943817139],"type":"Point"}
}