{
  "type": "Feature",
  "properties": {
    "addr:full":"Ober Kasteln Menznau Luzern 6122",
    "addr:postcode":"6122",
    "addr:street":"Ober Kasteln",
    "iso:country":"CH",
    "sg:address":"Ober Kasteln",
    "sg:city":"Menznau",
    "sg:orig_category":"Detailhandel mit Computern U Software Wartung U Reparatur von B\u00fcromaschinen, Datenverarbeitungsger\u00e4t",
    "sg:postcode":"6122",
    "sg:province":"Luzern",
    "wof:name":"Sonja Scherer Pc Service",
    "wof:placetype":"venue"
},
  "geometry": {"coordinates":[8.027595,47.081619],"type":"Point"}
}