{
  "type": "Feature",
  "properties": {
    "iso:country":"CH",
    "sg:address":"Hauptstrasse 11",
    "sg:city":"Giebenach",
    "sg:orig_category":"G\u00fcterbef\u00f6rderung im Strassenverkehr",
    "sg:phone":"+41 61 811 11 35",
    "sg:postcode":"4304",
    "sg:province":"Basel-Landschaft",
    "wof:name":"Straumann Alex, Transporte",
    "wof:placetype":"venue"
},
  "geometry": {"coordinates":[7.7476081848,47.5239372253],"type":"Point"}
}