{
  "type": "Feature",
  "properties": {
    "iso:country":"CH",
    "sg:address":"Lehnstrasse 16",
    "sg:city":"Appenzell",
    "sg:orig_category":"Unclassifiable Establishments",
    "sg:postcode":"9050",
    "sg:province":"Appenzell Innerhoden",
    "wof:name":"Ventura Holding Ag",
    "wof:placetype":"venue"
},
  "geometry": {"coordinates":[9.4068861008,47.3373641968],"type":"Point"}
}