{
  "type": "Feature",
  "properties": {
    "iso:country":"CH",
    "sg:address":"Dorfstrasse 4 6275 Ballwil. Postfach 200",
    "sg:city":"Ballwil",
    "sg:orig_category":"Herstellung von Metallerzeugnissen ohne Maschinenbau Herstellung von medizinischen U chirurgischen G",
    "sg:phone":"+41 41 449 78 88",
    "sg:postcode":"6275",
    "sg:province":"Luzern",
    "wof:name":"Belimed Ag",
    "wof:placetype":"venue"
},
  "geometry": {"coordinates":[8.3177623749,47.1526222229],"type":"Point"}
}