{
  "type": "Feature",
  "properties": {
    "iso:country":"CH",
    "sg:address":"Pfalzgasse 6 8001 Z\u00fcrich. Postfach",
    "sg:city":"Z\u00fcrich",
    "sg:orig_category":"Arztpraxen",
    "sg:phone":"+41 12118888",
    "sg:postcode":"8022",
    "sg:province":"Z\u00fcrich",
    "wof:name":"Dr.med.josef Huwyler Spezialarzt Fmh",
    "wof:placetype":"venue"
},
  "geometry": {"coordinates":[8.540938,47.372654],"type":"Point"}
}