{
  "type": "Feature",
  "properties": {
    "iso:country":"CH",
    "sg:address":"Bleichenbergstrasse 12",
    "sg:city":"Biberist",
    "sg:orig_category":"Herstellung von Elektrizit\u00e4tsverteilungs U schalteinrichtungen Herstellung von Metallerzeugnissen oh",
    "sg:phone":"+41 32 672 20 48",
    "sg:postcode":"4562",
    "sg:province":"Solothurn",
    "wof:name":"Kurth & Co.",
    "wof:placetype":"venue"
},
  "geometry": {"coordinates":[7.5634789467,47.1884727478],"type":"Point"}
}