{
  "type": "Feature",
  "properties": {
    "iso:country":"CH",
    "sg:address":"St. Wolfgangstrasse 27",
    "sg:city":"H\u00fcnenberg",
    "sg:orig_category":"Sonstiger Grosshandel",
    "sg:phone":"+41 41 781 03 33",
    "sg:postcode":"6331",
    "sg:province":"Zug",
    "wof:name":"F\u00fcrthaler Import & Export",
    "wof:placetype":"venue"
},
  "geometry": {"coordinates":[8.4239206314,47.1791038513],"type":"Point"}
}