{
  "type": "Feature",
  "properties": {
    "iso:country":"CH",
    "sg:address":"Im Esterli 9",
    "sg:city":"Riehen",
    "sg:orig_category":"Grosshandel mit Textilien",
    "sg:phone":"+41 61015197",
    "sg:postcode":"4125",
    "sg:province":"Basel-Stadt",
    "wof:name":"Cbs Shop Kiosk Rempfer",
    "wof:placetype":"venue"
},
  "geometry": {"coordinates":[7.6445088387,47.5763244629],"type":"Point"}
}