{
  "type": "Feature",
  "properties": {
    "iso:country":"CH",
    "sg:address":"Breitgasse 20",
    "sg:city":"Arth",
    "sg:orig_category":"HERSTELLUNG VON GER\u00c4TEN DER ELEKTRIZIT\u00c4TSERZEUGUNG, -VERTEILUNG U.\u00c4 Herstellung von Mess U Kontrolli",
    "sg:phone":"+41 71 970 09 70",
    "sg:postcode":"6415",
    "sg:province":"Schwyz",
    "wof:name":"Innotest Ag",
    "wof:placetype":"venue"
},
  "geometry": {"coordinates":[8.9591989517,47.4640159607],"type":"Point"}
}