{
  "type": "Feature",
  "properties": {
    "iso:country":"CH",
    "sg:address":"Les Longues Raies 2",
    "sg:city":"Sonceboz-sombeval",
    "sg:orig_category":"Grosshandel mit Getr\u00e4nken",
    "sg:phone":"+41 22 342 48 60",
    "sg:postcode":"2605",
    "sg:province":"Bern",
    "wof:name":"Austin Nichols & Co Inc. Succle De Gen\u00e8ve",
    "wof:placetype":"venue"
},
  "geometry": {"coordinates":[6.133035183,46.1768035889],"type":"Point"}
}