{
  "type": "Feature",
  "properties": {
    "iso:country":"CH",
    "sg:address":"Steinlerweg 11",
    "sg:city":"Niederdorf",
    "sg:orig_category":"Wirtschaftspr\u00fcfung, Steuerberatung U Treuhand",
    "sg:postcode":"4435",
    "sg:province":"Basel-Landschaft",
    "wof:name":"Kst-treuhand, Stuck-hess Kathrin",
    "wof:placetype":"venue"
},
  "geometry": {"coordinates":[7.7556138039,47.4090309143],"type":"Point"}
}