{
  "type": "Feature",
  "properties": {
    "iso:country":"CH",
    "sg:address":"Rosengarten",
    "sg:city":"M\u00fchlehorn",
    "sg:orig_category":"Mit dem Versicherungsgewerbe verbundene T\u00e4tigkeiten Verwaltung von Immobilien",
    "sg:postcode":"8874",
    "sg:province":"Glarus",
    "wof:name":"Vtb Versicherungs-treuhand Beider Basel Gmbh",
    "wof:placetype":"venue"
},
  "geometry": {"coordinates":[9.1736850739,47.1170196533],"type":"Point"}
}