{
  "type": "Feature",
  "properties": {
    "iso:country":"CH",
    "sg:address":"Bodenackerstasse 52",
    "sg:city":"Dulliken",
    "sg:orig_category":"Sonstiger Grosshandel",
    "sg:phone":"+41 62 295 49 78",
    "sg:postcode":"4657",
    "sg:province":"Solothurn",
    "wof:name":"Hort Hans-peter",
    "wof:placetype":"venue"
},
  "geometry": {"coordinates":[7.9526119232,47.3507156372],"type":"Point"}
}