{
  "type": "Feature",
  "properties": {
    "iso:country":"CH",
    "sg:address":"Dreibrunnenstrasse 5",
    "sg:city":"Sirnach",
    "sg:orig_category":"Grosshandel mit lebenden Tieren",
    "sg:phone":"+41 71 966 26 88",
    "sg:postcode":"8370",
    "sg:province":"Thurgau",
    "wof:name":"Emil Koster Viehhandel",
    "wof:placetype":"venue"
},
  "geometry": {"coordinates":[9.0221967697,47.4650192261],"type":"Point"}
}