{
  "type": "Feature",
  "properties": {
    "iso:country":"CH",
    "sg:address":"Weissbadstrasse 7",
    "sg:city":"Appenzell",
    "sg:orig_category":"Detailhandel mit Musikinstrumenten Detailhandel mit elektrischen Haushalts-,Radio U Fernsehger\u00e4ten s",
    "sg:phone":"+41 71 787 46 40",
    "sg:postcode":"9050",
    "sg:province":"Appenzell Innerhoden",
    "wof:name":"Broger Walter",
    "wof:placetype":"venue"
},
  "geometry": {"coordinates":[9.4118356705,47.3299064636],"type":"Point"}
}