{
  "type": "Feature",
  "properties": {
    "iso:country":"CH",
    "sg:address":"Industriestrasse 13a",
    "sg:city":"Zug",
    "sg:orig_category":"Herstellung von nichtelektrischen Haushaltsger\u00e4ten Private Haushalte",
    "sg:phone":"+41 41 727 80 39",
    "sg:postcode":"6300",
    "sg:province":"Zug",
    "wof:name":"Vitaactiva Ag",
    "wof:placetype":"venue"
},
  "geometry": {"coordinates":[8.5183839798,47.1725463867],"type":"Point"}
}