{
  "type": "Feature",
  "properties": {
    "addr:full":"Hauptgasse 54 Murten Fribourg 3280",
    "addr:housenumber":"54",
    "addr:postcode":"3280",
    "addr:street":"Hauptgasse",
    "iso:country":"CH",
    "sg:address":"Hauptgasse 54",
    "sg:city":"Murten",
    "sg:orig_category":"Advokaturb\u00fcros Notariate",
    "sg:phone":"+41 41 870 50 65",
    "sg:postcode":"3280",
    "sg:province":"Fribourg",
    "wof:name":"Markus Z\u00fcst Advokatur-& Notariatsb\u00fcro",
    "wof:placetype":"venue"
},
  "geometry": {"coordinates":[8.647308,46.877003],"type":"Point"}
}