{
  "type": "Feature",
  "properties": {
    "iso:country":"CH",
    "sg:address":"Luisenstrasse 17",
    "sg:city":"Z\u00fcrich",
    "sg:orig_category":"Webdesign",
    "sg:phone":"+41 43 366 87 29",
    "sg:postcode":"8005",
    "sg:province":"Z\u00fcrich",
    "wof:name":"Renato Morichetti Morichetti Studio's",
    "wof:placetype":"venue"
},
  "geometry": {"coordinates":[8.5289011002,47.3830909729],"type":"Point"}
}