{
  "type": "Feature",
  "properties": {
    "iso:country":"CH",
    "sg:address":"Dorfstrasse 90",
    "sg:city":"Embrach",
    "sg:orig_category":"Malerei",
    "sg:phone":"+41 52 649 19 94",
    "sg:postcode":"8424",
    "sg:province":"Z\u00fcrich",
    "wof:name":"Ernst Ochsner Malergesch\u00e4ft",
    "wof:placetype":"venue"
},
  "geometry": {"coordinates":[8.6709899902,47.7560501099],"type":"Point"}
}