{
  "type": "Feature",
  "properties": {
    "iso:country":"CH",
    "sg:address":"K\u00e4ferholzstrasse 252",
    "sg:city":"Z\u00fcrich",
    "sg:orig_category":"Elektroinstallation",
    "sg:phone":"+41 13716161",
    "sg:postcode":"8046",
    "sg:province":"Z\u00fcrich",
    "wof:name":"L\u00e4derach Walter, Elektroanlagen",
    "wof:placetype":"venue"
},
  "geometry": {"coordinates":[8.5241956711,47.4107551575],"type":"Point"}
}