{
  "type": "Feature",
  "properties": {
    "iso:country":"CH",
    "sg:address":"Birrfeldstrasse 8",
    "sg:city":"Birrhard",
    "sg:orig_category":"Instandhaltung U Reparatur von Automobilen",
    "sg:phone":"+41 56 225 10 60",
    "sg:postcode":"5244",
    "sg:province":"Aargau",
    "wof:name":"Garage Squillace S.",
    "wof:placetype":"venue"
},
  "geometry": {"coordinates":[8.240193367,47.4316978455],"type":"Point"}
}