{
  "type": "Feature",
  "properties": {
    "iso:country":"CH",
    "sg:address":"Rathausgasse 59 3011 Bern. Postfach",
    "sg:city":"Bern",
    "sg:classifiers":[
        {
            "category":"Restaurant",
            "type":"Food & Drink"
        }
    ],
    "sg:phone":"+41 31 318 33 13",
    "sg:postcode":"3000",
    "sg:province":"Bern",
    "sg:tags":[
        "tea-rooms",
        "restaurants"
    ],
    "wof:name":"Restaurant Taverne Kappadokia Obuz A.",
    "wof:placetype":"venue"
},
  "geometry": {"coordinates":[7.4492030144,46.948425293],"type":"Point"}
}