{
  "type": "Feature",
  "properties": {
    "iso:country":"CH",
    "sg:address":"Freie Strasse 37 4000 Basel. Postfach",
    "sg:city":"Basel",
    "sg:orig_category":"Architektur U Ingenieurb\u00fcros",
    "sg:postcode":"4001",
    "sg:province":"Basel-Stadt",
    "wof:name":"Architektur Agentur Morandi Brunone",
    "wof:placetype":"venue"
},
  "geometry": {"coordinates":[7.58982,47.556648],"type":"Point"}
}