{
  "type": "Feature",
  "properties": {
    "iso:country":"CH",
    "sg:address":"Altes Schulhaus",
    "sg:city":"Trub",
    "sg:orig_category":"Regionalbanken U Sparkassen",
    "sg:phone":"+41 34 461 81 71",
    "sg:postcode":"3556",
    "sg:province":"Bern",
    "wof:name":"Valiant Bank",
    "wof:placetype":"venue"
},
  "geometry": {"coordinates":[7.6849250793,47.0063858032],"type":"Point"}
}