{
  "type": "Feature",
  "properties": {
    "iso:country":"CH",
    "sg:address":"Stockerstrasse 27 8810 Horgen. Postfach",
    "sg:city":"Horgen",
    "sg:orig_category":"Pensionskassen",
    "sg:postcode":"8810",
    "sg:province":"Z\u00fcrich",
    "wof:name":"Vorsorgestiftung F\u00fcr Das Personal Der Grob Horgen Ag",
    "wof:placetype":"venue"
},
  "geometry": {"coordinates":[8.5927333832,47.2606582642],"type":"Point"}
}