{
  "type": "Feature",
  "properties": {
    "iso:country":"CH",
    "sg:address":"Bahnstrasse 14",
    "sg:city":"Schwerzenbach",
    "sg:classifiers":[
        {
            "category":"Communications",
            "subcategory":"Radio Station",
            "type":"Services"
        }
    ],
    "sg:phone":"+41 18255714",
    "sg:postcode":"8603",
    "sg:province":"Z\u00fcrich",
    "sg:tags":[
        "fernsehanstalten",
        "u"
    ],
    "wof:name":"Synchron Pfenninger W.",
    "wof:placetype":"venue"
},
  "geometry": {"coordinates":[8.6588096619,47.3848953247],"type":"Point"}
}