{
  "type": "Feature",
  "properties": {
    "iso:country":"CH",
    "sg:address":"Reinacherstrasse 10",
    "sg:city":"Basel",
    "sg:orig_category":"Herstellung von Bereifungen",
    "sg:phone":"+41 79 219 73 49",
    "sg:postcode":"4053",
    "sg:province":"Basel-Stadt",
    "wof:name":"High Speed Guimaraes Frias & Co",
    "wof:placetype":"venue"
},
  "geometry": {"coordinates":[7.6020708084,47.5413208008],"type":"Point"}
}