{
  "type": "Feature",
  "properties": {
    "iso:country":"CH",
    "sg:address":"B\u00e4retstrasse 1",
    "sg:city":"Visp",
    "sg:orig_category":"Herstellung von sonstigen elektrischen Ausr\u00fcstungen",
    "sg:postcode":"3930",
    "sg:province":"Valais",
    "wof:name":"Weber Ag",
    "wof:placetype":"venue"
},
  "geometry": {"coordinates":[7.8839149475,46.2939453125],"type":"Point"}
}