{
  "type": "Feature",
  "properties": {
    "iso:country":"CH",
    "sg:address":"Sch\u00fctzenweg 6",
    "sg:city":"H\u00e4gendorf",
    "sg:orig_category":"Herstellung von sonstigen elektrischen Ausr\u00fcstungen",
    "sg:phone":"+41 62 216 41 68",
    "sg:postcode":"4614",
    "sg:province":"Solothurn",
    "wof:name":"B\u00fcrki Sicherheitstechnik Ag",
    "wof:placetype":"venue"
},
  "geometry": {"coordinates":[7.8358078003,47.3329086304],"type":"Point"}
}