{
  "type": "Feature",
  "properties": {
    "iso:country":"CH",
    "sg:address":"Kapplerstrasse 39",
    "sg:city":"Ebnat",
    "sg:orig_category":"Technische, physikalische U chemische Untersuchung",
    "sg:phone":"+41 71 993 32 22",
    "sg:postcode":"9642",
    "sg:province":"St. Gallen",
    "wof:name":"Link Peter Ag",
    "wof:placetype":"venue"
},
  "geometry": {"coordinates":[9.1176214218,47.2675247192],"type":"Point"}
}