{
  "type": "Feature",
  "properties": {
    "iso:country":"CH",
    "sg:address":"9213",
    "sg:city":"Hauptwil",
    "sg:orig_category":"Primarschulen",
    "sg:phone":"+41 71 422 56 65",
    "sg:postcode":"9213",
    "sg:province":"Thurgau",
    "wof:name":"Primarschule",
    "wof:placetype":"venue"
},
  "geometry": {"coordinates":[9.2539901733,47.4825515747],"type":"Point"}
}