{
  "type": "Feature",
  "properties": {
    "iso:country":"CH",
    "sg:address":"Unterer St\u00fcnziweg 10a",
    "sg:city":"Oberrieden",
    "sg:orig_category":"Sanit\u00e4r, Heizungs U L\u00fcftungsinstallation",
    "sg:phone":"+41 19291966",
    "sg:postcode":"8942",
    "sg:province":"Z\u00fcrich",
    "wof:name":"Sanit\u00e4r Spenglerei Wernli Ag",
    "wof:placetype":"venue"
},
  "geometry": {"coordinates":[8.7239284515,47.2689056396],"type":"Point"}
}