{
  "type": "Feature",
  "properties": {
    "iso:country":"CH",
    "sg:address":"Grand-st-jean Rue 16 1003 Lausanne. Postfach",
    "sg:city":"Lausanne",
    "sg:orig_category":"Non-Classified Establishments",
    "sg:postcode":"1003",
    "sg:province":"Vaud",
    "wof:name":"Si Chailly-r\u00e9sidence C",
    "wof:placetype":"venue"
},
  "geometry": {"coordinates":[6.6313428879,46.5215911865],"type":"Point"}
}