{
  "type": "Feature",
  "properties": {
    "iso:country":"CH",
    "sg:address":"Z\u00fcrcherstrasse 67",
    "sg:city":"Oberengstringen",
    "sg:orig_category":"Reinigungsgewerbe",
    "sg:phone":"+41 17510089",
    "sg:postcode":"8102",
    "sg:province":"Z\u00fcrich",
    "wof:name":"Punkt Reinigung Gmbh",
    "wof:placetype":"venue"
},
  "geometry": {"coordinates":[8.4690828323,47.4068374634],"type":"Point"}
}