{
  "type": "Feature",
  "properties": {
    "iso:country":"CH",
    "sg:address":"Fritz-oppliger-strasse 7 2504 Biel/bienne. Postfach 6109",
    "sg:city":"Biel/bienne",
    "sg:orig_category":"Grosshandel mit sonstigen Maschinen U Ausr\u00fcstungen f\u00fcr Industrie, Handel U Schiffahrt Herstellung vo",
    "sg:phone":"+41 32 342 46 33",
    "sg:postcode":"2500",
    "sg:province":"Bern",
    "wof:name":"Niveltec Ag",
    "wof:placetype":"venue"
},
  "geometry": {"coordinates":[7.2835001945,47.160949707],"type":"Point"}
}