{
  "type": "Feature",
  "properties": {
    "iso:country":"CH",
    "sg:address":"Herrengrabenweg 32",
    "sg:city":"Basel",
    "sg:orig_category":"Datenverarbeitungsdienste Wirtschaftspr\u00fcfung, Steuerberatung U Treuhand",
    "sg:phone":"+41 61 281 12 87",
    "sg:postcode":"4054",
    "sg:province":"Basel-Stadt",
    "wof:name":"Iti Treuhand & Informatik Gmbh",
    "wof:placetype":"venue"
},
  "geometry": {"coordinates":[7.571745,47.555248],"type":"Point"}
}