{
  "type": "Feature",
  "properties": {
    "iso:country":"CH",
    "sg:address":"Rue Du Quai 8",
    "sg:city":"Montreux",
    "sg:orig_category":"Detailhandel mit Haustieren U zoologischem Bedarf",
    "sg:phone":"+41 21 963 18 21",
    "sg:postcode":"1820",
    "sg:province":"Vaud",
    "wof:name":"Amedeo Pacella Centre D'animaux Exotiques",
    "wof:placetype":"venue"
},
  "geometry": {"coordinates":[6.90955019,46.4307441711],"type":"Point"}
}