{
  "type": "Feature",
  "properties": {
    "iso:country":"CH",
    "sg:address":"Ausserdorfstrasse 9",
    "sg:city":"Rothenthurm",
    "sg:orig_category":"Herstellung von sonstigen landwirtschaftlichen Maschinen",
    "sg:phone":"+41 79 462 90 00",
    "sg:postcode":"6418",
    "sg:province":"Schwyz",
    "wof:name":"Moser Landmaschinen",
    "wof:placetype":"venue"
},
  "geometry": {"coordinates":[8.6754560471,47.1021118164],"type":"Point"}
}