{
  "type": "Feature",
  "properties": {
    "iso:country":"CH",
    "sg:address":"Hallwylstrasse 36",
    "sg:city":"Z\u00fcrich",
    "sg:orig_category":"Saunas, Solarien, Fitnesszentren U \u00e4hnliches",
    "sg:phone":"+41 12418844",
    "sg:postcode":"8004",
    "sg:province":"Z\u00fcrich",
    "wof:name":"New Sun Ag",
    "wof:placetype":"venue"
},
  "geometry": {"coordinates":[8.5287332535,47.3716468811],"type":"Point"}
}