{
  "type": "Feature",
  "properties": {
    "iso:country":"CH",
    "sg:address":"Eichmattstrasse 10",
    "sg:city":"Oftringen",
    "sg:orig_category":"Non-Classified Establishments",
    "sg:phone":"+41 31 980 84 44",
    "sg:postcode":"4665",
    "sg:province":"Aargau",
    "wof:name":"Adval Tech Holding Ag",
    "wof:placetype":"venue"
},
  "geometry": {"coordinates":[7.414276123,46.9228744507],"type":"Point"}
}