{
  "type": "Feature",
  "properties": {
    "iso:country":"CH",
    "sg:address":"Ratellerstr. 21",
    "sg:city":"Sargans",
    "sg:orig_category":"Herstellung von sonstigen elektrischen Ausr\u00fcstungen",
    "sg:phone":"+41 81 723 30 80",
    "sg:postcode":"7320",
    "sg:province":"St. Gallen",
    "wof:name":"Riekastar-brunner & K\u00e4ser",
    "wof:placetype":"venue"
},
  "geometry": {"coordinates":[9.4422073364,47.0535812378],"type":"Point"}
}