{
  "type": "Feature",
  "properties": {
    "iso:country":"CH",
    "sg:address":"Heglerstrasse 1",
    "sg:city":"Hitzkirch",
    "sg:orig_category":"Herstellung von sonstigen elektrischen Ausr\u00fcstungen",
    "sg:postcode":"6285",
    "sg:province":"Luzern",
    "wof:name":"Datashop Internet Gmbh Elektrische U. Elektron. Ger\u00e4te, Artikel; Fabrikation, Handel Usw",
    "wof:placetype":"venue"
},
  "geometry": {"coordinates":[8.2565326691,47.2252235413],"type":"Point"}
}