{
  "type": "Feature",
  "properties": {
    "addr:full":"Waldstrasse Susten Valais 3952",
    "addr:postcode":"3952",
    "addr:street":"Waldstrasse",
    "iso:country":"CH",
    "sg:address":"Waldstrasse",
    "sg:city":"Susten",
    "sg:orig_category":"Dachdeckerei Schlossereien",
    "sg:phone":"+41 27 473 22 02",
    "sg:postcode":"3952",
    "sg:province":"Valais",
    "wof:name":"Paul Pfaffen Sanit\u00e4re Anlagen Schlosserei",
    "wof:placetype":"venue"
},
  "geometry": {"coordinates":[7.636689,46.306873],"type":"Point"}
}