{
  "type": "Feature",
  "properties": {
    "iso:country":"CH",
    "sg:address":"M\u00e4rglenweid 2",
    "sg:city":"Hohenrain",
    "sg:orig_category":"Architekturb\u00fcros",
    "sg:phone":"+41 41 910 46 35",
    "sg:postcode":"6276",
    "sg:province":"Luzern",
    "wof:name":"Hans Meier Architekturb\u00fcro",
    "wof:placetype":"venue"
},
  "geometry": {"coordinates":[8.314154,47.180611],"type":"Point"}
}