{
  "type": "Feature",
  "properties": {
    "iso:country":"CH",
    "sg:address":"Strehlgasse 12 6430 Schwyz. Postfach 360",
    "sg:city":"Schwyz",
    "sg:orig_category":"Versicherungen Generalagenturen",
    "sg:phone":"+41 41 818 35 35",
    "sg:postcode":"6431",
    "sg:province":"Schwyz",
    "wof:name":"National-versicherungen Generalagentur",
    "wof:placetype":"venue"
},
  "geometry": {"coordinates":[8.6550016403,47.0201644897],"type":"Point"}
}