{
  "type": "Feature",
  "properties": {
    "iso:country":"CH",
    "sg:address":"Meisberg 9",
    "sg:city":"Gachnang",
    "sg:classifiers":[
        {
            "category":"Utilities",
            "subcategory":"Cable",
            "type":"Services"
        }
    ],
    "sg:phone":"+41 52 366 56 56",
    "sg:postcode":"8547",
    "sg:province":"Thurgau",
    "sg:tags":[
        "anti-virus",
        "software"
    ],
    "wof:name":"Mps Elektronik",
    "wof:placetype":"venue"
},
  "geometry": {"coordinates":[8.852095,47.537888],"type":"Point"}
}