{
  "type": "Feature",
  "properties": {
    "iso:country":"CH",
    "sg:address":"Eismattweg 5",
    "sg:city":"Oftringen",
    "sg:orig_category":"Bauspenglerei Sanit\u00e4rinstallation",
    "sg:phone":"+41 62 797 50 60",
    "sg:postcode":"4665",
    "sg:province":"Aargau",
    "wof:name":"Pfister Haustechnik Gmbh Sanit\u00e4r Heizung & Spenglerei",
    "wof:placetype":"venue"
},
  "geometry": {"coordinates":[7.913335,47.310074],"type":"Point"}
}