{
  "type": "Feature",
  "properties": {
    "iso:country":"CH",
    "sg:address":"2108",
    "sg:city":"Couvet",
    "sg:orig_category":"Verwertung von Milch",
    "sg:postcode":"2108",
    "sg:province":"Neuch\u00e2tel",
    "wof:name":"Syndicat Des Producteurs De Lait De La Commune De Landeron-combes Et Environs",
    "wof:placetype":"venue"
},
  "geometry": {"coordinates":[7.0641651154,47.0518341064],"type":"Point"}
}