{
  "type": "Feature",
  "properties": {
    "iso:country":"CH",
    "sg:address":"Chemin Malombr\u00e9 5",
    "sg:city":"Gen\u00e8ve",
    "sg:orig_category":"Medizinische Labors Technische, physikalische U chemische Untersuchung",
    "sg:phone":"+41 22 347 72 97",
    "sg:postcode":"1206",
    "sg:province":"Gen\u00e8ve",
    "wof:name":"Meditest, A. Samartzis",
    "wof:placetype":"venue"
},
  "geometry": {"coordinates":[6.1525678635,46.1959114075],"type":"Point"}
}