{
  "type": "Feature",
  "properties": {
    "iso:country":"CH",
    "sg:address":"Rugenparkstrasse 7",
    "sg:city":"Interlaken",
    "sg:orig_category":"Fachdetailhandel in Verkaufsr\u00e4umen",
    "sg:postcode":"3800",
    "sg:province":"Bern",
    "wof:name":"Knie Rolf Kunst Ag",
    "wof:placetype":"venue"
},
  "geometry": {"coordinates":[8.7995347977,47.2133331299],"type":"Point"}
}