{
  "type": "Feature",
  "properties": {
    "iso:country":"CH",
    "sg:address":"Buchackerweg 4",
    "sg:city":"Hochwald",
    "sg:orig_category":"Herstellung von sonstigen elektrischen Ausr\u00fcstungen",
    "sg:postcode":"4146",
    "sg:province":"Solothurn",
    "wof:name":"Dateltronic Biry F.",
    "wof:placetype":"venue"
},
  "geometry": {"coordinates":[7.6439709663,47.4553108215],"type":"Point"}
}