{
  "type": "Feature",
  "properties": {
    "addr:full":"Seestrasse 20 Bolken Solothurn 4556",
    "addr:housenumber":"20",
    "addr:postcode":"4556",
    "addr:street":"Seestrasse;Solothurn",
    "iso:country":"CH",
    "sg:address":"Seestrasse 20",
    "sg:city":"Bolken",
    "sg:orig_category":"Dauerkulturbau Gem\u00fcsebau",
    "sg:phone":"+41 79 208 64 33",
    "sg:postcode":"4556",
    "sg:province":"Solothurn",
    "wof:name":"L\u00e4ubli Ag Champignons",
    "wof:placetype":"venue"
},
  "geometry": {"coordinates":[7.660764,47.195999],"type":"Point"}
}