{
  "type": "Feature",
  "properties": {
    "iso:country":"CH",
    "sg:address":"Am Bach 5",
    "sg:city":"Glarus",
    "sg:orig_category":"Tierarztpraxis",
    "sg:phone":"+41 55 640 62 12",
    "sg:postcode":"8750",
    "sg:province":"Glarus",
    "wof:name":"Dr. Med. Vet. Jakob H\u00f6sli Tierarzt",
    "wof:placetype":"venue"
},
  "geometry": {"coordinates":[9.0704622269,47.0376739502],"type":"Point"}
}