{
  "type": "Feature",
  "properties": {
    "iso:country":"CH",
    "sg:address":"Niederb\u00fcrerstrasse 48",
    "sg:city":"Bischofszell",
    "sg:classifiers":[
        {
            "category":"Restaurant",
            "type":"Food & Drink"
        }
    ],
    "sg:phone":"+41 81 733 15 06",
    "sg:postcode":"9220",
    "sg:province":"Thurgau",
    "wof:name":"Gasthaus Walserhof",
    "wof:placetype":"venue"
},
  "geometry": {"coordinates":[9.3478088379,47.0789299011],"type":"Point"}
}