{
  "type": "Feature",
  "properties": {
    "iso:country":"CH",
    "sg:address":"Grabenmatt",
    "sg:city":"Trubschachen",
    "sg:orig_category":"Elektroinstallation Herstellung von Elektromotoren, Generatoren U Transformatoren",
    "sg:phone":"+41 34 495 56 32",
    "sg:postcode":"3555",
    "sg:province":"Bern",
    "wof:name":"Bkw Isp Ag Elektroinstallationen",
    "wof:placetype":"venue"
},
  "geometry": {"coordinates":[7.8407168388,46.9203987122],"type":"Point"}
}