{
  "type": "Feature",
  "properties": {
    "iso:country":"CH",
    "sg:address":"Frauenfelderstrasse 42",
    "sg:city":"Mettschlatt",
    "sg:orig_category":"Mechanische Werkst\u00e4tten",
    "sg:phone":"+41 52 657 21 05",
    "sg:postcode":"8252",
    "sg:province":"Thurgau",
    "wof:name":"Albert Bortolazzi Metallwaren",
    "wof:placetype":"venue"
},
  "geometry": {"coordinates":[8.6988162994,47.6564865112],"type":"Point"}
}