{
  "type": "Feature",
  "properties": {
    "iso:country":"CH",
    "sg:address":"Chemin De Champ-villiers 95b 2518 Nods. Postfach",
    "sg:city":"Biel/bienne",
    "sg:orig_category":"Detailhandel mit M\u00f6beln U Haushaltsgegenst\u00e4nden",
    "sg:phone":"+41 32 342 19 19",
    "sg:postcode":"2504",
    "sg:province":"Bern",
    "wof:name":"Gilbert Keller",
    "wof:placetype":"venue"
},
  "geometry": {"coordinates":[7.0795450211,47.1105003357],"type":"Point"}
}