{
  "type": "Feature",
  "properties": {
    "iso:country":"CH",
    "sg:address":"Lengnaustrasse 12",
    "sg:city":"Grenchen",
    "sg:orig_category":"Herstellung von Metallerzeugnissen ohne Maschinenbau Maschinenbau",
    "sg:phone":"+41 32 653 11 33",
    "sg:postcode":"2540",
    "sg:province":"Solothurn",
    "wof:name":"Itw Decorating Swiss Ag",
    "wof:placetype":"venue"
},
  "geometry": {"coordinates":[7.3817391396,47.1856460571],"type":"Point"}
}