{
  "type": "Feature",
  "properties": {
    "iso:country":"CH",
    "sg:address":"Chemin De Saule 62",
    "sg:city":"Bernex",
    "sg:orig_category":"Grosshandel mit Bekleidung",
    "sg:phone":"+41 22 757 10 00",
    "sg:postcode":"1233",
    "sg:province":"Gen\u00e8ve",
    "wof:name":"Carli Gry Schweiz Gmbh",
    "wof:placetype":"venue"
},
  "geometry": {"coordinates":[6.0697898865,46.1757545471],"type":"Point"}
}