{
  "type": "Feature",
  "properties": {
    "iso:country":"CH",
    "sg:address":"Pont La Ville",
    "sg:city":"Pont La Ville",
    "sg:classifiers":[
        {
            "category":"Banks & Credit Unions",
            "subcategory":"Bank",
            "type":"Services"
        }
    ],
    "sg:phone":"+41 26 413 35 50",
    "sg:postcode":"1649",
    "sg:province":"Fribourg",
    "wof:name":"Raiffeisen",
    "wof:placetype":"venue"
},
  "geometry": {"coordinates":[7.11097,46.703091],"type":"Point"}
}