{
  "type": "Feature",
  "properties": {
    "iso:country":"CH",
    "sg:address":"Dorfstrasse 16 5452 Oberrohrdorf. Postfach",
    "sg:city":"Oberrohrdorf",
    "sg:orig_category":"RESTAURANTS: TEA-ROOMS",
    "sg:phone":"+41 62 822 72 17",
    "sg:postcode":"5452",
    "sg:province":"Aargau",
    "wof:name":"Restaurant Frohsinn L. Und M. Zaffaroni",
    "wof:placetype":"venue"
},
  "geometry": {"coordinates":[8.0673761368,47.3901863098],"type":"Point"}
}