{
  "type": "Feature",
  "properties": {
    "addr:full":"Ebnetstrasse 5 W\u00e4ngi Thurgau 9545",
    "addr:housenumber":"5",
    "addr:postcode":"9545",
    "addr:street":"Ebnetstrasse;Thurgau",
    "iso:country":"CH",
    "sg:address":"Ebnetstrasse 5",
    "sg:city":"W\u00e4ngi",
    "sg:orig_category":"Berufsbildende weiterf\u00fchrende Schulen Massagestudios",
    "sg:phone":"+41 52 378 10 30",
    "sg:postcode":"9545",
    "sg:province":"Thurgau",
    "wof:name":"Trisana Massageschule",
    "wof:placetype":"venue"
},
  "geometry": {"coordinates":[8.947263,47.496319],"type":"Point"}
}