{
  "type": "Feature",
  "properties": {
    "iso:country":"CH",
    "sg:address":"Bahnhofstrasse 14",
    "sg:city":"Altnau",
    "sg:orig_category":"Nationale Postdienste",
    "sg:phone":"+41 71 695 19 25",
    "sg:postcode":"8595",
    "sg:province":"Thurgau",
    "wof:name":"Die Schweizerische Post",
    "wof:placetype":"venue"
},
  "geometry": {"coordinates":[9.2588939667,47.6122360229],"type":"Point"}
}