{
  "type": "Feature",
  "properties": {
    "iso:country":"CH",
    "sg:address":"Grand-places 14",
    "sg:city":"Fribourg",
    "sg:orig_category":"Finanzierungsinstitutionen",
    "sg:phone":"+41 26 424 17 77",
    "sg:postcode":"1700",
    "sg:province":"Fribourg",
    "wof:name":"P\u00e9rolles 2000 Sa",
    "wof:placetype":"venue"
},
  "geometry": {"coordinates":[7.153151989,46.8025512695],"type":"Point"}
}