{
  "type": "Feature",
  "properties": {
    "iso:country":"CH",
    "sg:address":"Faubourg Du Lac 33",
    "sg:city":"Neuch\u00e2tel",
    "sg:orig_category":"Vorschulen, Kinderg\u00e4rten",
    "sg:phone":"+41 32 853 37 36",
    "sg:postcode":"2000",
    "sg:province":"Neuch\u00e2tel",
    "wof:name":"Jardin D'enfants Le Chat Bott\u00e9 Madame Astrid Muriset",
    "wof:placetype":"venue"
},
  "geometry": {"coordinates":[6.9356408119,46.9937667847],"type":"Point"}
}