{
  "type": "Feature",
  "properties": {
    "iso:country":"CH",
    "sg:address":"Neptunstrasse 14",
    "sg:city":"Z\u00fcrich",
    "sg:orig_category":"Architekturb\u00fcros",
    "sg:phone":"+41 12520631",
    "sg:postcode":"8032",
    "sg:province":"Z\u00fcrich",
    "wof:name":"Dieter Schl\u00fcter Architekturb\u00fcro",
    "wof:placetype":"venue"
},
  "geometry": {"coordinates":[8.554465,47.368153],"type":"Point"}
}