{
  "type": "Feature",
  "properties": {
    "iso:country":"CH",
    "sg:address":"Grand-rue 19",
    "sg:city":"Corg\u00e9mont",
    "sg:orig_category":"Detailhandel mit Milcherzeugnissen U Eiern Verarbeitung von Milch",
    "sg:phone":"+41 26 929 82 09",
    "sg:postcode":"2606",
    "sg:province":"Bern",
    "wof:name":"Roland Buchs Molkerei",
    "wof:placetype":"venue"
},
  "geometry": {"coordinates":[-96.68799591059999,30.1493644714],"type":"Point"}
}