{
  "type": "Feature",
  "properties": {
    "iso:country":"CH",
    "sg:address":"Buchholzstrasse 24",
    "sg:city":"Zollikon",
    "sg:orig_category":"Primarschulen",
    "sg:phone":"+41 13918151",
    "sg:postcode":"8702",
    "sg:province":"Z\u00fcrich",
    "wof:name":"Primarschule Oescher",
    "wof:placetype":"venue"
},
  "geometry": {"coordinates":[8.5757913589,47.3401184082],"type":"Point"}
}