{
  "type": "Feature",
  "properties": {
    "iso:country":"CH",
    "sg:address":"Rue Dancet 31",
    "sg:city":"Gen\u00e8ve",
    "sg:orig_category":"Schreib U \u00dcbersetzungsb\u00fcros -\u00dcbersetzungsb\u00fcros",
    "sg:phone":"+41 22 321 46 63",
    "sg:postcode":"1205",
    "sg:province":"Gen\u00e8ve",
    "wof:name":"Brungger Elisabeth",
    "wof:placetype":"venue"
},
  "geometry": {"coordinates":[6.1428489685,46.1925086975],"type":"Point"}
}