{
  "type": "Feature",
  "properties": {
    "iso:country":"CH",
    "sg:address":"Luzernerstrasse 186 6402 Merlischachen. Postfach",
    "sg:city":"Merlischachen",
    "sg:orig_category":"Softwareentwicklung U beratung",
    "sg:postcode":"6402",
    "sg:province":"Schwyz",
    "wof:name":"Reltech Software Borb\u00e9ly Gabor",
    "wof:placetype":"venue"
},
  "geometry": {"coordinates":[8.4100608826,47.0669784546],"type":"Point"}
}