{
  "type": "Feature",
  "properties": {
    "iso:country":"CH",
    "sg:address":"Chemin F. Et J. Sablet 1",
    "sg:city":"Morges",
    "sg:orig_category":"Grosshandel mit Parf\u00fcmerieartikeln U K\u00f6rperpflegemitteln Herstellung von Duft U K\u00f6rperpflegemitteln",
    "sg:phone":"+41 21 803 69 60",
    "sg:postcode":"1110",
    "sg:province":"Vaud",
    "wof:name":"Comptoir Aul\u00e8ne Sa",
    "wof:placetype":"venue"
},
  "geometry": {"coordinates":[6.4929637909,46.5126647949],"type":"Point"}
}