{
  "type": "Feature",
  "properties": {
    "iso:country":"CH",
    "sg:address":"7078 Lenzerheide/lai. Postfach 971",
    "sg:city":"Lenzerheide/lai",
    "sg:orig_category":"Campingpl\u00e4tze",
    "sg:phone":"+41 81 384 23 35",
    "sg:postcode":"7078",
    "sg:province":"Graubunden",
    "wof:name":"Camping Gravas Tcs",
    "wof:placetype":"venue"
},
  "geometry": {"coordinates":[9.557853,46.724579],"type":"Point"}
}