{
  "type": "Feature",
  "properties": {
    "iso:country":"CH",
    "sg:address":"Cramerstrasse 16",
    "sg:city":"Z\u00fcrich",
    "sg:orig_category":"Sonstige Institutionen des Sozialwesens ohne Beherbergung",
    "sg:phone":"+41 12423737",
    "sg:postcode":"8004",
    "sg:province":"Z\u00fcrich",
    "wof:name":"Stiftung Hilfe F\u00fcr Kinder Unterst\u00fctzung Von Notleidenden Kindern U. Alten Menschen Usw",
    "wof:placetype":"venue"
},
  "geometry": {"coordinates":[8.5263700485,47.3736763],"type":"Point"}
}