{
  "type": "Feature",
  "properties": {
    "iso:country":"CH",
    "sg:address":"Baslerstrasse 50",
    "sg:city":"Binningen",
    "sg:orig_category":"Handels-H\u00e4user U Gesellschaften",
    "sg:phone":"+41 79 821 86 11",
    "sg:postcode":"4102",
    "sg:province":"Basel-Landschaft",
    "wof:name":"Agentur Comboeuf Jean",
    "wof:placetype":"venue"
},
  "geometry": {"coordinates":[7.5749740601,47.5383415222],"type":"Point"}
}