{
  "type": "Feature",
  "properties": {
    "iso:country":"CH",
    "sg:address":"Niklaus Wengistrasse 53",
    "sg:city":"Grenchen",
    "sg:orig_category":"Detailhandel mit Waren verschiedener Art, Hauptrichtung Nahrungsmittel",
    "sg:phone":"+41 56 664 31 71",
    "sg:postcode":"2540",
    "sg:province":"Solothurn",
    "wof:name":"Fritz Fahler Gem\u00fcse-& Fr\u00fcchtehandel",
    "wof:placetype":"venue"
},
  "geometry": {"coordinates":[8.3174819946,47.2825775146],"type":"Point"}
}