{
  "type": "Feature",
  "properties": {
    "iso:country":"CH",
    "sg:address":"Pestalozziweg 12",
    "sg:city":"Schlieren",
    "sg:orig_category":"Gemischte Landwirtschaft",
    "sg:phone":"+41 17306112",
    "sg:postcode":"8952",
    "sg:province":"Z\u00fcrich",
    "wof:name":"Haller H. R.",
    "wof:placetype":"venue"
},
  "geometry": {"coordinates":[8.4649829865,47.3954162598],"type":"Point"}
}