{
  "type": "Feature",
  "properties": {
    "addr:full":"Thunstrasse 10 - Bern Bern 3074",
    "addr:housenumber":"10",
    "addr:postcode":"3074",
    "addr:street":"Thunstrasse;Bern",
    "iso:country":"CH",
    "sg:address":"Thunstrasse 10 -",
    "sg:city":"Bern",
    "sg:classifiers":[
        {
            "category":"Professional",
            "subcategory":"Art Services",
            "type":"Services"
        }
    ],
    "sg:phone":"+41 31 950 65 65",
    "sg:postcode":"3074",
    "sg:province":"Bern",
    "sg:tags":[
        "export-import"
    ],
    "wof:name":"Lebanon Embassy",
    "wof:placetype":"venue"
},
  "geometry": {"coordinates":[7.478675,46.935539],"type":"Point"}
}