{
  "type": "Feature",
  "properties": {
    "iso:country":"CH",
    "sg:address":"Russenweg 18",
    "sg:city":"Z\u00fcrich",
    "sg:orig_category":"Vereine Quartier",
    "sg:postcode":"8008",
    "sg:province":"Z\u00fcrich",
    "wof:name":"Verein Aktives Balgrist",
    "wof:placetype":"venue"
},
  "geometry": {"coordinates":[8.5728807449,47.3558692932],"type":"Point"}
}