{
  "type": "Feature",
  "properties": {
    "iso:country":"CH",
    "sg:address":"Via Marter 2",
    "sg:city":"Porza",
    "sg:orig_category":"Detailhandel mit Brot, Back U S\u00fcsswaren",
    "sg:phone":"+41 91 941 17 71",
    "sg:postcode":"6948",
    "sg:province":"Ticino",
    "wof:name":"Dionisio Bonicelli Panetteria-pasticceria",
    "wof:placetype":"venue"
},
  "geometry": {"coordinates":[8.954693,46.028419],"type":"Point"}
}