{
  "type": "Feature",
  "properties": {
    "iso:country":"CH",
    "sg:address":"Breitenstrasse 14",
    "sg:city":"W\u00fcrenlingen",
    "sg:classifiers":[
        {
            "category":"Restaurant",
            "type":"Food & Drink"
        }
    ],
    "sg:phone":"+41 56 281 14 88",
    "sg:postcode":"5303",
    "sg:province":"Aargau",
    "wof:name":"Restaurant Sonne",
    "wof:placetype":"venue"
},
  "geometry": {"coordinates":[8.2533884048,47.5329742432],"type":"Point"}
}