{
  "type": "Feature",
  "properties": {
    "iso:country":"CH",
    "sg:address":"Rotgutbr\u00fccke",
    "sg:city":"Wiggen",
    "sg:orig_category":"Sonstiger Fachdetailhandel in Verkaufsr\u00e4umen",
    "sg:phone":"+41 41 486 22 59",
    "sg:postcode":"6192",
    "sg:province":"Luzern",
    "wof:name":"Reto Glanzmann B\u00fcchsenmacher",
    "wof:placetype":"venue"
},
  "geometry": {"coordinates":[7.9097008705,46.8958778381],"type":"Point"}
}