{
  "type": "Feature",
  "properties": {
    "iso:country":"CH",
    "sg:address":"Aarbergergasse 21 3005 Bern. Postfach",
    "sg:city":"Bern",
    "sg:orig_category":"Non-Classified Establishments",
    "sg:postcode":"3005",
    "sg:province":"Bern",
    "wof:name":"Steiger Iecs",
    "wof:placetype":"venue"
},
  "geometry": {"coordinates":[8.1839323044,47.2486724854],"type":"Point"}
}