{
  "type": "Feature",
  "properties": {
    "iso:country":"CH",
    "sg:address":"Unterm\u00fcli 5",
    "sg:city":"Zug",
    "sg:orig_category":"RESTAURANTS: TEA-ROOMS",
    "sg:postcode":"6300",
    "sg:province":"Zug",
    "wof:name":"Sandwich-factory Zug, Denise Ruchet-blum",
    "wof:placetype":"venue"
},
  "geometry": {"coordinates":[8.5173864365,47.1803779602],"type":"Point"}
}