{
  "type": "Feature",
  "properties": {
    "iso:country":"CH",
    "sg:address":"Gewerbestrasse 7",
    "sg:city":"Cham",
    "sg:orig_category":"Unclassifiable Establishments",
    "sg:postcode":"6330",
    "sg:province":"Zug",
    "wof:name":"Adula Produkte, Gebr. Christen",
    "wof:placetype":"venue"
},
  "geometry": {"coordinates":[8.7681436539,47.19871521],"type":"Point"}
}