{
  "type": "Feature",
  "properties": {
    "iso:country":"CH",
    "sg:address":"Courgenay Route De 24 2900 Porrentruy. Postfach",
    "sg:city":"Pruntrut",
    "sg:orig_category":"Oberfl\u00e4chenveredlung U W\u00e4rmebehandlung",
    "sg:phone":"+41 21 634 27 25",
    "sg:postcode":"2900",
    "sg:province":"Jura",
    "wof:name":"Atelier De Chromage Dur, P. Alunni",
    "wof:placetype":"venue"
},
  "geometry": {"coordinates":[6.579390049,46.5390815735],"type":"Point"}
}