{
  "type": "Feature",
  "properties": {
    "iso:country":"CH",
    "sg:address":"7437",
    "sg:city":"Nufenen",
    "sg:orig_category":"Detailhandel mit Milcherzeugnissen U Eiern Verarbeitung von Milch",
    "sg:postcode":"7437",
    "sg:province":"Graubunden",
    "wof:name":"Sennereigenossenschaft Aeugst Am Albis",
    "wof:placetype":"venue"
},
  "geometry": {"coordinates":[8.4854745865,47.2676887512],"type":"Point"}
}