{
  "type": "Feature",
  "properties": {
    "iso:country":"CH",
    "sg:address":"Bahnmatt 2",
    "sg:city":"Baar",
    "sg:classifiers":[
        {
            "category":"Social Services",
            "subcategory":"Retirement Home",
            "type":"Services"
        }
    ],
    "sg:phone":"+41 41 769 89 89",
    "sg:postcode":"6340",
    "sg:province":"Zug",
    "sg:tags":[
        "pflegeheime",
        "u",
        "alters"
    ],
    "wof:name":"Altersheim Betagtenzentrum",
    "wof:placetype":"venue"
},
  "geometry": {"coordinates":[8.522485,47.196712],"type":"Point"}
}