{
  "type": "Feature",
  "properties": {
    "iso:country":"CH",
    "sg:address":"Nordstrasse 140",
    "sg:city":"Z\u00fcrich",
    "sg:orig_category":"Allgemeiner Hoch U Tiefbau",
    "sg:phone":"+41 71 977 17 16",
    "sg:postcode":"8037",
    "sg:province":"Z\u00fcrich",
    "wof:name":"Lindemann & Co.",
    "wof:placetype":"venue"
},
  "geometry": {"coordinates":[8.972445,47.428165],"type":"Point"}
}