{
  "type": "Feature",
  "properties": {
    "iso:country":"CH",
    "sg:address":"Alpenblickstrasse 18",
    "sg:city":"Hinwil",
    "sg:orig_category":"Herstellung von Metallkonstruktionen Stahl U Leichtmetallbau",
    "sg:phone":"+41 62 875 11 77",
    "sg:postcode":"8340",
    "sg:province":"Z\u00fcrich",
    "wof:name":"Weiss Haustechnik Gmbh",
    "wof:placetype":"venue"
},
  "geometry": {"coordinates":[8.095331192,47.532951355],"type":"Point"}
}