{
  "type": "Feature",
  "properties": {
    "addr:full":"Gartenstrasse 7 Zug Zug 6300",
    "addr:housenumber":"7",
    "addr:postcode":"6300",
    "addr:street":"Gartenstrasse;Zug",
    "iso:country":"CH",
    "sg:address":"Gartenstrasse 7",
    "sg:city":"Zug",
    "sg:orig_category":"Architektur U Ingenieurb\u00fcros",
    "sg:phone":"+41 41 710 21 10",
    "sg:postcode":"6300",
    "sg:province":"Zug",
    "wof:name":"Atelier Iten Roger M., Architekt Htl",
    "wof:placetype":"venue"
},
  "geometry": {"coordinates":[8.514821,47.170074],"type":"Point"}
}