{
  "type": "Feature",
  "properties": {
    "iso:country":"CH",
    "sg:address":"Rue De Lausanne 32 1950 Sion Case Postale 946",
    "sg:city":"Sion",
    "sg:orig_category":"Notariate",
    "sg:phone":"+41 27 323 18 08",
    "sg:postcode":"1951",
    "sg:province":"Valais",
    "wof:name":"Freddy Michelet Etude De Notaire",
    "wof:placetype":"venue"
},
  "geometry": {"coordinates":[7.3548369408,46.2314033508],"type":"Point"}
}