{
  "type": "Feature",
  "properties": {
    "iso:country":"CH",
    "sg:address":"Gotthardstrasse 3 6300 Zug. Postfach",
    "sg:city":"Zug",
    "sg:orig_category":"Unternehmensberatung",
    "sg:phone":"+41 79 436 10 84",
    "sg:postcode":"6300",
    "sg:province":"Zug",
    "wof:name":"Blumo Management Services Gmbh Beratung Und Projektrealisierung In Der Unternehmens Und Organisationsentwicklung, Bes. Im Ber. Marketing",
    "wof:placetype":"venue"
},
  "geometry": {"coordinates":[8.5175666809,47.171585083],"type":"Point"}
}