{
  "type": "Feature",
  "properties": {
    "iso:country":"CH",
    "sg:address":"Vira",
    "sg:city":"Mezzovico",
    "sg:orig_category":"Sportvereine Ski",
    "sg:phone":"+41 79 688 06 21",
    "sg:postcode":"6805",
    "sg:province":"Ticino",
    "wof:name":"Sci Club Mezzovico-vira",
    "wof:placetype":"venue"
},
  "geometry": {"coordinates":[8.9207296371,46.0964508057],"type":"Point"}
}