{
  "type": "Feature",
  "properties": {
    "iso:country":"CH",
    "sg:address":"Hauptstr.",
    "sg:city":"Luzein",
    "sg:orig_category":"Zimmerei, Dachdeckerei, Bauspenglerei U Abdichtung",
    "sg:phone":"+41 81 332 24 63",
    "sg:postcode":"7242",
    "sg:province":"Graubunden",
    "wof:name":"Holzbau Hertner Ag",
    "wof:placetype":"venue"
},
  "geometry": {"coordinates":[9.8008871078,46.9507827759],"type":"Point"}
}