{
  "type": "Feature",
  "properties": {
    "iso:country":"CH",
    "sg:address":"Hauptstrasse 3818 Grindelwald. Postfach 88",
    "sg:city":"Grindelwald",
    "sg:orig_category":"Detailhandel mit Sportartikeln Fachdetailhandel in Verkaufsr\u00e4umen",
    "sg:phone":"+41 33 853 13 77",
    "sg:postcode":"3818",
    "sg:province":"Bern",
    "wof:name":"Andreas Und K\u00e4thi Schild-kaufmann, Sportgesch\u00e4ft",
    "wof:placetype":"venue"
},
  "geometry": {"coordinates":[8.0396413803,46.623500824],"type":"Point"}
}