{
  "type": "Feature",
  "properties": {
    "iso:country":"CH",
    "sg:address":"Via Camelia",
    "sg:city":"Locarno",
    "sg:orig_category":"G\u00fcterbef\u00f6rderung im Strassenverkehr",
    "sg:postcode":"6600",
    "sg:province":"Ticino",
    "wof:name":"Losa Fratelli Fu Gioachino.",
    "wof:placetype":"venue"
},
  "geometry": {"coordinates":[8.8003940582,46.1705741882],"type":"Point"}
}