{
  "type": "Feature",
  "properties": {
    "iso:country":"CH",
    "sg:address":"Wiesentalstrasse 19",
    "sg:city":"Oberuzwil",
    "sg:orig_category":"Sonstiger Grosshandel",
    "sg:postcode":"9242",
    "sg:province":"St. Gallen",
    "wof:name":"Mespo Gmbh",
    "wof:placetype":"venue"
},
  "geometry": {"coordinates":[9.1270551682,47.4311790466],"type":"Point"}
}