{
  "type": "Feature",
  "properties": {
    "iso:country":"CH",
    "sg:address":"Hauptstrasse 44",
    "sg:city":"Rorschach",
    "sg:orig_category":"Detailhandel mit M\u00f6beln U Haushaltsgegenst\u00e4nden Verlegen von Fussboden",
    "sg:phone":"+41 71 841 62 14",
    "sg:postcode":"9400",
    "sg:province":"St. Gallen",
    "wof:name":"Engensperger Int\u00e9rieurs",
    "wof:placetype":"venue"
},
  "geometry": {"coordinates":[9.4938097,47.4782409668],"type":"Point"}
}