{
  "type": "Feature",
  "properties": {
    "iso:country":"CH",
    "sg:address":"Landstrasse 114a",
    "sg:city":"Wettingen",
    "sg:orig_category":"Detailhandel mit Zeitungen U Zeitschriften Kioske",
    "sg:phone":"+41 56 426 11 41",
    "sg:postcode":"5430",
    "sg:province":"Aargau",
    "wof:name":"Brigitte Baur Kiosk Rebstock",
    "wof:placetype":"venue"
},
  "geometry": {"coordinates":[8.3289775848,47.4646759033],"type":"Point"}
}