{
  "type": "Feature",
  "properties": {
    "iso:country":"CH",
    "sg:address":"Bahnhofstr. 54 2500 Biel/bienne. Postfach",
    "sg:city":"Biel/bienne",
    "sg:classifiers":[
        {
            "category":"Travel",
            "subcategory":"Hotels & Motels",
            "type":"Entertainment"
        }
    ],
    "sg:postcode":"2501",
    "sg:province":"Bern",
    "sg:tags":[
        "hotels",
        "mit",
        "restaurant"
    ],
    "wof:name":"Scheibli Henri",
    "wof:placetype":"venue"
},
  "geometry": {"coordinates":[7.2463788986,47.1362495422],"type":"Point"}
}