{
  "type": "Feature",
  "properties": {
    "iso:country":"CH",
    "sg:address":"Jupiterstrasse 19",
    "sg:city":"Bern",
    "sg:orig_category":"Allgemeiner Hoch U Tiefbau",
    "sg:phone":"+41 31 921 46 46",
    "sg:postcode":"3015",
    "sg:province":"Bern",
    "wof:name":"Kocherhans Ag Bauunternehmung",
    "wof:placetype":"venue"
},
  "geometry": {"coordinates":[7.481842,46.93972],"type":"Point"}
}