{
  "type": "Feature",
  "properties": {
    "iso:country":"CH",
    "sg:address":"Hermesb\u00fchlstrasse 4",
    "sg:city":"Solothurn",
    "sg:orig_category":"Detailhandel mit Fahrr\u00e4dern Handel mit Motorr\u00e4dern, Teilen U Zubeh\u00f6r Instandhaltung U Reparatur von ",
    "sg:phone":"+41 32 622 15 36",
    "sg:postcode":"4500",
    "sg:province":"Solothurn",
    "wof:name":"Gertrud Keller Velos-motos",
    "wof:placetype":"venue"
},
  "geometry": {"coordinates":[7.5306100845,47.2091217041],"type":"Point"}
}