{
  "type": "Feature",
  "properties": {
    "iso:country":"CH",
    "sg:address":"Rte De Faubourg 42",
    "sg:city":"Sugiez",
    "sg:orig_category":"Druckweiterverarbeitung",
    "sg:phone":"+41 26 673 16 67",
    "sg:postcode":"1786",
    "sg:province":"Fribourg",
    "wof:name":"Media Tec Graphic Service Cerantola Dominique",
    "wof:placetype":"venue"
},
  "geometry": {"coordinates":[7.1121711731,46.965839386],"type":"Point"}
}