{
  "type": "Feature",
  "properties": {
    "iso:country":"CH",
    "sg:address":"Bahnhofstrasse 2",
    "sg:city":"Oensingen",
    "sg:orig_category":"RESTAURANTS: TEA-ROOMS",
    "sg:postcode":"4702",
    "sg:province":"Solothurn",
    "wof:name":"Nater-langenberger Heinz",
    "wof:placetype":"venue"
},
  "geometry": {"coordinates":[7.7069540024,47.2860527039],"type":"Point"}
}