{
  "type": "Feature",
  "properties": {
    "iso:country":"CH",
    "sg:address":"Casa Edith",
    "sg:city":"Carabietta",
    "sg:orig_category":"Grosshandel mit Eisenwaren sowie Installationsbedarf f\u00fcr Gas, Wasser U Heizung",
    "sg:phone":"+41 91 950 00 30",
    "sg:postcode":"6919",
    "sg:province":"Ticino",
    "wof:name":"Electro-oil (ticino) Sa Bruciatori Ad Olio & Gas",
    "wof:placetype":"venue"
},
  "geometry": {"coordinates":[8.8992729187,45.9679374695],"type":"Point"}
}