{
  "type": "Feature",
  "properties": {
    "iso:country":"CH",
    "sg:address":"Reiherweg 3",
    "sg:city":"Suhr",
    "sg:orig_category":"Verlegen von Fliesen U Platten",
    "sg:phone":"+41 41 670 04 05",
    "sg:postcode":"5034",
    "sg:province":"Aargau",
    "wof:name":"Cb Odermatt Gmbh Plattenbel\u00e4ge",
    "wof:placetype":"venue"
},
  "geometry": {"coordinates":[8.2744340897,46.9362068176],"type":"Point"}
}