{
  "type": "Feature",
  "properties": {
    "iso:country":"CH",
    "sg:address":"Route De La Placa",
    "sg:city":"Sierre",
    "sg:orig_category":"G\u00fcterbef\u00f6rderung im Strassenverkehr",
    "sg:postcode":"3960",
    "sg:province":"Valais",
    "wof:name":"Vibru Transporte Ag",
    "wof:placetype":"venue"
},
  "geometry": {"coordinates":[8.1872415543,47.3141784668],"type":"Point"}
}