{
  "type": "Feature",
  "properties": {
    "iso:country":"CH",
    "sg:address":"Luppmenstrasse 1",
    "sg:city":"Fehraltorf",
    "sg:orig_category":"Bibliotheken U Archive Pensionskassen",
    "sg:phone":"+41 61 816 22 16",
    "sg:postcode":"8320",
    "sg:province":"Z\u00fcrich",
    "wof:name":"Stiftung Pro Augusta Raurica",
    "wof:placetype":"venue"
},
  "geometry": {"coordinates":[7.721882,47.533955],"type":"Point"}
}