{
  "type": "Feature",
  "properties": {
    "iso:country":"CH",
    "sg:address":"La Maison",
    "sg:city":"Montricher",
    "sg:orig_category":"Herstellung von k\u00e4lte U lufttechnischen Erzeugnissen f\u00fcr gewerbliche Zwecke Sanit\u00e4rinstallation",
    "sg:phone":"+41 21 864 56 81",
    "sg:postcode":"1147",
    "sg:province":"Vaud",
    "wof:name":"Blanc Raymond Sa Inst.de Chauffage & Sanitaire",
    "wof:placetype":"venue"
},
  "geometry": {"coordinates":[6.3768401146,46.6003608704],"type":"Point"}
}