{
  "type": "Feature",
  "properties": {
    "iso:country":"CH",
    "sg:address":"Imbisb\u00fchlstrasse 91",
    "sg:city":"Z\u00fcrich",
    "sg:orig_category":"Zahntechnische Laboratorien",
    "sg:phone":"+41 13416883",
    "sg:postcode":"8049",
    "sg:province":"Z\u00fcrich",
    "wof:name":"Felix Stemmle Zahntechnisches Laboratorium",
    "wof:placetype":"venue"
},
  "geometry": {"coordinates":[8.4872522354,47.4050369263],"type":"Point"}
}