{
  "type": "Feature",
  "properties": {
    "iso:country":"CH",
    "sg:address":"Contra Di Sotto 6598 Tenero. Postfach Caselle Postale 385",
    "sg:city":"Tenero",
    "sg:orig_category":"Herstellung von Elektromotoren, Generatoren U Transformatoren Planer f\u00fcr Alternativenergie and Solar",
    "sg:phone":"+41 91 745 09 09",
    "sg:postcode":"6598",
    "sg:province":"Ticino",
    "wof:name":"Calor Service Sa",
    "wof:placetype":"venue"
},
  "geometry": {"coordinates":[8.8498601913,46.180896759],"type":"Point"}
}