{
  "type": "Feature",
  "properties": {
    "iso:country":"CH",
    "sg:address":"Corso San Gottardo 54a",
    "sg:city":"Chiasso",
    "sg:orig_category":"Grosshandel mit chemischen Erzeugnissen Herstellung von sonstigen chemischen Erzeugnissen",
    "sg:phone":"+41 71 973 75 80",
    "sg:postcode":"6830",
    "sg:province":"Ticino",
    "wof:name":"Firestar Ag",
    "wof:placetype":"venue"
},
  "geometry": {"coordinates":[8.9664497375,47.4594955444],"type":"Point"}
}