{
  "type": "Feature",
  "properties": {
    "iso:country":"CH",
    "sg:address":"Rue Du Rh\u00f4ne 114",
    "sg:city":"Gen\u00e8ve",
    "sg:orig_category":"Herstellung von Metallerzeugnissen ohne Maschinenbau Herstellung von Schmuck, Gold U Silberschmiedwa",
    "sg:phone":"+41 22 840 09 42",
    "sg:postcode":"1204",
    "sg:province":"Gen\u00e8ve",
    "wof:name":"Ayala Jewels Cr\u00e9ation Sa",
    "wof:placetype":"venue"
},
  "geometry": {"coordinates":[6.1541881561,46.2026062012],"type":"Point"}
}