{
  "type": "Feature",
  "properties": {
    "iso:country":"CH",
    "sg:address":"Via Monti Della Trinit\u00e0 40",
    "sg:city":"Locarno",
    "sg:orig_category":"Gesundheitswesen",
    "sg:postcode":"6600",
    "sg:province":"Ticino",
    "wof:name":"Alsima Sa",
    "wof:placetype":"venue"
},
  "geometry": {"coordinates":[8.7956609726,46.1729316711],"type":"Point"}
}