{
  "type": "Feature",
  "properties": {
    "iso:country":"CH",
    "sg:address":"Boulevard Carl-vogt 2",
    "sg:city":"Gen\u00e8ve",
    "sg:orig_category":"Softwareentwicklung U beratung",
    "sg:phone":"+41 52 242 73 55",
    "sg:postcode":"1205",
    "sg:province":"Gen\u00e8ve",
    "wof:name":"Roger Zehnder Integra Web",
    "wof:placetype":"venue"
},
  "geometry": {"coordinates":[8.7730827332,47.5072631836],"type":"Point"}
}