{
  "type": "Feature",
  "properties": {
    "iso:country":"CH",
    "sg:address":"Kirchgasse 2 5000 Aarau. Postfach",
    "sg:city":"Aarau",
    "sg:orig_category":"Detailhandel mit Bekleidung",
    "sg:postcode":"5000",
    "sg:province":"Aargau",
    "wof:name":"Boutique Naturel Gmbh",
    "wof:placetype":"venue"
},
  "geometry": {"coordinates":[8.043449,47.392807],"type":"Point"}
}