{
  "type": "Feature",
  "properties": {
    "iso:country":"CH",
    "sg:address":"Blankweg 18",
    "sg:city":"Ostermundigen",
    "sg:orig_category":"Herstellung von elektronischen Bauelementen",
    "sg:postcode":"3072",
    "sg:province":"Bern",
    "wof:name":"Hebratec, Hess Und Bracher",
    "wof:placetype":"venue"
},
  "geometry": {"coordinates":[7.4924240112,46.9573364258],"type":"Point"}
}