{
  "type": "Feature",
  "properties": {
    "iso:country":"CH",
    "sg:address":"Route De Meyrin 14",
    "sg:city":"Gen\u00e8ve",
    "sg:orig_category":"Institutionen f\u00fcr Behinderte Sonderschulen",
    "sg:phone":"+41 22 733 49 83",
    "sg:postcode":"1202",
    "sg:province":"Gen\u00e8ve",
    "wof:name":"Service M\u00e9dico-p\u00e9dagogique Jardin D'enfants Servette",
    "wof:placetype":"venue"
},
  "geometry": {"coordinates":[6.1271829605,46.2147750854],"type":"Point"}
}