{
  "type": "Feature",
  "properties": {
    "addr:full":"1997 Haute-nendaz Valais 1997",
    "addr:housenumber":"1997",
    "addr:postcode":"1997",
    "addr:street":"Haute-Nendaz Valais",
    "iso:country":"CH",
    "sg:address":"1997",
    "sg:city":"Haute-nendaz",
    "sg:orig_category":"Dachdeckerei Sanit\u00e4r, Heizungs U L\u00fcftungsinstallation",
    "sg:phone":"+41 27 288 38 18",
    "sg:postcode":"1997",
    "sg:province":"Valais",
    "wof:name":"Claivaz Et Schneiter",
    "wof:placetype":"venue"
},
  "geometry": {"coordinates":[7.29811,46.184151],"type":"Point"}
}