{
  "type": "Feature",
  "properties": {
    "addr:full":"Bachacherweg 6 M\u00fchleberg Bern 3203",
    "addr:housenumber":"6",
    "addr:postcode":"3203",
    "addr:street":"Bachacherweg",
    "iso:country":"CH",
    "sg:address":"Bachacherweg 6",
    "sg:city":"M\u00fchleberg",
    "sg:classifiers":[
        {
            "category":"Banks & Credit Unions",
            "subcategory":"Bank",
            "type":"Services"
        }
    ],
    "sg:phone":"+41 31 751 08 11",
    "sg:postcode":"3203",
    "sg:province":"Bern",
    "wof:name":"Rentenanstalt Swiss Life",
    "wof:placetype":"venue"
},
  "geometry": {"coordinates":[7.264665,46.95285],"type":"Point"}
}