{
  "type": "Feature",
  "properties": {
    "iso:country":"CH",
    "sg:address":"L\u00e4nggasse 1a",
    "sg:city":"Thun",
    "sg:orig_category":"Sonstige Aktivit\u00e4ten der nicht-\u00e4rztlichen Medizinalberufe",
    "sg:phone":"+41 33 222 46 04",
    "sg:postcode":"3600",
    "sg:province":"Bern",
    "wof:name":"Hannelore Frisch Akupunktur & Akupunkt-massage",
    "wof:placetype":"venue"
},
  "geometry": {"coordinates":[7.6269922256,46.7546844482],"type":"Point"}
}