{
  "type": "Feature",
  "properties": {
    "addr:full":"Kreuzmatte 2 Ennetb\u00fcrgen Nidwalden 6373",
    "addr:housenumber":"2",
    "addr:postcode":"6373",
    "addr:street":"Kreuzmatte",
    "iso:country":"CH",
    "sg:address":"Kreuzmatte 2",
    "sg:city":"Ennetb\u00fcrgen",
    "sg:orig_category":"Architektur U Ingenieurb\u00fcros",
    "sg:phone":"+41 41 340 66 80",
    "sg:postcode":"6373",
    "sg:province":"Nidwalden",
    "wof:name":"Infanger Ag Ennetb\u00fcrgen",
    "wof:placetype":"venue"
},
  "geometry": {"coordinates":[8.411502,46.985424],"type":"Point"}
}