{
  "type": "Feature",
  "properties": {
    "addr:full":"Imfeldstrasse 11 8037 Z\u00fcrich. Postfach Z\u00fcrich Z\u00fcrich 8037",
    "addr:housenumber":"11",
    "addr:postcode":"8037 zuerich. postfach;8037",
    "addr:street":"Imfeldstrasse",
    "iso:country":"CH",
    "sg:address":"Imfeldstrasse 11 8037 Z\u00fcrich. Postfach",
    "sg:city":"Z\u00fcrich",
    "sg:orig_category":"Betrieb von Taxis",
    "sg:phone":"+41 13666131",
    "sg:postcode":"8037",
    "sg:province":"Z\u00fcrich",
    "wof:name":"Poly Taxi Ag",
    "wof:placetype":"venue"
},
  "geometry": {"coordinates":[8.534963,47.388535],"type":"Point"}
}