{
  "type": "Feature",
  "properties": {
    "iso:country":"CH",
    "sg:address":"Kappellgasse 24",
    "sg:city":"Luzern",
    "sg:orig_category":"Fachdetailhandel in Verkaufsr\u00e4umen",
    "sg:phone":"+41 81 933 11 63",
    "sg:postcode":"6000",
    "sg:province":"Luzern",
    "wof:name":"Casanova-sport Ag",
    "wof:placetype":"venue"
},
  "geometry": {"coordinates":[9.1193504333,46.7563896179],"type":"Point"}
}