{
  "type": "Feature",
  "properties": {
    "iso:country":"CH",
    "sg:address":"Industriestrasse 8",
    "sg:city":"B\u00fctzberg",
    "sg:orig_category":"Herstellung von Metallerzeugnissen ohne Maschinenbau Herstellung von sonstigen Maschinen f\u00fcr unspezi",
    "sg:phone":"+41 71 463 41 41",
    "sg:postcode":"4922",
    "sg:province":"Bern",
    "wof:name":"Novorex-fritout Ag",
    "wof:placetype":"venue"
},
  "geometry": {"coordinates":[7.7550411224,47.2159347534],"type":"Point"}
}