{
  "type": "Feature",
  "properties": {
    "iso:country":"CH",
    "sg:address":"Tiefenaustrasse 127",
    "sg:city":"Bern",
    "sg:orig_category":"Herstellung von Teppichen Verlegen von Fliesen U Platten",
    "sg:phone":"+41 31 302 48 81",
    "sg:postcode":"3004",
    "sg:province":"Bern",
    "wof:name":"Solc\u00e0 F. Nachf. G\u00fcnther B. & Co",
    "wof:placetype":"venue"
},
  "geometry": {"coordinates":[7.4514498711,46.9731407166],"type":"Point"}
}