{
  "type": "Feature",
  "properties": {
    "iso:country":"CH",
    "sg:address":"Hofernring 6",
    "sg:city":"Adliswil",
    "sg:orig_category":"Sonstiger Grosshandel",
    "sg:phone":"+41 17090482",
    "sg:postcode":"8134",
    "sg:province":"Z\u00fcrich",
    "wof:name":"Taws Verwaltungs Ag",
    "wof:placetype":"venue"
},
  "geometry": {"coordinates":[8.517791748,47.3122406006],"type":"Point"}
}