{
  "type": "Feature",
  "properties": {
    "iso:country":"CH",
    "sg:address":"Weidenpark 3",
    "sg:city":"M\u00f6hlin",
    "sg:orig_category":"Abdichtung Bau von Sportanlagen",
    "sg:phone":"+41 34 402 37 01",
    "sg:postcode":"4313",
    "sg:province":"Aargau",
    "wof:name":"Beltec Belagstechnik Ag",
    "wof:placetype":"venue"
},
  "geometry": {"coordinates":[7.75759,46.949127],"type":"Point"}
}