{
  "type": "Feature",
  "properties": {
    "iso:country":"CH",
    "sg:address":"Imfeldstrasse 15",
    "sg:city":"Z\u00fcrich",
    "sg:orig_category":"Pensionskassen",
    "sg:postcode":"8037",
    "sg:province":"Z\u00fcrich",
    "wof:name":"Personalvorsorgestiftung Der Firma Meier A. & W. Meier & Co",
    "wof:placetype":"venue"
},
  "geometry": {"coordinates":[8.5345373154,47.3884353638],"type":"Point"}
}