{
  "type": "Feature",
  "properties": {
    "iso:country":"CH",
    "sg:address":"Gatternweg 10 4125 Riehen. Postfach",
    "sg:city":"Riehen",
    "sg:orig_category":"Sonstige mit der Informatik verbundene T\u00e4tigkeiten",
    "sg:postcode":"4125",
    "sg:province":"Basel-Stadt",
    "wof:name":"Artebis Ag Dienst Und Infrastrukturleistungen Im Ber. Daten Und Informations-bearbeitung Usw",
    "wof:placetype":"venue"
},
  "geometry": {"coordinates":[7.6443657875,47.5814628601],"type":"Point"}
}