{
  "type": "Feature",
  "properties": {
    "addr:full":"Riedlistrasse 40 Belp Bern 3123",
    "addr:housenumber":"40",
    "addr:postcode":"3123",
    "addr:street":"Riedlistrasse",
    "iso:country":"CH",
    "sg:address":"Riedlistrasse 40",
    "sg:city":"Belp",
    "sg:orig_category":"Architektur U Ingenieurb\u00fcros",
    "sg:phone":"+41 31 819 36 25",
    "sg:postcode":"3123",
    "sg:province":"Bern",
    "wof:name":"Christian Eicher Ingenieurb\u00fcro",
    "wof:placetype":"venue"
},
  "geometry": {"coordinates":[7.506594,46.877781],"type":"Point"}
}