{
  "type": "Feature",
  "properties": {
    "iso:country":"CH",
    "sg:address":"Rue Juste Olivier 22 1260 Nyon Case Postale 144",
    "sg:city":"Nyon",
    "sg:orig_category":"Versicherungen Hauptagenturen",
    "sg:phone":"+41 22 361 52 39",
    "sg:postcode":"1260",
    "sg:province":"Vaud",
    "wof:name":"Zurich-assurances Agence Principale De Nyon",
    "wof:placetype":"venue"
},
  "geometry": {"coordinates":[6.2381072044,46.3849716187],"type":"Point"}
}