{
  "type": "Feature",
  "properties": {
    "iso:country":"CH",
    "sg:address":"7083",
    "sg:city":"Lantsch/lenz",
    "sg:orig_category":"Vorschulen, Kinderg\u00e4rten",
    "sg:phone":"+41 31 859 25 48",
    "sg:postcode":"7083",
    "sg:province":"Graubunden",
    "wof:name":"Kindergarten Schulhaus Seedorf",
    "wof:placetype":"venue"
},
  "geometry": {"coordinates":[8.6164302826,46.8818702698],"type":"Point"}
}