{
  "type": "Feature",
  "properties": {
    "iso:country":"CH",
    "sg:address":"Chemin De Praz 2",
    "sg:city":"Crissier",
    "sg:orig_category":"Druck ohne Zeitungsdruck",
    "sg:postcode":"1023",
    "sg:province":"Vaud",
    "wof:name":"Imprimerie Annen",
    "wof:placetype":"venue"
},
  "geometry": {"coordinates":[6.5747318268,46.552520752],"type":"Point"}
}