{
  "type": "Feature",
  "properties": {
    "iso:country":"CH",
    "sg:address":"Chalet Le Flon",
    "sg:city":"Miex",
    "sg:orig_category":"Sportvereine Ski",
    "sg:phone":"+41 21 963 04 90",
    "sg:postcode":"1896",
    "sg:province":"Valais",
    "wof:name":"Ski-club Migros-jeunesse",
    "wof:placetype":"venue"
},
  "geometry": {"coordinates":[6.1353349686,46.1882514954],"type":"Point"}
}