{
  "type": "Feature",
  "properties": {
    "iso:country":"CH",
    "sg:address":"Rhodstr. 9 9450 Altst\u00e4tten Sg. Postfach",
    "sg:city":"Lienz",
    "sg:orig_category":"Elektroinstallation",
    "sg:phone":"+41 81 756 41 78",
    "sg:postcode":"9464",
    "sg:province":"St. Gallen",
    "wof:name":"Eggenberger Werner, Freileitungsbau",
    "wof:placetype":"venue"
},
  "geometry": {"coordinates":[9.4736442566,47.1674995422],"type":"Point"}
}