{
  "type": "Feature",
  "properties": {
    "iso:country":"CH",
    "sg:address":"St. Urbangasse 3 4500 Solothurn. Postfach",
    "sg:city":"Solothurn",
    "sg:orig_category":"Detailhandel mit Zeitungen U Zeitschriften Kioske",
    "sg:phone":"+41 32 622 55 04",
    "sg:postcode":"4502",
    "sg:province":"Solothurn",
    "wof:name":"Guido Jenny Kiosk Bieltor",
    "wof:placetype":"venue"
},
  "geometry": {"coordinates":[7.534845829,47.2082672119],"type":"Point"}
}