{
  "type": "Feature",
  "properties": {
    "iso:country":"CH",
    "sg:address":"Gloggershausstrasse 20",
    "sg:city":"Schweizersholz",
    "sg:orig_category":"Unclassifiable Establishments",
    "sg:postcode":"9223",
    "sg:province":"Thurgau",
    "wof:name":"Schweingruber W.",
    "wof:placetype":"venue"
},
  "geometry": {"coordinates":[9.1381845474,47.5666694641],"type":"Point"}
}