{
  "type": "Feature",
  "properties": {
    "iso:country":"CH",
    "sg:address":"Cho D'punt 49",
    "sg:city":"Samedan",
    "sg:orig_category":"Non-Classified Establishments",
    "sg:postcode":"7503",
    "sg:province":"Graubunden",
    "wof:name":"E-grafica Sa",
    "wof:placetype":"venue"
},
  "geometry": {"coordinates":[9.8728303909,46.5353507996],"type":"Point"}
}