{
  "type": "Feature",
  "properties": {
    "addr:full":"Lenzburgerstrasse 9 Othmarsingen Aargau 5504",
    "addr:housenumber":"9",
    "addr:postcode":"5504",
    "addr:street":"Lenzburgerstrasse",
    "iso:country":"CH",
    "sg:address":"Lenzburgerstrasse 9",
    "sg:city":"Othmarsingen",
    "sg:orig_category":"Architekturb\u00fcros",
    "sg:phone":"+41 56 222 91 42",
    "sg:postcode":"5504",
    "sg:province":"Aargau",
    "wof:name":"Dieter Gysin Architekturb\u00fcro",
    "wof:placetype":"venue"
},
  "geometry": {"coordinates":[8.213671,47.400501],"type":"Point"}
}