{
  "type": "Feature",
  "properties": {
    "iso:country":"CH",
    "sg:address":"St. Gallerstrasse 26",
    "sg:city":"Herisau",
    "sg:classifiers":[
        {
            "category":"Home & Garden",
            "subcategory":"Building Materials",
            "type":"Retail Goods"
        }
    ],
    "sg:phone":"+41 71 353 95 53",
    "sg:postcode":"9100",
    "sg:province":"Appenzell Ausserrhoden",
    "sg:tags":[
        "antiglare",
        "blind",
        "roller"
    ],
    "wof:name":"Assist System Ag",
    "wof:placetype":"venue"
},
  "geometry": {"coordinates":[9.275758,47.391407],"type":"Point"}
}