{
  "type": "Feature",
  "properties": {
    "iso:country":"CH",
    "sg:address":"Bettswilerstrasse 2 8344 B\u00e4retswil. Postfach",
    "sg:city":"B\u00e4retswil",
    "sg:orig_category":"Herstellung von Elektrizit\u00e4tsverteilungs U schalteinrichtungen",
    "sg:phone":"+41 19391072",
    "sg:postcode":"8344",
    "sg:province":"Z\u00fcrich",
    "wof:name":"Lendi Und Kast Ag",
    "wof:placetype":"venue"
},
  "geometry": {"coordinates":[8.8580245972,47.3342704773],"type":"Point"}
}