{
  "type": "Feature",
  "properties": {
    "iso:country":"CH",
    "sg:address":"Via Clem.maraini 8",
    "sg:city":"Lugano",
    "sg:orig_category":"Vermietung von Automobilen",
    "sg:phone":"+41 848 811 818",
    "sg:postcode":"6900",
    "sg:province":"Ticino",
    "wof:name":"Avis Autonoleggio",
    "wof:placetype":"venue"
},
  "geometry": {"coordinates":[8.945602417,45.9994163513],"type":"Point"}
}