{
  "type": "Feature",
  "properties": {
    "iso:country":"CH",
    "sg:address":"Z\u00fcrcherstrasse 45",
    "sg:city":"Frauenfeld",
    "sg:orig_category":"Fachdetailhandel in Verkaufsr\u00e4umen",
    "sg:postcode":"8500",
    "sg:province":"Thurgau",
    "wof:name":"Erotic-line Ag",
    "wof:placetype":"venue"
},
  "geometry": {"coordinates":[8.8804597855,47.5523757935],"type":"Point"}
}