{
  "type": "Feature",
  "properties": {
    "iso:country":"CH",
    "sg:address":"Feldstrasse 27 9445 Rebstein. Postfach 21",
    "sg:city":"Rebstein",
    "sg:orig_category":"Einzelhandel mit Automobilen Herstellung von Karosserien U Anh\u00e4ngern",
    "sg:phone":"+41 71 777 34 30",
    "sg:postcode":"9445",
    "sg:province":"St. Gallen",
    "wof:name":"Caravan, Camping Dietsche Gmbh",
    "wof:placetype":"venue"
},
  "geometry": {"coordinates":[9.5886907578,47.3973274231],"type":"Point"}
}