{
  "type": "Feature",
  "properties": {
    "iso:country":"CH",
    "sg:address":"Scherzinger Strasse 1",
    "sg:city":"Altnau",
    "sg:classifiers":[
        {
            "category":"Government",
            "subcategory":"Post Office",
            "type":"Public Place"
        }
    ],
    "sg:phone":"+41 71 695 19 66",
    "sg:postcode":"8595",
    "sg:province":"Thurgau",
    "sg:tags":[
        "caf\u00e9s",
        "tea-rooms"
    ],
    "wof:name":"Caf\u00e9 Niedermann",
    "wof:placetype":"venue"
},
  "geometry": {"coordinates":[9.2568883896,47.6108322144],"type":"Point"}
}