{
  "type": "Feature",
  "properties": {
    "iso:country":"CH",
    "sg:address":"Rue Vellaz-d'en-haut 1934 Le Ch\u00e2ble Vs. Postfach",
    "sg:city":"Verbier",
    "sg:classifiers":[
        {
            "category":"Travel",
            "subcategory":"Hotels & Motels",
            "type":"Entertainment"
        }
    ],
    "sg:postcode":"1936",
    "sg:province":"Valais",
    "sg:tags":[
        "hotels",
        "mit",
        "restaurant"
    ],
    "wof:name":"L'h\u00f4te Monique Et Porr Claude Mmes",
    "wof:placetype":"venue"
},
  "geometry": {"coordinates":[7.2125902176,46.0802307129],"type":"Point"}
}