{
  "type": "Feature",
  "properties": {
    "iso:country":"CH",
    "sg:address":"Baselstrasse 6210 Sursee. Postfach",
    "sg:city":"Sursee",
    "sg:orig_category":"Instandhaltung U Reparatur von Automobilen",
    "sg:phone":"+41 41 921 35 37",
    "sg:postcode":"6210",
    "sg:province":"Luzern",
    "wof:name":"Epper Mauensee Ag",
    "wof:placetype":"venue"
},
  "geometry": {"coordinates":[8.0923185349,47.1723098755],"type":"Point"}
}