{
  "type": "Feature",
  "properties": {
    "iso:country":"CH",
    "sg:address":"Hauptstrasse 33",
    "sg:city":"Rheineck",
    "sg:orig_category":"Maler U Glasergewerbe Verlegen von Fussboden",
    "sg:phone":"+41 71 880 07 78",
    "sg:postcode":"9424",
    "sg:province":"St. Gallen",
    "wof:name":"Miacolor Gmbh",
    "wof:placetype":"venue"
},
  "geometry": {"coordinates":[9.5905971527,47.4659843445],"type":"Point"}
}