{
  "type": "Feature",
  "properties": {
    "iso:country":"CH",
    "sg:address":"Hubenstrasse 14 8057 Z\u00fcrich. Postfach 117",
    "sg:city":"Z\u00fcrich",
    "sg:orig_category":"Unternehmensberatung",
    "sg:phone":"+41 13224470",
    "sg:postcode":"8062",
    "wof:name":"Nida Ag F\u00fcr Dienstleistung, Unternehmensberatung Und Verwaltung.",
    "wof:placetype":"venue"
},
  "geometry": {"coordinates":[8.5584030151,47.40366745],"type":"Point"}
}