{
  "type": "Feature",
  "properties": {
    "iso:country":"CH",
    "sg:address":"Bannhaldenweg 17",
    "sg:city":"Lenzburg",
    "sg:orig_category":"Sonstiger Grosshandel",
    "sg:postcode":"5600",
    "sg:province":"Aargau",
    "wof:name":"H.e. Roth Gmbh",
    "wof:placetype":"venue"
},
  "geometry": {"coordinates":[8.1884737015,47.3818283081],"type":"Point"}
}