{
  "type": "Feature",
  "properties": {
    "iso:country":"CH",
    "sg:address":"Hauptstrasse 277",
    "sg:city":"Zuben",
    "sg:classifiers":[
        {
            "category":"Restaurant",
            "type":"Food & Drink"
        }
    ],
    "sg:phone":"+41 71 695 18 84",
    "sg:postcode":"8585",
    "sg:province":"Thurgau",
    "wof:name":"Restaurant Schweizerbund",
    "wof:placetype":"venue"
},
  "geometry": {"coordinates":[9.2383699417,47.6081352234],"type":"Point"}
}