{
  "type": "Feature",
  "properties": {
    "iso:country":"CH",
    "sg:address":"3995",
    "sg:city":"Ausserbinn",
    "sg:orig_category":"Schulpflegen",
    "sg:postcode":"3995",
    "sg:province":"Valais",
    "wof:name":"Schulkommission Der Gemeinde Ausserbinn",
    "wof:placetype":"venue"
},
  "geometry": {"coordinates":[8.1467695236,46.382270813],"type":"Point"}
}