{
  "type": "Feature",
  "properties": {
    "iso:country":"CH",
    "sg:address":"Les Gros Buissons",
    "sg:city":"Salavaux",
    "sg:orig_category":"Betrieb U technische Hilfsdienste des Kultur U Unterhaltungswesens Sportvereine",
    "sg:phone":"+41 26 677 30 18",
    "sg:postcode":"1585",
    "sg:province":"Vaud",
    "wof:name":"Spartacus Events S\u00e0rl",
    "wof:placetype":"venue"
},
  "geometry": {"coordinates":[7.023468,46.924114],"type":"Point"}
}