{
  "type": "Feature",
  "properties": {
    "addr:full":"Z\u00fcrcherstrasse 137 Schlieren Z\u00fcrich 8952",
    "addr:housenumber":"137",
    "addr:postcode":"8952",
    "addr:street":"Zuercherstrasse",
    "iso:country":"CH",
    "sg:address":"Z\u00fcrcherstrasse 137",
    "sg:city":"Schlieren",
    "sg:classifiers":[
        {
            "category":"Manufacturing",
            "subcategory":"Chemicals & Compounds",
            "type":"Manufacturing & Wholesale Goods"
        }
    ],
    "sg:phone":"+41 17556700",
    "sg:postcode":"8952",
    "sg:province":"Z\u00fcrich",
    "sg:tags":[
        "analysis"
    ],
    "wof:name":"Biospectra Ag",
    "wof:placetype":"venue"
},
  "geometry": {"coordinates":[8.465982,47.396519],"type":"Point"}
}