{
  "type": "Feature",
  "properties": {
    "iso:country":"CH",
    "sg:address":"Viktoriastrasse 16",
    "sg:city":"Wabern",
    "sg:orig_category":"Fussreflexzonenmassage Shiatsu-Therapie",
    "sg:phone":"+41 31 747 52 46",
    "sg:postcode":"3084",
    "sg:province":"Bern",
    "wof:name":"Monique Luyten Massagen & Shiatsu",
    "wof:placetype":"venue"
},
  "geometry": {"coordinates":[7.2394919395,46.9084625244],"type":"Point"}
}