{
  "type": "Feature",
  "properties": {
    "iso:country":"CH",
    "sg:address":"Z\u00fcrcherstrasse 200",
    "sg:city":"Winterthur",
    "sg:classifiers":[
        {
            "category":"Professional",
            "subcategory":"Employment Agencies",
            "type":"Services"
        }
    ],
    "sg:phone":"+41 52 203 25 35",
    "sg:postcode":"8406",
    "sg:province":"Z\u00fcrich",
    "sg:tags":[
        "personal",
        "u",
        "stellenvermittlung"
    ],
    "wof:name":"M\u00dcller Bruno Consulting Unternehmensberatung, Coaching Usw",
    "wof:placetype":"venue"
},
  "geometry": {"coordinates":[8.7077503204,47.4606933594],"type":"Point"}
}