{
  "type": "Feature",
  "properties": {
    "iso:country":"CH",
    "sg:address":"8113",
    "sg:city":"Boppelsen",
    "sg:orig_category":"Sportvereine Sch\u00fctzen",
    "sg:phone":"+41 18691515",
    "sg:postcode":"8113",
    "sg:province":"Z\u00fcrich",
    "wof:name":"Schiessverein",
    "wof:placetype":"venue"
},
  "geometry": {"coordinates":[8.4056901932,47.4698905945],"type":"Point"}
}