{
  "type": "Feature",
  "properties": {
    "iso:country":"CH",
    "sg:address":"Route Des Falaises 7",
    "sg:city":"Neuch\u00e2tel",
    "sg:orig_category":"Herstellung von Metallerzeugnissen ohne Maschinenbau Maschinenbau",
    "sg:phone":"+41 32 729 93 00",
    "sg:postcode":"2000",
    "sg:province":"Neuch\u00e2tel",
    "wof:name":"Schalch Sa",
    "wof:placetype":"venue"
},
  "geometry": {"coordinates":[6.950138092,46.9972381592],"type":"Point"}
}