{
  "type": "Feature",
  "properties": {
    "iso:country":"CH",
    "sg:address":"B\u00f6rsenstrasse 16 8001 Z\u00fcrich. Postfach",
    "sg:city":"Z\u00fcrich",
    "sg:orig_category":"Finanzierungsinstitutionen",
    "sg:postcode":"8001",
    "sg:province":"Z\u00fcrich",
    "wof:name":"Marston Capital Partners Ag",
    "wof:placetype":"venue"
},
  "geometry": {"coordinates":[8.5792131424,47.3187255859],"type":"Point"}
}