{
  "type": "Feature",
  "properties": {
    "addr:full":"3993 Grengiols Valais 3993",
    "addr:housenumber":"3993",
    "addr:postcode":"3993",
    "iso:country":"CH",
    "sg:address":"3993",
    "sg:city":"Grengiols",
    "sg:orig_category":"Bauschreinerei Zimmerei, Dachdeckerei, Bauspenglerei U Abdichtung",
    "sg:phone":"+41 79 301 28 53",
    "sg:postcode":"3993",
    "sg:province":"Valais",
    "wof:name":"Peter Vick Menuiserie & Charpente",
    "wof:placetype":"venue"
},
  "geometry": {"coordinates":[6.123788,46.235931],"type":"Point"}
}