{
  "type": "Feature",
  "properties": {
    "iso:country":"CH",
    "sg:address":"St. Jakobs-strasse",
    "sg:city":"Basel",
    "sg:orig_category":"Unclassifiable Establishments",
    "sg:postcode":"4052",
    "sg:province":"Basel-Stadt",
    "wof:name":"Weixler Van Der Avoird + Van Der Avoird, Restaurant Pflugstein",
    "wof:placetype":"venue"
},
  "geometry": {"coordinates":[8.6081485748,47.2971458435],"type":"Point"}
}