{
  "type": "Feature",
  "properties": {
    "iso:country":"CH",
    "sg:address":"Ifangstrasse 11",
    "sg:city":"R\u00fcmlang",
    "sg:orig_category":"Handel mit Automobilen Instandhaltung U Reparatur von Automobilen",
    "sg:phone":"+41 18178888",
    "sg:postcode":"8153",
    "sg:province":"Z\u00fcrich",
    "wof:name":"Jensen Ag",
    "wof:placetype":"venue"
},
  "geometry": {"coordinates":[8.5340013504,47.452381134],"type":"Point"}
}