{
  "type": "Feature",
  "properties": {
    "iso:country":"CH",
    "sg:address":"Ch\u00e4pfli 263",
    "sg:city":"Trasadingen",
    "sg:orig_category":"Datenverarbeitungsdienste Softwareentwicklung U beratung",
    "sg:phone":"+41 52 682 23 43",
    "sg:postcode":"8219",
    "sg:province":"Schaffhausen",
    "wof:name":"Richard B\u00f6sch",
    "wof:placetype":"venue"
},
  "geometry": {"coordinates":[8.426402,47.66806],"type":"Point"}
}