{
  "type": "Feature",
  "properties": {
    "iso:country":"CH",
    "sg:address":"Klingenstrasse 42",
    "sg:city":"Z\u00fcrich",
    "sg:orig_category":"Erbringung von sonstigen Dienstleistungen f\u00fcr Unternehmen",
    "sg:phone":"+41 12716161",
    "sg:postcode":"8005",
    "sg:province":"Z\u00fcrich",
    "wof:name":"Acp Viviane Ehrli",
    "wof:placetype":"venue"
},
  "geometry": {"coordinates":[8.5344934464,47.3822441101],"type":"Point"}
}