{
  "type": "Feature",
  "properties": {
    "iso:country":"CH",
    "sg:address":"Agarn",
    "sg:city":"Agarn",
    "sg:classifiers":[
        {
            "category":"Banks & Credit Unions",
            "subcategory":"Bank",
            "type":"Services"
        }
    ],
    "sg:phone":"+41 27 473 15 71",
    "sg:postcode":"3951",
    "sg:province":"Valais",
    "wof:name":"Raiffeisenbank",
    "wof:placetype":"venue"
},
  "geometry": {"coordinates":[7.663592,46.296951],"type":"Point"}
}