{
  "type": "Feature",
  "properties": {
    "iso:country":"CH",
    "sg:address":"Kleinh\u00fcningerstrasse 137",
    "sg:city":"Basel",
    "sg:orig_category":"Grosshandel mit Nahrungsmitteln, Getr\u00e4nken U Tabakwaren ohne ausgepr\u00e4gten Schwerpunkt",
    "sg:phone":"+41 61 632 02 25",
    "sg:postcode":"4057",
    "sg:province":"Basel-Stadt",
    "wof:name":"Dreiland Shop, Ibili M.",
    "wof:placetype":"venue"
},
  "geometry": {"coordinates":[7.5899629593,47.5783615112],"type":"Point"}
}