{
  "type": "Feature",
  "properties": {
    "iso:country":"CH",
    "sg:address":"Dorfstrasse 77",
    "sg:city":"Oberschan",
    "sg:orig_category":"Elektrizit\u00e4tsversorgung",
    "sg:phone":"+41 32 374 40 90",
    "sg:postcode":"9479",
    "sg:province":"St. Gallen",
    "wof:name":"Elektroversorgung Studen",
    "wof:placetype":"venue"
},
  "geometry": {"coordinates":[7.3004808426,47.1149024963],"type":"Point"}
}