{
  "type": "Feature",
  "properties": {
    "iso:country":"CH",
    "sg:address":"R\u00f6merstrasse 181 8404 Oberwinterthur. Postfach",
    "sg:city":"Oberwinterthur",
    "sg:orig_category":"Unclassifiable Establishments",
    "sg:postcode":"8404",
    "sg:province":"Z\u00fcrich",
    "wof:name":"Pizza Kurier Pmp Piccolo Mondo Pasta, A. Caloro",
    "wof:placetype":"venue"
},
  "geometry": {"coordinates":[8.7553596497,47.507648468],"type":"Point"}
}