{
  "type": "Feature",
  "properties": {
    "iso:country":"CH",
    "sg:address":"Schermenweg 168",
    "sg:city":"Ostermundigen",
    "sg:orig_category":"Reparatur von Schuhen U Lederwaren",
    "sg:phone":"+41 31 931 04 48",
    "sg:postcode":"3072",
    "sg:province":"Bern",
    "wof:name":"Horst K\u00f6hler Schuhmacherei",
    "wof:placetype":"venue"
},
  "geometry": {"coordinates":[7.4802799225,46.9584388733],"type":"Point"}
}