{
  "type": "Feature",
  "properties": {
    "iso:country":"CH",
    "sg:address":"Blegistrasse 1",
    "sg:city":"Rotkreuz",
    "sg:orig_category":"G\u00fcterbef\u00f6rderung im Strassenverkehr Herstellung von medizinischen U chirurgischen Ger\u00e4ten sowie orth",
    "sg:phone":"+41 41 790 57 03",
    "sg:postcode":"6343",
    "sg:province":"Zug",
    "wof:name":"Polyrose Ag",
    "wof:placetype":"venue"
},
  "geometry": {"coordinates":[8.4361276627,47.1481895447],"type":"Point"}
}