{
  "type": "Feature",
  "properties": {
    "iso:country":"CH",
    "sg:address":"Br\u00fcnigstrasse 225",
    "sg:city":"Sachseln",
    "sg:orig_category":"Einzelhandel mit Automobilteilen U Zubeh\u00f6r Instandhaltung U Reparatur von Automobilen",
    "sg:phone":"+41 62 768 20 40",
    "sg:postcode":"6072",
    "sg:province":"Obwalden",
    "wof:name":"Garage Kohler Ag",
    "wof:placetype":"venue"
},
  "geometry": {"coordinates":[8.115694046,47.3291893005],"type":"Point"}
}