{
  "type": "Feature",
  "properties": {
    "iso:country":"CH",
    "sg:address":"Rh\u00f4ne Rue Du 50",
    "sg:city":"Gen\u00e8ve",
    "sg:orig_category":"Unclassifiable Establishments",
    "sg:phone":"+41 19290230",
    "sg:postcode":"1204",
    "sg:province":"Gen\u00e8ve",
    "wof:name":"Rodrigues Da Costa Gartenbau",
    "wof:placetype":"venue"
},
  "geometry": {"coordinates":[8.7213163376,47.2719802856],"type":"Point"}
}