{
  "type": "Feature",
  "properties": {
    "iso:country":"CH",
    "sg:address":"Route Du L\u00e9man",
    "sg:city":"Saxon",
    "sg:orig_category":"Autogaragen",
    "sg:phone":"+41 79 219 09 90",
    "sg:postcode":"1907",
    "sg:province":"Valais",
    "wof:name":"Jean-pierre Pellaud Garage Zodiac",
    "wof:placetype":"venue"
},
  "geometry": {"coordinates":[7.15555,46.140095],"type":"Point"}
}