{
  "type": "Feature",
  "properties": {
    "iso:country":"CH",
    "sg:address":"Avenue Alexandre Vinet 15 1815 Clarens Case Postale 70",
    "sg:city":"Clarens",
    "sg:orig_category":"Kantonalbanken",
    "sg:phone":"+41 21 989 44 50",
    "sg:postcode":"1815",
    "sg:province":"Vaud",
    "wof:name":"Banque Cantonale Vaudoise",
    "wof:placetype":"venue"
},
  "geometry": {"coordinates":[6.8934659958,46.441318512],"type":"Point"}
}