{
  "type": "Feature",
  "properties": {
    "iso:country":"CH",
    "sg:address":"Lausanne Rue De 20",
    "sg:city":"Payerne",
    "sg:orig_category":"Unclassifiable Establishments",
    "sg:postcode":"1530",
    "sg:province":"Vaud",
    "wof:name":"Au Robinson Bis, Josiane Vonlaufen",
    "wof:placetype":"venue"
},
  "geometry": {"coordinates":[6.9362120628,46.8202781677],"type":"Point"}
}