{
  "type": "Feature",
  "properties": {
    "iso:country":"CH",
    "sg:address":"Rafzerstrasse 7",
    "sg:city":"Rheinau",
    "sg:orig_category":"Sportvereine Wassersport Segeln",
    "sg:phone":"+41 52 319 15 83",
    "sg:postcode":"8462",
    "sg:province":"Z\u00fcrich",
    "wof:name":"Seglervereinigung Eschenz Svez",
    "wof:placetype":"venue"
},
  "geometry": {"coordinates":[8.5994176865,47.6361999512],"type":"Point"}
}