{
  "type": "Feature",
  "properties": {
    "iso:country":"CH",
    "sg:address":"Aarburgerstrasse 2",
    "sg:city":"Zofingen",
    "sg:orig_category":"Kinderkrippen U horte",
    "sg:postcode":"4800",
    "sg:province":"Aargau",
    "wof:name":"Kinderkrippe Domino",
    "wof:placetype":"venue"
},
  "geometry": {"coordinates":[7.9431848526,47.291557312],"type":"Point"}
}