{
  "type": "Feature",
  "properties": {
    "iso:country":"CH",
    "sg:address":"Bahnhofplatz 8",
    "sg:city":"Dietikon",
    "sg:orig_category":"Non-Classified Establishments",
    "sg:phone":"+41 71 744 93 40",
    "sg:postcode":"8953",
    "sg:province":"Z\u00fcrich",
    "wof:name":"Expressteam Gmbh",
    "wof:placetype":"venue"
},
  "geometry": {"coordinates":[9.6321973801,47.452960968],"type":"Point"}
}