{
  "type": "Feature",
  "properties": {
    "iso:country":"CH",
    "sg:address":"Kieswerkstrasse 50",
    "sg:city":"Utzenstorf",
    "sg:orig_category":"Allgemeiner Hoch U Tiefbau ohne ausgepr\u00e4gten Schwerpunkt",
    "sg:phone":"+41 32 662 41 62",
    "sg:postcode":"3427",
    "sg:province":"Bern",
    "wof:name":"Hans Zaugg Hoch-& Tiefbau",
    "wof:placetype":"venue"
},
  "geometry": {"coordinates":[7.54422,47.125263],"type":"Point"}
}