{
  "type": "Feature",
  "properties": {
    "iso:country":"CH",
    "sg:address":"Alte Landstrasse 17",
    "sg:city":"Unter\u00e4geri",
    "sg:orig_category":"Datenverarbeitungsdienste Wirtschaftspr\u00fcfung, Steuerberatung U Treuhand",
    "sg:phone":"+41 41 754 70 64",
    "sg:postcode":"6314",
    "sg:province":"Zug",
    "wof:name":"Rusconi Sylvia Consulting",
    "wof:placetype":"venue"
},
  "geometry": {"coordinates":[8.59176,47.13855],"type":"Point"}
}