{
  "type": "Feature",
  "properties": {
    "iso:country":"CH",
    "sg:address":"Via Girella",
    "sg:city":"Lamone",
    "sg:orig_category":"Elektroinstallation",
    "sg:phone":"+41 91 966 77 22",
    "sg:postcode":"6814",
    "sg:province":"Ticino",
    "wof:name":"Fondo Di Previdenza Per Il Personale Della Ditta Franchini Edmondo, Impianti Elettrici, Lugano",
    "wof:placetype":"venue"
},
  "geometry": {"coordinates":[8.9321250916,46.0429267883],"type":"Point"}
}