{
  "type": "Feature",
  "properties": {
    "iso:country":"CH",
    "sg:address":"Seestrasse 118",
    "sg:city":"R\u00fcschlikon",
    "sg:orig_category":"Sonstiger Grosshandel",
    "sg:postcode":"8803",
    "sg:province":"Z\u00fcrich",
    "wof:name":"Intermerkur Nesnidal Nora",
    "wof:placetype":"venue"
},
  "geometry": {"coordinates":[8.5610275269,47.3022689819],"type":"Point"}
}