{
  "type": "Feature",
  "properties": {
    "iso:country":"CH",
    "sg:address":"Webereistrasse 37",
    "sg:city":"Seon",
    "sg:orig_category":"Elektroinstallation",
    "sg:phone":"+41 62 769 80 70",
    "sg:postcode":"5703",
    "sg:province":"Aargau",
    "wof:name":"Ebl Elektro-bau L\u00fcscher Ag",
    "wof:placetype":"venue"
},
  "geometry": {"coordinates":[8.1665372849,47.3545761108],"type":"Point"}
}