{
  "type": "Feature",
  "properties": {
    "iso:country":"CH",
    "sg:address":"Br\u00fcnigstrasse",
    "sg:city":"Sarnen",
    "sg:orig_category":"Bezirks, Sekundar, Realschulen, Oberstufe der Primarschulen",
    "sg:phone":"+41 41 660 18 91",
    "sg:postcode":"6060",
    "sg:province":"Obwalden",
    "wof:name":"Sekundarschule Schulhaus Ii",
    "wof:placetype":"venue"
},
  "geometry": {"coordinates":[8.246549,46.900158],"type":"Point"}
}