{
  "type": "Feature",
  "properties": {
    "iso:country":"CH",
    "sg:address":"Reggenschwilerstrasse 4 9402 M\u00f6rschwil. Postfach 16",
    "sg:city":"M\u00f6rschwil",
    "sg:orig_category":"Handelsvermittlung U Grosshandel Sonstiger Grosshandel",
    "sg:phone":"+41 71 866 16 76",
    "sg:postcode":"9402",
    "sg:province":"St. Gallen",
    "wof:name":"Schneider Prokom Ag Handelsunternehmung",
    "wof:placetype":"venue"
},
  "geometry": {"coordinates":[9.4191656113,47.46534729],"type":"Point"}
}