{
  "type": "Feature",
  "properties": {
    "iso:country":"CH",
    "sg:address":"Feldkircherstrasse 7",
    "sg:city":"Schaan",
    "sg:orig_category":"Detailhandel mit Getr\u00e4nken",
    "sg:phone":"+41 71 966 25 70",
    "sg:postcode":"9494",
    "wof:name":"Hermann Keller Getr\u00e4nkehandlung",
    "wof:placetype":"venue"
},
  "geometry": {"coordinates":[9.0008058548,47.4763298035],"type":"Point"}
}