{
  "type": "Feature",
  "properties": {
    "iso:country":"CH",
    "sg:address":"6760 Faido Casella Postale",
    "sg:city":"Faido",
    "sg:orig_category":"Architektur U Ingenieurb\u00fcros Ingenieurb\u00fcros Geologie",
    "sg:phone":"+41 41 720 07 02",
    "sg:postcode":"6760",
    "sg:province":"Ticino",
    "wof:name":"Muttoni & Beffa Sa",
    "wof:placetype":"venue"
},
  "geometry": {"coordinates":[8.794981,46.47945],"type":"Point"}
}