{
  "type": "Feature",
  "properties": {
    "iso:country":"CH",
    "sg:address":"Blattenstrasse 11c",
    "sg:city":"Niederteufen",
    "sg:orig_category":"Sonstige Aktivit\u00e4ten der nicht-\u00e4rztlichen Medizinalberufe",
    "sg:phone":"+41 71 333 29 39",
    "sg:postcode":"9052",
    "sg:province":"Appenzell Ausserrhoden",
    "wof:name":"Katharina Bieri Natur\u00e4rztliche Praxis",
    "wof:placetype":"venue"
},
  "geometry": {"coordinates":[9.3880252838,47.3905220032],"type":"Point"}
}