{
  "type": "Feature",
  "properties": {
    "iso:country":"CH",
    "sg:address":"Schillerstrasse 10",
    "sg:city":"Birsfelden",
    "sg:orig_category":"G\u00fcterbef\u00f6rderung im Strassenverkehr",
    "sg:phone":"+41 61 311 56 09",
    "sg:postcode":"4127",
    "sg:province":"Basel-Landschaft",
    "wof:name":"Dominique Scheidegger Kleintransporte Umz\u00fcge",
    "wof:placetype":"venue"
},
  "geometry": {"coordinates":[7.6195192337,47.5562973022],"type":"Point"}
}