{
  "type": "Feature",
  "properties": {
    "iso:country":"CH",
    "sg:address":"1902",
    "sg:city":"Evionnaz",
    "sg:orig_category":"Maschinen-Fabrikation",
    "sg:phone":"+41 32 751 44 44",
    "sg:postcode":"1902",
    "sg:province":"Valais",
    "wof:name":"Eigenheer F\u00e9lix, Jelosil",
    "wof:placetype":"venue"
},
  "geometry": {"coordinates":[7.0782690048,47.0592651367],"type":"Point"}
}