{
  "type": "Feature",
  "properties": {
    "iso:country":"CH",
    "sg:address":"Neumattstrasse 6",
    "sg:city":"Sissach",
    "sg:orig_category":"Herstellung von Metallerzeugnissen ohne Maschinenbau Herstellung von medizinischen U chirurgischen G",
    "sg:phone":"+41 61 971 24 43",
    "sg:postcode":"4450",
    "sg:province":"Basel-Landschaft",
    "wof:name":"Ardo Medical Ag",
    "wof:placetype":"venue"
},
  "geometry": {"coordinates":[7.8093519211,47.4617080688],"type":"Point"}
}