{
  "type": "Feature",
  "properties": {
    "iso:country":"CH",
    "sg:address":"Hofstrasse 1",
    "sg:city":"Sch\u00fcbelbach",
    "sg:orig_category":"Buchf\u00fchrung Verwaltung von Immobilien",
    "sg:phone":"+41 55 462 39 00",
    "sg:postcode":"8862",
    "sg:province":"Schwyz",
    "wof:name":"Astal Treuhand & Verwaltungs Ag",
    "wof:placetype":"venue"
},
  "geometry": {"coordinates":[8.85363,47.185997],"type":"Point"}
}