{
  "type": "Feature",
  "properties": {
    "iso:country":"CH",
    "sg:address":"Neuwiesenstrasse 9a",
    "sg:city":"Uster",
    "sg:orig_category":"Sportschulen Fern\u00f6stliche Kampfsportarten",
    "sg:phone":"+41 81 756 65 24",
    "sg:postcode":"8610",
    "sg:province":"Z\u00fcrich",
    "wof:name":"Karate Schule",
    "wof:placetype":"venue"
},
  "geometry": {"coordinates":[9.4679021835,47.1581916809],"type":"Point"}
}