{
  "type": "Feature",
  "properties": {
    "iso:country":"CH",
    "sg:address":"Sumpfstrasse 3",
    "sg:city":"Zug",
    "sg:orig_category":"Architektur U Ingenieurb\u00fcros",
    "sg:phone":"+41 41 740 11 69",
    "sg:postcode":"6300",
    "sg:province":"Zug",
    "wof:name":"Ingenieurb\u00fcro S\u00e4gesser Beat",
    "wof:placetype":"venue"
},
  "geometry": {"coordinates":[8.490865,47.186146],"type":"Point"}
}