{
  "type": "Feature",
  "properties": {
    "addr:full":"Marktgasse 25/27 Rheinfelden Aargau 4310",
    "addr:housenumber":"25 / 27",
    "addr:postcode":"4310",
    "addr:street":"Marktgasse",
    "iso:country":"CH",
    "sg:address":"Marktgasse 25/27",
    "sg:city":"Rheinfelden",
    "sg:orig_category":"Aktivit\u00e4ten der Generalunternehmen im Baugewerbe Allgemeiner Hoch U Tiefbau",
    "sg:phone":"+41 41 870 04 10",
    "sg:postcode":"4310",
    "sg:province":"Aargau",
    "wof:name":"S.p.m. Swim Product Management Ag",
    "wof:placetype":"venue"
},
  "geometry": {"coordinates":[8.61643,46.881874],"type":"Point"}
}