{
  "type": "Feature",
  "properties": {
    "iso:country":"CH",
    "sg:address":"D\u00e4hlenweg 1",
    "sg:city":"Adelboden",
    "sg:orig_category":"Malerei",
    "sg:phone":"+41 33 673 28 35",
    "sg:postcode":"3715",
    "sg:province":"Bern",
    "wof:name":"Christian Pieren Malergesch\u00e4ft",
    "wof:placetype":"venue"
},
  "geometry": {"coordinates":[7.5616540909,46.484375],"type":"Point"}
}