{
  "type": "Feature",
  "properties": {
    "iso:country":"CH",
    "sg:address":"Clarastrasse 55",
    "sg:city":"Basel",
    "sg:orig_category":"Erbringung von Dienstleistungen f\u00fcr Unternehmen",
    "sg:phone":"+41 61 681 81 83",
    "sg:postcode":"4058",
    "sg:province":"Basel-Stadt",
    "wof:name":"Expo Consult Basel Gmbh",
    "wof:placetype":"venue"
},
  "geometry": {"coordinates":[7.5985069275,47.5633354187],"type":"Point"}
}