{
  "type": "Feature",
  "properties": {
    "iso:country":"CH",
    "sg:address":"Bondastrasse 91",
    "sg:city":"Chur",
    "sg:orig_category":"Verlegen von Fliesen U Platten Verlegen von Fussboden",
    "sg:phone":"+41 79 221 34 63",
    "sg:postcode":"7000",
    "sg:province":"Graubunden",
    "wof:name":"Cohen-berchtold M",
    "wof:placetype":"venue"
},
  "geometry": {"coordinates":[9.5462589264,46.8595695496],"type":"Point"}
}