{
  "type": "Feature",
  "properties": {
    "iso:country":"CH",
    "sg:address":"Delsbergerallee 53",
    "sg:city":"Basel",
    "sg:orig_category":"Softwareentwicklung U beratung",
    "sg:phone":"+41 61 303 31 35",
    "sg:postcode":"4053",
    "sg:province":"Basel-Stadt",
    "wof:name":"Itb Informatik Team Ag",
    "wof:placetype":"venue"
},
  "geometry": {"coordinates":[7.5996217728,47.5398368835],"type":"Point"}
}