{
  "type": "Feature",
  "properties": {
    "iso:country":"CH",
    "sg:address":"M\u00e4rtplatz 3",
    "sg:city":"Effretikon",
    "sg:orig_category":"Grosshandel mit M\u00f6beln, Wohnbedarf, Teppichen U Bodenbel\u00e4gen Herstellung von Schneidwaren U Bestecke",
    "sg:phone":"+41 21 616 53 85",
    "sg:postcode":"8307",
    "sg:province":"Z\u00fcrich",
    "wof:name":"Katz Fils",
    "wof:placetype":"venue"
},
  "geometry": {"coordinates":[6.6268501282,46.5132408142],"type":"Point"}
}