{
  "type": "Feature",
  "properties": {
    "iso:country":"CH",
    "sg:address":"3053",
    "sg:city":"M\u00fcnchenbuchsee",
    "sg:orig_category":"Schulpflegen",
    "sg:postcode":"3053",
    "sg:province":"Bern",
    "wof:name":"Sekundarschulkommission Der Gemeinde M\u00fcnchwilen",
    "wof:placetype":"venue"
},
  "geometry": {"coordinates":[8.9961204529,47.4795417786],"type":"Point"}
}