{
  "type": "Feature",
  "properties": {
    "iso:country":"CH",
    "sg:address":"Bahnhofstrasse 49",
    "sg:city":"Aarau",
    "sg:orig_category":"Pensionskassen",
    "sg:phone":"+41 62 838 80 80",
    "sg:postcode":"5000",
    "sg:province":"Aargau",
    "wof:name":"F\u00fcrsorgestiftung Der Neuen Aargauer Bank",
    "wof:placetype":"venue"
},
  "geometry": {"coordinates":[8.0484609604,47.3915405273],"type":"Point"}
}