{
  "type": "Feature",
  "properties": {
    "iso:country":"CH",
    "sg:address":"Regensbergstrasse 177",
    "sg:city":"Z\u00fcrich",
    "sg:orig_category":"Detailhandel mit Sportartikeln Fachdetailhandel in Verkaufsr\u00e4umen",
    "sg:phone":"+41 18223165",
    "sg:postcode":"8050",
    "sg:province":"Z\u00fcrich",
    "wof:name":"Unihoc Sport Gmbh",
    "wof:placetype":"venue"
},
  "geometry": {"coordinates":[8.5380506516,47.4089660645],"type":"Point"}
}