{
  "type": "Feature",
  "properties": {
    "iso:country":"CH",
    "sg:address":"Palazzo Sileno",
    "sg:city":"Rivera",
    "sg:orig_category":"Detailhandel mit Schreib U Papeteriewaren Herstellung von Schreibwaren U B\u00fcrobedarf aus Papier, Kart",
    "sg:phone":"+41 31 331 28 29",
    "sg:postcode":"6802",
    "sg:province":"Ticino",
    "wof:name":"Pap-art Ag",
    "wof:placetype":"venue"
},
  "geometry": {"coordinates":[7.4516129494,46.9559822083],"type":"Point"}
}