{
  "type": "Feature",
  "properties": {
    "addr:full":"Viale Stazione 25 Bellinzona Ticino 6500",
    "addr:housenumber":"25",
    "addr:postcode":"6500",
    "addr:street":"Viale Stazione",
    "iso:country":"CH",
    "sg:address":"Viale Stazione 25",
    "sg:city":"Bellinzona",
    "sg:classifiers":[
        {
            "category":"Banks & Credit Unions",
            "subcategory":"Bank",
            "type":"Services"
        }
    ],
    "sg:phone":"+41 91 820 61 11",
    "sg:postcode":"6500",
    "sg:province":"Ticino",
    "wof:name":"Banca Del Gottardo",
    "wof:placetype":"venue"
},
  "geometry": {"coordinates":[9.027143,46.194454],"type":"Point"}
}