{
  "type": "Feature",
  "properties": {
    "iso:country":"CH",
    "sg:address":"Lindenstrasse",
    "sg:city":"Kloten",
    "sg:orig_category":"Non-Classified Establishments",
    "sg:phone":"+41 56 225 03 51",
    "sg:postcode":"8302",
    "sg:province":"Z\u00fcrich",
    "wof:name":"Pyramedia Stalder",
    "wof:placetype":"venue"
},
  "geometry": {"coordinates":[8.2476234436,47.4612464905],"type":"Point"}
}