{
  "type": "Feature",
  "properties": {
    "iso:country":"CH",
    "sg:address":"Zentrum 1 8102 Oberengstringen. Postfach",
    "sg:city":"Oberengstringen",
    "sg:classifiers":[
        {
            "category":"Restaurant",
            "type":"Food & Drink"
        }
    ],
    "sg:phone":"+41 17500000",
    "sg:postcode":"8102",
    "sg:province":"Z\u00fcrich",
    "wof:name":"Restaurant Rebe",
    "wof:placetype":"venue"
},
  "geometry": {"coordinates":[8.4608974457,47.4086151123],"type":"Point"}
}