{
  "type": "Feature",
  "properties": {
    "iso:country":"CH",
    "sg:address":"Badstrasse 1 9230 Flawil. Postfach",
    "sg:city":"Flawil",
    "sg:orig_category":"Allgemeiner Hoch U Tiefbau S\u00e4gewerke",
    "sg:phone":"+41 71 393 16 72",
    "sg:postcode":"9230",
    "sg:province":"St. Gallen",
    "wof:name":"H\u00e4rtsch Ag, Flawil",
    "wof:placetype":"venue"
},
  "geometry": {"coordinates":[9.18702,47.411072],"type":"Point"}
}