{
  "type": "Feature",
  "properties": {
    "iso:country":"CH",
    "sg:address":"Ettiswilerstrasse",
    "sg:city":"Alberswil",
    "sg:classifiers":[
        {
            "category":"Banks & Credit Unions",
            "subcategory":"Bank",
            "type":"Services"
        }
    ],
    "sg:phone":"+41 4145712182",
    "sg:postcode":"6248",
    "sg:province":"Luzern",
    "wof:name":"Schweiz. Mobiliar",
    "wof:placetype":"venue"
},
  "geometry": {"coordinates":[8.005985,47.149784],"type":"Point"}
}