{
  "type": "Feature",
  "properties": {
    "addr:full":"Stalden 314 Biembach Bern 3419",
    "addr:housenumber":"314",
    "addr:postcode":"3419",
    "addr:street":"Stalden",
    "iso:country":"CH",
    "sg:address":"Stalden 314",
    "sg:city":"Biembach",
    "sg:orig_category":"Bauschreinerei Herstellung von Konstruktionsteilen, Fertigbauteilen U Ausbauelementen aus Holz",
    "sg:phone":"+41 34 461 27 55",
    "sg:postcode":"3419",
    "sg:province":"Bern",
    "wof:name":"Schreinerei Iseli Ag",
    "wof:placetype":"venue"
},
  "geometry": {"coordinates":[7.628309,47.002251],"type":"Point"}
}