{
  "type": "Feature",
  "properties": {
    "iso:country":"CH",
    "sg:address":"Hauptstrasse 148 2552 Orpund. Postfach",
    "sg:city":"Orpund",
    "sg:orig_category":"RESTAURANTS: TEA-ROOMS",
    "sg:phone":"+41 32 355 11 07",
    "sg:postcode":"2552",
    "sg:province":"Bern",
    "wof:name":"Werro Peter",
    "wof:placetype":"venue"
},
  "geometry": {"coordinates":[7.3025112152,47.1400299072],"type":"Point"}
}