{
  "type": "Feature",
  "properties": {
    "iso:country":"CH",
    "sg:address":"Aeulestrasse 22",
    "sg:city":"Triesen",
    "sg:orig_category":"Schlossereien Stahl U Leichtmetallbau",
    "sg:phone":"+41 26 912 68 10",
    "sg:postcode":"9495",
    "wof:name":"R. Morand & Fils Sa Constructions M\u00e9talliques",
    "wof:placetype":"venue"
},
  "geometry": {"coordinates":[7.0758109093,46.6026306152],"type":"Point"}
}