{
  "type": "Feature",
  "properties": {
    "iso:country":"CH",
    "sg:address":"1064",
    "sg:city":"St-cierges",
    "sg:orig_category":"Primarschulen",
    "sg:phone":"+41 21 905 31 53",
    "sg:postcode":"1064",
    "wof:name":"Ecole Primaire",
    "wof:placetype":"venue"
},
  "geometry": {"coordinates":[6.7349619865,46.6901321411],"type":"Point"}
}