{
  "type": "Feature",
  "properties": {
    "iso:country":"CH",
    "sg:address":"Sandstrasse 62",
    "sg:city":"Meiringen",
    "sg:orig_category":"Wirtschaftspr\u00fcfung, Steuerberatung U Treuhand",
    "sg:phone":"+41 33 971 26 78",
    "sg:postcode":"3860",
    "sg:province":"Bern",
    "wof:name":"Huber & Anderegg",
    "wof:placetype":"venue"
},
  "geometry": {"coordinates":[8.1937770844,46.7234725952],"type":"Point"}
}