{
  "type": "Feature",
  "properties": {
    "addr:full":"Morgartenstr. 1 Z\u00fcrich Z\u00fcrich 8004",
    "addr:housenumber":"1",
    "addr:postcode":"8004",
    "addr:street":"Morgartenstr.",
    "iso:country":"CH",
    "sg:address":"Morgartenstr. 1",
    "sg:city":"Z\u00fcrich",
    "sg:classifiers":[
        {
            "category":"Banks & Credit Unions",
            "subcategory":"Bank",
            "type":"Services"
        }
    ],
    "sg:phone":"+41 12952111",
    "sg:postcode":"8004",
    "sg:province":"Z\u00fcrich",
    "wof:name":"Cantrade Privatbank Ag",
    "wof:placetype":"venue"
},
  "geometry": {"coordinates":[8.529967,47.371037],"type":"Point"}
}