{
  "type": "Feature",
  "properties": {
    "iso:country":"CH",
    "sg:address":"6523",
    "sg:city":"Preonzo",
    "sg:orig_category":"Darlehenskassen U Raiffeisenbanken",
    "sg:phone":"+41 91 863 21 84",
    "sg:postcode":"6523",
    "sg:province":"Ticino",
    "wof:name":"Banca Raiffeisen",
    "wof:placetype":"venue"
},
  "geometry": {"coordinates":[8.999829,46.265148],"type":"Point"}
}