{
  "type": "Feature",
  "properties": {
    "iso:country":"CH",
    "sg:address":"6404",
    "sg:city":"Greppen",
    "sg:orig_category":"Wasserversorgung",
    "sg:phone":"+41 41 870 55 60",
    "sg:postcode":"6404",
    "sg:province":"Luzern",
    "wof:name":"Wasserversorgung",
    "wof:placetype":"venue"
},
  "geometry": {"coordinates":[8.639749527,46.8880310059],"type":"Point"}
}