{
  "type": "Feature",
  "properties": {
    "iso:country":"CH",
    "sg:address":"Gotthardstrasse 55",
    "sg:city":"Thalwil",
    "sg:orig_category":"Detailhandel mit Pelzwaren",
    "sg:phone":"+41 17723833",
    "sg:postcode":"8800",
    "sg:province":"Z\u00fcrich",
    "wof:name":"Pelzatelier Bachmann",
    "wof:placetype":"venue"
},
  "geometry": {"coordinates":[8.561955452,47.2977752686],"type":"Point"}
}