{
  "type": "Feature",
  "properties": {
    "iso:country":"CH",
    "sg:address":"Rue De Fontenay 15",
    "sg:city":"Yverdon-les-bains",
    "sg:orig_category":"Institutionen f\u00fcr psychosoziale F\u00e4lle",
    "sg:phone":"+41 24 425 09 98",
    "sg:postcode":"1400",
    "sg:province":"Vaud",
    "wof:name":"Apsip-foyer Du Mujon",
    "wof:placetype":"venue"
},
  "geometry": {"coordinates":[6.6329298019,46.7840003967],"type":"Point"}
}