{
  "type": "Feature",
  "properties": {
    "addr:full":"M\u00fchlestrasse 23a Schlosswil Bern 3082",
    "addr:housenumber":"23a",
    "addr:postcode":"3082",
    "addr:street":"Muehlestrasse",
    "iso:country":"CH",
    "sg:address":"M\u00fchlestrasse 23a",
    "sg:city":"Schlosswil",
    "sg:orig_category":"Bauschreinerei Zimmerei, Ingenieurholzbau",
    "sg:phone":"+41 31 711 29 49",
    "sg:postcode":"3082",
    "sg:province":"Bern",
    "wof:name":"Erwin Lehmann Holzbau",
    "wof:placetype":"venue"
},
  "geometry": {"coordinates":[7.598432,46.913956],"type":"Point"}
}