{
  "type": "Feature",
  "properties": {
    "iso:country":"CH",
    "sg:address":"Altmattweg 57 4600 Olten. Postfach",
    "sg:city":"Olten",
    "sg:orig_category":"Sonstige mit der Informatik verbundene T\u00e4tigkeiten",
    "sg:postcode":"4600",
    "sg:province":"Solothurn",
    "wof:name":"It Consulting Tiemann Beratungen Im Informatikbereich",
    "wof:placetype":"venue"
},
  "geometry": {"coordinates":[7.8909368515,47.3491668701],"type":"Point"}
}