{
  "type": "Feature",
  "properties": {
    "iso:country":"CH",
    "sg:address":"Milit\u00e4rstrasse 6 3604 Thun. Postfach",
    "sg:city":"Thun",
    "sg:orig_category":"Hardwareberatung",
    "sg:phone":"+41 33 221 52 23",
    "sg:postcode":"3604",
    "sg:province":"Bern",
    "wof:name":"Caretech Computing Gmbh Pc's U. Computernetzwerke Usw.; Verkauf",
    "wof:placetype":"venue"
},
  "geometry": {"coordinates":[7.6277151108,46.7410850525],"type":"Point"}
}