{
  "type": "Feature",
  "properties": {
    "iso:country":"CH",
    "sg:address":"Bleichestrasse 20",
    "sg:city":"Winterthur",
    "sg:orig_category":"Verlegen von Fliesen U Platten",
    "sg:phone":"+41 21 635 92 79",
    "sg:postcode":"8400",
    "sg:province":"Z\u00fcrich",
    "wof:name":"Gilbert Favre Carrelages & Rev\u00eatements",
    "wof:placetype":"venue"
},
  "geometry": {"coordinates":[6.59522295,46.53881073],"type":"Point"}
}