{
  "type": "Feature",
  "properties": {
    "iso:country":"CH",
    "sg:address":"Echallens Avenue D' 38",
    "sg:city":"Lausanne",
    "sg:classifiers":[
        {
            "category":"Bars & Pubs",
            "type":"Food & Drink"
        }
    ],
    "sg:postcode":"1004",
    "sg:province":"Vaud",
    "wof:name":"L'etrier, Papis",
    "wof:placetype":"venue"
},
  "geometry": {"coordinates":[6.856867,46.453026],"type":"Point"}
}