{
  "type": "Feature",
  "properties": {
    "addr:full":"Im Spitzacker 14 Basel Basel-Stadt 4059",
    "addr:housenumber":"14",
    "addr:postcode":"4059",
    "addr:street":"Im Spitzacker",
    "iso:country":"CH",
    "sg:address":"Im Spitzacker 14",
    "sg:city":"Basel",
    "sg:orig_category":"Architektur U Ingenieurb\u00fcros",
    "sg:postcode":"4059",
    "sg:province":"Basel-Stadt",
    "wof:name":"Polasek Dr. Wolfgang",
    "wof:placetype":"venue"
},
  "geometry": {"coordinates":[7.59947,47.528008],"type":"Point"}
}