{
  "type": "Feature",
  "properties": {
    "iso:country":"CH",
    "sg:address":"Wahlenweg 11",
    "sg:city":"M\u00fcnchenstein",
    "sg:orig_category":"Selbst\u00e4ndige bildende K\u00fcnstler",
    "sg:phone":"+41 61 411 72 19",
    "sg:postcode":"4142",
    "sg:province":"Basel-Landschaft",
    "wof:name":"Walter Kaufmann Bildhauerei, Herstellung V. Grabsteinen",
    "wof:placetype":"venue"
},
  "geometry": {"coordinates":[7.6032848358,47.5253105164],"type":"Point"}
}