{
  "type": "Feature",
  "properties": {
    "iso:country":"CH",
    "sg:address":"Bahnhofstrasse 21",
    "sg:city":"Romanshorn",
    "sg:orig_category":"RESTAURANTS: TEA-ROOMS",
    "sg:postcode":"8590",
    "sg:province":"Thurgau",
    "wof:name":"Burkhardt Manfred",
    "wof:placetype":"venue"
},
  "geometry": {"coordinates":[9.3734397888,47.5658111572],"type":"Point"}
}