{
  "type": "Feature",
  "properties": {
    "iso:country":"CH",
    "sg:address":"Auf Der Mauer",
    "sg:city":"Lohnstorf",
    "sg:orig_category":"Bauschreinerei Herstellung von M\u00f6beln",
    "sg:phone":"+41 31 809 01 80",
    "sg:postcode":"3127",
    "sg:province":"Bern",
    "wof:name":"Paul Burri Schlittenbau & Schreinerei",
    "wof:placetype":"venue"
},
  "geometry": {"coordinates":[7.507902,46.808746],"type":"Point"}
}