{
  "type": "Feature",
  "properties": {
    "iso:country":"CH",
    "sg:address":"Al Piano 6515 Gudo. Postfach",
    "sg:city":"Gudo",
    "sg:orig_category":"Verwaltung von Immobilien",
    "sg:postcode":"6515",
    "sg:province":"Ticino",
    "wof:name":"Giocasa Sa",
    "wof:placetype":"venue"
},
  "geometry": {"coordinates":[8.9543533325,46.1708755493],"type":"Point"}
}