{
  "type": "Feature",
  "properties": {
    "iso:country":"CH",
    "sg:address":"J\u00f6chlerweg 4a",
    "sg:city":"Baar",
    "sg:orig_category":"Maler U Glasergewerbe Tapeziererei",
    "sg:phone":"+41 41 761 05 05",
    "sg:postcode":"6340",
    "sg:province":"Zug",
    "wof:name":"Malergesch\u00e4ft Christmann Gmbh",
    "wof:placetype":"venue"
},
  "geometry": {"coordinates":[8.5264387131,47.2003974915],"type":"Point"}
}