{
  "type": "Feature",
  "properties": {
    "iso:country":"CH",
    "sg:address":"Mazot Blanc Ruelle Du",
    "sg:city":"Fully",
    "sg:orig_category":"Interessenvertretungen",
    "sg:postcode":"1926",
    "sg:province":"Valais",
    "wof:name":"Fondation Casa Juan Diego",
    "wof:placetype":"venue"
},
  "geometry": {"coordinates":[7.1149711609,46.1398735046],"type":"Point"}
}