{
  "type": "Feature",
  "properties": {
    "iso:country":"CH",
    "sg:address":"Im Halden\u00e4cher 4",
    "sg:city":"Bellikon",
    "sg:orig_category":"Vereine Diverse",
    "sg:phone":"+41 56 496 01 05",
    "sg:postcode":"5454",
    "sg:province":"Aargau",
    "wof:name":"Museumsverein Bellikon",
    "wof:placetype":"venue"
},
  "geometry": {"coordinates":[8.3468322754,47.3897590637],"type":"Point"}
}