{
  "type": "Feature",
  "properties": {
    "iso:country":"CH",
    "sg:address":"St. Alban-vorstadt 10",
    "sg:city":"Basel",
    "sg:orig_category":"Kunsthandel",
    "sg:phone":"+41 61 272 21 57",
    "sg:postcode":"4052",
    "sg:province":"Basel-Stadt",
    "wof:name":"Galerie Anita Neugebauer",
    "wof:placetype":"venue"
},
  "geometry": {"coordinates":[7.6016559601,47.5541038513],"type":"Point"}
}