{
  "type": "Feature",
  "properties": {
    "iso:country":"CH",
    "sg:address":"Dorfackerstrasse 3 4528 Zuchwil. Postfach",
    "sg:city":"Zuchwil",
    "sg:orig_category":"Grosshandel mit Holz U Baustoffen Herstellung von Erzeugnissen aus Beton, Gips U Zement",
    "sg:phone":"+41 56 225 11 76",
    "sg:postcode":"4528",
    "sg:province":"Solothurn",
    "wof:name":"Baustoff Birmenstorf Ag",
    "wof:placetype":"venue"
},
  "geometry": {"coordinates":[8.2584075928,47.449256897],"type":"Point"}
}