{
  "type": "Feature",
  "properties": {
    "iso:country":"CH",
    "sg:address":"6652 Tegna. Postfach",
    "sg:city":"Tegna",
    "sg:orig_category":"Elektroinstallation",
    "sg:phone":"+41 91 827 11 55",
    "sg:postcode":"6652",
    "sg:province":"Ticino",
    "wof:name":"Mondini Sa Elettrigil\u00c0 Impianti Elettrici, Televisivi Ecc; Progettaz., Esecuz., Installaz.",
    "wof:placetype":"venue"
},
  "geometry": {"coordinates":[9.1333045959,46.239276886],"type":"Point"}
}