{
  "type": "Feature",
  "properties": {
    "iso:country":"CH",
    "sg:address":"Zentralstrasse 56 2500 Biel/bienne. Postfach",
    "sg:city":"Biel/bienne",
    "sg:orig_category":"RESTAURANTS: TEA-ROOMS",
    "sg:postcode":"2502",
    "sg:province":"Bern",
    "wof:name":"Weidenbach Martin",
    "wof:placetype":"venue"
},
  "geometry": {"coordinates":[7.2478861809,47.1354560852],"type":"Point"}
}