{
  "type": "Feature",
  "properties": {
    "addr:full":"Mythenstrasse 15a Einsiedeln Schwyz 8840",
    "addr:housenumber":"15a",
    "addr:postcode":"8840",
    "addr:street":"Mythenstrasse;Schwyz",
    "iso:country":"CH",
    "sg:address":"Mythenstrasse 15a",
    "sg:city":"Einsiedeln",
    "sg:classifiers":[
        {
            "category":"Banks & Credit Unions",
            "subcategory":"Bureau De Change",
            "type":"Services"
        }
    ],
    "sg:phone":"+41 55 418 96 66",
    "sg:postcode":"8840",
    "sg:province":"Schwyz",
    "sg:tags":[
        "design",
        "system",
        "cad/cae"
    ],
    "wof:name":"Stefan K\u00e4lin Ag",
    "wof:placetype":"venue"
},
  "geometry": {"coordinates":[8.742991,47.12677],"type":"Point"}
}