{
  "type": "Feature",
  "properties": {
    "iso:country":"CH",
    "sg:address":"Staldenweg 54",
    "sg:city":"Berikon",
    "sg:orig_category":"Unternehmensberatung",
    "sg:postcode":"8965",
    "sg:province":"Aargau",
    "wof:name":"Orgex Georges Dupraz",
    "wof:placetype":"venue"
},
  "geometry": {"coordinates":[6.2295432091,46.2609291077],"type":"Point"}
}