{
  "type": "Feature",
  "properties": {
    "iso:country":"CH",
    "sg:address":"Menzbergstrasse 7",
    "sg:city":"Willisau",
    "sg:orig_category":"Detailhandel mit Damenbekleidung Herstellung von Oberbekleidung",
    "sg:phone":"+41 41 970 12 62",
    "sg:postcode":"6130",
    "sg:province":"Luzern",
    "wof:name":"Mode Zeder, Inhaberin Zeder Erika",
    "wof:placetype":"venue"
},
  "geometry": {"coordinates":[7.9944019318,47.1198997498],"type":"Point"}
}