{
  "type": "Feature",
  "properties": {
    "iso:country":"CH",
    "sg:address":"Moos\u00e4ckerstrasse 73 8105 Regensdorf. Postfach 447",
    "sg:city":"Regensdorf",
    "sg:orig_category":"Detailhandel mit elektrischen Haushalts-,Radio U Fernsehger\u00e4ten sowie Musikinstrumenten Grosshandel ",
    "sg:phone":"+41 79 402 69 11",
    "sg:postcode":"8105",
    "sg:province":"Z\u00fcrich",
    "wof:name":"Zoller B. Ag",
    "wof:placetype":"venue"
},
  "geometry": {"coordinates":[8.6049900055,47.3990058899],"type":"Point"}
}