{
  "type": "Feature",
  "properties": {
    "iso:country":"CH",
    "sg:address":"Utoquai 55 8008 Z\u00fcrich. Postfach",
    "sg:city":"Z\u00fcrich",
    "sg:orig_category":"Reiseb\u00fcros U Reiseveranstalter",
    "sg:postcode":"8022",
    "sg:province":"Z\u00fcrich",
    "wof:name":"Cosa Travel Ltd Reisen, Transporte Usw; Organisation",
    "wof:placetype":"venue"
},
  "geometry": {"coordinates":[8.5478601456,47.361782074],"type":"Point"}
}