{
  "type": "Feature",
  "properties": {
    "iso:country":"CH",
    "sg:address":"Parc-de-la-rouvraie Av. 10 1018 Lausanne. Postfach",
    "sg:city":"Lausanne",
    "sg:orig_category":"Fotografisches Gewerbe U fotografische Laboratorien",
    "sg:postcode":"1018",
    "sg:province":"Vaud",
    "wof:name":"Photographie Coudre",
    "wof:placetype":"venue"
},
  "geometry": {"coordinates":[6.1455068588,46.1831054688],"type":"Point"}
}