{
  "type": "Feature",
  "properties": {
    "iso:country":"CH",
    "sg:address":"Via Pitgmun 16",
    "sg:city":"Sedrun",
    "sg:orig_category":"Architektur U Ingenieurb\u00fcros Bauingenieurb\u00fcros",
    "sg:phone":"+41 81 949 20 60",
    "sg:postcode":"7188",
    "sg:province":"Graubunden",
    "wof:name":"Cridea Bauteam Gmbh",
    "wof:placetype":"venue"
},
  "geometry": {"coordinates":[8.773967,46.682091],"type":"Point"}
}