{
  "type": "Feature",
  "properties": {
    "iso:country":"CH",
    "sg:address":"Bahnhofstrasse 6",
    "sg:city":"Oensingen",
    "sg:orig_category":"Wirtschaftspr\u00fcfung, Steuerberatung U Treuhand",
    "sg:phone":"+41 62 396 12 12",
    "sg:postcode":"4702",
    "sg:province":"Solothurn",
    "wof:name":"Meier Urs Treuhand Gmbh",
    "wof:placetype":"venue"
},
  "geometry": {"coordinates":[7.707804203,47.2857246399],"type":"Point"}
}