{
  "type": "Feature",
  "properties": {
    "iso:country":"CH",
    "sg:address":"Forestier Route H. C. 1",
    "sg:city":"Meyrin",
    "sg:orig_category":"Sonstige Hilfs U Nebent\u00e4tigkeiten f\u00fcr die Luftfahrt",
    "sg:phone":"+41 22 717 83 83",
    "sg:postcode":"1217",
    "sg:province":"Gen\u00e8ve",
    "wof:name":"Swift Copters Sa",
    "wof:placetype":"venue"
},
  "geometry": {"coordinates":[6.0722160339,46.2284431458],"type":"Point"}
}