{
  "type": "Feature",
  "properties": {
    "iso:country":"CH",
    "sg:address":"Wilerstrasse 6 9554 T\u00e4gerschen. Postfach",
    "sg:city":"T\u00e4gerschen",
    "sg:orig_category":"RESTAURANTS: TEA-ROOMS",
    "sg:postcode":"9554",
    "sg:province":"Thurgau",
    "wof:name":"Weisskreuz Ag",
    "wof:placetype":"venue"
},
  "geometry": {"coordinates":[9.0302228928,47.5092086792],"type":"Point"}
}