{
  "type": "Feature",
  "properties": {
    "iso:country":"CH",
    "sg:address":"Industriestrasse 1",
    "sg:city":"M\u00fcnchenbuchsee",
    "sg:orig_category":"Interessenvertretungen",
    "sg:postcode":"3053",
    "sg:province":"Bern",
    "wof:name":"Schweiz. Stiftung F\u00fcr Forschung Und Ausbildung Qualit\u00e4t Sfaq",
    "wof:placetype":"venue"
},
  "geometry": {"coordinates":[7.4649147987,47.0037155151],"type":"Point"}
}