{
  "type": "Feature",
  "properties": {
    "iso:country":"CH",
    "sg:address":"Fluhmattstrasse 16 6004 Luzern. Postfach",
    "sg:city":"Luzern",
    "sg:orig_category":"Sanit\u00e4r, Heizungs U L\u00fcftungsinstallation",
    "sg:phone":"+41 21 866 77 08",
    "sg:postcode":"6003",
    "sg:province":"Luzern",
    "wof:name":"Junod M.",
    "wof:placetype":"venue"
},
  "geometry": {"coordinates":[6.5096879005,46.6576652527],"type":"Point"}
}