{
  "type": "Feature",
  "properties": {
    "iso:country":"CH",
    "sg:address":"Belv\u00e9d\u00e8re",
    "sg:city":"Leysin",
    "sg:classifiers":[
        {
            "category":"Bus Stop",
            "subcategory":"None",
            "type":"Transportation"
        }
    ],
    "sg:phone":"+41 24 493 45 90",
    "sg:postcode":"1854",
    "sg:province":"Vaud",
    "sg:tags":[
        "flat-wire",
        "spring"
    ],
    "wof:name":"La Manufacture",
    "wof:placetype":"venue"
},
  "geometry": {"coordinates":[7.0142121315,46.3459014893],"type":"Point"}
}