{
  "type": "Feature",
  "properties": {
    "iso:country":"CH",
    "sg:address":"Bourbakistrasse 11",
    "sg:city":"Solothurn",
    "sg:orig_category":"Kosmetikinstitute",
    "sg:phone":"+41 79 330 16 88",
    "sg:postcode":"4500",
    "sg:province":"Solothurn",
    "wof:name":"Isabelle K\u00f6hle Kosmetikinstitut Isabelle",
    "wof:placetype":"venue"
},
  "geometry": {"coordinates":[7.522233963,47.2110099792],"type":"Point"}
}