{
  "type": "Feature",
  "properties": {
    "iso:country":"CH",
    "sg:address":"Industrieplatz",
    "sg:city":"Neuhausen",
    "sg:orig_category":"Mechanik Schlossereien",
    "sg:phone":"+41 79 629 65 04",
    "sg:postcode":"8212",
    "sg:province":"Schaffhausen",
    "wof:name":"Schlosserei Vogelsanger",
    "wof:placetype":"venue"
},
  "geometry": {"coordinates":[8.6184167862,47.6796035767],"type":"Point"}
}