{
  "type": "Feature",
  "properties": {
    "iso:country":"CH",
    "sg:address":"Stauffacherstrasse 130a",
    "sg:city":"Bern",
    "sg:classifiers":[
        {
            "category":"Shopping",
            "subcategory":"Discount & Variety Stores",
            "type":"Retail Goods"
        }
    ],
    "sg:phone":"+41 31 332 66 16",
    "sg:postcode":"3014",
    "sg:province":"Bern",
    "sg:tags":[
        "shop",
        "locksmith's"
    ],
    "wof:name":"Casaulta & Klos",
    "wof:placetype":"venue"
},
  "geometry": {"coordinates":[7.4654288292,46.9684791565],"type":"Point"}
}