{
  "type": "Feature",
  "properties": {
    "iso:country":"CH",
    "sg:address":"Rampe De La Gare 7",
    "sg:city":"Versoix",
    "sg:classifiers":[
        {
            "category":"Manufacturing",
            "subcategory":"Glass & Minerals",
            "type":"Manufacturing & Wholesale Goods"
        }
    ],
    "sg:phone":"+41 22 755 50 59",
    "sg:postcode":"1290",
    "sg:province":"Gen\u00e8ve",
    "sg:tags":[
        "cleaning",
        "agent"
    ],
    "wof:name":"Louis Cuttat Lunetterie",
    "wof:placetype":"venue"
},
  "geometry": {"coordinates":[6.166966,46.279392],"type":"Point"}
}