{
  "type": "Feature",
  "properties": {
    "iso:country":"CH",
    "sg:address":"Piazzale Comunale 4",
    "sg:city":"Biasca",
    "sg:orig_category":"Versicherungen Hauptagenturen",
    "sg:phone":"+41 91 862 21 76",
    "sg:postcode":"6710",
    "sg:province":"Ticino",
    "wof:name":"Winterthur-assicurazioni Agenzia Principale M.locatelli",
    "wof:placetype":"venue"
},
  "geometry": {"coordinates":[8.9709844589,46.3609390259],"type":"Point"}
}