{
  "type": "Feature",
  "properties": {
    "iso:country":"CH",
    "sg:address":"Engelgasse 20",
    "sg:city":"St.gallen",
    "sg:orig_category":"Non-Classified Establishments",
    "sg:postcode":"9000",
    "sg:province":"St. Gallen",
    "wof:name":"Diavolinho Gmbh",
    "wof:placetype":"venue"
},
  "geometry": {"coordinates":[9.3749227524,47.4270362854],"type":"Point"}
}