{
  "type": "Feature",
  "properties": {
    "iso:country":"CH",
    "sg:address":"Seilerstrasse 1 6438 Ibach. Postfach 21",
    "sg:city":"Schwyz",
    "sg:orig_category":"Versicherungen Generalagenturen",
    "sg:phone":"+41 41 811 29 12",
    "sg:postcode":"6431",
    "sg:province":"Schwyz",
    "wof:name":"Alpina Versicherungen Generalagentur Schwyz",
    "wof:placetype":"venue"
},
  "geometry": {"coordinates":[8.6497507095,47.0175056458],"type":"Point"}
}