{
  "type": "Feature",
  "properties": {
    "iso:country":"CH",
    "sg:address":"Winterthurerstrasse",
    "sg:city":"Flurlingen",
    "sg:classifiers":[
        {
            "category":"Train Station",
            "subcategory":"Light Rail",
            "type":"Transportation"
        }
    ],
    "sg:phone":"+41 52 647 33 11",
    "sg:postcode":"8247",
    "sg:province":"Z\u00fcrich",
    "sg:tags":[
        "twine",
        "baler"
    ],
    "wof:name":"Arova Schaffhausen Ag",
    "wof:placetype":"venue"
},
  "geometry": {"coordinates":[8.633326,47.679173],"type":"Point"}
}