{
  "type": "Feature",
  "properties": {
    "iso:country":"CH",
    "sg:address":"6944",
    "sg:city":"Cureglia",
    "sg:orig_category":"Architekturb\u00fcros",
    "sg:phone":"+41 91 972 66 44",
    "sg:postcode":"6944",
    "sg:province":"Ticino",
    "wof:name":"Chico Sartori Studio D'architettura",
    "wof:placetype":"venue"
},
  "geometry": {"coordinates":[8.94409,46.03701],"type":"Point"}
}