{
  "type": "Feature",
  "properties": {
    "iso:country":"CH",
    "sg:address":"Sulzerstrasse 22 4054 Basel. Postfach",
    "sg:city":"Basel",
    "sg:orig_category":"Fachdetailhandel in Verkaufsr\u00e4umen",
    "sg:postcode":"4051",
    "sg:province":"Basel-Stadt",
    "wof:name":"Ani-land Conte Rita Et Daniel Alimentation Et Accessoires Pour Animaux; Commerce",
    "wof:placetype":"venue"
},
  "geometry": {"coordinates":[7.0641651154,47.0518341064],"type":"Point"}
}