{
  "type": "Feature",
  "properties": {
    "iso:country":"CH",
    "sg:address":"Avenue De Longemalle 21",
    "sg:city":"Renens",
    "sg:orig_category":"High-Precision Axes",
    "sg:phone":"+41 21 634 33 77",
    "sg:postcode":"1020",
    "sg:province":"Vaud",
    "wof:name":"Arcia Constructions M\u00e9talliques Sa",
    "wof:placetype":"venue"
},
  "geometry": {"coordinates":[6.5951161385,46.5269317627],"type":"Point"}
}