{
  "type": "Feature",
  "properties": {
    "iso:country":"CH",
    "sg:address":"Hasenrainstrasse 96",
    "sg:city":"Binningen",
    "sg:classifiers":[
        {
            "category":"Travel",
            "subcategory":"Hotels & Motels",
            "type":"Entertainment"
        }
    ],
    "sg:postcode":"4102",
    "sg:province":"Basel-Landschaft",
    "sg:tags":[
        "hotels",
        "mit",
        "restaurant"
    ],
    "wof:name":"Gastro Fatal Gmbh",
    "wof:placetype":"venue"
},
  "geometry": {"coordinates":[7.5694818497,47.5436553955],"type":"Point"}
}