{
  "type": "Feature",
  "properties": {
    "iso:country":"CH",
    "sg:address":"B\u00e4chliweg 8",
    "sg:city":"Waldkirch",
    "sg:orig_category":"Sportvereine Ballsport Tennis",
    "sg:phone":"+41 71 433 15 35",
    "sg:postcode":"9205",
    "sg:province":"St. Gallen",
    "wof:name":"Tc Gossau Sg",
    "wof:placetype":"venue"
},
  "geometry": {"coordinates":[9.2915458679,47.4696922302],"type":"Point"}
}