{
  "type": "Feature",
  "properties": {
    "iso:country":"CH",
    "sg:address":"Usterstrasse 31",
    "sg:city":"M\u00f6nchaltorf",
    "sg:orig_category":"Instandhaltung U Reparatur von Automobilen",
    "sg:phone":"+41 52 337 32 45",
    "sg:postcode":"8617",
    "sg:province":"Z\u00fcrich",
    "wof:name":"Garage M\u00f6rsburg Ag",
    "wof:placetype":"venue"
},
  "geometry": {"coordinates":[8.7963285446,47.5516471863],"type":"Point"}
}