{
  "type": "Feature",
  "properties": {
    "iso:country":"CH",
    "sg:address":"Beaumont",
    "sg:city":"Blonay",
    "sg:orig_category":"Unclassifiable Establishments",
    "sg:postcode":"1807",
    "sg:province":"Vaud",
    "wof:name":"Gameya Sa",
    "wof:placetype":"venue"
},
  "geometry": {"coordinates":[6.8949828148,46.4651298523],"type":"Point"}
}