{
  "type": "Feature",
  "properties": {
    "iso:country":"CH",
    "sg:address":"Neuch\u00e2tel Route De 34",
    "sg:city":"Prilly",
    "sg:orig_category":"Herstellung von Spielwaren",
    "sg:phone":"+41 33 971 59 50",
    "sg:postcode":"1008",
    "sg:province":"Vaud",
    "wof:name":"Cuboro Ag",
    "wof:placetype":"venue"
},
  "geometry": {"coordinates":[8.2095518112,46.7326622009],"type":"Point"}
}