{
  "type": "Feature",
  "properties": {
    "iso:country":"CH",
    "sg:address":"Gasse 7 8846 Willerzell. Postfach",
    "sg:city":"Willerzell",
    "sg:orig_category":"Sonstige Kurierdienste",
    "sg:postcode":"8846",
    "sg:province":"Schwyz",
    "wof:name":"Roll Gmbh",
    "wof:placetype":"venue"
},
  "geometry": {"coordinates":[8.2050695419,47.2697525024],"type":"Point"}
}