{
  "type": "Feature",
  "properties": {
    "iso:country":"CH",
    "sg:address":"Kellerstrasse 8",
    "sg:city":"Luzern",
    "sg:orig_category":"Verlagsgewerbe Zeitungsverlag",
    "sg:phone":"+41 41 368 48 70",
    "sg:postcode":"6005",
    "sg:province":"Luzern",
    "wof:name":"Insider Verlag Ag",
    "wof:placetype":"venue"
},
  "geometry": {"coordinates":[8.3114004135,47.0434761047],"type":"Point"}
}