{
  "type": "Feature",
  "properties": {
    "iso:country":"CH",
    "sg:address":"Str\u00e4ttlingerweg 1",
    "sg:city":"H\u00fcnibach",
    "sg:orig_category":"Unclassifiable Establishments",
    "sg:postcode":"3626",
    "sg:province":"Bern",
    "wof:name":"Alfred Schweri Seilbahn-& Industrie-bedarf",
    "wof:placetype":"venue"
},
  "geometry": {"coordinates":[7.6449651718,46.7447853088],"type":"Point"}
}