{
  "type": "Feature",
  "properties": {
    "iso:country":"CH",
    "sg:address":"Kesselstrasse 12 8200 Schaffhausen. Postfach",
    "sg:city":"Schaffhausen",
    "sg:orig_category":"Grosshandel mit Kaffee, Tee, Kakao U Gew\u00fcrzen Verarbeitung von Tee U Kaffee",
    "sg:phone":"+41 52 625 33 33",
    "sg:postcode":"8203",
    "sg:province":"Schaffhausen",
    "wof:name":"Albert Pletscher Ag Bogen-kaffee",
    "wof:placetype":"venue"
},
  "geometry": {"coordinates":[8.6491365433,47.7014274597],"type":"Point"}
}