{
  "type": "Feature",
  "properties": {
    "iso:country":"CH",
    "sg:address":"Alte Landstrasse 2b",
    "sg:city":"Brig",
    "sg:orig_category":"Instandhaltung U Reparatur von Automobilen",
    "sg:phone":"+41 27 923 68 17",
    "sg:postcode":"3900",
    "sg:province":"Valais",
    "wof:name":"Andres Adolf Autoelektro Und Elektronik.",
    "wof:placetype":"venue"
},
  "geometry": {"coordinates":[7.9599208832,46.3054962158],"type":"Point"}
}