{
  "type": "Feature",
  "properties": {
    "iso:country":"CH",
    "sg:address":"Untere Geerenstrasse 20c",
    "sg:city":"D\u00fcbendorf",
    "sg:orig_category":"Mit dem Versicherungsgewerbe verbundene T\u00e4tigkeiten",
    "sg:phone":"+41 18041188",
    "sg:postcode":"8600",
    "sg:province":"Z\u00fcrich",
    "wof:name":"Franz Kost Versicherungen",
    "wof:placetype":"venue"
},
  "geometry": {"coordinates":[8.6150951385,47.388885498],"type":"Point"}
}