{
  "type": "Feature",
  "properties": {
    "iso:country":"CH",
    "sg:address":"Neue Bahnhofstrasse 3",
    "sg:city":"M\u00fcnsingen",
    "sg:orig_category":"Fachdetailhandel in Verkaufsr\u00e4umen",
    "sg:phone":"+41 31 721 01 54",
    "sg:postcode":"3110",
    "sg:province":"Bern",
    "wof:name":"Urs Kocher",
    "wof:placetype":"venue"
},
  "geometry": {"coordinates":[7.5619440079,46.874256134],"type":"Point"}
}