{
  "type": "Feature",
  "properties": {
    "iso:country":"CH",
    "sg:address":"R\u00e4ffelstrasse 25",
    "sg:city":"Z\u00fcrich",
    "sg:orig_category":"Reiseb\u00fcros",
    "sg:phone":"+41 15437500",
    "sg:postcode":"8045",
    "sg:province":"Z\u00fcrich",
    "wof:name":"Beyoo.com Reiseb\u00fcro",
    "wof:placetype":"venue"
},
  "geometry": {"coordinates":[8.513171196,47.3630065918],"type":"Point"}
}