{
  "type": "Feature",
  "properties": {
    "iso:country":"CH",
    "sg:address":"Pr\u00e9-de-la-tour Chemin Du 10",
    "sg:city":"Pully",
    "sg:orig_category":"Non-Classified Establishments",
    "sg:postcode":"1009",
    "sg:province":"Vaud",
    "wof:name":"Do! L'agence, Orville, Duvoisin, L\u00fcthi",
    "wof:placetype":"venue"
},
  "geometry": {"coordinates":[6.6589741707,46.5119361877],"type":"Point"}
}