{
  "type": "Feature",
  "properties": {
    "iso:country":"CH",
    "sg:address":"Grand-rue 34",
    "sg:city":"Lutry",
    "sg:orig_category":"Detailhandel mit Brot, Back U S\u00fcsswaren",
    "sg:phone":"+41 21 691 59 20",
    "sg:postcode":"1095",
    "sg:province":"Vaud",
    "wof:name":"Boulangerie Willommet Raymond S\u00e0rl Boulangerie, P\u00e2tisserie, Confiserie Etc",
    "wof:placetype":"venue"
},
  "geometry": {"coordinates":[6.561132,46.525433],"type":"Point"}
}