{
  "type": "Feature",
  "properties": {
    "addr:full":"Z\u00fcrcherstrasse 156 Frauenfeld Thurgau 8500",
    "addr:housenumber":"156",
    "addr:postcode":"8500",
    "addr:street":"Zuercherstrasse",
    "iso:country":"CH",
    "sg:address":"Z\u00fcrcherstrasse 156",
    "sg:city":"Frauenfeld",
    "sg:orig_category":"Detailhandel mit Beleuchtungs U Haushaltsgegenst\u00e4nden",
    "sg:phone":"+41 52 721 19 49",
    "sg:postcode":"8500",
    "sg:province":"Thurgau",
    "wof:name":"Kurt Hugentobler Haushalt-fachgesch\u00e4ft",
    "wof:placetype":"venue"
},
  "geometry": {"coordinates":[8.897353,47.555721],"type":"Point"}
}