{
  "type": "Feature",
  "properties": {
    "iso:country":"CH",
    "sg:address":"B\u00fcndtenweg 2",
    "sg:city":"Kaiseraugst",
    "sg:orig_category":"Elektro- and elektronische Maschinen Grosshandel Hardwareberatung",
    "sg:phone":"+41 61 813 95 00",
    "sg:postcode":"4303",
    "sg:province":"Aargau",
    "wof:name":"Printcorner Gmbh F\u00fcr Computerzubeh\u00f6r",
    "wof:placetype":"venue"
},
  "geometry": {"coordinates":[7.7195601463,47.5393791199],"type":"Point"}
}