{
  "type": "Feature",
  "properties": {
    "iso:country":"CH",
    "sg:address":"8232",
    "sg:city":"Merishausen",
    "sg:orig_category":"Detailhandel mit Waren verschiedener Art, Hauptrichtung Nahrungsmittel",
    "sg:phone":"+41 31 765 50 66",
    "sg:postcode":"8232",
    "sg:province":"Schaffhausen",
    "wof:name":"Landwirtschaftliche Genossenschaft Messen Und Umgebung",
    "wof:placetype":"venue"
},
  "geometry": {"coordinates":[-82.59181976319999,33.4613304138],"type":"Point"}
}