{
  "type": "Feature",
  "properties": {
    "iso:country":"CH",
    "sg:address":"Zugerstrasse 37",
    "sg:city":"W\u00e4denswil",
    "sg:orig_category":"Rechtsberatung",
    "sg:postcode":"8820",
    "sg:province":"Z\u00fcrich",
    "wof:name":"Hexsan Gmbh",
    "wof:placetype":"venue"
},
  "geometry": {"coordinates":[8.6681480408,47.2298851013],"type":"Point"}
}