{
  "type": "Feature",
  "properties": {
    "iso:country":"CH",
    "sg:address":"Industriestrasse 10 9642 Ebnat-kappel. Postfach 364",
    "sg:city":"Ebnat-kappel",
    "sg:orig_category":"Herstellung von Sportger\u00e4ten",
    "sg:phone":"+41 71 992 66 33",
    "sg:postcode":"9642",
    "sg:province":"St. Gallen",
    "wof:name":"Alder & Eisenhut Ag Turn-& Sportger\u00e4tefabrik",
    "wof:placetype":"venue"
},
  "geometry": {"coordinates":[9.1155834198,47.265750885],"type":"Point"}
}