{
  "type": "Feature",
  "properties": {
    "iso:country":"CH",
    "sg:address":"Guggsb\u00fchlstrasse 3",
    "sg:city":"Schlieren",
    "sg:orig_category":"Inseratevermittlung",
    "sg:phone":"+41 17301178",
    "sg:postcode":"8952",
    "sg:province":"Z\u00fcrich",
    "wof:name":"Franz M\u00fcller Annoncen",
    "wof:placetype":"venue"
},
  "geometry": {"coordinates":[8.442363739,47.3941497803],"type":"Point"}
}