{
  "type": "Feature",
  "properties": {
    "iso:country":"CH",
    "sg:address":"Grubenstrasse 141",
    "sg:city":"Feuerthalen",
    "sg:orig_category":"Unternehmensberatung",
    "sg:phone":"+41 21 944 56 76",
    "sg:postcode":"8245",
    "sg:province":"Z\u00fcrich",
    "wof:name":"Vogt Paul",
    "wof:placetype":"venue"
},
  "geometry": {"coordinates":[6.8568668365,46.4530258179],"type":"Point"}
}