{
  "type": "Feature",
  "properties": {
    "iso:country":"CH",
    "sg:address":"Rue Du Temple 3",
    "sg:city":"B\u00f4le",
    "sg:orig_category":"Finanzierungsinstitutionen",
    "sg:phone":"+41 32 842 63 22",
    "sg:postcode":"2014",
    "sg:province":"Neuch\u00e2tel",
    "wof:name":"Credim, Marceau Kaub",
    "wof:placetype":"venue"
},
  "geometry": {"coordinates":[6.8411631584,46.9671096802],"type":"Point"}
}