{
  "type": "Feature",
  "properties": {
    "iso:country":"CH",
    "sg:address":"Industriestrasse 23",
    "sg:city":"Hittnau",
    "sg:orig_category":"Sanit\u00e4r, Heizungs U L\u00fcftungsinstallation Sanit\u00e4rinstallation",
    "sg:phone":"+41 79 644 37 52",
    "sg:postcode":"8335",
    "sg:province":"Z\u00fcrich",
    "wof:name":"Storrer Werner",
    "wof:placetype":"venue"
},
  "geometry": {"coordinates":[8.8200101852,47.3669319153],"type":"Point"}
}