{
  "type": "Feature",
  "properties": {
    "iso:country":"CH",
    "sg:address":"Gerbergasse 4",
    "sg:city":"Bischofszell",
    "sg:orig_category":"Vereine Damen Vereine Gesang",
    "sg:phone":"+41 71 422 17 58",
    "sg:postcode":"9220",
    "sg:province":"Thurgau",
    "wof:name":"Damenchor Bischofszell",
    "wof:placetype":"venue"
},
  "geometry": {"coordinates":[9.2414226532,47.4931793213],"type":"Point"}
}