{
  "type": "Feature",
  "properties": {
    "iso:country":"CH",
    "sg:address":"Juchstrasse 27",
    "sg:city":"Frauenfeld",
    "sg:orig_category":"Grosshandel mit sonstigen Gebrauchs U Verbrauchsg\u00fctern",
    "sg:postcode":"8500",
    "sg:province":"Thurgau",
    "wof:name":"Schefer & Co.",
    "wof:placetype":"venue"
},
  "geometry": {"coordinates":[8.9091587067,47.5696258545],"type":"Point"}
}