{
  "type": "Feature",
  "properties": {
    "iso:country":"CH",
    "sg:address":"Les Jacolats 1853 Yvorne. Postfach",
    "sg:city":"Yvorne",
    "sg:orig_category":"Mechanik",
    "sg:postcode":"1853",
    "sg:province":"Vaud",
    "wof:name":"Gigandet Marcel",
    "wof:placetype":"venue"
},
  "geometry": {"coordinates":[6.9504160881,46.3307723999],"type":"Point"}
}