{
  "type": "Feature",
  "properties": {
    "iso:country":"CH",
    "sg:address":"M\u00fchlebachstrasse",
    "sg:city":"Grindelwald",
    "sg:classifiers":[
        {
            "category":"Social Services",
            "subcategory":"Retirement Home",
            "type":"Services"
        }
    ],
    "sg:phone":"+41 33 853 27 88",
    "sg:postcode":"3818",
    "sg:province":"Bern",
    "sg:tags":[
        "pflegeheime",
        "u",
        "alters"
    ],
    "wof:name":"Altersheim Eigerblick",
    "wof:placetype":"venue"
},
  "geometry": {"coordinates":[8.034633,46.624371],"type":"Point"}
}