{
  "type": "Feature",
  "properties": {
    "iso:country":"CH",
    "sg:address":"Nordstrasse 30",
    "sg:city":"Schaffhausen",
    "sg:orig_category":"Arztpraxen",
    "sg:phone":"+41 52 624 42 66",
    "sg:postcode":"8200",
    "sg:province":"Schaffhausen",
    "wof:name":"Dr.med.reto Winkler Arzt F.allgemeine Medizin Fmh",
    "wof:placetype":"venue"
},
  "geometry": {"coordinates":[8.628059,47.701336],"type":"Point"}
}