{
  "type": "Feature",
  "properties": {
    "iso:country":"CH",
    "sg:address":"Wil 10",
    "sg:city":"Muotathal",
    "sg:orig_category":"G\u00fcterbef\u00f6rderung im Strassenverkehr",
    "sg:postcode":"6436",
    "sg:province":"Schwyz",
    "wof:name":"Transportgemeinschaft Bezirk Schwyz",
    "wof:placetype":"venue"
},
  "geometry": {"coordinates":[8.7607250214,46.9768829346],"type":"Point"}
}