{
  "type": "Feature",
  "properties": {
    "iso:country":"CH",
    "sg:address":"Froburgstrasse 9",
    "sg:city":"Olten",
    "sg:classifiers":[
        {
            "category":"Restaurant",
            "type":"Food & Drink"
        }
    ],
    "sg:phone":"+41 62 212 20 10",
    "sg:postcode":"4600",
    "sg:province":"Solothurn",
    "sg:tags":[
        "tea-rooms",
        "restaurants"
    ],
    "wof:name":"Cafeteria Cielo Azzurro Iaropoli Caterina",
    "wof:placetype":"venue"
},
  "geometry": {"coordinates":[7.9039731026,47.351978302],"type":"Point"}
}