{
  "type": "Feature",
  "properties": {
    "iso:country":"CH",
    "sg:address":"Schachen 18",
    "sg:city":"Aarau",
    "sg:classifiers":[
        {
            "category":"Restaurant",
            "type":"Food & Drink"
        }
    ],
    "sg:phone":"+41 62 822 13 72",
    "sg:postcode":"5000",
    "sg:province":"Aargau",
    "wof:name":"Brasserie M\u00fcrset",
    "wof:placetype":"venue"
},
  "geometry": {"coordinates":[8.0405483246,47.3912582397],"type":"Point"}
}