{
  "type": "Feature",
  "properties": {
    "iso:country":"CH",
    "sg:address":"5",
    "sg:city":"Gen\u00e8ve",
    "sg:classifiers":[
        {
            "category":"Industrial Area",
            "type":"Public Place"
        }
    ],
    "sg:phone":"+41 71 493 51 11",
    "sg:postcode":"1214",
    "sg:province":"Gen\u00e8ve",
    "sg:tags":[
        "large",
        "private"
    ],
    "wof:name":"Helvetia Patria Group",
    "wof:placetype":"venue"
},
  "geometry": {"coordinates":[9.3772001266,47.4321632385],"type":"Point"}
}