{
  "type": "Feature",
  "properties": {
    "iso:country":"CH",
    "sg:address":"Luzernerstrasse 21",
    "sg:city":"Meggen",
    "sg:orig_category":"Unclassifiable Establishments",
    "sg:postcode":"6045",
    "sg:province":"Luzern",
    "wof:name":"Apimedia Alex Piazza",
    "wof:placetype":"venue"
},
  "geometry": {"coordinates":[8.3687181473,47.0448112488],"type":"Point"}
}