{
  "type": "Feature",
  "properties": {
    "iso:country":"CH",
    "sg:address":"Gerbergasse 13",
    "sg:city":"Basel",
    "sg:orig_category":"Unclassifiable Establishments",
    "sg:postcode":"4001",
    "sg:province":"Basel-Stadt",
    "wof:name":"Symphony Shipping Gmbh",
    "wof:placetype":"venue"
},
  "geometry": {"coordinates":[7.5883450508,47.5571403503],"type":"Point"}
}