{
  "type": "Feature",
  "properties": {
    "iso:country":"CH",
    "sg:address":"Rue Du Clos 9-11 1200 Genf. Postfach",
    "sg:city":"Gen\u00e8ve",
    "sg:orig_category":"Finanzierungsinstitutionen",
    "sg:postcode":"1207",
    "sg:province":"Gen\u00e8ve",
    "wof:name":"Rdp Vorsorge-kompetenz, Dal Pian Robert M.",
    "wof:placetype":"venue"
},
  "geometry": {"coordinates":[8.8533735275,47.1925811768],"type":"Point"}
}