{
  "type": "Feature",
  "properties": {
    "iso:country":"CH",
    "sg:address":"Nelkenstrasse 6",
    "sg:city":"Degersheim",
    "sg:orig_category":"Detailhandel mit Musikinstrumenten Detailhandel mit elektrischen Haushalts-,Radio U Fernsehger\u00e4ten s",
    "sg:phone":"+41 71 371 26 85",
    "sg:postcode":"9113",
    "sg:province":"St. Gallen",
    "wof:name":"Peter & Partner, Musikinstrumente",
    "wof:placetype":"venue"
},
  "geometry": {"coordinates":[9.2033262253,47.3764724731],"type":"Point"}
}