{
  "type": "Feature",
  "properties": {
    "iso:country":"CH",
    "sg:address":"Sonnenhalde 7",
    "sg:city":"Bettwiesen",
    "sg:orig_category":"Fahrr\u00e4der and Zubeh\u00f6r Grosshandel Handel mit Motorr\u00e4dern, Teilen U Zubeh\u00f6r Instandhaltung U Reparatu",
    "sg:phone":"+41 71 911 66 16",
    "sg:postcode":"9553",
    "sg:province":"Thurgau",
    "wof:name":"Agentur Felix Ag",
    "wof:placetype":"venue"
},
  "geometry": {"coordinates":[9.024064064,47.4996948242],"type":"Point"}
}