{
  "type": "Feature",
  "properties": {
    "iso:country":"CH",
    "sg:address":"Konstanzerstrasse 14 Rossr\u00fcti 9552 Bronschhofen. Postfach",
    "sg:city":"Rossr\u00fcti",
    "sg:orig_category":"Herstellung von Werkzeugen",
    "sg:postcode":"9512",
    "sg:province":"St. Gallen",
    "wof:name":"Egli Gebr\u00fcder Maschinen Ag",
    "wof:placetype":"venue"
},
  "geometry": {"coordinates":[9.0359830856,47.4764137268],"type":"Point"}
}