{
  "type": "Feature",
  "properties": {
    "addr:full":"Place De La Gare 5 Morges Vaud 1110",
    "addr:housenumber":"5",
    "addr:postcode":"1110",
    "addr:street":"Place De La Gare",
    "iso:country":"CH",
    "sg:address":"Place De La Gare 5",
    "sg:city":"Morges",
    "sg:orig_category":"Detailhandel mit Blumen U Pflanzen",
    "sg:phone":"+41 21 801 18 54",
    "sg:postcode":"1110",
    "sg:province":"Vaud",
    "wof:name":"B. Cornut Fleuriste De La Gare",
    "wof:placetype":"venue"
},
  "geometry": {"coordinates":[6.494559,46.510574],"type":"Point"}
}