{
  "type": "Feature",
  "properties": {
    "iso:country":"CH",
    "sg:address":"Pulverm\u00fchlestr. 81",
    "sg:city":"Chur",
    "sg:classifiers":[
        {
            "category":"Manufacturing",
            "subcategory":"Glass & Minerals",
            "type":"Manufacturing & Wholesale Goods"
        }
    ],
    "sg:phone":"+41 81 286 96 86",
    "sg:postcode":"7001",
    "sg:province":"Graubunden",
    "sg:tags":[
        "building",
        "material"
    ],
    "wof:name":"Rastal Sahm & Co",
    "wof:placetype":"venue"
},
  "geometry": {"coordinates":[9.508979,46.854008],"type":"Point"}
}