{
  "type": "Feature",
  "properties": {
    "iso:country":"CH",
    "sg:address":"7122",
    "sg:city":"Carrera",
    "sg:orig_category":"HOTELS: OHNE RESTAURANT",
    "sg:phone":"+41 81 854 12 88",
    "sg:postcode":"7122",
    "sg:province":"Graubunden",
    "wof:name":"Pension Chesa",
    "wof:placetype":"venue"
},
  "geometry": {"coordinates":[9.9249753952,46.5796699524],"type":"Point"}
}