{
  "type": "Feature",
  "properties": {
    "iso:country":"CH",
    "sg:address":"Hollenweg 34",
    "sg:city":"Arlesheim",
    "sg:orig_category":"Interessenvertretungen",
    "sg:postcode":"4144",
    "sg:province":"Basel-Landschaft",
    "wof:name":"Kober-schwabe-stiftung",
    "wof:placetype":"venue"
},
  "geometry": {"coordinates":[7.6257810593,47.4880752563],"type":"Point"}
}