{
  "type": "Feature",
  "properties": {
    "iso:country":"CH",
    "sg:address":"Schulhausstrasse 3",
    "sg:city":"Subingen",
    "sg:orig_category":"Detailhandel mit Fleisch U Fleischwaren",
    "sg:phone":"+41 32 614 16 56",
    "sg:postcode":"4553",
    "sg:province":"Solothurn",
    "wof:name":"Kurt Dauwalder Metzgerei",
    "wof:placetype":"venue"
},
  "geometry": {"coordinates":[7.6176290512,47.1964569092],"type":"Point"}
}