{
  "type": "Feature",
  "properties": {
    "iso:country":"CH",
    "sg:address":"Pestalozzistrasse 2a",
    "sg:city":"Thun",
    "sg:orig_category":"Herstellung von Schl\u00f6ssern U Beschl\u00e4gen Mechanik",
    "sg:phone":"+41 55 283 10 67",
    "sg:postcode":"3600",
    "sg:province":"Bern",
    "wof:name":"Bellfer Ag",
    "wof:placetype":"venue"
},
  "geometry": {"coordinates":[9.0167894363,47.1893196106],"type":"Point"}
}