{
  "type": "Feature",
  "properties": {
    "iso:country":"CH",
    "sg:address":"Alte Badenerstr. 20",
    "sg:city":"Neerach",
    "sg:orig_category":"Unternehmensberatung",
    "sg:phone":"+41 71 385 61 95",
    "sg:postcode":"8173",
    "sg:province":"Z\u00fcrich",
    "wof:name":"F\u00fcrer Unternehmensberatung",
    "wof:placetype":"venue"
},
  "geometry": {"coordinates":[9.2514562607,47.4134788513],"type":"Point"}
}