{
  "type": "Feature",
  "properties": {
    "iso:country":"CH",
    "sg:address":"L\u00e4ttenstrasse 16",
    "sg:city":"Schlieren",
    "sg:orig_category":"\u00dcbersetzungsb\u00fcros",
    "sg:phone":"+41 12913005",
    "sg:postcode":"8952",
    "sg:province":"Z\u00fcrich",
    "wof:name":"Vetsch Business Translations",
    "wof:placetype":"venue"
},
  "geometry": {"coordinates":[8.4417600632,47.4030914307],"type":"Point"}
}