{
  "type": "Feature",
  "properties": {
    "iso:country":"CH",
    "sg:address":"Parkstrasse 24",
    "sg:city":"Weggis",
    "sg:orig_category":"Formboards",
    "sg:phone":"+41 41 670 38 31",
    "sg:postcode":"6353",
    "sg:province":"Luzern",
    "wof:name":"Winkler Coffrages Ag",
    "wof:placetype":"venue"
},
  "geometry": {"coordinates":[8.4264717102,47.0325050354],"type":"Point"}
}