{
  "type": "Feature",
  "properties": {
    "iso:country":"CH",
    "sg:address":"Marktplatz",
    "sg:city":"Grenchen",
    "sg:orig_category":"Detailhandel mit Uhren U Schmuck Fachdetailhandel in Verkaufsr\u00e4umen",
    "sg:phone":"+41 32 652 26 68",
    "sg:postcode":"2540",
    "sg:province":"Solothurn",
    "wof:name":"Bijouterie Maegli & Co",
    "wof:placetype":"venue"
},
  "geometry": {"coordinates":[7.3967900276,47.1931343079],"type":"Point"}
}