{
  "type": "Feature",
  "properties": {
    "iso:country":"CH",
    "sg:address":"Hohensaxstrasse 13",
    "sg:city":"Uster",
    "sg:orig_category":"Advokaturb\u00fcros",
    "sg:phone":"+41 19416060",
    "sg:postcode":"8610",
    "sg:province":"Z\u00fcrich",
    "wof:name":"Dr. Martin O. Huber Advokaturb\u00fcro",
    "wof:placetype":"venue"
},
  "geometry": {"coordinates":[8.719676,47.349201],"type":"Point"}
}