{
  "type": "Feature",
  "properties": {
    "iso:country":"CH",
    "sg:address":"Chollerstrasse 25",
    "sg:city":"Zug",
    "sg:orig_category":"Herstellung von Industriegasen",
    "sg:phone":"+41 41 743 03 30",
    "sg:postcode":"6300",
    "sg:province":"Zug",
    "wof:name":"Pangas-center Zug",
    "wof:placetype":"venue"
},
  "geometry": {"coordinates":[8.4885787964,47.1855506897],"type":"Point"}
}