{
  "type": "Feature",
  "properties": {
    "iso:country":"CH",
    "sg:address":"Boniswilerstrasse",
    "sg:city":"Seengen",
    "sg:orig_category":"Kauf U Verkauf von Immobilien auf eigene Rechnung",
    "sg:phone":"+41 71 855 01 11",
    "sg:postcode":"5707",
    "sg:province":"Aargau",
    "wof:name":"Espa Gmbh, Staad",
    "wof:placetype":"venue"
},
  "geometry": {"coordinates":[9.5433320999,47.4836082458],"type":"Point"}
}