{
  "type": "Feature",
  "properties": {
    "iso:country":"CH",
    "sg:address":"4952",
    "sg:city":"Eriswil",
    "sg:orig_category":"Grosshandel mit lebenden Tieren",
    "sg:phone":"+41 55 282 14 48",
    "sg:postcode":"4952",
    "sg:province":"Bern",
    "wof:name":"M\u00fcller Engelbert, Viehhandel",
    "wof:placetype":"venue"
},
  "geometry": {"coordinates":[8.9446897507,47.2491989136],"type":"Point"}
}