{
  "type": "Feature",
  "properties": {
    "iso:country":"CH",
    "sg:address":"Riond-bosson 3 1110 Morges. Postfach",
    "sg:city":"Morges",
    "sg:orig_category":"Grosshandel mit Getr\u00e4nken",
    "sg:phone":"+41 21 811 06 06",
    "sg:postcode":"1110",
    "sg:province":"Vaud",
    "wof:name":"Polyvins Sa",
    "wof:placetype":"venue"
},
  "geometry": {"coordinates":[6.4862098694,46.5052528381],"type":"Point"}
}