{
  "type": "Feature",
  "properties": {
    "addr:full":"Im Brunnen Lax Valais 3994",
    "addr:postcode":"3994",
    "addr:street":"Im Brunnen",
    "iso:country":"CH",
    "sg:address":"Im Brunnen",
    "sg:city":"Lax",
    "sg:orig_category":"Architektur U Ingenieurb\u00fcros Architekturb\u00fcros",
    "sg:phone":"+41 27 973 21 02",
    "sg:postcode":"3994",
    "sg:province":"Valais",
    "wof:name":"Seiler Architektur Gmbh",
    "wof:placetype":"venue"
},
  "geometry": {"coordinates":[8.116642,46.393902],"type":"Point"}
}