{
  "type": "Feature",
  "properties": {
    "iso:country":"CH",
    "sg:address":"Sonnhalde",
    "sg:city":"Ebikon",
    "sg:orig_category":"Unternehmensberatung",
    "sg:phone":"+41 41 440 34 78",
    "sg:postcode":"6030",
    "sg:province":"Luzern",
    "wof:name":"Big Fun Musikfachberatung Kern Michael.",
    "wof:placetype":"venue"
},
  "geometry": {"coordinates":[8.335940361,47.0823898315],"type":"Point"}
}