{
  "type": "Feature",
  "properties": {
    "iso:country":"CH",
    "sg:address":"Poststrasse 37",
    "sg:city":"Biel/bienne",
    "sg:orig_category":"Bahnhofbuffets Restaurants",
    "sg:phone":"+41 32 341 24 80",
    "sg:postcode":"2504",
    "sg:province":"Bern",
    "wof:name":"Restaurant Bahnhof Mett",
    "wof:placetype":"venue"
},
  "geometry": {"coordinates":[7.274409771,47.1472969055],"type":"Point"}
}