{
  "type": "Feature",
  "properties": {
    "iso:country":"CH",
    "sg:address":"Rengglochstrasse 11",
    "sg:city":"Obernau",
    "sg:orig_category":"Autogaragen",
    "sg:phone":"+41 41 320 24 40",
    "sg:postcode":"6012",
    "sg:province":"Luzern",
    "wof:name":"Toni Wicki Pilatus-garage",
    "wof:placetype":"venue"
},
  "geometry": {"coordinates":[8.255031,47.033382],"type":"Point"}
}