{
  "type": "Feature",
  "properties": {
    "iso:country":"CH",
    "sg:address":"Granges-saint-martin 7 1350 Orbe. Postfach",
    "sg:city":"Orbe",
    "sg:orig_category":"Reinigungsgewerbe",
    "sg:postcode":"1350",
    "sg:province":"Vaud",
    "wof:name":"M\u00e9datec S\u00e0rl Entretien Et Maintenance De B\u00e2timents. D\u00e9pannage Des Installations Etc",
    "wof:placetype":"venue"
},
  "geometry": {"coordinates":[6.5347127914,46.7206687927],"type":"Point"}
}