{
  "type": "Feature",
  "properties": {
    "iso:country":"CH",
    "sg:address":"Haselstrasse 16",
    "sg:city":"Baden",
    "sg:classifiers":[
        {
            "category":"Restaurant",
            "type":"Food & Drink"
        }
    ],
    "sg:phone":"+41 56 205 11 11",
    "sg:postcode":"5400",
    "sg:province":"Aargau",
    "wof:name":"Restaurant Arena Restorama Ag Abb Konnex",
    "wof:placetype":"venue"
},
  "geometry": {"coordinates":[8.305656,47.478016],"type":"Point"}
}