{
  "type": "Feature",
  "properties": {
    "addr:full":"Kriesbachstrasse 1 Wallisellen Z\u00fcrich 8304",
    "addr:housenumber":"1",
    "addr:postcode":"8304",
    "addr:street":"Kriesbachstrasse",
    "iso:country":"CH",
    "sg:address":"Kriesbachstrasse 1",
    "sg:city":"Wallisellen",
    "sg:orig_category":"Dienstleistungen, Versorger",
    "sg:phone":"+41 41018301025",
    "sg:postcode":"8304",
    "sg:province":"Z\u00fcrich",
    "wof:name":"K. M\u00fcller Ag",
    "wof:placetype":"venue"
},
  "geometry": {"coordinates":[8.612157,47.410656],"type":"Point"}
}