{
  "type": "Feature",
  "properties": {
    "iso:country":"CH",
    "sg:address":"Rue De Neuch\u00e2tel 16",
    "sg:city":"Yverdon-les-bains",
    "sg:orig_category":"Fachdetailhandel in Verkaufsr\u00e4umen",
    "sg:postcode":"1400",
    "sg:province":"Vaud",
    "wof:name":"Les Halles, Cruchet Val\u00e9rie",
    "wof:placetype":"venue"
},
  "geometry": {"coordinates":[6.6360602379,46.7815818787],"type":"Point"}
}