{
  "type": "Feature",
  "properties": {
    "iso:country":"CH",
    "sg:address":"Schipfe 41",
    "sg:city":"Z\u00fcrich",
    "sg:orig_category":"Innendekorationsateliers",
    "sg:phone":"+41 12117915",
    "sg:postcode":"8001",
    "sg:province":"Z\u00fcrich",
    "wof:name":"Otto Schmid Polster-& Tapezierergesch\u00e4ft",
    "wof:placetype":"venue"
},
  "geometry": {"coordinates":[8.5415716171,47.3733863831],"type":"Point"}
}