{
  "type": "Feature",
  "properties": {
    "iso:country":"CH",
    "sg:address":"Edisriederstrasse 57",
    "sg:city":"Sachseln",
    "sg:orig_category":"Herstellung von sonstigen landwirtschaftlichen Maschinen",
    "sg:phone":"+41 71 654 65 40",
    "sg:postcode":"6072",
    "sg:province":"Obwalden",
    "wof:name":"M\u00e4rla Ag",
    "wof:placetype":"venue"
},
  "geometry": {"coordinates":[9.0563354492,47.5365982056],"type":"Point"}
}