{
  "type": "Feature",
  "properties": {
    "addr:full":"D\u00fcnnistrasse 10 Bergdietikon Aargau 8962",
    "addr:housenumber":"10",
    "addr:postcode":"8962",
    "addr:street":"Duennistrasse",
    "iso:country":"CH",
    "sg:address":"D\u00fcnnistrasse 10",
    "sg:city":"Bergdietikon",
    "sg:orig_category":"Architektur U Ingenieurb\u00fcros",
    "sg:postcode":"8962",
    "sg:province":"Aargau",
    "wof:name":"Narayan Netzconsult Ing.",
    "wof:placetype":"venue"
},
  "geometry": {"coordinates":[8.392024,47.394459],"type":"Point"}
}