{
  "type": "Feature",
  "properties": {
    "iso:country":"CH",
    "sg:address":"Kirchenackerweg 31",
    "sg:city":"Z\u00fcrich",
    "sg:orig_category":"Fotografische Ateliers Radio U Fernsehanstalten",
    "sg:phone":"+41 13125355",
    "sg:postcode":"8050",
    "sg:province":"Z\u00fcrich",
    "wof:name":"Medialink, Gestaltung Und Visuelle Kommunikation, Hans Nick",
    "wof:placetype":"venue"
},
  "geometry": {"coordinates":[8.5534791946,47.4091110229],"type":"Point"}
}