{
  "type": "Feature",
  "properties": {
    "iso:country":"CH",
    "sg:address":"Obere Allmendstrasse 22",
    "sg:city":"Buttisholz",
    "sg:orig_category":"Herstellung von Konstruktionsteilen, Fertigbauteilen U Ausbauelementen aus Holz Herstellung von Verp",
    "sg:phone":"+41 41 928 12 42",
    "sg:postcode":"6018",
    "sg:province":"Luzern",
    "wof:name":"Walter Suppiger K\u00fcferei",
    "wof:placetype":"venue"
},
  "geometry": {"coordinates":[8.0905265808,47.1166229248],"type":"Point"}
}