{
  "type": "Feature",
  "properties": {
    "iso:country":"CH",
    "sg:city":"Eglisau",
    "sg:orig_category":"Finanzen, Investment",
    "sg:postcode":"8193",
    "sg:province":"Z\u00fcrich",
    "wof:name":"Crc Management",
    "wof:placetype":"venue"
},
  "geometry": {"coordinates":[8.521632,47.576324],"type":"Point"}
}