{
  "type": "Feature",
  "properties": {
    "iso:country":"CH",
    "sg:address":"Dorf 124",
    "sg:city":"Waldstatt",
    "sg:orig_category":"Nationale Postdienste",
    "sg:phone":"+41 71 351 22 31",
    "sg:postcode":"9104",
    "sg:province":"Appenzell Ausserrhoden",
    "wof:name":"Die Schweizerische Post",
    "wof:placetype":"venue"
},
  "geometry": {"coordinates":[9.286072731,47.3574905396],"type":"Point"}
}