{
  "type": "Feature",
  "properties": {
    "iso:country":"CH",
    "sg:address":"Zentralstrasse 49 2502 Biel/bienne. Postfach",
    "sg:city":"Biel/bienne",
    "sg:orig_category":"Bau\u00e4mter",
    "sg:phone":"+41 71 224 51 21",
    "sg:postcode":"2501",
    "sg:province":"Bern",
    "wof:name":"St\u00e4dtische Bauverwaltung",
    "wof:placetype":"venue"
},
  "geometry": {"coordinates":[9.376088,47.425499],"type":"Point"}
}