{
  "type": "Feature",
  "properties": {
    "iso:country":"CH",
    "sg:address":"Wittenberg",
    "sg:city":"Golaten",
    "sg:orig_category":"R\u00fcckgewinnung U Vorbereitung f\u00fcr die Wiederverwertung Recycling von nichtmetallischen Altmaterialien",
    "sg:phone":"+41 71 744 00 55",
    "sg:postcode":"3207",
    "sg:province":"Bern",
    "wof:name":"H\u00e4usle & Hofer Gmbh",
    "wof:placetype":"venue"
},
  "geometry": {"coordinates":[9.6374349594,47.4530105591],"type":"Point"}
}