{
  "type": "Feature",
  "properties": {
    "iso:country":"CH",
    "sg:address":"Rue Des Brues 7a",
    "sg:city":"Montagne-sonvilier",
    "sg:orig_category":"Instandhaltung U Reparatur von Automobilen",
    "sg:phone":"+41 32 941 43 03",
    "sg:postcode":"2615",
    "sg:province":"Bern",
    "wof:name":"Touring Fiorucci Sa",
    "wof:placetype":"venue"
},
  "geometry": {"coordinates":[6.9603881836,47.1365089417],"type":"Point"}
}