{
  "type": "Feature",
  "properties": {
    "iso:country":"CH",
    "sg:address":"Busswilstrasse 20",
    "sg:city":"Worben",
    "sg:orig_category":"G\u00fcterbef\u00f6rderung im Strassenverkehr",
    "sg:postcode":"3252",
    "sg:province":"Bern",
    "wof:name":"Tschan-transporte Ag",
    "wof:placetype":"venue"
},
  "geometry": {"coordinates":[7.2950367928,47.0988922119],"type":"Point"}
}