{
  "type": "Feature",
  "properties": {
    "iso:country":"CH",
    "sg:address":"Kramgasse 66",
    "sg:city":"Bern 7",
    "sg:orig_category":"Dienstleistungen, K\u00f6rper U Pflege",
    "sg:postcode":"3000",
    "sg:province":"Bern",
    "wof:name":"Hausbetreuungsdienst F\u00fcr Stadt Und Land Ag",
    "wof:placetype":"venue"
},
  "geometry": {"coordinates":[7.449285,46.948124],"type":"Point"}
}