{
  "type": "Feature",
  "properties": {
    "iso:country":"CH",
    "sg:address":"Hakabstrasse 2",
    "sg:city":"N\u00fcrensdorf",
    "sg:orig_category":"Technische, physikalische U chemische Untersuchung",
    "sg:phone":"+41 18370404",
    "sg:postcode":"8309",
    "sg:province":"Z\u00fcrich",
    "wof:name":"Vril Gmbh",
    "wof:placetype":"venue"
},
  "geometry": {"coordinates":[8.6512928009,47.450252533],"type":"Point"}
}