{
  "type": "Feature",
  "properties": {
    "iso:country":"CH",
    "sg:address":"Impasse Des Eglantines 1",
    "sg:city":"Fribourg",
    "sg:orig_category":"Grosshandel mit Maschinen U Ausr\u00fcstungen Wirtschaftspr\u00fcfung, Steuerberatung U Treuhand",
    "sg:phone":"+41 26 484 85 86",
    "sg:postcode":"1700",
    "sg:province":"Fribourg",
    "wof:name":"Jenag Sa",
    "wof:placetype":"venue"
},
  "geometry": {"coordinates":[7.1723389626,46.8086280823],"type":"Point"}
}