{
  "type": "Feature",
  "properties": {
    "iso:country":"CH",
    "sg:address":"3473",
    "sg:city":"Alchenstorf",
    "sg:orig_category":"Gemeindeverwaltungen",
    "sg:phone":"+41 61 486 25 25",
    "sg:postcode":"3473",
    "sg:province":"Bern",
    "wof:name":"Gemeindeverwaltung Allschwil",
    "wof:placetype":"venue"
},
  "geometry": {"coordinates":[7.5448598862,47.552646637],"type":"Point"}
}