{
  "type": "Feature",
  "properties": {
    "iso:country":"CH",
    "sg:address":"Obere Bahnhofstrasse 12c",
    "sg:city":"Spiez",
    "sg:orig_category":"Sonstige mit der Informatik verbundene T\u00e4tigkeiten",
    "sg:phone":"+41 79 404 00 80",
    "sg:postcode":"3700",
    "sg:province":"Bern",
    "wof:name":"Edv-perform Consulting Z\u00fcrcher Ren\u00e9",
    "wof:placetype":"venue"
},
  "geometry": {"coordinates":[9.0360298157,47.4124488831],"type":"Point"}
}