{
  "type": "Feature",
  "properties": {
    "iso:country":"CH",
    "sg:address":"Schaffhauserstrasse 345",
    "sg:city":"Z\u00fcrich",
    "sg:classifiers":[
        {
            "category":"Restaurant",
            "type":"Food & Drink"
        }
    ],
    "sg:phone":"+41 13124858",
    "sg:postcode":"8050",
    "sg:province":"Z\u00fcrich",
    "wof:name":"Pizzeria Santa Lucia",
    "wof:placetype":"venue"
},
  "geometry": {"coordinates":[8.5462770462,47.4091835022],"type":"Point"}
}