{
  "type": "Feature",
  "properties": {
    "iso:country":"CH",
    "sg:address":"Etzelstrasse 12a",
    "sg:city":"St\u00e4fa",
    "sg:orig_category":"Herstellung von sonstigen elektrischen Ausr\u00fcstungen",
    "sg:phone":"+41 19267253",
    "sg:postcode":"8712",
    "sg:province":"Z\u00fcrich",
    "wof:name":"Elevisor Ag",
    "wof:placetype":"venue"
},
  "geometry": {"coordinates":[8.7264165878,47.2440643311],"type":"Point"}
}