{
  "type": "Feature",
  "properties": {
    "iso:country":"CH",
    "sg:address":"1587",
    "sg:city":"Montmagny",
    "sg:orig_category":"Schulpflegen",
    "sg:phone":"+41 26 660 26 30",
    "sg:postcode":"1587",
    "sg:province":"Vaud",
    "wof:name":"Commission Scolaire De L'ecole Primaire",
    "wof:placetype":"venue"
},
  "geometry": {"coordinates":[7.0109500885,46.9260215759],"type":"Point"}
}