{
  "type": "Feature",
  "properties": {
    "iso:country":"CH",
    "sg:address":"Bohnackerstrasse 1-3",
    "sg:city":"Dielsdorf",
    "sg:orig_category":"Saunas, Solarien, Fitnesszentren U \u00e4hnliches",
    "sg:postcode":"8157",
    "sg:province":"Z\u00fcrich",
    "wof:name":"H\u00d6ller Michael, Health Management",
    "wof:placetype":"venue"
},
  "geometry": {"coordinates":[8.2712049484,47.4972648621],"type":"Point"}
}