{
  "type": "Feature",
  "properties": {
    "iso:country":"CH",
    "sg:address":"Au Village 24",
    "sg:city":"Montagny-la-ville",
    "sg:orig_category":"Unclassifiable Establishments",
    "sg:postcode":"1776",
    "sg:province":"Fribourg",
    "wof:name":"Bouvard & Cie, Jacques Bouvard Successeur",
    "wof:placetype":"venue"
},
  "geometry": {"coordinates":[6.1393971443,46.1857948303],"type":"Point"}
}