{
  "type": "Feature",
  "properties": {
    "iso:country":"CH",
    "sg:address":"Juchweg 19",
    "sg:city":"Moosleerau",
    "sg:orig_category":"Grosshandel mit Werkzeugmaschinen",
    "sg:phone":"+41 79 444 95 40",
    "sg:postcode":"5054",
    "sg:province":"Aargau",
    "wof:name":"Heinz Moser Ag Spezialmaschinen",
    "wof:placetype":"venue"
},
  "geometry": {"coordinates":[8.0625400543,47.2676353455],"type":"Point"}
}