{
  "type": "Feature",
  "properties": {
    "iso:country":"CH",
    "sg:address":"Hirschengraben 8",
    "sg:city":"Ranzo",
    "sg:orig_category":"Wohnheime",
    "sg:postcode":"6577",
    "sg:province":"Ticino",
    "wof:name":"Fondazione Bick Eduard",
    "wof:placetype":"venue"
},
  "geometry": {"coordinates":[8.7731876373,46.110408783],"type":"Point"}
}