{
  "type": "Feature",
  "properties": {
    "iso:country":"CH",
    "sg:address":"Route De Lannaz",
    "sg:city":"Evol\u00e8ne",
    "sg:orig_category":"Arztpraxen",
    "sg:phone":"+41 27 283 18 01",
    "sg:postcode":"1983",
    "sg:province":"Valais",
    "wof:name":"Dr M\u00e9d. Maurice Sermet M\u00e9decin G\u00e9n\u00e9raliste Fmh",
    "wof:placetype":"venue"
},
  "geometry": {"coordinates":[7.495541,46.111458],"type":"Point"}
}