{
  "type": "Feature",
  "properties": {
    "iso:country":"CH",
    "sg:address":"Niesenstrasse 14a",
    "sg:city":"Meinisberg",
    "sg:orig_category":"Unclassifiable Establishments",
    "sg:postcode":"2554",
    "sg:province":"Bern",
    "wof:name":"Oliver Baumann Spirits Of Nature",
    "wof:placetype":"venue"
},
  "geometry": {"coordinates":[7.3443078995,47.1567344666],"type":"Point"}
}