{
  "type": "Feature",
  "properties": {
    "iso:country":"CH",
    "sg:address":"Cully/treytorrens",
    "sg:city":"Puidoux-gare",
    "sg:orig_category":"Dauerkulturbau",
    "sg:postcode":"1070",
    "sg:province":"Vaud",
    "wof:name":"Ma\u00eetre Jean Sa",
    "wof:placetype":"venue"
},
  "geometry": {"coordinates":[6.7684,46.494549],"type":"Point"}
}