{
  "type": "Feature",
  "properties": {
    "iso:country":"CH",
    "sg:address":"Limmatstr. 210",
    "sg:city":"Z\u00fcrich",
    "sg:orig_category":"Industrial vehicles Precision Equipment Timekeeping equipement Vehicles and Transport Equipment",
    "sg:phone":"+41 32 911 91 91",
    "sg:postcode":"8031",
    "sg:province":"Z\u00fcrich",
    "wof:name":"Universo Sa",
    "wof:placetype":"venue"
},
  "geometry": {"coordinates":[6.8222551346,47.0944976807],"type":"Point"}
}