{
  "type": "Feature",
  "properties": {
    "iso:country":"CH",
    "sg:address":"Hofwiesenstrasse 27",
    "sg:city":"Gattikon",
    "sg:orig_category":"Vorschulen, Kinderg\u00e4rten",
    "sg:phone":"+41 17201527",
    "sg:postcode":"8136",
    "sg:province":"Z\u00fcrich",
    "wof:name":"Kindergarten Hof",
    "wof:placetype":"venue"
},
  "geometry": {"coordinates":[8.546918869,47.2869224548],"type":"Point"}
}