{
  "type": "Feature",
  "properties": {
    "iso:country":"CH",
    "sg:address":"Schulstrasse 1",
    "sg:city":"Flums",
    "sg:orig_category":"Primarschulen",
    "sg:phone":"+41 81 733 23 63",
    "sg:postcode":"8890",
    "sg:province":"St. Gallen",
    "wof:name":"Primarschulgem.flums-dorf- Hochwiesen Altes Schulh.dorf",
    "wof:placetype":"venue"
},
  "geometry": {"coordinates":[9.3443508148,47.0921440125],"type":"Point"}
}