{
  "type": "Feature",
  "properties": {
    "iso:country":"CH",
    "sg:address":"Rebweg 1",
    "sg:city":"H\u00fcttikon",
    "sg:classifiers":[
        {
            "category":"Banks & Credit Unions",
            "subcategory":"Bureau De Change",
            "type":"Services"
        }
    ],
    "sg:phone":"+41 18443240",
    "sg:postcode":"8115",
    "sg:province":"Z\u00fcrich",
    "sg:tags":[
        "postage",
        "stamp",
        "trade"
    ],
    "wof:name":"Heinrich Ankersmit",
    "wof:placetype":"venue"
},
  "geometry": {"coordinates":[8.3886899948,47.444519043],"type":"Point"}
}