{
  "type": "Feature",
  "properties": {
    "iso:country":"CH",
    "sg:address":"Rebbergstrasse 28",
    "sg:city":"Untersiggenthal",
    "sg:orig_category":"Bastel- and Hobbyartikel Detailhandel",
    "sg:phone":"+41 56 290 33 34",
    "sg:postcode":"5417",
    "sg:province":"Aargau",
    "wof:name":"Manfred Schenk Eagleshop",
    "wof:placetype":"venue"
},
  "geometry": {"coordinates":[8.249182,47.504387],"type":"Point"}
}