{
  "type": "Feature",
  "properties": {
    "iso:country":"CH",
    "sg:address":"Bahnhofstrasse 57",
    "sg:city":"Burgdorf",
    "sg:orig_category":"Grosshandel mit Nahrungsmitteln, Getr\u00e4nken U Tabakwaren ohne ausgepr\u00e4gten Schwerpunkt",
    "sg:phone":"+41 34 420 34 34",
    "sg:postcode":"3400",
    "sg:province":"Bern",
    "wof:name":"Allfood Ag",
    "wof:placetype":"venue"
},
  "geometry": {"coordinates":[7.621732235,47.0602302551],"type":"Point"}
}