{
  "type": "Feature",
  "properties": {
    "iso:country":"CH",
    "sg:address":"Bettnaustrasse 17",
    "sg:city":"Siebnen",
    "sg:orig_category":"Detailhandel mit Fahrr\u00e4dern Handel mit Motorr\u00e4dern, Teilen U Zubeh\u00f6r Instandhaltung U Reparatur von ",
    "sg:phone":"+41 55 440 20 60",
    "sg:postcode":"8854",
    "sg:province":"Schwyz",
    "wof:name":"Ernst Pfister Velos-motos",
    "wof:placetype":"venue"
},
  "geometry": {"coordinates":[8.9108295441,47.1737709045],"type":"Point"}
}