{
  "type": "Feature",
  "properties": {
    "iso:country":"CH",
    "sg:address":"Unterstadt 28",
    "sg:city":"Schaffhausen",
    "sg:orig_category":"Drogerien Sonstiger Fachdetailhandel mit Nahrungsmitteln, Getr\u00e4nken U Tabak in Verkaufsr\u00e4umen",
    "sg:phone":"+41 52 624 50 30",
    "sg:postcode":"8200",
    "sg:province":"Schaffhausen",
    "wof:name":"Chr\u00fcter-drogerie Egger",
    "wof:placetype":"venue"
},
  "geometry": {"coordinates":[8.6393985748,47.695854187],"type":"Point"}
}