{
  "type": "Feature",
  "properties": {
    "iso:country":"CH",
    "sg:address":"Fronhofenstrasse 13",
    "sg:city":"Stans",
    "sg:orig_category":"Kaminfeger",
    "sg:phone":"+41 56 664 30 11",
    "sg:postcode":"6370",
    "sg:province":"Nidwalden",
    "wof:name":"Alois H\u00fcsler Kaminfegergesch\u00e4ft",
    "wof:placetype":"venue"
},
  "geometry": {"coordinates":[8.3174819946,47.2825775146],"type":"Point"}
}