{
  "type": "Feature",
  "properties": {
    "iso:country":"CH",
    "sg:address":"Postmatte 2",
    "sg:city":"Freienbach",
    "sg:orig_category":"Unternehmensberatung",
    "sg:postcode":"8807",
    "sg:province":"Schwyz",
    "wof:name":"Bms Board & Management Support Kn\u00fcsel Niklaus",
    "wof:placetype":"venue"
},
  "geometry": {"coordinates":[8.7585916519,47.2063484192],"type":"Point"}
}