{
  "type": "Feature",
  "properties": {
    "iso:country":"CH",
    "sg:address":"Route De Lugnez 26b",
    "sg:city":"Montignez",
    "sg:orig_category":"Bauschreinerei Zimmerei, Dachdeckerei, Bauspenglerei U Abdichtung",
    "sg:phone":"+41 32 475 57 73",
    "sg:postcode":"2924",
    "sg:province":"Jura",
    "wof:name":"Raymond & Daniel Terrier Sa Menuiserie & Charpente",
    "wof:placetype":"venue"
},
  "geometry": {"coordinates":[7.062298,47.487106],"type":"Point"}
}