{
  "type": "Feature",
  "properties": {
    "iso:country":"CH",
    "sg:address":"S\u00e4ndli 8783 Linthal. Postfach 67",
    "sg:city":"Linthal",
    "sg:orig_category":"Allgemeiner Hoch U Tiefbau Allgemeiner Hochbau",
    "sg:phone":"+41 55 643 13 77",
    "sg:postcode":"8783",
    "sg:province":"Glarus",
    "wof:name":"Marti Balz Ag, Baugesch\u00e4ft",
    "wof:placetype":"venue"
},
  "geometry": {"coordinates":[8.99973,46.923344],"type":"Point"}
}