{
  "type": "Feature",
  "properties": {
    "iso:country":"CH",
    "sg:address":"Bahnhofstrasse 14",
    "sg:city":"Aadorf",
    "sg:orig_category":"Elektroinstallation",
    "sg:phone":"+41 52 365 22 88",
    "sg:postcode":"8355",
    "sg:province":"Thurgau",
    "wof:name":"Schenk Elektrotechnische Unternehmung Ag",
    "wof:placetype":"venue"
},
  "geometry": {"coordinates":[8.9019708633,47.4888877869],"type":"Point"}
}