{
  "type": "Feature",
  "properties": {
    "iso:country":"CH",
    "sg:address":"Via Gratello 12",
    "sg:city":"Losone",
    "sg:orig_category":"Maler U Glasergewerbe Malerei",
    "sg:phone":"+41 79 351 26 57",
    "sg:postcode":"6616",
    "sg:province":"Ticino",
    "wof:name":"Vincenzo Mora Impresa Di Pittura",
    "wof:placetype":"venue"
},
  "geometry": {"coordinates":[8.7580280304,46.1713562012],"type":"Point"}
}