{
  "type": "Feature",
  "properties": {
    "addr:full":"Stauffacherstrasse 106 8004 Z\u00fcrich. Postfach Z\u00fcrich Z\u00fcrich 8026",
    "addr:housenumber":"106",
    "addr:postcode":"8004 zuerich. postfach;8026",
    "addr:street":"Stauffacherstrasse",
    "iso:country":"CH",
    "sg:address":"Stauffacherstrasse 106 8004 Z\u00fcrich. Postfach",
    "sg:city":"Z\u00fcrich",
    "sg:orig_category":"Architekturb\u00fcros",
    "sg:phone":"+41 12427188",
    "sg:postcode":"8026",
    "sg:province":"Z\u00fcrich",
    "wof:name":"Kellenberger Architekten Architekturb\u00fcro.",
    "wof:placetype":"venue"
},
  "geometry": {"coordinates":[8.525032,47.376816],"type":"Point"}
}