{
  "type": "Feature",
  "properties": {
    "iso:country":"CH",
    "sg:address":"3952",
    "sg:city":"Susten",
    "sg:orig_category":"Polizei",
    "sg:phone":"+41 27 473 12 18",
    "sg:postcode":"3952",
    "sg:province":"Valais",
    "wof:name":"Kantonale Polizei",
    "wof:placetype":"venue"
},
  "geometry": {"coordinates":[7.6420202255,46.3115081787],"type":"Point"}
}