{
  "type": "Feature",
  "properties": {
    "iso:country":"CH",
    "sg:address":"Hauptstrasse 20",
    "sg:city":"Lippoldswilen",
    "sg:orig_category":"Handel mit Automobilen",
    "sg:phone":"+41 71 695 31 15",
    "sg:postcode":"8566",
    "sg:province":"Thurgau",
    "wof:name":"Sommer Management",
    "wof:placetype":"venue"
},
  "geometry": {"coordinates":[9.1345405579,47.6218528748],"type":"Point"}
}