{
  "type": "Feature",
  "properties": {
    "iso:country":"CH",
    "sg:address":"Herrengasse 46",
    "sg:city":"Oltingen",
    "sg:orig_category":"Unclassifiable Establishments",
    "sg:postcode":"4494",
    "sg:province":"Basel-Landschaft",
    "wof:name":"Peter M\u00fcller Elektrobauleitung Gmbh",
    "wof:placetype":"venue"
},
  "geometry": {"coordinates":[8.6842269897,47.2698020935],"type":"Point"}
}