{
  "type": "Feature",
  "properties": {
    "iso:country":"CH",
    "sg:address":"Gotthardstrasse 217",
    "sg:city":"Silenen",
    "sg:orig_category":"Gemeindeverwaltungen",
    "sg:phone":"+41 79 610 39 00",
    "sg:postcode":"6473",
    "sg:province":"Uri",
    "wof:name":"Gemeindeverwaltung Sils Im Domleschg",
    "wof:placetype":"venue"
},
  "geometry": {"coordinates":[9.4555253983,46.7018165588],"type":"Point"}
}