{
  "type": "Feature",
  "properties": {
    "iso:country":"CH",
    "sg:address":"Pierre Rue Saint- 18",
    "sg:city":"Fribourg",
    "sg:orig_category":"Reiseb\u00fcros U Reiseveranstalter",
    "sg:phone":"+41 79 379 81 08",
    "sg:postcode":"1700",
    "sg:province":"Fribourg",
    "wof:name":"Asia Cyber Travel Sa Planification, Organisation, Vente Et Courtage De Produits Etc. Dans Le Dom. Touristique, Principalement En Asie",
    "wof:placetype":"venue"
},
  "geometry": {"coordinates":[7.1558661461,46.8040313721],"type":"Point"}
}