{
  "type": "Feature",
  "properties": {
    "iso:country":"CH",
    "sg:address":"Tittwiesenstrasse 11 7000 Chur. Postfach",
    "sg:city":"Lenzerheide/lai",
    "sg:orig_category":"Rechtsberatung",
    "sg:postcode":"7078",
    "sg:province":"Graubunden",
    "wof:name":"Medina Ag",
    "wof:placetype":"venue"
},
  "geometry": {"coordinates":[9.5262269974,46.8597946167],"type":"Point"}
}