{
  "type": "Feature",
  "properties": {
    "iso:country":"CH",
    "sg:address":"Archstrasse 1",
    "sg:city":"Thalwil",
    "sg:orig_category":"Betrieb von Taxis",
    "sg:phone":"+41 19100441",
    "sg:postcode":"8800",
    "sg:province":"Z\u00fcrich",
    "wof:name":"Gh - Service Taxi Hermann Gerald Taxi Und Kurierdienst",
    "wof:placetype":"venue"
},
  "geometry": {"coordinates":[8.583126,47.326599],"type":"Point"}
}