{
  "type": "Feature",
  "properties": {
    "iso:country":"CH",
    "sg:address":"Hauptstrasse 22",
    "sg:city":"Tobel",
    "sg:orig_category":"Gemeindeverwaltungen",
    "sg:phone":"+41 71 917 14 91",
    "sg:postcode":"9555",
    "sg:province":"Thurgau",
    "wof:name":"Gemeindeverwaltung Tobel",
    "wof:placetype":"venue"
},
  "geometry": {"coordinates":[9.0325546265,47.5166778564],"type":"Point"}
}