{
  "type": "Feature",
  "properties": {
    "iso:country":"CH",
    "sg:address":"Scalettastrasse 19",
    "sg:city":"Chur",
    "sg:orig_category":"Fussreflexzonenmassage Kinesiologie",
    "sg:postcode":"7000",
    "sg:province":"Graubunden",
    "wof:name":"Marianna Flepp Kinesiologie & Massagen",
    "wof:placetype":"venue"
},
  "geometry": {"coordinates":[9.5259170532,46.8548431396],"type":"Point"}
}