{
  "type": "Feature",
  "properties": {
    "addr:full":"Dorfpl. Unterb\u00e4ch Valais 3944",
    "addr:postcode":"3944",
    "iso:country":"CH",
    "sg:address":"Dorfpl.",
    "sg:city":"Unterb\u00e4ch",
    "sg:classifiers":[
        {
            "category":"Banks & Credit Unions",
            "subcategory":"Bank",
            "type":"Services"
        }
    ],
    "sg:phone":"+41 27 934 17 84",
    "sg:postcode":"3944",
    "sg:province":"Valais",
    "wof:name":"Walliser Kantonalbank",
    "wof:placetype":"venue"
},
  "geometry": {"coordinates":[7.800761,46.28455],"type":"Point"}
}