{
  "type": "Feature",
  "properties": {
    "iso:country":"CH",
    "sg:address":"St. Alban-anlage 26 4052 Basel. Postfach 3855",
    "sg:city":"Basel",
    "sg:orig_category":"Unternehmensberatung",
    "sg:phone":"+41 32 843 03 55",
    "sg:postcode":"4052",
    "sg:province":"Basel-Stadt",
    "wof:name":"Servision Sa",
    "wof:placetype":"venue"
},
  "geometry": {"coordinates":[6.8612399101,46.98828125],"type":"Point"}
}