{
  "type": "Feature",
  "properties": {
    "iso:country":"CH",
    "sg:address":"Ifangstrasse 5 9602 Bazenheid. Postfach",
    "sg:city":"Bazenheid",
    "sg:orig_category":"Verwaltung der Strafvollzuganstalten Wohnheime",
    "sg:phone":"+41 17621402",
    "sg:postcode":"9602",
    "sg:province":"St. Gallen",
    "wof:name":"Bezirksgef\u00e4ngnis",
    "wof:placetype":"venue"
},
  "geometry": {"coordinates":[8.4483203888,47.2746734619],"type":"Point"}
}