{
  "type": "Feature",
  "properties": {
    "iso:country":"CH",
    "sg:address":"Obergiessenstrasse 35",
    "sg:city":"Diepoldsau",
    "sg:orig_category":"Architektur U Ingenieurb\u00fcros",
    "sg:phone":"+41 22 796 91 25",
    "sg:postcode":"9444",
    "sg:province":"St. Gallen",
    "wof:name":"Georges Buricod Bureau D'ing\u00e9nieur",
    "wof:placetype":"venue"
},
  "geometry": {"coordinates":[6.106382,46.220554],"type":"Point"}
}