{
  "type": "Feature",
  "properties": {
    "iso:country":"CH",
    "sg:address":"Peney-dessus Route 1242 Satigny. Postfach",
    "sg:city":"Satigny",
    "sg:orig_category":"Unclassifiable Establishments",
    "sg:postcode":"1242",
    "sg:province":"Gen\u00e8ve",
    "wof:name":"Russo C\u00e9dric Transports Dans Le Domaine Des Travaux Publics",
    "wof:placetype":"venue"
},
  "geometry": {"coordinates":[6.036345005,46.2024612427],"type":"Point"}
}