{
  "type": "Feature",
  "properties": {
    "iso:country":"CH",
    "sg:address":"Grosshaslistrasse 6",
    "sg:city":"Kriens",
    "sg:orig_category":"Vereine Damen Vereine Gesang",
    "sg:postcode":"6010",
    "sg:province":"Luzern",
    "wof:name":"Gemischter Chor Kriens",
    "wof:placetype":"venue"
},
  "geometry": {"coordinates":[8.2769794464,47.0287666321],"type":"Point"}
}