{
  "type": "Feature",
  "properties": {
    "iso:country":"CH",
    "sg:address":"Hettlingerstrasse 5",
    "sg:city":"Seuzach",
    "sg:orig_category":"Instandhaltung U Reparatur von Automobilen",
    "sg:phone":"+41 52 335 41 44",
    "sg:postcode":"8472",
    "sg:province":"Z\u00fcrich",
    "wof:name":"Ferrante Luigi, Autoreparaturen",
    "wof:placetype":"venue"
},
  "geometry": {"coordinates":[8.7285871506,47.537651062],"type":"Point"}
}