{
  "type": "Feature",
  "properties": {
    "iso:country":"CH",
    "sg:address":"Bahnhofstrasse 13",
    "sg:city":"Widnau",
    "sg:classifiers":[
        {
            "category":"Professional",
            "subcategory":"Employment Agencies",
            "type":"Services"
        }
    ],
    "sg:phone":"+41 71 722 62 62",
    "sg:postcode":"9443",
    "sg:province":"St. Gallen",
    "sg:tags":[
        "personal",
        "u",
        "stellenvermittlung"
    ],
    "wof:name":"Acurra Gmbh Personalvermittlung",
    "wof:placetype":"venue"
},
  "geometry": {"coordinates":[9.6323852539,47.4069366455],"type":"Point"}
}