{
  "type": "Feature",
  "properties": {
    "iso:country":"CH",
    "sg:address":"Kl\u00fcnenfeldstrasse 20",
    "sg:city":"Muttenz",
    "sg:orig_category":"Non-Classified Establishments",
    "sg:postcode":"4132",
    "sg:province":"Basel-Landschaft",
    "wof:name":"Flux Holding Ag",
    "wof:placetype":"venue"
},
  "geometry": {"coordinates":[7.630382061,47.543674469],"type":"Point"}
}