{
  "type": "Feature",
  "properties": {
    "iso:country":"CH",
    "sg:address":"3780",
    "sg:city":"Gstaad",
    "sg:orig_category":"Campingpl\u00e4tze",
    "sg:phone":"+41 33 744 63 30",
    "sg:postcode":"3780",
    "sg:province":"Bern",
    "wof:name":"Camping Bellerive Caravan Waibel Ag",
    "wof:placetype":"venue"
},
  "geometry": {"coordinates":[7.28395,46.476238],"type":"Point"}
}