{
  "type": "Feature",
  "properties": {
    "iso:country":"CH",
    "sg:address":"Place Du March\u00e9 32",
    "sg:city":"Bex",
    "sg:orig_category":"Erbringung von Dienstleistungen f\u00fcr Unternehmen",
    "sg:phone":"+41 24 463 26 46",
    "sg:postcode":"1880",
    "sg:province":"Vaud",
    "wof:name":"Arcad\u00e9co Giorgianni Giuseppe",
    "wof:placetype":"venue"
},
  "geometry": {"coordinates":[7.0142478943,46.2509803772],"type":"Point"}
}