{
  "type": "Feature",
  "properties": {
    "iso:country":"CH",
    "sg:address":"Rue De Vigneule 16",
    "sg:city":"Montagne-moutier",
    "sg:orig_category":"Unternehmensberatung",
    "sg:phone":"+41 55 416 54 00",
    "sg:postcode":"2740",
    "sg:province":"Bern",
    "wof:name":"Cemroc Management Ag",
    "wof:placetype":"venue"
},
  "geometry": {"coordinates":[8.7755222321,47.2052307129],"type":"Point"}
}