{
  "type": "Feature",
  "properties": {
    "iso:country":"CH",
    "sg:address":"Industriestrasse 59",
    "sg:city":"Glattbrugg",
    "sg:orig_category":"Body Fat Analysing Scales",
    "sg:phone":"+41 18286260",
    "sg:postcode":"8152",
    "sg:province":"Z\u00fcrich",
    "wof:name":"Arnold Bott Ag",
    "wof:placetype":"venue"
},
  "geometry": {"coordinates":[8.55692,47.430481],"type":"Point"}
}