{
  "type": "Feature",
  "properties": {
    "iso:country":"CH",
    "sg:address":"Quellenweg 2",
    "sg:city":"M\u00f6rigen",
    "sg:orig_category":"Vereine Gesang",
    "sg:phone":"+41 31 839 64 00",
    "sg:postcode":"2572",
    "sg:province":"Bern",
    "wof:name":"M\u00e4nnerch.r\u00fcfenacht-allmend.",
    "wof:placetype":"venue"
},
  "geometry": {"coordinates":[7.5442538261,46.927406311],"type":"Point"}
}