{
  "type": "Feature",
  "properties": {
    "addr:full":"Neherstieg 41 Schaffhausen Schaffhausen 8200",
    "addr:housenumber":"41",
    "addr:postcode":"8200",
    "addr:street":"Neherstieg",
    "iso:country":"CH",
    "sg:address":"Neherstieg 41",
    "sg:city":"Schaffhausen",
    "sg:orig_category":"Detailhandel mit Damenbekleidung",
    "sg:phone":"+41 32 841 21 93",
    "sg:postcode":"8200",
    "sg:province":"Schaffhausen",
    "wof:name":"Evemode",
    "wof:placetype":"venue"
},
  "geometry": {"coordinates":[6.858539,46.966022],"type":"Point"}
}