{
  "type": "Feature",
  "properties": {
    "iso:country":"CH",
    "sg:address":"Pfaffenwiesenstrasse 31",
    "sg:city":"Stadel(winterthur)",
    "sg:orig_category":"Wirtschaftspr\u00fcfung, Steuerberatung U Treuhand",
    "sg:phone":"+41 52 246 12 30",
    "sg:postcode":"8404",
    "sg:province":"Z\u00fcrich",
    "wof:name":"Apk Treuhand Ag",
    "wof:placetype":"venue"
},
  "geometry": {"coordinates":[8.75822258,47.5065689087],"type":"Point"}
}