{
  "type": "Feature",
  "properties": {
    "iso:country":"CH",
    "sg:address":"Industriestr. 81",
    "sg:city":"Inwil",
    "sg:classifiers":[
        {
            "category":"Home & Garden",
            "subcategory":"Furniture",
            "type":"Retail Goods"
        }
    ],
    "sg:phone":"+41 56 267 01 01",
    "sg:postcode":"6034",
    "sg:province":"Luzern",
    "sg:tags":[
        "household",
        "wood"
    ],
    "wof:name":"Ever-plast Ag",
    "wof:placetype":"venue"
},
  "geometry": {"coordinates":[8.3629980087,47.5679893494],"type":"Point"}
}