{
  "type": "Feature",
  "properties": {
    "iso:country":"CH",
    "sg:address":"Eugen Huber-strasse 164",
    "sg:city":"Z\u00fcrich",
    "sg:orig_category":"Maler U Glasergewerbe",
    "sg:postcode":"8048",
    "sg:province":"Z\u00fcrich",
    "wof:name":"Pfister Beat, Maler Und Tapezierergesch\u00e4ft",
    "wof:placetype":"venue"
},
  "geometry": {"coordinates":[8.471862793,47.3890533447],"type":"Point"}
}