{
  "type": "Feature",
  "properties": {
    "iso:country":"CH",
    "sg:address":"Fraubrunnenstrasse 3",
    "sg:city":"Aefligen",
    "sg:orig_category":"Softwareentwicklung U beratung Webdesign",
    "sg:phone":"+41 31 971 55 73",
    "sg:postcode":"3426",
    "sg:province":"Bern",
    "wof:name":"Alisys Engineering Ag",
    "wof:placetype":"venue"
},
  "geometry": {"coordinates":[7.5565581322,47.0938339233],"type":"Point"}
}