{
  "type": "Feature",
  "properties": {
    "iso:country":"CH",
    "sg:address":"Rue Du Chne-berchtold 43",
    "sg:city":"Sion",
    "sg:orig_category":"RESTAURANTS: TEA-ROOMS",
    "sg:postcode":"1950",
    "sg:province":"Valais",
    "wof:name":"Gaspoz Bernard",
    "wof:placetype":"venue"
},
  "geometry": {"coordinates":[7.3653459549,46.2321510315],"type":"Point"}
}