{
  "type": "Feature",
  "properties": {
    "iso:country":"CH",
    "sg:address":"Hinterbergstrasse 55 6312 Steinhausen. Postfach",
    "sg:city":"Steinhausen",
    "sg:orig_category":"Werbegrafikateliers",
    "sg:phone":"+41 41 741 79 64",
    "sg:postcode":"6312",
    "sg:province":"Zug",
    "wof:name":"Armin Siegrist Grafik",
    "wof:placetype":"venue"
},
  "geometry": {"coordinates":[8.4758405685,47.1937065125],"type":"Point"}
}