{
  "type": "Feature",
  "properties": {
    "iso:country":"CH",
    "sg:address":"Rte De La Petite-corniche 5",
    "sg:city":"Cully",
    "sg:orig_category":"RESTAURANTS: TEA-ROOMS",
    "sg:postcode":"1096",
    "sg:province":"Vaud",
    "wof:name":"Velen Denis",
    "wof:placetype":"venue"
},
  "geometry": {"coordinates":[6.7303199768,46.4881858826],"type":"Point"}
}