{
  "type": "Feature",
  "properties": {
    "iso:country":"CH",
    "sg:address":"Buchsistrasse 28",
    "sg:city":"Th\u00f6rigen",
    "sg:orig_category":"Instandhaltung U Reparatur von Automobilen",
    "sg:postcode":"3367",
    "sg:province":"Bern",
    "wof:name":"Carrosserie Sedak Carrosseriearbeiten An Fahrzeugen U. Autos",
    "wof:placetype":"venue"
},
  "geometry": {"coordinates":[8.8035001755,47.3288803101],"type":"Point"}
}