{
  "type": "Feature",
  "properties": {
    "iso:country":"CH",
    "sg:address":"Urdorferstrasse 11",
    "sg:city":"Dietikon",
    "sg:orig_category":"Interessenvertretungen",
    "sg:postcode":"8953",
    "sg:province":"Z\u00fcrich",
    "wof:name":"Jugendschiessen Limmattal Dietikon",
    "wof:placetype":"venue"
},
  "geometry": {"coordinates":[8.4140663147,47.3987236023],"type":"Point"}
}