{
  "type": "Feature",
  "properties": {
    "iso:country":"CH",
    "sg:address":"Schwefelstrasse 17",
    "sg:city":"Vaduz",
    "sg:orig_category":"Vorschulen, Kinderg\u00e4rten",
    "sg:phone":"+41 17152162",
    "sg:postcode":"9490",
    "wof:name":"Kindergarten Schwelle I",
    "wof:placetype":"venue"
},
  "geometry": {"coordinates":[8.5454130173,47.3209609985],"type":"Point"}
}