{
  "type": "Feature",
  "properties": {
    "iso:country":"CH",
    "sg:address":"Wattenwylstrasse 4",
    "sg:city":"Emmenbr\u00fccke",
    "sg:orig_category":"Sonstige Aktivit\u00e4ten der nicht-\u00e4rztlichen Medizinalberufe",
    "sg:phone":"+41 41 280 22 07",
    "sg:postcode":"6020",
    "sg:province":"Luzern",
    "wof:name":"Ernst Peter Atemschule",
    "wof:placetype":"venue"
},
  "geometry": {"coordinates":[8.2785720825,47.0812530518],"type":"Point"}
}