{
  "type": "Feature",
  "properties": {
    "iso:country":"CH",
    "sg:address":"Rue Des Remparts 18 1400 Yverdon-les-bains Case Postale 276",
    "sg:city":"Yverdon",
    "sg:orig_category":"Grosshandel mit H\u00e4uten, Fellen U Leder Grosshandel mit sonstigen Maschinen U Ausr\u00fcstungen f\u00fcr Indust",
    "sg:phone":"+41 24 425 21 91",
    "sg:postcode":"1401",
    "sg:province":"Vaud",
    "wof:name":"Ajimex Sa",
    "wof:placetype":"venue"
},
  "geometry": {"coordinates":[6.639731884,46.780002594],"type":"Point"}
}