{
  "type": "Feature",
  "properties": {
    "iso:country":"CH",
    "sg:address":"Thiersteinerallee 14 4053 Basel. Postfach",
    "sg:city":"Basel",
    "sg:orig_category":"Pensionskassen",
    "sg:postcode":"4053",
    "sg:province":"Basel-Stadt",
    "wof:name":"Stiftung F\u00fcr Soziale Zwecke Des Angestelltenvereins Coop Schweiz",
    "wof:placetype":"venue"
},
  "geometry": {"coordinates":[7.5985407829,47.5430717468],"type":"Point"}
}