{
  "type": "Feature",
  "properties": {
    "iso:country":"CH",
    "sg:address":"1628",
    "sg:city":"Vuadens",
    "sg:orig_category":"Sportvereine Ski",
    "sg:postcode":"1628",
    "sg:province":"Fribourg",
    "wof:name":"Ski-club Colombettes",
    "wof:placetype":"venue"
},
  "geometry": {"coordinates":[7.0192427635,46.6172447205],"type":"Point"}
}