{
  "type": "Feature",
  "properties": {
    "iso:country":"CH",
    "sg:address":"Rue De La Fontaine 5",
    "sg:city":"Paudex",
    "sg:orig_category":"Detailhandel mit B\u00fcchern, Zeitungen, Schreib U Papeteriewaren Detailhandel mit Zeitungen U Zeitschri",
    "sg:phone":"+41 21 791 57 72",
    "sg:postcode":"1094",
    "sg:province":"Vaud",
    "wof:name":"Kiosque De La Fontaine, Fracheboud",
    "wof:placetype":"venue"
},
  "geometry": {"coordinates":[6.672365,46.506355],"type":"Point"}
}