{
  "type": "Feature",
  "properties": {
    "iso:country":"CH",
    "sg:address":"Place Saint-fran\u00e7ois 11 1003 Lausanne Case Postale 3390",
    "sg:city":"Lausanne",
    "sg:orig_category":"Advokaturb\u00fcros",
    "sg:phone":"+41 21 312 54 77",
    "sg:postcode":"1002",
    "sg:province":"Vaud",
    "wof:name":"Mercier & Gonset Etude D'avocat",
    "wof:placetype":"venue"
},
  "geometry": {"coordinates":[6.633963,46.519798],"type":"Point"}
}