{
  "type": "Feature",
  "properties": {
    "iso:country":"CH",
    "sg:address":"Rte D' Ovronnaz",
    "sg:city":"Leytron",
    "sg:classifiers":[
        {
            "category":"Banks & Credit Unions",
            "subcategory":"Bank",
            "type":"Services"
        }
    ],
    "sg:phone":"+41 27 306 29 85",
    "sg:postcode":"1912",
    "sg:province":"Valais",
    "wof:name":"Raiffeisen",
    "wof:placetype":"venue"
},
  "geometry": {"coordinates":[7.207323,46.188499],"type":"Point"}
}