{
  "type": "Feature",
  "properties": {
    "iso:country":"CH",
    "sg:address":"Chiboz 1926 1926 Fully. Postfach",
    "sg:city":"Fully",
    "sg:orig_category":"Interessenvertretungen",
    "sg:postcode":"1926",
    "sg:province":"Valais",
    "wof:name":"Fondation Du Musee Charlie Chaplin Mus\u00e9e Charlie Chaplin Etc",
    "wof:placetype":"venue"
},
  "geometry": {"coordinates":[5.1808700562,45.8973388672],"type":"Point"}
}