{
  "type": "Feature",
  "properties": {
    "iso:country":"CH",
    "sg:address":"Fehlwiesstrasse 22",
    "sg:city":"Amriswil",
    "sg:orig_category":"Sonstiger Grosshandel",
    "sg:phone":"+41 79 344 02 02",
    "sg:postcode":"8580",
    "sg:province":"Thurgau",
    "wof:name":"Maze Gmbh",
    "wof:placetype":"venue"
},
  "geometry": {"coordinates":[9.3107795715,47.5495491028],"type":"Point"}
}