{
  "type": "Feature",
  "properties": {
    "iso:country":"CH",
    "sg:address":"Rte De Lausanne 1400 Yverdon-les-bains. Postfach",
    "sg:city":"Yverdon-les-bains",
    "sg:orig_category":"Pensionskassen",
    "sg:postcode":"1400",
    "sg:province":"Vaud",
    "wof:name":"Fonds De Pr\u00e9voyance En Faveur Du Personnel De Valdar Sa",
    "wof:placetype":"venue"
},
  "geometry": {"coordinates":[6.237830162,46.6010818481],"type":"Point"}
}