{
  "type": "Feature",
  "properties": {
    "iso:country":"CH",
    "sg:address":"8036 Z\u00fcrich. Postfach",
    "sg:city":"Z\u00fcrich",
    "sg:orig_category":"Detailhandel mit B\u00fcchern, Zeitungen, Schreib U Papeteriewaren",
    "sg:postcode":"8036",
    "sg:province":"Z\u00fcrich",
    "wof:name":"Freihofer Ag, Wissenschaftliche Buchhandlungen",
    "wof:placetype":"venue"
},
  "geometry": {"coordinates":[8.53801,47.369091],"type":"Point"}
}