{
  "type": "Feature",
  "properties": {
    "iso:country":"CH",
    "sg:address":"Eugen Huber-strasse 107 8048 Z\u00fcrich. Postfach",
    "sg:city":"Z\u00fcrich",
    "sg:orig_category":"Offsetdruck",
    "sg:phone":"+41 12413212",
    "sg:postcode":"8026",
    "sg:province":"Z\u00fcrich",
    "wof:name":"Zindel Druck Gmbh Drucksachen; Herstellung Usw",
    "wof:placetype":"venue"
},
  "geometry": {"coordinates":[8.4761533737,47.3873977661],"type":"Point"}
}