{
  "type": "Feature",
  "properties": {
    "iso:country":"CH",
    "sg:address":"Grand Rue 11",
    "sg:city":"Echallens",
    "sg:orig_category":"Zahnarztpraxen",
    "sg:phone":"+41 21 881 31 83",
    "sg:postcode":"1040",
    "sg:province":"Vaud",
    "wof:name":"Dr M\u00e9d. Dent. Christian Clerc M\u00e9decin-dentiste",
    "wof:placetype":"venue"
},
  "geometry": {"coordinates":[6.6335201263,46.641292572],"type":"Point"}
}