{
  "type": "Feature",
  "properties": {
    "iso:country":"CH",
    "sg:address":"Fichtenstrasse 71",
    "sg:city":"Uzwil",
    "sg:orig_category":"Instandhaltung U Reparatur von Automobilen Tankstellen",
    "sg:phone":"+41 71 951 55 63",
    "sg:postcode":"9240",
    "sg:province":"St. Gallen",
    "wof:name":"Lindenplatz-garage Widmer Bruno",
    "wof:placetype":"venue"
},
  "geometry": {"coordinates":[9.1357460022,47.4343910217],"type":"Point"}
}