{
  "type": "Feature",
  "properties": {
    "addr:full":"Riedli 30 Galmiz Fribourg 3285",
    "addr:housenumber":"30",
    "addr:postcode":"3285",
    "addr:street":"Riedli;Fribourg",
    "iso:country":"CH",
    "sg:address":"Riedli 30",
    "sg:city":"Galmiz",
    "sg:orig_category":"Allgemeiner Hoch U Tiefbau",
    "sg:postcode":"3285",
    "sg:province":"Fribourg",
    "wof:name":"Generalunternehmung Lehmann K. Gmbh",
    "wof:placetype":"venue"
},
  "geometry": {"coordinates":[7.154493,46.944839],"type":"Point"}
}