{
  "type": "Feature",
  "properties": {
    "iso:country":"CH",
    "sg:address":"Neuenburgstrasse 132 2500 Biel/bienne. Postfach",
    "sg:city":"Biel/bienne",
    "sg:orig_category":"Sonstige mit Sport verbundene T\u00e4tigkeiten",
    "sg:postcode":"2505",
    "sg:province":"Bern",
    "wof:name":"Windsurf-center Piranha, Bruppacher D.",
    "wof:placetype":"venue"
},
  "geometry": {"coordinates":[7.2271609306,47.1335754395],"type":"Point"}
}