{
  "type": "Feature",
  "properties": {
    "iso:country":"CH",
    "sg:address":"Z\u00fcrcherstrasse 65",
    "sg:city":"Dietikon",
    "sg:orig_category":"Autospenglereien",
    "sg:phone":"+41 79 414 26 40",
    "sg:postcode":"8953",
    "sg:province":"Z\u00fcrich",
    "wof:name":"Roberto Portaluri Carrosserie",
    "wof:placetype":"venue"
},
  "geometry": {"coordinates":[8.406858,47.40221],"type":"Point"}
}