{
  "type": "Feature",
  "properties": {
    "iso:country":"CH",
    "sg:address":"Junkerngasse 52",
    "sg:city":"Bern",
    "sg:orig_category":"Kunsthandel",
    "sg:phone":"+41 31 311 80 33",
    "sg:postcode":"3011",
    "sg:province":"Bern",
    "wof:name":"Marlyse Aebli Galerie",
    "wof:placetype":"venue"
},
  "geometry": {"coordinates":[7.4528250694,46.9477081299],"type":"Point"}
}