{
  "type": "Feature",
  "properties": {
    "iso:country":"CH",
    "sg:address":"Bahnhofstrasse 51 8854 Siebnen. Postfach",
    "sg:city":"Siebnen",
    "sg:orig_category":"Architektur U Ingenieurb\u00fcros",
    "sg:phone":"+41 55 440 50 50",
    "sg:postcode":"8854",
    "sg:province":"Schwyz",
    "wof:name":"Vogt & Partner Gmbh, Architekturb\u00fcro",
    "wof:placetype":"venue"
},
  "geometry": {"coordinates":[8.897491,47.180466],"type":"Point"}
}