{
  "type": "Feature",
  "properties": {
    "iso:country":"CH",
    "sg:address":"Via Alpsu 74",
    "sg:city":"Sedrun",
    "sg:orig_category":"Autogaragen",
    "sg:phone":"+41 79 413 01 18",
    "sg:postcode":"7188",
    "sg:province":"Graubunden",
    "wof:name":"Toni Riedi Garage Badus",
    "wof:placetype":"venue"
},
  "geometry": {"coordinates":[8.768884,46.678917],"type":"Point"}
}