{
  "type": "Feature",
  "properties": {
    "iso:country":"CH",
    "sg:address":"Feldbergstrasse 112",
    "sg:city":"Basel",
    "sg:orig_category":"Stukkateurgewerbe, Gipserei U Verputzerei",
    "sg:postcode":"4057",
    "sg:province":"Basel-Stadt",
    "wof:name":"Gipser Und Malergesch\u00e4ft Badalli",
    "wof:placetype":"venue"
},
  "geometry": {"coordinates":[7.5954189301,47.5669136047],"type":"Point"}
}