{
  "type": "Feature",
  "properties": {
    "iso:country":"CH",
    "sg:address":"Schmalen",
    "sg:city":"Erschwil",
    "sg:orig_category":"Gartenbau",
    "sg:phone":"+41 61 781 21 04",
    "sg:postcode":"4228",
    "sg:province":"Solothurn",
    "wof:name":"Gartenbau Neuschwander Paul",
    "wof:placetype":"venue"
},
  "geometry": {"coordinates":[7.5328850746,47.3742752075],"type":"Point"}
}