{
  "type": "Feature",
  "properties": {
    "iso:country":"CH",
    "sg:address":"Arsenalstrasse 37",
    "sg:city":"Kriens",
    "sg:orig_category":"Handels-H\u00e4user U Gesellschaften",
    "sg:postcode":"6010",
    "sg:province":"Luzern",
    "wof:name":"Goodtrade Gmbh",
    "wof:placetype":"venue"
},
  "geometry": {"coordinates":[8.2968530655,47.0356750488],"type":"Point"}
}