{
  "type": "Feature",
  "properties": {
    "iso:country":"CH",
    "sg:address":"Althaustrasse 22",
    "sg:city":"Spreitenbach",
    "sg:orig_category":"Softwareentwicklung U beratung",
    "sg:phone":"+41 56 410 23 43",
    "sg:postcode":"8957",
    "sg:province":"Aargau",
    "wof:name":"Olivier Zaugg Highway-express",
    "wof:placetype":"venue"
},
  "geometry": {"coordinates":[8.3606872559,47.41929245],"type":"Point"}
}