{
  "type": "Feature",
  "properties": {
    "iso:country":"CH",
    "sg:address":"Sihlquai 55",
    "sg:city":"Z\u00fcrich",
    "sg:orig_category":"Herstellung von Lederbekleidung",
    "sg:phone":"+41 12720083",
    "sg:postcode":"8005",
    "sg:province":"Z\u00fcrich",
    "wof:name":"Monney Anna, Lederwerkstatt Z\u00fcrich Lederbekleidung, Accessoires; \u00c4nderung, Anfertigung, Reparatur",
    "wof:placetype":"venue"
},
  "geometry": {"coordinates":[8.5377597809,47.3819656372],"type":"Point"}
}