{
  "type": "Feature",
  "properties": {
    "iso:country":"CH",
    "sg:address":"Altishoferstrasse 9 6252 Dagmersellen. Postfach",
    "sg:city":"Dagmersellen",
    "sg:orig_category":"RESTAURANTS: TEA-ROOMS",
    "sg:postcode":"6252",
    "sg:province":"Luzern",
    "wof:name":"Snack-bar \u00d6ztoprak\u00e7i Hasan",
    "wof:placetype":"venue"
},
  "geometry": {"coordinates":[7.988134861,47.2119827271],"type":"Point"}
}