{
  "type": "Feature",
  "properties": {
    "addr:full":"Herrengasse 23 Schwyz Schwyz 6430",
    "addr:housenumber":"23",
    "addr:postcode":"6430",
    "addr:street":"Herrengasse",
    "iso:country":"CH",
    "sg:address":"Herrengasse 23",
    "sg:city":"Schwyz",
    "sg:classifiers":[
        {
            "category":"Banks & Credit Unions",
            "subcategory":"Bank",
            "type":"Services"
        }
    ],
    "sg:phone":"+41 41 819 02 50",
    "sg:postcode":"6430",
    "sg:province":"Schwyz",
    "wof:name":"Sparkasse Schwyz",
    "wof:placetype":"venue"
},
  "geometry": {"coordinates":[8.650956,47.022007],"type":"Point"}
}