{
  "type": "Feature",
  "properties": {
    "iso:country":"CH",
    "sg:address":"Ruelle Glarey 1",
    "sg:city":"Bex",
    "sg:orig_category":"Bauschreinerei Herstellung von Konstruktionsteilen, Fertigbauteilen U Ausbauelementen aus Holz",
    "sg:phone":"+41 24 463 23 30",
    "sg:postcode":"1880",
    "sg:province":"Vaud",
    "wof:name":"Stauber Roland",
    "wof:placetype":"venue"
},
  "geometry": {"coordinates":[7.022831,46.251545],"type":"Point"}
}