{
  "type": "Feature",
  "properties": {
    "iso:country":"CH",
    "sg:address":"Quai Robert-comtesse 4 2000 Neuenburg. Postfach",
    "sg:city":"Neuenburg",
    "sg:orig_category":"RESTAURANTS: TEA-ROOMS",
    "sg:postcode":"2000",
    "sg:province":"Neuch\u00e2tel",
    "wof:name":"Le M\u00fbrier S\u00e0rl",
    "wof:placetype":"venue"
},
  "geometry": {"coordinates":[6.9446401596,46.9946136475],"type":"Point"}
}