{
  "type": "Feature",
  "properties": {
    "addr:full":"Rue Du Lac 28b Vevey Vaud 1800",
    "addr:housenumber":"28b",
    "addr:postcode":"1800",
    "addr:street":"Rue Du Lac",
    "iso:country":"CH",
    "sg:address":"Rue Du Lac 28b",
    "sg:city":"Vevey",
    "sg:orig_category":"Detailhandel mit Bekleidung",
    "sg:phone":"+41 21 922 43 61",
    "sg:postcode":"1800",
    "sg:province":"Vaud",
    "wof:name":"Boutique Teinture D'iode",
    "wof:placetype":"venue"
},
  "geometry": {"coordinates":[6.84572,46.458939],"type":"Point"}
}