{
  "type": "Feature",
  "properties": {
    "iso:country":"CH",
    "sg:address":"Avenue Des Alpes 120",
    "sg:city":"Montreux",
    "sg:orig_category":"Arztpraxen",
    "sg:phone":"+41 21 963 13 10",
    "sg:postcode":"1820",
    "sg:province":"Vaud",
    "wof:name":"Dr M\u00e9d. Zivomir Tomic M\u00e9decin Sp\u00e9cialiste",
    "wof:placetype":"venue"
},
  "geometry": {"coordinates":[6.907826,46.438679],"type":"Point"}
}