{
  "type": "Feature",
  "properties": {
    "iso:country":"CH",
    "sg:address":"Casa Le Palme",
    "sg:city":"Contone",
    "sg:orig_category":"Detailhandel mit elektrischen Haushaltsger\u00e4ten Reparatur von elektrischen Haushaltsger\u00e4ten",
    "sg:phone":"+41 91 858 20 56",
    "sg:postcode":"6594",
    "sg:province":"Ticino",
    "wof:name":"Armando Liesch Liesch Servizio",
    "wof:placetype":"venue"
},
  "geometry": {"coordinates":[8.9260749817,46.148525238],"type":"Point"}
}