{
  "type": "Feature",
  "properties": {
    "iso:country":"CH",
    "sg:address":"Bolligenstrasse 24b",
    "sg:city":"Bern",
    "sg:orig_category":"Sportvereine Turnen Vereine Damen",
    "sg:phone":"+41 33 823 42 34",
    "sg:postcode":"3006",
    "sg:province":"Bern",
    "wof:name":"Damen-& Frauenr.r'berg-goldsw.",
    "wof:placetype":"venue"
},
  "geometry": {"coordinates":[7.8976860046,46.7034339905],"type":"Point"}
}