{
  "type": "Feature",
  "properties": {
    "iso:country":"CH",
    "sg:address":"Hauptstrasse",
    "sg:city":"Altwis",
    "sg:orig_category":"Instandhaltung U Reparatur von Automobilen",
    "sg:phone":"+41 41 917 13 17",
    "sg:postcode":"6286",
    "sg:province":"Luzern",
    "wof:name":"H\u00f6ltschi Jos.",
    "wof:placetype":"venue"
},
  "geometry": {"coordinates":[8.2500953674,47.2402763367],"type":"Point"}
}