{
  "type": "Feature",
  "properties": {
    "iso:country":"CH",
    "sg:address":"1270",
    "sg:city":"Tr\u00e9lex",
    "sg:orig_category":"Allgemeiner Gartenbau",
    "sg:phone":"+41 22 369 21 52",
    "sg:postcode":"1270",
    "sg:province":"Vaud",
    "wof:name":"Arbosoins Sa",
    "wof:placetype":"venue"
},
  "geometry": {"coordinates":[6.19475,46.420471],"type":"Point"}
}