{
  "type": "Feature",
  "properties": {
    "iso:country":"CH",
    "sg:address":"Cantonale Route 95",
    "sg:city":"Charmoille",
    "sg:orig_category":"G\u00fcterbef\u00f6rderung im Strassenverkehr",
    "sg:phone":"+41 52 742 09 09",
    "sg:postcode":"2947",
    "sg:province":"Jura",
    "wof:name":"Tit Imhof Ag",
    "wof:placetype":"venue"
},
  "geometry": {"coordinates":[8.8529138565,47.6523857117],"type":"Point"}
}