{
  "type": "Feature",
  "properties": {
    "addr:full":"R\u00e4bengasse 11 Steinen Schwyz 6422",
    "addr:housenumber":"11",
    "addr:postcode":"6422",
    "addr:street":"Raebengasse;Schwyz",
    "iso:country":"CH",
    "sg:address":"R\u00e4bengasse 11",
    "sg:city":"Steinen",
    "sg:orig_category":"Allgemeiner Hoch U Tiefbau Maurerarbeiten",
    "sg:phone":"+41 79 432 88 80",
    "sg:postcode":"6422",
    "sg:province":"Schwyz",
    "wof:name":"Bissig Altbautechnik",
    "wof:placetype":"venue"
},
  "geometry": {"coordinates":[8.614058,47.04818],"type":"Point"}
}