{
  "type": "Feature",
  "properties": {
    "iso:country":"CH",
    "sg:address":"Unterdorfstrasse 2",
    "sg:city":"Kaisten",
    "sg:orig_category":"Physiotherapie",
    "sg:phone":"+41 62 874 13 25",
    "sg:postcode":"5082",
    "sg:province":"Aargau",
    "wof:name":"Christine Wunderlin Physiotherapie",
    "wof:placetype":"venue"
},
  "geometry": {"coordinates":[8.0446062088,47.5412712097],"type":"Point"}
}