{
  "type": "Feature",
  "properties": {
    "iso:country":"CH",
    "sg:address":"Koppigensstrasse 25a",
    "sg:city":"Utzenstorf",
    "sg:orig_category":"Herstellung von Elektromotoren, Generatoren U Transformatoren",
    "sg:phone":"+41 32 665 05 50",
    "sg:postcode":"3427",
    "sg:province":"Bern",
    "wof:name":"Bkw Isp Ag, Zweigniederlassung Utzenstorf",
    "wof:placetype":"venue"
},
  "geometry": {"coordinates":[7.561811924,47.1282958984],"type":"Point"}
}