{
  "type": "Feature",
  "properties": {
    "iso:country":"CH",
    "sg:address":"In Gassen 11",
    "sg:city":"Z\u00fcrich",
    "sg:orig_category":"Markt U Meinungsforschung",
    "sg:postcode":"8001",
    "sg:province":"Z\u00fcrich",
    "wof:name":"Bch Ag",
    "wof:placetype":"venue"
},
  "geometry": {"coordinates":[8.540230751,47.3704719543],"type":"Point"}
}