{
  "type": "Feature",
  "properties": {
    "iso:country":"CH",
    "sg:address":"Via Cantonale 33",
    "sg:city":"Cadempino",
    "sg:orig_category":"Architektur U Ingenieurb\u00fcros",
    "sg:phone":"+41 91 967 19 35",
    "sg:postcode":"6814",
    "sg:province":"Ticino",
    "wof:name":"Globalcasa Sa",
    "wof:placetype":"venue"
},
  "geometry": {"coordinates":[8.935721,46.031719],"type":"Point"}
}