{
  "type": "Feature",
  "properties": {
    "iso:country":"CH",
    "sg:address":"Bodenacker 23",
    "sg:city":"Bolligen",
    "sg:orig_category":"Handelsvermittlung U Grosshandel",
    "sg:phone":"+41 31 921 00 07",
    "sg:postcode":"3065",
    "sg:province":"Bern",
    "wof:name":"Martin Hofer Handelsagentur",
    "wof:placetype":"venue"
},
  "geometry": {"coordinates":[7.4986667633,46.9804229736],"type":"Point"}
}