{
  "type": "Feature",
  "properties": {
    "iso:country":"CH",
    "sg:address":"Seefeldstrasse 7 8008 Z\u00fcrich. Postfach 903",
    "sg:city":"Z\u00fcrich",
    "sg:orig_category":"Advokaturb\u00fcros",
    "sg:phone":"+41 12613381",
    "sg:postcode":"8034",
    "sg:province":"Z\u00fcrich",
    "wof:name":"Dr.max Glauser Advokaturb\u00fcro",
    "wof:placetype":"venue"
},
  "geometry": {"coordinates":[8.548545,47.36475],"type":"Point"}
}