{
  "type": "Feature",
  "properties": {
    "iso:country":"CH",
    "sg:address":"Es-planches 146 2842 Rossemaison. Postfach",
    "sg:city":"Rossemaison",
    "sg:orig_category":"Herstellung von Radio U Fernsehger\u00e4ten sowie phono U videotechnischen Ger\u00e4ten",
    "sg:postcode":"2842",
    "sg:province":"Jura",
    "wof:name":"Telecompro, Catellani Christian",
    "wof:placetype":"venue"
},
  "geometry": {"coordinates":[7.3489208221,47.3450241089],"type":"Point"}
}