{
  "type": "Feature",
  "properties": {
    "iso:country":"CH",
    "sg:address":"Rue De L'eglise 1",
    "sg:city":"Chamoson",
    "sg:orig_category":"Rebbau",
    "sg:phone":"+41 27 306 16 44",
    "sg:postcode":"1955",
    "sg:province":"Valais",
    "wof:name":"Provins Valais Cave Coop\u00e9rative",
    "wof:placetype":"venue"
},
  "geometry": {"coordinates":[7.2413878441,46.1952590942],"type":"Point"}
}