{
  "type": "Feature",
  "properties": {
    "iso:country":"CH",
    "sg:address":"Chemin De L'argili\u00e8re 4",
    "sg:city":"Vessy",
    "sg:orig_category":"Non-Classified Establishments",
    "sg:postcode":"1234",
    "sg:province":"Gen\u00e8ve",
    "wof:name":"Dls Import Sarl",
    "wof:placetype":"venue"
},
  "geometry": {"coordinates":[6.1551117897,46.1745567322],"type":"Point"}
}