{
  "type": "Feature",
  "properties": {
    "iso:country":"CH",
    "sg:address":"Rue Ferrier 17 1200 Genf. Postfach",
    "sg:city":"Gen\u00e8ve",
    "sg:orig_category":"Detailhandel mit Waren verschiedener Art, Hauptrichtung Nahrungsmittel",
    "sg:postcode":"1201",
    "sg:province":"Gen\u00e8ve",
    "wof:name":"Cama\u00cfs S\u00e0rl",
    "wof:placetype":"venue"
},
  "geometry": {"coordinates":[6.14671278,46.2163925171],"type":"Point"}
}