{
  "type": "Feature",
  "properties": {
    "iso:country":"CH",
    "sg:address":"Wyler",
    "sg:city":"Isenthal",
    "sg:orig_category":"Hoch U Tiefbau",
    "sg:phone":"+41 41 878 12 65",
    "sg:postcode":"6461",
    "sg:province":"Uri",
    "wof:name":"Oskar Bissig Bauunternehmung",
    "wof:placetype":"venue"
},
  "geometry": {"coordinates":[8.5660848618,46.9100761414],"type":"Point"}
}