{
  "type": "Feature",
  "properties": {
    "addr:full":"Avenue De La Gare 20 1920 Martigny. Postfach Martigny Valais 1920",
    "addr:housenumber":"20",
    "addr:postcode":"1920 martigny. postfach;1920",
    "addr:street":"Avenue De La Gare",
    "iso:country":"CH",
    "sg:address":"Avenue De La Gare 20 1920 Martigny. Postfach",
    "sg:city":"Martigny",
    "sg:orig_category":"Detailhandel mit Brot, Back U S\u00fcsswaren",
    "sg:postcode":"1920",
    "sg:province":"Valais",
    "wof:name":"Coddeville Pascal",
    "wof:placetype":"venue"
},
  "geometry": {"coordinates":[7.075002,46.10273],"type":"Point"}
}