{
  "type": "Feature",
  "properties": {
    "iso:country":"CH",
    "sg:address":"Unterbiel 5",
    "sg:city":"Reigoldswil",
    "sg:orig_category":"Detailhandel mit Blumen U Pflanzen",
    "sg:phone":"+41 61 941 22 65",
    "sg:postcode":"4418",
    "sg:province":"Basel-Landschaft",
    "wof:name":"Bettina D\u00fcrr-roth Blumenhaus Sonne",
    "wof:placetype":"venue"
},
  "geometry": {"coordinates":[7.691585,47.397976],"type":"Point"}
}