{
  "type": "Feature",
  "properties": {
    "iso:country":"CH",
    "sg:address":"Trichtenhausenstrasse 130",
    "sg:city":"Z\u00fcrich",
    "sg:orig_category":"Softwareentwicklung U beratung",
    "sg:phone":"+41 13859030",
    "sg:postcode":"8053",
    "sg:province":"Z\u00fcrich",
    "wof:name":"Bosshard Audiovisionstechnik Gmbh",
    "wof:placetype":"venue"
},
  "geometry": {"coordinates":[8.6010551453,47.3541069031],"type":"Point"}
}