{
  "type": "Feature",
  "properties": {
    "iso:country":"CH",
    "sg:address":"St. Niklausenstrasse 103 6047 Kastanienbaum. Postfach",
    "sg:city":"Kastanienbaum",
    "sg:orig_category":"Vermietung U Verpachtung von eigenen Immobilien",
    "sg:postcode":"6047",
    "sg:province":"Luzern",
    "wof:name":"Robal Ag",
    "wof:placetype":"venue"
},
  "geometry": {"coordinates":[8.340294838,47.007686615],"type":"Point"}
}