{
  "type": "Feature",
  "properties": {
    "iso:country":"CH",
    "sg:address":"4805",
    "sg:city":"Brittnau",
    "sg:orig_category":"Vereine Vogel-& Naturschutz",
    "sg:phone":"+41 62 751 48 04",
    "sg:postcode":"4805",
    "sg:province":"Aargau",
    "wof:name":"Ornithologische Gesellschaft",
    "wof:placetype":"venue"
},
  "geometry": {"coordinates":[7.9466080666,47.2601356506],"type":"Point"}
}