{
  "type": "Feature",
  "properties": {
    "iso:country":"CH",
    "sg:address":"Burgdorfstrasse 56 3510 Konolfingen. Postfach",
    "sg:city":"Konolfingen",
    "sg:orig_category":"Sonstige pers\u00f6nliche Dienstleistungen",
    "sg:postcode":"3510",
    "sg:province":"Bern",
    "wof:name":"In-process Consulting Gmbh Dienstleistungen Im Bereich Business - U. It Consulting Usw.",
    "wof:placetype":"venue"
},
  "geometry": {"coordinates":[7.6280808449,46.8869056702],"type":"Point"}
}