{
  "type": "Feature",
  "properties": {
    "iso:country":"CH",
    "sg:address":"Seebacherstrasse 100",
    "sg:city":"Z\u00fcrich",
    "sg:orig_category":"Detailhandel mit Radio U Fernsehger\u00e4ten",
    "sg:phone":"+41 32 652 33 33",
    "sg:postcode":"8050",
    "sg:province":"Z\u00fcrich",
    "wof:name":"Audio Video Baumann Ag",
    "wof:placetype":"venue"
},
  "geometry": {"coordinates":[7.3660998344,47.1816177368],"type":"Point"}
}