{
  "type": "Feature",
  "properties": {
    "iso:country":"CH",
    "sg:address":"Ch\u00f6renmattweg 6",
    "sg:city":"Berikon",
    "sg:orig_category":"Hardwareberatung",
    "sg:postcode":"8965",
    "sg:province":"Aargau",
    "wof:name":"Malaxit Ag",
    "wof:placetype":"venue"
},
  "geometry": {"coordinates":[8.3669500351,47.3564872742],"type":"Point"}
}