{
  "type": "Feature",
  "properties": {
    "iso:country":"CH",
    "sg:address":"Chemin Des Colombaires 27",
    "sg:city":"Cully",
    "sg:orig_category":"Zimmerei, Dachdeckerei, Bauspenglerei U Abdichtung",
    "sg:postcode":"1096",
    "sg:province":"Vaud",
    "wof:name":"Anderegg Marcel",
    "wof:placetype":"venue"
},
  "geometry": {"coordinates":[6.7260499001,46.4901657104],"type":"Point"}
}