{
  "type": "Feature",
  "properties": {
    "iso:country":"CH",
    "sg:address":"Tufertschwil 90 9604 L\u00fctisburg. Postfach",
    "sg:city":"L\u00fctisburg",
    "sg:orig_category":"Betrieb U technische Hilfsdienste des Kultur U Unterhaltungswesens Fahrschulen, Flugschulen",
    "sg:phone":"+41 22 342 16 22",
    "sg:postcode":"9604",
    "sg:province":"St. Gallen",
    "wof:name":"Claude Passello Auto-\u00e9cole",
    "wof:placetype":"venue"
},
  "geometry": {"coordinates":[6.1426,46.183056],"type":"Point"}
}