{
  "type": "Feature",
  "properties": {
    "iso:country":"CH",
    "sg:address":"General-dufour-strasse 28",
    "sg:city":"Biel/bienne",
    "sg:orig_category":"Detailhandel mit Radio U Fernsehger\u00e4ten Fachdetailhandel in Verkaufsr\u00e4umen",
    "sg:phone":"+41 32 323 53 53",
    "sg:postcode":"2502",
    "sg:province":"Bern",
    "wof:name":"Facchinetti & Schmidt Ag, Photo-video Dufour",
    "wof:placetype":"venue"
},
  "geometry": {"coordinates":[7.2491521835,47.1404037476],"type":"Point"}
}