{
  "type": "Feature",
  "properties": {
    "iso:country":"CH",
    "sg:address":"Stegreutiweg 42",
    "sg:city":"M\u00fcnsingen",
    "sg:orig_category":"Fahrschulen, Flugschulen",
    "sg:phone":"+41 56 622 58 80",
    "sg:postcode":"3110",
    "sg:province":"Bern",
    "wof:name":"Rainer R\u00fcegger Fahrschule",
    "wof:placetype":"venue"
},
  "geometry": {"coordinates":[8.2889947891,47.3454360962],"type":"Point"}
}