{
  "type": "Feature",
  "properties": {
    "addr:full":"Haus Allegra Fanas Graubunden 7215",
    "addr:housenumber":"7215",
    "iso:country":"CH",
    "sg:address":"Haus Allegra",
    "sg:city":"Fanas",
    "sg:orig_category":"Architektur U Ingenieurb\u00fcros",
    "sg:phone":"+41 81 325 23 23",
    "sg:postcode":"7215",
    "sg:province":"Graubunden",
    "wof:name":"Inatec Ag Planungsb\u00fcro",
    "wof:placetype":"venue"
},
  "geometry": {"coordinates":[9.665347,46.984989],"type":"Point"}
}