{
  "type": "Feature",
  "properties": {
    "iso:country":"CH",
    "sg:address":"Lengnau",
    "sg:city":"Lengnau",
    "sg:classifiers":[
        {
            "category":"Banks & Credit Unions",
            "subcategory":"Bank",
            "type":"Services"
        }
    ],
    "sg:phone":"+41 4156511451",
    "sg:postcode":"5426",
    "sg:province":"Aargau",
    "wof:name":"Raiffeisenbank Lengnau",
    "wof:placetype":"venue"
},
  "geometry": {"coordinates":[8.3281326294,47.5216293335],"type":"Point"}
}