{
  "type": "Feature",
  "properties": {
    "iso:country":"CH",
    "sg:address":"Hohlweg 7 3612 Steffisburg. Postfach",
    "sg:city":"Steffisburg",
    "sg:orig_category":"Hardwareberatung",
    "sg:postcode":"3613",
    "sg:province":"Bern",
    "wof:name":"X-soft Ag Ger\u00e4te, Systeme F\u00fcr Daten-erfassung- U. Verarbeitung, Bes. Computer- U. Sicherheitssysteme; Verkauf U. Applikation Usw",
    "wof:placetype":"venue"
},
  "geometry": {"coordinates":[7.6333169937,46.782535553],"type":"Point"}
}