{
  "type": "Feature",
  "properties": {
    "iso:country":"CH",
    "sg:address":"Stadtplatz 34",
    "sg:city":"Aarberg",
    "sg:orig_category":"Detailhandel mit Waren verschiedener Art, Hauptrichtung Nahrungsmittel",
    "sg:phone":"+41 32 392 22 22",
    "sg:postcode":"3270",
    "sg:province":"Bern",
    "wof:name":"Stedtli-ch\u00e4si K\u00e4serei",
    "wof:placetype":"venue"
},
  "geometry": {"coordinates":[7.2758340836,47.0445747375],"type":"Point"}
}