{
  "type": "Feature",
  "properties": {
    "iso:country":"CH",
    "sg:address":"Eschikerstrasse 74 8307 Effretikon. Postfach",
    "sg:city":"Effretikon",
    "sg:orig_category":"Sonstiger Grosshandel",
    "sg:phone":"+41 18607758",
    "sg:postcode":"8307",
    "sg:province":"Z\u00fcrich",
    "wof:name":"Gruva R. Gr\u00fcter",
    "wof:placetype":"venue"
},
  "geometry": {"coordinates":[8.6879911423,47.4361572266],"type":"Point"}
}