{
  "type": "Feature",
  "properties": {
    "iso:country":"CH",
    "sg:address":"1526 Cremin. Postfach",
    "sg:city":"Cremin",
    "sg:orig_category":"RESTAURANTS: TEA-ROOMS",
    "sg:postcode":"1526",
    "sg:province":"Vaud",
    "wof:name":"Swin-golf De Cremin Le Restaurant A La Ferme, Bessard Liliane",
    "wof:placetype":"venue"
},
  "geometry": {"coordinates":[6.8417801857,46.7248840332],"type":"Point"}
}