{
  "type": "Feature",
  "properties": {
    "addr:full":"Obstgartenstrasse 20 8006 Z\u00fcrich. Postfach Z\u00fcrich Z\u00fcrich 8001",
    "addr:housenumber":"20",
    "addr:postcode":"8006 zuerich. postfach;8001",
    "addr:street":"Obstgartenstrasse",
    "iso:country":"CH",
    "sg:address":"Obstgartenstrasse 20 8006 Z\u00fcrich. Postfach",
    "sg:city":"Z\u00fcrich",
    "sg:orig_category":"Architektur U Ingenieurb\u00fcros",
    "sg:phone":"+41 13614477",
    "sg:postcode":"8001",
    "sg:province":"Z\u00fcrich",
    "wof:name":"Kuster & Hager Ingenieurb\u00fcro Ag I",
    "wof:placetype":"venue"
},
  "geometry": {"coordinates":[8.542686,47.382439],"type":"Point"}
}