{
  "type": "Feature",
  "properties": {
    "iso:country":"CH",
    "sg:address":"Seebleichestrasse 60 9404 Rorschacherberg. Postfach 12",
    "sg:city":"Rorschach",
    "sg:orig_category":"Offsetdruck",
    "sg:phone":"+41 71 855 70 90",
    "sg:postcode":"9401",
    "sg:province":"St. Gallen",
    "wof:name":"Interform-druck Ag",
    "wof:placetype":"venue"
},
  "geometry": {"coordinates":[9.520403862,47.4787559509],"type":"Point"}
}