{
  "type": "Feature",
  "properties": {
    "iso:country":"CH",
    "sg:address":"4126",
    "sg:city":"Bettingen",
    "sg:orig_category":"Universit\u00e4tsspit\u00e4ler, Spit\u00e4ler f\u00fcr allgemeine Pflege",
    "sg:phone":"+41 56 619 61 11",
    "sg:postcode":"4126",
    "sg:province":"Basel-Stadt",
    "wof:name":"Reusspark Zentrum F\u00fcr Pflege",
    "wof:placetype":"venue"
},
  "geometry": {"coordinates":[8.2951402664,47.3776512146],"type":"Point"}
}