{
  "type": "Feature",
  "properties": {
    "iso:country":"CH",
    "sg:address":"G\u00fcetli 13 9100 Herisau. Postfach",
    "sg:city":"Herisau",
    "sg:orig_category":"Non-Classified Establishments",
    "sg:postcode":"9100",
    "sg:province":"Appenzell Ausserrhoden",
    "wof:name":"Scheiben Design Pc-support, Web-design, Privatunterricht Usw",
    "wof:placetype":"venue"
},
  "geometry": {"coordinates":[9.2756357193,47.3805236816],"type":"Point"}
}