{
  "type": "Feature",
  "properties": {
    "iso:country":"CH",
    "sg:address":"Grand-chemin 59",
    "sg:city":"Epalinges",
    "sg:orig_category":"Kunststoff-Produkte",
    "sg:phone":"+41 62 822 09 15",
    "sg:postcode":"1066",
    "sg:province":"Vaud",
    "wof:name":"Cartofont Buchs Ag",
    "wof:placetype":"venue"
},
  "geometry": {"coordinates":[8.0822200775,47.3880195618],"type":"Point"}
}