{
  "type": "Feature",
  "properties": {
    "iso:country":"CH",
    "sg:address":"Erlenstrasse 36",
    "sg:city":"Br\u00fcgg",
    "sg:classifiers":[
        {
            "category":"Health Services",
            "subcategory":"Hospital",
            "type":"Services"
        }
    ],
    "sg:phone":"+41 32 374 25 85",
    "sg:postcode":"2555",
    "sg:province":"Bern",
    "sg:tags":[
        "hip",
        "implant",
        "ball"
    ],
    "wof:name":"Saphirwerk Industrieprodukte Ag",
    "wof:placetype":"venue"
},
  "geometry": {"coordinates":[7.269755,47.119423],"type":"Point"}
}