{
  "type": "Feature",
  "properties": {
    "iso:country":"CH",
    "sg:address":"Kalchb\u00fchlstr. 40",
    "sg:city":"Chur",
    "sg:classifiers":[
        {
            "category":"Manufacturing",
            "subcategory":"Wood Products",
            "type":"Manufacturing & Wholesale Goods"
        }
    ],
    "sg:phone":"+41 81 252 63 36",
    "sg:postcode":"7000",
    "sg:province":"Graubunden",
    "sg:tags":[
        "-",
        "machine",
        "engineering",
        "mechanical",
        "professional",
        "furniture"
    ],
    "wof:name":"G Hammer Ag Grossk\u00dccheneinrichtungen",
    "wof:placetype":"venue"
},
  "geometry": {"coordinates":[9.5068750381,46.8466873169],"type":"Point"}
}