{
  "type": "Feature",
  "properties": {
    "addr:full":"Landstrasse Filzbach Glarus 8757",
    "addr:postcode":"8757",
    "addr:street":"Landstrasse",
    "iso:country":"CH",
    "sg:address":"Landstrasse",
    "sg:city":"Filzbach",
    "sg:orig_category":"Detailhandel an Verkaufsst\u00e4nden U auf M\u00e4rkten Detailhandel mit Zeitungen U Zeitschriften Kioske",
    "sg:phone":"+41 55 614 14 41",
    "sg:postcode":"8757",
    "sg:province":"Glarus",
    "wof:name":"Ursula Merz Bazar Kiosk",
    "wof:placetype":"venue"
},
  "geometry": {"coordinates":[9.127264,47.121162],"type":"Point"}
}