{
  "type": "Feature",
  "properties": {
    "iso:country":"CH",
    "sg:address":"Hauptstrasse 154",
    "sg:city":"Bubendorf",
    "sg:orig_category":"Instandhaltung U Reparatur von Automobilen",
    "sg:phone":"+41 61 935 96 96",
    "sg:postcode":"4416",
    "sg:province":"Basel-Landschaft",
    "wof:name":"Garage B\u00fcchi Willy",
    "wof:placetype":"venue"
},
  "geometry": {"coordinates":[7.7318911552,47.4427108765],"type":"Point"}
}