{
  "type": "Feature",
  "properties": {
    "iso:country":"CH",
    "sg:address":"Baarerstrasse 75",
    "sg:city":"Zug",
    "sg:orig_category":"Wirtschaftspr\u00fcfung, Steuerberatung U Treuhand",
    "sg:phone":"+41 41 710 24 10",
    "sg:postcode":"6300",
    "sg:province":"Zug",
    "wof:name":"Contrenda Revisions- & Treuhand Ag",
    "wof:placetype":"venue"
},
  "geometry": {"coordinates":[8.517616272,47.1769981384],"type":"Point"}
}