{
  "type": "Feature",
  "properties": {
    "addr:full":"L\u00e4ttenstrasse 39 Dietikon Z\u00fcrich 8953",
    "addr:housenumber":"39",
    "addr:postcode":"8953",
    "addr:street":"Laettenstrasse",
    "iso:country":"CH",
    "sg:address":"L\u00e4ttenstrasse 39",
    "sg:city":"Dietikon",
    "sg:orig_category":"Dachdeckerei Zimmerei, Dachdeckerei, Bauspenglerei U Abdichtung",
    "sg:phone":"+41 17413803",
    "sg:postcode":"8953",
    "sg:province":"Z\u00fcrich",
    "wof:name":"Bosshard W. Ag",
    "wof:placetype":"venue"
},
  "geometry": {"coordinates":[8.383271,47.402924],"type":"Point"}
}