{
  "type": "Feature",
  "properties": {
    "iso:country":"CH",
    "sg:address":"Wilerstrasse 20 9602 Bazenheid. Postfach",
    "sg:city":"Bazenheid",
    "sg:orig_category":"Handel mit Automobilen",
    "sg:postcode":"9602",
    "sg:province":"St. Gallen",
    "wof:name":"Autotuning By Barone G.",
    "wof:placetype":"venue"
},
  "geometry": {"coordinates":[9.402428627,47.4355697632],"type":"Point"}
}