{
  "type": "Feature",
  "properties": {
    "iso:country":"CH",
    "sg:address":"6964",
    "sg:city":"Davesco-soragno",
    "sg:orig_category":"Elektroinstallation",
    "sg:phone":"+41 91 941 50 02",
    "sg:postcode":"6964",
    "sg:province":"Ticino",
    "wof:name":"Elettro Frigerio Sa",
    "wof:placetype":"venue"
},
  "geometry": {"coordinates":[8.9895296097,46.0325584412],"type":"Point"}
}