{
  "type": "Feature",
  "properties": {
    "iso:country":"CH",
    "sg:address":"Beaumaroche",
    "sg:city":"Chardonne",
    "sg:orig_category":"Institutionen des Sozialwesens ohne Beherbergung",
    "sg:postcode":"1803",
    "sg:province":"Vaud",
    "wof:name":"La Maison Du P\u00e9lerin",
    "wof:placetype":"venue"
},
  "geometry": {"coordinates":[6.8397789001,46.4863052368],"type":"Point"}
}