{
  "type": "Feature",
  "properties": {
    "iso:country":"CH",
    "sg:address":"Murstrasse 3",
    "sg:city":"Breitenbach",
    "sg:orig_category":"Kosmetikinstitute",
    "sg:phone":"+41 61 712 05 05",
    "sg:postcode":"4226",
    "sg:province":"Solothurn",
    "wof:name":"Claudia Heller Kosmetikinstitut Claudia",
    "wof:placetype":"venue"
},
  "geometry": {"coordinates":[7.5467858315,47.4094963074],"type":"Point"}
}