{
  "type": "Feature",
  "properties": {
    "iso:country":"CH",
    "sg:address":"Via Vedeggi",
    "sg:city":"Magliaso",
    "sg:orig_category":"Aktivit\u00e4ten der Generalunternehmen im Baugewerbe Architekturb\u00fcros",
    "sg:phone":"+41 91 606 19 61",
    "sg:postcode":"6983",
    "sg:province":"Ticino",
    "wof:name":"Giovanni Conte Studio D'architettura",
    "wof:placetype":"venue"
},
  "geometry": {"coordinates":[8.886805,45.979099],"type":"Point"}
}