{
  "type": "Feature",
  "properties": {
    "iso:country":"CH",
    "sg:address":"Br\u00fcschweid",
    "sg:city":"Ottikon",
    "sg:orig_category":"Innenausbau Zimmerei, Dachdeckerei, Bauspenglerei U Abdichtung",
    "sg:phone":"+41 19354142",
    "sg:postcode":"8626",
    "sg:province":"Z\u00fcrich",
    "wof:name":"Gerber Holzbau Ag",
    "wof:placetype":"venue"
},
  "geometry": {"coordinates":[8.7774343491,47.2934265137],"type":"Point"}
}