{
  "type": "Feature",
  "properties": {
    "iso:country":"CH",
    "sg:address":"Gotthardstrasse 34",
    "sg:city":"Arth",
    "sg:orig_category":"Sonstige Kurierdienste",
    "sg:phone":"+41 76 368 44 00",
    "sg:postcode":"6415",
    "sg:province":"Schwyz",
    "wof:name":"Scooter Multi-services, Ducret Jean-christian Transport Rapide De Courrier Etc",
    "wof:placetype":"venue"
},
  "geometry": {"coordinates":[6.4576601982,46.5044631958],"type":"Point"}
}