{
  "type": "Feature",
  "properties": {
    "iso:country":"CH",
    "sg:address":"Industriestrasse 405",
    "sg:city":"Gunzgen",
    "sg:orig_category":"Allgemeiner Hoch U Tiefbau",
    "sg:postcode":"4617",
    "sg:province":"Solothurn",
    "wof:name":"Hurni Systembauten",
    "wof:placetype":"venue"
},
  "geometry": {"coordinates":[7.828239,47.324223],"type":"Point"}
}