{
  "type": "Feature",
  "properties": {
    "iso:country":"CH",
    "sg:address":"Waldeggstrasse 44 6020 Emmenbr\u00fccke. Postfach",
    "sg:city":"Emmenbr\u00fccke",
    "sg:orig_category":"Herstellung von medizinischen U chirurgischen Ger\u00e4ten sowie orthop\u00e4dischen Vorrichtungen",
    "sg:phone":"+41 41 280 71 21",
    "sg:postcode":"6020",
    "sg:province":"Luzern",
    "wof:name":"Koller Franz Heim Und Spitalbedarf Gmbh",
    "wof:placetype":"venue"
},
  "geometry": {"coordinates":[8.2740678787,47.0848274231],"type":"Point"}
}