{
  "type": "Feature",
  "properties": {
    "iso:country":"CH",
    "sg:address":"Chemin Des Cruz 1180 Rolle. Postfach",
    "sg:city":"Rolle",
    "sg:orig_category":"Herstellung von Getr\u00e4nken Rebbau",
    "sg:phone":"+41 21 825 11 41",
    "sg:postcode":"1180",
    "sg:province":"Vaud",
    "wof:name":"Hammel Sa",
    "wof:placetype":"venue"
},
  "geometry": {"coordinates":[6.3295588493,46.4619026184],"type":"Point"}
}