{
  "type": "Feature",
  "properties": {
    "iso:country":"CH",
    "sg:address":"Le Petit-marais",
    "sg:city":"Yverdon-les-bains",
    "sg:orig_category":"Gem\u00fcsebau",
    "sg:phone":"+41 24 447 35 35",
    "sg:postcode":"1400",
    "sg:province":"Vaud",
    "wof:name":"Stoll Fr\u00e8res Mara\u00eecher",
    "wof:placetype":"venue"
},
  "geometry": {"coordinates":[6.621035,46.779819],"type":"Point"}
}