{
  "type": "Feature",
  "properties": {
    "iso:country":"CH",
    "sg:address":"Route Cho\u00ebx",
    "sg:city":"Cho\u00ebx",
    "sg:classifiers":[
        {
            "category":"Restaurant",
            "type":"Food & Drink"
        }
    ],
    "sg:phone":"+41 24 471 21 95",
    "sg:postcode":"1871",
    "sg:province":"Valais",
    "wof:name":"Restaurant Du Repos",
    "wof:placetype":"venue"
},
  "geometry": {"coordinates":[6.9656281471,46.2410240173],"type":"Point"}
}