{
  "type": "Feature",
  "properties": {
    "iso:country":"CH",
    "sg:address":"En Bovery Collombey-le-grand 1868 Collombey Case Postale 45",
    "sg:city":"Collombey",
    "sg:orig_category":"Grosshandel mit Erzen U Metallen R\u00fcckgewinnung U Vorbereitung f\u00fcr die Wiederverwertung Recycling",
    "sg:phone":"+41 24 472 72 02",
    "sg:postcode":"1868",
    "sg:province":"Valais",
    "wof:name":"Trottet R\u00e9cuperation Sa",
    "wof:placetype":"venue"
},
  "geometry": {"coordinates":[6.9433250427,46.277961731],"type":"Point"}
}