{
  "type": "Feature",
  "properties": {
    "iso:country":"CH",
    "sg:address":"Schiffl\u00e4nde26",
    "sg:city":"Z\u00fcrich",
    "sg:orig_category":"Advokaturb\u00fcros",
    "sg:phone":"+41 12512828",
    "sg:postcode":"8001",
    "sg:province":"Z\u00fcrich",
    "wof:name":"Martin Rickli Rechtsanwalt",
    "wof:placetype":"venue"
},
  "geometry": {"coordinates":[8.545147,47.368073],"type":"Point"}
}