{
  "type": "Feature",
  "properties": {
    "iso:country":"CH",
    "sg:address":"Riesbachstrasse 52",
    "sg:city":"Z\u00fcrich",
    "sg:orig_category":"Unclassifiable Establishments",
    "sg:phone":"+41 13877600",
    "sg:postcode":"8008",
    "sg:province":"Z\u00fcrich",
    "wof:name":"Atmos Ag",
    "wof:placetype":"venue"
},
  "geometry": {"coordinates":[8.5549974442,47.3583335876],"type":"Point"}
}