{
  "type": "Feature",
  "properties": {
    "iso:country":"CH",
    "sg:address":"Seestrasse 164",
    "sg:city":"Steckborn",
    "sg:orig_category":"Detailhandel mit Sportartikeln",
    "sg:phone":"+41 79 430 59 14",
    "sg:postcode":"8266",
    "sg:province":"Thurgau",
    "wof:name":"J\u00fcrg & Rosmarie Tschiemer Schiffsladen",
    "wof:placetype":"venue"
},
  "geometry": {"coordinates":[8.9778165817,47.6637458801],"type":"Point"}
}