{
  "type": "Feature",
  "properties": {
    "iso:country":"CH",
    "sg:address":"Avenue De Chailly 52",
    "sg:city":"Lausanne",
    "sg:orig_category":"Arztpraxen",
    "sg:phone":"+41 21 213 77 77",
    "sg:postcode":"1012",
    "sg:province":"Vaud",
    "wof:name":"Dr M\u00e9d. Jean-paul Rubin M\u00e9decin Sp\u00e9cialiste Fmh",
    "wof:placetype":"venue"
},
  "geometry": {"coordinates":[6.655912,46.522793],"type":"Point"}
}