{
  "type": "Feature",
  "properties": {
    "iso:country":"CH",
    "sg:address":"Goldackerweg 31",
    "sg:city":"L\u00f6hningen",
    "sg:orig_category":"Herstellung von Konstruktionsteilen, Fertigbauteilen U Ausbauelementen aus Holz",
    "sg:phone":"+41 52 685 23 85",
    "sg:postcode":"8224",
    "sg:province":"Schaffhausen",
    "wof:name":"Walter Z\u00e4une Ag",
    "wof:placetype":"venue"
},
  "geometry": {"coordinates":[8.5484972,47.6989212036],"type":"Point"}
}