{
  "type": "Feature",
  "properties": {
    "iso:country":"CH",
    "sg:address":"In Den Weihern 122",
    "sg:city":"Arisdorf",
    "sg:orig_category":"Sanit\u00e4r U Heizungsinstallation Sanit\u00e4r, Heizungs U L\u00fcftungsinstallation",
    "sg:phone":"+41 61 811 21 29",
    "sg:postcode":"4422",
    "sg:province":"Basel-Landschaft",
    "wof:name":"Urs Itin Feuerungen Ag",
    "wof:placetype":"venue"
},
  "geometry": {"coordinates":[7.7667598724,47.4979286194],"type":"Point"}
}