{
  "type": "Feature",
  "properties": {
    "iso:country":"CH",
    "sg:address":"Aeschbrunnhof 75",
    "sg:city":"Anwil",
    "sg:orig_category":"Detailhandel mit Waren verschiedener Art, Hauptrichtung Nahrungsmittel",
    "sg:phone":"+41 61 991 05 10",
    "sg:postcode":"4469",
    "sg:province":"Basel-Landschaft",
    "wof:name":"Rudolf Speiser Oeko-produkte",
    "wof:placetype":"venue"
},
  "geometry": {"coordinates":[7.9512901306,47.456829071],"type":"Point"}
}