{
  "type": "Feature",
  "properties": {
    "iso:country":"CH",
    "sg:address":"Stationsweg 2",
    "sg:city":"Siebnen",
    "sg:orig_category":"Abbruch U Sprenggewerbe",
    "sg:phone":"+41 55 440 80 93",
    "sg:postcode":"8854",
    "sg:province":"Schwyz",
    "wof:name":"Karl Kamer Abbruchunternehmung",
    "wof:placetype":"venue"
},
  "geometry": {"coordinates":[8.901915,47.1824],"type":"Point"}
}