{
  "type": "Feature",
  "properties": {
    "addr:full":"Letzistr. 20 Villnachern Aargau 5213",
    "addr:housenumber":"20",
    "addr:postcode":"5213",
    "addr:street":"Letzistr.",
    "iso:country":"CH",
    "sg:address":"Letzistr. 20",
    "sg:city":"Villnachern",
    "sg:orig_category":"Ackerbau",
    "sg:phone":"+41 56 441 71 51",
    "sg:postcode":"5213",
    "sg:province":"Aargau",
    "wof:name":"Schneiter Willi Dipl. Agro-ing. Htl",
    "wof:placetype":"venue"
},
  "geometry": {"coordinates":[8.157299,47.468491],"type":"Point"}
}