{
  "type": "Feature",
  "properties": {
    "iso:country":"CH",
    "sg:address":"5037 Muhen. Postfach",
    "sg:city":"Muhen",
    "sg:orig_category":"Sportvereine Ballsport Tennis",
    "sg:phone":"+41 62 723 20 30",
    "sg:postcode":"5037",
    "sg:province":"Aargau",
    "wof:name":"Tennisclub Muhen",
    "wof:placetype":"venue"
},
  "geometry": {"coordinates":[8.0539398193,47.3407707214],"type":"Point"}
}