{
  "type": "Feature",
  "properties": {
    "iso:country":"CH",
    "sg:address":"Stationsweg 5 3627 Heimberg. Postfach 9",
    "sg:city":"Heimberg",
    "sg:orig_category":"Arztpraxen",
    "sg:phone":"+41 27 952 20 01",
    "sg:postcode":"3627",
    "sg:province":"Bern",
    "wof:name":"Dr.med.daniel Eggenschwiler Arzt F.allgemeine Medizin Fmh",
    "wof:placetype":"venue"
},
  "geometry": {"coordinates":[7.87745,46.252312],"type":"Point"}
}