{
  "type": "Feature",
  "properties": {
    "iso:country":"CH",
    "sg:address":"Schw\u00e4galp",
    "sg:city":"Urn\u00e4sch",
    "sg:orig_category":"Seilbahnen",
    "sg:phone":"+41 71 277 99 55",
    "sg:postcode":"9107",
    "sg:province":"Appenzell Ausserrhoden",
    "wof:name":"Luftseilbahn Schw\u00e4galp-s\u00e4ntis",
    "wof:placetype":"venue"
},
  "geometry": {"coordinates":[9.2806816101,47.3161125183],"type":"Point"}
}