{
  "type": "Feature",
  "properties": {
    "addr:full":"Gartenstrasse 19 Richterswil Z\u00fcrich 8805",
    "addr:housenumber":"19",
    "addr:postcode":"8805",
    "addr:street":"Gartenstrasse",
    "iso:country":"CH",
    "sg:address":"Gartenstrasse 19",
    "sg:city":"Richterswil",
    "sg:classifiers":[
        {
            "category":"Wholesale",
            "subcategory":"Plants",
            "type":"Manufacturing & Wholesale Goods"
        }
    ],
    "sg:phone":"+41 17844777",
    "sg:postcode":"8805",
    "sg:province":"Z\u00fcrich",
    "sg:tags":[
        "air-conditioning",
        "fresh-air",
        "supply"
    ],
    "wof:name":"Air-o-clean Ag",
    "wof:placetype":"venue"
},
  "geometry": {"coordinates":[8.708017,47.205795],"type":"Point"}
}