{
  "type": "Feature",
  "properties": {
    "iso:country":"CH",
    "sg:address":"Route De Lully 35",
    "sg:city":"Estavayer-le-lac",
    "sg:classifiers":[
        {
            "category":"Military Area",
            "subcategory":"Air Force Base",
            "type":"Public Place"
        }
    ],
    "sg:phone":"+41 26 663 94 94",
    "sg:postcode":"1470",
    "sg:province":"Fribourg",
    "sg:tags":[
        "grates",
        "louver",
        "directional"
    ],
    "wof:name":"Lamelcolor S.a.",
    "wof:placetype":"venue"
},
  "geometry": {"coordinates":[6.846853,46.841755],"type":"Point"}
}