{
  "type": "Feature",
  "properties": {
    "iso:country":"CH",
    "sg:address":"Strehlgasse 19",
    "sg:city":"Schwyz",
    "sg:orig_category":"Detailhandel mit Waren verschiedener Art, Hauptrichtung Nahrungsmittel",
    "sg:phone":"+41 41 810 14 55",
    "sg:postcode":"6430",
    "sg:province":"Schwyz",
    "wof:name":"Regenbogen Bioladen",
    "wof:placetype":"venue"
},
  "geometry": {"coordinates":[8.655828476,47.0202331543],"type":"Point"}
}