{
  "type": "Feature",
  "properties": {
    "iso:country":"CH",
    "sg:address":"Marktplatz 30 A",
    "sg:city":"Basel",
    "sg:orig_category":"Gesundheitswesen",
    "sg:phone":"+41 32 968 08 29",
    "sg:postcode":"4001",
    "sg:province":"Basel-Stadt",
    "wof:name":"Centre Tomatis La Chaux-de-fonds S\u00e0rl",
    "wof:placetype":"venue"
},
  "geometry": {"coordinates":[6.8310189247,47.1036148071],"type":"Point"}
}