{
  "type": "Feature",
  "properties": {
    "iso:country":"CH",
    "sg:address":"Creux-de-la-terre 43",
    "sg:city":"Del\u00e9mont",
    "sg:orig_category":"Satzherstellung U Reproduktion",
    "sg:phone":"+41 32 365 32 12",
    "sg:postcode":"2800",
    "sg:province":"Jura",
    "wof:name":"Laurent Kohler Layout Express",
    "wof:placetype":"venue"
},
  "geometry": {"coordinates":[7.3333601952,47.3689498901],"type":"Point"}
}