{
  "type": "Feature",
  "properties": {
    "iso:country":"CH",
    "sg:address":"Schinzenhof",
    "sg:city":"Horgen",
    "sg:orig_category":"Kauf U Verkauf von Immobilien auf eigene Rechnung Verwaltung von Immobilien",
    "sg:phone":"+41 17252114",
    "sg:postcode":"8810",
    "sg:province":"Z\u00fcrich",
    "wof:name":"Verwaltungsb\u00fcro Hofmann",
    "wof:placetype":"venue"
},
  "geometry": {"coordinates":[8.599029541,47.2600440979],"type":"Point"}
}