{
  "type": "Feature",
  "properties": {
    "iso:country":"CH",
    "sg:address":"Sonnrain 16 6247 Sch\u00f6tz. Postfach",
    "sg:city":"Sch\u00f6tz",
    "sg:orig_category":"Elektroinstallation",
    "sg:phone":"+41 79 653 44 57",
    "sg:postcode":"6247",
    "sg:province":"Luzern",
    "wof:name":"Peter Hans",
    "wof:placetype":"venue"
},
  "geometry": {"coordinates":[7.9833240509,47.174987793],"type":"Point"}
}