{
  "type": "Feature",
  "properties": {
    "iso:country":"CH",
    "sg:address":"Dorfstrasse 25b",
    "sg:city":"Hindelbank",
    "sg:classifiers":[
        {
            "category":"Social Services",
            "subcategory":"Retirement Home",
            "type":"Services"
        }
    ],
    "sg:phone":"+41 34 411 28 11",
    "sg:postcode":"3324",
    "sg:province":"Bern",
    "sg:tags":[
        "pflegeheime",
        "u",
        "alters"
    ],
    "wof:name":"Alters-& Pflegeheim Brunnenhof",
    "wof:placetype":"venue"
},
  "geometry": {"coordinates":[7.540867,47.046223],"type":"Point"}
}