{
  "type": "Feature",
  "properties": {
    "iso:country":"CH",
    "sg:address":"La Riveraine",
    "sg:city":"St-prex",
    "sg:orig_category":"Erwachsenenbildung U Unterricht",
    "sg:phone":"+41 21 806 17 31",
    "sg:postcode":"1162",
    "sg:province":"Vaud",
    "wof:name":"Executive Training Institute, Edward Charnaud",
    "wof:placetype":"venue"
},
  "geometry": {"coordinates":[6.4576702118,46.4821166992],"type":"Point"}
}