{
  "type": "Feature",
  "properties": {
    "iso:country":"CH",
    "sg:address":"Rue De Moron 6",
    "sg:city":"Montagne-moutier",
    "sg:orig_category":"Interessenvertretungen",
    "sg:postcode":"2740",
    "sg:province":"Bern",
    "wof:name":"Fondation Suzanne Schwab",
    "wof:placetype":"venue"
},
  "geometry": {"coordinates":[7.3578982353,47.2766418457],"type":"Point"}
}