{
  "type": "Feature",
  "properties": {
    "iso:country":"CH",
    "sg:address":"Z\u00fcrcherstrasse 144",
    "sg:city":"Dietikon",
    "sg:orig_category":"Detailhandel mit Musikinstrumenten Detailhandel mit elektrischen Haushalts-,Radio U Fernsehger\u00e4ten s",
    "sg:phone":"+41 17401385",
    "sg:postcode":"8953",
    "sg:province":"Z\u00fcrich",
    "wof:name":"Musikhaus Biedermann Theddy + Co",
    "wof:placetype":"venue"
},
  "geometry": {"coordinates":[8.4136362076,47.3994674683],"type":"Point"}
}