{
  "type": "Feature",
  "properties": {
    "iso:country":"CH",
    "sg:address":"Route Du Pr\u00e9-au-comte 6",
    "sg:city":"Villeneuve",
    "sg:classifiers":[
        {
            "category":"Professional",
            "subcategory":"Computer Services",
            "type":"Services"
        }
    ],
    "sg:phone":"+41 21 967 15 60",
    "sg:postcode":"1844",
    "sg:province":"Vaud",
    "sg:tags":[
        "development",
        "software"
    ],
    "wof:name":"Cds Engineering Sa",
    "wof:placetype":"venue"
},
  "geometry": {"coordinates":[6.9298648834,46.3934364319],"type":"Point"}
}