{
  "type": "Feature",
  "properties": {
    "addr:full":"Allschwilerstrasse 35 Basel Basel-Stadt 4055",
    "addr:housenumber":"35",
    "addr:postcode":"4055",
    "addr:street":"Allschwilerstrasse",
    "iso:country":"CH",
    "sg:address":"Allschwilerstrasse 35",
    "sg:city":"Basel",
    "sg:orig_category":"Bauschreinerei Herstellung von Konstruktionsteilen, Fertigbauteilen U Ausbauelementen aus Holz",
    "sg:phone":"+41 71 278 36 75",
    "sg:postcode":"4055",
    "sg:province":"Basel-Stadt",
    "wof:name":"Tachezy + Vonaesch",
    "wof:placetype":"venue"
},
  "geometry": {"coordinates":[9.322069,47.410488],"type":"Point"}
}