{
  "type": "Feature",
  "properties": {
    "iso:country":"CH",
    "sg:address":"Sch\u00f6nenboden",
    "sg:city":"Wildhaus",
    "sg:orig_category":"Architekturb\u00fcros",
    "sg:phone":"+41 55 442 32 05",
    "sg:postcode":"9658",
    "sg:province":"St. Gallen",
    "wof:name":"Rudolf H\u00f6rner Architekturb\u00fcro",
    "wof:placetype":"venue"
},
  "geometry": {"coordinates":[9.368189,47.205349],"type":"Point"}
}