{
  "type": "Feature",
  "properties": {
    "iso:country":"CH",
    "sg:address":"Wiesstrasse 32",
    "sg:city":"Oberegg",
    "sg:orig_category":"Wirtschafts U Arbeitgeberverb\u00e4nde",
    "sg:postcode":"9413",
    "sg:province":"Appenzell Innerhoden",
    "wof:name":"Schweizerischer Viehh\u00e4ndlerverband Svv",
    "wof:placetype":"venue"
},
  "geometry": {"coordinates":[9.552312851,47.426815033],"type":"Point"}
}