{
  "type": "Feature",
  "properties": {
    "iso:country":"CH",
    "sg:address":"H\u00f4tel-de-ville",
    "sg:city":"Attalens",
    "sg:classifiers":[
        {
            "category":"Travel",
            "subcategory":"Hotels & Motels",
            "type":"Entertainment"
        }
    ],
    "sg:postcode":"1616",
    "sg:province":"Fribourg",
    "sg:tags":[
        "hotels",
        "mit",
        "restaurant"
    ],
    "wof:name":"Vauthey G\u00e9rard",
    "wof:placetype":"venue"
},
  "geometry": {"coordinates":[6.8493890762,46.5091896057],"type":"Point"}
}