{
  "type": "Feature",
  "properties": {
    "iso:country":"CH",
    "sg:address":"Seestrasse 25",
    "sg:city":"Z\u00fcrich",
    "sg:orig_category":"Detailhandel mit Radio U Fernsehger\u00e4ten",
    "sg:phone":"+41 12021522",
    "sg:postcode":"8002",
    "sg:province":"Z\u00fcrich",
    "wof:name":"Rediffusion Ag",
    "wof:placetype":"venue"
},
  "geometry": {"coordinates":[8.5315589905,47.3637008667],"type":"Point"}
}