{
  "type": "Feature",
  "properties": {
    "iso:country":"CH",
    "sg:address":"Gos Rue Albert- 7 1206 Gen\u00e8ve. Postfach",
    "sg:city":"Gen\u00e8ve",
    "sg:orig_category":"Non-Classified Establishments",
    "sg:postcode":"1206",
    "sg:province":"Gen\u00e8ve",
    "wof:name":"Learnstar Gmbh",
    "wof:placetype":"venue"
},
  "geometry": {"coordinates":[9.3142166138,47.4091873169],"type":"Point"}
}