{
  "type": "Feature",
  "properties": {
    "iso:country":"CH",
    "sg:address":"Eichenweg 16",
    "sg:city":"Langenthal",
    "sg:orig_category":"Grosshandel mit Maschinen U Ausr\u00fcstungen",
    "sg:phone":"+41 62 922 80 20",
    "sg:postcode":"4900",
    "sg:province":"Bern",
    "wof:name":"\u00d6stling Markiersysteme Ag",
    "wof:placetype":"venue"
},
  "geometry": {"coordinates":[7.7817869186,47.2247543335],"type":"Point"}
}