{
  "type": "Feature",
  "properties": {
    "iso:country":"CH",
    "sg:address":"Riond-bosson 13",
    "sg:city":"Morges",
    "sg:classifiers":[
        {
            "category":"Home & Garden",
            "subcategory":"Hardware",
            "type":"Retail Goods"
        }
    ],
    "sg:phone":"+41 21 804 18 85",
    "sg:postcode":"1110",
    "sg:province":"Vaud",
    "sg:tags":[
        "bellow"
    ],
    "wof:name":"Vogel-bucher Sa",
    "wof:placetype":"venue"
},
  "geometry": {"coordinates":[6.485284,46.503094],"type":"Point"}
}