{
  "type": "Feature",
  "properties": {
    "addr:full":"Hubel 131 Unterlangenegg Bern 3614",
    "addr:housenumber":"131",
    "addr:postcode":"3614",
    "addr:street":"Hubel",
    "iso:country":"CH",
    "sg:address":"Hubel 131",
    "sg:city":"Unterlangenegg",
    "sg:orig_category":"Allgemeiner Hoch U Tiefbau",
    "sg:postcode":"3614",
    "sg:province":"Bern",
    "wof:name":"Baugesch\u00e4ft Felder J.",
    "wof:placetype":"venue"
},
  "geometry": {"coordinates":[8.31951,47.128242],"type":"Point"}
}