{
  "type": "Feature",
  "properties": {
    "iso:country":"CH",
    "sg:address":"August M\u00fcllerstrasse 7",
    "sg:city":"Adliswil",
    "sg:orig_category":"Interessenvertretungen U sonstige Vereinigungen Sportvereine",
    "sg:phone":"+41 17101342",
    "sg:postcode":"8134",
    "sg:province":"Z\u00fcrich",
    "wof:name":"Schweizerischer Rollsport-verband Srv",
    "wof:placetype":"venue"
},
  "geometry": {"coordinates":[8.5190505981,47.3219528198],"type":"Point"}
}