{
  "type": "Feature",
  "properties": {
    "iso:country":"CH",
    "sg:address":"Altdorfstrasse",
    "sg:city":"Vitznau",
    "sg:orig_category":"Herstellung von Metallkonstruktionen",
    "sg:phone":"+41 41 397 13 50",
    "sg:postcode":"6354",
    "sg:province":"Luzern",
    "wof:name":"Theiler Team Gmbh",
    "wof:placetype":"venue"
},
  "geometry": {"coordinates":[8.4853210449,47.0092887878],"type":"Point"}
}