{
  "type": "Feature",
  "properties": {
    "iso:country":"CH",
    "sg:address":"Via San Gottardo 71",
    "sg:city":"Massagno",
    "sg:orig_category":"Zahnarztpraxen",
    "sg:phone":"+41 91 966 25 63",
    "sg:postcode":"6900",
    "sg:province":"Ticino",
    "wof:name":"Dott. Med. Dent. Andr\u00e9 Staub Dentista",
    "wof:placetype":"venue"
},
  "geometry": {"coordinates":[8.9468727112,46.0120697021],"type":"Point"}
}