{
  "type": "Feature",
  "properties": {
    "iso:country":"CH",
    "sg:address":"Yverdon Route D' 20",
    "sg:city":"Estavayer-le-lac",
    "sg:orig_category":"Saunas, Solarien, Fitnesszentren U \u00e4hnliches",
    "sg:postcode":"1470",
    "sg:province":"Fribourg",
    "wof:name":"Transcom Estavayer-le-lac Sa",
    "wof:placetype":"venue"
},
  "geometry": {"coordinates":[6.8482699394,46.8487892151],"type":"Point"}
}