{
  "type": "Feature",
  "properties": {
    "iso:country":"CH",
    "sg:address":"Kirchstrasse 7",
    "sg:city":"Wettingen",
    "sg:orig_category":"Herstellung von Metallerzeugnissen ohne Maschinenbau Maschinenbau",
    "sg:phone":"+41 56 426 66 32",
    "sg:postcode":"5430",
    "sg:province":"Aargau",
    "wof:name":"Schmid & Sp\u00f6rri Maschinen Und Apparatebau Ag",
    "wof:placetype":"venue"
},
  "geometry": {"coordinates":[8.3302307129,47.4664154053],"type":"Point"}
}