{
  "type": "Feature",
  "properties": {
    "iso:country":"CH",
    "sg:address":"Quartier Des Pugessies 4",
    "sg:city":"Yverdon-les-bains",
    "sg:orig_category":"Grosshandel mit Getr\u00e4nken",
    "sg:postcode":"1400",
    "sg:province":"Vaud",
    "wof:name":"Primovin, J.-d. Pilloud",
    "wof:placetype":"venue"
},
  "geometry": {"coordinates":[6.6408958435,46.7731933594],"type":"Point"}
}