{
  "type": "Feature",
  "properties": {
    "iso:country":"CH",
    "sg:address":"Landstrasse 16",
    "sg:city":"Wettingen",
    "sg:classifiers":[
        {
            "category":"Retail",
            "subcategory":"Event Space",
            "type":"Services"
        }
    ],
    "sg:phone":"+41 56 426 23 24",
    "sg:postcode":"5430",
    "sg:province":"Aargau",
    "sg:tags":[
        "telecommunication"
    ],
    "wof:name":"Gmw W. Messerli",
    "wof:placetype":"venue"
},
  "geometry": {"coordinates":[8.3183326721,47.4693946838],"type":"Point"}
}