{
  "type": "Feature",
  "properties": {
    "iso:country":"CH",
    "sg:address":"Habsburgerstrasse 23",
    "sg:city":"Luzern",
    "sg:orig_category":"Unclassifiable Establishments",
    "sg:phone":"+41 41 210 64 41",
    "sg:postcode":"6003",
    "sg:province":"Luzern",
    "wof:name":"Arlecchino Luzern",
    "wof:placetype":"venue"
},
  "geometry": {"coordinates":[8.307267189,47.0467529297],"type":"Point"}
}