{
  "type": "Feature",
  "properties": {
    "iso:country":"CH",
    "sg:address":"Viaduktstrasse 8",
    "sg:city":"Pratteln",
    "sg:orig_category":"Freizeit, Sport",
    "sg:phone":"+41 61 821 47 60",
    "sg:postcode":"4133",
    "sg:province":"Basel-Landschaft",
    "wof:name":"Bogensport Von Arx & Rohrer",
    "wof:placetype":"venue"
},
  "geometry": {"coordinates":[7.69991,47.522709],"type":"Point"}
}