{
  "type": "Feature",
  "properties": {
    "iso:country":"CH",
    "sg:address":"Schlossweg 14",
    "sg:city":"L\u00e4ufelfingen",
    "sg:orig_category":"Detailhandel mit Geschenkartikeln U Souvenirs",
    "sg:phone":"+41 62 299 19 20",
    "sg:postcode":"4448",
    "sg:province":"Basel-Landschaft",
    "wof:name":"Kunstl\u00e4deli Trinidad Fricker",
    "wof:placetype":"venue"
},
  "geometry": {"coordinates":[7.8553352356,47.3976097107],"type":"Point"}
}