{
  "type": "Feature",
  "properties": {
    "addr:full":"Aegertstrasse 12 Dietlikon Z\u00fcrich 8305",
    "addr:housenumber":"12",
    "addr:postcode":"8305",
    "addr:street":"Aegertstrasse",
    "iso:country":"CH",
    "sg:address":"Aegertstrasse 12",
    "sg:city":"Dietlikon",
    "sg:orig_category":"Allgemeiner Hoch U Tiefbau",
    "sg:phone":"+41 71 277 00 21",
    "sg:postcode":"8305",
    "sg:province":"Z\u00fcrich",
    "wof:name":"Steiner Rolf Gmbh Ausf\u00fchrung V. Umbauten, Isolationen, Renovationen. Warenhandel Usw",
    "wof:placetype":"venue"
},
  "geometry": {"coordinates":[9.33633,47.40992],"type":"Point"}
}