{
  "type": "Feature",
  "properties": {
    "iso:country":"CH",
    "sg:address":"Contrada Alla Cantina 6934 Bioggio. Postfach",
    "sg:city":"Bioggio",
    "sg:orig_category":"Vermietung U Verpachtung von eigenen Immobilien",
    "sg:postcode":"6934",
    "sg:province":"Ticino",
    "wof:name":"Pranemo Sa",
    "wof:placetype":"venue"
},
  "geometry": {"coordinates":[8.9082450867,46.0152549744],"type":"Point"}
}