{
  "type": "Feature",
  "properties": {
    "iso:country":"CH",
    "sg:address":"Rue Rainer-maria-rilke",
    "sg:city":"Sierre",
    "sg:orig_category":"Unclassifiable Establishments",
    "sg:postcode":"3960",
    "sg:province":"Valais",
    "wof:name":"S. B\u00fcrge Und Partner",
    "wof:placetype":"venue"
},
  "geometry": {"coordinates":[8.7793397903,47.4662590027],"type":"Point"}
}