{
  "type": "Feature",
  "properties": {
    "iso:country":"CH",
    "sg:address":"Place De La Gare 4 1003 Lausanne Case Postale 804",
    "sg:city":"Lausanne",
    "sg:orig_category":"Grosshandel mit B\u00fcromaschinen Grosshandel mit Datenverarbeitungsger\u00e4ten",
    "sg:phone":"+41 22 793 83 20",
    "sg:postcode":"1001",
    "sg:province":"Vaud",
    "wof:name":"Gs Informatique",
    "wof:placetype":"venue"
},
  "geometry": {"coordinates":[6.1190571785,46.1903877258],"type":"Point"}
}