{
  "type": "Feature",
  "properties": {
    "iso:country":"CH",
    "sg:address":"Habsburgerstrasse 33",
    "sg:city":"Luzern",
    "sg:orig_category":"Datenverarbeitungsdienste Softwareentwicklung U beratung",
    "sg:phone":"+41 41 227 11 33",
    "sg:postcode":"6003",
    "sg:province":"Luzern",
    "wof:name":"Performa Gmbh",
    "wof:placetype":"venue"
},
  "geometry": {"coordinates":[8.30611,47.046257],"type":"Point"}
}