{
  "type": "Feature",
  "properties": {
    "addr:full":"Z\u00fcrich Z\u00fcrich 8704",
    "addr:postcode":"8704",
    "iso:country":"CH",
    "sg:city":"Z\u00fcrich",
    "sg:orig_category":"Freizeit, Sport",
    "sg:postcode":"8704",
    "sg:province":"Z\u00fcrich",
    "wof:name":"Bildergalerie Von Top Bodybuilderinnen",
    "wof:placetype":"venue"
},
  "geometry": {"coordinates":[8.613538,47.286198],"type":"Point"}
}