{
  "type": "Feature",
  "properties": {
    "iso:country":"CH",
    "sg:address":"Bitzistrasse 2",
    "sg:city":"Stans",
    "sg:orig_category":"Detailhandel mit Lederwaren U Reiseartikeln Detailhandel mit Textilien",
    "sg:phone":"+41 34 402 19 39",
    "sg:postcode":"6370",
    "sg:province":"Nidwalden",
    "wof:name":"Lehmann M\u00f6bel Interieur Ag Wasserbettcenter",
    "wof:placetype":"venue"
},
  "geometry": {"coordinates":[7.757589817,46.9491271973],"type":"Point"}
}