{
  "type": "Feature",
  "properties": {
    "iso:country":"CH",
    "sg:address":"Industriestrasse 2",
    "sg:city":"Hitzkirch",
    "sg:orig_category":"Pensionskassen",
    "sg:phone":"+41 41 917 01 85",
    "sg:postcode":"6285",
    "sg:province":"Luzern",
    "wof:name":"Personalvorsorgestiftung Der Steiner Computer Ag",
    "wof:placetype":"venue"
},
  "geometry": {"coordinates":[8.258439064,47.2247810364],"type":"Point"}
}