{
  "type": "Feature",
  "properties": {
    "iso:country":"CH",
    "sg:address":"Mythencenterstrasse 16",
    "sg:city":"Ibach",
    "sg:orig_category":"Detailhandel mit Waren verschiedener Art, Hauptrichtung Nahrungsmittel Fachdetailhandel mit Nahrungs",
    "sg:phone":"+41 17132026",
    "sg:postcode":"6438",
    "sg:province":"Schwyz",
    "wof:name":"Sergio Manuzzi Fr\u00fcchte & Delikatessen",
    "wof:placetype":"venue"
},
  "geometry": {"coordinates":[8.5404014587,47.2887573242],"type":"Point"}
}