{
  "type": "Feature",
  "properties": {
    "iso:country":"CH",
    "sg:address":"Boulevard De P\u00e9rolles 2 1700 Fribourg Case Postale 23",
    "sg:city":"Fribourg",
    "sg:classifiers":[
        {
            "category":"Professional",
            "subcategory":"Employment Agencies",
            "type":"Services"
        }
    ],
    "sg:phone":"+41 26 347 19 19",
    "sg:postcode":"1701",
    "sg:province":"Fribourg",
    "sg:tags":[
        "personal",
        "u",
        "stellenvermittlung"
    ],
    "wof:name":"Adecco Ressources Humaines S.a.",
    "wof:placetype":"venue"
},
  "geometry": {"coordinates":[7.1516289711,46.8023262024],"type":"Point"}
}