{
  "type": "Feature",
  "properties": {
    "iso:country":"CH",
    "sg:address":"M\u00fcnsterberg 1",
    "sg:city":"Basel",
    "sg:orig_category":"Ingenieurb\u00fcros Umwelttechnik and \u00d6kologie Ingenieurb\u00fcros Wasserbau",
    "sg:phone":"+41 61 283 12 55",
    "sg:postcode":"4051",
    "sg:province":"Basel-Stadt",
    "wof:name":"Markus Kn\u00f6pfli Knoepfli Process Engineering",
    "wof:placetype":"venue"
},
  "geometry": {"coordinates":[7.5909328461,47.555141449],"type":"Point"}
}