{
  "type": "Feature",
  "properties": {
    "iso:country":"CH",
    "sg:address":"Austrasse 25",
    "sg:city":"Flawil",
    "sg:orig_category":"Herstellung von sonstigen Maschinen f\u00fcr unspezifische Verwendung",
    "sg:postcode":"9230",
    "sg:province":"St. Gallen",
    "wof:name":"Ff Feuerl\u00f6scher Flawil H\u00fcni Gerhard",
    "wof:placetype":"venue"
},
  "geometry": {"coordinates":[9.1847896576,47.4101753235],"type":"Point"}
}