{
  "type": "Feature",
  "properties": {
    "iso:country":"CH",
    "sg:address":"Rue Rainer Maria Rilke 4 3960 Sierre Case Postale 772",
    "sg:city":"Sierre",
    "sg:orig_category":"Architektur U Ingenieurb\u00fcros Architekturb\u00fcros",
    "sg:phone":"+41 32 931 59 62",
    "sg:postcode":"3960",
    "sg:province":"Valais",
    "wof:name":"Atelier D'architecture Partners, Schwab Et R\u00f6thlisberger S\u00e0rl",
    "wof:placetype":"venue"
},
  "geometry": {"coordinates":[6.758619,47.061653],"type":"Point"}
}