{
  "type": "Feature",
  "properties": {
    "iso:country":"CH",
    "sg:address":"Niederhaslistrasse 184",
    "sg:city":"Watt",
    "sg:orig_category":"Elektroinstallation",
    "sg:phone":"+41 18400802",
    "sg:postcode":"8105",
    "sg:province":"Z\u00fcrich",
    "wof:name":"Markus Patscheider Elektroinstallationen",
    "wof:placetype":"venue"
},
  "geometry": {"coordinates":[8.4844799042,47.4503898621],"type":"Point"}
}