{
  "type": "Feature",
  "properties": {
    "iso:country":"CH",
    "sg:address":"Badenerstrasse 4 8104 Weiningen Zh. Postfach",
    "sg:city":"Dietikon",
    "sg:orig_category":"Berufsbildende weiterf\u00fchrende Schulen",
    "sg:postcode":"8953",
    "sg:province":"Z\u00fcrich",
    "wof:name":"Boge Ag",
    "wof:placetype":"venue"
},
  "geometry": {"coordinates":[8.433789,47.419689],"type":"Point"}
}