{
  "type": "Feature",
  "properties": {
    "iso:country":"CH",
    "sg:address":"Weinbergweg 2",
    "sg:city":"W\u00fcrenlingen",
    "sg:orig_category":"Sportvereine Ballsport Handball",
    "sg:phone":"+41 56 281 14 52",
    "sg:postcode":"5303",
    "sg:province":"Aargau",
    "wof:name":"Handballclub Etv W\u00fcrenlingen",
    "wof:placetype":"venue"
},
  "geometry": {"coordinates":[8.2596206665,47.5359458923],"type":"Point"}
}