{
  "type": "Feature",
  "properties": {
    "iso:country":"CH",
    "sg:address":"Lindachstrasse 66",
    "sg:city":"Kirchlindach",
    "sg:orig_category":"Bauspenglerei Sanit\u00e4r, Heizungs U L\u00fcftungsinstallation",
    "sg:phone":"+41 31 829 01 48",
    "sg:postcode":"3038",
    "sg:province":"Bern",
    "wof:name":"Gebr. Marthaler Ag",
    "wof:placetype":"venue"
},
  "geometry": {"coordinates":[7.424039,47.002483],"type":"Point"}
}