{
  "type": "Feature",
  "properties": {
    "iso:country":"CH",
    "sg:address":"Coll\u00e8ge",
    "sg:city":"Juriens",
    "sg:classifiers":[
        {
            "category":"Banks & Credit Unions",
            "subcategory":"Bank",
            "type":"Services"
        }
    ],
    "sg:phone":"+41 24 453 12 52",
    "sg:postcode":"1326",
    "sg:province":"Vaud",
    "wof:name":"Raiffeisen",
    "wof:placetype":"venue"
},
  "geometry": {"coordinates":[6.450215,46.691341],"type":"Point"}
}