{
  "type": "Feature",
  "properties": {
    "iso:country":"CH",
    "sg:address":"Juraweg 29 4852 Rothrist. Postfach",
    "sg:city":"Rothrist",
    "sg:orig_category":"Herstellung von Maschinen f\u00fcr die Nahrungsmittel, Getr\u00e4nkeherstellung U die Tabakverarbeitung Herste",
    "sg:phone":"+41 62 794 33 45",
    "sg:postcode":"4852",
    "sg:province":"Aargau",
    "wof:name":"Rewi Maschinenfabrik Gmbh",
    "wof:placetype":"venue"
},
  "geometry": {"coordinates":[7.8794298172,47.3082885742],"type":"Point"}
}