{
  "type": "Feature",
  "properties": {
    "iso:country":"CH",
    "sg:address":"Steinerbergstrasse 54",
    "sg:city":"Goldau",
    "sg:orig_category":"Handelsvermittlung U Grosshandel",
    "sg:phone":"+41 41 855 49 22",
    "sg:postcode":"6410",
    "sg:province":"Schwyz",
    "wof:name":"Nussbaumer & Suter Meliordepot & Landesprodukte",
    "wof:placetype":"venue"
},
  "geometry": {"coordinates":[8.5585107803,47.0526275635],"type":"Point"}
}