{
  "type": "Feature",
  "properties": {
    "iso:country":"CH",
    "sg:address":"Pr\u00e9-bouvier Rue Du 8-10",
    "sg:city":"Satigny",
    "sg:orig_category":"Technische, physikalische U chemische Untersuchung",
    "sg:postcode":"1242",
    "sg:province":"Gen\u00e8ve",
    "wof:name":"Leuzinger Yves, Natura Etude En Biologie Appliqu\u00e9e",
    "wof:placetype":"venue"
},
  "geometry": {"coordinates":[7.0831661224,47.2244720459],"type":"Point"}
}