{
  "type": "Feature",
  "properties": {
    "addr:full":"Largo Mario Soldini 1 Mendrisio Ticino 6850",
    "addr:housenumber":"1",
    "addr:postcode":"6850",
    "addr:street":"Largo Mario Soldini",
    "iso:country":"CH",
    "sg:address":"Largo Mario Soldini 1",
    "sg:city":"Mendrisio",
    "sg:classifiers":[
        {
            "category":"Bars & Pubs",
            "type":"Food & Drink"
        }
    ],
    "sg:phone":"+41 91 646 18 98",
    "sg:postcode":"6850",
    "sg:province":"Ticino",
    "wof:name":"Bar Colonne",
    "wof:placetype":"venue"
},
  "geometry": {"coordinates":[8.989305,45.869877],"type":"Point"}
}