{
  "type": "Feature",
  "properties": {
    "iso:country":"CH",
    "sg:address":"Bottigenstrasse 2 3000 Bern. Postfach",
    "sg:city":"Bern",
    "sg:orig_category":"Fachdetailhandel in Verkaufsr\u00e4umen",
    "sg:postcode":"3003",
    "sg:province":"Bern",
    "wof:name":"Hofer Inh. Scarcia-hofer K.",
    "wof:placetype":"venue"
},
  "geometry": {"coordinates":[7.38996315,46.9399795532],"type":"Point"}
}