{
  "type": "Feature",
  "properties": {
    "iso:country":"CH",
    "sg:address":"Unter-kapf 5",
    "sg:city":"Emmenbr\u00fccke",
    "sg:orig_category":"Verlagsgewerbe",
    "sg:phone":"+41 41 280 00 47",
    "sg:postcode":"6020",
    "sg:province":"Luzern",
    "wof:name":"Gabrielle Bl\u00e4ttler Verlag",
    "wof:placetype":"venue"
},
  "geometry": {"coordinates":[8.2783231735,47.0916175842],"type":"Point"}
}