{
  "type": "Feature",
  "properties": {
    "iso:country":"CH",
    "sg:address":"Carl B\u00f6ckli-weg 1 9410 Heiden. Postfach 262",
    "sg:city":"Heiden",
    "sg:orig_category":"Verlagsgewerbe Werbevermittlung",
    "sg:phone":"+41 71 898 80 11",
    "sg:postcode":"9410",
    "sg:province":"Appenzell Ausserrhoden",
    "wof:name":"Publica-press Public Relations Ag",
    "wof:placetype":"venue"
},
  "geometry": {"coordinates":[9.5318078995,47.4467735291],"type":"Point"}
}