{
  "type": "Feature",
  "properties": {
    "iso:country":"CH",
    "sg:address":"Siewerdtstrasse 25 8050 Z\u00fcrich. Postfach",
    "sg:city":"Z\u00fcrich",
    "sg:orig_category":"Elektroinstallation Herstellung von sonstigen elektrischen Ausr\u00fcstungen",
    "sg:phone":"+41 13158787",
    "sg:postcode":"8050",
    "sg:province":"Z\u00fcrich",
    "wof:name":"Bischofberger Ag, Elektrotechnische Anlagen",
    "wof:placetype":"venue"
},
  "geometry": {"coordinates":[8.5499095917,47.4123497009],"type":"Point"}
}