{
  "type": "Feature",
  "properties": {
    "iso:country":"CH",
    "sg:address":"Bachtelweg 9",
    "sg:city":"Volketswil",
    "sg:orig_category":"Detailhandel mit Schuhen U Lederwaren Handelsvermittlung von Textilien, Bekleidung, Schuhen U Lederw",
    "sg:phone":"+41 19972045",
    "sg:postcode":"8604",
    "sg:province":"Z\u00fcrich",
    "wof:name":"Silma Consulting Vallese Maurizio",
    "wof:placetype":"venue"
},
  "geometry": {"coordinates":[8.6813697815,47.3901672363],"type":"Point"}
}