{
  "type": "Feature",
  "properties": {
    "iso:country":"CH",
    "sg:address":"Hofwiesenstrasse 267 8000 Z\u00fcrich. Postfach 8050 Z\u00fcrich",
    "sg:city":"Zust",
    "sg:orig_category":"Herstellung von Radio U Fernsehger\u00e4ten sowie phono U videotechnischen Ger\u00e4ten",
    "sg:postcode":"50",
    "wof:name":"Audio Art Gmbh",
    "wof:placetype":"venue"
},
  "geometry": {"coordinates":[8.5378417969,47.4066925049],"type":"Point"}
}