{
  "type": "Feature",
  "properties": {
    "iso:country":"CH",
    "sg:address":"Centro Commerciale Contone 1",
    "sg:city":"Contone",
    "sg:orig_category":"Vermietung U Verpachtung von eigenen Immobilien",
    "sg:postcode":"6594",
    "sg:province":"Ticino",
    "wof:name":"La Rotonda Sa",
    "wof:placetype":"venue"
},
  "geometry": {"coordinates":[8.9260749817,46.148525238],"type":"Point"}
}