{
  "type": "Feature",
  "properties": {
    "iso:country":"CH",
    "sg:address":"Hadlaubstrasse 40",
    "sg:city":"Z\u00fcrich",
    "sg:orig_category":"Sportvereine Ballsport Handball",
    "sg:phone":"+41 13619775",
    "sg:postcode":"8044",
    "sg:province":"Z\u00fcrich",
    "wof:name":"Handballclub Z\u00fcrcher Sc",
    "wof:placetype":"venue"
},
  "geometry": {"coordinates":[8.5542221069,47.3836364746],"type":"Point"}
}