{
  "type": "Feature",
  "properties": {
    "iso:country":"CH",
    "sg:address":"Langensandstrasse 91 6005 Luzern. Postfach",
    "sg:city":"Luzern",
    "sg:orig_category":"Instandhaltung U Reparatur von Automobilen",
    "sg:phone":"+41 33 676 14 70",
    "sg:postcode":"6003",
    "sg:province":"Luzern",
    "wof:name":"Garage Rentsch",
    "wof:placetype":"venue"
},
  "geometry": {"coordinates":[7.6830301285,46.6123580933],"type":"Point"}
}