{
  "type": "Feature",
  "properties": {
    "iso:country":"CH",
    "sg:address":"Avenue De Rumine 20 1005 Lausanne. Postfach",
    "sg:city":"Lausanne",
    "sg:orig_category":"Versicherungen Generalagenturen",
    "sg:phone":"+41 22 300 11 47",
    "sg:postcode":"1001",
    "sg:province":"Vaud",
    "wof:name":"Yves Jacquesson Agence G\u00e9n\u00e9rale",
    "wof:placetype":"venue"
},
  "geometry": {"coordinates":[6.14204216,46.1858139038],"type":"Point"}
}