{
  "type": "Feature",
  "properties": {
    "iso:country":"CH",
    "sg:address":"Luzernerstrasse 13",
    "sg:city":"Hitzkirch",
    "sg:orig_category":"Non-Classified Establishments",
    "sg:postcode":"6285",
    "sg:province":"Luzern",
    "wof:name":"Winterthur Versicherungen Hauptagentur Hitzkirchertal Josef Lang-beeler",
    "wof:placetype":"venue"
},
  "geometry": {"coordinates":[8.2640419006,47.2234992981],"type":"Point"}
}