{
  "type": "Feature",
  "properties": {
    "iso:country":"CH",
    "sg:address":"7312",
    "sg:city":"Pf\u00e4fers",
    "sg:orig_category":"Vorschulen, Kinderg\u00e4rten",
    "sg:postcode":"7312",
    "sg:province":"St. Gallen",
    "wof:name":"Kindergarten Linde",
    "wof:placetype":"venue"
},
  "geometry": {"coordinates":[9.5100097656,46.9865913391],"type":"Point"}
}