{
  "type": "Feature",
  "properties": {
    "iso:country":"CH",
    "sg:address":"Rue De La Tuilerie 1",
    "sg:city":"Court\u00e9telle",
    "sg:orig_category":"Sportvereine Velo Rad-& Motorfahrer-Bund SRB",
    "sg:postcode":"2852",
    "sg:province":"Jura",
    "wof:name":"V\u00e9lo-club La P\u00e9dale",
    "wof:placetype":"venue"
},
  "geometry": {"coordinates":[7.3200011253,47.3333816528],"type":"Point"}
}