{
  "type": "Feature",
  "properties": {
    "iso:country":"CH",
    "sg:address":"Via Peri 11",
    "sg:city":"Lugano",
    "sg:orig_category":"Detailhandel mit M\u00f6beln U Haushaltsgegenst\u00e4nden",
    "sg:phone":"+41 91 922 91 71",
    "sg:postcode":"6900",
    "sg:province":"Ticino",
    "wof:name":"G.a. Decorart Sa",
    "wof:placetype":"venue"
},
  "geometry": {"coordinates":[8.9505815506,46.0058631897],"type":"Point"}
}