{
  "type": "Feature",
  "properties": {
    "iso:country":"CH",
    "sg:address":"Adlerstrasse 31 4052 Basel. Postfach",
    "sg:city":"Basel",
    "sg:orig_category":"Sonstiger Grosshandel",
    "sg:phone":"+41 61 311 75 65",
    "sg:postcode":"4051",
    "sg:province":"Basel-Stadt",
    "wof:name":"Martin Metzger-importagentur Importagentur F\u00fcr Waren Aller Art",
    "wof:placetype":"venue"
},
  "geometry": {"coordinates":[7.6108198166,47.5464401245],"type":"Point"}
}