{
  "type": "Feature",
  "properties": {
    "iso:country":"CH",
    "sg:address":"Grand-rue 54",
    "sg:city":"Morges",
    "sg:orig_category":"Museen",
    "sg:phone":"+41 21 801 26 47",
    "sg:postcode":"1110",
    "sg:province":"Vaud",
    "wof:name":"Mus\u00e9e Alexis Forel",
    "wof:placetype":"venue"
},
  "geometry": {"coordinates":[6.498213768,46.5091972351],"type":"Point"}
}