{
  "type": "Feature",
  "properties": {
    "iso:country":"CH",
    "sg:address":"Rue De Pierre-pertuis 25",
    "sg:city":"Tavannes",
    "sg:orig_category":"Sanit\u00e4r U Heizungsinstallation Sanit\u00e4rinstallation",
    "sg:phone":"+41 32 481 25 85",
    "sg:postcode":"2710",
    "sg:province":"Bern",
    "wof:name":"Liechti & Cie Inst.sanitaires & Chauffages",
    "wof:placetype":"venue"
},
  "geometry": {"coordinates":[7.1972489357,47.2179946899],"type":"Point"}
}