{
  "type": "Feature",
  "properties": {
    "iso:country":"CH",
    "sg:address":"Zentralstrasse 27 2502 Biel/bienne. Postfach 1036",
    "sg:city":"Biel/bienne",
    "sg:orig_category":"Detailhandel mit M\u00f6beln U Haushaltsgegenst\u00e4nden Detailhandel mit Teppichen",
    "sg:phone":"+41 32 322 52 31",
    "sg:postcode":"2501",
    "sg:province":"Bern",
    "wof:name":"Brodbeck Ag",
    "wof:placetype":"venue"
},
  "geometry": {"coordinates":[7.2465372086,47.1370010376],"type":"Point"}
}