{
  "type": "Feature",
  "properties": {
    "iso:country":"CH",
    "sg:address":"S\u00f6\u00f6ggen",
    "sg:city":"Quarten",
    "sg:orig_category":"RESTAURANTS: TEA-ROOMS",
    "sg:postcode":"8883",
    "sg:province":"St. Gallen",
    "wof:name":"Zeller-meier Josef",
    "wof:placetype":"venue"
},
  "geometry": {"coordinates":[9.2411851883,47.1078948975],"type":"Point"}
}