{
  "type": "Feature",
  "properties": {
    "iso:country":"CH",
    "sg:address":"Rue Des Moulins 56bis",
    "sg:city":"Yverdon-les-bains",
    "sg:orig_category":"Sportvereine Unihockey",
    "sg:phone":"+41 24 426 14 01",
    "sg:postcode":"1400",
    "sg:province":"Vaud",
    "wof:name":"Uh Yverdon",
    "wof:placetype":"venue"
},
  "geometry": {"coordinates":[6.6347379684,46.776512146],"type":"Point"}
}