{
  "type": "Feature",
  "properties": {
    "iso:country":"CH",
    "sg:address":"Ebnaterstrasse 136",
    "sg:city":"Wattwil",
    "sg:classifiers":[
        {
            "category":"Restaurant",
            "type":"Food & Drink"
        }
    ],
    "sg:phone":"+41 71 988 13 44",
    "sg:postcode":"9630",
    "sg:province":"St. Gallen",
    "wof:name":"Restaurant Krone",
    "wof:placetype":"venue"
},
  "geometry": {"coordinates":[9.0972385406,47.2918167114],"type":"Point"}
}