{
  "type": "Feature",
  "properties": {
    "iso:country":"CH",
    "sg:address":"Landstrasse",
    "sg:city":"Gebenstorf",
    "sg:orig_category":"Finanzierungsinstitutionen",
    "sg:postcode":"5412",
    "sg:province":"Aargau",
    "wof:name":"Vesna-finanz Cagalj Vladimir",
    "wof:placetype":"venue"
},
  "geometry": {"coordinates":[8.2449941635,47.4886703491],"type":"Point"}
}