{
  "type": "Feature",
  "properties": {
    "iso:country":"CH",
    "sg:address":"Freiestrasse 65",
    "sg:city":"Z\u00fcrich",
    "sg:classifiers":[
        {
            "category":"Social Services",
            "subcategory":"Retirement Home",
            "type":"Services"
        }
    ],
    "sg:phone":"+41 34 435 12 34",
    "sg:postcode":"8032",
    "sg:province":"Z\u00fcrich",
    "sg:tags":[
        "pflegeheime",
        "u",
        "alters"
    ],
    "wof:name":"Weimatt Altersheim",
    "wof:placetype":"venue"
},
  "geometry": {"coordinates":[7.748954,47.06142],"type":"Point"}
}