{
  "type": "Feature",
  "properties": {
    "iso:country":"CH",
    "sg:address":"Rue Du Bon-port 2",
    "sg:city":"Territet-veytaux",
    "sg:orig_category":"RESTAURANTS: TEA-ROOMS",
    "sg:postcode":"1820",
    "sg:province":"Vaud",
    "wof:name":"Restaurant Le Postillon, Wirthner & Co",
    "wof:placetype":"venue"
},
  "geometry": {"coordinates":[8.2027425766,46.4432945251],"type":"Point"}
}