{
  "type": "Feature",
  "properties": {
    "addr:full":"Avenue Eug\u00e8ne Burnand 26a 1510 Moudon Case Postale 66 Moudon Vaud 1510",
    "addr:housenumber":"26a;66",
    "addr:postcode":"1510;1510",
    "addr:street":"Avenue Euge\u0300Ne Burnand;Case Postale",
    "iso:country":"CH",
    "sg:address":"Avenue Eug\u00e8ne Burnand 26a 1510 Moudon Case Postale 66",
    "sg:city":"Moudon",
    "sg:classifiers":[
        {
            "category":"Social Services",
            "subcategory":"Retirement Home",
            "type":"Services"
        }
    ],
    "sg:phone":"+41 21 905 10 46",
    "sg:postcode":"1510",
    "sg:province":"Vaud",
    "sg:tags":[
        "pflegeheime",
        "u",
        "alters"
    ],
    "wof:name":"La Ch\u00e2telaine Etablissement M\u00e9dico-social",
    "wof:placetype":"venue"
},
  "geometry": {"coordinates":[6.795387,46.662655],"type":"Point"}
}