{
  "type": "Feature",
  "properties": {
    "iso:country":"CH",
    "sg:address":"Zeughausplatz 4410 Liestal. Postfach",
    "sg:city":"Liestal",
    "sg:orig_category":"Verwertung von Milch",
    "sg:phone":"+41 61 921 00 55",
    "sg:postcode":"4410",
    "sg:province":"Basel-Landschaft",
    "wof:name":"Milch Und Landwirtschaftliche Genossenschaft Liestal",
    "wof:placetype":"venue"
},
  "geometry": {"coordinates":[7.7354450226,47.4849014282],"type":"Point"}
}