{
  "type": "Feature",
  "properties": {
    "iso:country":"CH",
    "sg:address":"Rue Du Ch\u00e2teau-d'en-bas 2",
    "sg:city":"Bulle",
    "sg:orig_category":"Detailhandel mit Schuhen",
    "sg:phone":"+41 26 912 56 14",
    "sg:postcode":"1630",
    "sg:province":"Fribourg",
    "wof:name":"Bata Chaussures",
    "wof:placetype":"venue"
},
  "geometry": {"coordinates":[7.0823850632,46.5843086243],"type":"Point"}
}