{
  "type": "Feature",
  "properties": {
    "iso:country":"CH",
    "sg:address":"Hauptstrasse 58",
    "sg:city":"Messen",
    "sg:orig_category":"Grosshandel mit Getreide, Saatgut U Futtermitteln Herstellung von Futtermitteln f\u00fcr Nutztiere",
    "sg:phone":"+41 79 341 58 38",
    "sg:postcode":"3254",
    "sg:province":"Solothurn",
    "wof:name":"Utro Fikovit Ag",
    "wof:placetype":"venue"
},
  "geometry": {"coordinates":[8.3098268509,46.9964103699],"type":"Point"}
}