{
  "type": "Feature",
  "properties": {
    "iso:country":"CH",
    "sg:address":"Im Br\u00fcnneli 15",
    "sg:city":"Opfikon",
    "sg:orig_category":"Hardwareberatung",
    "sg:postcode":"8152",
    "sg:province":"Z\u00fcrich",
    "wof:name":"Voxtronic (schweiz) Ag",
    "wof:placetype":"venue"
},
  "geometry": {"coordinates":[8.5746965408,47.4383049011],"type":"Point"}
}