{
  "type": "Feature",
  "properties": {
    "iso:country":"CH",
    "sg:address":"Route D'echallens 34",
    "sg:city":"Romanel-s-lausanne",
    "sg:orig_category":"Reinigungsgewerbe",
    "sg:postcode":"1032",
    "sg:province":"Vaud",
    "wof:name":"Nettoyages Jaccard Sa",
    "wof:placetype":"venue"
},
  "geometry": {"coordinates":[6.6049871445,46.5690307617],"type":"Point"}
}