{
  "type": "Feature",
  "properties": {
    "iso:country":"CH",
    "sg:address":"Rue Eug\u00e8ne-marziano 33",
    "sg:city":"Gen\u00e8ve",
    "sg:orig_category":"G\u00fcterbef\u00f6rderung im Strassenverkehr",
    "sg:phone":"+41 77442109",
    "sg:postcode":"1200",
    "sg:province":"Gen\u00e8ve",
    "wof:name":"Rea-trans Walder Reto",
    "wof:placetype":"venue"
},
  "geometry": {"coordinates":[7.5997080803,47.4792556763],"type":"Point"}
}