{
  "type": "Feature",
  "properties": {
    "iso:country":"CH",
    "sg:address":"Chemin De La Gravi\u00e8re 4 1200 Gen\u00e8ve. Postfach",
    "sg:city":"Genf",
    "sg:orig_category":"Detailhandel mit Metallwaren, Anstrichmitteln, Glaswaren, Bau U Heimwerkerbedarf",
    "sg:postcode":"1200",
    "sg:province":"Gen\u00e8ve",
    "wof:name":"Outillage Richard Adler Sa Achat, Vente, Repr\u00e9sent., Import, Et Export. D'outillage D'aciers Et Articles Techn. P. L'industrie, La M\u00e9canique Et Le B\u00e2timent",
    "wof:placetype":"venue"
},
  "geometry": {"coordinates":[6.1298217773,46.1965713501],"type":"Point"}
}