{
  "type": "Feature",
  "properties": {
    "iso:country":"CH",
    "sg:address":"Rue Des Malvoisins",
    "sg:city":"Porrentruy",
    "sg:orig_category":"Detailhandel Reparatur von Gebrauchsg\u00fctern Vermietung von Gebrauchsg\u00fctern",
    "sg:phone":"+41 32 466 46 16",
    "sg:postcode":"2900",
    "sg:province":"Jura",
    "wof:name":"Vid\u00e9o Club D'ajoie Hubert Zaugg",
    "wof:placetype":"venue"
},
  "geometry": {"coordinates":[7.073800087,47.4170036316],"type":"Point"}
}