{
  "type": "Feature",
  "properties": {
    "iso:country":"CH",
    "sg:address":"Gewerbestrasse 2",
    "sg:city":"Bonau",
    "sg:orig_category":"Handelsvermittlung U Grosshandel mit Automobilen Herstellung von B\u00fcromaschinen",
    "sg:phone":"+41 79 417 42 73",
    "sg:postcode":"8554",
    "sg:province":"Thurgau",
    "wof:name":"Ernst Ramser Ag Staplerhandel",
    "wof:placetype":"venue"
},
  "geometry": {"coordinates":[9.0468063354,47.5831031799],"type":"Point"}
}