{
  "type": "Feature",
  "properties": {
    "iso:country":"CH",
    "sg:address":"Monti Di Piazzogna",
    "sg:city":"Piazzogna",
    "sg:orig_category":"Sonstiger Grosshandel",
    "sg:postcode":"6579",
    "sg:province":"Ticino",
    "wof:name":"La Forchetta D'oro Sagl",
    "wof:placetype":"venue"
},
  "geometry": {"coordinates":[8.8242521286,46.1352119446],"type":"Point"}
}