{
  "type": "Feature",
  "properties": {
    "iso:country":"CH",
    "sg:address":"Spitalstrasse 31",
    "sg:city":"Schlieren",
    "sg:orig_category":"Grosshandel mit Kaffee, Tee, Kakao U Gew\u00fcrzen",
    "sg:postcode":"8952",
    "sg:province":"Z\u00fcrich",
    "wof:name":"Gew\u00fcrze-vertrieb Huwyler Jos.",
    "wof:placetype":"venue"
},
  "geometry": {"coordinates":[8.4280424118,47.3938179016],"type":"Point"}
}