{
  "type": "Feature",
  "properties": {
    "iso:country":"CH",
    "sg:address":"8583",
    "sg:city":"Donzhausen",
    "sg:orig_category":"Primarschulen",
    "sg:phone":"+41 71 642 21 55",
    "sg:postcode":"8583",
    "sg:province":"Thurgau",
    "wof:name":"Primarschule",
    "wof:placetype":"venue"
},
  "geometry": {"coordinates":[9.1964502335,47.5544395447],"type":"Point"}
}