{
  "type": "Feature",
  "properties": {
    "iso:country":"CH",
    "sg:address":"Hegibachstrasse 102",
    "sg:city":"Z\u00fcrich",
    "sg:orig_category":"Arztpraxen",
    "sg:phone":"+41 13811666",
    "sg:postcode":"8032",
    "sg:province":"Z\u00fcrich",
    "wof:name":"Dr.med.hans Br\u00fcndler Spezialarzt Fmh",
    "wof:placetype":"venue"
},
  "geometry": {"coordinates":[8.56663,47.364674],"type":"Point"}
}