{
  "type": "Feature",
  "properties": {
    "iso:country":"CH",
    "sg:address":"Blauenrainstrasse 3a 4422 Arisdorf. Postfach",
    "sg:city":"Arisdorf",
    "sg:orig_category":"Softwareentwicklung U beratung",
    "sg:phone":"+41 61 811 61 36",
    "sg:postcode":"4422",
    "sg:province":"Basel-Landschaft",
    "wof:name":"Sowebco Gmbh Hard- U. Software, Hompages U. Multi- Media-produkte; Verkauf, Reparatur U. Herstellung Usw",
    "wof:placetype":"venue"
},
  "geometry": {"coordinates":[7.7661290169,47.5121688843],"type":"Point"}
}