{
  "type": "Feature",
  "properties": {
    "iso:country":"CH",
    "sg:address":"Bahnhofstrasse 7",
    "sg:city":"Ostermundigen",
    "sg:orig_category":"Arztpraxen",
    "sg:phone":"+41 31 931 60 73",
    "sg:postcode":"3072",
    "sg:province":"Bern",
    "wof:name":"Dr.med.susanne Sch\u00e4rer Spezial\u00e4rztin",
    "wof:placetype":"venue"
},
  "geometry": {"coordinates":[7.483948,46.955326],"type":"Point"}
}