{
  "type": "Feature",
  "properties": {
    "iso:country":"CH",
    "sg:address":"Burgstrasse 26",
    "sg:city":"Z\u00fcrich",
    "sg:orig_category":"Grosshandel mit Textilien",
    "sg:postcode":"8037",
    "sg:province":"Z\u00fcrich",
    "wof:name":"Barry Aziz Waren, Bes. Textilien U. Modeschmuck Aus Afrika; Handel",
    "wof:placetype":"venue"
},
  "geometry": {"coordinates":[8.5260038376,47.3918075562],"type":"Point"}
}