{
  "type": "Feature",
  "properties": {
    "iso:country":"CH",
    "sg:address":"Schmiedengasse 43",
    "sg:city":"Sch\u00f6nenwerd",
    "sg:orig_category":"Handel mit Automobilteilen U Zubeh\u00f6r",
    "sg:postcode":"5012",
    "sg:province":"Solothurn",
    "wof:name":"Filios Car Styling",
    "wof:placetype":"venue"
},
  "geometry": {"coordinates":[8.0065250397,47.3716316223],"type":"Point"}
}