{
  "type": "Feature",
  "properties": {
    "addr:full":"Gipserh\u00fctte 2 Ennenda Glarus 8755",
    "addr:housenumber":"2",
    "addr:postcode":"8755",
    "addr:street":"Gipserhuette",
    "iso:country":"CH",
    "sg:address":"Gipserh\u00fctte 2",
    "sg:city":"Ennenda",
    "sg:orig_category":"Allgemeiner Hoch U Tiefbau Allgemeiner Hochbau",
    "sg:phone":"+41 55 640 18 58",
    "sg:postcode":"8755",
    "sg:province":"Glarus",
    "wof:name":"Jenny & Co Ag, Bauunternehmung",
    "wof:placetype":"venue"
},
  "geometry": {"coordinates":[9.078343,47.030746],"type":"Point"}
}