{
  "type": "Feature",
  "properties": {
    "iso:country":"CH",
    "sg:address":"Chalet Nymph\u00e9a Rte Des Pars",
    "sg:city":"Gryon",
    "sg:orig_category":"Geb\u00e4ude, Wohnungsreinigung",
    "sg:phone":"+41 32 841 32 60",
    "sg:postcode":"1882",
    "sg:province":"Vaud",
    "wof:name":"Fran\u00e7oise Turberg Entreprise De Nettoyages",
    "wof:placetype":"venue"
},
  "geometry": {"coordinates":[6.8580021858,46.9651832581],"type":"Point"}
}