{
  "type": "Feature",
  "properties": {
    "iso:country":"CH",
    "sg:address":"Oberes Surbtal",
    "sg:city":"Unterehrendingen",
    "sg:orig_category":"Abwasserreinigung",
    "sg:phone":"+41 56 222 71 94",
    "sg:postcode":"5424",
    "wof:name":"Kl\u00e4ranlage",
    "wof:placetype":"venue"
},
  "geometry": {"coordinates":[8.35523,47.496101],"type":"Point"}
}