{
  "type": "Feature",
  "properties": {
    "iso:country":"CH",
    "sg:address":"Ever Green Park",
    "sg:city":"Origlio",
    "sg:orig_category":"Herstellung von Klebstoffen U Gelatinen",
    "sg:phone":"+41 91 945 27 19",
    "sg:postcode":"6945",
    "sg:province":"Ticino",
    "wof:name":"Widmer Ren\u00e9",
    "wof:placetype":"venue"
},
  "geometry": {"coordinates":[8.9446210861,46.0543479919],"type":"Point"}
}