{
  "type": "Feature",
  "properties": {
    "iso:country":"CH",
    "sg:address":"Plattenstrasse 3",
    "sg:city":"Glattbrugg",
    "sg:orig_category":"Wirtschaftspr\u00fcfung, Steuerberatung U Treuhand",
    "sg:postcode":"8152",
    "sg:province":"Z\u00fcrich",
    "wof:name":"Litonia Ag",
    "wof:placetype":"venue"
},
  "geometry": {"coordinates":[8.5651521683,47.4354743958],"type":"Point"}
}