{
  "type": "Feature",
  "properties": {
    "iso:country":"CH",
    "sg:address":"Gerbergasse 1 4001 Basel. Postfach",
    "sg:city":"Basel",
    "sg:orig_category":"Technische, physikalische U chemische Untersuchung",
    "sg:postcode":"4001",
    "sg:province":"Basel-Stadt",
    "wof:name":"Stiftung F\u00fcr Trinationalen Umweltschutz Unterst\u00fctzung Von Umweltprojekten In Der Region Basiliensis, Usw",
    "wof:placetype":"venue"
},
  "geometry": {"coordinates":[7.5880060196,47.557636261],"type":"Point"}
}