{
  "type": "Feature",
  "properties": {
    "iso:country":"CH",
    "sg:address":"Im Zentrum 18",
    "sg:city":"Volketswil",
    "sg:orig_category":"Kantonalbanken",
    "sg:phone":"+41 19082525",
    "sg:postcode":"8604",
    "sg:province":"Z\u00fcrich",
    "wof:name":"Z\u00fcrcher Kantonalbank",
    "wof:placetype":"venue"
},
  "geometry": {"coordinates":[8.6810903549,47.3881340027],"type":"Point"}
}