{
  "type": "Feature",
  "properties": {
    "iso:country":"CH",
    "sg:address":"Freiestrasse 4",
    "sg:city":"Schlieren",
    "sg:orig_category":"Detailhandel mit Damenbekleidung Herstellung von W\u00e4sche",
    "sg:phone":"+41 17311990",
    "sg:postcode":"8952",
    "sg:province":"Z\u00fcrich",
    "wof:name":"Impero Moda, Terio + Valero",
    "wof:placetype":"venue"
},
  "geometry": {"coordinates":[8.4476671219,47.3961524963],"type":"Point"}
}