{
  "type": "Feature",
  "properties": {
    "addr:full":"Avenue Henri-dunant 11 Gen\u00e8ve Gen\u00e8ve 1205",
    "addr:housenumber":"11",
    "addr:postcode":"1205",
    "addr:street":"Avenue Henri-Dunant",
    "iso:country":"CH",
    "sg:address":"Avenue Henri-dunant 11",
    "sg:city":"Gen\u00e8ve",
    "sg:orig_category":"Detailhandel mit Brillen U anderen Sehhilfen",
    "sg:phone":"+41 22 329 98 42",
    "sg:postcode":"1205",
    "sg:province":"Gen\u00e8ve",
    "wof:name":"Houria Fleury Optique",
    "wof:placetype":"venue"
},
  "geometry": {"coordinates":[6.142145,46.196411],"type":"Point"}
}