{
  "type": "Feature",
  "properties": {
    "iso:country":"CH",
    "sg:address":"Industriestrasse 9",
    "sg:city":"Niedererlinsbach",
    "sg:orig_category":"Sonstiger spezialisierter Hoch U Tiefbau",
    "sg:phone":"+41 79 434 21 07",
    "sg:postcode":"5015",
    "sg:province":"Solothurn",
    "wof:name":"Betoncoupe Ag",
    "wof:placetype":"venue"
},
  "geometry": {"coordinates":[8.0086021423,47.3893013],"type":"Point"}
}