{
  "type": "Feature",
  "properties": {
    "iso:country":"CH",
    "sg:address":"Juraweg 484",
    "sg:city":"Uerkheim",
    "sg:orig_category":"Herstellung von Konstruktionsteilen, Fertigbauteilen U Ausbauelementen aus Holz",
    "sg:phone":"+41 62213110",
    "sg:postcode":"4813",
    "sg:province":"Aargau",
    "wof:name":"Kundenschreiner Hp. Bopp",
    "wof:placetype":"venue"
},
  "geometry": {"coordinates":[8.0291976929,47.3033752441],"type":"Point"}
}