{
  "type": "Feature",
  "properties": {
    "iso:country":"CH",
    "sg:address":"Dorf 6162 Entlebuch. Postfach",
    "sg:city":"Entlebuch",
    "sg:orig_category":"Regionalbanken U Sparkassen",
    "sg:phone":"+41 41 208 07 07",
    "sg:postcode":"6162",
    "sg:province":"Luzern",
    "wof:name":"Eb Entlebucher Bank",
    "wof:placetype":"venue"
},
  "geometry": {"coordinates":[8.0651550293,46.9935340881],"type":"Point"}
}