{
  "type": "Feature",
  "properties": {
    "iso:country":"CH",
    "sg:address":"Luzernerstrasse 30",
    "sg:city":"Kriens",
    "sg:orig_category":"Mineralwasser Detailhandel Wein Detailhandel",
    "sg:phone":"+41 24 499 12 57",
    "sg:postcode":"6010",
    "sg:province":"Luzern",
    "wof:name":"Franz Joss Vins Eaux Min\u00e9rales",
    "wof:placetype":"venue"
},
  "geometry": {"coordinates":[6.3582320213,44.5042152405],"type":"Point"}
}