{
  "type": "Feature",
  "properties": {
    "addr:full":"S\u00e4listrasse 9 Dulliken Solothurn 4657",
    "addr:housenumber":"9",
    "addr:postcode":"4657",
    "addr:street":"Saelistrasse",
    "iso:country":"CH",
    "sg:address":"S\u00e4listrasse 9",
    "sg:city":"Dulliken",
    "sg:orig_category":"Allgemeiner Hoch U Tiefbau Allgemeiner Hochbau",
    "sg:phone":"+41 62 295 24 06",
    "sg:postcode":"4657",
    "sg:province":"Solothurn",
    "wof:name":"Giuseppe Morgillo Hoch-& Tiefbau",
    "wof:placetype":"venue"
},
  "geometry": {"coordinates":[7.93909,47.347649],"type":"Point"}
}