{
  "type": "Feature",
  "properties": {
    "iso:country":"CH",
    "sg:address":"Bodenacherstrasse 2",
    "sg:city":"Volketswil",
    "sg:orig_category":"G\u00fcterbef\u00f6rderung im Strassenverkehr",
    "sg:phone":"+41 19455100",
    "sg:postcode":"8604",
    "sg:province":"Z\u00fcrich",
    "wof:name":"Ernst Saxer Transporte",
    "wof:placetype":"venue"
},
  "geometry": {"coordinates":[8.6814517975,47.4043769836],"type":"Point"}
}