{
  "type": "Feature",
  "properties": {
    "iso:country":"CH",
    "sg:address":"Rehweg 37",
    "sg:city":"Winterthur",
    "sg:orig_category":"Wirtschaftspr\u00fcfung, Steuerberatung U Treuhand",
    "sg:phone":"+41 71 755 76 03",
    "sg:postcode":"8400",
    "sg:province":"Z\u00fcrich",
    "wof:name":"Hangartner Treuhand Und Unternehmensberatung",
    "wof:placetype":"venue"
},
  "geometry": {"coordinates":[9.5588188171,47.3799476624],"type":"Point"}
}