{
  "type": "Feature",
  "properties": {
    "iso:country":"CH",
    "sg:address":"Hauptstrasse 38",
    "sg:city":"Tenniken",
    "sg:orig_category":"Kosmetikinstitute",
    "sg:phone":"+41 61 971 77 48",
    "sg:postcode":"4456",
    "sg:province":"Basel-Landschaft",
    "wof:name":"Evelyne Kunz Kosmetikinstitut",
    "wof:placetype":"venue"
},
  "geometry": {"coordinates":[7.8104782104,47.4354820251],"type":"Point"}
}