{
  "type": "Feature",
  "properties": {
    "iso:country":"CH",
    "sg:address":"Avenue C.-f.-ramuz 81",
    "sg:city":"Pully",
    "sg:orig_category":"Detailhandel mit Waren verschiedener Art, Hauptrichtung Nahrungsmittel",
    "sg:postcode":"1009",
    "sg:province":"Vaud",
    "wof:name":"Wyss H.",
    "wof:placetype":"venue"
},
  "geometry": {"coordinates":[6.6446528435,46.5091438293],"type":"Point"}
}