{
  "type": "Feature",
  "properties": {
    "iso:country":"CH",
    "sg:address":"Port De Vidy 1007 Lausanne Case Postale 323",
    "sg:city":"Lausanne",
    "sg:classifiers":[
        {
            "category":"Restaurant",
            "type":"Food & Drink"
        }
    ],
    "sg:phone":"+41 24 445 40 55",
    "sg:postcode":"1001",
    "sg:province":"Vaud",
    "wof:name":"Cercle De La Voile Restaurant Du",
    "wof:placetype":"venue"
},
  "geometry": {"coordinates":[6.6397790909,46.8051719666],"type":"Point"}
}