{
  "type": "Feature",
  "properties": {
    "iso:country":"CH",
    "sg:address":"Route De Mi\u00e8ge 6",
    "sg:city":"Sierre",
    "sg:orig_category":"Massagestudios",
    "sg:phone":"+41 27 456 10 21",
    "sg:postcode":"3960",
    "sg:province":"Valais",
    "wof:name":"Ravir-relax Masasge De Sant\u00e9",
    "wof:placetype":"venue"
},
  "geometry": {"coordinates":[7.5415358543,46.2980918884],"type":"Point"}
}