{
  "type": "Feature",
  "properties": {
    "iso:country":"CH",
    "sg:address":"Klosterstrasse 3",
    "sg:city":"Engelberg",
    "sg:orig_category":"Sonstige mit Sport verbundene T\u00e4tigkeiten",
    "sg:phone":"+41 41 637 30 40",
    "sg:postcode":"6390",
    "sg:province":"Obwalden",
    "wof:name":"Neue Skischule Engelberg",
    "wof:placetype":"venue"
},
  "geometry": {"coordinates":[8.4055109024,46.8206329346],"type":"Point"}
}