{
  "type": "Feature",
  "properties": {
    "iso:country":"CH",
    "sg:address":"Kirchgasse 174",
    "sg:city":"Staffelbach",
    "sg:orig_category":"Tanzschulen, Tanzlehrer",
    "sg:phone":"+41 62 721 18 98",
    "sg:postcode":"5053",
    "sg:province":"Aargau",
    "wof:name":"Club 94 Tanzschule",
    "wof:placetype":"venue"
},
  "geometry": {"coordinates":[8.0473327637,47.2831993103],"type":"Point"}
}