{
  "type": "Feature",
  "properties": {
    "iso:country":"CH",
    "sg:address":"Eggstrasse 21 8102 Oberengstringen. Postfach",
    "sg:city":"Oberengstringen",
    "sg:orig_category":"Architektur U Ingenieurb\u00fcros",
    "sg:postcode":"8102",
    "sg:province":"Z\u00fcrich",
    "wof:name":"Davitti Engineering Und Immobilien Beratung Im Bereich Engineering. Immobilien; Planung, Bau, Handel",
    "wof:placetype":"venue"
},
  "geometry": {"coordinates":[8.470757,47.407913],"type":"Point"}
}