{
  "type": "Feature",
  "properties": {
    "iso:country":"CH",
    "sg:address":"Alte Landstr. 332 8708 M\u00e4nnedorf. Postfach",
    "sg:city":"M\u00e4nnedorf",
    "sg:orig_category":"K\u00fcnstlerische U schriftstellerische T\u00e4tigkeiten U Darbietungen",
    "sg:postcode":"8708",
    "sg:province":"Z\u00fcrich",
    "wof:name":"Morell, Eugen",
    "wof:placetype":"venue"
},
  "geometry": {"coordinates":[8.701174736,47.2501907349],"type":"Point"}
}