{
  "type": "Feature",
  "properties": {
    "iso:country":"CH",
    "sg:address":"Gellertstrasse 53",
    "sg:city":"Basel",
    "sg:orig_category":"Detailhandel mit Teppichen Verlegen von Fussboden",
    "sg:phone":"+41 62 771 75 73",
    "sg:postcode":"4052",
    "sg:province":"Basel-Stadt",
    "wof:name":"Jolanda Hess Teppiche & Bodenbel\u00e4ge",
    "wof:placetype":"venue"
},
  "geometry": {"coordinates":[8.1962118149,47.2648735046],"type":"Point"}
}