{
  "type": "Feature",
  "properties": {
    "iso:country":"CH",
    "sg:address":"Br\u00fchlstrasse 4",
    "sg:city":"Safenwil",
    "sg:orig_category":"G\u00fcterbef\u00f6rderung im Strassenverkehr",
    "sg:phone":"+41 62 797 13 74",
    "sg:postcode":"5745",
    "sg:province":"Aargau",
    "wof:name":"Sergio Protopapa, Transporte Und M\u00f6belmontage",
    "wof:placetype":"venue"
},
  "geometry": {"coordinates":[7.9790182114,47.3184814453],"type":"Point"}
}