{
  "type": "Feature",
  "properties": {
    "iso:country":"CH",
    "sg:address":"Z\u00fcrcherstrasse 137",
    "sg:city":"Schlieren",
    "sg:classifiers":[
        {
            "category":"Banks & Credit Unions",
            "subcategory":"Bank",
            "type":"Services"
        }
    ],
    "sg:phone":"+41 17310546",
    "sg:postcode":"8952",
    "sg:province":"Z\u00fcrich",
    "wof:name":"Bank Aufina",
    "wof:placetype":"venue"
},
  "geometry": {"coordinates":[8.465982,47.396519],"type":"Point"}
}