{
  "type": "Feature",
  "properties": {
    "iso:country":"CH",
    "sg:address":"3156",
    "sg:city":"Riffenmatt",
    "sg:orig_category":"Personenbef\u00f6rderung im Linienverkehr zu Land",
    "sg:phone":"+41 31 738 88 00",
    "sg:postcode":"3156",
    "sg:province":"Bern",
    "wof:name":"Skilift Riffenmatt Ag",
    "wof:placetype":"venue"
},
  "geometry": {"coordinates":[7.3531298637,46.7652893066],"type":"Point"}
}