{
  "type": "Feature",
  "properties": {
    "iso:country":"CH",
    "sg:address":"Lagerweg 8",
    "sg:city":"Bern",
    "sg:orig_category":"Sonstige pers\u00f6nliche Dienstleistungen",
    "sg:postcode":"3013",
    "sg:province":"Bern",
    "wof:name":"Aviola Partner Gmbh",
    "wof:placetype":"venue"
},
  "geometry": {"coordinates":[7.4461507797,46.9567565918],"type":"Point"}
}