{
  "type": "Feature",
  "properties": {
    "iso:country":"CH",
    "sg:address":"Seilerweg 9 2503 Biel/bienne. Postfach",
    "sg:city":"Biel/bienne",
    "sg:orig_category":"Unclassifiable Establishments",
    "sg:phone":"+41 32 365 85 49",
    "sg:postcode":"2503",
    "sg:province":"Bern",
    "wof:name":"Cardinaux Ren\u00e9 Cc Cardicommerce",
    "wof:placetype":"venue"
},
  "geometry": {"coordinates":[7.2609848976,47.1376342773],"type":"Point"}
}