{
  "type": "Feature",
  "properties": {
    "iso:country":"CH",
    "sg:address":"Maraini Via 44a",
    "sg:city":"Pregassona",
    "sg:orig_category":"Sanit\u00e4r, Heizungs U L\u00fcftungsinstallation",
    "sg:postcode":"6963",
    "sg:province":"Ticino",
    "wof:name":"Sanidraulica Sagl",
    "wof:placetype":"venue"
},
  "geometry": {"coordinates":[8.9727811813,46.0194549561],"type":"Point"}
}