{
  "type": "Feature",
  "properties": {
    "iso:country":"CH",
    "sg:address":"1589",
    "sg:city":"Chabrey",
    "sg:orig_category":"Dienstleistungen von Beteiligungsgesellschaften",
    "sg:postcode":"1589",
    "sg:province":"Vaud",
    "wof:name":"Archipress, Claudia Berke & B\u00e4nz L\u00fcthi",
    "wof:placetype":"venue"
},
  "geometry": {"coordinates":[6.9800100327,46.9260597229],"type":"Point"}
}