{
  "type": "Feature",
  "properties": {
    "iso:country":"CH",
    "sg:address":"Kreuzlinger Strasse 132",
    "sg:city":"Amriswil",
    "sg:orig_category":"Unternehmensberatung Wirtschaftspr\u00fcfung, Steuerberatung U Treuhand",
    "sg:phone":"+41 71 282 30 60",
    "sg:postcode":"8580",
    "sg:province":"Thurgau",
    "wof:name":"Kobelt Treuhand St. Gallen Ag",
    "wof:placetype":"venue"
},
  "geometry": {"coordinates":[9.4149198532,47.438205719],"type":"Point"}
}