{
  "type": "Feature",
  "properties": {
    "iso:country":"CH",
    "sg:address":"Im F\u00fcchsli 20",
    "sg:city":"B\u00fclach",
    "sg:orig_category":"Softwareentwicklung U beratung",
    "sg:phone":"+41 18606531",
    "sg:postcode":"8180",
    "sg:province":"Z\u00fcrich",
    "wof:name":"Santamato A.o.",
    "wof:placetype":"venue"
},
  "geometry": {"coordinates":[8.5442171097,47.5231513977],"type":"Point"}
}