{
  "type": "Feature",
  "properties": {
    "addr:full":"Grand-rue 47 Ch\u00e9zard-st-martin Neuch\u00e2tel 2054",
    "addr:housenumber":"47",
    "addr:postcode":"2054",
    "addr:street":"Grand-Rue;Che\u0301Zard-St-Martin Neucha\u0302Tel",
    "iso:country":"CH",
    "sg:address":"Grand-rue 47",
    "sg:city":"Ch\u00e9zard-st-martin",
    "sg:orig_category":"Darlehenskassen U Raiffeisenbanken",
    "sg:phone":"+41 21 960 13 32",
    "sg:postcode":"2054",
    "sg:province":"Neuch\u00e2tel",
    "wof:name":"Banque Raiffeisen",
    "wof:placetype":"venue"
},
  "geometry": {"coordinates":[6.92413,46.396301],"type":"Point"}
}