{
  "type": "Feature",
  "properties": {
    "iso:country":"CH",
    "sg:address":"Br\u00fchlwiesenstrasse 2",
    "sg:city":"W\u00e4ngi",
    "sg:orig_category":"Verwertung von Milch",
    "sg:postcode":"9545",
    "sg:province":"Thurgau",
    "wof:name":"Markus H\u00e4nni",
    "wof:placetype":"venue"
},
  "geometry": {"coordinates":[8.9716596603,47.5773010254],"type":"Point"}
}