{
  "type": "Feature",
  "properties": {
    "iso:country":"CH",
    "sg:address":"Furkastrasse 34",
    "sg:city":"Naters",
    "sg:orig_category":"RESTAURANTS: TEA-ROOMS",
    "sg:postcode":"3904",
    "sg:province":"Valais",
    "wof:name":"Popic Und Blatter Gmbh",
    "wof:placetype":"venue"
},
  "geometry": {"coordinates":[7.9908027649,46.3235206604],"type":"Point"}
}