{
  "type": "Feature",
  "properties": {
    "iso:country":"CH",
    "sg:address":"Valdani Via 1",
    "sg:city":"Chiasso",
    "sg:orig_category":"Unclassifiable Establishments",
    "sg:phone":"+41 91 695 60 50",
    "sg:postcode":"6830",
    "sg:province":"Ticino",
    "wof:name":"Prisma Holding Sa",
    "wof:placetype":"venue"
},
  "geometry": {"coordinates":[9.0288763046,45.8359642029],"type":"Point"}
}