{
  "type": "Feature",
  "properties": {
    "iso:country":"CH",
    "sg:address":"Tribschenstrasse 9 6005 Luzern. Postfach",
    "sg:city":"Luzern",
    "sg:classifiers":[
        {
            "category":"Professional",
            "subcategory":"Employment Agencies",
            "type":"Services"
        }
    ],
    "sg:phone":"+41 41 368 11 22",
    "sg:postcode":"6005",
    "sg:province":"Luzern",
    "sg:tags":[
        "personal",
        "u",
        "stellenvermittlung"
    ],
    "wof:name":"Bpz Betonpumpen Ag Zentralschweiz",
    "wof:placetype":"venue"
},
  "geometry": {"coordinates":[8.3126792908,47.0440940857],"type":"Point"}
}