{
  "type": "Feature",
  "properties": {
    "iso:country":"CH",
    "sg:address":"Rue Saint-germain 66",
    "sg:city":"Courfaivre",
    "sg:orig_category":"Grosshandel mit Textilien Grosshandel mit sonstigen Konsumg\u00fctern",
    "sg:phone":"+41 32 426 88 33",
    "sg:postcode":"2853",
    "sg:province":"Jura",
    "wof:name":"Staccato-design, Klezar S.",
    "wof:placetype":"venue"
},
  "geometry": {"coordinates":[7.284142971,47.3346366882],"type":"Point"}
}