{
  "type": "Feature",
  "properties": {
    "iso:country":"CH",
    "sg:address":"4232",
    "sg:city":"Fehren",
    "sg:orig_category":"Schulpflegen",
    "sg:postcode":"4232",
    "sg:province":"Solothurn",
    "wof:name":"Schulkommission Der Gemeinde Fehren",
    "wof:placetype":"venue"
},
  "geometry": {"coordinates":[7.580930233,47.4025001526],"type":"Point"}
}