{
  "type": "Feature",
  "properties": {
    "iso:country":"CH",
    "sg:address":"Sch\u00fcrmattstrasse",
    "sg:city":"Sins",
    "sg:orig_category":"Grosshandel mit Maschinen U Ausr\u00fcstungen Herstellung von Pumpen U Kompressoren",
    "sg:phone":"+41 61 751 42 51",
    "sg:postcode":"5643",
    "sg:province":"Aargau",
    "wof:name":"Ghibli Hochdruck Ag",
    "wof:placetype":"venue"
},
  "geometry": {"coordinates":[7.5951371193,47.4777832031],"type":"Point"}
}