{
  "type": "Feature",
  "properties": {
    "iso:country":"CH",
    "sg:address":"Forchstrasse 158",
    "sg:city":"Z\u00fcrich",
    "sg:orig_category":"Architekturb\u00fcros",
    "sg:phone":"+41 13820290",
    "sg:postcode":"8032",
    "sg:province":"Z\u00fcrich",
    "wof:name":"Hanspeter Crameri Architekturb\u00fcro",
    "wof:placetype":"venue"
},
  "geometry": {"coordinates":[8.564445,47.360287],"type":"Point"}
}