{
  "type": "Feature",
  "properties": {
    "iso:country":"CH",
    "sg:address":"Leimgrubenweg 27",
    "sg:city":"Basel",
    "sg:orig_category":"Detailhandel mit Sportartikeln Fachdetailhandel in Verkaufsr\u00e4umen",
    "sg:phone":"+41 61 333 10 60",
    "sg:postcode":"4053",
    "sg:province":"Basel-Stadt",
    "wof:name":"Athleticum Sportmarkets Ag",
    "wof:placetype":"venue"
},
  "geometry": {"coordinates":[7.6062278748,47.536655426],"type":"Point"}
}