{
  "type": "Feature",
  "properties": {
    "iso:country":"CH",
    "sg:address":"Gamlikon 302",
    "sg:city":"Stallikon",
    "sg:orig_category":"Autogaragen",
    "sg:phone":"+41 17000258",
    "sg:postcode":"8143",
    "sg:province":"Z\u00fcrich",
    "wof:name":"Max Huber Autoreparaturen",
    "wof:placetype":"venue"
},
  "geometry": {"coordinates":[8.493825,47.31179],"type":"Point"}
}