{
  "type": "Feature",
  "properties": {
    "iso:country":"CH",
    "sg:address":"Hauptstrasse 57",
    "sg:city":"Kreuzlingen",
    "sg:orig_category":"Detailhandel mit Schreib U Papeteriewaren",
    "sg:phone":"+41 71 672 45 13",
    "sg:postcode":"8280",
    "sg:province":"Thurgau",
    "wof:name":"Rosemarie Bitsche Papeterie",
    "wof:placetype":"venue"
},
  "geometry": {"coordinates":[9.1750898361,47.648563385],"type":"Point"}
}