{
  "type": "Feature",
  "properties": {
    "iso:country":"CH",
    "sg:address":"Mittelstrasse 4 2560 Nidau. Postfach 244",
    "sg:city":"Nidau",
    "sg:orig_category":"Detailhandel mit Fahrr\u00e4dern Fachdetailhandel in Verkaufsr\u00e4umen",
    "sg:phone":"+41 32 331 57 33",
    "sg:postcode":"2560",
    "sg:province":"Bern",
    "wof:name":"Buba's Velo-shop Gmbh",
    "wof:placetype":"venue"
},
  "geometry": {"coordinates":[7.2399468422,47.1253814697],"type":"Point"}
}