{
  "type": "Feature",
  "properties": {
    "iso:country":"CH",
    "sg:address":"Rue Du Temple 17 2024 St-aubin-sauges Case Postale 131",
    "sg:city":"St-aubin-sauges",
    "sg:orig_category":"Detailhandel mit Lederwaren U Reiseartikeln Herstellung von Reiseartikeln, Leder U Sattlerwaren",
    "sg:phone":"+41 32 913 91 78",
    "sg:postcode":"2024",
    "sg:province":"Neuch\u00e2tel",
    "wof:name":"Marmotline Sa",
    "wof:placetype":"venue"
},
  "geometry": {"coordinates":[6.8257160187,47.1000175476],"type":"Point"}
}