{
  "type": "Feature",
  "properties": {
    "iso:country":"CH",
    "sg:address":"Bossons Chemin Des 47 1018 Lausanne. Postfach",
    "sg:city":"Lausanne",
    "sg:orig_category":"Non-Classified Establishments",
    "sg:postcode":"1018",
    "sg:province":"Vaud",
    "wof:name":"Fiorio Fassadentechnik",
    "wof:placetype":"venue"
},
  "geometry": {"coordinates":[9.1210298538,47.4768638611],"type":"Point"}
}