{
  "type": "Feature",
  "properties": {
    "iso:country":"CH",
    "sg:address":"Rue Des Champs 7",
    "sg:city":"Echallens",
    "sg:orig_category":"Versicherungen Hauptagenturen",
    "sg:phone":"+41 21 881 20 21",
    "sg:postcode":"1040",
    "sg:province":"Vaud",
    "wof:name":"Assurance Cantonale Contre L'incendie & Les \u00e9l\u00e9ments Nat.",
    "wof:placetype":"venue"
},
  "geometry": {"coordinates":[6.6362271309,46.6378173828],"type":"Point"}
}