{
  "type": "Feature",
  "properties": {
    "iso:country":"CH",
    "sg:address":"Werkhofstrasse 24 6005 Luzern. Postfach",
    "sg:city":"Luzern",
    "sg:orig_category":"Herstellung von K\u00fcchenm\u00f6beln",
    "sg:postcode":"6003",
    "sg:province":"Luzern",
    "wof:name":"Gr\u00fcter-suter Gastro Ag",
    "wof:placetype":"venue"
},
  "geometry": {"coordinates":[8.3139867783,47.0437812805],"type":"Point"}
}