{
  "type": "Feature",
  "properties": {
    "iso:country":"CH",
    "sg:address":"Z\u00fcrichstrasse 14",
    "sg:city":"Neftenbach",
    "sg:orig_category":"Herstellung von Konstruktionsteilen, Fertigbauteilen U Ausbauelementen aus Holz",
    "sg:postcode":"8413",
    "sg:province":"Z\u00fcrich",
    "wof:name":"Schneider U., Schreinerei",
    "wof:placetype":"venue"
},
  "geometry": {"coordinates":[8.6652364731,47.5272865295],"type":"Point"}
}