{
  "type": "Feature",
  "properties": {
    "iso:country":"CH",
    "sg:address":"Schwandenstrasse 3 8143 Stallikon. Postfach",
    "sg:city":"Stallikon",
    "sg:orig_category":"Grosshandel mit sonstigen Halbwaren",
    "sg:phone":"+41 17012200",
    "sg:postcode":"8143",
    "sg:province":"Z\u00fcrich",
    "wof:name":"Forma Ag Kunststoffprodukte",
    "wof:placetype":"venue"
},
  "geometry": {"coordinates":[8.472659111,47.3517074585],"type":"Point"}
}