{
  "type": "Feature",
  "properties": {
    "iso:country":"CH",
    "sg:address":"Aavorstadt 1",
    "sg:city":"Lenzburg",
    "sg:orig_category":"Interessenvertretungen",
    "sg:postcode":"5600",
    "sg:province":"Aargau",
    "wof:name":"Stiftung Sylvain App",
    "wof:placetype":"venue"
},
  "geometry": {"coordinates":[8.1788988113,47.3868598938],"type":"Point"}
}