{
  "type": "Feature",
  "properties": {
    "iso:country":"CH",
    "sg:address":"Andreasstrasse 65",
    "sg:city":"Z\u00fcrich",
    "sg:orig_category":"Fotografische Ateliers Fotografisches Gewerbe U fotografische Laboratorien",
    "sg:phone":"+41 13001108",
    "sg:postcode":"8050",
    "sg:province":"Z\u00fcrich",
    "wof:name":"L & G Fotostudio Gmbh",
    "wof:placetype":"venue"
},
  "geometry": {"coordinates":[8.5531730652,47.4136505127],"type":"Point"}
}