{
  "type": "Feature",
  "properties": {
    "iso:country":"CH",
    "sg:address":"Lindenstrasse 10",
    "sg:city":"Wildegg",
    "sg:orig_category":"Technische, physikalische U chemische Untersuchung",
    "sg:postcode":"5103",
    "sg:province":"Aargau",
    "wof:name":"Tecnat Sa",
    "wof:placetype":"venue"
},
  "geometry": {"coordinates":[6.9731612206,46.2920532227],"type":"Point"}
}