{
  "type": "Feature",
  "properties": {
    "iso:country":"CH",
    "sg:address":"Markgr\u00e4flerstrasse 36 4057 Basel. Postfach 325",
    "sg:city":"Basel",
    "sg:orig_category":"Unclassifiable Establishments",
    "sg:phone":"+41 81 300 08 88",
    "sg:postcode":"4057",
    "sg:province":"Basel-Stadt",
    "wof:name":"Glas Tr\u00f6sch Ag Malans",
    "wof:placetype":"venue"
},
  "geometry": {"coordinates":[9.5621557236,46.9718551636],"type":"Point"}
}