{
  "type": "Feature",
  "properties": {
    "addr:full":"Castione. Lumino Ticino 6533",
    "addr:postcode":"6533",
    "iso:country":"CH",
    "sg:address":"Castione.",
    "sg:city":"Lumino",
    "sg:orig_category":"Detailhandel mit B\u00fcchern, Zeitungen, Schreib U Papeteriewaren",
    "sg:postcode":"6533",
    "sg:province":"Ticino",
    "wof:name":"Dellamonica Rosanna.",
    "wof:placetype":"venue"
},
  "geometry": {"coordinates":[9.05023,46.22707],"type":"Point"}
}