{
  "type": "Feature",
  "properties": {
    "iso:country":"CH",
    "sg:address":"Neugasse 12",
    "sg:city":"St.gallen",
    "sg:orig_category":"Detailhandel mit Damenbekleidung",
    "sg:phone":"+41 71 911 00 45",
    "sg:postcode":"9000",
    "sg:province":"St. Gallen",
    "wof:name":"Schaad Mode Ag",
    "wof:placetype":"venue"
},
  "geometry": {"coordinates":[9.046934,47.465443],"type":"Point"}
}