{
  "type": "Feature",
  "properties": {
    "iso:country":"CH",
    "sg:address":"Generoso Via",
    "sg:city":"Rovio",
    "sg:orig_category":"Herstellung von sonstigen Waren aus Papier, Karton U Pappe",
    "sg:phone":"+41 31 335 77 77",
    "sg:postcode":"6821",
    "sg:province":"Ticino",
    "wof:name":"Hawe Hugentobler Ag Selbstklebebeschichtungen Usw; Herst, Handel.",
    "wof:placetype":"venue"
},
  "geometry": {"coordinates":[7.4552497864,46.9563751221],"type":"Point"}
}