{
  "type": "Feature",
  "properties": {
    "iso:country":"CH",
    "sg:address":"Via Nosetto 28",
    "sg:city":"Caslano",
    "sg:orig_category":"Grosshandel mit Getr\u00e4nken",
    "sg:phone":"+41 79 408 48 07",
    "sg:postcode":"6987",
    "sg:province":"Ticino",
    "wof:name":"Enoteca Tre Palme Di Schmutz Elmar",
    "wof:placetype":"venue"
},
  "geometry": {"coordinates":[8.8792104721,45.9782485962],"type":"Point"}
}