{
  "type": "Feature",
  "properties": {
    "addr:full":"Thuraustrasse 18 Wil St. Gallen 9500",
    "addr:housenumber":"18;st.",
    "addr:postcode":"9500",
    "addr:street":"Thuraustrasse;Wil",
    "iso:country":"CH",
    "sg:address":"Thuraustrasse 18",
    "sg:city":"Wil",
    "sg:classifiers":[
        {
            "category":"Manufacturing",
            "subcategory":"Chemicals & Compounds",
            "type":"Manufacturing & Wholesale Goods"
        }
    ],
    "sg:phone":"+41 71 912 12 77",
    "sg:postcode":"9500",
    "sg:province":"St. Gallen",
    "sg:tags":[
        "analysis"
    ],
    "wof:name":"Ms Wil Gmbh",
    "wof:placetype":"venue"
},
  "geometry": {"coordinates":[9.050411,47.46106],"type":"Point"}
}