{
  "type": "Feature",
  "properties": {
    "iso:country":"CH",
    "sg:address":"Chalet Aiguille-verte",
    "sg:city":"Chesi\u00e8res",
    "sg:orig_category":"Detailhandel mit Brennstoffen U Heizmaterial Grosshandel mit festen Brennstoffen U Mineral\u00f6lerzeugni",
    "sg:phone":"+41 24 495 14 09",
    "sg:postcode":"1885",
    "sg:province":"Vaud",
    "wof:name":"Von Gr\u00fcnigen & Cie.",
    "wof:placetype":"venue"
},
  "geometry": {"coordinates":[7.04348,46.301109],"type":"Point"}
}