{
  "type": "Feature",
  "properties": {
    "iso:country":"CH",
    "sg:address":"Wigetstrasse 5a",
    "sg:city":"Wattwil",
    "sg:orig_category":"Blumen U Zierpflanzenbau Detailhandel mit Blumen U Pflanzen",
    "sg:phone":"+41 71 988 12 26",
    "sg:postcode":"9630",
    "sg:province":"St. Gallen",
    "wof:name":"Sibold Paul Ag",
    "wof:placetype":"venue"
},
  "geometry": {"coordinates":[9.088344,47.305885],"type":"Point"}
}