{
  "type": "Feature",
  "properties": {
    "iso:country":"CH",
    "sg:address":"Industriestrasse 15 6345 Neuheim. Postfach",
    "sg:city":"Neuheim",
    "sg:orig_category":"Pensionskassen",
    "sg:postcode":"6345",
    "sg:province":"Zug",
    "wof:name":"Personalvorsorgestiftung Der Bucher Hydraulics Ag",
    "wof:placetype":"venue"
},
  "geometry": {"coordinates":[8.5793581009,47.203453064],"type":"Point"}
}