{
  "type": "Feature",
  "properties": {
    "iso:country":"CH",
    "sg:address":"Piazza S.stefano",
    "sg:city":"Rancate",
    "sg:orig_category":"Grosshandel mit sonstigen Maschinen U Ausr\u00fcstungen f\u00fcr Industrie, Handel U Schiffahrt",
    "sg:phone":"+41 91 646 99 81",
    "sg:postcode":"6862",
    "sg:province":"Ticino",
    "wof:name":"Nochifra Sagl",
    "wof:placetype":"venue"
},
  "geometry": {"coordinates":[8.9681348801,45.8714981079],"type":"Point"}
}