{
  "type": "Feature",
  "properties": {
    "addr:full":"Hauptgasse 40 Morat Fribourg 3280",
    "addr:housenumber":"40",
    "addr:postcode":"3280",
    "addr:street":"Hauptgasse",
    "iso:country":"CH",
    "sg:address":"Hauptgasse 40",
    "sg:city":"Morat",
    "sg:orig_category":"Detailhandel mit Brot, Back U S\u00fcsswaren",
    "sg:phone":"+41 26 670 22 27",
    "sg:postcode":"3280",
    "sg:province":"Fribourg",
    "wof:name":"B\u00e4ckerei Aebersold Gmbh",
    "wof:placetype":"venue"
},
  "geometry": {"coordinates":[7.117901,46.928551],"type":"Point"}
}