{
  "type": "Feature",
  "properties": {
    "iso:country":"CH",
    "sg:address":"Wieslerstrasse 22",
    "sg:city":"Zollikon",
    "sg:orig_category":"Unternehmensberatung",
    "sg:phone":"+41 13915086",
    "sg:postcode":"8702",
    "sg:province":"Z\u00fcrich",
    "wof:name":"Heller Kommunikationstraining",
    "wof:placetype":"venue"
},
  "geometry": {"coordinates":[8.5794248581,47.3375968933],"type":"Point"}
}