{
  "type": "Feature",
  "properties": {
    "iso:country":"CH",
    "sg:address":"Rue Bel-air 2",
    "sg:city":"Saignel\u00e9gier",
    "sg:orig_category":"Detailhandel mit Blumen U Pflanzen",
    "sg:phone":"+41 32 951 19 60",
    "sg:postcode":"2350",
    "sg:province":"Jura",
    "wof:name":"Yvanie Cattin Fleurs Le Muguet",
    "wof:placetype":"venue"
},
  "geometry": {"coordinates":[6.995349,47.255974],"type":"Point"}
}