{
  "type": "Feature",
  "properties": {
    "iso:country":"CH",
    "sg:address":"Pr\u00e8s-des-rives",
    "sg:city":"L'abbaye",
    "sg:orig_category":"Erbringung von Dienstleistungen f\u00fcr Unternehmen",
    "sg:phone":"+41 21 848 18 81",
    "sg:postcode":"1344",
    "sg:province":"Vaud",
    "wof:name":"Golay Murielle D\u00e9coration",
    "wof:placetype":"venue"
},
  "geometry": {"coordinates":[-89.0508117676,36.3560791016],"type":"Point"}
}