{
  "type": "Feature",
  "properties": {
    "iso:country":"CH",
    "sg:address":"Giardino Via 12 6517 Arbedo. Postfach",
    "sg:city":"Arbedo",
    "sg:orig_category":"Unternehmensberatung",
    "sg:phone":"+41 91 820 11 10",
    "sg:postcode":"6517",
    "sg:province":"Ticino",
    "wof:name":"Si Cert Sagl Certificazione Di Sistemi Di Qualit\u00e0 Iso Ecc",
    "wof:placetype":"venue"
},
  "geometry": {"coordinates":[9.0454978943,46.2179069519],"type":"Point"}
}