{
  "type": "Feature",
  "properties": {
    "iso:country":"CH",
    "sg:address":"Baslerstrasse 50",
    "sg:city":"Z\u00fcrich",
    "sg:orig_category":"W\u00e4scherei U chemische Reinigung",
    "sg:phone":"+41 71 223 34 94",
    "sg:postcode":"8048",
    "sg:province":"Z\u00fcrich",
    "wof:name":"Texsana-reinigung St.gallen-heiligkreuz Ag",
    "wof:placetype":"venue"
},
  "geometry": {"coordinates":[9.3936862946,47.4407424927],"type":"Point"}
}