{
  "type": "Feature",
  "properties": {
    "iso:country":"CH",
    "sg:address":"Feldm\u00fchlestrasse 11 9400 Rorschach. Postfach",
    "sg:city":"Rorschach",
    "sg:orig_category":"Kantonalbanken",
    "sg:phone":"+41 71 231 34 00",
    "sg:postcode":"9401",
    "sg:province":"St. Gallen",
    "wof:name":"St.galler Kantonalbank",
    "wof:placetype":"venue"
},
  "geometry": {"coordinates":[9.3314723969,47.4089775085],"type":"Point"}
}