{
  "type": "Feature",
  "properties": {
    "iso:country":"CH",
    "sg:address":"Talackerstrasse 8152 Glattbrugg. Postfach",
    "sg:city":"Z\u00fcrich",
    "sg:orig_category":"Grosshandel mit Bekleidung Handelsvermittlung von Textilien, Bekleidung, Schuhen U Lederwaren",
    "sg:phone":"+41 17511117",
    "sg:postcode":"8065",
    "sg:province":"Z\u00fcrich",
    "wof:name":"Modeagentur Sch\u00f6llkopf Esther",
    "wof:placetype":"venue"
},
  "geometry": {"coordinates":[8.4432592392,47.4175300598],"type":"Point"}
}