{
  "type": "Feature",
  "properties": {
    "iso:country":"CH",
    "sg:address":"Chemin De Pierrefleur 38",
    "sg:city":"Lausanne",
    "sg:orig_category":"Drogerien Fachdetailhandel mit pharmazeutischen Produkten",
    "sg:phone":"+41 21 646 05 18",
    "sg:postcode":"1004",
    "sg:province":"Vaud",
    "wof:name":"Haroun E. Pharmacie Et Comm. De Parfumerie.",
    "wof:placetype":"venue"
},
  "geometry": {"coordinates":[6.6161108017,46.5355300903],"type":"Point"}
}