{
  "type": "Feature",
  "properties": {
    "iso:country":"CH",
    "sg:address":"Leso",
    "sg:city":"Mesocco",
    "sg:orig_category":"Schlossereien Schmieden",
    "sg:phone":"+41 91 831 16 65",
    "sg:postcode":"6563",
    "sg:province":"Graubunden",
    "wof:name":"Renzo Furger Officina Di Fabbro",
    "wof:placetype":"venue"
},
  "geometry": {"coordinates":[9.232509613,46.3926467896],"type":"Point"}
}