{
  "type": "Feature",
  "properties": {
    "iso:country":"CH",
    "sg:address":"1845",
    "sg:city":"Noville",
    "sg:orig_category":"Verwertung von Milch",
    "sg:postcode":"1845",
    "sg:province":"Vaud",
    "wof:name":"Soci\u00e9t\u00e9 De Laiterie De Nuvilly",
    "wof:placetype":"venue"
},
  "geometry": {"coordinates":[6.8926100731,46.8147010803],"type":"Point"}
}