{
  "type": "Feature",
  "properties": {
    "iso:country":"CH",
    "sg:address":"Castel Rue Du 30",
    "sg:city":"St-aubin-sauges",
    "sg:orig_category":"Herstellung von Elektrizit\u00e4tsverteilungs U schalteinrichtungen",
    "sg:phone":"+41 41 926 05 50",
    "sg:postcode":"2024",
    "sg:province":"Neuch\u00e2tel",
    "wof:name":"Renergy Ag, Mess, Steuer Und Regeltechnik",
    "wof:placetype":"venue"
},
  "geometry": {"coordinates":[8.1144742966,47.1603279114],"type":"Point"}
}