{
  "type": "Feature",
  "properties": {
    "iso:country":"CH",
    "sg:address":"Rue Du Chasseron",
    "sg:city":"Payerne",
    "sg:orig_category":"Unclassifiable Establishments",
    "sg:postcode":"1530",
    "sg:province":"Vaud",
    "wof:name":"Les Grandes Rayes C Sa",
    "wof:placetype":"venue"
},
  "geometry": {"coordinates":[6.9284749031,46.8212394714],"type":"Point"}
}