{
  "type": "Feature",
  "properties": {
    "iso:country":"CH",
    "sg:address":"Bei Der Kirche",
    "sg:city":"Br\u00fclisau",
    "sg:orig_category":"Detailhandel mit Waren verschiedener Art, Hauptrichtung Nahrungsmittel",
    "sg:phone":"+41 71 799 15 55",
    "sg:postcode":"9058",
    "sg:province":"Appenzell Innerhoden",
    "wof:name":"Johann Sutter Lebensmittel",
    "wof:placetype":"venue"
},
  "geometry": {"coordinates":[9.4545249939,47.2966156006],"type":"Point"}
}