{
  "type": "Feature",
  "properties": {
    "iso:country":"CH",
    "sg:address":"Dorfstrasse 38",
    "sg:city":"Halden",
    "sg:orig_category":"Unclassifiable Establishments",
    "sg:postcode":"9223",
    "sg:province":"Thurgau",
    "wof:name":"Guido Pfister Transporte",
    "wof:placetype":"venue"
},
  "geometry": {"coordinates":[9.2083587646,47.5055923462],"type":"Point"}
}