{
  "type": "Feature",
  "properties": {
    "iso:country":"CH",
    "sg:address":"Bruy\u00e8re Chemin De La 32",
    "sg:city":"Prangins",
    "sg:orig_category":"Hardwareberatung",
    "sg:phone":"+41 79 232 18 18",
    "sg:postcode":"1197",
    "sg:province":"Vaud",
    "wof:name":"Vap Diffusion, C. Dalla Palma",
    "wof:placetype":"venue"
},
  "geometry": {"coordinates":[5.1808700562,45.8973388672],"type":"Point"}
}