{
  "type": "Feature",
  "properties": {
    "iso:country":"CH",
    "sg:address":"Via Agostino Maspoli 51 6850 Mendrisio Casella Postale 5",
    "sg:city":"Mendrisio",
    "sg:orig_category":"Fachdetailhandel in Verkaufsr\u00e4umen Herstellung U Zusammensetzung von Uhren",
    "sg:phone":"+41 91 646 35 78",
    "sg:postcode":"6850",
    "sg:province":"Ticino",
    "wof:name":"Terna Sa",
    "wof:placetype":"venue"
},
  "geometry": {"coordinates":[8.9880838394,45.870098114],"type":"Point"}
}