{
  "type": "Feature",
  "properties": {
    "iso:country":"CH",
    "sg:address":"Untere Halde 11",
    "sg:city":"Baden",
    "sg:orig_category":"Interessenvertretungen",
    "sg:phone":"+41 56 430 03 40",
    "sg:postcode":"5400",
    "sg:province":"Aargau",
    "wof:name":"Ht Marketing Gmbh",
    "wof:placetype":"venue"
},
  "geometry": {"coordinates":[8.3096818924,47.4721946716],"type":"Point"}
}