{
  "type": "Feature",
  "properties": {
    "iso:country":"CH",
    "sg:address":"Planachaux",
    "sg:city":"Champ\u00e9ry",
    "sg:classifiers":[
        {
            "category":"Restaurant",
            "type":"Food & Drink"
        }
    ],
    "sg:phone":"+41 21 634 69 20",
    "sg:postcode":"1874",
    "sg:province":"Valais",
    "wof:name":"Caf\u00e9 Le Coin Internetcaf\u00e9",
    "wof:placetype":"venue"
},
  "geometry": {"coordinates":[6.5901389122,46.529258728],"type":"Point"}
}