{
  "type": "Feature",
  "properties": {
    "iso:country":"CH",
    "sg:address":"Bernstrasse 67 3122 Kehrsatz. Postfach",
    "sg:city":"Kehrsatz",
    "sg:orig_category":"Unternehmensberatung",
    "sg:phone":"+41 31 961 29 64",
    "sg:postcode":"3122",
    "sg:province":"Bern",
    "wof:name":"Rdp Gmbh",
    "wof:placetype":"venue"
},
  "geometry": {"coordinates":[7.468457222,46.9138374329],"type":"Point"}
}