{
  "type": "Feature",
  "properties": {
    "iso:country":"CH",
    "sg:address":"Geiselfeldstrasse 1",
    "sg:city":"Gerlafingen",
    "sg:orig_category":"G\u00fcterbef\u00f6rderung im Strassenverkehr",
    "sg:phone":"+41 32 675 14 25",
    "sg:postcode":"4563",
    "sg:province":"Solothurn",
    "wof:name":"Salamanca Giuseppe",
    "wof:placetype":"venue"
},
  "geometry": {"coordinates":[7.576072216,47.1702537537],"type":"Point"}
}