{
  "type": "Feature",
  "properties": {
    "iso:country":"CH",
    "sg:address":"Rosengartenstrasse 178",
    "sg:city":"Gontenschwil",
    "sg:classifiers":[
        {
            "category":"Restaurant",
            "type":"Food & Drink"
        }
    ],
    "sg:phone":"+41 62 773 12 26",
    "sg:postcode":"5728",
    "sg:province":"Aargau",
    "wof:name":"Restaurant Helvetia",
    "wof:placetype":"venue"
},
  "geometry": {"coordinates":[8.1469583511,47.2720489502],"type":"Point"}
}