{
  "type": "Feature",
  "properties": {
    "iso:country":"CH",
    "sg:address":"Monbijoustrasse 120 3007 Bern. Postfach 8154",
    "sg:city":"Bern",
    "sg:orig_category":"Interessenvertretungen U sonstige Vereinigungen Organisationen der Wohlfahrtspflege",
    "sg:phone":"+41 31 370 75 75",
    "sg:postcode":"3001",
    "sg:province":"Bern",
    "wof:name":"Schweiz.fl\u00fcchtlingshilfe",
    "wof:placetype":"venue"
},
  "geometry": {"coordinates":[7.4364719391,46.9361572266],"type":"Point"}
}