{
  "type": "Feature",
  "properties": {
    "iso:country":"CH",
    "sg:address":"1041",
    "sg:city":"Poliez-le-grand",
    "sg:orig_category":"Interessenvertretungen U sonstige Vereinigungen",
    "sg:postcode":"1041",
    "sg:province":"Vaud",
    "wof:name":"Ass.vaudoise Judo & Ju-jitsu",
    "wof:placetype":"venue"
},
  "geometry": {"coordinates":[6.6645698547,46.6371917725],"type":"Point"}
}