{
  "type": "Feature",
  "properties": {
    "iso:country":"CH",
    "sg:address":"Corso San Gottardo 54b 6830 Chiasso. Postfach",
    "sg:city":"Chiasso",
    "sg:orig_category":"Allgemeiner Hoch U Tiefbau",
    "sg:postcode":"6830",
    "sg:province":"Ticino",
    "wof:name":"Ico Sa Lavori D. Genio Civile, Lavori Di Sopra- E Sottostruttura, Spec. Costruz. Di Strade Ecc",
    "wof:placetype":"venue"
},
  "geometry": {"coordinates":[9.028363,45.835094],"type":"Point"}
}