{
  "type": "Feature",
  "properties": {
    "iso:country":"CH",
    "sg:address":"Via Trevano 23",
    "sg:city":"Lugano",
    "sg:orig_category":"Primarschulen",
    "sg:postcode":"6900",
    "sg:province":"Ticino",
    "wof:name":"Scuola Elementare Molino Nuovo",
    "wof:placetype":"venue"
},
  "geometry": {"coordinates":[8.9550876617,46.0148391724],"type":"Point"}
}