{
  "type": "Feature",
  "properties": {
    "iso:country":"CH",
    "sg:address":"Zentralstrasse 45",
    "sg:city":"Luzern",
    "sg:orig_category":"Rechtsberatung",
    "sg:phone":"+41 61 831 46 36",
    "sg:postcode":"6003",
    "sg:province":"Luzern",
    "wof:name":"Chermaco Ag",
    "wof:placetype":"venue"
},
  "geometry": {"coordinates":[8.3098945618,47.0461921692],"type":"Point"}
}