{
  "type": "Feature",
  "properties": {
    "iso:country":"CH",
    "sg:address":"Leuholz 21",
    "sg:city":"Wangen",
    "sg:orig_category":"Ceiling Formworks",
    "sg:phone":"+41 55 440 80 87",
    "sg:postcode":"8855",
    "sg:province":"Schwyz",
    "wof:name":"Paschal Ag",
    "wof:placetype":"venue"
},
  "geometry": {"coordinates":[8.879512,47.195332],"type":"Point"}
}