{
  "type": "Feature",
  "properties": {
    "iso:country":"CH",
    "sg:address":"1323 Romainm\u00f4tier. Postfach",
    "sg:city":"Romainm\u00f4tier",
    "sg:orig_category":"Zimmerei, Dachdeckerei, Bauspenglerei U Abdichtung",
    "sg:postcode":"1323",
    "sg:province":"Vaud",
    "wof:name":"B\u00e2tinozon S\u00e0rl",
    "wof:placetype":"venue"
},
  "geometry": {"coordinates":[6.4607200623,46.6934509277],"type":"Point"}
}