{
  "type": "Feature",
  "properties": {
    "iso:country":"CH",
    "sg:address":"Rheinstr. 38",
    "sg:city":"Igis",
    "sg:orig_category":"Sonstige mit Sport verbundene T\u00e4tigkeiten",
    "sg:postcode":"7206",
    "sg:province":"Graubunden",
    "wof:name":"Alfa Romeo Club Graub\u00fcnden (arcg)",
    "wof:placetype":"venue"
},
  "geometry": {"coordinates":[9.5733108521,46.9458618164],"type":"Point"}
}