{
  "type": "Feature",
  "properties": {
    "addr:full":"Route Du Nant-d'avril 56 Vernier Gen\u00e8ve 1214",
    "addr:housenumber":"56",
    "addr:postcode":"1214",
    "addr:street":"Route Du Nant-D'Avril",
    "iso:country":"CH",
    "sg:address":"Route Du Nant-d'avril 56",
    "sg:city":"Vernier",
    "sg:classifiers":[
        {
            "category":"Professional",
            "subcategory":"Advertising",
            "type":"Services"
        }
    ],
    "sg:phone":"+41 22 341 13 22",
    "sg:postcode":"1214",
    "sg:province":"Gen\u00e8ve",
    "sg:tags":[
        "imprint"
    ],
    "wof:name":"Imprimerie Lenzi Sa",
    "wof:placetype":"venue"
},
  "geometry": {"coordinates":[6.08047,46.212341],"type":"Point"}
}