{
  "type": "Feature",
  "properties": {
    "iso:country":"CH",
    "sg:address":"Kirchweg 5",
    "sg:city":"Konolfingen",
    "sg:orig_category":"Softwareentwicklung U beratung",
    "sg:phone":"+41 71 477 35 85",
    "sg:postcode":"3510",
    "sg:province":"Bern",
    "wof:name":"Kuschko Consulting Gmbh",
    "wof:placetype":"venue"
},
  "geometry": {"coordinates":[7.6197309494,46.8775100708],"type":"Point"}
}