{
  "type": "Feature",
  "properties": {
    "iso:country":"CH",
    "sg:address":"Aeschenplatz 2",
    "sg:city":"Basel",
    "sg:orig_category":"Saunas, Solarien, Fitnesszentren U \u00e4hnliches Solarien",
    "sg:phone":"+41 61 271 67 57",
    "sg:postcode":"4052",
    "sg:province":"Basel-Stadt",
    "wof:name":"Sun Line Solarium Studio Breitenmoser J.",
    "wof:placetype":"venue"
},
  "geometry": {"coordinates":[7.5956292152,47.551235199],"type":"Point"}
}