{
  "type": "Feature",
  "properties": {
    "iso:country":"CH",
    "sg:address":"Weierstrasse 10",
    "sg:city":"Oberb\u00fcren",
    "sg:orig_category":"Herstellung von Konstruktionsteilen, Fertigbauteilen U Ausbauelementen aus Holz",
    "sg:phone":"+41 31 839 85 85",
    "sg:postcode":"9245",
    "sg:province":"St. Gallen",
    "wof:name":"R\u00fcfenacht Ag Schreinerei",
    "wof:placetype":"venue"
},
  "geometry": {"coordinates":[7.5292420387,46.936580658],"type":"Point"}
}