{
  "type": "Feature",
  "properties": {
    "iso:country":"CH",
    "sg:address":"Industriestrasse 24 6300 Zug. Postfach 2303",
    "sg:city":"Zug",
    "sg:orig_category":"Dienstleistungen von Beteiligungsgesellschaften",
    "sg:phone":"+41 41 729 01 01",
    "sg:postcode":"6302",
    "sg:province":"Zug",
    "wof:name":"Aureus Management Ag",
    "wof:placetype":"venue"
},
  "geometry": {"coordinates":[8.519452095,47.1751670837],"type":"Point"}
}