{
  "type": "Feature",
  "properties": {
    "iso:country":"CH",
    "sg:address":"Place De La Gare 25 2800 Del\u00e9mont Case Postale",
    "sg:city":"Delsberg",
    "sg:orig_category":"Grosshandel mit lebenden Tieren",
    "sg:postcode":"2800",
    "sg:province":"Jura",
    "wof:name":"Meyer Camille B\u00e9tails; Achat, Vente, Comm.",
    "wof:placetype":"venue"
},
  "geometry": {"coordinates":[7.3494381905,47.362247467],"type":"Point"}
}