{
  "type": "Feature",
  "properties": {
    "iso:country":"CH",
    "sg:address":"Zentralstrasse 89 2503 Biel/bienne. Postfach 1146",
    "sg:city":"Biel/bienne",
    "sg:orig_category":"Einbau von Schreinerwaren Verlegen von Fliesen U Platten",
    "sg:phone":"+41 32 328 28 28",
    "sg:postcode":"2501",
    "sg:province":"Bern",
    "wof:name":"Sabag Ag Biel",
    "wof:placetype":"venue"
},
  "geometry": {"coordinates":[7.249475956,47.1343727112],"type":"Point"}
}