{
  "type": "Feature",
  "properties": {
    "iso:country":"CH",
    "sg:address":"Schochenhauserzelg 14",
    "sg:city":"Egnach",
    "sg:orig_category":"Herstellung von Metallkonstruktionen",
    "sg:postcode":"9322",
    "sg:province":"Thurgau",
    "wof:name":"M\u00fcller H.r. Aussen Und Innenisolationen",
    "wof:placetype":"venue"
},
  "geometry": {"coordinates":[9.3818778992,47.5442619324],"type":"Point"}
}