{
  "type": "Feature",
  "properties": {
    "iso:country":"CH",
    "sg:address":"Hauptstrasse 74",
    "sg:city":"B\u00f6nigen",
    "sg:orig_category":"Sonstiges Versicherungsgewerbe",
    "sg:phone":"+41 31 781 05 58",
    "sg:postcode":"3806",
    "sg:province":"Bern",
    "wof:name":"Emmentalische Mobiliarversich. Agentur Klaus & Sylvia Zwahlen",
    "wof:placetype":"venue"
},
  "geometry": {"coordinates":[7.5562500954,46.8115386963],"type":"Point"}
}