{
  "type": "Feature",
  "properties": {
    "iso:country":"CH",
    "sg:address":"Lettenstrasse 8",
    "sg:city":"Rotkreuz",
    "sg:orig_category":"Offsetdruck Satzherstellung U Reproduktion",
    "sg:phone":"+41 22 342 04 05",
    "sg:postcode":"6343",
    "sg:province":"Zug",
    "wof:name":"Andr\u00e9 Reymond Photocomposition Arp",
    "wof:placetype":"venue"
},
  "geometry": {"coordinates":[6.1455068588,46.1831054688],"type":"Point"}
}