{
  "type": "Feature",
  "properties": {
    "iso:country":"CH",
    "sg:address":"Rittergasse 35 4051 Basel. Postfach Postfach",
    "sg:city":"Basel",
    "sg:orig_category":"G\u00fcterbef\u00f6rderung im Strassenverkehr Sonstige Verkehrsvermittlung",
    "sg:phone":"+41 61 270 92 30",
    "sg:postcode":"4010",
    "sg:province":"Basel-Stadt",
    "wof:name":"Central Station Ag",
    "wof:placetype":"venue"
},
  "geometry": {"coordinates":[7.5945091248,47.554889679],"type":"Point"}
}