{
  "type": "Feature",
  "properties": {
    "iso:country":"CH",
    "sg:address":"Via Mottarone 3",
    "sg:city":"Bellinzona",
    "sg:orig_category":"Grosshandel mit sonstigen Maschinen U Ausr\u00fcstungen f\u00fcr Industrie, Handel U Schiffahrt Sonstiger Gros",
    "sg:postcode":"6503",
    "sg:province":"Ticino",
    "wof:name":"Fidamacc Sa",
    "wof:placetype":"venue"
},
  "geometry": {"coordinates":[9.0315380096,46.2130508423],"type":"Point"}
}