{
  "type": "Feature",
  "properties": {
    "iso:country":"CH",
    "sg:address":"Feldstrasse 61",
    "sg:city":"Thalwil",
    "sg:orig_category":"Unternehmensberatung",
    "sg:phone":"+41 17206547",
    "sg:postcode":"8800",
    "sg:province":"Z\u00fcrich",
    "wof:name":"Hattich M. K. & Co",
    "wof:placetype":"venue"
},
  "geometry": {"coordinates":[8.5580797195,47.2891311646],"type":"Point"}
}