{
  "type": "Feature",
  "properties": {
    "iso:country":"CH",
    "sg:address":"Waldeggstrasse 34 3800 Interlaken. Postfach 377",
    "sg:city":"Interlaken",
    "sg:orig_category":"Vermietung von Automobilen",
    "sg:phone":"+41 33 822 19 39",
    "sg:postcode":"3800",
    "sg:province":"Bern",
    "wof:name":"Holk Oertel Waldegg-garage",
    "wof:placetype":"venue"
},
  "geometry": {"coordinates":[7.8553481102,46.6799812317],"type":"Point"}
}