{
  "type": "Feature",
  "properties": {
    "iso:country":"CH",
    "sg:address":"Zugerstrasse 9 6030 Ebikon. Postfach",
    "sg:city":"Ebikon",
    "sg:orig_category":"Pensionskassen",
    "sg:postcode":"6030",
    "sg:province":"Luzern",
    "wof:name":"Hofer-stiftung Albert",
    "wof:placetype":"venue"
},
  "geometry": {"coordinates":[8.3495168686,47.0870475769],"type":"Point"}
}