{
  "type": "Feature",
  "properties": {
    "iso:country":"CH",
    "sg:address":"R\u00fcchligstrasse 10 8953 Dietikon. Postfach 638",
    "sg:city":"Dietikon",
    "sg:orig_category":"Spezieller Tiefbau",
    "sg:phone":"+41 17557777",
    "sg:postcode":"8953",
    "sg:province":"Z\u00fcrich",
    "wof:name":"H\u00e4chler-reutlinger Ag Kanal-& Schachtreinigung",
    "wof:placetype":"venue"
},
  "geometry": {"coordinates":[8.4066972733,47.4099998474],"type":"Point"}
}