{
  "type": "Feature",
  "properties": {
    "iso:country":"CH",
    "sg:address":"R\u00fctistrasse 3a 5400 Baden. Postfach 359",
    "sg:city":"Baden",
    "sg:orig_category":"Wirtschaftspr\u00fcfung, Steuerberatung U Treuhand",
    "sg:phone":"+41 56 221 67 67",
    "sg:postcode":"5401",
    "sg:province":"Aargau",
    "wof:name":"Gefon Ag Treuhandb\u00fcro",
    "wof:placetype":"venue"
},
  "geometry": {"coordinates":[8.3055257797,47.4746665955],"type":"Point"}
}