{
  "type": "Feature",
  "properties": {
    "iso:country":"CH",
    "sg:address":"Baarerstrasse 19",
    "sg:city":"Zug",
    "sg:orig_category":"Detailhandel mit Getr\u00e4nken",
    "sg:phone":"+41 41 712 06 08",
    "sg:postcode":"6300",
    "sg:province":"Zug",
    "wof:name":"Weinkiste St. Jakob",
    "wof:placetype":"venue"
},
  "geometry": {"coordinates":[8.516125679,47.1720924377],"type":"Point"}
}