{
  "type": "Feature",
  "properties": {
    "iso:country":"CH",
    "sg:address":"Glennerstrasse 10",
    "sg:city":"Ilanz",
    "sg:orig_category":"Detailhandel mit Schreib U Papeteriewaren Detailhandel mit Spielwaren",
    "sg:phone":"+41 81 925 61 00",
    "sg:postcode":"7130",
    "sg:province":"Graubunden",
    "wof:name":"Box Stores Robert Tschuor",
    "wof:placetype":"venue"
},
  "geometry": {"coordinates":[9.2063398361,46.7740936279],"type":"Point"}
}