{
  "type": "Feature",
  "properties": {
    "iso:country":"CH",
    "sg:address":"Waldeggstrasse 49",
    "sg:city":"Interlaken",
    "sg:classifiers":[
        {
            "category":"Professional",
            "subcategory":"Computer Services",
            "type":"Services"
        }
    ],
    "sg:phone":"+41 33 821 02 65",
    "sg:postcode":"3800",
    "sg:province":"Bern",
    "sg:tags":[
        "development",
        "software"
    ],
    "wof:name":"Mime-informatik + Elektronik",
    "wof:placetype":"venue"
},
  "geometry": {"coordinates":[7.8569297791,46.6812515259],"type":"Point"}
}