{
  "type": "Feature",
  "properties": {
    "iso:country":"CH",
    "sg:address":"Rue Du Perron 5",
    "sg:city":"Coppet",
    "sg:orig_category":"Arztpraxen",
    "sg:phone":"+41 22 776 40 25",
    "sg:postcode":"1296",
    "sg:province":"Vaud",
    "wof:name":"Dr M\u00e9d. Jean-claude Volant M\u00e9decin G\u00e9n\u00e9raliste",
    "wof:placetype":"venue"
},
  "geometry": {"coordinates":[6.192234,46.316174],"type":"Point"}
}