{
  "type": "Feature",
  "properties": {
    "iso:country":"CH",
    "sg:address":"Kurzenerchingerstrasse 1",
    "sg:city":"Frauenfeld",
    "sg:orig_category":"Veterin\u00e4rwesen",
    "sg:phone":"+41 52 654 16 26",
    "sg:postcode":"8500",
    "sg:province":"Thurgau",
    "wof:name":"Dr.med.vet. Brigitta Monhart Tierarztpraxis Gr\u00fcntal",
    "wof:placetype":"venue"
},
  "geometry": {"coordinates":[8.7042856216,47.6614341736],"type":"Point"}
}