{
  "type": "Feature",
  "properties": {
    "iso:country":"CH",
    "sg:address":"Feldstrasse 111",
    "sg:city":"Z\u00fcrich",
    "sg:orig_category":"Vereine Gemeinn\u00fctzige",
    "sg:phone":"+41 41 870 25 93",
    "sg:postcode":"8004",
    "sg:province":"Z\u00fcrich",
    "wof:name":"H\u00f6rbehinderten Verein Uri",
    "wof:placetype":"venue"
},
  "geometry": {"coordinates":[8.6171979904,46.881942749],"type":"Point"}
}