{
  "type": "Feature",
  "properties": {
    "addr:full":"Papierm\u00fchlestrasse 130 Ittigen Bern 3063",
    "addr:housenumber":"130",
    "addr:postcode":"3063",
    "addr:street":"Papiermuehlestrasse",
    "iso:country":"CH",
    "sg:address":"Papierm\u00fchlestrasse 130",
    "sg:city":"Ittigen",
    "sg:orig_category":"Berufliche Weiterbildung, Erwachsenenbildung Softwareentwicklung U beratung",
    "sg:phone":"+41 31 633 29 11",
    "sg:postcode":"3063",
    "sg:province":"Bern",
    "wof:name":"Bedag Informatik Bedag Computer College",
    "wof:placetype":"venue"
},
  "geometry": {"coordinates":[7.47183,46.971142],"type":"Point"}
}