{
  "type": "Feature",
  "properties": {
    "iso:country":"CH",
    "sg:address":"Bederstrasse 109",
    "sg:city":"Z\u00fcrich",
    "sg:classifiers":[
        {
            "category":"Professional",
            "subcategory":"Advertising",
            "type":"Services"
        }
    ],
    "sg:phone":"+41 12857878",
    "sg:postcode":"8002",
    "sg:province":"Z\u00fcrich",
    "sg:tags":[
        "poster"
    ],
    "wof:name":"J. E. Wolfensberger Ag",
    "wof:placetype":"venue"
},
  "geometry": {"coordinates":[8.525536,47.361038],"type":"Point"}
}