{
  "type": "Feature",
  "properties": {
    "iso:country":"CH",
    "sg:address":"Kartausstrasse 8008 Z\u00fcrich. Postfach",
    "sg:city":"Z\u00fcrich",
    "sg:orig_category":"Architektur U Ingenieurb\u00fcros",
    "sg:phone":"+41 14201300",
    "sg:postcode":"8008",
    "sg:province":"Z\u00fcrich",
    "wof:name":"Ormec Systems Corp., Rochester (newyork, Usa), Zweigniederlassung Z\u00fcrich",
    "wof:placetype":"venue"
},
  "geometry": {"coordinates":[8.567122,47.356968],"type":"Point"}
}