{
  "type": "Feature",
  "properties": {
    "iso:country":"CH",
    "sg:address":"Lausanne Rue De 67 1202 Gen\u00e8ve. Postfach",
    "sg:city":"Gen\u00e8ve",
    "sg:orig_category":"Detailhandel mit Bekleidung",
    "sg:postcode":"1202",
    "sg:province":"Gen\u00e8ve",
    "wof:name":"Avermaete Daria V\u00eatements; Importation Et Vente",
    "wof:placetype":"venue"
},
  "geometry": {"coordinates":[6.147376,46.216225],"type":"Point"}
}