{
  "type": "Feature",
  "properties": {
    "iso:country":"CH",
    "sg:address":"Obere Bahnhofstrasse 13 5507 Mellingen. Postfach 103",
    "sg:city":"Mellingen",
    "sg:orig_category":"Herstellung von konfektionierten Textilwaren ohne Bekleidung",
    "sg:phone":"+41 56 491 02 00",
    "sg:postcode":"5507",
    "sg:province":"Aargau",
    "wof:name":"Storosol Mellingen Gmbh",
    "wof:placetype":"venue"
},
  "geometry": {"coordinates":[8.2721204758,47.4292144775],"type":"Point"}
}