{
  "type": "Feature",
  "properties": {
    "iso:country":"CH",
    "sg:address":"Dorfstrasse 19",
    "sg:city":"Steckborn",
    "sg:orig_category":"Allgemeiner Hoch U Tiefbau Hoch U Tiefbau",
    "sg:phone":"+41 52 761 14 87",
    "sg:postcode":"8266",
    "sg:province":"Thurgau",
    "wof:name":"Traber Bauunternehmung Ag",
    "wof:placetype":"venue"
},
  "geometry": {"coordinates":[8.985476,47.664448],"type":"Point"}
}