{
  "type": "Feature",
  "properties": {
    "iso:country":"CH",
    "sg:address":"Seestrasse 513",
    "sg:city":"Z\u00fcrich",
    "sg:orig_category":"Betrieb U technische Hilfsdienste des Kultur U Unterhaltungswesens",
    "sg:postcode":"8038",
    "sg:province":"Z\u00fcrich",
    "wof:name":"Blue Balls Music Gmbh",
    "wof:placetype":"venue"
},
  "geometry": {"coordinates":[8.53943,47.336937],"type":"Point"}
}