{
  "type": "Feature",
  "properties": {
    "iso:country":"CH",
    "sg:address":"Schulstrasse 44 8050 Z\u00fcrich. Postfach 579",
    "sg:city":"Z\u00fcrich",
    "sg:orig_category":"Kosmetikinstitute Sonstiges Gesundheitswesen",
    "sg:phone":"+41 13173090",
    "sg:postcode":"8037",
    "sg:province":"Z\u00fcrich",
    "wof:name":"Abaris Wellness Club Im Swissotel Abaris Gmbh",
    "wof:placetype":"venue"
},
  "geometry": {"coordinates":[8.543592453,47.4107627869],"type":"Point"}
}