{
  "type": "Feature",
  "properties": {
    "iso:country":"CH",
    "sg:address":"Falknerstrasse 26",
    "sg:city":"Basel",
    "sg:orig_category":"Wirtschafts- and Arbeitgeberverb\u00e4nde",
    "sg:phone":"+41 55 644 20 12",
    "sg:postcode":"4001",
    "sg:province":"Basel-Stadt",
    "wof:name":"Aerzteges.des Kantons Glarus Pr\u00e4s.hrn Dr.med.peter Kamm",
    "wof:placetype":"venue"
},
  "geometry": {"coordinates":[9.0752897263,46.9953117371],"type":"Point"}
}