{
  "type": "Feature",
  "properties": {
    "iso:country":"CH",
    "sg:address":"Neuengasse 37 3011 Bern. Postfach",
    "sg:city":"Bern",
    "sg:orig_category":"Allgemeinbildende weiterf\u00fchrende Schulen",
    "sg:phone":"+41 31111896",
    "sg:postcode":"3005",
    "sg:province":"Bern",
    "wof:name":"B\u00e9n\u00e9dict-schule, J. Bernhard",
    "wof:placetype":"venue"
},
  "geometry": {"coordinates":[7.441666,46.948986],"type":"Point"}
}