{
  "type": "Feature",
  "properties": {
    "iso:country":"CH",
    "sg:address":"Rosenweg 8b 6340 Baar. Postfach 2635",
    "sg:city":"Zug",
    "sg:orig_category":"Rechtsberatung Steuerberatung",
    "sg:phone":"+41 41 763 69 44",
    "sg:postcode":"6302",
    "sg:province":"Zug",
    "wof:name":"Adrian Muster Dipl. Steuerexperte",
    "wof:placetype":"venue"
},
  "geometry": {"coordinates":[8.5225639343,47.1859931946],"type":"Point"}
}