{
  "type": "Feature",
  "properties": {
    "iso:country":"CH",
    "sg:address":"Oberdorf 195",
    "sg:city":"Hellikon",
    "sg:orig_category":"Bauschreinerei",
    "sg:phone":"+41 61 871 04 67",
    "sg:postcode":"4316",
    "sg:province":"Aargau",
    "wof:name":"Heinz Hasler Schreinerei",
    "wof:placetype":"venue"
},
  "geometry": {"coordinates":[7.916234,47.508125],"type":"Point"}
}