{
  "type": "Feature",
  "properties": {
    "iso:country":"CH",
    "sg:address":"Ch. Des Muscadelles 1185 Mont-sur-rolle Case Postale 66",
    "sg:city":"Mont-sur-rolle",
    "sg:orig_category":"Non-Classified Establishments",
    "sg:phone":"+41 21 825 48 48",
    "sg:postcode":"1185",
    "sg:province":"Vaud",
    "wof:name":"Fontana Michel",
    "wof:placetype":"venue"
},
  "geometry": {"coordinates":[6.3389229774,46.4751167297],"type":"Point"}
}