{
  "type": "Feature",
  "properties": {
    "iso:country":"CH",
    "sg:address":"Allschwilerstrasse 31 4054 Basel. Postfach",
    "sg:city":"Basel",
    "sg:orig_category":"Grosshandel mit Getr\u00e4nken Grosshandel mit Wein U Spirituosen",
    "sg:phone":"+41 61 711 65 83",
    "sg:postcode":"4009",
    "sg:province":"Basel-Stadt",
    "wof:name":"Wiener Weinhof Gmbh",
    "wof:placetype":"venue"
},
  "geometry": {"coordinates":[7.5979452133,47.490978241],"type":"Point"}
}