{
  "type": "Feature",
  "properties": {
    "iso:country":"CH",
    "sg:address":"Rue De Lyon 21",
    "sg:city":"Gen\u00e8ve",
    "sg:orig_category":"Detailhandel mit Fahrr\u00e4dern Reparatur von sonstigen Gebrauchsg\u00fctern",
    "sg:phone":"+41 22 344 07 30",
    "sg:postcode":"1201",
    "sg:province":"Gen\u00e8ve",
    "wof:name":"Bs Bikes",
    "wof:placetype":"venue"
},
  "geometry": {"coordinates":[6.1377639771,46.2088699341],"type":"Point"}
}