{
  "type": "Feature",
  "properties": {
    "iso:country":"CH",
    "sg:address":"Eisengasse 9 8008 Z\u00fcrich. Postfach",
    "sg:city":"Z\u00fcrich",
    "sg:orig_category":"Architektur U Ingenieurb\u00fcros",
    "sg:phone":"+41 12669211",
    "sg:postcode":"8008",
    "sg:province":"Z\u00fcrich",
    "wof:name":"Domostatik Ag",
    "wof:placetype":"venue"
},
  "geometry": {"coordinates":[8.551344,47.362694],"type":"Point"}
}