{
  "type": "Feature",
  "properties": {
    "iso:country":"CH",
    "sg:address":"Piazza Ponte 7 6850 Mendrisio. Postfach",
    "sg:city":"Mendrisio",
    "sg:orig_category":"Fachdetailhandel mit pharmazeutischen Produkten",
    "sg:phone":"+41 62 771 10 38",
    "sg:postcode":"6850",
    "sg:province":"Ticino",
    "wof:name":"Dr. Franz Kesselring, Central-apotheke Reinach (aarg.)",
    "wof:placetype":"venue"
},
  "geometry": {"coordinates":[8.1832437515,47.2529830933],"type":"Point"}
}