{
  "type": "Feature",
  "properties": {
    "iso:country":"CH",
    "sg:address":"Bachstrasse 2",
    "sg:city":"Lenzburg",
    "sg:orig_category":"Mahl U Sch\u00e4lm\u00fchlen",
    "sg:phone":"+41 62 891 27 71",
    "sg:postcode":"5600",
    "sg:province":"Aargau",
    "wof:name":"Ad. Remund Ag M\u00fchle",
    "wof:placetype":"venue"
},
  "geometry": {"coordinates":[8.1763782501,47.3879089355],"type":"Point"}
}