{
  "type": "Feature",
  "properties": {
    "iso:country":"CH",
    "sg:address":"Grossenacherstrasse 36",
    "sg:city":"Gutenswil",
    "sg:orig_category":"Bauspenglerei Herstellung von Metallerzeugnissen ohne Maschinenbau",
    "sg:phone":"+41 19459030",
    "sg:postcode":"8605",
    "sg:province":"Z\u00fcrich",
    "wof:name":"Kuchelmeister Blechverarbeitung Ag",
    "wof:placetype":"venue"
},
  "geometry": {"coordinates":[8.71823,47.3815],"type":"Point"}
}