{
  "type": "Feature",
  "properties": {
    "iso:country":"CH",
    "sg:address":"Im Langhag 19",
    "sg:city":"Effretikon",
    "sg:orig_category":"Grosshandel mit landwirtschaftlichen Maschinen U Ger\u00e4ten Grosshandel mit sonstigen Maschinen U Ausr\u00fc",
    "sg:phone":"+41 52 355 35 35",
    "sg:postcode":"8307",
    "sg:province":"Z\u00fcrich",
    "wof:name":"Altor Ag",
    "wof:placetype":"venue"
},
  "geometry": {"coordinates":[8.6883687973,47.4395675659],"type":"Point"}
}