{
  "type": "Feature",
  "properties": {
    "iso:country":"CH",
    "sg:address":"Quadras Sut",
    "sg:city":"Sumvitg",
    "sg:orig_category":"Sanit\u00e4r, Heizungs U L\u00fcftungsinstallation",
    "sg:postcode":"7175",
    "sg:province":"Graubunden",
    "wof:name":"Bearth Haustechnik",
    "wof:placetype":"venue"
},
  "geometry": {"coordinates":[8.9354305267,46.726360321],"type":"Point"}
}