{
  "type": "Feature",
  "properties": {
    "iso:country":"CH",
    "sg:address":"St.-antons-gasse 4a",
    "sg:city":"Zug",
    "sg:orig_category":"Unclassifiable Establishments",
    "sg:postcode":"6300",
    "sg:province":"Zug",
    "wof:name":"Aldon Ag",
    "wof:placetype":"venue"
},
  "geometry": {"coordinates":[8.5165901184,47.1672706604],"type":"Point"}
}