{
  "type": "Feature",
  "properties": {
    "iso:country":"CH",
    "sg:address":"Koblenzerstrasse 99",
    "sg:city":"Koblenz",
    "sg:classifiers":[
        {
            "category":"Autos & Motor Vehicles",
            "subcategory":"Auto Supplies",
            "type":"Retail Goods"
        }
    ],
    "sg:phone":"+41 56 246 16 33",
    "sg:postcode":"5322",
    "sg:province":"Aargau",
    "sg:tags":[
        "automobile",
        "accessory"
    ],
    "wof:name":"Spica Ag",
    "wof:placetype":"venue"
},
  "geometry": {"coordinates":[8.228685,47.596668],"type":"Point"}
}