{
  "type": "Feature",
  "properties": {
    "iso:country":"CH",
    "sg:address":"Moncor Route De 2",
    "sg:city":"Villars-sur-gl\u00e2ne",
    "sg:orig_category":"Unternehmensberatung",
    "sg:phone":"+41 31 351 81 51",
    "sg:postcode":"1752",
    "sg:province":"Fribourg",
    "wof:name":"Elasa Ag Wirtschafts- U Handelsberatungen",
    "wof:placetype":"venue"
},
  "geometry": {"coordinates":[7.4738268852,46.9448471069],"type":"Point"}
}