{
  "type": "Feature",
  "properties": {
    "iso:country":"CH",
    "sg:address":"Weiherfeldstrasse 3",
    "sg:city":"Rheinfelden",
    "sg:orig_category":"Detailhandel mit Haustieren U zoologischem Bedarf",
    "sg:phone":"+41 31 747 70 70",
    "sg:postcode":"4310",
    "sg:province":"Aargau",
    "wof:name":"H. & A. Mauerhofer Bio Katzen-& Hundefutter",
    "wof:placetype":"venue"
},
  "geometry": {"coordinates":[7.2392859459,46.9097671509],"type":"Point"}
}