{
  "type": "Feature",
  "properties": {
    "addr:full":"Principala Voa 26 7078 Lenzerheide/lai. Postfach Lenzerheide/lai Graubunden 7078",
    "addr:housenumber":"26",
    "addr:postcode":"7078;postfach;7078",
    "addr:street":"Voa",
    "iso:country":"CH",
    "sg:address":"Principala Voa 26 7078 Lenzerheide/lai. Postfach",
    "sg:city":"Lenzerheide/lai",
    "sg:orig_category":"Abwasserreinigung, Abfallbeseitigung U sonstige Entsorgung",
    "sg:phone":"+41 71 966 44 64",
    "sg:postcode":"7078",
    "sg:province":"Graubunden",
    "wof:name":"M\u00fcller Hans-peter",
    "wof:placetype":"venue"
},
  "geometry": {"coordinates":[8.999125,47.473232],"type":"Point"}
}