{
  "type": "Feature",
  "properties": {
    "iso:country":"CH",
    "sg:address":"Steinh\u00fcgelstrasse 15",
    "sg:city":"Berikon",
    "sg:orig_category":"Softwareentwicklung U beratung",
    "sg:postcode":"8965",
    "sg:province":"Aargau",
    "wof:name":"Mastertools Gmbh",
    "wof:placetype":"venue"
},
  "geometry": {"coordinates":[8.3657989502,47.362739563],"type":"Point"}
}