{
  "type": "Feature",
  "properties": {
    "iso:country":"CH",
    "sg:address":"Rue Du Tir 28 1636 Broc Case Postale 92",
    "sg:city":"Broc",
    "sg:orig_category":"Instandhaltung U Reparatur von Automobilen",
    "sg:phone":"+41 26 436 15 60",
    "sg:postcode":"1636",
    "sg:province":"Fribourg",
    "wof:name":"Garage Du Stand Sa.",
    "wof:placetype":"venue"
},
  "geometry": {"coordinates":[7.1639299393,46.770614624],"type":"Point"}
}