{
  "type": "Feature",
  "properties": {
    "iso:country":"CH",
    "sg:address":"Glockengasse 4b",
    "sg:city":"Basel",
    "sg:orig_category":"Schmieden",
    "sg:phone":"+41 61 261 96 09",
    "sg:postcode":"4051",
    "sg:province":"Basel-Stadt",
    "wof:name":"Messerschmiede Martin",
    "wof:placetype":"venue"
},
  "geometry": {"coordinates":[7.5870480537,47.5577697754],"type":"Point"}
}