{
  "type": "Feature",
  "properties": {
    "iso:country":"CH",
    "sg:address":"Bernstrasse 80",
    "sg:city":"Rudolfstetten",
    "sg:classifiers":[
        {
            "category":"Restaurant",
            "type":"Food & Drink"
        }
    ],
    "sg:phone":"+41 56 633 14 27",
    "sg:postcode":"8964",
    "sg:province":"Aargau",
    "wof:name":"Restaurant Zur Alten Post",
    "wof:placetype":"venue"
},
  "geometry": {"coordinates":[8.3803386688,47.3683662415],"type":"Point"}
}