{
  "type": "Feature",
  "properties": {
    "iso:country":"CH",
    "sg:address":"Aewilerstrasse 11",
    "sg:city":"Ganterschwil",
    "sg:orig_category":"Fussboden, Fliesen U Plattenlegerei, Tapeziererei",
    "sg:postcode":"9608",
    "sg:province":"St. Gallen",
    "wof:name":"M\u00fchlethaler Marc",
    "wof:placetype":"venue"
},
  "geometry": {"coordinates":[6.8302140236,47.1054840088],"type":"Point"}
}