{
  "type": "Feature",
  "properties": {
    "iso:country":"CH",
    "sg:address":"Obere Kirchmatte 3",
    "sg:city":"Nottwil",
    "sg:orig_category":"Erbringung von sonstigen Dienstleistungen f\u00fcr Unterhaltung, Erholung U Freizeit",
    "sg:phone":"+41 79 335 01 63",
    "sg:postcode":"6207",
    "sg:province":"Luzern",
    "wof:name":"Factory Kunst Gmbh",
    "wof:placetype":"venue"
},
  "geometry": {"coordinates":[8.1380586624,47.1337013245],"type":"Point"}
}