{
  "type": "Feature",
  "properties": {
    "iso:country":"CH",
    "sg:address":"1470",
    "sg:city":"Estavayer-le-lac",
    "sg:orig_category":"Schulpflegen",
    "sg:phone":"+41 26 663 54 38",
    "sg:postcode":"1470",
    "sg:province":"Fribourg",
    "wof:name":"Commission Scolaire De L'\u00e9cole Primaire",
    "wof:placetype":"venue"
},
  "geometry": {"coordinates":[6.8482789993,46.8487930298],"type":"Point"}
}