{
  "type": "Feature",
  "properties": {
    "iso:country":"CH",
    "sg:address":"L\u00e4tti 217a",
    "sg:city":"M\u00fcnchenbuchsee",
    "sg:orig_category":"Maurerarbeiten",
    "sg:phone":"+41 26 411 92 22",
    "sg:postcode":"3053",
    "sg:province":"Bern",
    "wof:name":"Art-tisons Sa Ma\u00e7onnerie & Taille De Pierre",
    "wof:placetype":"venue"
},
  "geometry": {"coordinates":[7.0851511955,46.7216148376],"type":"Point"}
}