{
  "type": "Feature",
  "properties": {
    "iso:country":"CH",
    "sg:address":"Gewerbestr. 3",
    "sg:city":"Steinmaur",
    "sg:classifiers":[
        {
            "category":"Transit Center",
            "subcategory":"Freight",
            "type":"Transportation"
        }
    ],
    "sg:phone":"+41 4118532949",
    "sg:postcode":"8162",
    "sg:province":"Z\u00fcrich",
    "sg:tags":[
        "metallurgy",
        "pipe",
        "metalworking",
        "sheet"
    ],
    "wof:name":"Gueng Ag",
    "wof:placetype":"venue"
},
  "geometry": {"coordinates":[8.4470129013,47.4881362915],"type":"Point"}
}