{
  "type": "Feature",
  "properties": {
    "iso:country":"CH",
    "sg:address":"Kipfgasse 2",
    "sg:city":"M\u00fcnchenbuchsee",
    "sg:orig_category":"Handel mit Motorr\u00e4dern, Teilen U Zubeh\u00f6r Instandhaltung U Reparatur von Motorr\u00e4dern Mechanische Werk",
    "sg:phone":"+41 91 646 17 24",
    "sg:postcode":"3053",
    "sg:province":"Bern",
    "wof:name":"Abomoto Sa",
    "wof:placetype":"venue"
},
  "geometry": {"coordinates":[9.0076999664,45.8654785156],"type":"Point"}
}