{
  "type": "Feature",
  "properties": {
    "iso:country":"CH",
    "sg:address":"Hauptstrasse 18 5314 Kleind\u00f6ttingen. Postfach",
    "sg:city":"Kleind\u00f6ttingen",
    "sg:orig_category":"Wirtschaftspr\u00fcfung, Steuerberatung U Treuhand",
    "sg:postcode":"5314",
    "sg:province":"Aargau",
    "wof:name":"Matania Aktiengesellschaft",
    "wof:placetype":"venue"
},
  "geometry": {"coordinates":[8.247926712,47.5718421936],"type":"Point"}
}