{
  "type": "Feature",
  "properties": {
    "iso:country":"CH",
    "sg:address":"Industriestrasse 1",
    "sg:city":"Dielsdorf",
    "sg:orig_category":"Non-Classified Establishments",
    "sg:postcode":"8157",
    "sg:province":"Z\u00fcrich",
    "wof:name":"Crf Holding",
    "wof:placetype":"venue"
},
  "geometry": {"coordinates":[8.4620065689,47.4831924438],"type":"Point"}
}