{
  "type": "Feature",
  "properties": {
    "iso:country":"CH",
    "sg:address":"Mont-de-faux Chemin 6",
    "sg:city":"Crissier",
    "sg:orig_category":"Druckweiterverarbeitung",
    "sg:phone":"+41 71 250 06 36",
    "sg:postcode":"1023",
    "sg:province":"Vaud",
    "wof:name":"Shot Media - Fps Frei Daniel M.",
    "wof:placetype":"venue"
},
  "geometry": {"coordinates":[9.3926410675,47.4329566956],"type":"Point"}
}