{
  "type": "Feature",
  "properties": {
    "iso:country":"CH",
    "sg:address":"L\u00f6wenstrasse 34",
    "sg:city":"Dietikon",
    "sg:orig_category":"Bijouterien Reparatur von Uhren U Schmuck",
    "sg:phone":"+41 32 914 10 05",
    "sg:postcode":"8953",
    "sg:province":"Z\u00fcrich",
    "wof:name":"Christ Uhren & Schmuck Ag",
    "wof:placetype":"venue"
},
  "geometry": {"coordinates":[6.829905,47.10281],"type":"Point"}
}