{
  "type": "Feature",
  "properties": {
    "iso:country":"CH",
    "sg:address":"Bernstrasse 89 3324 Hindelbank. Postfach 44",
    "sg:city":"Hindelbank",
    "sg:orig_category":"Instandhaltung U Reparatur von Automobilen",
    "sg:phone":"+41 34 411 11 74",
    "sg:postcode":"3324",
    "sg:province":"Bern",
    "wof:name":"Garage B\u00fcrki Ag",
    "wof:placetype":"venue"
},
  "geometry": {"coordinates":[7.5376138687,47.0351104736],"type":"Point"}
}