{
  "type": "Feature",
  "properties": {
    "iso:country":"CH",
    "sg:address":"Ruessenstrasse 6",
    "sg:city":"Baar",
    "sg:orig_category":"Fachdetailhandel in Verkaufsr\u00e4umen",
    "sg:phone":"+41 41 769 72 40",
    "sg:postcode":"6340",
    "sg:province":"Zug",
    "wof:name":"Uvex (schweiz) Ag",
    "wof:placetype":"venue"
},
  "geometry": {"coordinates":[8.5604944229,47.2117652893],"type":"Point"}
}