{
  "type": "Feature",
  "properties": {
    "iso:country":"CH",
    "sg:address":"Gare Rampe De La 3",
    "sg:city":"Versoix",
    "sg:orig_category":"Sonstiges Versicherungsgewerbe",
    "sg:phone":"+41 22 755 31 00",
    "sg:postcode":"1290",
    "sg:province":"Gen\u00e8ve",
    "wof:name":"Netcoman Sa",
    "wof:placetype":"venue"
},
  "geometry": {"coordinates":[6.1671500206,46.280292511],"type":"Point"}
}