{
  "type": "Feature",
  "properties": {
    "iso:country":"CH",
    "sg:address":"Chemin De Chamblandes 16",
    "sg:city":"Pully",
    "sg:orig_category":"Malerei Stukkateurgewerbe, Gipserei U Verputzerei",
    "sg:phone":"+41 21 728 96 15",
    "sg:postcode":"1009",
    "sg:province":"Vaud",
    "wof:name":"Jos\u00e9 Garrido Entreprise De Peinture",
    "wof:placetype":"venue"
},
  "geometry": {"coordinates":[6.6503539085,46.508430481],"type":"Point"}
}