{
  "type": "Feature",
  "properties": {
    "iso:country":"CH",
    "sg:address":"Kirchweg 23",
    "sg:city":"H\u00fcttlingen",
    "sg:orig_category":"Landesverteidigung, Sozialversicherung \u00d6ffentliche Verwaltung",
    "sg:phone":"+41 52 765 20 62",
    "sg:postcode":"8553",
    "sg:province":"Thurgau",
    "wof:name":"Zivilschutzstelle H\u00fcttlingen",
    "wof:placetype":"venue"
},
  "geometry": {"coordinates":[8.9790859222,47.5776176453],"type":"Point"}
}