{
  "type": "Feature",
  "properties": {
    "iso:country":"CH",
    "sg:address":"Zeughausstrasse 5",
    "sg:city":"Sursee",
    "sg:orig_category":"Brillen Detailhandel",
    "sg:phone":"+41 71 911 22 55",
    "sg:postcode":"6210",
    "sg:province":"Luzern",
    "wof:name":"Alfons Zeller Zeller Optik",
    "wof:placetype":"venue"
},
  "geometry": {"coordinates":[9.043572,47.462261],"type":"Point"}
}