{
  "type": "Feature",
  "properties": {
    "iso:country":"CH",
    "sg:address":"Faubourg De France 24 2900 Pruntrut. Postfach",
    "sg:city":"Pruntrut",
    "sg:orig_category":"Herstellung von Radio U Fernsehger\u00e4ten sowie phono U videotechnischen Ger\u00e4ten",
    "sg:postcode":"2900",
    "sg:province":"Jura",
    "wof:name":"Giokagames, Giovanni Germano",
    "wof:placetype":"venue"
},
  "geometry": {"coordinates":[7.0736298561,47.4190368652],"type":"Point"}
}