{
  "type": "Feature",
  "properties": {
    "iso:country":"CH",
    "sg:address":"1569 Autavaux. Postfach",
    "sg:city":"Autavaux",
    "sg:orig_category":"Mechanik",
    "sg:phone":"+41 21 635 79 40",
    "sg:postcode":"1569",
    "wof:name":"Dupuis Jean-jacques",
    "wof:placetype":"venue"
},
  "geometry": {"coordinates":[6.5716891289,46.539478302],"type":"Point"}
}