{
  "type": "Feature",
  "properties": {
    "iso:country":"CH",
    "sg:address":"8784",
    "sg:city":"Braunwald",
    "sg:orig_category":"Detailhandel mit Milcherzeugnissen U Eiern Detailhandel mit Waren verschiedener Art, Hauptrichtung N",
    "sg:phone":"+41 32 751 32 53",
    "sg:postcode":"8784",
    "sg:province":"Glarus",
    "wof:name":"Ursula Blanchard Laiterie-alimentation",
    "wof:placetype":"venue"
},
  "geometry": {"coordinates":[7.0646061897,47.0525283813],"type":"Point"}
}