{
  "type": "Feature",
  "properties": {
    "iso:country":"CH",
    "sg:address":"Oberdorfstr. 17",
    "sg:city":"Arch",
    "sg:orig_category":"Verwertung von Milch",
    "sg:phone":"+41 32 679 30 38",
    "sg:postcode":"3296",
    "sg:province":"Bern",
    "wof:name":"K\u00e4serei Arch, Zbinden + P\u00fcrro",
    "wof:placetype":"venue"
},
  "geometry": {"coordinates":[7.4301700592,47.1656913757],"type":"Point"}
}