{
  "type": "Feature",
  "properties": {
    "iso:country":"CH",
    "sg:address":"Am H\u00e4gli 1",
    "sg:city":"Dottikon",
    "sg:orig_category":"Detailhandel mit Metallwaren, Anstrichmitteln, Glaswaren, Bau U Heimwerkerbedarf",
    "sg:postcode":"5605",
    "sg:province":"Aargau",
    "wof:name":"Technomat Mathis",
    "wof:placetype":"venue"
},
  "geometry": {"coordinates":[8.2316179276,47.3799133301],"type":"Point"}
}