{
  "type": "Feature",
  "properties": {
    "iso:country":"CH",
    "sg:address":"Ruchholzstrasse 47",
    "sg:city":"Bottmingen",
    "sg:orig_category":"Ingenieurb\u00fcros Elektro",
    "sg:phone":"+41 61 423 98 55",
    "sg:postcode":"4103",
    "sg:province":"Basel-Landschaft",
    "wof:name":"Hans U. Tanner Ingenieurb\u00fcro",
    "wof:placetype":"venue"
},
  "geometry": {"coordinates":[7.5747151375,47.5252952576],"type":"Point"}
}