{
  "type": "Feature",
  "properties": {
    "iso:country":"CH",
    "sg:address":"Schreinergasse 8",
    "sg:city":"Derendingen",
    "sg:orig_category":"Vorschulen, Kinderg\u00e4rten",
    "sg:phone":"+41 32 618 15 16",
    "sg:postcode":"4552",
    "sg:province":"Solothurn",
    "wof:name":"Kindergarten Steinmatt",
    "wof:placetype":"venue"
},
  "geometry": {"coordinates":[7.5869498253,47.1967544556],"type":"Point"}
}