{
  "type": "Feature",
  "properties": {
    "iso:country":"CH",
    "sg:address":"Neuhofstrasse 21c",
    "sg:city":"Baar",
    "sg:classifiers":[
        {
            "category":"Manufacturing",
            "subcategory":"Wood Products",
            "type":"Manufacturing & Wholesale Goods"
        }
    ],
    "sg:phone":"+41 41 767 71 71",
    "sg:postcode":"6340",
    "sg:province":"Zug",
    "sg:tags":[
        "gate",
        "made",
        "door"
    ],
    "wof:name":"Franz Schmidiger Fensterfabrikation",
    "wof:placetype":"venue"
},
  "geometry": {"coordinates":[8.5149717331,47.189868927],"type":"Point"}
}