{
  "type": "Feature",
  "properties": {
    "iso:country":"CH",
    "sg:address":"La Villette",
    "sg:city":"Semsales",
    "sg:orig_category":"Kosmetikinstitute",
    "sg:phone":"+41 26 918 55 06",
    "sg:postcode":"1623",
    "sg:province":"Fribourg",
    "wof:name":"Institut Nepherty - Vuichard Jacqueline",
    "wof:placetype":"venue"
},
  "geometry": {"coordinates":[6.9295248985,46.57604599],"type":"Point"}
}