{
  "type": "Feature",
  "properties": {
    "iso:country":"CH",
    "sg:address":"Puits Chemin Du 5",
    "sg:city":"Commugny",
    "sg:orig_category":"Architektur U Ingenieurb\u00fcros",
    "sg:phone":"+41 22 776 46 38",
    "sg:postcode":"1291",
    "sg:province":"Vaud",
    "wof:name":"M\u00e9trailler Andr\u00e9",
    "wof:placetype":"venue"
},
  "geometry": {"coordinates":[6.173852,46.319466],"type":"Point"}
}