{
  "type": "Feature",
  "properties": {
    "addr:full":"En Vannel Bex Vaud 1880",
    "addr:postcode":"1880",
    "iso:country":"CH",
    "sg:address":"En Vannel",
    "sg:city":"Bex",
    "sg:classifiers":[
        {
            "category":"Manufacturing",
            "subcategory":"Petroleum Products",
            "type":"Manufacturing & Wholesale Goods"
        }
    ],
    "sg:phone":"+41 24 463 06 06",
    "sg:postcode":"1880",
    "sg:province":"Vaud",
    "sg:tags":[
        "pump",
        "oil",
        "transformer",
        "circulation"
    ],
    "wof:name":"Plumettaz S.a.",
    "wof:placetype":"venue"
},
  "geometry": {"coordinates":[6.999065,46.248344],"type":"Point"}
}