{
  "type": "Feature",
  "properties": {
    "iso:country":"CH",
    "sg:address":"Les Grands-champs 162",
    "sg:city":"Rossemaison",
    "sg:orig_category":"Herstellung von k\u00e4lte U lufttechnischen Erzeugnissen f\u00fcr gewerbliche Zwecke Installation von Heizung",
    "sg:phone":"+41 56 633 56 54",
    "sg:postcode":"2842",
    "sg:province":"Jura",
    "wof:name":"Climair Steuerungen Jan Topinka",
    "wof:placetype":"venue"
},
  "geometry": {"coordinates":[8.344452858,47.3506698608],"type":"Point"}
}