{
  "type": "Feature",
  "properties": {
    "iso:country":"CH",
    "sg:address":"1428",
    "sg:city":"Provence",
    "sg:orig_category":"Sonstiger Fachdetailhandel mit Nahrungsmitteln, Getr\u00e4nken U Tabak in Verkaufsr\u00e4umen",
    "sg:phone":"+41 24 434 11 63",
    "sg:postcode":"1428",
    "sg:province":"Vaud",
    "wof:name":"Fragni\u00e8re Pierre-andr\u00e9",
    "wof:placetype":"venue"
},
  "geometry": {"coordinates":[6.7277708054,46.8915061951],"type":"Point"}
}