{
  "type": "Feature",
  "properties": {
    "iso:country":"CH",
    "sg:address":"Place Du Midi 44",
    "sg:city":"Sion",
    "sg:orig_category":"Detailhandel mit Schuhen",
    "sg:phone":"+41 31 859 19 20",
    "sg:postcode":"1950",
    "sg:province":"Valais",
    "wof:name":"Botty Maikler Ag Schuhpavillon",
    "wof:placetype":"venue"
},
  "geometry": {"coordinates":[7.4995298386,47.0204238892],"type":"Point"}
}