{
  "type": "Feature",
  "properties": {
    "iso:country":"CH",
    "sg:address":"Bahnhofstrasse 28 6300 Zug. Postfach 251",
    "sg:city":"Zug",
    "sg:orig_category":"Detailhandel mit Herrenbekleidung Detailhandel mit Sportartikeln",
    "sg:phone":"+41 41 711 10 64",
    "sg:postcode":"6301",
    "sg:province":"Zug",
    "wof:name":"Herren Globus Ag",
    "wof:placetype":"venue"
},
  "geometry": {"coordinates":[8.5159921646,47.1701126099],"type":"Point"}
}