{
  "type": "Feature",
  "properties": {
    "iso:country":"CH",
    "sg:address":"Romanshornerstrasse 10",
    "sg:city":"Kronb\u00fchl",
    "sg:classifiers":[
        {
            "category":"Travel",
            "subcategory":"Hotels & Motels",
            "type":"Entertainment"
        }
    ],
    "sg:phone":"+41 71 278 32 33",
    "sg:postcode":"9302",
    "sg:tags":[
        "hotels",
        "mit",
        "restaurant"
    ],
    "wof:name":"Hotel R\u00f6ssli",
    "wof:placetype":"venue"
},
  "geometry": {"coordinates":[9.393204689,47.4593696594],"type":"Point"}
}