{
  "type": "Feature",
  "properties": {
    "iso:country":"CH",
    "sg:address":"Buchenstrasse 5",
    "sg:city":"Speicher",
    "sg:orig_category":"Detailhandel mit Bekleidung Detailhandel mit Textilien",
    "sg:phone":"+41 71 344 41 31",
    "sg:postcode":"9042",
    "sg:province":"Appenzell Ausserrhoden",
    "wof:name":"Fantasia Wolle Gmbh",
    "wof:placetype":"venue"
},
  "geometry": {"coordinates":[9.445787,47.409191],"type":"Point"}
}