{
  "type": "Feature",
  "properties": {
    "iso:country":"CH",
    "sg:address":"Industriegasse 43 3178 B\u00f6singen. Postfach",
    "sg:city":"B\u00f6singen",
    "sg:orig_category":"Instandhaltung U Reparatur von Automobilen",
    "sg:postcode":"3178",
    "sg:province":"Fribourg",
    "wof:name":"Grandinetti Mario Garage",
    "wof:placetype":"venue"
},
  "geometry": {"coordinates":[7.229118824,46.9007301331],"type":"Point"}
}