{
  "type": "Feature",
  "properties": {
    "iso:country":"CH",
    "sg:address":"Langendorfstrasse 26",
    "sg:city":"Solothurn",
    "sg:orig_category":"Wohnheime",
    "sg:phone":"+41 71 352 16 56",
    "sg:postcode":"4500",
    "sg:province":"Solothurn",
    "wof:name":"Wohngemeinschaft Wir Wolfenswiler",
    "wof:placetype":"venue"
},
  "geometry": {"coordinates":[9.2422275543,47.3834190369],"type":"Point"}
}