{
  "type": "Feature",
  "properties": {
    "addr:full":"Flughafen Frachthof West Z\u00fcrich Z\u00fcrich 8058",
    "addr:postcode":"8058",
    "addr:street":"West",
    "iso:country":"CH",
    "sg:address":"Flughafen Frachthof West",
    "sg:city":"Z\u00fcrich",
    "sg:classifiers":[
        {
            "category":"Airport",
            "type":"Transportation"
        }
    ],
    "sg:phone":"+41 4118142144",
    "sg:postcode":"8058",
    "sg:province":"Z\u00fcrich",
    "sg:tags":[
        "transport",
        "air"
    ],
    "wof:name":"Comet Air-transport Ag",
    "wof:placetype":"venue"
},
  "geometry": {"coordinates":[8.53801,47.369091],"type":"Point"}
}