{
  "type": "Feature",
  "properties": {
    "iso:country":"CH",
    "sg:address":"Furkastrasse 1 3904 Naters. Postfach",
    "sg:city":"Naters",
    "sg:orig_category":"Fachdetailhandel mit pharmazeutischen Produkten",
    "sg:phone":"+41 27 923 51 51",
    "sg:postcode":"3904",
    "sg:province":"Valais",
    "wof:name":"Central-apotheke, Fallert Dr. Heinz",
    "wof:placetype":"venue"
},
  "geometry": {"coordinates":[7.9863510132,46.3224258423],"type":"Point"}
}