{
  "type": "Feature",
  "properties": {
    "iso:country":"CH",
    "sg:address":"Oberdorf 9533 Kirchberg Sg. Postfach",
    "sg:city":"M\u00fcselbach",
    "sg:orig_category":"RESTAURANTS: TEA-ROOMS",
    "sg:phone":"+41 71 277 26 98",
    "sg:postcode":"9602",
    "sg:province":"St. Gallen",
    "wof:name":"Rest. Rose, Rechsteiner R.",
    "wof:placetype":"venue"
},
  "geometry": {"coordinates":[9.3358201981,47.4105110168],"type":"Point"}
}