{
  "type": "Feature",
  "properties": {
    "iso:country":"CH",
    "sg:address":"Chemin Des Platanes 5",
    "sg:city":"Lausanne",
    "sg:orig_category":"Vereine Hundedressur",
    "sg:phone":"+41 79 212 60 48",
    "sg:postcode":"1005",
    "sg:province":"Vaud",
    "wof:name":"St\u00e9 Vaudoise De Cynologie",
    "wof:placetype":"venue"
},
  "geometry": {"coordinates":[6.6517949104,46.515007019],"type":"Point"}
}