{
  "type": "Feature",
  "properties": {
    "iso:country":"CH",
    "sg:address":"Chemin Antoine-verch\u00e8re 5",
    "sg:city":"Meyrin",
    "sg:classifiers":[
        {
            "category":"Organizations",
            "subcategory":"Labor Organization",
            "type":"Services"
        }
    ],
    "sg:phone":"+41 22 782 32 22",
    "sg:postcode":"1217",
    "sg:province":"Gen\u00e8ve",
    "sg:tags":[
        "sail",
        "maker"
    ],
    "wof:name":"Voiles Phi S.a.",
    "wof:placetype":"venue"
},
  "geometry": {"coordinates":[6.0720257759,46.2280197144],"type":"Point"}
}