{
  "type": "Feature",
  "properties": {
    "iso:country":"CH",
    "sg:address":"Urs Graf-strasse 1",
    "sg:city":"Basel",
    "sg:orig_category":"Architektur U Ingenieurb\u00fcros",
    "sg:phone":"+41 61 311 17 14",
    "sg:postcode":"4052",
    "sg:province":"Basel-Stadt",
    "wof:name":"Ibk Integrale Bauphysik, Schluchter Ph.",
    "wof:placetype":"venue"
},
  "geometry": {"coordinates":[7.611639,47.548885],"type":"Point"}
}