{
  "type": "Feature",
  "properties": {
    "iso:country":"CH",
    "sg:address":"Matt 3",
    "sg:city":"Schmiedrued",
    "sg:orig_category":"Kauf U Verkauf von Immobilien auf eigene Rechnung",
    "sg:postcode":"5046",
    "sg:province":"Aargau",
    "wof:name":"Rw Immobilien Ag",
    "wof:placetype":"venue"
},
  "geometry": {"coordinates":[9.5499105453,47.3331031799],"type":"Point"}
}