{
  "type": "Feature",
  "properties": {
    "iso:country":"CH",
    "sg:address":"Via Maggio 1",
    "sg:city":"Lugano",
    "sg:orig_category":"Sanit\u00e4r, Heizungs U L\u00fcftungsinstallation",
    "sg:phone":"+41 91 967 13 37",
    "sg:postcode":"6900",
    "sg:province":"Ticino",
    "wof:name":"Idrocalor Sa",
    "wof:placetype":"venue"
},
  "geometry": {"coordinates":[8.961098671,46.0080337524],"type":"Point"}
}