{
  "type": "Feature",
  "properties": {
    "iso:country":"CH",
    "sg:address":"Frauentalstrasse 1 6332 Hagendorn. Postfach",
    "sg:city":"Hagendorn",
    "sg:orig_category":"Versandhandel",
    "sg:phone":"+41 41 785 64 84",
    "sg:postcode":"6332",
    "sg:province":"Zug",
    "wof:name":"Aston Ag",
    "wof:placetype":"venue"
},
  "geometry": {"coordinates":[8.4297409058,47.2036552429],"type":"Point"}
}