{
  "type": "Feature",
  "properties": {
    "iso:country":"CH",
    "sg:address":"Seefeldstrasse 88 8702 Zollikon. Postfach",
    "sg:city":"Z\u00fcrich",
    "sg:orig_category":"Unternehmensberatung",
    "sg:phone":"+41 13966896",
    "sg:postcode":"8008",
    "sg:province":"Z\u00fcrich",
    "wof:name":"Friedli P. & Partner",
    "wof:placetype":"venue"
},
  "geometry": {"coordinates":[8.5654582977,47.3464202881],"type":"Point"}
}