{
  "type": "Feature",
  "properties": {
    "iso:country":"CH",
    "sg:address":"Im Angelrain 11",
    "sg:city":"Winkel",
    "sg:orig_category":"Elektroinstallation Herstellung von sonstigen elektrischen Ausr\u00fcstungen",
    "sg:phone":"+41 81 756 40 40",
    "sg:postcode":"8185",
    "sg:province":"Z\u00fcrich",
    "wof:name":"Bren Funktechnik Radio Tv",
    "wof:placetype":"venue"
},
  "geometry": {"coordinates":[9.477938652,47.1595497131],"type":"Point"}
}