{
  "type": "Feature",
  "properties": {
    "iso:country":"CH",
    "sg:address":"Ch\u00e2tel-saint-denis 57",
    "sg:city":"Blonay",
    "sg:orig_category":"Hochschulen U h\u00f6here Ausbildung",
    "sg:postcode":"1807",
    "sg:province":"Vaud",
    "wof:name":"Pr Diffusion, Riat Patrick",
    "wof:placetype":"venue"
},
  "geometry": {"coordinates":[6.893447876,46.4764900208],"type":"Point"}
}