{
  "type": "Feature",
  "properties": {
    "iso:country":"CH",
    "sg:address":"Hauptgasse 41",
    "sg:city":"Solothurn",
    "sg:orig_category":"RESTAURANTS: TEA-ROOMS",
    "sg:phone":"+41 32 626 28 48",
    "sg:postcode":"4500",
    "sg:province":"Solothurn",
    "wof:name":"Zunfthaus Zu Wirthen",
    "wof:placetype":"venue"
},
  "geometry": {"coordinates":[7.5369710922,47.2075653076],"type":"Point"}
}