{
  "type": "Feature",
  "properties": {
    "iso:country":"CH",
    "sg:address":"Hanselenstrasse",
    "sg:city":"Scharnachtal",
    "sg:orig_category":"Hoch U Tiefbau",
    "sg:phone":"+41 33 676 18 46",
    "sg:postcode":"3722",
    "sg:province":"Bern",
    "wof:name":"Gottfried Von K\u00e4nel Baugesch\u00e4ft",
    "wof:placetype":"venue"
},
  "geometry": {"coordinates":[7.699283123,46.6156005859],"type":"Point"}
}