{
  "type": "Feature",
  "properties": {
    "addr:full":"Hinterz\u00e4unen Unterlangenegg Bern 3614",
    "addr:postcode":"3614",
    "iso:country":"CH",
    "sg:address":"Hinterz\u00e4unen",
    "sg:city":"Unterlangenegg",
    "sg:orig_category":"Blumen U Zierpflanzenbau",
    "sg:phone":"+41 33 453 22 55",
    "sg:postcode":"3614",
    "sg:province":"Bern",
    "wof:name":"G\u00e4rtnerei Kropf",
    "wof:placetype":"venue"
},
  "geometry": {"coordinates":[7.691376,46.801052],"type":"Point"}
}