{
  "type": "Feature",
  "properties": {
    "iso:country":"CH",
    "sg:address":"Chemin De Palud 12",
    "sg:city":"Chamb\u00e9sy",
    "sg:orig_category":"Sportvereine P\u00e9tanque",
    "sg:phone":"+41 22 758 10 21",
    "sg:postcode":"1292",
    "sg:province":"Gen\u00e8ve",
    "wof:name":"P\u00e9tanque-club Les Pradel",
    "wof:placetype":"venue"
},
  "geometry": {"coordinates":[6.1370592117,46.2365989685],"type":"Point"}
}