{
  "type": "Feature",
  "properties": {
    "addr:full":"Langstrasse 138 Z\u00fcrich Z\u00fcrich 8004",
    "addr:housenumber":"138",
    "addr:postcode":"8004",
    "addr:street":"Langstrasse",
    "iso:country":"CH",
    "sg:address":"Langstrasse 138",
    "sg:city":"Z\u00fcrich",
    "sg:classifiers":[
        {
            "category":"Bars & Pubs",
            "type":"Food & Drink"
        }
    ],
    "sg:phone":"+41 12429139",
    "sg:postcode":"8004",
    "sg:province":"Z\u00fcrich",
    "wof:name":"Bar Ol\u00e9-ol\u00e9",
    "wof:placetype":"venue"
},
  "geometry": {"coordinates":[8.528035,47.379997],"type":"Point"}
}