{
  "type": "Feature",
  "properties": {
    "iso:country":"CH",
    "sg:address":"Avenue Parc-de-la-rouvraie 25",
    "sg:city":"Lausanne",
    "sg:orig_category":"Grosshandel mit Maschinen U Ausr\u00fcstungen Herstellung von sonstigen Maschinen f\u00fcr unspezifische Verwe",
    "sg:phone":"+41 21 646 61 60",
    "sg:postcode":"1018",
    "sg:province":"Vaud",
    "wof:name":"Mitch",
    "wof:placetype":"venue"
},
  "geometry": {"coordinates":[6.6349349022,46.529510498],"type":"Point"}
}