{
  "type": "Feature",
  "properties": {
    "iso:country":"CH",
    "sg:address":"Unterdorfstrasse 39",
    "sg:city":"Diepoldsau",
    "sg:orig_category":"Werbeagenturen",
    "sg:phone":"+41 71 733 32 78",
    "sg:postcode":"9444",
    "sg:province":"St. Gallen",
    "wof:name":"Udo Heinzle Werbeberatung",
    "wof:placetype":"venue"
},
  "geometry": {"coordinates":[9.6475133896,47.3872108459],"type":"Point"}
}