{
  "type": "Feature",
  "properties": {
    "iso:country":"CH",
    "sg:address":"Rebgasse 108",
    "sg:city":"Binningen",
    "sg:orig_category":"Unclassifiable Establishments",
    "sg:phone":"+41 61 301 27 11",
    "sg:postcode":"4102",
    "sg:province":"Basel-Landschaft",
    "wof:name":"Ameropa Holding Ag",
    "wof:placetype":"venue"
},
  "geometry": {"coordinates":[7.566549778,47.5417709351],"type":"Point"}
}