{
  "type": "Feature",
  "properties": {
    "iso:country":"CH",
    "sg:address":"3267 Seedorf Be. Postfach",
    "sg:city":"Lobsigen",
    "sg:orig_category":"Mechanik",
    "sg:postcode":"3268",
    "sg:province":"Bern",
    "wof:name":"Zingg Metalltechnik",
    "wof:placetype":"venue"
},
  "geometry": {"coordinates":[8.1856975555,47.2346878052],"type":"Point"}
}