{
  "type": "Feature",
  "properties": {
    "addr:full":"Hauptstrasse 28 Weite St. Gallen 9476",
    "addr:housenumber":"28;st.",
    "addr:postcode":"9476",
    "addr:street":"Hauptstrasse;Weite",
    "iso:country":"CH",
    "sg:address":"Hauptstrasse 28",
    "sg:city":"Weite",
    "sg:classifiers":[
        {
            "category":"Banks & Credit Unions",
            "subcategory":"Bank",
            "type":"Services"
        }
    ],
    "sg:phone":"+41 81 783 22 55",
    "sg:postcode":"9476",
    "sg:province":"St. Gallen",
    "wof:name":"Raiffeisenbank Wartau",
    "wof:placetype":"venue"
},
  "geometry": {"coordinates":[9.499055,47.092422],"type":"Point"}
}