{
  "type": "Feature",
  "properties": {
    "iso:country":"CH",
    "sg:address":"Hegisplatz 6",
    "sg:city":"Chur",
    "sg:orig_category":"Fotografische Ateliers",
    "sg:phone":"+41 81 252 17 23",
    "sg:postcode":"7000",
    "sg:province":"Graubunden",
    "wof:name":"Konrad Kunz Atelier F\u00fcr Grafik & Foto",
    "wof:placetype":"venue"
},
  "geometry": {"coordinates":[9.5342340469,46.8491325378],"type":"Point"}
}