{
  "type": "Feature",
  "properties": {
    "iso:country":"CH",
    "sg:address":"Spalenring 126",
    "sg:city":"Basel",
    "sg:classifiers":[
        {
            "category":"Restaurant",
            "type":"Food & Drink"
        }
    ],
    "sg:phone":"+41 61 301 00 11",
    "sg:postcode":"4055",
    "sg:province":"Basel-Stadt",
    "wof:name":"Cafe-bar Classico",
    "wof:placetype":"venue"
},
  "geometry": {"coordinates":[7.5755581856,47.5557289124],"type":"Point"}
}