{
  "type": "Feature",
  "properties": {
    "iso:country":"CH",
    "sg:address":"Feldstrasse 15",
    "sg:city":"Richterswil",
    "sg:orig_category":"Handelsvermittlung U Grosshandel Sonstiger Grosshandel",
    "sg:phone":"+41 17846052",
    "sg:postcode":"8805",
    "sg:province":"Z\u00fcrich",
    "wof:name":"Seatco J.burri Trading",
    "wof:placetype":"venue"
},
  "geometry": {"coordinates":[8.689956665,47.2089805603],"type":"Point"}
}