{
  "type": "Feature",
  "properties": {
    "iso:country":"CH",
    "sg:address":"Hofwiesenstr. 16 8800 Thalwil. Postfach",
    "sg:city":"Gattikon",
    "sg:orig_category":"Instandhaltung U Reparatur von Automobilen",
    "sg:phone":"+41 19150087",
    "sg:postcode":"8136",
    "sg:province":"Z\u00fcrich",
    "wof:name":"Hausheer R. & Co, Automobile Jaguar",
    "wof:placetype":"venue"
},
  "geometry": {"coordinates":[8.564707756,47.2947349548],"type":"Point"}
}