{
  "type": "Feature",
  "properties": {
    "iso:country":"CH",
    "sg:address":"Birreria Via 10 6503 Bellinzona. Postfach",
    "sg:city":"Bellinzona",
    "sg:orig_category":"RESTAURANTS: TEA-ROOMS",
    "sg:phone":"+41 91 826 37 12",
    "sg:postcode":"6503",
    "sg:province":"Ticino",
    "wof:name":"Mascanzoni Sonia",
    "wof:placetype":"venue"
},
  "geometry": {"coordinates":[9.015879631,46.2039718628],"type":"Point"}
}