{
  "type": "Feature",
  "properties": {
    "addr:full":"Stauffenbach Ochlenberg Bern 3367",
    "addr:postcode":"3367",
    "addr:street":"Stauffenbach Ochlenberg Bern",
    "iso:country":"CH",
    "sg:address":"Stauffenbach",
    "sg:city":"Ochlenberg",
    "sg:orig_category":"Bauschreinerei Erbringung von sonstigen Dienstleistungen f\u00fcr Unternehmen",
    "sg:phone":"+41 62 961 73 33",
    "sg:postcode":"3367",
    "sg:province":"Bern",
    "wof:name":"Hansj\u00fcrg Landolt Modellschreinerei",
    "wof:placetype":"venue"
},
  "geometry": {"coordinates":[7.73305,47.149509],"type":"Point"}
}