{
  "type": "Feature",
  "properties": {
    "iso:country":"CH",
    "sg:address":"8887",
    "sg:city":"Mels",
    "sg:orig_category":"Wirtschaftsverb\u00e4nde Industrie, Handel and Gewerbe",
    "sg:phone":"+41 31 330 51 11",
    "sg:postcode":"8887",
    "sg:province":"St. Gallen",
    "wof:name":"Nat.ges.z.f\u00f6rderung D.indust. Atomtechn.c/o Bern.kraftwerke",
    "wof:placetype":"venue"
},
  "geometry": {"coordinates":[7.4508781433,46.9550361633],"type":"Point"}
}