{
  "type": "Feature",
  "properties": {
    "iso:country":"CH",
    "sg:address":"Arminstrasse 24",
    "sg:city":"Z\u00fcrich",
    "sg:orig_category":"Bauspenglerei Dachdeckerei",
    "sg:phone":"+41 13127723",
    "sg:postcode":"8050",
    "sg:province":"Z\u00fcrich",
    "wof:name":"Ernst Kolb Spenglerei & Bedachungen",
    "wof:placetype":"venue"
},
  "geometry": {"coordinates":[8.557724,47.407841],"type":"Point"}
}