{
  "type": "Feature",
  "properties": {
    "iso:country":"CH",
    "sg:address":"Schwarzenburgstrasse 818 3145 Niederscherli. Postfach 77",
    "sg:city":"K\u00f6niz",
    "sg:orig_category":"Fachdetailhandel mit pharmazeutischen Produkten",
    "sg:phone":"+41 31 859 20 33",
    "sg:postcode":"3098",
    "sg:province":"Bern",
    "wof:name":"Apotheke 2000 Bionova Ag",
    "wof:placetype":"venue"
},
  "geometry": {"coordinates":[7.4949731827,47.0172996521],"type":"Point"}
}