{
  "type": "Feature",
  "properties": {
    "addr:full":"Aspstrasse 12 Seuzach Z\u00fcrich 8472",
    "addr:housenumber":"12",
    "addr:postcode":"8472",
    "addr:street":"Aspstrasse",
    "iso:country":"CH",
    "sg:address":"Aspstrasse 12",
    "sg:city":"Seuzach",
    "sg:orig_category":"Architektur U Ingenieurb\u00fcros",
    "sg:phone":"+41 52 235 00 20",
    "sg:postcode":"8472",
    "sg:province":"Z\u00fcrich",
    "wof:name":"Inwag, Otto Wyss",
    "wof:placetype":"venue"
},
  "geometry": {"coordinates":[8.707273,47.527687],"type":"Point"}
}