{
  "type": "Feature",
  "properties": {
    "iso:country":"CH",
    "sg:address":"Safenwilerstrasse 14 5742 K\u00f6lliken. Postfach 118",
    "sg:city":"K\u00f6lliken",
    "sg:orig_category":"Detailhandel mit Fahrr\u00e4dern Handel mit Motorr\u00e4dern, Teilen U Zubeh\u00f6r Instandhaltung U Reparatur von ",
    "sg:phone":"+41 31 332 13 00",
    "sg:postcode":"5742",
    "sg:province":"Aargau",
    "wof:name":"Mr. Feelgood, Hafner Christophe",
    "wof:placetype":"venue"
},
  "geometry": {"coordinates":[7.4521360397,46.9623794556],"type":"Point"}
}