{
  "type": "Feature",
  "properties": {
    "addr:full":"Bienkenstrasse 10 Oensingen Solothurn 4702",
    "addr:housenumber":"10",
    "addr:postcode":"4702",
    "addr:street":"Bienkenstrasse",
    "iso:country":"CH",
    "sg:address":"Bienkenstrasse 10",
    "sg:city":"Oensingen",
    "sg:orig_category":"Allgemeiner Hoch U Tiefbau",
    "sg:phone":"+41 55 251 50 55",
    "sg:postcode":"4702",
    "sg:province":"Solothurn",
    "wof:name":"Wagner Unternehmungen Ag",
    "wof:placetype":"venue"
},
  "geometry": {"coordinates":[8.851405,47.259937],"type":"Point"}
}