{
  "type": "Feature",
  "properties": {
    "iso:country":"CH",
    "sg:address":"Rue De La Dixence 21",
    "sg:city":"Sion",
    "sg:orig_category":"Arztpraxen",
    "sg:phone":"+41 27 322 77 77",
    "sg:postcode":"1950",
    "sg:province":"Valais",
    "wof:name":"Dr M\u00e9d. Daniel Antonioli M\u00e9decin Sp\u00e9cialiste Fmh",
    "wof:placetype":"venue"
},
  "geometry": {"coordinates":[7.363818,46.230503],"type":"Point"}
}