{
  "type": "Feature",
  "properties": {
    "iso:country":"CH",
    "sg:address":"Tufertschwil 90 9604 L\u00fctisburg. Postfach",
    "sg:city":"L\u00fctisburg",
    "sg:orig_category":"Betrieb U technische Hilfsdienste des Kultur U Unterhaltungswesens Event Agenturen",
    "sg:phone":"+41 71 931 32 22",
    "sg:postcode":"9604",
    "sg:province":"St. Gallen",
    "wof:name":"Open Air Tufertschwil Gmbh Open Air Veranstaltungen U. Konzerte; Organisation Usw.",
    "wof:placetype":"venue"
},
  "geometry": {"coordinates":[9.10125,47.394241],"type":"Point"}
}