{
  "type": "Feature",
  "properties": {
    "iso:country":"CH",
    "sg:address":"Pressoirs Route Des 15",
    "sg:city":"Lonay",
    "sg:orig_category":"Wirtschaftspr\u00fcfung, Steuerberatung U Treuhand",
    "sg:phone":"+41 21 311 58 64",
    "sg:postcode":"1027",
    "sg:province":"Vaud",
    "wof:name":"Gfc Consult S\u00e0rl",
    "wof:placetype":"venue"
},
  "geometry": {"coordinates":[6.5199542046,46.525302887],"type":"Point"}
}