{
  "type": "Feature",
  "properties": {
    "iso:country":"CH",
    "sg:address":"Rickstrasse 6 8274 T\u00e4gerwilen. Postfach 60",
    "sg:city":"T\u00e4gerwilen",
    "sg:orig_category":"Praxis f\u00fcr Atlaslogie",
    "sg:phone":"+41 79 407 65 81",
    "sg:postcode":"8274",
    "sg:province":"Thurgau",
    "wof:name":"Martha Giuffr\u00e8 Atlaslogie",
    "wof:placetype":"venue"
},
  "geometry": {"coordinates":[9.132941246,47.6555290222],"type":"Point"}
}