{
  "type": "Feature",
  "properties": {
    "iso:country":"CH",
    "sg:address":"Waldstrasse 27",
    "sg:city":"Biberist",
    "sg:orig_category":"Institutionen f\u00fcr Behinderte Sonderschulen",
    "sg:phone":"+41 32 671 26 14",
    "sg:postcode":"4562",
    "sg:province":"Solothurn",
    "wof:name":"Behindertenheim Oberwald Wohn-& Sonderschulheim",
    "wof:placetype":"venue"
},
  "geometry": {"coordinates":[7.5530629158,47.1875953674],"type":"Point"}
}