{
  "type": "Feature",
  "properties": {
    "iso:country":"CH",
    "sg:address":"Luegislandstr. 485",
    "sg:city":"Z\u00fcrich",
    "sg:orig_category":"Architektur U Ingenieurb\u00fcros",
    "sg:phone":"+41 13423616",
    "sg:postcode":"8000",
    "sg:province":"Z\u00fcrich",
    "wof:name":"Dataplan-ingenieurb\u00fcro, Balint Zsolt",
    "wof:placetype":"venue"
},
  "geometry": {"coordinates":[8.578599,47.408005],"type":"Point"}
}