{
  "type": "Feature",
  "properties": {
    "iso:country":"CH",
    "sg:address":"Dogana",
    "sg:city":"Arogno",
    "sg:orig_category":"Tankstellen",
    "sg:phone":"+41 91 649 60 96",
    "sg:postcode":"6822",
    "sg:province":"Ticino",
    "wof:name":"Valmarashop Sa Stazione Di Servizio Mobil",
    "wof:placetype":"venue"
},
  "geometry": {"coordinates":[8.9867334366,45.958896637],"type":"Point"}
}