{
  "type": "Feature",
  "properties": {
    "iso:country":"CH",
    "sg:address":"Route De L'auberge Du Ch\u00eane",
    "sg:city":"Pampigny",
    "sg:orig_category":"Mechanik Werkzeugschleifereien",
    "sg:phone":"+41 79 412 83 34",
    "sg:postcode":"1142",
    "sg:province":"Vaud",
    "wof:name":"Jmd Aff\u00fbtage S\u00e0rl",
    "wof:placetype":"venue"
},
  "geometry": {"coordinates":[6.4278202057,46.580078125],"type":"Point"}
}