{
  "type": "Feature",
  "properties": {
    "iso:country":"CH",
    "sg:address":"M\u00fchlegasse 12a",
    "sg:city":"Baar",
    "sg:orig_category":"Unternehmensberatung",
    "sg:phone":"+41 41 763 11 55",
    "sg:postcode":"6340",
    "sg:province":"Zug",
    "wof:name":"Emo-trans Betriebs Ag",
    "wof:placetype":"venue"
},
  "geometry": {"coordinates":[8.5280370712,47.1993522644],"type":"Point"}
}