{
  "type": "Feature",
  "properties": {
    "iso:country":"CH",
    "sg:address":"Schildstrasse",
    "sg:city":"Sevelen",
    "sg:classifiers":[
        {
            "category":"Travel",
            "subcategory":"Hotels & Motels",
            "type":"Entertainment"
        }
    ],
    "sg:phone":"+41 81 785 12 43",
    "sg:postcode":"9475",
    "sg:province":"St. Gallen",
    "sg:tags":[
        "hotels",
        "mit",
        "restaurant"
    ],
    "wof:name":"Duwa Ag",
    "wof:placetype":"venue"
},
  "geometry": {"coordinates":[9.4878911972,47.129901886],"type":"Point"}
}