{
  "type": "Feature",
  "properties": {
    "addr:full":"Via Al Municipio 21 Barbengo Ticino 6917",
    "addr:housenumber":"21",
    "addr:postcode":"6917",
    "addr:street":"Via Al Municipio;Ticino",
    "iso:country":"CH",
    "sg:address":"Via Al Municipio 21",
    "sg:city":"Barbengo",
    "sg:orig_category":"Arztpraxen",
    "sg:phone":"+41 91 995 15 15",
    "sg:postcode":"6917",
    "sg:province":"Ticino",
    "wof:name":"Dott.med.francesco Denti Medico Generico Fmh",
    "wof:placetype":"venue"
},
  "geometry": {"coordinates":[8.915997,45.959179],"type":"Point"}
}