{
  "type": "Feature",
  "properties": {
    "iso:country":"CH",
    "sg:address":"Hauptstrasse 58",
    "sg:city":"Unterentfelden",
    "sg:orig_category":"Detailhandel mit Getr\u00e4nken Grosshandel mit Getr\u00e4nken",
    "sg:phone":"+41 62 724 07 40",
    "sg:postcode":"5035",
    "sg:province":"Aargau",
    "wof:name":"Weinkiste St. Jakob, Meier Roland",
    "wof:placetype":"venue"
},
  "geometry": {"coordinates":[8.0448131561,47.3692703247],"type":"Point"}
}