{
  "type": "Feature",
  "properties": {
    "iso:country":"CH",
    "sg:address":"Waldhofstrasse 4",
    "sg:city":"Unter\u00e4geri",
    "sg:orig_category":"Unternehmensberatung",
    "sg:postcode":"6314",
    "sg:province":"Zug",
    "wof:name":"Sommer Dr. Wirtschaftspr\u00fcfungs, Revisions Und Steuerberatungs Ag",
    "wof:placetype":"venue"
},
  "geometry": {"coordinates":[8.5766935349,47.1421585083],"type":"Point"}
}