{
  "type": "Feature",
  "properties": {
    "iso:country":"CH",
    "sg:address":"Heimstrasse 4",
    "sg:city":"Amriswil",
    "sg:orig_category":"Allgemeiner Hochbau Strassenbau",
    "sg:phone":"+41 21 652 62 75",
    "sg:postcode":"8580",
    "sg:province":"Thurgau",
    "wof:name":"Oyex, Chessex Et Cie Sa",
    "wof:placetype":"venue"
},
  "geometry": {"coordinates":[6.666006,46.506939],"type":"Point"}
}