{
  "type": "Feature",
  "properties": {
    "addr:full":"Thurgauerstrasse 40 Z\u00fcrich Z\u00fcrich 8050",
    "addr:housenumber":"40",
    "addr:postcode":"8050",
    "addr:street":"Thurgauerstrasse",
    "iso:country":"CH",
    "sg:address":"Thurgauerstrasse 40",
    "sg:city":"Z\u00fcrich",
    "sg:orig_category":"Internet, Sonstige Internetdienstleistungen",
    "sg:phone":"+41 4113065701",
    "sg:postcode":"8050",
    "sg:province":"Z\u00fcrich",
    "wof:name":"Immo Winner Ag",
    "wof:placetype":"venue"
},
  "geometry": {"coordinates":[8.552161,47.415112],"type":"Point"}
}