{
  "type": "Feature",
  "properties": {
    "iso:country":"CH",
    "sg:address":"Rundbuckstrasse 2 8212 Neuhausen. Postfach",
    "sg:city":"F\u00e4llanden",
    "sg:orig_category":"Herstellung von elektronischen Bauelementen",
    "sg:phone":"+41 52 674 07 07",
    "sg:postcode":"8117",
    "sg:province":"Z\u00fcrich",
    "wof:name":"Weidm\u00fcller Schweiz Ag",
    "wof:placetype":"venue"
},
  "geometry": {"coordinates":[8.6049861908,47.6753997803],"type":"Point"}
}