{
  "type": "Feature",
  "properties": {
    "iso:country":"CH",
    "sg:address":"Rue Maurice 3",
    "sg:city":"Gen\u00e8ve",
    "sg:orig_category":"Grosshandel mit Schmuck Grosshandel mit Uhren",
    "sg:phone":"+41 22 310 70 36",
    "sg:postcode":"1204",
    "sg:province":"Gen\u00e8ve",
    "wof:name":"Antea Sa",
    "wof:placetype":"venue"
},
  "geometry": {"coordinates":[6.1497969627,46.1992416382],"type":"Point"}
}