{
  "type": "Feature",
  "properties": {
    "iso:country":"CH",
    "sg:address":"Hauptstrasse",
    "sg:city":"Feschel",
    "sg:orig_category":"Herstellung von sonstigen landwirtschaftlichen Maschinen",
    "sg:phone":"+41 27 473 16 03",
    "sg:postcode":"3956",
    "sg:province":"Valais",
    "wof:name":"Meichtry Reinhard, Landmaschinen",
    "wof:placetype":"venue"
},
  "geometry": {"coordinates":[7.6783471107,46.3293647766],"type":"Point"}
}