{
  "type": "Feature",
  "properties": {
    "iso:country":"CH",
    "sg:address":"Strada Di Gandria 8",
    "sg:city":"Castagnola",
    "sg:orig_category":"Nationale Postdienste",
    "sg:phone":"+41 91 971 32 27",
    "sg:postcode":"6976",
    "sg:province":"Ticino",
    "wof:name":"La Posta Svizzera",
    "wof:placetype":"venue"
},
  "geometry": {"coordinates":[8.9758014679,46.0013465881],"type":"Point"}
}