{
  "type": "Feature",
  "properties": {
    "iso:country":"CH",
    "sg:address":"Elfenweg 17 8000 Z\u00fcrich. Postfach 781",
    "sg:city":"Z\u00fcrich",
    "sg:orig_category":"Handelsvermittlung U Grosshandel Sonstiger Grosshandel",
    "sg:phone":"+41 14830777",
    "sg:postcode":"8038",
    "sg:province":"Z\u00fcrich",
    "wof:name":"Silogran Trading Ag",
    "wof:placetype":"venue"
},
  "geometry": {"coordinates":[8.5238866806,47.348400116],"type":"Point"}
}