{
  "type": "Feature",
  "properties": {
    "iso:country":"CH",
    "sg:address":"Hegenheimerstrasse 171",
    "sg:city":"Basel",
    "sg:orig_category":"Vermietung U Verpachtung von eigenen Immobilien",
    "sg:postcode":"4055",
    "sg:province":"Basel-Stadt",
    "wof:name":"Pausima Ag",
    "wof:placetype":"venue"
},
  "geometry": {"coordinates":[7.565305233,47.563419342],"type":"Point"}
}