{
  "type": "Feature",
  "properties": {
    "iso:country":"CH",
    "sg:address":"Leberngasse 7 4600 Olten. Postfach",
    "sg:city":"Olten",
    "sg:orig_category":"Advokaturb\u00fcros",
    "sg:phone":"+41 62 212 52 66",
    "sg:postcode":"4603",
    "sg:province":"Solothurn",
    "wof:name":"Gabriela Von Arx Advokaturb\u00fcro",
    "wof:placetype":"venue"
},
  "geometry": {"coordinates":[7.900693,47.34901],"type":"Point"}
}