{
  "type": "Feature",
  "properties": {
    "iso:country":"CH",
    "sg:address":"Halden",
    "sg:city":"Eggersriet",
    "sg:orig_category":"Tierarztpraxis",
    "sg:phone":"+41 71 891 40 44",
    "sg:postcode":"9034",
    "sg:province":"St. Gallen",
    "wof:name":"Dr. Med. Vet. Ludwig Egger Tierarzt",
    "wof:placetype":"venue"
},
  "geometry": {"coordinates":[9.4867744446,47.4417190552],"type":"Point"}
}