{
  "type": "Feature",
  "properties": {
    "iso:country":"CH",
    "sg:address":"Rue De La Carri\u00e8re 11",
    "sg:city":"Fribourg",
    "sg:orig_category":"Herstellung von Duft U K\u00f6rperpflegemitteln",
    "sg:phone":"+41 26 422 20 20",
    "sg:postcode":"1700",
    "sg:province":"Fribourg",
    "wof:name":"Gasser S. Cosm\u00e9tique - Flore",
    "wof:placetype":"venue"
},
  "geometry": {"coordinates":[7.1452441216,46.8029823303],"type":"Point"}
}