{
  "type": "Feature",
  "properties": {
    "iso:country":"CH",
    "sg:address":"Heiterweid 9 6014 Littau. Postfach",
    "sg:city":"Littau",
    "sg:orig_category":"Non-Classified Establishments",
    "sg:postcode":"6014",
    "sg:province":"Luzern",
    "wof:name":"Huber Distribution",
    "wof:placetype":"venue"
},
  "geometry": {"coordinates":[8.2846059799,47.0608177185],"type":"Point"}
}