{
  "type": "Feature",
  "properties": {
    "iso:country":"CH",
    "sg:address":"M\u00f6hrlistrasse 59",
    "sg:city":"Z\u00fcrich",
    "sg:orig_category":"Sonstige Aktivit\u00e4ten der nicht-\u00e4rztlichen Medizinalberufe",
    "sg:phone":"+41 41 811 70 88",
    "sg:postcode":"8006",
    "sg:province":"Z\u00fcrich",
    "wof:name":"Ruth Quesada Heilpraktikerin & Massagen",
    "wof:placetype":"venue"
},
  "geometry": {"coordinates":[8.6326417923,47.0282554626],"type":"Point"}
}