{
  "type": "Feature",
  "properties": {
    "iso:country":"CH",
    "sg:address":"Nordstrasse 70",
    "sg:city":"Z\u00fcrich",
    "sg:orig_category":"Arztpraxen",
    "sg:phone":"+41 13622548",
    "sg:postcode":"8006",
    "sg:province":"Z\u00fcrich",
    "wof:name":"Dr.med.hans-peter Jung Spezialarzt Fmh",
    "wof:placetype":"venue"
},
  "geometry": {"coordinates":[8.537386,47.387119],"type":"Point"}
}