{
  "type": "Feature",
  "properties": {
    "iso:country":"CH",
    "sg:address":"Hubzelg Bahnhofstrasse 54a",
    "sg:city":"Romanshorn",
    "sg:orig_category":"Unclassifiable Establishments",
    "sg:postcode":"8590",
    "sg:province":"Thurgau",
    "wof:name":"M-electronic St.gallen",
    "wof:placetype":"venue"
},
  "geometry": {"coordinates":[9.3705272675,47.4222297668],"type":"Point"}
}