{
  "type": "Feature",
  "properties": {
    "iso:country":"CH",
    "sg:address":"Fliederweg 458",
    "sg:city":"Staffelbach",
    "sg:orig_category":"Sonstiges Versicherungsgewerbe",
    "sg:phone":"+41 55 264 14 30",
    "sg:postcode":"5053",
    "sg:province":"Aargau",
    "wof:name":"Arc, Keller Ernst, Gesellschaftsunabh\u00e4ngige Versicherungsberatungen",
    "wof:placetype":"venue"
},
  "geometry": {"coordinates":[8.0430116653,47.2823600769],"type":"Point"}
}