{
  "type": "Feature",
  "properties": {
    "iso:country":"CH",
    "sg:address":"Widenstrasse 7",
    "sg:city":"Rorschach",
    "sg:orig_category":"Herstellung von sonstigen Holzwaren",
    "sg:phone":"+41 33 951 11 59",
    "sg:postcode":"9400",
    "sg:province":"St. Gallen",
    "wof:name":"Rodi Guido.",
    "wof:placetype":"venue"
},
  "geometry": {"coordinates":[8.0529747009,46.7510986328],"type":"Point"}
}