{
  "type": "Feature",
  "properties": {
    "iso:country":"CH",
    "sg:address":"Kantonsstrasse 5",
    "sg:city":"Zizers",
    "sg:orig_category":"Zimmerei, Dachdeckerei, Bauspenglerei U Abdichtung",
    "sg:postcode":"7205",
    "sg:province":"Graubunden",
    "wof:name":"Casut A. + M. Ag",
    "wof:placetype":"venue"
},
  "geometry": {"coordinates":[9.5673341751,46.9395370483],"type":"Point"}
}