{
  "type": "Feature",
  "properties": {
    "iso:country":"CH",
    "sg:address":"Praille Chemin De La 24 1920 Martigny. Postfach",
    "sg:city":"Martigny",
    "sg:orig_category":"Sonstiger spezialisierter Hoch U Tiefbau",
    "sg:postcode":"1920",
    "sg:province":"Valais",
    "wof:name":"Mba Construction Sa Traveaux De Ma\u00e7onnerie Etc",
    "wof:placetype":"venue"
},
  "geometry": {"coordinates":[7.0729198456,46.1013793945],"type":"Point"}
}