{
  "type": "Feature",
  "properties": {
    "iso:country":"CH",
    "sg:address":"Bergstrasse 8881 Walenstadtberg. Postfach",
    "sg:city":"Walenstadtberg",
    "sg:classifiers":[
        {
            "category":"Travel",
            "subcategory":"Hotels & Motels",
            "type":"Entertainment"
        }
    ],
    "sg:postcode":"8881",
    "sg:province":"St. Gallen",
    "sg:tags":[
        "hotels",
        "mit",
        "restaurant"
    ],
    "wof:name":"Schmid",
    "wof:placetype":"venue"
},
  "geometry": {"coordinates":[9.2957086563,47.1362075806],"type":"Point"}
}