{
  "type": "Feature",
  "properties": {
    "iso:country":"CH",
    "sg:address":"6562",
    "sg:city":"Soazza",
    "sg:orig_category":"Wirtschaftspr\u00fcfung, Steuerberatung U Treuhand",
    "sg:phone":"+41 91 831 19 48",
    "sg:postcode":"6562",
    "sg:province":"Graubunden",
    "wof:name":"Studio Fiduciario Canonica Moreno",
    "wof:placetype":"venue"
},
  "geometry": {"coordinates":[9.2218103409,46.3655471802],"type":"Point"}
}