{
  "type": "Feature",
  "properties": {
    "iso:country":"CH",
    "sg:address":"Oberer Gansbach 1",
    "sg:city":"Appenzell",
    "sg:classifiers":[
        {
            "category":"Restaurant",
            "type":"Food & Drink"
        }
    ],
    "sg:phone":"+41 71 787 14 32",
    "sg:postcode":"9050",
    "sg:province":"Appenzell Innerhoden",
    "wof:name":"Wirtschaft Zur Post",
    "wof:placetype":"venue"
},
  "geometry": {"coordinates":[9.4084873199,47.3298797607],"type":"Point"}
}