{
  "type": "Feature",
  "properties": {
    "iso:country":"CH",
    "sg:address":"Auf Dem Wolf 32",
    "sg:city":"Basel",
    "sg:orig_category":"Instandhaltung U Reparatur von Automobilen",
    "sg:phone":"+41 61 313 55 30",
    "sg:postcode":"4052",
    "sg:province":"Basel-Stadt",
    "wof:name":"Garage + Carrosserie Blasutto A.",
    "wof:placetype":"venue"
},
  "geometry": {"coordinates":[7.6142730713,47.5402412415],"type":"Point"}
}