{
  "type": "Feature",
  "properties": {
    "iso:country":"CH",
    "sg:address":"Dorfstrasse 9 8484 Weisslingen. Postfach",
    "sg:city":"Weisslingen",
    "sg:orig_category":"Detailhandel mit Waren verschiedener Art, Hauptrichtung Nahrungsmittel Landwirtschaftliche Genossens",
    "sg:phone":"+41 52 384 12 94",
    "sg:postcode":"8484",
    "sg:province":"Z\u00fcrich",
    "wof:name":"Landi Weisslingen-zell",
    "wof:placetype":"venue"
},
  "geometry": {"coordinates":[8.7648591995,47.4301147461],"type":"Point"}
}