{
  "type": "Feature",
  "properties": {
    "iso:country":"CH",
    "sg:address":"Alpenstrasse 205 Magglingen 2533 Evilard. Postfach",
    "sg:city":"Magglingen/macolin",
    "sg:orig_category":"Verwaltung von Immobilien",
    "sg:postcode":"2532",
    "sg:province":"Bern",
    "wof:name":"Salvato Gian-franco",
    "wof:placetype":"venue"
},
  "geometry": {"coordinates":[7.2369737625,47.149307251],"type":"Point"}
}