{
  "type": "Feature",
  "properties": {
    "addr:full":"Via Lucmagn Disentis/must\u00e9r Graubunden 7180",
    "addr:postcode":"7180",
    "addr:street":"Via Lucmagn",
    "iso:country":"CH",
    "sg:address":"Via Lucmagn",
    "sg:city":"Disentis/must\u00e9r",
    "sg:orig_category":"Bauschreinerei",
    "sg:phone":"+41 81 947 53 84",
    "sg:postcode":"7180",
    "sg:province":"Graubunden",
    "wof:name":"Fidel Deflorin Schreinerei",
    "wof:placetype":"venue"
},
  "geometry": {"coordinates":[8.853021,46.702709],"type":"Point"}
}