{
  "type": "Feature",
  "properties": {
    "iso:country":"CH",
    "sg:address":"Gotthardstrasse 30 6490 Andermatt. Postfach 21",
    "sg:city":"Andermatt",
    "sg:orig_category":"Detailhandel mit Waren verschiedener Art, Hauptrichtung Nahrungsmittel",
    "sg:phone":"+41 41 887 12 22",
    "sg:postcode":"6490",
    "sg:province":"Uri",
    "wof:name":"Coop Center",
    "wof:placetype":"venue"
},
  "geometry": {"coordinates":[8.5962677002,46.6343727112],"type":"Point"}
}