{
  "type": "Feature",
  "properties": {
    "iso:country":"CH",
    "sg:address":"Holunderweg 71 4500 Solothurn. Postfach",
    "sg:city":"Solothurn",
    "sg:orig_category":"Fachdetailhandel in Verkaufsr\u00e4umen",
    "sg:postcode":"4500",
    "sg:province":"Solothurn",
    "wof:name":"For Roses, Schnetzer Nicole Blumen, Pflanzen, Gebinde Und Dekorationsmaterial; Import Handel Und Vertrieb",
    "wof:placetype":"venue"
},
  "geometry": {"coordinates":[8.7844800949,47.2016906738],"type":"Point"}
}