{
  "type": "Feature",
  "properties": {
    "iso:country":"CH",
    "sg:address":"Trottgasse 11",
    "sg:city":"Gipf Oberfrick",
    "sg:classifiers":[
        {
            "category":"Banks & Credit Unions",
            "subcategory":"Bank",
            "type":"Services"
        }
    ],
    "sg:phone":"+41 4164611048",
    "sg:postcode":"5264",
    "wof:name":"Schweiz. Mobiliar",
    "wof:placetype":"venue"
},
  "geometry": {"coordinates":[8.004329,47.502754],"type":"Point"}
}