{
  "type": "Feature",
  "properties": {
    "iso:country":"CH",
    "sg:address":"Cornelistrasse 12",
    "sg:city":"Hitzkirch",
    "sg:orig_category":"Fussboden, Fliesen U Plattenlegerei, Tapeziererei",
    "sg:postcode":"6285",
    "sg:province":"Luzern",
    "wof:name":"Bachmann P. Ofenbau & Plattenbel\u00e4ge",
    "wof:placetype":"venue"
},
  "geometry": {"coordinates":[8.2618207932,47.2236938477],"type":"Point"}
}