{
  "type": "Feature",
  "properties": {
    "iso:country":"CH",
    "sg:address":"Krummatt 1",
    "sg:city":"Seengen",
    "sg:orig_category":"P\u00e9dicure",
    "sg:phone":"+41 62 777 20 20",
    "sg:postcode":"5707",
    "sg:province":"Aargau",
    "wof:name":"Marlies K\u00fcndig P\u00e9dicure",
    "wof:placetype":"venue"
},
  "geometry": {"coordinates":[8.2115097046,47.3271408081],"type":"Point"}
}