{
  "type": "Feature",
  "properties": {
    "iso:country":"CH",
    "sg:address":"Buckhauserstrasse 24 8048 Z\u00fcrich. Postfach Postfach 2260",
    "sg:city":"Z\u00fcrich",
    "sg:orig_category":"Telefonmarketingagenturen",
    "sg:phone":"+41 71 555 08 00",
    "sg:postcode":"8040",
    "sg:province":"Z\u00fcrich",
    "wof:name":"Call World Telemarketing Ag",
    "wof:placetype":"venue"
},
  "geometry": {"coordinates":[9.395459,47.435478],"type":"Point"}
}