{
  "type": "Feature",
  "properties": {
    "iso:country":"CH",
    "sg:address":"Baarerstrasse 10 6300 Zug. Postfach 439",
    "sg:city":"Zug",
    "sg:orig_category":"Non-Classified Establishments",
    "sg:phone":"+41 41 711 33 18",
    "sg:postcode":"6300",
    "sg:province":"Zug",
    "wof:name":"Abucon Holding Ag",
    "wof:placetype":"venue"
},
  "geometry": {"coordinates":[8.5164327621,47.1715621948],"type":"Point"}
}