{
  "type": "Feature",
  "properties": {
    "iso:country":"CH",
    "sg:address":"8526",
    "sg:city":"Oberneunforn",
    "sg:orig_category":"Sportvereine Sch\u00fctzen",
    "sg:phone":"+41 52 761 18 69",
    "sg:postcode":"8526",
    "sg:province":"Thurgau",
    "wof:name":"Feldsch\u00fctzengesellschaft",
    "wof:placetype":"venue"
},
  "geometry": {"coordinates":[8.7669696808,47.6066207886],"type":"Point"}
}