{
  "type": "Feature",
  "properties": {
    "iso:country":"CH",
    "sg:address":"Colons Sous Les 31",
    "sg:city":"Malleray",
    "sg:orig_category":"G\u00fcterbef\u00f6rderung im Strassenverkehr",
    "sg:phone":"+41 33 681 17 82",
    "sg:postcode":"2735",
    "sg:province":"Bern",
    "wof:name":"Moser Markus",
    "wof:placetype":"venue"
},
  "geometry": {"coordinates":[7.5236182213,46.6585121155],"type":"Point"}
}