{
  "type": "Feature",
  "properties": {
    "iso:country":"CH",
    "sg:address":"Bahnhofstrasse 42",
    "sg:city":"Baden",
    "sg:orig_category":"Betrieb U technische Hilfsdienste des Kultur U Unterhaltungswesens",
    "sg:postcode":"5400",
    "sg:province":"Aargau",
    "wof:name":"Badenfahrtkomitee",
    "wof:placetype":"venue"
},
  "geometry": {"coordinates":[8.308808,47.477551],"type":"Point"}
}