{
  "type": "Feature",
  "properties": {
    "iso:country":"CH",
    "sg:address":"Rheinstrasse 1",
    "sg:city":"Widnau",
    "sg:orig_category":"Detailhandel mit Radio U Fernsehger\u00e4ten Fachdetailhandel in Verkaufsr\u00e4umen",
    "sg:postcode":"9443",
    "sg:province":"St. Gallen",
    "wof:name":"Foto-radio N\u00fcesch",
    "wof:placetype":"venue"
},
  "geometry": {"coordinates":[9.647395134,47.4071235657],"type":"Point"}
}