{
  "type": "Feature",
  "properties": {
    "iso:country":"CH",
    "sg:address":"Waffengasse 20",
    "sg:city":"Biel/bienne",
    "sg:orig_category":"Religi\u00f6se Vereinigungen",
    "sg:postcode":"2500",
    "sg:province":"Bern",
    "wof:name":"Schweizerische Islamische Glaubensgemeinschaft (sig)",
    "wof:placetype":"venue"
},
  "geometry": {"coordinates":[8.7955217361,47.309967041],"type":"Point"}
}