{
  "type": "Feature",
  "properties": {
    "addr:full":"Rue Du Ch\u00e2teau 7 Bevaix Neuch\u00e2tel 2022",
    "addr:housenumber":"7",
    "addr:postcode":"2022",
    "addr:street":"Rue Du Cha\u0302Teau;Neucha\u0302Tel",
    "iso:country":"CH",
    "sg:address":"Rue Du Ch\u00e2teau 7",
    "sg:city":"Bevaix",
    "sg:orig_category":"Arztpraxen",
    "sg:phone":"+41 79 606 34 51",
    "sg:postcode":"2022",
    "sg:province":"Neuch\u00e2tel",
    "wof:name":"Dr M\u00e9d. Francis Racine M\u00e9decin G\u00e9n\u00e9raliste",
    "wof:placetype":"venue"
},
  "geometry": {"coordinates":[6.812833,46.928131],"type":"Point"}
}