{
  "type": "Feature",
  "properties": {
    "iso:country":"CH",
    "sg:address":"Willadingweg 42",
    "sg:city":"Bern",
    "sg:orig_category":"Elektroinstallation",
    "sg:phone":"+41 31 352 27 27",
    "sg:postcode":"3000",
    "sg:province":"Bern",
    "wof:name":"Pauli-elektro Ag Elektroger\u00e4te; Handel, Installationen",
    "wof:placetype":"venue"
},
  "geometry": {"coordinates":[7.4650421143,46.9369277954],"type":"Point"}
}