{
  "type": "Feature",
  "properties": {
    "iso:country":"CH",
    "sg:address":"Im Str\u00e4ler 7",
    "sg:city":"Z\u00fcrich",
    "sg:classifiers":[
        {
            "category":"Professional",
            "subcategory":"Employment Agencies",
            "type":"Services"
        }
    ],
    "sg:phone":"+41 14918449",
    "sg:postcode":"8047",
    "sg:province":"Z\u00fcrich",
    "sg:tags":[
        "factoring"
    ],
    "wof:name":"Gosa Ag",
    "wof:placetype":"venue"
},
  "geometry": {"coordinates":[8.5001964569,47.3720703125],"type":"Point"}
}