{
  "type": "Feature",
  "properties": {
    "addr:full":"Waffenplatzstrasse 64 Z\u00fcrich Z\u00fcrich 8002",
    "addr:housenumber":"64",
    "addr:postcode":"8002",
    "addr:street":"Waffenplatzstrasse",
    "iso:country":"CH",
    "sg:address":"Waffenplatzstrasse 64",
    "sg:city":"Z\u00fcrich",
    "sg:orig_category":"Allgemeiner Hoch U Tiefbau Strassenbau",
    "sg:phone":"+41 12813058",
    "sg:postcode":"8002",
    "sg:province":"Z\u00fcrich",
    "wof:name":"Meier Gebr\u00fcder Ag Tiefbauunternehmung",
    "wof:placetype":"venue"
},
  "geometry": {"coordinates":[8.52688,47.357552],"type":"Point"}
}