{
  "type": "Feature",
  "properties": {
    "iso:country":"CH",
    "sg:address":"Talackerstrasse 65a",
    "sg:city":"Thun",
    "sg:orig_category":"Grosshandel mit Holz U Baustoffen",
    "sg:phone":"+41 33 335 21 84",
    "sg:postcode":"3604",
    "sg:province":"Bern",
    "wof:name":"Futura Invest Consulting Gmbh",
    "wof:placetype":"venue"
},
  "geometry": {"coordinates":[7.6124329567,46.7433853149],"type":"Point"}
}