{
  "type": "Feature",
  "properties": {
    "iso:country":"CH",
    "sg:address":"W\u00fclflingerstrasse 393",
    "sg:city":"Winterthur",
    "sg:orig_category":"Instandhaltung U Reparatur von Automobilen",
    "sg:postcode":"8408",
    "sg:province":"Z\u00fcrich",
    "wof:name":"Garage Sancassani Ag",
    "wof:placetype":"venue"
},
  "geometry": {"coordinates":[8.679810524,47.5160446167],"type":"Point"}
}