{
  "type": "Feature",
  "properties": {
    "iso:country":"CH",
    "sg:address":"Rankhofstrasse 22",
    "sg:city":"Luzern",
    "sg:orig_category":"Interessenvertretungen",
    "sg:postcode":"6006",
    "sg:province":"Luzern",
    "wof:name":"Jugendalp Eigenthal",
    "wof:placetype":"venue"
},
  "geometry": {"coordinates":[8.3130168915,47.0637397766],"type":"Point"}
}