{
  "type": "Feature",
  "properties": {
    "addr:full":"Husacher 6 M\u00fcnchringen Bern 3303",
    "addr:housenumber":"6",
    "addr:postcode":"3303",
    "addr:street":"Husacher",
    "iso:country":"CH",
    "sg:address":"Husacher 6",
    "sg:city":"M\u00fcnchringen",
    "sg:orig_category":"Datenverarbeitungsdienste",
    "sg:phone":"+41 31 761 37 91",
    "sg:postcode":"3303",
    "sg:province":"Bern",
    "wof:name":"Fredy Graber Ag Edv-realisierung",
    "wof:placetype":"venue"
},
  "geometry": {"coordinates":[7.524543,47.046562],"type":"Point"}
}