{
  "type": "Feature",
  "properties": {
    "iso:country":"CH",
    "sg:address":"Collombey Route De 35",
    "sg:city":"Monthey",
    "sg:orig_category":"Softwareentwicklung U beratung",
    "sg:postcode":"1870",
    "sg:province":"Valais",
    "wof:name":"Color Pix Gmbh",
    "wof:placetype":"venue"
},
  "geometry": {"coordinates":[9.1504201889,47.5487518311],"type":"Point"}
}