{
  "type": "Feature",
  "properties": {
    "iso:country":"CH",
    "sg:address":"Schachenstr. 1",
    "sg:city":"Spiez",
    "sg:classifiers":[
        {
            "category":"Autos & Motor Vehicles",
            "subcategory":"Boat Sales",
            "type":"Retail Goods"
        }
    ],
    "sg:phone":"+41 33 654 34 74",
    "sg:postcode":"3700",
    "sg:province":"Bern",
    "sg:tags":[
        "equipment",
        "transport"
    ],
    "wof:name":"Mueller Ag Yacht Und Bootswerft Spiez",
    "wof:placetype":"venue"
},
  "geometry": {"coordinates":[7.687122,46.688614],"type":"Point"}
}