{
  "type": "Feature",
  "properties": {
    "iso:country":"CH",
    "sg:address":"Piazzo",
    "sg:city":"Brusio",
    "sg:orig_category":"Autogaragen Autospenglereien",
    "sg:phone":"+41 79 611 08 11",
    "sg:postcode":"7743",
    "sg:province":"Graubunden",
    "wof:name":"Quinto Crameri Garage & Carrozzeria",
    "wof:placetype":"venue"
},
  "geometry": {"coordinates":[10.120435,46.260849],"type":"Point"}
}