{
  "type": "Feature",
  "properties": {
    "iso:country":"CH",
    "sg:address":"Vallera Via",
    "sg:city":"Genestrerio",
    "sg:orig_category":"Detailhandel mit Antiquit\u00e4ten U Gebrauchtwaren in Verkaufsr\u00e4umen",
    "sg:phone":"+41 91 647 31 11",
    "sg:postcode":"6852",
    "sg:province":"Ticino",
    "wof:name":"Alberto Sanguin, Succ. A Francesco Lur\u00e0",
    "wof:placetype":"venue"
},
  "geometry": {"coordinates":[8.960767,45.857136],"type":"Point"}
}