{
  "type": "Feature",
  "properties": {
    "iso:country":"CH",
    "sg:address":"Route Du Vieux Canal 2",
    "sg:city":"Givisiez",
    "sg:orig_category":"Pensionskassen",
    "sg:postcode":"1762",
    "sg:province":"Fribourg",
    "wof:name":"Fondation En Faveur Du Personnel De La Soci\u00e9t\u00e9 Anonyme Des Pneumatiques Michelin",
    "wof:placetype":"venue"
},
  "geometry": {"coordinates":[7.1174001694,46.8140716553],"type":"Point"}
}