{
  "type": "Feature",
  "properties": {
    "iso:country":"CH",
    "sg:address":"Chalet Primev\u00e8re",
    "sg:city":"Morgins",
    "sg:orig_category":"Detailhandel mit Antiquit\u00e4ten",
    "sg:phone":"+41 24 477 14 42",
    "sg:postcode":"1875",
    "sg:province":"Valais",
    "wof:name":"G\u00e9rald Lange Antiquit\u00e9s",
    "wof:placetype":"venue"
},
  "geometry": {"coordinates":[6.858753,46.237522],"type":"Point"}
}