{
  "type": "Feature",
  "properties": {
    "iso:country":"CH",
    "sg:address":"Bahnhofstrasse 24",
    "sg:city":"Inkwil",
    "sg:orig_category":"Softwareentwicklung U beratung",
    "sg:postcode":"3375",
    "sg:province":"Bern",
    "wof:name":"Schaad A., Research United Technologies",
    "wof:placetype":"venue"
},
  "geometry": {"coordinates":[7.6723709106,47.1971740723],"type":"Point"}
}