{
  "type": "Feature",
  "properties": {
    "iso:country":"CH",
    "sg:address":"R\u00f6merstrasse 10",
    "sg:city":"Nidau",
    "sg:classifiers":[
        {
            "category":"Banks & Credit Unions",
            "subcategory":"Investment Brokerage",
            "type":"Services"
        }
    ],
    "sg:phone":"+41 32 331 82 48",
    "sg:postcode":"2560",
    "sg:province":"Bern",
    "sg:tags":[
        "cavity",
        "sinking",
        "operation",
        "cnc"
    ],
    "wof:name":"Paoluzzo Ag",
    "wof:placetype":"venue"
},
  "geometry": {"coordinates":[7.249241,47.122799],"type":"Point"}
}