{
  "type": "Feature",
  "properties": {
    "iso:country":"CH",
    "sg:address":"Mellingerstrasse 1",
    "sg:city":"Baden",
    "sg:orig_category":"Grosshandel mit Erzen U Metallen",
    "sg:phone":"+41 56 203 60 40",
    "sg:postcode":"5400",
    "sg:province":"Aargau",
    "wof:name":"Bekaert (schweiz) Ag",
    "wof:placetype":"venue"
},
  "geometry": {"coordinates":[8.3052854538,47.4710121155],"type":"Point"}
}