{
  "type": "Feature",
  "properties": {
    "iso:country":"CH",
    "sg:address":"Morystrasse 53d",
    "sg:city":"Riehen",
    "sg:orig_category":"Grosshandel mit pharmazeutischen Erzeugnissen, medizinischen U orthop\u00e4dischen Artikeln",
    "sg:postcode":"4125",
    "sg:province":"Basel-Stadt",
    "wof:name":"Digi Artis Ag",
    "wof:placetype":"venue"
},
  "geometry": {"coordinates":[7.6429800987,47.571308136],"type":"Point"}
}