{
  "type": "Feature",
  "properties": {
    "iso:country":"CH",
    "sg:address":"Promenthoux 1197 Prangins. Postfach",
    "sg:city":"Prangins",
    "sg:orig_category":"Grosshandel mit Getr\u00e4nken",
    "sg:postcode":"1197",
    "sg:province":"Vaud",
    "wof:name":"K & K Promotions Sa, Succursale De Prangins N\u00e9goce De Vins Et Spiritueux",
    "wof:placetype":"venue"
},
  "geometry": {"coordinates":[6.2568249702,46.3939590454],"type":"Point"}
}