{
  "type": "Feature",
  "properties": {
    "iso:country":"CH",
    "sg:address":"G\u00e4rischstrasse 1",
    "sg:city":"Bellach",
    "sg:orig_category":"RESTAURANTS: TEA-ROOMS",
    "sg:phone":"+41 32 618 21 84",
    "sg:postcode":"4512",
    "sg:province":"Solothurn",
    "wof:name":"Knubel W.",
    "wof:placetype":"venue"
},
  "geometry": {"coordinates":[7.5007138252,47.2139625549],"type":"Point"}
}