{
  "type": "Feature",
  "properties": {
    "iso:country":"CH",
    "sg:address":"T\u00f6distrasse 5",
    "sg:city":"Wil",
    "sg:classifiers":[
        {
            "category":"Manufacturing",
            "subcategory":"Wood Products",
            "type":"Manufacturing & Wholesale Goods"
        }
    ],
    "sg:phone":"+41 71 923 29 29",
    "sg:postcode":"9500",
    "sg:province":"St. Gallen",
    "sg:tags":[
        "made",
        "balcony"
    ],
    "wof:name":"Thalmann Holzbau Ag",
    "wof:placetype":"venue"
},
  "geometry": {"coordinates":[9.044886,47.459232],"type":"Point"}
}