{
  "type": "Feature",
  "properties": {
    "addr:full":"Feffetstrasse 14 R\u00fcthi St. Gallen 9464",
    "addr:housenumber":"14;st.",
    "addr:postcode":"9464",
    "addr:street":"Feffetstrasse",
    "iso:country":"CH",
    "sg:address":"Feffetstrasse 14",
    "sg:city":"R\u00fcthi",
    "sg:orig_category":"Decorative Fittings, Frames, Profiles, Embossing",
    "sg:phone":"+41 71 767 90 10",
    "sg:postcode":"9464",
    "sg:province":"St. Gallen",
    "wof:name":"Wkw Kunststofftechnik Ag",
    "wof:placetype":"venue"
},
  "geometry": {"coordinates":[9.536935,47.288345],"type":"Point"}
}