{
  "type": "Feature",
  "properties": {
    "iso:country":"CH",
    "sg:address":"Alemannengasse 88",
    "sg:city":"Basel",
    "sg:orig_category":"Physiotherapie",
    "sg:phone":"+41 61 691 38 02",
    "sg:postcode":"4058",
    "sg:province":"Basel-Stadt",
    "wof:name":"Physiotherapie Rolfing",
    "wof:placetype":"venue"
},
  "geometry": {"coordinates":[7.6044168472,47.5578689575],"type":"Point"}
}