{
  "type": "Feature",
  "properties": {
    "iso:country":"CH",
    "sg:address":"Grand-rue 37",
    "sg:city":"Nyon",
    "sg:orig_category":"Architektur U Ingenieurb\u00fcros",
    "sg:phone":"+41 22 361 36 10",
    "sg:postcode":"1260",
    "sg:province":"Vaud",
    "wof:name":"Adn Atelier D'architecture S\u00e0rl",
    "wof:placetype":"venue"
},
  "geometry": {"coordinates":[6.238233,46.380733],"type":"Point"}
}