{
  "type": "Feature",
  "properties": {
    "iso:country":"CH",
    "sg:address":"Kinderspital Luzern",
    "sg:city":"Luzern",
    "sg:orig_category":"Gesundheitswesen",
    "sg:postcode":"6000",
    "sg:province":"Luzern",
    "wof:name":"Schweizerische Gesellschaft F\u00fcr Impfpromotion Sgip",
    "wof:placetype":"venue"
},
  "geometry": {"coordinates":[8.4066858292,46.9998283386],"type":"Point"}
}