{
  "type": "Feature",
  "properties": {
    "iso:country":"CH",
    "sg:address":"Leberngasse 19",
    "sg:city":"Olten",
    "sg:orig_category":"Saunas Solarien",
    "sg:phone":"+41 62 212 07 26",
    "sg:postcode":"4600",
    "sg:province":"Solothurn",
    "wof:name":"Massagen Carina",
    "wof:placetype":"venue"
},
  "geometry": {"coordinates":[7.9012880325,47.3490524292],"type":"Point"}
}