{
  "type": "Feature",
  "properties": {
    "iso:country":"CH",
    "sg:address":"Farbgasse 14",
    "sg:city":"Langenthal",
    "sg:orig_category":"Wohnheime",
    "sg:phone":"+41 62 922 20 12",
    "sg:postcode":"4900",
    "sg:province":"Bern",
    "wof:name":"B\u00fchler-toschi Martha Lina Stiftung",
    "wof:placetype":"venue"
},
  "geometry": {"coordinates":[7.7886691093,47.2109260559],"type":"Point"}
}