{
  "type": "Feature",
  "properties": {
    "iso:country":"CH",
    "sg:address":"Bucherstrasse 1-3",
    "sg:city":"Burgdorf",
    "sg:orig_category":"Pensionskassen",
    "sg:phone":"+41 31 555 18 11",
    "sg:postcode":"3400",
    "sg:province":"Bern",
    "wof:name":"Pensionskasse Sbb",
    "wof:placetype":"venue"
},
  "geometry": {"coordinates":[7.4297409058,46.9449501038],"type":"Point"}
}