{
  "type": "Feature",
  "properties": {
    "iso:country":"CH",
    "sg:address":"Wetzikerstrasse 31",
    "sg:city":"Hittnau",
    "sg:orig_category":"Erbringung von Dienstleistungen f\u00fcr Unternehmen",
    "sg:phone":"+41 19504783",
    "sg:postcode":"8335",
    "sg:province":"Z\u00fcrich",
    "wof:name":"Fischer Meinrad",
    "wof:placetype":"venue"
},
  "geometry": {"coordinates":[8.8236131668,47.359500885],"type":"Point"}
}