{
  "type": "Feature",
  "properties": {
    "iso:country":"CH",
    "sg:address":"Lausanne Rue De 19",
    "sg:city":"Payerne",
    "sg:orig_category":"Unclassifiable Establishments",
    "sg:postcode":"1530",
    "sg:province":"Vaud",
    "wof:name":"Pharma Von Arx Sa",
    "wof:placetype":"venue"
},
  "geometry": {"coordinates":[6.9367489815,46.8198814392],"type":"Point"}
}