{
  "type": "Feature",
  "properties": {
    "iso:country":"CH",
    "sg:address":"Baarerstrasse 63",
    "sg:city":"Zug",
    "sg:orig_category":"Sonstiger Grosshandel",
    "sg:phone":"+41 17801091",
    "sg:postcode":"6300",
    "sg:province":"Zug",
    "wof:name":"Trapol Ag",
    "wof:placetype":"venue"
},
  "geometry": {"coordinates":[8.5173740387,47.1761703491],"type":"Point"}
}