{
  "type": "Feature",
  "properties": {
    "iso:country":"CH",
    "sg:address":"Gartenstrasse 3",
    "sg:city":"Schlieren",
    "sg:orig_category":"Sonstige Kurierdienste",
    "sg:phone":"+41 56 633 53 34",
    "sg:postcode":"8952",
    "sg:province":"Z\u00fcrich",
    "wof:name":"Ryffel Hans",
    "wof:placetype":"venue"
},
  "geometry": {"coordinates":[8.344452858,47.3506698608],"type":"Point"}
}