{
  "type": "Feature",
  "properties": {
    "iso:country":"CH",
    "sg:address":"Gribbio",
    "sg:city":"Chironico",
    "sg:orig_category":"Haltung von Rindern",
    "sg:postcode":"6747",
    "sg:province":"Ticino",
    "wof:name":"Consorzio Allevamento Bestiame Bovino Di Gribbio",
    "wof:placetype":"venue"
},
  "geometry": {"coordinates":[8.8077201843,46.4542007446],"type":"Point"}
}