{
  "type": "Feature",
  "properties": {
    "iso:country":"CH",
    "sg:address":"Regensbergstrasse 238",
    "sg:city":"Z\u00fcrich",
    "sg:orig_category":"Unclassifiable Establishments",
    "sg:postcode":"8050",
    "sg:province":"Z\u00fcrich",
    "wof:name":"Greif Spain Holdings, S.l., Bilbao, Zweigniederlassung Z\u00fcrich",
    "wof:placetype":"venue"
},
  "geometry": {"coordinates":[8.5319814682,47.4107475281],"type":"Point"}
}