{
  "type": "Feature",
  "properties": {
    "iso:country":"CH",
    "sg:address":"M\u00fchlehof",
    "sg:city":"Herisau",
    "sg:orig_category":"Sanit\u00e4rinstallation U Spenglerei Zimmerei, Dachdeckerei, Bauspenglerei U Abdichtung",
    "sg:phone":"+41 71 350 07 20",
    "sg:postcode":"9100",
    "sg:province":"Appenzell Ausserrhoden",
    "wof:name":"Alder Spenglerei, Inhaber Jud Fio",
    "wof:placetype":"venue"
},
  "geometry": {"coordinates":[9.2721443176,47.3836097717],"type":"Point"}
}