{
  "type": "Feature",
  "properties": {
    "iso:country":"CH",
    "sg:address":"Pappelweg 4",
    "sg:city":"Horgen",
    "sg:orig_category":"Vereine Gesang",
    "sg:phone":"+41 17255730",
    "sg:postcode":"8810",
    "sg:province":"Z\u00fcrich",
    "wof:name":"Arbeiter-s\u00e4ngerbund",
    "wof:placetype":"venue"
},
  "geometry": {"coordinates":[8.6190214157,47.2526168823],"type":"Point"}
}