{
  "type": "Feature",
  "properties": {
    "iso:country":"CH",
    "sg:address":"4493",
    "sg:city":"Wenslingen",
    "sg:orig_category":"Bezirks, Sekundar, Realschulen, Oberstufe der Primarschulen",
    "sg:phone":"+41 61 911 95 25",
    "sg:postcode":"4493",
    "sg:province":"Basel-Landschaft",
    "wof:name":"Kreisschule Dorneckberg Rektorat",
    "wof:placetype":"venue"
},
  "geometry": {"coordinates":[7.666419,47.449715],"type":"Point"}
}