{
  "type": "Feature",
  "properties": {
    "iso:country":"CH",
    "sg:address":"1679",
    "sg:city":"Villaraboud",
    "sg:orig_category":"Detailhandel mit Waren verschiedener Art, Hauptrichtung Nahrungsmittel",
    "sg:phone":"+41 26 655 15 71",
    "sg:postcode":"1679",
    "sg:province":"Fribourg",
    "wof:name":"Paul Ayer Epicerie",
    "wof:placetype":"venue"
},
  "geometry": {"coordinates":[6.9131598473,46.6603393555],"type":"Point"}
}