{
  "type": "Feature",
  "properties": {
    "iso:country":"CH",
    "sg:address":"Chemin De Montelly 48",
    "sg:city":"Lausanne",
    "sg:orig_category":"Satzherstellung U Reproduktion Schnelldruck U Kopierservice",
    "sg:phone":"+41 21 626 06 65",
    "sg:postcode":"1007",
    "sg:province":"Vaud",
    "wof:name":"G.m. Tschudi Sa Photocomposition",
    "wof:placetype":"venue"
},
  "geometry": {"coordinates":[6.6093111038,46.5216026306],"type":"Point"}
}