{
  "type": "Feature",
  "properties": {
    "iso:country":"CH",
    "sg:address":"Im Gugel 403",
    "sg:city":"T\u00e4gerig",
    "sg:classifiers":[
        {
            "category":"Banks & Credit Unions",
            "subcategory":"Bank",
            "type":"Services"
        }
    ],
    "sg:phone":"+41 4156913313",
    "sg:postcode":"5522",
    "sg:province":"Aargau",
    "wof:name":"Aargauische Kantonalbank",
    "wof:placetype":"venue"
},
  "geometry": {"coordinates":[8.2734,47.404202],"type":"Point"}
}