{
  "type": "Feature",
  "properties": {
    "iso:country":"CH",
    "sg:address":"Lindenstrasse 94",
    "sg:city":"Effretikon",
    "sg:orig_category":"Erschliessung von Grundst\u00fccken",
    "sg:phone":"+41 52 347 04 14",
    "sg:postcode":"8307",
    "sg:province":"Z\u00fcrich",
    "wof:name":"Baugenossenschaft Illeffi",
    "wof:placetype":"venue"
},
  "geometry": {"coordinates":[8.699174881,47.426109314],"type":"Point"}
}