{
  "type": "Feature",
  "properties": {
    "iso:country":"CH",
    "sg:address":"Wunderklingen 541",
    "sg:city":"Hallau",
    "sg:orig_category":"Zoll- and Grenzb\u00fcros",
    "sg:phone":"+41 52 681 32 89",
    "sg:postcode":"8215",
    "sg:province":"Schaffhausen",
    "wof:name":"Eidg. Zollverwaltung Zollamt Wunderklingen",
    "wof:placetype":"venue"
},
  "geometry": {"coordinates":[8.4525499344,47.6964111328],"type":"Point"}
}