{
  "type": "Feature",
  "properties": {
    "iso:country":"CH",
    "sg:address":"Bahnhofstrasse 3 8272 Ermatingen. Postfach",
    "sg:city":"Ermatingen",
    "sg:orig_category":"Elektroinstallation",
    "sg:phone":"+41 71 660 00 60",
    "sg:postcode":"8272",
    "sg:province":"Thurgau",
    "wof:name":"H\u00e4mmerli Ch.",
    "wof:placetype":"venue"
},
  "geometry": {"coordinates":[9.0844888687,47.6699752808],"type":"Point"}
}