{
  "type": "Feature",
  "properties": {
    "addr:full":"Bruchbachweg 26 3312 Fraubrunnen. Postfach Fraubrunnen Bern 3312",
    "addr:housenumber":"26",
    "addr:postcode":"3312 fraubrunnen. postfach;3312",
    "addr:street":"Bruchbachweg",
    "iso:country":"CH",
    "sg:address":"Bruchbachweg 26 3312 Fraubrunnen. Postfach",
    "sg:city":"Fraubrunnen",
    "sg:orig_category":"Architektur U Ingenieurb\u00fcros Bauingenieurb\u00fcros",
    "sg:phone":"+41 26 672 91 81",
    "sg:postcode":"3312",
    "sg:province":"Bern",
    "wof:name":"Benninger Ingenieure Ag",
    "wof:placetype":"venue"
},
  "geometry": {"coordinates":[7.108453,46.925232],"type":"Point"}
}