{
  "type": "Feature",
  "properties": {
    "iso:country":"CH",
    "sg:address":"Kreuzhausweg 1",
    "sg:city":"Kriens",
    "sg:classifiers":[
        {
            "category":"Home & Garden",
            "subcategory":"Furniture",
            "type":"Retail Goods"
        }
    ],
    "sg:phone":"+41 41 320 23 23",
    "sg:postcode":"6010",
    "sg:province":"Luzern",
    "sg:tags":[
        "wood"
    ],
    "wof:name":"Lachappelle Ag",
    "wof:placetype":"venue"
},
  "geometry": {"coordinates":[8.2693033218,47.0348701477],"type":"Point"}
}