{
  "type": "Feature",
  "properties": {
    "iso:country":"CH",
    "sg:address":"Groppenackerstrasse 7",
    "sg:city":"Spreitenbach",
    "sg:orig_category":"Handelsvermittlung U Grosshandel R\u00fcckgewinnung U Vorbereitung f\u00fcr die Wiederverwertung Recycling",
    "sg:phone":"+41 56 401 24 40",
    "sg:postcode":"8957",
    "sg:province":"Aargau",
    "wof:name":"Walter Wiederkehr Altmetalle",
    "wof:placetype":"venue"
},
  "geometry": {"coordinates":[8.3605365753,47.4215354919],"type":"Point"}
}