{
  "type": "Feature",
  "properties": {
    "iso:country":"CH",
    "sg:address":"Baarerstrasse 38",
    "sg:city":"Zug",
    "sg:orig_category":"Berufsbildende weiterf\u00fchrende Schulen",
    "sg:phone":"+41 41 710 43 55",
    "sg:postcode":"6300",
    "sg:province":"Zug",
    "wof:name":"Marco Capellini",
    "wof:placetype":"venue"
},
  "geometry": {"coordinates":[8.517145,47.174397],"type":"Point"}
}