{
  "type": "Feature",
  "properties": {
    "iso:country":"CH",
    "sg:address":"Via Serafino Balestra",
    "sg:city":"Lugano",
    "sg:orig_category":"Handels-H\u00e4user U Gesellschaften",
    "sg:postcode":"6900",
    "sg:province":"Ticino",
    "wof:name":"Incomat Sa",
    "wof:placetype":"venue"
},
  "geometry": {"coordinates":[8.9554004669,46.0080299377],"type":"Point"}
}