{
  "type": "Feature",
  "properties": {
    "iso:country":"CH",
    "sg:address":"Rouges-terres 22-24",
    "sg:city":"Hauterive",
    "sg:orig_category":"Instandhaltung U Reparatur von Automobilen",
    "sg:phone":"+41 32 724 44 24",
    "sg:postcode":"2068",
    "sg:province":"Neuch\u00e2tel",
    "wof:name":"Garage Du 1er Mars Sa",
    "wof:placetype":"venue"
},
  "geometry": {"coordinates":[6.9767570496,47.0122413635],"type":"Point"}
}