{
  "type": "Feature",
  "properties": {
    "iso:country":"CH",
    "sg:address":"Musackerweg 224",
    "sg:city":"Hirschthal",
    "sg:orig_category":"Verlegen von Fliesen U Platten",
    "sg:phone":"+41 62 721 32 88",
    "sg:postcode":"5042",
    "sg:province":"Aargau",
    "wof:name":"Hans Kamer Decken-& Wandverkleidungen",
    "wof:placetype":"venue"
},
  "geometry": {"coordinates":[8.0560398102,47.3219490051],"type":"Point"}
}