{
  "type": "Feature",
  "properties": {
    "iso:country":"CH",
    "sg:address":"Chilchweg 18",
    "sg:city":"Neuendorf",
    "sg:orig_category":"Nationale Postdienste",
    "sg:phone":"+41 62 398 47 00",
    "sg:postcode":"4623",
    "sg:province":"Solothurn",
    "wof:name":"Die Schweizerische Post",
    "wof:placetype":"venue"
},
  "geometry": {"coordinates":[7.7960519791,47.3007888794],"type":"Point"}
}