{
  "type": "Feature",
  "properties": {
    "addr:full":"Burghalde 19 Lenzburg Aargau 5600",
    "addr:housenumber":"19",
    "addr:postcode":"5600",
    "addr:street":"Burghalde",
    "iso:country":"CH",
    "sg:address":"Burghalde 19",
    "sg:city":"Lenzburg",
    "sg:orig_category":"Advokaturb\u00fcros Notariate",
    "sg:phone":"+41 62 891 22 80",
    "sg:postcode":"5600",
    "sg:province":"Aargau",
    "wof:name":"Gloor Fischer Hunziker Advokatur- & Notariatsb\u00fcro",
    "wof:placetype":"venue"
},
  "geometry": {"coordinates":[8.179571,47.385727],"type":"Point"}
}