{
  "type": "Feature",
  "properties": {
    "iso:country":"CH",
    "sg:address":"Heidenweg 2",
    "sg:city":"Erlach",
    "sg:classifiers":[
        {
            "category":"Restaurant",
            "type":"Food & Drink"
        }
    ],
    "sg:phone":"+41 32 338 16 35",
    "sg:postcode":"3235",
    "sg:province":"Bern",
    "wof:name":"Restaurant Du Port",
    "wof:placetype":"venue"
},
  "geometry": {"coordinates":[7.0992970467,47.0452804565],"type":"Point"}
}