{
  "type": "Feature",
  "properties": {
    "iso:country":"CH",
    "sg:address":"Hauptbahnhofstrasse 1 4500 Solothurn. Postfach",
    "sg:city":"Solothurn",
    "sg:orig_category":"Detailhandel mit Brillen U anderen Sehhilfen Fachdetailhandel in Verkaufsr\u00e4umen",
    "sg:phone":"+41 32 622 11 53",
    "sg:postcode":"4501",
    "sg:province":"Solothurn",
    "wof:name":"Stocker Optik Ag",
    "wof:placetype":"venue"
},
  "geometry": {"coordinates":[7.54048,47.205311],"type":"Point"}
}