{
  "type": "Feature",
  "properties": {
    "iso:country":"CH",
    "sg:address":"3716",
    "sg:city":"Kandergrund",
    "sg:classifiers":[
        {
            "category":"Government",
            "subcategory":"Post Office",
            "type":"Public Place"
        }
    ],
    "sg:phone":"+41 33 671 13 05",
    "sg:postcode":"3716",
    "sg:province":"Bern",
    "sg:tags":[
        "die",
        "poststellen"
    ],
    "wof:name":"Die Post",
    "wof:placetype":"venue"
},
  "geometry": {"coordinates":[7.6618871689,46.5452346802],"type":"Point"}
}