{
  "type": "Feature",
  "properties": {
    "iso:country":"CH",
    "sg:address":"Route Du Faubourg 13",
    "sg:city":"Avenches",
    "sg:orig_category":"Benzin, Heiz\u00f6l and Mineral\u00f6lprodukte Grosshandel Tankstellen",
    "sg:phone":"+41 21 944 16 65",
    "sg:postcode":"1580",
    "sg:province":"Vaud",
    "wof:name":"Agip (suisse) Sa",
    "wof:placetype":"venue"
},
  "geometry": {"coordinates":[6.856131,46.452225],"type":"Point"}
}