{
  "type": "Feature",
  "properties": {
    "iso:country":"CH",
    "sg:address":"Zypressenstrasse 71",
    "sg:city":"Z\u00fcrich",
    "sg:classifiers":[
        {
            "category":"Internet Cafe",
            "subcategory":"None",
            "type":"Food & Drink"
        }
    ],
    "sg:phone":"+41 12477070",
    "sg:postcode":"8004",
    "sg:province":"Z\u00fcrich",
    "sg:tags":[
        "provider"
    ],
    "wof:name":"Netcetera Ag Informationstechnologien",
    "wof:placetype":"venue"
},
  "geometry": {"coordinates":[8.5144348145,47.3785705566],"type":"Point"}
}