{
  "type": "Feature",
  "properties": {
    "iso:country":"CH",
    "sg:address":"Sperrstrasse 104b 4057 Basel. Postfach",
    "sg:city":"Basel",
    "sg:orig_category":"Architektur U Ingenieurb\u00fcros",
    "sg:phone":"+41 61 601 32 82",
    "sg:postcode":"4051",
    "sg:province":"Basel-Stadt",
    "wof:name":"Peter Hanhart, Architekt Htl Architektur U. Design.",
    "wof:placetype":"venue"
},
  "geometry": {"coordinates":[7.597218,47.565887],"type":"Point"}
}