{
  "type": "Feature",
  "properties": {
    "iso:country":"CH",
    "sg:address":"Zum Rank 134",
    "sg:city":"Beggingen",
    "sg:orig_category":"G\u00fcterbef\u00f6rderung im Strassenverkehr",
    "sg:postcode":"8228",
    "sg:province":"Schaffhausen",
    "wof:name":"Vogelsanger K.",
    "wof:placetype":"venue"
},
  "geometry": {"coordinates":[8.5382404327,47.7657546997],"type":"Point"}
}