{
  "type": "Feature",
  "properties": {
    "iso:country":"CH",
    "sg:address":"Schwertgasse 13",
    "sg:city":"Zurzach",
    "sg:classifiers":[
        {
            "category":"Travel",
            "subcategory":"Hotels & Motels",
            "type":"Entertainment"
        }
    ],
    "sg:phone":"+41 56 249 11 80",
    "sg:postcode":"5330",
    "sg:province":"Aargau",
    "sg:tags":[
        "hotels",
        "mit",
        "restaurant"
    ],
    "wof:name":"Restaurant Schwert",
    "wof:placetype":"venue"
},
  "geometry": {"coordinates":[8.294880867,47.5870857239],"type":"Point"}
}