{
  "type": "Feature",
  "properties": {
    "iso:country":"CH",
    "sg:address":"Mauerrain 1 3012 Bern. Postfach",
    "sg:city":"Bern",
    "sg:orig_category":"Detailhandel mit elektrischen Haushalts-,Radio U Fernsehger\u00e4ten sowie Musikinstrumenten",
    "sg:phone":"+41 17849728",
    "sg:postcode":"3005",
    "sg:province":"Bern",
    "wof:name":"Heinz Ammann Blockfl\u00f6tenbauer",
    "wof:placetype":"venue"
},
  "geometry": {"coordinates":[8.7341480255,47.1973953247],"type":"Point"}
}