{
  "type": "Feature",
  "properties": {
    "iso:country":"CH",
    "sg:address":"Amthausgasse",
    "sg:city":"Frutigen",
    "sg:orig_category":"RESTAURANTS: TEA-ROOMS",
    "sg:phone":"+41 33 671 16 44",
    "sg:postcode":"3714",
    "sg:province":"Bern",
    "wof:name":"Alfred Zimmermann-sarbach",
    "wof:placetype":"venue"
},
  "geometry": {"coordinates":[7.6462950706,46.5885314941],"type":"Point"}
}