{
  "type": "Feature",
  "properties": {
    "iso:country":"CH",
    "sg:address":"Quadera",
    "sg:city":"Luzein",
    "sg:orig_category":"Personenbef\u00f6rderung im Linienverkehr zu Land",
    "sg:phone":"+41 81 332 18 02",
    "sg:postcode":"7242",
    "sg:province":"Graubunden",
    "wof:name":"Skiclub Pany",
    "wof:placetype":"venue"
},
  "geometry": {"coordinates":[9.7649412155,46.9191970825],"type":"Point"}
}