{
  "type": "Feature",
  "properties": {
    "iso:country":"CH",
    "sg:address":"Pflegezentrum Feldheim",
    "sg:city":"Reiden",
    "sg:orig_category":"Sonstiges Gesundheitswesen",
    "sg:phone":"+41 62 758 24 24",
    "sg:postcode":"6260",
    "sg:province":"Luzern",
    "wof:name":"Krankenmobilien",
    "wof:placetype":"venue"
},
  "geometry": {"coordinates":[7.971282959,47.2432365417],"type":"Point"}
}