{
  "type": "Feature",
  "properties": {
    "iso:country":"CH",
    "sg:address":"Konstanzermatte",
    "sg:city":"Rothenburg",
    "sg:classifiers":[
        {
            "category":"Education",
            "subcategory":"Library",
            "type":"Public Place"
        }
    ],
    "sg:phone":"+41 41 280 12 09",
    "sg:postcode":"6023",
    "sg:province":"Luzern",
    "sg:tags":[
        "u",
        "bibliotheken",
        "archive"
    ],
    "wof:name":"Bibliothek",
    "wof:placetype":"venue"
},
  "geometry": {"coordinates":[8.268987,47.09729],"type":"Point"}
}