{
  "type": "Feature",
  "properties": {
    "iso:country":"CH",
    "sg:address":"Hauptstrasse 42 4450 Sissach. Postfach",
    "sg:city":"Sissach",
    "sg:orig_category":"Informatikschulen Sonstige mit der Informatik verbundene T\u00e4tigkeiten",
    "sg:phone":"+41 61 973 26 00",
    "sg:postcode":"4450",
    "sg:province":"Basel-Landschaft",
    "wof:name":"Pro Sl Informatik Gmbh Pc-schulungen Usw",
    "wof:placetype":"venue"
},
  "geometry": {"coordinates":[7.8146700859,47.4632339478],"type":"Point"}
}