{
  "type": "Feature",
  "properties": {
    "iso:country":"CH",
    "sg:address":"Dorfstrasse 12",
    "sg:city":"Hindelbank",
    "sg:classifiers":[
        {
            "category":"Government",
            "subcategory":"Post Office",
            "type":"Public Place"
        }
    ],
    "sg:phone":"+41 34 411 11 77",
    "sg:postcode":"3324",
    "sg:province":"Bern",
    "sg:tags":[
        "caf\u00e9s",
        "tea-rooms"
    ],
    "wof:name":"Caf\u00e9 F\u00fc\u00fcrio",
    "wof:placetype":"venue"
},
  "geometry": {"coordinates":[7.540500164,47.0442886353],"type":"Point"}
}