{
  "type": "Feature",
  "properties": {
    "iso:country":"CH",
    "sg:address":"Mittler-langnau",
    "sg:city":"Schachen",
    "sg:orig_category":"Chemico-Technical Articles",
    "sg:phone":"+41 41 499 97 97",
    "sg:postcode":"6105",
    "sg:province":"Luzern",
    "wof:name":"Werthenstein Chemie Ag",
    "wof:placetype":"venue"
},
  "geometry": {"coordinates":[8.12932,47.041996],"type":"Point"}
}