{
  "type": "Feature",
  "properties": {
    "iso:country":"CH",
    "sg:address":"1673",
    "sg:city":"Promasens",
    "sg:orig_category":"Haltung von Rindern",
    "sg:postcode":"1673",
    "sg:province":"Fribourg",
    "wof:name":"Syndicat D'\u00e9levage De La Race Tachet\u00e9e Rouge De Cottens",
    "wof:placetype":"venue"
},
  "geometry": {"coordinates":[7.0379500389,46.7550582886],"type":"Point"}
}