{
  "type": "Feature",
  "properties": {
    "addr:full":"Via Mulino Rosso 10 Arbedo Ticino 6517",
    "addr:housenumber":"10",
    "addr:postcode":"6517",
    "addr:street":"Via Mulino Rosso",
    "iso:country":"CH",
    "sg:address":"Via Mulino Rosso 10",
    "sg:city":"Arbedo",
    "sg:orig_category":"Advokaturb\u00fcros",
    "sg:phone":"+41 91 829 44 29",
    "sg:postcode":"6517",
    "sg:province":"Ticino",
    "wof:name":"Carlo Brusatori Studio Legale",
    "wof:placetype":"venue"
},
  "geometry": {"coordinates":[9.041426,46.21138],"type":"Point"}
}