{
  "type": "Feature",
  "properties": {
    "iso:country":"CH",
    "sg:address":"2732",
    "sg:city":"Reconvilier",
    "sg:orig_category":"G\u00fcterbef\u00f6rderung im Strassenverkehr",
    "sg:postcode":"2732",
    "sg:province":"Bern",
    "wof:name":"Barthe G. S\u00e0rl",
    "wof:placetype":"venue"
},
  "geometry": {"coordinates":[7.2253198624,47.2346115112],"type":"Point"}
}