{
  "type": "Feature",
  "properties": {
    "iso:country":"CH",
    "sg:address":"8608",
    "sg:city":"Bubikon",
    "sg:orig_category":"Politische Parteien CVP",
    "sg:phone":"+41 55 243 24 28",
    "sg:postcode":"8608",
    "sg:province":"Z\u00fcrich",
    "wof:name":"Cvp Sektion Bubikon",
    "wof:placetype":"venue"
},
  "geometry": {"coordinates":[8.8189096451,47.2684555054],"type":"Point"}
}