{
  "type": "Feature",
  "properties": {
    "iso:country":"CH",
    "sg:address":"Rue Virginio-malnati 59",
    "sg:city":"Meyrin",
    "sg:orig_category":"Sportvereine Ski",
    "sg:postcode":"1217",
    "sg:province":"Gen\u00e8ve",
    "wof:name":"Ski-club La Cure",
    "wof:placetype":"venue"
},
  "geometry": {"coordinates":[6.0752902031,46.4615402222],"type":"Point"}
}