{
  "type": "Feature",
  "properties": {
    "iso:country":"CH",
    "sg:address":"Brandschenkestrasse 10",
    "sg:city":"Z\u00fcrich",
    "sg:orig_category":"Advokaturb\u00fcros",
    "sg:phone":"+41 12812724",
    "sg:postcode":"8002",
    "sg:province":"Z\u00fcrich",
    "wof:name":"Class, M\u00f6ssinger, W\u00fcest Advokaturb\u00fcro",
    "wof:placetype":"venue"
},
  "geometry": {"coordinates":[8.533394,47.369621],"type":"Point"}
}