{
  "type": "Feature",
  "properties": {
    "addr:full":"St. Gallerstrasse 87 Sargans St. Gallen 7320",
    "addr:housenumber":"87",
    "addr:postcode":"7320",
    "addr:street":"St. Gallerstrasse",
    "iso:country":"CH",
    "sg:address":"St. Gallerstrasse 87",
    "sg:city":"Sargans",
    "sg:orig_category":"Architektur U Ingenieurb\u00fcros",
    "sg:phone":"+41 79 420 43 75",
    "sg:postcode":"7320",
    "sg:province":"St. Gallen",
    "wof:name":"Hobi H.",
    "wof:placetype":"venue"
},
  "geometry": {"coordinates":[8.793303,47.320061],"type":"Point"}
}