{
  "type": "Feature",
  "properties": {
    "iso:country":"CH",
    "sg:address":"Dorfstrasse 1",
    "sg:city":"Wabern",
    "sg:orig_category":"Unternehmensberatung",
    "sg:phone":"+41 76 337 20 05",
    "sg:postcode":"3084",
    "sg:province":"Bern",
    "wof:name":"D. Safret Management Consulting",
    "wof:placetype":"venue"
},
  "geometry": {"coordinates":[8.6026678085,47.3233642578],"type":"Point"}
}