{
  "type": "Feature",
  "properties": {
    "iso:country":"CH",
    "sg:address":"Souli\u00e9 Rue C\u00e9sar 3",
    "sg:city":"Nyon",
    "sg:orig_category":"Unclassifiable Establishments",
    "sg:postcode":"1260",
    "sg:province":"Vaud",
    "wof:name":"Si D'oulteret Nyon Sa",
    "wof:placetype":"venue"
},
  "geometry": {"coordinates":[6.2434692383,46.3836517334],"type":"Point"}
}