{
  "type": "Feature",
  "properties": {
    "iso:country":"CH",
    "sg:address":"Starenweg 3 4144 Arlesheim. Postfach 462",
    "sg:city":"Arlesheim",
    "sg:orig_category":"Grosshandel mit sonstigen Maschinen U Ausr\u00fcstungen f\u00fcr Industrie, Handel U Schiffahrt",
    "sg:phone":"+41 61 701 26 00",
    "sg:postcode":"4144",
    "sg:province":"Basel-Landschaft",
    "wof:name":"J. Kuster Ag Maschinenhandel",
    "wof:placetype":"venue"
},
  "geometry": {"coordinates":[7.6262478828,47.486869812],"type":"Point"}
}