{
  "type": "Feature",
  "properties": {
    "iso:country":"CH",
    "sg:address":"R\u00fchrbergweg 7",
    "sg:city":"Pratteln",
    "sg:orig_category":"Architektur U Ingenieurb\u00fcros",
    "sg:postcode":"4133",
    "sg:province":"Basel-Landschaft",
    "wof:name":"Horewo Gmbh",
    "wof:placetype":"venue"
},
  "geometry": {"coordinates":[8.59735,47.326317],"type":"Point"}
}