{
  "type": "Feature",
  "properties": {
    "iso:country":"CH",
    "sg:address":"Pelikanweg 6",
    "sg:city":"Basel",
    "sg:orig_category":"Detailhandel mit Damenbekleidung",
    "sg:phone":"+41 61 281 34 19",
    "sg:postcode":"4054",
    "sg:province":"Basel-Stadt",
    "wof:name":"Hilda Gsell Couture Hildegard",
    "wof:placetype":"venue"
},
  "geometry": {"coordinates":[7.58131,47.549988],"type":"Point"}
}