{
  "type": "Feature",
  "properties": {
    "iso:country":"CH",
    "sg:address":"Neuf Chemin 4 1955 Chamoson. Postfach",
    "sg:city":"Chamoson",
    "sg:orig_category":"Sonstige mit der Informatik verbundene T\u00e4tigkeiten",
    "sg:postcode":"1955",
    "sg:province":"Valais",
    "wof:name":"Jld Promotion S\u00e0rl Produits Et Services Informatique. Op\u00e9rations Financi\u00e8res Etc",
    "wof:placetype":"venue"
},
  "geometry": {"coordinates":[7.2253789902,46.2008628845],"type":"Point"}
}