{
  "type": "Feature",
  "properties": {
    "iso:country":"CH",
    "sg:address":"Aubrigstrasse 21",
    "sg:city":"Thalwil",
    "sg:orig_category":"Softwareentwicklung U beratung",
    "sg:phone":"+41 22 839 47 69",
    "sg:postcode":"8800",
    "sg:province":"Z\u00fcrich",
    "wof:name":"Assigestion Sa Assistance Et Gestion Informatique",
    "wof:placetype":"venue"
},
  "geometry": {"coordinates":[6.15290308,46.1993293762],"type":"Point"}
}