{
  "type": "Feature",
  "properties": {
    "iso:country":"CH",
    "sg:address":"Place Du Nord 7",
    "sg:city":"Lausanne",
    "sg:classifiers":[
        {
            "category":"Banks & Credit Unions",
            "subcategory":"Investment Brokerage",
            "type":"Services"
        }
    ],
    "sg:phone":"+41 21 312 40 92",
    "sg:postcode":"1005",
    "sg:province":"Vaud",
    "wof:name":"Orgaprim Porret S.a.",
    "wof:placetype":"venue"
},
  "geometry": {"coordinates":[6.6364059448,46.5257148743],"type":"Point"}
}