{
  "type": "Feature",
  "properties": {
    "iso:country":"CH",
    "sg:address":"Breitistrasse 2",
    "sg:city":"Winkel",
    "sg:orig_category":"Sanit\u00e4r, Heizungs U L\u00fcftungsinstallation Sanit\u00e4rinstallation",
    "sg:phone":"+41 18601476",
    "sg:postcode":"8185",
    "sg:province":"Z\u00fcrich",
    "wof:name":"Maag Hans Ag",
    "wof:placetype":"venue"
},
  "geometry": {"coordinates":[8.5461215973,47.4963760376],"type":"Point"}
}