{
  "type": "Feature",
  "properties": {
    "iso:country":"CH",
    "sg:address":"Salvatorenstrasse 90",
    "sg:city":"Chur",
    "sg:orig_category":"Sonstige Personenbef\u00f6rderung im Landverkehr",
    "sg:phone":"+41 81 252 29 67",
    "sg:postcode":"7000",
    "sg:province":"Graubunden",
    "wof:name":"Zumstein Car-reisen Ag",
    "wof:placetype":"venue"
},
  "geometry": {"coordinates":[9.5148887634,46.8501739502],"type":"Point"}
}