{
  "type": "Feature",
  "properties": {
    "iso:country":"CH",
    "sg:address":"L\u00f6wenstrasse 19",
    "sg:city":"Z\u00fcrich",
    "sg:orig_category":"Unclassifiable Establishments",
    "sg:phone":"+41 12257020",
    "sg:postcode":"8001",
    "sg:province":"Z\u00fcrich",
    "wof:name":"Sihi-international Ag",
    "wof:placetype":"venue"
},
  "geometry": {"coordinates":[8.5352783203,47.3741416931],"type":"Point"}
}