{
  "type": "Feature",
  "properties": {
    "iso:country":"CH",
    "sg:address":"Wichel 1",
    "sg:city":"Sachseln",
    "sg:orig_category":"Bauschreinerei",
    "sg:phone":"+41 41 660 30 44",
    "sg:postcode":"6072",
    "sg:province":"Obwalden",
    "wof:name":"Karl Rohrer Schreinerei/zimmerei",
    "wof:placetype":"venue"
},
  "geometry": {"coordinates":[8.218587,46.85791],"type":"Point"}
}