{
  "type": "Feature",
  "properties": {
    "iso:country":"CH",
    "sg:address":"Viale Stazione 31",
    "sg:city":"Bellinzona",
    "sg:classifiers":[
        {
            "category":"Restaurant",
            "type":"Food & Drink"
        }
    ],
    "sg:phone":"+41 91 825 29 21",
    "sg:postcode":"6500",
    "sg:province":"Ticino",
    "wof:name":"Ristorante Casa Del Popolo",
    "wof:placetype":"venue"
},
  "geometry": {"coordinates":[9.0277776718,46.194858551],"type":"Point"}
}