{
  "type": "Feature",
  "properties": {
    "addr:full":"In Der Weid 15 Binz Z\u00fcrich 8122",
    "addr:housenumber":"15",
    "addr:postcode":"8122",
    "addr:street":"In Der Weid",
    "iso:country":"CH",
    "sg:address":"In Der Weid 15",
    "sg:city":"Binz",
    "sg:orig_category":"Bauschreinerei Erbringung von sonstigen Dienstleistungen f\u00fcr Unternehmen",
    "sg:phone":"+41 19803450",
    "sg:postcode":"8122",
    "sg:province":"Z\u00fcrich",
    "wof:name":"Atelier Walter Wolf Gmbh Modellbau",
    "wof:placetype":"venue"
},
  "geometry": {"coordinates":[8.623122,47.360699],"type":"Point"}
}