{
  "type": "Feature",
  "properties": {
    "iso:country":"CH",
    "sg:address":"Petersgraben 3",
    "sg:city":"Basel",
    "sg:orig_category":"Detailhandel mit Antiquit\u00e4ten Detailhandel mit M\u00f6beln",
    "sg:phone":"+41 61 261 38 78",
    "sg:postcode":"4051",
    "sg:province":"Basel-Stadt",
    "wof:name":"Trouvaille V.cattelani Inneneinrichtungen M\u00f6bel",
    "wof:placetype":"venue"
},
  "geometry": {"coordinates":[7.5856919289,47.56092453],"type":"Point"}
}