{
  "type": "Feature",
  "properties": {
    "iso:country":"CH",
    "sg:address":"Rheinweg 4 8200 Schaffhausen. Postfach 612",
    "sg:city":"Schaffhausen",
    "sg:orig_category":"Detailhandel mit Uhren U Schmuck",
    "sg:phone":"+41 52 624 27 74",
    "sg:postcode":"8201",
    "sg:province":"Schaffhausen",
    "wof:name":"Hochstrasser & Co Edelsteinschleiferei",
    "wof:placetype":"venue"
},
  "geometry": {"coordinates":[8.6347980499,47.6939506531],"type":"Point"}
}