{
  "type": "Feature",
  "properties": {
    "iso:country":"CH",
    "sg:address":"Place Du Midi 24",
    "sg:city":"Sion",
    "sg:orig_category":"Grosshandel mit Schmuck Grosshandel mit Textilien",
    "sg:phone":"+41 27 322 32 80",
    "sg:postcode":"1950",
    "sg:province":"Valais",
    "wof:name":"Entire-handels Ag",
    "wof:placetype":"venue"
},
  "geometry": {"coordinates":[7.3609991074,46.2313194275],"type":"Point"}
}