{
  "type": "Feature",
  "properties": {
    "iso:country":"CH",
    "sg:address":"Route Vignoble 2",
    "sg:city":"Bonvillars",
    "sg:classifiers":[
        {
            "category":"Restaurant",
            "type":"Food & Drink"
        }
    ],
    "sg:phone":"+41 24 436 13 44",
    "sg:postcode":"1427",
    "sg:province":"Vaud",
    "wof:name":"Restaurant Du Midi",
    "wof:placetype":"venue"
},
  "geometry": {"coordinates":[6.6679730415,46.8394927979],"type":"Point"}
}