{
  "type": "Feature",
  "properties": {
    "iso:country":"CH",
    "sg:address":"Aegeristrasse 66",
    "sg:city":"Zug",
    "sg:orig_category":"Markt U Meinungsforschung",
    "sg:phone":"+41 32 730 60 55",
    "sg:postcode":"6300",
    "sg:province":"Zug",
    "wof:name":"Newmark International Sa Coordonner P. Le Compte De La Maison-m\u00e8re La Diff. Sur Les March\u00e9s Internat. De Tous Produits Horlogers Et M\u00e9caniques",
    "wof:placetype":"venue"
},
  "geometry": {"coordinates":[6.817855835,47.4077529907],"type":"Point"}
}