{
  "type": "Feature",
  "properties": {
    "iso:country":"CH",
    "sg:address":"Bahnstrasse 58/60",
    "sg:city":"Regensdorf",
    "sg:orig_category":"Hardwareberatung",
    "sg:postcode":"8105",
    "sg:province":"Z\u00fcrich",
    "wof:name":"Bechtle Data Ag",
    "wof:placetype":"venue"
},
  "geometry": {"coordinates":[8.4610319138,47.442779541],"type":"Point"}
}