{
  "type": "Feature",
  "properties": {
    "iso:country":"CH",
    "sg:address":"Rue Du Canal 12",
    "sg:city":"Courroux",
    "sg:orig_category":"Elektroinstallation Installation von Heizungs, L\u00fcftungs U Klimaanlagen",
    "sg:phone":"+41 32 422 00 51",
    "sg:postcode":"2822",
    "sg:province":"Jura",
    "wof:name":"Berosa-jura Sys. D'aspirations Centralis\u00e9s",
    "wof:placetype":"venue"
},
  "geometry": {"coordinates":[7.3738431931,47.358997345],"type":"Point"}
}