{
  "type": "Feature",
  "properties": {
    "iso:country":"CH",
    "sg:address":"Hauptstrasse 28",
    "sg:city":"M\u00e4genwil",
    "sg:classifiers":[
        {
            "category":"Restaurant",
            "type":"Food & Drink"
        }
    ],
    "sg:phone":"+41 61 711 43 30",
    "sg:postcode":"5506",
    "sg:province":"Aargau",
    "wof:name":"Restaurant Brauerei",
    "wof:placetype":"venue"
},
  "geometry": {"coordinates":[7.591917038,47.4934082031],"type":"Point"}
}