{
  "type": "Feature",
  "properties": {
    "iso:country":"CH",
    "sg:address":"Sch\u00fcrz 2",
    "sg:city":"Schafisheim",
    "sg:orig_category":"Herstellung von k\u00e4lte U lufttechnischen Erzeugnissen f\u00fcr gewerbliche Zwecke",
    "sg:phone":"+41 62 891 61 88",
    "sg:postcode":"5503",
    "sg:province":"Aargau",
    "wof:name":"B & E Luftkanalreinigungs Gmbh",
    "wof:placetype":"venue"
},
  "geometry": {"coordinates":[8.1423416138,47.3774604797],"type":"Point"}
}