{
  "type": "Feature",
  "properties": {
    "addr:full":"Austrasse 19 Steffisburg Bern 3612",
    "addr:housenumber":"19",
    "addr:postcode":"3612",
    "addr:street":"Austrasse;Bern",
    "iso:country":"CH",
    "sg:address":"Austrasse 19",
    "sg:city":"Steffisburg",
    "sg:orig_category":"Bauschreinerei",
    "sg:phone":"+41 33 437 80 84",
    "sg:postcode":"3612",
    "sg:province":"Bern",
    "wof:name":"Hans-ulrich H\u00e4nni Schreinerei",
    "wof:placetype":"venue"
},
  "geometry": {"coordinates":[7.632964,46.776463],"type":"Point"}
}