{
  "type": "Feature",
  "properties": {
    "iso:country":"CH",
    "sg:address":"Halten 39 Oberstocken",
    "sg:city":"Stocken",
    "sg:orig_category":"Herstellung von industriellen Prozesssteuerungsanlagen",
    "sg:phone":"+41 33 341 03 41",
    "sg:postcode":"3632",
    "sg:province":"Bern",
    "wof:name":"Schranz Elektronik",
    "wof:placetype":"venue"
},
  "geometry": {"coordinates":[7.5561900139,46.7165985107],"type":"Point"}
}