{
  "type": "Feature",
  "properties": {
    "iso:country":"CH",
    "sg:address":"Dorfstrasse 25b",
    "sg:city":"Opfikon",
    "sg:orig_category":"Einbau von Schreinerwaren Handelsvermittlung U Grosshandel",
    "sg:phone":"+41 18110102",
    "sg:postcode":"8152",
    "sg:province":"Z\u00fcrich",
    "wof:name":"Ymac Gmbh",
    "wof:placetype":"venue"
},
  "geometry": {"coordinates":[8.5754423141,47.4319877625],"type":"Point"}
}