{
  "type": "Feature",
  "properties": {
    "iso:country":"CH",
    "sg:address":"Dornacherstrasse 101",
    "sg:city":"Basel",
    "sg:orig_category":"Detailhandel mit M\u00f6beln Erbringung von Dienstleistungen f\u00fcr Unternehmen",
    "sg:phone":"+41 61 361 00 51",
    "sg:postcode":"4053",
    "sg:province":"Basel-Stadt",
    "wof:name":"Woxx Designobjekte Eric Baier",
    "wof:placetype":"venue"
},
  "geometry": {"coordinates":[7.5889911652,47.5436401367],"type":"Point"}
}