{
  "type": "Feature",
  "properties": {
    "addr:full":"1416 Pailly Vaud 1416",
    "addr:housenumber":"1416",
    "addr:postcode":"1416",
    "addr:street":"Pailly",
    "iso:country":"CH",
    "sg:address":"1416",
    "sg:city":"Pailly",
    "sg:classifiers":[
        {
            "category":"Education",
            "subcategory":"Library",
            "type":"Public Place"
        }
    ],
    "sg:postcode":"1416",
    "sg:province":"Vaud",
    "sg:tags":[
        "u",
        "bibliotheken",
        "archive"
    ],
    "wof:name":"Biblioth\u00e8que Populaire",
    "wof:placetype":"venue"
},
  "geometry": {"coordinates":[6.67459,46.699108],"type":"Point"}
}