{
  "type": "Feature",
  "properties": {
    "iso:country":"CH",
    "sg:address":"Vollandes Rue Des 26",
    "sg:city":"Gen\u00e8ve",
    "sg:orig_category":"Sonstiger Grosshandel",
    "sg:phone":"+41 71 245 30 33",
    "sg:postcode":"1207",
    "sg:province":"Gen\u00e8ve",
    "wof:name":"Patrick G. Sa",
    "wof:placetype":"venue"
},
  "geometry": {"coordinates":[6.1606712341,46.2046585083],"type":"Point"}
}