{
  "type": "Feature",
  "properties": {
    "iso:country":"CH",
    "sg:address":"Moosweg 1",
    "sg:city":"Safnern",
    "sg:orig_category":"Sportvereine Turnen Vereine Damen",
    "sg:phone":"+41 32 355 26 07",
    "sg:postcode":"2553",
    "sg:province":"Bern",
    "wof:name":"Frauenriege Stv Safnern",
    "wof:placetype":"venue"
},
  "geometry": {"coordinates":[7.3292961121,47.1542053223],"type":"Point"}
}