{
  "type": "Feature",
  "properties": {
    "iso:country":"CH",
    "sg:address":"Rue Des Alpes 51",
    "sg:city":"Crissier",
    "sg:orig_category":"P\u00e9dicure",
    "sg:phone":"+41 21 635 12 03",
    "sg:postcode":"1023",
    "sg:province":"Vaud",
    "wof:name":"Corinne Gay P\u00e9dicure",
    "wof:placetype":"venue"
},
  "geometry": {"coordinates":[6.5800662041,46.5414199829],"type":"Point"}
}