{
  "type": "Feature",
  "properties": {
    "iso:country":"CH",
    "sg:address":"Rue Des Moulins 90",
    "sg:city":"Yverdon-les-bains",
    "sg:orig_category":"Detailhandel mit elektrischen Haushalts-,Radio U Fernsehger\u00e4ten sowie Musikinstrumenten Verlag von b",
    "sg:phone":"+41 24 425 96 82",
    "sg:postcode":"1400",
    "sg:province":"Vaud",
    "wof:name":"Rey Fernand",
    "wof:placetype":"venue"
},
  "geometry": {"coordinates":[6.6313347816,46.7734451294],"type":"Point"}
}