{
  "type": "Feature",
  "properties": {
    "iso:country":"CH",
    "sg:address":"Bahnhofstrasse 14",
    "sg:city":"Chur",
    "sg:orig_category":"Wirtschafts- and Arbeitgeberverb\u00e4nde",
    "sg:phone":"+41 81 252 32 32",
    "sg:postcode":"7000",
    "sg:province":"Graubunden",
    "wof:name":"Schweiz.verband D.immobilien- Treuh\u00e4nder Svit Sektion Gr",
    "wof:placetype":"venue"
},
  "geometry": {"coordinates":[9.5310373306,46.8522262573],"type":"Point"}
}