{
  "type": "Feature",
  "properties": {
    "iso:country":"CH",
    "sg:address":"Via San Gottardo 18 6600 Muralto. Postfach",
    "sg:city":"Muralto",
    "sg:orig_category":"Unclassifiable Establishments",
    "sg:phone":"+41 91 743 31 83",
    "sg:postcode":"6600",
    "sg:province":"Ticino",
    "wof:name":"Albergo Garni Gottardo",
    "wof:placetype":"venue"
},
  "geometry": {"coordinates":[8.8058166504,46.1741142273],"type":"Point"}
}