{
  "type": "Feature",
  "properties": {
    "iso:country":"CH",
    "sg:address":"Stockhornstrasse 30",
    "sg:city":"Toffen",
    "sg:orig_category":"Herstellung von Teppichen",
    "sg:phone":"+41 31 819 20 97",
    "sg:postcode":"3125",
    "sg:province":"Bern",
    "wof:name":"Roland Hofmann",
    "wof:placetype":"venue"
},
  "geometry": {"coordinates":[7.4931030273,46.8564682007],"type":"Point"}
}