{
  "type": "Feature",
  "properties": {
    "iso:country":"CH",
    "sg:address":"Grand-rue 1470 Estavayer-le-lac. Postfach",
    "sg:city":"Estavayer-le-lac",
    "sg:orig_category":"Detailhandel mit elektrischen Haushalts-,Radio U Fernsehger\u00e4ten sowie Musikinstrumenten",
    "sg:postcode":"1470",
    "sg:province":"Fribourg",
    "wof:name":"Tv Schneuwly S\u00e0rl Commerce De Radio, T\u00e9l\u00e9vision Etc",
    "wof:placetype":"venue"
},
  "geometry": {"coordinates":[6.8453001976,46.8496932983],"type":"Point"}
}