{
  "type": "Feature",
  "properties": {
    "iso:country":"CH",
    "sg:address":"Mittelfeldweg 6",
    "sg:city":"Frenkendorf",
    "sg:orig_category":"Stukkateurgewerbe, Gipserei U Verputzerei",
    "sg:phone":"+41 79 644 23 72",
    "sg:postcode":"4402",
    "sg:province":"Basel-Landschaft",
    "wof:name":"Peter H.j. Ag",
    "wof:placetype":"venue"
},
  "geometry": {"coordinates":[7.71961689,47.5050811768],"type":"Point"}
}