{
  "type": "Feature",
  "properties": {
    "iso:country":"CH",
    "sg:address":"Hafenstrasse 20 8280 Kreuzlingen. Postfach",
    "sg:city":"Kreuzlingen",
    "sg:orig_category":"Finanzierungsinstitutionen Kunsthandel",
    "sg:phone":"+41 71 677 17 00",
    "sg:postcode":"8280",
    "sg:province":"Thurgau",
    "wof:name":"Anifa M\u00fcller & Cie Verwaltung, Handel U. Dienstleistungen Im Finanzbereich. Kunstgegenst\u00e4nde; Handel Usw",
    "wof:placetype":"venue"
},
  "geometry": {"coordinates":[9.1776790619,47.6516227722],"type":"Point"}
}