{
  "type": "Feature",
  "properties": {
    "iso:country":"CH",
    "sg:address":"Wollbacherstrasse 23 4000 Basel. Postfach",
    "sg:city":"Basel",
    "sg:orig_category":"Architektur U Ingenieurb\u00fcros",
    "sg:phone":"+41 61 603 23 45",
    "sg:postcode":"4051",
    "sg:province":"Basel-Stadt",
    "wof:name":"Crobe Engineering Gmbh",
    "wof:placetype":"venue"
},
  "geometry": {"coordinates":[7.619013,47.566982],"type":"Point"}
}