{
  "type": "Feature",
  "properties": {
    "iso:country":"CH",
    "sg:address":"Sonneckstrasse 14",
    "sg:city":"Bubendorf",
    "sg:orig_category":"Aktivit\u00e4ten der Krankenschwestern U Hebammen, Hauspflege Organisationen des Gesundheitswesen",
    "sg:phone":"+41 61 931 35 35",
    "sg:postcode":"4416",
    "sg:province":"Basel-Landschaft",
    "wof:name":"Haus-& Krankenpflegeverein Spitex-st\u00fctzpunkt",
    "wof:placetype":"venue"
},
  "geometry": {"coordinates":[7.740239,47.451488],"type":"Point"}
}