{
  "type": "Feature",
  "properties": {
    "iso:country":"CH",
    "sg:address":"Balestra Via 15a",
    "sg:city":"Mezzovico",
    "sg:orig_category":"Elektroinstallation",
    "sg:phone":"+41 91 946 23 14",
    "sg:postcode":"6805",
    "sg:province":"Ticino",
    "wof:name":"Gabutti Elettricit\u00e0 Sa",
    "wof:placetype":"venue"
},
  "geometry": {"coordinates":[8.9207315445,46.0964546204],"type":"Point"}
}