{
  "type": "Feature",
  "properties": {
    "iso:country":"CH",
    "sg:address":"Geispelgasse 4",
    "sg:city":"Muttenz",
    "sg:orig_category":"Werbegrafikateliers",
    "sg:phone":"+41 61 461 49 20",
    "sg:postcode":"4132",
    "sg:province":"Basel-Landschaft",
    "wof:name":"Eugen & Nelly Spitteler Grafik & Beratung Asg",
    "wof:placetype":"venue"
},
  "geometry": {"coordinates":[7.6447319984,47.5220146179],"type":"Point"}
}