{
  "type": "Feature",
  "properties": {
    "iso:country":"CH",
    "sg:address":"Kreuzgasse 4",
    "sg:city":"Untervaz",
    "sg:orig_category":"Herstellung von Pumpen U Kompressoren",
    "sg:postcode":"7204",
    "sg:province":"Graubunden",
    "wof:name":"Pme Reto Hug",
    "wof:placetype":"venue"
},
  "geometry": {"coordinates":[9.5339870453,46.92760849],"type":"Point"}
}