{
  "type": "Feature",
  "properties": {
    "iso:country":"CH",
    "sg:address":"Pletschen",
    "sg:city":"Susten",
    "sg:orig_category":"Campingpl\u00e4tze Detailhandel mit Zeitungen U Zeitschriften Kioske",
    "sg:phone":"+41 71 744 44 64",
    "sg:postcode":"3952",
    "sg:province":"Valais",
    "wof:name":"Campingplatz Bruggerhorn Kiosk",
    "wof:placetype":"venue"
},
  "geometry": {"coordinates":[9.63487,47.451469],"type":"Point"}
}