{
  "type": "Feature",
  "properties": {
    "iso:country":"CH",
    "sg:address":"Huggerwald 480",
    "sg:city":"Kleinl\u00fctzel",
    "sg:orig_category":"Herstellung von Metallkonstruktionen Mechanik",
    "sg:phone":"+41 79 682 70 07",
    "sg:postcode":"4245",
    "sg:province":"Solothurn",
    "wof:name":"Altermatt Robert",
    "wof:placetype":"venue"
},
  "geometry": {"coordinates":[7.4169588089,47.4207725525],"type":"Point"}
}