{
  "type": "Feature",
  "properties": {
    "addr:full":"Zentralstrasse 5a Uster Z\u00fcrich 8610",
    "addr:housenumber":"5a",
    "addr:postcode":"8610",
    "addr:street":"Zentralstrasse",
    "iso:country":"CH",
    "sg:address":"Zentralstrasse 5a",
    "sg:city":"Uster",
    "sg:orig_category":"Detailhandel mit Bekleidung Fachdetailhandel in Verkaufsr\u00e4umen",
    "sg:phone":"+41 19420616",
    "sg:postcode":"8610",
    "sg:province":"Z\u00fcrich",
    "wof:name":"Sport Shop Time Out Uster Ag",
    "wof:placetype":"venue"
},
  "geometry": {"coordinates":[8.718341,47.347691],"type":"Point"}
}