{
  "type": "Feature",
  "properties": {
    "iso:country":"CH",
    "sg:address":"L\u00fctzelmattweg 10 6006 Luzern. Postfach",
    "sg:city":"Luzern",
    "sg:orig_category":"Detailhandel mit Waren verschiedener Art, Hauptrichtung Nahrungsmittel",
    "sg:postcode":"6003",
    "sg:province":"Luzern",
    "wof:name":"Verein Zur F\u00f6rderung Der Viehwirtschaft Im Sahel Und In Der Savanne Im Sahel U. Der Savanne; F\u00f6rderung Der Eigeninitiative V. Viehz\u00fcchtern Usw",
    "wof:placetype":"venue"
},
  "geometry": {"coordinates":[8.3319759369,47.059261322],"type":"Point"}
}