{
  "type": "Feature",
  "properties": {
    "iso:country":"CH",
    "sg:address":"Levron",
    "sg:city":"Levron",
    "sg:orig_category":"Grosshandel mit sonstigen Halbwaren",
    "sg:postcode":"1942",
    "sg:province":"Valais",
    "wof:name":"Corema Pack, Maltese Fausto",
    "wof:placetype":"venue"
},
  "geometry": {"coordinates":[7.160490036,46.0950317383],"type":"Point"}
}