{
  "type": "Feature",
  "properties": {
    "iso:country":"CH",
    "sg:address":"Bahnhofstrasse 2a 3900 Brig. Postfach",
    "sg:city":"Brig",
    "sg:orig_category":"Warenh\u00e4user",
    "sg:phone":"+41 27 923 22 22",
    "sg:postcode":"3900",
    "sg:province":"Valais",
    "wof:name":"Loeb Ag Bern",
    "wof:placetype":"venue"
},
  "geometry": {"coordinates":[7.9880189896,46.3186187744],"type":"Point"}
}