{
  "type": "Feature",
  "properties": {
    "iso:country":"CH",
    "sg:address":"Chemin D'eysins 49b",
    "sg:city":"Nyon",
    "sg:orig_category":"Grosshandel mit festen Brennstoffen U Mineral\u00f6lerzeugnissen Mineral\u00f6lverarbeitung",
    "sg:phone":"+41 22 827 16 16",
    "sg:postcode":"1260",
    "sg:province":"Vaud",
    "wof:name":"Oceania Trading & Bunkering Otb Sa",
    "wof:placetype":"venue"
},
  "geometry": {"coordinates":[6.1356110573,46.187084198],"type":"Point"}
}