{
  "type": "Feature",
  "properties": {
    "iso:country":"CH",
    "sg:address":"Frohaldenstrasse 60",
    "sg:city":"B\u00fclach",
    "sg:orig_category":"Maler U Glasergewerbe Malerei",
    "sg:phone":"+41 79 423 10 52",
    "sg:postcode":"8180",
    "sg:province":"Z\u00fcrich",
    "wof:name":"Maler-atelier-b\u00fclach Beat Spengler",
    "wof:placetype":"venue"
},
  "geometry": {"coordinates":[8.5512332916,47.5245552063],"type":"Point"}
}