{
  "type": "Feature",
  "properties": {
    "iso:country":"CH",
    "sg:address":"1934 Bagnes. Postfach",
    "sg:city":"M\u00e9di\u00e8res",
    "sg:orig_category":"RESTAURANTS: TEA-ROOMS",
    "sg:postcode":"1936",
    "sg:province":"Valais",
    "wof:name":"Michelod-spleiss, Jeanne",
    "wof:placetype":"venue"
},
  "geometry": {"coordinates":[6.9953799248,46.2966117859],"type":"Point"}
}