{
  "type": "Feature",
  "properties": {
    "iso:country":"CH",
    "sg:address":"Pfarrgasse 9",
    "sg:city":"Schwyz",
    "sg:orig_category":"Unclassifiable Establishments",
    "sg:postcode":"6430",
    "sg:province":"Schwyz",
    "wof:name":"Iso-holding Ag",
    "wof:placetype":"venue"
},
  "geometry": {"coordinates":[8.6526908875,47.0212974548],"type":"Point"}
}