{
  "type": "Feature",
  "properties": {
    "iso:country":"CH",
    "sg:address":"Z\u00e4hlerweg 4",
    "sg:city":"Zug",
    "sg:orig_category":"Unclassifiable Establishments",
    "sg:postcode":"6300",
    "sg:province":"Zug",
    "wof:name":"British American Tobacco International Holdings (switzerland) Ltd",
    "wof:placetype":"venue"
},
  "geometry": {"coordinates":[8.5134401321,47.1762542725],"type":"Point"}
}