{
  "type": "Feature",
  "properties": {
    "iso:country":"CH",
    "sg:address":"Rue Pierre-p\u00e9quignat 1",
    "sg:city":"Del\u00e9mont",
    "sg:orig_category":"Darlehenskassen U Raiffeisenbanken",
    "sg:phone":"+41 32 423 03 17",
    "sg:postcode":"2800",
    "sg:province":"Jura",
    "wof:name":"Banque Raiffeisen R\u00e9gion Del\u00e9mont",
    "wof:placetype":"venue"
},
  "geometry": {"coordinates":[7.344743,47.365013],"type":"Point"}
}