{
  "type": "Feature",
  "properties": {
    "addr:full":"Im Buechwald 35 Oberuzwil St. Gallen 9242",
    "addr:housenumber":"35",
    "addr:postcode":"9242",
    "addr:street":"Im Buechwald",
    "iso:country":"CH",
    "sg:address":"Im Buechwald 35",
    "sg:city":"Oberuzwil",
    "sg:orig_category":"Bauschreinerei Herstellung von Konstruktionsteilen, Fertigbauteilen U Ausbauelementen aus Holz",
    "sg:phone":"+41 71 633 31 30",
    "sg:postcode":"9242",
    "sg:province":"St. Gallen",
    "wof:name":"Bilger Ag",
    "wof:placetype":"venue"
},
  "geometry": {"coordinates":[9.122963,47.427464],"type":"Point"}
}