{
  "type": "Feature",
  "properties": {
    "iso:country":"CH",
    "sg:address":"1288",
    "sg:city":"Aire-la-ville",
    "sg:orig_category":"Vereine Gesang",
    "sg:phone":"+41 22 757 12 14",
    "sg:postcode":"1288",
    "sg:province":"Gen\u00e8ve",
    "wof:name":"Chorale Catholique",
    "wof:placetype":"venue"
},
  "geometry": {"coordinates":[6.0444102287,46.1905593872],"type":"Point"}
}