{
  "type": "Feature",
  "properties": {
    "iso:country":"CH",
    "sg:address":"Dorfstrasse 1",
    "sg:city":"Schaffhausen",
    "sg:orig_category":"Detailhandel mit Brot, Back U S\u00fcsswaren",
    "sg:phone":"+41 52 625 16 50",
    "sg:postcode":"8203",
    "sg:province":"Schaffhausen",
    "wof:name":"Willy B\u00e4r B\u00e4ckerei-konditorei",
    "wof:placetype":"venue"
},
  "geometry": {"coordinates":[8.655226,47.697502],"type":"Point"}
}