{
  "type": "Feature",
  "properties": {
    "iso:country":"CH",
    "sg:address":"Hobelwerkweg 7",
    "sg:city":"Winterthur",
    "sg:classifiers":[
        {
            "category":"Wholesale",
            "subcategory":"Chemicals & Plastics",
            "type":"Manufacturing & Wholesale Goods"
        }
    ],
    "sg:phone":"+41 52 242 44 27",
    "sg:postcode":"8404",
    "sg:province":"Z\u00fcrich",
    "sg:tags":[
        "pharmaceutical",
        "-",
        "wood",
        "by-product",
        "chemistry",
        "furniture"
    ],
    "wof:name":"K\u00c4lin & Co Ag",
    "wof:placetype":"venue"
},
  "geometry": {"coordinates":[8.761763,47.507645],"type":"Point"}
}