{
  "type": "Feature",
  "properties": {
    "iso:country":"CH",
    "sg:address":"Kreuzb\u00fchlstrasse 5a",
    "sg:city":"D\u00fcbendorf",
    "sg:orig_category":"Werbeagenturen",
    "sg:phone":"+41 17401644",
    "sg:postcode":"8600",
    "sg:province":"Z\u00fcrich",
    "wof:name":"Eduard Cincera Werbeagentur",
    "wof:placetype":"venue"
},
  "geometry": {"coordinates":[8.455909729,47.3601608276],"type":"Point"}
}