{
  "type": "Feature",
  "properties": {
    "iso:country":"CH",
    "sg:address":"1453",
    "sg:city":"Bullet",
    "sg:orig_category":"Verwertung von Milch",
    "sg:postcode":"1453",
    "sg:province":"Vaud",
    "wof:name":"Laiterie Du Chalet-neuf De Bullet",
    "wof:placetype":"venue"
},
  "geometry": {"coordinates":[6.5547862053,46.8312492371],"type":"Point"}
}