{
  "type": "Feature",
  "properties": {
    "iso:country":"CH",
    "sg:address":"Guglern 1",
    "sg:city":"Buttisholz",
    "sg:orig_category":"Malerei",
    "sg:phone":"+41 55 410 18 14",
    "sg:postcode":"6018",
    "sg:province":"Luzern",
    "wof:name":"Albert Z\u00fcnd Malergesch\u00e4ft",
    "wof:placetype":"venue"
},
  "geometry": {"coordinates":[8.7829809189,47.1976356506],"type":"Point"}
}