{
  "type": "Feature",
  "properties": {
    "addr:full":"Pilatusstrasse 30 Luzern Luzern 6003",
    "addr:housenumber":"30",
    "addr:postcode":"6003",
    "addr:street":"Pilatusstrasse",
    "iso:country":"CH",
    "sg:address":"Pilatusstrasse 30",
    "sg:city":"Luzern",
    "sg:orig_category":"Arztpraxen",
    "sg:phone":"+41 17004993",
    "sg:postcode":"6003",
    "sg:province":"Luzern",
    "wof:name":"Dr.med.heidi Osterwalder Spezial\u00e4rztin",
    "wof:placetype":"venue"
},
  "geometry": {"coordinates":[8.452336,47.277546],"type":"Point"}
}