{
  "type": "Feature",
  "properties": {
    "iso:country":"CH",
    "sg:address":"Springiszaun 81a",
    "sg:city":"Blumenstein",
    "sg:orig_category":"Fahrschulen, Flugschulen",
    "sg:phone":"+41 33 356 29 22",
    "sg:postcode":"3638",
    "sg:province":"Bern",
    "wof:name":"Stefan Wittwer Autofahrschule",
    "wof:placetype":"venue"
},
  "geometry": {"coordinates":[7.5190310478,46.7379760742],"type":"Point"}
}