{
  "type": "Feature",
  "properties": {
    "iso:country":"CH",
    "sg:address":"Feld 11",
    "sg:city":"Stansstad",
    "sg:orig_category":"Unclassifiable Establishments",
    "sg:phone":"+41 61 713 85 32",
    "sg:postcode":"6362",
    "sg:province":"Nidwalden",
    "wof:name":"Webmotions, Internet & Webdesign, Eichenberger R. Internetauftritte (websites) F\u00fcr Kmu's; Planen, Konzipieren, Realisieren. Edv, Internet, Webdesign; Schulung",
    "wof:placetype":"venue"
},
  "geometry": {"coordinates":[7.5918130875,47.4886245728],"type":"Point"}
}