{
  "type": "Feature",
  "properties": {
    "iso:country":"CH",
    "sg:address":"Ergetenstrasse 32 9445 Rebstein. Postfach",
    "sg:city":"Rebstein",
    "sg:orig_category":"Herstellung von Seifen, Wasch U Reinigungsmitteln",
    "sg:phone":"+41 52 742 02 42",
    "sg:postcode":"9445",
    "sg:province":"St. Gallen",
    "wof:name":"Permatin Ag",
    "wof:placetype":"venue"
},
  "geometry": {"coordinates":[8.8537988663,47.6531677246],"type":"Point"}
}