{
  "type": "Feature",
  "properties": {
    "iso:country":"CH",
    "sg:address":"Eugen Huber-strasse 35",
    "sg:city":"Z\u00fcrich",
    "sg:orig_category":"Erschliessung von Grundst\u00fccken",
    "sg:postcode":"8048",
    "sg:province":"Z\u00fcrich",
    "wof:name":"Baugenossenschaft Alterswohnungen Affoltern A.a.",
    "wof:placetype":"venue"
},
  "geometry": {"coordinates":[8.4497928619,47.2702445984],"type":"Point"}
}