{
  "type": "Feature",
  "properties": {
    "iso:country":"CH",
    "sg:address":"Ruisseau-martin Ch. Du 12 1066 Epalinges. Postfach",
    "sg:city":"Epalinges",
    "sg:orig_category":"M\u00f6belschreinereien",
    "sg:postcode":"1066",
    "sg:province":"Vaud",
    "wof:name":"Gautschi Schick S\u00e0rl Eb\u00e9nisterie, Menuiserie; Fabrication, Pose Etc",
    "wof:placetype":"venue"
},
  "geometry": {"coordinates":[6.6665802002,46.5548248291],"type":"Point"}
}