{
  "type": "Feature",
  "properties": {
    "iso:country":"CH",
    "sg:address":"Rheinklingen",
    "sg:city":"Kaltenbach",
    "sg:orig_category":"Primarschulen",
    "sg:phone":"+41 31 755 88 89",
    "sg:postcode":"8259",
    "sg:province":"Thurgau",
    "wof:name":"Primarschule",
    "wof:placetype":"venue"
},
  "geometry": {"coordinates":[7.1838450432,46.9537696838],"type":"Point"}
}