{
  "type": "Feature",
  "properties": {
    "iso:country":"CH",
    "sg:address":"7610",
    "sg:city":"Soglio",
    "sg:classifiers":[
        {
            "category":"Travel",
            "subcategory":"Hotels & Motels",
            "type":"Entertainment"
        }
    ],
    "sg:postcode":"7610",
    "sg:province":"Graubunden",
    "sg:tags":[
        "hotels",
        "mit",
        "restaurant"
    ],
    "wof:name":"Albergo Panorama Klomann Axel E Johanna",
    "wof:placetype":"venue"
},
  "geometry": {"coordinates":[8.7835540771,46.1219673157],"type":"Point"}
}