{
  "type": "Feature",
  "properties": {
    "addr:full":"Hodlerstrasse 16 Bern Bern 3011",
    "addr:housenumber":"16",
    "addr:postcode":"3011",
    "addr:street":"Hodlerstrasse",
    "iso:country":"CH",
    "sg:address":"Hodlerstrasse 16",
    "sg:city":"Bern",
    "sg:orig_category":"Detailhandel mit B\u00fcchern",
    "sg:phone":"+41 31 311 68 21",
    "sg:postcode":"3011",
    "sg:province":"Bern",
    "wof:name":"Culinarium Kochbuchhandlung",
    "wof:placetype":"venue"
},
  "geometry": {"coordinates":[7.442654,46.951279],"type":"Point"}
}