{
  "type": "Feature",
  "properties": {
    "iso:country":"CH",
    "sg:address":"Gassmatt",
    "sg:city":"Buttisholz",
    "sg:orig_category":"Fernmeldedienste",
    "sg:postcode":"6018",
    "sg:province":"Luzern",
    "wof:name":"Genossenschaft Gemeinschafts-antennenanlage Sempach-station",
    "wof:placetype":"venue"
},
  "geometry": {"coordinates":[8.1998643875,47.1159324646],"type":"Point"}
}