{
  "type": "Feature",
  "properties": {
    "iso:country":"CH",
    "sg:address":"Dorfstrasse",
    "sg:city":"Sigriswil",
    "sg:orig_category":"Detailhandel mit Milcherzeugnissen U Eiern Verarbeitung von Milch",
    "sg:phone":"+41 33 251 37 30",
    "sg:postcode":"3655",
    "sg:province":"Bern",
    "wof:name":"K\u00e4serei Sigriswil",
    "wof:placetype":"venue"
},
  "geometry": {"coordinates":[7.7135767937,46.7171478271],"type":"Point"}
}