{
  "type": "Feature",
  "properties": {
    "iso:country":"CH",
    "sg:address":"Dorfstrasse 72 3555 Trubschachen. Postfach",
    "sg:city":"Trubschachen",
    "sg:orig_category":"Maler U Glasergewerbe Malerei",
    "sg:phone":"+41 56 426 21 78",
    "sg:postcode":"3555",
    "sg:province":"Bern",
    "wof:name":"B\u00fchler Ag, Malergesch\u00e4ft",
    "wof:placetype":"venue"
},
  "geometry": {"coordinates":[8.3214740753,47.4676246643],"type":"Point"}
}