{
  "type": "Feature",
  "properties": {
    "iso:country":"CH",
    "sg:address":"Chemin Des Plantaz 56",
    "sg:city":"Nyon",
    "sg:orig_category":"RESTAURANTS: TEA-ROOMS",
    "sg:postcode":"1260",
    "sg:province":"Vaud",
    "wof:name":"Restaurant Les Pilons - Iacobazzi Caf\u00e9-restaurant",
    "wof:placetype":"venue"
},
  "geometry": {"coordinates":[6.7419509888,47.0549354553],"type":"Point"}
}