{
  "type": "Feature",
  "properties": {
    "iso:country":"CH",
    "sg:address":"5046",
    "sg:city":"Schmiedrued",
    "sg:orig_category":"Landesverteidigung, Sozialversicherung \u00d6ffentliche Verwaltung",
    "sg:phone":"+41 81 404 10 66",
    "sg:postcode":"5046",
    "sg:province":"Aargau",
    "wof:name":"Zivilschutzstelle Schmitten (albula)",
    "wof:placetype":"venue"
},
  "geometry": {"coordinates":[9.6728239059,46.6879615784],"type":"Point"}
}