{
  "type": "Feature",
  "properties": {
    "iso:country":"CH",
    "sg:address":"Affolterstrasse 29",
    "sg:city":"Luterbach",
    "sg:orig_category":"Unclassifiable Establishments",
    "sg:postcode":"4542",
    "sg:province":"Solothurn",
    "wof:name":"Heinz Peter Transporte",
    "wof:placetype":"venue"
},
  "geometry": {"coordinates":[7.5935921669,47.2149505615],"type":"Point"}
}