{
  "type": "Feature",
  "properties": {
    "iso:country":"CH",
    "sg:address":"Fenil Route De",
    "sg:city":"Corsier-sur-vevey",
    "sg:orig_category":"Technische, physikalische U chemische Untersuchung",
    "sg:phone":"+41 21 923 20 00",
    "sg:postcode":"1804",
    "sg:province":"Vaud",
    "wof:name":"Laboratoires Serono Sa",
    "wof:placetype":"venue"
},
  "geometry": {"coordinates":[6.8735852242,46.4897689819],"type":"Point"}
}