{
  "type": "Feature",
  "properties": {
    "iso:country":"CH",
    "sg:address":"Rigistrasse 7",
    "sg:city":"Dierikon",
    "sg:orig_category":"G\u00fcterbef\u00f6rderung im Strassenverkehr",
    "sg:phone":"+41 71 622 44 01",
    "sg:postcode":"6036",
    "sg:province":"Luzern",
    "wof:name":"Huber & Co, Spezialtransporte Und Kanalreinigungen",
    "wof:placetype":"venue"
},
  "geometry": {"coordinates":[9.1381845474,47.5666694641],"type":"Point"}
}