{
  "type": "Feature",
  "properties": {
    "iso:country":"CH",
    "sg:address":"Hauptstrasse 71",
    "sg:city":"Balgach",
    "sg:orig_category":"Pensionskassen",
    "sg:postcode":"9436",
    "sg:province":"St. Gallen",
    "wof:name":"Bvg-stiftung Der N\u00fcesch Emil Ag, Weinkellerei, Balgach",
    "wof:placetype":"venue"
},
  "geometry": {"coordinates":[9.6004514694,47.4035568237],"type":"Point"}
}