{
  "type": "Feature",
  "properties": {
    "iso:country":"CH",
    "sg:address":"1973",
    "sg:city":"Nax",
    "sg:orig_category":"Technische B\u00fcros Hoch-& Tiefbau",
    "sg:phone":"+41 31 972 28 19",
    "sg:postcode":"1973",
    "sg:province":"Valais",
    "wof:name":"C. Schmid Silecco",
    "wof:placetype":"venue"
},
  "geometry": {"coordinates":[7.4148378372,46.9100074768],"type":"Point"}
}