{
  "type": "Feature",
  "properties": {
    "addr:full":"Weingartenstrasse 52 Naters Valais 3904",
    "addr:housenumber":"52",
    "addr:postcode":"3904",
    "addr:street":"Weingartenstrasse",
    "iso:country":"CH",
    "sg:address":"Weingartenstrasse 52",
    "sg:city":"Naters",
    "sg:orig_category":"Bauschreinerei Herstellung von Konstruktionsteilen, Fertigbauteilen U Ausbauelementen aus Holz",
    "sg:phone":"+41 27 923 89 10",
    "sg:postcode":"3904",
    "sg:province":"Valais",
    "wof:name":"Ricco Amherd Schreinerei",
    "wof:placetype":"venue"
},
  "geometry": {"coordinates":[8.005557,46.326794],"type":"Point"}
}