{
  "type": "Feature",
  "properties": {
    "iso:country":"CH",
    "sg:address":"Piazza Orico 6",
    "sg:city":"Bellinzona",
    "sg:orig_category":"Reparatur von Schuhen U Lederwaren",
    "sg:phone":"+41 32 913 11 91",
    "sg:postcode":"6500",
    "sg:province":"Ticino",
    "wof:name":"Letterio D'ignoti Cordonnerie Miami",
    "wof:placetype":"venue"
},
  "geometry": {"coordinates":[6.827958107,47.1007461548],"type":"Point"}
}