{
  "type": "Feature",
  "properties": {
    "iso:country":"CH",
    "sg:address":"Xxxi-d\u00e9cembre Rue Du 14 1207 Gen\u00e8ve. Postfach",
    "sg:city":"Gen\u00e8ve",
    "sg:orig_category":"Satzherstellung U Reproduktion",
    "sg:phone":"+41 31 372 46 72",
    "sg:postcode":"1207",
    "sg:province":"Gen\u00e8ve",
    "wof:name":"Giganto Strizzolo Reprotechnik",
    "wof:placetype":"venue"
},
  "geometry": {"coordinates":[7.4378900528,46.9404945374],"type":"Point"}
}