{
  "type": "Feature",
  "properties": {
    "iso:country":"CH",
    "sg:address":"Eschfeldstrasse 2",
    "sg:city":"Steinhausen",
    "sg:orig_category":"Markt U Meinungsforschung",
    "sg:postcode":"6312",
    "sg:province":"Zug",
    "wof:name":"Marcello Hagmayer, Marketing Und Verkaufsstrategie-beratung",
    "wof:placetype":"venue"
},
  "geometry": {"coordinates":[8.4857091904,47.197769165],"type":"Point"}
}