{
  "type": "Feature",
  "properties": {
    "iso:country":"CH",
    "sg:address":"Via Alberto Franzoni 69 6600 Locarno. Postfach Caselle Postale 205",
    "sg:city":"Locarno",
    "sg:orig_category":"Architektur U Ingenieurb\u00fcros",
    "sg:phone":"+41 91 752 22 23",
    "sg:postcode":"6604",
    "sg:province":"Ticino",
    "wof:name":"Anastasi Sa Ingegneria",
    "wof:placetype":"venue"
},
  "geometry": {"coordinates":[8.778822,46.168987],"type":"Point"}
}