{
  "type": "Feature",
  "properties": {
    "iso:country":"CH",
    "sg:address":"Rue De Saint-jean 58 1200 Genf. Postfach",
    "sg:city":"Gen\u00e8ve",
    "sg:orig_category":"RESTAURANTS: TEA-ROOMS",
    "sg:postcode":"1203",
    "sg:province":"Gen\u00e8ve",
    "wof:name":"Silvio Mezzanotte",
    "wof:placetype":"venue"
},
  "geometry": {"coordinates":[6.1324448586,46.2052726746],"type":"Point"}
}