{
  "type": "Feature",
  "properties": {
    "iso:country":"CH",
    "sg:address":"B\u00fcndnerstrasse 32",
    "sg:city":"Basel",
    "sg:orig_category":"Herstellung von elektrischen Lampen U Leuchten Vermietung von sonstigen Maschinen U Ger\u00e4ten",
    "sg:phone":"+41 71 940 00 20",
    "sg:postcode":"4055",
    "sg:province":"Basel-Stadt",
    "wof:name":"Light Factory Ag",
    "wof:placetype":"venue"
},
  "geometry": {"coordinates":[9.1234006882,47.4656410217],"type":"Point"}
}