{
  "type": "Feature",
  "properties": {
    "addr:full":"Hauptstrasse 2 Sutz Bern 2572",
    "addr:housenumber":"2",
    "addr:postcode":"2572",
    "addr:street":"Hauptstrasse",
    "iso:country":"CH",
    "sg:address":"Hauptstrasse 2",
    "sg:city":"Sutz",
    "sg:orig_category":"Bauschreinerei Innenausbau",
    "sg:phone":"+41 32 396 24 52",
    "sg:postcode":"2572",
    "sg:province":"Bern",
    "wof:name":"Daniel Hunziker Schreinerei-innenausbau",
    "wof:placetype":"venue"
},
  "geometry": {"coordinates":[7.221249,47.1036],"type":"Point"}
}