{
  "type": "Feature",
  "properties": {
    "iso:country":"CH",
    "sg:address":"Rue Du Breuil 16a",
    "sg:city":"Biel/bienne",
    "sg:orig_category":"Unclassifiable Establishments",
    "sg:postcode":"2500",
    "sg:province":"Bern",
    "wof:name":"Matthey Claude",
    "wof:placetype":"venue"
},
  "geometry": {"coordinates":[7.2532877922,47.1367530823],"type":"Point"}
}