{
  "type": "Feature",
  "properties": {
    "iso:country":"CH",
    "sg:address":"Bahnhofstrasse 7",
    "sg:city":"Zug",
    "sg:orig_category":"Wirtschaftspr\u00fcfung, Steuerberatung U Treuhand",
    "sg:phone":"+41 41 727 22 27",
    "sg:postcode":"6300",
    "sg:province":"Zug",
    "wof:name":"Limacher Consulting",
    "wof:placetype":"venue"
},
  "geometry": {"coordinates":[8.5155220032,47.168586731],"type":"Point"}
}