{
  "type": "Feature",
  "properties": {
    "iso:country":"CH",
    "sg:address":"M\u00fchlewiesenstrasse 30",
    "sg:city":"Aadorf",
    "sg:orig_category":"Fotografische Ateliers",
    "sg:phone":"+41 52 365 18 11",
    "sg:postcode":"8355",
    "sg:province":"Thurgau",
    "wof:name":"Thomas Bachmann Fotoreportagen",
    "wof:placetype":"venue"
},
  "geometry": {"coordinates":[8.9064102173,47.4980545044],"type":"Point"}
}