{
  "type": "Feature",
  "properties": {
    "iso:country":"CH",
    "sg:address":"Mohrenplatz 1 6130 Willisau. Postfach",
    "sg:city":"Willisau",
    "sg:classifiers":[
        {
            "category":"Travel",
            "subcategory":"Hotels & Motels",
            "type":"Entertainment"
        }
    ],
    "sg:phone":"+41 41 970 11 10",
    "sg:postcode":"6130",
    "sg:province":"Luzern",
    "sg:tags":[
        "hotels",
        "mit",
        "restaurant"
    ],
    "wof:name":"Hotel Mohren Ag, Willisau",
    "wof:placetype":"venue"
},
  "geometry": {"coordinates":[7.9931149483,47.1204528809],"type":"Point"}
}