{
  "type": "Feature",
  "properties": {
    "iso:country":"CH",
    "sg:address":"Vogelsangstrasse 14",
    "sg:city":"Effretikon",
    "sg:orig_category":"Detailhandel mit Sportartikeln",
    "sg:phone":"+41 52 354 12 12",
    "sg:postcode":"8307",
    "sg:province":"Z\u00fcrich",
    "wof:name":"Smash-sport Tennisartikel",
    "wof:placetype":"venue"
},
  "geometry": {"coordinates":[8.6825590134,47.4201507568],"type":"Point"}
}