{
  "type": "Feature",
  "properties": {
    "iso:country":"CH",
    "sg:address":"Pestalozzistrasse 10",
    "sg:city":"Weinfelden",
    "sg:orig_category":"Detailhandel mit Radio U Fernsehger\u00e4ten Detailhandel mit elektrischen Haushalts-,Radio U Fernsehger\u00e4",
    "sg:phone":"+41 71 622 34 34",
    "sg:postcode":"8570",
    "sg:province":"Thurgau",
    "wof:name":"Thomas Raisig Radio-tv",
    "wof:placetype":"venue"
},
  "geometry": {"coordinates":[9.1082487106,47.5675048828],"type":"Point"}
}