{
  "type": "Feature",
  "properties": {
    "iso:country":"CH",
    "sg:address":"Grande Place 27",
    "sg:city":"Vevey",
    "sg:orig_category":"Detailhandel mit S\u00e4uglings U Kinderbekleidung Sonstiger Fachdetailhandel in Verkaufsr\u00e4umen",
    "sg:phone":"+41 21 922 64 04",
    "sg:postcode":"1800",
    "sg:province":"Vaud",
    "wof:name":"Christine Amiguet Boutique Am Starm Gram",
    "wof:placetype":"venue"
},
  "geometry": {"coordinates":[6.8422617912,46.4607505798],"type":"Point"}
}