{
  "type": "Feature",
  "properties": {
    "iso:country":"CH",
    "sg:address":"Square M\u00e9tropole 7. 1000 Lausanne Case Postale",
    "sg:city":"Lausanne",
    "sg:orig_category":"Sonstiger Grosshandel",
    "sg:postcode":"1000",
    "sg:province":"Vaud",
    "wof:name":"Venezia James. Importations Diverses En Gros; Exportation De Produits Suisses Et Repr\u00e9sentations En Cycles, Accessoires \u00e9lectrotechniques.",
    "wof:placetype":"venue"
},
  "geometry": {"coordinates":[6.6947751045,46.5545883179],"type":"Point"}
}