{
  "type": "Feature",
  "properties": {
    "iso:country":"CH",
    "sg:address":"Seefeldstrasse 90 8008 Z\u00fcrich. Postfach",
    "sg:city":"Z\u00fcrich",
    "sg:orig_category":"Grosshandel mit Textilien",
    "sg:phone":"+41 13836601",
    "sg:postcode":"8001",
    "sg:province":"Z\u00fcrich",
    "wof:name":"Hartmann J\u00fcrg Textilien; Handel. Videofilmen; Grosshandel",
    "wof:placetype":"venue"
},
  "geometry": {"coordinates":[8.5521678925,47.3601036072],"type":"Point"}
}