{
  "type": "Feature",
  "properties": {
    "iso:country":"CH",
    "sg:address":"Altweg 96",
    "sg:city":"Schwaderloch",
    "sg:orig_category":"Detailhandel mit elektrischen Haushalts-,Radio U Fernsehger\u00e4ten sowie Musikinstrumenten",
    "sg:phone":"+41 56 247 18 38",
    "sg:postcode":"5326",
    "sg:province":"Aargau",
    "wof:name":"G\u00fcller Urs Radio-tv-sat Schwaderloch",
    "wof:placetype":"venue"
},
  "geometry": {"coordinates":[8.1467227936,47.5875053406],"type":"Point"}
}