{
  "type": "Feature",
  "properties": {
    "iso:country":"CH",
    "sg:address":"Altweg 4",
    "sg:city":"Frauenfeld",
    "sg:orig_category":"Architektur U Ingenieurb\u00fcros",
    "sg:phone":"+41 52 730 15 18",
    "sg:postcode":"8500",
    "sg:province":"Thurgau",
    "wof:name":"R. Adank",
    "wof:placetype":"venue"
},
  "geometry": {"coordinates":[8.894473,47.55434],"type":"Point"}
}