{
  "type": "Feature",
  "properties": {
    "iso:country":"CH",
    "sg:address":"Hauptstrasse 20",
    "sg:city":"Kreuzlingen",
    "sg:orig_category":"Fachdetailhandel mit pharmazeutischen Produkten",
    "sg:phone":"+41 71 672 20 55",
    "sg:postcode":"8280",
    "sg:province":"Thurgau",
    "wof:name":"Apotheke Richter Kreuzlingen. Inh. V. Pavlicek.",
    "wof:placetype":"venue"
},
  "geometry": {"coordinates":[9.1735544205,47.652671814],"type":"Point"}
}