{
  "type": "Feature",
  "properties": {
    "iso:country":"CH",
    "sg:address":"Bahnhofstrasse 13",
    "sg:city":"Laufen",
    "sg:classifiers":[
        {
            "category":"Insurance",
            "subcategory":"Insurance Agent",
            "type":"Services"
        }
    ],
    "sg:phone":"+41 81 410 07 18",
    "sg:postcode":"4242",
    "sg:province":"Basel-Landschaft",
    "sg:tags":[
        "versicherungsagenturen",
        "-broker"
    ],
    "wof:name":"Rentenanstalt/swiss Life Maarten Bauriedl",
    "wof:placetype":"venue"
},
  "geometry": {"coordinates":[9.8305082321,46.7986831665],"type":"Point"}
}