{
  "type": "Feature",
  "properties": {
    "iso:country":"CH",
    "sg:address":"In Der Ballota 1",
    "sg:city":"Schaan",
    "sg:orig_category":"Geb\u00e4ude, Wohnungsreinigung",
    "sg:phone":"+423 232 32 36",
    "sg:postcode":"9494",
    "wof:name":"Refeka Eugen Kaufmann Geb\u00e4udereinigung",
    "wof:placetype":"venue"
},
  "geometry": {"coordinates":[9.5132904053,47.1639060974],"type":"Point"}
}