{
  "type": "Feature",
  "properties": {
    "iso:country":"CH",
    "sg:address":"Z\u00fcrichstrasse 38 8306 Br\u00fcttisellen. Postfach",
    "sg:city":"Br\u00fcttisellen",
    "sg:orig_category":"Nahrungsmittel-Industrie: Rohstoffe",
    "sg:postcode":"8306",
    "sg:province":"Z\u00fcrich",
    "wof:name":"Argo",
    "wof:placetype":"venue"
},
  "geometry": {"coordinates":[-79.6232376099,40.4171600342],"type":"Point"}
}