{
  "type": "Feature",
  "properties": {
    "iso:country":"CH",
    "sg:address":"Eichwaldstrasse 13 6005 Luzern. Postfach",
    "sg:city":"Luzern",
    "sg:orig_category":"Detailhandel mit elektrischen Haushalts-,Radio U Fernsehger\u00e4ten sowie Musikinstrumenten",
    "sg:postcode":"6003",
    "sg:province":"Luzern",
    "wof:name":"Tms Trading Merchandising Services, International Musical Instruments, Lucerne Musikinstrumente Usw; Handel",
    "wof:placetype":"venue"
},
  "geometry": {"coordinates":[8.3009052277,47.0382766724],"type":"Point"}
}