{
  "type": "Feature",
  "properties": {
    "iso:country":"CH",
    "sg:address":"Haldengasse 3",
    "sg:city":"Zeiningen",
    "sg:orig_category":"Nationale Postdienste",
    "sg:phone":"+41 61 851 11 10",
    "sg:postcode":"4314",
    "sg:province":"Aargau",
    "wof:name":"Die Schweizerische Post",
    "wof:placetype":"venue"
},
  "geometry": {"coordinates":[7.8716349602,47.5431213379],"type":"Point"}
}