{
  "type": "Feature",
  "properties": {
    "iso:country":"CH",
    "sg:address":"Avenue De La Vogeaz 15",
    "sg:city":"Morges",
    "sg:orig_category":"Interessenvertretungen",
    "sg:postcode":"1110",
    "sg:province":"Vaud",
    "wof:name":"Arib - Association Romande D'impregnateurs Du Bois",
    "wof:placetype":"venue"
},
  "geometry": {"coordinates":[6.4808149338,46.5111503601],"type":"Point"}
}