{
  "type": "Feature",
  "properties": {
    "iso:country":"CH",
    "sg:address":"Z.i. Ile Falcon 27 Sierre 3960 Siders. Postfach",
    "sg:city":"Sierre",
    "sg:orig_category":"Fachdetailhandel in Verkaufsr\u00e4umen",
    "sg:postcode":"3960",
    "sg:province":"Valais",
    "wof:name":"Maxi Fun Ren S\u00e0rl",
    "wof:placetype":"venue"
},
  "geometry": {"coordinates":[7.5306549072,46.2924041748],"type":"Point"}
}