{
  "type": "Feature",
  "properties": {
    "iso:country":"CH",
    "sg:address":"St\u00e4gh\u00fcsli 6017 Ruswil. Postfach",
    "sg:city":"Ruswil",
    "sg:orig_category":"Handel mit Automobilen",
    "sg:postcode":"6017",
    "sg:province":"Luzern",
    "wof:name":"L\u00e4uppi Heinz Automobile",
    "wof:placetype":"venue"
},
  "geometry": {"coordinates":[7.9599142075,47.3240432739],"type":"Point"}
}