{
  "type": "Feature",
  "properties": {
    "iso:country":"CH",
    "sg:address":"St. Jakobs-strasse 101",
    "sg:city":"Basel",
    "sg:orig_category":"Schaustellergewerbe U Vergn\u00fcgungsparks",
    "sg:postcode":"4052",
    "sg:province":"Basel-Stadt",
    "wof:name":"H.p. Maier Karussellbetriebe Ag",
    "wof:placetype":"venue"
},
  "geometry": {"coordinates":[7.6011571884,47.5467071533],"type":"Point"}
}