{
  "type": "Feature",
  "properties": {
    "iso:country":"CH",
    "sg:address":"Kasernenstrasse 28",
    "sg:city":"Aarau",
    "sg:orig_category":"Berufsbildende weiterf\u00fchrende Schulen",
    "sg:phone":"+41 62 824 76 33",
    "sg:postcode":"5000",
    "sg:province":"Aargau",
    "wof:name":"Coiffeurfachschule Livio",
    "wof:placetype":"venue"
},
  "geometry": {"coordinates":[8.049294,47.391785],"type":"Point"}
}