{
  "type": "Feature",
  "properties": {
    "iso:country":"CH",
    "sg:address":"R. Beauregard 5 Case Postale 92",
    "sg:city":"Peseux",
    "sg:classifiers":[
        {
            "category":"Wholesale",
            "subcategory":"Machinery & Supplies",
            "type":"Manufacturing & Wholesale Goods"
        }
    ],
    "sg:phone":"+41 32 967 00 00",
    "sg:postcode":"2034",
    "sg:province":"Neuch\u00e2tel",
    "sg:tags":[
        "equipment",
        "equipement",
        "precision",
        "timekeeping"
    ],
    "wof:name":"Stern Cr\u00c9ations Branch Of Richmond Sa",
    "wof:placetype":"venue"
},
  "geometry": {"coordinates":[-118.9051818848,35.2933692932],"type":"Point"}
}