{
  "type": "Feature",
  "properties": {
    "iso:country":"CH",
    "sg:address":"Im Winkel 25",
    "sg:city":"Recherswil",
    "sg:orig_category":"Bauschreinerei Herstellung von M\u00f6beln verschiedener Art",
    "sg:phone":"+41 32 675 36 36",
    "sg:postcode":"4565",
    "sg:province":"Solothurn",
    "wof:name":"Wirth Parkett Ag",
    "wof:placetype":"venue"
},
  "geometry": {"coordinates":[7.597215,47.163425],"type":"Point"}
}