{
  "type": "Feature",
  "properties": {
    "iso:country":"CH",
    "sg:address":"M\u00fcllerstrasse 48",
    "sg:city":"Z\u00fcrich",
    "sg:orig_category":"Grosshandel mit Wein U Spirituosen Grosshandel mit sonstigen Nahrungsmitteln",
    "sg:postcode":"8004",
    "sg:province":"Z\u00fcrich",
    "wof:name":"Weink\u00f6nig Ag Import & En Gros",
    "wof:placetype":"venue"
},
  "geometry": {"coordinates":[8.529712677,47.3754234314],"type":"Point"}
}