{
  "type": "Feature",
  "properties": {
    "iso:country":"CH",
    "sg:address":"Place Du March\u00e9 6",
    "sg:city":"Montreux",
    "sg:orig_category":"Detailhandel Reparatur von Gebrauchsg\u00fctern",
    "sg:phone":"+41 21 963 11 24",
    "sg:postcode":"1820",
    "sg:province":"Vaud",
    "wof:name":"Kelly Maroquinerie",
    "wof:placetype":"venue"
},
  "geometry": {"coordinates":[6.9094290733,46.4319496155],"type":"Point"}
}