{
  "type": "Feature",
  "properties": {
    "iso:country":"CH",
    "sg:address":"Hasenwiese 19",
    "sg:city":"Mollis",
    "sg:orig_category":"Detailhandel mit Teppichen Verlegen von Fussboden",
    "sg:phone":"+41 55 612 15 25",
    "sg:postcode":"8753",
    "sg:province":"Glarus",
    "wof:name":"Rolf Salandi Bodenbel\u00e4ge Teppiche",
    "wof:placetype":"venue"
},
  "geometry": {"coordinates":[9.0740909576,47.0955657959],"type":"Point"}
}