{
  "type": "Feature",
  "properties": {
    "iso:country":"CH",
    "sg:address":"Seestrasse 79",
    "sg:city":"Kilchberg",
    "sg:classifiers":[
        {
            "category":"Coffee & Tea",
            "type":"Food & Drink"
        }
    ],
    "sg:phone":"+41 17242182",
    "sg:postcode":"8802",
    "sg:province":"Z\u00fcrich",
    "sg:tags":[
        "fruit"
    ],
    "wof:name":"J\u00fcttner & Partner",
    "wof:placetype":"venue"
},
  "geometry": {"coordinates":[8.5476160049,47.3283424377],"type":"Point"}
}