{
  "type": "Feature",
  "properties": {
    "iso:country":"CH",
    "sg:address":"Chemin De La Redoute 4",
    "sg:city":"Villars-sur-gl\u00e2ne",
    "sg:classifiers":[
        {
            "category":"Professional",
            "subcategory":"Engineering",
            "type":"Services"
        }
    ],
    "sg:phone":"+41 26 402 33 03",
    "sg:postcode":"1752",
    "sg:province":"Fribourg",
    "sg:tags":[
        "automotive",
        "expert"
    ],
    "wof:name":"Autoexperts Services Sa",
    "wof:placetype":"venue"
},
  "geometry": {"coordinates":[7.135182,46.800629],"type":"Point"}
}