{
  "type": "Feature",
  "properties": {
    "iso:country":"CH",
    "sg:address":"Zimmertalstrasse 1",
    "sg:city":"Sarnen",
    "sg:orig_category":"Unclassifiable Establishments",
    "sg:postcode":"6060",
    "sg:province":"Obwalden",
    "wof:name":"Dona Und Studhalter Gmbh",
    "wof:placetype":"venue"
},
  "geometry": {"coordinates":[8.2454061508,46.9051132202],"type":"Point"}
}