{
  "type": "Feature",
  "properties": {
    "iso:country":"CH",
    "sg:address":"Schlossstrasse 3 6005 Luzern. Postfach",
    "sg:city":"Luzern",
    "sg:orig_category":"Instandhaltung U Reparatur von Automobilen",
    "sg:phone":"+41 41 250 26 51",
    "sg:postcode":"6003",
    "sg:province":"Luzern",
    "wof:name":"Mengis Gebr. Garage U. Maschinenbau.",
    "wof:placetype":"venue"
},
  "geometry": {"coordinates":[8.3020868301,47.0425643921],"type":"Point"}
}