{
  "type": "Feature",
  "properties": {
    "iso:country":"CH",
    "sg:address":"Hasenrainstrasse 59 4102 Binningen. Postfach",
    "sg:city":"Birsfelden",
    "sg:classifiers":[
        {
            "category":"Restaurant",
            "type":"Food & Drink"
        }
    ],
    "sg:phone":"+41 61 421 77 22",
    "sg:postcode":"4127",
    "sg:province":"Basel-Landschaft",
    "sg:tags":[
        "tea-rooms",
        "restaurants"
    ],
    "wof:name":"Qualigast Gmbh Gastronomiebetriebe, Delikatessenvertrieb Usw",
    "wof:placetype":"venue"
},
  "geometry": {"coordinates":[7.569560051,47.5439147949],"type":"Point"}
}