{
  "type": "Feature",
  "properties": {
    "iso:country":"CH",
    "sg:address":"Unterm\u00fcli 11 6300 Zug. Postfach",
    "sg:city":"Zug",
    "sg:orig_category":"Handels-H\u00e4user U Gesellschaften",
    "sg:phone":"+41 41 760 84 85",
    "sg:postcode":"6300",
    "sg:province":"Zug",
    "wof:name":"Project Dynamics Gmbh",
    "wof:placetype":"venue"
},
  "geometry": {"coordinates":[8.5173511505,47.1806297302],"type":"Point"}
}