{
  "type": "Feature",
  "properties": {
    "addr:full":"Jomini Avenue 8 Lausanne Vaud 1003",
    "addr:postcode":"1003",
    "addr:street":"Jomini Avenue 8",
    "iso:country":"CH",
    "sg:address":"Jomini Avenue 8",
    "sg:city":"Lausanne",
    "sg:orig_category":"Campingpl\u00e4tze",
    "sg:phone":"+41 21 646 93 33",
    "sg:postcode":"1003",
    "sg:province":"Vaud",
    "wof:name":"Camping-caravaning Club Vaudois (cccv)",
    "wof:placetype":"venue"
},
  "geometry": {"coordinates":[6.62721,46.528198],"type":"Point"}
}