{
  "type": "Feature",
  "properties": {
    "iso:country":"CH",
    "sg:address":"Waidackerstrasse 32",
    "sg:city":"Uttwil",
    "sg:orig_category":"Non-Classified Establishments",
    "sg:postcode":"8592",
    "sg:province":"Thurgau",
    "wof:name":"Opptimax Results Ag",
    "wof:placetype":"venue"
},
  "geometry": {"coordinates":[9.345410347,47.5785484314],"type":"Point"}
}