{
  "type": "Feature",
  "properties": {
    "iso:country":"CH",
    "sg:address":"Solothurnstrasse 2",
    "sg:city":"Jegenstorf",
    "sg:classifiers":[
        {
            "category":"Travel",
            "subcategory":"Hotels & Motels",
            "type":"Entertainment"
        }
    ],
    "sg:phone":"+41 31 761 02 01",
    "sg:postcode":"3303",
    "sg:province":"Bern",
    "sg:tags":[
        "hotels",
        "mit",
        "restaurant"
    ],
    "wof:name":"Gasthof Kreuz, Sommerhalder Peter",
    "wof:placetype":"venue"
},
  "geometry": {"coordinates":[7.5076870918,47.0501213074],"type":"Point"}
}