{
  "type": "Feature",
  "properties": {
    "iso:country":"CH",
    "sg:address":"Oristalstrasse 46",
    "sg:city":"Liestal",
    "sg:orig_category":"Detailhandel mit M\u00f6beln",
    "sg:phone":"+41 61 921 23 61",
    "sg:postcode":"4410",
    "sg:province":"Basel-Landschaft",
    "wof:name":"Josef Degen Stilm\u00f6bel & M\u00f6bel",
    "wof:placetype":"venue"
},
  "geometry": {"coordinates":[7.7304329872,47.4808311462],"type":"Point"}
}