{
  "type": "Feature",
  "properties": {
    "iso:country":"CH",
    "sg:address":"Chantemerle Route De 58",
    "sg:city":"Granges-paccot",
    "sg:orig_category":"Grosshandel mit Erzen U Metallen",
    "sg:postcode":"1763",
    "sg:province":"Fribourg",
    "wof:name":"Smt Swiss Metal Trade Corp",
    "wof:placetype":"venue"
},
  "geometry": {"coordinates":[7.140182972,46.820224762],"type":"Point"}
}