{
  "type": "Feature",
  "properties": {
    "iso:country":"CH",
    "sg:address":"Looslistrasse 50",
    "sg:city":"Bern",
    "sg:orig_category":"Webdesign",
    "sg:phone":"+41 31 998 21 69",
    "sg:postcode":"3027",
    "sg:province":"Bern",
    "wof:name":"Stefan Burri It Development",
    "wof:placetype":"venue"
},
  "geometry": {"coordinates":[7.3962421417,46.9477539062],"type":"Point"}
}