{
  "type": "Feature",
  "properties": {
    "iso:country":"CH",
    "sg:address":"Fontaine Chemin De La 2",
    "sg:city":"Nyon",
    "sg:orig_category":"Saunas, Solarien, Fitnesszentren U \u00e4hnliches",
    "sg:phone":"+41 22 361 77 88",
    "sg:postcode":"1260",
    "sg:province":"Vaud",
    "wof:name":"Sport Et Sant\u00e9 Des Fontaines S\u00e0rl",
    "wof:placetype":"venue"
},
  "geometry": {"coordinates":[6.2390799522,46.3823661804],"type":"Point"}
}