{
  "type": "Feature",
  "properties": {
    "iso:country":"CH",
    "sg:address":"Rue Des Uttins 22",
    "sg:city":"Yverdon-les-bains",
    "sg:classifiers":[
        {
            "category":"Restaurant",
            "type":"Food & Drink"
        }
    ],
    "sg:phone":"+41 24 445 41 31",
    "sg:postcode":"1400",
    "sg:province":"Vaud",
    "wof:name":"Caf\u00e9 Des Uttins",
    "wof:placetype":"venue"
},
  "geometry": {"coordinates":[6.6276798248,46.7851333618],"type":"Point"}
}