{
  "type": "Feature",
  "properties": {
    "iso:country":"CH",
    "sg:address":"Im Weissgrien 30.",
    "sg:city":"M\u00fcnchenstein",
    "sg:orig_category":"Grosshandel mit sonstigen Maschinen U Ausr\u00fcstungen f\u00fcr Industrie, Handel U Schiffahrt",
    "sg:phone":"+41 21 634 10 52",
    "sg:postcode":"4142",
    "sg:province":"Basel-Landschaft",
    "wof:name":"Paco Enterprises S\u00e0rl",
    "wof:placetype":"venue"
},
  "geometry": {"coordinates":[6.591714859,46.5391654968],"type":"Point"}
}