{
  "type": "Feature",
  "properties": {
    "iso:country":"CH",
    "sg:address":"Rosengasse 8",
    "sg:city":"Schaffhausen",
    "sg:orig_category":"Strassenverkehrs\u00e4mter and -inspektorate -Schifffahrts\u00e4mter",
    "sg:phone":"+41 52 632 71 11",
    "sg:postcode":"8200",
    "sg:province":"Schaffhausen",
    "wof:name":"Strassenverkehrs-& Schiff- Fahrtsamt Des Kantons Sh",
    "wof:placetype":"venue"
},
  "geometry": {"coordinates":[8.6342983246,47.6943359375],"type":"Point"}
}