{
  "type": "Feature",
  "properties": {
    "iso:country":"CH",
    "sg:address":"Bsetzi 21b 7204 Untervaz. Postfach",
    "sg:city":"Untervaz",
    "sg:orig_category":"Herstellung von Gummi U Kunststoffwaren Herstellung von Reiseartikeln, Leder U Sattlerwaren",
    "sg:phone":"+41 17640875",
    "sg:postcode":"7204",
    "sg:province":"Graubunden",
    "wof:name":"Markus Holder Koffer-fabrikation",
    "wof:placetype":"venue"
},
  "geometry": {"coordinates":[8.5325202942,47.2461013794],"type":"Point"}
}