{
  "type": "Feature",
  "properties": {
    "iso:country":"CH",
    "sg:address":"Grand-rue 5 2105 Travers Case Postale 53",
    "sg:city":"Travers",
    "sg:orig_category":"Detailhandel mit Fleisch U Fleischwaren",
    "sg:phone":"+41 32 863 13 42",
    "sg:postcode":"2105",
    "sg:province":"Neuch\u00e2tel",
    "wof:name":"Ricca Charles.",
    "wof:placetype":"venue"
},
  "geometry": {"coordinates":[6.6771020889,46.9407196045],"type":"Point"}
}