{
  "type": "Feature",
  "properties": {
    "iso:country":"CH",
    "sg:address":"La Cure",
    "sg:city":"Saubraz",
    "sg:orig_category":"Softwareentwicklung U beratung",
    "sg:phone":"+41 21 828 40 88",
    "sg:postcode":"1189",
    "sg:province":"Vaud",
    "wof:name":"Sme Services S\u00e0rl",
    "wof:placetype":"venue"
},
  "geometry": {"coordinates":[6.3310799599,46.516960144],"type":"Point"}
}