{
  "type": "Feature",
  "properties": {
    "iso:country":"CH",
    "sg:address":"Hochstrasse 348 8200 Schaffhausen. Postfach 255",
    "sg:city":"Schaffhausen",
    "sg:orig_category":"Sanit\u00e4r U Heizungsinstallation Sanit\u00e4r, Heizungs U L\u00fcftungsinstallation",
    "sg:phone":"+41 52 643 17 33",
    "sg:postcode":"8205",
    "sg:province":"Schaffhausen",
    "wof:name":"Meier J. Ag",
    "wof:placetype":"venue"
},
  "geometry": {"coordinates":[8.6508703232,47.717010498],"type":"Point"}
}