{
  "type": "Feature",
  "properties": {
    "iso:country":"CH",
    "sg:address":"Marktgasse 6",
    "sg:city":"Zofingen",
    "sg:orig_category":"Kunstschlosserei Stahl U Leichtmetallbau",
    "sg:phone":"+41 62 751 12 28",
    "sg:postcode":"4800",
    "sg:province":"Aargau",
    "wof:name":"Bernhard B\u00fchler Metallbau & Kunstschlosserei",
    "wof:placetype":"venue"
},
  "geometry": {"coordinates":[7.9454870224,47.2882118225],"type":"Point"}
}