{
  "type": "Feature",
  "properties": {
    "iso:country":"CH",
    "sg:address":"Grand-ch\u00eane Rue Du 8 1003 Lausanne. Postfach",
    "sg:city":"Lausanne",
    "sg:orig_category":"Unclassifiable Establishments",
    "sg:postcode":"1003",
    "sg:province":"Vaud",
    "wof:name":"Si De Montbenon",
    "wof:placetype":"venue"
},
  "geometry": {"coordinates":[6.6303920746,46.5198554993],"type":"Point"}
}