{
  "type": "Feature",
  "properties": {
    "iso:country":"CH",
    "sg:address":"Forchstrasse 2",
    "sg:city":"Z\u00fcrich",
    "sg:orig_category":"Unclassifiable Establishments",
    "sg:postcode":"8005",
    "sg:province":"Z\u00fcrich",
    "wof:name":"Gwx Global Wine Exchange Gmbh",
    "wof:placetype":"venue"
},
  "geometry": {"coordinates":[8.554772377,47.3644638062],"type":"Point"}
}