{
  "type": "Feature",
  "properties": {
    "iso:country":"CH",
    "sg:address":"Grand-rue 63",
    "sg:city":"Morges",
    "sg:orig_category":"Detailhandel mit Fleisch U Fleischwaren",
    "sg:phone":"+41 21 921 10 53",
    "sg:postcode":"1110",
    "sg:province":"Vaud",
    "wof:name":"Roger Matthey Boucherie-charcuterie",
    "wof:placetype":"venue"
},
  "geometry": {"coordinates":[6.8432750702,46.4621353149],"type":"Point"}
}