{
  "type": "Feature",
  "properties": {
    "iso:country":"CH",
    "sg:address":"Uttigenstrasse 27a",
    "sg:city":"Uetendorf",
    "sg:orig_category":"Detektivb\u00fcros U \u00dcberwachung",
    "sg:postcode":"3661",
    "sg:province":"Bern",
    "wof:name":"Suter Begleitschutz Personen Und Wertsachenbegleitschutz",
    "wof:placetype":"venue"
},
  "geometry": {"coordinates":[8.1840133667,47.4149246216],"type":"Point"}
}