{
  "type": "Feature",
  "properties": {
    "iso:country":"CH",
    "sg:address":"Via Campo Marzio 6",
    "sg:city":"Bellinzona",
    "sg:orig_category":"Arztpraxen",
    "sg:phone":"+41 79 337 22 22",
    "sg:postcode":"6500",
    "sg:province":"Ticino",
    "wof:name":"Dott.med.desa Zanini Medico Generico",
    "wof:placetype":"venue"
},
  "geometry": {"coordinates":[9.0209,46.194489],"type":"Point"}
}