{
  "type": "Feature",
  "properties": {
    "iso:country":"CH",
    "sg:address":"Schulstrasse 2",
    "sg:city":"Seengen",
    "sg:orig_category":"RESTAURANTS: TEA-ROOMS",
    "sg:phone":"+41 62 777 12 07",
    "sg:postcode":"5707",
    "sg:province":"Aargau",
    "wof:name":"Restaurant Burgturm & Jockey Bar",
    "wof:placetype":"venue"
},
  "geometry": {"coordinates":[8.2050590515,47.3267555237],"type":"Point"}
}