{
  "type": "Feature",
  "properties": {
    "iso:country":"CH",
    "sg:address":"Zofoldweg 442",
    "sg:city":"Hirschthal",
    "sg:orig_category":"Verm\u00f6gensverwaltung",
    "sg:phone":"+41 33 744 60 20",
    "sg:postcode":"5042",
    "sg:province":"Aargau",
    "wof:name":"Icc Trust Ltd Verm\u00f6gensverwaltung",
    "wof:placetype":"venue"
},
  "geometry": {"coordinates":[7.2861051559,46.4732818604],"type":"Point"}
}