{
  "type": "Feature",
  "properties": {
    "iso:country":"CH",
    "sg:address":"Schulstrasse 44",
    "sg:city":"Wiesendangen",
    "sg:orig_category":"Sportvereine Wassersport",
    "sg:phone":"+41 19109050",
    "sg:postcode":"8542",
    "sg:province":"Z\u00fcrich",
    "wof:name":"Wasserballklub Aquastar",
    "wof:placetype":"venue"
},
  "geometry": {"coordinates":[8.5822019577,47.3262825012],"type":"Point"}
}