{
  "type": "Feature",
  "properties": {
    "iso:country":"CH",
    "sg:address":"Jubil\u00e4umsstrasse 15 3005 Bern. Postfach",
    "sg:city":"Bern",
    "sg:orig_category":"Handelsvermittlung von Maschinen, technischem Bedarf, Wasser U Luftfahrzeugen",
    "sg:postcode":"3005",
    "sg:province":"Bern",
    "wof:name":"Willy Spichiger-godet Industrievertretungen",
    "wof:placetype":"venue"
},
  "geometry": {"coordinates":[7.4521541595,46.9391479492],"type":"Point"}
}