{
  "type": "Feature",
  "properties": {
    "iso:country":"CH",
    "sg:address":"Inselistrasse 15",
    "sg:city":"Konolfingen",
    "sg:orig_category":"Detailhandel mit Zeitungen U Zeitschriften Kioske",
    "sg:phone":"+41 31 791 25 66",
    "sg:postcode":"3510",
    "sg:province":"Bern",
    "wof:name":"Schwimmbad Konolfingen",
    "wof:placetype":"venue"
},
  "geometry": {"coordinates":[7.6244702339,46.8758621216],"type":"Point"}
}