{
  "type": "Feature",
  "properties": {
    "iso:country":"CH",
    "sg:address":"Stadthausstrasse 103",
    "sg:city":"Winterthur",
    "sg:orig_category":"Architekturb\u00fcros",
    "sg:phone":"+41 52 213 11 06",
    "sg:postcode":"8400",
    "sg:province":"Z\u00fcrich",
    "wof:name":"Rolf Juzi Architekturb\u00fcro",
    "wof:placetype":"venue"
},
  "geometry": {"coordinates":[8.728018,47.499969],"type":"Point"}
}