{
  "type": "Feature",
  "properties": {
    "iso:country":"CH",
    "sg:address":"Chemin Du Boisy 46",
    "sg:city":"Lausanne",
    "sg:orig_category":"Bauschreinerei",
    "sg:phone":"+41 21 646 39 97",
    "sg:postcode":"1004",
    "sg:province":"Vaud",
    "wof:name":"Alain Delacr\u00e9taz Menuiserie De L'orio",
    "wof:placetype":"venue"
},
  "geometry": {"coordinates":[6.613893,46.536617],"type":"Point"}
}