{
  "type": "Feature",
  "properties": {
    "iso:country":"CH",
    "sg:address":"Bahnhofplatz",
    "sg:city":"Luzern",
    "sg:orig_category":"Bijouterien Gold- and Silberschmuck Detailhandel",
    "sg:phone":"+41 41 210 21 80",
    "sg:postcode":"6003",
    "sg:province":"Luzern",
    "wof:name":"Ruckli Goldschmied Ag Schmuck & Uhren Gesch\u00e4ft",
    "wof:placetype":"venue"
},
  "geometry": {"coordinates":[8.309277,47.050419],"type":"Point"}
}