{
  "type": "Feature",
  "properties": {
    "iso:country":"CH",
    "sg:address":"Zimmeregg 4",
    "sg:city":"Littau",
    "sg:orig_category":"Non-Classified Establishments",
    "sg:postcode":"6014",
    "sg:province":"Luzern",
    "wof:name":"Katarzyna Kuhn Ern\u00e4hrungsberatung",
    "wof:placetype":"venue"
},
  "geometry": {"coordinates":[8.2660827637,47.0528144836],"type":"Point"}
}