{
  "type": "Feature",
  "properties": {
    "iso:country":"CH",
    "sg:address":"Hauptstrasse 157",
    "sg:city":"Zetzwil",
    "sg:orig_category":"Detailhandel mit Antiquit\u00e4ten",
    "sg:phone":"+41 62 773 14 25",
    "sg:postcode":"5732",
    "sg:province":"Aargau",
    "wof:name":"Hans-joachim & Ruth Alhausen Antiquit\u00e4ten",
    "wof:placetype":"venue"
},
  "geometry": {"coordinates":[8.15225,47.284767],"type":"Point"}
}