{
  "type": "Feature",
  "properties": {
    "iso:country":"CH",
    "sg:address":"Mellingerstrasse 12",
    "sg:city":"Niederrohrdorf",
    "sg:orig_category":"High Voltage Insulation Testing Instruments",
    "sg:phone":"+41 56 496 74 80",
    "sg:postcode":"5443",
    "sg:province":"Aargau",
    "wof:name":"Seitz Instruments Ag",
    "wof:placetype":"venue"
},
  "geometry": {"coordinates":[8.300028801,47.424949646],"type":"Point"}
}