{
  "type": "Feature",
  "properties": {
    "iso:country":"CH",
    "sg:address":"M\u00f6rsbergerstrasse 54",
    "sg:city":"Basel",
    "sg:orig_category":"Kunsthandel",
    "sg:phone":"+41 61 683 13 05",
    "sg:postcode":"4057",
    "sg:province":"Basel-Stadt",
    "wof:name":"Art & Vision Association Urwyler Sharif & G\u00fcnay",
    "wof:placetype":"venue"
},
  "geometry": {"coordinates":[7.5935339928,47.56823349],"type":"Point"}
}