{
  "type": "Feature",
  "properties": {
    "iso:country":"CH",
    "sg:address":"Obergrundstrasse 106",
    "sg:city":"Luzern",
    "sg:orig_category":"RESTAURANTS: TEA-ROOMS",
    "sg:phone":"+41 41 811 10 87",
    "sg:postcode":"6005",
    "sg:province":"Luzern",
    "wof:name":"Elsener Hans-peter",
    "wof:placetype":"venue"
},
  "geometry": {"coordinates":[8.3011074066,47.0403060913],"type":"Point"}
}