{
  "type": "Feature",
  "properties": {
    "iso:country":"CH",
    "sg:address":"Via Crusch 6 7402 Bonaduz. Postfach",
    "sg:city":"Bonaduz",
    "sg:orig_category":"Malerei RESTAURANTS: TEA-ROOMS",
    "sg:phone":"+41 81 641 16 64",
    "sg:postcode":"7402",
    "sg:province":"Graubunden",
    "wof:name":"Anton Maissen",
    "wof:placetype":"venue"
},
  "geometry": {"coordinates":[9.3985242844,46.8079490662],"type":"Point"}
}