{
  "type": "Feature",
  "properties": {
    "iso:country":"CH",
    "sg:address":"2607",
    "sg:city":"Cort\u00e9bert",
    "sg:orig_category":"Sportvereine Turnen",
    "sg:postcode":"2607",
    "sg:province":"Bern",
    "wof:name":"St\u00e9 De Gymnastique",
    "wof:placetype":"venue"
},
  "geometry": {"coordinates":[7.1092700958,47.1873588562],"type":"Point"}
}