{
  "type": "Feature",
  "properties": {
    "iso:country":"CH",
    "sg:address":"Hallerstrasse 41",
    "sg:city":"Bern",
    "sg:orig_category":"Personal U Stellenvermittlung Unternehmensberatung",
    "sg:phone":"+41 31 301 70 55",
    "sg:postcode":"3012",
    "sg:province":"Bern",
    "wof:name":"R\u00fcegg K\u00f6nig Claudia",
    "wof:placetype":"venue"
},
  "geometry": {"coordinates":[7.4374380112,46.9540863037],"type":"Point"}
}