{
  "type": "Feature",
  "properties": {
    "iso:country":"CH",
    "sg:address":"Hauptstrasse 2",
    "sg:city":"Steinmaur",
    "sg:orig_category":"Apple Juice Concentrators",
    "sg:phone":"+41 18531555",
    "sg:postcode":"8162",
    "sg:province":"Z\u00fcrich",
    "wof:name":"E. Brunner Ag",
    "wof:placetype":"venue"
},
  "geometry": {"coordinates":[8.446243,47.492279],"type":"Point"}
}