{
  "type": "Feature",
  "properties": {
    "iso:country":"CH",
    "sg:address":"Chemin De Pensionnats 2",
    "sg:city":"Fribourg",
    "sg:classifiers":[
        {
            "category":"Banks & Credit Unions",
            "subcategory":"Bank",
            "type":"Services"
        }
    ],
    "sg:phone":"+41 37248838",
    "sg:postcode":"1700",
    "sg:province":"Fribourg",
    "wof:name":"Banque De L'etat De Fribourg",
    "wof:placetype":"venue"
},
  "geometry": {"coordinates":[7.138097,46.80088],"type":"Point"}
}