{
  "type": "Feature",
  "properties": {
    "iso:country":"CH",
    "sg:address":"Untere Rebgasse 6",
    "sg:city":"Basel",
    "sg:orig_category":"Wirtschafts- and Arbeitgeberverb\u00e4nde",
    "sg:phone":"+41 61 641 04 32",
    "sg:postcode":"4058",
    "sg:province":"Basel-Stadt",
    "wof:name":"Drogistenverband Basel-stadt",
    "wof:placetype":"venue"
},
  "geometry": {"coordinates":[7.5930328369,47.5620231628],"type":"Point"}
}