{
  "type": "Feature",
  "properties": {
    "iso:country":"CH",
    "sg:address":"Jegerlehnerweg 11",
    "sg:city":"Kriens",
    "sg:orig_category":"Arztpraxen",
    "sg:phone":"+41 41 311 10 15",
    "sg:postcode":"6010",
    "sg:province":"Luzern",
    "wof:name":"Dr.med. Peter Mattmann Aerzte F\u00fcr Allgemeine Medizin",
    "wof:placetype":"venue"
},
  "geometry": {"coordinates":[8.285038,47.033783],"type":"Point"}
}