{
  "type": "Feature",
  "properties": {
    "iso:country":"CH",
    "sg:address":"Voia Principala",
    "sg:city":"Lantsch/lenz",
    "sg:orig_category":"Grosshandel mit chemischen Erzeugnissen Grosshandel mit sonstigen Maschinen U Ausr\u00fcstungen f\u00fcr Indus",
    "sg:phone":"+41 81 681 11 27",
    "sg:postcode":"7083",
    "sg:province":"Graubunden",
    "wof:name":"Kew Reinigungstechnik Hochdruckreiniger",
    "wof:placetype":"venue"
},
  "geometry": {"coordinates":[9.5655345917,46.6821784973],"type":"Point"}
}