{
  "type": "Feature",
  "properties": {
    "iso:country":"CH",
    "sg:address":"Bahnhofstrasse 20",
    "sg:city":"Toffen",
    "sg:orig_category":"Kauf U Verkauf von Immobilien auf eigene Rechnung",
    "sg:postcode":"3125",
    "sg:province":"Bern",
    "wof:name":"Contabau Ag Toffen",
    "wof:placetype":"venue"
},
  "geometry": {"coordinates":[7.4945421219,46.859828949],"type":"Point"}
}