{
  "type": "Feature",
  "properties": {
    "iso:country":"CH",
    "sg:address":"Obere H\u00f6nggerstrasse 29a",
    "sg:city":"Unterengstringen",
    "sg:orig_category":"Detailhandel mit Textilien Sonstiger Detailhandel mit Metallwaren, Anstrichmitteln, Glaswaren, Bau U",
    "sg:phone":"+41 32 968 75 35",
    "sg:postcode":"8103",
    "sg:province":"Z\u00fcrich",
    "wof:name":"Monika Freitag La Bricole",
    "wof:placetype":"venue"
},
  "geometry": {"coordinates":[6.8311982155,47.1070251465],"type":"Point"}
}