{
  "type": "Feature",
  "properties": {
    "iso:country":"CH",
    "sg:address":"Weiherstrasse 2",
    "sg:city":"Wallisellen",
    "sg:orig_category":"Detailhandel mit Brennstoffen U Heizmaterial Grosshandel mit festen Brennstoffen U Mineral\u00f6lerzeugni",
    "sg:phone":"+41 18306457",
    "sg:postcode":"8304",
    "sg:province":"Z\u00fcrich",
    "wof:name":"M\u00fcller Karl",
    "wof:placetype":"venue"
},
  "geometry": {"coordinates":[8.59791,47.41827],"type":"Point"}
}