{
  "type": "Feature",
  "properties": {
    "iso:country":"CH",
    "sg:address":"Waldeckstrasse 100 4132 Muttenz. Postfach",
    "sg:city":"Birsfelden",
    "sg:orig_category":"Grosshandel mit Textilien Grosshandel mit sonstigen Konsumg\u00fctern",
    "sg:phone":"+41 71 686 58 09",
    "sg:postcode":"4127",
    "sg:province":"Basel-Landschaft",
    "wof:name":"Maniro Gmbh",
    "wof:placetype":"venue"
},
  "geometry": {"coordinates":[9.1834068298,47.6360282898],"type":"Point"}
}