{
  "type": "Feature",
  "properties": {
    "iso:country":"CH",
    "sg:address":"Sulgenbachstrasse 55",
    "sg:city":"Bern",
    "sg:orig_category":"Institutionen des Sozialwesens ohne Beherbergung",
    "sg:phone":"+41 31 371 12 33",
    "sg:postcode":"3007",
    "sg:province":"Bern",
    "wof:name":"Go East Beratungs Ag",
    "wof:placetype":"venue"
},
  "geometry": {"coordinates":[7.4336128235,46.9407424927],"type":"Point"}
}