{
  "type": "Feature",
  "properties": {
    "iso:country":"CH",
    "sg:address":"Arcas 1",
    "sg:city":"Chur",
    "sg:classifiers":[
        {
            "category":"Education",
            "subcategory":"Library",
            "type":"Public Place"
        }
    ],
    "sg:phone":"+41 81 252 61 40",
    "sg:postcode":"7000",
    "sg:province":"Graubunden",
    "sg:tags":[
        "u",
        "bibliotheken",
        "archive"
    ],
    "wof:name":"B\u00fcndner Volksbibliothek",
    "wof:placetype":"venue"
},
  "geometry": {"coordinates":[9.531882,46.847881],"type":"Point"}
}