{
  "type": "Feature",
  "properties": {
    "iso:country":"CH",
    "sg:address":"Bahnstrasse 1",
    "sg:city":"T\u00e4gerwilen",
    "sg:orig_category":"Einbau von Schreinerwaren",
    "sg:phone":"+41 71 666 72 50",
    "sg:postcode":"8274",
    "sg:province":"Thurgau",
    "wof:name":"Gastro Tec Ag",
    "wof:placetype":"venue"
},
  "geometry": {"coordinates":[9.1285419464,47.6600036621],"type":"Point"}
}