{
  "type": "Feature",
  "properties": {
    "iso:country":"CH",
    "sg:address":"6042",
    "sg:city":"Dietwil",
    "sg:orig_category":"Primarschulen",
    "sg:phone":"+41 31 879 15 71",
    "sg:postcode":"6042",
    "sg:province":"Aargau",
    "wof:name":"Primarschule",
    "wof:placetype":"venue"
},
  "geometry": {"coordinates":[8.3944396973,47.149559021],"type":"Point"}
}