{
  "type": "Feature",
  "properties": {
    "iso:country":"CH",
    "sg:address":"Usteristrasse 10 8001 Z\u00fcrich. Postfach 7080",
    "sg:city":"Z\u00fcrich",
    "sg:orig_category":"Advokaturb\u00fcros",
    "sg:phone":"+41 12213161",
    "sg:postcode":"8023",
    "sg:province":"Z\u00fcrich",
    "wof:name":"Dr.klaus Hery Anwaltsb\u00fcro",
    "wof:placetype":"venue"
},
  "geometry": {"coordinates":[8.536881,47.37587],"type":"Point"}
}