{
  "type": "Feature",
  "properties": {
    "iso:country":"CH",
    "sg:address":"Seestrasse 29",
    "sg:city":"Sutz",
    "sg:orig_category":"Werbung",
    "sg:postcode":"2572",
    "sg:province":"Bern",
    "wof:name":"Cosix, Beatrice Cosandier-blaser",
    "wof:placetype":"venue"
},
  "geometry": {"coordinates":[7.2109928131,47.0979576111],"type":"Point"}
}