{
  "type": "Feature",
  "properties": {
    "iso:country":"CH",
    "sg:address":"Zelgliweg 1 4452 Itingen. Postfach",
    "sg:city":"Itingen",
    "sg:orig_category":"Pensionskassen",
    "sg:phone":"+41 61 975 11 11",
    "sg:postcode":"4452",
    "sg:province":"Basel-Landschaft",
    "wof:name":"Pensionskasse Rcc, Research And Consulting Company",
    "wof:placetype":"venue"
},
  "geometry": {"coordinates":[7.7794828415,47.4702987671],"type":"Point"}
}