{
  "type": "Feature",
  "properties": {
    "iso:country":"CH",
    "sg:address":"Hardmattstrasse 5",
    "sg:city":"Pratteln",
    "sg:orig_category":"Reiseb\u00fcros U Reiseveranstalter",
    "sg:postcode":"4133",
    "sg:province":"Basel-Landschaft",
    "wof:name":"Ferizaji Reisen, Gurgurovci Hamdi",
    "wof:placetype":"venue"
},
  "geometry": {"coordinates":[7.6857409477,47.5234947205],"type":"Point"}
}