{
  "type": "Feature",
  "properties": {
    "iso:country":"CH",
    "sg:address":"Birsigstrasse 90",
    "sg:city":"Basel",
    "sg:orig_category":"Innendekorationsateliers",
    "sg:phone":"+41 61 281 36 74",
    "sg:postcode":"4054",
    "sg:province":"Basel-Stadt",
    "wof:name":"Desimir Polsterei & Innendekoration",
    "wof:placetype":"venue"
},
  "geometry": {"coordinates":[7.5799341202,47.5499649048],"type":"Point"}
}