{
  "type": "Feature",
  "properties": {
    "iso:country":"CH",
    "sg:address":"Ceresio Via 34a",
    "sg:city":"Pregassona",
    "sg:orig_category":"Schreib U \u00dcbersetzungsb\u00fcros",
    "sg:postcode":"6963",
    "sg:province":"Ticino",
    "wof:name":"Simultanphone Sa",
    "wof:placetype":"venue"
},
  "geometry": {"coordinates":[8.9667263031,46.0198364258],"type":"Point"}
}