{
  "type": "Feature",
  "properties": {
    "iso:country":"CH",
    "sg:address":"6903 Lugano Casella Postale 79",
    "sg:city":"Lugano",
    "sg:orig_category":"Allgemeiner Hoch U Tiefbau",
    "sg:phone":"+41 91 605 60 93",
    "sg:postcode":"6903",
    "sg:province":"Ticino",
    "wof:name":"Skory Sa Impresa Costruzioni",
    "wof:placetype":"venue"
},
  "geometry": {"coordinates":[8.946136,45.976784],"type":"Point"}
}