{
  "type": "Feature",
  "properties": {
    "iso:country":"CH",
    "sg:address":"Haupstrasse 69",
    "sg:city":"Muhen",
    "sg:orig_category":"Sanit\u00e4r, Heizungs U L\u00fcftungsinstallation Sanit\u00e4rinstallation",
    "sg:phone":"+41 62 724 12 96",
    "sg:postcode":"5037",
    "sg:province":"Aargau",
    "wof:name":"Gallo Haustechnik Sanit\u00e4r/heizung",
    "wof:placetype":"venue"
},
  "geometry": {"coordinates":[8.0556898117,47.3333892822],"type":"Point"}
}