{
  "type": "Feature",
  "properties": {
    "iso:country":"CH",
    "sg:address":"Zelglistrasse 15",
    "sg:city":"Fehraltorf",
    "sg:orig_category":"Wirtschaftspr\u00fcfung, Steuerberatung U Treuhand",
    "sg:phone":"+41 19956031",
    "sg:postcode":"8320",
    "sg:province":"Z\u00fcrich",
    "wof:name":"Gasser Urs",
    "wof:placetype":"venue"
},
  "geometry": {"coordinates":[8.7547426224,47.3936500549],"type":"Point"}
}