{
  "type": "Feature",
  "properties": {
    "iso:country":"CH",
    "sg:address":"Webergasse 50-52 8200 Schaffhausen. Postfach",
    "sg:city":"Schaffhausen",
    "sg:orig_category":"Detailhandel mit Haustieren U zoologischem Bedarf",
    "sg:phone":"+41 52 625 20 85",
    "sg:postcode":"8201",
    "sg:province":"Schaffhausen",
    "wof:name":"Zoo Beutler",
    "wof:placetype":"venue"
},
  "geometry": {"coordinates":[8.6349506378,47.698513031],"type":"Point"}
}