{
  "type": "Feature",
  "properties": {
    "iso:country":"CH",
    "sg:address":"Huzlenstrasse 3",
    "sg:city":"Volketswil",
    "sg:orig_category":"Arztpraxen",
    "sg:phone":"+41 19451510",
    "sg:postcode":"8604",
    "sg:province":"Z\u00fcrich",
    "wof:name":"Dr.med.titus Morger Spezialarzt Fmh",
    "wof:placetype":"venue"
},
  "geometry": {"coordinates":[8.685085,47.393887],"type":"Point"}
}