{
  "type": "Feature",
  "properties": {
    "iso:country":"CH",
    "sg:address":"Avenue De Lonay 27",
    "sg:city":"Morges",
    "sg:orig_category":"Architektur U Ingenieurb\u00fcros",
    "sg:phone":"+41 21 801 34 20",
    "sg:postcode":"1110",
    "sg:province":"Vaud",
    "wof:name":"Jean-henri Rinderknecht Bureau D'ing\u00e9nieur",
    "wof:placetype":"venue"
},
  "geometry": {"coordinates":[6.509109,46.520222],"type":"Point"}
}