{
  "type": "Feature",
  "properties": {
    "iso:country":"CH",
    "sg:address":"Sevogelstrasse 28",
    "sg:city":"Muttenz",
    "sg:orig_category":"Interessenvertretungen",
    "sg:postcode":"4132",
    "sg:province":"Basel-Landschaft",
    "wof:name":"Stiftung Pfadihuus Herzberg",
    "wof:placetype":"venue"
},
  "geometry": {"coordinates":[7.6433558464,47.5268516541],"type":"Point"}
}