{
  "type": "Feature",
  "properties": {
    "addr:full":"La Cotze Orsi\u00e8res Valais 1937",
    "addr:postcode":"1937",
    "iso:country":"CH",
    "sg:address":"La Cotze",
    "sg:city":"Orsi\u00e8res",
    "sg:orig_category":"Allgemeiner Hoch U Tiefbau Allgemeiner Hochbau",
    "sg:phone":"+41 27 783 23 53",
    "sg:postcode":"1937",
    "sg:province":"Valais",
    "wof:name":"Charly Lovey Sa Ma\u00e7onnerie & Travaux Publics",
    "wof:placetype":"venue"
},
  "geometry": {"coordinates":[7.14472,46.029701],"type":"Point"}
}