{
  "type": "Feature",
  "properties": {
    "iso:country":"CH",
    "sg:address":"Chollerstrasse 38",
    "sg:city":"Zug",
    "sg:orig_category":"Hardwareberatung Softwareentwicklung U beratung",
    "sg:phone":"+41 41 747 37 37",
    "sg:postcode":"6300",
    "sg:province":"Zug",
    "wof:name":"Copex Consulting Group S\u00e0rl",
    "wof:placetype":"venue"
},
  "geometry": {"coordinates":[8.4930562973,47.1862182617],"type":"Point"}
}