{
  "type": "Feature",
  "properties": {
    "addr:full":"Baumgarten L\u00fctschental Bern 3816",
    "addr:postcode":"3816",
    "iso:country":"CH",
    "sg:address":"Baumgarten",
    "sg:city":"L\u00fctschental",
    "sg:orig_category":"Campingpl\u00e4tze",
    "sg:phone":"+41 33 853 18 24",
    "sg:postcode":"3816",
    "sg:province":"Bern",
    "wof:name":"Dany's Camp",
    "wof:placetype":"venue"
},
  "geometry": {"coordinates":[7.930674,46.637573],"type":"Point"}
}