{
  "type": "Feature",
  "properties": {
    "iso:country":"CH",
    "sg:address":"Bahnhofstrasse 27",
    "sg:city":"Spreitenbach",
    "sg:orig_category":"Herstellung von Teppichen Verlegen von Fussboden",
    "sg:phone":"+41 33 951 19 64",
    "sg:postcode":"8957",
    "sg:province":"Aargau",
    "wof:name":"Fl\u00fcbo Brienz Ag Bodenbel\u00e4ge M\u00f6bel",
    "wof:placetype":"venue"
},
  "geometry": {"coordinates":[8.0230760574,46.7568626404],"type":"Point"}
}