{
  "type": "Feature",
  "properties": {
    "iso:country":"CH",
    "sg:address":"Kantonsstrasse 7",
    "sg:city":"Nottwil",
    "sg:orig_category":"G\u00fcterbef\u00f6rderung im Strassenverkehr",
    "sg:phone":"+41 79 608 42 86",
    "sg:postcode":"6207",
    "sg:province":"Luzern",
    "wof:name":"Anton Hunger Transporte",
    "wof:placetype":"venue"
},
  "geometry": {"coordinates":[9.315530777,46.6826171875],"type":"Point"}
}