{
  "type": "Feature",
  "properties": {
    "addr:full":"Fluhmattweg 4 Luzern Luzern 6004",
    "addr:housenumber":"4",
    "addr:postcode":"6004",
    "addr:street":"Fluhmattweg",
    "iso:country":"CH",
    "sg:address":"Fluhmattweg 4",
    "sg:city":"Luzern",
    "sg:orig_category":"Akupunktur",
    "sg:phone":"+41 41 410 55 88",
    "sg:postcode":"6004",
    "sg:province":"Luzern",
    "wof:name":"Heidi Br\u00fcgger Praxis F\u00fcr Akupunktur",
    "wof:placetype":"venue"
},
  "geometry": {"coordinates":[8.30904,47.058079],"type":"Point"}
}