{
  "type": "Feature",
  "properties": {
    "iso:country":"CH",
    "sg:address":"Oberdorfstrasse 91",
    "sg:city":"M\u00fcnchenbuchsee",
    "sg:classifiers":[
        {
            "category":"Restaurant",
            "type":"Food & Drink"
        }
    ],
    "sg:phone":"+41 31 869 22 46",
    "sg:postcode":"3053",
    "sg:province":"Bern",
    "wof:name":"Restaurant Obi's Corner",
    "wof:placetype":"venue"
},
  "geometry": {"coordinates":[7.4369797707,47.0197906494],"type":"Point"}
}