{
  "type": "Feature",
  "properties": {
    "iso:country":"CH",
    "sg:address":"Grabenstrasse 21",
    "sg:city":"Neunkirch",
    "sg:classifiers":[
        {
            "category":"Professional",
            "subcategory":"Art Services",
            "type":"Services"
        }
    ],
    "sg:phone":"+41 52 681 39 11",
    "sg:postcode":"8213",
    "sg:province":"Schaffhausen",
    "sg:tags":[
        "development",
        "packaging",
        "product",
        "design"
    ],
    "wof:name":"Hvb Haist Verpackungs-beratung",
    "wof:placetype":"venue"
},
  "geometry": {"coordinates":[8.497399,47.689365],"type":"Point"}
}