{
  "type": "Feature",
  "properties": {
    "iso:country":"CH",
    "sg:address":"Viale Officina 3",
    "sg:city":"Bellinzona",
    "sg:orig_category":"Pensionskassen",
    "sg:postcode":"6500",
    "sg:province":"Ticino",
    "wof:name":"Fondo Di Previdenza Sociale Per Il Personale Della Bermi Watch Sa",
    "wof:placetype":"venue"
},
  "geometry": {"coordinates":[9.0213098526,45.8488502502],"type":"Point"}
}