{
  "type": "Feature",
  "properties": {
    "iso:country":"CH",
    "sg:address":"Rickstr. 12b 9042 Speicher. Postfach",
    "sg:city":"Speicherschwendi",
    "sg:orig_category":"Herstellung von k\u00e4lte U lufttechnischen Erzeugnissen f\u00fcr gewerbliche Zwecke",
    "sg:postcode":"9037",
    "sg:province":"Appenzell Ausserrhoden",
    "wof:name":"R\u00fcegg Walter, Entstaubungs, L\u00fcftungs Und Klimaanlagen",
    "wof:placetype":"venue"
},
  "geometry": {"coordinates":[9.1546421051,47.5675811768],"type":"Point"}
}