{
  "type": "Feature",
  "properties": {
    "addr:full":"1533 M\u00e9ni\u00e8res Fribourg 1533",
    "addr:housenumber":"1533",
    "addr:postcode":"1533",
    "addr:street":"Me\u0301Nie\u0300Res Fribourg",
    "iso:country":"CH",
    "sg:address":"1533",
    "sg:city":"M\u00e9ni\u00e8res",
    "sg:orig_category":"Aktivit\u00e4ten der Generalunternehmen im Baugewerbe Allgemeiner Hoch U Tiefbau",
    "sg:phone":"+41 26 665 18 34",
    "sg:postcode":"1533",
    "sg:province":"Fribourg",
    "wof:name":"Reymo Constructions Sa Entreprise G\u00e9n.du B\u00e2timent",
    "wof:placetype":"venue"
},
  "geometry": {"coordinates":[6.88425,46.785789],"type":"Point"}
}