{
  "type": "Feature",
  "properties": {
    "iso:country":"CH",
    "sg:address":"Kasernenstrasse 27",
    "sg:city":"Bern",
    "sg:orig_category":"Detailhandel mit Zeitungen U Zeitschriften Kioske",
    "sg:phone":"+41 27 957 29 86",
    "sg:postcode":"3013",
    "sg:province":"Bern",
    "wof:name":"Emil Andenmatten Kiosk",
    "wof:placetype":"venue"
},
  "geometry": {"coordinates":[7.9573631287,46.0964317322],"type":"Point"}
}