{
  "type": "Feature",
  "properties": {
    "iso:country":"CH",
    "sg:address":"Grossfeldstrasse 3",
    "sg:city":"Kriens",
    "sg:classifiers":[
        {
            "category":"Banks & Credit Unions",
            "subcategory":"Bank",
            "type":"Services"
        }
    ],
    "sg:phone":"+41 4141410050",
    "sg:postcode":"6010",
    "sg:province":"Luzern",
    "wof:name":"Depositenkasse Des Verbandes, Liberaler Baugenossenschaften",
    "wof:placetype":"venue"
},
  "geometry": {"coordinates":[8.283514,47.033577],"type":"Point"}
}