{
  "type": "Feature",
  "properties": {
    "iso:country":"CH",
    "sg:address":"Karl-neuhaus-strasse 40 2502 Biel/bienne. Postfach",
    "sg:city":"Biel/bienne",
    "sg:orig_category":"Detailhandel mit Uhren U Schmuck",
    "sg:phone":"+41 32 322 64 65",
    "sg:postcode":"2501",
    "sg:province":"Bern",
    "wof:name":"Yakup Sevin\u00e7 Exclusive Jewellery",
    "wof:placetype":"venue"
},
  "geometry": {"coordinates":[7.2451238632,47.1357917786],"type":"Point"}
}