{
  "type": "Feature",
  "properties": {
    "iso:country":"CH",
    "sg:address":"Villars Route De 1",
    "sg:city":"Fribourg",
    "sg:orig_category":"Werbung",
    "sg:phone":"+41 79 206 90 90",
    "sg:postcode":"1700",
    "sg:province":"Fribourg",
    "wof:name":"Rohrbasser Mme St\u00e9phanie, Rectoverso",
    "wof:placetype":"venue"
},
  "geometry": {"coordinates":[7.1536831856,46.8037452698],"type":"Point"}
}