{
  "type": "Feature",
  "properties": {
    "iso:country":"CH",
    "sg:address":"Dorfstrasse 16",
    "sg:city":"Schneisingen",
    "sg:orig_category":"Architekturb\u00fcros",
    "sg:phone":"+41 56 241 13 76",
    "sg:postcode":"5425",
    "sg:province":"Aargau",
    "wof:name":"Rolf Schurgast Architekturb\u00fcro",
    "wof:placetype":"venue"
},
  "geometry": {"coordinates":[8.36512,47.517769],"type":"Point"}
}