{
  "type": "Feature",
  "properties": {
    "iso:country":"CH",
    "sg:address":"Talstrasse 82",
    "sg:city":"Z\u00fcrich",
    "sg:orig_category":"Inkassob\u00fcros",
    "sg:phone":"+41 31 358 99 11",
    "sg:postcode":"8001",
    "sg:province":"Z\u00fcrich",
    "wof:name":"Weco Inkasso Ag",
    "wof:placetype":"venue"
},
  "geometry": {"coordinates":[7.4179668427,46.9401931763],"type":"Point"}
}