{
  "type": "Feature",
  "properties": {
    "iso:country":"CH",
    "sg:address":"Thiersteinerrain 15",
    "sg:city":"Basel",
    "sg:orig_category":"Allgemeiner Hoch U Tiefbau",
    "sg:phone":"+41 61 332 21 04",
    "sg:postcode":"4053",
    "sg:province":"Basel-Stadt",
    "wof:name":"Trinler J\u00fcrgen",
    "wof:placetype":"venue"
},
  "geometry": {"coordinates":[7.596503,47.538353],"type":"Point"}
}