{
  "type": "Feature",
  "properties": {
    "iso:country":"CH",
    "sg:address":"Vordergasse 3",
    "sg:city":"Schaffhausen",
    "sg:orig_category":"Finanzierungsinstitutionen",
    "sg:postcode":"8200",
    "sg:province":"Schaffhausen",
    "wof:name":"Icg Investment Und Consulting Gmbh",
    "wof:placetype":"venue"
},
  "geometry": {"coordinates":[8.6378498077,47.6957054138],"type":"Point"}
}