{
  "type": "Feature",
  "properties": {
    "iso:country":"CH",
    "sg:address":"Ebnater Strasse 234a",
    "sg:city":"Ulisbach",
    "sg:orig_category":"Sportvereine Velo Rad-& Motorfahrer-Bund SRB",
    "sg:postcode":"9631",
    "sg:province":"St. Gallen",
    "wof:name":"Arbeiter-touring-bund",
    "wof:placetype":"venue"
},
  "geometry": {"coordinates":[9.1013441086,47.2839317322],"type":"Point"}
}