{
  "type": "Feature",
  "properties": {
    "iso:country":"CH",
    "sg:address":"Gartenstrasse 23",
    "sg:city":"Allschwil",
    "sg:orig_category":"Herstellung von Konstruktionsteilen, Fertigbauteilen U Ausbauelementen aus Holz",
    "sg:phone":"+41 61 481 58 50",
    "sg:postcode":"4123",
    "sg:province":"Basel-Landschaft",
    "wof:name":"J\u00f6rger Z\u00e4une Zaunfabrikation",
    "wof:placetype":"venue"
},
  "geometry": {"coordinates":[7.5415701866,47.5507888794],"type":"Point"}
}