{
  "type": "Feature",
  "properties": {
    "iso:country":"CH",
    "sg:address":"Watterstrasse 9 42",
    "sg:city":"Regensdorf",
    "sg:orig_category":"Detailhandel mit Brillen U anderen Sehhilfen Fachdetailhandel in Verkaufsr\u00e4umen",
    "sg:phone":"+41 31 931 36 56",
    "sg:postcode":"8105",
    "sg:province":"Z\u00fcrich",
    "wof:name":"Ehrensperger Ulrich",
    "wof:placetype":"venue"
},
  "geometry": {"coordinates":[7.483066,46.956055],"type":"Point"}
}