{
  "type": "Feature",
  "properties": {
    "iso:country":"CH",
    "sg:address":"P\u00e9rolles Boulevard De 55",
    "sg:city":"Fribourg",
    "sg:orig_category":"Rechtsberatung",
    "sg:postcode":"1700",
    "sg:province":"Fribourg",
    "wof:name":"A + D Verwaltungs Gmbh",
    "wof:placetype":"venue"
},
  "geometry": {"coordinates":[8.2240428925,46.8806610107],"type":"Point"}
}