{
  "type": "Feature",
  "properties": {
    "iso:country":"CH",
    "sg:address":"Nesslerenweg 82",
    "sg:city":"K\u00f6niz",
    "sg:orig_category":"Handel mit Automobilen",
    "sg:phone":"+41 22 343 23 20",
    "sg:postcode":"3098",
    "sg:province":"Bern",
    "wof:name":"Carouge Automobiles, Potet Thierry",
    "wof:placetype":"venue"
},
  "geometry": {"coordinates":[6.1356940269,46.1844787598],"type":"Point"}
}