{
  "type": "Feature",
  "properties": {
    "iso:country":"CH",
    "sg:address":"9512",
    "sg:city":"Rossr\u00fcti",
    "sg:classifiers":[
        {
            "category":"Restaurant",
            "type":"Food & Drink"
        }
    ],
    "sg:phone":"+41 33 765 34 34",
    "sg:postcode":"9512",
    "sg:province":"St. Gallen",
    "wof:name":"Restaurant R\u00f6sti Factory",
    "wof:placetype":"venue"
},
  "geometry": {"coordinates":[7.3220500946,46.4248199463],"type":"Point"}
}