{
  "type": "Feature",
  "properties": {
    "iso:country":"CH",
    "sg:address":"Belchenstrasse 2a",
    "sg:city":"Basel",
    "sg:orig_category":"Elektroinstallation",
    "sg:postcode":"4054",
    "sg:province":"Basel-Stadt",
    "wof:name":"Eccom Engineering Culture And Communication Buholzer & Kaufmann",
    "wof:placetype":"venue"
},
  "geometry": {"coordinates":[7.5739102364,47.5542984009],"type":"Point"}
}