{
  "type": "Feature",
  "properties": {
    "iso:country":"CH",
    "sg:address":"Im Moos 16",
    "sg:city":"Interlaken",
    "sg:orig_category":"Autospenglereien",
    "sg:phone":"+41 33 823 84 85",
    "sg:postcode":"3800",
    "sg:province":"Bern",
    "wof:name":"Robert Moser Sendli-carrosserie",
    "wof:placetype":"venue"
},
  "geometry": {"coordinates":[7.884295,46.689117],"type":"Point"}
}