{
  "type": "Feature",
  "properties": {
    "iso:country":"CH",
    "sg:address":"Birchhausstrasse 330",
    "sg:city":"Oberwil-lieli",
    "sg:orig_category":"Politische Parteien SVP",
    "sg:phone":"+41 56 633 10 44",
    "sg:postcode":"8966",
    "sg:province":"Aargau",
    "wof:name":"Svp Ortspartei Oberwil",
    "wof:placetype":"venue"
},
  "geometry": {"coordinates":[8.4039897919,47.3381652832],"type":"Point"}
}