{
  "type": "Feature",
  "properties": {
    "iso:country":"CH",
    "sg:address":"Via Rinaldo Simen 8a",
    "sg:city":"Chiasso",
    "sg:orig_category":"Detailhandel mit Brot, Back U S\u00fcsswaren Detailhandel mit Waren verschiedener Art, Hauptrichtung Nahr",
    "sg:phone":"+41 91 682 55 32",
    "sg:postcode":"6830",
    "sg:province":"Ticino",
    "wof:name":"Bossi Sergio",
    "wof:placetype":"venue"
},
  "geometry": {"coordinates":[9.028412,45.838219],"type":"Point"}
}