{
  "type": "Feature",
  "properties": {
    "iso:country":"CH",
    "sg:address":"Dubematt 2",
    "sg:city":"Rain",
    "sg:orig_category":"Sanit\u00e4r, Heizungs U L\u00fcftungsinstallation Sanit\u00e4rinstallation",
    "sg:phone":"+41 41 458 14 27",
    "sg:postcode":"6026",
    "sg:province":"Luzern",
    "wof:name":"Estermann Gebr. Ag",
    "wof:placetype":"venue"
},
  "geometry": {"coordinates":[8.2447519302,47.1245803833],"type":"Point"}
}