{
  "type": "Feature",
  "properties": {
    "iso:country":"CH",
    "sg:address":"Chemin Du Marais",
    "sg:city":"Founex",
    "sg:orig_category":"Softwareentwicklung U beratung",
    "sg:phone":"+41 22 884 05 05",
    "sg:postcode":"1297",
    "sg:province":"Vaud",
    "wof:name":"Mars Electronics International Inc., Wilmington, Delaware, Succursale De Plan-les-ouates Pr\u00e8s Gen\u00e8ve",
    "wof:placetype":"venue"
},
  "geometry": {"coordinates":[6.108081,46.170498],"type":"Point"}
}