{
  "type": "Feature",
  "properties": {
    "iso:country":"CH",
    "sg:address":"Grosser Letten 6",
    "sg:city":"Neunkirch",
    "sg:orig_category":"Museen",
    "sg:postcode":"8213",
    "sg:province":"Schaffhausen",
    "wof:name":"Sch\u00e4rrer Kurt-stiftung",
    "wof:placetype":"venue"
},
  "geometry": {"coordinates":[8.4989824295,47.6886253357],"type":"Point"}
}