{
  "type": "Feature",
  "properties": {
    "iso:country":"CH",
    "sg:address":"Avenue De La Gare 7",
    "sg:city":"Monthey",
    "sg:orig_category":"Bauspenglerei Zimmerei, Dachdeckerei, Bauspenglerei U Abdichtung",
    "sg:phone":"+41 24 471 75 80",
    "sg:postcode":"1870",
    "sg:province":"Valais",
    "wof:name":"Stoppini Michel",
    "wof:placetype":"venue"
},
  "geometry": {"coordinates":[6.948132,46.252815],"type":"Point"}
}