{
  "type": "Feature",
  "properties": {
    "iso:country":"CH",
    "sg:address":"Zugerstrasse 77",
    "sg:city":"Baar",
    "sg:orig_category":"Herstellung von sonstigen Erzeugnissen",
    "sg:phone":"+41 71 460 09 60",
    "sg:postcode":"6340",
    "sg:province":"Zug",
    "wof:name":"Molly's Buttons Brunner Ursi Ansteckkn\u00f6pfe; Produktion, Vertrieb",
    "wof:placetype":"venue"
},
  "geometry": {"coordinates":[9.1882553101,47.5617599487],"type":"Point"}
}