{
  "type": "Feature",
  "properties": {
    "iso:country":"CH",
    "sg:address":"Brand-strasse 18",
    "sg:city":"M\u00fchleberg",
    "sg:orig_category":"S\u00e4ge, Hobel U Holzimpr\u00e4gnierwerke S\u00e4gewerke",
    "sg:phone":"+41 31 751 01 24",
    "sg:postcode":"3203",
    "sg:province":"Bern",
    "wof:name":"Joh. Schiess Erben S\u00e4gerei & Hobelwerk",
    "wof:placetype":"venue"
},
  "geometry": {"coordinates":[7.2769179344,46.9622001648],"type":"Point"}
}