{
  "type": "Feature",
  "properties": {
    "addr:full":"Oberfeldstrasse 104 8408 Winterthur. Postfach 199 Winterthur Z\u00fcrich 8408",
    "addr:housenumber":"104;199",
    "addr:postcode":"8408;8408",
    "addr:street":"Oberfeldstrasse;Postfach",
    "iso:country":"CH",
    "sg:address":"Oberfeldstrasse 104 8408 Winterthur. Postfach 199",
    "sg:city":"Winterthur",
    "sg:orig_category":"Allgemeiner Hoch U Tiefbau Allgemeiner Hochbau",
    "sg:phone":"+41 52 222 48 07",
    "sg:postcode":"8408",
    "sg:province":"Z\u00fcrich",
    "wof:name":"B\u00fcttner & Co Bauunternehmung",
    "wof:placetype":"venue"
},
  "geometry": {"coordinates":[8.697601,47.50872],"type":"Point"}
}