{
  "type": "Feature",
  "properties": {
    "iso:country":"CH",
    "sg:address":"Marktgasse 59",
    "sg:city":"Rheinfelden",
    "sg:orig_category":"Detailhandel mit Bekleidung Detailhandel mit Herrenbekleidung",
    "sg:phone":"+41 22 311 86 66",
    "sg:postcode":"4310",
    "sg:province":"Aargau",
    "wof:name":"Pkz Burger-kehl & Cie Sa",
    "wof:placetype":"venue"
},
  "geometry": {"coordinates":[6.14535,46.203697],"type":"Point"}
}