{
  "type": "Feature",
  "properties": {
    "iso:country":"CH",
    "sg:address":"Rivage Rue Du 12",
    "sg:city":"Yverdon-les-bains",
    "sg:classifiers":[
        {
            "category":"Professional",
            "subcategory":"Employment Agencies",
            "type":"Services"
        }
    ],
    "sg:postcode":"1400",
    "sg:province":"Vaud",
    "sg:tags":[
        "personal",
        "u",
        "stellenvermittlung"
    ],
    "wof:name":"Menita Models Agency, Ianuario",
    "wof:placetype":"venue"
},
  "geometry": {"coordinates":[6.6368041039,46.7866783142],"type":"Point"}
}