{
  "type": "Feature",
  "properties": {
    "iso:country":"CH",
    "sg:address":"Riedholzstrasse 1",
    "sg:city":"Ebikon",
    "sg:orig_category":"Herstellung von Medikamenten U sonstigen pharmazeutischen Erzeugnissen Herstellung von pharmazeutisc",
    "sg:phone":"+41 41 440 99 66",
    "sg:postcode":"6030",
    "sg:province":"Luzern",
    "wof:name":"Regena Ag",
    "wof:placetype":"venue"
},
  "geometry": {"coordinates":[8.3426733017,47.0876121521],"type":"Point"}
}