{
  "type": "Feature",
  "properties": {
    "iso:country":"CH",
    "sg:address":"Thannerstr. 15",
    "sg:city":"Basel",
    "sg:classifiers":[
        {
            "category":"Manufacturing",
            "subcategory":"Tools & Machinery",
            "type":"Manufacturing & Wholesale Goods"
        }
    ],
    "sg:phone":"+41 61 306 88 22",
    "sg:postcode":"4009",
    "sg:province":"Basel-Stadt",
    "sg:tags":[
        "equipment",
        "measurement",
        "-",
        "precision",
        "instrument"
    ],
    "wof:name":"Jaquet Ag",
    "wof:placetype":"venue"
},
  "geometry": {"coordinates":[7.5748758316,47.5543823242],"type":"Point"}
}