{
  "type": "Feature",
  "properties": {
    "iso:country":"CH",
    "sg:address":"Niesenweg 4 3012 Bern. Postfach",
    "sg:city":"Bern",
    "sg:orig_category":"Dienstleistungen von Beteiligungsgesellschaften",
    "sg:postcode":"3005",
    "sg:province":"Bern",
    "wof:name":"Ksw Belo Horizonte Ag",
    "wof:placetype":"venue"
},
  "geometry": {"coordinates":[8.7833595276,47.2014961243],"type":"Point"}
}