{
  "type": "Feature",
  "properties": {
    "iso:country":"CH",
    "sg:address":"1812",
    "sg:city":"Rivaz",
    "sg:orig_category":"Rebbau",
    "sg:phone":"+41 21 946 13 56",
    "sg:postcode":"1812",
    "wof:name":"Alois Imhof Viticulteur",
    "wof:placetype":"venue"
},
  "geometry": {"coordinates":[6.7786898613,46.4763259888],"type":"Point"}
}