{
  "type": "Feature",
  "properties": {
    "iso:country":"CH",
    "sg:address":"Au Village",
    "sg:city":"Villars-epeney",
    "sg:orig_category":"Erbringung von sonstigen Dienstleistungen f\u00fcr Unterhaltung, Erholung U Freizeit",
    "sg:phone":"+41 24 420 25 65",
    "sg:postcode":"1404",
    "sg:province":"Vaud",
    "wof:name":"Nick Music, Nicole Schneider Macherel",
    "wof:placetype":"venue"
},
  "geometry": {"coordinates":[6.6966900826,46.7808113098],"type":"Point"}
}