{
  "type": "Feature",
  "properties": {
    "iso:country":"CH",
    "sg:address":"3824",
    "sg:city":"Stechelberg",
    "sg:orig_category":"Sportvereine Sch\u00fctzen",
    "sg:phone":"+41 33 755 16 10",
    "sg:postcode":"3824",
    "sg:province":"Bern",
    "wof:name":"Feldsch\u00fctzengesellschaft",
    "wof:placetype":"venue"
},
  "geometry": {"coordinates":[7.9027700424,46.5547103882],"type":"Point"}
}