{
  "type": "Feature",
  "properties": {
    "iso:country":"CH",
    "sg:address":"Angensteinerstrasse 20",
    "sg:city":"Basel",
    "sg:orig_category":"Fotografische Ateliers Fotografisches Gewerbe U fotografische Laboratorien",
    "sg:phone":"+41 61 312 56 23",
    "sg:postcode":"4052",
    "sg:province":"Basel-Stadt",
    "wof:name":"Fotoatelier Siegfried Ag",
    "wof:placetype":"venue"
},
  "geometry": {"coordinates":[7.6036739349,47.5490188599],"type":"Point"}
}