{
  "type": "Feature",
  "properties": {
    "iso:country":"CH",
    "sg:address":"Rue De La Gare 11 A",
    "sg:city":"Courrendlin",
    "sg:orig_category":"Bauschreinerei Herstellung von Konstruktionsteilen, Fertigbauteilen U Ausbauelementen aus Holz",
    "sg:phone":"+41 32 435 52 82",
    "sg:postcode":"2830",
    "sg:province":"Jura",
    "wof:name":"Michel Rhis",
    "wof:placetype":"venue"
},
  "geometry": {"coordinates":[7.370272,47.339657],"type":"Point"}
}