{
  "type": "Feature",
  "properties": {
    "iso:country":"CH",
    "sg:address":"1588",
    "sg:city":"Champmartin",
    "sg:orig_category":"Kauf U Verkauf von Immobilien auf eigene Rechnung",
    "sg:postcode":"1588",
    "sg:province":"Vaud",
    "wof:name":"Hostettler Arnold.",
    "wof:placetype":"venue"
},
  "geometry": {"coordinates":[6.9994101524,46.9411888123],"type":"Point"}
}