{
  "type": "Feature",
  "properties": {
    "iso:country":"CH",
    "sg:address":"Balderngasse 9 8001 Z\u00fcrich. Postfach",
    "sg:city":"Z\u00fcrich",
    "sg:orig_category":"Wirtschaftspr\u00fcfung, Steuerberatung U Treuhand",
    "sg:phone":"+41 12136969",
    "sg:postcode":"8039",
    "wof:name":"Baumgartner, Knobel & Partner, Treuhandgesellschaft",
    "wof:placetype":"venue"
},
  "geometry": {"coordinates":[8.5355577469,47.3697128296],"type":"Point"}
}