{
  "type": "Feature",
  "properties": {
    "iso:country":"CH",
    "sg:address":"Augartenstrasse 4",
    "sg:city":"Rheinfelden",
    "sg:orig_category":"Sonstige mit der Informatik verbundene T\u00e4tigkeiten",
    "sg:postcode":"4310",
    "sg:province":"Aargau",
    "wof:name":"Dr. Bender Gmbh",
    "wof:placetype":"venue"
},
  "geometry": {"coordinates":[7.7705111504,47.5485649109],"type":"Point"}
}