{
  "type": "Feature",
  "properties": {
    "iso:country":"CH",
    "sg:address":"6370",
    "sg:city":"Stans",
    "sg:orig_category":"Vorschulen, Kinderg\u00e4rten",
    "sg:phone":"+41 33 783 15 65",
    "sg:postcode":"6370",
    "sg:province":"Nidwalden",
    "wof:name":"Kindergarten Turnhalle",
    "wof:placetype":"venue"
},
  "geometry": {"coordinates":[8.5074367523,47.1491966248],"type":"Point"}
}