{
  "type": "Feature",
  "properties": {
    "iso:country":"CH",
    "sg:address":"Amriswiler Strasse 44",
    "sg:city":"Steinebrunn",
    "sg:orig_category":"RESTAURANTS: TEA-ROOMS",
    "sg:phone":"+41 71 891 15 26",
    "sg:postcode":"9314",
    "sg:province":"Thurgau",
    "wof:name":"Restaurant Gr\u00fcner Baum",
    "wof:placetype":"venue"
},
  "geometry": {"coordinates":[9.5715618134,47.416633606],"type":"Point"}
}