{
  "type": "Feature",
  "properties": {
    "iso:country":"CH",
    "sg:address":"Rue De Lausanne 147",
    "sg:city":"Gen\u00e8ve",
    "sg:orig_category":"Grosshandel mit Erzen U Metallen Handelsvermittlung von Brennstoffen, Erzen, Metallen U Chemikalien",
    "sg:phone":"+41 22 732 39 50",
    "sg:postcode":"1202",
    "sg:province":"Gen\u00e8ve",
    "wof:name":"Arag Traders Sa",
    "wof:placetype":"venue"
},
  "geometry": {"coordinates":[6.1483058929,46.223613739],"type":"Point"}
}