{
  "type": "Feature",
  "properties": {
    "iso:country":"CH",
    "sg:address":"Bernstrasse 14",
    "sg:city":"Z\u00e4ziwil",
    "sg:orig_category":"Detailhandel mit Fahrr\u00e4dern Handel mit Motorr\u00e4dern, Teilen U Zubeh\u00f6r Instandhaltung U Reparatur von ",
    "sg:phone":"+41 31 711 10 55",
    "sg:postcode":"3532",
    "sg:province":"Bern",
    "wof:name":"Bieri Ernst, Velo Motos",
    "wof:placetype":"venue"
},
  "geometry": {"coordinates":[7.6584529877,46.902217865],"type":"Point"}
}