{
  "type": "Feature",
  "properties": {
    "iso:country":"CH",
    "sg:address":"Rue Du L\u00e9man 1",
    "sg:city":"Montreux",
    "sg:orig_category":"Sonstiger spezialisierter Hoch U Tiefbau",
    "sg:postcode":"1820",
    "sg:province":"Vaud",
    "wof:name":"Entreprise Robert Et Andr\u00e9 Colombo",
    "wof:placetype":"venue"
},
  "geometry": {"coordinates":[6.891146183,46.4555511475],"type":"Point"}
}