{
  "type": "Feature",
  "properties": {
    "iso:country":"CH",
    "sg:address":"Wiesentalstrasse 105",
    "sg:city":"Chur",
    "sg:orig_category":"Grosshandel mit Obst U Gem\u00fcse",
    "sg:phone":"+41 81 353 41 77",
    "sg:postcode":"7000",
    "sg:province":"Graubunden",
    "wof:name":"Euro-reisen Talesa Giovannina + Mammone Mario",
    "wof:placetype":"venue"
},
  "geometry": {"coordinates":[9.5302505493,46.8635520935],"type":"Point"}
}