{
  "type": "Feature",
  "properties": {
    "iso:country":"CH",
    "sg:address":"Hirzbodenpark 10 4052 Basel. Postfach",
    "sg:city":"Basel",
    "sg:orig_category":"Grosshandel mit medizinischen U orthop\u00e4dischen Artikeln",
    "sg:phone":"+41 61 312 01 39",
    "sg:postcode":"4020",
    "sg:province":"Basel-Stadt",
    "wof:name":"Hans Mohler & Co. Laborbedarf Usw; Handel",
    "wof:placetype":"venue"
},
  "geometry": {"coordinates":[7.6093120575,47.5520515442],"type":"Point"}
}