{
  "type": "Feature",
  "properties": {
    "iso:country":"CH",
    "sg:address":"Brandbachstr. 10",
    "sg:city":"Dietlikon",
    "sg:classifiers":[
        {
            "category":"Manufacturing",
            "subcategory":"Tools & Machinery",
            "type":"Manufacturing & Wholesale Goods"
        }
    ],
    "sg:phone":"+41 4118353711",
    "sg:postcode":"8305",
    "sg:province":"Z\u00fcrich",
    "sg:tags":[
        "equipment",
        "measurement",
        "-",
        "precision",
        "instrument"
    ],
    "wof:name":"Datacolor Ag",
    "wof:placetype":"venue"
},
  "geometry": {"coordinates":[8.6214799881,47.4149093628],"type":"Point"}
}