{
  "type": "Feature",
  "properties": {
    "iso:country":"CH",
    "sg:address":"Alte Steinhauserstrasse 19 6330 Cham. Postfach",
    "sg:city":"Cham",
    "sg:orig_category":"Textilveredlung",
    "sg:phone":"+41 22 343 11 62",
    "sg:postcode":"6330",
    "sg:province":"Zug",
    "wof:name":"Andrey Nicole.",
    "wof:placetype":"venue"
},
  "geometry": {"coordinates":[6.1385560036,46.1879920959],"type":"Point"}
}