{
  "type": "Feature",
  "properties": {
    "iso:country":"CH",
    "sg:address":"R\u00fcttihardstrasse 7",
    "sg:city":"Birsfelden",
    "sg:orig_category":"Herstellung von Teppichen Verlegen von Fussboden",
    "sg:phone":"+41 61 311 70 00",
    "sg:postcode":"4127",
    "sg:province":"Basel-Landschaft",
    "wof:name":"Said Zaabat Teppiche Bodenbel\u00e4ge Parkett",
    "wof:placetype":"venue"
},
  "geometry": {"coordinates":[7.629887104,47.5526809692],"type":"Point"}
}