{
  "type": "Feature",
  "properties": {
    "iso:country":"CH",
    "sg:address":"Ronystrasse 6a",
    "sg:city":"H\u00fcnenberg",
    "sg:orig_category":"Unternehmensberatung",
    "sg:phone":"+41 41 780 52 35",
    "sg:postcode":"6331",
    "sg:province":"Zug",
    "wof:name":"Bs Consulting, Svensson Bo",
    "wof:placetype":"venue"
},
  "geometry": {"coordinates":[8.4248876572,47.1794929504],"type":"Point"}
}