{
  "type": "Feature",
  "properties": {
    "iso:country":"CH",
    "sg:address":"Gewerbehaus Schwarz",
    "sg:city":"Bubikon",
    "sg:orig_category":"Non-Classified Establishments",
    "sg:postcode":"8608",
    "sg:province":"Z\u00fcrich",
    "wof:name":"Berec Design Caprez",
    "wof:placetype":"venue"
},
  "geometry": {"coordinates":[8.8189096451,47.2684555054],"type":"Point"}
}