{
  "type": "Feature",
  "properties": {
    "iso:country":"CH",
    "sg:address":"Route De Gen\u00e8ve 9",
    "sg:city":"Commugny",
    "sg:orig_category":"Tanzschulen, Tanzlehrer",
    "sg:phone":"+41 22 734 66 00",
    "sg:postcode":"1291",
    "sg:province":"Vaud",
    "wof:name":"American Dance Center Ecole De Danse Et De Ballet",
    "wof:placetype":"venue"
},
  "geometry": {"coordinates":[6.1737442017,46.3177337646],"type":"Point"}
}