{
  "type": "Feature",
  "properties": {
    "iso:country":"CH",
    "sg:address":"Gartenstrasse 32",
    "sg:city":"Zuchwil",
    "sg:orig_category":"Grosshandel mit Getreide, Saatgut U Futtermitteln",
    "sg:phone":"+41 32 686 68 68",
    "sg:postcode":"4528",
    "sg:province":"Solothurn",
    "wof:name":"Wyss Samen & Pflanzen Ag",
    "wof:placetype":"venue"
},
  "geometry": {"coordinates":[7.5651760101,47.2067871094],"type":"Point"}
}