{
  "type": "Feature",
  "properties": {
    "iso:country":"CH",
    "sg:address":"Nova Via 12",
    "sg:city":"Domat/ems",
    "sg:orig_category":"RESTAURANTS: TEA-ROOMS",
    "sg:postcode":"7013",
    "sg:province":"Graubunden",
    "wof:name":"Wasescha Robert",
    "wof:placetype":"venue"
},
  "geometry": {"coordinates":[9.4470062256,46.8333053589],"type":"Point"}
}