{
  "type": "Feature",
  "properties": {
    "addr:full":"En Bellanger Givrins Vaud 1271",
    "addr:postcode":"1271",
    "addr:street":"En",
    "iso:country":"CH",
    "sg:address":"En Bellanger",
    "sg:city":"Givrins",
    "sg:orig_category":"Architektur U Ingenieurb\u00fcros",
    "sg:phone":"+41 22 369 10 80",
    "sg:postcode":"1271",
    "sg:province":"Vaud",
    "wof:name":"Kurt P. Cuttat Kbc System Engineering",
    "wof:placetype":"venue"
},
  "geometry": {"coordinates":[6.200972,46.429764],"type":"Point"}
}