{
  "type": "Feature",
  "properties": {
    "addr:full":"Mettlenbachstrasse 27 M\u00f6nchaltorf Z\u00fcrich 8617",
    "addr:housenumber":"27",
    "addr:postcode":"8617",
    "addr:street":"Mettlenbachstrasse;Zuerich",
    "iso:country":"CH",
    "sg:address":"Mettlenbachstrasse 27",
    "sg:city":"M\u00f6nchaltorf",
    "sg:classifiers":[
        {
            "category":"Manufacturing",
            "subcategory":"Tools & Machinery",
            "type":"Manufacturing & Wholesale Goods"
        }
    ],
    "sg:phone":"+41 19481111",
    "sg:postcode":"8617",
    "sg:province":"Z\u00fcrich",
    "sg:tags":[
        "machine",
        "allround",
        "turning",
        "milling",
        "drilling"
    ],
    "wof:name":"Reimmann Ag",
    "wof:placetype":"venue"
},
  "geometry": {"coordinates":[8.722043,47.304455],"type":"Point"}
}