{
  "type": "Feature",
  "properties": {
    "iso:country":"CH",
    "sg:address":"Rue Du Petit-ch\u00e9zard 1",
    "sg:city":"Ch\u00e9zard-st-martin",
    "sg:orig_category":"Altersheime Wohnheime",
    "sg:phone":"+41 38535067",
    "sg:postcode":"2054",
    "sg:province":"Neuch\u00e2tel",
    "wof:name":"Home Du Petit Ch\u00e9zard, Addor Josiane",
    "wof:placetype":"venue"
},
  "geometry": {"coordinates":[6.920727,47.064423],"type":"Point"}
}