{
  "type": "Feature",
  "properties": {
    "iso:country":"CH",
    "sg:address":"Prati Via Ai",
    "sg:city":"Gorduno",
    "sg:orig_category":"Detailhandel mit Schuhen U Lederwaren",
    "sg:postcode":"6518",
    "sg:province":"Ticino",
    "wof:name":"Piller Paolo",
    "wof:placetype":"venue"
},
  "geometry": {"coordinates":[9.0349397659,46.2185401917],"type":"Point"}
}