{
  "type": "Feature",
  "properties": {
    "iso:country":"CH",
    "sg:address":"Rothenburgstrasse 80 6020 Emmenbr\u00fccke. Postfach",
    "sg:city":"Emmenbr\u00fccke",
    "sg:orig_category":"Erbringung von Dienstleistungen f\u00fcr Unternehmen",
    "sg:phone":"+41 41 289 30 60",
    "sg:postcode":"6020",
    "sg:province":"Luzern",
    "wof:name":"Zentrex Ag",
    "wof:placetype":"venue"
},
  "geometry": {"coordinates":[8.2736949921,47.0919418335],"type":"Point"}
}