{
  "type": "Feature",
  "properties": {
    "iso:country":"CH",
    "sg:address":"Sagenmatt 6156 Luthern. Postfach",
    "sg:city":"Luthern",
    "sg:orig_category":"S\u00e4ge, Hobel U Holzimpr\u00e4gnierwerke",
    "sg:phone":"+41 41 970 48 27",
    "sg:postcode":"6156",
    "sg:province":"Luzern",
    "wof:name":"S\u00e4gewerk Christen Ag Luthern",
    "wof:placetype":"venue"
},
  "geometry": {"coordinates":[7.9165320396,47.0619125366],"type":"Point"}
}