{
  "type": "Feature",
  "properties": {
    "iso:country":"CH",
    "sg:address":"Alexander Sch\u00f6ni-strasse 43",
    "sg:city":"Biel/bienne",
    "sg:orig_category":"Architektur U Ingenieurb\u00fcros Architekturb\u00fcros",
    "sg:phone":"+41 32 322 86 84",
    "sg:postcode":"2503",
    "sg:province":"Bern",
    "wof:name":"Mollet Henri Architectes Associ\u00e9s Sa",
    "wof:placetype":"venue"
},
  "geometry": {"coordinates":[7.251213,47.138119],"type":"Point"}
}