{
  "type": "Feature",
  "properties": {
    "iso:country":"CH",
    "sg:address":"Quartier-latin",
    "sg:city":"Saxon",
    "sg:classifiers":[
        {
            "category":"Restaurant",
            "type":"Food & Drink"
        }
    ],
    "sg:phone":"+41 27 744 14 56",
    "sg:postcode":"1907",
    "sg:province":"Valais",
    "wof:name":"Caf\u00e9 Place",
    "wof:placetype":"venue"
},
  "geometry": {"coordinates":[7.1804451942,46.1454315186],"type":"Point"}
}