{
  "type": "Feature",
  "properties": {
    "iso:country":"CH",
    "sg:address":"Chalet Lengmatt.",
    "sg:city":"Kandersteg",
    "sg:orig_category":"Allgemeiner Hoch U Tiefbau",
    "sg:phone":"+41 33 675 17 22",
    "sg:postcode":"3718",
    "sg:province":"Bern",
    "wof:name":"Sommer Emil",
    "wof:placetype":"venue"
},
  "geometry": {"coordinates":[7.673047,46.494984],"type":"Point"}
}