{
  "type": "Feature",
  "properties": {
    "iso:country":"CH",
    "sg:address":"Bahnstrasse 24",
    "sg:city":"Schwerzenbach",
    "sg:orig_category":"Finanzierungsinstitutionen",
    "sg:phone":"+41 848 800 737",
    "sg:postcode":"8603",
    "sg:province":"Z\u00fcrich",
    "wof:name":"Your Property Ag",
    "wof:placetype":"venue"
},
  "geometry": {"coordinates":[8.656211853,47.3864746094],"type":"Point"}
}