{
  "type": "Feature",
  "properties": {
    "iso:country":"CH",
    "sg:address":"Neuhofstrasse 52",
    "sg:city":"Neuheim",
    "sg:orig_category":"Unternehmensberatung",
    "sg:phone":"+41 79 215 67 21",
    "sg:postcode":"6345",
    "sg:province":"Zug",
    "wof:name":"Thurnheer Unternehmungsberatung",
    "wof:placetype":"venue"
},
  "geometry": {"coordinates":[8.5731296539,47.2015647888],"type":"Point"}
}