{
  "type": "Feature",
  "properties": {
    "iso:country":"CH",
    "sg:address":"Hauptstr. 3",
    "sg:city":"Oberentfelden",
    "sg:classifiers":[
        {
            "category":"Travel",
            "subcategory":"Hotels & Motels",
            "type":"Entertainment"
        }
    ],
    "sg:phone":"+41 79 336 31 58",
    "sg:postcode":"5036",
    "sg:province":"Aargau",
    "sg:tags":[
        "hotels",
        "mit",
        "restaurant"
    ],
    "wof:name":"M. Guillod Gasthof Engel",
    "wof:placetype":"venue"
},
  "geometry": {"coordinates":[8.050909996,47.3471794128],"type":"Point"}
}