{
  "type": "Feature",
  "properties": {
    "iso:country":"CH",
    "sg:address":"L\u00f6wengasse 9 4710 Balsthal. Postfach 728",
    "sg:city":"Balsthal",
    "sg:orig_category":"Innenarchitekturb\u00fcros",
    "sg:phone":"+41 62 212 34 89",
    "sg:postcode":"4710",
    "sg:province":"Solothurn",
    "wof:name":"Bernhard Herzog Innenarchitektur Licht Planung",
    "wof:placetype":"venue"
},
  "geometry": {"coordinates":[7.6973757744,47.3166122437],"type":"Point"}
}