{
  "type": "Feature",
  "properties": {
    "iso:country":"CH",
    "sg:address":"Fabrikstrasse 10",
    "sg:city":"Herzogenbuchsee",
    "sg:orig_category":"Detailhandel mit Waren verschiedener Art, Hauptrichtung Nahrungsmittel",
    "sg:phone":"+41 62 961 33 22",
    "sg:postcode":"3360",
    "sg:province":"Bern",
    "wof:name":"Denner Top Superdiscount",
    "wof:placetype":"venue"
},
  "geometry": {"coordinates":[7.7046642303,47.1888618469],"type":"Point"}
}