{
  "type": "Feature",
  "properties": {
    "addr:full":"Chemin David Munier 22a Cologny Gen\u00e8ve 1223",
    "addr:housenumber":"22a",
    "addr:postcode":"1223",
    "addr:street":"Chemin David Munier",
    "iso:country":"CH",
    "sg:address":"Chemin David Munier 22a",
    "sg:city":"Cologny",
    "sg:orig_category":"Architektur U Ingenieurb\u00fcros",
    "sg:postcode":"1223",
    "sg:province":"Gen\u00e8ve",
    "wof:name":"Scientex Sa",
    "wof:placetype":"venue"
},
  "geometry": {"coordinates":[6.18999,46.207699],"type":"Point"}
}