{
  "type": "Feature",
  "properties": {
    "iso:country":"CH",
    "sg:address":"Crapera-damiez",
    "sg:city":"Lenzerheide/lai",
    "sg:orig_category":"Logistikberatung Unternehmensberatung",
    "sg:phone":"+41 81 384 33 59",
    "sg:postcode":"7078",
    "sg:province":"Graubunden",
    "wof:name":"Crapera Management Ag",
    "wof:placetype":"venue"
},
  "geometry": {"coordinates":[9.5643806458,46.7278594971],"type":"Point"}
}