{
  "type": "Feature",
  "properties": {
    "iso:country":"CH",
    "sg:address":"Talweg 116",
    "sg:city":"Uster",
    "sg:orig_category":"Erbringung von Dienstleistungen f\u00fcr Unternehmen",
    "sg:postcode":"8610",
    "sg:province":"Z\u00fcrich",
    "wof:name":"S & R Comline, Beltrame & Partner",
    "wof:placetype":"venue"
},
  "geometry": {"coordinates":[8.7319669724,47.348072052],"type":"Point"}
}