{
  "type": "Feature",
  "properties": {
    "iso:country":"CH",
    "sg:address":"1564",
    "sg:city":"Domdidier",
    "sg:orig_category":"Verwertung von Milch",
    "sg:postcode":"1564",
    "sg:province":"Fribourg",
    "wof:name":"Soci\u00e9t\u00e9 De Laiterie De Domdidier",
    "wof:placetype":"venue"
},
  "geometry": {"coordinates":[7.0151348114,46.8653068542],"type":"Point"}
}