{
  "type": "Feature",
  "properties": {
    "iso:country":"CH",
    "sg:address":"Gummenstrasse 4",
    "sg:city":"Th\u00f6rishaus",
    "sg:orig_category":"Gartenbau",
    "sg:phone":"+41 79 429 70 27",
    "sg:postcode":"3174",
    "sg:province":"Bern",
    "wof:name":"Kurt Streit G\u00e4rtnerei",
    "wof:placetype":"venue"
},
  "geometry": {"coordinates":[7.3477659225,46.8951301575],"type":"Point"}
}