{
  "type": "Feature",
  "properties": {
    "iso:country":"CH",
    "sg:address":"Limmatquai 82",
    "sg:city":"Z\u00fcrich",
    "sg:orig_category":"Detailhandel mit Uhren U Schmuck Reparatur von Uhren U Schmuck",
    "sg:phone":"+41 12525515",
    "sg:postcode":"8001",
    "sg:province":"Z\u00fcrich",
    "wof:name":"Max Affolter Uhren & Bijouterie",
    "wof:placetype":"venue"
},
  "geometry": {"coordinates":[8.5429048538,47.3734931946],"type":"Point"}
}