{
  "type": "Feature",
  "properties": {
    "iso:country":"CH",
    "sg:address":"Rue Du Vieux-moulin 50",
    "sg:city":"Sion",
    "sg:orig_category":"Organisationen der Wohlfahrtspflege",
    "sg:phone":"+41 32 841 19 15",
    "sg:postcode":"1950",
    "sg:province":"Valais",
    "wof:name":"Pro Juventute",
    "wof:placetype":"venue"
},
  "geometry": {"coordinates":[6.8600978851,46.9662590027],"type":"Point"}
}