{
  "type": "Feature",
  "properties": {
    "iso:country":"CH",
    "sg:address":"Chemin Du Bois-gentil 2",
    "sg:city":"Lausanne",
    "sg:orig_category":"Verwaltung der Strafvollzuganstalten Wohnheime",
    "sg:phone":"+41 27 458 43 18",
    "sg:postcode":"1018",
    "sg:province":"Vaud",
    "wof:name":"P\u00e9nitencier De Cr\u00eatelongue",
    "wof:placetype":"venue"
},
  "geometry": {"coordinates":[7.463640213,46.2584381104],"type":"Point"}
}