{
  "type": "Feature",
  "properties": {
    "iso:country":"CH",
    "sg:address":"Stammeraustrasse 8",
    "sg:city":"Frauenfeld",
    "sg:orig_category":"Tierarztpraxis",
    "sg:phone":"+41 52 720 48 48",
    "sg:postcode":"8500",
    "sg:province":"Thurgau",
    "wof:name":"Dr.med.vet.monika Frei Tier\u00e4rztin",
    "wof:placetype":"venue"
},
  "geometry": {"coordinates":[8.8931407928,47.5542488098],"type":"Point"}
}