{
  "type": "Feature",
  "properties": {
    "iso:country":"CH",
    "sg:address":"Herrenackerstrasse 16 8730 Uznach. Postfach",
    "sg:city":"Uznach",
    "sg:orig_category":"Pensionskassen",
    "sg:phone":"+41 79 343 67 12",
    "sg:postcode":"8730",
    "sg:province":"St. Gallen",
    "wof:name":"Personalf\u00fcrsorgestiftung Der Strumpffabrik Flexy Ag.",
    "wof:placetype":"venue"
},
  "geometry": {"coordinates":[9.5697870255,47.3932342529],"type":"Point"}
}