{
  "type": "Feature",
  "properties": {
    "iso:country":"CH",
    "sg:address":"Rennweg 26 2504 Biel/bienne. Postfach",
    "sg:city":"Biel/bienne",
    "sg:orig_category":"Erbringung von sonstigen Dienstleistungen f\u00fcr Unterhaltung, Erholung U Freizeit",
    "sg:phone":"+41 32 345 16 09",
    "sg:postcode":"2502",
    "sg:province":"Bern",
    "wof:name":"Troubleshooter Event Gmbh Events; Planung, Durchf\u00fchrung. Arbeiten In Den Bereichen Infrastruktur, Technik, Support, Bau, Gewerbe Usw",
    "wof:placetype":"venue"
},
  "geometry": {"coordinates":[7.2659702301,47.1444206238],"type":"Point"}
}