{
  "type": "Feature",
  "properties": {
    "iso:country":"CH",
    "sg:address":"Kapellenstrasse 21",
    "sg:city":"Bern",
    "sg:orig_category":"Hardwareberatung",
    "sg:phone":"+41 31 381 48 37",
    "sg:postcode":"3011",
    "sg:province":"Bern",
    "wof:name":"Globasol Gmbh",
    "wof:placetype":"venue"
},
  "geometry": {"coordinates":[7.4344139099,46.9449882507],"type":"Point"}
}