{
  "type": "Feature",
  "properties": {
    "iso:country":"CH",
    "sg:address":"Bahnhofstrasse 44",
    "sg:city":"Chur",
    "sg:orig_category":"Finanzierungsinstitutionen",
    "sg:phone":"+41 81 255 33 77",
    "sg:postcode":"7000",
    "sg:province":"Graubunden",
    "wof:name":"Grisa Trading Gmbh",
    "wof:placetype":"venue"
},
  "geometry": {"coordinates":[9.5317850113,46.8509750366],"type":"Point"}
}