{
  "type": "Feature",
  "properties": {
    "iso:country":"CH",
    "sg:address":"Bienenstrasse 45",
    "sg:city":"Niederuzwil",
    "sg:orig_category":"Sonstige Kurierdienste",
    "sg:phone":"+41 71 950 20 00",
    "sg:postcode":"9244",
    "sg:province":"St. Gallen",
    "wof:name":"Beat Moser Overnight-kurier",
    "wof:placetype":"venue"
},
  "geometry": {"coordinates":[9.1412153244,47.4475440979],"type":"Point"}
}