{
  "type": "Feature",
  "properties": {
    "iso:country":"CH",
    "sg:address":"Ursiacker 11",
    "sg:city":"Gretzenbach",
    "sg:orig_category":"Stukkateurgewerbe, Gipserei U Verputzerei",
    "sg:phone":"+41 62 849 50 37",
    "sg:postcode":"5014",
    "sg:province":"Solothurn",
    "wof:name":"Schenker Gebr. Gipserei",
    "wof:placetype":"venue"
},
  "geometry": {"coordinates":[7.998251915,47.3611106873],"type":"Point"}
}