{
  "type": "Feature",
  "properties": {
    "addr:full":"Grand-rue 71 Chavornay Vaud 1373",
    "addr:housenumber":"71",
    "addr:postcode":"1373",
    "addr:street":"Grand-Rue",
    "iso:country":"CH",
    "sg:address":"Grand-rue 71",
    "sg:city":"Chavornay",
    "sg:orig_category":"Bauschreinerei Zimmerei, Ingenieurholzbau",
    "sg:phone":"+41 24 441 49 47",
    "sg:postcode":"1373",
    "sg:province":"Vaud",
    "wof:name":"Robert Thibaud Menuiserie & Charpente",
    "wof:placetype":"venue"
},
  "geometry": {"coordinates":[6.569374,46.707291],"type":"Point"}
}