{
  "type": "Feature",
  "properties": {
    "iso:country":"CH",
    "sg:address":"Worbstrasse 153 3073 G\u00fcmligen. Postfach",
    "sg:city":"G\u00fcmligen",
    "sg:orig_category":"Zimmerei, Dachdeckerei, Bauspenglerei U Abdichtung",
    "sg:phone":"+41 31 951 81 47",
    "sg:postcode":"3073",
    "sg:province":"Bern",
    "wof:name":"Zaugg Hans",
    "wof:placetype":"venue"
},
  "geometry": {"coordinates":[7.4995670319,46.9351539612],"type":"Point"}
}