{
  "type": "Feature",
  "properties": {
    "iso:country":"CH",
    "sg:address":"Bersnstrasse 24",
    "sg:city":"Flamatt",
    "sg:orig_category":"Allgemeiner Hoch U Tiefbau Allgemeiner Hochbau",
    "sg:phone":"+41 31 741 00 92",
    "sg:postcode":"3175",
    "sg:province":"Fribourg",
    "wof:name":"Costrava Hoch Und Tiefbau Ag",
    "wof:placetype":"venue"
},
  "geometry": {"coordinates":[7.31651,46.890076],"type":"Point"}
}