{
  "type": "Feature",
  "properties": {
    "iso:country":"CH",
    "sg:address":"Bl\u00fcmlisalpstrasse 73",
    "sg:city":"Z\u00fcrich",
    "sg:orig_category":"Interessenvertretungen",
    "sg:phone":"+41 13629859",
    "sg:postcode":"8006",
    "sg:province":"Z\u00fcrich",
    "wof:name":"Haus Raphael",
    "wof:placetype":"venue"
},
  "geometry": {"coordinates":[8.548707962,47.3918762207],"type":"Point"}
}