{
  "type": "Feature",
  "properties": {
    "iso:country":"CH",
    "sg:address":"Hirschweg 8",
    "sg:city":"Grabs",
    "sg:orig_category":"Sportvereine Turnen Damen",
    "sg:phone":"+41 81 771 27 38",
    "sg:postcode":"9472",
    "sg:province":"St. Gallen",
    "wof:name":"Damenriege Grabs",
    "wof:placetype":"venue"
},
  "geometry": {"coordinates":[9.4521341324,47.1710891724],"type":"Point"}
}