{
  "type": "Feature",
  "properties": {
    "iso:country":"CH",
    "sg:address":"Schaffhauserstrasse 439",
    "sg:city":"Z\u00fcrich",
    "sg:orig_category":"Grosshandel mit Nahrungsmitteln, Getr\u00e4nken U Tabakwaren ohne ausgepr\u00e4gten Schwerpunkt",
    "sg:phone":"+41 81 756 04 08",
    "sg:postcode":"8050",
    "sg:province":"Z\u00fcrich",
    "wof:name":"D S Demirovska Bosna Warenmarkt",
    "wof:placetype":"venue"
},
  "geometry": {"coordinates":[9.4827594757,47.1726951599],"type":"Point"}
}