{
  "type": "Feature",
  "properties": {
    "iso:country":"CH",
    "sg:address":"Okenstrasse 4 8037 Z\u00fcrich. Postfach 748",
    "sg:city":"Z\u00fcrich",
    "sg:orig_category":"Hoch U Tiefbau",
    "sg:phone":"+41 81 911 41 71",
    "sg:postcode":"8037",
    "sg:province":"Z\u00fcrich",
    "wof:name":"Z\u00fcger & Flury Ag Baugesch\u00e4ft",
    "wof:placetype":"venue"
},
  "geometry": {"coordinates":[9.3010149002,46.8348617554],"type":"Point"}
}