{
  "type": "Feature",
  "properties": {
    "iso:country":"CH",
    "sg:address":"Giacomettistrasse 16",
    "sg:city":"Bern",
    "sg:orig_category":"Selbst\u00e4ndige bildende K\u00fcnstler",
    "sg:phone":"+41 31 352 40 40",
    "sg:postcode":"3006",
    "sg:province":"Bern",
    "wof:name":"Ursula Koch Atelier F\u00fcr Heraldik",
    "wof:placetype":"venue"
},
  "geometry": {"coordinates":[7.4735012054,46.9453239441],"type":"Point"}
}