{
  "type": "Feature",
  "properties": {
    "iso:country":"CH",
    "sg:address":"Rattenholz",
    "sg:city":"Niedermuhlern",
    "sg:orig_category":"Beherbergungsgewerbe",
    "sg:phone":"+41 31 819 04 38",
    "sg:postcode":"3087",
    "sg:province":"Bern",
    "wof:name":"Wohn Und Ferienheim 'am Waldrand'",
    "wof:placetype":"venue"
},
  "geometry": {"coordinates":[7.459027,46.852261],"type":"Point"}
}