{
  "type": "Feature",
  "properties": {
    "iso:country":"CH",
    "sg:address":"Rue Des Eaux",
    "sg:city":"Tavannes",
    "sg:orig_category":"Einzelhandel mit Automobilteilen U Zubeh\u00f6r Fachdetailhandel in Verkaufsr\u00e4umen",
    "sg:phone":"+41 32 481 48 88",
    "sg:postcode":"2710",
    "sg:province":"Bern",
    "wof:name":"Liechti Marcel Tavanauto",
    "wof:placetype":"venue"
},
  "geometry": {"coordinates":[7.1983699799,47.2192268372],"type":"Point"}
}