{
  "type": "Feature",
  "properties": {
    "addr:full":"Seevorstadt 77 Biel/bienne Bern 2502",
    "addr:housenumber":"77",
    "addr:postcode":"2502",
    "addr:street":"Seevorstadt",
    "iso:country":"CH",
    "sg:address":"Seevorstadt 77",
    "sg:city":"Biel/bienne",
    "sg:classifiers":[
        {
            "category":"Social Services",
            "subcategory":"Retirement Home",
            "type":"Services"
        }
    ],
    "sg:phone":"+41 32 322 73 20",
    "sg:postcode":"2502",
    "sg:province":"Bern",
    "sg:tags":[
        "pflegeheime",
        "u",
        "alters"
    ],
    "wof:name":"Wohnheim Favorita Burgergemeinde Biel",
    "wof:placetype":"venue"
},
  "geometry": {"coordinates":[7.24111,47.139172],"type":"Point"}
}