{
  "type": "Feature",
  "properties": {
    "iso:country":"CH",
    "sg:address":"Birrenstrasse - Schindellegi",
    "sg:city":"Feusisberg",
    "sg:orig_category":"Haltung von Rindern",
    "sg:postcode":"8835",
    "sg:province":"Schwyz",
    "wof:name":"Viehzuchtgenossenschaft Fischbach Oberwil I.s.",
    "wof:placetype":"venue"
},
  "geometry": {"coordinates":[7.4359397888,46.6566810608],"type":"Point"}
}