{
  "type": "Feature",
  "properties": {
    "iso:country":"CH",
    "sg:address":"Laubiweg 8",
    "sg:city":"Z\u00fcrich",
    "sg:orig_category":"Gartenbau",
    "sg:phone":"+41 13618400",
    "sg:postcode":"8057",
    "sg:province":"Z\u00fcrich",
    "wof:name":"Hans-ulrich Weber Gartenarchitekt Thm",
    "wof:placetype":"venue"
},
  "geometry": {"coordinates":[8.5345077515,47.3935127258],"type":"Point"}
}