{
  "type": "Feature",
  "properties": {
    "iso:country":"CH",
    "sg:address":"Rue De La Gare 6 2500 Biel/bienne. Postfach",
    "sg:city":"Biel/bienne",
    "sg:orig_category":"Unclassifiable Establishments",
    "sg:postcode":"2502",
    "sg:province":"Bern",
    "wof:name":"Nugerol Holding Sa, Succursale De Bienne",
    "wof:placetype":"venue"
},
  "geometry": {"coordinates":[7.2437710762,47.1338615417],"type":"Point"}
}