{
  "type": "Feature",
  "properties": {
    "iso:country":"CH",
    "sg:address":"9507",
    "sg:city":"Stettfurt",
    "sg:orig_category":"Vereine Musik/Blasmusik",
    "sg:postcode":"9507",
    "sg:province":"Thurgau",
    "wof:name":"Musikverein Edelweiss",
    "wof:placetype":"venue"
},
  "geometry": {"coordinates":[8.9596796036,47.5253105164],"type":"Point"}
}