{
  "type": "Feature",
  "properties": {
    "iso:country":"CH",
    "sg:address":"Hochstrasse 14",
    "sg:city":"Konolfingen",
    "sg:orig_category":"Allgemeiner Hoch U Tiefbau Strassenbau",
    "sg:phone":"+41 31 771 00 79",
    "sg:postcode":"3510",
    "sg:province":"Bern",
    "wof:name":"Bee-bau Ag",
    "wof:placetype":"venue"
},
  "geometry": {"coordinates":[7.624964,46.886024],"type":"Point"}
}