{
  "type": "Feature",
  "properties": {
    "iso:country":"CH",
    "sg:address":"Binzring 11 8000 Z\u00fcrich. Postfach 8045 Z\u00fcrich",
    "sg:city":"Zust",
    "sg:orig_category":"Non-Classified Establishments",
    "sg:postcode":"45",
    "wof:name":"Transall Transporte Ag",
    "wof:placetype":"venue"
},
  "geometry": {"coordinates":[8.5103883743,47.3606414795],"type":"Point"}
}