{
  "type": "Feature",
  "properties": {
    "iso:country":"CH",
    "sg:address":"Bahnhofstrasse 67",
    "sg:city":"Arbon",
    "sg:orig_category":"Detailhandel mit Schuhen",
    "sg:phone":"+41 71 440 04 05",
    "sg:postcode":"9320",
    "sg:province":"Thurgau",
    "wof:name":"Karl V\u00f6gele Ag",
    "wof:placetype":"venue"
},
  "geometry": {"coordinates":[9.4342069626,47.5073318481],"type":"Point"}
}