{
  "type": "Feature",
  "properties": {
    "iso:country":"CH",
    "sg:address":"Poststrasse 39a",
    "sg:city":"Dietikon",
    "sg:orig_category":"Vereine Geselligkeit",
    "sg:postcode":"8953",
    "sg:province":"Z\u00fcrich",
    "wof:name":"Ass.portugaise De Monthey/env.",
    "wof:placetype":"venue"
},
  "geometry": {"coordinates":[6.9562368393,46.2528686523],"type":"Point"}
}