{
  "type": "Feature",
  "properties": {
    "iso:country":"CH",
    "sg:address":"Rue G\u00e9n\u00e9ral-dufour 4",
    "sg:city":"Biel/bienne",
    "sg:orig_category":"Grosshandel mit Getr\u00e4nken",
    "sg:phone":"+41 32 323 12 40",
    "sg:postcode":"2500",
    "sg:province":"Bern",
    "wof:name":"Vallonio Beniamino",
    "wof:placetype":"venue"
},
  "geometry": {"coordinates":[7.2464981079,47.1391716003],"type":"Point"}
}