{
  "type": "Feature",
  "properties": {
    "iso:country":"CH",
    "sg:address":"Rte Du Creux",
    "sg:city":"Verbier",
    "sg:orig_category":"Unclassifiable Establishments",
    "sg:postcode":"1936",
    "sg:province":"Valais",
    "wof:name":"P\u00d4le Nord Verbier Sarl",
    "wof:placetype":"venue"
},
  "geometry": {"coordinates":[7.2256298065,46.1031341553],"type":"Point"}
}