{
  "type": "Feature",
  "properties": {
    "iso:country":"CH",
    "sg:address":"Pflugg\u00e4sslein 5 4001 Basel. Postfach 917",
    "sg:city":"Basel",
    "sg:orig_category":"P\u00e9dicure",
    "sg:phone":"+41 61 261 41 17",
    "sg:postcode":"4001",
    "sg:province":"Basel-Stadt",
    "wof:name":"Josianne Faesch P\u00e9dicure",
    "wof:placetype":"venue"
},
  "geometry": {"coordinates":[7.589179039,47.5559234619],"type":"Point"}
}