{
  "type": "Feature",
  "properties": {
    "iso:country":"CH",
    "sg:address":"Badhus 1",
    "sg:city":"Grosswangen",
    "sg:orig_category":"Detailhandel mit Getr\u00e4nken Detailhandel mit Sportartikeln",
    "sg:phone":"+41 41 980 19 74",
    "sg:postcode":"6022",
    "sg:province":"Luzern",
    "wof:name":"Ren\u00e9 & Rosmarie Koller Getr\u00e4nke Zelt-& Mietwaren",
    "wof:placetype":"venue"
},
  "geometry": {"coordinates":[8.0426263809,47.1348838806],"type":"Point"}
}