{
  "type": "Feature",
  "properties": {
    "iso:country":"CH",
    "sg:address":"Steinackerstr. 29 Pf 8030",
    "sg:city":"Kloten",
    "sg:classifiers":[
        {
            "category":"Utilities",
            "subcategory":"Electric",
            "type":"Services"
        }
    ],
    "sg:phone":"+41 4118152233",
    "sg:postcode":"8302",
    "sg:province":"Z\u00fcrich",
    "sg:tags":[
        "electricity",
        "electronic",
        "electrical",
        "equipment"
    ],
    "wof:name":"Wisar Wyser + Anliker Ag",
    "wof:placetype":"venue"
},
  "geometry": {"coordinates":[8.5806808472,47.4521408081],"type":"Point"}
}