{
  "type": "Feature",
  "properties": {
    "iso:country":"CH",
    "sg:address":"Chemin De La Mousse 78",
    "sg:city":"Th\u00f4nex",
    "sg:orig_category":"Grosshandel mit Tabakwaren",
    "sg:postcode":"1226",
    "sg:province":"Gen\u00e8ve",
    "wof:name":"Belimex, Belser Ekkehart",
    "wof:placetype":"venue"
},
  "geometry": {"coordinates":[6.2062997818,46.1968765259],"type":"Point"}
}