{
  "type": "Feature",
  "properties": {
    "iso:country":"CH",
    "sg:address":"Rue Du Rh\u00f4ne 30",
    "sg:city":"Gen\u00e8ve",
    "sg:orig_category":"Gesundheitswesen",
    "sg:phone":"+41 22 310 60 59",
    "sg:postcode":"1204",
    "sg:province":"Gen\u00e8ve",
    "wof:name":"Falkon Sa",
    "wof:placetype":"venue"
},
  "geometry": {"coordinates":[6.145966053,46.2044143677],"type":"Point"}
}