{
  "type": "Feature",
  "properties": {
    "iso:country":"CH",
    "sg:address":"Rue Ren\u00e9-louis-piachaud 1",
    "sg:city":"Gen\u00e8ve",
    "sg:orig_category":"Datenverarbeitungsdienste Softwareentwicklung U beratung",
    "sg:phone":"+41 22 311 13 83",
    "sg:postcode":"1204",
    "sg:province":"Gen\u00e8ve",
    "wof:name":"Coprocess Sa",
    "wof:placetype":"venue"
},
  "geometry": {"coordinates":[6.148166,46.199711],"type":"Point"}
}