{
  "type": "Feature",
  "properties": {
    "iso:country":"CH",
    "sg:address":"Industriestrasse 48",
    "sg:city":"Bergdietikon",
    "sg:orig_category":"Herstellung von unbespielten Ton, Bild U Datentr\u00e4gern Vervielf\u00e4ltigung von bespielten Tontr\u00e4gern",
    "sg:phone":"+41 62 209 57 00",
    "sg:postcode":"8962",
    "sg:province":"Aargau",
    "wof:name":"Edel Records (switzerland) Ag",
    "wof:placetype":"venue"
},
  "geometry": {"coordinates":[7.8549938202,47.3366966248],"type":"Point"}
}