{
  "type": "Feature",
  "properties": {
    "iso:country":"CH",
    "sg:address":"Dammstrasse 9",
    "sg:city":"Zug",
    "sg:orig_category":"Personal U Stellenvermittlung Unternehmensberatung",
    "sg:phone":"+41 31 390 13 13",
    "sg:postcode":"6300",
    "sg:province":"Zug",
    "wof:name":"Mercuri Urval Ag Zweigniederlassung Zug",
    "wof:placetype":"venue"
},
  "geometry": {"coordinates":[8.5143356323,47.1740036011],"type":"Point"}
}