{
  "type": "Feature",
  "properties": {
    "addr:full":"Route De Ch\u00eane 53 Gen\u00e8ve Gen\u00e8ve 1208",
    "addr:housenumber":"53",
    "addr:postcode":"1208",
    "addr:street":"Route De Che\u0302Ne",
    "iso:country":"CH",
    "sg:address":"Route De Ch\u00eane 53",
    "sg:city":"Gen\u00e8ve",
    "sg:orig_category":"Architektur U Ingenieurb\u00fcros Architekturb\u00fcros",
    "sg:phone":"+41 22 786 22 66",
    "sg:postcode":"1208",
    "sg:province":"Gen\u00e8ve",
    "wof:name":"Velebit & Architectes Associ\u00e9s Sa",
    "wof:placetype":"venue"
},
  "geometry": {"coordinates":[6.173026,46.200027],"type":"Point"}
}