{
  "type": "Feature",
  "properties": {
    "addr:full":"Hauptstrasse 10 Leuggern Aargau 5316",
    "addr:housenumber":"10",
    "addr:postcode":"5316",
    "addr:street":"Hauptstrasse",
    "iso:country":"CH",
    "sg:address":"Hauptstrasse 10",
    "sg:city":"Leuggern",
    "sg:classifiers":[
        {
            "category":"Banks & Credit Unions",
            "subcategory":"Investment Brokerage",
            "type":"Services"
        }
    ],
    "sg:phone":"+41 56 268 63 00",
    "sg:postcode":"5316",
    "sg:province":"Aargau",
    "sg:tags":[
        "grinder",
        "cutter"
    ],
    "wof:name":"S. Dietsche Ag",
    "wof:placetype":"venue"
},
  "geometry": {"coordinates":[8.218372,47.579166],"type":"Point"}
}