{
  "type": "Feature",
  "properties": {
    "iso:country":"CH",
    "sg:address":"Sunnmatt 9 6390 Engelberg. Postfach",
    "sg:city":"Engelberg",
    "sg:orig_category":"Rechtsberatung",
    "sg:phone":"+41 41 637 14 61",
    "sg:postcode":"6390",
    "sg:province":"Obwalden",
    "wof:name":"Geotech-lizenz Ag",
    "wof:placetype":"venue"
},
  "geometry": {"coordinates":[8.4043922424,46.8209877014],"type":"Point"}
}