{
  "type": "Feature",
  "properties": {
    "iso:country":"CH",
    "sg:address":"Rheinstrasse 11",
    "sg:city":"Frauenfeld",
    "sg:classifiers":[
        {
            "category":"Professional",
            "subcategory":"Employment Agencies",
            "type":"Services"
        }
    ],
    "sg:phone":"+41 52 720 57 20",
    "sg:postcode":"8500",
    "sg:province":"Thurgau",
    "sg:tags":[
        "personal",
        "u",
        "stellenvermittlung"
    ],
    "wof:name":"B & L Personaltreuhand Gmbh",
    "wof:placetype":"venue"
},
  "geometry": {"coordinates":[8.8955364227,47.5561943054],"type":"Point"}
}