{
  "type": "Feature",
  "properties": {
    "iso:country":"CH",
    "sg:address":"Les P\u00e2quiers M2",
    "sg:city":"Chavornay",
    "sg:orig_category":"Fischzucht, Teichwirtschaft",
    "sg:phone":"+41 24 441 83 91",
    "sg:postcode":"1373",
    "sg:province":"Vaud",
    "wof:name":"Percitech Sa Aquaculture",
    "wof:placetype":"venue"
},
  "geometry": {"coordinates":[6.5702109337,46.7084541321],"type":"Point"}
}