{
  "type": "Feature",
  "properties": {
    "iso:country":"CH",
    "sg:address":"Winterthurerstrasse 467 8051 Z\u00fcrich. Postfach 322",
    "sg:city":"Z\u00fcrich",
    "sg:orig_category":"Geb\u00e4ude, Wohnungsreinigung",
    "sg:phone":"+41 18654003",
    "sg:postcode":"8051",
    "sg:province":"Z\u00fcrich",
    "wof:name":"Albert Betschart Glas-& Geb\u00e4udereinigung",
    "wof:placetype":"venue"
},
  "geometry": {"coordinates":[8.5686712265,47.4040489197],"type":"Point"}
}