{
  "type": "Feature",
  "properties": {
    "iso:country":"CH",
    "sg:address":"Stockhornstrasse 40",
    "sg:city":"Toffen",
    "sg:orig_category":"Mit Sport verbundene T\u00e4tigkeiten",
    "sg:phone":"+41 31 819 43 06",
    "sg:postcode":"3125",
    "sg:province":"Bern",
    "wof:name":"Reithalle Toffen Inh.f.bommes",
    "wof:placetype":"venue"
},
  "geometry": {"coordinates":[7.4932951927,46.8552284241],"type":"Point"}
}