{
  "type": "Feature",
  "properties": {
    "iso:country":"CH",
    "sg:address":"Rue Du Picholin 5",
    "sg:city":"Vouvry",
    "sg:orig_category":"Vermietung U Verpachtung von eigenen Immobilien",
    "sg:postcode":"1896",
    "sg:province":"Valais",
    "wof:name":"Sinigaglia Marino",
    "wof:placetype":"venue"
},
  "geometry": {"coordinates":[6.8890790939,46.3364486694],"type":"Point"}
}