{
  "type": "Feature",
  "properties": {
    "iso:country":"CH",
    "sg:address":"Willigen 3860 Meiringen. Postfach 259",
    "sg:city":"Meiringen",
    "sg:orig_category":"Elektrizit\u00e4tsversorgung",
    "sg:phone":"+41 33 971 61 00",
    "sg:postcode":"3860",
    "sg:province":"Bern",
    "wof:name":"Ewr Energie Ag",
    "wof:placetype":"venue"
},
  "geometry": {"coordinates":[8.186214447,46.7278556824],"type":"Point"}
}