{
  "type": "Feature",
  "properties": {
    "iso:country":"CH",
    "sg:address":"Rte Du Lac 40 1820 Montreux. Postfach",
    "sg:city":"Clarens",
    "sg:orig_category":"Vermietung von Gebrauchsg\u00fctern",
    "sg:postcode":"1815",
    "sg:province":"Vaud",
    "wof:name":"Vid\u00e9o V\u00e9nus, Philippe Abate",
    "wof:placetype":"venue"
},
  "geometry": {"coordinates":[6.9017748833,46.4410400391],"type":"Point"}
}