{
  "type": "Feature",
  "properties": {
    "iso:country":"CH",
    "sg:address":"Schulstrasse 73",
    "sg:city":"Landquart",
    "sg:orig_category":"Detailhandel mit elektrischen Haushalts-,Radio U Fernsehger\u00e4ten sowie Musikinstrumenten K\u00fcnstlerisch",
    "sg:phone":"+41 81 322 99 06",
    "sg:postcode":"7302",
    "sg:province":"Graubunden",
    "wof:name":"Bp Beivi Music & Percussion Schlagzeugschule",
    "wof:placetype":"venue"
},
  "geometry": {"coordinates":[9.5621013641,46.9594306946],"type":"Point"}
}