{
  "type": "Feature",
  "properties": {
    "iso:country":"CH",
    "sg:address":"M\u00fchlegutstrasse 22 9403 Goldach. Postfach",
    "sg:city":"Goldach",
    "sg:orig_category":"Aktivit\u00e4ten der Krankenschwestern U Hebammen, Hauspflege Organisationen des Gesundheitswesen",
    "sg:phone":"+41 79 216 31 67",
    "sg:postcode":"9403",
    "sg:province":"St. Gallen",
    "wof:name":"Spitex-zentrum M\u00fchlegut Gemeindekrankenpflege",
    "wof:placetype":"venue"
},
  "geometry": {"coordinates":[9.463704,47.475731],"type":"Point"}
}