{
  "type": "Feature",
  "properties": {
    "iso:country":"CH",
    "sg:address":"Kirchlindachstrasse 2",
    "sg:city":"Zollikofen",
    "sg:orig_category":"Grosshandel mit Getr\u00e4nken",
    "sg:phone":"+41 31 911 10 61",
    "sg:postcode":"3052",
    "sg:province":"Bern",
    "wof:name":"Gmp Global Millenium Products B\u00fchlmann",
    "wof:placetype":"venue"
},
  "geometry": {"coordinates":[7.4611039162,47.0001449585],"type":"Point"}
}