{
  "type": "Feature",
  "properties": {
    "iso:country":"CH",
    "sg:address":"G\u00e9n\u00e9ral-guisan Avenue 44",
    "sg:city":"Pully",
    "sg:orig_category":"Finanzierungsinstitutionen",
    "sg:phone":"+41 21 721 01 31",
    "sg:postcode":"1009",
    "sg:province":"Vaud",
    "wof:name":"Igi Investissement Et Gestion Sa",
    "wof:placetype":"venue"
},
  "geometry": {"coordinates":[6.6492700577,46.5065956116],"type":"Point"}
}