{
  "type": "Feature",
  "properties": {
    "addr:full":"Schlattstrasse 22 Herrliberg Z\u00fcrich 8704",
    "addr:housenumber":"22",
    "addr:postcode":"8704",
    "addr:street":"Schlattstrasse",
    "iso:country":"CH",
    "sg:address":"Schlattstrasse 22",
    "sg:city":"Herrliberg",
    "sg:orig_category":"Allgemeiner Hoch U Tiefbau Hoch U Tiefbau",
    "sg:phone":"+41 19151981",
    "sg:postcode":"8704",
    "sg:province":"Z\u00fcrich",
    "wof:name":"Bauunternehmung Christian Barth",
    "wof:placetype":"venue"
},
  "geometry": {"coordinates":[8.622363,47.28746],"type":"Point"}
}