{
  "type": "Feature",
  "properties": {
    "iso:country":"CH",
    "sg:address":"Talstrasse 5",
    "sg:city":"Zollikon",
    "sg:orig_category":"Informatikdienste",
    "sg:phone":"+41 13820467",
    "sg:postcode":"8702",
    "sg:province":"Z\u00fcrich",
    "wof:name":"Menet Webdesign",
    "wof:placetype":"venue"
},
  "geometry": {"coordinates":[8.5854215622,47.3517799377],"type":"Point"}
}