{
  "type": "Feature",
  "properties": {
    "iso:country":"CH",
    "sg:address":"H\u00e4bernbadstrasse",
    "sg:city":"Huttwil",
    "sg:orig_category":"Diskotheken, Dancings, Night Clubs",
    "sg:phone":"+41 62 962 17 71",
    "sg:postcode":"4950",
    "sg:province":"Bern",
    "wof:name":"Pizzeria H\u00e4bernbad & Disco Pub",
    "wof:placetype":"venue"
},
  "geometry": {"coordinates":[7.8286018372,47.1169815063],"type":"Point"}
}