{
  "type": "Feature",
  "properties": {
    "iso:country":"CH",
    "sg:address":"Salvatorenstrasse 82",
    "sg:city":"Chur",
    "sg:orig_category":"G\u00fcterbef\u00f6rderung im Strassenverkehr",
    "sg:phone":"+41 81 252 04 22",
    "sg:postcode":"7000",
    "sg:province":"Graubunden",
    "wof:name":"Transport-union",
    "wof:placetype":"venue"
},
  "geometry": {"coordinates":[9.5163621902,46.8502807617],"type":"Point"}
}