{
  "type": "Feature",
  "properties": {
    "iso:country":"CH",
    "sg:address":"Stade Rue Du 16",
    "sg:city":"Sion",
    "sg:orig_category":"Vermietung U Verpachtung von eigenen Immobilien",
    "sg:phone":"+41 27 203 23 63",
    "sg:postcode":"1950",
    "sg:province":"Valais",
    "wof:name":"St\u00e9g\u00e9fr\u00e9dar Sa",
    "wof:placetype":"venue"
},
  "geometry": {"coordinates":[7.3588571548,46.2280921936],"type":"Point"}
}