{
  "type": "Feature",
  "properties": {
    "iso:country":"CH",
    "sg:address":"St\u00f6cklimattweg 4",
    "sg:city":"Muhen",
    "sg:orig_category":"G\u00fcterbef\u00f6rderung im Strassenverkehr",
    "sg:phone":"+41 77475255",
    "sg:postcode":"5037",
    "sg:province":"Aargau",
    "wof:name":"Max Burgherr M\u00f6beltransporte",
    "wof:placetype":"venue"
},
  "geometry": {"coordinates":[8.0569114685,47.3292045593],"type":"Point"}
}