{
  "type": "Feature",
  "properties": {
    "iso:country":"CH",
    "sg:address":"Niesenweg 32",
    "sg:city":"M\u00fcnsingen",
    "sg:orig_category":"Elektroinstallation Herstellung von sonstigen elektrischen Ausr\u00fcstungen",
    "sg:postcode":"3110",
    "sg:province":"Bern",
    "wof:name":"Ciro Gmbh",
    "wof:placetype":"venue"
},
  "geometry": {"coordinates":[7.556634903,46.8704681396],"type":"Point"}
}