{
  "type": "Feature",
  "properties": {
    "iso:country":"CH",
    "sg:address":"Monts Route Des",
    "sg:city":"Blonay",
    "sg:orig_category":"Unternehmensberatung",
    "sg:phone":"+41 19323838",
    "sg:postcode":"1807",
    "sg:province":"Vaud",
    "wof:name":"Hagmayer & Partner Unternehmensberatung",
    "wof:placetype":"venue"
},
  "geometry": {"coordinates":[8.7892742157,47.3072013855],"type":"Point"}
}