{
  "type": "Feature",
  "properties": {
    "iso:country":"CH",
    "sg:address":"Mercerie Rue 9 1003 Lausanne. Postfach",
    "sg:city":"Lausanne",
    "sg:orig_category":"RESTAURANTS: TEA-ROOMS",
    "sg:postcode":"1003",
    "sg:province":"Vaud",
    "wof:name":"Pascal Corine. Caf\u00e9-restaurant Sans Alcool Et Cr\u00eaperie La Chandeleur.",
    "wof:placetype":"venue"
},
  "geometry": {"coordinates":[6.6350111961,46.5217056274],"type":"Point"}
}