{
  "type": "Feature",
  "properties": {
    "iso:country":"CH",
    "sg:address":"Rennweg 39",
    "sg:city":"W\u00fcrenlingen",
    "sg:orig_category":"Physiotherapie",
    "sg:phone":"+41 56 281 21 89",
    "sg:postcode":"5303",
    "sg:province":"Aargau",
    "wof:name":"Willie J. Van Stiphout Physiotherapie",
    "wof:placetype":"venue"
},
  "geometry": {"coordinates":[8.258058548,47.5353240967],"type":"Point"}
}