{
  "type": "Feature",
  "properties": {
    "iso:country":"CH",
    "sg:address":"Br\u00e4nngarten 196",
    "sg:city":"Effingen",
    "sg:orig_category":"Rebbau",
    "sg:phone":"+41 62 876 10 75",
    "sg:postcode":"5078",
    "sg:province":"Aargau",
    "wof:name":"Willy B\u00fcchli Weinbau",
    "wof:placetype":"venue"
},
  "geometry": {"coordinates":[8.1039733887,47.4887199402],"type":"Point"}
}