{
  "type": "Feature",
  "properties": {
    "iso:country":"CH",
    "sg:address":"Schwerzelbodenstrasse 41",
    "sg:city":"Dietlikon",
    "sg:orig_category":"Alters U Pflegeheime Institutionen f\u00fcr Behinderte",
    "sg:phone":"+41 18057272",
    "sg:postcode":"8305",
    "sg:province":"Z\u00fcrich",
    "wof:name":"Krankenheim Im Rotacher",
    "wof:placetype":"venue"
},
  "geometry": {"coordinates":[8.612273,47.421169],"type":"Point"}
}