{
  "type": "Feature",
  "properties": {
    "iso:country":"CH",
    "sg:address":"S\u00e4ndli",
    "sg:city":"Unterwasser",
    "sg:orig_category":"Bauspenglerei Sanit\u00e4rinstallation",
    "sg:phone":"+41 71 999 12 60",
    "sg:postcode":"9657",
    "sg:province":"St. Gallen",
    "wof:name":"Heinz Br\u00fcgger Sanit\u00e4re Anlagen & Spenglerei",
    "wof:placetype":"venue"
},
  "geometry": {"coordinates":[9.304125,47.198673],"type":"Point"}
}