{
  "type": "Feature",
  "properties": {
    "iso:country":"CH",
    "sg:address":"Termenweg 75",
    "sg:city":"Brig",
    "sg:orig_category":"Kauf U Verkauf von Immobilien auf eigene Rechnung",
    "sg:postcode":"3900",
    "sg:province":"Valais",
    "wof:name":"Schneller Paul, Vermietung Und Verwaltung Von Liegenschaften Sowie Technische Beratungen",
    "wof:placetype":"venue"
},
  "geometry": {"coordinates":[7.997551918,46.3169288635],"type":"Point"}
}