{
  "type": "Feature",
  "properties": {
    "iso:country":"CH",
    "sg:address":"3453",
    "sg:city":"Heimisbach",
    "sg:orig_category":"Landw. Genossenschaften Viehzucht",
    "sg:phone":"+41 34 431 21 87",
    "sg:postcode":"3453",
    "sg:province":"Bern",
    "wof:name":"Viehzuchtgenossenschaft",
    "wof:placetype":"venue"
},
  "geometry": {"coordinates":[7.760310173,47.0117492676],"type":"Point"}
}