{
  "type": "Feature",
  "properties": {
    "iso:country":"CH",
    "sg:address":"Weissenb\u00fchlweg 36",
    "sg:city":"Bern",
    "sg:orig_category":"Detailhandel mit Brot, Back U S\u00fcsswaren",
    "sg:postcode":"3007",
    "sg:province":"Bern",
    "wof:name":"Hans Rudolf W\u00fcthrich B\u00e4ckerei-konditorei.",
    "wof:placetype":"venue"
},
  "geometry": {"coordinates":[7.436126,46.937038],"type":"Point"}
}