{
  "type": "Feature",
  "properties": {
    "iso:country":"CH",
    "sg:address":"Route Des Artisans",
    "sg:city":"Ch\u00e2tel-st-denis",
    "sg:orig_category":"Sanit\u00e4r, Heizungs U L\u00fcftungsinstallation Sanit\u00e4rinstallation",
    "sg:phone":"+41 71 385 08 40",
    "sg:postcode":"1618",
    "sg:province":"Fribourg",
    "wof:name":"Rs Geb\u00e4udetechnik Ag",
    "wof:placetype":"venue"
},
  "geometry": {"coordinates":[9.2615814209,47.4168663025],"type":"Point"}
}