{
  "type": "Feature",
  "properties": {
    "iso:country":"CH",
    "sg:address":"Rte De Sion 24",
    "sg:city":"Sierre",
    "sg:orig_category":"RESTAURANTS: TEA-ROOMS",
    "sg:postcode":"3960",
    "sg:province":"Valais",
    "wof:name":"Sansonnens-gillioz Mme Andr\u00e9e",
    "wof:placetype":"venue"
},
  "geometry": {"coordinates":[7.5241880417,46.2896118164],"type":"Point"}
}