{
  "type": "Feature",
  "properties": {
    "iso:country":"CH",
    "sg:address":"Madretschstrasse 108 2503 Biel/bienne. Postfach",
    "sg:city":"Biel/bienne",
    "sg:orig_category":"Herstellung von Duft U K\u00f6rperpflegemitteln",
    "sg:postcode":"2503",
    "sg:province":"Bern",
    "wof:name":"Cannizzo G.",
    "wof:placetype":"venue"
},
  "geometry": {"coordinates":[7.2573571205,47.1358070374],"type":"Point"}
}