{
  "type": "Feature",
  "properties": {
    "iso:country":"CH",
    "sg:address":"Avenue De La Plantaud 14",
    "sg:city":"Monthey",
    "sg:orig_category":"Hochschulen U h\u00f6here Ausbildung",
    "sg:postcode":"1870",
    "sg:province":"Valais",
    "wof:name":"Securetude G\u00e9rald Sellie",
    "wof:placetype":"venue"
},
  "geometry": {"coordinates":[6.9511351585,46.2508544922],"type":"Point"}
}