{
  "type": "Feature",
  "properties": {
    "iso:country":"CH",
    "sg:address":"Oberhofenstrasse 3",
    "sg:city":"Sirnach",
    "sg:orig_category":"Organisationen des Gesundheitswesen",
    "sg:phone":"+41 27 973 33 66",
    "sg:postcode":"8370",
    "sg:province":"Thurgau",
    "wof:name":"Samariterverein M\u00fcnster",
    "wof:placetype":"venue"
},
  "geometry": {"coordinates":[8.2618379593,46.4867591858],"type":"Point"}
}