{
  "type": "Feature",
  "properties": {
    "iso:country":"CH",
    "sg:address":"Luzernerstrasse 4",
    "sg:city":"Kriens",
    "sg:orig_category":"Detailhandel mit Fleisch U Fleischwaren",
    "sg:phone":"+41 41 320 44 52",
    "sg:postcode":"6010",
    "sg:province":"Luzern",
    "wof:name":"Keller Fritz",
    "wof:placetype":"venue"
},
  "geometry": {"coordinates":[8.2782697678,47.0336532593],"type":"Point"}
}