{
  "type": "Feature",
  "properties": {
    "iso:country":"CH",
    "sg:address":"Route Du Jura 29 1700 Freiburg. Postfach",
    "sg:city":"Fribourg",
    "sg:orig_category":"Finanzierungsinstitutionen",
    "sg:postcode":"1702",
    "sg:province":"Fribourg",
    "wof:name":"Allfingest-phaceia Sa",
    "wof:placetype":"venue"
},
  "geometry": {"coordinates":[7.1498708725,46.8094062805],"type":"Point"}
}