{
  "type": "Feature",
  "properties": {
    "iso:country":"CH",
    "sg:address":"Wehntalerstr. 39",
    "sg:city":"H\u00f6ri",
    "sg:orig_category":"Detailhandel mit M\u00f6beln U Haushaltsgegenst\u00e4nden",
    "sg:phone":"+41 18609059",
    "sg:postcode":"8181",
    "sg:province":"Z\u00fcrich",
    "wof:name":"M\u00f6bel Maag",
    "wof:placetype":"venue"
},
  "geometry": {"coordinates":[8.5085802078,47.5073013306],"type":"Point"}
}