{
  "type": "Feature",
  "properties": {
    "iso:country":"CH",
    "sg:address":"Hotzestrasse 29",
    "sg:city":"Z\u00fcrich",
    "sg:orig_category":"Vermittlungen Wohnungs-Agenturen,",
    "sg:phone":"+41 13506040",
    "sg:postcode":"8006",
    "sg:province":"Z\u00fcrich",
    "wof:name":"Wohnung + Haus Meyer Monika",
    "wof:placetype":"venue"
},
  "geometry": {"coordinates":[8.540845871,47.3906173706],"type":"Point"}
}