{
  "type": "Feature",
  "properties": {
    "iso:country":"CH",
    "sg:address":"Balestra Via 22b 6900 Lugano. Postfach",
    "sg:city":"Lugano",
    "sg:orig_category":"Herstellung von sonstigen Maschinen f\u00fcr bestimmte Verwendung",
    "sg:phone":"+41 71 911 87 32",
    "sg:postcode":"6900",
    "sg:province":"Ticino",
    "wof:name":"Terranera Ag",
    "wof:placetype":"venue"
},
  "geometry": {"coordinates":[9.0449714661,47.4638404846],"type":"Point"}
}