{
  "type": "Feature",
  "properties": {
    "iso:country":"CH",
    "sg:address":"6694 Prato-sornico. Postfach",
    "sg:city":"Prato-sornico",
    "sg:orig_category":"Maler U Glasergewerbe",
    "sg:postcode":"6694",
    "sg:province":"Ticino",
    "wof:name":"Foresti Fernando",
    "wof:placetype":"venue"
},
  "geometry": {"coordinates":[8.6546068192,46.395690918],"type":"Point"}
}