{
  "type": "Feature",
  "properties": {
    "iso:country":"CH",
    "sg:address":"Gotthardstrasse",
    "sg:city":"Schattdorf",
    "sg:orig_category":"Chemische Industrie",
    "sg:phone":"+41 41871166",
    "sg:postcode":"6467",
    "sg:province":"Uri",
    "wof:name":"Coop Tankstelle",
    "wof:placetype":"venue"
},
  "geometry": {"coordinates":[8.645114,46.844105],"type":"Point"}
}