{
  "type": "Feature",
  "properties": {
    "iso:country":"CH",
    "sg:address":"Route De Sion 39",
    "sg:city":"Sierre",
    "sg:classifiers":[
        {
            "category":"Professional",
            "subcategory":"Employment Agencies",
            "type":"Services"
        }
    ],
    "sg:phone":"+41 27 456 93 03",
    "sg:postcode":"3960",
    "sg:province":"Valais",
    "sg:tags":[
        "personal",
        "u",
        "stellenvermittlung"
    ],
    "wof:name":"Adecco Ressources Humaines Sa",
    "wof:placetype":"venue"
},
  "geometry": {"coordinates":[7.5244679451,46.2894325256],"type":"Point"}
}