{
  "type": "Feature",
  "properties": {
    "iso:country":"CH",
    "sg:address":"Grossholzstrasse",
    "sg:city":"Diessenhofen",
    "sg:orig_category":"Pensionskassen",
    "sg:phone":"+41 52 646 04 40",
    "sg:postcode":"8253",
    "sg:province":"Thurgau",
    "wof:name":"Personalf\u00fcrsorgestiftung Der Firma Veith Ag.",
    "wof:placetype":"venue"
},
  "geometry": {"coordinates":[8.7569541931,47.683429718],"type":"Point"}
}