{
  "type": "Feature",
  "properties": {
    "iso:country":"CH",
    "sg:address":"Niederfeldweg 25",
    "sg:city":"Niederbipp",
    "sg:orig_category":"Elektroinstallation",
    "sg:phone":"+41 33 676 86 86",
    "sg:postcode":"4704",
    "sg:province":"Bern",
    "wof:name":"Aellig Jonathan, Elektroinstallationen",
    "wof:placetype":"venue"
},
  "geometry": {"coordinates":[7.6810369492,46.6101570129],"type":"Point"}
}