{
  "type": "Feature",
  "properties": {
    "iso:country":"CH",
    "sg:address":"Boulevard Carl-vogt 35",
    "sg:city":"Gen\u00e8ve",
    "sg:classifiers":[
        {
            "category":"Restaurant",
            "type":"Food & Drink"
        }
    ],
    "sg:phone":"+41 22 321 31 00",
    "sg:postcode":"1205",
    "sg:province":"Gen\u00e8ve",
    "wof:name":"Trattoria Pirandello",
    "wof:placetype":"venue"
},
  "geometry": {"coordinates":[6.1333999634,46.19947052],"type":"Point"}
}