{
  "type": "Feature",
  "properties": {
    "iso:country":"CH",
    "sg:address":"Dorf",
    "sg:city":"Wyssachen",
    "sg:classifiers":[
        {
            "category":"Banks & Credit Unions",
            "subcategory":"Bank",
            "type":"Services"
        }
    ],
    "sg:phone":"+41 62 844 35 15",
    "sg:postcode":"4954",
    "sg:province":"Bern",
    "wof:name":"Esparniskasse Erlinsbach",
    "wof:placetype":"venue"
},
  "geometry": {"coordinates":[7.99957,47.412319],"type":"Point"}
}