{
  "type": "Feature",
  "properties": {
    "iso:country":"CH",
    "sg:address":"3981",
    "sg:city":"Obergesteln",
    "sg:orig_category":"Detailhandel mit Waren verschiedener Art, Hauptrichtung Nahrungsmittel Grosshandel mit Nahrungsmitte",
    "sg:phone":"+41 27 973 11 54",
    "sg:postcode":"3981",
    "wof:name":"Imwinkelried Geschwister.",
    "wof:placetype":"venue"
},
  "geometry": {"coordinates":[8.324174881,46.5138473511],"type":"Point"}
}