{
  "type": "Feature",
  "properties": {
    "iso:country":"CH",
    "sg:address":"Winterthurerstrasse 48",
    "sg:city":"Uster",
    "sg:orig_category":"Elektro- and elektronische Maschinen Grosshandel",
    "sg:phone":"+41 19416266",
    "sg:postcode":"8610",
    "sg:province":"Z\u00fcrich",
    "wof:name":"Sigrist H. & Partner Ag Automatisierung&dosiertechnik",
    "wof:placetype":"venue"
},
  "geometry": {"coordinates":[8.711889267,47.3579101562],"type":"Point"}
}