{
  "type": "Feature",
  "properties": {
    "iso:country":"CH",
    "sg:address":"Ackersteinstrasse 116 8049 Z\u00fcrich. Postfach",
    "sg:city":"Z\u00fcrich",
    "sg:orig_category":"Druck ohne Zeitungsdruck",
    "sg:postcode":"8049",
    "sg:province":"Z\u00fcrich",
    "wof:name":"Druckerei Perfect + Atar Ag",
    "wof:placetype":"venue"
},
  "geometry": {"coordinates":[8.5057916641,47.3977203369],"type":"Point"}
}