{
  "type": "Feature",
  "properties": {
    "iso:country":"CH",
    "sg:address":"Holeeholzweg 19",
    "sg:city":"Binningen",
    "sg:orig_category":"Unternehmensberatung",
    "sg:postcode":"4102",
    "sg:province":"Basel-Landschaft",
    "wof:name":"Con-concept Gmbh",
    "wof:placetype":"venue"
},
  "geometry": {"coordinates":[7.5558700562,47.5417442322],"type":"Point"}
}