{
  "type": "Feature",
  "properties": {
    "iso:country":"CH",
    "sg:address":"Dorfstrasse 49",
    "sg:city":"Ersigen",
    "sg:orig_category":"Herstellung von \u00d6fen U Brennern Verlegen von Fliesen U Platten",
    "sg:postcode":"3423",
    "sg:province":"Bern",
    "wof:name":"Roland Zurfl\u00fch",
    "wof:placetype":"venue"
},
  "geometry": {"coordinates":[7.5959978104,47.0951423645],"type":"Point"}
}