{
  "type": "Feature",
  "properties": {
    "iso:country":"CH",
    "sg:address":"Monbijoustrasse 24",
    "sg:city":"Bern",
    "sg:orig_category":"Chiropraktik",
    "sg:phone":"+41 31 381 08 44",
    "sg:postcode":"3011",
    "sg:province":"Bern",
    "wof:name":"Arthur Hess Chiropraktor",
    "wof:placetype":"venue"
},
  "geometry": {"coordinates":[7.435907,46.944183],"type":"Point"}
}