{
  "type": "Feature",
  "properties": {
    "iso:country":"CH",
    "sg:address":"Morgenstrasse 121 3018 Bern. Postfach 753",
    "sg:city":"Bern",
    "sg:orig_category":"Grosshandel mit B\u00fcromaschinen Grosshandel mit Datenverarbeitungsger\u00e4ten",
    "sg:phone":"+41 32 922 62 36",
    "sg:postcode":"3018",
    "sg:province":"Bern",
    "wof:name":"Tsd - Technical System Development",
    "wof:placetype":"venue"
},
  "geometry": {"coordinates":[6.8203921318,47.0923194885],"type":"Point"}
}