{
  "type": "Feature",
  "properties": {
    "iso:country":"CH",
    "sg:address":"Hauptstrasse 145",
    "sg:city":"Au",
    "sg:classifiers":[
        {
            "category":"Manufacturing",
            "subcategory":"Printing",
            "type":"Manufacturing & Wholesale Goods"
        }
    ],
    "sg:phone":"+41 71 740 08 29",
    "sg:postcode":"9434",
    "sg:province":"St. Gallen",
    "sg:tags":[
        "house",
        "book"
    ],
    "wof:name":"C-type Gmbh",
    "wof:placetype":"venue"
},
  "geometry": {"coordinates":[9.63594,47.42617],"type":"Point"}
}