{
  "type": "Feature",
  "properties": {
    "iso:country":"CH",
    "sg:address":"Chemin Du Raffort",
    "sg:city":"Romanel-s-lausanne",
    "sg:orig_category":"Grosshandel mit elektrischen Haushaltsger\u00e4ten Maschinen and Apparate divers Grosshandel",
    "sg:phone":"+41 21 731 92 10",
    "sg:postcode":"1032",
    "sg:province":"Vaud",
    "wof:name":"Fcc Food Equipment Sa",
    "wof:placetype":"venue"
},
  "geometry": {"coordinates":[6.6062550545,46.568069458],"type":"Point"}
}