{
  "type": "Feature",
  "properties": {
    "addr:full":"Klotenerstrasse 76 Bassersdorf Z\u00fcrich 8303",
    "addr:housenumber":"76",
    "addr:postcode":"8303",
    "addr:street":"Klotenerstrasse",
    "iso:country":"CH",
    "sg:address":"Klotenerstrasse 76",
    "sg:city":"Bassersdorf",
    "sg:classifiers":[
        {
            "category":"Utilities",
            "subcategory":"Water",
            "type":"Services"
        }
    ],
    "sg:phone":"+41 43 266 20 30",
    "sg:postcode":"8303",
    "sg:province":"Z\u00fcrich",
    "sg:tags":[
        "tub",
        "replacement",
        "bath"
    ],
    "wof:name":"Wintsch-tonercote Ag",
    "wof:placetype":"venue"
},
  "geometry": {"coordinates":[8.622948,47.444931],"type":"Point"}
}