{
  "type": "Feature",
  "properties": {
    "iso:country":"CH",
    "sg:address":"Au Village",
    "sg:city":"Vaulruz",
    "sg:orig_category":"Detailhandel mit Waren verschiedener Art, Hauptrichtung Nahrungsmittel",
    "sg:phone":"+41 26 912 71 21",
    "sg:postcode":"1627",
    "sg:province":"Fribourg",
    "wof:name":"Sudan Murielle",
    "wof:placetype":"venue"
},
  "geometry": {"coordinates":[6.9883079529,46.6200714111],"type":"Point"}
}