{
  "type": "Feature",
  "properties": {
    "iso:country":"CH",
    "sg:address":"Innpark C",
    "sg:city":"Schlarigna",
    "sg:orig_category":"Architektur U Ingenieurb\u00fcros Architekturb\u00fcros",
    "sg:phone":"+41 81 833 77 64",
    "sg:postcode":"7505",
    "sg:province":"Graubunden",
    "wof:name":"Malgiaritta Roland Architekturb\u00fcro Htl/stv",
    "wof:placetype":"venue"
},
  "geometry": {"coordinates":[9.860075,46.51268],"type":"Point"}
}