{
  "type": "Feature",
  "properties": {
    "iso:country":"CH",
    "sg:address":"Abendruh",
    "sg:city":"Daiwil",
    "sg:orig_category":"Malerei",
    "sg:phone":"+41 41 970 24 34",
    "sg:postcode":"6126",
    "sg:province":"Luzern",
    "wof:name":"Julius Steinger Malergesch\u00e4ft",
    "wof:placetype":"venue"
},
  "geometry": {"coordinates":[8.0132741928,47.0967407227],"type":"Point"}
}