{
  "type": "Feature",
  "properties": {
    "iso:country":"CH",
    "sg:address":"Bernstrasse 9 3421 Lyssach. Postfach",
    "sg:city":"Lyssach",
    "sg:orig_category":"Allgemeiner Hoch U Tiefbau",
    "sg:postcode":"3421",
    "sg:province":"Bern",
    "wof:name":"Vsm Service Gmbh",
    "wof:placetype":"venue"
},
  "geometry": {"coordinates":[9.045185,47.463203],"type":"Point"}
}