{
  "type": "Feature",
  "properties": {
    "iso:country":"CH",
    "sg:address":"B\u00fcrglistrasse 31",
    "sg:city":"Wallisellen",
    "sg:orig_category":"Unclassifiable Establishments",
    "sg:postcode":"8304",
    "sg:province":"Z\u00fcrich",
    "wof:name":"Zw\u00e4ngiweg Holding Ag",
    "wof:placetype":"venue"
},
  "geometry": {"coordinates":[8.6000518799,47.4156723022],"type":"Point"}
}