{
  "type": "Feature",
  "properties": {
    "iso:country":"CH",
    "sg:address":"Pelikanweg 6 4054 Basel. Postfach",
    "sg:city":"Basel",
    "sg:orig_category":"Wett U Lotteriewesen",
    "sg:postcode":"4051",
    "sg:province":"Basel-Stadt",
    "wof:name":"System Lotto 2000, Winter P.",
    "wof:placetype":"venue"
},
  "geometry": {"coordinates":[7.5813097954,47.549987793],"type":"Point"}
}