{
  "type": "Feature",
  "properties": {
    "iso:country":"CH",
    "sg:address":"Lochstiegweg 24",
    "sg:city":"M\u00fcnchenbuchsee",
    "sg:orig_category":"Sportvereine Ballsport Tischtennis",
    "sg:phone":"+41 31 869 26 09",
    "sg:postcode":"3053",
    "sg:province":"Bern",
    "wof:name":"Ttc M\u00fcnchenbuchsee",
    "wof:placetype":"venue"
},
  "geometry": {"coordinates":[7.4363350868,47.0236282349],"type":"Point"}
}