{
  "type": "Feature",
  "properties": {
    "iso:country":"CH",
    "sg:address":"Rte Des Jeunes 28",
    "sg:city":"Grand-lancy",
    "sg:orig_category":"R\u00fcckgewinnung U Vorbereitung f\u00fcr die Wiederverwertung Recycling von nichtmetallischen Altmaterialien",
    "sg:postcode":"1212",
    "sg:province":"Gen\u00e8ve",
    "wof:name":"Inrec Sa",
    "wof:placetype":"venue"
},
  "geometry": {"coordinates":[6.1276431084,46.1762619019],"type":"Point"}
}