{
  "type": "Feature",
  "properties": {
    "iso:country":"CH",
    "sg:address":"Zedernweg 5",
    "sg:city":"Schafisheim",
    "sg:orig_category":"Gartenbau",
    "sg:phone":"+41 19101310",
    "sg:postcode":"5503",
    "sg:province":"Aargau",
    "wof:name":"Erwin Tobler Gartenbau",
    "wof:placetype":"venue"
},
  "geometry": {"coordinates":[8.5828771591,47.3265037537],"type":"Point"}
}