{
  "type": "Feature",
  "properties": {
    "iso:country":"CH",
    "sg:address":"Hauptstrasse 23",
    "sg:city":"Zurzach",
    "sg:orig_category":"Grosshandel mit B\u00fcromaschinen Grosshandel mit Datenverarbeitungsger\u00e4ten",
    "sg:phone":"+41 34 461 19 09",
    "sg:postcode":"5330",
    "sg:province":"Aargau",
    "wof:name":"Blaser Elektronik",
    "wof:placetype":"venue"
},
  "geometry": {"coordinates":[7.705493927,46.9844818115],"type":"Point"}
}