{
  "type": "Feature",
  "properties": {
    "addr:full":"Rue Des Grottes 13 Gen\u00e8ve Gen\u00e8ve 1201",
    "addr:housenumber":"13",
    "addr:postcode":"1201",
    "addr:street":"Rue Des Grottes",
    "iso:country":"CH",
    "sg:address":"Rue Des Grottes 13",
    "sg:city":"Gen\u00e8ve",
    "sg:classifiers":[
        {
            "category":"Bars & Pubs",
            "type":"Food & Drink"
        }
    ],
    "sg:phone":"+41 22 733 61 65",
    "sg:postcode":"1201",
    "sg:province":"Gen\u00e8ve",
    "sg:tags":[
        "restaurant"
    ],
    "wof:name":"Bar-restaurant Evid\u00e8nce",
    "wof:placetype":"venue"
},
  "geometry": {"coordinates":[6.138919,46.210587],"type":"Point"}
}