{
  "type": "Feature",
  "properties": {
    "addr:full":"Route Des Rottes 24 Conthey Valais 1964",
    "addr:housenumber":"24",
    "addr:postcode":"1964",
    "addr:street":"Route Des Rottes",
    "iso:country":"CH",
    "sg:address":"Route Des Rottes 24",
    "sg:city":"Conthey",
    "sg:orig_category":"Carpets, Hand-Woven",
    "sg:phone":"+41 27 346 51 66",
    "sg:postcode":"1964",
    "sg:province":"Valais",
    "wof:name":"Maison Gamgoum Sa",
    "wof:placetype":"venue"
},
  "geometry": {"coordinates":[7.299881,46.222897],"type":"Point"}
}