{
  "type": "Feature",
  "properties": {
    "iso:country":"CH",
    "sg:address":"Gehrisberg",
    "sg:city":"Wyssachen",
    "sg:orig_category":"Detailhandel mit Milcherzeugnissen U Eiern Verarbeitung von Milch",
    "sg:phone":"+41 62 966 19 50",
    "sg:postcode":"4954",
    "sg:province":"Bern",
    "wof:name":"Thomas Fankhauser K\u00e4serei",
    "wof:placetype":"venue"
},
  "geometry": {"coordinates":[7.8306388855,47.0730552673],"type":"Point"}
}