{
  "type": "Feature",
  "properties": {
    "iso:country":"CH",
    "sg:address":"Steinerstrasse",
    "sg:city":"Niederteufen",
    "sg:orig_category":"Detailhandel mit Getr\u00e4nken Grosshandel mit Getr\u00e4nken",
    "sg:phone":"+41 71 333 11 78",
    "sg:postcode":"9052",
    "sg:province":"Appenzell Ausserrhoden",
    "wof:name":"Gm\u00fcr Alex",
    "wof:placetype":"venue"
},
  "geometry": {"coordinates":[9.3642950058,47.3936843872],"type":"Point"}
}