{
  "type": "Feature",
  "properties": {
    "iso:country":"CH",
    "sg:address":"Huobmattstrasse 5",
    "sg:city":"Meggen",
    "sg:orig_category":"Unclassifiable Establishments",
    "sg:phone":"+41 56 441 62 80",
    "sg:postcode":"6045",
    "sg:province":"Luzern",
    "wof:name":"Neumarkt-drogerie H.p. W\u00f6rndli",
    "wof:placetype":"venue"
},
  "geometry": {"coordinates":[8.2079238892,47.4831848145],"type":"Point"}
}