{
  "type": "Feature",
  "properties": {
    "iso:country":"CH",
    "sg:address":"B\u00e4ckerei La Boh\u00e8me",
    "sg:city":"Leukerbad",
    "sg:orig_category":"Non-Classified Establishments",
    "sg:postcode":"3954",
    "sg:province":"Valais",
    "wof:name":"B\u00e4ckerei-konditorei Caf\u00e9 La Boh\u00e8me Gmbh",
    "wof:placetype":"venue"
},
  "geometry": {"coordinates":[7.6253261566,46.3759307861],"type":"Point"}
}