{
  "type": "Feature",
  "properties": {
    "iso:country":"CH",
    "sg:address":"Rue De Coppet 4",
    "sg:city":"Monthey",
    "sg:classifiers":[
        {
            "category":"Insurance",
            "subcategory":"Insurance Agent",
            "type":"Services"
        }
    ],
    "sg:phone":"+41 24 471 30 19",
    "sg:postcode":"1870",
    "sg:province":"Valais",
    "sg:tags":[
        "versicherungsagenturen",
        "-broker"
    ],
    "wof:name":"Elvia Assurances Agence",
    "wof:placetype":"venue"
},
  "geometry": {"coordinates":[6.9491910934,46.2522583008],"type":"Point"}
}