{
  "type": "Feature",
  "properties": {
    "iso:country":"CH",
    "sg:address":"Vignettaz Route De La 53",
    "sg:city":"Fribourg",
    "sg:orig_category":"Schreib U \u00dcbersetzungsb\u00fcros",
    "sg:phone":"+41 26 424 24 92",
    "sg:postcode":"1700",
    "sg:province":"Fribourg",
    "wof:name":"Botrad, Bossart Pierre",
    "wof:placetype":"venue"
},
  "geometry": {"coordinates":[7.1536831856,46.8037452698],"type":"Point"}
}