{
  "type": "Feature",
  "properties": {
    "iso:country":"CH",
    "sg:address":"Gartenstrasse 3",
    "sg:city":"Zug",
    "sg:orig_category":"Grosshandel mit chemischen Erzeugnissen",
    "sg:postcode":"6300",
    "sg:province":"Zug",
    "wof:name":"Molan Ag",
    "wof:placetype":"venue"
},
  "geometry": {"coordinates":[8.5148210526,47.1700744629],"type":"Point"}
}