{
  "type": "Feature",
  "properties": {
    "iso:country":"CH",
    "sg:address":"Moosmattstrasse 64",
    "sg:city":"Luzern",
    "sg:orig_category":"Fachdetailhandel in Verkaufsr\u00e4umen",
    "sg:phone":"+41 41 311 24 66",
    "sg:postcode":"6005",
    "sg:province":"Luzern",
    "wof:name":"Bafix Ag",
    "wof:placetype":"venue"
},
  "geometry": {"coordinates":[8.3031415939,47.0364456177],"type":"Point"}
}