{
  "type": "Feature",
  "properties": {
    "iso:country":"CH",
    "sg:address":"M\u00fchlenstrasse 19 Postfach",
    "sg:city":"Schaffhausen",
    "sg:classifiers":[
        {
            "category":"Utilities",
            "type":"Services"
        }
    ],
    "sg:phone":"+41 52 635 11 00",
    "sg:postcode":"8201",
    "sg:province":"Schaffhausen",
    "sg:tags":[
        "raw",
        "energy",
        "material"
    ],
    "wof:name":"Gaswerke Schaffhausen",
    "wof:placetype":"venue"
},
  "geometry": {"coordinates":[8.5652303696,53.736000061],"type":"Point"}
}