{
  "type": "Feature",
  "properties": {
    "iso:country":"CH",
    "sg:address":"3770 Zweisimmen. Postfach",
    "sg:city":"Zweisimmen",
    "sg:orig_category":"Detailhandel mit Waren verschiedener Art, Hauptrichtung Nahrungsmittel",
    "sg:postcode":"3770",
    "sg:province":"Bern",
    "wof:name":"Landwirtschaftliche Genossenschaft Zweisimmen Und Umgebung",
    "wof:placetype":"venue"
},
  "geometry": {"coordinates":[7.3726348877,46.5528755188],"type":"Point"}
}