{
  "type": "Feature",
  "properties": {
    "iso:country":"CH",
    "sg:address":"Clausiusstrasse 41 8006 Z\u00fcrich. Postfach 425",
    "sg:city":"Z\u00fcrich",
    "sg:orig_category":"Vermietung U Verpachtung von eigenen Immobilien",
    "sg:phone":"+41 12623611",
    "sg:postcode":"8006",
    "sg:province":"Z\u00fcrich",
    "wof:name":"Mettler Immobilien Ag",
    "wof:placetype":"venue"
},
  "geometry": {"coordinates":[8.5458297729,47.3792610168],"type":"Point"}
}