{
  "type": "Feature",
  "properties": {
    "iso:country":"CH",
    "sg:address":"Route De Corserey 80",
    "sg:city":"Prez-vers-nor\u00e9az",
    "sg:orig_category":"Grosshandel mit Parf\u00fcmerieartikeln U K\u00f6rperpflegemitteln Kosmetikinstitute",
    "sg:phone":"+41 26 470 02 72",
    "sg:postcode":"1746",
    "sg:province":"Fribourg",
    "wof:name":"Skinepil S\u00e0rl",
    "wof:placetype":"venue"
},
  "geometry": {"coordinates":[7.0054039955,46.7790794373],"type":"Point"}
}