{
  "type": "Feature",
  "properties": {
    "iso:country":"CH",
    "sg:address":"Hardturmstr.181",
    "sg:city":"Z\u00fcrich",
    "sg:classifiers":[
        {
            "category":"Professional",
            "subcategory":"Advertising",
            "type":"Services"
        }
    ],
    "sg:phone":"+41 71 274 66 66",
    "sg:postcode":"8010",
    "sg:province":"Z\u00fcrich",
    "sg:tags":[
        "marketing",
        "medium",
        "communication"
    ],
    "wof:name":"Ms Mail Service Ag",
    "wof:placetype":"venue"
},
  "geometry": {"coordinates":[9.350457,47.414181],"type":"Point"}
}