{
  "type": "Feature",
  "properties": {
    "iso:country":"CH",
    "sg:address":"Im Kirschgarten 5",
    "sg:city":"H\u00f6lstein",
    "sg:orig_category":"Herstellung U Zusammensetzung von Grossuhren Herstellung U Zusammensetzung von Uhren",
    "sg:phone":"+41 61 951 19 63",
    "sg:postcode":"4434",
    "sg:province":"Basel-Landschaft",
    "wof:name":"Heinrich Althaus Atelier F\u00fcr Grossuhren",
    "wof:placetype":"venue"
},
  "geometry": {"coordinates":[7.7693099976,47.4197425842],"type":"Point"}
}