{
  "type": "Feature",
  "properties": {
    "iso:country":"CH",
    "sg:address":"Walde",
    "sg:city":"Gunzwil",
    "sg:orig_category":"Grosshandel mit Milch, Milcherzeugnissen, Eiern, Speise\u00f6len U Nahrungsfetten Haltung von Legehennen ",
    "sg:phone":"+41 41 497 23 30",
    "sg:postcode":"6222",
    "sg:province":"Luzern",
    "wof:name":"Fischer Thomas & Stefan Eier Und Eiprodukte",
    "wof:placetype":"venue"
},
  "geometry": {"coordinates":[8.1827249527,47.0368156433],"type":"Point"}
}