{
  "type": "Feature",
  "properties": {
    "iso:country":"CH",
    "sg:address":"Place De La Gare 4 1003 Lausanne. Postfach",
    "sg:city":"Lausanne",
    "sg:orig_category":"Wirtschaftspr\u00fcfung, Steuerberatung U Treuhand",
    "sg:phone":"+41 21 320 66 41",
    "sg:postcode":"1001",
    "sg:province":"Vaud",
    "wof:name":"Deloitte & Touche Sa",
    "wof:placetype":"venue"
},
  "geometry": {"coordinates":[6.6290988922,46.5175209045],"type":"Point"}
}