{
  "type": "Feature",
  "properties": {
    "iso:country":"CH",
    "sg:address":"2316",
    "sg:city":"Ponts-de-martel",
    "sg:classifiers":[
        {
            "category":"Education",
            "subcategory":"Vocational School",
            "type":"Public Place"
        }
    ],
    "sg:postcode":"2316",
    "sg:province":"Neuch\u00e2tel",
    "sg:tags":[
        "koch-",
        "haushaltschulen"
    ],
    "wof:name":"Ecole M\u00e9nag\u00e8re",
    "wof:placetype":"venue"
},
  "geometry": {"coordinates":[7.0049629211,47.2118835449],"type":"Point"}
}