{
  "type": "Feature",
  "properties": {
    "iso:country":"CH",
    "sg:address":"Rue Des Places",
    "sg:city":"Vouvry",
    "sg:orig_category":"Wirtschaftspr\u00fcfung, Steuerberatung U Treuhand",
    "sg:phone":"+41 24 481 44 35",
    "sg:postcode":"1896",
    "sg:province":"Valais",
    "wof:name":"Ariane Reymond-pot Secr\u00e9tariat-service",
    "wof:placetype":"venue"
},
  "geometry": {"coordinates":[6.8903398514,46.338394165],"type":"Point"}
}