{
  "type": "Feature",
  "properties": {
    "iso:country":"CH",
    "sg:address":"Riedtalstrasse 14",
    "sg:city":"Zofingen",
    "sg:orig_category":"Sonstige Hilfsdienste des Kultur U Unterhaltungswesens",
    "sg:phone":"+41 62 751 25 75",
    "sg:postcode":"4800",
    "sg:province":"Aargau",
    "wof:name":"Creation Music Gmbh Tonstudio",
    "wof:placetype":"venue"
},
  "geometry": {"coordinates":[7.9566469193,47.2778549194],"type":"Point"}
}