{
  "type": "Feature",
  "properties": {
    "iso:country":"CH",
    "sg:address":"Pizolstrasse 12",
    "sg:city":"Sargans",
    "sg:orig_category":"Zahnarztpraxen",
    "sg:phone":"+41 81 710 45 45",
    "sg:postcode":"7320",
    "sg:province":"St. Gallen",
    "wof:name":"Dr. Med. Dent. Johnny Sele Zahnarzt",
    "wof:placetype":"venue"
},
  "geometry": {"coordinates":[9.440864563,47.0445480347],"type":"Point"}
}