{
  "type": "Feature",
  "properties": {
    "iso:country":"CH",
    "sg:address":"Bankstrasse 7",
    "sg:city":"Glarus",
    "sg:orig_category":"Verwaltung von Immobilien Wirtschaftspr\u00fcfung, Steuerberatung U Treuhand",
    "sg:phone":"+41 55 640 40 94",
    "sg:postcode":"8750",
    "sg:province":"Glarus",
    "wof:name":"Bernet & Lehner Treuhand Ag",
    "wof:placetype":"venue"
},
  "geometry": {"coordinates":[9.0696754456,47.0407371521],"type":"Point"}
}