{
  "type": "Feature",
  "properties": {
    "iso:country":"CH",
    "sg:address":"Gr\u00fczefeldstrasse 35",
    "sg:city":"Winterthur",
    "sg:classifiers":[
        {
            "category":"Professional",
            "subcategory":"Advertising",
            "type":"Services"
        }
    ],
    "sg:phone":"+41 52 232 18 94",
    "sg:postcode":"8404",
    "sg:province":"Z\u00fcrich",
    "sg:tags":[
        "poster"
    ],
    "wof:name":"Blum Offsetdruck Ag",
    "wof:placetype":"venue"
},
  "geometry": {"coordinates":[8.752741,47.494148],"type":"Point"}
}