{
  "type": "Feature",
  "properties": {
    "addr:full":"Cr\u00eat-georges Rue Du 49 Tramelan Bern 2720",
    "addr:postcode":"2720",
    "addr:street":"Rue Du 49;Bern",
    "iso:country":"CH",
    "sg:address":"Cr\u00eat-georges Rue Du 49",
    "sg:city":"Tramelan",
    "sg:orig_category":"Architektur U Ingenieurb\u00fcros",
    "sg:phone":"+41 19108272",
    "sg:postcode":"2720",
    "sg:province":"Bern",
    "wof:name":"I.t.c. Intertecnoconsult Ltd",
    "wof:placetype":"venue"
},
  "geometry": {"coordinates":[8.589521,47.322498],"type":"Point"}
}