{
  "type": "Feature",
  "properties": {
    "iso:country":"CH",
    "sg:address":"Untere Sternengasse 44",
    "sg:city":"Solothurn",
    "sg:orig_category":"Vorschulen, Kinderg\u00e4rten",
    "sg:postcode":"4500",
    "sg:province":"Solothurn",
    "wof:name":"Kindergarten",
    "wof:placetype":"venue"
},
  "geometry": {"coordinates":[7.5483717918,47.2089118958],"type":"Point"}
}