{
  "type": "Feature",
  "properties": {
    "iso:country":"CH",
    "sg:address":"Margritenweg 6",
    "sg:city":"Dielsdorf",
    "sg:classifiers":[
        {
            "category":"Building & Trades",
            "subcategory":"Plumbing",
            "type":"Services"
        }
    ],
    "sg:phone":"+41 56 401 11 23",
    "sg:postcode":"8157",
    "sg:province":"Z\u00fcrich",
    "sg:tags":[
        "pipe",
        "sewer",
        "reconstruction"
    ],
    "wof:name":"Rohrputz Ag",
    "wof:placetype":"venue"
},
  "geometry": {"coordinates":[8.4540195465,47.4801673889],"type":"Point"}
}