{
  "type": "Feature",
  "properties": {
    "iso:country":"CH",
    "sg:address":"Les Monts-de-corsier Les Espe",
    "sg:city":"Corsier-sur-vevey",
    "sg:orig_category":"Wirtschaftspr\u00fcfung, Steuerberatung U Treuhand",
    "sg:phone":"+41 21 971 16 52",
    "sg:postcode":"1804",
    "sg:province":"Vaud",
    "wof:name":"Swmh Fiduciaire Et Conseils S\u00e0rl",
    "wof:placetype":"venue"
},
  "geometry": {"coordinates":[6.8414001465,46.4704856873],"type":"Point"}
}