{
  "type": "Feature",
  "properties": {
    "addr:full":"2103 Noiraigue Neuch\u00e2tel 2103",
    "addr:housenumber":"2103",
    "addr:postcode":"2103",
    "addr:street":"Noiraigue Neucha\u0302Tel",
    "iso:country":"CH",
    "sg:address":"2103",
    "sg:city":"Noiraigue",
    "sg:classifiers":[
        {
            "category":"Education",
            "subcategory":"Library",
            "type":"Public Place"
        }
    ],
    "sg:phone":"+41 32 855 13 54",
    "sg:postcode":"2103",
    "sg:province":"Neuch\u00e2tel",
    "sg:tags":[
        "u",
        "bibliotheken",
        "archive"
    ],
    "wof:name":"Biblioth\u00e8que Communale",
    "wof:placetype":"venue"
},
  "geometry": {"coordinates":[6.718931,46.956524],"type":"Point"}
}