{
  "type": "Feature",
  "properties": {
    "iso:country":"CH",
    "sg:address":"Unterseestrasse 65 8280 Kreuzlingen. Postfach 863",
    "sg:city":"Kreuzlingen",
    "sg:orig_category":"Pensionskassen",
    "sg:phone":"+41 34 402 22 94",
    "sg:postcode":"8280",
    "sg:province":"Thurgau",
    "wof:name":"Personalvorsorgestiftung Der Multi-extrakt Ag",
    "wof:placetype":"venue"
},
  "geometry": {"coordinates":[7.757589817,46.9491271973],"type":"Point"}
}