{
  "type": "Feature",
  "properties": {
    "iso:country":"CH",
    "sg:address":"Route De Corcelles",
    "sg:city":"Attalens",
    "sg:orig_category":"Maler U Glasergewerbe Malerei",
    "sg:phone":"+41 21 947 51 23",
    "sg:postcode":"1616",
    "sg:province":"Fribourg",
    "wof:name":"Michel Haselwander Entreprise De Peinture",
    "wof:placetype":"venue"
},
  "geometry": {"coordinates":[6.8485898972,46.5137290955],"type":"Point"}
}