{
  "type": "Feature",
  "properties": {
    "iso:country":"CH",
    "sg:address":"Frontenex Route De 82 1208 Gen\u00e8ve. Postfach",
    "sg:city":"Gen\u00e8ve",
    "sg:orig_category":"Unclassifiable Establishments",
    "sg:postcode":"1208",
    "sg:province":"Gen\u00e8ve",
    "wof:name":"Soci\u00e9t\u00e9 Immobili\u00e8re Bourdigny-dessus",
    "wof:placetype":"venue"
},
  "geometry": {"coordinates":[6.1713747978,46.2050552368],"type":"Point"}
}