{
  "type": "Feature",
  "properties": {
    "iso:country":"CH",
    "sg:address":"Route De Frontenex 63",
    "sg:city":"Gen\u00e8ve",
    "sg:orig_category":"Innenarchitekturb\u00fcros",
    "sg:phone":"+41 22 736 48 00",
    "sg:postcode":"1207",
    "sg:province":"Gen\u00e8ve",
    "wof:name":"Plan Service Architecture D'int\u00e9rieur",
    "wof:placetype":"venue"
},
  "geometry": {"coordinates":[6.1668338776,46.2033576965],"type":"Point"}
}