{
  "type": "Feature",
  "properties": {
    "iso:country":"CH",
    "sg:address":"Steinbach",
    "sg:city":"Einsiedeln",
    "sg:orig_category":"RESTAURANTS: TEA-ROOMS",
    "sg:postcode":"8840",
    "sg:province":"Schwyz",
    "wof:name":"Kriesche Rudolf Walter",
    "wof:placetype":"venue"
},
  "geometry": {"coordinates":[8.7911815643,47.0976257324],"type":"Point"}
}