{
  "type": "Feature",
  "properties": {
    "iso:country":"CH",
    "sg:address":"Hohlstrasse 359 8004 Z\u00fcrich. Postfach",
    "sg:city":"Z\u00fcrich",
    "sg:orig_category":"Sonstiger Grosshandel",
    "sg:phone":"+41 14923109",
    "sg:postcode":"8001",
    "sg:province":"Z\u00fcrich",
    "wof:name":"Shala S. Waren Usw; Imp., Exp., Handel",
    "wof:placetype":"venue"
},
  "geometry": {"coordinates":[8.5088787079,47.3848381042],"type":"Point"}
}