{
  "type": "Feature",
  "properties": {
    "iso:country":"CH",
    "sg:address":"Zugerstrasse 6330 Cham. Postfach",
    "sg:city":"Cham",
    "sg:orig_category":"K\u00fcnstlerische U schriftstellerische T\u00e4tigkeiten U Darbietungen",
    "sg:postcode":"6330",
    "sg:province":"Zug",
    "wof:name":"Rothenfluh Erich J., Genealogie + Heraldik Bilder U. Zubeh\u00f6r Usw.; Verkauf, Beratung, Handel. Namens, Familien- U. Wappenforschung",
    "wof:placetype":"venue"
},
  "geometry": {"coordinates":[8.4735536575,47.184513092],"type":"Point"}
}