{
  "type": "Feature",
  "properties": {
    "iso:country":"CH",
    "sg:address":"Route De Gen\u00e8ve 80",
    "sg:city":"Pr\u00e9verenges",
    "sg:orig_category":"Fahrschulen, Flugschulen",
    "sg:phone":"+41 79 301 20 00",
    "sg:postcode":"1028",
    "sg:province":"Vaud",
    "wof:name":"Yvette Rochat Auto-\u00e9cole",
    "wof:placetype":"venue"
},
  "geometry": {"coordinates":[6.537607193,46.5147247314],"type":"Point"}
}