{
  "type": "Feature",
  "properties": {
    "iso:country":"CH",
    "sg:address":"G\u00e4nsackerweg 13",
    "sg:city":"Gipf-oberfrick",
    "sg:orig_category":"Unclassifiable Establishments",
    "sg:postcode":"5073",
    "sg:province":"Aargau",
    "wof:name":"Xpertise Ag",
    "wof:placetype":"venue"
},
  "geometry": {"coordinates":[8.0019197464,47.4995117188],"type":"Point"}
}