{
  "type": "Feature",
  "properties": {
    "iso:country":"CH",
    "sg:address":"Chantemerle Route De 1",
    "sg:city":"Granges-paccot",
    "sg:orig_category":"Unclassifiable Establishments",
    "sg:phone":"+41 55 416 71 11",
    "sg:postcode":"1763",
    "sg:province":"Fribourg",
    "wof:name":"Charles V\u00f6gele Holding Ag",
    "wof:placetype":"venue"
},
  "geometry": {"coordinates":[8.7886457443,47.2017974854],"type":"Point"}
}