{
  "type": "Feature",
  "properties": {
    "iso:country":"CH",
    "sg:address":"T\u00f6distrasse 32",
    "sg:city":"Horgen",
    "sg:orig_category":"Sonstige mit der Informatik verbundene T\u00e4tigkeiten",
    "sg:phone":"+41 17260828",
    "sg:postcode":"8810",
    "sg:province":"Z\u00fcrich",
    "wof:name":"Pc-consulting Zimmermann Gmbh",
    "wof:placetype":"venue"
},
  "geometry": {"coordinates":[8.5846033096,47.260761261],"type":"Point"}
}