{
  "type": "Feature",
  "properties": {
    "iso:country":"CH",
    "sg:address":"Grand-rue 18",
    "sg:city":"Ch\u00e2telard-lutry",
    "sg:orig_category":"RESTAURANTS: TEA-ROOMS",
    "sg:postcode":"1095",
    "sg:province":"Vaud",
    "wof:name":"Mascon-resplendino, Mme",
    "wof:placetype":"venue"
},
  "geometry": {"coordinates":[6.6845779419,46.5025024414],"type":"Point"}
}