{
  "type": "Feature",
  "properties": {
    "addr:full":"Quartierstrasse 2 Niederg\u00f6sgen Solothurn 5013",
    "addr:housenumber":"2",
    "addr:postcode":"5013",
    "addr:street":"Quartierstrasse;Solothurn",
    "iso:country":"CH",
    "sg:address":"Quartierstrasse 2",
    "sg:city":"Niederg\u00f6sgen",
    "sg:orig_category":"Arbeitnehmerverb\u00e4nde",
    "sg:phone":"+41 62 849 74 22",
    "sg:postcode":"5013",
    "sg:province":"Solothurn",
    "wof:name":"Lehrerverein G\u00f6sgen Pr\u00e4s.herrn Peter Spielmann",
    "wof:placetype":"venue"
},
  "geometry": {"coordinates":[7.986342,47.369553],"type":"Point"}
}