{
  "type": "Feature",
  "properties": {
    "addr:full":"Kurfirstenstrasse 16 8002 Z\u00fcrich. Postfach Z\u00fcrich Z\u00fcrich 8001",
    "addr:housenumber":"16",
    "addr:postcode":"8002 zuerich. postfach;8001",
    "addr:street":"Kurfirstenstrasse",
    "iso:country":"CH",
    "sg:address":"Kurfirstenstrasse 16 8002 Z\u00fcrich. Postfach",
    "sg:city":"Z\u00fcrich",
    "sg:orig_category":"Detailhandel mit Computern U Software Softwareentwicklung U beratung",
    "sg:phone":"+41 43 344 55 66",
    "sg:postcode":"8001",
    "sg:province":"Z\u00fcrich",
    "wof:name":"Speedscript Gmbh",
    "wof:placetype":"venue"
},
  "geometry": {"coordinates":[8.527762,47.356541],"type":"Point"}
}