{
  "type": "Feature",
  "properties": {
    "iso:country":"CH",
    "sg:address":"Sch\u00fctzenstrasse 29",
    "sg:city":"Dietikon",
    "sg:orig_category":"Detailhandel mit Fleisch U Fleischwaren",
    "sg:phone":"+41 17400335",
    "sg:postcode":"8953",
    "sg:province":"Z\u00fcrich",
    "wof:name":"Metzgerei Bl\u00e4ttler Bruno",
    "wof:placetype":"venue"
},
  "geometry": {"coordinates":[8.3916044235,47.4043045044],"type":"Point"}
}