{
  "type": "Feature",
  "properties": {
    "iso:country":"CH",
    "sg:address":"Ruessenstrasse 6",
    "sg:city":"Baar",
    "sg:orig_category":"Herstellung von Sportger\u00e4ten",
    "sg:postcode":"6340",
    "sg:province":"Zug",
    "wof:name":"V\u00f6lkl Tennis Gmbh",
    "wof:placetype":"venue"
},
  "geometry": {"coordinates":[8.5604944229,47.2117652893],"type":"Point"}
}