{
  "type": "Feature",
  "properties": {
    "iso:country":"CH",
    "sg:address":"Rue Bonivard 9",
    "sg:city":"Veytaux",
    "sg:orig_category":"Bauschreinerei Herstellung von M\u00f6beln verschiedener Art",
    "sg:phone":"+41 21 963 65 38",
    "sg:postcode":"1820",
    "sg:province":"Vaud",
    "wof:name":"Christophe Dubois Menuiserie & \u00e9b\u00e9nisterie",
    "wof:placetype":"venue"
},
  "geometry": {"coordinates":[6.92859,46.420956],"type":"Point"}
}