{
  "type": "Feature",
  "properties": {
    "iso:country":"CH",
    "sg:address":"Kreuzbuchstrasse 7 6006 Luzern. Postfach",
    "sg:city":"Luzern",
    "sg:orig_category":"Herstellung von Spielwaren",
    "sg:postcode":"6006",
    "sg:province":"Luzern",
    "wof:name":"Zapmyday Ag Spiele; Entwicklung, Vermarktung. Dienstleistungen Im Bereich Multimedia Usw",
    "wof:placetype":"venue"
},
  "geometry": {"coordinates":[8.3294067383,47.0555000305],"type":"Point"}
}