{
  "type": "Feature",
  "properties": {
    "iso:country":"CH",
    "sg:address":"Hauptstrasse 300",
    "sg:city":"Wittnau",
    "sg:classifiers":[
        {
            "category":"Home & Garden",
            "subcategory":"Building Materials",
            "type":"Retail Goods"
        }
    ],
    "sg:phone":"+41 62 871 10 88",
    "sg:postcode":"5064",
    "sg:province":"Aargau",
    "sg:tags":[
        "fa\u00e7ade",
        "enamelled",
        "element"
    ],
    "wof:name":"Bauwerk-parkett Ag",
    "wof:placetype":"venue"
},
  "geometry": {"coordinates":[7.9887299538,47.4844894409],"type":"Point"}
}