{
  "type": "Feature",
  "properties": {
    "addr:full":"St. Niklausstrasse 60 Solothurn Solothurn 4500",
    "addr:housenumber":"60",
    "addr:postcode":"4500",
    "addr:street":"St. Niklausstrasse",
    "iso:country":"CH",
    "sg:address":"St. Niklausstrasse 60",
    "sg:city":"Solothurn",
    "sg:orig_category":"Bauingenieurb\u00fcros Heizung L\u00fcftung Klima Ingenieurb\u00fcros Umwelttechnik and \u00d6kologie",
    "sg:phone":"+41 32 623 02 62",
    "sg:postcode":"4500",
    "sg:province":"Solothurn",
    "wof:name":"Tuffli Hautle & Partner Ag Ingenieure & Planer",
    "wof:placetype":"venue"
},
  "geometry": {"coordinates":[7.543087,47.217628],"type":"Point"}
}