{
  "type": "Feature",
  "properties": {
    "iso:country":"CH",
    "sg:address":"Nauengasse 14",
    "sg:city":"Rorbas",
    "sg:orig_category":"Grosshandel mit B\u00fcromaschinen Grosshandel mit Datenverarbeitungsger\u00e4ten",
    "sg:phone":"+41 71 393 82 82",
    "sg:postcode":"8427",
    "sg:province":"Z\u00fcrich",
    "wof:name":"Icon Computer Ag",
    "wof:placetype":"venue"
},
  "geometry": {"coordinates":[9.2117004395,47.4424667358],"type":"Point"}
}