{
  "type": "Feature",
  "properties": {
    "addr:full":"Hallenstrasse 15 Z\u00fcrich Z\u00fcrich 8008",
    "addr:housenumber":"15",
    "addr:postcode":"8008",
    "addr:street":"Hallenstrasse",
    "iso:country":"CH",
    "sg:address":"Hallenstrasse 15",
    "sg:city":"Z\u00fcrich",
    "sg:orig_category":"Bauingenieurb\u00fcros Unternehmensberatung",
    "sg:phone":"+41 12603474",
    "sg:postcode":"8008",
    "sg:province":"Z\u00fcrich",
    "wof:name":"D + D Projekt Consult Ag",
    "wof:placetype":"venue"
},
  "geometry": {"coordinates":[8.54831,47.3633],"type":"Point"}
}