{
  "type": "Feature",
  "properties": {
    "iso:country":"CH",
    "sg:address":"Huebackerstrasse 5 8265 Mammern. Postfach",
    "sg:city":"Mammern",
    "sg:orig_category":"Sonstige mit der Informatik verbundene T\u00e4tigkeiten",
    "sg:postcode":"8265",
    "sg:province":"Thurgau",
    "wof:name":"Compedit Gmbh",
    "wof:placetype":"venue"
},
  "geometry": {"coordinates":[8.9125499725,47.6423606873],"type":"Point"}
}