{
  "type": "Feature",
  "properties": {
    "iso:country":"CH",
    "sg:address":"Place De La Gare 1890 St-maurice Case Postale 115",
    "sg:city":"St-maurice",
    "sg:orig_category":"Zahnarztpraxen",
    "sg:phone":"+41 24 485 11 28",
    "sg:postcode":"1890",
    "sg:province":"Valais",
    "wof:name":"Dr M\u00e9d. Dent. Andr\u00e9 Olivier M\u00e9decin-dentiste",
    "wof:placetype":"venue"
},
  "geometry": {"coordinates":[7.0021791458,46.2172470093],"type":"Point"}
}