{
  "type": "Feature",
  "properties": {
    "iso:country":"CH",
    "sg:address":"Sonnhaldenweg 11 4314 Zeiningen. Postfach",
    "sg:city":"Zeiningen",
    "sg:orig_category":"Herstellung von sonstigen chemischen Erzeugnissen",
    "sg:phone":"+41 61 853 09 09",
    "sg:postcode":"4314",
    "sg:province":"Aargau",
    "wof:name":"Almatechnik Gammenthaler Chemie, Industrietechnik; Handel, Beratung",
    "wof:placetype":"venue"
},
  "geometry": {"coordinates":[7.871322155,47.5453414917],"type":"Point"}
}