{
  "type": "Feature",
  "properties": {
    "iso:country":"CH",
    "sg:address":"Regensdorferstrasse 5",
    "sg:city":"Z\u00fcrich",
    "sg:classifiers":[
        {
            "category":"Organizations",
            "subcategory":"Non-profit Organization",
            "type":"Services"
        }
    ],
    "sg:phone":"+41 13421212",
    "sg:postcode":"8049",
    "sg:province":"Z\u00fcrich",
    "sg:tags":[
        "alarm",
        "system"
    ],
    "wof:name":"Marcel Albrecht Sicherheits-und Elektrotechnik",
    "wof:placetype":"venue"
},
  "geometry": {"coordinates":[8.499031,47.402325],"type":"Point"}
}