{
  "type": "Feature",
  "properties": {
    "iso:country":"CH",
    "sg:address":"Toggenburgstrasse 85",
    "sg:city":"Rohrbach",
    "sg:orig_category":"Elektrizit\u00e4tsversorgung",
    "sg:postcode":"4938",
    "sg:province":"Bern",
    "wof:name":"L\u00fcthi W. Umwelttechnik Gmbh",
    "wof:placetype":"venue"
},
  "geometry": {"coordinates":[7.824739933,47.1363182068],"type":"Point"}
}