{
  "type": "Feature",
  "properties": {
    "iso:country":"CH",
    "sg:address":"Via Emilio Bossi 20",
    "sg:city":"Chiasso",
    "sg:orig_category":"Elektroinstallation",
    "sg:phone":"+41 91 682 46 14",
    "sg:postcode":"6830",
    "sg:province":"Ticino",
    "wof:name":"Giordano Arrigo",
    "wof:placetype":"venue"
},
  "geometry": {"coordinates":[9.0315132141,45.834980011],"type":"Point"}
}