{
  "type": "Feature",
  "properties": {
    "iso:country":"CH",
    "sg:address":"Poststrasse 9 9113 Degersheim. Postfach",
    "sg:city":"Degersheim",
    "sg:orig_category":"Nationale Postdienste",
    "sg:phone":"+41 71 371 11 61",
    "sg:postcode":"9113",
    "sg:province":"St. Gallen",
    "wof:name":"Die Schweizerische Post",
    "wof:placetype":"venue"
},
  "geometry": {"coordinates":[9.1980104446,47.3725509644],"type":"Point"}
}