{
  "type": "Feature",
  "properties": {
    "iso:country":"CH",
    "sg:address":"H\u00f6ckleriweg 59",
    "sg:city":"Widen",
    "sg:orig_category":"Sonstige Hilfs U Nebent\u00e4tigkeiten f\u00fcr den Landverkehr",
    "sg:postcode":"8967",
    "sg:province":"Aargau",
    "wof:name":"Kino Park Betriebsgesellschaft Ag",
    "wof:placetype":"venue"
},
  "geometry": {"coordinates":[8.3587999344,47.3716201782],"type":"Point"}
}