{
  "type": "Feature",
  "properties": {
    "iso:country":"CH",
    "sg:address":"Bleikimatt 5",
    "sg:city":"Willisau",
    "sg:orig_category":"Museen",
    "sg:phone":"+41 41 970 28 54",
    "sg:postcode":"6130",
    "sg:province":"Luzern",
    "wof:name":"Wiggertaler-museum",
    "wof:placetype":"venue"
},
  "geometry": {"coordinates":[7.994656086,47.1175575256],"type":"Point"}
}