{
  "type": "Feature",
  "properties": {
    "iso:country":"CH",
    "sg:address":"3963",
    "sg:city":"Crans-sur-sierre",
    "sg:classifiers":[
        {
            "category":"Restaurant",
            "type":"Food & Drink"
        }
    ],
    "sg:postcode":"3963",
    "sg:province":"Valais",
    "wof:name":"Snack Bar Restaurante A Bifana Parreira Do Nascimento Antonio Gastronomiebetrieb",
    "wof:placetype":"venue"
},
  "geometry": {"coordinates":[-4.4151101112,48.4458312988],"type":"Point"}
}