{
  "type": "Feature",
  "properties": {
    "iso:country":"CH",
    "sg:address":"Seestrasse 38 8803 R\u00fcschlikon. Postfach",
    "sg:city":"R\u00fcschlikon",
    "sg:orig_category":"Grosshandel mit Getr\u00e4nken",
    "sg:postcode":"8803",
    "sg:province":"Z\u00fcrich",
    "wof:name":"S\u00fcdhang Gmbh",
    "wof:placetype":"venue"
},
  "geometry": {"coordinates":[8.5567131042,47.3106575012],"type":"Point"}
}