{
  "type": "Feature",
  "properties": {
    "iso:country":"CH",
    "sg:address":"Milchgasse 25",
    "sg:city":"Aarau",
    "sg:orig_category":"Architekturb\u00fcros",
    "sg:phone":"+41 62 824 48 28",
    "sg:postcode":"5000",
    "sg:province":"Aargau",
    "wof:name":"Oehler Architekten Sia/swb",
    "wof:placetype":"venue"
},
  "geometry": {"coordinates":[8.04343,47.392071],"type":"Point"}
}