{
  "type": "Feature",
  "properties": {
    "iso:country":"CH",
    "sg:address":"Gerbestrasse 18",
    "sg:city":"R\u00fcegsauschachen",
    "sg:orig_category":"Zahnarztpraxen",
    "sg:phone":"+41 71 761 26 79",
    "sg:postcode":"3415",
    "sg:province":"Bern",
    "wof:name":"Dr.med.dent.bozidar Bozikovic Zahnarzt",
    "wof:placetype":"venue"
},
  "geometry": {"coordinates":[9.569644928,47.3293151855],"type":"Point"}
}