{
  "type": "Feature",
  "properties": {
    "iso:country":"CH",
    "sg:address":"Kosthausstrasse 6 6010 Kriens. Postfach",
    "sg:city":"Kriens",
    "sg:orig_category":"Grosshandel mit Getr\u00e4nken",
    "sg:postcode":"6010",
    "sg:province":"Luzern",
    "wof:name":"Vino & Vino Terramia Gulli",
    "wof:placetype":"venue"
},
  "geometry": {"coordinates":[8.2751569748,47.0337677002],"type":"Point"}
}