{
  "type": "Feature",
  "properties": {
    "iso:country":"CH",
    "sg:address":"Kottenring 16",
    "sg:city":"Sursee",
    "sg:orig_category":"Unternehmensberatung",
    "sg:postcode":"6210",
    "sg:province":"Luzern",
    "wof:name":"Controlling And Management Baumli Martin",
    "wof:placetype":"venue"
},
  "geometry": {"coordinates":[8.0942764282,47.1719017029],"type":"Point"}
}