{
  "type": "Feature",
  "properties": {
    "iso:country":"CH",
    "sg:address":"Z\u00fcrcherstrasse 34",
    "sg:city":"Volketswil",
    "sg:orig_category":"Handel mit Automobilen Instandhaltung U Reparatur von Automobilen",
    "sg:phone":"+41 19451313",
    "sg:postcode":"8604",
    "sg:province":"Z\u00fcrich",
    "wof:name":"Garage Schiess Ag",
    "wof:placetype":"venue"
},
  "geometry": {"coordinates":[8.65721035,47.3940887451],"type":"Point"}
}