{
  "type": "Feature",
  "properties": {
    "iso:country":"CH",
    "sg:address":"Chemin De La Milice 22",
    "sg:city":"Plan-les-ouates",
    "sg:orig_category":"Detailhandel mit Getr\u00e4nken Grosshandel mit Getr\u00e4nken",
    "sg:phone":"+41 41 630 17 48",
    "sg:postcode":"1228",
    "sg:province":"Gen\u00e8ve",
    "wof:name":"Bl\u00e4ttler Franz, Valser-deposit\u00e4r",
    "wof:placetype":"venue"
},
  "geometry": {"coordinates":[8.3144884109,46.9900932312],"type":"Point"}
}