{
  "type": "Feature",
  "properties": {
    "iso:country":"CH",
    "sg:address":"Paradisstrasse 10 9402 M\u00f6rschwil. Postfach 120",
    "sg:city":"M\u00f6rschwil",
    "sg:orig_category":"Grosshandel mit B\u00fcromaschinen Grosshandel mit Datenverarbeitungsger\u00e4ten",
    "sg:phone":"+41 71 868 70 25",
    "sg:postcode":"9402",
    "sg:province":"St. Gallen",
    "wof:name":"Eo Tech Gmbh",
    "wof:placetype":"venue"
},
  "geometry": {"coordinates":[9.4171352386,47.4674339294],"type":"Point"}
}