{
  "type": "Feature",
  "properties": {
    "iso:country":"CH",
    "sg:address":"Grossrieden 73",
    "sg:city":"Aedermannsdorf",
    "sg:classifiers":[
        {
            "category":"Restaurant",
            "type":"Food & Drink"
        }
    ],
    "sg:phone":"+41 62 390 15 98",
    "sg:postcode":"4714",
    "sg:province":"Solothurn",
    "wof:name":"Bergwirtschaft Rinderweid",
    "wof:placetype":"venue"
},
  "geometry": {"coordinates":[7.7530999184,47.3325614929],"type":"Point"}
}