{
  "type": "Feature",
  "properties": {
    "iso:country":"CH",
    "sg:address":"Rue De L'industrie 25",
    "sg:city":"Del\u00e9mont",
    "sg:orig_category":"Reinigungsgewerbe",
    "sg:phone":"+41 32 422 28 72",
    "sg:postcode":"2800",
    "sg:province":"Jura",
    "wof:name":"Perma-express, Python G\u00e9rard.",
    "wof:placetype":"venue"
},
  "geometry": {"coordinates":[7.3480629921,47.3652954102],"type":"Point"}
}