{
  "type": "Feature",
  "properties": {
    "iso:country":"CH",
    "sg:address":"2830",
    "sg:city":"Courrendlin",
    "sg:orig_category":"Vereine Musik/Blasmusik",
    "sg:postcode":"2830",
    "sg:province":"Jura",
    "wof:name":"Fanfare Municipale",
    "wof:placetype":"venue"
},
  "geometry": {"coordinates":[7.3730211258,47.3398246765],"type":"Point"}
}