{
  "type": "Feature",
  "properties": {
    "iso:country":"CH",
    "sg:address":"6818",
    "sg:city":"Melano",
    "sg:orig_category":"Sportvereine Ballsport Fussball",
    "sg:phone":"+41 91 648 28 45",
    "sg:postcode":"6818",
    "sg:province":"Ticino",
    "wof:name":"Fc Melano",
    "wof:placetype":"venue"
},
  "geometry": {"coordinates":[8.9924497604,45.9219512939],"type":"Point"}
}