{
  "type": "Feature",
  "properties": {
    "iso:country":"CH",
    "sg:address":"Funtenenstrasse 1 3860 Meiringen. Postfach 282",
    "sg:city":"Meiringen",
    "sg:orig_category":"Elektroinstallation",
    "sg:phone":"+41 71 383 26 83",
    "sg:postcode":"3860",
    "sg:province":"Bern",
    "wof:name":"Egger S. Gmbh",
    "wof:placetype":"venue"
},
  "geometry": {"coordinates":[9.269238472,47.4380226135],"type":"Point"}
}