{
  "type": "Feature",
  "properties": {
    "iso:country":"CH",
    "sg:address":"Hauptstrasse 83",
    "sg:city":"Rorschach",
    "sg:orig_category":"Detailhandel mit Schuhen",
    "sg:phone":"+41 71 840 09 55",
    "sg:postcode":"9400",
    "sg:province":"St. Gallen",
    "wof:name":"Dosenbach Schuhe",
    "wof:placetype":"venue"
},
  "geometry": {"coordinates":[9.4907360077,47.4788475037],"type":"Point"}
}