{
  "type": "Feature",
  "properties": {
    "iso:country":"CH",
    "sg:address":"M\u00fcnsterberg 2/4 4051 Basel. Postfach",
    "sg:city":"Basel",
    "sg:orig_category":"Herstellung von Oberbekleidung",
    "sg:phone":"+41 61 272 53 34",
    "sg:postcode":"4001",
    "sg:province":"Basel-Stadt",
    "wof:name":"Metzger & Lampert Ag Boutique",
    "wof:placetype":"venue"
},
  "geometry": {"coordinates":[7.591122,47.555134],"type":"Point"}
}