{
  "type": "Feature",
  "properties": {
    "iso:country":"CH",
    "sg:address":"Talstrasse 5",
    "sg:city":"Zollikon",
    "sg:orig_category":"Informatikdienste",
    "sg:phone":"+41 31 765 50 63",
    "sg:postcode":"8702",
    "sg:province":"Z\u00fcrich",
    "wof:name":"Mfb-geoconsulting Gmbh",
    "wof:placetype":"venue"
},
  "geometry": {"coordinates":[-82.59181976319999,33.4613304138],"type":"Point"}
}