{
  "type": "Feature",
  "properties": {
    "iso:country":"CH",
    "sg:address":"M\u00fchlebr\u00fccke 2",
    "sg:city":"Biel/bienne",
    "sg:orig_category":"Unclassifiable Establishments",
    "sg:postcode":"2502",
    "sg:province":"Bern",
    "wof:name":"Bodler Industries Ag",
    "wof:placetype":"venue"
},
  "geometry": {"coordinates":[7.243871212,47.1399307251],"type":"Point"}
}