{
  "type": "Feature",
  "properties": {
    "iso:country":"CH",
    "sg:address":"Neuberg 14",
    "sg:city":"Erlinsbach",
    "sg:orig_category":"Unclassifiable Establishments",
    "sg:postcode":"5018",
    "sg:province":"Solothurn",
    "wof:name":"Wenger Ag, Gartenbau",
    "wof:placetype":"venue"
},
  "geometry": {"coordinates":[8.002623558,47.410949707],"type":"Point"}
}