{
  "type": "Feature",
  "properties": {
    "iso:country":"CH",
    "sg:address":"Rue Des Lilas 16",
    "sg:city":"Del\u00e9mont",
    "sg:orig_category":"Betrieb von Taxis",
    "sg:phone":"+41 79 251 01 00",
    "sg:postcode":"2800",
    "sg:province":"Jura",
    "wof:name":"Paul Broquet Aat Taxis",
    "wof:placetype":"venue"
},
  "geometry": {"coordinates":[7.356797,47.36729],"type":"Point"}
}