{
  "type": "Feature",
  "properties": {
    "iso:country":"CH",
    "sg:address":"Linde",
    "sg:city":"Grosswangen",
    "sg:classifiers":[
        {
            "category":"Social Services",
            "subcategory":"Retirement Home",
            "type":"Services"
        }
    ],
    "sg:phone":"+41 41 984 29 29",
    "sg:postcode":"6022",
    "sg:province":"Luzern",
    "sg:tags":[
        "pflegeheime",
        "u",
        "alters"
    ],
    "wof:name":"Betagtenzentrum Linde Alters-& Pflegeheim",
    "wof:placetype":"venue"
},
  "geometry": {"coordinates":[8.051434,47.133263],"type":"Point"}
}