{
  "type": "Feature",
  "properties": {
    "iso:country":"CH",
    "sg:address":"6672",
    "sg:city":"Gordevio",
    "sg:orig_category":"Kinderkrippen U horte Vorschulen, Kinderg\u00e4rten",
    "sg:postcode":"6672",
    "sg:province":"Ticino",
    "wof:name":"Scuola Materna E Asilo Suore Sacra Famiglia",
    "wof:placetype":"venue"
},
  "geometry": {"coordinates":[8.7423295975,46.225151062],"type":"Point"}
}