{
  "type": "Feature",
  "properties": {
    "iso:country":"CH",
    "sg:address":"Montreuxstrasse 234f",
    "sg:city":"Zweisimmen",
    "sg:orig_category":"Grosshandel mit Getr\u00e4nken",
    "sg:postcode":"3770",
    "sg:province":"Bern",
    "wof:name":"M\u00e4der Getr\u00e4nke Ag",
    "wof:placetype":"venue"
},
  "geometry": {"coordinates":[7.3739881516,46.5546455383],"type":"Point"}
}