{
  "type": "Feature",
  "properties": {
    "iso:country":"CH",
    "sg:address":"Vulkanstrasse 35",
    "sg:city":"Z\u00fcrich",
    "sg:orig_category":"R\u00fcckgewinnung U Vorbereitung f\u00fcr die Wiederverwertung Recycling von nichtmetallischen Altmaterialien",
    "sg:phone":"+41 41 480 33 40",
    "sg:postcode":"8048",
    "sg:province":"Z\u00fcrich",
    "wof:name":"White Recycling Gmbh",
    "wof:placetype":"venue"
},
  "geometry": {"coordinates":[8.0499401093,46.9792098999],"type":"Point"}
}