{
  "type": "Feature",
  "properties": {
    "iso:country":"CH",
    "sg:address":"Langmattstrasse 24",
    "sg:city":"Aarburg",
    "sg:orig_category":"Maler U Glasergewerbe Malerei",
    "sg:postcode":"4663",
    "sg:province":"Aargau",
    "wof:name":"Maria Trapp-weissenbach",
    "wof:placetype":"venue"
},
  "geometry": {"coordinates":[7.9062919617,47.331489563],"type":"Point"}
}