{
  "type": "Feature",
  "properties": {
    "addr:full":"Kirchgasse 73 Remigen Aargau 5236",
    "addr:housenumber":"73",
    "addr:postcode":"5236",
    "addr:street":"Kirchgasse",
    "iso:country":"CH",
    "sg:address":"Kirchgasse 73",
    "sg:city":"Remigen",
    "sg:orig_category":"Bauschreinerei Herstellung von Konstruktionsteilen, Fertigbauteilen U Ausbauelementen aus Holz",
    "sg:phone":"+41 56 284 51 18",
    "sg:postcode":"5236",
    "sg:province":"Aargau",
    "wof:name":"Fehlmann Urs",
    "wof:placetype":"venue"
},
  "geometry": {"coordinates":[8.18794,47.516613],"type":"Point"}
}