{
  "type": "Feature",
  "properties": {
    "iso:country":"CH",
    "sg:address":"Hauptstrasse 22",
    "sg:city":"Kleind\u00f6ttingen",
    "sg:classifiers":[
        {
            "category":"Travel",
            "subcategory":"Hotels & Motels",
            "type":"Entertainment"
        }
    ],
    "sg:phone":"+41 71 636 14 55",
    "sg:postcode":"5314",
    "sg:province":"Aargau",
    "sg:tags":[
        "hotels",
        "mit",
        "restaurant"
    ],
    "wof:name":"Gasthaus Zum Bahnhof Berg Ag",
    "wof:placetype":"venue"
},
  "geometry": {"coordinates":[9.1742582321,47.5816459656],"type":"Point"}
}