{
  "type": "Feature",
  "properties": {
    "iso:country":"CH",
    "sg:address":"Gl\u00e4rnischstrasse 31",
    "sg:city":"Richterswil",
    "sg:orig_category":"Kauf U Verkauf von Immobilien auf eigene Rechnung",
    "sg:postcode":"8805",
    "sg:province":"Z\u00fcrich",
    "wof:name":"Hasler & Co",
    "wof:placetype":"venue"
},
  "geometry": {"coordinates":[8.6951084137,47.2092132568],"type":"Point"}
}