{
  "type": "Feature",
  "properties": {
    "iso:country":"CH",
    "sg:address":"Rue De Lausanne 44",
    "sg:city":"Morges",
    "sg:orig_category":"Instandhaltung U Reparatur von Automobilen",
    "sg:postcode":"1110",
    "sg:province":"Vaud",
    "wof:name":"Schlechten J.",
    "wof:placetype":"venue"
},
  "geometry": {"coordinates":[6.5037469864,46.514919281],"type":"Point"}
}