{
  "type": "Feature",
  "properties": {
    "addr:full":"Haselmatt 156a Wynigen Bern 3472",
    "addr:housenumber":"156a",
    "addr:postcode":"3472",
    "addr:street":"Haselmatt",
    "iso:country":"CH",
    "sg:address":"Haselmatt 156a",
    "sg:city":"Wynigen",
    "sg:orig_category":"Bauschreinerei Herstellung von Konstruktionsteilen, Fertigbauteilen U Ausbauelementen aus Holz",
    "sg:phone":"+41 34 415 11 88",
    "sg:postcode":"3472",
    "sg:province":"Bern",
    "wof:name":"Lips-friedli Ag",
    "wof:placetype":"venue"
},
  "geometry": {"coordinates":[7.667828,47.106079],"type":"Point"}
}