{
  "type": "Feature",
  "properties": {
    "iso:country":"CH",
    "sg:address":"G\u00e9n\u00e9ral-guisan Avenue 56",
    "sg:city":"Pully",
    "sg:orig_category":"Pensionskassen",
    "sg:phone":"+41 21 311 36 33",
    "sg:postcode":"1009",
    "sg:province":"Vaud",
    "wof:name":"Caisse De Pr\u00e9voyance En Faveur Des Agents Ext\u00e9rieurs De L'etablissement D'assurance Contre L'incendie Et Les \u00e9l\u00e9ments Naturelsdu Canton De Vaud.",
    "wof:placetype":"venue"
},
  "geometry": {"coordinates":[6.6470570564,46.5066375732],"type":"Point"}
}