{
  "type": "Feature",
  "properties": {
    "iso:country":"CH",
    "sg:address":"Rue Centrale 62 1880 Bex. Postfach",
    "sg:city":"Bex",
    "sg:orig_category":"Architektur U Ingenieurb\u00fcros",
    "sg:phone":"+41 61 401 47 02",
    "sg:postcode":"1880",
    "sg:province":"Vaud",
    "wof:name":"Bertschin Design",
    "wof:placetype":"venue"
},
  "geometry": {"coordinates":[7.541873,47.511112],"type":"Point"}
}