{
  "type": "Feature",
  "properties": {
    "iso:country":"CH",
    "sg:address":"Ziegelbr\u00fcckstrasse 22a",
    "sg:city":"Niederurnen",
    "sg:orig_category":"Herstellung von sonstigen Maschinen f\u00fcr bestimmte Verwendung",
    "sg:postcode":"8867",
    "sg:province":"Glarus",
    "wof:name":"Graphicus Ag, Niederurnen",
    "wof:placetype":"venue"
},
  "geometry": {"coordinates":[9.0556774139,47.1275749207],"type":"Point"}
}