{
  "type": "Feature",
  "properties": {
    "iso:country":"CH",
    "sg:address":"Route De Saint-julien 298",
    "sg:city":"Perly",
    "sg:orig_category":"Instandhaltung U Reparatur von Automobilen",
    "sg:phone":"+41 22 771 23 68",
    "sg:postcode":"1258",
    "sg:province":"Gen\u00e8ve",
    "wof:name":"Philippe Gillabert Carrosserie Moderne",
    "wof:placetype":"venue"
},
  "geometry": {"coordinates":[6.0910968781,46.1528549194],"type":"Point"}
}