{
  "type": "Feature",
  "properties": {
    "iso:country":"CH",
    "sg:address":"Gl\u00e4rnischstrasse 31",
    "sg:city":"Glarus",
    "sg:orig_category":"Allgemeiner Hochbau Zimmerei, Dachdeckerei, Bauspenglerei U Abdichtung",
    "sg:phone":"+41 31 951 01 20",
    "sg:postcode":"8750",
    "sg:province":"Glarus",
    "wof:name":"Keller & Sch\u00e4r Ag",
    "wof:placetype":"venue"
},
  "geometry": {"coordinates":[7.501724,46.925701],"type":"Point"}
}