{
  "type": "Feature",
  "properties": {
    "iso:country":"CH",
    "sg:address":"Seidengasse 17",
    "sg:city":"Meilen",
    "sg:orig_category":"Herstellung von Duft U K\u00f6rperpflegemitteln",
    "sg:postcode":"8706",
    "sg:province":"Z\u00fcrich",
    "wof:name":"Schwarz W. & Cie Ag",
    "wof:placetype":"venue"
},
  "geometry": {"coordinates":[8.6549291611,47.2660636902],"type":"Point"}
}