{
  "type": "Feature",
  "properties": {
    "iso:country":"CH",
    "sg:address":"Route Des Buchilles 42",
    "sg:city":"Boudry",
    "sg:orig_category":"Non-Classified Establishments",
    "sg:postcode":"2017",
    "sg:province":"Neuch\u00e2tel",
    "wof:name":"Thi\u00e9baud Mary Ecgf Etudes, Conseils, G\u00e9nie Civil Et Ferroviaire",
    "wof:placetype":"venue"
},
  "geometry": {"coordinates":[6.8298120499,46.9470405579],"type":"Point"}
}