{
  "type": "Feature",
  "properties": {
    "iso:country":"CH",
    "sg:address":"Avenue De La Sallaz 76",
    "sg:city":"Lausanne",
    "sg:orig_category":"Detailhandel mit fotografischen Artikeln",
    "sg:phone":"+41 21 653 94 74",
    "sg:postcode":"1010",
    "sg:province":"Vaud",
    "wof:name":"Photo-d\u00e9clic G\u00e9rald Brechb\u00fchl",
    "wof:placetype":"venue"
},
  "geometry": {"coordinates":[6.6469020844,46.5320777893],"type":"Point"}
}