{
  "type": "Feature",
  "properties": {
    "iso:country":"CH",
    "sg:address":"6390",
    "sg:city":"Engelberg",
    "sg:classifiers":[
        {
            "category":"Travel",
            "subcategory":"Hotels & Motels",
            "type":"Entertainment"
        }
    ],
    "sg:phone":"+41 41 637 12 26",
    "sg:postcode":"6390",
    "sg:province":"Obwalden",
    "sg:tags":[
        "hotels",
        "mit",
        "restaurant"
    ],
    "wof:name":"Bergrestaurant Untertr\u00fcbsee",
    "wof:placetype":"venue"
},
  "geometry": {"coordinates":[8.4227695465,46.8370513916],"type":"Point"}
}