{
  "type": "Feature",
  "properties": {
    "iso:country":"CH",
    "sg:address":"Z\u00fcrcherstrasse 6",
    "sg:city":"Schlieren",
    "sg:orig_category":"Saunas, Solarien, Fitnesszentren U \u00e4hnliches Tanzschulen, Tanzlehrer",
    "sg:phone":"+41 17302917",
    "sg:postcode":"8952",
    "sg:province":"Z\u00fcrich",
    "wof:name":"Heidi D\u00e4ster Meier Gymnastik-& Tanzschule",
    "wof:placetype":"venue"
},
  "geometry": {"coordinates":[8.4488449097,47.3974380493],"type":"Point"}
}