{
  "type": "Feature",
  "properties": {
    "addr:full":"7440 Andeer Graubunden 7440",
    "addr:housenumber":"7440",
    "addr:postcode":"7440",
    "addr:street":"Andeer Graubunden",
    "iso:country":"CH",
    "sg:address":"7440",
    "sg:city":"Andeer",
    "sg:orig_category":"Arbeitnehmerverb\u00e4nde",
    "sg:phone":"+41 32 384 65 02",
    "sg:postcode":"7440",
    "sg:province":"Graubunden",
    "wof:name":"Schweiz.verband Evangelischer Arbeitnehmer,sektion Lyss",
    "wof:placetype":"venue"
},
  "geometry": {"coordinates":[7.322186,47.099239],"type":"Point"}
}