{
  "type": "Feature",
  "properties": {
    "iso:country":"CH",
    "sg:address":"Les R\u00e2pes",
    "sg:city":"Vuisternens-romont",
    "sg:orig_category":"Stukkateurgewerbe, Gipserei U Verputzerei Tapeziererei",
    "sg:phone":"+41 91 792 17 69",
    "sg:postcode":"1687",
    "sg:province":"Fribourg",
    "wof:name":"Paolo Senn Impresa Di Pittura",
    "wof:placetype":"venue"
},
  "geometry": {"coordinates":[8.7395572662,46.1533927917],"type":"Point"}
}