{
  "type": "Feature",
  "properties": {
    "addr:full":"Therwilerstrasse 73 Bottmingen Basel-Landschaft 4103",
    "addr:housenumber":"73",
    "addr:postcode":"4103",
    "addr:street":"Therwilerstrasse",
    "iso:country":"CH",
    "sg:address":"Therwilerstrasse 73",
    "sg:city":"Bottmingen",
    "sg:orig_category":"Datenverarbeitungsdienste Unternehmensberatung",
    "sg:phone":"+41 62 772 21 72",
    "sg:postcode":"4103",
    "sg:province":"Basel-Landschaft",
    "wof:name":"Wiederkehr Solutions Gmbh Edv-dienstleist.& Schulung",
    "wof:placetype":"venue"
},
  "geometry": {"coordinates":[8.204543,47.26358],"type":"Point"}
}