{
  "type": "Feature",
  "properties": {
    "iso:country":"CH",
    "sg:address":"Chemin Du Bois 9",
    "sg:city":"Veyrier",
    "sg:orig_category":"Sportvereine Ballsport Volleyball",
    "sg:phone":"+41 22 774 06 15",
    "sg:postcode":"1255",
    "sg:province":"Gen\u00e8ve",
    "wof:name":"Volleyball-club Ch\u00eanois",
    "wof:placetype":"venue"
},
  "geometry": {"coordinates":[6.1747632027,46.1695671082],"type":"Point"}
}