{
  "type": "Feature",
  "properties": {
    "iso:country":"CH",
    "sg:address":"Seestrasse 441",
    "sg:city":"Z\u00fcrich",
    "sg:orig_category":"Sonstiger Grosshandel",
    "sg:phone":"+41 12213633",
    "sg:postcode":"8038",
    "sg:province":"Z\u00fcrich",
    "wof:name":"Alwarda Gmbh",
    "wof:placetype":"venue"
},
  "geometry": {"coordinates":[8.5371322632,47.3414421082],"type":"Point"}
}