{
  "type": "Feature",
  "properties": {
    "iso:country":"CH",
    "sg:address":"Sonnhalde 21",
    "sg:city":"Appenzell",
    "sg:classifiers":[
        {
            "category":"Social Services",
            "subcategory":"Retirement Home",
            "type":"Services"
        }
    ],
    "sg:phone":"+41 71 787 12 26",
    "sg:postcode":"9050",
    "sg:province":"Appenzell Innerhoden",
    "sg:tags":[
        "pflegeheime",
        "u",
        "alters"
    ],
    "wof:name":"B\u00fcrgerheim Appenzell",
    "wof:placetype":"venue"
},
  "geometry": {"coordinates":[9.41423,47.33448],"type":"Point"}
}