{
  "type": "Feature",
  "properties": {
    "iso:country":"CH",
    "sg:address":"Romelles Route Des 5",
    "sg:city":"Bellevue",
    "sg:orig_category":"Grosshandel mit Erzen U Metallen",
    "sg:phone":"+41 21 800 43 96",
    "sg:postcode":"1293",
    "sg:province":"Gen\u00e8ve",
    "wof:name":"Sona, Altaf Hussain Khan",
    "wof:placetype":"venue"
},
  "geometry": {"coordinates":[6.1551737785,46.2550239563],"type":"Point"}
}