{
  "type": "Feature",
  "properties": {
    "iso:country":"CH",
    "sg:address":"Zorten",
    "sg:city":"Vaz/obervaz",
    "sg:classifiers":[
        {
            "category":"Social Services",
            "subcategory":"Retirement Home",
            "type":"Services"
        }
    ],
    "sg:phone":"+41 91 911 21 11",
    "sg:postcode":"7082",
    "sg:province":"Graubunden",
    "sg:tags":[
        "pflegeheime",
        "u",
        "alters"
    ],
    "wof:name":"Casa Serena Abitazione Per Persone Anziane",
    "wof:placetype":"venue"
},
  "geometry": {"coordinates":[8.959033,46.013317],"type":"Point"}
}