{
  "type": "Feature",
  "properties": {
    "iso:country":"CH",
    "sg:address":"Brambergstrasse 30",
    "sg:city":"Luzern",
    "sg:orig_category":"Architektur U Ingenieurb\u00fcros Architekturb\u00fcros",
    "sg:phone":"+41 71 744 54 68",
    "sg:postcode":"6000",
    "sg:province":"Luzern",
    "wof:name":"Architekturb\u00fcro Litscher",
    "wof:placetype":"venue"
},
  "geometry": {"coordinates":[9.6278066635,47.4298095703],"type":"Point"}
}