{
  "type": "Feature",
  "properties": {
    "iso:country":"CH",
    "sg:address":"Kirchstr. 194 3098 K\u00f6niz. Postfach",
    "sg:city":"Wabern",
    "sg:orig_category":"Stukkateurgewerbe, Gipserei U Verputzerei",
    "sg:postcode":"3084",
    "sg:province":"Bern",
    "wof:name":"Andreoli Gebr. A. & R.",
    "wof:placetype":"venue"
},
  "geometry": {"coordinates":[7.437620163,46.9306983948],"type":"Point"}
}