{
  "type": "Feature",
  "properties": {
    "iso:country":"CH",
    "sg:address":"Route De Chaluet 32",
    "sg:city":"Court",
    "sg:orig_category":"G\u00fcterbef\u00f6rderung im Strassenverkehr",
    "sg:phone":"+41 32 497 92 95",
    "sg:postcode":"2738",
    "sg:province":"Bern",
    "wof:name":"Cano Transports S\u00e0rl",
    "wof:placetype":"venue"
},
  "geometry": {"coordinates":[7.3596038818,47.2421073914],"type":"Point"}
}