{
  "type": "Feature",
  "properties": {
    "iso:country":"CH",
    "sg:address":"Zentralstr. 66",
    "sg:city":"Biel/bienne",
    "sg:orig_category":"Grosshandel mit Erzen U Metallen Vermittlung von Immobilien",
    "sg:phone":"+41 26 912 03 04",
    "sg:postcode":"2500",
    "sg:province":"Bern",
    "wof:name":"Boland Sa",
    "wof:placetype":"venue"
},
  "geometry": {"coordinates":[7.0572118759,46.6404914856],"type":"Point"}
}