{
  "type": "Feature",
  "properties": {
    "iso:country":"CH",
    "sg:address":"Marktgasse 46 8400 Winterthur. Postfach 440",
    "sg:city":"Winterthur",
    "sg:orig_category":"Fachdetailhandel mit pharmazeutischen Produkten",
    "sg:phone":"+41 52 213 23 42",
    "sg:postcode":"8401",
    "sg:province":"Z\u00fcrich",
    "wof:name":"Kreyenb\u00fchl Christina, Sternen-apotheke",
    "wof:placetype":"venue"
},
  "geometry": {"coordinates":[8.7286653519,47.4997673035],"type":"Point"}
}