{
  "type": "Feature",
  "properties": {
    "iso:country":"CH",
    "sg:address":"Breitenstrasse 28",
    "sg:city":"Fulenbach",
    "sg:orig_category":"Grosshandel mit B\u00fcromaschinen Grosshandel mit Datenverarbeitungsger\u00e4ten",
    "sg:phone":"+41 62 926 39 84",
    "sg:postcode":"4629",
    "sg:province":"Solothurn",
    "wof:name":"Ioservice Gmbh",
    "wof:placetype":"venue"
},
  "geometry": {"coordinates":[7.8368968964,47.2739868164],"type":"Point"}
}