{
  "type": "Feature",
  "properties": {
    "iso:country":"CH",
    "sg:address":"Rheinsfelderstrasse 24",
    "sg:city":"Eglisau/z\u00fcrich",
    "sg:orig_category":"Shopping U Fachgesch\u00e4fte, Lederwaren",
    "sg:phone":"+41 18673429",
    "sg:postcode":"8193",
    "sg:province":"Z\u00fcrich",
    "wof:name":"Antiquit\u00e4ten \u00b4zum Buurehus\u00b4",
    "wof:placetype":"venue"
},
  "geometry": {"coordinates":[8.514608,47.574917],"type":"Point"}
}