{
  "type": "Feature",
  "properties": {
    "iso:country":"CH",
    "sg:address":"Selnaustrasse 32",
    "sg:city":"Z\u00fcrich",
    "sg:orig_category":"Non-Classified Establishments",
    "sg:postcode":"8001",
    "sg:province":"Z\u00fcrich",
    "wof:name":"Maria Isabel Haldner Galerie Zeitgen\u00f6ssische Kunst",
    "wof:placetype":"venue"
},
  "geometry": {"coordinates":[8.5316209793,47.3712844849],"type":"Point"}
}