{
  "type": "Feature",
  "properties": {
    "addr:full":"Immeuble Imp\u00e9rial Crans-sur-sierre Valais 3963",
    "addr:postcode":"3963",
    "iso:country":"CH",
    "sg:address":"Immeuble Imp\u00e9rial",
    "sg:city":"Crans-sur-sierre",
    "sg:orig_category":"Detailhandel mit Brillen U anderen Sehhilfen Fachdetailhandel in Verkaufsr\u00e4umen",
    "sg:phone":"+41 27 481 11 49",
    "sg:postcode":"3963",
    "sg:province":"Valais",
    "wof:name":"L'optique Du Plateau, Roy Fran\u00e7ois",
    "wof:placetype":"venue"
},
  "geometry": {"coordinates":[7.469152,46.305954],"type":"Point"}
}