{
  "type": "Feature",
  "properties": {
    "iso:country":"CH",
    "sg:address":"Rue Du Mont 3",
    "sg:city":"Crissier",
    "sg:orig_category":"Instandhaltung U Reparatur von Automobilen",
    "sg:phone":"+41 21 634 57 21",
    "sg:postcode":"1023",
    "sg:province":"Vaud",
    "wof:name":"Emilio Todeschini Garage Du Mont",
    "wof:placetype":"venue"
},
  "geometry": {"coordinates":[6.5773968697,46.5389137268],"type":"Point"}
}