{
  "type": "Feature",
  "properties": {
    "iso:country":"CH",
    "sg:address":"Dorf 93",
    "sg:city":"Walzenhausen",
    "sg:orig_category":"Zahnarztpraxen",
    "sg:phone":"+41 71 888 30 10",
    "sg:postcode":"9428",
    "sg:province":"Appenzell Ausserrhoden",
    "wof:name":"Dr. Med. Dent. Eric Seger Zahnarzt",
    "wof:placetype":"venue"
},
  "geometry": {"coordinates":[9.6030273438,47.4509963989],"type":"Point"}
}