{
  "type": "Feature",
  "properties": {
    "iso:country":"CH",
    "sg:address":"Sonnhaldeweg 14",
    "sg:city":"Ebikon",
    "sg:orig_category":"Softwareentwicklung U beratung",
    "sg:phone":"+41 79 341 99 51",
    "sg:postcode":"6030",
    "sg:province":"Luzern",
    "wof:name":"Hufschmid Hans",
    "wof:placetype":"venue"
},
  "geometry": {"coordinates":[8.332616806,47.0805778503],"type":"Point"}
}