{
  "type": "Feature",
  "properties": {
    "iso:country":"CH",
    "sg:address":"B\u00fcrenstrasse 27",
    "sg:city":"Arch",
    "sg:orig_category":"Handel mit Motorr\u00e4dern, Teilen U Zubeh\u00f6r Instandhaltung U Reparatur von Motorr\u00e4dern",
    "sg:phone":"+41 32 679 09 01",
    "sg:postcode":"3296",
    "sg:province":"Bern",
    "wof:name":"Moto Poschung",
    "wof:placetype":"venue"
},
  "geometry": {"coordinates":[7.4234471321,47.1645469666],"type":"Point"}
}