{
  "type": "Feature",
  "properties": {
    "iso:country":"CH",
    "sg:address":"Fl\u00e4ckehof 78",
    "sg:city":"Rothenburg",
    "sg:orig_category":"Grosshandel mit Textilien",
    "sg:phone":"+41 41 280 60 56",
    "sg:postcode":"6023",
    "sg:province":"Luzern",
    "wof:name":"Shirtolino Gmbh",
    "wof:placetype":"venue"
},
  "geometry": {"coordinates":[8.2669448853,47.0930137634],"type":"Point"}
}