{
  "type": "Feature",
  "properties": {
    "iso:country":"CH",
    "sg:address":"Karl V\u00f6lkerstrasse 2",
    "sg:city":"Heerbrugg",
    "sg:orig_category":"Elektrizit\u00e4tsversorgung Herstellung von \u00d6fen U Brennern",
    "sg:phone":"+41 41 497 00 17",
    "sg:postcode":"9435",
    "sg:province":"St. Gallen",
    "wof:name":"Egs Energie Genossenschaft Schwarzenberg",
    "wof:placetype":"venue"
},
  "geometry": {"coordinates":[8.178735733,47.0170669556],"type":"Point"}
}