{
  "type": "Feature",
  "properties": {
    "iso:country":"CH",
    "sg:address":"Palazzo Impregest 6926 Montagnola. Postfach",
    "sg:city":"Grancia",
    "sg:orig_category":"Herstellung von medizinischen U chirurgischen Ger\u00e4ten sowie orthop\u00e4dischen Vorrichtungen",
    "sg:postcode":"6916",
    "sg:province":"Ticino",
    "wof:name":"Medcenter Sa",
    "wof:placetype":"venue"
},
  "geometry": {"coordinates":[8.9169063568,45.981918335],"type":"Point"}
}