{
  "type": "Feature",
  "properties": {
    "iso:country":"CH",
    "sg:address":"2926",
    "sg:city":"Boncourt",
    "sg:orig_category":"Sportvereine Sch\u00fctzen",
    "sg:postcode":"2926",
    "sg:province":"Jura",
    "wof:name":"St\u00e9 De Tir Armes R\u00e9unies",
    "wof:placetype":"venue"
},
  "geometry": {"coordinates":[7.0156798363,47.4972915649],"type":"Point"}
}