{
  "type": "Feature",
  "properties": {
    "iso:country":"CH",
    "sg:address":"Route Du Simplon 67",
    "sg:city":"Ardon",
    "sg:orig_category":"Drogerien",
    "sg:phone":"+41 27 306 18 00",
    "sg:postcode":"1957",
    "sg:province":"Valais",
    "wof:name":"Naturellement V\u00f4tre Gmbh Produits Bio & Naturels",
    "wof:placetype":"venue"
},
  "geometry": {"coordinates":[7.254336834,46.2080192566],"type":"Point"}
}