{
  "type": "Feature",
  "properties": {
    "iso:country":"CH",
    "sg:address":"Ecole",
    "sg:city":"Morlon",
    "sg:classifiers":[
        {
            "category":"Banks & Credit Unions",
            "subcategory":"Bank",
            "type":"Services"
        }
    ],
    "sg:phone":"+41 2925212",
    "sg:postcode":"1638",
    "sg:province":"Fribourg",
    "wof:name":"Banque Raiffeisen",
    "wof:placetype":"venue"
},
  "geometry": {"coordinates":[7.084085,46.624653],"type":"Point"}
}