{
  "type": "Feature",
  "properties": {
    "iso:country":"CH",
    "sg:address":"Therwilerstrasse 7-9",
    "sg:city":"Ettingen",
    "sg:orig_category":"Pensionskassen",
    "sg:phone":"+41 61 726 11 11",
    "sg:postcode":"4107",
    "sg:province":"Basel-Landschaft",
    "wof:name":"Personalvorsorgestiftung Jordan",
    "wof:placetype":"venue"
},
  "geometry": {"coordinates":[7.5473480225,47.4841918945],"type":"Point"}
}