{
  "type": "Feature",
  "properties": {
    "iso:country":"CH",
    "sg:address":"Rte Des Acacias 41",
    "sg:city":"Gen\u00e8ve",
    "sg:orig_category":"Tankstellen",
    "sg:phone":"+41 22 343 59 60",
    "sg:postcode":"1200",
    "sg:province":"Gen\u00e8ve",
    "wof:name":"Station Shell, Savoie Michel",
    "wof:placetype":"venue"
},
  "geometry": {"coordinates":[6.1319541931,46.1896705627],"type":"Point"}
}