{
  "type": "Feature",
  "properties": {
    "iso:country":"CH",
    "sg:address":"Industriestrasse 9552 Bronschhofen. Postfach",
    "sg:city":"Bronschhofen",
    "sg:orig_category":"Pensionskassen",
    "sg:postcode":"9552",
    "sg:province":"St. Gallen",
    "wof:name":"F\u00fcrsorgefonds Der Thyssen (schweiz) Ag",
    "wof:placetype":"venue"
},
  "geometry": {"coordinates":[9.0344800949,47.4732666016],"type":"Point"}
}