{
  "type": "Feature",
  "properties": {
    "iso:country":"CH",
    "sg:address":"Grunerstrasse 20",
    "sg:city":"Burgdorf",
    "sg:orig_category":"Grosshandel mit sonstigen Halbwaren",
    "sg:postcode":"3400",
    "sg:province":"Bern",
    "wof:name":"Vvs Lm Gmbh",
    "wof:placetype":"venue"
},
  "geometry": {"coordinates":[7.6272268295,47.0495986938],"type":"Point"}
}