{
  "type": "Feature",
  "properties": {
    "iso:country":"CH",
    "sg:address":"Eichenweg 13",
    "sg:city":"B\u00fcsserach",
    "sg:orig_category":"Politische Parteien FDP",
    "sg:postcode":"4227",
    "sg:province":"Solothurn",
    "wof:name":"Fdp Ortspartei Davos",
    "wof:placetype":"venue"
},
  "geometry": {"coordinates":[9.8219165802,46.7939949036],"type":"Point"}
}