{
  "type": "Feature",
  "properties": {
    "iso:country":"CH",
    "sg:address":"Schaffhauserstrasse 7 8152 Glattbrugg. Postfach",
    "sg:city":"Glattbrugg",
    "sg:orig_category":"Sanit\u00e4r, Heizungs U L\u00fcftungsinstallation",
    "sg:postcode":"8152",
    "sg:province":"Z\u00fcrich",
    "wof:name":"Kaldewei Franz Ag Sanit\u00e4re Produkte; Vermittlung, Vertrieb. Warenhandel",
    "wof:placetype":"venue"
},
  "geometry": {"coordinates":[7.8675351143,47.3397026062],"type":"Point"}
}