{
  "type": "Feature",
  "properties": {
    "addr:full":"Willadingenstrasse 10 Koppigen Bern 3425",
    "addr:housenumber":"10",
    "addr:postcode":"3425",
    "addr:street":"Willadingenstrasse",
    "iso:country":"CH",
    "sg:address":"Willadingenstrasse 10",
    "sg:city":"Koppigen",
    "sg:orig_category":"Bauspenglerei Zimmerei, Dachdeckerei, Bauspenglerei U Abdichtung",
    "sg:phone":"+41 34 413 11 36",
    "sg:postcode":"3425",
    "sg:province":"Bern",
    "wof:name":"Baumberger Heinz",
    "wof:placetype":"venue"
},
  "geometry": {"coordinates":[7.605125,47.133377],"type":"Point"}
}