{
  "type": "Feature",
  "properties": {
    "iso:country":"CH",
    "sg:address":"Bischofszellerstrasse 311 9212 Arnegg. Postfach",
    "sg:city":"Arnegg",
    "sg:orig_category":"Allgemeiner Hoch U Tiefbau",
    "sg:postcode":"9212",
    "sg:province":"St. Gallen",
    "wof:name":"Manser Arnegg Zweigniederlassung Der Kibag Strassen Und Tiefbau",
    "wof:placetype":"venue"
},
  "geometry": {"coordinates":[9.254779,47.44051],"type":"Point"}
}