{
  "type": "Feature",
  "properties": {
    "iso:country":"CH",
    "sg:address":"Seegartenstrasse 6",
    "sg:city":"Z\u00fcrich",
    "sg:orig_category":"Unternehmensberatung",
    "sg:phone":"+41 13896070",
    "sg:postcode":"8008",
    "sg:province":"Z\u00fcrich",
    "wof:name":"Brainwork M. Arter Unternehmensberatung F\u00fcr Oeffentlichkeitsarbeit",
    "wof:placetype":"venue"
},
  "geometry": {"coordinates":[8.5481863022,47.3612174988],"type":"Point"}
}