{
  "type": "Feature",
  "properties": {
    "iso:country":"CH",
    "sg:address":"Boulevard Du Pont-d'arve 57",
    "sg:city":"Gen\u00e8ve",
    "sg:orig_category":"Detailhandel mit Bekleidung Herstellung von Arbeits U Berufsbekleidung",
    "sg:phone":"+41 22 329 11 55",
    "sg:postcode":"1205",
    "sg:province":"Gen\u00e8ve",
    "wof:name":"Profess, Herter Karin",
    "wof:placetype":"venue"
},
  "geometry": {"coordinates":[6.190062,46.196907],"type":"Point"}
}