{
  "type": "Feature",
  "properties": {
    "iso:country":"CH",
    "sg:address":"1700",
    "sg:city":"Fribourg",
    "sg:orig_category":"Interessenvertretungen",
    "sg:postcode":"1700",
    "sg:province":"Fribourg",
    "wof:name":"Fondation Pour La Promotion De L'enseignement Social Chr\u00e9tien",
    "wof:placetype":"venue"
},
  "geometry": {"coordinates":[7.1746201515,46.8062400818],"type":"Point"}
}