{
  "type": "Feature",
  "properties": {
    "iso:country":"CH",
    "sg:address":"Custerstrasse 7",
    "sg:city":"Balgach",
    "sg:orig_category":"Interessenvertretungen U sonstige Vereinigungen",
    "sg:phone":"+41 71 722 35 33",
    "sg:postcode":"9436",
    "sg:province":"St. Gallen",
    "wof:name":"Saeev",
    "wof:placetype":"venue"
},
  "geometry": {"coordinates":[9.5961008072,47.4040985107],"type":"Point"}
}