{
  "type": "Feature",
  "properties": {
    "iso:country":"CH",
    "sg:address":"Florastrasse 7",
    "sg:city":"Adliswil",
    "sg:orig_category":"Filmverleih U Videoprogrammanbieter",
    "sg:phone":"+41 17101444",
    "sg:postcode":"8134",
    "sg:province":"Z\u00fcrich",
    "wof:name":"Eberle Filmequipment Verleih",
    "wof:placetype":"venue"
},
  "geometry": {"coordinates":[8.5245780945,47.311706543],"type":"Point"}
}