{
  "type": "Feature",
  "properties": {
    "addr:full":"Rue Monnier 1 Gen\u00e8ve Gen\u00e8ve 1206",
    "addr:housenumber":"1",
    "addr:postcode":"1206",
    "addr:street":"Rue Monnier",
    "iso:country":"CH",
    "sg:address":"Rue Monnier 1",
    "sg:city":"Gen\u00e8ve",
    "sg:orig_category":"Arztpraxen",
    "sg:phone":"+41 22 346 08 33",
    "sg:postcode":"1206",
    "sg:province":"Gen\u00e8ve",
    "wof:name":"Dr M\u00e9d. Jean-emmanuel Strasser M\u00e9decin G\u00e9n\u00e9raliste",
    "wof:placetype":"venue"
},
  "geometry": {"coordinates":[6.152126,46.195339],"type":"Point"}
}