{
  "type": "Feature",
  "properties": {
    "iso:country":"CH",
    "sg:address":"Av.des Quatre Marroniers 28",
    "sg:city":"Yverdon-les-bains",
    "sg:orig_category":"Detailhandel mit Zeitungen U Zeitschriften Kioske",
    "sg:phone":"+41 24 426 56 36",
    "sg:postcode":"1400",
    "sg:province":"Vaud",
    "wof:name":"Lucien Valceschini Kiosque Des Marronniers",
    "wof:placetype":"venue"
},
  "geometry": {"coordinates":[6.6527061462,46.777507782],"type":"Point"}
}