{
  "type": "Feature",
  "properties": {
    "iso:country":"CH",
    "sg:address":"Route Aloys-fauquez 111",
    "sg:city":"Lausanne",
    "sg:orig_category":"Detailhandel mit Radio U Fernsehger\u00e4ten",
    "sg:phone":"+41 21 648 44 44",
    "sg:postcode":"1018",
    "sg:province":"Vaud",
    "wof:name":"Egea D\u00e9pannage Vid\u00e9o Tv Radio",
    "wof:placetype":"venue"
},
  "geometry": {"coordinates":[6.6336550713,46.5384216309],"type":"Point"}
}