{
  "type": "Feature",
  "properties": {
    "addr:full":"Stutzrain 9 Ettingen Basel-Landschaft 4107",
    "addr:housenumber":"9",
    "addr:postcode":"4107",
    "addr:street":"Stutzrain",
    "iso:country":"CH",
    "sg:address":"Stutzrain 9",
    "sg:city":"Ettingen",
    "sg:orig_category":"Architektur U Ingenieurb\u00fcros",
    "sg:postcode":"4107",
    "sg:province":"Basel-Landschaft",
    "wof:name":"Cms Engineering, M. Stamm",
    "wof:placetype":"venue"
},
  "geometry": {"coordinates":[7.551419,47.486279],"type":"Point"}
}