{
  "type": "Feature",
  "properties": {
    "iso:country":"CH",
    "sg:address":"Via Pico 8 6900 Lugano. Postfach",
    "sg:city":"Calprino",
    "sg:classifiers":[
        {
            "category":"Travel",
            "subcategory":"Hotels & Motels",
            "type":"Entertainment"
        }
    ],
    "sg:postcode":"6900",
    "sg:province":"Ticino",
    "sg:tags":[
        "hotels",
        "mit",
        "restaurant"
    ],
    "wof:name":"Helfensberger Eugenio Carlo",
    "wof:placetype":"venue"
},
  "geometry": {"coordinates":[8.9700689316,46.0065689087],"type":"Point"}
}