{
  "type": "Feature",
  "properties": {
    "iso:country":"CH",
    "sg:address":"Weidstrasse 23",
    "sg:city":"Zug",
    "sg:orig_category":"Wirtschaftspr\u00fcfung, Steuerberatung U Treuhand",
    "sg:postcode":"6300",
    "sg:province":"Zug",
    "wof:name":"Treuhandb\u00fcro K. Neininger",
    "wof:placetype":"venue"
},
  "geometry": {"coordinates":[8.5287704468,47.1695098877],"type":"Point"}
}