{
  "type": "Feature",
  "properties": {
    "iso:country":"CH",
    "sg:address":"Chemin De Mont\u00e9clard 16",
    "sg:city":"Epalinges",
    "sg:orig_category":"Unternehmensberatung",
    "sg:phone":"+41 21 784 25 13",
    "sg:postcode":"1066",
    "sg:province":"Vaud",
    "wof:name":"Koch Walter E.",
    "wof:placetype":"venue"
},
  "geometry": {"coordinates":[6.6616368294,46.5490036011],"type":"Point"}
}