{
  "type": "Feature",
  "properties": {
    "addr:full":"Schulhausstrasse 9 Ennetb\u00fcrgen Nidwalden 6373",
    "addr:housenumber":"9",
    "addr:postcode":"6373",
    "addr:street":"Schulhausstrasse",
    "iso:country":"CH",
    "sg:address":"Schulhausstrasse 9",
    "sg:city":"Ennetb\u00fcrgen",
    "sg:orig_category":"Arztpraxen",
    "sg:phone":"+41 41 624 93 93",
    "sg:postcode":"6373",
    "sg:province":"Nidwalden",
    "wof:name":"Dr.med.peter G\u00fcrber Spezialarzt Fmh",
    "wof:placetype":"venue"
},
  "geometry": {"coordinates":[8.41592,46.98415],"type":"Point"}
}