{
  "type": "Feature",
  "properties": {
    "iso:country":"CH",
    "sg:address":"Kettenackerweg 19",
    "sg:city":"Riehen",
    "sg:orig_category":"Verlagsgewerbe",
    "sg:phone":"+41 61 641 64 53",
    "sg:postcode":"4125",
    "sg:province":"Basel-Stadt",
    "wof:name":"In Verlag R\u00fcger & Hoenen",
    "wof:placetype":"venue"
},
  "geometry": {"coordinates":[7.6535210609,47.5895690918],"type":"Point"}
}