{
  "type": "Feature",
  "properties": {
    "iso:country":"CH",
    "sg:address":"Kaffeegasse 16",
    "sg:city":"Altnau",
    "sg:orig_category":"Detailhandel mit Textilien Innendekorationsateliers",
    "sg:phone":"+41 71 695 11 88",
    "sg:postcode":"8595",
    "sg:province":"Thurgau",
    "wof:name":"Hermann Kn\u00f6pfli Bettwaren & Polsterei",
    "wof:placetype":"venue"
},
  "geometry": {"coordinates":[9.2556190491,47.6087379456],"type":"Point"}
}