{
  "type": "Feature",
  "properties": {
    "iso:country":"CH",
    "sg:address":"Chemin Champ-des-pierres 9",
    "sg:city":"Mont-sur-lausanne",
    "sg:orig_category":"Maler U Glasergewerbe Sonstiger Fachdetailhandel in Verkaufsr\u00e4umen",
    "sg:phone":"+41 21 652 87 30",
    "sg:postcode":"1052",
    "sg:province":"Vaud",
    "wof:name":"Dufour Alain",
    "wof:placetype":"venue"
},
  "geometry": {"coordinates":[6.6365947723,46.5482368469],"type":"Point"}
}