{
  "type": "Feature",
  "properties": {
    "iso:country":"CH",
    "sg:address":"Rue Du Maupas 17",
    "sg:city":"Lausanne",
    "sg:orig_category":"RESTAURANTS: TEA-ROOMS",
    "sg:phone":"+41 21 646 54 12",
    "sg:postcode":"1004",
    "sg:province":"Vaud",
    "wof:name":"La Nonna Sa",
    "wof:placetype":"venue"
},
  "geometry": {"coordinates":[6.6257758141,46.5247993469],"type":"Point"}
}