{
  "type": "Feature",
  "properties": {
    "iso:country":"CH",
    "sg:address":"Meierackerstrasse 23",
    "sg:city":"Uster",
    "sg:orig_category":"Herstellung von Sportger\u00e4ten",
    "sg:postcode":"8610",
    "sg:province":"Z\u00fcrich",
    "wof:name":"Inter-fish Pf\u00e4ffikon (sz) Ag",
    "wof:placetype":"venue"
},
  "geometry": {"coordinates":[8.7784986496,47.2003517151],"type":"Point"}
}