{
  "type": "Feature",
  "properties": {
    "addr:full":"Grand'rue. Estavayer-le-lac Fribourg 1470",
    "addr:postcode":"estavayer-le-lac;1470",
    "iso:country":"CH",
    "sg:address":"Grand'rue.",
    "sg:city":"Estavayer-le-lac",
    "sg:orig_category":"Allgemeiner Hoch U Tiefbau",
    "sg:phone":"+41 24 424 11 99",
    "sg:postcode":"1470",
    "sg:province":"Fribourg",
    "wof:name":"Ernest Gabella Sa",
    "wof:placetype":"venue"
},
  "geometry": {"coordinates":[6.846984,46.849445],"type":"Point"}
}