{
  "type": "Feature",
  "properties": {
    "iso:country":"CH",
    "sg:address":"Hofstettenstrasse 14 3600 Thun. Postfach 145",
    "sg:city":"Thun",
    "sg:orig_category":"Schulpflegen",
    "sg:phone":"+41 71 931 27 70",
    "sg:postcode":"3602",
    "sg:province":"Bern",
    "wof:name":"Schulgemeinde Kirchberg Sekretariat",
    "wof:placetype":"venue"
},
  "geometry": {"coordinates":[9.0388717651,47.4116020203],"type":"Point"}
}