{
  "type": "Feature",
  "properties": {
    "iso:country":"CH",
    "sg:address":"Tripolistrasse 12",
    "sg:city":"Winznau",
    "sg:orig_category":"Hoch U Tiefbau",
    "sg:phone":"+41 62 295 44 34",
    "sg:postcode":"4652",
    "sg:province":"Solothurn",
    "wof:name":"Cervi Ag Baugesch\u00e4ft",
    "wof:placetype":"venue"
},
  "geometry": {"coordinates":[7.9180779457,47.3705825806],"type":"Point"}
}