{
  "type": "Feature",
  "properties": {
    "iso:country":"CH",
    "sg:address":"Rue Des Noyers 11 Case Postale 58",
    "sg:city":"Neuch\u00e2tel",
    "sg:classifiers":[
        {
            "category":"Manufacturing",
            "subcategory":"Paper Products",
            "type":"Manufacturing & Wholesale Goods"
        }
    ],
    "sg:phone":"+41 32 731 93 31",
    "sg:postcode":"2003",
    "sg:province":"Neuch\u00e2tel",
    "sg:tags":[
        "finished",
        "cardboard",
        "-"
    ],
    "wof:name":"Pierre Lenzlinger Sa",
    "wof:placetype":"venue"
},
  "geometry": {"coordinates":[1.3407150507,49.287437439],"type":"Point"}
}