{
  "type": "Feature",
  "properties": {
    "iso:country":"CH",
    "sg:address":"Turbistrasse 14 6280 Hochdorf. Postfach 844",
    "sg:city":"Hochdorf",
    "sg:orig_category":"Architektur U Ingenieurb\u00fcros Architekturb\u00fcros",
    "sg:phone":"+41 31 351 33 53",
    "sg:postcode":"6281",
    "sg:province":"Luzern",
    "wof:name":"Architekturb\u00fcro Emch & M\u00fcller",
    "wof:placetype":"venue"
},
  "geometry": {"coordinates":[7.470109,46.942375],"type":"Point"}
}