{
  "type": "Feature",
  "properties": {
    "iso:country":"CH",
    "sg:address":"R\u00f6merstrasse 142",
    "sg:city":"Stadel(winterthur)",
    "sg:orig_category":"Herstellung von Schl\u00f6ssern U Beschl\u00e4gen Schlossereien",
    "sg:postcode":"8404",
    "sg:province":"Z\u00fcrich",
    "wof:name":"Karl Aschwanden Ag",
    "wof:placetype":"venue"
},
  "geometry": {"coordinates":[8.75822258,47.5065689087],"type":"Point"}
}