{
  "type": "Feature",
  "properties": {
    "iso:country":"CH",
    "sg:address":"Felsenaustrasse 61",
    "sg:city":"Chur",
    "sg:orig_category":"Campingpl\u00e4tze",
    "sg:phone":"+41 81 284 22 83",
    "sg:postcode":"7000",
    "sg:province":"Graubunden",
    "wof:name":"Camp Au Chur",
    "wof:placetype":"venue"
},
  "geometry": {"coordinates":[9.507919,46.861359],"type":"Point"}
}