{
  "type": "Feature",
  "properties": {
    "iso:country":"CH",
    "sg:address":"Ostring 58 3006 Bern. Postfach",
    "sg:city":"Bern",
    "sg:orig_category":"Sonstiger Grosshandel",
    "sg:phone":"+41 31 351 90 18",
    "sg:postcode":"3005",
    "sg:province":"Bern",
    "wof:name":"Palma Gjilan Gmbh Waren; Importieren, Exportieren, Vertreiben Usw.",
    "wof:placetype":"venue"
},
  "geometry": {"coordinates":[7.4714040756,46.9442863464],"type":"Point"}
}