{
  "type": "Feature",
  "properties": {
    "iso:country":"CH",
    "sg:address":"Dorfstrasse 35",
    "sg:city":"Allenwinden",
    "sg:classifiers":[
        {
            "category":"Restaurant",
            "type":"Food & Drink"
        }
    ],
    "sg:phone":"+41 41 711 09 25",
    "sg:postcode":"6319",
    "sg:province":"Zug",
    "wof:name":"Gasthaus L\u00f6wen",
    "wof:placetype":"venue"
},
  "geometry": {"coordinates":[8.5533771515,47.1664733887],"type":"Point"}
}