{
  "type": "Feature",
  "properties": {
    "iso:country":"CH",
    "sg:address":"Sonnenweg 130",
    "sg:city":"Kestenholz",
    "sg:orig_category":"Vereine Vogel-& Naturschutz",
    "sg:phone":"+41 62 393 25 00",
    "sg:postcode":"4703",
    "sg:province":"Solothurn",
    "wof:name":"Ornitholog.verein Oensingen",
    "wof:placetype":"venue"
},
  "geometry": {"coordinates":[7.7569499016,47.2809181213],"type":"Point"}
}