{
  "type": "Feature",
  "properties": {
    "iso:country":"CH",
    "sg:address":"Alte Uznabergstrasse 15",
    "sg:city":"Uznach",
    "sg:classifiers":[
        {
            "category":"Restaurant",
            "type":"Food & Drink"
        }
    ],
    "sg:phone":"+41 41 988 11 60",
    "sg:postcode":"8730",
    "sg:province":"St. Gallen",
    "wof:name":"Gasthaus Fisch",
    "wof:placetype":"venue"
},
  "geometry": {"coordinates":[7.9089632034,47.1522140503],"type":"Point"}
}