{
  "type": "Feature",
  "properties": {
    "iso:country":"CH",
    "sg:address":"Winterhalde 37",
    "sg:city":"Wintersingen",
    "sg:orig_category":"Herstellung von Mess U Kontrollinstrumenten U vorrichtungen Mechanische Werkst\u00e4tten",
    "sg:phone":"+41 32 351 35 29",
    "sg:postcode":"4451",
    "sg:province":"Basel-Landschaft",
    "wof:name":"Par Pr\u00e4zisions-apparatebau R\u00fcti, Oskar Stauffer",
    "wof:placetype":"venue"
},
  "geometry": {"coordinates":[7.4071240425,47.1493453979],"type":"Point"}
}