{
  "type": "Feature",
  "properties": {
    "iso:country":"CH",
    "sg:address":"Nordstrasse 280",
    "sg:city":"Z\u00fcrich",
    "sg:orig_category":"Detailhandel mit Beleuchtungs U Haushaltsgegenst\u00e4nden Erbringung von Dienstleistungen f\u00fcr Unternehme",
    "sg:phone":"+41 12714171",
    "sg:postcode":"8037",
    "sg:province":"Z\u00fcrich",
    "wof:name":"Ht Heim-trends Ag Wohnberatung Vorhang-atelier",
    "wof:placetype":"venue"
},
  "geometry": {"coordinates":[8.524632,47.395157],"type":"Point"}
}