{
  "type": "Feature",
  "properties": {
    "iso:country":"CH",
    "sg:address":"Steinstrasse 21 8003 Z\u00fcrich. Postfach",
    "sg:city":"Z\u00fcrich",
    "sg:orig_category":"Grosshandel mit sonstigen Gebrauchs U Verbrauchsg\u00fctern",
    "sg:phone":"+41 14510605",
    "sg:postcode":"8001",
    "sg:province":"Z\u00fcrich",
    "wof:name":"Ruff Hans W. Edelsteine, Uhren, Schmuck; Im, Export, Handel",
    "wof:placetype":"venue"
},
  "geometry": {"coordinates":[8.5198450089,47.3681640625],"type":"Point"}
}