{
  "type": "Feature",
  "properties": {
    "iso:country":"CH",
    "sg:address":"Gotthardstrasse 21",
    "sg:city":"Z\u00fcrich",
    "sg:orig_category":"Finanzierungsinstitutionen",
    "sg:phone":"+41 71 245 51 51",
    "sg:postcode":"8002",
    "sg:province":"Z\u00fcrich",
    "wof:name":"Svilar Financial Services Ag",
    "wof:placetype":"venue"
},
  "geometry": {"coordinates":[9.3854007721,47.4347572327],"type":"Point"}
}