{
  "type": "Feature",
  "properties": {
    "iso:country":"CH",
    "sg:address":"Route De Sous-moulin 15",
    "sg:city":"Ch\u00eane-bourg",
    "sg:orig_category":"Grosshandel mit Eisenwaren sowie Installationsbedarf f\u00fcr Gas, Wasser U Heizung Grosshandel mit Masch",
    "sg:postcode":"1225",
    "sg:province":"Gen\u00e8ve",
    "wof:name":"Emb-pumpen Ag",
    "wof:placetype":"venue"
},
  "geometry": {"coordinates":[6.1929059029,46.1927833557],"type":"Point"}
}