{
  "type": "Feature",
  "properties": {
    "iso:country":"CH",
    "sg:address":"5444 K\u00fcnten. Postfach",
    "sg:city":"K\u00fcnten",
    "sg:orig_category":"Sportvereine Ballsport Fussball",
    "sg:postcode":"5444",
    "sg:province":"Aargau",
    "wof:name":"Sv Waidberg-nirwana",
    "wof:placetype":"venue"
},
  "geometry": {"coordinates":[8.3263196945,47.3879318237],"type":"Point"}
}