{
  "type": "Feature",
  "properties": {
    "addr:full":"Dorfstr. 12 8602 Wangen Zh. Postfach Br\u00fcttisellen Z\u00fcrich 8306",
    "addr:housenumber":"12",
    "addr:postcode":"8602;8306",
    "addr:street":"Dorfstr.;Zuerich",
    "iso:country":"CH",
    "sg:address":"Dorfstr. 12 8602 Wangen Zh. Postfach",
    "sg:city":"Br\u00fcttisellen",
    "sg:orig_category":"Architektur U Ingenieurb\u00fcros",
    "sg:postcode":"8306",
    "sg:province":"Z\u00fcrich",
    "wof:name":"Krucker Bruno, Architekt",
    "wof:placetype":"venue"
},
  "geometry": {"coordinates":[8.645645,47.410656],"type":"Point"}
}