{
  "type": "Feature",
  "properties": {
    "iso:country":"CH",
    "sg:address":"Bahnhofstrasse 34",
    "sg:city":"Steinhausen",
    "sg:orig_category":"Sonstige mit der Informatik verbundene T\u00e4tigkeiten",
    "sg:phone":"+41 55 410 45 37",
    "sg:postcode":"6312",
    "sg:province":"Zug",
    "wof:name":"Mbic Gmbh Dienstleistungen Im Informatikbereich",
    "wof:placetype":"venue"
},
  "geometry": {"coordinates":[8.7781352997,47.2013778687],"type":"Point"}
}