{
  "type": "Feature",
  "properties": {
    "iso:country":"CH",
    "sg:address":"7245",
    "sg:city":"Ascharina",
    "sg:classifiers":[
        {
            "category":"Travel",
            "subcategory":"Hotels & Motels",
            "type":"Entertainment"
        }
    ],
    "sg:postcode":"7245",
    "sg:province":"Graubunden",
    "sg:tags":[
        "hotels",
        "mit",
        "restaurant"
    ],
    "wof:name":"Hotel R\u00e4tia Ag",
    "wof:placetype":"venue"
},
  "geometry": {"coordinates":[9.8019695282,46.9529800415],"type":"Point"}
}