{
  "type": "Feature",
  "properties": {
    "iso:country":"CH",
    "sg:address":"Dorfplatz 4",
    "sg:city":"M\u00fcnsingen",
    "sg:orig_category":"Non-Classified Establishments",
    "sg:postcode":"3110",
    "sg:province":"Bern",
    "wof:name":"Sarotec Althaus",
    "wof:placetype":"venue"
},
  "geometry": {"coordinates":[7.5626950264,46.8746604919],"type":"Point"}
}