{
  "type": "Feature",
  "properties": {
    "iso:country":"CH",
    "sg:address":"Winterthurerstrasse",
    "sg:city":"Flurlingen",
    "sg:orig_category":"Herstellung von Elektrizit\u00e4tsverteilungs U schalteinrichtungen",
    "sg:phone":"+41 79 605 76 55",
    "sg:postcode":"8247",
    "sg:province":"Z\u00fcrich",
    "wof:name":"Peter Meister Ag Elektrische Schaltanlagen",
    "wof:placetype":"venue"
},
  "geometry": {"coordinates":[8.6333255768,47.6791725159],"type":"Point"}
}