{
  "type": "Feature",
  "properties": {
    "iso:country":"CH",
    "sg:address":"Hauptstrasse 28",
    "sg:city":"Salenstein",
    "sg:orig_category":"Unclassifiable Establishments",
    "sg:postcode":"8268",
    "sg:province":"Thurgau",
    "wof:name":"Vbb Gmbh (vertrieb / Beteiligung / Beratung)",
    "wof:placetype":"venue"
},
  "geometry": {"coordinates":[9.0533599854,47.6733818054],"type":"Point"}
}