{
  "type": "Feature",
  "properties": {
    "iso:country":"CH",
    "sg:address":"3945",
    "sg:city":"Gampel",
    "sg:orig_category":"Landw. Genossenschaften Viehzucht",
    "sg:postcode":"3945",
    "sg:province":"Valais",
    "wof:name":"Viehzuchtgenossenschaft",
    "wof:placetype":"venue"
},
  "geometry": {"coordinates":[7.7440090179,46.3165092468],"type":"Point"}
}