{
  "type": "Feature",
  "properties": {
    "iso:country":"CH",
    "sg:address":"Dolderweg 2",
    "sg:city":"Basel",
    "sg:orig_category":"Interessenvertretungen",
    "sg:phone":"+41 61 681 17 90",
    "sg:postcode":"4058",
    "sg:province":"Basel-Stadt",
    "wof:name":"Schuldhess-stiftung J\u00f6rg Shimon",
    "wof:placetype":"venue"
},
  "geometry": {"coordinates":[7.5948619843,47.5605278015],"type":"Point"}
}