{
  "type": "Feature",
  "properties": {
    "iso:country":"CH",
    "sg:address":"Hummel 21",
    "sg:city":"Schmerikon",
    "sg:orig_category":"Organisationen des Gesundheitswesen",
    "sg:phone":"+41 55 282 10 56",
    "sg:postcode":"8716",
    "sg:province":"St. Gallen",
    "wof:name":"Samariterverein",
    "wof:placetype":"venue"
},
  "geometry": {"coordinates":[8.9456233978,47.2284736633],"type":"Point"}
}