{
  "type": "Feature",
  "properties": {
    "iso:country":"CH",
    "sg:address":"B\u00e4lliz 46 3600 Thun. Postfach",
    "sg:city":"Thun",
    "sg:orig_category":"RESTAURANTS: TEA-ROOMS",
    "sg:phone":"+41 33 222 60 33",
    "sg:postcode":"3600",
    "sg:province":"Bern",
    "wof:name":"Lanzrein Daniel",
    "wof:placetype":"venue"
},
  "geometry": {"coordinates":[7.627532959,46.7581748962],"type":"Point"}
}