{
  "type": "Feature",
  "properties": {
    "iso:country":"CH",
    "sg:address":"Kasernenstrasse 43",
    "sg:city":"Herisau",
    "sg:orig_category":"Maler U Glasergewerbe",
    "sg:postcode":"9100",
    "sg:province":"Appenzell Ausserrhoden",
    "wof:name":"Malergesch\u00e4ft Walti Scheuber Gmbh",
    "wof:placetype":"venue"
},
  "geometry": {"coordinates":[8.3959350586,46.9378242493],"type":"Point"}
}