{
  "type": "Feature",
  "properties": {
    "iso:country":"CH",
    "sg:address":"Effingerstrasse 51",
    "sg:city":"Bern",
    "sg:classifiers":[
        {
            "category":"Restaurant",
            "type":"Food & Drink"
        }
    ],
    "sg:phone":"+41 55 220 72 82",
    "sg:postcode":"3008",
    "sg:province":"Bern",
    "wof:name":"Restaurant Villa Aurum",
    "wof:placetype":"venue"
},
  "geometry": {"coordinates":[8.8234291077,47.2292671204],"type":"Point"}
}