{
  "type": "Feature",
  "properties": {
    "iso:country":"CH",
    "sg:address":"6984",
    "sg:city":"Pura",
    "sg:orig_category":"Darlehenskassen U Raiffeisenbanken",
    "sg:phone":"+41 91 606 38 75",
    "sg:postcode":"6984",
    "sg:province":"Ticino",
    "wof:name":"Banca Raiffeisen",
    "wof:placetype":"venue"
},
  "geometry": {"coordinates":[8.86382,45.98283],"type":"Point"}
}