{
  "type": "Feature",
  "properties": {
    "iso:country":"CH",
    "sg:address":"Tunau 4",
    "sg:city":"Gr\u00e4nichen",
    "sg:orig_category":"Herstellung von k\u00e4lte U lufttechnischen Erzeugnissen f\u00fcr gewerbliche Zwecke",
    "sg:phone":"+41 79 696 47 28",
    "sg:postcode":"5722",
    "sg:province":"Aargau",
    "wof:name":"Heizplan Hpa Ag",
    "wof:placetype":"venue"
},
  "geometry": {"coordinates":[9.5551738739,47.3814544678],"type":"Point"}
}