{
  "type": "Feature",
  "properties": {
    "iso:country":"CH",
    "sg:address":"1805",
    "sg:city":"Jongny",
    "sg:orig_category":"Sanit\u00e4r, Heizungs U L\u00fcftungsinstallation",
    "sg:postcode":"1805",
    "sg:province":"Vaud",
    "wof:name":"Francelet Paul Mme Francelet Succ.",
    "wof:placetype":"venue"
},
  "geometry": {"coordinates":[6.8477101326,46.4874382019],"type":"Point"}
}