{
  "type": "Feature",
  "properties": {
    "iso:country":"CH",
    "sg:address":"Asetstrasse 43",
    "sg:city":"Ibach",
    "sg:orig_category":"Bauschreinerei",
    "sg:phone":"+41 79 341 60 81",
    "sg:postcode":"6438",
    "sg:province":"Schwyz",
    "wof:name":"Ueli St\u00f6ssel & Armin Horat Kundenschreinerei",
    "wof:placetype":"venue"
},
  "geometry": {"coordinates":[8.647667,47.007008],"type":"Point"}
}