{
  "type": "Feature",
  "properties": {
    "iso:country":"CH",
    "sg:address":"Neuenburgstrasse 14",
    "sg:city":"Gampelen",
    "sg:orig_category":"G\u00fcterbef\u00f6rderung im Strassenverkehr Sonstiger Grosshandel",
    "sg:phone":"+41 32 313 47 53",
    "sg:postcode":"3236",
    "sg:province":"Bern",
    "wof:name":"Stv Seeland Transport & Vertriebs Ag",
    "wof:placetype":"venue"
},
  "geometry": {"coordinates":[7.0559601784,47.0152587891],"type":"Point"}
}