{
  "type": "Feature",
  "properties": {
    "iso:country":"CH",
    "sg:address":"G\u00e4ssli 1",
    "sg:city":"Staufen",
    "sg:orig_category":"Detailhandel mit Waren verschiedener Art, Hauptrichtung Nahrungsmittel",
    "sg:phone":"+41 62 891 26 71",
    "sg:postcode":"5603",
    "sg:province":"Aargau",
    "wof:name":"Volg Laden",
    "wof:placetype":"venue"
},
  "geometry": {"coordinates":[8.1680908203,47.3832206726],"type":"Point"}
}