{
  "type": "Feature",
  "properties": {
    "iso:country":"CH",
    "sg:address":"3960",
    "sg:city":"Sierre",
    "sg:classifiers":[
        {
            "category":"Education",
            "subcategory":"Library",
            "type":"Public Place"
        }
    ],
    "sg:postcode":"3960",
    "sg:province":"Valais",
    "sg:tags":[
        "u",
        "bibliotheken",
        "archive"
    ],
    "wof:name":"Biblioth\u00e8que Populaire De La Paroisse Catholique",
    "wof:placetype":"venue"
},
  "geometry": {"coordinates":[7.530655,46.292404],"type":"Point"}
}