{
  "type": "Feature",
  "properties": {
    "iso:country":"CH",
    "sg:address":"Fischerg\u00e4ssli 6",
    "sg:city":"Ermatingen",
    "sg:orig_category":"Sportvereine Sch\u00fctzen",
    "sg:phone":"+41 71 664 13 10",
    "sg:postcode":"8272",
    "sg:province":"Thurgau",
    "wof:name":"Sch\u00fctzengesellschaft",
    "wof:placetype":"venue"
},
  "geometry": {"coordinates":[9.0833921432,47.6740608215],"type":"Point"}
}