{
  "type": "Feature",
  "properties": {
    "iso:country":"CH",
    "sg:address":"1735",
    "sg:city":"Giffers",
    "sg:orig_category":"Sportvereine Ballsport Fussball Vereine Damen",
    "sg:postcode":"1735",
    "sg:province":"Fribourg",
    "wof:name":"Fc Gossau Abt.damen",
    "wof:placetype":"venue"
},
  "geometry": {"coordinates":[9.2548904419,47.4220199585],"type":"Point"}
}