{
  "type": "Feature",
  "properties": {
    "iso:country":"CH",
    "sg:address":"Dachslernstrasse 5",
    "sg:city":"Z\u00fcrich",
    "sg:orig_category":"RESTAURANTS: TEA-ROOMS",
    "sg:phone":"+41 71 944 15 55",
    "sg:postcode":"8048",
    "sg:province":"Z\u00fcrich",
    "wof:name":"Restaurant Lindenhof Gmbh",
    "wof:placetype":"venue"
},
  "geometry": {"coordinates":[9.1233997345,47.4656410217],"type":"Point"}
}