{
  "type": "Feature",
  "properties": {
    "iso:country":"CH",
    "sg:address":"Hauptstrasse",
    "sg:city":"Surava",
    "sg:orig_category":"Detailhandel mit Waren verschiedener Art, Hauptrichtung Nahrungsmittel Grosshandel mit Nahrungsmitte",
    "sg:phone":"+41 81 681 17 18",
    "sg:postcode":"7472",
    "sg:province":"Graubunden",
    "wof:name":"Puracenter Ag Spar-supermarkt",
    "wof:placetype":"venue"
},
  "geometry": {"coordinates":[9.6153678894,46.6665725708],"type":"Point"}
}