{
  "type": "Feature",
  "properties": {
    "iso:country":"CH",
    "sg:address":"Maiackerstrasse 29",
    "sg:city":"Rudolfstetten",
    "sg:orig_category":"Grosshandel mit Eisenwaren sowie Installationsbedarf f\u00fcr Gas, Wasser U Heizung",
    "sg:phone":"+41 79 605 30 60",
    "sg:postcode":"8964",
    "sg:province":"Aargau",
    "wof:name":"Huber Heinz, Huspa Whirlpools",
    "wof:placetype":"venue"
},
  "geometry": {"coordinates":[8.3727769852,47.3623847961],"type":"Point"}
}