{
  "type": "Feature",
  "properties": {
    "iso:country":"CH",
    "sg:address":"Morand Rue Marc 17",
    "sg:city":"Martigny",
    "sg:orig_category":"Non-Classified Establishments",
    "sg:postcode":"1920",
    "sg:province":"Valais",
    "wof:name":"Berisha Montage, Echafaudages, Services Sarl",
    "wof:placetype":"venue"
},
  "geometry": {"coordinates":[7.0716309547,46.1038246155],"type":"Point"}
}