{
  "type": "Feature",
  "properties": {
    "addr:full":"Itramen Grindelwald Bern 3818",
    "addr:postcode":"3818",
    "iso:country":"CH",
    "sg:address":"Itramen",
    "sg:city":"Grindelwald",
    "sg:orig_category":"Abbruch U Sprenggewerbe, Erdbewegungsarbeiten Erdbewegungsarbeiten",
    "sg:phone":"+41 33 853 16 87",
    "sg:postcode":"3818",
    "sg:province":"Bern",
    "wof:name":"Peter Arthur Ag",
    "wof:placetype":"venue"
},
  "geometry": {"coordinates":[7.99189,46.618679],"type":"Point"}
}