{
  "type": "Feature",
  "properties": {
    "iso:country":"CH",
    "sg:address":"Chemin Des Roches 41 1066 Epalinges. Postfach",
    "sg:city":"Epalinges",
    "sg:orig_category":"Fussboden, Fliesen U Plattenlegerei, Tapeziererei",
    "sg:phone":"+41 91 606 60 58",
    "sg:postcode":"1066",
    "sg:province":"Vaud",
    "wof:name":"Spinka Parchetto Di Marschalkova Beata",
    "wof:placetype":"venue"
},
  "geometry": {"coordinates":[8.8564577103,45.9699325562],"type":"Point"}
}