{
  "type": "Feature",
  "properties": {
    "iso:country":"CH",
    "sg:address":"General Guisan-strasse 80",
    "sg:city":"Basel",
    "sg:orig_category":"Detailhandel mit Brot, Back U S\u00fcsswaren",
    "sg:phone":"+41 61 302 18 08",
    "sg:postcode":"4054",
    "sg:province":"Basel-Stadt",
    "wof:name":"Pasticceria La Delizia, Maria Puglisi",
    "wof:placetype":"venue"
},
  "geometry": {"coordinates":[7.565986,47.55003],"type":"Point"}
}