{
  "type": "Feature",
  "properties": {
    "iso:country":"CH",
    "sg:address":"Chlosterweg 14",
    "sg:city":"Sch\u00fcpfheim",
    "sg:orig_category":"Maturit\u00e4tsschulen, Lehrerseminarien",
    "sg:phone":"+41 41 484 16 36",
    "sg:postcode":"6170",
    "sg:province":"Luzern",
    "wof:name":"Kantonsschule",
    "wof:placetype":"venue"
},
  "geometry": {"coordinates":[8.0209445953,46.9556732178],"type":"Point"}
}