{
  "type": "Feature",
  "properties": {
    "iso:country":"CH",
    "sg:address":"Aretshalde 74",
    "sg:city":"Aathal-seegr\u00e4ben",
    "sg:orig_category":"Detailhandel mit elektrischen Haushalts-,Radio U Fernsehger\u00e4ten sowie Musikinstrumenten",
    "sg:postcode":"8607",
    "sg:province":"Z\u00fcrich",
    "wof:name":"Leuenberger + Co",
    "wof:placetype":"venue"
},
  "geometry": {"coordinates":[8.7723760605,47.3348236084],"type":"Point"}
}