{
  "type": "Feature",
  "properties": {
    "iso:country":"CH",
    "sg:address":"Heinrichstrasse 95",
    "sg:city":"Z\u00fcrich",
    "sg:orig_category":"Reinigungsgewerbe",
    "sg:phone":"+41 12713660",
    "sg:postcode":"8005",
    "sg:province":"Z\u00fcrich",
    "wof:name":"Ulasch Textilreinigung Ulas A. & S.",
    "wof:placetype":"venue"
},
  "geometry": {"coordinates":[8.5289783478,47.3853340149],"type":"Point"}
}