{
  "type": "Feature",
  "properties": {
    "iso:country":"CH",
    "sg:address":"Trinermatten 4800 Zofingen. Postfach 462",
    "sg:city":"Zofingen",
    "sg:orig_category":"Sportvereine Turnen",
    "sg:phone":"+41 62 752 15 02",
    "sg:postcode":"4800",
    "sg:province":"Aargau",
    "wof:name":"Turnverein Zofingen Tvz Stadion Zielturm",
    "wof:placetype":"venue"
},
  "geometry": {"coordinates":[7.9463100433,47.2886199951],"type":"Point"}
}