{
  "type": "Feature",
  "properties": {
    "iso:country":"CH",
    "sg:address":"Lehr\u00fcti",
    "sg:city":"Unterterzen",
    "sg:orig_category":"Detailhandel mit Waren verschiedener Art, Hauptrichtung Nahrungsmittel",
    "sg:phone":"+41 81 738 14 50",
    "sg:postcode":"8882",
    "sg:province":"St. Gallen",
    "wof:name":"Konsumgenossenschaft Quarten",
    "wof:placetype":"venue"
},
  "geometry": {"coordinates":[9.2456235886,47.1115837097],"type":"Point"}
}