{
  "type": "Feature",
  "properties": {
    "addr:full":"Kosthausstrasse 6 Kriens Luzern 6010",
    "addr:housenumber":"6",
    "addr:postcode":"6010",
    "addr:street":"Kosthausstrasse",
    "iso:country":"CH",
    "sg:address":"Kosthausstrasse 6",
    "sg:city":"Kriens",
    "sg:orig_category":"Allgemeiner Hoch U Tiefbau Allgemeiner Hochbau",
    "sg:phone":"+41 41 320 37 45",
    "sg:postcode":"6010",
    "sg:province":"Luzern",
    "wof:name":"Schmidhof Ag Kriens",
    "wof:placetype":"venue"
},
  "geometry": {"coordinates":[8.275157,47.033768],"type":"Point"}
}