{
  "type": "Feature",
  "properties": {
    "iso:country":"CH",
    "sg:address":"Eichengasse 1 6331 H\u00fcnenberg. Postfach 243",
    "sg:city":"H\u00fcnenberg",
    "sg:classifiers":[
        {
            "category":"Bars & Pubs",
            "type":"Food & Drink"
        }
    ],
    "sg:phone":"+41 41 781 03 88",
    "sg:postcode":"6331",
    "sg:province":"Zug",
    "sg:tags":[
        "restaurant"
    ],
    "wof:name":"Restaurant Eiche Bar Art",
    "wof:placetype":"venue"
},
  "geometry": {"coordinates":[8.426361,47.175457],"type":"Point"}
}