{
  "type": "Feature",
  "properties": {
    "iso:country":"CH",
    "sg:address":"Im Lenz 113d",
    "sg:city":"Hinwil",
    "sg:orig_category":"Detailhandel mit Getr\u00e4nken",
    "sg:phone":"+41 79 413 26 49",
    "sg:postcode":"8340",
    "sg:province":"Z\u00fcrich",
    "wof:name":"Studer Weine",
    "wof:placetype":"venue"
},
  "geometry": {"coordinates":[8.8431787491,47.2966384888],"type":"Point"}
}