{
  "type": "Feature",
  "properties": {
    "iso:country":"CH",
    "sg:address":"Im Eichli 9",
    "sg:city":"Ober\u00e4geri",
    "sg:orig_category":"Softwareentwicklung U beratung",
    "sg:phone":"+41 55 462 28 08",
    "sg:postcode":"6315",
    "sg:province":"Zug",
    "wof:name":"Activ Media Development Bellodi",
    "wof:placetype":"venue"
},
  "geometry": {"coordinates":[8.8614273071,47.2024002075],"type":"Point"}
}