{
  "type": "Feature",
  "properties": {
    "iso:country":"CH",
    "sg:address":"Rue De La Gare 41 1530 Payerne Case Postale 347",
    "sg:city":"Payerne",
    "sg:orig_category":"Detailhandel mit B\u00fcchern, Zeitungen, Schreib U Papeteriewaren Detailhandel mit Zeitungen U Zeitschri",
    "sg:phone":"+41 26 660 45 23",
    "sg:postcode":"1530",
    "sg:province":"Vaud",
    "wof:name":"Kiosque 2000 Rapha\u00ebl Ciambriello",
    "wof:placetype":"venue"
},
  "geometry": {"coordinates":[6.940019,46.820232],"type":"Point"}
}