{
  "type": "Feature",
  "properties": {
    "iso:country":"CH",
    "sg:address":"Bahnhofstrasse 1",
    "sg:city":"Worb",
    "sg:orig_category":"Alters U Pflegeheime Interessenvertretungen",
    "sg:phone":"+41 31 838 17 17",
    "sg:postcode":"3076",
    "sg:province":"Bern",
    "wof:name":"Altersheim Vechigen/worb",
    "wof:placetype":"venue"
},
  "geometry": {"coordinates":[7.563951,46.929379],"type":"Point"}
}