{
  "type": "Feature",
  "properties": {
    "iso:country":"CH",
    "sg:address":"Obergrundstrasse 51 6003 Luzern. Postfach",
    "sg:city":"Luzern",
    "sg:orig_category":"Sonstiges Versicherungsgewerbe",
    "sg:postcode":"6002",
    "sg:province":"Luzern",
    "wof:name":"Winterthur Schweizerische Versicherungs-gesellschaft",
    "wof:placetype":"venue"
},
  "geometry": {"coordinates":[7.4399499893,46.9482498169],"type":"Point"}
}