{
  "type": "Feature",
  "properties": {
    "iso:country":"CH",
    "sg:address":"Warteggstrasse 5",
    "sg:city":"Luzern",
    "sg:orig_category":"Vorschulen, Kinderg\u00e4rten",
    "sg:phone":"+41 41 368 08 51",
    "sg:postcode":"6005",
    "sg:province":"Luzern",
    "wof:name":"Kindergarten Wartegg",
    "wof:placetype":"venue"
},
  "geometry": {"coordinates":[8.3243608475,47.0396842957],"type":"Point"}
}