{
  "type": "Feature",
  "properties": {
    "iso:country":"CH",
    "sg:address":"Le Gottau",
    "sg:city":"Ch\u00e2tel-st-denis",
    "sg:orig_category":"Herstellung von Betonerzeugnissen f\u00fcr den Bau Herstellung von Transportbeton",
    "sg:phone":"+41 21 948 74 22",
    "sg:postcode":"1618",
    "sg:province":"Fribourg",
    "wof:name":"Bff B\u00e9ton Frais Sa",
    "wof:placetype":"venue"
},
  "geometry": {"coordinates":[6.9084758759,46.5302238464],"type":"Point"}
}