{
  "type": "Feature",
  "properties": {
    "iso:country":"CH",
    "sg:address":"H\u00e4usern\u00e4bnit",
    "sg:city":"R\u00fcedisbach",
    "sg:orig_category":"Erdbewegungsarbeiten G\u00fcterbef\u00f6rderung im Strassenverkehr",
    "sg:phone":"+41 79 656 57 36",
    "sg:postcode":"3474",
    "sg:province":"Bern",
    "wof:name":"Ernst Lempen Trax-& Transportunternehmen",
    "wof:placetype":"venue"
},
  "geometry": {"coordinates":[7.4360799789,46.4718894958],"type":"Point"}
}