{
  "type": "Feature",
  "properties": {
    "iso:country":"CH",
    "sg:address":"Hauptstrasse 72",
    "sg:city":"Galmiz",
    "sg:classifiers":[
        {
            "category":"Restaurant",
            "type":"Food & Drink"
        }
    ],
    "sg:phone":"+41 62 390 17 57",
    "sg:postcode":"3285",
    "sg:province":"Fribourg",
    "wof:name":"Restaurant Frohsinn",
    "wof:placetype":"venue"
},
  "geometry": {"coordinates":[7.7536468506,47.3325576782],"type":"Point"}
}