{
  "type": "Feature",
  "properties": {
    "iso:country":"CH",
    "sg:address":"Bernstrasse 102",
    "sg:city":"Zollikofen",
    "sg:orig_category":"Instandhaltung U Reparatur von Automobilen",
    "sg:postcode":"3052",
    "sg:province":"Bern",
    "wof:name":"E. Marschall",
    "wof:placetype":"venue"
},
  "geometry": {"coordinates":[7.8617801666,49.1125106812],"type":"Point"}
}