{
  "type": "Feature",
  "properties": {
    "iso:country":"CH",
    "sg:address":"Obergrundstrasse 78",
    "sg:city":"Luzern",
    "sg:orig_category":"Fahrschulen, Flugschulen",
    "sg:phone":"+41 41 310 61 61",
    "sg:postcode":"6005",
    "sg:province":"Luzern",
    "wof:name":"Bruno Muff Fahrschule",
    "wof:placetype":"venue"
},
  "geometry": {"coordinates":[8.3027896881,47.0433197021],"type":"Point"}
}