{
  "type": "Feature",
  "properties": {
    "iso:country":"CH",
    "sg:address":"Zelgstrasse 91",
    "sg:city":"Uetendorf",
    "sg:orig_category":"Instandhaltung U Reparatur von Automobilen",
    "sg:phone":"+41 17500828",
    "sg:postcode":"3661",
    "sg:province":"Bern",
    "wof:name":"Garage M. Lang",
    "wof:placetype":"venue"
},
  "geometry": {"coordinates":[8.4364204407,47.4189071655],"type":"Point"}
}