{
  "type": "Feature",
  "properties": {
    "iso:country":"CH",
    "sg:address":"Seestrasse 565",
    "sg:city":"Z\u00fcrich",
    "sg:orig_category":"Kauf U Verkauf von Immobilien auf eigene Rechnung",
    "sg:phone":"+41 14828622",
    "sg:postcode":"8038",
    "sg:province":"Z\u00fcrich",
    "wof:name":"R\u00f6llin Erwin Immobilien",
    "wof:placetype":"venue"
},
  "geometry": {"coordinates":[8.5415973663,47.3351173401],"type":"Point"}
}