{
  "type": "Feature",
  "properties": {
    "iso:country":"CH",
    "sg:address":"Bleichestrasse 15 8280 Kreuzlingen. Postfach 3",
    "sg:city":"Kreuzlingen",
    "sg:orig_category":"Verbraucherm\u00e4rkte > 2500 m2",
    "sg:phone":"+41 71 688 92 22",
    "sg:postcode":"8280",
    "sg:province":"Thurgau",
    "wof:name":"Seepark Einkaufszentrum",
    "wof:placetype":"venue"
},
  "geometry": {"coordinates":[9.1963224411,47.6417884827],"type":"Point"}
}