{
  "type": "Feature",
  "properties": {
    "iso:country":"CH",
    "sg:address":"Moosacherstr. 7",
    "sg:city":"W\u00e4denswil",
    "sg:orig_category":"Mechanik",
    "sg:postcode":"8820",
    "sg:province":"Z\u00fcrich",
    "wof:name":"Oeschger R. Gmbh",
    "wof:placetype":"venue"
},
  "geometry": {"coordinates":[8.6413583755,47.2399139404],"type":"Point"}
}