{
  "type": "Feature",
  "properties": {
    "addr:full":"Bahnhofstrasse 2 Unterseen Bern 3800",
    "addr:housenumber":"2",
    "addr:postcode":"3800",
    "addr:street":"Bahnhofstrasse",
    "iso:country":"CH",
    "sg:address":"Bahnhofstrasse 2",
    "sg:city":"Unterseen",
    "sg:orig_category":"Detailhandel mit Sportartikeln Fachdetailhandel in Verkaufsr\u00e4umen",
    "sg:phone":"+41 41 240 12 12",
    "sg:postcode":"3800",
    "sg:province":"Bern",
    "wof:name":"Eiselin Max",
    "wof:placetype":"venue"
},
  "geometry": {"coordinates":[8.303685,47.044773],"type":"Point"}
}