{
  "type": "Feature",
  "properties": {
    "iso:country":"CH",
    "sg:address":"Obergrundstrasse 51",
    "sg:city":"Luzern",
    "sg:orig_category":"Innendekorationsateliers",
    "sg:phone":"+41 41 240 75 38",
    "sg:postcode":"6003",
    "sg:province":"Luzern",
    "wof:name":"Hans Sch\u00e4r Innendekorationen",
    "wof:placetype":"venue"
},
  "geometry": {"coordinates":[8.3041810989,47.0453720093],"type":"Point"}
}