{
  "type": "Feature",
  "properties": {
    "iso:country":"CH",
    "sg:address":"Chemin De La Crettaz",
    "sg:city":"Savi\u00e8se",
    "sg:orig_category":"Datenverarbeitungsdienste",
    "sg:phone":"+41 77212808",
    "sg:postcode":"1965",
    "sg:province":"Valais",
    "wof:name":"Jac Info Conseil En Informatique",
    "wof:placetype":"venue"
},
  "geometry": {"coordinates":[7.345654,46.247818],"type":"Point"}
}