{
  "type": "Feature",
  "properties": {
    "iso:country":"CH",
    "sg:address":"Amriswilerstrasse 9",
    "sg:city":"Arbon",
    "sg:orig_category":"Zimmerei, Dachdeckerei, Bauspenglerei U Abdichtung",
    "sg:phone":"+41 71 222 94 62",
    "sg:postcode":"9320",
    "sg:province":"Thurgau",
    "wof:name":"H\u00f6chner Spenglertechnik",
    "wof:placetype":"venue"
},
  "geometry": {"coordinates":[9.4123134613,47.5209083557],"type":"Point"}
}