{
  "type": "Feature",
  "properties": {
    "iso:country":"CH",
    "sg:address":"Dorf",
    "sg:city":"Blausee-mitholz",
    "sg:orig_category":"G\u00fcterbef\u00f6rderung im Strassenverkehr",
    "sg:phone":"+41 33 671 37 36",
    "sg:postcode":"3717",
    "sg:province":"Bern",
    "wof:name":"Hans M\u00fcller Transporte",
    "wof:placetype":"venue"
},
  "geometry": {"coordinates":[7.6687889099,46.533405304],"type":"Point"}
}