{
  "type": "Feature",
  "properties": {
    "iso:country":"CH",
    "sg:address":"Dorfstrasse 21",
    "sg:city":"Reidermoos",
    "sg:orig_category":"Non-Classified Establishments",
    "sg:postcode":"6260",
    "sg:province":"Luzern",
    "wof:name":"Eugster & Partner Ag",
    "wof:placetype":"venue"
},
  "geometry": {"coordinates":[7.9904799461,47.2548217773],"type":"Point"}
}