{
  "type": "Feature",
  "properties": {
    "iso:country":"CH",
    "sg:address":"Carouge Rue De 8 1205 Gen\u00e8ve. Postfach",
    "sg:city":"Gen\u00e8ve",
    "sg:orig_category":"Allgemeiner Hoch U Tiefbau",
    "sg:phone":"+41 22 320 30 41",
    "sg:postcode":"1205",
    "sg:province":"Gen\u00e8ve",
    "wof:name":"Ryser Olivier, Bureau D'\u00e9tudes Solaires Et Sanitaires Projets Pour Div. Types De B\u00e2timents Concernant Les Installations Sanitaires Etc",
    "wof:placetype":"venue"
},
  "geometry": {"coordinates":[6.142836,46.197376],"type":"Point"}
}