{
  "type": "Feature",
  "properties": {
    "iso:country":"CH",
    "sg:address":"Wehri",
    "sg:city":"Gampel",
    "sg:orig_category":"Bauspenglerei Sanit\u00e4rinstallation",
    "sg:phone":"+41 56 441 83 84",
    "sg:postcode":"3945",
    "sg:province":"Valais",
    "wof:name":"Rolf Hirt Sanit\u00e4re Anlagen & Spenglerei",
    "wof:placetype":"venue"
},
  "geometry": {"coordinates":[8.223185,47.492668],"type":"Point"}
}