{
  "type": "Feature",
  "properties": {
    "iso:country":"CH",
    "sg:address":"Wilstrasse 16 6370 Oberdorf Nw. Postfach",
    "sg:city":"Stans",
    "sg:orig_category":"Sportvereine Sch\u00fctzen",
    "sg:postcode":"6371",
    "sg:province":"Nidwalden",
    "wof:name":"Sch\u00fctzenges.b\u00fcren-oberdorf",
    "wof:placetype":"venue"
},
  "geometry": {"coordinates":[8.3834657669,46.9575157166],"type":"Point"}
}