{
  "type": "Feature",
  "properties": {
    "iso:country":"CH",
    "sg:address":"Degersheimer Strasse",
    "sg:city":"Dicken",
    "sg:classifiers":[
        {
            "category":"Restaurant",
            "type":"Food & Drink"
        }
    ],
    "sg:phone":"+41 71 377 11 12",
    "sg:postcode":"9115",
    "sg:province":"St. Gallen",
    "wof:name":"Restaurant Freihof",
    "wof:placetype":"venue"
},
  "geometry": {"coordinates":[9.1904716492,47.3367614746],"type":"Point"}
}