{
  "type": "Feature",
  "properties": {
    "iso:country":"CH",
    "sg:address":"Knubelstrasse 22",
    "sg:city":"Unterkulm",
    "sg:orig_category":"Herstellung von sonstigen Maschinen f\u00fcr unspezifische Verwendung",
    "sg:phone":"+41 62 777 29 76",
    "sg:postcode":"5726",
    "sg:province":"Aargau",
    "wof:name":"Pro-can Ag",
    "wof:placetype":"venue"
},
  "geometry": {"coordinates":[8.1189346313,47.3101043701],"type":"Point"}
}