{
  "type": "Feature",
  "properties": {
    "iso:country":"CH",
    "sg:address":"Unterdorf 4",
    "sg:city":"Mosnang",
    "sg:orig_category":"Detailhandel mit Schuhen",
    "sg:phone":"+41 79 694 54 05",
    "sg:postcode":"9607",
    "sg:province":"St. Gallen",
    "wof:name":"Rosmarie Walliser Schuhhaus",
    "wof:placetype":"venue"
},
  "geometry": {"coordinates":[9.0405168533,47.3629188538],"type":"Point"}
}