{
  "type": "Feature",
  "properties": {
    "iso:country":"CH",
    "sg:address":"Grellingerstrasse",
    "sg:city":"Basel",
    "sg:orig_category":"Non-Classified Establishments",
    "sg:postcode":"4000",
    "sg:province":"Basel-Stadt",
    "wof:name":"Hpi Holding Gmbh",
    "wof:placetype":"venue"
},
  "geometry": {"coordinates":[7.6073198318,47.5513801575],"type":"Point"}
}