{
  "type": "Feature",
  "properties": {
    "iso:country":"CH",
    "sg:address":"Hauptstrasse 37 9506 Lommis. Postfach",
    "sg:city":"Fahrweid",
    "sg:orig_category":"Herstellung von Radio U Fernsehger\u00e4ten sowie phono U videotechnischen Ger\u00e4ten",
    "sg:phone":"+41 17480644",
    "sg:postcode":"8951",
    "sg:province":"Z\u00fcrich",
    "wof:name":"Schwyter Electronic",
    "wof:placetype":"venue"
},
  "geometry": {"coordinates":[8.9916334152,47.5169677734],"type":"Point"}
}