{
  "type": "Feature",
  "properties": {
    "iso:country":"CH",
    "sg:address":"Entfelderstrasse 19 5000 Aarau. Postfach",
    "sg:city":"Aarau",
    "sg:orig_category":"Herstellung von medizinischen U chirurgischen Ger\u00e4ten sowie orthop\u00e4dischen Vorrichtungen Zahntechnis",
    "sg:phone":"+41 79 204 83 88",
    "sg:postcode":"5001",
    "sg:province":"Aargau",
    "wof:name":"Joho J\u00f6rg Ag",
    "wof:placetype":"venue"
},
  "geometry": {"coordinates":[8.0493154526,47.3884048462],"type":"Point"}
}