{
  "type": "Feature",
  "properties": {
    "iso:country":"CH",
    "sg:address":"Buchenweg 16",
    "sg:city":"Dulliken",
    "sg:orig_category":"Erbringung von Dienstleistungen f\u00fcr Unternehmen",
    "sg:phone":"+41 62 295 69 59",
    "sg:postcode":"4657",
    "sg:province":"Solothurn",
    "wof:name":"Cr\u00e9ative-atelier, Salzmann Peter",
    "wof:placetype":"venue"
},
  "geometry": {"coordinates":[7.9348769188,47.3514556885],"type":"Point"}
}