{
  "type": "Feature",
  "properties": {
    "iso:country":"CH",
    "sg:address":"Rindermarkt 8 8001 Z\u00fcrich. Postfach",
    "sg:city":"Z\u00fcrich",
    "sg:orig_category":"Unternehmensberatung",
    "sg:phone":"+41 12525080",
    "sg:postcode":"8001",
    "sg:province":"Z\u00fcrich",
    "wof:name":"Zenh\u00e4usern + Partner, Inhaber Zenh\u00e4usern R. Unternehmensberatung",
    "wof:placetype":"venue"
},
  "geometry": {"coordinates":[8.5443782806,47.3722763062],"type":"Point"}
}