{
  "type": "Feature",
  "properties": {
    "iso:country":"CH",
    "sg:address":"Kaiserstuhlerstrasse 306 8173 Neerach. Postfach",
    "sg:city":"Neerach",
    "sg:orig_category":"Gartenbau Hoch U Tiefbau",
    "sg:phone":"+41 355744",
    "sg:postcode":"8173",
    "sg:province":"Z\u00fcrich",
    "wof:name":"Kelpe & Gr\u00f6schel Baugesch\u00e4ft & Gartenbau",
    "wof:placetype":"venue"
},
  "geometry": {"coordinates":[8.4739999771,47.5153007507],"type":"Point"}
}