{
  "type": "Feature",
  "properties": {
    "iso:country":"CH",
    "sg:address":"Hauptstrasse 15",
    "sg:city":"Amlikon",
    "sg:orig_category":"Sonstiger Fachdetailhandel mit Nahrungsmitteln, Getr\u00e4nken U Tabak in Verkaufsr\u00e4umen",
    "sg:postcode":"8514",
    "sg:province":"Thurgau",
    "wof:name":"Thurmilch Gmbh",
    "wof:placetype":"venue"
},
  "geometry": {"coordinates":[9.0602731705,47.570766449],"type":"Point"}
}