{
  "type": "Feature",
  "properties": {
    "iso:country":"CH",
    "sg:address":"Limmattalstrasse 358",
    "sg:city":"Z\u00fcrich",
    "sg:orig_category":"Fachdetailhandel in Verkaufsr\u00e4umen",
    "sg:phone":"+41 13417129",
    "sg:postcode":"8049",
    "sg:province":"Z\u00fcrich",
    "wof:name":"Walter Tr\u00fcb Reproduktionsfotograf",
    "wof:placetype":"venue"
},
  "geometry": {"coordinates":[8.4848928452,47.4044303894],"type":"Point"}
}