{
  "type": "Feature",
  "properties": {
    "iso:country":"CH",
    "sg:address":"Baarerstrasse 63",
    "sg:city":"Zug",
    "sg:orig_category":"Unclassifiable Establishments",
    "sg:phone":"+41 41 728 60 50",
    "sg:postcode":"6300",
    "sg:province":"Zug",
    "wof:name":"Wells Fargo Finance Holding Ag",
    "wof:placetype":"venue"
},
  "geometry": {"coordinates":[8.5173740387,47.1761703491],"type":"Point"}
}