{
  "type": "Feature",
  "properties": {
    "iso:country":"CH",
    "sg:address":"9034",
    "sg:city":"Eggersriet",
    "sg:orig_category":"Sportvereine Sch\u00fctzen",
    "sg:postcode":"9034",
    "sg:province":"St. Gallen",
    "wof:name":"Milit\u00e4rsch\u00fctzenverein",
    "wof:placetype":"venue"
},
  "geometry": {"coordinates":[9.5031204224,47.4540405273],"type":"Point"}
}