{
  "type": "Feature",
  "properties": {
    "iso:country":"CH",
    "sg:address":"Rue De La Gru\u00e8re 7",
    "sg:city":"Saignel\u00e9gier",
    "sg:orig_category":"Detailhandel mit Geschenkartikeln U Souvenirs",
    "sg:phone":"+41 31 301 01 75",
    "sg:postcode":"2350",
    "sg:province":"Jura",
    "wof:name":"Jacques-r\u00e9my Schaerer Kunsthandwerk",
    "wof:placetype":"venue"
},
  "geometry": {"coordinates":[7.4358801842,46.9787254333],"type":"Point"}
}