{
  "type": "Feature",
  "properties": {
    "iso:country":"CH",
    "sg:address":"Avenir Rue De L' 23",
    "sg:city":"Del\u00e9mont",
    "sg:orig_category":"Non-Classified Establishments",
    "sg:postcode":"2800",
    "sg:province":"Jura",
    "wof:name":"Zollinger Ag Radio - Tv - Hifi - Video",
    "wof:placetype":"venue"
},
  "geometry": {"coordinates":[178.69096374509999,-7.4715299606],"type":"Point"}
}