{
  "type": "Feature",
  "properties": {
    "iso:country":"CH",
    "sg:address":"Rainallee 6",
    "sg:city":"Riehen",
    "sg:orig_category":"Finanzierungsinstitutionen Wirtschaftspr\u00fcfung, Steuerberatung U Treuhand",
    "sg:phone":"+41 61 383 16 10",
    "sg:postcode":"4125",
    "sg:province":"Basel-Stadt",
    "wof:name":"Alrona Gmbh",
    "wof:placetype":"venue"
},
  "geometry": {"coordinates":[7.640953064,47.5738220215],"type":"Point"}
}