{
  "type": "Feature",
  "properties": {
    "iso:country":"CH",
    "sg:address":"Aargauerstrasse 1",
    "sg:city":"Z\u00fcrich",
    "sg:orig_category":"Grosshandel mit Obst U Gem\u00fcse",
    "sg:phone":"+41 22 343 67 15",
    "sg:postcode":"8048",
    "sg:province":"Z\u00fcrich",
    "wof:name":"Gabriel & Pierre Gillabert Pommes De Terre Engros",
    "wof:placetype":"venue"
},
  "geometry": {"coordinates":[6.1300001144,46.1833229065],"type":"Point"}
}