{
  "type": "Feature",
  "properties": {
    "iso:country":"CH",
    "sg:address":"Magdenerstrasse 8",
    "sg:city":"Rheinfelden",
    "sg:orig_category":"Erschliessung von Grundst\u00fccken",
    "sg:postcode":"4310",
    "sg:province":"Aargau",
    "wof:name":"Baugenossenschaft Riburgerstrasse Rheinfelden",
    "wof:placetype":"venue"
},
  "geometry": {"coordinates":[7.7982401848,47.5509757996],"type":"Point"}
}