{
  "type": "Feature",
  "properties": {
    "iso:country":"CH",
    "sg:address":"Gaisgass 1a",
    "sg:city":"Rheineck",
    "sg:orig_category":"Kosmetikinstitute",
    "sg:phone":"+41 71 888 58 68",
    "sg:postcode":"9424",
    "sg:province":"St. Gallen",
    "wof:name":"Maria Grazia Camarata Kosmetikinstitut Maria Grazia",
    "wof:placetype":"venue"
},
  "geometry": {"coordinates":[9.5904302597,47.4652748108],"type":"Point"}
}