{
  "type": "Feature",
  "properties": {
    "iso:country":"CH",
    "sg:address":"Riond-bosson 12",
    "sg:city":"Morges",
    "sg:orig_category":"Sonstige mit Sport verbundene T\u00e4tigkeiten",
    "sg:phone":"+41 21 802 68 48",
    "sg:postcode":"1110",
    "sg:province":"Vaud",
    "wof:name":"Scub'h20, Chauvy Martial",
    "wof:placetype":"venue"
},
  "geometry": {"coordinates":[6.4850478172,46.5042762756],"type":"Point"}
}