{
  "type": "Feature",
  "properties": {
    "iso:country":"CH",
    "sg:address":"Biberiststrasse 14a",
    "sg:city":"Solothurn",
    "sg:orig_category":"Werbung",
    "sg:postcode":"4500",
    "sg:province":"Solothurn",
    "wof:name":"Zack Werbung Gmbh",
    "wof:placetype":"venue"
},
  "geometry": {"coordinates":[7.5420022011,47.2022094727],"type":"Point"}
}