{
  "type": "Feature",
  "properties": {
    "iso:country":"CH",
    "sg:address":"Principala Via",
    "sg:city":"Falera",
    "sg:orig_category":"RESTAURANTS: TEA-ROOMS",
    "sg:phone":"+41 81 921 30 48",
    "sg:postcode":"7153",
    "sg:province":"Graubunden",
    "wof:name":"Jos\u00e9-fernando De Queiroz",
    "wof:placetype":"venue"
},
  "geometry": {"coordinates":[9.2315282822,46.80078125],"type":"Point"}
}