{
  "type": "Feature",
  "properties": {
    "iso:country":"CH",
    "sg:address":"1445 Peney (vuiteboeuf). Postfach",
    "sg:city":"Vuiteboeuf",
    "sg:orig_category":"Grosshandel mit Obst U Gem\u00fcse",
    "sg:postcode":"1445",
    "sg:province":"Vaud",
    "wof:name":"Floravert S\u00e0rl",
    "wof:placetype":"venue"
},
  "geometry": {"coordinates":[6.5610051155,46.8027954102],"type":"Point"}
}