{
  "type": "Feature",
  "properties": {
    "iso:country":"CH",
    "sg:address":"Waffenplatzstrasse 64 8002 Z\u00fcrich. Postfach 657",
    "sg:city":"Z\u00fcrich",
    "sg:orig_category":"Unternehmensberatung",
    "sg:postcode":"8027",
    "sg:province":"Z\u00fcrich",
    "wof:name":"Buff Consulting",
    "wof:placetype":"venue"
},
  "geometry": {"coordinates":[7.6753058434,47.4499740601],"type":"Point"}
}