{
  "type": "Feature",
  "properties": {
    "iso:country":"CH",
    "sg:address":"Kasernenstrasse 57a",
    "sg:city":"Liestal",
    "sg:orig_category":"RESTAURANTS: TEA-ROOMS",
    "sg:postcode":"4410",
    "sg:province":"Basel-Landschaft",
    "wof:name":"Restaurant Arena Hug Urs",
    "wof:placetype":"venue"
},
  "geometry": {"coordinates":[7.7413239479,47.4802818298],"type":"Point"}
}