{
  "type": "Feature",
  "properties": {
    "iso:country":"CH",
    "sg:address":"Thunstrasse 38 3113 Rubigen. Postfach 172",
    "sg:city":"Rubigen",
    "sg:orig_category":"Dachdeckerei Ger\u00fcstbau",
    "sg:phone":"+41 31 721 26 00",
    "sg:postcode":"3113",
    "sg:province":"Bern",
    "wof:name":"Johann R\u00fcfenacht Ag Bedachungen & Ger\u00fcstbau",
    "wof:placetype":"venue"
},
  "geometry": {"coordinates":[7.54548,46.896515],"type":"Point"}
}