{
  "type": "Feature",
  "properties": {
    "iso:country":"CH",
    "sg:address":"Hauptstrasse 71 5330 Zurzach. Postfach",
    "sg:city":"Zurzach",
    "sg:orig_category":"Hardwareberatung",
    "sg:postcode":"5330",
    "sg:province":"Aargau",
    "wof:name":"Universum Communication, Petrella + Buonocore",
    "wof:placetype":"venue"
},
  "geometry": {"coordinates":[8.2936544418,47.5895500183],"type":"Point"}
}