{
  "type": "Feature",
  "properties": {
    "iso:country":"CH",
    "sg:address":"3862",
    "sg:city":"Innertkirchen",
    "sg:orig_category":"Pensionskassen",
    "sg:phone":"+41 33 982 20 11",
    "sg:postcode":"3862",
    "sg:province":"Bern",
    "wof:name":"Personalfonds Der Kraftwerke Oberhasli Ag",
    "wof:placetype":"venue"
},
  "geometry": {"coordinates":[8.2280960083,46.7054328918],"type":"Point"}
}