{
  "type": "Feature",
  "properties": {
    "iso:country":"CH",
    "sg:address":"Bederstrasse 28",
    "sg:city":"Z\u00fcrich",
    "sg:classifiers":[
        {
            "category":"Communications",
            "subcategory":"Film & Video Production",
            "type":"Services"
        }
    ],
    "sg:phone":"+41 12015080",
    "sg:postcode":"8002",
    "sg:province":"Z\u00fcrich",
    "sg:tags":[
        "videofilmherstellung",
        "u"
    ],
    "wof:name":"Ren\u00e9 Martinet Filmproduktion Rcm",
    "wof:placetype":"venue"
},
  "geometry": {"coordinates":[8.528881073,47.3642463684],"type":"Point"}
}