{
  "type": "Feature",
  "properties": {
    "iso:country":"CH",
    "sg:address":"Fraum\u00fcnsterstrasse 16 8001 Z\u00fcrich. Postfach 9321",
    "sg:city":"Z\u00fcrich",
    "sg:orig_category":"Softwareentwicklung U beratung Unternehmensberatung",
    "sg:phone":"+41 12199889",
    "sg:postcode":"8022",
    "sg:province":"Z\u00fcrich",
    "wof:name":"Accenture Ag",
    "wof:placetype":"venue"
},
  "geometry": {"coordinates":[8.5410699844,47.3687973022],"type":"Point"}
}