{
  "type": "Feature",
  "properties": {
    "iso:country":"CH",
    "sg:address":"Hinterer Steinacker 55",
    "sg:city":"Olten",
    "sg:orig_category":"Organisationen des Gesundheitswesen",
    "sg:phone":"+41 79 204 81 19",
    "sg:postcode":"4600",
    "sg:province":"Solothurn",
    "wof:name":"Dip - Die Individuelle Privatpflege",
    "wof:placetype":"venue"
},
  "geometry": {"coordinates":[7.9050898552,47.3443145752],"type":"Point"}
}