{
  "type": "Feature",
  "properties": {
    "iso:country":"CH",
    "sg:address":"Place Centrale 8",
    "sg:city":"Martigny",
    "sg:classifiers":[
        {
            "category":"Banks & Credit Unions",
            "subcategory":"Investment Brokerage",
            "type":"Services"
        }
    ],
    "sg:phone":"+41 27 946 46 00",
    "sg:postcode":"1920",
    "sg:province":"Valais",
    "sg:tags":[
        "caf\u00e9s",
        "tea-rooms",
        "restaurants"
    ],
    "wof:name":"Barock Caf\u00e9, Studer & Tenisch",
    "wof:placetype":"venue"
},
  "geometry": {"coordinates":[7.0728359222,46.1015129089],"type":"Point"}
}