{
  "type": "Feature",
  "properties": {
    "iso:country":"CH",
    "sg:address":"Dorfstr. 23",
    "sg:city":"Fislisbach",
    "sg:classifiers":[
        {
            "category":"Shopping",
            "subcategory":"Computers & Home Electronics",
            "type":"Retail Goods"
        }
    ],
    "sg:phone":"+41 56 470 00 77",
    "sg:postcode":"5442",
    "sg:province":"Aargau",
    "sg:tags":[
        "equipment",
        "electrical",
        "component",
        "electric",
        "electronic"
    ],
    "wof:name":"W Schmid Ag Elektro Apparatebau",
    "wof:placetype":"venue"
},
  "geometry": {"coordinates":[8.296344,47.436634],"type":"Point"}
}