{
  "type": "Feature",
  "properties": {
    "iso:country":"CH",
    "sg:address":"Kanderstegstrasse 3714 Frutigen. Postfach",
    "sg:city":"Frutigen",
    "sg:orig_category":"Granit",
    "sg:phone":"+41 33 672 80 70",
    "sg:postcode":"3714",
    "sg:province":"Bern",
    "wof:name":"Shb Steinbruch Und Hartschotterwerk Blausee-mitholz Ag",
    "wof:placetype":"venue"
},
  "geometry": {"coordinates":[7.6457967758,46.5882873535],"type":"Point"}
}