{
  "type": "Feature",
  "properties": {
    "iso:country":"CH",
    "sg:address":"Langenmoos",
    "sg:city":"Truttikon",
    "sg:orig_category":"Vereine Trachten",
    "sg:postcode":"8467",
    "sg:province":"Z\u00fcrich",
    "wof:name":"Trachtengruppe Weinland",
    "wof:placetype":"venue"
},
  "geometry": {"coordinates":[8.7047395706,47.6315917969],"type":"Point"}
}