{
  "type": "Feature",
  "properties": {
    "iso:country":"CH",
    "sg:address":"Reinacherstrasse 138",
    "sg:city":"Basel",
    "sg:orig_category":"Motorcycle Gauntlets",
    "sg:phone":"+41 61 331 56 30",
    "sg:postcode":"4053",
    "sg:province":"Basel-Stadt",
    "wof:name":"Bhg Motos Felix Brotbeck",
    "wof:placetype":"venue"
},
  "geometry": {"coordinates":[7.6043729782,47.5357093811],"type":"Point"}
}