{
  "type": "Feature",
  "properties": {
    "iso:country":"CH",
    "sg:address":"Hopfenstrasse 19 8045 Z\u00fcrich. Postfach 8045 Z\u00fcrich",
    "sg:city":"Zust",
    "sg:orig_category":"RESTAURANTS: TEA-ROOMS",
    "sg:postcode":"45",
    "wof:name":"Restaurant Habsburg, Pfister & Williner",
    "wof:placetype":"venue"
},
  "geometry": {"coordinates":[8.5199165344,47.3651123047],"type":"Point"}
}