{
  "type": "Feature",
  "properties": {
    "iso:country":"CH",
    "sg:address":"Z\u00fcrichstrasse 5",
    "sg:city":"Biel/bienne",
    "sg:orig_category":"Autoelektro and -elektronik Werkst\u00e4tten",
    "sg:phone":"+41 32 341 41 14",
    "sg:postcode":"2504",
    "sg:province":"Bern",
    "wof:name":"Mcz Gmbh Fahrzeugelektrik Klimaservice",
    "wof:placetype":"venue"
},
  "geometry": {"coordinates":[7.28898,47.1609],"type":"Point"}
}