{
  "type": "Feature",
  "properties": {
    "iso:country":"CH",
    "sg:address":"R\u00e4mistrasse 4",
    "sg:city":"Z\u00fcrich",
    "sg:orig_category":"Interessenvertretungen",
    "sg:postcode":"8001",
    "sg:province":"Z\u00fcrich",
    "wof:name":"Siegrist John Stiftung Stiftung F\u00fcr Mgl Schweiz. Barkeeper-union",
    "wof:placetype":"venue"
},
  "geometry": {"coordinates":[8.5457315445,47.367565155],"type":"Point"}
}