{
  "type": "Feature",
  "properties": {
    "iso:country":"CH",
    "sg:address":"Via Ai Chiabi 21",
    "sg:city":"Biasca",
    "sg:orig_category":"Detailhandel mit Textilien Herstellung von Reiseartikeln, Leder U Sattlerwaren",
    "sg:phone":"+41 56 441 20 78",
    "sg:postcode":"6710",
    "sg:province":"Ticino",
    "wof:name":"Hans Rudolf Frey Sattlerei Bettwaren",
    "wof:placetype":"venue"
},
  "geometry": {"coordinates":[8.2113456726,47.48412323],"type":"Point"}
}