{
  "type": "Feature",
  "properties": {
    "iso:country":"CH",
    "sg:address":"Petit-cordex",
    "sg:city":"Genolier",
    "sg:orig_category":"Allgemeiner Gartenbau Blumen U Zierpflanzenbau",
    "sg:phone":"+41 91 683 16 16",
    "sg:postcode":"1272",
    "sg:province":"Vaud",
    "wof:name":"Ennio Camponovo Floricoltura-orticoltura Serre",
    "wof:placetype":"venue"
},
  "geometry": {"coordinates":[9.023459,45.850235],"type":"Point"}
}