{
  "type": "Feature",
  "properties": {
    "iso:country":"CH",
    "sg:address":"Pictet Avenue Ernest- 23 1203 Gen\u00e8ve. Postfach",
    "sg:city":"Gen\u00e8ve",
    "sg:orig_category":"Fachdetailhandel mit pharmazeutischen Produkten",
    "sg:postcode":"1203",
    "sg:province":"Gen\u00e8ve",
    "wof:name":"Pharmacie De Vieusseux, Jo\u00eblle Golan, Murielle Oberson Et No\u00e9mie Rajczyk",
    "wof:placetype":"venue"
},
  "geometry": {"coordinates":[6.1253199577,46.2122268677],"type":"Point"}
}