{
  "type": "Feature",
  "properties": {
    "iso:country":"CH",
    "sg:address":"3961",
    "sg:city":"Ayer",
    "sg:orig_category":"Grosshandel mit Holz U Bauelementen aus Holz",
    "sg:phone":"+41 27 475 18 28",
    "sg:postcode":"3961",
    "sg:province":"Valais",
    "wof:name":"R\u00e9my Epiney Commerce De Bois",
    "wof:placetype":"venue"
},
  "geometry": {"coordinates":[7.603741169,46.1775054932],"type":"Point"}
}