{
  "type": "Feature",
  "properties": {
    "iso:country":"CH",
    "sg:address":"Tittwiesenstrasse 22",
    "sg:city":"Chur",
    "sg:orig_category":"Wirtschaftspr\u00fcfung, Steuerberatung U Treuhand",
    "sg:phone":"+41 56 666 26 66",
    "sg:postcode":"7000",
    "sg:province":"Graubunden",
    "wof:name":"Schmid-steudler Yvonne, Yvoffice - Das Externe B\u00fcro",
    "wof:placetype":"venue"
},
  "geometry": {"coordinates":[8.2909803391,47.3503837585],"type":"Point"}
}