{
  "type": "Feature",
  "properties": {
    "addr:full":"Allmend 423 Wilderswil Bern 3812",
    "addr:housenumber":"423",
    "addr:postcode":"3812",
    "addr:street":"Allmend",
    "iso:country":"CH",
    "sg:address":"Allmend 423",
    "sg:city":"Wilderswil",
    "sg:orig_category":"Bauschreinerei Innenausbau",
    "sg:phone":"+41 31 930 00 00",
    "sg:postcode":"3812",
    "sg:province":"Bern",
    "wof:name":"Hartmann Holzbau Ag Zimmerei Schreinerei Parkett",
    "wof:placetype":"venue"
},
  "geometry": {"coordinates":[7.515227,46.958321],"type":"Point"}
}