{
  "type": "Feature",
  "properties": {
    "iso:country":"CH",
    "sg:address":"Ledi",
    "sg:city":"Feutersoey",
    "sg:classifiers":[
        {
            "category":"Restaurant",
            "type":"Food & Drink"
        }
    ],
    "sg:phone":"+41 33 755 15 00",
    "sg:postcode":"3784",
    "sg:province":"Bern",
    "wof:name":"Restaurant Cheeserli",
    "wof:placetype":"venue"
},
  "geometry": {"coordinates":[7.2706618309,46.4198074341],"type":"Point"}
}