{
  "type": "Feature",
  "properties": {
    "iso:country":"CH",
    "sg:address":"Wilerstrasse 77",
    "sg:city":"Bazenheid",
    "sg:orig_category":"Sportvereine Velo Rad-& Motorfahrer-Bund SRB",
    "sg:phone":"+41 79 434 13 15",
    "sg:postcode":"9602",
    "sg:province":"St. Gallen",
    "wof:name":"Rad-& Motoclub B\u00fctschwil",
    "wof:placetype":"venue"
},
  "geometry": {"coordinates":[9.0629882812,47.4187507629],"type":"Point"}
}