{
  "type": "Feature",
  "properties": {
    "iso:country":"CH",
    "sg:address":"R\u00f6merstr. 83",
    "sg:city":"Reinach",
    "sg:classifiers":[
        {
            "category":"Manufacturing",
            "subcategory":"Rubber & Plastics",
            "type":"Manufacturing & Wholesale Goods"
        }
    ],
    "sg:phone":"+41 61 715 24 24",
    "sg:postcode":"4153",
    "sg:province":"Basel-Landschaft",
    "wof:name":"Crown Obrist Ag",
    "wof:placetype":"venue"
},
  "geometry": {"coordinates":[7.5961041451,47.4903106689],"type":"Point"}
}