{
  "type": "Feature",
  "properties": {
    "iso:country":"CH",
    "sg:address":"Pilatusstrasse 23",
    "sg:city":"Menziken",
    "sg:orig_category":"Paintwork Supraregional",
    "sg:phone":"+41 62 771 95 04",
    "sg:postcode":"5737",
    "sg:province":"Aargau",
    "wof:name":"Top Gipserei Gmbh",
    "wof:placetype":"venue"
},
  "geometry": {"coordinates":[8.1828737259,47.2418327332],"type":"Point"}
}