{
  "type": "Feature",
  "properties": {
    "iso:country":"CH",
    "sg:address":"Bois De Bay Route Du 28",
    "sg:city":"Satigny",
    "sg:orig_category":"Mechanik",
    "sg:postcode":"1242",
    "sg:province":"Gen\u00e8ve",
    "wof:name":"Perrin Pascal",
    "wof:placetype":"venue"
},
  "geometry": {"coordinates":[6.0632400513,46.1992721558],"type":"Point"}
}