{
  "type": "Feature",
  "properties": {
    "iso:country":"CH",
    "sg:address":"Avenue De Beauregard 22",
    "sg:city":"Vevey",
    "sg:orig_category":"Ger\u00fcstbau Stukkateurgewerbe, Gipserei U Verputzerei",
    "sg:phone":"+41 21 921 07 09",
    "sg:postcode":"1800",
    "sg:province":"Vaud",
    "wof:name":"Delaquis Pl\u00e2trerie & Peinture S\u00e0rl",
    "wof:placetype":"venue"
},
  "geometry": {"coordinates":[6.8501739502,46.4677391052],"type":"Point"}
}