{
  "type": "Feature",
  "properties": {
    "iso:country":"CH",
    "sg:address":"Rue De Guillermaux 27",
    "sg:city":"Payerne",
    "sg:orig_category":"Grosshandel mit Nahrungsmitteln, Getr\u00e4nken U Tabakwaren ohne ausgepr\u00e4gten Schwerpunkt",
    "sg:phone":"+41 26 660 22 12",
    "sg:postcode":"1530",
    "sg:province":"Vaud",
    "wof:name":"Truong Qui Minh",
    "wof:placetype":"venue"
},
  "geometry": {"coordinates":[6.9334759712,46.8201293945],"type":"Point"}
}