{
  "type": "Feature",
  "properties": {
    "iso:country":"CH",
    "sg:address":"B\u00e4pfert",
    "sg:city":"Meilen",
    "sg:orig_category":"Erschliessung von Grundst\u00fccken",
    "sg:phone":"+41 19230016",
    "sg:postcode":"8706",
    "sg:province":"Z\u00fcrich",
    "wof:name":"Baugenossenschaft Ormis",
    "wof:placetype":"venue"
},
  "geometry": {"coordinates":[8.6607265472,47.2762451172],"type":"Point"}
}