{
  "type": "Feature",
  "properties": {
    "iso:country":"CH",
    "sg:address":"Ale Rue De L' 16",
    "sg:city":"Lausanne",
    "sg:orig_category":"Unclassifiable Establishments",
    "sg:phone":"+41 21 312 09 76",
    "sg:postcode":"1003",
    "sg:province":"Vaud",
    "wof:name":"Boucherie De L'arcade, J.-m. Ballaman",
    "wof:placetype":"venue"
},
  "geometry": {"coordinates":[6.6304497719,46.5199890137],"type":"Point"}
}