{
  "type": "Feature",
  "properties": {
    "iso:country":"CH",
    "sg:address":"Stabile Filanda 6818 Melano. Postfach Caselle Postale 27",
    "sg:city":"Melano",
    "sg:orig_category":"Herstellung von W\u00e4sche Textilgewerbe",
    "sg:phone":"+41 91 648 15 14",
    "sg:postcode":"6818",
    "sg:province":"Ticino",
    "wof:name":"Bundy Sa Biancheria & Capi D'abbigliam.",
    "wof:placetype":"venue"
},
  "geometry": {"coordinates":[8.9848747253,45.9209709167],"type":"Point"}
}