{
  "type": "Feature",
  "properties": {
    "iso:country":"CH",
    "sg:address":"Haslistrasse 18",
    "sg:city":"Wimmis",
    "sg:orig_category":"Unternehmensberatung",
    "sg:phone":"+41 33 657 00 51",
    "sg:postcode":"3752",
    "sg:province":"Bern",
    "wof:name":"Regez Management Unternehmensberatung",
    "wof:placetype":"venue"
},
  "geometry": {"coordinates":[7.6420550346,46.6724967957],"type":"Point"}
}