{
  "type": "Feature",
  "properties": {
    "iso:country":"CH",
    "sg:address":"Avenue Louis-casa\u00ef 79-81",
    "sg:city":"Meyrin",
    "sg:orig_category":"Betrieb U technische Hilfsdienste des Kultur U Unterhaltungswesens",
    "sg:postcode":"1217",
    "sg:province":"Gen\u00e8ve",
    "wof:name":"Subway Gmbh",
    "wof:placetype":"venue"
},
  "geometry": {"coordinates":[8.344078,47.351105],"type":"Point"}
}