{
  "type": "Feature",
  "properties": {
    "iso:country":"CH",
    "sg:address":"1957",
    "sg:city":"Ardon",
    "sg:orig_category":"Mechanik",
    "sg:postcode":"1957",
    "sg:province":"Valais",
    "wof:name":"Atelier M\u00e9canique, Kolly Willy",
    "wof:placetype":"venue"
},
  "geometry": {"coordinates":[7.0641021729,46.767616272],"type":"Point"}
}