{
  "type": "Feature",
  "properties": {
    "iso:country":"CH",
    "sg:address":"Seestattstrasse 23",
    "sg:city":"Altendorf",
    "sg:classifiers":[
        {
            "category":"Travel",
            "subcategory":"Hotels & Motels",
            "type":"Entertainment"
        }
    ],
    "sg:phone":"+41 55 451 01 00",
    "sg:postcode":"8852",
    "sg:province":"Schwyz",
    "sg:tags":[
        "hotels",
        "mit",
        "restaurant"
    ],
    "wof:name":"Seehotel Hecht, Jenny Hansj\u00f6rg",
    "wof:placetype":"venue"
},
  "geometry": {"coordinates":[8.8319664001,47.1948318481],"type":"Point"}
}