{
  "type": "Feature",
  "properties": {
    "iso:country":"CH",
    "sg:address":"B\u00e4chliwis 23",
    "sg:city":"Bachenb\u00fclach",
    "sg:orig_category":"Sonstiger Grosshandel",
    "sg:postcode":"8184",
    "sg:province":"Z\u00fcrich",
    "wof:name":"Prikler & Co",
    "wof:placetype":"venue"
},
  "geometry": {"coordinates":[8.5439662933,47.5060806274],"type":"Point"}
}