{
  "type": "Feature",
  "properties": {
    "iso:country":"CH",
    "sg:address":"St\u00e4gh\u00fcsli 6106 Werthenstein. Postfach 42",
    "sg:city":"Werthenstein",
    "sg:orig_category":"Handel mit Automobilen Handel mit Automobilteilen U Zubeh\u00f6r",
    "sg:phone":"+41 41 490 19 39",
    "sg:postcode":"6106",
    "sg:province":"Luzern",
    "wof:name":"Lustenberger Ag Autoverwertung Autorecycling",
    "wof:placetype":"venue"
},
  "geometry": {"coordinates":[8.1030015945,47.0553703308],"type":"Point"}
}