{
  "type": "Feature",
  "properties": {
    "iso:country":"CH",
    "sg:address":"Buchenstrasse 4 6020 Emmenbr\u00fccke. Postfach",
    "sg:city":"Emmenbr\u00fccke",
    "sg:orig_category":"Kauf U Verkauf von Immobilien auf eigene Rechnung",
    "sg:phone":"+41 41 260 45 05",
    "sg:postcode":"6020",
    "sg:province":"Luzern",
    "wof:name":"Indoor Paradise Ag",
    "wof:placetype":"venue"
},
  "geometry": {"coordinates":[8.2754926682,47.078086853],"type":"Point"}
}