{
  "type": "Feature",
  "properties": {
    "iso:country":"CH",
    "sg:address":"Nussbaummatte 237",
    "sg:city":"Uetendorf",
    "sg:orig_category":"Handelsvermittlung U Grosshandel",
    "sg:phone":"+41 71 636 15 24",
    "sg:postcode":"3661",
    "sg:province":"Bern",
    "wof:name":"Agrifeed Mischfuttertechnik Ag",
    "wof:placetype":"venue"
},
  "geometry": {"coordinates":[9.1670570374,47.5773124695],"type":"Point"}
}