{
  "type": "Feature",
  "properties": {
    "iso:country":"CH",
    "sg:address":"Z\u00fcrichstrasse 10",
    "sg:city":"Uster",
    "sg:orig_category":"Non-Classified Establishments",
    "sg:phone":"+41 848 888 018",
    "sg:postcode":"8610",
    "sg:province":"Z\u00fcrich",
    "wof:name":"Generali Versicherungen Generalagentur",
    "wof:placetype":"venue"
},
  "geometry": {"coordinates":[8.7174005508,47.3487052917],"type":"Point"}
}