{
  "type": "Feature",
  "properties": {
    "iso:country":"CH",
    "sg:address":"Dorfstrasse",
    "sg:city":"M\u00fcrren",
    "sg:orig_category":"Detailhandel mit Waren verschiedener Art, Hauptrichtung Nahrungsmittel",
    "sg:phone":"+41 33 676 11 87",
    "sg:postcode":"3825",
    "sg:province":"Bern",
    "wof:name":"Coop Berner Oberland",
    "wof:placetype":"venue"
},
  "geometry": {"coordinates":[7.6900019646,46.6245803833],"type":"Point"}
}