{
  "type": "Feature",
  "properties": {
    "iso:country":"CH",
    "sg:address":"Route Des Jeunes 7",
    "sg:city":"Gen\u00e8ve",
    "sg:orig_category":"Stukkateurgewerbe, Gipserei U Verputzerei",
    "sg:postcode":"1200",
    "sg:province":"Gen\u00e8ve",
    "wof:name":"Zonno Fr\u00e8res",
    "wof:placetype":"venue"
},
  "geometry": {"coordinates":[6.128390789,46.1890487671],"type":"Point"}
}