{
  "type": "Feature",
  "properties": {
    "iso:country":"CH",
    "sg:address":"Rue Des Jardinets 2",
    "sg:city":"Chippis",
    "sg:orig_category":"Werbeagenturen Werbegrafikateliers",
    "sg:phone":"+41 32 926 54 78",
    "sg:postcode":"3965",
    "sg:province":"Valais",
    "wof:name":"Graphit' Atelier De Publicit\u00e9",
    "wof:placetype":"venue"
},
  "geometry": {"coordinates":[6.8142490387,47.0982971191],"type":"Point"}
}