{
  "type": "Feature",
  "properties": {
    "iso:country":"CH",
    "sg:address":"Gemmo Via 11",
    "sg:city":"Lugano",
    "sg:orig_category":"RESTAURANTS: TEA-ROOMS",
    "sg:postcode":"6900",
    "sg:province":"Ticino",
    "wof:name":"Feridale Sa",
    "wof:placetype":"venue"
},
  "geometry": {"coordinates":[8.8604135513,45.9691696167],"type":"Point"}
}