{
  "type": "Feature",
  "properties": {
    "iso:country":"CH",
    "sg:address":"Bahnhofstrasse 3",
    "sg:city":"Steinhausen",
    "sg:orig_category":"Reiseb\u00fcros U Reiseveranstalter",
    "sg:postcode":"6312",
    "sg:province":"Zug",
    "wof:name":"Lgr Landis Gesundheits Reisen.",
    "wof:placetype":"venue"
},
  "geometry": {"coordinates":[8.4839468002,47.19581604],"type":"Point"}
}