{
  "type": "Feature",
  "properties": {
    "iso:country":"CH",
    "sg:address":"Franscini Viale 17",
    "sg:city":"Lugano",
    "sg:orig_category":"Handels-H\u00e4user U Gesellschaften",
    "sg:phone":"+41 91 921 48 68",
    "sg:postcode":"6900",
    "sg:province":"Ticino",
    "wof:name":"Ls Adhesives Sa",
    "wof:placetype":"venue"
},
  "geometry": {"coordinates":[8.9538116455,46.0102424622],"type":"Point"}
}