{
  "type": "Feature",
  "properties": {
    "iso:country":"CH",
    "sg:address":"Mittlerer Kreis 2",
    "sg:city":"Therwil",
    "sg:orig_category":"Fotografische Ateliers",
    "sg:phone":"+41 61 721 85 00",
    "sg:postcode":"4106",
    "sg:province":"Basel-Landschaft",
    "wof:name":"Kurt B\u00fcrki Photo-studio Zentrum",
    "wof:placetype":"venue"
},
  "geometry": {"coordinates":[7.5530180931,47.4988899231],"type":"Point"}
}