{
  "type": "Feature",
  "properties": {
    "iso:country":"CH",
    "sg:address":"Oelestr. 2a.",
    "sg:city":"Interlaken",
    "sg:orig_category":"Zimmerei, Dachdeckerei, Bauspenglerei U Abdichtung",
    "sg:phone":"+41 79 658 88 70",
    "sg:postcode":"3800",
    "sg:province":"Bern",
    "wof:name":"A. Weibel",
    "wof:placetype":"venue"
},
  "geometry": {"coordinates":[7.8685350418,46.6842308044],"type":"Point"}
}