{
  "type": "Feature",
  "properties": {
    "iso:country":"CH",
    "sg:address":"Route De Porrentruy 10",
    "sg:city":"Del\u00e9mont",
    "sg:classifiers":[
        {
            "category":"Travel",
            "subcategory":"Hotels & Motels",
            "type":"Entertainment"
        }
    ],
    "sg:phone":"+41 21 841 17 71",
    "sg:postcode":"2800",
    "sg:province":"Jura",
    "sg:tags":[
        "hotels",
        "mit",
        "restaurant"
    ],
    "wof:name":"H\u00f4tel De La Truite",
    "wof:placetype":"venue"
},
  "geometry": {"coordinates":[6.3251419067,46.6680450439],"type":"Point"}
}