{
  "type": "Feature",
  "properties": {
    "iso:country":"CH",
    "sg:address":"Rue Du Chalet 3",
    "sg:city":"Tavannes",
    "sg:orig_category":"Bauschreinerei Herstellung von Konstruktionsteilen, Fertigbauteilen U Ausbauelementen aus Holz",
    "sg:phone":"+41 32 481 42 55",
    "sg:postcode":"2710",
    "sg:province":"Bern",
    "wof:name":"Gerber + B\u00f6gli Sa",
    "wof:placetype":"venue"
},
  "geometry": {"coordinates":[7.202496,47.225529],"type":"Point"}
}