{
  "type": "Feature",
  "properties": {
    "addr:full":"Bergstrasse 8 St\u00e4fa Z\u00fcrich 8712",
    "addr:housenumber":"8",
    "addr:postcode":"8712",
    "addr:street":"Bergstrasse;Zuerich",
    "iso:country":"CH",
    "sg:address":"Bergstrasse 8",
    "sg:city":"St\u00e4fa",
    "sg:classifiers":[
        {
            "category":"Banks & Credit Unions",
            "subcategory":"Bank",
            "type":"Services"
        }
    ],
    "sg:phone":"+41 19265353",
    "sg:postcode":"8712",
    "sg:province":"Z\u00fcrich",
    "wof:name":"Sparkasse St\u00e4fa",
    "wof:placetype":"venue"
},
  "geometry": {"coordinates":[8.720911,47.241531],"type":"Point"}
}