{
  "type": "Feature",
  "properties": {
    "iso:country":"CH",
    "sg:address":"Tannenbergstrasse 5",
    "sg:city":"Engelburg",
    "sg:orig_category":"Elektroinstallation Herstellung von Elektrizit\u00e4tsverteilungs U schalteinrichtungen",
    "sg:phone":"+41 71 622 20 30",
    "sg:postcode":"9032",
    "sg:province":"St. Gallen",
    "wof:name":"Huber Ag Elektro & Telefon Schalttafelbau",
    "wof:placetype":"venue"
},
  "geometry": {"coordinates":[9.1381845474,47.5666694641],"type":"Point"}
}