{
  "type": "Feature",
  "properties": {
    "addr:full":"Laubstenstrasse 20c St\u00e4fa Z\u00fcrich 8712",
    "addr:housenumber":"20c staefa",
    "addr:postcode":"8712",
    "addr:street":"Laubstenstrasse",
    "iso:country":"CH",
    "sg:address":"Laubstenstrasse 20c",
    "sg:city":"St\u00e4fa",
    "sg:orig_category":"Architekturb\u00fcros",
    "sg:phone":"+41 19262263",
    "sg:postcode":"8712",
    "sg:province":"Z\u00fcrich",
    "wof:name":"Daniel M\u00fcller Architekturb\u00fcro Eth Sia",
    "wof:placetype":"venue"
},
  "geometry": {"coordinates":[8.724179,47.246243],"type":"Point"}
}