{
  "type": "Feature",
  "properties": {
    "iso:country":"CH",
    "sg:address":"Austrasse 26",
    "sg:city":"Volketswil",
    "sg:orig_category":"Softwareentwicklung U beratung",
    "sg:phone":"+41 31 971 86 08",
    "sg:postcode":"8604",
    "sg:province":"Z\u00fcrich",
    "wof:name":"Rentsch + Maurer Ag",
    "wof:placetype":"venue"
},
  "geometry": {"coordinates":[7.4309468269,46.930809021],"type":"Point"}
}