{
  "type": "Feature",
  "properties": {
    "iso:country":"CH",
    "sg:address":"6527",
    "sg:city":"Lodrino",
    "sg:classifiers":[
        {
            "category":"Education",
            "subcategory":"Library",
            "type":"Public Place"
        }
    ],
    "sg:postcode":"6527",
    "sg:province":"Ticino",
    "sg:tags":[
        "u",
        "bibliotheken",
        "archive"
    ],
    "wof:name":"Biblioteca Popolare",
    "wof:placetype":"venue"
},
  "geometry": {"coordinates":[8.981131,46.299667],"type":"Point"}
}