{
  "type": "Feature",
  "properties": {
    "iso:country":"CH",
    "sg:address":"Wies 2",
    "sg:city":"Speicher",
    "sg:orig_category":"Architektur U Ingenieurb\u00fcros Architekturb\u00fcros",
    "sg:phone":"+41 71 344 38 65",
    "sg:postcode":"9042",
    "sg:province":"Appenzell Ausserrhoden",
    "wof:name":"Hartmann + Rutz Architekten Ag",
    "wof:placetype":"venue"
},
  "geometry": {"coordinates":[9.446927,47.413094],"type":"Point"}
}