{
  "type": "Feature",
  "properties": {
    "iso:country":"CH",
    "sg:address":"7186",
    "sg:city":"Segnas",
    "sg:orig_category":"Detailhandel mit Zeitungen U Zeitschriften Kioske",
    "sg:phone":"+41 81 947 54 90",
    "sg:postcode":"7186",
    "sg:province":"Graubunden",
    "wof:name":"Lucia Maissen Kiosk",
    "wof:placetype":"venue"
},
  "geometry": {"coordinates":[8.8285303116,46.6946182251],"type":"Point"}
}