{
  "type": "Feature",
  "properties": {
    "iso:country":"CH",
    "sg:address":"Laimgasse",
    "sg:city":"Ibach",
    "sg:orig_category":"Detailhandel mit Getr\u00e4nken Mineralquellen, Herstellung von alkoholfreien Getr\u00e4nken",
    "sg:phone":"+41 41 811 28 87",
    "sg:postcode":"6438",
    "sg:province":"Schwyz",
    "wof:name":"Str\u00fcby Xaver",
    "wof:placetype":"venue"
},
  "geometry": {"coordinates":[8.6485528946,47.0070457458],"type":"Point"}
}