{
  "type": "Feature",
  "properties": {
    "addr:full":"Bernstrasse 45 Konolfingen Bern 3510",
    "addr:housenumber":"45",
    "addr:postcode":"3510",
    "addr:street":"Bernstrasse;Bern",
    "iso:country":"CH",
    "sg:address":"Bernstrasse 45",
    "sg:city":"Konolfingen",
    "sg:orig_category":"Blumen U Zierpflanzenbau Detailhandel mit Blumen U Pflanzen",
    "sg:phone":"+41 31 791 01 75",
    "sg:postcode":"3510",
    "sg:province":"Bern",
    "wof:name":"Alfred Hofmann G\u00e4rtnerei & Orchideenkulturen",
    "wof:placetype":"venue"
},
  "geometry": {"coordinates":[7.612157,46.878189],"type":"Point"}
}