{
  "type": "Feature",
  "properties": {
    "iso:country":"CH",
    "sg:address":"Michaelskreuzstrasse 15",
    "sg:city":"Root",
    "sg:orig_category":"Reiseb\u00fcros U Reiseveranstalter",
    "sg:phone":"+41 41 450 20 43",
    "sg:postcode":"6037",
    "sg:province":"Luzern",
    "wof:name":"Akwamoa Pronito & Waptours",
    "wof:placetype":"venue"
},
  "geometry": {"coordinates":[8.3961277008,47.1186714172],"type":"Point"}
}