{
  "type": "Feature",
  "properties": {
    "iso:country":"CH",
    "sg:address":"Gewerbestr. 20",
    "sg:city":"Aegerten",
    "sg:orig_category":"Sanit\u00e4r, Heizungs U L\u00fcftungsinstallation",
    "sg:phone":"+41 32 373 48 22",
    "sg:postcode":"2558",
    "sg:province":"Bern",
    "wof:name":"Von Ballmoos-heizungen",
    "wof:placetype":"venue"
},
  "geometry": {"coordinates":[7.2961711884,47.1252822876],"type":"Point"}
}