{
  "type": "Feature",
  "properties": {
    "iso:country":"CH",
    "sg:address":"Trittligasse 2",
    "sg:city":"Z\u00fcrich",
    "sg:orig_category":"Vorschulen, Kinderg\u00e4rten",
    "sg:phone":"+41 19303739",
    "sg:postcode":"8001",
    "sg:province":"Z\u00fcrich",
    "wof:name":"Ambulant.sprachheilunterricht",
    "wof:placetype":"venue"
},
  "geometry": {"coordinates":[8.8133382797,47.331325531],"type":"Point"}
}