{
  "type": "Feature",
  "properties": {
    "iso:country":"CH",
    "sg:address":"Rue Emile-yung 11",
    "sg:city":"Gen\u00e8ve",
    "sg:orig_category":"Zahntechnische Laboratorien",
    "sg:phone":"+41 71 277 61 90",
    "sg:postcode":"1205",
    "sg:province":"Gen\u00e8ve",
    "wof:name":"Alfred Juchli Zahntechnisches Labor",
    "wof:placetype":"venue"
},
  "geometry": {"coordinates":[9.3571472168,47.4212112427],"type":"Point"}
}