{
  "type": "Feature",
  "properties": {
    "iso:country":"CH",
    "sg:address":"R\u00fctmattstrasse 3 6017 Ruswil. Postfach",
    "sg:city":"Ruswil",
    "sg:orig_category":"Erbringung von Dienstleistungen f\u00fcr Unternehmen",
    "sg:postcode":"6017",
    "sg:province":"Luzern",
    "wof:name":"Swiss Prototech Ag",
    "wof:placetype":"venue"
},
  "geometry": {"coordinates":[8.1394329071,47.0810165405],"type":"Point"}
}