{
  "type": "Feature",
  "properties": {
    "iso:country":"CH",
    "sg:address":"France Faubourg De 10",
    "sg:city":"Porrentruy",
    "sg:orig_category":"Grosshandel mit sonstigen Maschinen U Ausr\u00fcstungen f\u00fcr Industrie, Handel U Schiffahrt",
    "sg:postcode":"2900",
    "sg:province":"Jura",
    "wof:name":"Roth Loader & Equipment S\u00e0rl",
    "wof:placetype":"venue"
},
  "geometry": {"coordinates":[7.0782270432,47.4170303345],"type":"Point"}
}