{
  "type": "Feature",
  "properties": {
    "iso:country":"CH",
    "sg:address":"Route De Mandement 197 1242 Satigny Case Postale 136",
    "sg:city":"Satigny",
    "sg:orig_category":"Detailhandel mit Brennstoffen U Heizmaterial Grosshandel mit festen Brennstoffen U Mineral\u00f6lerzeugni",
    "sg:phone":"+41 22 753 24 03",
    "sg:postcode":"1242",
    "sg:province":"Gen\u00e8ve",
    "wof:name":"L\u00e9ger Mazout Sa",
    "wof:placetype":"venue"
},
  "geometry": {"coordinates":[6.030959,46.212788],"type":"Point"}
}