{
  "type": "Feature",
  "properties": {
    "iso:country":"CH",
    "sg:address":"Bahnhofstrasse 10",
    "sg:city":"Schwerzenbach",
    "sg:orig_category":"Vereine Frauen Vereine Gemeinn\u00fctzige",
    "sg:phone":"+41 18253340",
    "sg:postcode":"8603",
    "sg:province":"Z\u00fcrich",
    "wof:name":"Frauenverein Schwerzenbach",
    "wof:placetype":"venue"
},
  "geometry": {"coordinates":[8.6544828415,47.3820533752],"type":"Point"}
}