{
  "type": "Feature",
  "properties": {
    "iso:country":"CH",
    "sg:address":"Avenue Dapples 17 1006 Lausanne. Postfach",
    "sg:city":"Lausanne",
    "sg:orig_category":"Architektur U Ingenieurb\u00fcros Architekturb\u00fcros",
    "sg:phone":"+41 21 601 12 28",
    "sg:postcode":"1003",
    "sg:province":"Vaud",
    "wof:name":"Widmer & Henzelin Architectes Sa",
    "wof:placetype":"venue"
},
  "geometry": {"coordinates":[6.627496,46.51442],"type":"Point"}
}