{
  "type": "Feature",
  "properties": {
    "iso:country":"CH",
    "sg:address":"Lindenhofstrasse 8",
    "sg:city":"Oftringen",
    "sg:orig_category":"Arztpraxen",
    "sg:phone":"+41 62 797 12 60",
    "sg:postcode":"4665",
    "sg:province":"Aargau",
    "wof:name":"Dr.med.lorenz Gerber Arzt F.allgemeine Medizin Fmh",
    "wof:placetype":"venue"
},
  "geometry": {"coordinates":[7.917014,47.316353],"type":"Point"}
}