{
  "type": "Feature",
  "properties": {
    "iso:country":"CH",
    "sg:address":"Riom",
    "sg:city":"Riom",
    "sg:classifiers":[
        {
            "category":"Banks & Credit Unions",
            "subcategory":"Bank",
            "type":"Services"
        }
    ],
    "sg:phone":"+41 81 684 11 66",
    "sg:postcode":"7463",
    "sg:province":"Graubunden",
    "wof:name":"Raiffeisen Riom",
    "wof:placetype":"venue"
},
  "geometry": {"coordinates":[9.58282,46.604912],"type":"Point"}
}