{
  "type": "Feature",
  "properties": {
    "iso:country":"CH",
    "sg:address":"Avenue De La Gare",
    "sg:city":"St-l\u00e9onard",
    "sg:orig_category":"Grosshandel mit festen Brennstoffen U Mineral\u00f6lerzeugnissen",
    "sg:phone":"+41 27 203 13 61",
    "sg:postcode":"1958",
    "sg:province":"Valais",
    "wof:name":"Cresa Sa",
    "wof:placetype":"venue"
},
  "geometry": {"coordinates":[7.4193029404,46.2515258789],"type":"Point"}
}