{
  "type": "Feature",
  "properties": {
    "iso:country":"CH",
    "sg:address":"Sunnetalstrasse 11",
    "sg:city":"F\u00e4llanden",
    "sg:orig_category":"Markt U Meinungsforschung",
    "sg:phone":"+41 18250402",
    "sg:postcode":"8117",
    "sg:province":"Z\u00fcrich",
    "wof:name":"Sulger Marketing & Communications",
    "wof:placetype":"venue"
},
  "geometry": {"coordinates":[8.6431112289,47.3714332581],"type":"Point"}
}