{
  "type": "Feature",
  "properties": {
    "addr:full":"Koppigenstrasse 8 Utzenstorf Bern 3427",
    "addr:housenumber":"8",
    "addr:postcode":"3427",
    "addr:street":"Koppigenstrasse",
    "iso:country":"CH",
    "sg:address":"Koppigenstrasse 8",
    "sg:city":"Utzenstorf",
    "sg:orig_category":"Berufsorganisationen",
    "sg:postcode":"3427",
    "sg:province":"Bern",
    "wof:name":"Team 93",
    "wof:placetype":"venue"
},
  "geometry": {"coordinates":[8.856864,47.651268],"type":"Point"}
}