{
  "type": "Feature",
  "properties": {
    "iso:country":"CH",
    "sg:address":"Rue Des Hautes-bornes 5",
    "sg:city":"Ligni\u00e8res",
    "sg:orig_category":"Mit Sport verbundene T\u00e4tigkeiten",
    "sg:phone":"+41 32 751 15 95",
    "sg:postcode":"2523",
    "sg:province":"Neuch\u00e2tel",
    "wof:name":"Gilbert Gauchat Centre \u00e9questre",
    "wof:placetype":"venue"
},
  "geometry": {"coordinates":[7.0658922195,47.0823822021],"type":"Point"}
}