{
  "type": "Feature",
  "properties": {
    "iso:country":"CH",
    "sg:address":"Dorfstrasse 101",
    "sg:city":"Glattfelden",
    "sg:orig_category":"Detailhandel mit Milcherzeugnissen U Eiern",
    "sg:phone":"+41 18671333",
    "sg:postcode":"8192",
    "sg:province":"Z\u00fcrich",
    "wof:name":"Heidi K\u00fcndig Milchladen",
    "wof:placetype":"venue"
},
  "geometry": {"coordinates":[8.4967937469,47.5603027344],"type":"Point"}
}