{
  "type": "Feature",
  "properties": {
    "iso:country":"CH",
    "sg:address":"1897",
    "sg:city":"Bouveret",
    "sg:orig_category":"Instandhaltung U Reparatur von Automobilen",
    "sg:phone":"+41 24 481 28 17",
    "sg:postcode":"1897",
    "sg:province":"Valais",
    "wof:name":"Garage Peiry, Le Bouveret",
    "wof:placetype":"venue"
},
  "geometry": {"coordinates":[6.8527798653,46.3853187561],"type":"Point"}
}