{
  "type": "Feature",
  "properties": {
    "iso:country":"CH",
    "sg:address":"Rue Maunoir 19",
    "sg:city":"Gen\u00e8ve",
    "sg:orig_category":"Detailhandel mit medizinischen U orthop\u00e4dischen Artikeln Reparatur von Schuhen U Lederwaren",
    "sg:phone":"+41 22 735 83 01",
    "sg:postcode":"1207",
    "sg:province":"Gen\u00e8ve",
    "wof:name":"Jos\u00e9 Luis Pombo Cordonnerie & Orthop\u00e9die",
    "wof:placetype":"venue"
},
  "geometry": {"coordinates":[6.1610488892,46.2032814026],"type":"Point"}
}