{
  "type": "Feature",
  "properties": {
    "iso:country":"CH",
    "sg:address":"Breisacherstrasse 65",
    "sg:city":"Basel",
    "sg:orig_category":"Sonstige mit der Informatik verbundene T\u00e4tigkeiten",
    "sg:phone":"+41 61 381 71 25",
    "sg:postcode":"4057",
    "sg:province":"Basel-Stadt",
    "wof:name":"Duschletta Beratungen",
    "wof:placetype":"venue"
},
  "geometry": {"coordinates":[7.5886459351,47.5669937134],"type":"Point"}
}