{
  "type": "Feature",
  "properties": {
    "iso:country":"CH",
    "sg:address":"N\u00e4geligaessli 7",
    "sg:city":"Port",
    "sg:orig_category":"Herstellung von Spirituosen",
    "sg:phone":"+41 32 331 85 83",
    "sg:postcode":"2562",
    "sg:province":"Bern",
    "wof:name":"Z\u00fcrcher Heinz, Brennerei.",
    "wof:placetype":"venue"
},
  "geometry": {"coordinates":[7.2432169914,47.1168785095],"type":"Point"}
}