{
  "type": "Feature",
  "properties": {
    "iso:country":"CH",
    "sg:address":"Zurlindenstrasse 211 8003 Z\u00fcrich. Postfach",
    "sg:city":"Z\u00fcrich",
    "sg:orig_category":"Fachdetailhandel mit pharmazeutischen Produkten",
    "sg:phone":"+41 14512073",
    "sg:postcode":"8004",
    "sg:province":"Z\u00fcrich",
    "wof:name":"Idaplatz-apotheke, K\u00e4lin Katharina",
    "wof:placetype":"venue"
},
  "geometry": {"coordinates":[8.5144033432,47.3745231628],"type":"Point"}
}