{
  "type": "Feature",
  "properties": {
    "iso:country":"CH",
    "sg:address":"Sch\u00fctzenstrasse 29",
    "sg:city":"Feuerthalen",
    "sg:orig_category":"Detailhandel mit Teppichen",
    "sg:phone":"+41 52 647 46 10",
    "sg:postcode":"8245",
    "sg:province":"Z\u00fcrich",
    "wof:name":"Top Tip Rudolf M\u00fcller Ag M\u00f6bel Teppiche",
    "wof:placetype":"venue"
},
  "geometry": {"coordinates":[8.6472520828,47.6911773682],"type":"Point"}
}