{
  "type": "Feature",
  "properties": {
    "iso:country":"CH",
    "sg:address":"Greyerzerstrasse 48 3013 Bern. Postfach",
    "sg:city":"Bern",
    "sg:orig_category":"K\u00fcnstlerische U schriftstellerische T\u00e4tigkeiten U Darbietungen",
    "sg:postcode":"3013",
    "sg:province":"Bern",
    "wof:name":"Boutique Margrit Kunstgewerbe Ag, St. Moritz.",
    "wof:placetype":"venue"
},
  "geometry": {"coordinates":[9.8381109238,46.4978523254],"type":"Point"}
}