{
  "type": "Feature",
  "properties": {
    "iso:country":"CH",
    "sg:address":"Arbonerstrasse 6 Kronb\u00fchl 9303 Wittenbach. Postfach",
    "sg:city":"Kronb\u00fchl",
    "sg:classifiers":[
        {
            "category":"Communications",
            "subcategory":"Radio Station",
            "type":"Services"
        }
    ],
    "sg:postcode":"9302",
    "sg:tags":[
        "fernsehanstalten",
        "u"
    ],
    "wof:name":"Grb Kobi & Co",
    "wof:placetype":"venue"
},
  "geometry": {"coordinates":[8.3114833832,46.9857254028],"type":"Point"}
}