{
  "type": "Feature",
  "properties": {
    "iso:country":"CH",
    "sg:address":"Zum Graben 1",
    "sg:city":"Termen",
    "sg:orig_category":"Detailhandel mit M\u00f6beln Verlegen von Fussboden",
    "sg:phone":"+41 27 923 30 87",
    "sg:postcode":"3912",
    "sg:province":"Valais",
    "wof:name":"Josef Guntern M\u00f6bel-& Teppichhaus",
    "wof:placetype":"venue"
},
  "geometry": {"coordinates":[8.0156860352,46.323184967],"type":"Point"}
}