{
  "type": "Feature",
  "properties": {
    "iso:country":"CH",
    "sg:address":"1071",
    "sg:city":"Chexbres",
    "sg:orig_category":"Sportvereine Sch\u00fctzen",
    "sg:postcode":"1071",
    "sg:province":"Vaud",
    "wof:name":"St\u00e9 De Tir Armes De Guerre",
    "wof:placetype":"venue"
},
  "geometry": {"coordinates":[6.7695250511,46.5411186218],"type":"Point"}
}