{
  "type": "Feature",
  "properties": {
    "iso:country":"CH",
    "sg:address":"Industriestr. 211",
    "sg:city":"Olten",
    "sg:classifiers":[
        {
            "category":"Manufacturing",
            "subcategory":"Metals",
            "type":"Manufacturing & Wholesale Goods"
        }
    ],
    "sg:phone":"+41 62 287 87 87",
    "sg:postcode":"4601",
    "sg:province":"Solothurn",
    "sg:tags":[
        "metallurgy",
        "metalworking",
        "processing"
    ],
    "wof:name":"Xaloy Ag",
    "wof:placetype":"venue"
},
  "geometry": {"coordinates":[7.9189381599,47.3658676147],"type":"Point"}
}