{
  "type": "Feature",
  "properties": {
    "iso:country":"CH",
    "sg:address":"Centrale Rue 25 1003 Lausanne. Postfach",
    "sg:city":"Lausanne",
    "sg:orig_category":"Detailhandel mit Bekleidung",
    "sg:phone":"+41 56 442 25 75",
    "sg:postcode":"1003",
    "sg:province":"Vaud",
    "wof:name":"Boutique Fil \u00e0 Fil Ag",
    "wof:placetype":"venue"
},
  "geometry": {"coordinates":[8.207113,47.484673],"type":"Point"}
}