{
  "type": "Feature",
  "properties": {
    "iso:country":"CH",
    "sg:address":"Zi De Maillarde",
    "sg:city":"Romont",
    "sg:classifiers":[
        {
            "category":"Manufacturing",
            "subcategory":"Glass & Minerals",
            "type":"Manufacturing & Wholesale Goods"
        }
    ],
    "sg:phone":"+41 26 651 94 20",
    "sg:postcode":"1680",
    "sg:province":"Fribourg",
    "sg:tags":[
        "building",
        "material"
    ],
    "wof:name":"Securit Sa",
    "wof:placetype":"venue"
},
  "geometry": {"coordinates":[6.9034991264,46.6823425293],"type":"Point"}
}