{
  "type": "Feature",
  "properties": {
    "iso:country":"CH",
    "sg:address":"St. Galler Strasse 89",
    "sg:city":"Flawil",
    "sg:orig_category":"Pensionskassen",
    "sg:phone":"+41 71 393 45 75",
    "sg:postcode":"9230",
    "sg:province":"St. Gallen",
    "wof:name":"Pensionskasse St. Gallischer Gemeinden",
    "wof:placetype":"venue"
},
  "geometry": {"coordinates":[9.1934785843,47.4125137329],"type":"Point"}
}