{
  "type": "Feature",
  "properties": {
    "iso:country":"CH",
    "sg:address":"Saint-pierre Rue 2",
    "sg:city":"Lausanne",
    "sg:orig_category":"Interessenvertretungen",
    "sg:postcode":"1003",
    "sg:province":"Vaud",
    "wof:name":"Fondation M\u00e9moire \u00e9ditoriale",
    "wof:placetype":"venue"
},
  "geometry": {"coordinates":[6.6367921829,46.5196075439],"type":"Point"}
}