{
  "type": "Feature",
  "properties": {
    "iso:country":"CH",
    "sg:address":"Route Du Mont Carmel 11",
    "sg:city":"Givisiez",
    "sg:orig_category":"Finanzierungsinstitutionen",
    "sg:phone":"+41 26 466 43 53",
    "sg:postcode":"1762",
    "sg:province":"Fribourg",
    "wof:name":"Marnan Investments Sa",
    "wof:placetype":"venue"
},
  "geometry": {"coordinates":[7.1352229118,46.8137435913],"type":"Point"}
}