{
  "type": "Feature",
  "properties": {
    "iso:country":"CH",
    "sg:address":"Bahnhofstrasse 3",
    "sg:city":"Herzogenbuchsee",
    "sg:orig_category":"Detailhandel mit Schuhen Grosshandel mit Schuhen",
    "sg:phone":"+41 62 961 29 79",
    "sg:postcode":"3360",
    "sg:province":"Bern",
    "wof:name":"Rudolf Staub",
    "wof:placetype":"venue"
},
  "geometry": {"coordinates":[7.7034978867,47.1874961853],"type":"Point"}
}