{
  "type": "Feature",
  "properties": {
    "iso:country":"CH",
    "sg:address":"Neubr\u00fcckstrasse 105 3000 Bern. Postfach",
    "sg:city":"Bern",
    "sg:orig_category":"Softwareentwicklung U beratung",
    "sg:postcode":"3005",
    "sg:province":"Bern",
    "wof:name":"Alfimacro Systems Ai Fedail",
    "wof:placetype":"venue"
},
  "geometry": {"coordinates":[7.4353709221,46.9592857361],"type":"Point"}
}