{
  "type": "Feature",
  "properties": {
    "iso:country":"CH",
    "sg:address":"Via Giuseppe Bagutti 14 6900 Lugano. Postfach",
    "sg:city":"Lugano",
    "sg:orig_category":"Finanzierungsinstitutionen",
    "sg:postcode":"6900",
    "sg:province":"Ticino",
    "wof:name":"B & B Swiss Capital Advisor Gmbh Servizi E Prodotti Assicurativi E Bancari Rel. Agli Investimenti Di Capitali; Promozione, Intermediazione Ecc",
    "wof:placetype":"venue"
},
  "geometry": {"coordinates":[8.9565076828,46.0146102905],"type":"Point"}
}