{
  "type": "Feature",
  "properties": {
    "iso:country":"CH",
    "sg:address":"Strada Cantonale",
    "sg:city":"Gordevio",
    "sg:classifiers":[
        {
            "category":"Government",
            "subcategory":"Post Office",
            "type":"Public Place"
        }
    ],
    "sg:phone":"+41 91 753 23 76",
    "sg:postcode":"6672",
    "sg:province":"Ticino",
    "sg:tags":[
        "caf\u00e9s",
        "tea-rooms"
    ],
    "wof:name":"Tea-room-bar Portico",
    "wof:placetype":"venue"
},
  "geometry": {"coordinates":[8.7422895432,46.2240104675],"type":"Point"}
}