{
  "type": "Feature",
  "properties": {
    "iso:country":"CH",
    "sg:address":"Neumarktstrasse 10",
    "sg:city":"Biel/bienne",
    "sg:orig_category":"RESTAURANTS: TEA-ROOMS",
    "sg:postcode":"2502",
    "sg:province":"Bern",
    "wof:name":"Pizzeria Delfino Gmbh",
    "wof:placetype":"venue"
},
  "geometry": {"coordinates":[7.2479310036,47.1405067444],"type":"Point"}
}