{
  "type": "Feature",
  "properties": {
    "iso:country":"CH",
    "sg:address":"Balierestrasse 10 8500 Frauenfeld. Postfach 3083",
    "sg:city":"Frauenfeld",
    "sg:orig_category":"Herstellung von Radio U Fernsehger\u00e4ten sowie phono U videotechnischen Ger\u00e4ten",
    "sg:phone":"+41 52 722 44 33",
    "sg:postcode":"8500",
    "sg:province":"Thurgau",
    "wof:name":"H+mmusic Meyer & Partner",
    "wof:placetype":"venue"
},
  "geometry": {"coordinates":[8.8950929642,47.555103302],"type":"Point"}
}