{
  "type": "Feature",
  "properties": {
    "iso:country":"CH",
    "sg:address":"Oberdorf 116",
    "sg:city":"Beggingen",
    "sg:orig_category":"Herstellung von Elektrizit\u00e4tsverteilungs U schalteinrichtungen Herstellung von elektronischen Bauele",
    "sg:phone":"+41 52 680 22 25",
    "sg:postcode":"8228",
    "sg:province":"Schaffhausen",
    "wof:name":"W. Leu Gmbh Elektroapparate Schaltanlagen",
    "wof:placetype":"venue"
},
  "geometry": {"coordinates":[8.5389347076,47.7653083801],"type":"Point"}
}