{
  "type": "Feature",
  "properties": {
    "iso:country":"CH",
    "sg:address":"Langmauerstrasse 109",
    "sg:city":"Z\u00fcrich",
    "sg:orig_category":"Vermittlung von Immobilien Verwaltung von Immobilien",
    "sg:phone":"+41 71 282 50 11",
    "sg:postcode":"8006",
    "sg:province":"Z\u00fcrich",
    "wof:name":"Stephanshorn Treuhand Ag Liegenschaften; An, Verkauf, Vermittlung, Verwaltung Usw",
    "wof:placetype":"venue"
},
  "geometry": {"coordinates":[9.4093389511,47.439655304],"type":"Point"}
}