{
  "type": "Feature",
  "properties": {
    "iso:country":"CH",
    "sg:address":"Flughofstrasse 37 8152 Glattbrugg. Postfach",
    "sg:city":"Glattbrugg",
    "sg:orig_category":"Herstellung von optischen U fotografischen Ger\u00e4ten",
    "sg:postcode":"8152",
    "sg:province":"Z\u00fcrich",
    "wof:name":"Movie Island, R\u00fcfli & L\u00f6pfe",
    "wof:placetype":"venue"
},
  "geometry": {"coordinates":[9.382484436,47.4332046509],"type":"Point"}
}