{
  "type": "Feature",
  "properties": {
    "iso:country":"CH",
    "sg:address":"Fendt Rue 4 1201 Gen\u00e8ve. Postfach",
    "sg:city":"Gen\u00e8ve",
    "sg:orig_category":"Forstwirtschaft ohne Dienstleistungen in der Forstwirtschaft",
    "sg:postcode":"1201",
    "sg:province":"Gen\u00e8ve",
    "wof:name":"L'association Pour La Sauvegarde Et La Protection Des For\u00eats",
    "wof:placetype":"venue"
},
  "geometry": {"coordinates":[6.1411252022,46.2108383179],"type":"Point"}
}