{
  "type": "Feature",
  "properties": {
    "iso:country":"CH",
    "sg:address":"Via Maistra",
    "sg:city":"Susch",
    "sg:classifiers":[
        {
            "category":"Travel",
            "subcategory":"Hotels & Motels",
            "type":"Entertainment"
        }
    ],
    "sg:phone":"+41 81 862 29 43",
    "sg:postcode":"7542",
    "sg:province":"Graubunden",
    "sg:tags":[
        "hotels",
        "mit",
        "restaurant"
    ],
    "wof:name":"Hotel Schweizerhof",
    "wof:placetype":"venue"
},
  "geometry": {"coordinates":[10.0782909393,46.74792099],"type":"Point"}
}