{
  "type": "Feature",
  "properties": {
    "iso:country":"CH",
    "sg:address":"6952",
    "sg:city":"Canobbio",
    "sg:orig_category":"Non-Classified Establishments",
    "sg:phone":"+41 91 941 85 00",
    "sg:postcode":"6952",
    "sg:province":"Ticino",
    "wof:name":"Fratelli Martinenghi Sa",
    "wof:placetype":"venue"
},
  "geometry": {"coordinates":[8.9687299728,46.0362205505],"type":"Point"}
}