{
  "type": "Feature",
  "properties": {
    "iso:country":"CH",
    "sg:address":"Route De Beaumont 20",
    "sg:city":"Fribourg",
    "sg:classifiers":[
        {
            "category":"Professional",
            "subcategory":"Engineering",
            "type":"Services"
        }
    ],
    "sg:phone":"+41 26 425 50 60",
    "sg:postcode":"1700",
    "sg:province":"Fribourg",
    "sg:tags":[
        "application",
        "engineer"
    ],
    "wof:name":"Pierre Chuard S.a.",
    "wof:placetype":"venue"
},
  "geometry": {"coordinates":[7.140626,46.796673],"type":"Point"}
}