{
  "type": "Feature",
  "properties": {
    "iso:country":"CH",
    "sg:address":"Corraterie Rue De La 9 1204 Gen\u00e8ve. Postfach",
    "sg:city":"Gen\u00e8ve",
    "sg:orig_category":"Non-Classified Establishments",
    "sg:postcode":"1204",
    "sg:province":"Gen\u00e8ve",
    "wof:name":"Hadiag Ag",
    "wof:placetype":"venue"
},
  "geometry": {"coordinates":[9.2689399719,47.4146232605],"type":"Point"}
}