{
  "type": "Feature",
  "properties": {
    "iso:country":"CH",
    "sg:address":"Birmensdorferstrasse",
    "sg:city":"Urdorf",
    "sg:orig_category":"Unclassifiable Establishments",
    "sg:postcode":"8902",
    "sg:province":"Z\u00fcrich",
    "wof:name":"Kleiner Konditorei-b\u00e4ckerei Ag",
    "wof:placetype":"venue"
},
  "geometry": {"coordinates":[8.4174947739,47.3929748535],"type":"Point"}
}