{
  "type": "Feature",
  "properties": {
    "iso:country":"CH",
    "sg:address":"Hauptstrasse 61",
    "sg:city":"Magden",
    "sg:orig_category":"Einzelhandel mit Automobilteilen U Zubeh\u00f6r",
    "sg:phone":"+41 32 931 13 69",
    "sg:postcode":"4312",
    "sg:province":"Aargau",
    "wof:name":"Antonio Marcello Fiore Pneus",
    "wof:placetype":"venue"
},
  "geometry": {"coordinates":[6.7593607903,47.0633125305],"type":"Point"}
}