{
  "type": "Feature",
  "properties": {
    "iso:country":"CH",
    "sg:address":"Wiesliacher 87 8053 Z\u00fcrich. Postfach",
    "sg:city":"Z\u00fcrich",
    "sg:orig_category":"Interessenvertretungen",
    "sg:phone":"+41 14220879",
    "sg:postcode":"8053",
    "sg:province":"Z\u00fcrich",
    "wof:name":"Ring Thomas-stiftung Weiterentwicklung Des Werkes V. Thomas Ring Usw",
    "wof:placetype":"venue"
},
  "geometry": {"coordinates":[8.5969314575,47.3547782898],"type":"Point"}
}