{
  "type": "Feature",
  "properties": {
    "iso:country":"CH",
    "sg:address":"Z.i. Chemin Du Bief 6",
    "sg:city":"Lonay",
    "sg:orig_category":"Grosshandel mit Getr\u00e4nken",
    "sg:phone":"+41 41 870 77 77",
    "sg:postcode":"1027",
    "sg:province":"Vaud",
    "wof:name":"Aschwanden Franz Mineralwasser",
    "wof:placetype":"venue"
},
  "geometry": {"coordinates":[8.6527862549,46.8749656677],"type":"Point"}
}