{
  "type": "Feature",
  "properties": {
    "iso:country":"CH",
    "sg:address":"Untere Fischbachstrasse 3",
    "sg:city":"Mettmenstetten",
    "sg:orig_category":"Informatikdienste Sonstiger Grosshandel",
    "sg:phone":"+41 17768636",
    "sg:postcode":"8932",
    "sg:province":"Z\u00fcrich",
    "wof:name":"Walter Data",
    "wof:placetype":"venue"
},
  "geometry": {"coordinates":[8.4574832916,47.2458839417],"type":"Point"}
}