{
  "type": "Feature",
  "properties": {
    "iso:country":"CH",
    "sg:address":"Hauptstrasse 90",
    "sg:city":"Degersheim",
    "sg:orig_category":"Vereine Geselligkeit",
    "sg:phone":"+41 71 371 35 98",
    "sg:postcode":"9113",
    "sg:province":"St. Gallen",
    "wof:name":"T\u00fcrkischer Kultur Verein",
    "wof:placetype":"venue"
},
  "geometry": {"coordinates":[9.1947050095,47.371421814],"type":"Point"}
}