{
  "type": "Feature",
  "properties": {
    "iso:country":"CH",
    "sg:address":"Parkstrasse 22",
    "sg:city":"Sch\u00f6nenwerd",
    "sg:orig_category":"Grosshandel mit Erzen U Metallen Grosshandel mit Holz U Baustoffen",
    "sg:phone":"+41 62 849 01 51",
    "sg:postcode":"5012",
    "sg:province":"Solothurn",
    "wof:name":"Vms Ag Stahlzargen Beschl\u00e4ge",
    "wof:placetype":"venue"
},
  "geometry": {"coordinates":[7.9984688759,47.3703842163],"type":"Point"}
}