{
  "type": "Feature",
  "properties": {
    "iso:country":"CH",
    "sg:address":"Rue Du Moutier 11",
    "sg:city":"Vallorbe",
    "sg:orig_category":"Detailhandel mit Textilien Sonstiger Grosshandel",
    "sg:phone":"+41 21 843 17 43",
    "sg:postcode":"1337",
    "sg:province":"Vaud",
    "wof:name":"La Soie Sa",
    "wof:placetype":"venue"
},
  "geometry": {"coordinates":[6.374723,46.711205],"type":"Point"}
}