{
  "type": "Feature",
  "properties": {
    "iso:country":"CH",
    "sg:address":"Strandweg 32",
    "sg:city":"Nidau",
    "sg:orig_category":"Sportvereine J and S Fachleiter Sportvereine Wassersport Schwimmen",
    "sg:phone":"+41 32 331 73 76",
    "sg:postcode":"2560",
    "sg:province":"Bern",
    "wof:name":"J & S Fachleiter",
    "wof:placetype":"venue"
},
  "geometry": {"coordinates":[7.234254837,47.1247062683],"type":"Point"}
}