{
  "type": "Feature",
  "properties": {
    "iso:country":"CH",
    "sg:address":"Kirchtalstrasse 25",
    "sg:city":"Seon",
    "sg:orig_category":"Kaminfeger",
    "sg:phone":"+41 62 775 19 27",
    "sg:postcode":"5703",
    "sg:province":"Aargau",
    "wof:name":"Ulrich L\u00fcscher Kaminfegermeister",
    "wof:placetype":"venue"
},
  "geometry": {"coordinates":[8.1551876068,47.3507461548],"type":"Point"}
}