{
  "type": "Feature",
  "properties": {
    "iso:country":"CH",
    "sg:address":"Gibelinstrasse 25",
    "sg:city":"Solothurn",
    "sg:orig_category":"Werbevermittlung",
    "sg:phone":"+41 32 623 69 18",
    "sg:postcode":"4500",
    "sg:province":"Solothurn",
    "wof:name":"Apg/sga Allgemeine Plakatgesellschaft",
    "wof:placetype":"venue"
},
  "geometry": {"coordinates":[7.5257458687,47.2085266113],"type":"Point"}
}