{
  "type": "Feature",
  "properties": {
    "iso:country":"CH",
    "sg:address":"Hauptbahnhofstrasse 12",
    "sg:city":"Solothurn",
    "sg:orig_category":"Vermietung U Verpachtung von eigenen Immobilien",
    "sg:postcode":"4500",
    "sg:province":"Solothurn",
    "wof:name":"Soreal Immobilien Ag",
    "wof:placetype":"venue"
},
  "geometry": {"coordinates":[7.5416560173,47.2044639587],"type":"Point"}
}