{
  "type": "Feature",
  "properties": {
    "addr:full":"Via Ferruccio Pelli 7 Lugano Ticino 6900",
    "addr:housenumber":"7",
    "addr:postcode":"6900",
    "addr:street":"Via Ferruccio Pelli",
    "iso:country":"CH",
    "sg:address":"Via Ferruccio Pelli 7",
    "sg:city":"Lugano",
    "sg:orig_category":"Ackerbau Grosshandel mit Nahrungsmitteln, Getr\u00e4nken U Tabakwaren",
    "sg:phone":"+41 91 912 30 19",
    "sg:postcode":"6900",
    "sg:province":"Ticino",
    "wof:name":"Imexho Sa",
    "wof:placetype":"venue"
},
  "geometry": {"coordinates":[8.950673,46.007595],"type":"Point"}
}