{
  "type": "Feature",
  "properties": {
    "addr:full":"Limmatstrasse 4 Spreitenbach Aargau 8957",
    "addr:housenumber":"4",
    "addr:postcode":"8957",
    "addr:street":"Limmatstrasse",
    "iso:country":"CH",
    "sg:address":"Limmatstrasse 4",
    "sg:city":"Spreitenbach",
    "sg:classifiers":[
        {
            "category":"Utilities",
            "subcategory":"Natural Gas",
            "type":"Services"
        }
    ],
    "sg:phone":"+41 56 417 20 00",
    "sg:postcode":"8957",
    "sg:province":"Aargau",
    "sg:tags":[
        "baking",
        "oven"
    ],
    "wof:name":"Miele Ag",
    "wof:placetype":"venue"
},
  "geometry": {"coordinates":[8.371922,47.429214],"type":"Point"}
}