{
  "type": "Feature",
  "properties": {
    "iso:country":"CH",
    "sg:address":"Dufourstrasse 17 3005 Bern. Postfach 223",
    "sg:city":"Bern",
    "sg:orig_category":"Werbung",
    "sg:phone":"+41 31 352 24 48",
    "sg:postcode":"3005",
    "sg:province":"Bern",
    "wof:name":"Paul Kreis Ag",
    "wof:placetype":"venue"
},
  "geometry": {"coordinates":[7.4547591209,46.9423141479],"type":"Point"}
}