{
  "type": "Feature",
  "properties": {
    "iso:country":"CH",
    "sg:address":"Rte De Lossy 20",
    "sg:city":"Belfaux",
    "sg:classifiers":[
        {
            "category":"Manufacturing",
            "subcategory":"Rubber & Plastics",
            "type":"Manufacturing & Wholesale Goods"
        }
    ],
    "sg:phone":"+41 26 475 91 11",
    "sg:postcode":"1782",
    "sg:province":"Fribourg",
    "wof:name":"Boxal Suisse Sa",
    "wof:placetype":"venue"
},
  "geometry": {"coordinates":[7.109822,46.823578],"type":"Point"}
}