{
  "type": "Feature",
  "properties": {
    "iso:country":"CH",
    "sg:address":"Flurstrasse 2",
    "sg:city":"Sirnach",
    "sg:orig_category":"Erbringung von Dienstleistungen f\u00fcr Unternehmen",
    "sg:phone":"+41 71 910 00 65",
    "sg:postcode":"8370",
    "sg:province":"Thurgau",
    "wof:name":"Rebsamen K. Tema Form",
    "wof:placetype":"venue"
},
  "geometry": {"coordinates":[8.9927616119,47.4639816284],"type":"Point"}
}