{
  "type": "Feature",
  "properties": {
    "iso:country":"CH",
    "sg:address":"1290 Versoix. Postfach",
    "sg:city":"Versoix",
    "sg:orig_category":"Wasserversorgung",
    "sg:postcode":"1290",
    "sg:province":"Gen\u00e8ve",
    "wof:name":"Union Des Propri\u00e9taires De Droits D'eau Sur La Versoix",
    "wof:placetype":"venue"
},
  "geometry": {"coordinates":[6.1671500206,46.280292511],"type":"Point"}
}