{
  "type": "Feature",
  "properties": {
    "iso:country":"CH",
    "sg:address":"Lagerplatz 27 8400 Winterthur. Postfach",
    "sg:city":"Winterthur",
    "sg:orig_category":"Herstellung von Musikinstrumenten",
    "sg:phone":"+41 52 213 11 66",
    "sg:postcode":"8400",
    "sg:province":"Z\u00fcrich",
    "wof:name":"Horak Pianos Klavierbauer Und Stimmer",
    "wof:placetype":"venue"
},
  "geometry": {"coordinates":[8.7175207138,47.4938240051],"type":"Point"}
}