{
  "type": "Feature",
  "properties": {
    "iso:country":"CH",
    "sg:address":"Z\u00fcrcherstrasse 330 8500 Frauenfeld. Postfach",
    "sg:city":"Frauenfeld",
    "sg:orig_category":"Instandhaltung U Reparatur von Automobilen",
    "sg:phone":"+41 79 436 43 17",
    "sg:postcode":"8503",
    "sg:province":"Thurgau",
    "wof:name":"Autolackier-fachbetrieb Marjai",
    "wof:placetype":"venue"
},
  "geometry": {"coordinates":[9.544678688,47.4842567444],"type":"Point"}
}