{
  "type": "Feature",
  "properties": {
    "iso:country":"CH",
    "sg:address":"Route De Martigny 117",
    "sg:city":"Fully",
    "sg:orig_category":"Instandhaltung U Reparatur von Automobilen",
    "sg:phone":"+41 27 746 10 75",
    "sg:postcode":"1926",
    "sg:province":"Valais",
    "wof:name":"Christian Carron Carrosserie De La Louye",
    "wof:placetype":"venue"
},
  "geometry": {"coordinates":[7.1072697639,46.1321563721],"type":"Point"}
}