{
  "type": "Feature",
  "properties": {
    "iso:country":"CH",
    "sg:address":"9427 Wolfhalden. Postfach",
    "sg:city":"Wolfhalden",
    "sg:orig_category":"Gemeindeverwaltungen",
    "sg:phone":"+41 71 898 82 84",
    "sg:postcode":"9427",
    "sg:province":"Appenzell Ausserrhoden",
    "wof:name":"Gemeindeverwaltung Wolfhalden",
    "wof:placetype":"venue"
},
  "geometry": {"coordinates":[9.5497522354,47.453414917],"type":"Point"}
}