{
  "type": "Feature",
  "properties": {
    "iso:country":"CH",
    "sg:address":"Stationsstrasse 13",
    "sg:city":"Bonstetten",
    "sg:orig_category":"Grosshandel mit Maschinen U Ausr\u00fcstungen Grosshandel mit sonstigen Maschinen U Ausr\u00fcstungen f\u00fcr Indu",
    "sg:phone":"+41 17001424",
    "sg:postcode":"8906",
    "sg:province":"Z\u00fcrich",
    "wof:name":"Schlegel Ag, Blechbearbeitungsmaschinen",
    "wof:placetype":"venue"
},
  "geometry": {"coordinates":[8.4612493515,47.316532135],"type":"Point"}
}