{
  "type": "Feature",
  "properties": {
    "iso:country":"CH",
    "sg:address":"Carmen Via Monte 1a",
    "sg:city":"Lugano",
    "sg:orig_category":"Herstellung von medizinischen U chirurgischen Ger\u00e4ten sowie orthop\u00e4dischen Vorrichtungen",
    "sg:postcode":"6900",
    "sg:province":"Ticino",
    "wof:name":"Estetiker Laboratorio D'odontotecnica Di Frigerio Damiano E Fieni Marisa",
    "wof:placetype":"venue"
},
  "geometry": {"coordinates":[8.9524908066,46.0125846863],"type":"Point"}
}