{
  "type": "Feature",
  "properties": {
    "iso:country":"CH",
    "sg:address":"Spitalgass-passage 16",
    "sg:city":"Bern",
    "sg:classifiers":[
        {
            "category":"Government",
            "subcategory":"Post Office",
            "type":"Public Place"
        }
    ],
    "sg:phone":"+41 22 300 20 98",
    "sg:postcode":"3011",
    "sg:province":"Bern",
    "sg:tags":[
        "caf\u00e9s",
        "tea-rooms"
    ],
    "wof:name":"Caf\u00e9-bar Au Petit Coll\u00e9ge",
    "wof:placetype":"venue"
},
  "geometry": {"coordinates":[6.1405858994,46.1833686829],"type":"Point"}
}