{
  "type": "Feature",
  "properties": {
    "iso:country":"CH",
    "sg:address":"Seelandweg 9",
    "sg:city":"Biel/bienne",
    "sg:orig_category":"Geb\u00e4ude, Wohnungsreinigung Reinigungsgewerbe",
    "sg:phone":"+41 32 365 45 15",
    "sg:postcode":"2503",
    "sg:province":"Bern",
    "wof:name":"Arn Reinigungen Ag",
    "wof:placetype":"venue"
},
  "geometry": {"coordinates":[7.2500910759,47.1313896179],"type":"Point"}
}