{
  "type": "Feature",
  "properties": {
    "iso:country":"CH",
    "sg:address":"Obergass 40",
    "sg:city":"Eglisau",
    "sg:orig_category":"Detailhandel mit Brot, Back U S\u00fcsswaren",
    "sg:postcode":"8193",
    "sg:province":"Z\u00fcrich",
    "wof:name":"Antonio's Torten - Goncalves",
    "wof:placetype":"venue"
},
  "geometry": {"coordinates":[8.525126,47.575645],"type":"Point"}
}