{
  "type": "Feature",
  "properties": {
    "iso:country":"CH",
    "sg:address":"20 Route De Pr\u00e9-bois",
    "sg:city":"Geneva",
    "sg:classifiers":[
        {
            "category":"Industrial Area",
            "type":"Public Place"
        }
    ],
    "sg:phone":"+41 61 325 35 10",
    "sg:postcode":"1215",
    "sg:province":"Gen\u00e8ve",
    "sg:tags":[
        "large",
        "private"
    ],
    "wof:name":"Swiss International Air Lines Ltd.",
    "wof:placetype":"venue"
},
  "geometry": {"coordinates":[7.587679863,47.548740387],"type":"Point"}
}