{
  "type": "Feature",
  "properties": {
    "iso:country":"CH",
    "sg:address":"M\u00fcnchensteinerstrasse 134",
    "sg:city":"Basel",
    "sg:orig_category":"RESTAURANTS: TEA-ROOMS",
    "sg:phone":"+41 61 331 91 52",
    "sg:postcode":"4053",
    "sg:province":"Basel-Stadt",
    "wof:name":"Christen E.",
    "wof:placetype":"venue"
},
  "geometry": {"coordinates":[7.6004281044,47.5425643921],"type":"Point"}
}