{
  "type": "Feature",
  "properties": {
    "iso:country":"CH",
    "sg:address":"Chemin De Chatanerie 10",
    "sg:city":"Crissier",
    "sg:orig_category":"Herstellung von k\u00e4lte U lufttechnischen Erzeugnissen f\u00fcr gewerbliche Zwecke Sanit\u00e4r U Heizungsinstal",
    "sg:phone":"+41 21 826 00 54",
    "sg:postcode":"1023",
    "sg:province":"Vaud",
    "wof:name":"Chaleur Sa Succursale De Rolle",
    "wof:placetype":"venue"
},
  "geometry": {"coordinates":[6.5695710182,46.5556106567],"type":"Point"}
}