{
  "type": "Feature",
  "properties": {
    "iso:country":"CH",
    "sg:address":"Oberalpstrasse 52",
    "sg:city":"Disentis/must\u00e9r",
    "sg:classifiers":[
        {
            "category":"Travel",
            "subcategory":"Hotels & Motels",
            "type":"Entertainment"
        }
    ],
    "sg:phone":"+41 81 929 55 55",
    "sg:postcode":"7180",
    "sg:province":"Graubunden",
    "sg:tags":[
        "hotels",
        "mit",
        "restaurant"
    ],
    "wof:name":"Schwarz Gion",
    "wof:placetype":"venue"
},
  "geometry": {"coordinates":[8.8531293869,46.7046012878],"type":"Point"}
}