{
  "type": "Feature",
  "properties": {
    "iso:country":"CH",
    "sg:address":"Franklinstrasse 3",
    "sg:city":"Z\u00fcrich",
    "sg:orig_category":"Zahntechnische Laboratorien",
    "sg:phone":"+41 13118629",
    "sg:postcode":"8050",
    "sg:province":"Z\u00fcrich",
    "wof:name":"Armin Lorenzon Praxis F\u00fcr Zahnprothetik",
    "wof:placetype":"venue"
},
  "geometry": {"coordinates":[8.5458946228,47.4086952209],"type":"Point"}
}