{
  "type": "Feature",
  "properties": {
    "iso:country":"CH",
    "sg:address":"Dorfstrasse 15",
    "sg:city":"Besenb\u00fcren",
    "sg:classifiers":[
        {
            "category":"Restaurant",
            "type":"Food & Drink"
        }
    ],
    "sg:phone":"+41 56 666 12 66",
    "sg:postcode":"5627",
    "sg:province":"Aargau",
    "wof:name":"Restaurant Frohsinn",
    "wof:placetype":"venue"
},
  "geometry": {"coordinates":[8.3417072296,47.3130683899],"type":"Point"}
}