{
  "type": "Feature",
  "properties": {
    "iso:country":"CH",
    "sg:address":"Unterdorfstrasse 26",
    "sg:city":"Villmergen",
    "sg:orig_category":"Bauschreinerei Herstellung von Konstruktionsteilen, Fertigbauteilen U Ausbauelementen aus Holz",
    "sg:phone":"+41 56 622 10 48",
    "sg:postcode":"5612",
    "sg:province":"Aargau",
    "wof:name":"Xaver Meyer Schreinerei Ag",
    "wof:placetype":"venue"
},
  "geometry": {"coordinates":[8.243645,47.349007],"type":"Point"}
}