{
  "type": "Feature",
  "properties": {
    "iso:country":"CH",
    "sg:address":"Wengistrasse 2",
    "sg:city":"Solothurn",
    "sg:orig_category":"Allgemeiner Hoch U Tiefbau",
    "sg:postcode":"4500",
    "sg:province":"Solothurn",
    "wof:name":"Vigierhof Ag",
    "wof:placetype":"venue"
},
  "geometry": {"coordinates":[7.534564,47.206409],"type":"Point"}
}