{
  "type": "Feature",
  "properties": {
    "addr:full":"Im Grund 1 Ebmatingen Z\u00fcrich 8123",
    "addr:housenumber":"1",
    "addr:postcode":"8123",
    "addr:street":"Im Grund;Ebmatingen Zuerich",
    "iso:country":"CH",
    "sg:address":"Im Grund 1",
    "sg:city":"Ebmatingen",
    "sg:orig_category":"Datenverarbeitungsdienste Informatikschulen",
    "sg:phone":"+41 18876511",
    "sg:postcode":"8123",
    "sg:province":"Z\u00fcrich",
    "wof:name":"Iten Consulting",
    "wof:placetype":"venue"
},
  "geometry": {"coordinates":[8.641848,47.350468],"type":"Point"}
}