{
  "type": "Feature",
  "properties": {
    "addr:full":"B\u00fcel 9 Matzingen Thurgau 9548",
    "addr:housenumber":"9",
    "addr:postcode":"9548",
    "addr:street":"Bueel",
    "iso:country":"CH",
    "sg:address":"B\u00fcel 9",
    "sg:city":"Matzingen",
    "sg:orig_category":"Dachdeckerei Zimmerei, Dachdeckerei, Bauspenglerei U Abdichtung",
    "sg:phone":"+41 52 376 18 50",
    "sg:postcode":"9548",
    "sg:province":"Thurgau",
    "wof:name":"J. Schellenbaum Ag Bedachungen",
    "wof:placetype":"venue"
},
  "geometry": {"coordinates":[8.92597,47.516838],"type":"Point"}
}