{
  "type": "Feature",
  "properties": {
    "iso:country":"CH",
    "sg:address":"Auwisstrasse 23",
    "sg:city":"Forch",
    "sg:orig_category":"Fussreflexzonenmassage",
    "sg:phone":"+41 32 621 51 49",
    "sg:postcode":"8127",
    "sg:province":"Z\u00fcrich",
    "wof:name":"Helga G. Dobrowolski Massagen",
    "wof:placetype":"venue"
},
  "geometry": {"coordinates":[7.5006327629,47.2299537659],"type":"Point"}
}