{
  "type": "Feature",
  "properties": {
    "iso:country":"CH",
    "sg:address":"Farnsburgerstrasse 52",
    "sg:city":"Basel",
    "sg:orig_category":"Allgemeiner Hoch U Tiefbau",
    "sg:postcode":"4052",
    "sg:province":"Basel-Stadt",
    "wof:name":"Serafin Ag",
    "wof:placetype":"venue"
},
  "geometry": {"coordinates":[7.613734,47.554478],"type":"Point"}
}