{
  "type": "Feature",
  "properties": {
    "iso:country":"CH",
    "sg:address":"Moorbodenstrasse 6",
    "sg:city":"Bilten",
    "sg:orig_category":"Detailhandel mit Sportartikeln Fachdetailhandel in Verkaufsr\u00e4umen",
    "sg:phone":"+41 55 619 55 60",
    "sg:postcode":"8865",
    "sg:province":"Glarus",
    "wof:name":"Nautic Sport Ag",
    "wof:placetype":"venue"
},
  "geometry": {"coordinates":[9.0319814682,47.1517486572],"type":"Point"}
}