{
  "type": "Feature",
  "properties": {
    "iso:country":"CH",
    "sg:address":"Rue Des Deux-march\u00e9s 27",
    "sg:city":"Vevey",
    "sg:orig_category":"Detailhandel mit Waren verschiedener Art, Hauptrichtung Nahrungsmittel Grosshandel mit Obst U Gem\u00fcse",
    "sg:phone":"+41 21 921 65 79",
    "sg:postcode":"1800",
    "sg:province":"Vaud",
    "wof:name":"Alfred Volet Magasin Primeurs",
    "wof:placetype":"venue"
},
  "geometry": {"coordinates":[6.8431129456,46.4600601196],"type":"Point"}
}