{
  "type": "Feature",
  "properties": {
    "iso:country":"CH",
    "sg:address":"Stettemerstrasse 153",
    "sg:city":"Schaffhausen",
    "sg:orig_category":"Chiropraktik",
    "sg:phone":"+41 52 643 64 33",
    "sg:postcode":"8207",
    "sg:province":"Schaffhausen",
    "wof:name":"Dr.colette Faas Chiropraktik",
    "wof:placetype":"venue"
},
  "geometry": {"coordinates":[8.66005,47.726933],"type":"Point"}
}