{
  "type": "Feature",
  "properties": {
    "iso:country":"CH",
    "sg:address":"Emmenhofstrasse 4 4552 Derendingen. Postfach",
    "sg:city":"Derendingen",
    "sg:orig_category":"Architektur U Ingenieurb\u00fcros Architekturb\u00fcros",
    "sg:phone":"+41 32 682 33 33",
    "sg:postcode":"4552",
    "sg:province":"Solothurn",
    "wof:name":"Schenker & Ritschard, Dipl Architekten Htl/hfg Architekturb\u00fcro",
    "wof:placetype":"venue"
},
  "geometry": {"coordinates":[7.583208,47.195248],"type":"Point"}
}