{
  "type": "Feature",
  "properties": {
    "iso:country":"CH",
    "sg:address":"Bielstrasse 103",
    "sg:city":"Gamsen",
    "sg:orig_category":"Interessenvertretungen",
    "sg:postcode":"3900",
    "sg:province":"Valais",
    "wof:name":"European Federation Of Operating Room Technicians (efort) F\u00f6rderung Der Technischen Operationsassistenten Usw.",
    "wof:placetype":"venue"
},
  "geometry": {"coordinates":[9.370803833,47.4276008606],"type":"Point"}
}