{
  "type": "Feature",
  "properties": {
    "iso:country":"CH",
    "sg:address":"1831",
    "sg:city":"L'etivaz",
    "sg:orig_category":"Pensionen mit Restaurant",
    "sg:phone":"+41 26 924 53 98",
    "sg:postcode":"1831",
    "wof:name":"Pension Le Clos Des Tzams",
    "wof:placetype":"venue"
},
  "geometry": {"coordinates":[151.32858276370001,-33.6186408997],"type":"Point"}
}