{
  "type": "Feature",
  "properties": {
    "iso:country":"CH",
    "sg:address":"Oristalstrasse 98 4410 Liestal. Postfach",
    "sg:city":"Liestal",
    "sg:orig_category":"Pensionskassen",
    "sg:postcode":"4410",
    "sg:province":"Basel-Landschaft",
    "wof:name":"Rudolf Und Lina Wirz-stiftung",
    "wof:placetype":"venue"
},
  "geometry": {"coordinates":[7.7206549644,47.4753608704],"type":"Point"}
}