{
  "type": "Feature",
  "properties": {
    "iso:country":"CH",
    "sg:address":"Hinterdorfstrasse 91",
    "sg:city":"Truttikon",
    "sg:orig_category":"Sportvereine Sch\u00fctzen Armbrust",
    "sg:phone":"+41 55 256 20 30",
    "sg:postcode":"8467",
    "sg:province":"Z\u00fcrich",
    "wof:name":"Armbrustsch\u00fctzen Ried-gibswil",
    "wof:placetype":"venue"
},
  "geometry": {"coordinates":[8.916469574,47.2938194275],"type":"Point"}
}