{
  "type": "Feature",
  "properties": {
    "iso:country":"CH",
    "sg:address":"Spalenring 40",
    "sg:city":"Basel",
    "sg:orig_category":"Physiotherapie",
    "sg:phone":"+41 61 381 18 18",
    "sg:postcode":"4055",
    "sg:province":"Basel-Stadt",
    "wof:name":"Denise Rimmer Physiotherapie",
    "wof:placetype":"venue"
},
  "geometry": {"coordinates":[7.5740990639,47.5598640442],"type":"Point"}
}