{
  "type": "Feature",
  "properties": {
    "iso:country":"CH",
    "sg:address":"Hauptgasse 29",
    "sg:city":"Appenzell",
    "sg:orig_category":"Detailhandel mit Bekleidung Stickerei",
    "sg:phone":"+41 71 787 33 13",
    "sg:postcode":"9050",
    "sg:province":"Appenzell Innerhoden",
    "wof:name":"Doris Margreiter Stickereien",
    "wof:placetype":"venue"
},
  "geometry": {"coordinates":[9.408213,47.330994],"type":"Point"}
}