{
  "type": "Feature",
  "properties": {
    "iso:country":"CH",
    "sg:address":"Brunng\u00e4sslein 3 4052 Basel. Postfach",
    "sg:city":"Basel",
    "sg:orig_category":"RESTAURANTS: TEA-ROOMS",
    "sg:postcode":"4051",
    "sg:province":"Basel-Stadt",
    "wof:name":"Haller Raymond Restaurant Glogge",
    "wof:placetype":"venue"
},
  "geometry": {"coordinates":[7.595872879,47.5524635315],"type":"Point"}
}