{
  "type": "Feature",
  "properties": {
    "iso:country":"CH",
    "sg:address":"Bahnhofstrasse 11 6390 Engelberg. Postfach 146",
    "sg:city":"Engelberg",
    "sg:orig_category":"Detailhandel mit Damenbekleidung Detailhandel mit Herrenbekleidung",
    "sg:phone":"+41 41 637 11 78",
    "sg:postcode":"6390",
    "sg:province":"Obwalden",
    "wof:name":"Cristallina Sport & Mode",
    "wof:placetype":"venue"
},
  "geometry": {"coordinates":[8.4025354385,46.8197212219],"type":"Point"}
}