{
  "type": "Feature",
  "properties": {
    "iso:country":"CH",
    "sg:address":"1002 Lausanne. Postfach",
    "sg:city":"Lausanne",
    "sg:orig_category":"Vereine FKK",
    "sg:postcode":"1002",
    "sg:province":"Vaud",
    "wof:name":"Fkk Club Gymnique Lumi\u00e8re",
    "wof:placetype":"venue"
},
  "geometry": {"coordinates":[6.1399297714,46.2038192749],"type":"Point"}
}