{
  "type": "Feature",
  "properties": {
    "iso:country":"CH",
    "sg:address":"2854 Bassecourt Case Postale 48",
    "sg:city":"Bassecourt",
    "sg:orig_category":"Sportvereine Velo Rad-& Motorfahrer-Bund SRB",
    "sg:postcode":"2854",
    "sg:province":"Jura",
    "wof:name":"V\u00e9lo-club Jurassia Bassecourt",
    "wof:placetype":"venue"
},
  "geometry": {"coordinates":[7.2450351715,47.3370552063],"type":"Point"}
}