{
  "type": "Feature",
  "properties": {
    "iso:country":"CH",
    "sg:address":"Ottikerstrasse 35 8000 Z\u00fcrich. Postfach 2619",
    "sg:city":"Z\u00fcrich",
    "sg:orig_category":"Grosshandel mit Getr\u00e4nken",
    "sg:postcode":"8033",
    "sg:province":"Z\u00fcrich",
    "wof:name":"Divinum Martinelli",
    "wof:placetype":"venue"
},
  "geometry": {"coordinates":[8.5459060669,47.3861923218],"type":"Point"}
}