{
  "type": "Feature",
  "properties": {
    "iso:country":"CH",
    "sg:address":"Seeweg 22",
    "sg:city":"Cham",
    "sg:orig_category":"Allgemeiner Hoch U Tiefbau Architekturb\u00fcros",
    "sg:phone":"+41 19150440",
    "sg:postcode":"6330",
    "sg:province":"Zug",
    "wof:name":"Waldvogel J\u00fcrg, Architektur Und Bauleitung",
    "wof:placetype":"venue"
},
  "geometry": {"coordinates":[8.59856,47.295769],"type":"Point"}
}