{
  "type": "Feature",
  "properties": {
    "iso:country":"CH",
    "sg:address":"Lindenstrasse 7",
    "sg:city":"Sarnen",
    "sg:classifiers":[
        {
            "category":"Government",
            "subcategory":"Post Office",
            "type":"Public Place"
        }
    ],
    "sg:phone":"+41 41 660 17 24",
    "sg:postcode":"6060",
    "sg:province":"Obwalden",
    "sg:tags":[
        "caf\u00e9s",
        "tea-rooms"
    ],
    "wof:name":"Caf\u00e9 Christen",
    "wof:placetype":"venue"
},
  "geometry": {"coordinates":[8.247174263,46.8968887329],"type":"Point"}
}