{
  "type": "Feature",
  "properties": {
    "iso:country":"CH",
    "sg:address":"Wilbrunnenstrasse 110",
    "sg:city":"Unter\u00e4geri",
    "sg:orig_category":"Vermietung U Verpachtung von eigenen Immobilien",
    "sg:postcode":"6314",
    "sg:province":"Zug",
    "wof:name":"Renatoka Ag",
    "wof:placetype":"venue"
},
  "geometry": {"coordinates":[8.5917081833,47.1249313354],"type":"Point"}
}