{
  "type": "Feature",
  "properties": {
    "iso:country":"CH",
    "sg:address":"24 Quai Du Gal Guisan",
    "sg:city":"Gen\u00e8ve",
    "sg:classifiers":[
        {
            "category":"Wholesale",
            "subcategory":"Machinery & Supplies",
            "type":"Manufacturing & Wholesale Goods"
        }
    ],
    "sg:phone":"+41 22 818 20 00",
    "sg:postcode":"1204",
    "sg:province":"Gen\u00e8ve",
    "sg:tags":[
        "equipment",
        "equipement",
        "precision",
        "timekeeping"
    ],
    "wof:name":"Harry Winston",
    "wof:placetype":"venue"
},
  "geometry": {"coordinates":[6.1502709389,46.2038726807],"type":"Point"}
}