{
  "type": "Feature",
  "properties": {
    "iso:country":"CH",
    "sg:address":"Sch\u00f6neichstrasse 2 8051 Z\u00fcrich. Postfach 132",
    "sg:city":"Z\u00fcrich",
    "sg:orig_category":"Jugendorganisationen",
    "sg:phone":"+41 13113026",
    "sg:postcode":"8062",
    "wof:name":"Jugendmusiker",
    "wof:placetype":"venue"
},
  "geometry": {"coordinates":[8.5599498749,47.4044647217],"type":"Point"}
}