{
  "type": "Feature",
  "properties": {
    "iso:country":"CH",
    "sg:address":"St. Niklausstrasse 1",
    "sg:city":"Solothurn",
    "sg:orig_category":"Non-Classified Establishments",
    "sg:phone":"+41 81 415 21 21",
    "sg:postcode":"4500",
    "sg:province":"Solothurn",
    "wof:name":"Davos Tourismus (dt)",
    "wof:placetype":"venue"
},
  "geometry": {"coordinates":[9.8220462799,46.7973747253],"type":"Point"}
}