{
  "type": "Feature",
  "properties": {
    "iso:country":"CH",
    "sg:address":"B\u00fcelenstrasse 16",
    "sg:city":"W\u00e4denswil",
    "sg:orig_category":"Finanzierungsinstitutionen Handelsvermittlung U Grosshandel",
    "sg:phone":"+41 17802137",
    "sg:postcode":"8820",
    "sg:province":"Z\u00fcrich",
    "wof:name":"Contarewo Gmbh",
    "wof:placetype":"venue"
},
  "geometry": {"coordinates":[8.6624240875,47.2326507568],"type":"Point"}
}