{
  "type": "Feature",
  "properties": {
    "addr:full":"Rue De La Gare 10 1110 Morges Case Postale Morges Vaud 1110",
    "addr:housenumber":"10",
    "addr:postcode":"1110;case postale morges;1110",
    "addr:street":"Rue De La Gare",
    "iso:country":"CH",
    "sg:address":"Rue De La Gare 10 1110 Morges Case Postale",
    "sg:city":"Morges",
    "sg:orig_category":"Mechanik",
    "sg:phone":"+41 21 801 24 50",
    "sg:postcode":"1110",
    "sg:province":"Vaud",
    "wof:name":"Atelier M\u00e9canique D\u00fcrst Bruno",
    "wof:placetype":"venue"
},
  "geometry": {"coordinates":[6.496372,46.508636],"type":"Point"}
}