{
  "type": "Feature",
  "properties": {
    "iso:country":"CH",
    "sg:address":"S\u00e4gestrasse 22",
    "sg:city":"Lenzburg",
    "sg:orig_category":"Herstellung von Werkzeugen Mechanische Werkst\u00e4tten",
    "sg:phone":"+41 17493939",
    "sg:postcode":"5600",
    "sg:province":"Aargau",
    "wof:name":"Leitz Gmbh Sch\u00e4rfservice",
    "wof:placetype":"venue"
},
  "geometry": {"coordinates":[8.1785697937,47.3929748535],"type":"Point"}
}