{
  "type": "Feature",
  "properties": {
    "iso:country":"CH",
    "sg:address":"Collex Route De 20 B 1293 Bellevue. Postfach",
    "sg:city":"Bellevue",
    "sg:orig_category":"Berufsbildende weiterf\u00fchrende Schulen",
    "sg:phone":"+41 81 756 19 32",
    "sg:postcode":"1293",
    "sg:province":"Gen\u00e8ve",
    "wof:name":"Werner Gantenbein Massagefachschule Cellsan",
    "wof:placetype":"venue"
},
  "geometry": {"coordinates":[9.476811,47.169212],"type":"Point"}
}