{
  "type": "Feature",
  "properties": {
    "iso:country":"CH",
    "sg:address":"Ruhebergstrasse 12",
    "sg:city":"T\u00fcbach",
    "sg:orig_category":"Architektur U Ingenieurb\u00fcros Architekturb\u00fcros",
    "sg:phone":"+41 71 841 08 48",
    "sg:postcode":"9327",
    "sg:province":"St. Gallen",
    "wof:name":"T\u00fcbag Ag",
    "wof:placetype":"venue"
},
  "geometry": {"coordinates":[9.451759,47.486115],"type":"Point"}
}