{
  "type": "Feature",
  "properties": {
    "iso:country":"CH",
    "sg:address":"Heinrich-wild-strasse",
    "sg:city":"Heerbrugg",
    "sg:orig_category":"Grosshandel mit Foto U Kinoger\u00e4ten, feinmechanischen U optischen Erzeugnissen Herstellung von optisc",
    "sg:phone":"+41 21 635 35 53",
    "sg:postcode":"9435",
    "sg:province":"St. Gallen",
    "wof:name":"Leica Geosystems Sa",
    "wof:placetype":"venue"
},
  "geometry": {"coordinates":[6.5909309387,46.5329780579],"type":"Point"}
}