{
  "type": "Feature",
  "properties": {
    "iso:country":"CH",
    "sg:address":"Grand-record Chemin Du 10",
    "sg:city":"Vufflens-ch\u00e2teau",
    "sg:orig_category":"Handel mit Automobilen",
    "sg:postcode":"1134",
    "sg:province":"Vaud",
    "wof:name":"Automanagement Armeno Gmbh Fahrzeuge; Handel Usw.",
    "wof:placetype":"venue"
},
  "geometry": {"coordinates":[7.585392952,47.0822753906],"type":"Point"}
}