{
  "type": "Feature",
  "properties": {
    "iso:country":"CH",
    "sg:address":"Hinterlauben 8 9000 St.gallen. Postfach",
    "sg:city":"St.gallen",
    "sg:orig_category":"Grosshandel mit Erzen U Metallen",
    "sg:phone":"+41 71 274 33 18",
    "sg:postcode":"9000",
    "sg:province":"St. Gallen",
    "wof:name":"Debrunner Ag, Zweigniederlassung St. Gallen",
    "wof:placetype":"venue"
},
  "geometry": {"coordinates":[9.3415384293,47.4091567993],"type":"Point"}
}