{
  "type": "Feature",
  "properties": {
    "iso:country":"CH",
    "sg:address":"Zelgliweg 2",
    "sg:city":"Eschlikon",
    "sg:classifiers":[
        {
            "category":"Shopping",
            "subcategory":"Thrift Store",
            "type":"Retail Goods"
        }
    ],
    "sg:phone":"+41 71 971 48 20",
    "sg:postcode":"8360",
    "sg:province":"Thurgau",
    "sg:tags":[
        "gesundheit",
        "u",
        "fachgesch\u00e4fte"
    ],
    "wof:name":"Watrap",
    "wof:placetype":"venue"
},
  "geometry": {"coordinates":[8.97039,47.465141],"type":"Point"}
}