{
  "type": "Feature",
  "properties": {
    "iso:country":"CH",
    "sg:address":"Klosterplatz 20 4600 Olten. Postfach",
    "sg:city":"Olten",
    "sg:orig_category":"Kinos",
    "sg:postcode":"4601",
    "sg:province":"Solothurn",
    "wof:name":"Pahud Marc",
    "wof:placetype":"venue"
},
  "geometry": {"coordinates":[5.1808700562,45.8973388672],"type":"Point"}
}