{
  "type": "Feature",
  "properties": {
    "iso:country":"CH",
    "sg:address":"Tufertschwil 20",
    "sg:city":"L\u00fctisburg",
    "sg:classifiers":[
        {
            "category":"Travel",
            "subcategory":"Hotels & Motels",
            "type":"Entertainment"
        }
    ],
    "sg:postcode":"9604",
    "sg:province":"St. Gallen",
    "sg:tags":[
        "hotels",
        "mit",
        "restaurant"
    ],
    "wof:name":"Landgasthof R\u00f6ssli, Kohler Kaspar",
    "wof:placetype":"venue"
},
  "geometry": {"coordinates":[8.111123085,46.7384567261],"type":"Point"}
}