{
  "type": "Feature",
  "properties": {
    "iso:country":"CH",
    "sg:address":"Ch. Du Bois-genoud 6",
    "sg:city":"Lausanne",
    "sg:orig_category":"Non-Classified Establishments",
    "sg:postcode":"1000",
    "sg:province":"Vaud",
    "wof:name":"Get It, Dubi",
    "wof:placetype":"venue"
},
  "geometry": {"coordinates":[6.5925869942,46.5650367737],"type":"Point"}
}