{
  "type": "Feature",
  "properties": {
    "iso:country":"CH",
    "sg:address":"Z\u00fcrcherstrasse 31",
    "sg:city":"Lufingen",
    "sg:orig_category":"Gasth\u00f6fe/Gasth\u00e4user mit Restaurant",
    "sg:phone":"+41 34 493 33 01",
    "sg:postcode":"8426",
    "sg:province":"Z\u00fcrich",
    "wof:name":"Gasthof Zum Kreuz",
    "wof:placetype":"venue"
},
  "geometry": {"coordinates":[7.8967900276,46.8511390686],"type":"Point"}
}