{
  "type": "Feature",
  "properties": {
    "iso:country":"CH",
    "sg:address":"Oberstadtstrasse 2 5400 Baden. Postfach",
    "sg:city":"Baden",
    "sg:orig_category":"Fotografisches Gewerbe U fotografische Laboratorien",
    "sg:postcode":"5400",
    "sg:province":"Aargau",
    "wof:name":"Gendre Daniel Fran\u00e7ois",
    "wof:placetype":"venue"
},
  "geometry": {"coordinates":[8.5732803345,47.3299980164],"type":"Point"}
}