{
  "type": "Feature",
  "properties": {
    "iso:country":"CH",
    "sg:address":"Via Cantonale",
    "sg:city":"Tegna",
    "sg:classifiers":[
        {
            "category":"Restaurant",
            "type":"Food & Drink"
        }
    ],
    "sg:phone":"+41 91 796 23 13",
    "sg:postcode":"6652",
    "sg:province":"Ticino",
    "wof:name":"Ristorante-pizzeria Giardinetto",
    "wof:placetype":"venue"
},
  "geometry": {"coordinates":[8.7470493317,46.1871185303],"type":"Point"}
}