{
  "type": "Feature",
  "properties": {
    "iso:country":"CH",
    "sg:address":"Rue Ferdinand-hodler 11",
    "sg:city":"Gen\u00e8ve",
    "sg:orig_category":"Malerei",
    "sg:phone":"+41 32 322 82 19",
    "sg:postcode":"1207",
    "sg:province":"Gen\u00e8ve",
    "wof:name":"Jean-no\u00ebl Husson Peinture",
    "wof:placetype":"venue"
},
  "geometry": {"coordinates":[7.2732338905,47.1254768372],"type":"Point"}
}