{
  "type": "Feature",
  "properties": {
    "iso:country":"CH",
    "sg:address":"Bielstrasse 119",
    "sg:city":"Solothurn",
    "sg:orig_category":"Herstellung von Musikinstrumenten",
    "sg:phone":"+41 79 439 23 13",
    "sg:postcode":"4500",
    "sg:province":"Solothurn",
    "wof:name":"Pianohaus Billeter Stefan",
    "wof:placetype":"venue"
},
  "geometry": {"coordinates":[7.5188179016,47.2121353149],"type":"Point"}
}