{
  "type": "Feature",
  "properties": {
    "iso:country":"CH",
    "sg:address":"1730 Ecuvillens. Postfach",
    "sg:city":"Ecuvillens",
    "sg:orig_category":"Interessenvertretungen",
    "sg:postcode":"1730",
    "sg:province":"Fribourg",
    "wof:name":"Flying Stearman Association",
    "wof:placetype":"venue"
},
  "geometry": {"coordinates":[7.0892109871,46.7579231262],"type":"Point"}
}