{
  "type": "Feature",
  "properties": {
    "iso:country":"CH",
    "sg:address":"Dammerkirchstrasse 80 4056 Basel. Postfach",
    "sg:city":"Basel",
    "sg:orig_category":"Detailhandel mit Brot, Back U S\u00fcsswaren",
    "sg:phone":"+41 61 321 46 54",
    "sg:postcode":"4025",
    "sg:province":"Basel-Stadt",
    "wof:name":"B\u00e4ckerei A. Wischlen Ag",
    "wof:placetype":"venue"
},
  "geometry": {"coordinates":[7.565705,47.566116],"type":"Point"}
}