{
  "type": "Feature",
  "properties": {
    "iso:country":"CH",
    "sg:address":"Torre Dei Fiori",
    "sg:city":"Coldrerio",
    "sg:orig_category":"Herstellung von sonstigen Kunststoffwaren",
    "sg:phone":"+41 91 683 83 46",
    "sg:postcode":"6877",
    "sg:province":"Ticino",
    "wof:name":"Tina Grendelmeier Fabbricazione Fiori Artistici",
    "wof:placetype":"venue"
},
  "geometry": {"coordinates":[8.987575531,45.8543815613],"type":"Point"}
}