{
  "type": "Feature",
  "properties": {
    "iso:country":"CH",
    "sg:address":"Eben-ezer 50",
    "sg:city":"Frenkendorf",
    "sg:orig_category":"Pensionskassen",
    "sg:phone":"+41 61 901 19 00",
    "sg:postcode":"4402",
    "sg:province":"Basel-Landschaft",
    "wof:name":"Stiftung Eben-ezer",
    "wof:placetype":"venue"
},
  "geometry": {"coordinates":[7.7084798813,47.4996490479],"type":"Point"}
}