{
  "type": "Feature",
  "properties": {
    "iso:country":"CH",
    "sg:address":"Im Zentrum 1a",
    "sg:city":"Sarmenstorf",
    "sg:orig_category":"Nationale Postdienste",
    "sg:phone":"+41 56 667 11 30",
    "sg:postcode":"5614",
    "sg:province":"Aargau",
    "wof:name":"Die Schweizerische Post",
    "wof:placetype":"venue"
},
  "geometry": {"coordinates":[8.2512702942,47.3109016418],"type":"Point"}
}