{
  "type": "Feature",
  "properties": {
    "iso:country":"CH",
    "sg:address":"Bernstrasse 11",
    "sg:city":"Thun",
    "sg:classifiers":[
        {
            "category":"Manufacturing",
            "subcategory":"Jewelry",
            "type":"Manufacturing & Wholesale Goods"
        }
    ],
    "sg:phone":"+41 33 226 82 82",
    "sg:postcode":"3600",
    "sg:province":"Bern",
    "sg:tags":[
        "bearing",
        "jewel"
    ],
    "wof:name":"Comadur Sa",
    "wof:placetype":"venue"
},
  "geometry": {"coordinates":[7.628005,46.763161],"type":"Point"}
}