{
  "type": "Feature",
  "properties": {
    "iso:country":"CH",
    "sg:address":"7203",
    "sg:city":"Trimmis",
    "sg:orig_category":"Landwirtschaft, Jagd U damit verbundene Dienstleistungen",
    "sg:phone":"+41 81 322 28 38",
    "sg:postcode":"7203",
    "sg:province":"Graubunden",
    "wof:name":"Gutsbetrieb Molin\u00e4ra Stefan Ackermann",
    "wof:placetype":"venue"
},
  "geometry": {"coordinates":[9.5628290176,46.8994636536],"type":"Point"}
}