{
  "type": "Feature",
  "properties": {
    "iso:country":"CH",
    "sg:address":"S\u00fcdstrasse 1 8952 Schlieren. Postfach",
    "sg:city":"Z\u00fcrich-m\u00fclligen",
    "sg:orig_category":"Landesverteidigung, Sozialversicherung \u00d6ffentliche Verwaltung",
    "sg:phone":"+41 17303681",
    "sg:postcode":"8010",
    "sg:province":"Z\u00fcrich",
    "wof:name":"Automobilwerkst\u00e4tte Ptt Schlieren",
    "wof:placetype":"venue"
},
  "geometry": {"coordinates":[8.4634246826,47.399974823],"type":"Point"}
}