{
  "type": "Feature",
  "properties": {
    "iso:country":"CH",
    "sg:address":"6995",
    "sg:city":"Molinazzo",
    "sg:orig_category":"Schulpflegen",
    "sg:postcode":"6995",
    "sg:province":"Ticino",
    "wof:name":"Delegazione Scolastica Del Comune Di Morbio Superiore",
    "wof:placetype":"venue"
},
  "geometry": {"coordinates":[9.0503702164,45.870098114],"type":"Point"}
}