{
  "type": "Feature",
  "properties": {
    "iso:country":"CH",
    "sg:address":"Obere L\u00e4ttenstrasse 11",
    "sg:city":"Winkel",
    "sg:orig_category":"Unternehmensberatung",
    "sg:phone":"+41 18862141",
    "sg:postcode":"8185",
    "sg:province":"Z\u00fcrich",
    "wof:name":"Cornelia Daftarian-graf Kommunikationsberatung",
    "wof:placetype":"venue"
},
  "geometry": {"coordinates":[8.5591831207,47.4906311035],"type":"Point"}
}