{
  "type": "Feature",
  "properties": {
    "iso:country":"CH",
    "sg:address":"B\u00e4umliackerweg 3",
    "sg:city":"Villnachern",
    "sg:orig_category":"Grosshandel mit pharmazeutischen Erzeugnissen, medizinischen U orthop\u00e4dischen Artikeln",
    "sg:phone":"+41 56 441 48 32",
    "sg:postcode":"5213",
    "sg:province":"Aargau",
    "wof:name":"Brunner Consulting",
    "wof:placetype":"venue"
},
  "geometry": {"coordinates":[8.1625061035,47.4668922424],"type":"Point"}
}