{
  "type": "Feature",
  "properties": {
    "iso:country":"CH",
    "sg:address":"Chesa Funtauna 7513 Silvaplana. Postfach",
    "sg:city":"Silvaplana",
    "sg:orig_category":"Reiseb\u00fcros U Reiseveranstalter",
    "sg:postcode":"7513",
    "sg:province":"Graubunden",
    "wof:name":"Willy Rominger Residenza Lagrev",
    "wof:placetype":"venue"
},
  "geometry": {"coordinates":[9.764169693,46.4287605286],"type":"Point"}
}