{
  "type": "Feature",
  "properties": {
    "iso:country":"CH",
    "sg:address":"Ruchstuckstrasse 2",
    "sg:city":"Br\u00fcttisellen",
    "sg:orig_category":"Naturheil\u00e4rzte and Heilpraktiker",
    "sg:phone":"+41 19374820",
    "sg:postcode":"8306",
    "sg:province":"Z\u00fcrich",
    "wof:name":"Hans Ruedi Aeberli Naturheilpraxis",
    "wof:placetype":"venue"
},
  "geometry": {"coordinates":[8.846953392,47.299243927],"type":"Point"}
}