{
  "type": "Feature",
  "properties": {
    "iso:country":"CH",
    "sg:address":"Falkenstrasse 19 2502 Biel/bienne. Postfach",
    "sg:city":"Biel/bienne",
    "sg:orig_category":"Grosshandel mit Uhren Herstellung von Uhren",
    "sg:phone":"+41 32 341 27 47",
    "sg:postcode":"2501",
    "sg:province":"Bern",
    "wof:name":"Montres Choisi Sa",
    "wof:placetype":"venue"
},
  "geometry": {"coordinates":[7.2581400871,47.1468658447],"type":"Point"}
}