{
  "type": "Feature",
  "properties": {
    "iso:country":"CH",
    "sg:address":"Buechstrasse 25",
    "sg:city":"Jona",
    "sg:orig_category":"Herstellung von Metallerzeugnissen ohne Maschinenbau Herstellung von sonstigen Metallwaren",
    "sg:phone":"+41 55 212 70 71",
    "sg:postcode":"8645",
    "sg:province":"St. Gallen",
    "wof:name":"Sp\u00f6rri Metall Gmbh",
    "wof:placetype":"venue"
},
  "geometry": {"coordinates":[8.8670740128,47.2273635864],"type":"Point"}
}