{
  "type": "Feature",
  "properties": {
    "iso:country":"CH",
    "sg:address":"Rue De La Mauguettaz 2",
    "sg:city":"Yvonand",
    "sg:orig_category":"Non-Classified Establishments",
    "sg:postcode":"1462",
    "sg:province":"Vaud",
    "wof:name":"Boutique Markisa, J. Francesevic",
    "wof:placetype":"venue"
},
  "geometry": {"coordinates":[8.8165988922,47.2260322571],"type":"Point"}
}