{
  "type": "Feature",
  "properties": {
    "iso:country":"CH",
    "sg:address":"Eggbrunnenweg 35",
    "sg:city":"Russikon",
    "sg:orig_category":"Softwareentwicklung U beratung",
    "sg:phone":"+41 19565555",
    "sg:postcode":"8332",
    "sg:province":"Z\u00fcrich",
    "wof:name":"Kaufmann & Meier Ag",
    "wof:placetype":"venue"
},
  "geometry": {"coordinates":[8.7718009949,47.3993988037],"type":"Point"}
}