{
  "type": "Feature",
  "properties": {
    "iso:country":"CH",
    "sg:address":"Hornstrasse 2",
    "sg:city":"Feldbach",
    "sg:orig_category":"Detailhandel mit Waren verschiedener Art, Hauptrichtung Nahrungsmittel",
    "sg:phone":"+41 55 244 12 61",
    "sg:postcode":"8714",
    "sg:province":"Z\u00fcrich",
    "wof:name":"Eduard Senn Lebensmittel",
    "wof:placetype":"venue"
},
  "geometry": {"coordinates":[8.786857605,47.2392578125],"type":"Point"}
}