{
  "type": "Feature",
  "properties": {
    "iso:country":"CH",
    "sg:address":"Industriestrasse 6",
    "sg:city":"Hendschiken",
    "sg:classifiers":[
        {
            "category":"Community Center",
            "subcategory":"Youth",
            "type":"Public Place"
        }
    ],
    "sg:phone":"+41 62 891 43 33",
    "sg:postcode":"5604",
    "sg:province":"Aargau",
    "sg:tags":[
        "plant",
        "flower",
        "artificial"
    ],
    "wof:name":"Vogt Ag",
    "wof:placetype":"venue"
},
  "geometry": {"coordinates":[8.203343,47.390003],"type":"Point"}
}