{
  "type": "Feature",
  "properties": {
    "iso:country":"CH",
    "sg:address":"Tannliberg 65",
    "sg:city":"Biezwil",
    "sg:orig_category":"Bauschreinerei",
    "sg:phone":"+41 32 351 36 65",
    "sg:postcode":"4585",
    "sg:province":"Solothurn",
    "wof:name":"Urs Orschel Schreinerei",
    "wof:placetype":"venue"
},
  "geometry": {"coordinates":[7.417171,47.115898],"type":"Point"}
}