{
  "type": "Feature",
  "properties": {
    "iso:country":"CH",
    "sg:address":"Hauptgasse 15",
    "sg:city":"Solothurn",
    "sg:orig_category":"Pensionskassen",
    "sg:postcode":"4500",
    "sg:province":"Solothurn",
    "wof:name":"Wohlfahrtsfonds F\u00fcr Die Angestellten Der Firma Schenker Zum Roten Stiefel",
    "wof:placetype":"venue"
},
  "geometry": {"coordinates":[7.535987854,47.2068901062],"type":"Point"}
}