{
  "type": "Feature",
  "properties": {
    "iso:country":"CH",
    "sg:address":"Gouttes-d'or Route Des 5 2000 Neuenburg Case Postale 139",
    "sg:city":"Neuenburg",
    "sg:orig_category":"Fotografisches Gewerbe U fotografische Laboratorien",
    "sg:phone":"+41 32 724 54 03",
    "sg:postcode":"2000",
    "sg:province":"Neuch\u00e2tel",
    "wof:name":"Six Degr\u00e9s Est S\u00e0rl Atelier De Photographie Artistique Et Industriel",
    "wof:placetype":"venue"
},
  "geometry": {"coordinates":[6.941450119,46.9826812744],"type":"Point"}
}