{
  "type": "Feature",
  "properties": {
    "iso:country":"CH",
    "sg:address":"B\u00e4lliz 29",
    "sg:city":"Thun",
    "sg:orig_category":"Herstellung von Duft U K\u00f6rperpflegemitteln",
    "sg:postcode":"3600",
    "sg:province":"Bern",
    "wof:name":"Jolin Ag",
    "wof:placetype":"venue"
},
  "geometry": {"coordinates":[7.627322197,46.7589187622],"type":"Point"}
}