{
  "type": "Feature",
  "properties": {
    "iso:country":"CH",
    "sg:address":"Bahnhofstrasse 11",
    "sg:city":"Wattwil",
    "sg:orig_category":"Detailhandel mit Radio U Fernsehger\u00e4ten Elektroinstallation",
    "sg:phone":"+41 71 987 60 88",
    "sg:postcode":"9630",
    "sg:province":"St. Gallen",
    "wof:name":"Bichler Ag",
    "wof:placetype":"venue"
},
  "geometry": {"coordinates":[9.086730957,47.3002319336],"type":"Point"}
}