{
  "type": "Feature",
  "properties": {
    "iso:country":"CH",
    "sg:address":"Kalchengasse 10",
    "sg:city":"Kloten",
    "sg:classifiers":[
        {
            "category":"Autos & Motor Vehicles",
            "subcategory":"Auto Supplies",
            "type":"Retail Goods"
        }
    ],
    "sg:phone":"+41 18143270",
    "sg:postcode":"8302",
    "sg:province":"Z\u00fcrich",
    "sg:tags":[
        "machine",
        "addressing"
    ],
    "wof:name":"Multimail Sa",
    "wof:placetype":"venue"
},
  "geometry": {"coordinates":[8.582568,47.45237],"type":"Point"}
}