{
  "type": "Feature",
  "properties": {
    "iso:country":"CH",
    "sg:address":"Rasch\u00e4renstrasse 48",
    "sg:city":"Chur",
    "sg:orig_category":"Autogaragen Instandhaltung U Reparatur von Automobilen",
    "sg:phone":"+41 81 756 46 36",
    "sg:postcode":"7000",
    "sg:province":"Graubunden",
    "wof:name":"Garage Cudazzo Gmbh",
    "wof:placetype":"venue"
},
  "geometry": {"coordinates":[9.480428,47.154549],"type":"Point"}
}