{
  "type": "Feature",
  "properties": {
    "addr:full":"Wasgenring 78 Basel Basel-Stadt 4055",
    "addr:housenumber":"78",
    "addr:postcode":"4055",
    "addr:street":"Wasgenring",
    "iso:country":"CH",
    "sg:address":"Wasgenring 78",
    "sg:city":"Basel",
    "sg:orig_category":"Betrieb von Taxis",
    "sg:phone":"+41 61 322 46 61",
    "sg:postcode":"4055",
    "sg:province":"Basel-Stadt",
    "wof:name":"Margrit Brem Taxi",
    "wof:placetype":"venue"
},
  "geometry": {"coordinates":[7.564192,47.560966],"type":"Point"}
}