{
  "type": "Feature",
  "properties": {
    "iso:country":"CH",
    "sg:address":"Via Muraccio 6",
    "sg:city":"Ascona",
    "sg:classifiers":[
        {
            "category":"Restaurant",
            "type":"Food & Drink"
        }
    ],
    "sg:phone":"+41 91 791 03 98",
    "sg:postcode":"6612",
    "sg:province":"Ticino",
    "wof:name":"Snack-bar Muraccio",
    "wof:placetype":"venue"
},
  "geometry": {"coordinates":[8.7743740082,46.1541366577],"type":"Point"}
}