{
  "type": "Feature",
  "properties": {
    "iso:country":"CH",
    "sg:address":"Interlakenstr. 78 3700 Spiez. Postfach",
    "sg:city":"Faulensee",
    "sg:orig_category":"RESTAURANTS: TEA-ROOMS",
    "sg:phone":"+41 62 961 14 18",
    "sg:postcode":"3705",
    "sg:province":"Bern",
    "wof:name":"Minder U. Kofmel",
    "wof:placetype":"venue"
},
  "geometry": {"coordinates":[7.6600971222,47.1817588806],"type":"Point"}
}