{
  "type": "Feature",
  "properties": {
    "iso:country":"CH",
    "sg:address":"Avenue De Champel 35",
    "sg:city":"Gen\u00e8ve",
    "sg:orig_category":"Wirtschaftsverb\u00e4nde Industrie, Handel and Gewerbe",
    "sg:phone":"+41 22 346 49 45",
    "sg:postcode":"1206",
    "sg:province":"Gen\u00e8ve",
    "wof:name":"Assoc.suisse D.importateurs De Volaille & Gibier,m.jean Gaeng",
    "wof:placetype":"venue"
},
  "geometry": {"coordinates":[6.1533689499,46.1934432983],"type":"Point"}
}