{
  "type": "Feature",
  "properties": {
    "iso:country":"CH",
    "sg:address":"Schiben",
    "sg:city":"Untereggen",
    "sg:orig_category":"Sanit\u00e4r, Heizungs U L\u00fcftungsinstallation",
    "sg:postcode":"9033",
    "sg:province":"St. Gallen",
    "wof:name":"Imhof Ag Untereggen",
    "wof:placetype":"venue"
},
  "geometry": {"coordinates":[9.4358892441,47.4462432861],"type":"Point"}
}