{
  "type": "Feature",
  "properties": {
    "iso:country":"CH",
    "sg:address":"Gravi\u00e8re Chemin De La 8",
    "sg:city":"Lausanne",
    "sg:orig_category":"Stukkateurgewerbe, Gipserei U Verputzerei",
    "sg:postcode":"1007",
    "sg:province":"Vaud",
    "wof:name":"Monti Willy Et Michel Sa",
    "wof:placetype":"venue"
},
  "geometry": {"coordinates":[6.632335186,46.5195960999],"type":"Point"}
}