{
  "type": "Feature",
  "properties": {
    "iso:country":"CH",
    "sg:address":"Wyssenschwendi",
    "sg:city":"Unter\u00e4geri",
    "sg:orig_category":"Sonstiger Fachdetailhandel mit Nahrungsmitteln, Getr\u00e4nken U Tabak in Verkaufsr\u00e4umen",
    "sg:phone":"+41 41 630 01 12",
    "sg:postcode":"6314",
    "sg:province":"Zug",
    "wof:name":"Helix Import-export Ag",
    "wof:placetype":"venue"
},
  "geometry": {"coordinates":[8.3073587418,46.9956970215],"type":"Point"}
}