{
  "type": "Feature",
  "properties": {
    "addr:full":"Schneckelerstrasse 9 4414 F\u00fcllinsdorf. Postfach 889 F\u00fcllinsdorf Basel-Landschaft 4414",
    "addr:housenumber":"9;889",
    "addr:postcode":"4414;4414",
    "addr:street":"Schneckelerstrasse;Postfach",
    "iso:country":"CH",
    "sg:address":"Schneckelerstrasse 9 4414 F\u00fcllinsdorf. Postfach 889",
    "sg:city":"F\u00fcllinsdorf",
    "sg:orig_category":"Architektur U Ingenieurb\u00fcros",
    "sg:phone":"+41 61 906 95 55",
    "sg:postcode":"4414",
    "sg:province":"Basel-Landschaft",
    "wof:name":"Gnehm Sch\u00e4fer Ingenieure Ag",
    "wof:placetype":"venue"
},
  "geometry": {"coordinates":[7.720965,47.513084],"type":"Point"}
}