{
  "type": "Feature",
  "properties": {
    "iso:country":"CH",
    "sg:address":"Les Places Champlan",
    "sg:city":"Grimisuat",
    "sg:orig_category":"Grosshandel mit Getr\u00e4nken Rebbau",
    "sg:phone":"+41 27 398 31 43",
    "sg:postcode":"1971",
    "sg:province":"Valais",
    "wof:name":"Hug Laurent",
    "wof:placetype":"venue"
},
  "geometry": {"coordinates":[7.3867740631,46.2607192993],"type":"Point"}
}