{
  "type": "Feature",
  "properties": {
    "iso:country":"CH",
    "sg:address":"Alte Landstrasse 22",
    "sg:city":"Obfelden",
    "sg:orig_category":"Instandhaltung U Reparatur von Automobilen",
    "sg:phone":"+41 17614068",
    "sg:postcode":"8912",
    "sg:province":"Z\u00fcrich",
    "wof:name":"Stieger Martin",
    "wof:placetype":"venue"
},
  "geometry": {"coordinates":[8.4341497421,47.2632102966],"type":"Point"}
}