{
  "type": "Feature",
  "properties": {
    "iso:country":"CH",
    "sg:address":"Linth-escher-strasse 3 8865 Bilten. Postfach",
    "sg:city":"Bilten",
    "sg:orig_category":"Grosshandel mit B\u00fcromaschinen U einrichtungen",
    "sg:postcode":"8865",
    "sg:province":"Glarus",
    "wof:name":"Ropf Gmbh",
    "wof:placetype":"venue"
},
  "geometry": {"coordinates":[9.0265388489,47.1525535583],"type":"Point"}
}