{
  "type": "Feature",
  "properties": {
    "iso:country":"CH",
    "sg:address":"Tittwiesenstrasse 66",
    "sg:city":"Chur",
    "sg:orig_category":"Tanzschulen, Tanzlehrer",
    "sg:phone":"+41 81 284 60 00",
    "sg:postcode":"7000",
    "sg:province":"Graubunden",
    "wof:name":"Elisabeth & Daniela B\u00e4der Tanz-& Balletschule",
    "wof:placetype":"venue"
},
  "geometry": {"coordinates":[9.5266103745,46.8591156006],"type":"Point"}
}