{
  "type": "Feature",
  "properties": {
    "iso:country":"CH",
    "sg:address":"Hauptstrasse 35",
    "sg:city":"Hornussen",
    "sg:classifiers":[
        {
            "category":"Banks & Credit Unions",
            "subcategory":"Bank",
            "type":"Services"
        }
    ],
    "sg:phone":"+41 41 340 56 22",
    "sg:postcode":"5257",
    "wof:name":"Raiffeisenbank Horw",
    "wof:placetype":"venue"
},
  "geometry": {"coordinates":[8.31152,47.01915],"type":"Point"}
}