{
  "type": "Feature",
  "properties": {
    "iso:country":"CH",
    "sg:address":"Studen",
    "sg:city":"Nottwil",
    "sg:orig_category":"RESTAURANTS: TEA-ROOMS",
    "sg:phone":"+41 77434616",
    "sg:postcode":"6207",
    "sg:province":"Luzern",
    "wof:name":"Fries Gastro Team Ag",
    "wof:placetype":"venue"
},
  "geometry": {"coordinates":[8.1474752426,47.1262207031],"type":"Point"}
}