{
  "type": "Feature",
  "properties": {
    "iso:country":"CH",
    "sg:address":"6718",
    "sg:city":"Olivone",
    "sg:orig_category":"Reiseb\u00fcros U Reiseveranstalter",
    "sg:phone":"+41 61 712 18 27",
    "sg:postcode":"6718",
    "sg:province":"Ticino",
    "wof:name":"Otrag Gmbh",
    "wof:placetype":"venue"
},
  "geometry": {"coordinates":[7.590528965,47.4900131226],"type":"Point"}
}