{
  "type": "Feature",
  "properties": {
    "iso:country":"CH",
    "sg:address":"Z\u00fcrcherstrasse 119",
    "sg:city":"Winterthur",
    "sg:orig_category":"Arztpraxen",
    "sg:phone":"+41 52 203 84 40",
    "sg:postcode":"8406",
    "sg:province":"Z\u00fcrich",
    "wof:name":"Dr.med.alexander Erlach Arzt F\u00fcr Allgemeine Medizin",
    "wof:placetype":"venue"
},
  "geometry": {"coordinates":[8.704547,47.481495],"type":"Point"}
}