{
  "type": "Feature",
  "properties": {
    "iso:country":"CH",
    "sg:address":"Br\u00e4gg",
    "sg:city":"Bazenheid",
    "sg:orig_category":"Instandhaltung U Reparatur von Automobilen",
    "sg:phone":"+41 71 931 10 10",
    "sg:postcode":"9602",
    "sg:province":"St. Gallen",
    "wof:name":"Garage Ammann Ag.",
    "wof:placetype":"venue"
},
  "geometry": {"coordinates":[9.0685997009,47.4126701355],"type":"Point"}
}