{
  "type": "Feature",
  "properties": {
    "iso:country":"CH",
    "sg:address":"Sentimattstrasse 7",
    "sg:city":"Luzern",
    "sg:orig_category":"Religi\u00f6se Vereinigungen",
    "sg:phone":"+41 41 249 98 50",
    "sg:postcode":"6003",
    "sg:province":"Luzern",
    "wof:name":"Dianetik & Scientology Luzern, Mission Der Scientology Kirche",
    "wof:placetype":"venue"
},
  "geometry": {"coordinates":[8.2945566177,47.0545272827],"type":"Point"}
}