{
  "type": "Feature",
  "properties": {
    "iso:country":"CH",
    "sg:address":"Mousquines Avenue Des 1 1005 Lausanne. Postfach",
    "sg:city":"Lausanne",
    "sg:orig_category":"RESTAURANTS: TEA-ROOMS",
    "sg:postcode":"1003",
    "sg:province":"Vaud",
    "wof:name":"Bertini Iside. Caf\u00e9-restaurant Snack Bar Park.",
    "wof:placetype":"venue"
},
  "geometry": {"coordinates":[6.6436648369,46.5179481506],"type":"Point"}
}