{
  "type": "Feature",
  "properties": {
    "iso:country":"CH",
    "sg:address":"Holderstrasse 19",
    "sg:city":"Basel",
    "sg:orig_category":"Unclassifiable Establishments",
    "sg:postcode":"4057",
    "sg:province":"Basel-Stadt",
    "wof:name":"Gulli Eisenleger",
    "wof:placetype":"venue"
},
  "geometry": {"coordinates":[7.5906510353,47.5761795044],"type":"Point"}
}