{
  "type": "Feature",
  "properties": {
    "iso:country":"CH",
    "sg:address":"H\u00f6heweg 1e",
    "sg:city":"Spiez",
    "sg:orig_category":"Fahrschulen, Flugschulen",
    "sg:phone":"+41 33 654 25 86",
    "sg:postcode":"3700",
    "sg:province":"Bern",
    "wof:name":"Martin Steuri Autofahrschule",
    "wof:placetype":"venue"
},
  "geometry": {"coordinates":[7.6773228645,46.6847686768],"type":"Point"}
}