{
  "type": "Feature",
  "properties": {
    "iso:country":"CH",
    "sg:address":"Obertor 37",
    "sg:city":"Winterthur",
    "sg:orig_category":"Detailhandel mit elektrischen Haushalts-,Radio U Fernsehger\u00e4ten sowie Musikinstrumenten Elektroinsta",
    "sg:phone":"+41 52 212 55 58",
    "sg:postcode":"8400",
    "sg:province":"Z\u00fcrich",
    "wof:name":"Dietiker & Humbel Ag",
    "wof:placetype":"venue"
},
  "geometry": {"coordinates":[8.7313919067,47.4998550415],"type":"Point"}
}