{
  "type": "Feature",
  "properties": {
    "iso:country":"CH",
    "sg:address":"Hauptstrasse 49",
    "sg:city":"Glarus",
    "sg:orig_category":"Interessenvertretungen",
    "sg:postcode":"8750",
    "sg:province":"Glarus",
    "wof:name":"Gr\u00fcner Janura Ag",
    "wof:placetype":"venue"
},
  "geometry": {"coordinates":[9.066986084,47.0410118103],"type":"Point"}
}