{
  "type": "Feature",
  "properties": {
    "iso:country":"CH",
    "sg:address":"St. Gallerstrasse 145",
    "sg:city":"Jona",
    "sg:orig_category":"Kosmetikinstitute",
    "sg:phone":"+41 55 212 45 70",
    "sg:postcode":"8645",
    "sg:province":"St. Gallen",
    "wof:name":"Manuela Dello Stritto Kosmetikinstitut Manuela",
    "wof:placetype":"venue"
},
  "geometry": {"coordinates":[8.8507862091,47.2305374146],"type":"Point"}
}