{
  "type": "Feature",
  "properties": {
    "iso:country":"CH",
    "sg:address":"Michele Via San 20",
    "sg:city":"Ascona",
    "sg:orig_category":"Vermietung U Verpachtung von eigenen Immobilien",
    "sg:postcode":"6612",
    "sg:province":"Ticino",
    "wof:name":"Immobiliare Rao Livio",
    "wof:placetype":"venue"
},
  "geometry": {"coordinates":[8.7651691437,46.1546440125],"type":"Point"}
}