{
  "type": "Feature",
  "properties": {
    "iso:country":"CH",
    "sg:address":"Rue Du Pr\u00e9 Bernard 6",
    "sg:city":"Tavannes",
    "sg:orig_category":"Wirtschaftspr\u00fcfung, Steuerberatung U Treuhand",
    "sg:phone":"+41 32 481 47 08",
    "sg:postcode":"2710",
    "sg:province":"Bern",
    "wof:name":"Cornu Pascal",
    "wof:placetype":"venue"
},
  "geometry": {"coordinates":[7.2048330307,47.219619751],"type":"Point"}
}