{
  "type": "Feature",
  "properties": {
    "iso:country":"CH",
    "sg:address":"Eigerweg 7 Sch\u00f6nb\u00fchl.",
    "sg:city":"Sch\u00f6nb\u00fchl-urtenen",
    "sg:orig_category":"Detailhandel mit elektrischen Haushalts-,Radio U Fernsehger\u00e4ten sowie Musikinstrumenten",
    "sg:phone":"+41 31 859 42 42",
    "sg:postcode":"3322",
    "sg:province":"Bern",
    "wof:name":"Kurt Geissb\u00fchler",
    "wof:placetype":"venue"
},
  "geometry": {"coordinates":[7.4995298386,47.0204238892],"type":"Point"}
}