{
  "type": "Feature",
  "properties": {
    "iso:country":"CH",
    "sg:address":"Furkastrasse 58",
    "sg:city":"Naters",
    "sg:orig_category":"Fussboden, Fliesen U Plattenlegerei, Tapeziererei Verlegen von Fliesen U Platten",
    "sg:phone":"+41 27 923 21 53",
    "sg:postcode":"3904",
    "sg:province":"Valais",
    "wof:name":"Liechti L\u00e9on",
    "wof:placetype":"venue"
},
  "geometry": {"coordinates":[7.9953241348,46.324798584],"type":"Point"}
}