{
  "type": "Feature",
  "properties": {
    "iso:country":"CH",
    "sg:address":"3963",
    "sg:city":"Crans-sur-sierre",
    "sg:orig_category":"Sessellifte and Skilifte",
    "sg:phone":"+41 27 483 17 71",
    "sg:postcode":"3963",
    "sg:province":"Valais",
    "wof:name":"Trainers-skilift Sa",
    "wof:placetype":"venue"
},
  "geometry": {"coordinates":[7.4617700577,46.3076210022],"type":"Point"}
}