{
  "type": "Feature",
  "properties": {
    "addr:full":"Finsterg\u00e4sschen 352 4323 Wallbach. Postfach Wallbach Aargau 4323",
    "addr:housenumber":"352",
    "addr:postcode":"4323 wallbach. postfach wallbach;4323",
    "iso:country":"CH",
    "sg:address":"Finsterg\u00e4sschen 352 4323 Wallbach. Postfach",
    "sg:city":"Wallbach",
    "sg:orig_category":"Architektur U Ingenieurb\u00fcros Architekturb\u00fcros",
    "sg:phone":"+41 61 861 15 49",
    "sg:postcode":"4323",
    "sg:province":"Aargau",
    "wof:name":"Starch Architekturb\u00fcro Stolz Renato Techn. Ts Hochbau",
    "wof:placetype":"venue"
},
  "geometry": {"coordinates":[7.89833,47.560081],"type":"Point"}
}