{
  "type": "Feature",
  "properties": {
    "iso:country":"CH",
    "sg:address":"Suhrenmattstr. 34",
    "sg:city":"Unterentfelden",
    "sg:classifiers":[
        {
            "category":"Shopping",
            "subcategory":"Computers & Home Electronics",
            "type":"Retail Goods"
        }
    ],
    "sg:phone":"+41 62 723 79 79",
    "sg:postcode":"5035",
    "sg:province":"Aargau",
    "sg:tags":[
        "equipment",
        "electrical",
        "component",
        "electric",
        "electronic"
    ],
    "wof:name":"W Klingler Fahrzeugtechnik Ag",
    "wof:placetype":"venue"
},
  "geometry": {"coordinates":[8.0480461121,47.3632354736],"type":"Point"}
}