{
  "type": "Feature",
  "properties": {
    "addr:full":"1428 Mutrux Vaud 1428",
    "addr:postcode":"1428;1428",
    "iso:country":"CH",
    "sg:address":"1428",
    "sg:city":"Mutrux",
    "sg:orig_category":"Bauschreinerei Herstellung von Konstruktionsteilen, Fertigbauteilen U Ausbauelementen aus Holz",
    "sg:phone":"+41 24 434 15 69",
    "sg:postcode":"1428",
    "sg:province":"Vaud",
    "wof:name":"Raymondaz Andr\u00e9.",
    "wof:placetype":"venue"
},
  "geometry": {"coordinates":[6.727121,46.883614],"type":"Point"}
}