{
  "type": "Feature",
  "properties": {
    "iso:country":"CH",
    "sg:address":"Feldstrasse 33",
    "sg:city":"Degersheim",
    "sg:orig_category":"Sportvereine Turnen",
    "sg:postcode":"9113",
    "sg:province":"St. Gallen",
    "wof:name":"Turnverein Degersheim",
    "wof:placetype":"venue"
},
  "geometry": {"coordinates":[9.1924638748,47.370803833],"type":"Point"}
}