{
  "type": "Feature",
  "properties": {
    "addr:full":"Uetlibergstrasse 113 Z\u00fcrich Z\u00fcrich 8045",
    "addr:housenumber":"113",
    "addr:postcode":"8045",
    "addr:street":"Uetlibergstrasse",
    "iso:country":"CH",
    "sg:address":"Uetlibergstrasse 113",
    "sg:city":"Z\u00fcrich",
    "sg:orig_category":"Autogaragen",
    "sg:phone":"+41 14624247",
    "sg:postcode":"8045",
    "sg:province":"Z\u00fcrich",
    "wof:name":"Garage Ignazio Pezzino",
    "wof:placetype":"venue"
},
  "geometry": {"coordinates":[8.517074,47.36076],"type":"Point"}
}