{
  "type": "Feature",
  "properties": {
    "iso:country":"CH",
    "sg:address":"Grendelstrasse 30",
    "sg:city":"Ennetbaden",
    "sg:orig_category":"Softwareentwicklung U beratung",
    "sg:phone":"+41 56 210 35 21",
    "sg:postcode":"5408",
    "sg:province":"Aargau",
    "wof:name":"Graf-schait & Co Solutions",
    "wof:placetype":"venue"
},
  "geometry": {"coordinates":[8.3175468445,47.4783477783],"type":"Point"}
}