{
  "type": "Feature",
  "properties": {
    "iso:country":"CH",
    "sg:address":"Els\u00e4sserstrasse 34",
    "sg:city":"Basel",
    "sg:orig_category":"Bau U Wohngenossenschaften",
    "sg:postcode":"4056",
    "sg:province":"Basel-Stadt",
    "wof:name":"Bwg Zu Den Alten Schollen",
    "wof:placetype":"venue"
},
  "geometry": {"coordinates":[7.579728,47.568951],"type":"Point"}
}