{
  "type": "Feature",
  "properties": {
    "iso:country":"CH",
    "sg:address":"Birkenmatte 6/8 6343 Rotkreuz. Postfach",
    "sg:city":"Rotkreuz",
    "sg:orig_category":"Interessenvertretungen",
    "sg:postcode":"6343",
    "sg:province":"Zug",
    "wof:name":"Institut F\u00fcr Medizinische Fortbildung Imforganisation Ag Lehr- U. Informationsveranstaltungen. Medizinische Publikationen; Verlag, Herausgabe Usw",
    "wof:placetype":"venue"
},
  "geometry": {"coordinates":[8.4288902283,47.1431884766],"type":"Point"}
}