{
  "type": "Feature",
  "properties": {
    "iso:country":"CH",
    "sg:address":"Al Chiosso",
    "sg:city":"Cadenazzo",
    "sg:orig_category":"Hoch U Tiefbau",
    "sg:phone":"+41 79 620 81 29",
    "sg:postcode":"6593",
    "sg:province":"Ticino",
    "wof:name":"Giovanni Rota & Co Impresa Costruzione",
    "wof:placetype":"venue"
},
  "geometry": {"coordinates":[8.9523019791,46.1495780945],"type":"Point"}
}