{
  "type": "Feature",
  "properties": {
    "iso:country":"CH",
    "sg:address":"Kolinplatz 2 6300 Zug. Postfach",
    "sg:city":"Zug",
    "sg:orig_category":"Grosshandel mit sonstigen Gebrauchs U Verbrauchsg\u00fctern",
    "sg:postcode":"6300",
    "sg:province":"Zug",
    "wof:name":"Cadeaux Ginkgo Juwelen Ag Juwelen, Schmuckst\u00fccke; Kauf, Verkauf, Vertrieb Usw",
    "wof:placetype":"venue"
},
  "geometry": {"coordinates":[8.515376091,47.1663856506],"type":"Point"}
}