{
  "type": "Feature",
  "properties": {
    "iso:country":"CH",
    "sg:address":"Rikonerstrasse 4 8307 Effretikon. Postfach 368",
    "sg:city":"Effretikon",
    "sg:orig_category":"Architektur U Ingenieurb\u00fcros",
    "sg:phone":"+41 52 354 21 11",
    "sg:postcode":"8307",
    "sg:province":"Z\u00fcrich",
    "wof:name":"Winkler Ernst + Partner Ag, Ingenieur Und Vermessungsb\u00fcro",
    "wof:placetype":"venue"
},
  "geometry": {"coordinates":[8.686599,47.42783],"type":"Point"}
}