{
  "type": "Feature",
  "properties": {
    "iso:country":"CH",
    "sg:address":"Sch\u00fctzenweg 1 4528 Zuchwil. Postfach",
    "sg:city":"Zuchwil",
    "sg:orig_category":"Herstellung von Betonerzeugnissen f\u00fcr den Bau Herstellung von Transportbeton",
    "sg:phone":"+41 61 701 19 82",
    "sg:postcode":"4528",
    "sg:province":"Solothurn",
    "wof:name":"Frischbeton Ag",
    "wof:placetype":"venue"
},
  "geometry": {"coordinates":[7.604391098,47.4798736572],"type":"Point"}
}