{
  "type": "Feature",
  "properties": {
    "iso:country":"CH",
    "sg:address":"Z\u00fcrcherstrasse 16a",
    "sg:city":"Altendorf",
    "sg:classifiers":[
        {
            "category":"Restaurant",
            "type":"Food & Drink"
        }
    ],
    "sg:phone":"+41 55 442 79 19",
    "sg:postcode":"8852",
    "sg:province":"Schwyz",
    "wof:name":"Caf\u00e9 Bar Seepark",
    "wof:placetype":"venue"
},
  "geometry": {"coordinates":[8.8278093338,47.1929321289],"type":"Point"}
}