{
  "type": "Feature",
  "properties": {
    "iso:country":"CH",
    "sg:address":"Route De Villarepos 35 1595 Faoug. Postfach",
    "sg:city":"Faoug",
    "sg:orig_category":"Herstellung von elektronischen Bauelementen",
    "sg:postcode":"1595",
    "sg:province":"Bern",
    "wof:name":"Rcs Senaud Roland Concept",
    "wof:placetype":"venue"
},
  "geometry": {"coordinates":[7.0786538124,46.9071884155],"type":"Point"}
}