{
  "type": "Feature",
  "properties": {
    "iso:country":"CH",
    "sg:address":"Zeughausstr 9 8592 Uttwil. Postfach 38",
    "sg:city":"Freiburg",
    "sg:orig_category":"Fachdetailhandel in Verkaufsr\u00e4umen",
    "sg:phone":"+41 71 463 30 59",
    "sg:postcode":"1700",
    "sg:province":"Fribourg",
    "wof:name":"Lindner Falzlos-gesellschaft Kg, Sch\u00f6mberg, Zweigniederlassung Uttwil.",
    "wof:placetype":"venue"
},
  "geometry": {"coordinates":[9.3431119919,47.582408905],"type":"Point"}
}