{
  "type": "Feature",
  "properties": {
    "iso:country":"CH",
    "sg:address":"Merkurstrasse 13 6210 Sursee. Postfach 3052",
    "sg:city":"Sursee",
    "sg:orig_category":"Detailhandel mit M\u00f6beln U Haushaltsgegenst\u00e4nden Verlegen von Fussboden",
    "sg:phone":"+41 41 921 55 22",
    "sg:postcode":"6210",
    "sg:province":"Luzern",
    "wof:name":"Kunz Teppich + Wohnbedarf Ag",
    "wof:placetype":"venue"
},
  "geometry": {"coordinates":[8.1031150818,47.1663970947],"type":"Point"}
}