{
  "type": "Feature",
  "properties": {
    "iso:country":"CH",
    "sg:address":"Via St. Maria 52",
    "sg:city":"Gordola",
    "sg:classifiers":[
        {
            "category":"Manufacturing",
            "subcategory":"Wood Products",
            "type":"Manufacturing & Wholesale Goods"
        }
    ],
    "sg:phone":"+41 91 745 18 16",
    "sg:postcode":"6596",
    "sg:province":"Ticino",
    "sg:tags":[
        "gate",
        "made",
        "door"
    ],
    "wof:name":"Sergio Togni Sa",
    "wof:placetype":"venue"
},
  "geometry": {"coordinates":[8.86532,46.173908],"type":"Point"}
}