{
  "type": "Feature",
  "properties": {
    "iso:country":"CH",
    "sg:address":"Z\u00fcrcherstrasse 127",
    "sg:city":"Basel",
    "sg:orig_category":"Reparatur von Schuhen U Lederwaren",
    "sg:phone":"+41 61 312 48 30",
    "sg:postcode":"4052",
    "sg:province":"Basel-Stadt",
    "wof:name":"Armando Faggiorini Schuhservice",
    "wof:placetype":"venue"
},
  "geometry": {"coordinates":[7.6122331619,47.5550994873],"type":"Point"}
}