{
  "type": "Feature",
  "properties": {
    "iso:country":"CH",
    "sg:address":"Schmiedengasse 16",
    "sg:city":"Burgdorf",
    "sg:orig_category":"Detailhandel mit Schuhen U Lederwaren",
    "sg:postcode":"3400",
    "sg:province":"Bern",
    "wof:name":"Schuhhaus Silvia Burkhalter-biedermann",
    "wof:placetype":"venue"
},
  "geometry": {"coordinates":[7.625934124,47.0557556152],"type":"Point"}
}