{
  "type": "Feature",
  "properties": {
    "iso:country":"CH",
    "sg:address":"Charrat",
    "sg:city":"Charrat",
    "sg:classifiers":[
        {
            "category":"Banks & Credit Unions",
            "subcategory":"Bank",
            "type":"Services"
        }
    ],
    "sg:phone":"+41 27 746 32 92",
    "sg:postcode":"1906",
    "sg:province":"Valais",
    "wof:name":"Credit Suisse, Repr\u00e9s. Darioly G\u00e9rard",
    "wof:placetype":"venue"
},
  "geometry": {"coordinates":[7.129689,46.124989],"type":"Point"}
}