{
  "type": "Feature",
  "properties": {
    "iso:country":"CH",
    "sg:address":"Chemin De La Grand-vigne 3",
    "sg:city":"Prilly",
    "sg:orig_category":"Primarschulen",
    "sg:postcode":"1008",
    "sg:province":"Vaud",
    "wof:name":"Ecole Primaire Coll\u00e8ge Grand-pr\u00e9",
    "wof:placetype":"venue"
},
  "geometry": {"coordinates":[6.606757164,46.5404205322],"type":"Point"}
}