{
  "type": "Feature",
  "properties": {
    "iso:country":"CH",
    "sg:address":"Penate Via 4 6850 Mendrisio Casella Postale",
    "sg:city":"Mendrisio",
    "sg:orig_category":"Versandhandel",
    "sg:phone":"+41 91 646 80 51",
    "sg:postcode":"6850",
    "sg:province":"Ticino",
    "wof:name":"Solis Mail Sa",
    "wof:placetype":"venue"
},
  "geometry": {"coordinates":[8.9880838394,45.870098114],"type":"Point"}
}