{
  "type": "Feature",
  "properties": {
    "iso:country":"CH",
    "sg:address":"Dorfstrasse 17",
    "sg:city":"Osterfingen",
    "sg:orig_category":"Detailhandel mit Waren verschiedener Art, Hauptrichtung Nahrungsmittel",
    "sg:phone":"+41 27 783 13 08",
    "sg:postcode":"8218",
    "sg:province":"Schaffhausen",
    "wof:name":"Georges & Brunette Darbellay Epicerie",
    "wof:placetype":"venue"
},
  "geometry": {"coordinates":[7.1808519363,46.0040893555],"type":"Point"}
}