{
  "type": "Feature",
  "properties": {
    "iso:country":"CH",
    "sg:address":"Hubel 73",
    "sg:city":"Reitnau",
    "sg:orig_category":"Allgemeiner Hoch U Tiefbau",
    "sg:phone":"+41 62 726 17 75",
    "sg:postcode":"5057",
    "sg:province":"Aargau",
    "wof:name":"W. Klauser Baugesch\u00e4ft Ag",
    "wof:placetype":"venue"
},
  "geometry": {"coordinates":[8.04244,47.248806],"type":"Point"}
}