{
  "type": "Feature",
  "properties": {
    "iso:country":"CH",
    "sg:address":"Redingstrasse 2",
    "sg:city":"Kreuzlingen",
    "sg:orig_category":"Architektur U Ingenieurb\u00fcros",
    "sg:phone":"+41 71 677 99 83",
    "sg:postcode":"8280",
    "sg:province":"Thurgau",
    "wof:name":"Rindlisbacher Architekt",
    "wof:placetype":"venue"
},
  "geometry": {"coordinates":[9.164148,47.647499],"type":"Point"}
}