{
  "type": "Feature",
  "properties": {
    "iso:country":"CH",
    "sg:address":"Via Adamini 20 6900 Lugano. Postfach Caselle Postale 66 6907 Lugano",
    "sg:city":"Caselle",
    "sg:orig_category":"Handelsvermittlung U Grosshandel mit Automobilteilen U Zubeh\u00f6r Herstellung von Bereifungen",
    "sg:phone":"+41 91 994 25 41",
    "sg:postcode":"7",
    "wof:name":"Belimport Sa",
    "wof:placetype":"venue"
},
  "geometry": {"coordinates":[8.9446401596,45.9980697632],"type":"Point"}
}