{
  "type": "Feature",
  "properties": {
    "iso:country":"CH",
    "sg:address":"Freidorfweg 3",
    "sg:city":"Pieterlen",
    "sg:orig_category":"Allgemeiner Hochbau Strassenbau",
    "sg:phone":"+41 27 473 13 42",
    "sg:postcode":"2542",
    "sg:province":"Bern",
    "wof:name":"Raphael Kuonen Baugesch\u00e4ft",
    "wof:placetype":"venue"
},
  "geometry": {"coordinates":[7.63466,46.31633],"type":"Point"}
}