{
  "type": "Feature",
  "properties": {
    "iso:country":"CH",
    "sg:address":"Marktgasse 47a 8400 Winterthur. Postfach",
    "sg:city":"Winterthur",
    "sg:orig_category":"Reiseb\u00fcros U Reiseveranstalter",
    "sg:phone":"+41 12778111",
    "sg:postcode":"8402",
    "sg:province":"Z\u00fcrich",
    "wof:name":"Hotelplan Internationale Reiseorganisation Ag",
    "wof:placetype":"venue"
},
  "geometry": {"coordinates":[7.4438471794,46.9482154846],"type":"Point"}
}