{
  "type": "Feature",
  "properties": {
    "addr:full":"Baumastrasse 5 B\u00e4retswil Z\u00fcrich 8344",
    "addr:housenumber":"5",
    "addr:postcode":"8344",
    "addr:street":"Baumastrasse;Zuerich",
    "iso:country":"CH",
    "sg:address":"Baumastrasse 5",
    "sg:city":"B\u00e4retswil",
    "sg:orig_category":"Bauspenglerei Sanit\u00e4rinstallation U Spenglerei",
    "sg:phone":"+41 19391893",
    "sg:postcode":"8344",
    "sg:province":"Z\u00fcrich",
    "wof:name":"Bruno Kirsch Spenglerei",
    "wof:placetype":"venue"
},
  "geometry": {"coordinates":[8.857037,47.336777],"type":"Point"}
}