{
  "type": "Feature",
  "properties": {
    "iso:country":"CH",
    "sg:address":"Jupiterstrasse 45",
    "sg:city":"Bern",
    "sg:orig_category":"Verarbeitung U Veredlung von Flachglas",
    "sg:postcode":"3015",
    "sg:province":"Bern",
    "wof:name":"Roboleas Ag",
    "wof:placetype":"venue"
},
  "geometry": {"coordinates":[7.4846258163,46.9389457703],"type":"Point"}
}