{
  "type": "Feature",
  "properties": {
    "iso:country":"CH",
    "sg:address":"Sportplatzweg 40",
    "sg:city":"Naters",
    "sg:orig_category":"Malerei",
    "sg:phone":"+41 18582344",
    "sg:postcode":"3904",
    "sg:province":"Valais",
    "wof:name":"Egidio Fortino Malergesch\u00e4ft",
    "wof:placetype":"venue"
},
  "geometry": {"coordinates":[8.4186058044,47.5673446655],"type":"Point"}
}