{
  "type": "Feature",
  "properties": {
    "iso:country":"CH",
    "sg:address":"Paradiso Riva 30 6900 Paradiso. Postfach",
    "sg:city":"Paradiso",
    "sg:orig_category":"Gartenbau",
    "sg:phone":"+41 79 688 45 42",
    "sg:postcode":"6900",
    "sg:province":"Ticino",
    "wof:name":"Massei-van Anke Overeem",
    "wof:placetype":"venue"
},
  "geometry": {"coordinates":[8.9516515732,45.9899597168],"type":"Point"}
}