{
  "type": "Feature",
  "properties": {
    "iso:country":"CH",
    "sg:address":"Unterdorf 18",
    "sg:city":"Maisprach",
    "sg:classifiers":[
        {
            "category":"Travel",
            "subcategory":"Hotels & Motels",
            "type":"Entertainment"
        }
    ],
    "sg:phone":"+41 41 885 11 31",
    "sg:postcode":"4464",
    "sg:province":"Basel-Landschaft",
    "sg:tags":[
        "hotels",
        "mit",
        "restaurant"
    ],
    "wof:name":"Hotel Alte Post",
    "wof:placetype":"venue"
},
  "geometry": {"coordinates":[8.5989398956,46.7059593201],"type":"Point"}
}