{
  "type": "Feature",
  "properties": {
    "iso:country":"CH",
    "sg:address":"Rue De Lausanne 40",
    "sg:city":"Gen\u00e8ve",
    "sg:classifiers":[
        {
            "category":"Travel",
            "subcategory":"Hotels & Motels",
            "type":"Entertainment"
        }
    ],
    "sg:phone":"+41 22 731 44 90",
    "sg:postcode":"1201",
    "sg:province":"Gen\u00e8ve",
    "sg:tags":[
        "oder",
        "bar",
        "restaurant"
    ],
    "wof:name":"Andie's Bar",
    "wof:placetype":"venue"
},
  "geometry": {"coordinates":[6.145794,46.213364],"type":"Point"}
}