{
  "type": "Feature",
  "properties": {
    "addr:full":"Wangenerstrasse 21 Effretikon Z\u00fcrich 8307",
    "addr:housenumber":"21",
    "addr:postcode":"8307",
    "addr:street":"Wangenerstrasse",
    "iso:country":"CH",
    "sg:address":"Wangenerstrasse 21",
    "sg:city":"Effretikon",
    "sg:orig_category":"Detailhandel mit Brot, Back U S\u00fcsswaren",
    "sg:phone":"+41 52 343 11 23",
    "sg:postcode":"8307",
    "sg:province":"Z\u00fcrich",
    "wof:name":"B\u00e4ckerei-konditorei Trudel J\u00fcrg & Sandra Gadient",
    "wof:placetype":"venue"
},
  "geometry": {"coordinates":[8.68406,47.425999],"type":"Point"}
}