{
  "type": "Feature",
  "properties": {
    "iso:country":"CH",
    "sg:address":"Rue Pestalozzi 18",
    "sg:city":"Yverdon-les-bains",
    "sg:orig_category":"Sanit\u00e4r U Heizungsinstallation Sanit\u00e4r, Heizungs U L\u00fcftungsinstallation",
    "sg:phone":"+41 41 930 14 80",
    "sg:postcode":"1400",
    "sg:province":"Vaud",
    "wof:name":"Stocker Walter",
    "wof:placetype":"venue"
},
  "geometry": {"coordinates":[8.1478500366,47.2238731384],"type":"Point"}
}