{
  "type": "Feature",
  "properties": {
    "iso:country":"CH",
    "sg:address":"Winzerhalde 24 8049 Z\u00fcrich. Postfach",
    "sg:city":"Z\u00fcrich",
    "sg:orig_category":"Fachdetailhandel in Verkaufsr\u00e4umen",
    "sg:postcode":"8052",
    "sg:province":"Z\u00fcrich",
    "wof:name":"Vertigo Handels Gmbh Waren, Bes. Schmuckwaren Usw; Imp., Exp., Handel",
    "wof:placetype":"venue"
},
  "geometry": {"coordinates":[8.4919338226,47.3998603821],"type":"Point"}
}