{
  "type": "Feature",
  "properties": {
    "iso:country":"CH",
    "sg:address":"Pilatusstrasse 6",
    "sg:city":"Dierikon",
    "sg:orig_category":"Herstellung von Teppichen Verlegen von Fussboden",
    "sg:phone":"+41 41 450 51 21",
    "sg:postcode":"6036",
    "sg:province":"Luzern",
    "wof:name":"Carpet-land (suisse) Sa",
    "wof:placetype":"venue"
},
  "geometry": {"coordinates":[8.364112854,47.0945396423],"type":"Point"}
}