{
  "type": "Feature",
  "properties": {
    "iso:country":"CH",
    "sg:address":"H\u00f6nggerstrasse 115",
    "sg:city":"Z\u00fcrich",
    "sg:orig_category":"Unclassifiable Establishments",
    "sg:phone":"+41 12714022",
    "sg:postcode":"8037",
    "sg:province":"Z\u00fcrich",
    "wof:name":"Bindella Terra Vite Vita Sa",
    "wof:placetype":"venue"
},
  "geometry": {"coordinates":[8.5190238953,47.3952102661],"type":"Point"}
}