{
  "type": "Feature",
  "properties": {
    "iso:country":"CH",
    "sg:address":"Hardhof 120",
    "sg:city":"Zunzgen",
    "sg:orig_category":"Landw. Genossenschaften Viehzucht",
    "sg:postcode":"4455",
    "sg:province":"Basel-Landschaft",
    "wof:name":"Viehzuchtgenossenschaft Sulz",
    "wof:placetype":"venue"
},
  "geometry": {"coordinates":[8.0957698822,47.5344696045],"type":"Point"}
}