{
  "type": "Feature",
  "properties": {
    "iso:country":"CH",
    "sg:address":"Vorderer Hauptgasse 2",
    "sg:city":"Zofingen",
    "sg:orig_category":"Advokaturb\u00fcros",
    "sg:phone":"+41 62 751 51 11",
    "sg:postcode":"4800",
    "sg:province":"Aargau",
    "wof:name":"Markus Henzer Advokaturb\u00fcro",
    "wof:placetype":"venue"
},
  "geometry": {"coordinates":[7.94385,47.290569],"type":"Point"}
}