{
  "type": "Feature",
  "properties": {
    "iso:country":"CH",
    "sg:address":"8259",
    "sg:city":"Kaltenbach",
    "sg:orig_category":"Schulpflegen",
    "sg:postcode":"8259",
    "sg:province":"Thurgau",
    "wof:name":"Primarschulkommission Der Gemeinde Kaltenbach",
    "wof:placetype":"venue"
},
  "geometry": {"coordinates":[8.8427000046,47.6529884338],"type":"Point"}
}