{
  "type": "Feature",
  "properties": {
    "iso:country":"CH",
    "sg:address":"Fuchslochstrasse 2",
    "sg:city":"Lostorf",
    "sg:orig_category":"Instandhaltung U Reparatur von Automobilen",
    "sg:phone":"+41 62 298 17 71",
    "sg:postcode":"4654",
    "sg:province":"Solothurn",
    "wof:name":"Carrosserie Di Nunzio Ag",
    "wof:placetype":"venue"
},
  "geometry": {"coordinates":[7.94977808,47.3790817261],"type":"Point"}
}