{
  "type": "Feature",
  "properties": {
    "iso:country":"CH",
    "sg:address":"Gr\u00fcnfeldweg 5",
    "sg:city":"Weite",
    "sg:orig_category":"Herstellung von Ger\u00e4ten der Elektrizit\u00e4tserzeugung, -verteilung u.\u00e4. -Herstellung von elektronischen",
    "sg:phone":"+41 32 655 61 11",
    "sg:postcode":"9476",
    "sg:province":"St. Gallen",
    "wof:name":"Rado Uhren Ag",
    "wof:placetype":"venue"
},
  "geometry": {"coordinates":[7.3615560532,47.180305481],"type":"Point"}
}