{
  "type": "Feature",
  "properties": {
    "iso:country":"CH",
    "sg:address":"Heuelstrasse 14 8800 Thalwil. Postfach 121",
    "sg:city":"Thalwil",
    "sg:orig_category":"Grosshandel mit Parf\u00fcmerieartikeln U K\u00f6rperpflegemitteln",
    "sg:phone":"+41 17206108",
    "sg:postcode":"8800",
    "sg:province":"Z\u00fcrich",
    "wof:name":"Ellen Schimmelpfeng Gmbh Bio-kosmetik",
    "wof:placetype":"venue"
},
  "geometry": {"coordinates":[8.5543422699,47.2965431213],"type":"Point"}
}