{
  "type": "Feature",
  "properties": {
    "iso:country":"CH",
    "sg:address":"Route Du Simplon",
    "sg:city":"Ardon",
    "sg:orig_category":"Druck ohne Zeitungsdruck Offsetdruck",
    "sg:phone":"+41 32 969 28 28",
    "sg:postcode":"1957",
    "sg:province":"Valais",
    "wof:name":"Imprimerie Des Montagnes Sa",
    "wof:placetype":"venue"
},
  "geometry": {"coordinates":[6.8344697952,47.1017494202],"type":"Point"}
}