{
  "type": "Feature",
  "properties": {
    "iso:country":"CH",
    "sg:address":"Dynamoweg 40 8050 Z\u00fcrich",
    "sg:city":"Zust",
    "sg:orig_category":"G\u00fcterbef\u00f6rderung im Strassenverkehr",
    "sg:phone":"+41 41 820 50 10",
    "sg:postcode":"50",
    "wof:name":"Zoll - Fix Gmbh",
    "wof:placetype":"venue"
},
  "geometry": {"coordinates":[8.6302995682,47.0264511108],"type":"Point"}
}