{
  "type": "Feature",
  "properties": {
    "iso:country":"CH",
    "sg:address":"Hauptstrasse 80",
    "sg:city":"Binningen",
    "sg:orig_category":"Sonstige mit der Informatik verbundene T\u00e4tigkeiten",
    "sg:phone":"+41 61 421 04 85",
    "sg:postcode":"4102",
    "sg:province":"Basel-Landschaft",
    "wof:name":"Esys Gmbh",
    "wof:placetype":"venue"
},
  "geometry": {"coordinates":[7.5728058815,47.5397949219],"type":"Point"}
}