{
  "type": "Feature",
  "properties": {
    "addr:full":"Grand-rue 24 Payerne Vaud 1530",
    "addr:housenumber":"24",
    "addr:postcode":"1530",
    "addr:street":"Grand-Rue",
    "iso:country":"CH",
    "sg:address":"Grand-rue 24",
    "sg:city":"Payerne",
    "sg:orig_category":"Detailhandel mit Brot, Back U S\u00fcsswaren",
    "sg:phone":"+41 32 913 35 50",
    "sg:postcode":"1530",
    "sg:province":"Vaud",
    "wof:name":"Tea-room Jean-p. Freyburger",
    "wof:placetype":"venue"
},
  "geometry": {"coordinates":[6.82728,47.102707],"type":"Point"}
}