{
  "type": "Feature",
  "properties": {
    "iso:country":"CH",
    "sg:address":"In Der Bettenen 4",
    "sg:city":"Feldmeilen",
    "sg:orig_category":"Gesundheitswesen",
    "sg:postcode":"8706",
    "sg:province":"Z\u00fcrich",
    "wof:name":"Nyffeler Beatrice, Kochservice",
    "wof:placetype":"venue"
},
  "geometry": {"coordinates":[8.623418808,47.2807121277],"type":"Point"}
}