{
  "type": "Feature",
  "properties": {
    "iso:country":"CH",
    "sg:address":"Wetzikerstrasse 26",
    "sg:city":"B\u00e4retswil",
    "sg:orig_category":"Vereine Vogel-& Naturschutz",
    "sg:phone":"+41 71 455 15 89",
    "sg:postcode":"8344",
    "sg:province":"Z\u00fcrich",
    "wof:name":"Ornithologischer Verein",
    "wof:placetype":"venue"
},
  "geometry": {"coordinates":[9.3755149841,47.4928779602],"type":"Point"}
}