{
  "type": "Feature",
  "properties": {
    "iso:country":"CH",
    "sg:address":"Oberbreiti 229 8454 Buchberg. Postfach",
    "sg:city":"Thal",
    "sg:orig_category":"Herstellung von k\u00e4lte U lufttechnischen Erzeugnissen f\u00fcr gewerbliche Zwecke",
    "sg:postcode":"9425",
    "sg:province":"St. Gallen",
    "wof:name":"Teamprojekt Ag",
    "wof:placetype":"venue"
},
  "geometry": {"coordinates":[7.5479288101,47.516166687],"type":"Point"}
}