{
  "type": "Feature",
  "properties": {
    "iso:country":"CH",
    "sg:address":"Schwellbrunner Strasse 10",
    "sg:city":"Dicken",
    "sg:orig_category":"Herstellung von Baubedarfsartikeln aus Kunststoff Herstellung von Fenstern U T\u00fcren aus Holz",
    "sg:phone":"+41 19703050",
    "sg:postcode":"9115",
    "sg:province":"St. Gallen",
    "wof:name":"Helag Fenstertechnik Ag Kunststoff-fenstersystem",
    "wof:placetype":"venue"
},
  "geometry": {"coordinates":[8.8084897995,47.3316688538],"type":"Point"}
}