{
  "type": "Feature",
  "properties": {
    "addr:full":"M\u00fchlegutstrasse 15 Steinach St. Gallen 9323",
    "addr:housenumber":"15;st.",
    "addr:postcode":"9323",
    "addr:street":"Muehlegutstrasse;Steinach",
    "iso:country":"CH",
    "sg:address":"M\u00fchlegutstrasse 15",
    "sg:city":"Steinach",
    "sg:orig_category":"Dachdeckerei Zimmerei, Dachdeckerei, Bauspenglerei U Abdichtung",
    "sg:phone":"+41 41 811 72 07",
    "sg:postcode":"9323",
    "sg:province":"St. Gallen",
    "wof:name":"Lagler Franz",
    "wof:placetype":"venue"
},
  "geometry": {"coordinates":[8.630891,47.01907],"type":"Point"}
}