{
  "type": "Feature",
  "properties": {
    "iso:country":"CH",
    "sg:address":"Hauptstrasse 30 4466 Ormalingen. Postfach",
    "sg:city":"Ormalingen",
    "sg:orig_category":"Elektroinstallation",
    "sg:phone":"+41 32 499 90 02",
    "sg:postcode":"4466",
    "sg:province":"Basel-Landschaft",
    "wof:name":"Brand Jean-claude",
    "wof:placetype":"venue"
},
  "geometry": {"coordinates":[7.4550700188,47.285369873],"type":"Point"}
}