{
  "type": "Feature",
  "properties": {
    "addr:full":"Mattweg 85 Arlesheim Basel-Landschaft 4144",
    "addr:housenumber":"85",
    "addr:postcode":"4144",
    "addr:street":"Mattweg",
    "iso:country":"CH",
    "sg:address":"Mattweg 85",
    "sg:city":"Arlesheim",
    "sg:orig_category":"Blumen U Zierpflanzenbau",
    "sg:phone":"+41 61 701 19 10",
    "sg:postcode":"4144",
    "sg:province":"Basel-Landschaft",
    "wof:name":"Sommerer & Co.",
    "wof:placetype":"venue"
},
  "geometry": {"coordinates":[7.616068,47.502403],"type":"Point"}
}