{
  "type": "Feature",
  "properties": {
    "iso:country":"CH",
    "sg:address":"Bahnhofstrasse 12 8583 Sulgen. Postfach 125",
    "sg:city":"Sulgen",
    "sg:orig_category":"Verwaltung von Immobilien Wirtschaftspr\u00fcfung, Steuerberatung U Treuhand",
    "sg:phone":"+41 61 483 09 09",
    "sg:postcode":"8583",
    "sg:province":"Thurgau",
    "wof:name":"Treu & Co",
    "wof:placetype":"venue"
},
  "geometry": {"coordinates":[7.5373158455,47.5525817871],"type":"Point"}
}