{
  "type": "Feature",
  "properties": {
    "iso:country":"CH",
    "sg:address":"Chemin Des Plant\u00e9es 3 1131 Tolochenaz Case Postale 80",
    "sg:city":"Tolochenaz",
    "sg:orig_category":"Grosshandel mit festen Brennstoffen U Mineral\u00f6lerzeugnissen Mineral\u00f6lverarbeitung",
    "sg:phone":"+41 21 803 06 49",
    "sg:postcode":"1131",
    "sg:province":"Vaud",
    "wof:name":"Solumat Sa",
    "wof:placetype":"venue"
},
  "geometry": {"coordinates":[6.4773159027,46.5083045959],"type":"Point"}
}