{
  "type": "Feature",
  "properties": {
    "iso:country":"CH",
    "sg:address":"Avenue Du Guintzet 8 1700 Fribourg Case Postale 50",
    "sg:city":"Fribourg",
    "sg:orig_category":"Elektro- and elektronische Maschinen Grosshandel Herstellung von sonstigen elektrischen Ausr\u00fcstungen",
    "sg:phone":"+41 26 424 44 56",
    "sg:postcode":"1703",
    "wof:name":"Wolf Electronic Sa",
    "wof:placetype":"venue"
},
  "geometry": {"coordinates":[7.1448478699,46.8042182922],"type":"Point"}
}