{
  "type": "Feature",
  "properties": {
    "addr:full":"Zentrumstrasse 16 H\u00e4gglingen Aargau 5607",
    "addr:housenumber":"16",
    "addr:postcode":"5607",
    "addr:street":"Zentrumstrasse",
    "iso:country":"CH",
    "sg:address":"Zentrumstrasse 16",
    "sg:city":"H\u00e4gglingen",
    "sg:classifiers":[
        {
            "category":"Shopping Center",
            "type":"Public Place"
        }
    ],
    "sg:phone":"+41 56 624 21 40",
    "sg:postcode":"5607",
    "sg:province":"Aargau",
    "sg:tags":[
        "aluminium",
        "casting"
    ],
    "wof:name":"Hubert Schmid Metall-giesserei",
    "wof:placetype":"venue"
},
  "geometry": {"coordinates":[8.251714,47.386745],"type":"Point"}
}