{
  "type": "Feature",
  "properties": {
    "iso:country":"CH",
    "sg:address":"Dorfstrasse 41",
    "sg:city":"Richterswil",
    "sg:orig_category":"Detailhandel mit Brillen U anderen Sehhilfen Fachdetailhandel in Verkaufsr\u00e4umen",
    "sg:phone":"+41 17845757",
    "sg:postcode":"8805",
    "sg:province":"Z\u00fcrich",
    "wof:name":"Koller Optik",
    "wof:placetype":"venue"
},
  "geometry": {"coordinates":[8.704895,47.207664],"type":"Point"}
}