{
  "type": "Feature",
  "properties": {
    "iso:country":"CH",
    "sg:address":"Rybr\u00fcggstrasse 1",
    "sg:city":"Frutigen",
    "sg:classifiers":[
        {
            "category":"Restaurant",
            "type":"Food & Drink"
        }
    ],
    "sg:phone":"+41 33 671 13 53",
    "sg:postcode":"3714",
    "sg:province":"Bern",
    "wof:name":"Restaurant Rybr\u00fcgg",
    "wof:placetype":"venue"
},
  "geometry": {"coordinates":[7.6535811424,46.5746154785],"type":"Point"}
}