{
  "type": "Feature",
  "properties": {
    "iso:country":"CH",
    "sg:address":"Hub 271 9492 Eschen. Postfach 163",
    "sg:city":"Eschen",
    "sg:orig_category":"Sanit\u00e4r U Heizungsinstallation Sanit\u00e4rinstallation",
    "sg:phone":"+41 75 373 37 36",
    "sg:postcode":"9492",
    "wof:name":"Oehri Ag Haustechnik Sanit\u00e4r Heizung & L\u00fcftung",
    "wof:placetype":"venue"
},
  "geometry": {"coordinates":[9.5301799774,47.209728241],"type":"Point"}
}