{
  "type": "Feature",
  "properties": {
    "iso:country":"CH",
    "sg:address":"Rue Des Murs 16",
    "sg:city":"Coppet",
    "sg:classifiers":[
        {
            "category":"Restaurant",
            "type":"Food & Drink"
        }
    ],
    "sg:phone":"+41 22 776 10 36",
    "sg:postcode":"1296",
    "sg:province":"Vaud",
    "wof:name":"Auberge Du Ch\u00e2teau",
    "wof:placetype":"venue"
},
  "geometry": {"coordinates":[6.191380024,46.3166694641],"type":"Point"}
}