{
  "type": "Feature",
  "properties": {
    "iso:country":"CH",
    "sg:address":"Morgartenstrasse 5 6003 Luzern. Postfach",
    "sg:city":"Luzern",
    "sg:orig_category":"Aktivit\u00e4t der Bankinstitute",
    "sg:phone":"+41 41 226 46 46",
    "sg:postcode":"6002",
    "sg:province":"Luzern",
    "wof:name":"Bank Coop Gesch\u00e4ftsstelle Luzern",
    "wof:placetype":"venue"
},
  "geometry": {"coordinates":[8.308199,47.049236],"type":"Point"}
}