{
  "type": "Feature",
  "properties": {
    "iso:country":"CH",
    "sg:address":"Grabenstrasse 5",
    "sg:city":"Riggisberg",
    "sg:orig_category":"Detailhandel mit elektrischen Haushalts, Radio U Fernsehger\u00e4ten ohne ausgepr\u00e4gten Schwerpunkt Elektr",
    "sg:phone":"+41 31 809 18 18",
    "sg:postcode":"3132",
    "sg:province":"Bern",
    "wof:name":"Elektrohus Riggisberg Ag",
    "wof:placetype":"venue"
},
  "geometry": {"coordinates":[7.4792637825,46.8104057312],"type":"Point"}
}