{
  "type": "Feature",
  "properties": {
    "iso:country":"CH",
    "sg:address":"8133",
    "sg:city":"Esslingen",
    "sg:orig_category":"Sportvereine Sch\u00fctzen",
    "sg:phone":"+41 17000770",
    "sg:postcode":"8133",
    "sg:province":"Z\u00fcrich",
    "wof:name":"Feldsch\u00fctzenverein",
    "wof:placetype":"venue"
},
  "geometry": {"coordinates":[8.4601297379,47.3635101318],"type":"Point"}
}