{
  "type": "Feature",
  "properties": {
    "iso:country":"CH",
    "sg:address":"St. Gallerstrasse 26a",
    "sg:city":"M\u00f6rschwil",
    "sg:orig_category":"Herstellung von Duft U K\u00f6rperpflegemitteln",
    "sg:phone":"+41 71 866 21 69",
    "sg:postcode":"9402",
    "sg:province":"St. Gallen",
    "wof:name":"Bz Collection Zanga",
    "wof:placetype":"venue"
},
  "geometry": {"coordinates":[9.4200963974,47.4660224915],"type":"Point"}
}