{
  "type": "Feature",
  "properties": {
    "addr:full":"Albisstrasse 71 Z\u00fcrich Z\u00fcrich 8038",
    "addr:housenumber":"71",
    "addr:postcode":"8038",
    "addr:street":"Albisstrasse",
    "iso:country":"CH",
    "sg:address":"Albisstrasse 71",
    "sg:city":"Z\u00fcrich",
    "sg:orig_category":"Betrieb U technische Hilfsdienste des Kultur U Unterhaltungswesens Sonstige Hilfsdienste des Kultur ",
    "sg:phone":"+41 14828011",
    "sg:postcode":"8038",
    "sg:province":"Z\u00fcrich",
    "wof:name":"Sos Recording, Schilling T.",
    "wof:placetype":"venue"
},
  "geometry": {"coordinates":[8.530795,47.341648],"type":"Point"}
}