{
  "type": "Feature",
  "properties": {
    "addr:full":"Ronchini Aurigeno Ticino 6677",
    "addr:postcode":"6677",
    "iso:country":"CH",
    "sg:address":"Ronchini",
    "sg:city":"Aurigeno",
    "sg:orig_category":"Bauspenglerei Sanit\u00e4rinstallation",
    "sg:phone":"+41 91 753 16 54",
    "sg:postcode":"6677",
    "sg:province":"Ticino",
    "wof:name":"Ivo Caprari Imp.sanitari & Lattoniere",
    "wof:placetype":"venue"
},
  "geometry": {"coordinates":[8.7122,46.231056],"type":"Point"}
}