{
  "type": "Feature",
  "properties": {
    "addr:full":"Bahnstrasse 14 Rickenbach-attikon Z\u00fcrich 8544",
    "addr:housenumber":"14",
    "addr:postcode":"8544",
    "addr:street":"Bahnstrasse;Zuerich",
    "iso:country":"CH",
    "sg:address":"Bahnstrasse 14",
    "sg:city":"Rickenbach-attikon",
    "sg:classifiers":[
        {
            "category":"Manufacturing",
            "subcategory":"Wood Products",
            "type":"Manufacturing & Wholesale Goods"
        }
    ],
    "sg:phone":"+41 52 320 99 11",
    "sg:postcode":"8544",
    "sg:province":"Z\u00fcrich",
    "sg:tags":[
        "case"
    ],
    "wof:name":"Wegm\u00fcller Ag",
    "wof:placetype":"venue"
},
  "geometry": {"coordinates":[8.796525,47.536209],"type":"Point"}
}