{
  "type": "Feature",
  "properties": {
    "iso:country":"CH",
    "sg:address":"Bastions Cours Des 6 1201 Gen\u00e8ve. Postfach",
    "sg:city":"Gen\u00e8ve",
    "sg:orig_category":"Architektur U Ingenieurb\u00fcros",
    "sg:postcode":"1205",
    "sg:province":"Gen\u00e8ve",
    "wof:name":"Geneva Technology Innovation Center Disposition De Locaux Et De Services \u00e0 Toute Soci\u00e9t\u00e9 Active Dans Le D\u00e9velopp. De Technologies Innovantes Etc",
    "wof:placetype":"venue"
},
  "geometry": {"coordinates":[6.142701,46.208359],"type":"Point"}
}