{
  "type": "Feature",
  "properties": {
    "iso:country":"CH",
    "sg:address":"Rue D'octodure 10b",
    "sg:city":"Martigny",
    "sg:orig_category":"Organisationen des Gesundheitswesen",
    "sg:phone":"+41 32 466 59 41",
    "sg:postcode":"1920",
    "sg:province":"Valais",
    "wof:name":"Service R\u00e9g.d'aide & De Soins \u00e0 Domicile Ajoie-centre",
    "wof:placetype":"venue"
},
  "geometry": {"coordinates":[7.0716500282,47.4152297974],"type":"Point"}
}