{
  "type": "Feature",
  "properties": {
    "iso:country":"CH",
    "sg:address":"1987",
    "sg:city":"H\u00e9r\u00e9mence",
    "sg:orig_category":"Instandhaltung U Reparatur von Automobilen",
    "sg:phone":"+41 79 425 04 76",
    "sg:postcode":"1987",
    "sg:province":"Valais",
    "wof:name":"Jeanneret Fran\u00e7ois, Garage Eyra",
    "wof:placetype":"venue"
},
  "geometry": {"coordinates":[6.7595500946,47.0636444092],"type":"Point"}
}