{
  "type": "Feature",
  "properties": {
    "iso:country":"CH",
    "sg:address":"Neuhofstrasse 4 6340 Baar. Postfach",
    "sg:city":"Baar",
    "sg:orig_category":"Unclassifiable Establishments",
    "sg:phone":"+41 41 728 73 73",
    "sg:postcode":"6340",
    "sg:province":"Zug",
    "wof:name":"Immago-rent Ag Hoteleinrichtungen, -ausstattungen, -installationen Usw.; Vermietung",
    "wof:placetype":"venue"
},
  "geometry": {"coordinates":[8.5136909485,47.1903457642],"type":"Point"}
}