{
  "type": "Feature",
  "properties": {
    "iso:country":"CH",
    "sg:address":"Hofackerstrasse 3a",
    "sg:city":"Muttenz",
    "sg:orig_category":"Pensionskassen",
    "sg:phone":"+41 61 311 80 28",
    "sg:postcode":"4132",
    "sg:province":"Basel-Landschaft",
    "wof:name":"Personalvorsorgestiftung Der Mabesa Gruppe",
    "wof:placetype":"venue"
},
  "geometry": {"coordinates":[7.6469759941,47.5329208374],"type":"Point"}
}