{
  "type": "Feature",
  "properties": {
    "iso:country":"CH",
    "sg:address":"9042",
    "sg:city":"Speicher",
    "sg:orig_category":"Organisationen des Gesundheitswesen",
    "sg:postcode":"9042",
    "sg:province":"Appenzell Ausserrhoden",
    "wof:name":"Samariterverein Speicher",
    "wof:placetype":"venue"
},
  "geometry": {"coordinates":[9.4437513351,47.4104042053],"type":"Point"}
}