{
  "type": "Feature",
  "properties": {
    "iso:country":"CH",
    "sg:address":"Vonmattstrasse 44",
    "sg:city":"Luzern",
    "sg:orig_category":"Sonstiger Grosshandel",
    "sg:postcode":"6003",
    "sg:province":"Luzern",
    "wof:name":"Pan-ic Distribution Rosa Salmon De La Jara-wipfli",
    "wof:placetype":"venue"
},
  "geometry": {"coordinates":[8.30057621,47.0464897156],"type":"Point"}
}