{
  "type": "Feature",
  "properties": {
    "iso:country":"CH",
    "sg:address":"Riva Albertolli 5",
    "sg:city":"Lugano",
    "sg:classifiers":[
        {
            "category":"Restaurant",
            "type":"Food & Drink"
        }
    ],
    "sg:phone":"+41 91 921 40 77",
    "sg:postcode":"6900",
    "sg:province":"Ticino",
    "wof:name":"Ristorante Ars Caf\u00e9",
    "wof:placetype":"venue"
},
  "geometry": {"coordinates":[8.9541244507,46.0037689209],"type":"Point"}
}