{
  "type": "Feature",
  "properties": {
    "iso:country":"CH",
    "sg:address":"Malerne 1965 Chandolin-savi\u00e8se. Postfach",
    "sg:city":"Chandolin-savi\u00e8se",
    "sg:orig_category":"Sanit\u00e4r, Heizungs U L\u00fcftungsinstallation",
    "sg:phone":"+41 27 395 41 04",
    "sg:postcode":"1965",
    "sg:province":"Valais",
    "wof:name":"H\u00e9ritier Claude-alain Chauffage, Sanitaire, Ventilation, Climatisation; Installation Etc",
    "wof:placetype":"venue"
},
  "geometry": {"coordinates":[7.3348011971,46.2544631958],"type":"Point"}
}