{
  "type": "Feature",
  "properties": {
    "iso:country":"CH",
    "sg:address":"Schulstrasse 4",
    "sg:city":"Tuggen",
    "sg:orig_category":"Primarschulen",
    "sg:phone":"+41 55 445 16 74",
    "sg:postcode":"8856",
    "sg:province":"Schwyz",
    "wof:name":"Primarschule Eneda",
    "wof:placetype":"venue"
},
  "geometry": {"coordinates":[8.9455022812,47.2019348145],"type":"Point"}
}