{
  "type": "Feature",
  "properties": {
    "iso:country":"CH",
    "sg:address":"Route De Collombey 99 Bis",
    "sg:city":"Monthey",
    "sg:orig_category":"G\u00fcterbef\u00f6rderung im Strassenverkehr",
    "sg:postcode":"1870",
    "sg:province":"Valais",
    "wof:name":"Granger Pierre-marie",
    "wof:placetype":"venue"
},
  "geometry": {"coordinates":[6.9456782341,46.2637062073],"type":"Point"}
}