{
  "type": "Feature",
  "properties": {
    "iso:country":"CH",
    "sg:address":"Sch\u00fcrmattstrasse 2a",
    "sg:city":"H\u00fcnenberg",
    "sg:orig_category":"Gartenbau",
    "sg:phone":"+41 52 355 20 20",
    "sg:postcode":"6331",
    "sg:province":"Zug",
    "wof:name":"Lamprecht Pflanzen Ag G\u00e4rtnerei",
    "wof:placetype":"venue"
},
  "geometry": {"coordinates":[8.7239246368,47.4074707031],"type":"Point"}
}