{
  "type": "Feature",
  "properties": {
    "iso:country":"CH",
    "sg:address":"Poststrasse 2",
    "sg:city":"Winterthur",
    "sg:orig_category":"Softwareentwicklung U beratung Sonstige mit der Informatik verbundene T\u00e4tigkeiten",
    "sg:phone":"+41 18655055",
    "sg:postcode":"8406",
    "sg:province":"Z\u00fcrich",
    "wof:name":"Webstyling Gmbh",
    "wof:placetype":"venue"
},
  "geometry": {"coordinates":[8.7057561874,47.4903831482],"type":"Point"}
}