{
  "type": "Feature",
  "properties": {
    "iso:country":"CH",
    "sg:address":"Br\u00fcckenweg 6",
    "sg:city":"Visp",
    "sg:orig_category":"Gesundheitswesen",
    "sg:phone":"+41 27 946 11 45",
    "sg:postcode":"3930",
    "sg:province":"Valais",
    "wof:name":"Stoffel Anita, Gesundheitsvorsorge",
    "wof:placetype":"venue"
},
  "geometry": {"coordinates":[7.8800721169,46.2930450439],"type":"Point"}
}