{
  "type": "Feature",
  "properties": {
    "iso:country":"CH",
    "sg:address":"Lyss-strasse 51",
    "sg:city":"Nidau",
    "sg:orig_category":"Hoch U Tiefbau",
    "sg:phone":"+41 32 365 83 42",
    "sg:postcode":"2560",
    "sg:province":"Bern",
    "wof:name":"Rudolf Friedli Baugesch\u00e4ft",
    "wof:placetype":"venue"
},
  "geometry": {"coordinates":[7.248032093,47.1254806519],"type":"Point"}
}