{
  "type": "Feature",
  "properties": {
    "iso:country":"CH",
    "sg:address":"Repfergasse 15",
    "sg:city":"Schaffhausen",
    "sg:orig_category":"W\u00e4schereien",
    "sg:phone":"+41 52 625 88 80",
    "sg:postcode":"8200",
    "sg:province":"Schaffhausen",
    "wof:name":"Kundenw\u00e4scherei Silvia Silvia Schrag",
    "wof:placetype":"venue"
},
  "geometry": {"coordinates":[8.635974884,47.6977233887],"type":"Point"}
}