{
  "type": "Feature",
  "properties": {
    "iso:country":"CH",
    "sg:address":"Schulstrasse 13",
    "sg:city":"Schlieren",
    "sg:orig_category":"Detailhandel mit Brot, Back U S\u00fcsswaren",
    "sg:phone":"+41 17301060",
    "sg:postcode":"8952",
    "sg:province":"Z\u00fcrich",
    "wof:name":"Max Epple B\u00e4ckerei-konditorei",
    "wof:placetype":"venue"
},
  "geometry": {"coordinates":[8.451164,47.396957],"type":"Point"}
}