{
  "type": "Feature",
  "properties": {
    "iso:country":"CH",
    "sg:address":"Gesellschaftsstrasse 6 3012 Bern. Postfach",
    "sg:city":"Bern",
    "sg:orig_category":"Interessenvertretungen",
    "sg:postcode":"3005",
    "sg:province":"Bern",
    "wof:name":"Karl Und Hanna Uelliger Stiftung",
    "wof:placetype":"venue"
},
  "geometry": {"coordinates":[9.3895149231,47.4160308838],"type":"Point"}
}