{
  "type": "Feature",
  "properties": {
    "iso:country":"CH",
    "sg:address":"Langs\u00e4gestrasse 7",
    "sg:city":"Kriens",
    "sg:orig_category":"Autogaragen Instandhaltung U Reparatur von Automobilen",
    "sg:phone":"+41 41 310 65 43",
    "sg:postcode":"6010",
    "sg:province":"Luzern",
    "wof:name":"Ibh Garage Gmbh",
    "wof:placetype":"venue"
},
  "geometry": {"coordinates":[8.29222,47.037521],"type":"Point"}
}