{
  "type": "Feature",
  "properties": {
    "iso:country":"CH",
    "sg:address":"3963",
    "sg:city":"Crans-sur-sierre",
    "sg:classifiers":[
        {
            "category":"Insurance",
            "subcategory":"Insurance Agent",
            "type":"Services"
        }
    ],
    "sg:phone":"+41 27 481 92 92",
    "sg:postcode":"3963",
    "sg:province":"Valais",
    "sg:tags":[
        "versicherungsagenturen",
        "-broker"
    ],
    "wof:name":"Winterthur-assurances Agence Gaston Barras",
    "wof:placetype":"venue"
},
  "geometry": {"coordinates":[7.4617700577,46.3076210022],"type":"Point"}
}