{
  "type": "Feature",
  "properties": {
    "iso:country":"CH",
    "sg:address":"1545",
    "sg:city":"Chevroux",
    "sg:orig_category":"Sportvereine Sch\u00fctzen",
    "sg:phone":"+41 26 667 23 63",
    "sg:postcode":"1545",
    "sg:province":"Vaud",
    "wof:name":"St\u00e9 De Tir Jeune Helv\u00e9tie",
    "wof:placetype":"venue"
},
  "geometry": {"coordinates":[6.9055051804,46.8907432556],"type":"Point"}
}