{
  "type": "Feature",
  "properties": {
    "iso:country":"CH",
    "sg:address":"Kestenholzerstrasse 19",
    "sg:city":"Wolfwil",
    "sg:orig_category":"Oberfl\u00e4chenveredlung U W\u00e4rmebehandlung",
    "sg:postcode":"4628",
    "sg:province":"Solothurn",
    "wof:name":"Ackermann Oberfl\u00e4chen",
    "wof:placetype":"venue"
},
  "geometry": {"coordinates":[7.7911877632,47.2691001892],"type":"Point"}
}