{
  "type": "Feature",
  "properties": {
    "iso:country":"CH",
    "sg:address":"Verbier 1936 Verbier. Postfach",
    "sg:city":"Verbier",
    "sg:orig_category":"RESTAURANTS: TEA-ROOMS",
    "sg:postcode":"1936",
    "sg:province":"Valais",
    "wof:name":"Le Forum D\u00e9runs Et Stauffer Caf\u00e9 Le Forum",
    "wof:placetype":"venue"
},
  "geometry": {"coordinates":[6.8288140297,47.1026878357],"type":"Point"}
}