{
  "type": "Feature",
  "properties": {
    "iso:country":"CH",
    "sg:address":"Hansmatt 30",
    "sg:city":"Stans",
    "sg:orig_category":"Herstellung von Maschinen f\u00fcr die Nahrungsmittel, Getr\u00e4nkeherstellung U die Tabakverarbeitung",
    "sg:postcode":"6370",
    "sg:province":"Nidwalden",
    "wof:name":"Drytec Ag",
    "wof:placetype":"venue"
},
  "geometry": {"coordinates":[8.3517436981,46.9677658081],"type":"Point"}
}