{
  "type": "Feature",
  "properties": {
    "iso:country":"CH",
    "sg:address":"Talweg 1",
    "sg:city":"Grellingen",
    "sg:orig_category":"Herstellung von keramischen Wand U Bodenfliesen U platten",
    "sg:postcode":"4203",
    "sg:province":"Basel-Landschaft",
    "wof:name":"Mosimann Peter, Keramische Wand Und Bodenbel\u00e4ge",
    "wof:placetype":"venue"
},
  "geometry": {"coordinates":[7.5920758247,47.4403762817],"type":"Point"}
}