{
  "type": "Feature",
  "properties": {
    "iso:country":"CH",
    "sg:address":"Hauptstrasse",
    "sg:city":"Summaprada",
    "sg:orig_category":"Detailhandel mit Radio U Fernsehger\u00e4ten Detailhandel mit elektrischen Haushalts-,Radio U Fernsehger\u00e4",
    "sg:phone":"+41 81 651 27 05",
    "sg:postcode":"7421",
    "sg:province":"Graubunden",
    "wof:name":"Audio-& Video-service S.parg\u00e4tzi",
    "wof:placetype":"venue"
},
  "geometry": {"coordinates":[9.4346675873,46.7130622864],"type":"Point"}
}