{
  "type": "Feature",
  "properties": {
    "iso:country":"CH",
    "sg:address":"Brunaustrasse 21",
    "sg:city":"Z\u00fcrich",
    "sg:orig_category":"Finanzierungsinstitutionen",
    "sg:postcode":"8002",
    "sg:province":"Z\u00fcrich",
    "wof:name":"Bruno Consulting",
    "wof:placetype":"venue"
},
  "geometry": {"coordinates":[7.5622549057,47.5154075623],"type":"Point"}
}