{
  "type": "Feature",
  "properties": {
    "iso:country":"CH",
    "sg:address":"Schleifetobelweg 1",
    "sg:city":"Horgen",
    "sg:orig_category":"Softwareentwicklung U beratung",
    "sg:postcode":"8810",
    "sg:province":"Z\u00fcrich",
    "wof:name":"Concepts Information Management Systems Marco Gertsch",
    "wof:placetype":"venue"
},
  "geometry": {"coordinates":[8.5971260071,47.2575721741],"type":"Point"}
}