{
  "type": "Feature",
  "properties": {
    "addr:full":"L\u00e4nggasse 1b Thun Bern 3600",
    "addr:housenumber":"1b",
    "addr:postcode":"3600",
    "addr:street":"Laenggasse;Bern",
    "iso:country":"CH",
    "sg:address":"L\u00e4nggasse 1b",
    "sg:city":"Thun",
    "sg:orig_category":"Arztpraxen",
    "sg:phone":"+41 33 222 20 21",
    "sg:postcode":"3600",
    "sg:province":"Bern",
    "wof:name":"Dr.med.rudolf Christen Spezialarzt Fmh",
    "wof:placetype":"venue"
},
  "geometry": {"coordinates":[7.626992,46.754684],"type":"Point"}
}