{
  "type": "Feature",
  "properties": {
    "iso:country":"CH",
    "sg:address":"Falkenblickstrasse 9",
    "sg:city":"Eichberg",
    "sg:orig_category":"Sportvereine Alpinismus",
    "sg:phone":"+41 71 750 02 22",
    "sg:postcode":"9453",
    "sg:province":"St. Gallen",
    "wof:name":"Sac Sektion Rhein",
    "wof:placetype":"venue"
},
  "geometry": {"coordinates":[9.5272445679,47.343662262],"type":"Point"}
}