{
  "type": "Feature",
  "properties": {
    "addr:full":"Oberg\u00fctschrain 2 Luzern Luzern 6003",
    "addr:housenumber":"2",
    "addr:postcode":"6003",
    "addr:street":"Oberguetschrain",
    "iso:country":"CH",
    "sg:address":"Oberg\u00fctschrain 2",
    "sg:city":"Luzern",
    "sg:orig_category":"Aktivit\u00e4ten der Generalunternehmen im Baugewerbe Baugewerbe",
    "sg:phone":"+41 71 228 60 00",
    "sg:postcode":"6003",
    "sg:province":"Luzern",
    "wof:name":"Mobag Ag",
    "wof:placetype":"venue"
},
  "geometry": {"coordinates":[9.374541,47.42569],"type":"Point"}
}