{
  "type": "Feature",
  "properties": {
    "iso:country":"CH",
    "sg:address":"Waisenhausplatz 25",
    "sg:city":"Bern",
    "sg:classifiers":[
        {
            "category":"Banks & Credit Unions",
            "subcategory":"Bank",
            "type":"Services"
        }
    ],
    "sg:postcode":"3001",
    "sg:province":"Bern",
    "wof:name":"Abz-finanz-und Beteiligungsgesellschaft Ag",
    "wof:placetype":"venue"
},
  "geometry": {"coordinates":[8.51621,47.171501],"type":"Point"}
}