{
  "type": "Feature",
  "properties": {
    "iso:country":"CH",
    "sg:address":"5064",
    "sg:city":"Wittnau",
    "sg:orig_category":"Organisationen des Gesundheitswesen",
    "sg:phone":"+41 56 622 58 43",
    "sg:postcode":"5064",
    "sg:province":"Aargau",
    "wof:name":"Samariterverein Wohlen",
    "wof:placetype":"venue"
},
  "geometry": {"coordinates":[8.2791404724,47.3595924377],"type":"Point"}
}