{
  "type": "Feature",
  "properties": {
    "iso:country":"CH",
    "sg:address":"Holzwiesweg 19",
    "sg:city":"Z\u00fcrich",
    "sg:orig_category":"Reiseb\u00fcros U Reiseveranstalter",
    "sg:postcode":"8047",
    "sg:province":"Z\u00fcrich",
    "wof:name":"Huber Markus Consulting & Services",
    "wof:placetype":"venue"
},
  "geometry": {"coordinates":[8.4967660904,47.3771934509],"type":"Point"}
}