{
  "type": "Feature",
  "properties": {
    "iso:country":"CH",
    "sg:address":"Holzr\u00fcti 2 8840 Einsiedeln. Postfach",
    "sg:city":"Einsiedeln",
    "sg:classifiers":[
        {
            "category":"Professional",
            "subcategory":"Employment Agencies",
            "type":"Services"
        }
    ],
    "sg:postcode":"8840",
    "sg:province":"Schwyz",
    "sg:tags":[
        "personal",
        "u",
        "stellenvermittlung"
    ],
    "wof:name":"Abegg + Tonazzi Ag",
    "wof:placetype":"venue"
},
  "geometry": {"coordinates":[8.7507076263,47.1429405212],"type":"Point"}
}