{
  "type": "Feature",
  "properties": {
    "iso:country":"CH",
    "sg:address":"Oberdorfstrasse 16 5502 Hunzenschwil. Postfach",
    "sg:city":"Hunzenschwil",
    "sg:classifiers":[
        {
            "category":"Manufacturing",
            "subcategory":"Metals",
            "type":"Manufacturing & Wholesale Goods"
        }
    ],
    "sg:phone":"+41 62 897 24 40",
    "sg:postcode":"5502",
    "sg:province":"Aargau",
    "sg:tags":[
        "u",
        "leichtmetallbau",
        "stahl"
    ],
    "wof:name":"H\u00e4fliger Philipp Metall- & Stahlbau Metall Und Stahlbau. Schlosserarbeiten Usw",
    "wof:placetype":"venue"
},
  "geometry": {"coordinates":[8.1185150146,47.3800201416],"type":"Point"}
}