{
  "type": "Feature",
  "properties": {
    "iso:country":"CH",
    "sg:address":"Brugghof 7.",
    "sg:city":"Niederurnen",
    "sg:orig_category":"W\u00e4scherei U chemische Reinigung",
    "sg:postcode":"8867",
    "sg:province":"Glarus",
    "wof:name":"Textilreinigung, Keller Hans",
    "wof:placetype":"venue"
},
  "geometry": {"coordinates":[9.0582857132,47.130317688],"type":"Point"}
}