{
  "type": "Feature",
  "properties": {
    "addr:full":"1532 F\u00e9tigny Fribourg 1532",
    "addr:housenumber":"1532",
    "addr:postcode":"1532",
    "addr:street":"Fe\u0301Tigny Fribourg",
    "iso:country":"CH",
    "sg:address":"1532",
    "sg:city":"F\u00e9tigny",
    "sg:classifiers":[
        {
            "category":"Education",
            "subcategory":"Library",
            "type":"Public Place"
        }
    ],
    "sg:postcode":"1532",
    "sg:province":"Fribourg",
    "sg:tags":[
        "u",
        "bibliotheken",
        "archive"
    ],
    "wof:name":"Biblioth\u00e8que Paroissiale Catholique",
    "wof:placetype":"venue"
},
  "geometry": {"coordinates":[6.91368,46.794571],"type":"Point"}
}