{
  "type": "Feature",
  "properties": {
    "iso:country":"CH",
    "sg:address":"1681",
    "sg:city":"Billens",
    "sg:orig_category":"Organisationen des Gesundheitswesen",
    "sg:phone":"+41 26 422 54 60",
    "sg:postcode":"1681",
    "sg:province":"Fribourg",
    "wof:name":"Soins \u00e0 Domicile",
    "wof:placetype":"venue"
},
  "geometry": {"coordinates":[7.1378288269,46.8038368225],"type":"Point"}
}