{
  "type": "Feature",
  "properties": {
    "iso:country":"CH",
    "sg:address":"Letzistrasse 2 5213 Villnachern. Postfach",
    "sg:city":"Villnachern",
    "sg:orig_category":"Grosshandel mit sonstigen Maschinen U Ausr\u00fcstungen f\u00fcr Industrie, Handel U Schiffahrt",
    "sg:postcode":"5213",
    "sg:province":"Aargau",
    "wof:name":"Fertech Ag",
    "wof:placetype":"venue"
},
  "geometry": {"coordinates":[8.1595840454,47.4706192017],"type":"Point"}
}