{
  "type": "Feature",
  "properties": {
    "iso:country":"CH",
    "sg:address":"Hohle Gasse 2",
    "sg:city":"Uster",
    "sg:orig_category":"Fachdetailhandel in Verkaufsr\u00e4umen",
    "sg:phone":"+41 19415588",
    "sg:postcode":"8610",
    "sg:province":"Z\u00fcrich",
    "wof:name":"Flor - Art Gueti Idee Gmbh",
    "wof:placetype":"venue"
},
  "geometry": {"coordinates":[8.6995697021,47.3481712341],"type":"Point"}
}