{
  "type": "Feature",
  "properties": {
    "iso:country":"CH",
    "sg:address":"Route De La Mine",
    "sg:city":"Gr\u00f4ne",
    "sg:orig_category":"Bauschreinerei Herstellung von Konstruktionsteilen, Fertigbauteilen U Ausbauelementen aus Holz",
    "sg:phone":"+41 27 458 17 29",
    "sg:postcode":"3979",
    "sg:province":"Valais",
    "wof:name":"Vuigner Jo\u00ebl",
    "wof:placetype":"venue"
},
  "geometry": {"coordinates":[7.469735,46.255539],"type":"Point"}
}