{
  "type": "Feature",
  "properties": {
    "addr:full":"Portstrasse 20 2500 Biel/bienne. Postfach Biel/bienne Bern 2502",
    "addr:housenumber":"20",
    "addr:postcode":"2500;postfach;2502",
    "addr:street":"Portstrasse",
    "iso:country":"CH",
    "sg:address":"Portstrasse 20 2500 Biel/bienne. Postfach",
    "sg:city":"Biel/bienne",
    "sg:orig_category":"Architektur U Ingenieurb\u00fcros",
    "sg:postcode":"2502",
    "sg:province":"Bern",
    "wof:name":"Kaestli Ren\u00e9 Architekturbureau - Generalbau Gmbh",
    "wof:placetype":"venue"
},
  "geometry": {"coordinates":[7.258829,47.126144],"type":"Point"}
}