{
  "type": "Feature",
  "properties": {
    "iso:country":"CH",
    "sg:address":"Portstrasse 20 2500 Biel/bienne. Postfach",
    "sg:city":"Biel/bienne",
    "sg:orig_category":"Architektur U Ingenieurb\u00fcros",
    "sg:postcode":"2502",
    "sg:province":"Bern",
    "wof:name":"Kaestli Ren\u00e9 Architekturbureau - Generalbau Gmbh",
    "wof:placetype":"venue"
},
  "geometry": {"coordinates":[7.258829,47.126144],"type":"Point"}
}