{
  "type": "Feature",
  "properties": {
    "iso:country":"CH",
    "sg:address":"Fahrnstrasse 24",
    "sg:city":"M\u00f6rschwil",
    "sg:orig_category":"Fahrschulen, Flugschulen",
    "sg:phone":"+41 79 629 29 89",
    "sg:postcode":"9402",
    "sg:province":"St. Gallen",
    "wof:name":"Elmar Weibel Autofahrschule",
    "wof:placetype":"venue"
},
  "geometry": {"coordinates":[9.4307441711,47.4643211365],"type":"Point"}
}