{
  "type": "Feature",
  "properties": {
    "addr:full":"Sonnhaldenstrasse 11 Wilen Thurgau 9535",
    "addr:housenumber":"11",
    "addr:postcode":"9535",
    "addr:street":"Sonnhaldenstrasse",
    "iso:country":"CH",
    "sg:address":"Sonnhaldenstrasse 11",
    "sg:city":"Wilen",
    "sg:classifiers":[
        {
            "category":"Government",
            "subcategory":"Post Office",
            "type":"Public Place"
        }
    ],
    "sg:phone":"+41 71 923 43 89",
    "sg:postcode":"9535",
    "sg:province":"Thurgau",
    "sg:tags":[
        "blade",
        "saw",
        "circular"
    ],
    "wof:name":"Sumag S\u00e4gen Ag",
    "wof:placetype":"venue"
},
  "geometry": {"coordinates":[9.031385,47.450966],"type":"Point"}
}