{
  "type": "Feature",
  "properties": {
    "iso:country":"CH",
    "sg:address":"Hintermattstrasse 11",
    "sg:city":"Ziefen",
    "sg:orig_category":"Gartenbau Gem\u00fcsebau",
    "sg:phone":"+41 61 931 15 90",
    "sg:postcode":"4417",
    "sg:province":"Basel-Landschaft",
    "wof:name":"Baumgartner G\u00e4rtnerei Ag",
    "wof:placetype":"venue"
},
  "geometry": {"coordinates":[7.7017998695,47.4313278198],"type":"Point"}
}