{
  "type": "Feature",
  "properties": {
    "iso:country":"CH",
    "sg:address":"Coll\u00e8ge Du Sud",
    "sg:city":"Bulle",
    "sg:orig_category":"Non-Classified Establishments",
    "sg:postcode":"1630",
    "sg:province":"Fribourg",
    "wof:name":"Fondation Mon Petit Bonheur",
    "wof:placetype":"venue"
},
  "geometry": {"coordinates":[5.1808700562,45.8973388672],"type":"Point"}
}