{
  "type": "Feature",
  "properties": {
    "iso:country":"CH",
    "sg:address":"Kunimattstrasse 10",
    "sg:city":"Pratteln",
    "sg:orig_category":"Vermietung U Verpachtung von eigenen Immobilien",
    "sg:postcode":"4133",
    "sg:province":"Basel-Landschaft",
    "wof:name":"Cosi Compagnie De Services Immobiliers",
    "wof:placetype":"venue"
},
  "geometry": {"coordinates":[6.1399998665,46.1868400574],"type":"Point"}
}