{
  "type": "Feature",
  "properties": {
    "iso:country":"CH",
    "sg:address":"Eigenstr. 1033",
    "sg:city":"Hallau",
    "sg:orig_category":"Grosshandel mit Getr\u00e4nken",
    "sg:phone":"+41 52 681 20 12",
    "sg:postcode":"8215",
    "sg:province":"Schaffhausen",
    "wof:name":"Kurt Gasser Weinkellerei",
    "wof:placetype":"venue"
},
  "geometry": {"coordinates":[8.4639186859,47.6972045898],"type":"Point"}
}