{
  "type": "Feature",
  "properties": {
    "iso:country":"CH",
    "sg:address":"Nordstrasse 1 8000 Z\u00fcrich. Postfach",
    "sg:city":"Z\u00fcrich",
    "sg:orig_category":"Vermietung U Verpachtung von eigenen Immobilien",
    "sg:postcode":"8001",
    "sg:province":"Z\u00fcrich",
    "wof:name":"Brantschen Eve Marie Bau Und Immobilien Treuhand",
    "wof:placetype":"venue"
},
  "geometry": {"coordinates":[8.5403432846,47.3836402893],"type":"Point"}
}