{
  "type": "Feature",
  "properties": {
    "addr:full":"Eichbergstrasse 87 Egliswil Aargau 5704",
    "addr:housenumber":"87",
    "addr:postcode":"5704",
    "addr:street":"Eichbergstrasse",
    "iso:country":"CH",
    "sg:address":"Eichbergstrasse 87",
    "sg:city":"Egliswil",
    "sg:classifiers":[
        {
            "category":"Organizations",
            "subcategory":"Labor Organization",
            "type":"Services"
        }
    ],
    "sg:phone":"+41 62 775 49 09",
    "sg:postcode":"5704",
    "sg:province":"Aargau",
    "sg:tags":[
        "work",
        "assembling",
        "assembly",
        "contract"
    ],
    "wof:name":"Ulrich Holliger Montagen",
    "wof:placetype":"venue"
},
  "geometry": {"coordinates":[8.19503,47.345879],"type":"Point"}
}