{
  "type": "Feature",
  "properties": {
    "iso:country":"CH",
    "sg:address":"Museggstrasse 32",
    "sg:city":"Luzern",
    "sg:orig_category":"Architekturb\u00fcros",
    "sg:phone":"+41 41 410 42 64",
    "sg:postcode":"6004",
    "sg:province":"Luzern",
    "wof:name":"Andy Raeber Architekturb\u00fcro",
    "wof:placetype":"venue"
},
  "geometry": {"coordinates":[8.304172,47.053841],"type":"Point"}
}