{
  "type": "Feature",
  "properties": {
    "addr:full":"Waldgasse 19 Herzogenbuchsee Bern 3360",
    "addr:housenumber":"19",
    "addr:postcode":"3360",
    "addr:street":"Waldgasse;Bern",
    "iso:country":"CH",
    "sg:address":"Waldgasse 19",
    "sg:city":"Herzogenbuchsee",
    "sg:classifiers":[
        {
            "category":"Manufacturing",
            "subcategory":"Tools & Machinery",
            "type":"Manufacturing & Wholesale Goods"
        }
    ],
    "sg:phone":"+41 62 956 55 55",
    "sg:postcode":"3360",
    "sg:province":"Bern",
    "sg:tags":[
        "part",
        "turned",
        "cnc"
    ],
    "wof:name":"Duap Ag",
    "wof:placetype":"venue"
},
  "geometry": {"coordinates":[7.707879,47.194717],"type":"Point"}
}