{
  "type": "Feature",
  "properties": {
    "iso:country":"CH",
    "sg:address":"S\u00fcdringstrasse 2",
    "sg:city":"Oensingen",
    "sg:classifiers":[
        {
            "category":"Transit Center",
            "subcategory":"Passenger",
            "type":"Transportation"
        }
    ],
    "sg:phone":"+41 62 388 03 30",
    "sg:postcode":"4702",
    "sg:province":"Solothurn",
    "sg:tags":[
        "rolling",
        "industry",
        "door",
        "doors",
        "sectional"
    ],
    "wof:name":"Crawford Hafa Ag",
    "wof:placetype":"venue"
},
  "geometry": {"coordinates":[7.71961689,47.280166626],"type":"Point"}
}