{
  "type": "Feature",
  "properties": {
    "addr:full":"Rue Bellefontaine 2 Lausanne Vaud 1003",
    "addr:housenumber":"2",
    "addr:postcode":"1003",
    "addr:street":"Rue Bellefontaine",
    "iso:country":"CH",
    "sg:address":"Rue Bellefontaine 2",
    "sg:city":"Lausanne",
    "sg:classifiers":[
        {
            "category":"Professional",
            "subcategory":"Advertising",
            "type":"Services"
        }
    ],
    "sg:phone":"+41 21 341 71 71",
    "sg:postcode":"1003",
    "sg:province":"Vaud",
    "sg:tags":[
        "communication",
        "medium"
    ],
    "wof:name":"Interannonces Sa",
    "wof:placetype":"venue"
},
  "geometry": {"coordinates":[6.637971,46.516521],"type":"Point"}
}