{
  "type": "Feature",
  "properties": {
    "iso:country":"CH",
    "sg:address":"Rue De La Blancherie 51 1950 Sion Case Postale 36",
    "sg:city":"Sion",
    "sg:orig_category":"Herstellung von Reiseartikeln, Leder U Sattlerwaren Interessenvertretungen",
    "sg:phone":"+41 27 323 35 43",
    "sg:postcode":"1951",
    "sg:province":"Valais",
    "wof:name":"Fondation Foyers-ateliers St-hubert",
    "wof:placetype":"venue"
},
  "geometry": {"coordinates":[7.351054,46.225445],"type":"Point"}
}