{
  "type": "Feature",
  "properties": {
    "addr:full":"Avenue De La Harpe 2 Lausanne Vaud 1007",
    "addr:housenumber":"2",
    "addr:postcode":"1007",
    "addr:street":"Avenue De La Harpe",
    "iso:country":"CH",
    "sg:address":"Avenue De La Harpe 2",
    "sg:city":"Lausanne",
    "sg:classifiers":[
        {
            "category":"Education",
            "subcategory":"Library",
            "type":"Public Place"
        }
    ],
    "sg:phone":"+41 21 616 58 08",
    "sg:postcode":"1007",
    "sg:province":"Vaud",
    "sg:tags":[
        "u",
        "bibliotheken",
        "archive"
    ],
    "wof:name":"Biblioth\u00e8que Municipale Montriond",
    "wof:placetype":"venue"
},
  "geometry": {"coordinates":[6.625429,46.513218],"type":"Point"}
}