{
  "type": "Feature",
  "properties": {
    "iso:country":"CH",
    "sg:address":"Winterthurerstrasse 54",
    "sg:city":"Sirnach",
    "sg:orig_category":"Offsetdruck Verlagsgewerbe",
    "sg:phone":"+41 71 966 28 88",
    "sg:postcode":"8370",
    "sg:province":"Thurgau",
    "wof:name":"Werbesga Sport-& Werbeverlag",
    "wof:placetype":"venue"
},
  "geometry": {"coordinates":[8.9935216904,47.463432312],"type":"Point"}
}