{
  "type": "Feature",
  "properties": {
    "iso:country":"CH",
    "sg:address":"Oberdorf",
    "sg:city":"Gettnau",
    "sg:orig_category":"Herstellung von Metallkonstruktionen",
    "sg:phone":"+41 41 970 22 35",
    "sg:postcode":"6142",
    "sg:province":"Luzern",
    "wof:name":"Wyss Metallbau Ag",
    "wof:placetype":"venue"
},
  "geometry": {"coordinates":[7.9671750069,47.1398468018],"type":"Point"}
}