{
  "type": "Feature",
  "properties": {
    "iso:country":"CH",
    "sg:address":"Riedthofstrasse 100 8105 Regensdorf. Postfach 548",
    "sg:city":"Regensdorf",
    "sg:orig_category":"Werbevermittlung Werbung",
    "sg:phone":"+41 18701155",
    "sg:postcode":"8105",
    "sg:province":"Z\u00fcrich",
    "wof:name":"Adra Werbeagentur Ag",
    "wof:placetype":"venue"
},
  "geometry": {"coordinates":[8.4660282135,47.4378433228],"type":"Point"}
}