{
  "type": "Feature",
  "properties": {
    "iso:country":"CH",
    "sg:address":"Murzelenstrasse 31",
    "sg:city":"Murzelen",
    "sg:orig_category":"Verarbeitung von Milch Verwertung von Milch",
    "sg:postcode":"3034",
    "sg:province":"Bern",
    "wof:name":"K\u00e4sereigenossenschaft Murzelen",
    "wof:placetype":"venue"
},
  "geometry": {"coordinates":[7.3164448738,46.9816398621],"type":"Point"}
}