{
  "type": "Feature",
  "properties": {
    "iso:country":"CH",
    "sg:address":"Au Moulin",
    "sg:city":"Remaufens",
    "sg:orig_category":"Abwasserreinigung, Abfallbeseitigung U sonstige Entsorgung",
    "sg:phone":"+41 21 947 41 70",
    "sg:postcode":"1617",
    "sg:province":"Fribourg",
    "wof:name":"Corboz-dewarrat Sa",
    "wof:placetype":"venue"
},
  "geometry": {"coordinates":[6.88229,46.526234],"type":"Point"}
}