{
  "type": "Feature",
  "properties": {
    "iso:country":"CH",
    "sg:address":"Petit-pont Rue Du 1 1964 Conthey. Postfach",
    "sg:city":"Conthey",
    "sg:orig_category":"Elektroinstallation",
    "sg:phone":"+41 27 346 11 29",
    "sg:postcode":"1964",
    "sg:province":"Valais",
    "wof:name":"Lambert Bernard, \u00e9lectrotechnique Tableaux \u00e9lectriques; Conception, Vente, Achat, R\u00e9paration Etc",
    "wof:placetype":"venue"
},
  "geometry": {"coordinates":[7.2956581116,46.213306427],"type":"Point"}
}