{
  "type": "Feature",
  "properties": {
    "iso:country":"CH",
    "sg:address":"Dorfstrasse 3",
    "sg:city":"Engelberg",
    "sg:orig_category":"Sonstige Kultur U Unterhaltungseinrichtungen Spielsalons",
    "sg:phone":"+41 81 832 10 80",
    "sg:postcode":"6390",
    "sg:province":"Obwalden",
    "wof:name":"Casino St.moritz Operating Ag",
    "wof:placetype":"venue"
},
  "geometry": {"coordinates":[9.8412885666,46.4993057251],"type":"Point"}
}