{
  "type": "Feature",
  "properties": {
    "iso:country":"CH",
    "sg:address":"Rue Voltaire 1",
    "sg:city":"Lausanne",
    "sg:classifiers":[
        {
            "category":"Insurance",
            "subcategory":"Insurance Agent",
            "type":"Services"
        }
    ],
    "sg:phone":"+41 21 617 01 43",
    "sg:postcode":"1006",
    "sg:province":"Vaud",
    "sg:tags":[
        "versicherungsagenturen",
        "-broker"
    ],
    "wof:name":"Nordstern Assurances Agence Mme A.joyet",
    "wof:placetype":"venue"
},
  "geometry": {"coordinates":[6.627989769,46.5129203796],"type":"Point"}
}