{
  "type": "Feature",
  "properties": {
    "addr:full":"Amlehnstrasse 38 6010 Kriens. Postfach 150 Kriens Luzern 6011",
    "addr:housenumber":"38;150",
    "addr:postcode":"6010 kriens.;6011",
    "addr:street":"Amlehnstrasse;Postfach",
    "iso:country":"CH",
    "sg:address":"Amlehnstrasse 38 6010 Kriens. Postfach 150",
    "sg:city":"Kriens",
    "sg:orig_category":"Detailhandel mit Brot, Back U S\u00fcsswaren Herstellung von Kakao, Schokoladeerzeugnissen U Zuckerwaren",
    "sg:phone":"+41 31 747 88 94",
    "sg:postcode":"6011",
    "sg:province":"Luzern",
    "wof:name":"Isenschmid Fruits-confits Ag",
    "wof:placetype":"venue"
},
  "geometry": {"coordinates":[7.237785,46.906277],"type":"Point"}
}