{
  "type": "Feature",
  "properties": {
    "iso:country":"CH",
    "sg:address":"6214",
    "sg:city":"Schenkon",
    "sg:classifiers":[
        {
            "category":"Travel",
            "subcategory":"Hotels & Motels",
            "type":"Entertainment"
        }
    ],
    "sg:postcode":"6214",
    "sg:province":"Luzern",
    "sg:tags":[
        "hotels",
        "mit",
        "restaurant"
    ],
    "wof:name":"Mattmann-bachmann Anton",
    "wof:placetype":"venue"
},
  "geometry": {"coordinates":[8.138297081,47.1724777222],"type":"Point"}
}