{
  "type": "Feature",
  "properties": {
    "iso:country":"CH",
    "sg:address":"Sch\u00f6nenstrasse 43",
    "sg:city":"R\u00fcschlikon",
    "sg:orig_category":"Sonstige Kurierdienste",
    "sg:postcode":"8803",
    "sg:province":"Z\u00fcrich",
    "wof:name":"Imseng D. & Co",
    "wof:placetype":"venue"
},
  "geometry": {"coordinates":[8.5513620377,47.3141212463],"type":"Point"}
}