{
  "type": "Feature",
  "properties": {
    "iso:country":"CH",
    "sg:address":"Baumackerstrasse 28",
    "sg:city":"Z\u00fcrich",
    "sg:orig_category":"Sonstiges Versicherungsgewerbe",
    "sg:phone":"+41 13113300",
    "sg:postcode":"8050",
    "sg:province":"Z\u00fcrich",
    "wof:name":"Kkv Krankenkassenvergleiche Grujovic",
    "wof:placetype":"venue"
},
  "geometry": {"coordinates":[8.5445289612,47.4088516235],"type":"Point"}
}