{
  "type": "Feature",
  "properties": {
    "iso:country":"CH",
    "sg:address":"Hinterbergstrasse 17",
    "sg:city":"Cham",
    "sg:orig_category":"Allgemeiner Hoch U Tiefbau",
    "sg:postcode":"6330",
    "sg:province":"Zug",
    "wof:name":"Az + Gu Management Gmbh",
    "wof:placetype":"venue"
},
  "geometry": {"coordinates":[8.477724,47.187317],"type":"Point"}
}