{
  "type": "Feature",
  "properties": {
    "iso:country":"CH",
    "sg:address":"Eggenschwand",
    "sg:city":"Kandersteg",
    "sg:orig_category":"Wohnheime",
    "sg:phone":"+41 33 675 12 40",
    "sg:postcode":"3718",
    "sg:province":"Bern",
    "wof:name":"Ferienheim Sunneblick Basel & Lyss",
    "wof:placetype":"venue"
},
  "geometry": {"coordinates":[7.6666998863,46.4832992554],"type":"Point"}
}