{
  "type": "Feature",
  "properties": {
    "iso:country":"CH",
    "sg:address":"Lehnstrasse 8 9014 St. Gallen",
    "sg:city":"Zust",
    "sg:orig_category":"Erbringung von Dienstleistungen f\u00fcr Unternehmen",
    "sg:phone":"+41 71 278 74 87",
    "sg:postcode":"14",
    "wof:name":"Osterwalder Und Mauch",
    "wof:placetype":"venue"
},
  "geometry": {"coordinates":[9.3363304138,47.4099197388],"type":"Point"}
}