{
  "type": "Feature",
  "properties": {
    "iso:country":"CH",
    "sg:address":"F\u00fcrstenlandstrasse 169 9014 St. Gallen. Postfach 331 9014 St. Gallen",
    "sg:city":"Zust",
    "sg:orig_category":"Betrieb von Taxis",
    "sg:phone":"+41 71 277 41 41",
    "sg:postcode":"14",
    "wof:name":"Taxi West Zimmermann",
    "wof:placetype":"venue"
},
  "geometry": {"coordinates":[9.334289,47.409882],"type":"Point"}
}