{
  "type": "Feature",
  "properties": {
    "iso:country":"CH",
    "sg:address":"Favre Rue Louis- 29",
    "sg:city":"Boudry",
    "sg:orig_category":"Herstellung von Sportger\u00e4ten",
    "sg:phone":"+41 71 877 29 10",
    "sg:postcode":"2017",
    "sg:province":"Neuch\u00e2tel",
    "wof:name":"Labelle Menet Peter, S\u00e4ttel F\u00fcr Stil Und Perfektion",
    "wof:placetype":"venue"
},
  "geometry": {"coordinates":[9.4726400375,47.4360389709],"type":"Point"}
}