{
  "type": "Feature",
  "properties": {
    "iso:country":"CH",
    "sg:address":"Sonn Egg 4 6044 Udligenswil. Postfach",
    "sg:city":"Udligenswil",
    "sg:orig_category":"Non-Classified Establishments",
    "sg:postcode":"6044",
    "sg:province":"Luzern",
    "wof:name":"Huber G\u00e4rtnerei Gmbh",
    "wof:placetype":"venue"
},
  "geometry": {"coordinates":[8.3981952667,47.0962715149],"type":"Point"}
}