{
  "type": "Feature",
  "properties": {
    "iso:country":"CH",
    "sg:address":"Jungfraustrasse 37",
    "sg:city":"Uetendorf",
    "sg:orig_category":"Instandhaltung U Reparatur von Automobilen",
    "sg:phone":"+41 33 345 60 76",
    "sg:postcode":"3661",
    "sg:province":"Bern",
    "wof:name":"Garage Reber",
    "wof:placetype":"venue"
},
  "geometry": {"coordinates":[7.5926671028,46.7787055969],"type":"Point"}
}