{
  "type": "Feature",
  "properties": {
    "iso:country":"CH",
    "sg:address":"Claridenstrasse 7",
    "sg:city":"Z\u00fcrich",
    "sg:orig_category":"Sonstige Kultur U Unterhaltungseinrichtungen",
    "sg:phone":"+41 12063434",
    "sg:postcode":"8002",
    "sg:province":"Z\u00fcrich",
    "wof:name":"Tonhalle",
    "wof:placetype":"venue"
},
  "geometry": {"coordinates":[8.5380249023,47.3661613464],"type":"Point"}
}