{
  "type": "Feature",
  "properties": {
    "iso:country":"CH",
    "sg:address":"Aarauerstrasse 2",
    "sg:city":"Wildegg",
    "sg:orig_category":"Architekturb\u00fcros",
    "sg:phone":"+41 41 630 29 07",
    "sg:postcode":"5103",
    "sg:province":"Aargau",
    "wof:name":"Remi Niederberger Architekturb\u00fcro",
    "wof:placetype":"venue"
},
  "geometry": {"coordinates":[8.308707,46.996689],"type":"Point"}
}