{
  "type": "Feature",
  "properties": {
    "iso:country":"CH",
    "sg:address":"Alleeweg 10",
    "sg:city":"Kreuzlingen",
    "sg:orig_category":"Sportschulen Wassersport",
    "sg:phone":"+41 71 672 38 27",
    "sg:postcode":"8280",
    "sg:province":"Thurgau",
    "wof:name":"Windsurfschule Herren Markus & Otto Lohr",
    "wof:placetype":"venue"
},
  "geometry": {"coordinates":[9.1703262329,47.6481246948],"type":"Point"}
}