{
  "type": "Feature",
  "properties": {
    "iso:country":"CH",
    "sg:address":"Bahnhofstrasse 10",
    "sg:city":"Dottikon",
    "sg:orig_category":"Architektur U Ingenieurb\u00fcros",
    "sg:phone":"+41 56 624 23 75",
    "sg:postcode":"5605",
    "sg:province":"Aargau",
    "wof:name":"Ag F\u00fcr Produkte-innovation Api",
    "wof:placetype":"venue"
},
  "geometry": {"coordinates":[8.241665,47.382607],"type":"Point"}
}