{
  "type": "Feature",
  "properties": {
    "iso:country":"CH",
    "sg:address":"Hohfuristrasse 12",
    "sg:city":"Neerach",
    "sg:orig_category":"Unternehmensberatung",
    "sg:phone":"+41 26 663 44 54",
    "sg:postcode":"8173",
    "sg:province":"Z\u00fcrich",
    "wof:name":"Strategos S\u00e0rl",
    "wof:placetype":"venue"
},
  "geometry": {"coordinates":[6.5586180687,46.5114364624],"type":"Point"}
}