{
  "type": "Feature",
  "properties": {
    "iso:country":"CH",
    "sg:address":"Musslistrasse 11",
    "sg:city":"Nunningen",
    "sg:orig_category":"Zahnarztpraxen",
    "sg:phone":"+41 61 791 09 52",
    "sg:postcode":"4208",
    "sg:province":"Solothurn",
    "wof:name":"Dr. Med. Dent. Halina Trzeciak Zahn\u00e4rztin",
    "wof:placetype":"venue"
},
  "geometry": {"coordinates":[7.6270699501,47.3946342468],"type":"Point"}
}