{
  "type": "Feature",
  "properties": {
    "iso:country":"CH",
    "sg:address":"Zugerstrasse 45",
    "sg:city":"Cham",
    "sg:orig_category":"Hochschulen U h\u00f6here Ausbildung",
    "sg:phone":"+41 41 781 26 49",
    "sg:postcode":"6330",
    "sg:province":"Zug",
    "wof:name":"Amstutz, F\u00fchrung & Marketing",
    "wof:placetype":"venue"
},
  "geometry": {"coordinates":[8.466340065,47.1819763184],"type":"Point"}
}