{
  "type": "Feature",
  "properties": {
    "iso:country":"CH",
    "sg:address":"Marktplatz 34",
    "sg:city":"Basel",
    "sg:classifiers":[
        {
            "category":"Restaurant",
            "type":"Food & Drink"
        }
    ],
    "sg:phone":"+41 22 300 42 90",
    "sg:postcode":"4001",
    "sg:province":"Basel-Stadt",
    "wof:name":"Restaurant Javardo",
    "wof:placetype":"venue"
},
  "geometry": {"coordinates":[6.1343698502,46.1879043579],"type":"Point"}
}