{
  "type": "Feature",
  "properties": {
    "addr:full":"Bahnhofstrasse 2 3860 Meiringen. Postfach 664 Meiringen Bern 3860",
    "addr:housenumber":"2;664",
    "addr:postcode":"3860 meiringen.;3860",
    "addr:street":"Bahnhofstrasse;Postfach",
    "iso:country":"CH",
    "sg:address":"Bahnhofstrasse 2 3860 Meiringen. Postfach 664",
    "sg:city":"Meiringen",
    "sg:orig_category":"Architektur U Ingenieurb\u00fcros Architekturb\u00fcros",
    "sg:phone":"+41 71 672 53 50",
    "sg:postcode":"3860",
    "sg:province":"Bern",
    "wof:name":"Amstutz Markus Architekt",
    "wof:placetype":"venue"
},
  "geometry": {"coordinates":[9.171472,47.644718],"type":"Point"}
}