{
  "type": "Feature",
  "properties": {
    "iso:country":"CH",
    "sg:address":"Zugerstrasse 11",
    "sg:city":"Ebikon",
    "sg:orig_category":"Informatikdienste Wirtschaftspr\u00fcfung, Steuerberatung U Treuhand",
    "sg:phone":"+41 55 410 51 41",
    "sg:postcode":"6030",
    "sg:province":"Luzern",
    "wof:name":"Dmf Gmbh Kontrollstellmandaten, Steuerberatung, Unternehmensberatung Usw",
    "wof:placetype":"venue"
},
  "geometry": {"coordinates":[8.7711448669,47.1977119446],"type":"Point"}
}