{
  "type": "Feature",
  "properties": {
    "iso:country":"CH",
    "sg:address":"Chemin Des Cytises 12",
    "sg:city":"Veyrier",
    "sg:classifiers":[
        {
            "category":"Home & Garden",
            "subcategory":"Household Appliances",
            "type":"Retail Goods"
        }
    ],
    "sg:phone":"+41 22 890 01 75",
    "sg:postcode":"1255",
    "sg:province":"Gen\u00e8ve",
    "sg:tags":[
        "cleaner",
        "industrial",
        "vacuum"
    ],
    "wof:name":"J. Mengel Aspirateurs Industriels S\u00e0rl",
    "wof:placetype":"venue"
},
  "geometry": {"coordinates":[6.1743488312,46.1642112732],"type":"Point"}
}