{
  "type": "Feature",
  "properties": {
    "iso:country":"CH",
    "sg:address":"Heiggenstrasse 2",
    "sg:city":"Amden",
    "sg:orig_category":"RESTAURANTS: TEA-ROOMS",
    "sg:postcode":"8873",
    "sg:province":"St. Gallen",
    "wof:name":"Arvenh\u00f6he Ag, Caf\u00e9-restaurant",
    "wof:placetype":"venue"
},
  "geometry": {"coordinates":[9.1756401062,47.1488990784],"type":"Point"}
}