{
  "type": "Feature",
  "properties": {
    "iso:country":"CH",
    "sg:address":"7545",
    "sg:city":"Guarda",
    "sg:classifiers":[
        {
            "category":"Travel",
            "subcategory":"Hotels & Motels",
            "type":"Entertainment"
        }
    ],
    "sg:phone":"+41 81 413 60 46",
    "sg:postcode":"7545",
    "sg:province":"Graubunden",
    "sg:tags":[
        "hotels",
        "mit",
        "restaurant"
    ],
    "wof:name":"Ag National Davos",
    "wof:placetype":"venue"
},
  "geometry": {"coordinates":[9.819189,46.794361],"type":"Point"}
}