{
  "type": "Feature",
  "properties": {
    "iso:country":"CH",
    "sg:address":"Grand-pr\u00e9 Rue Du 8 1007 Lausanne. Postfach",
    "sg:city":"Lausanne",
    "sg:orig_category":"Detektivb\u00fcros U \u00dcberwachung",
    "sg:phone":"+41 32 924 50 50",
    "sg:postcode":"1003",
    "sg:province":"Vaud",
    "wof:name":"As Protect' Service, Schmidt Patrick & Cie",
    "wof:placetype":"venue"
},
  "geometry": {"coordinates":[6.8299050331,47.102809906],"type":"Point"}
}