{
  "type": "Feature",
  "properties": {
    "iso:country":"CH",
    "sg:address":"Romont Rue De 2",
    "sg:city":"Fribourg",
    "sg:orig_category":"Handelsvermittlung von Brennstoffen, Erzen, Metallen U Chemikalien",
    "sg:phone":"+41 26 323 14 50",
    "sg:postcode":"1700",
    "sg:province":"Fribourg",
    "wof:name":"Delfinet S\u00e0rl \u00e0 Luxembourg (luxembourg) Succursale De Fribourg",
    "wof:placetype":"venue"
},
  "geometry": {"coordinates":[7.1554617882,46.8049125671],"type":"Point"}
}