{
  "type": "Feature",
  "properties": {
    "iso:country":"CH",
    "sg:address":"Bahnhofplatz 5 2502 Biel/bienne. Postfach",
    "sg:city":"Biel/bienne",
    "sg:orig_category":"Reiseb\u00fcros",
    "sg:phone":"+41 32 323 14 10",
    "sg:postcode":"2501",
    "sg:province":"Bern",
    "wof:name":"Wasteels Reisen Ag",
    "wof:placetype":"venue"
},
  "geometry": {"coordinates":[7.2423501015,47.1338768005],"type":"Point"}
}