{
  "type": "Feature",
  "properties": {
    "iso:country":"CH",
    "sg:address":"Thunstrasse 2",
    "sg:city":"Z\u00e4ziwil",
    "sg:orig_category":"Sanit\u00e4r, Heizungs U L\u00fcftungsinstallation",
    "sg:phone":"+41 31 711 48 02",
    "sg:postcode":"3532",
    "sg:province":"Bern",
    "wof:name":"Pennella G.- Heizungen, Steuerungen, Sanit\u00e4re Anlagen",
    "wof:placetype":"venue"
},
  "geometry": {"coordinates":[7.6609840393,46.9016647339],"type":"Point"}
}