{
  "type": "Feature",
  "properties": {
    "iso:country":"CH",
    "sg:address":"Palais Du Gouvernement 1950 Sion Case Postale 340",
    "sg:city":"Sion",
    "sg:orig_category":"Verwaltung der Volkswirtschaft",
    "sg:phone":"+41 27 606 72 00",
    "sg:postcode":"1951",
    "sg:province":"Valais",
    "wof:name":"D\u00e9partement Des Finances & De L'\u00e9conomie",
    "wof:placetype":"venue"
},
  "geometry": {"coordinates":[7.3588571548,46.2280921936],"type":"Point"}
}