{
  "type": "Feature",
  "properties": {
    "iso:country":"CH",
    "sg:address":"Allmendstr. 11",
    "sg:city":"Horw",
    "sg:classifiers":[
        {
            "category":"Wholesale",
            "subcategory":"Machinery & Supplies",
            "type":"Manufacturing & Wholesale Goods"
        }
    ],
    "sg:phone":"+41 32 351 23 22",
    "sg:postcode":"6048",
    "sg:province":"Luzern",
    "sg:tags":[
        "handling",
        "material",
        "-",
        "machine",
        "equipment",
        "engineering",
        "mechanical"
    ],
    "wof:name":"Mk System 2000 Ag",
    "wof:placetype":"venue"
},
  "geometry": {"coordinates":[7.3854727745,47.1434135437],"type":"Point"}
}