{
  "type": "Feature",
  "properties": {
    "iso:country":"CH",
    "sg:address":"G\u00e4chlingerstrasse 2",
    "sg:city":"Neunkirch",
    "sg:orig_category":"G\u00fcterbef\u00f6rderung im Strassenverkehr",
    "sg:phone":"+41 52 681 14 97",
    "sg:postcode":"8213",
    "sg:province":"Schaffhausen",
    "wof:name":"Wildberger-transporte Inh.walter Stamm",
    "wof:placetype":"venue"
},
  "geometry": {"coordinates":[8.5015830994,47.6906394958],"type":"Point"}
}