{
  "type": "Feature",
  "properties": {
    "iso:country":"CH",
    "sg:address":"Rue De Montchoisy 36",
    "sg:city":"Gen\u00e8ve",
    "sg:orig_category":"Einbau von Schreinerwaren Herstellung von K\u00fcchenm\u00f6beln",
    "sg:phone":"+41 27 722 96 29",
    "sg:postcode":"1207",
    "sg:province":"Gen\u00e8ve",
    "wof:name":"Thomas Cuisines Sa Agencement De Cuisines, D'armoires De Rangement Etc",
    "wof:placetype":"venue"
},
  "geometry": {"coordinates":[7.0963430405,46.1079216003],"type":"Point"}
}