{
  "type": "Feature",
  "properties": {
    "iso:country":"CH",
    "sg:address":"Beatenbergstrasse 136",
    "sg:city":"Unterseen",
    "sg:orig_category":"M\u00f6belschreinereien",
    "sg:phone":"+41 33 823 57 82",
    "sg:postcode":"3800",
    "sg:province":"Bern",
    "wof:name":"Asiana Gmbh",
    "wof:placetype":"venue"
},
  "geometry": {"coordinates":[7.840941906,46.6896781921],"type":"Point"}
}