{
  "type": "Feature",
  "properties": {
    "iso:country":"CH",
    "sg:address":"Rebgasse 1 4058 Basel. Postfach",
    "sg:city":"Basel",
    "sg:orig_category":"Detailhandel mit B\u00fcchern",
    "sg:phone":"+41 61 681 12 22",
    "sg:postcode":"4005",
    "sg:province":"Basel-Stadt",
    "wof:name":"Wohler & Co Buchhandlung Claraplatz",
    "wof:placetype":"venue"
},
  "geometry": {"coordinates":[7.593751,47.561359],"type":"Point"}
}