{
  "type": "Feature",
  "properties": {
    "iso:country":"CH",
    "sg:address":"M\u00fchlebachstrasse 19 6340 Baar. Postfach",
    "sg:city":"Baar",
    "sg:orig_category":"Sonstiger Grosshandel",
    "sg:phone":"+41 41 760 89 76",
    "sg:postcode":"6340",
    "sg:province":"Zug",
    "wof:name":"Cakar Export",
    "wof:placetype":"venue"
},
  "geometry": {"coordinates":[8.5213851929,47.2010116577],"type":"Point"}
}