{
  "type": "Feature",
  "properties": {
    "iso:country":"CH",
    "sg:address":"Titlisstrasse 6",
    "sg:city":"Menziken",
    "sg:orig_category":"Fahrschulen, Flugschulen",
    "sg:phone":"+41 79 333 72 72",
    "sg:postcode":"5737",
    "sg:province":"Aargau",
    "wof:name":"Rolf Pfeiffer Autofahrschule",
    "wof:placetype":"venue"
},
  "geometry": {"coordinates":[8.1846599579,47.2410774231],"type":"Point"}
}