{
  "type": "Feature",
  "properties": {
    "iso:country":"CH",
    "sg:address":"Gottardo Via San 83 6900 Massagno. Postfach",
    "sg:city":"Massagno",
    "sg:orig_category":"Fachdetailhandel in Verkaufsr\u00e4umen",
    "sg:postcode":"6900",
    "sg:province":"Ticino",
    "wof:name":"Genflor Sa",
    "wof:placetype":"venue"
},
  "geometry": {"coordinates":[8.945233345,46.0128707886],"type":"Point"}
}