{
  "type": "Feature",
  "properties": {
    "iso:country":"CH",
    "sg:address":"Deinikon",
    "sg:city":"Baar",
    "sg:orig_category":"S\u00e4gewerke",
    "sg:phone":"+41 41 760 39 49",
    "sg:postcode":"6340",
    "sg:province":"Zug",
    "wof:name":"Josef Hotz S\u00e4gerei",
    "wof:placetype":"venue"
},
  "geometry": {"coordinates":[8.5408096313,47.2050895691],"type":"Point"}
}