{
  "type": "Feature",
  "properties": {
    "iso:country":"CH",
    "sg:address":"Schaffhauserstrasse 87a 8500 Frauenfeld. Postfach",
    "sg:city":"Frauenfeld",
    "sg:orig_category":"Lettershops and Versandservice Vervielf\u00e4ltigung von bespielten Ton, Bild U Datentr\u00e4gern",
    "sg:postcode":"8501",
    "sg:province":"Thurgau",
    "wof:name":"Digicon Ag Switzerland",
    "wof:placetype":"venue"
},
  "geometry": {"coordinates":[9.1739635468,47.6526565552],"type":"Point"}
}