{
  "type": "Feature",
  "properties": {
    "addr:full":"Wallisellenstr.5 Z\u00fcrich Z\u00fcrich 8050",
    "addr:postcode":"8050",
    "iso:country":"CH",
    "sg:address":"Wallisellenstr.5",
    "sg:city":"Z\u00fcrich",
    "sg:orig_category":"Dienstleistungen, Sonstige Dienstleistungen",
    "sg:postcode":"8050",
    "sg:province":"Z\u00fcrich",
    "wof:name":"Mahubena",
    "wof:placetype":"venue"
},
  "geometry": {"coordinates":[8.547726,47.410431],"type":"Point"}
}