{
  "type": "Feature",
  "properties": {
    "addr:full":"Via Camogh\u00e9 1 Lugano Ticino 6900",
    "addr:housenumber":"1",
    "addr:postcode":"6900",
    "addr:street":"Via Camoghe\u0301",
    "iso:country":"CH",
    "sg:address":"Via Camogh\u00e9 1",
    "sg:city":"Lugano",
    "sg:orig_category":"Detailhandel mit Beleuchtungs U Haushaltsgegenst\u00e4nden Detailhandel mit elektrischen Haushalts-,Radio",
    "sg:postcode":"6900",
    "sg:province":"Ticino",
    "wof:name":"D'alesio Silvano",
    "wof:placetype":"venue"
},
  "geometry": {"coordinates":[8.957273,46.011948],"type":"Point"}
}