{
  "type": "Feature",
  "properties": {
    "addr:full":"Im Ziel 27 Zollikerberg Z\u00fcrich 8125",
    "addr:housenumber":"27",
    "addr:postcode":"8125",
    "addr:street":"Im Ziel",
    "iso:country":"CH",
    "sg:address":"Im Ziel 27",
    "sg:city":"Zollikerberg",
    "sg:orig_category":"Bauspenglerei Sanit\u00e4r, Heizungs U L\u00fcftungsinstallation",
    "sg:phone":"+41 13916194",
    "sg:postcode":"8125",
    "sg:province":"Z\u00fcrich",
    "wof:name":"Sibold Ag",
    "wof:placetype":"venue"
},
  "geometry": {"coordinates":[8.594237,47.346123],"type":"Point"}
}