{
  "type": "Feature",
  "properties": {
    "iso:country":"CH",
    "sg:address":"Chemin De Praz-lau 3",
    "sg:city":"Cheseaux-lausanne",
    "sg:orig_category":"Elektroinstallation",
    "sg:phone":"+41 21 731 22 91",
    "sg:postcode":"1033",
    "sg:province":"Vaud",
    "wof:name":"Bally Guy.",
    "wof:placetype":"venue"
},
  "geometry": {"coordinates":[6.6048598289,46.5855407715],"type":"Point"}
}