{
  "type": "Feature",
  "properties": {
    "iso:country":"CH",
    "sg:address":"Mittengrabenstrasse 39",
    "sg:city":"Interlaken",
    "sg:orig_category":"D\u00e4mmung gegen K\u00e4lte, W\u00e4rme, Schall U Ersch\u00fctterung Verlegen von Fussboden",
    "sg:phone":"+41 79 656 65 66",
    "sg:postcode":"3800",
    "sg:province":"Bern",
    "wof:name":"P. L\u00fcthi Ag",
    "wof:placetype":"venue"
},
  "geometry": {"coordinates":[7.8719611168,46.6870765686],"type":"Point"}
}