{
  "type": "Feature",
  "properties": {
    "iso:country":"CH",
    "sg:address":"1880",
    "sg:city":"Fenalet-sur-bex",
    "sg:orig_category":"Bauschreinerei Zimmerei, Ingenieurholzbau",
    "sg:phone":"+41 24 492 32 42",
    "sg:postcode":"1880",
    "sg:province":"Vaud",
    "wof:name":"Pierre Checcacci Constr.de Chalets & Menuiserie",
    "wof:placetype":"venue"
},
  "geometry": {"coordinates":[7.158712,46.35004],"type":"Point"}
}