{
  "type": "Feature",
  "properties": {
    "iso:country":"CH",
    "sg:address":"Sagenrain",
    "sg:city":"Dagmersellen",
    "sg:orig_category":"Sanit\u00e4r, Heizungs U L\u00fcftungsinstallation",
    "sg:postcode":"6252",
    "sg:province":"Luzern",
    "wof:name":"Zemp Und Erni Gmbh, Zweigniederlassung Dagmersellen",
    "wof:placetype":"venue"
},
  "geometry": {"coordinates":[7.9755711555,47.2182617188],"type":"Point"}
}