{
  "type": "Feature",
  "properties": {
    "iso:country":"CH",
    "sg:address":"6542",
    "sg:city":"Buseno",
    "sg:classifiers":[
        {
            "category":"Restaurant",
            "type":"Food & Drink"
        }
    ],
    "sg:phone":"+41 91 827 13 10",
    "sg:postcode":"6542",
    "sg:province":"Graubunden",
    "wof:name":"Osteria Marcacci",
    "wof:placetype":"venue"
},
  "geometry": {"coordinates":[9.1070585251,46.2732925415],"type":"Point"}
}