{
  "type": "Feature",
  "properties": {
    "iso:country":"CH",
    "sg:address":"Valdani Via 9",
    "sg:city":"Chiasso",
    "sg:orig_category":"Sonstiger Grosshandel",
    "sg:phone":"+41 91 682 41 31",
    "sg:postcode":"6830",
    "sg:province":"Ticino",
    "wof:name":"Sanyo Sa",
    "wof:placetype":"venue"
},
  "geometry": {"coordinates":[9.0292825699,45.8382568359],"type":"Point"}
}