{
  "type": "Feature",
  "properties": {
    "iso:country":"CH",
    "sg:address":"Heimatstrasse 1",
    "sg:city":"Baar",
    "sg:orig_category":"Vereine Orchester",
    "sg:postcode":"6340",
    "sg:province":"Zug",
    "wof:name":"Orchesterverein Baar",
    "wof:placetype":"venue"
},
  "geometry": {"coordinates":[8.5216960907,47.1983146667],"type":"Point"}
}