{
  "type": "Feature",
  "properties": {
    "addr:full":"Dammstrasse 25 Hochdorf Luzern 6280",
    "addr:housenumber":"25",
    "addr:postcode":"6280",
    "addr:street":"Dammstrasse",
    "iso:country":"CH",
    "sg:address":"Dammstrasse 25",
    "sg:city":"Hochdorf",
    "sg:orig_category":"Allgemeiner Gartenbau Dienstleistungen im Gartenbau",
    "sg:phone":"+41 41 910 66 24",
    "sg:postcode":"6280",
    "sg:province":"Luzern",
    "wof:name":"Abelia G\u00e4rten Dieter Marbach",
    "wof:placetype":"venue"
},
  "geometry": {"coordinates":[8.294558,47.164761],"type":"Point"}
}