{
  "type": "Feature",
  "properties": {
    "iso:country":"CH",
    "sg:address":"Rue Des Alpes 58",
    "sg:city":"Fribourg",
    "sg:orig_category":"Interessenvertretungen",
    "sg:postcode":"1700",
    "sg:province":"Fribourg",
    "wof:name":"Fondation Organes Artificiels",
    "wof:placetype":"venue"
},
  "geometry": {"coordinates":[6.2168269157,46.4602355957],"type":"Point"}
}