{
  "type": "Feature",
  "properties": {
    "iso:country":"CH",
    "sg:address":"Via Clemente Maraini 17a",
    "sg:city":"Lugano",
    "sg:orig_category":"Unternehmensberatung",
    "sg:postcode":"6900",
    "sg:province":"Ticino",
    "wof:name":"Balocco Francesco",
    "wof:placetype":"venue"
},
  "geometry": {"coordinates":[8.9457406998,45.9991493225],"type":"Point"}
}