{
  "type": "Feature",
  "properties": {
    "iso:country":"CH",
    "sg:address":"Neugutstrasse 19",
    "sg:city":"Z\u00fcrich",
    "sg:orig_category":"Detektivb\u00fcros U \u00dcberwachung",
    "sg:postcode":"8002",
    "sg:province":"Z\u00fcrich",
    "wof:name":"Ips Hazazi",
    "wof:placetype":"venue"
},
  "geometry": {"coordinates":[8.5261878967,47.3589668274],"type":"Point"}
}