{
  "type": "Feature",
  "properties": {
    "iso:country":"CH",
    "sg:address":"Avenue G\u00e9n\u00e9ral-guisan 13",
    "sg:city":"Pully",
    "sg:orig_category":"Sportvereine Turnen Vereine Damen",
    "sg:postcode":"1009",
    "sg:province":"Vaud",
    "wof:name":"St\u00e9 De Gymnastique De Dames",
    "wof:placetype":"venue"
},
  "geometry": {"coordinates":[6.6563310623,46.5065536499],"type":"Point"}
}