{
  "type": "Feature",
  "properties": {
    "iso:country":"CH",
    "sg:address":"La Chaux",
    "sg:city":"Ste-croix",
    "sg:orig_category":"RESTAURANTS: TEA-ROOMS",
    "sg:postcode":"1450",
    "sg:province":"Vaud",
    "wof:name":"Jacdine S\u00e0rl Caf\u00e9s, Restaurants, Auberges, H\u00f4tels Etc",
    "wof:placetype":"venue"
},
  "geometry": {"coordinates":[7.2086448669,46.1864585876],"type":"Point"}
}