{
  "type": "Feature",
  "properties": {
    "iso:country":"CH",
    "sg:address":"Coll\u00e8ge Rue Du 26 1815 Clarens Case Postale 288",
    "sg:city":"Clarens",
    "sg:orig_category":"Unclassifiable Establishments",
    "sg:phone":"+41 21 983 23 23",
    "sg:postcode":"1815",
    "sg:province":"Vaud",
    "wof:name":"Estelec S.a.",
    "wof:placetype":"venue"
},
  "geometry": {"coordinates":[6.8935799599,46.4435043335],"type":"Point"}
}