{
  "type": "Feature",
  "properties": {
    "iso:country":"CH",
    "sg:address":"Seetalstrasse 20",
    "sg:city":"Schafisheim",
    "sg:orig_category":"Kunsthandel",
    "sg:phone":"+41 71 278 14 74",
    "sg:postcode":"5503",
    "sg:province":"Aargau",
    "wof:name":"Elisabeth Inauen Galerie",
    "wof:placetype":"venue"
},
  "geometry": {"coordinates":[9.3563957214,47.42162323],"type":"Point"}
}