{
  "type": "Feature",
  "properties": {
    "iso:country":"CH",
    "sg:address":"S\u00e4gereistrasse 5",
    "sg:city":"Niederglatt",
    "sg:classifiers":[
        {
            "category":"Banks & Credit Unions",
            "subcategory":"Investment Brokerage",
            "type":"Services"
        }
    ],
    "sg:phone":"+41 18501440",
    "sg:postcode":"8172",
    "sg:province":"Z\u00fcrich",
    "sg:tags":[
        "picture",
        "frame",
        "moulding"
    ],
    "wof:name":"Rahmen & Goldleisten R. Ammann",
    "wof:placetype":"venue"
},
  "geometry": {"coordinates":[8.5046243668,47.4911575317],"type":"Point"}
}