{
  "type": "Feature",
  "properties": {
    "iso:country":"CH",
    "sg:address":"Via Peri 18",
    "sg:city":"Lugano",
    "sg:orig_category":"B\u00e4ckereien Konditoreien",
    "sg:phone":"+41 91 921 24 64",
    "sg:postcode":"6900",
    "sg:province":"Ticino",
    "wof:name":"Giancarlo Seitz Sa Panetteria-pasticceria",
    "wof:placetype":"venue"
},
  "geometry": {"coordinates":[8.950789,46.00629],"type":"Point"}
}