{
  "type": "Feature",
  "properties": {
    "iso:country":"CH",
    "sg:address":"Route De L'h\u00f4pital 3",
    "sg:city":"Sierre",
    "sg:orig_category":"Geb\u00e4ude, Wohnungsreinigung",
    "sg:postcode":"3960",
    "sg:province":"Valais",
    "wof:name":"Peter L\u00e4derach Blitz-geb\u00e4udereinigung",
    "wof:placetype":"venue"
},
  "geometry": {"coordinates":[7.5831208229,47.0874671936],"type":"Point"}
}