{
  "type": "Feature",
  "properties": {
    "iso:country":"CH",
    "sg:address":"Rosengasse 27 8750 Glarus. Postfach",
    "sg:city":"Glarus",
    "sg:orig_category":"Softwareentwicklung U beratung",
    "sg:phone":"+41 55 640 70 28",
    "sg:postcode":"8750",
    "sg:province":"Glarus",
    "wof:name":"Schlittler Informatik-dienstleistungen Gmbh",
    "wof:placetype":"venue"
},
  "geometry": {"coordinates":[9.0711984634,47.0371513367],"type":"Point"}
}