{
  "type": "Feature",
  "properties": {
    "iso:country":"CH",
    "sg:address":"H\u00f6henweg 20",
    "sg:city":"M\u00f6rigen",
    "sg:orig_category":"Sonstige mit Sport verbundene T\u00e4tigkeiten",
    "sg:phone":"+41 32 397 19 77",
    "sg:postcode":"2572",
    "sg:province":"Bern",
    "wof:name":"Take-off Balloon Ag",
    "wof:placetype":"venue"
},
  "geometry": {"coordinates":[7.2143387794,47.0804023743],"type":"Point"}
}