{
  "type": "Feature",
  "properties": {
    "iso:country":"CH",
    "sg:address":"1997 Haute-nendaz. Postfach",
    "sg:city":"Vernami\u00e8ge",
    "sg:orig_category":"Gemischte Landwirtschaft",
    "sg:postcode":"1961",
    "sg:province":"Valais",
    "wof:name":"Fournier Jean-yves",
    "wof:placetype":"venue"
},
  "geometry": {"coordinates":[7.2981119156,46.1841583252],"type":"Point"}
}