{
  "type": "Feature",
  "properties": {
    "iso:country":"CH",
    "sg:address":"Chemin Des Cornillons",
    "sg:city":"Chamb\u00e9sy",
    "sg:orig_category":"Innenarchitekturb\u00fcros",
    "sg:phone":"+41 22 758 27 74",
    "sg:postcode":"1292",
    "sg:province":"Gen\u00e8ve",
    "wof:name":"Catherine K\u00f6ssler Architecture D'int\u00e9rieur",
    "wof:placetype":"venue"
},
  "geometry": {"coordinates":[6.1459851265,46.2421073914],"type":"Point"}
}