{
  "type": "Feature",
  "properties": {
    "iso:country":"CH",
    "sg:address":"Hagenacherstrasse 21",
    "sg:city":"Effretikon",
    "sg:orig_category":"Sonstige Institutionen des Sozialwesens ohne Beherbergung",
    "sg:phone":"+41 52 343 01 14",
    "sg:postcode":"8307",
    "sg:province":"Z\u00fcrich",
    "wof:name":"Verein F\u00e4hre Sozialer Dienst",
    "wof:placetype":"venue"
},
  "geometry": {"coordinates":[8.684586525,47.4262123108],"type":"Point"}
}