{
  "type": "Feature",
  "properties": {
    "iso:country":"CH",
    "sg:address":"Veronikaweg 11",
    "sg:city":"Aarau",
    "sg:orig_category":"Unternehmensberatung",
    "sg:phone":"+41 62 823 00 30",
    "sg:postcode":"5000",
    "sg:province":"Aargau",
    "wof:name":"Pwm Walde Patrick Management",
    "wof:placetype":"venue"
},
  "geometry": {"coordinates":[8.0423135757,47.3836784363],"type":"Point"}
}