{
  "type": "Feature",
  "properties": {
    "iso:country":"CH",
    "sg:address":"Oltnerstrasse 39",
    "sg:city":"Sch\u00f6nenwerd",
    "sg:orig_category":"Detailhandel mit Textilien",
    "sg:phone":"+41 62 849 19 66",
    "sg:postcode":"5012",
    "sg:province":"Solothurn",
    "wof:name":"Susi Meier Wullest\u00fcbli",
    "wof:placetype":"venue"
},
  "geometry": {"coordinates":[8.0016860962,47.3697624207],"type":"Point"}
}