{
  "type": "Feature",
  "properties": {
    "iso:country":"CH",
    "sg:address":"Marktgasse 52 4310 Rheinfelden. Postfach",
    "sg:city":"Rheinfelden",
    "sg:orig_category":"Detailhandel mit Spielwaren Fachdetailhandel in Verkaufsr\u00e4umen",
    "sg:phone":"+41 61 831 21 12",
    "sg:postcode":"4310",
    "sg:province":"Aargau",
    "wof:name":"Diabolo Gmbh",
    "wof:placetype":"venue"
},
  "geometry": {"coordinates":[7.7913928032,47.5550575256],"type":"Point"}
}