{
  "type": "Feature",
  "properties": {
    "iso:country":"CH",
    "sg:address":"Wolfacker 6",
    "sg:city":"Dulliken",
    "sg:orig_category":"Grosshandel mit Nahrungsmitteln, Getr\u00e4nken U Tabakwaren Grosshandel mit chemischen Erzeugnissen",
    "sg:phone":"+41 62 295 20 41",
    "sg:postcode":"4657",
    "sg:province":"Solothurn",
    "wof:name":"R. Orfei Inh.hans D'arco Oele-fette Chem'techn.produkte",
    "wof:placetype":"venue"
},
  "geometry": {"coordinates":[7.936275959,47.3544616699],"type":"Point"}
}