{
  "type": "Feature",
  "properties": {
    "iso:country":"CH",
    "sg:address":"Ringstrasse 5 4600 Olten. Postfach",
    "sg:city":"Olten",
    "sg:orig_category":"Aktivit\u00e4t der Bankinstitute",
    "sg:phone":"+41 61 645 63 63",
    "sg:postcode":"4603",
    "sg:province":"Solothurn",
    "wof:name":"Migros Bank",
    "wof:placetype":"venue"
},
  "geometry": {"coordinates":[7.651324,47.585453],"type":"Point"}
}