{
  "type": "Feature",
  "properties": {
    "iso:country":"CH",
    "sg:address":"Oltnerstrasse 9",
    "sg:city":"Winznau",
    "sg:orig_category":"Arztpraxen",
    "sg:phone":"+41 62 295 53 33",
    "sg:postcode":"4652",
    "sg:province":"Solothurn",
    "wof:name":"Dr.med.friedrich Husi Spezialarzt Fmh",
    "wof:placetype":"venue"
},
  "geometry": {"coordinates":[7.931913,47.364471],"type":"Point"}
}