{
  "type": "Feature",
  "properties": {
    "iso:country":"CH",
    "sg:address":"Brunnacherstrasse 24",
    "sg:city":"Stadel",
    "sg:orig_category":"Sportvereine Ballsport Tennis",
    "sg:phone":"+41 18581234",
    "sg:postcode":"8174",
    "sg:province":"Z\u00fcrich",
    "wof:name":"Tc Stadel",
    "wof:placetype":"venue"
},
  "geometry": {"coordinates":[8.4598550797,47.530040741],"type":"Point"}
}