{
  "type": "Feature",
  "properties": {
    "iso:country":"CH",
    "sg:address":"Schutzengelstrasse 36",
    "sg:city":"Baar",
    "sg:orig_category":"Finanzierungsinstitutionen",
    "sg:postcode":"6340",
    "sg:province":"Zug",
    "wof:name":"Danaos Ag",
    "wof:placetype":"venue"
},
  "geometry": {"coordinates":[8.5367145538,47.1975212097],"type":"Point"}
}