{
  "type": "Feature",
  "properties": {
    "iso:country":"CH",
    "sg:address":"La Roug\u00e8ve",
    "sg:city":"Semsales",
    "sg:orig_category":"Bauschreinerei",
    "sg:phone":"+41 26 918 52 67",
    "sg:postcode":"1623",
    "sg:province":"Fribourg",
    "wof:name":"Philippe & Louis Vial S\u00e0rl Menuiserie & \u00e9b\u00e9nisterie",
    "wof:placetype":"venue"
},
  "geometry": {"coordinates":[6.906856,46.564934],"type":"Point"}
}