{
  "type": "Feature",
  "properties": {
    "iso:country":"CH",
    "sg:address":"Gasstrasse 15",
    "sg:city":"Basel",
    "sg:orig_category":"Allgemeiner Hoch U Tiefbau Strassenbau",
    "sg:phone":"+41 26 652 20 27",
    "sg:postcode":"4056",
    "sg:province":"Basel-Stadt",
    "wof:name":"Gobet G\u00e9nie Civil Sa",
    "wof:placetype":"venue"
},
  "geometry": {"coordinates":[6.93189,46.634991],"type":"Point"}
}