{
  "type": "Feature",
  "properties": {
    "iso:country":"CH",
    "sg:address":"Haglenweg 3",
    "sg:city":"Gempen",
    "sg:orig_category":"Sonstige mit der Informatik verbundene T\u00e4tigkeiten",
    "sg:postcode":"4145",
    "sg:province":"Solothurn",
    "wof:name":"3byte Gmbh",
    "wof:placetype":"venue"
},
  "geometry": {"coordinates":[7.6638360023,47.4751701355],"type":"Point"}
}