{
  "type": "Feature",
  "properties": {
    "iso:country":"CH",
    "sg:address":"R\u00fctsch 14",
    "sg:city":"Willisau",
    "sg:orig_category":"Grosshandel mit Parf\u00fcmerieartikeln U K\u00f6rperpflegemitteln Grosshandel mit chemischen Erzeugnissen",
    "sg:phone":"+41 41 970 05 51",
    "sg:postcode":"6130",
    "sg:province":"Luzern",
    "wof:name":"Hans Aregger K\u00f6rper-& Haushaltpflegeart.",
    "wof:placetype":"venue"
},
  "geometry": {"coordinates":[7.9990859032,47.1132850647],"type":"Point"}
}