{
  "type": "Feature",
  "properties": {
    "iso:country":"CH",
    "sg:address":"Strada Collina",
    "sg:city":"Ascona",
    "sg:classifiers":[
        {
            "category":"Travel",
            "subcategory":"Hotels & Motels",
            "type":"Entertainment"
        }
    ],
    "sg:postcode":"6612",
    "sg:province":"Ticino",
    "sg:tags":[
        "hotels",
        "mit",
        "restaurant"
    ],
    "wof:name":"Walter Tobler",
    "wof:placetype":"venue"
},
  "geometry": {"coordinates":[8.7643737793,46.1574897766],"type":"Point"}
}