{
  "type": "Feature",
  "properties": {
    "iso:country":"CH",
    "sg:address":"Nidelbadstrasse 79",
    "sg:city":"Z\u00fcrich",
    "sg:orig_category":"Unternehmensberatung Werbung",
    "sg:phone":"+41 14815055",
    "sg:postcode":"8038",
    "sg:province":"Z\u00fcrich",
    "wof:name":"Weiss Ag F\u00fcr Kommunikation",
    "wof:placetype":"venue"
},
  "geometry": {"coordinates":[8.534787178,47.3331756592],"type":"Point"}
}