{
  "type": "Feature",
  "properties": {
    "iso:country":"CH",
    "sg:address":"Gr\u00fcendlerstrasse 13",
    "sg:city":"Rudolfstetten",
    "sg:orig_category":"Technische, physikalische U chemische Untersuchung Werbeberatung",
    "sg:phone":"+41 56 640 06 40",
    "sg:postcode":"8964",
    "sg:province":"Aargau",
    "wof:name":"Intrastella Gmbh",
    "wof:placetype":"venue"
},
  "geometry": {"coordinates":[8.3781366348,47.36876297],"type":"Point"}
}