{
  "type": "Feature",
  "properties": {
    "iso:country":"CH",
    "sg:address":"La Malc\u00f4te",
    "sg:city":"Asuel",
    "sg:orig_category":"Vermittlung U Verwaltung von Immobilien",
    "sg:phone":"+41 32 462 28 81",
    "sg:postcode":"2954",
    "sg:province":"Jura",
    "wof:name":"Cwm Sa",
    "wof:placetype":"venue"
},
  "geometry": {"coordinates":[7.1972198486,47.3998146057],"type":"Point"}
}