{
  "type": "Feature",
  "properties": {
    "iso:country":"CH",
    "sg:address":"Kirchstrasse 26",
    "sg:city":"Menziken",
    "sg:classifiers":[
        {
            "category":"Restaurant",
            "type":"Food & Drink"
        }
    ],
    "sg:phone":"+41 55 644 34 02",
    "sg:postcode":"5737",
    "sg:province":"Aargau",
    "wof:name":"Restaurant Raben",
    "wof:placetype":"venue"
},
  "geometry": {"coordinates":[9.0622205734,46.983631134],"type":"Point"}
}