{
  "type": "Feature",
  "properties": {
    "addr:full":"Fronwagplatz 13 8200 Schaffhausen. Postfach 986 Schaffhausen Schaffhausen 8201",
    "addr:housenumber":"13;986",
    "addr:postcode":"8200 schaffhausen.;8201",
    "addr:street":"Fronwagplatz;Postfach",
    "iso:country":"CH",
    "sg:address":"Fronwagplatz 13 8200 Schaffhausen. Postfach 986",
    "sg:city":"Schaffhausen",
    "sg:orig_category":"Detailhandel mit B\u00fcchern",
    "sg:phone":"+41 52 625 41 44",
    "sg:postcode":"8201",
    "sg:province":"Schaffhausen",
    "wof:name":"Meili B\u00fccher & Medien, Inh. Claudia Meili Und Claudio Senn",
    "wof:placetype":"venue"
},
  "geometry": {"coordinates":[8.633357,47.696842],"type":"Point"}
}