{
  "type": "Feature",
  "properties": {
    "iso:country":"CH",
    "sg:address":"L\u00f6wenstrasse 1",
    "sg:city":"Z\u00fcrich",
    "sg:orig_category":"Interessenvertretungen",
    "sg:postcode":"8001",
    "sg:province":"Z\u00fcrich",
    "wof:name":"Stiftung F\u00fcr Eine Nachhaltige Ern\u00e4hrung Durch Die Schweizerische Landwirtschaft",
    "wof:placetype":"venue"
},
  "geometry": {"coordinates":[8.2048416138,47.4841842651],"type":"Point"}
}