{
  "type": "Feature",
  "properties": {
    "iso:country":"CH",
    "sg:address":"Bahnhofstrasse 9",
    "sg:city":"Baar",
    "sg:orig_category":"Public-Relations-Agenturen Unternehmensberatung",
    "sg:phone":"+41 56 621 93 14",
    "sg:postcode":"6340",
    "sg:province":"Zug",
    "wof:name":"Keist Ren\u00e9 Organisationsberatung Und Coaching",
    "wof:placetype":"venue"
},
  "geometry": {"coordinates":[8.2983760834,47.3739204407],"type":"Point"}
}