{
  "type": "Feature",
  "properties": {
    "iso:country":"CH",
    "sg:address":"Meisenweg 25 4552 Derendingen. Postfach",
    "sg:city":"Derendingen",
    "sg:orig_category":"Architektur U Ingenieurb\u00fcros",
    "sg:phone":"+41 79 415 78 68",
    "sg:postcode":"4552",
    "sg:province":"Solothurn",
    "wof:name":"Pb Konstruktionen Gmbh",
    "wof:placetype":"venue"
},
  "geometry": {"coordinates":[7.591151,47.199516],"type":"Point"}
}