{
  "type": "Feature",
  "properties": {
    "iso:country":"CH",
    "sg:address":"Fronwagplatz 6 8200 Schaffhausen. Postfach",
    "sg:city":"Schaffhausen",
    "sg:orig_category":"Fachdetailhandel in Verkaufsr\u00e4umen",
    "sg:postcode":"8202",
    "sg:province":"Schaffhausen",
    "wof:name":"Foto Da Vinci Keidler E. + Calabrese T. Foto-fachgesch\u00e4ft",
    "wof:placetype":"venue"
},
  "geometry": {"coordinates":[8.6335878372,47.6965675354],"type":"Point"}
}